Workbook

Sheet Index
B9: Click to go
B10: Assumption
B11: Historical P & L
B12: Historical Balance Sheet
B13: Revenue Build_Up
B14: Cost Build_Up
B15: Working Capital Schedules
B16: Debt Schedules
B17: Balance_Sheet Forecasting
B18: Forecasted Income Statement
B19: Forecasted Balance Sheet
B20: Common Size Statement
B21: Cash Flow | H21: ISIN Code | J21: INE769A01020
B22: Equity Market | H22: NSE | J22: AARTIIND
B23: Beta | H23: BSE | J23: 524208
B24: Relative Valuation
B25: WACC | G25: Detailed & Dynamic DCF Analysis
B26: DCF Model
B27: FootBall Field Analysis | G27: - Dhiraj Mehta
B28: Ratios Analysis
B29: Charts

Sheet Assumption
B8: BSE: 524208 | NSE: AARTIIND
B11: Scenario | E11: Company Name | F11: Aarti Industries Ltd
B12: Base Case | C12: =IF(B12="Best Case",1,IF(B12="Base Case",2,3)) -> 2 | E12: ISIN Code | F12: INE769A01020
E13: Sector Name | F13: Specialty Chemicals
E14: Industry | F14: Chemicals & Petrochemicals
B15: Assumptions | E15: Exchange Name | F15: BSE: 524208 | NSE: AARTIIND
B16: Transaction Date | C16: 45888 | E16: Website | F16: www.aarti-industries.com
B17: Fiscal Year End | C17: 46112 | E17: Company Description | F17: Aarti Industries Ltd, the flagship company of the Aarti group, manufacturing organic and inorganic chemicals at its major facilities in Vapi, Jhagadia, Dahej and Kutch, in Gujarat and in Tarapur in Maharashtra. The company has a strong market position in the NCB-based specialty chemicals segment. Aarti Industries is a diversified chemicals company engaged in specialty chemicals, agrochemicals and fertilizers, dyes, pigments and printing inks, pharmaceutical intermediates, polymer and additives, energy-related chemicals, and other specialty applications.
B18: Annual growth Tapering | C18: ='Revenue Build_up'!C29 -> 0.08
B19: Risk Free Rate | C19: 0.06512
B20: Tax Rate | C20: ='Cost Build_up'!H39 -> 0.061471938
B21: EV/EBITDA Multiple | C21: ='Comps '!E40 -> 27.029875
B22: Perpetual Growth Rate | C22: 0.06
B23: Discount Rate | C23: =WACC!F53 -> 0.10941091
B24: Shares Outstanding(Cr.) | C24: 36.26
B25: Current Market Price | C25: 389.45
B26: Market Cap (Cr.) | C26: =C25*C24 -> 14121.457
B28: Colour Code
B29: Blue colour | C29: Hardcoded Figures
B30: Black colour | C30: Calculated Figures
B31: Green Colour | C31: Link Data figures
B33: Items | C33: Sheet | D33: Reference | F33: Assumption
B35: Revenue from operation | C35: Revenue Buildup | D35: B32:Q39 | F35: Revenue from operation is forecasted on the three case , base, best and worst case. For this I make a scenario and take max for the best case, min for the worst case and average for the base case. Max, min and Average is consider from the last four year growth rate. for best case there is 37 % growth rate , for average 13% and for worst it is -4%. also take the annual growth tapering of 8 %.
B39: Total Net Revenue | C39: Revenue Buildup | D39: B18:Q19 | F39: The total net Revenue is forecasted by using Revenue from operation Minus the GST tax.
B41: Other Income | C41: Revenue Buildup | D41: B27:Q28 | F41: The Other Income is compared with the % as the revenue and for the future projection I took average of the 5 year historical data.
B43: GST Collected | C43: Revenue Buildup | D43: B16:Q16 | F43: The GST collected is compared with the % as the revenue and for the future projection I took average of the 5 year historical data which is 10%.
B45: Cost of materials consumed | C45: Cost Build_up | D45: B16:Q17 | F45: Cost of material Consumed is compare with the % of revenue , and take the average of the 5 Year for the future prediction.
B49: Purchases of stock, Changes in inventories of finished goods, wip and stock in-trade | C49: Cost Build_up | D49: B19:Q23 | F49: Purchase of stocks and Changes in inventories of the finished goods, works in progress and stock in trade is compare with the % of revenue , for the forecasted year I take the average of the 5 year historical for both items.
B54: Employee benefits expense, Other Expenses | C54: Cost Build_up | D54: B30:Q34 | F54: Employee Benefits Expenses & Other Expenses is compare with the % of revenue , for the forecasted year I take the average of the 5 year historical for the employee benefits and for the other expenses I take average for the future year.
B58: Perpetual Growth Rate | C58: Assumptions | D58: C21 | F58: I take the 6 % Growth rate for the terminal Value as india GDP growth rate for the year is forecasted 6.4%.
B60: Effective Tax Rate | C60: Cost Build_up | D60: B39:Q39 | F60: Effective Tax Rate is compare with the % of EBT , for the forecasted year I take the 6% , which is average of the last 5 year.
B62: Non -Current Assets Items | C62: B_sheet | D62: B14:Q21 | F62: The Non-Current Assets items taken as the average of the historical year with Compare with the % of the Reveneu.
B65: Current Assets | C65: B_sheet | D65: B23:Q31 | F65: The Current Assets items taken as the average of the historical year with Compare with the % of the Reveneu.
... B104: Comparable valuation | C104: Comps | D104: B37:L47 | F104: The Comparable valustion is calculated by taking the peers company which same industry and taken Average and median data of EV/EBITDA, EV/sales and P/E ratio for company Valuation.

Sheet Historical P&L
B7: BSE: 524208 | NSE: AARTIIND
B8: Income Statement
B9: All Figure In INR Cr.
B10: Particulars | C10: 2021 | D10: =C10+1 -> 2022 | E10: =D10+1 -> 2023 | F10: =E10+1 -> 2024 | G10: =F10+1 -> 2025
B11: REVENUE
B12: Revenue from Operations | C12: 5023.28 | D12: 6871.05 | E12: 7282.62 | F12: 7010.56 | G12: 8046.01
B13: Less: GST Collected | C13: -517.18 | D13: -785.54 | E13: -664.04 | F13: -639.76 | G13: -774.69
B14: Net Revenue from Operations | C14: =SUM(C12:C13) -> 4506.1 | D14: =SUM(D12:D13) -> 6085.51 | E14: =SUM(E12:E13) -> 6618.58 | F14: =SUM(F12:F13) -> 6370.8 | G14: =SUM(G12:G13) -> 7271.32
B15: Other Income | C15: 0.7 | D15: 0.77 | E15: 0.86 | F15: 10.86 | G15: 14.12
B16: Total Revenue | C16: =SUM(C14:C15) -> 4506.8 | D16: =SUM(D14:D15) -> 6086.28 | E16: =SUM(E14:E15) -> 6619.44 | F16: =SUM(F14:F15) -> 6381.66 | G16: =SUM(G14:G15) -> 7285.44
B17: EXPENSES
B18: Cost of Materials Consumed (Incl. Packing Material, Fuel, Stores & Spares) | C18: 1937.57 | D18: 2794.06 | E18: 3462.03 | F18: 3771.5 | G18: 4381.36
B19: Purchases of Stock-in-Trade | C19: 244.24 | D19: 270.88 | E19: 313.94 | F19: 203.95 | G19: 219.73
B20: Changes in Inventories of Finished Goods, Work-in-progress and Stock-in-Trade | C20: -53.25 | D20: -210.49 | E20: 65.7 | F20: -93.57 | G20: 54.03
B21: Employee Benefits Expenses | C21: 371.38 | D21: 356.96 | E21: 385.33 | F21: 403.74 | G21: 422.42
B22: Finance Costs | C22: 86.37 | D22: 102.33 | E22: 168.28 | F22: 211.47 | G22: 275.44
B23: Depreciation and Amortisation Expenses | C23: 231.31 | D23: 246.4 | E23: 310.45 | F23: 378.12 | G23: 434.27
B24: Other Expenses | C24: 1024.63 | D24: 1153.99 | E24: 1302.61 | F24: 1111.03 | G24: 1193.33
B25: Total Expenses | C25: =-SUM(C18:C24) -> -3842.25 | D25: =-SUM(D18:D24) -> -4714.13 | E25: =-SUM(E18:E24) -> -6008.34 | F25: =-SUM(F18:F24) -> -5986.24 | G25: =-SUM(G18:G24) -> -6980.58
B26: PROFIT BEFORE TAX | C26: =SUM(C16,C25) -> 664.55 | D26: =SUM(D16,D25) -> 1372.15 | E26: =SUM(E16,E25) -> 611.1 | F26: =SUM(F16,F25) -> 395.42 | G26: =SUM(G16,G25) -> 304.86
B27: Exceptional Item
B28: Gain on Disposal of step down subsidiary | C28: 0 | D28: 0 | E28: 0 | F28: 0 | G28: 2.37
B29: PROFIT AFTER EXCEPTIONAL ITEMS | C29: =SUM(C26:C28) -> 664.55 | D29: =SUM(D26:D28) -> 1372.15 | E29: =SUM(E26:E28) -> 611.1 | F29: =SUM(F26:F28) -> 395.42 | G29: =SUM(G26:G28) -> 307.23
B30: Total Tax Expenses | C30: -129.33 | D30: -186.25 | E30: -65.87 | F30: 21.05 | G30: 23.64
B31: PROFIT AFTER TAX BEFORE NON CONTROLLING INTEREST AND SHARE OF PROFIT/(LOSS) OF ASSOCIATES | C31: =SUM(C29:C30) -> 535.22 | D31: =SUM(D29:D30) -> 1185.9 | E31: =SUM(E29:E30) -> 545.23 | F31: =SUM(F29:F30) -> 416.47 | G31: =SUM(G29:G30) -> 330.87
B32: Profit attributable to Non Controlling Interest | C32: -11.75 | D32: -0.23 | E32: 0 | F32: 0 | G32: 0
B33: Profit/(Loss) for the period | C33: =SUM(C31:C32) -> 523.47 | D33: =SUM(D31:D32) -> 1185.67 | E33: =SUM(E31:E32) -> 545.23 | F33: =SUM(F31:F32) -> 416.47 | G33: =SUM(G31:G32) -> 330.87
B35: Earnings Per Equity Share (EPS) (in `)
B36: Basic/Diluted | C36: 30.04 | D36: 36.06 | E36: 15.04 | F36: 11.49 | G36: 9.13
B37: Basic/Diluted after considering issue of bonus equity shares | C37: 15.02 | D37: 36.06 | E37: 15.04 | F37: 11.49 | G37: 9.12

Sheet Historical balance Sheet
B9: BSE: 524208 | NSE: AARTIIND
B10: Particulars | C10: 2021 | D10: =C10+1 -> 2022 | E10: =D10+1 -> 2023 | F10: =E10+1 -> 2024 | G10: =F10+1 -> 2025
B11: All Figure In INR Cr.
B12: Assets
B13: Non-Current Assets
B14: Property Plant and Equipment | C14: 3592.48 | D14: 3577.7 | E14: 4829.18 | F14: 5583.06 | G14: 6277.48
B15: Capital Work-in-Progress | C15: 1297.91 | D15: 1303.02 | E15: 988.98 | F15: 1058.54 | G15: 1273.8
B16: Right of use Assets | C16: 0 | D16: 16.95 | E16: 30.3 | F16: 53.42 | G16: 51.06
B17: Intangible Assets | C17: 0.1 | D17: 0 | E17: 1.47 | F17: 12.92 | G17: 48.25
B18: Intangible Assets under Development | C18: 0 | D18: 42.97 | E18: 107.24 | F18: 170.51 | G18: 180.41
B19: Financial Assets
B20: Investments | C20: 63.52 | D20: 28.29 | E20: 17.17 | F20: 22.92 | G20: 47.63
B21: Loans & Advances | C21: 320.07 | D21: 0 | E21: 0.01 | F21: 0.3 | G21: 0.06
B22: Deferred Tax Assets | C22: 0 | D22: 27.74 | E22: 52.78 | F22: 143.55 | G22: 217.99
B23: Other Non-Current Assets | C23: 0 | D23: 155.19 | E23: 94.5 | F23: 110.89 | G23: 122.1
B25: Total Non-Current Assets | C25: =SUM(C14:C23) -> 5274.08 | D25: =SUM(D14:D23) -> 5151.86 | E25: =SUM(E14:E23) -> 6121.63 | F25: =SUM(F14:F23) -> 7156.11 | G25: =SUM(G14:G23) -> 8218.78
B27: Current Assets:
B28: Inventories | C28: 935.68 | D28: 934.12 | E28: 1031.05 | F28: 1159.65 | G28: 1454.02
B29: Financial Assets:
B30: Trade Receivables | C30: 793.73 | D30: 1091.52 | E30: 940.49 | F30: 854.18 | G30: 786.06
B31: Cash and Cash Equivalents | C31: 412.32 | D31: 93.63 | E31: 167.45 | F31: 428.29 | G31: 199.39
B32: Bank Balances | C32: 0 | D32: 79.93 | E32: 33.28 | F32: 87.95 | G32: 95.58
B33: Loans and Advances | C33: 0 | D33: 0 | E33: 32.03 | F33: 8.28 | G33: 6.27
B34: Others Current Financial Assets | C34: 187.48 | D34: 407.3 | E34: 160.74 | F34: 16.71 | G34: 16.32
B35: Current Tax Assets (Net) | C35: 0 | D35: 55.42 | E35: 55.48 | F35: 71.16 | G35: 13.89
B36: Other Current Assets | C36: 38.39 | D36: 36.91 | E36: 38.75 | F36: 332.84 | G36: 323.21
B38: Total Current Assets | C38: =SUM(C28:C36) -> 2367.6 | D38: =SUM(D28:D36) -> 2698.83 | E38: =SUM(E28:E36) -> 2459.27 | F38: =SUM(F28:F36) -> 2959.06 | G38: =SUM(G28:G36) -> 2894.74
B40: TOTAL ASSETS | C40: =C38+C25 -> 7641.68 | D40: =D38+D25 -> 7850.69 | E40: =E38+E25 -> 8580.9 | F40: =F38+F25 -> 10115.17 | G40: =G38+G25 -> 11113.52
B42: EQUITY AND LIABILITIES
B43: EQUITY
B44: Equity Share Capital | C44: 87.12 | D44: 181.25 | E44: 181.25 | F44: 181.25 | G44: 181.26
B45: Other Equity | C45: 3415.78 | D45: 4334.73 | E45: 4738.83 | F45: 5108.52 | G45: 5423.86
B46: Non Controlling Interest | C46: 12.24 | D46: 0.72 | E46: 0.72 | F46: 0.72 | G46: 0.1
B47: Total Equity | C47: =SUM(C44:C46) -> 3515.14 | D47: =SUM(D44:D46) -> 4516.7 | E47: =SUM(E44:E46) -> 4920.8 | F47: =SUM(F44:F46) -> 5290.49 | G47: =SUM(G44:G46) -> 5605.22
B49: LIABILITIES
B50: Non-Current Liabilities:
B51: Financial Liabilities
B52: (i) Borrowings | C52: 1268.05 | D52: 929.85 | E52: 634.71 | F52: 1523.87 | G52: 1867.42
B53: (ii) Lease Liabilities | D53: 14.91 | E53: 25.26 | F53: 49.31 | G53: 47.13
B54: Other Non-Current Liabilitie | C54: 224.41 | D54: 223.58 | E54: 216.81 | F54: 175.29 | G54: 112.16
B55: Deferred Tax Liabilities (Net) | C55: 233.94 | D55: 0 | E55: 0 | F55: 0 | G55: 0
B56: Provisions | F56: 13.76 | G56: 15.19
B57: Total Non-Current Liabilities | C57: =SUM(C52:C55) -> 1726.4 | D57: =SUM(D52:D55) -> 1168.34 | E57: =SUM(E52:E55) -> 876.78 | F57: =SUM(F52:F56) -> 1762.23 | G57: =SUM(G52:G56) -> 2041.9
B59: Current Liabilities:
B60: Financial Liabilities
B61: (i) Borrowings | C61: 1224.07 | D61: 1638.12 | E61: 2239.32 | F61: 2040.42 | G61: 1922.13
B62: (ii) Lease Liabilities | C62: 0 | D62: 4.07 | E62: 8.02 | F62: 9.07 | G62: 11.11
B63: (iii) Trade Payables
B64: Micro and Small Enterprise | D64: 69.28 | E64: 48.66 | F64: 47.45 | G64: 26.48
B65: Other than Micro and Small Enterprise | C65: 576.33 | D65: 275.57 | E65: 166.94 | F65: 677.47 | G65: 1211
B66: (iv)Other Financial Liabilities | C66: 0 | D66: 2.23 | E66: 191.26 | F66: 136.56 | G66: 202.26
B67: Other Current Liabilities | C67: 559.62 | D67: 144.7 | E67: 99.26 | F67: 124.97 | G67: 77.51
B68: Provisions | C68: 40.12 | D68: 31.68 | E68: 29.86 | F68: 26.51 | G68: 15.91
B70: Total Current Liabilities | C70: =SUM(C61:C68) -> 2400.14 | D70: =SUM(D61:D68) -> 2165.65 | E70: =SUM(E61:E68) -> 2783.32 | F70: =SUM(F61:F68) -> 3062.45 | G70: =SUM(G61:G68) -> 3466.4
B72: Total Liabilities | C72: =C70+C57 -> 4126.54 | D72: =D70+D57 -> 3333.99 | E72: =E70+E57 -> 3660.1 | F72: =F70+F57 -> 4824.68 | G72: =G70+G57 -> 5508.3
B74: TOTAL EQUITY AND LIABILITIES | C74: =C72+C47 -> 7641.68 | D74: =D72+D47 -> 7850.69 | E74: =E72+E47 -> 8580.9 | F74: =F72+F47 -> 10115.17 | G74: =G72+G47 -> 11113.52
B76: Check | C76: =C74=C40 -> TRUE | D76: =D74=D40 -> TRUE | E76: =E74=E40 -> TRUE | F76: =F74=F40 -> TRUE | G76: =G74=G40 -> TRUE

Sheet Revenue Build_up
B7: BSE: 524208 | NSE: AARTIIND
B8: Revenue Build_up
B9: All Figure In INR Cr.
B10: Particulars | C10: 2021 | D10: =C10+1 -> 2022 | E10: =D10+1 -> 2023 | F10: =E10+1 -> 2024 | G10: =F10+1 -> 2025 | H10: =G10+1 -> 2026 | I10: =H10+1 -> 2027 | J10: =I10+1 -> 2028 | K10: =J10+1 -> 2029 | ... Q10: =P10+1 -> 2035
C11: Aduited | D11: Aduited | E11: Aduited | F11: Aduited | G11: Aduited | H11: Forecasted | I11: Forecasted | J11: Forecasted | K11: Forecasted | L11: Forecasted | M11: Forecasted | N11: Forecasted | O11: Forecasted | P11: Forecasted | Q11: Forecasted
B14: Revenue from Operation | C14: ='Historical P&L'!C12 -> 5023.28 | D14: ='Historical P&L'!D12 -> 6871.05 | E14: ='Historical P&L'!E12 -> 7282.62 | F14: ='Historical P&L'!F12 -> 7010.56 | G14: ='Historical P&L'!G12 -> 8046.01 | H14: =G14*(1+H15) -> 9128.3626 | I14: =H14*(1+I15) -> 10258.078 | J14: =I14*(1+J15) -> 11426.043 | K14: =J14*(1+K15) -> 12622.914 | L14: =K14*(1+L15) -> 13839.378 | M14: =L14*(1+M15) -> 15066.376 | N14: =M14*(1+N15) -> 16295.297 | O14: =N14*(1+O15) -> 17518.124 | ... Q14: =P14*(1+Q15) -> 19917.035
B15: Growth | D15: =D14/C14-1 -> 0.36784133 | E15: =E14/D14-1 -> 0.059899142 | F15: =F14/E14-1 -> -0.037357435 | G15: =G14/F14-1 -> 0.14769861 | H15: =CHOOSE(Assumption!$C$12,'Revenue Build_up'!$H$26:$Q$26,'Revenue Build_up'!$H$27:$Q$27,'Revenue Build_up'!$H$28:$Q$28) -> 0.13452041 | I15: =CHOOSE(Assumption!$C$12,'Revenue Build_up'!$H$26:$Q$26,'Revenue Build_up'!$H$27:$Q$27,'Revenue Build_up'!$H$28:$Q$28) -> 0.12375878 | J15: =CHOOSE(Assumption!$C$12,'Revenue Build_up'!$H$26:$Q$26,'Revenue Build_up'!$H$27:$Q$27,'Revenue Build_up'!$H$28:$Q$28) -> 0.11385808 | K15: =CHOOSE(Assumption!$C$12,'Revenue Build_up'!$H$26:$Q$26,'Revenue Build_up'!$H$27:$Q$27,'Revenue Build_up'!$H$28:$Q$28) -> 0.10474943 | L15: =CHOOSE(Assumption!$C$12,'Revenue Build_up'!$H$26:$Q$26,'Revenue Build_up'!$H$27:$Q$27,'Revenue Build_up'!$H$28:$Q$28) -> 0.096369477 | M15: =CHOOSE(Assumption!$C$12,'Revenue Build_up'!$H$26:$Q$26,'Revenue Build_up'!$H$27:$Q$27,'Revenue Build_up'!$H$28:$Q$28) -> 0.088659919 | N15: =CHOOSE(Assumption!$C$12,'Revenue Build_up'!$H$26:$Q$26,'Revenue Build_up'!$H$27:$Q$27,'Revenue Build_up'!$H$28:$Q$28) -> 0.081567125 | O15: =CHOOSE(Assumption!$C$12,'Revenue Build_up'!$H$26:$Q$26,'Revenue Build_up'!$H$27:$Q$27,'Revenue Build_up'!$H$28:$Q$28) -> 0.075041755 | ... Q15: =CHOOSE(Assumption!$C$12,'Revenue Build_up'!$H$26:$Q$26,'Revenue Build_up'!$H$27:$Q$27,'Revenue Build_up'!$H$28:$Q$28) -> 0.063515342
B16: Less: GST Collected | C16: 517.18 | D16: 785.54 | E16: 664.04 | F16: 639.76 | G16: 774.69 | H16: =H14*H17 -> 905.53955 | I16: =I14*I17 -> 1017.608 | J16: =J14*J17 -> 1133.4709 | K16: =K14*K17 -> 1252.2014 | L16: =L14*L17 -> 1372.8753 | M16: =M14*M17 -> 1494.5944 | N16: =N14*N17 -> 1616.5041 | O16: =O14*O17 -> 1737.8094 | ... Q16: =Q14*Q17 -> 1975.7829
B17: % of Gross Revenue | C17: =C16/C14 -> 0.10295663 | D17: =D16/D14 -> 0.11432605 | E17: =E16/E14 -> 0.09118147 | F17: =F16/F14 -> 0.091256619 | G17: =G16/G14 -> 0.096282505 | H17: =AVERAGE(C17:G17) -> 0.099200655 | I17: =H17 -> 0.099200655 | J17: =I17 -> 0.099200655 | K17: =J17 -> 0.099200655 | L17: =K17 -> 0.099200655 | M17: =L17 -> 0.099200655 | N17: =M17 -> 0.099200655 | O17: =N17 -> 0.099200655 | P17: =O17 -> 0.099200655 | Q17: =P17 -> 0.099200655
B18: Total Revenue (Net) | C18: =C14-C16 -> 4506.1 | D18: =D14-D16 -> 6085.51 | E18: =E14-E16 -> 6618.58 | F18: =F14-F16 -> 6370.8 | G18: =G14-G16 -> 7271.32 | H18: =H14-H16 -> 8222.823 | I18: =I14-I16 -> 9240.4696 | J18: =J14-J16 -> 10292.572 | ... Q18: =Q14-Q16 -> 17941.252
B21: Other Income | C21: ='Historical P&L'!C15 -> 0.7 | D21: ='Historical P&L'!D15 -> 0.77 | E21: ='Historical P&L'!E15 -> 0.86 | F21: ='Historical P&L'!F15 -> 10.86 | G21: ='Historical P&L'!G15 -> 14.12 | H21: =H22*H18 -> 6.6742032 | I21: =I22*I18 -> 7.5001944 | J21: =J22*J18 -> 8.3541521 | K21: =K22*K18 -> 9.2292448 | L21: =L22*L18 -> 10.118662 | M21: =M22*M18 -> 11.015782 | N21: =N22*N18 -> 11.914308 | O21: =O22*O18 -> 12.808378 | ... Q21: =Q22*Q18 -> 14.562342
B22: % of Net Revenue | C22: =C21/C18 -> 0.00015534498 | D22: =D21/D18 -> 0.00012653007 | E22: =E21/E18 -> 0.00012993724 | F22: =F21/F18 -> 0.0017046525 | G22: =G21/G18 -> 0.0019418758 | H22: =AVERAGE(C22:G22) -> 0.0008116681 | I22: =H22 -> 0.0008116681 | J22: =I22 -> 0.0008116681 | K22: =J22 -> 0.0008116681 | L22: =K22 -> 0.0008116681 | M22: =L22 -> 0.0008116681 | N22: =M22 -> 0.0008116681 | O22: =N22 -> 0.0008116681 | P22: =O22 -> 0.0008116681 | Q22: =P22 -> 0.0008116681
B25: Scenario | C25: Growth
B26: Best Case | C26: =MAX(D15:G15) -> 0.36784133 | H26: =C26 -> 0.36784133 | I26: =H26*(1-$C$29) -> 0.33841402 | J26: =I26*(1-$C$29) -> 0.3113409 | K26: =J26*(1-$C$29) -> 0.28643363 | L26: =K26*(1-$C$29) -> 0.26351894 | M26: =L26*(1-$C$29) -> 0.24243742 | N26: =M26*(1-$C$29) -> 0.22304243 | O26: =N26*(1-$C$29) -> 0.20519904 | P26: =O26*(1-$C$29) -> 0.18878311 | Q26: =P26*(1-$C$29) -> 0.17368046
B27: Base Case | C27: =AVERAGE(D15:G15) -> 0.13452041 | H27: =C27 -> 0.13452041 | I27: =H27*(1-$C$29) -> 0.12375878 | J27: =I27*(1-$C$29) -> 0.11385808 | K27: =J27*(1-$C$29) -> 0.10474943 | L27: =K27*(1-$C$29) -> 0.096369477 | M27: =L27*(1-$C$29) -> 0.088659919 | N27: =M27*(1-$C$29) -> 0.081567125 | O27: =N27*(1-$C$29) -> 0.075041755 | P27: =O27*(1-$C$29) -> 0.069038415 | Q27: =P27*(1-$C$29) -> 0.063515342
B28: Worst Case | C28: =MIN(D15:G15) -> -0.037357435 | H28: =C28 -> -0.037357435 | I28: =H28*(1-$C$29) -> -0.03436884 | J28: =I28*(1-$C$29) -> -0.031619333 | K28: =J28*(1-$C$29) -> -0.029089786 | L28: =K28*(1-$C$29) -> -0.026762603 | M28: =L28*(1-$C$29) -> -0.024621595 | N28: =M28*(1-$C$29) -> -0.022651867 | O28: =N28*(1-$C$29) -> -0.020839718 | P28: =O28*(1-$C$29) -> -0.01917254 | Q28: =P28*(1-$C$29) -> -0.017638737
B29: Annual growth Tapering | C29: 0.08

Sheet Cost Build_up
B7: BSE: 524208 | NSE: AARTIIND
B8: Cost Build_Up
B9: All Figure In INR Cr.
B10: Particulars | C10: 2021 | D10: =C10+1 -> 2022 | E10: =D10+1 -> 2023 | F10: =E10+1 -> 2024 | G10: =F10+1 -> 2025 | H10: =G10+1 -> 2026 | I10: =H10+1 -> 2027 | J10: =I10+1 -> 2028 | K10: =J10+1 -> 2029 | ... Q10: =P10+1 -> 2035
C11: Aduited | D11: Aduited | E11: Aduited | F11: Aduited | G11: Aduited | H11: Forecasted | I11: Forecasted | J11: Forecasted | K11: Forecasted | L11: Forecasted | M11: Forecasted | N11: Forecasted | O11: Forecasted | P11: Forecasted | Q11: Forecasted
B13: Revenue | C13: ='Revenue Build_up'!C18 -> 4506.1 | D13: ='Revenue Build_up'!D18 -> 6085.51 | E13: ='Revenue Build_up'!E18 -> 6618.58 | F13: ='Revenue Build_up'!F18 -> 6370.8 | G13: ='Revenue Build_up'!G18 -> 7271.32 | H13: ='Revenue Build_up'!H18 -> 8222.823 | I13: ='Revenue Build_up'!I18 -> 9240.4696 | J13: ='Revenue Build_up'!J18 -> 10292.572 | ... Q13: ='Revenue Build_up'!Q18 -> 17941.252
B16: Cost of materials consumed | C16: ='Historical P&L'!C18 -> 1937.57 | D16: ='Historical P&L'!D18 -> 2794.06 | E16: ='Historical P&L'!E18 -> 3462.03 | F16: ='Historical P&L'!F18 -> 3771.5 | G16: ='Historical P&L'!G18 -> 4381.36 | H16: =H13*H17 -> 4286.9695 | I16: =I13*I17 -> 4817.5196 | J16: =J13*J17 -> 5366.0331 | K16: =K13*K17 -> 5928.122 | L16: =L13*L17 -> 6499.412 | M16: =M13*M17 -> 7075.6494 | N16: =N13*N17 -> 7652.7897 | O16: =O13*O17 -> 8227.0685 | ... Q16: =Q13*Q17 -> 9353.673
B17: % of Revenue | C17: =C16/C13 -> 0.42998824 | D17: =D16/D13 -> 0.45913325 | E17: =E16/E13 -> 0.52307746 | F17: =F16/F13 -> 0.59199787 | G17: =G16/G13 -> 0.60255359 | H17: =AVERAGE(C17:G17) -> 0.52135008 | I17: =H17 -> 0.52135008 | J17: =I17 -> 0.52135008 | K17: =J17 -> 0.52135008 | L17: =K17 -> 0.52135008 | M17: =L17 -> 0.52135008 | N17: =M17 -> 0.52135008 | O17: =N17 -> 0.52135008 | P17: =O17 -> 0.52135008 | Q17: =P17 -> 0.52135008
B19: Purchases of stock-in-trade | C19: ='Historical P&L'!C19 -> 244.24 | D19: ='Historical P&L'!D19 -> 270.88 | E19: ='Historical P&L'!E19 -> 313.94 | F19: ='Historical P&L'!F19 -> 203.95 | G19: ='Historical P&L'!G19 -> 219.73 | H19: =H20*H13 -> 342.69352 | I19: =I20*I13 -> 385.10485 | J19: =J20*J13 -> 428.95215 | K19: =K20*K13 -> 473.88464 | L19: =L20*L13 -> 519.55265 | M19: =M20*M13 -> 565.61615 | N19: =N20*N13 -> 611.75183 | O19: =O20*O13 -> 657.65877 | ... Q19: =Q20*Q13 -> 747.71774
B20: % of Revenue | C20: =C19/C13 -> 0.054202082 | D20: =D19/D13 -> 0.044512292 | E20: =E19/E13 -> 0.047433135 | F20: =F19/F13 -> 0.032013248 | G20: =G19/G13 -> 0.030218722 | H20: =AVERAGE(C20:G20) -> 0.041675896 | I20: =H20 -> 0.041675896 | J20: =I20 -> 0.041675896 | K20: =J20 -> 0.041675896 | L20: =K20 -> 0.041675896 | M20: =L20 -> 0.041675896 | N20: =M20 -> 0.041675896 | O20: =N20 -> 0.041675896 | P20: =O20 -> 0.041675896 | Q20: =P20 -> 0.041675896
B22: Changes in inventories of finished goods, work-in-progress and stock in-trade | C22: ='Historical P&L'!C20 -> -53.25 | D22: ='Historical P&L'!D20 -> -210.49 | E22: ='Historical P&L'!E20 -> 65.7 | F22: ='Historical P&L'!F20 -> -93.57 | G22: ='Historical P&L'!G20 -> 54.03 | H22: =H13*H23 -> -71.926997 | I22: =I13*I23 -> -80.828594 | J22: =J13*J23 -> -90.031583 | K22: =K13*K23 -> -99.46234 | L22: =L13*L23 -> -109.04747 | M22: =M13*M23 -> -118.71561 | N22: =N13*N23 -> -128.3989 | O22: =O13*O23 -> -138.03418 | ... Q22: =Q13*Q23 -> -156.93641
B23: % of Revenue | C23: =C22/C13 -> -0.011817314 | D23: =D22/D13 -> -0.03458872 | E23: =E22/E13 -> 0.0099266006 | F23: =F22/F13 -> -0.014687323 | G23: =G22/G13 -> 0.0074305628 | H23: =AVERAGE(C23:G23) -> -0.0087472388 | I23: =H23 -> -0.0087472388 | J23: =I23 -> -0.0087472388 | K23: =J23 -> -0.0087472388 | L23: =K23 -> -0.0087472388 | M23: =L23 -> -0.0087472388 | N23: =M23 -> -0.0087472388 | O23: =N23 -> -0.0087472388 | P23: =O23 -> -0.0087472388 | Q23: =P23 -> -0.0087472388
B25: COGS | C25: =C22+C19+C16 -> 2128.56 | D25: =D22+D19+D16 -> 2854.45 | E25: =E22+E19+E16 -> 3841.67 | F25: =F22+F19+F16 -> 3881.88 | G25: =G22+G19+G16 -> 4655.12 | H25: =H22+H19+H16 -> 4557.736 | I25: =I22+I19+I16 -> 5121.7958 | J25: =J22+J19+J16 -> 5704.9537 | ... Q25: =Q22+Q19+Q16 -> 9944.4544
B26: % of Revenue | C26: =C25/C13 -> 0.47237301 | D26: =D25/D13 -> 0.46905683 | E26: =E25/E13 -> 0.58043719 | F26: =F25/F13 -> 0.60932379 | G26: =G25/G13 -> 0.64020288 | H26: =H25/H13 -> 0.55427874 | I26: =I25/I13 -> 0.55427874 | J26: =J25/J13 -> 0.55427874 | ... Q26: =Q25/Q13 -> 0.55427874
B28: Gross Profit Margin | C28: =(C13-C25)/C13 -> 0.52762699 | D28: =(D13-D25)/D13 -> 0.53094317 | E28: =(E13-E25)/E13 -> 0.41956281 | F28: =(F13-F25)/F13 -> 0.39067621 | G28: =(G13-G25)/G13 -> 0.35979712 | H28: =(H13-H25)/H13 -> 0.44572126 | I28: =(I13-I25)/I13 -> 0.44572126 | J28: =(J13-J25)/J13 -> 0.44572126 | ... Q28: =(Q13-Q25)/Q13 -> 0.44572126
B30: Employee benefits expense | C30: ='Historical P&L'!C21 -> 371.38 | D30: ='Historical P&L'!D21 -> 356.96 | E30: ='Historical P&L'!E21 -> 385.33 | F30: ='Historical P&L'!F21 -> 403.74 | G30: ='Historical P&L'!G21 -> 422.42 | H30: =H31*H13 -> 527.51298 | I30: =I31*I13 -> 592.79734 | J30: =J31*J13 -> 660.29211 | K30: =K31*K13 -> 729.45733 | L30: =L31*L13 -> 799.75475 | M30: =M31*M13 -> 870.66094 | N30: =N31*N13 -> 941.67825 | O30: =O31*O13 -> 1012.3434 | ... Q30: =Q31*Q13 -> 1150.9725
B31: % of Revenue | C31: =C30/C13 -> 0.082417168 | D31: =D30/D13 -> 0.058657368 | E31: =E30/E13 -> 0.058219437 | F31: =F30/F13 -> 0.063373517 | G31: =G30/G13 -> 0.058093991 | H31: =AVERAGE(C31:G31) -> 0.064152296 | I31: =H31 -> 0.064152296 | J31: =I31 -> 0.064152296 | K31: =J31 -> 0.064152296 | L31: =K31 -> 0.064152296 | M31: =L31 -> 0.064152296 | N31: =M31 -> 0.064152296 | O31: =N31 -> 0.064152296 | P31: =O31 -> 0.064152296 | Q31: =P31 -> 0.064152296
B33: Other expenses | C33: ='Historical P&L'!C24 -> 1024.63 | D33: ='Historical P&L'!D24 -> 1153.99 | E33: ='Historical P&L'!E24 -> 1302.61 | F33: ='Historical P&L'!F24 -> 1111.03 | G33: ='Historical P&L'!G24 -> 1193.33 | H33: =H34*H13 -> 1566.1786 | I33: =I34*I13 -> 1760.0069 | J33: =J34*J13 -> 1960.3979 | K33: =K34*K13 -> 2165.7485 | L33: =L34*L13 -> 2374.4605 | M33: =M34*M13 -> 2584.98 | N33: =N34*N13 -> 2795.8294 | O33: =O34*O13 -> 3005.6333 | ... Q33: =Q34*Q13 -> 3417.221
B34: % of Revenue | C34: =C33/C13 -> 0.22738732 | D34: =D33/D13 -> 0.18962914 | E34: =E33/E13 -> 0.1968111 | F34: =F33/F13 -> 0.17439411 | G34: =G33/G13 -> 0.16411463 | H34: =AVERAGE(C34:G34) -> 0.19046726 | I34: =H34 -> 0.19046726 | J34: =I34 -> 0.19046726 | K34: =J34 -> 0.19046726 | L34: =K34 -> 0.19046726 | M34: =L34 -> 0.19046726 | N34: =M34 -> 0.19046726 | O34: =N34 -> 0.19046726 | P34: =O34 -> 0.19046726 | Q34: =P34 -> 0.19046726
B36: Opex | C36: =C33+C30 -> 1396.01 | D36: =D33+D30 -> 1510.95 | E36: =E33+E30 -> 1687.94 | F36: =F33+F30 -> 1514.77 | G36: =G33+G30 -> 1615.75 | H36: =H33+H30 -> 2093.6915 | I36: =I33+I30 -> 2352.8043 | J36: =J33+J30 -> 2620.69 | ... Q36: =Q33+Q30 -> 4568.1935
B37: % of Revenue | C37: =C36/C13 -> 0.30980449 | D37: =D36/D13 -> 0.2482865 | E37: =E36/E13 -> 0.25503054 | F37: =F36/F13 -> 0.23776763 | G37: =G36/G13 -> 0.22220862 | H37: =H36/H13 -> 0.25461956 | I37: =I36/I13 -> 0.25461956 | J37: =J36/J13 -> 0.25461956 | ... Q37: =Q36/Q13 -> 0.25461956
B39: Effective Tax Rate | C39: =-'Historical P&L'!C30/'Historical P&L'!C26 -> 0.1946129 | D39: =-'Historical P&L'!D30/'Historical P&L'!D26 -> 0.13573589 | E39: =-'Historical P&L'!E30/'Historical P&L'!E26 -> 0.10778923 | F39: =-'Historical P&L'!F30/'Historical P&L'!F26 -> -0.053234535 | G39: =-'Historical P&L'!G30/'Historical P&L'!G26 -> -0.077543791 | H39: =AVERAGE(C39:G39) -> 0.061471938 | I39: =H39 -> 0.061471938 | J39: =I39 -> 0.061471938 | K39: =J39 -> 0.061471938 | L39: =K39 -> 0.061471938 | M39: =L39 -> 0.061471938 | N39: =M39 -> 0.061471938 | O39: =N39 -> 0.061471938 | P39: =O39 -> 0.061471938 | Q39: =P39 -> 0.061471938

Sheet Working Capital Schedules
B7: BSE: 524208 | NSE: AARTIIND
B8: Working Capital Schedules
B9: All Figure In INR Cr.
B10: Particulars | C10: 2021 | D10: =C10+1 -> 2022 | E10: =D10+1 -> 2023 | F10: =E10+1 -> 2024 | G10: =F10+1 -> 2025 | H10: =G10+1 -> 2026 | I10: =H10+1 -> 2027 | J10: =I10+1 -> 2028 | K10: =J10+1 -> 2029 | ... Q10: =P10+1 -> 2035
C11: Aduited | D11: Aduited | E11: Aduited | F11: Aduited | G11: Aduited | H11: Forecasted | I11: Forecasted | J11: Forecasted | K11: Forecasted | L11: Forecasted | M11: Forecasted | N11: Forecasted | O11: Forecasted | P11: Forecasted | Q11: Forecasted
B12: Days of operation | C12: 365 | D12: =C12 -> 365 | E12: =D12 -> 365 | F12: =E12 -> 365 | G12: =F12 -> 365 | H12: =G12 -> 365 | I12: =H12 -> 365 | J12: =I12 -> 365 | K12: =J12 -> 365 | ... Q12: =P12 -> 365
B14: Inventores | C14: ='Historical balance Sheet'!C28 -> 935.68 | D14: ='Historical balance Sheet'!D28 -> 934.12 | E14: ='Historical balance Sheet'!E28 -> 1031.05 | F14: ='Historical balance Sheet'!F28 -> 1159.65 | G14: ='Historical balance Sheet'!G28 -> 1454.02 | H14: =(H21*'Cost Build_up'!H25)/'Working Capital Schedules'!H12 -> 1500.6825 | I14: =(I21*'Cost Build_up'!I25)/'Working Capital Schedules'!I12 -> 1686.4051 | J14: =(J21*'Cost Build_up'!J25)/'Working Capital Schedules'!J12 -> 1878.416 | K14: =(K21*'Cost Build_up'!K25)/'Working Capital Schedules'!K12 -> 2075.179 | L14: =(L21*'Cost Build_up'!L25)/'Working Capital Schedules'!L12 -> 2275.1629 | M14: =(M21*'Cost Build_up'!M25)/'Working Capital Schedules'!M12 -> 2476.8786 | N14: =(N21*'Cost Build_up'!N25)/'Working Capital Schedules'!N12 -> 2678.9105 | O14: =(O21*'Cost Build_up'!O25)/'Working Capital Schedules'!O12 -> 2879.9406 | ... Q14: =(Q21*'Cost Build_up'!Q25)/'Working Capital Schedules'!Q12 -> 3274.3161
B15: Recievables | C15: ='Historical balance Sheet'!C30 -> 793.73 | D15: ='Historical balance Sheet'!D30 -> 1091.52 | E15: ='Historical balance Sheet'!E30 -> 940.49 | F15: ='Historical balance Sheet'!F30 -> 854.18 | G15: ='Historical balance Sheet'!G30 -> 786.06 | H15: =(H22*'Cost Build_up'!H13)/'Working Capital Schedules'!H12 -> 1216.6315 | I15: =(I22*'Cost Build_up'!I13)/'Working Capital Schedules'!I12 -> 1367.2003 | J15: =(J22*'Cost Build_up'!J13)/'Working Capital Schedules'!J12 -> 1522.8671 | K15: =(K22*'Cost Build_up'!K13)/'Working Capital Schedules'!K12 -> 1682.3866 | L15: =(L22*'Cost Build_up'!L13)/'Working Capital Schedules'!L12 -> 1844.5173 | M15: =(M22*'Cost Build_up'!M13)/'Working Capital Schedules'!M12 -> 2008.052 | N15: =(N22*'Cost Build_up'!N13)/'Working Capital Schedules'!N12 -> 2171.8431 | O15: =(O22*'Cost Build_up'!O13)/'Working Capital Schedules'!O12 -> 2334.822 | ... Q15: =(Q22*'Cost Build_up'!Q13)/'Working Capital Schedules'!Q12 -> 2654.5496
B16: Trade payables | C16: ='Historical balance Sheet'!C64+'Historical balance Sheet'!C65 -> 576.33 | D16: ='Historical balance Sheet'!D64+'Historical balance Sheet'!D65 -> 344.85 | E16: ='Historical balance Sheet'!E64+'Historical balance Sheet'!E65 -> 215.6 | F16: ='Historical balance Sheet'!F64+'Historical balance Sheet'!F65 -> 724.92 | G16: ='Historical balance Sheet'!G64+'Historical balance Sheet'!G65 -> 1237.48 | H16: =(H23*'Cost Build_up'!H25)/'Working Capital Schedules'!H12 -> 820.63851 | I16: =(I23*'Cost Build_up'!I25)/'Working Capital Schedules'!I12 -> 922.19973 | J16: =(J23*'Cost Build_up'!J25)/'Working Capital Schedules'!J12 -> 1027.1996 | K16: =(K23*'Cost Build_up'!K25)/'Working Capital Schedules'!K12 -> 1134.7982 | L16: =(L23*'Cost Build_up'!L25)/'Working Capital Schedules'!L12 -> 1244.1581 | M16: =(M23*'Cost Build_up'!M25)/'Working Capital Schedules'!M12 -> 1354.4651 | N16: =(N23*'Cost Build_up'!N25)/'Working Capital Schedules'!N12 -> 1464.9449 | O16: =(O23*'Cost Build_up'!O25)/'Working Capital Schedules'!O12 -> 1574.8769 | ... Q16: =(Q23*'Cost Build_up'!Q25)/'Working Capital Schedules'!Q12 -> 1790.5386
B17: Net Working Capital | C17: =C14+C15-C16 -> 1153.08 | D17: =D14+D15-D16 -> 1680.79 | E17: =E14+E15-E16 -> 1755.94 | F17: =F14+F15-F16 -> 1288.91 | G17: =G14+G15-G16 -> 1002.6 | H17: =H14+H15-H16 -> 1896.6755 | I17: =I14+I15-I16 -> 2131.4057 | J17: =J14+J15-J16 -> 2374.0835 | ... Q17: =Q14+Q15-Q16 -> 4138.3272
B21: DIO | C21: =(C14/'Cost Build_up'!C25)*'Working Capital Schedules'!C12 -> 160.448 | D21: =(D14/'Cost Build_up'!D25)*'Working Capital Schedules'!D12 -> 119.44641 | E21: =(E14/'Cost Build_up'!E25)*'Working Capital Schedules'!E12 -> 97.960848 | F21: =(F14/'Cost Build_up'!F25)*'Working Capital Schedules'!F12 -> 109.03795 | G21: =(G14/'Cost Build_up'!G25)*'Working Capital Schedules'!G12 -> 114.00722 | H21: =AVERAGE(C21:G21) -> 120.18009 | I21: =H21 -> 120.18009 | J21: =I21 -> 120.18009 | K21: =J21 -> 120.18009 | L21: =K21 -> 120.18009 | M21: =L21 -> 120.18009 | N21: =M21 -> 120.18009 | O21: =N21 -> 120.18009 | P21: =O21 -> 120.18009 | Q21: =P21 -> 120.18009
B22: DSO | C22: =C15/'Revenue Build_up'!C18*'Working Capital Schedules'!C12 -> 64.293169 | D22: =D15/'Revenue Build_up'!D18*'Working Capital Schedules'!D12 -> 65.467775 | E22: =E15/'Revenue Build_up'!E18*'Working Capital Schedules'!E12 -> 51.865936 | F22: =F15/'Revenue Build_up'!F18*'Working Capital Schedules'!F12 -> 48.938234 | G22: =G15/'Revenue Build_up'!G18*'Working Capital Schedules'!G12 -> 39.458021 | H22: =AVERAGE(C22:G22) -> 54.004627 | I22: =H22 -> 54.004627 | J22: =I22 -> 54.004627 | K22: =J22 -> 54.004627 | L22: =K22 -> 54.004627 | M22: =L22 -> 54.004627 | N22: =M22 -> 54.004627 | O22: =N22 -> 54.004627 | P22: =O22 -> 54.004627 | Q22: =P22 -> 54.004627
B23: DPO | C23: =C16/'Cost Build_up'!C25*'Working Capital Schedules'!C12 -> 98.827588 | D23: =D16/'Cost Build_up'!D25*'Working Capital Schedules'!D12 -> 44.096148 | E23: =E16/'Cost Build_up'!E25*'Working Capital Schedules'!E12 -> 20.484321 | F23: =F16/'Cost Build_up'!F25*'Working Capital Schedules'!F12 -> 68.161767 | G23: =G16/'Cost Build_up'!G25*'Working Capital Schedules'!G12 -> 97.028691 | H23: =AVERAGE(C23:G23) -> 65.719703 | I23: =H23 -> 65.719703 | J23: =I23 -> 65.719703 | K23: =J23 -> 65.719703 | L23: =K23 -> 65.719703 | M23: =L23 -> 65.719703 | N23: =M23 -> 65.719703 | O23: =N23 -> 65.719703 | P23: =O23 -> 65.719703 | Q23: =P23 -> 65.719703
B24: Net Trade Cycle | C24: =C21+C22-C23 -> 125.91358 | D24: =D21+D22-D23 -> 140.81804 | E24: =E21+E22-E23 -> 129.34246 | F24: =F21+F22-F23 -> 89.81442 | G24: =G21+G22-G23 -> 56.436553 | H24: =H21+H22-H23 -> 108.46501 | I24: =I21+I22-I23 -> 108.46501 | J24: =J21+J22-J23 -> 108.46501 | ... Q24: =Q21+Q22-Q23 -> 108.46501

Sheet Dep and Capex Schedules
B7: BSE: 524208 | NSE: AARTIIND
B8: Dep and Capex Schedules
B9: All Figure In INR Cr.
B10: Particulars | C10: 2021 | D10: =C10+1 -> 2022 | E10: =D10+1 -> 2023 | F10: =E10+1 -> 2024 | G10: =F10+1 -> 2025 | H10: =G10+1 -> 2026 | I10: =H10+1 -> 2027 | J10: =I10+1 -> 2028 | K10: =J10+1 -> 2029 | ... Q10: =P10+1 -> 2035
B11: Deperciation schedules
B12: PPE Opening | D12: =C15 -> 4890.49 | E12: =D15 -> 4940.64 | F12: =E15 -> 5957.17 | G12: =F15 -> 6878.45 | H12: =G15 -> 7831 | I12: =H15 -> 8420.4297 | J12: =I15 -> 9151.7759 | K12: =J15 -> 10031.488 | ... Q12: =P15 -> 18641.109
B13: Plus -Capex | D13: =D15-D12-D14 -> 296.55 | E13: =E15-E12-E14 -> 1326.98 | F13: =F15-F12-F14 -> 1299.4 | G13: =G15-G12-G14 -> 1386.82 | H13: =H18*'Revenue Build_up'!H18 -> 1058.9518 | I13: =I18*'Revenue Build_up'!I18 -> 1236.2088 | J13: =J18*'Revenue Build_up'!J18 -> 1428.424 | K13: =K18*'Revenue Build_up'!K18 -> 1634.9042 | L13: =L18*'Revenue Build_up'!L18 -> 1854.7915 | M13: =M18*'Revenue Build_up'!M18 -> 2087.0961 | N13: =N18*'Revenue Build_up'!N18 -> 2330.7285 | O13: =O18*'Revenue Build_up'!O18 -> 2584.532 | ... Q13: =Q18*'Revenue Build_up'!Q18 -> 3117.8671
B14: Less-Dep | C14: =-'Historical P&L'!C23 -> -231.31 | D14: =-'Historical P&L'!D23 -> -246.4 | E14: =-'Historical P&L'!E23 -> -310.45 | F14: =-'Historical P&L'!F23 -> -378.12 | G14: =-'Historical P&L'!G23 -> -434.27 | H14: =-H17*H12 -> -469.52218 | I14: =-I17*I12 -> -504.86253 | J14: =-J17*J12 -> -548.71175 | K14: =-K17*K12 -> -601.45654 | L14: =-L17*L12 -> -663.41881 | M14: =-M17*M12 -> -734.84978 | N14: =-N17*N12 -> -815.92623 | O14: =-O17*O12 -> -906.74901 | ... Q14: =-Q17*Q12 -> -1117.6624
B15: PPE Closing | C15: =SUM('Historical balance Sheet'!C14:C18) -> 4890.49 | D15: =SUM('Historical balance Sheet'!D14:D18) -> 4940.64 | E15: =SUM('Historical balance Sheet'!E14:E18) -> 5957.17 | F15: =SUM('Historical balance Sheet'!F14:F18) -> 6878.45 | G15: =SUM('Historical balance Sheet'!G14:G18) -> 7831 | H15: =SUM(H12:H14) -> 8420.4297 | I15: =SUM(I12:I14) -> 9151.7759 | J15: =SUM(J12:J14) -> 10031.488 | K15: =SUM(K12:K14) -> 11064.936 | L15: =SUM(L12:L14) -> 12256.308 | M15: =SUM(M12:M14) -> 13608.555 | N15: =SUM(N12:N14) -> 15123.357 | O15: =SUM(O12:O14) -> 16801.14 | ... Q15: =SUM(Q12:Q14) -> 20641.314
B17: Deperciation & Amotisartion Exp. (%of PPE) | C17: 0 | D17: =-D14/D12 -> 0.050383499 | E17: =-E14/E12 -> 0.062835989 | F17: =-F14/F12 -> 0.063473092 | G17: =-G14/G12 -> 0.063134863 | H17: =AVERAGE(D17:G17) -> 0.059956861 | I17: =H17 -> 0.059956861 | J17: =I17 -> 0.059956861 | K17: =J17 -> 0.059956861 | L17: =K17 -> 0.059956861 | M17: =L17 -> 0.059956861 | N17: =M17 -> 0.059956861 | O17: =N17 -> 0.059956861 | P17: =O17 -> 0.059956861 | Q17: =P17 -> 0.059956861
B18: Capex % of Revenue | C18: 0 | D18: =D13/'Revenue Build_up'!D18 -> 0.048730509 | E18: =E13/'Revenue Build_up'!E18 -> 0.20049316 | F18: =F13/'Revenue Build_up'!F18 -> 0.20396183 | G18: =G13/'Revenue Build_up'!G18 -> 0.19072466 | H18: =AVERAGE(C18:G18) -> 0.12878203 | I18: =H18+0.5% -> 0.13378203 | J18: =I18+0.5% -> 0.13878203 | K18: =J18+0.5% -> 0.14378203 | L18: =K18+0.5% -> 0.14878203 | M18: =L18+0.5% -> 0.15378203 | N18: =M18+0.5% -> 0.15878203 | O18: =N18+0.5% -> 0.16378203 | P18: =O18+0.5% -> 0.16878203 | Q18: =P18+0.5% -> 0.17378203

Sheet Debt Schedules
B7: BSE: 524208 | NSE: AARTIIND
B8: Debt Schedules
B9: All Figure In INR Cr.
B10: Particulars | C10: 2021 | D10: =C10+1 -> 2022 | E10: =D10+1 -> 2023 | F10: =E10+1 -> 2024 | G10: =F10+1 -> 2025 | H10: =G10+1 -> 2026 | I10: =H10+1 -> 2027 | J10: =I10+1 -> 2028 | K10: =J10+1 -> 2029 | ... Q10: =P10+1 -> 2035
C11: Aduited | D11: Aduited | E11: Aduited | F11: Aduited | G11: Aduited | H11: Forecasted | I11: Forecasted | J11: Forecasted | K11: Forecasted | L11: Forecasted | M11: Forecasted | N11: Forecasted | O11: Forecasted | P11: Forecasted | Q11: Forecasted
B13: Opening Balance | D13: =C15 -> 2492.12 | E13: =D15 -> 2586.95 | F13: =E15 -> 2907.31 | G13: =F15 -> 3622.67 | H13: =G15 -> 3847.79 | I13: =H15 -> 4136.4578 | J13: =I15 -> 4648.3808 | K13: =J15 -> 5177.6365 | ... Q13: =P15 -> 8486.2659
B14: New Issuance/ Repayment | D14: =D15-D13 -> 94.83 | E14: =E15-E13 -> 320.36 | F14: =F15-F13 -> 715.36 | G14: =G15-G13 -> 225.12 | H14: =H15-H13 -> 288.66779 | I14: =I15-I13 -> 511.92297 | J14: =J15-J13 -> 529.2557 | K14: =K15-K13 -> 542.35448 | ... Q14: =Q15-Q13 -> 539.00808
B15: Closing Balance | C15: ='Historical balance Sheet'!C52+'Historical balance Sheet'!C53+'Historical balance Sheet'!C61+'Historical balance Sheet'!C62 -> 2492.12 | D15: ='Historical balance Sheet'!D52+'Historical balance Sheet'!D53+'Historical balance Sheet'!D61+'Historical balance Sheet'!D62 -> 2586.95 | E15: ='Historical balance Sheet'!E52+'Historical balance Sheet'!E53+'Historical balance Sheet'!E61+'Historical balance Sheet'!E62 -> 2907.31 | F15: ='Historical balance Sheet'!F52+'Historical balance Sheet'!F53+'Historical balance Sheet'!F61+'Historical balance Sheet'!F62 -> 3622.67 | G15: ='Historical balance Sheet'!G52+'Historical balance Sheet'!G53+'Historical balance Sheet'!G61+'Historical balance Sheet'!G62 -> 3847.79 | H15: =Balance_Sheet!H36+Balance_Sheet!H38+Balance_Sheet!H48+Balance_Sheet!H50 -> 4136.4578 | I15: =Balance_Sheet!I36+Balance_Sheet!I38+Balance_Sheet!I48+Balance_Sheet!I50 -> 4648.3808 | J15: =Balance_Sheet!J36+Balance_Sheet!J38+Balance_Sheet!J48+Balance_Sheet!J50 -> 5177.6365 | K15: =Balance_Sheet!K36+Balance_Sheet!K38+Balance_Sheet!K48+Balance_Sheet!K50 -> 5719.9909 | L15: =Balance_Sheet!L36+Balance_Sheet!L38+Balance_Sheet!L48+Balance_Sheet!L50 -> 6271.2235 | M15: =Balance_Sheet!M36+Balance_Sheet!M38+Balance_Sheet!M48+Balance_Sheet!M50 -> 6827.2296 | N15: =Balance_Sheet!N36+Balance_Sheet!N38+Balance_Sheet!N48+Balance_Sheet!N50 -> 7384.1071 | O15: =Balance_Sheet!O36+Balance_Sheet!O38+Balance_Sheet!O48+Balance_Sheet!O50 -> 7938.2235 | ... Q15: =Balance_Sheet!Q36+Balance_Sheet!Q38+Balance_Sheet!Q48+Balance_Sheet!Q50 -> 9025.2739
B16: Interest rate | D16: ='Historical P&L'!D22/'Debt Schedules'!D13 -> 0.041061426 | E16: ='Historical P&L'!E22/'Debt Schedules'!E13 -> 0.065049576 | F16: ='Historical P&L'!F22/'Debt Schedules'!F13 -> 0.072737341 | G16: ='Historical P&L'!G22/'Debt Schedules'!G13 -> 0.076032319 | H16: =AVERAGE(D16:G16) -> 0.063720165 | I16: =H16 -> 0.063720165 | J16: =I16 -> 0.063720165 | K16: =J16 -> 0.063720165 | L16: =K16 -> 0.063720165 | M16: =L16 -> 0.063720165 | N16: =M16 -> 0.063720165 | O16: =N16 -> 0.063720165 | P16: =O16 -> 0.063720165 | Q16: =P16 -> 0.063720165
B17: Interest Expense | C17: ='Historical P&L'!C22 -> 86.37 | D17: ='Historical P&L'!D22 -> 102.33 | E17: ='Historical P&L'!E22 -> 168.28 | F17: ='Historical P&L'!F22 -> 211.47 | G17: ='Historical P&L'!G22 -> 275.44 | H17: =H16*H13 -> 245.18182 | I17: =I16*I13 -> 263.57577 | J17: =J16*J13 -> 296.19559 | K17: =K16*K13 -> 329.91985 | L17: =L16*L13 -> 364.47877 | M17: =M16*M13 -> 399.6034 | N17: =N16*N13 -> 435.0322 | O17: =O16*O13 -> 470.51653 | ... Q17: =Q16*Q13 -> 540.74626

Sheet Balance_Sheet
B7: BSE: 524208 | NSE: AARTIIND
B8: Balance _Sheet Forecasting
B9: All Figure In INR Cr.
B10: Particulars | C10: 2021 | D10: =C10+1 -> 2022 | E10: =D10+1 -> 2023 | F10: =E10+1 -> 2024 | G10: =F10+1 -> 2025 | H10: =G10+1 -> 2026 | I10: =H10+1 -> 2027 | J10: =I10+1 -> 2028 | K10: =J10+1 -> 2029 | ... Q10: =P10+1 -> 2035
C11: Aduited | D11: Aduited | E11: Aduited | F11: Aduited | G11: Aduited | H11: Forecasted | I11: Forecasted | J11: Forecasted | K11: Forecasted | L11: Forecasted | M11: Forecasted | N11: Forecasted | O11: Forecasted | P11: Forecasted | Q11: Forecasted
B12: Assets
B13: Non-Current Assets
B14: Investments | C14: ='Historical balance Sheet'!C20 -> 63.52 | D14: ='Historical balance Sheet'!D20 -> 28.29 | E14: ='Historical balance Sheet'!E20 -> 17.17 | F14: ='Historical balance Sheet'!F20 -> 22.92 | G14: ='Historical balance Sheet'!G20 -> 47.63 | H14: =H15*'Revenue Build_up'!H$18 -> 51.783168 | I14: =I15*'Revenue Build_up'!I$18 -> 58.19179 | J14: =J15*'Revenue Build_up'!J$18 -> 64.817395 | K14: =K15*'Revenue Build_up'!K$18 -> 71.60698 | L14: =L15*'Revenue Build_up'!L$18 -> 78.507708 | M14: =M15*'Revenue Build_up'!M$18 -> 85.468195 | N14: =N15*'Revenue Build_up'!N$18 -> 92.43959 | O14: =O15*'Revenue Build_up'!O$18 -> 99.376419 | ... Q14: =Q15*'Revenue Build_up'!Q$18 -> 112.9849
B15: % of Revenue | C15: =C14/'Revenue Build_up'!C$18 -> 0.014096447 | D15: =D14/'Revenue Build_up'!D$18 -> 0.0046487476 | E15: =E14/'Revenue Build_up'!E$18 -> 0.0025942121 | F15: =F14/'Revenue Build_up'!F$18 -> 0.0035976643 | G15: =G14/'Revenue Build_up'!G$18 -> 0.0065503925 | H15: =AVERAGE(C15:G15) -> 0.0062974927 | I15: =H15 -> 0.0062974927 | J15: =I15 -> 0.0062974927 | K15: =J15 -> 0.0062974927 | L15: =K15 -> 0.0062974927 | M15: =L15 -> 0.0062974927 | N15: =M15 -> 0.0062974927 | O15: =N15 -> 0.0062974927 | P15: =O15 -> 0.0062974927 | Q15: =P15 -> 0.0062974927
B16: Loans & Advances | C16: ='Historical balance Sheet'!C21 -> 320.07 | D16: ='Historical balance Sheet'!D21 -> 0 | E16: ='Historical balance Sheet'!E21 -> 0.01 | F16: ='Historical balance Sheet'!F21 -> 0.3 | G16: ='Historical balance Sheet'!G21 -> 0.06 | H16: =H17*'Revenue Build_up'!H$18 -> 0.11687169 | I16: =I17*'Revenue Build_up'!I$18 -> 0.13133558 | J16: =J17*'Revenue Build_up'!J$18 -> 0.1462892 | K16: =K17*'Revenue Build_up'!K$18 -> 0.16161291 | L16: =L17*'Revenue Build_up'!L$18 -> 0.17718746 | M16: =M17*'Revenue Build_up'!M$18 -> 0.19289689 | N16: =N17*'Revenue Build_up'!N$18 -> 0.20863094 | O16: =O17*'Revenue Build_up'!O$18 -> 0.22428697 | ... Q16: =Q17*'Revenue Build_up'!Q$18 -> 0.25500055
B17: % of Revenue | C17: =C16/'Revenue Build_up'!C$18 -> 0.071030381 | D17: =D16/'Revenue Build_up'!D$18 -> 0 | E17: =E16/'Revenue Build_up'!E$18 -> 1.5108981e-06 | F17: =F16/'Revenue Build_up'!F$18 -> 4.7089847e-05 | G17: =G16/'Revenue Build_up'!G$18 -> 8.2515967e-06 | H17: =AVERAGE(D17:G17) -> 1.4213086e-05 | I17: =H17 -> 1.4213086e-05 | J17: =I17 -> 1.4213086e-05 | K17: =J17 -> 1.4213086e-05 | L17: =K17 -> 1.4213086e-05 | M17: =L17 -> 1.4213086e-05 | N17: =M17 -> 1.4213086e-05 | O17: =N17 -> 1.4213086e-05 | P17: =O17 -> 1.4213086e-05 | Q17: =P17 -> 1.4213086e-05
B18: Deferred Tax Assets | C18: ='Historical balance Sheet'!C22 -> 0 | D18: ='Historical balance Sheet'!D22 -> 27.74 | E18: ='Historical balance Sheet'!E22 -> 52.78 | F18: ='Historical balance Sheet'!F22 -> 143.55 | G18: ='Historical balance Sheet'!G22 -> 217.99 | H18: =H19*'Revenue Build_up'!H$18 -> 106.97039 | I18: =I19*'Revenue Build_up'!I$18 -> 120.20891 | J18: =J19*'Revenue Build_up'!J$18 -> 133.89567 | K18: =K19*'Revenue Build_up'!K$18 -> 147.92116 | L18: =L19*'Revenue Build_up'!L$18 -> 162.17625 | M18: =M19*'Revenue Build_up'!M$18 -> 176.55478 | N18: =N19*'Revenue Build_up'!N$18 -> 190.95585 | O18: =O19*'Revenue Build_up'!O$18 -> 205.28551 | ... Q18: =Q19*'Revenue Build_up'!Q$18 -> 233.39705
B19: % of Revenue | C19: =C18/'Revenue Build_up'!C$18 -> 0 | D19: =D18/'Revenue Build_up'!D$18 -> 0.004558369 | E19: =E18/'Revenue Build_up'!E$18 -> 0.0079745202 | F19: =F18/'Revenue Build_up'!F$18 -> 0.022532492 | G19: =G18/'Revenue Build_up'!G$18 -> 0.029979426 | H19: =AVERAGE(C19:G19) -> 0.013008961 | I19: =H19 -> 0.013008961 | J19: =I19 -> 0.013008961 | K19: =J19 -> 0.013008961 | L19: =K19 -> 0.013008961 | M19: =L19 -> 0.013008961 | N19: =M19 -> 0.013008961 | O19: =N19 -> 0.013008961 | P19: =O19 -> 0.013008961 | Q19: =P19 -> 0.013008961
B20: Other Non-Current Assets | C20: ='Historical balance Sheet'!C23 -> 0 | D20: ='Historical balance Sheet'!D23 -> 155.19 | E20: ='Historical balance Sheet'!E23 -> 94.5 | F20: ='Historical balance Sheet'!F23 -> 110.89 | G20: ='Historical balance Sheet'!G23 -> 122.1 | H20: =H21*'Revenue Build_up'!H$18 -> 121.66082 | I20: =I21*'Revenue Build_up'!I$18 -> 136.71741 | J20: =J21*'Revenue Build_up'!J$18 -> 152.28379 | K20: =K21*'Revenue Build_up'!K$18 -> 168.23543 | L20: =L21*'Revenue Build_up'!L$18 -> 184.4482 | M20: =M21*'Revenue Build_up'!M$18 -> 200.80136 | N20: =N21*'Revenue Build_up'!N$18 -> 217.18015 | O20: =O21*'Revenue Build_up'!O$18 -> 233.47773 | ... Q20: =Q21*'Revenue Build_up'!Q$18 -> 265.44988
B21: % of Revenue | C21: =C20/'Revenue Build_up'!C$18 -> 0 | D21: =D20/'Revenue Build_up'!D$18 -> 0.02550156 | E21: =E20/'Revenue Build_up'!E$18 -> 0.014277987 | F21: =F20/'Revenue Build_up'!F$18 -> 0.017405977 | G21: =G20/'Revenue Build_up'!G$18 -> 0.016791999 | H21: =AVERAGE(C21:G21) -> 0.014795505 | I21: =H21 -> 0.014795505 | J21: =I21 -> 0.014795505 | K21: =J21 -> 0.014795505 | L21: =K21 -> 0.014795505 | M21: =L21 -> 0.014795505 | N21: =M21 -> 0.014795505 | O21: =N21 -> 0.014795505 | P21: =O21 -> 0.014795505 | Q21: =P21 -> 0.014795505
B23: Current Assets:
B24: Loans and Advances | C24: ='Historical balance Sheet'!C33 -> 0 | D24: ='Historical balance Sheet'!D33 -> 0 | E24: ='Historical balance Sheet'!E33 -> 32.03 | F24: ='Historical balance Sheet'!F33 -> 8.28 | G24: ='Historical balance Sheet'!G33 -> 6.27 | H24: =H25*'Revenue Build_up'!H$18 -> 11.514219 | I24: =I25*'Revenue Build_up'!I$18 -> 12.939205 | J24: =J25*'Revenue Build_up'!J$18 -> 14.412438 | K24: =K25*'Revenue Build_up'!K$18 -> 15.922132 | L24: =L25*'Revenue Build_up'!L$18 -> 17.45654 | M24: =M25*'Revenue Build_up'!M$18 -> 19.004235 | N24: =N25*'Revenue Build_up'!N$18 -> 20.554356 | O24: =O25*'Revenue Build_up'!O$18 -> 22.096791 | ... Q24: =Q25*'Revenue Build_up'!Q$18 -> 25.122698
B25: % of Revenue | C25: =C24/'Revenue Build_up'!C$18 -> 0 | D25: =D24/'Revenue Build_up'!D$18 -> 0 | E25: =E24/'Revenue Build_up'!E$18 -> 0.0048394066 | F25: =F24/'Revenue Build_up'!F$18 -> 0.0012996798 | G25: =G24/'Revenue Build_up'!G$18 -> 0.00086229185 | H25: =AVERAGE(C25:G25) -> 0.0014002757 | I25: =H25 -> 0.0014002757 | J25: =I25 -> 0.0014002757 | K25: =J25 -> 0.0014002757 | L25: =K25 -> 0.0014002757 | M25: =L25 -> 0.0014002757 | N25: =M25 -> 0.0014002757 | O25: =N25 -> 0.0014002757 | P25: =O25 -> 0.0014002757 | Q25: =P25 -> 0.0014002757
B26: Others Current Financial Assets | C26: ='Historical balance Sheet'!C34 -> 187.48 | D26: ='Historical balance Sheet'!D34 -> 407.3 | E26: ='Historical balance Sheet'!E34 -> 160.74 | F26: ='Historical balance Sheet'!F34 -> 16.71 | G26: ='Historical balance Sheet'!G34 -> 16.32 | H26: =H27*'Revenue Build_up'!H$18 -> 226.43815 | I26: =I27*'Revenue Build_up'!I$18 -> 254.46186 | J26: =J27*'Revenue Build_up'!J$18 -> 283.4344 | K26: =K27*'Revenue Build_up'!K$18 -> 313.12399 | L26: =L27*'Revenue Build_up'!L$18 -> 343.29959 | M26: =M27*'Revenue Build_up'!M$18 -> 373.7365 | N26: =N27*'Revenue Build_up'!N$18 -> 404.22111 | O26: =O27*'Revenue Build_up'!O$18 -> 434.55457 | ... Q26: =Q27*'Revenue Build_up'!Q$18 -> 494.06194
B27: % of Revenue | C27: =C26/'Revenue Build_up'!C$18 -> 0.041605823 | D27: =D26/'Revenue Build_up'!D$18 -> 0.066929477 | E27: =E26/'Revenue Build_up'!E$18 -> 0.024286176 | F27: =F26/'Revenue Build_up'!F$18 -> 0.0026229045 | G27: =G26/'Revenue Build_up'!G$18 -> 0.0022444343 | H27: =AVERAGE(C27:G27) -> 0.027537763 | I27: =H27 -> 0.027537763 | J27: =I27 -> 0.027537763 | K27: =J27 -> 0.027537763 | L27: =K27 -> 0.027537763 | M27: =L27 -> 0.027537763 | N27: =M27 -> 0.027537763 | O27: =N27 -> 0.027537763 | P27: =O27 -> 0.027537763 | Q27: =P27 -> 0.027537763
B28: Current Tax Assets (Net) | C28: ='Historical balance Sheet'!C35 -> 0 | D28: ='Historical balance Sheet'!D35 -> 55.42 | E28: ='Historical balance Sheet'!E35 -> 55.48 | F28: ='Historical balance Sheet'!F35 -> 71.16 | G28: ='Historical balance Sheet'!G35 -> 13.89 | H28: =H29*'Revenue Build_up'!H$18 -> 50.273185 | I28: =I29*'Revenue Build_up'!I$18 -> 56.494933 | J28: =J29*'Revenue Build_up'!J$18 -> 62.927337 | K28: =K29*'Revenue Build_up'!K$18 -> 69.51894 | L28: =L29*'Revenue Build_up'!L$18 -> 76.218444 | M28: =M29*'Revenue Build_up'!M$18 -> 82.975965 | N28: =N29*'Revenue Build_up'!N$18 -> 89.744076 | O28: =O29*'Revenue Build_up'!O$18 -> 96.478629 | ... Q28: =Q29*'Revenue Build_up'!Q$18 -> 109.69029
B29: % of Revenue | C29: =C28/'Revenue Build_up'!C$18 -> 0 | D29: =D28/'Revenue Build_up'!D$18 -> 0.0091068785 | E29: =E28/'Revenue Build_up'!E$18 -> 0.0083824627 | F29: =F28/'Revenue Build_up'!F$18 -> 0.011169712 | G29: =G28/'Revenue Build_up'!G$18 -> 0.0019102446 | H29: =AVERAGE(C29:G29) -> 0.0061138595 | I29: =H29 -> 0.0061138595 | J29: =I29 -> 0.0061138595 | K29: =J29 -> 0.0061138595 | L29: =K29 -> 0.0061138595 | M29: =L29 -> 0.0061138595 | N29: =M29 -> 0.0061138595 | O29: =N29 -> 0.0061138595 | P29: =O29 -> 0.0061138595 | Q29: =P29 -> 0.0061138595
B30: Other Current Assets | C30: ='Historical balance Sheet'!C36 -> 38.39 | D30: ='Historical balance Sheet'!D36 -> 36.91 | E30: ='Historical balance Sheet'!E36 -> 38.75 | F30: ='Historical balance Sheet'!F36 -> 332.84 | G30: ='Historical balance Sheet'!G36 -> 323.21 | H30: =H31*'Revenue Build_up'!H$18 -> 192.63461 | I30: =I31*'Revenue Build_up'!I$18 -> 216.47484 | J30: =J31*'Revenue Build_up'!J$18 -> 241.12225 | K30: =K31*'Revenue Build_up'!K$18 -> 266.37967 | L30: =L31*'Revenue Build_up'!L$18 -> 292.05054 | M30: =M31*'Revenue Build_up'!M$18 -> 317.94371 | N30: =N31*'Revenue Build_up'!N$18 -> 343.87747 | O30: =O31*'Revenue Build_up'!O$18 -> 369.68264 | ... Q30: =Q31*'Revenue Build_up'!Q$18 -> 420.30652
B31: % of Revenue | C31: =C30/'Revenue Build_up'!C$18 -> 0.0085195624 | D31: =D30/'Revenue Build_up'!D$18 -> 0.0060652271 | E31: =E30/'Revenue Build_up'!E$18 -> 0.0058547302 | F31: =F30/'Revenue Build_up'!F$18 -> 0.052244616 | G31: =G30/'Revenue Build_up'!G$18 -> 0.044449976 | H31: =AVERAGE(C31:G31) -> 0.023426822 | I31: =H31 -> 0.023426822 | J31: =I31 -> 0.023426822 | K31: =J31 -> 0.023426822 | L31: =K31 -> 0.023426822 | M31: =L31 -> 0.023426822 | N31: =M31 -> 0.023426822 | O31: =N31 -> 0.023426822 | P31: =O31 -> 0.023426822 | Q31: =P31 -> 0.023426822
B34: LIABILITIES
B35: Non-Current Liabilities:
B36: (i) Borrowings | C36: ='Historical balance Sheet'!C52 -> 1268.05 | D36: ='Historical balance Sheet'!D52 -> 929.85 | E36: ='Historical balance Sheet'!E52 -> 634.71 | F36: ='Historical balance Sheet'!F52 -> 1523.87 | G36: ='Historical balance Sheet'!G52 -> 1867.42 | H36: =H37*'Revenue Build_up'!H$18 -> 1687.519 | I36: =I37*'Revenue Build_up'!I$18 -> 1896.3643 | J36: =J37*'Revenue Build_up'!J$18 -> 2112.2806 | K36: =K37*'Revenue Build_up'!K$18 -> 2333.5408 | L36: =L37*'Revenue Build_up'!L$18 -> 2558.423 | M36: =M37*'Revenue Build_up'!M$18 -> 2785.2525 | N36: =N37*'Revenue Build_up'!N$18 -> 3012.4376 | O36: =O37*'Revenue Build_up'!O$18 -> 3238.4962 | ... Q36: =Q37*'Revenue Build_up'!Q$18 -> 3681.9718
B37: % of Revenue | C37: =C36/'Revenue Build_up'!C$18 -> 0.28140743 | D37: =D36/'Revenue Build_up'!D$18 -> 0.15279738 | E37: =E36/'Revenue Build_up'!E$18 -> 0.095898214 | F37: =F36/'Revenue Build_up'!F$18 -> 0.23919602 | G37: =G36/'Revenue Build_up'!G$18 -> 0.25681994 | H37: =AVERAGE(C37:G37) -> 0.2052238 | I37: =H37 -> 0.2052238 | J37: =I37 -> 0.2052238 | K37: =J37 -> 0.2052238 | L37: =K37 -> 0.2052238 | M37: =L37 -> 0.2052238 | N37: =M37 -> 0.2052238 | O37: =N37 -> 0.2052238 | P37: =O37 -> 0.2052238 | Q37: =P37 -> 0.2052238
B38: (ii) Lease Liabilities | C38: ='Historical balance Sheet'!C53 -> 0 | D38: ='Historical balance Sheet'!D53 -> 14.91 | E38: ='Historical balance Sheet'!E53 -> 25.26 | F38: ='Historical balance Sheet'!F53 -> 49.31 | G38: ='Historical balance Sheet'!G53 -> 47.13 | H38: =H39*'Revenue Build_up'!H$18 -> 33.694237 | I38: =I39*'Revenue Build_up'!I$18 -> 37.864194 | J38: =J39*'Revenue Build_up'!J$18 -> 42.175339 | K38: =K39*'Revenue Build_up'!K$18 -> 46.593181 | L38: =L39*'Revenue Build_up'!L$18 -> 51.083342 | M38: =M39*'Revenue Build_up'!M$18 -> 55.612387 | N38: =N39*'Revenue Build_up'!N$18 -> 60.148529 | O38: =O39*'Revenue Build_up'!O$18 -> 64.66218 | ... Q38: =Q39*'Revenue Build_up'!Q$18 -> 73.516939
B39: % of Revenue | C39: =C38/'Revenue Build_up'!C$18 -> 0 | D39: =D38/'Revenue Build_up'!D$18 -> 0.0024500822 | E39: =E38/'Revenue Build_up'!E$18 -> 0.0038165286 | F39: =F38/'Revenue Build_up'!F$18 -> 0.0077400013 | G39: =G38/'Revenue Build_up'!G$18 -> 0.0064816292 | H39: =AVERAGE(C39:G39) -> 0.0040976483 | I39: =H39 -> 0.0040976483 | J39: =I39 -> 0.0040976483 | K39: =J39 -> 0.0040976483 | L39: =K39 -> 0.0040976483 | M39: =L39 -> 0.0040976483 | N39: =M39 -> 0.0040976483 | O39: =N39 -> 0.0040976483 | P39: =O39 -> 0.0040976483 | Q39: =P39 -> 0.0040976483
B40: Other Non-Current Liabilitie | C40: ='Historical balance Sheet'!C54 -> 224.41 | D40: ='Historical balance Sheet'!D54 -> 223.58 | E40: ='Historical balance Sheet'!E54 -> 216.81 | F40: ='Historical balance Sheet'!F54 -> 175.29 | G40: ='Historical balance Sheet'!G54 -> 112.16 | H40: =H41*'Revenue Build_up'!H$18 -> 266.81166 | I40: =I41*'Revenue Build_up'!I$18 -> 299.83194 | J40: =J41*'Revenue Build_up'!J$18 -> 333.97023 | K40: =K41*'Revenue Build_up'!K$18 -> 368.95342 | L40: =L41*'Revenue Build_up'!L$18 -> 404.50927 | M40: =M41*'Revenue Build_up'!M$18 -> 440.37303 | N40: =N41*'Revenue Build_up'!N$18 -> 476.29299 | O40: =O41*'Revenue Build_up'!O$18 -> 512.03485 | ... Q40: =Q41*'Revenue Build_up'!Q$18 -> 582.15227
B41: % of Revenue | C41: =C40/'Revenue Build_up'!C$18 -> 0.04980138 | D41: =D40/'Revenue Build_up'!D$18 -> 0.036739731 | E41: =E40/'Revenue Build_up'!E$18 -> 0.032757782 | F41: =F40/'Revenue Build_up'!F$18 -> 0.027514598 | G41: =G40/'Revenue Build_up'!G$18 -> 0.015424985 | H41: =AVERAGE(C41:G41) -> 0.032447695 | I41: =H41 -> 0.032447695 | J41: =I41 -> 0.032447695 | K41: =J41 -> 0.032447695 | L41: =K41 -> 0.032447695 | M41: =L41 -> 0.032447695 | N41: =M41 -> 0.032447695 | O41: =N41 -> 0.032447695 | P41: =O41 -> 0.032447695 | Q41: =P41 -> 0.032447695
B42: Provisions | C42: ='Historical balance Sheet'!C56 -> 0 | D42: ='Historical balance Sheet'!D56 -> 0 | E42: ='Historical balance Sheet'!E56 -> 0 | F42: ='Historical balance Sheet'!F56 -> 13.76 | G42: ='Historical balance Sheet'!G56 -> 15.19 | H42: =H43*'Revenue Build_up'!H$18 -> 8.7344544 | I42: =I43*'Revenue Build_up'!I$18 -> 9.8154198 | J42: =J43*'Revenue Build_up'!J$18 -> 10.932985 | K42: =K43*'Revenue Build_up'!K$18 -> 12.078209 | L42: =L43*'Revenue Build_up'!L$18 -> 13.242179 | M42: =M43*'Revenue Build_up'!M$18 -> 14.41623 | N42: =N43*'Revenue Build_up'!N$18 -> 15.59212 | O42: =O43*'Revenue Build_up'!O$18 -> 16.76218 | ... Q42: =Q43*'Revenue Build_up'!Q$18 -> 19.057572
B43: % of Revenue | C43: =C42/'Revenue Build_up'!C$18 -> 0 | D43: =D42/'Revenue Build_up'!D$18 -> 0 | E43: =E42/'Revenue Build_up'!E$18 -> 0 | F43: =F42/'Revenue Build_up'!F$18 -> 0.0021598543 | G43: =G42/'Revenue Build_up'!G$18 -> 0.0020890292 | H43: =AVERAGE(D43:G43) -> 0.0010622209 | I43: =H43 -> 0.0010622209 | J43: =I43 -> 0.0010622209 | K43: =J43 -> 0.0010622209 | L43: =K43 -> 0.0010622209 | M43: =L43 -> 0.0010622209 | N43: =M43 -> 0.0010622209 | O43: =N43 -> 0.0010622209 | P43: =O43 -> 0.0010622209 | Q43: =P43 -> 0.0010622209
B44: Deferred Tax Liabilities (Net) | C44: ='Historical balance Sheet'!C55 -> 233.94 | D44: ='Historical balance Sheet'!D55 -> 0 | E44: ='Historical balance Sheet'!E55 -> 0 | F44: ='Historical balance Sheet'!F55 -> 0 | G44: ='Historical balance Sheet'!G55 -> 0 | H44: =H45*'Revenue Build_up'!H$18 -> 85.379695 | I44: =I45*'Revenue Build_up'!I$18 -> 95.946182 | J44: =J45*'Revenue Build_up'!J$18 -> 106.87043 | K44: =K45*'Revenue Build_up'!K$18 -> 118.06505 | L44: =L45*'Revenue Build_up'!L$18 -> 129.44291 | M44: =M45*'Revenue Build_up'!M$18 -> 140.91931 | N44: =N45*'Revenue Build_up'!N$18 -> 152.41369 | O44: =O45*'Revenue Build_up'!O$18 -> 163.85109 | ... Q44: =Q45*'Revenue Build_up'!Q$18 -> 186.28865
B45: % of Revenue | C45: =C44/'Revenue Build_up'!C$18 -> 0.051916291 | D45: =D44/'Revenue Build_up'!D$18 -> 0 | E45: =E44/'Revenue Build_up'!E$18 -> 0 | F45: =F44/'Revenue Build_up'!F$18 -> 0 | G45: =G44/'Revenue Build_up'!G$18 -> 0 | H45: =AVERAGE(C45:G45) -> 0.010383258 | I45: =H45 -> 0.010383258 | J45: =I45 -> 0.010383258 | K45: =J45 -> 0.010383258 | L45: =K45 -> 0.010383258 | M45: =L45 -> 0.010383258 | N45: =M45 -> 0.010383258 | O45: =N45 -> 0.010383258 | P45: =O45 -> 0.010383258 | Q45: =P45 -> 0.010383258
B47: Current Liabilities:
B48: (i) Borrowings | C48: ='Historical balance Sheet'!C61 -> 1224.07 | D48: ='Historical balance Sheet'!D61 -> 1638.12 | E48: ='Historical balance Sheet'!E61 -> 2239.32 | F48: ='Historical balance Sheet'!F61 -> 2040.42 | G48: ='Historical balance Sheet'!G61 -> 1922.13 | H48: =H49*'Revenue Build_up'!H$18 -> 2407.2978 | I48: =I49*'Revenue Build_up'!I$18 -> 2705.2221 | J48: =J49*'Revenue Build_up'!J$18 -> 3013.2334 | K48: =K49*'Revenue Build_up'!K$18 -> 3328.8679 | L48: =L49*'Revenue Build_up'!L$18 -> 3649.6692 | M48: =M49*'Revenue Build_up'!M$18 -> 3973.2486 | N48: =N49*'Revenue Build_up'!N$18 -> 4297.335 | O48: =O49*'Revenue Build_up'!O$18 -> 4619.8146 | ... Q48: =Q49*'Revenue Build_up'!Q$18 -> 5252.4462
B49: % of Revenue | C49: =C48/'Revenue Build_up'!C$18 -> 0.27164732 | D49: =D48/'Revenue Build_up'!D$18 -> 0.26918368 | E49: =E48/'Revenue Build_up'!E$18 -> 0.33833844 | F49: =F48/'Revenue Build_up'!F$18 -> 0.32027689 | G49: =G48/'Revenue Build_up'!G$18 -> 0.26434403 | H49: =AVERAGE(C49:G49) -> 0.29275807 | I49: =H49 -> 0.29275807 | J49: =I49 -> 0.29275807 | K49: =J49 -> 0.29275807 | L49: =K49 -> 0.29275807 | M49: =L49 -> 0.29275807 | N49: =M49 -> 0.29275807 | O49: =N49 -> 0.29275807 | P49: =O49 -> 0.29275807 | Q49: =P49 -> 0.29275807
B50: (ii) Lease Liabilities | C50: ='Historical balance Sheet'!C62 -> 0 | D50: ='Historical balance Sheet'!D62 -> 4.07 | E50: ='Historical balance Sheet'!E62 -> 8.02 | F50: ='Historical balance Sheet'!F62 -> 9.07 | G50: ='Historical balance Sheet'!G62 -> 11.11 | H50: =H51*'Revenue Build_up'!H$18 -> 7.9467759 | I50: =I51*'Revenue Build_up'!I$18 -> 8.9302592 | J50: =J51*'Revenue Build_up'!J$18 -> 9.9470414 | K50: =K51*'Revenue Build_up'!K$18 -> 10.988988 | L50: =L51*'Revenue Build_up'!L$18 -> 12.047991 | M50: =M51*'Revenue Build_up'!M$18 -> 13.116165 | N50: =N51*'Revenue Build_up'!N$18 -> 14.186013 | O50: =O51*'Revenue Build_up'!O$18 -> 15.250557 | ... Q50: =Q51*'Revenue Build_up'!Q$18 -> 17.338949
B51: % of Revenue | C51: =C50/'Revenue Build_up'!C$18 -> 0 | D51: =D50/'Revenue Build_up'!D$18 -> 0.00066880179 | E51: =E50/'Revenue Build_up'!E$18 -> 0.0012117403 | F51: =F50/'Revenue Build_up'!F$18 -> 0.0014236831 | G51: =G50/'Revenue Build_up'!G$18 -> 0.0015279207 | H51: =AVERAGE(C51:G51) -> 0.00096642916 | I51: =H51 -> 0.00096642916 | J51: =I51 -> 0.00096642916 | K51: =J51 -> 0.00096642916 | L51: =K51 -> 0.00096642916 | M51: =L51 -> 0.00096642916 | N51: =M51 -> 0.00096642916 | O51: =N51 -> 0.00096642916 | P51: =O51 -> 0.00096642916 | Q51: =P51 -> 0.00096642916
B52: (iv)Other Financial Liabilities | C52: ='Historical balance Sheet'!C66 -> 0 | D52: ='Historical balance Sheet'!D66 -> 2.23 | E52: ='Historical balance Sheet'!E66 -> 191.26 | F52: ='Historical balance Sheet'!F66 -> 136.56 | G52: ='Historical balance Sheet'!G66 -> 202.26 | H52: =H53*'Revenue Build_up'!H$18 -> 129.1235 | I52: =I53*'Revenue Build_up'!I$18 -> 145.10367 | J52: =J53*'Revenue Build_up'!J$18 -> 161.6249 | K52: =K53*'Revenue Build_up'!K$18 -> 178.55501 | L52: =L53*'Revenue Build_up'!L$18 -> 195.76227 | M52: =M53*'Revenue Build_up'!M$18 -> 213.11853 | N52: =N53*'Revenue Build_up'!N$18 -> 230.502 | O52: =O53*'Revenue Build_up'!O$18 -> 247.79927 | ... Q52: =Q53*'Revenue Build_up'!Q$18 -> 281.7326
B53: % of Revenue | C53: =C52/'Revenue Build_up'!C$18 -> 0 | D53: =D52/'Revenue Build_up'!D$18 -> 0.00036644423 | E53: =E52/'Revenue Build_up'!E$18 -> 0.028897437 | F53: =F52/'Revenue Build_up'!F$18 -> 0.021435299 | G53: =G52/'Revenue Build_up'!G$18 -> 0.027816132 | H53: =AVERAGE(C53:G53) -> 0.015703062 | I53: =H53 -> 0.015703062 | J53: =I53 -> 0.015703062 | K53: =J53 -> 0.015703062 | L53: =K53 -> 0.015703062 | M53: =L53 -> 0.015703062 | N53: =M53 -> 0.015703062 | O53: =N53 -> 0.015703062 | P53: =O53 -> 0.015703062 | Q53: =P53 -> 0.015703062
B54: Other Current Liabilities | C54: ='Historical balance Sheet'!C67 -> 559.62 | D54: ='Historical balance Sheet'!D67 -> 144.7 | E54: ='Historical balance Sheet'!E67 -> 99.26 | F54: ='Historical balance Sheet'!F67 -> 124.97 | G54: ='Historical balance Sheet'!G67 -> 77.51 | H54: =H55*'Revenue Build_up'!H$18 -> 317.79956 | I54: =I55*'Revenue Build_up'!I$18 -> 357.13004 | J54: =J55*'Revenue Build_up'!J$18 -> 397.79218 | K54: =K55*'Revenue Build_up'!K$18 -> 439.46069 | L54: =L55*'Revenue Build_up'!L$18 -> 481.81129 | M54: =M55*'Revenue Build_up'!M$18 -> 524.52864 | N54: =N55*'Revenue Build_up'!N$18 -> 567.31293 | O54: =O55*'Revenue Build_up'!O$18 -> 609.88509 | ... Q54: =Q55*'Revenue Build_up'!Q$18 -> 693.40199
B55: % of Revenue | C55: =C54/'Revenue Build_up'!C$18 -> 0.12419165 | D55: =D54/'Revenue Build_up'!D$18 -> 0.023777793 | E55: =E54/'Revenue Build_up'!E$18 -> 0.014997175 | F55: =F54/'Revenue Build_up'!F$18 -> 0.019616061 | G55: =G54/'Revenue Build_up'!G$18 -> 0.010659688 | H55: =AVERAGE(C55:G55) -> 0.038648474 | I55: =H55 -> 0.038648474 | J55: =I55 -> 0.038648474 | K55: =J55 -> 0.038648474 | L55: =K55 -> 0.038648474 | M55: =L55 -> 0.038648474 | N55: =M55 -> 0.038648474 | O55: =N55 -> 0.038648474 | P55: =O55 -> 0.038648474 | Q55: =P55 -> 0.038648474
B56: Provisions | C56: ='Historical balance Sheet'!C68 -> 40.12 | D56: ='Historical balance Sheet'!D68 -> 31.68 | E56: ='Historical balance Sheet'!E68 -> 29.86 | F56: ='Historical balance Sheet'!F68 -> 26.51 | G56: ='Historical balance Sheet'!G68 -> 15.91 | H56: =H57*'Revenue Build_up'!H$18 -> 41.064874 | I56: =I57*'Revenue Build_up'!I$18 -> 46.147012 | J56: =J57*'Revenue Build_up'!J$18 -> 51.401222 | K56: =K57*'Revenue Build_up'!K$18 -> 56.785471 | L56: =L57*'Revenue Build_up'!L$18 -> 62.257857 | M56: =M57*'Revenue Build_up'!M$18 -> 67.777634 | N56: =N57*'Revenue Build_up'!N$18 -> 73.306061 | O56: =O57*'Revenue Build_up'!O$18 -> 78.807076 | ... Q56: =Q57*'Revenue Build_up'!Q$18 -> 89.598819
B57: % of Revenue | C57: =C56/'Revenue Build_up'!C$18 -> 0.0089034864 | D57: =D56/'Revenue Build_up'!D$18 -> 0.0052058086 | E57: =E56/'Revenue Build_up'!E$18 -> 0.0045115418 | F57: =F56/'Revenue Build_up'!F$18 -> 0.0041611729 | G57: =G56/'Revenue Build_up'!G$18 -> 0.0021880484 | H57: =AVERAGE(C57:G57) -> 0.0049940116 | I57: =H57 -> 0.0049940116 | J57: =I57 -> 0.0049940116 | K57: =J57 -> 0.0049940116 | L57: =K57 -> 0.0049940116 | M57: =L57 -> 0.0049940116 | N57: =M57 -> 0.0049940116 | O57: =N57 -> 0.0049940116 | P57: =O57 -> 0.0049940116 | Q57: =P57 -> 0.0049940116

Sheet Income statement
B7: BSE: 524208 | NSE: AARTIIND
B8: Income Statement
B9: All Figure In INR Cr.
B10: Particulars | C10: 2021 | D10: =C10+1 -> 2022 | E10: =D10+1 -> 2023 | F10: =E10+1 -> 2024 | G10: =F10+1 -> 2025 | H10: =G10+1 -> 2026 | I10: =H10+1 -> 2027 | J10: =I10+1 -> 2028 | K10: =J10+1 -> 2029 | ... Q10: =P10+1 -> 2035
C11: Aduited | D11: Aduited | E11: Aduited | F11: Aduited | G11: Aduited | H11: Forecasted | I11: Forecasted | J11: Forecasted | K11: Forecasted | L11: Forecasted | M11: Forecasted | N11: Forecasted | O11: Forecasted | P11: Forecasted | Q11: Forecasted
B13: Revenue | C13: ='Historical P&L'!C14 -> 4506.1 | D13: ='Historical P&L'!D14 -> 6085.51 | E13: ='Historical P&L'!E14 -> 6618.58 | F13: ='Historical P&L'!F14 -> 6370.8 | G13: ='Historical P&L'!G14 -> 7271.32 | H13: ='Revenue Build_up'!H18 -> 8222.823 | I13: ='Revenue Build_up'!I18 -> 9240.4696 | J13: ='Revenue Build_up'!J18 -> 10292.572 | K13: ='Revenue Build_up'!K18 -> 11370.713 | L13: ='Revenue Build_up'!L18 -> 12466.502 | M13: ='Revenue Build_up'!M18 -> 13571.781 | N13: ='Revenue Build_up'!N18 -> 14678.793 | O13: ='Revenue Build_up'!O18 -> 15780.315 | ... Q13: ='Revenue Build_up'!Q18 -> 17941.252
B14: COGS | C14: =-SUM('Historical P&L'!C18:C20) -> -2128.56 | D14: =-SUM('Historical P&L'!D18:D20) -> -2854.45 | E14: =-SUM('Historical P&L'!E18:E20) -> -3841.67 | F14: =-SUM('Historical P&L'!F18:F20) -> -3881.88 | G14: =-SUM('Historical P&L'!G18:G20) -> -4655.12 | H14: =-'Cost Build_up'!H25 -> -4557.736 | I14: =-'Cost Build_up'!I25 -> -5121.7958 | J14: =-'Cost Build_up'!J25 -> -5704.9537 | K14: =-'Cost Build_up'!K25 -> -6302.5443 | L14: =-'Cost Build_up'!L25 -> -6909.9172 | M14: =-'Cost Build_up'!M25 -> -7522.5499 | N14: =-'Cost Build_up'!N25 -> -8136.1427 | O14: =-'Cost Build_up'!O25 -> -8746.6931 | ... Q14: =-'Cost Build_up'!Q25 -> -9944.4544
B15: Gross Profit | C15: =SUM(C13:C14) -> 2377.54 | D15: =SUM(D13:D14) -> 3231.06 | E15: =SUM(E13:E14) -> 2776.91 | F15: =SUM(F13:F14) -> 2488.92 | G15: =SUM(G13:G14) -> 2616.2 | H15: =SUM(H13:H14) -> 3665.0871 | I15: =SUM(I13:I14) -> 4118.6738 | J15: =SUM(J13:J14) -> 4587.618 | ... Q15: =SUM(Q13:Q14) -> 7996.7973
B16: Gross Margin | C16: =C15/C13 -> 0.52762699 | D16: =D15/D13 -> 0.53094317 | E16: =E15/E13 -> 0.41956281 | F16: =F15/F13 -> 0.39067621 | G16: =G15/G13 -> 0.35979712 | H16: =H15/H13 -> 0.44572126 | I16: =I15/I13 -> 0.44572126 | J16: =J15/J13 -> 0.44572126 | ... Q16: =Q15/Q13 -> 0.44572126
B18: Salaries & Benefits | C18: =-'Cost Build_up'!C30 -> -371.38 | D18: =-'Cost Build_up'!D30 -> -356.96 | E18: =-'Cost Build_up'!E30 -> -385.33 | F18: =-'Cost Build_up'!F30 -> -403.74 | G18: =-'Cost Build_up'!G30 -> -422.42 | H18: =-'Cost Build_up'!H30 -> -527.51298 | I18: =-'Cost Build_up'!I30 -> -592.79734 | J18: =-'Cost Build_up'!J30 -> -660.29211 | ... Q18: =-'Cost Build_up'!Q30 -> -1150.9725
B19: S&G Expenses | C19: =-'Cost Build_up'!C33 -> -1024.63 | D19: =-'Cost Build_up'!D33 -> -1153.99 | E19: =-'Cost Build_up'!E33 -> -1302.61 | F19: =-'Cost Build_up'!F33 -> -1111.03 | G19: =-'Cost Build_up'!G33 -> -1193.33 | H19: =-'Cost Build_up'!H33 -> -1566.1786 | I19: =-'Cost Build_up'!I33 -> -1760.0069 | J19: =-'Cost Build_up'!J33 -> -1960.3979 | ... Q19: =-'Cost Build_up'!Q33 -> -3417.221
B21: EBITDA | C21: =SUM(C15,C18,C19) -> 981.53 | D21: =SUM(D15,D18,D19) -> 1720.11 | E21: =SUM(E15,E18,E19) -> 1088.97 | F21: =SUM(F15,F18,F19) -> 974.15 | G21: =SUM(G15,G18,G19) -> 1000.45 | H21: =SUM(H15,H18,H19) -> 1571.3955 | I21: =SUM(I15,I18,I19) -> 1765.8695 | J21: =SUM(J15,J18,J19) -> 1966.928 | ... Q21: =SUM(Q15,Q18,Q19) -> 3428.6038
B22: EBITDA Margin | C22: =C21/C13 -> 0.21782251 | D22: =D21/D13 -> 0.28265667 | E22: =E21/E13 -> 0.16453227 | F22: =F21/F13 -> 0.15290858 | G22: =G21/G13 -> 0.1375885 | H22: =H21/H13 -> 0.19110171 | I22: =I21/I13 -> 0.19110171 | J22: =J21/J13 -> 0.19110171 | ... Q22: =Q21/Q13 -> 0.19110171
B24: Dep & Amortization | C24: =-'Historical P&L'!C23 -> -231.31 | D24: =-'Historical P&L'!D23 -> -246.4 | E24: =-'Historical P&L'!E23 -> -310.45 | F24: =-'Historical P&L'!F23 -> -378.12 | G24: =-'Historical P&L'!G23 -> -434.27 | H24: ='Dep and Capex Schedules'!H14 -> -469.52218 | I24: ='Dep and Capex Schedules'!I14 -> -504.86253 | J24: ='Dep and Capex Schedules'!J14 -> -548.71175 | K24: ='Dep and Capex Schedules'!K14 -> -601.45654 | L24: ='Dep and Capex Schedules'!L14 -> -663.41881 | M24: ='Dep and Capex Schedules'!M14 -> -734.84978 | N24: ='Dep and Capex Schedules'!N14 -> -815.92623 | O24: ='Dep and Capex Schedules'!O14 -> -906.74901 | ... Q24: ='Dep and Capex Schedules'!Q14 -> -1117.6624
B26: EBIT | C26: =C21+C24 -> 750.22 | D26: =D21+D24 -> 1473.71 | E26: =E21+E24 -> 778.52 | F26: =F21+F24 -> 596.03 | G26: =G21+G24 -> 566.18 | H26: =H21+H24 -> 1101.8733 | I26: =I21+I24 -> 1261.007 | J26: =J21+J24 -> 1418.2163 | ... Q26: =Q21+Q24 -> 2310.9414
B27: EBIT Margin | C27: =C26/C13 -> 0.16648987 | D27: =D26/D13 -> 0.24216705 | E27: =E26/E13 -> 0.11762644 | F27: =F26/F13 -> 0.093556539 | G27: =G26/G13 -> 0.077864817 | H27: =H26/H13 -> 0.13400183 | I27: =I26/I13 -> 0.13646568 | J27: =J26/J13 -> 0.13779027 | ... Q27: =Q26/Q13 -> 0.12880603
B29: Interest Cost | C29: =-'Debt Schedules'!C17 -> -86.37 | D29: =-'Debt Schedules'!D17 -> -102.33 | E29: =-'Debt Schedules'!E17 -> -168.28 | F29: =-'Debt Schedules'!F17 -> -211.47 | G29: =-'Debt Schedules'!G17 -> -275.44 | H29: =-'Debt Schedules'!H17 -> -245.18182 | I29: =-'Debt Schedules'!I17 -> -263.57577 | J29: =-'Debt Schedules'!J17 -> -296.19559 | ... Q29: =-'Debt Schedules'!Q17 -> -540.74626
B30: Other Income | C30: ='Revenue Build_up'!C21 -> 0.7 | D30: ='Revenue Build_up'!D21 -> 0.77 | E30: ='Revenue Build_up'!E21 -> 0.86 | F30: ='Revenue Build_up'!F21 -> 10.86 | G30: ='Revenue Build_up'!G21 -> 14.12 | H30: ='Revenue Build_up'!H21 -> 6.6742032 | I30: ='Revenue Build_up'!I21 -> 7.5001944 | J30: ='Revenue Build_up'!J21 -> 8.3541521 | ... Q30: ='Revenue Build_up'!Q21 -> 14.562342
B32: Profit before Expectional Items and tax | C32: =SUM(C26,C29,C30) -> 664.55 | D32: =SUM(D26,D29,D30) -> 1372.15 | E32: =SUM(E26,E29,E30) -> 611.1 | F32: =SUM(F26,F29,F30) -> 395.42 | G32: =SUM(G26,G29,G30) -> 304.86 | H32: =SUM(H26,H29,H30) -> 863.36572 | I32: =SUM(I26,I29,I30) -> 1004.9314 | J32: =SUM(J26,J29,J30) -> 1130.3748 | ... Q32: =SUM(Q26,Q29,Q30) -> 1784.7575
B34: Exceptional item | C34: ='Historical P&L'!C28 -> 0 | D34: ='Historical P&L'!D28 -> 0 | E34: ='Historical P&L'!E28 -> 0 | F34: ='Historical P&L'!F28 -> 0 | G34: ='Historical P&L'!G28 -> 2.37 | H34: ='Historical P&L'!H28 -> 0 | I34: ='Historical P&L'!I28 -> 0 | J34: ='Historical P&L'!J28 -> 0 | ... Q34: ='Historical P&L'!Q28 -> 0
B36: EBT | C36: =SUM(C32:C34) -> 664.55 | D36: =SUM(D32:D34) -> 1372.15 | E36: =SUM(E32:E34) -> 611.1 | F36: =SUM(F32:F34) -> 395.42 | G36: =SUM(G32:G34) -> 307.23 | H36: =SUM(H32:H34) -> 863.36572 | I36: =SUM(I32:I34) -> 1004.9314 | J36: =SUM(J32:J34) -> 1130.3748 | ... Q36: =SUM(Q32:Q34) -> 1784.7575
B37: EBT Margin | C37: =C36/C13 -> 0.14747786 | D37: =D36/D13 -> 0.22547823 | E37: =E36/E13 -> 0.092330983 | F37: =F36/F13 -> 0.062067558 | G37: =G36/G13 -> 0.042252301 | H37: =H36/H13 -> 0.10499627 | I37: =I36/I13 -> 0.10875328 | J37: =J36/J13 -> 0.10982433 | ... Q37: =Q36/Q13 -> 0.09947787
B39: Tax | C39: ='Historical P&L'!C30 -> -129.33 | D39: ='Historical P&L'!D30 -> -186.25 | E39: ='Historical P&L'!E30 -> -65.87 | F39: ='Historical P&L'!F30 -> 21.05 | G39: ='Historical P&L'!G30 -> 23.64 | H39: =-H36*'Cost Build_up'!H39 -> -53.072764 | I39: =-I36*'Cost Build_up'!I39 -> -61.775081 | J39: =-J36*'Cost Build_up'!J39 -> -69.486331 | K39: =-K36*'Cost Build_up'!K39 -> -76.890051 | L39: =-L36*'Cost Build_up'!L39 -> -83.884051 | M39: =-M36*'Cost Build_up'!M39 -> -90.373167 | N39: =-N36*'Cost Build_up'!N39 -> -96.271092 | O39: =-O36*'Cost Build_up'!O39 -> -101.50172 | ... Q39: =-Q36*'Cost Build_up'!Q39 -> -109.7125
B41: Profit After Tax Before Non Controlling Interest | C41: =SUM(C36,C39) -> 535.22 | D41: =SUM(D36,D39) -> 1185.9 | E41: =SUM(E36,E39) -> 545.23 | F41: =SUM(F36,F39) -> 416.47 | G41: =SUM(G36,G39) -> 330.87 | H41: =SUM(H36,H39) -> 810.29296 | I41: =SUM(I36,I39) -> 943.15631 | J41: =SUM(J36,J39) -> 1060.8885 | ... Q41: =SUM(Q36,Q39) -> 1675.045
B42: Profit attributable to Non Controlling Interest | C42: ='Historical P&L'!C32 -> -11.75 | D42: ='Historical P&L'!D32 -> -0.23 | E42: ='Historical P&L'!E32 -> 0 | F42: ='Historical P&L'!F32 -> 0 | G42: ='Historical P&L'!G32 -> 0 | H42: ='Historical P&L'!H32 -> 0 | I42: ='Historical P&L'!I32 -> 0 | J42: ='Historical P&L'!J32 -> 0 | ... Q42: ='Historical P&L'!Q32 -> 0
B44: Net Profit | C44: =SUM(C41,C42) -> 523.47 | D44: =SUM(D41,D42) -> 1185.67 | E44: =SUM(E41,E42) -> 545.23 | F44: =SUM(F41,F42) -> 416.47 | G44: =SUM(G41,G42) -> 330.87 | H44: =SUM(H41,H42) -> 810.29296 | I44: =SUM(I41,I42) -> 943.15631 | J44: =SUM(J41,J42) -> 1060.8885 | ... Q44: =SUM(Q41,Q42) -> 1675.045
B45: Net Profit Margin | C45: =C44/C13 -> 0.11616919 | D45: =D44/D13 -> 0.19483494 | E45: =E44/E13 -> 0.082378698 | F45: =F44/F13 -> 0.065371696 | G45: =G44/G13 -> 0.04550343 | H45: =H44/H13 -> 0.098541943 | I45: =I44/I13 -> 0.10206801 | J45: =J44/J13 -> 0.10307322 | ... Q45: =Q44/Q13 -> 0.093362772
B47: EPS in Rs. | C47: =C44/36.3 -> 14.420661 | D47: =D44/36.3 -> 32.663085 | E47: =E44/36.3 -> 15.02011 | F47: =F44/36.3 -> 11.473003 | G47: =G44/36.3 -> 9.114876 | H47: =H44/36.3 -> 22.32212 | I47: =I44/36.3 -> 25.982268 | J47: =J44/36.3 -> 29.225578 | ... Q47: =Q44/36.3 -> 46.14449
B49: Dividend | C49: -45.09 | D49: -126.88 | E49: -90.63 | F49: -54.38 | G49: -36.25 | H49: =-H44*H50 -> -97.154883 | I49: =-I44*I50 -> -113.08532 | J49: =-J44*J50 -> -127.20152 | K49: =-K44*K50 -> -140.75475 | L49: =-L44*L50 -> -153.55795 | M49: =-M44*M50 -> -165.43691 | N49: =-N44*N50 -> -176.23364 | O49: =-O44*O50 -> -185.80883 | ... Q49: =-Q44*Q50 -> -200.83946
B50: Dividend Payout % | C50: =-C49/C44 -> 0.086136741 | D50: =-D49/D44 -> 0.10701123 | E50: =-E49/E44 -> 0.16622343 | F50: =-F49/F44 -> 0.13057363 | G50: =-G49/G44 -> 0.10955965 | H50: =AVERAGE(C50:G50) -> 0.11990093 | I50: =H50 -> 0.11990093 | J50: =I50 -> 0.11990093 | K50: =J50 -> 0.11990093 | L50: =K50 -> 0.11990093 | M50: =L50 -> 0.11990093 | N50: =M50 -> 0.11990093 | O50: =N50 -> 0.11990093 | P50: =O50 -> 0.11990093 | Q50: =P50 -> 0.11990093
B52: Retained Earning | C52: =C44+C49 -> 478.38 | D52: =D44+D49 -> 1058.79 | E52: =E44+E49 -> 454.6 | F52: =F44+F49 -> 362.09 | G52: =G44+G49 -> 294.62 | H52: =H44+H49 -> 713.13808 | I52: =I44+I49 -> 830.07099 | J52: =J44+J49 -> 933.68697 | ... Q52: =Q44+Q49 -> 1474.2055
B53: Retained % | C53: =C52/C44 -> 0.91386326 | D53: =D52/D44 -> 0.89298877 | E53: =E52/E44 -> 0.83377657 | F53: =F52/F44 -> 0.86942637 | G53: =G52/G44 -> 0.89044035 | H53: =H52/H44 -> 0.88009907 | I53: =I52/I44 -> 0.88009907 | J53: =J52/J44 -> 0.88009907 | ... Q53: =Q52/Q44 -> 0.88009907

Sheet Balance Sheet
B7: BSE: 524208 | NSE: AARTIIND
B8: Balance Sheet
B9: All Figure In INR Cr.
B10: Master Check | C10: =IF(SUM(C72:Q72)=0,"Ok","Error") -> Ok
B11: Particulars | C11: 2021 | D11: =C11+1 -> 2022 | E11: =D11+1 -> 2023 | F11: =E11+1 -> 2024 | G11: =F11+1 -> 2025 | H11: =G11+1 -> 2026 | I11: =H11+1 -> 2027 | J11: =I11+1 -> 2028 | K11: =J11+1 -> 2029 | ... Q11: =P11+1 -> 2035
C12: Aduited | D12: Aduited | E12: Aduited | F12: Aduited | G12: Aduited | H12: Forecasted | I12: Forecasted | J12: Forecasted | K12: Forecasted | L12: Forecasted | M12: Forecasted | N12: Forecasted | O12: Forecasted | P12: Forecasted | Q12: Forecasted
B13: Assets
B14: Non-Current Assets
B15: Property Plant and Equipment | C15: =SUM('Historical balance Sheet'!C14:C18) -> 4890.49 | D15: =SUM('Historical balance Sheet'!D14:D18) -> 4940.64 | E15: =SUM('Historical balance Sheet'!E14:E18) -> 5957.17 | F15: =SUM('Historical balance Sheet'!F14:F18) -> 6878.45 | G15: =SUM('Historical balance Sheet'!G14:G18) -> 7831 | H15: ='Dep and Capex Schedules'!H15 -> 8420.4297 | I15: ='Dep and Capex Schedules'!I15 -> 9151.7759 | J15: ='Dep and Capex Schedules'!J15 -> 10031.488 | K15: ='Dep and Capex Schedules'!K15 -> 11064.936 | L15: ='Dep and Capex Schedules'!L15 -> 12256.308 | M15: ='Dep and Capex Schedules'!M15 -> 13608.555 | N15: ='Dep and Capex Schedules'!N15 -> 15123.357 | O15: ='Dep and Capex Schedules'!O15 -> 16801.14 | ... Q15: ='Dep and Capex Schedules'!Q15 -> 20641.314
B16: Financial Assets
B17: Investments | C17: ='Historical balance Sheet'!C20 -> 63.52 | D17: ='Historical balance Sheet'!D20 -> 28.29 | E17: ='Historical balance Sheet'!E20 -> 17.17 | F17: ='Historical balance Sheet'!F20 -> 22.92 | G17: ='Historical balance Sheet'!G20 -> 47.63 | H17: =VLOOKUP($B17,Balance_Sheet!$B$14:$Q$20,COUNTBLANK('Balance Sheet'!$H$10:H$10)+6,0) -> 51.783168 | I17: =VLOOKUP($B17,Balance_Sheet!$B$14:$Q$20,COUNTBLANK('Balance Sheet'!$H$10:I$10)+6,0) -> 58.19179 | J17: =VLOOKUP($B17,Balance_Sheet!$B$14:$Q$20,COUNTBLANK('Balance Sheet'!$H$10:J$10)+6,0) -> 64.817395 | K17: =VLOOKUP($B17,Balance_Sheet!$B$14:$Q$20,COUNTBLANK('Balance Sheet'!$H$10:K$10)+6,0) -> 71.60698 | L17: =VLOOKUP($B17,Balance_Sheet!$B$14:$Q$20,COUNTBLANK('Balance Sheet'!$H$10:L$10)+6,0) -> 78.507708 | M17: =VLOOKUP($B17,Balance_Sheet!$B$14:$Q$20,COUNTBLANK('Balance Sheet'!$H$10:M$10)+6,0) -> 85.468195 | N17: =VLOOKUP($B17,Balance_Sheet!$B$14:$Q$20,COUNTBLANK('Balance Sheet'!$H$10:N$10)+6,0) -> 92.43959 | O17: =VLOOKUP($B17,Balance_Sheet!$B$14:$Q$20,COUNTBLANK('Balance Sheet'!$H$10:O$10)+6,0) -> 99.376419 | ... Q17: =VLOOKUP($B17,Balance_Sheet!$B$14:$Q$20,COUNTBLANK('Balance Sheet'!$H$10:Q$10)+6,0) -> 112.9849
B18: Loans & Advances | C18: ='Historical balance Sheet'!C21 -> 320.07 | D18: ='Historical balance Sheet'!D21 -> 0 | E18: ='Historical balance Sheet'!E21 -> 0.01 | F18: ='Historical balance Sheet'!F21 -> 0.3 | G18: ='Historical balance Sheet'!G21 -> 0.06 | H18: =VLOOKUP($B18,Balance_Sheet!$B$14:$Q$20,COUNTBLANK('Balance Sheet'!$H$10:H$10)+6,0) -> 0.11687169 | I18: =VLOOKUP($B18,Balance_Sheet!$B$14:$Q$20,COUNTBLANK('Balance Sheet'!$H$10:I$10)+6,0) -> 0.13133558 | J18: =VLOOKUP($B18,Balance_Sheet!$B$14:$Q$20,COUNTBLANK('Balance Sheet'!$H$10:J$10)+6,0) -> 0.1462892 | K18: =VLOOKUP($B18,Balance_Sheet!$B$14:$Q$20,COUNTBLANK('Balance Sheet'!$H$10:K$10)+6,0) -> 0.16161291 | L18: =VLOOKUP($B18,Balance_Sheet!$B$14:$Q$20,COUNTBLANK('Balance Sheet'!$H$10:L$10)+6,0) -> 0.17718746 | M18: =VLOOKUP($B18,Balance_Sheet!$B$14:$Q$20,COUNTBLANK('Balance Sheet'!$H$10:M$10)+6,0) -> 0.19289689 | N18: =VLOOKUP($B18,Balance_Sheet!$B$14:$Q$20,COUNTBLANK('Balance Sheet'!$H$10:N$10)+6,0) -> 0.20863094 | O18: =VLOOKUP($B18,Balance_Sheet!$B$14:$Q$20,COUNTBLANK('Balance Sheet'!$H$10:O$10)+6,0) -> 0.22428697 | ... Q18: =VLOOKUP($B18,Balance_Sheet!$B$14:$Q$20,COUNTBLANK('Balance Sheet'!$H$10:Q$10)+6,0) -> 0.25500055
B19: Deferred Tax Assets | C19: ='Historical balance Sheet'!C22 -> 0 | D19: ='Historical balance Sheet'!D22 -> 27.74 | E19: ='Historical balance Sheet'!E22 -> 52.78 | F19: ='Historical balance Sheet'!F22 -> 143.55 | G19: ='Historical balance Sheet'!G22 -> 217.99 | H19: =VLOOKUP($B19,Balance_Sheet!$B$14:$Q$20,COUNTBLANK('Balance Sheet'!$H$10:H$10)+6,0) -> 106.97039 | I19: =VLOOKUP($B19,Balance_Sheet!$B$14:$Q$20,COUNTBLANK('Balance Sheet'!$H$10:I$10)+6,0) -> 120.20891 | J19: =VLOOKUP($B19,Balance_Sheet!$B$14:$Q$20,COUNTBLANK('Balance Sheet'!$H$10:J$10)+6,0) -> 133.89567 | K19: =VLOOKUP($B19,Balance_Sheet!$B$14:$Q$20,COUNTBLANK('Balance Sheet'!$H$10:K$10)+6,0) -> 147.92116 | L19: =VLOOKUP($B19,Balance_Sheet!$B$14:$Q$20,COUNTBLANK('Balance Sheet'!$H$10:L$10)+6,0) -> 162.17625 | M19: =VLOOKUP($B19,Balance_Sheet!$B$14:$Q$20,COUNTBLANK('Balance Sheet'!$H$10:M$10)+6,0) -> 176.55478 | N19: =VLOOKUP($B19,Balance_Sheet!$B$14:$Q$20,COUNTBLANK('Balance Sheet'!$H$10:N$10)+6,0) -> 190.95585 | O19: =VLOOKUP($B19,Balance_Sheet!$B$14:$Q$20,COUNTBLANK('Balance Sheet'!$H$10:O$10)+6,0) -> 205.28551 | ... Q19: =VLOOKUP($B19,Balance_Sheet!$B$14:$Q$20,COUNTBLANK('Balance Sheet'!$H$10:Q$10)+6,0) -> 233.39705
B20: Other Non-Current Assets | C20: ='Historical balance Sheet'!C23 -> 0 | D20: ='Historical balance Sheet'!D23 -> 155.19 | E20: ='Historical balance Sheet'!E23 -> 94.5 | F20: ='Historical balance Sheet'!F23 -> 110.89 | G20: ='Historical balance Sheet'!G23 -> 122.1 | H20: =VLOOKUP($B20,Balance_Sheet!$B$14:$Q$20,COUNTBLANK('Balance Sheet'!$H$10:H$10)+6,0) -> 121.66082 | I20: =VLOOKUP($B20,Balance_Sheet!$B$14:$Q$20,COUNTBLANK('Balance Sheet'!$H$10:I$10)+6,0) -> 136.71741 | J20: =VLOOKUP($B20,Balance_Sheet!$B$14:$Q$20,COUNTBLANK('Balance Sheet'!$H$10:J$10)+6,0) -> 152.28379 | K20: =VLOOKUP($B20,Balance_Sheet!$B$14:$Q$20,COUNTBLANK('Balance Sheet'!$H$10:K$10)+6,0) -> 168.23543 | L20: =VLOOKUP($B20,Balance_Sheet!$B$14:$Q$20,COUNTBLANK('Balance Sheet'!$H$10:L$10)+6,0) -> 184.4482 | M20: =VLOOKUP($B20,Balance_Sheet!$B$14:$Q$20,COUNTBLANK('Balance Sheet'!$H$10:M$10)+6,0) -> 200.80136 | N20: =VLOOKUP($B20,Balance_Sheet!$B$14:$Q$20,COUNTBLANK('Balance Sheet'!$H$10:N$10)+6,0) -> 217.18015 | O20: =VLOOKUP($B20,Balance_Sheet!$B$14:$Q$20,COUNTBLANK('Balance Sheet'!$H$10:O$10)+6,0) -> 233.47773 | ... Q20: =VLOOKUP($B20,Balance_Sheet!$B$14:$Q$20,COUNTBLANK('Balance Sheet'!$H$10:Q$10)+6,0) -> 265.44988
B22: Total Non-Current Assets | C22: =SUM(C15:C20) -> 5274.08 | D22: =SUM(D15:D20) -> 5151.86 | E22: =SUM(E15:E20) -> 6121.63 | F22: =SUM(F15:F20) -> 7156.11 | G22: =SUM(G15:G20) -> 8218.78 | H22: =SUM(H15:H20) -> 8700.9609 | I22: =SUM(I15:I20) -> 9467.0254 | J22: =SUM(J15:J20) -> 10382.631 | ... Q22: =SUM(Q15:Q20) -> 21253.401
B24: Current Assets:
B25: Inventories | C25: ='Historical balance Sheet'!C28 -> 935.68 | D25: ='Historical balance Sheet'!D28 -> 934.12 | E25: ='Historical balance Sheet'!E28 -> 1031.05 | F25: ='Historical balance Sheet'!F28 -> 1159.65 | G25: ='Historical balance Sheet'!G28 -> 1454.02 | H25: ='Working Capital Schedules'!H14 -> 1500.6825 | I25: ='Working Capital Schedules'!I14 -> 1686.4051 | J25: ='Working Capital Schedules'!J14 -> 1878.416 | K25: ='Working Capital Schedules'!K14 -> 2075.179 | L25: ='Working Capital Schedules'!L14 -> 2275.1629 | M25: ='Working Capital Schedules'!M14 -> 2476.8786 | N25: ='Working Capital Schedules'!N14 -> 2678.9105 | O25: ='Working Capital Schedules'!O14 -> 2879.9406 | ... Q25: ='Working Capital Schedules'!Q14 -> 3274.3161
B26: Financial Assets:
B27: Trade Receivables | C27: ='Historical balance Sheet'!C30 -> 793.73 | D27: ='Historical balance Sheet'!D30 -> 1091.52 | E27: ='Historical balance Sheet'!E30 -> 940.49 | F27: ='Historical balance Sheet'!F30 -> 854.18 | G27: ='Historical balance Sheet'!G30 -> 786.06 | H27: ='Working Capital Schedules'!H15 -> 1216.6315 | I27: ='Working Capital Schedules'!I15 -> 1367.2003 | J27: ='Working Capital Schedules'!J15 -> 1522.8671 | K27: ='Working Capital Schedules'!K15 -> 1682.3866 | L27: ='Working Capital Schedules'!L15 -> 1844.5173 | M27: ='Working Capital Schedules'!M15 -> 2008.052 | N27: ='Working Capital Schedules'!N15 -> 2171.8431 | O27: ='Working Capital Schedules'!O15 -> 2334.822 | ... Q27: ='Working Capital Schedules'!Q15 -> 2654.5496
B28: Cash and Cash Equivalents | C28: ='Historical balance Sheet'!C31 -> 412.32 | D28: ='Historical balance Sheet'!D31 -> 93.63 | E28: ='Historical balance Sheet'!E31 -> 167.45 | F28: ='Historical balance Sheet'!F31 -> 428.29 | G28: ='Historical balance Sheet'!G31 -> 199.39 | H28: ='Cashflow Statement'!H61 -> 225.13307 | I28: ='Cashflow Statement'!I61 -> 611.8822 | J28: ='Cashflow Statement'!J61 -> 963.63327 | K28: ='Cashflow Statement'!K61 -> 1268.5024 | L28: ='Cashflow Statement'!L61 -> 1514.4199 | M28: ='Cashflow Statement'!M61 -> 1689.3437 | N28: ='Cashflow Statement'!N61 -> 1781.4522 | O28: ='Cashflow Statement'!O61 -> 1779.3103 | ... Q28: ='Cashflow Statement'!Q61 -> 1449.2727
B29: Bank Balances | C29: ='Historical balance Sheet'!C32 -> 0 | D29: ='Historical balance Sheet'!D32 -> 79.93 | E29: ='Historical balance Sheet'!E32 -> 33.28 | F29: ='Historical balance Sheet'!F32 -> 87.95 | G29: ='Historical balance Sheet'!G32 -> 95.58 | H29: 0 | I29: 0 | J29: 0 | K29: 0 | L29: 0 | M29: 0 | N29: 0 | O29: 0 | P29: 0 | Q29: 0
B30: Loans and Advances | C30: ='Historical balance Sheet'!C33 -> 0 | D30: ='Historical balance Sheet'!D33 -> 0 | E30: ='Historical balance Sheet'!E33 -> 32.03 | F30: ='Historical balance Sheet'!F33 -> 8.28 | G30: ='Historical balance Sheet'!G33 -> 6.27 | H30: =VLOOKUP($B30,Balance_Sheet!$B$24:$Q$30,COUNTBLANK('Balance Sheet'!$H$10:H$10)+6,0) -> 11.514219 | I30: =VLOOKUP($B30,Balance_Sheet!$B$24:$Q$30,COUNTBLANK('Balance Sheet'!$H$10:I$10)+6,0) -> 12.939205 | J30: =VLOOKUP($B30,Balance_Sheet!$B$24:$Q$30,COUNTBLANK('Balance Sheet'!$H$10:J$10)+6,0) -> 14.412438 | K30: =VLOOKUP($B30,Balance_Sheet!$B$24:$Q$30,COUNTBLANK('Balance Sheet'!$H$10:K$10)+6,0) -> 15.922132 | L30: =VLOOKUP($B30,Balance_Sheet!$B$24:$Q$30,COUNTBLANK('Balance Sheet'!$H$10:L$10)+6,0) -> 17.45654 | M30: =VLOOKUP($B30,Balance_Sheet!$B$24:$Q$30,COUNTBLANK('Balance Sheet'!$H$10:M$10)+6,0) -> 19.004235 | N30: =VLOOKUP($B30,Balance_Sheet!$B$24:$Q$30,COUNTBLANK('Balance Sheet'!$H$10:N$10)+6,0) -> 20.554356 | O30: =VLOOKUP($B30,Balance_Sheet!$B$24:$Q$30,COUNTBLANK('Balance Sheet'!$H$10:O$10)+6,0) -> 22.096791 | ... Q30: =VLOOKUP($B30,Balance_Sheet!$B$24:$Q$30,COUNTBLANK('Balance Sheet'!$H$10:Q$10)+6,0) -> 25.122698
B31: Others Current Financial Assets | C31: ='Historical balance Sheet'!C34 -> 187.48 | D31: ='Historical balance Sheet'!D34 -> 407.3 | E31: ='Historical balance Sheet'!E34 -> 160.74 | F31: ='Historical balance Sheet'!F34 -> 16.71 | G31: ='Historical balance Sheet'!G34 -> 16.32 | H31: =VLOOKUP($B31,Balance_Sheet!$B$24:$Q$30,COUNTBLANK('Balance Sheet'!$H$10:H$10)+6,0) -> 226.43815 | I31: =VLOOKUP($B31,Balance_Sheet!$B$24:$Q$30,COUNTBLANK('Balance Sheet'!$H$10:I$10)+6,0) -> 254.46186 | J31: =VLOOKUP($B31,Balance_Sheet!$B$24:$Q$30,COUNTBLANK('Balance Sheet'!$H$10:J$10)+6,0) -> 283.4344 | K31: =VLOOKUP($B31,Balance_Sheet!$B$24:$Q$30,COUNTBLANK('Balance Sheet'!$H$10:K$10)+6,0) -> 313.12399 | L31: =VLOOKUP($B31,Balance_Sheet!$B$24:$Q$30,COUNTBLANK('Balance Sheet'!$H$10:L$10)+6,0) -> 343.29959 | M31: =VLOOKUP($B31,Balance_Sheet!$B$24:$Q$30,COUNTBLANK('Balance Sheet'!$H$10:M$10)+6,0) -> 373.7365 | N31: =VLOOKUP($B31,Balance_Sheet!$B$24:$Q$30,COUNTBLANK('Balance Sheet'!$H$10:N$10)+6,0) -> 404.22111 | O31: =VLOOKUP($B31,Balance_Sheet!$B$24:$Q$30,COUNTBLANK('Balance Sheet'!$H$10:O$10)+6,0) -> 434.55457 | ... Q31: =VLOOKUP($B31,Balance_Sheet!$B$24:$Q$30,COUNTBLANK('Balance Sheet'!$H$10:Q$10)+6,0) -> 494.06194
B32: Current Tax Assets (Net) | C32: ='Historical balance Sheet'!C35 -> 0 | D32: ='Historical balance Sheet'!D35 -> 55.42 | E32: ='Historical balance Sheet'!E35 -> 55.48 | F32: ='Historical balance Sheet'!F35 -> 71.16 | G32: ='Historical balance Sheet'!G35 -> 13.89 | H32: =VLOOKUP($B32,Balance_Sheet!$B$24:$Q$30,COUNTBLANK('Balance Sheet'!$H$10:H$10)+6,0) -> 50.273185 | I32: =VLOOKUP($B32,Balance_Sheet!$B$24:$Q$30,COUNTBLANK('Balance Sheet'!$H$10:I$10)+6,0) -> 56.494933 | J32: =VLOOKUP($B32,Balance_Sheet!$B$24:$Q$30,COUNTBLANK('Balance Sheet'!$H$10:J$10)+6,0) -> 62.927337 | K32: =VLOOKUP($B32,Balance_Sheet!$B$24:$Q$30,COUNTBLANK('Balance Sheet'!$H$10:K$10)+6,0) -> 69.51894 | L32: =VLOOKUP($B32,Balance_Sheet!$B$24:$Q$30,COUNTBLANK('Balance Sheet'!$H$10:L$10)+6,0) -> 76.218444 | M32: =VLOOKUP($B32,Balance_Sheet!$B$24:$Q$30,COUNTBLANK('Balance Sheet'!$H$10:M$10)+6,0) -> 82.975965 | N32: =VLOOKUP($B32,Balance_Sheet!$B$24:$Q$30,COUNTBLANK('Balance Sheet'!$H$10:N$10)+6,0) -> 89.744076 | O32: =VLOOKUP($B32,Balance_Sheet!$B$24:$Q$30,COUNTBLANK('Balance Sheet'!$H$10:O$10)+6,0) -> 96.478629 | ... Q32: =VLOOKUP($B32,Balance_Sheet!$B$24:$Q$30,COUNTBLANK('Balance Sheet'!$H$10:Q$10)+6,0) -> 109.69029
B33: Other Current Assets | C33: ='Historical balance Sheet'!C36 -> 38.39 | D33: ='Historical balance Sheet'!D36 -> 36.91 | E33: ='Historical balance Sheet'!E36 -> 38.75 | F33: ='Historical balance Sheet'!F36 -> 332.84 | G33: ='Historical balance Sheet'!G36 -> 323.21 | H33: =VLOOKUP($B33,Balance_Sheet!$B$24:$Q$30,COUNTBLANK('Balance Sheet'!$H$10:H$10)+6,0) -> 192.63461 | I33: =VLOOKUP($B33,Balance_Sheet!$B$24:$Q$30,COUNTBLANK('Balance Sheet'!$H$10:I$10)+6,0) -> 216.47484 | J33: =VLOOKUP($B33,Balance_Sheet!$B$24:$Q$30,COUNTBLANK('Balance Sheet'!$H$10:J$10)+6,0) -> 241.12225 | K33: =VLOOKUP($B33,Balance_Sheet!$B$24:$Q$30,COUNTBLANK('Balance Sheet'!$H$10:K$10)+6,0) -> 266.37967 | L33: =VLOOKUP($B33,Balance_Sheet!$B$24:$Q$30,COUNTBLANK('Balance Sheet'!$H$10:L$10)+6,0) -> 292.05054 | M33: =VLOOKUP($B33,Balance_Sheet!$B$24:$Q$30,COUNTBLANK('Balance Sheet'!$H$10:M$10)+6,0) -> 317.94371 | N33: =VLOOKUP($B33,Balance_Sheet!$B$24:$Q$30,COUNTBLANK('Balance Sheet'!$H$10:N$10)+6,0) -> 343.87747 | O33: =VLOOKUP($B33,Balance_Sheet!$B$24:$Q$30,COUNTBLANK('Balance Sheet'!$H$10:O$10)+6,0) -> 369.68264 | ... Q33: =VLOOKUP($B33,Balance_Sheet!$B$24:$Q$30,COUNTBLANK('Balance Sheet'!$H$10:Q$10)+6,0) -> 420.30652
B35: Total Current Assets | C35: =SUM(C25:C33) -> 2367.6 | D35: =SUM(D25:D33) -> 2698.83 | E35: =SUM(E25:E33) -> 2459.27 | F35: =SUM(F25:F33) -> 2959.06 | G35: =SUM(G25:G33) -> 2894.74 | H35: =SUM(H25:H33) -> 3423.3072 | I35: =SUM(I25:I33) -> 4205.8585 | J35: =SUM(J25:J33) -> 4966.8128 | ... Q35: =SUM(Q25:Q33) -> 8427.3199
B37: TOTAL ASSETS | C37: =C35+C22 -> 7641.68 | D37: =D35+D22 -> 7850.69 | E37: =E35+E22 -> 8580.9 | F37: =F35+F22 -> 10115.17 | G37: =G35+G22 -> 11113.52 | H37: =H35+H22 -> 12124.268 | I37: =I35+I22 -> 13672.884 | J37: =J35+J22 -> 15349.444 | ... Q37: =Q35+Q22 -> 29680.721
B39: EQUITY AND LIABILITIES
B40: EQUITY
B41: Equity Share Capital | C41: ='Historical balance Sheet'!C44 -> 87.12 | D41: ='Historical balance Sheet'!D44 -> 181.25 | E41: ='Historical balance Sheet'!E44 -> 181.25 | F41: ='Historical balance Sheet'!F44 -> 181.25 | G41: ='Historical balance Sheet'!G44 -> 181.26 | H41: =G41 -> 181.26 | I41: =H41 -> 181.26 | J41: =I41 -> 181.26 | K41: =J41 -> 181.26 | L41: =K41 -> 181.26 | M41: =L41 -> 181.26 | N41: =M41 -> 181.26 | O41: =N41 -> 181.26 | ... Q41: =P41 -> 181.26
B42: Other Equity | C42: ='Historical balance Sheet'!C45 -> 3415.78 | D42: ='Historical balance Sheet'!D45 -> 4334.73 | E42: ='Historical balance Sheet'!E45 -> 4738.83 | F42: ='Historical balance Sheet'!F45 -> 5108.52 | G42: ='Historical balance Sheet'!G45 -> 5423.86 | H42: =G42+'Income statement'!H44+'Income statement'!H49 -> 6136.9981 | I42: =H42+'Income statement'!I44+'Income statement'!I49 -> 6967.0691 | J42: =I42+'Income statement'!J44+'Income statement'!J49 -> 7900.756 | K42: =J42+'Income statement'!K44+'Income statement'!K49 -> 8933.9267 | L42: =K42+'Income statement'!L44+'Income statement'!L49 -> 10061.076 | M42: =L42+'Income statement'!M44+'Income statement'!M49 -> 11275.419 | N42: =M42+'Income statement'!N44+'Income statement'!N49 -> 12569.012 | O42: =N42+'Income statement'!O44+'Income statement'!O49 -> 13932.89 | ... Q42: =P42+'Income statement'!Q44+'Income statement'!Q49 -> 16831.416
B43: Non Controlling Interest | C43: ='Historical balance Sheet'!C46 -> 12.24 | D43: ='Historical balance Sheet'!D46 -> 0.72 | E43: ='Historical balance Sheet'!E46 -> 0.72 | F43: ='Historical balance Sheet'!F46 -> 0.72 | G43: ='Historical balance Sheet'!G46 -> 0.1 | H43: 0 | I43: 0 | J43: 0 | K43: 0 | L43: 0 | M43: 0 | N43: 0 | O43: 0 | P43: 0 | Q43: 0
B44: Total Equity | C44: =SUM(C41:C43) -> 3515.14 | D44: =SUM(D41:D43) -> 4516.7 | E44: =SUM(E41:E43) -> 4920.8 | F44: =SUM(F41:F43) -> 5290.49 | G44: =SUM(G41:G43) -> 5605.22 | H44: =SUM(H41:H43) -> 6318.2581 | I44: =SUM(I41:I43) -> 7148.3291 | J44: =SUM(J41:J43) -> 8082.016 | ... Q44: =SUM(Q41:Q43) -> 17012.676
B46: LIABILITIES
B47: Non-Current Liabilities:
B48: Financial Liabilities
B49: (i) Borrowings | C49: ='Historical balance Sheet'!C52 -> 1268.05 | D49: ='Historical balance Sheet'!D52 -> 929.85 | E49: ='Historical balance Sheet'!E52 -> 634.71 | F49: ='Historical balance Sheet'!F52 -> 1523.87 | G49: ='Historical balance Sheet'!G52 -> 1867.42 | H49: =VLOOKUP($B49,Balance_Sheet!$B$36:$Q$42,COUNTBLANK('Balance Sheet'!$H$10:H$10)+6,0) -> 1687.519 | I49: =VLOOKUP($B49,Balance_Sheet!$B$36:$Q$42,COUNTBLANK('Balance Sheet'!$H$10:I$10)+6,0) -> 1896.3643 | J49: =VLOOKUP($B49,Balance_Sheet!$B$36:$Q$42,COUNTBLANK('Balance Sheet'!$H$10:J$10)+6,0) -> 2112.2806 | K49: =VLOOKUP($B49,Balance_Sheet!$B$36:$Q$42,COUNTBLANK('Balance Sheet'!$H$10:K$10)+6,0) -> 2333.5408 | L49: =VLOOKUP($B49,Balance_Sheet!$B$36:$Q$42,COUNTBLANK('Balance Sheet'!$H$10:L$10)+6,0) -> 2558.423 | M49: =VLOOKUP($B49,Balance_Sheet!$B$36:$Q$42,COUNTBLANK('Balance Sheet'!$H$10:M$10)+6,0) -> 2785.2525 | N49: =VLOOKUP($B49,Balance_Sheet!$B$36:$Q$42,COUNTBLANK('Balance Sheet'!$H$10:N$10)+6,0) -> 3012.4376 | O49: =VLOOKUP($B49,Balance_Sheet!$B$36:$Q$42,COUNTBLANK('Balance Sheet'!$H$10:O$10)+6,0) -> 3238.4962 | ... Q49: =VLOOKUP($B49,Balance_Sheet!$B$36:$Q$42,COUNTBLANK('Balance Sheet'!$H$10:Q$10)+6,0) -> 3681.9718
B50: (ii) Lease Liabilities | C50: ='Historical balance Sheet'!C53 -> 0 | D50: ='Historical balance Sheet'!D53 -> 14.91 | E50: ='Historical balance Sheet'!E53 -> 25.26 | F50: ='Historical balance Sheet'!F53 -> 49.31 | G50: ='Historical balance Sheet'!G53 -> 47.13 | H50: =VLOOKUP($B50,Balance_Sheet!$B$36:$Q$42,COUNTBLANK('Balance Sheet'!$H$10:H$10)+6,0) -> 33.694237 | I50: =VLOOKUP($B50,Balance_Sheet!$B$36:$Q$42,COUNTBLANK('Balance Sheet'!$H$10:I$10)+6,0) -> 37.864194 | J50: =VLOOKUP($B50,Balance_Sheet!$B$36:$Q$42,COUNTBLANK('Balance Sheet'!$H$10:J$10)+6,0) -> 42.175339 | K50: =VLOOKUP($B50,Balance_Sheet!$B$36:$Q$42,COUNTBLANK('Balance Sheet'!$H$10:K$10)+6,0) -> 46.593181 | L50: =VLOOKUP($B50,Balance_Sheet!$B$36:$Q$42,COUNTBLANK('Balance Sheet'!$H$10:L$10)+6,0) -> 51.083342 | M50: =VLOOKUP($B50,Balance_Sheet!$B$36:$Q$42,COUNTBLANK('Balance Sheet'!$H$10:M$10)+6,0) -> 55.612387 | N50: =VLOOKUP($B50,Balance_Sheet!$B$36:$Q$42,COUNTBLANK('Balance Sheet'!$H$10:N$10)+6,0) -> 60.148529 | O50: =VLOOKUP($B50,Balance_Sheet!$B$36:$Q$42,COUNTBLANK('Balance Sheet'!$H$10:O$10)+6,0) -> 64.66218 | ... Q50: =VLOOKUP($B50,Balance_Sheet!$B$36:$Q$42,COUNTBLANK('Balance Sheet'!$H$10:Q$10)+6,0) -> 73.516939
B51: Other Non-Current Liabilitie | C51: ='Historical balance Sheet'!C54 -> 224.41 | D51: ='Historical balance Sheet'!D54 -> 223.58 | E51: ='Historical balance Sheet'!E54 -> 216.81 | F51: ='Historical balance Sheet'!F54 -> 175.29 | G51: ='Historical balance Sheet'!G54 -> 112.16 | H51: =VLOOKUP($B51,Balance_Sheet!$B$36:$Q$42,COUNTBLANK('Balance Sheet'!$H$10:H$10)+6,0) -> 266.81166 | I51: =VLOOKUP($B51,Balance_Sheet!$B$36:$Q$42,COUNTBLANK('Balance Sheet'!$H$10:I$10)+6,0) -> 299.83194 | J51: =VLOOKUP($B51,Balance_Sheet!$B$36:$Q$42,COUNTBLANK('Balance Sheet'!$H$10:J$10)+6,0) -> 333.97023 | K51: =VLOOKUP($B51,Balance_Sheet!$B$36:$Q$42,COUNTBLANK('Balance Sheet'!$H$10:K$10)+6,0) -> 368.95342 | L51: =VLOOKUP($B51,Balance_Sheet!$B$36:$Q$42,COUNTBLANK('Balance Sheet'!$H$10:L$10)+6,0) -> 404.50927 | M51: =VLOOKUP($B51,Balance_Sheet!$B$36:$Q$42,COUNTBLANK('Balance Sheet'!$H$10:M$10)+6,0) -> 440.37303 | N51: =VLOOKUP($B51,Balance_Sheet!$B$36:$Q$42,COUNTBLANK('Balance Sheet'!$H$10:N$10)+6,0) -> 476.29299 | O51: =VLOOKUP($B51,Balance_Sheet!$B$36:$Q$42,COUNTBLANK('Balance Sheet'!$H$10:O$10)+6,0) -> 512.03485 | ... Q51: =VLOOKUP($B51,Balance_Sheet!$B$36:$Q$42,COUNTBLANK('Balance Sheet'!$H$10:Q$10)+6,0) -> 582.15227
B52: Provisions | C52: ='Historical balance Sheet'!C56 -> 0 | D52: ='Historical balance Sheet'!D56 -> 0 | E52: ='Historical balance Sheet'!E56 -> 0 | F52: ='Historical balance Sheet'!F56 -> 13.76 | G52: ='Historical balance Sheet'!G56 -> 15.19 | H52: =VLOOKUP($B52,Balance_Sheet!$B$36:$Q$42,COUNTBLANK('Balance Sheet'!$H$10:H$10)+6,0) -> 8.7344544 | I52: =VLOOKUP($B52,Balance_Sheet!$B$36:$Q$42,COUNTBLANK('Balance Sheet'!$H$10:I$10)+6,0) -> 9.8154198 | J52: =VLOOKUP($B52,Balance_Sheet!$B$36:$Q$42,COUNTBLANK('Balance Sheet'!$H$10:J$10)+6,0) -> 10.932985 | K52: =VLOOKUP($B52,Balance_Sheet!$B$36:$Q$42,COUNTBLANK('Balance Sheet'!$H$10:K$10)+6,0) -> 12.078209 | L52: =VLOOKUP($B52,Balance_Sheet!$B$36:$Q$42,COUNTBLANK('Balance Sheet'!$H$10:L$10)+6,0) -> 13.242179 | M52: =VLOOKUP($B52,Balance_Sheet!$B$36:$Q$42,COUNTBLANK('Balance Sheet'!$H$10:M$10)+6,0) -> 14.41623 | N52: =VLOOKUP($B52,Balance_Sheet!$B$36:$Q$42,COUNTBLANK('Balance Sheet'!$H$10:N$10)+6,0) -> 15.59212 | O52: =VLOOKUP($B52,Balance_Sheet!$B$36:$Q$42,COUNTBLANK('Balance Sheet'!$H$10:O$10)+6,0) -> 16.76218 | ... Q52: =VLOOKUP($B52,Balance_Sheet!$B$36:$Q$42,COUNTBLANK('Balance Sheet'!$H$10:Q$10)+6,0) -> 19.057572
B53: Deferred Tax Liabilities (Net) | C53: =Balance_Sheet!C44 -> 233.94 | D53: =Balance_Sheet!D44 -> 0 | E53: =Balance_Sheet!E44 -> 0 | F53: =Balance_Sheet!F44 -> 0 | G53: =Balance_Sheet!G44 -> 0 | H53: =Balance_Sheet!H44 -> 85.379695 | I53: =Balance_Sheet!I44 -> 95.946182 | J53: =Balance_Sheet!J44 -> 106.87043 | ... Q53: =Balance_Sheet!Q44 -> 186.28865
B54: Total Non-Current Liabilities | C54: =SUM(C49:C53) -> 1726.4 | D54: =SUM(D49:D53) -> 1168.34 | E54: =SUM(E49:E53) -> 876.78 | F54: =SUM(F49:F53) -> 1762.23 | G54: =SUM(G49:G53) -> 2041.9 | H54: =SUM(H49:H53) -> 2082.139 | I54: =SUM(I49:I53) -> 2339.822 | J54: =SUM(J49:J53) -> 2606.2296 | ... Q54: =SUM(Q49:Q53) -> 4542.9872
B56: Current Liabilities:
B57: Financial Liabilities
B58: (i) Borrowings | C58: ='Historical balance Sheet'!C61 -> 1224.07 | D58: ='Historical balance Sheet'!D61 -> 1638.12 | E58: ='Historical balance Sheet'!E61 -> 2239.32 | F58: ='Historical balance Sheet'!F61 -> 2040.42 | G58: ='Historical balance Sheet'!G61 -> 1922.13 | H58: =Balance_Sheet!H48 -> 2407.2978 | I58: =Balance_Sheet!I48 -> 2705.2221 | J58: =Balance_Sheet!J48 -> 3013.2334 | K58: =Balance_Sheet!K48 -> 3328.8679 | L58: =Balance_Sheet!L48 -> 3649.6692 | M58: =Balance_Sheet!M48 -> 3973.2486 | N58: =Balance_Sheet!N48 -> 4297.335 | O58: =Balance_Sheet!O48 -> 4619.8146 | ... Q58: =Balance_Sheet!Q48 -> 5252.4462
B59: (ii) Lease Liabilities | C59: ='Historical balance Sheet'!C62 -> 0 | D59: ='Historical balance Sheet'!D62 -> 4.07 | E59: ='Historical balance Sheet'!E62 -> 8.02 | F59: ='Historical balance Sheet'!F62 -> 9.07 | G59: ='Historical balance Sheet'!G62 -> 11.11 | H59: =Balance_Sheet!H50 -> 7.9467759 | I59: =Balance_Sheet!I50 -> 8.9302592 | J59: =Balance_Sheet!J50 -> 9.9470414 | K59: =Balance_Sheet!K50 -> 10.988988 | L59: =Balance_Sheet!L50 -> 12.047991 | M59: =Balance_Sheet!M50 -> 13.116165 | N59: =Balance_Sheet!N50 -> 14.186013 | O59: =Balance_Sheet!O50 -> 15.250557 | ... Q59: =Balance_Sheet!Q50 -> 17.338949
B60: (iii) Trade Payables | C60: ='Historical balance Sheet'!C64+'Historical balance Sheet'!C65 -> 576.33 | D60: ='Historical balance Sheet'!D64+'Historical balance Sheet'!D65 -> 344.85 | E60: ='Historical balance Sheet'!E64+'Historical balance Sheet'!E65 -> 215.6 | F60: ='Historical balance Sheet'!F64+'Historical balance Sheet'!F65 -> 724.92 | G60: ='Historical balance Sheet'!G64+'Historical balance Sheet'!G65 -> 1237.48 | H60: ='Working Capital Schedules'!H16 -> 820.63851 | I60: ='Working Capital Schedules'!I16 -> 922.19973 | J60: ='Working Capital Schedules'!J16 -> 1027.1996 | K60: ='Working Capital Schedules'!K16 -> 1134.7982 | L60: ='Working Capital Schedules'!L16 -> 1244.1581 | M60: ='Working Capital Schedules'!M16 -> 1354.4651 | N60: ='Working Capital Schedules'!N16 -> 1464.9449 | O60: ='Working Capital Schedules'!O16 -> 1574.8769 | ... Q60: ='Working Capital Schedules'!Q16 -> 1790.5386
B61: (iv)Other Financial Liabilities | C61: ='Historical balance Sheet'!C66 -> 0 | D61: ='Historical balance Sheet'!D66 -> 2.23 | E61: ='Historical balance Sheet'!E66 -> 191.26 | F61: ='Historical balance Sheet'!F66 -> 136.56 | G61: ='Historical balance Sheet'!G66 -> 202.26 | H61: =Balance_Sheet!H52 -> 129.1235 | I61: =Balance_Sheet!I52 -> 145.10367 | J61: =Balance_Sheet!J52 -> 161.6249 | K61: =Balance_Sheet!K52 -> 178.55501 | L61: =Balance_Sheet!L52 -> 195.76227 | M61: =Balance_Sheet!M52 -> 213.11853 | N61: =Balance_Sheet!N52 -> 230.502 | O61: =Balance_Sheet!O52 -> 247.79927 | ... Q61: =Balance_Sheet!Q52 -> 281.7326
B62: Other Current Liabilities | C62: ='Historical balance Sheet'!C67 -> 559.62 | D62: ='Historical balance Sheet'!D67 -> 144.7 | E62: ='Historical balance Sheet'!E67 -> 99.26 | F62: ='Historical balance Sheet'!F67 -> 124.97 | G62: ='Historical balance Sheet'!G67 -> 77.51 | H62: =Balance_Sheet!H54 -> 317.79956 | I62: =Balance_Sheet!I54 -> 357.13004 | J62: =Balance_Sheet!J54 -> 397.79218 | K62: =Balance_Sheet!K54 -> 439.46069 | L62: =Balance_Sheet!L54 -> 481.81129 | M62: =Balance_Sheet!M54 -> 524.52864 | N62: =Balance_Sheet!N54 -> 567.31293 | O62: =Balance_Sheet!O54 -> 609.88509 | ... Q62: =Balance_Sheet!Q54 -> 693.40199
B63: Provisions | C63: ='Historical balance Sheet'!C68 -> 40.12 | D63: ='Historical balance Sheet'!D68 -> 31.68 | E63: ='Historical balance Sheet'!E68 -> 29.86 | F63: ='Historical balance Sheet'!F68 -> 26.51 | G63: ='Historical balance Sheet'!G68 -> 15.91 | H63: =Balance_Sheet!H56 -> 41.064874 | I63: =Balance_Sheet!I56 -> 46.147012 | J63: =Balance_Sheet!J56 -> 51.401222 | K63: =Balance_Sheet!K56 -> 56.785471 | L63: =Balance_Sheet!L56 -> 62.257857 | M63: =Balance_Sheet!M56 -> 67.777634 | N63: =Balance_Sheet!N56 -> 73.306061 | O63: =Balance_Sheet!O56 -> 78.807076 | ... Q63: =Balance_Sheet!Q56 -> 89.598819
B65: Total Current Liabilities | C65: =SUM(C58:C64) -> 2400.14 | D65: =SUM(D58:D64) -> 2165.65 | E65: =SUM(E58:E64) -> 2783.32 | F65: =SUM(F58:F64) -> 3062.45 | G65: =SUM(G58:G64) -> 3466.4 | H65: =SUM(H58:H64) -> 3723.871 | I65: =SUM(I58:I64) -> 4184.7328 | J65: =SUM(J58:J64) -> 4661.1984 | ... Q65: =SUM(Q58:Q64) -> 8125.0572
B67: Total Liabilities | C67: =C65+C54 -> 4126.54 | D67: =D65+D54 -> 3333.99 | E67: =E65+E54 -> 3660.1 | F67: =F65+F54 -> 4824.68 | G67: =G65+G54 -> 5508.3 | H67: =H65+H54 -> 5806.01 | I67: =I65+I54 -> 6524.5548 | J67: =J65+J54 -> 7267.428 | ... Q67: =Q65+Q54 -> 12668.044
B69: TOTAL EQUITY AND LIABILITIES | C69: =C44+C67 -> 7641.68 | D69: =D44+D67 -> 7850.69 | E69: =E44+E67 -> 8580.9 | F69: =F44+F67 -> 10115.17 | G69: =G44+G67 -> 11113.52 | H69: =H44+H67 -> 12124.268 | I69: =I44+I67 -> 13672.884 | J69: =J44+J67 -> 15349.444 | ... Q69: =Q44+Q67 -> 29680.721
B71: Check | C71: =C69=C37 -> TRUE | D71: =D69=D37 -> TRUE | E71: =E69=E37 -> TRUE | F71: =F69=F37 -> TRUE | G71: =G69=G37 -> TRUE | H71: =H69=H37 -> TRUE | I71: =I69=I37 -> TRUE | J71: =J69=J37 -> TRUE | ... Q71: =Q69=Q37 -> TRUE
B72: Check | C72: =C69-C37 -> 0 | D72: =D69-D37 -> 0 | E72: =E69-E37 -> 0 | F72: =F69-F37 -> 0 | G72: =G69-G37 -> 0 | H72: =H69-H37 -> 0 | I72: =I69-I37 -> 0 | J72: =J69-J37 -> 0 | ... Q72: =Q69-Q37 -> 0

Sheet Cashflow Statement
B7: BSE: 524208 | NSE: AARTIIND
B8: Cashflow statement
B10: Particulars | C10: 2021 | D10: =C10+1 -> 2022 | E10: =D10+1 -> 2023 | F10: =E10+1 -> 2024 | G10: =F10+1 -> 2025 | H10: =G10+1 -> 2026 | I10: =H10+1 -> 2027 | J10: =I10+1 -> 2028 | K10: =J10+1 -> 2029 | ... Q10: =P10+1 -> 2035
B12: Cash Flow from Operating Activities:
B13: Net Profit before Tax and Exceptional/Extraordinary Items | C13: 664.55 | D13: 1372.14 | E13: 611.1 | F13: 395.42 | G13: 304.86 | H13: ='Income statement'!H32 -> 863.36572 | I13: ='Income statement'!I32 -> 1004.9314 | J13: ='Income statement'!J32 -> 1130.3748 | K13: ='Income statement'!K32 -> 1250.8155 | L13: ='Income statement'!L32 -> 1364.591 | M13: ='Income statement'!M32 -> 1470.1532 | N13: ='Income statement'!N32 -> 1566.0982 | O13: ='Income statement'!O32 -> 1651.188 | ... Q13: ='Income statement'!Q32 -> 1784.7575
B14: Adjustments for:
B15: Finance Costs | C15: 86.37 | D15: 102.33 | E15: 168.28 | F15: 211.47 | G15: 275.44 | H15: =-'Income statement'!H29 -> 245.18182 | I15: =-'Income statement'!I29 -> 263.57577 | J15: =-'Income statement'!J29 -> 296.19559 | K15: =-'Income statement'!K29 -> 329.91985 | L15: =-'Income statement'!L29 -> 364.47877 | M15: =-'Income statement'!M29 -> 399.6034 | N15: =-'Income statement'!N29 -> 435.0322 | O15: =-'Income statement'!O29 -> 470.51653 | ... Q15: =-'Income statement'!Q29 -> 540.74626
B16: Depreciation | C16: 231.31 | D16: 246.4 | E16: 310.45 | F16: 378.12 | G16: 434.27 | H16: =-'Income statement'!H24 -> 469.52218 | I16: =-'Income statement'!I24 -> 504.86253 | J16: =-'Income statement'!J24 -> 548.71175 | K16: =-'Income statement'!K24 -> 601.45654 | L16: =-'Income statement'!L24 -> 663.41881 | M16: =-'Income statement'!M24 -> 734.84978 | N16: =-'Income statement'!N24 -> 815.92623 | O16: =-'Income statement'!O24 -> 906.74901 | ... Q16: =-'Income statement'!Q24 -> 1117.6624
B17: Loss on Sale of Assets | C17: 0 | D17: 0 | E17: 0 | F17: 12.48 | G17: 0 | H17: 0 | I17: 0 | J17: 0 | K17: 0 | L17: 0 | M17: 0 | N17: 0 | O17: 0 | P17: 0 | Q17: 0
B18: Unrealised Foreign Exchange | C18: 0 | D18: 0 | E18: 0 | F18: -8.62 | G18: 6.72 | H18: 0 | I18: 0 | J18: 0 | K18: 0 | L18: 0 | M18: 0 | N18: 0 | O18: 0 | P18: 0 | Q18: 0
B19: Consolidated Adjustments | C19: -5.26 | D19: -0.33 | E19: -0.61 | F19: -0.51 | G19: -1.09 | H19: 0 | I19: 0 | J19: 0 | K19: 0 | L19: 0 | M19: 0 | N19: 0 | O19: 0 | P19: 0 | Q19: 0
B20: Total | C20: =SUM(C13:C19) -> 976.97 | D20: =SUM(D13:D19) -> 1720.54 | E20: =SUM(E13:E19) -> 1089.22 | F20: =SUM(F13:F19) -> 988.36 | G20: =SUM(G13:G19) -> 1020.2 | H20: =SUM(H13:H19) -> 1578.0697 | I20: =SUM(I13:I19) -> 1773.3697 | J20: =SUM(J13:J19) -> 1975.2822 | ... Q20: =SUM(Q13:Q19) -> 3443.1662
B21: Profit on Sale of Investments/Assets | C21: -0.34 | D21: -0.61 | E21: -0.23 | F21: -8.5 | G21: -0.27 | H21: 0 | I21: 0 | J21: 0 | K21: 0 | L21: 0 | M21: 0 | N21: 0 | O21: 0 | P21: 0 | Q21: 0
B22: Interest Income | F22: -7.09 | G22: -14.95 | H22: =-'Income statement'!H30 -> -6.6742032 | I22: =-'Income statement'!I30 -> -7.5001944 | J22: =-'Income statement'!J30 -> -8.3541521 | K22: =-'Income statement'!K30 -> -9.2292448 | L22: =-'Income statement'!L30 -> -10.118662 | M22: =-'Income statement'!M30 -> -11.015782 | N22: =-'Income statement'!N30 -> -11.914308 | O22: =-'Income statement'!O30 -> -12.808378 | ... Q22: =-'Income statement'!Q30 -> -14.562342
B23: Dividend Received from other Investments | C23: -0.02 | D23: 0 | E23: 0 | F23: 0 | G23: 0 | H23: 0 | I23: 0 | J23: 0 | K23: 0 | L23: 0 | M23: 0 | N23: 0 | O23: 0 | P23: 0 | Q23: 0
B24: Lease Rent Received | C24: -0.05 | D24: 0 | E24: -0.06 | F24: -0.03 | G24: -0.06 | H24: 0 | I24: 0 | J24: 0 | K24: 0 | L24: 0 | M24: 0 | N24: 0 | O24: 0 | P24: 0 | Q24: 0
B25: Operating Profit before Working Capital Changes | C25: =SUM(C20:C24) -> 976.56 | D25: =SUM(D20:D24) -> 1719.93 | E25: =SUM(E20:E24) -> 1088.93 | F25: =SUM(F20:F24) -> 972.74 | G25: =SUM(G20:G24) -> 1004.92 | H25: =SUM(H20:H24) -> 1571.3955 | I25: =SUM(I20:I24) -> 1765.8695 | J25: =SUM(J20:J24) -> 1966.928 | ... Q25: =SUM(Q20:Q24) -> 3428.6038
B27: Adjustments for:
B28: (Increase)/Decrease in Trade and Other Receivables | C28: -25.01 | D28: -498.05 | E28: 421.99 | F28: 78.83 | G28: 43.77 | H28: =SUM('Balance Sheet'!G27,'Balance Sheet'!G30:G33)-SUM('Balance Sheet'!H27,'Balance Sheet'!H30:H33) -> -551.74166 | I28: =SUM('Balance Sheet'!H27,'Balance Sheet'!H30:H33)-SUM('Balance Sheet'!I27,'Balance Sheet'!I30:I33) -> -210.0795 | J28: =SUM('Balance Sheet'!I27,'Balance Sheet'!I30:I33)-SUM('Balance Sheet'!J27,'Balance Sheet'!J30:J33) -> -217.19238 | K28: =SUM('Balance Sheet'!J27,'Balance Sheet'!J30:J33)-SUM('Balance Sheet'!K27,'Balance Sheet'!K30:K33) -> -222.56777 | L28: =SUM('Balance Sheet'!K27,'Balance Sheet'!K30:K33)-SUM('Balance Sheet'!L27,'Balance Sheet'!L30:L33) -> -226.21109 | M28: =SUM('Balance Sheet'!L27,'Balance Sheet'!L30:L33)-SUM('Balance Sheet'!M27,'Balance Sheet'!M30:M33) -> -228.17006 | N28: =SUM('Balance Sheet'!M27,'Balance Sheet'!M30:M33)-SUM('Balance Sheet'!N27,'Balance Sheet'!N30:N33) -> -228.52763 | O28: =SUM('Balance Sheet'!N27,'Balance Sheet'!N30:N33)-SUM('Balance Sheet'!O27,'Balance Sheet'!O30:O33) -> -227.39454 | ... Q28: =SUM('Balance Sheet'!P27,'Balance Sheet'!P30:P33)-SUM('Balance Sheet'!Q27,'Balance Sheet'!Q30:Q33) -> -221.1945
B29: Increase/(Decrease) in Trade Payables and Other Current Liabilities | C29: 128.78 | D29: -37.73 | E29: -13.31 | F29: 388.23 | G29: 480.77 | H29: =SUM('Balance Sheet'!H58:H63)-SUM('Balance Sheet'!G58:G63) -> 257.47103 | I29: =SUM('Balance Sheet'!I58:I63)-SUM('Balance Sheet'!H58:H63) -> 460.86174 | J29: =SUM('Balance Sheet'!J58:J63)-SUM('Balance Sheet'!I58:I63) -> 476.46563 | K29: =SUM('Balance Sheet'!K58:K63)-SUM('Balance Sheet'!J58:J63) -> 488.25788 | L29: =SUM('Balance Sheet'!L58:L63)-SUM('Balance Sheet'!K58:K63) -> 496.25041 | M29: =SUM('Balance Sheet'!M58:M63)-SUM('Balance Sheet'!L58:L63) -> 500.5479 | N29: =SUM('Balance Sheet'!N58:N63)-SUM('Balance Sheet'!M58:M63) -> 501.33232 | O29: =SUM('Balance Sheet'!O58:O63)-SUM('Balance Sheet'!N58:N63) -> 498.84659 | ... Q29: =SUM('Balance Sheet'!Q58:Q63)-SUM('Balance Sheet'!P58:P63) -> 485.24527
B30: (Increase)/Decrease in Inventories | C30: -111 | D30: -419.66 | E30: -96.92 | F30: -144.56 | G30: -294.38 | H30: ='Balance Sheet'!G25-'Balance Sheet'!H25 -> -46.662481 | I30: ='Balance Sheet'!H25-'Balance Sheet'!I25 -> -185.72263 | J30: ='Balance Sheet'!I25-'Balance Sheet'!J25 -> -192.01084 | K30: ='Balance Sheet'!J25-'Balance Sheet'!K25 -> -196.763 | L30: ='Balance Sheet'!K25-'Balance Sheet'!L25 -> -199.98391 | M30: ='Balance Sheet'!L25-'Balance Sheet'!M25 -> -201.71576 | N30: ='Balance Sheet'!M25-'Balance Sheet'!N25 -> -202.03187 | O30: ='Balance Sheet'!N25-'Balance Sheet'!O25 -> -201.03015 | ... Q30: ='Balance Sheet'!P25-'Balance Sheet'!Q25 -> -195.54895
B31: Cash Generated from Operations | C31: =SUM(C25:C30) -> 969.33 | D31: =SUM(D25:D30) -> 764.49 | E31: =SUM(E25:E30) -> 1400.69 | F31: =SUM(F25:F30) -> 1295.24 | G31: =SUM(G25:G30) -> 1235.08 | H31: =SUM(H25:H30) -> 1230.4624 | I31: =SUM(I25:I30) -> 1830.9291 | J31: =SUM(J25:J30) -> 2034.1904 | ... Q31: =SUM(Q25:Q30) -> 3497.1056
B32: Direct Taxes Paid | C32: -96.62 | D32: -245.84 | E32: -90.89 | F32: -85.67 | G32: 6.85 | H32: ='Income statement'!H39 -> -53.072764 | I32: ='Income statement'!I39 -> -61.775081 | J32: ='Income statement'!J39 -> -69.486331 | K32: ='Income statement'!K39 -> -76.890051 | L32: ='Income statement'!L39 -> -83.884051 | M32: ='Income statement'!M39 -> -90.373167 | N32: ='Income statement'!N39 -> -96.271092 | O32: ='Income statement'!O39 -> -101.50172 | ... Q32: ='Income statement'!Q39 -> -109.7125
B34: Net Cash Flow from Operating Activities (A) | C34: =SUM(C31:C32) -> 872.71 | D34: =SUM(D31:D32) -> 518.65 | E34: =SUM(E31:E32) -> 1309.8 | F34: =SUM(F31:F32) -> 1209.57 | G34: =SUM(G31:G32) -> 1241.93 | H34: =SUM(H31:H32) -> 1177.3896 | I34: =SUM(I31:I32) -> 1769.154 | J34: =SUM(J31:J32) -> 1964.7041 | ... Q34: =SUM(Q31:Q32) -> 3387.3931
B36: Cash Flow from Investing Activities:
B37: Addition to Property, Plant & Equipment/Capital WIP | C37: -1314.82 | D37: -1165.42 | E37: -1326.3 | F37: -1328.06 | G37: -1385.97 | H37: =-'Dep and Capex Schedules'!H13 -> -1058.9518 | I37: =-'Dep and Capex Schedules'!I13 -> -1236.2088 | J37: =-'Dep and Capex Schedules'!J13 -> -1428.424 | K37: =-'Dep and Capex Schedules'!K13 -> -1634.9042 | L37: =-'Dep and Capex Schedules'!L13 -> -1854.7915 | M37: =-'Dep and Capex Schedules'!M13 -> -2087.0961 | N37: =-'Dep and Capex Schedules'!N13 -> -2330.7285 | O37: =-'Dep and Capex Schedules'!O13 -> -2584.532 | ... Q37: =-'Dep and Capex Schedules'!Q13 -> -3117.8671
B38: Sale/Written off of Property, Plant & Equipment | C38: 0.43 | D38: 0.42 | F38: 21.98 | G38: 7.1 | H38: 0 | I38: 0 | J38: 0 | K38: 0 | L38: 0 | M38: 0 | N38: 0 | O38: 0 | P38: 0 | Q38: 0
B39: (Increase)/Decrease in Other Investments | C39: -7.82 | D39: -5 | E39: -3.54 | F39: -15.57 | G39: -2.72 | H39: =SUM('Balance Sheet'!G17,'Balance Sheet'!G20)-SUM('Balance Sheet'!H17,'Balance Sheet'!H20)+('Balance Sheet'!G18-'Balance Sheet'!H18) -> -3.7708574 | I39: =SUM('Balance Sheet'!H17,'Balance Sheet'!H20)-SUM('Balance Sheet'!I17,'Balance Sheet'!I20)+('Balance Sheet'!H18-'Balance Sheet'!I18) -> -21.47968 | J39: =SUM('Balance Sheet'!I17,'Balance Sheet'!I20)-SUM('Balance Sheet'!J17,'Balance Sheet'!J20)+('Balance Sheet'!I18-'Balance Sheet'!J18) -> -22.206941 | K39: =SUM('Balance Sheet'!J17,'Balance Sheet'!J20)-SUM('Balance Sheet'!K17,'Balance Sheet'!K20)+('Balance Sheet'!J18-'Balance Sheet'!K18) -> -22.75655 | L39: =SUM('Balance Sheet'!K17,'Balance Sheet'!K20)-SUM('Balance Sheet'!L17,'Balance Sheet'!L20)+('Balance Sheet'!K18-'Balance Sheet'!L18) -> -23.129063 | M39: =SUM('Balance Sheet'!L17,'Balance Sheet'!L20)-SUM('Balance Sheet'!M17,'Balance Sheet'!M20)+('Balance Sheet'!L18-'Balance Sheet'!M18) -> -23.329358 | N39: =SUM('Balance Sheet'!M17,'Balance Sheet'!M20)-SUM('Balance Sheet'!N17,'Balance Sheet'!N20)+('Balance Sheet'!M18-'Balance Sheet'!N18) -> -23.365918 | O39: =SUM('Balance Sheet'!N17,'Balance Sheet'!N20)-SUM('Balance Sheet'!O17,'Balance Sheet'!O20)+('Balance Sheet'!N18-'Balance Sheet'!O18) -> -23.250065 | ... Q39: =SUM('Balance Sheet'!P17,'Balance Sheet'!P20)-SUM('Balance Sheet'!Q17,'Balance Sheet'!Q20)+('Balance Sheet'!P18-'Balance Sheet'!Q18) -> -22.616139
B40: Dividend Received from Other Investments | C40: 0.02 | D40: 0.52 | E40: 0 | F40: 0 | G40: 0 | H40: ='Balance Sheet'!H43-'Balance Sheet'!G43 -> -0.1 | I40: ='Balance Sheet'!I43-'Balance Sheet'!H43 -> 0 | J40: ='Balance Sheet'!J43-'Balance Sheet'!I43 -> 0 | K40: ='Balance Sheet'!K43-'Balance Sheet'!J43 -> 0 | L40: ='Balance Sheet'!L43-'Balance Sheet'!K43 -> 0 | M40: ='Balance Sheet'!M43-'Balance Sheet'!L43 -> 0 | N40: ='Balance Sheet'!N43-'Balance Sheet'!M43 -> 0 | O40: ='Balance Sheet'!O43-'Balance Sheet'!N43 -> 0 | ... Q40: ='Balance Sheet'!Q43-'Balance Sheet'!P43 -> 0
B41: (Increase)/Decrease in Other Bank Balance | C41: 0 | D41: ='Balance Sheet'!C29-'Balance Sheet'!D29 -> -79.93 | E41: ='Balance Sheet'!D29-'Balance Sheet'!E29 -> 46.65 | F41: ='Balance Sheet'!E29-'Balance Sheet'!F29 -> -54.67 | G41: ='Balance Sheet'!F29-'Balance Sheet'!G29 -> -7.63 | H41: ='Balance Sheet'!G29-'Balance Sheet'!H29 -> 95.58 | I41: ='Balance Sheet'!H29-'Balance Sheet'!I29 -> 0 | J41: ='Balance Sheet'!I29-'Balance Sheet'!J29 -> 0 | K41: ='Balance Sheet'!J29-'Balance Sheet'!K29 -> 0 | ... Q41: ='Balance Sheet'!P29-'Balance Sheet'!Q29 -> 0
B42: Investment in Joint Venture | C42: 0 | D42: 0 | E42: 0 | F42: 0 | G42: -23.45 | H42: 0 | I42: 0 | J42: 0 | K42: 0 | L42: 0 | M42: 0 | N42: 0 | O42: 0 | P42: 0 | Q42: 0
B43: Interest Income | C43: 0 | D43: 0 | E43: 0 | F43: 7.09 | G43: 14.95 | H43: ='Income statement'!H30 -> 6.6742032 | I43: ='Income statement'!I30 -> 7.5001944 | J43: ='Income statement'!J30 -> 8.3541521 | K43: ='Income statement'!K30 -> 9.2292448 | L43: ='Income statement'!L30 -> 10.118662 | M43: ='Income statement'!M30 -> 11.015782 | N43: ='Income statement'!N30 -> 11.914308 | O43: ='Income statement'!O30 -> 12.808378 | ... Q43: ='Income statement'!Q30 -> 14.562342
B44: Profit on Sale of Investments | C44: 0 | D44: 0 | E44: 0 | F44: 0 | G44: 0 | H44: 0 | I44: 0 | J44: 0 | K44: 0 | L44: 0 | M44: 0 | N44: 0 | O44: 0 | P44: 0 | Q44: 0
B45: Lease Rent Received | C45: 0.05 | D45: 0.05 | E45: 0.06 | F45: 0.03 | G45: 0.06 | H45: 0 | I45: 0 | J45: 0 | K45: 0 | L45: 0 | M45: 0 | N45: 0 | O45: 0 | P45: 0 | Q45: 0
B46: Deferref Taxes | C46: 0 | D46: 0 | E46: 0 | F46: 0 | G46: 0 | H46: ='Balance Sheet'!G19-'Balance Sheet'!H19 -> 111.01961 | I46: ='Balance Sheet'!H19-'Balance Sheet'!I19 -> -13.238525 | J46: ='Balance Sheet'!I19-'Balance Sheet'!J19 -> -13.686756 | K46: ='Balance Sheet'!J19-'Balance Sheet'!K19 -> -14.025495 | L46: ='Balance Sheet'!K19-'Balance Sheet'!L19 -> -14.255085 | M46: ='Balance Sheet'!L19-'Balance Sheet'!M19 -> -14.378533 | N46: ='Balance Sheet'!M19-'Balance Sheet'!N19 -> -14.401066 | O46: ='Balance Sheet'!N19-'Balance Sheet'!O19 -> -14.329662 | ... Q46: ='Balance Sheet'!P19-'Balance Sheet'!Q19 -> -13.938956
B47: Net Cash Flow from Investing Activities (B) | C47: =SUM(C37:C46) -> -1322.14 | D47: =SUM(D37:D46) -> -1249.36 | E47: =SUM(E37:E46) -> -1283.13 | F47: =SUM(F37:F46) -> -1369.2 | G47: =SUM(G37:G46) -> -1397.66 | H47: =SUM(H37:H46) -> -849.54888 | I47: =SUM(I37:I46) -> -1263.4268 | J47: =SUM(J37:J46) -> -1455.9635 | ... Q47: =SUM(Q37:Q46) -> -3139.8599
B49: Cash Flow from Financing Activities:
B50: Proceeds of Long-Term Borrowings | C50: 1007.99 | D50: -594.54 | E50: -300.9 | F50: 1291.88 | G50: 592.7 | H50: ='Balance Sheet'!H49-'Balance Sheet'!G49 -> -179.90103 | I50: ='Balance Sheet'!I49-'Balance Sheet'!H49 -> 208.84529 | J50: ='Balance Sheet'!J49-'Balance Sheet'!I49 -> 215.91639 | K50: ='Balance Sheet'!K49-'Balance Sheet'!J49 -> 221.2602 | L50: ='Balance Sheet'!L49-'Balance Sheet'!K49 -> 224.88211 | M50: ='Balance Sheet'!M49-'Balance Sheet'!L49 -> 226.82957 | N50: ='Balance Sheet'!N49-'Balance Sheet'!M49 -> 227.18504 | O50: ='Balance Sheet'!O49-'Balance Sheet'!N49 -> 226.0586 | ... Q50: ='Balance Sheet'!Q49-'Balance Sheet'!P49 -> 219.89499
B51: Repayment of Long-Term Borrowings | C51: -256.48 | D51: 0 | E51: 0 | F51: -402.71 | G51: -454.97 | H51: 0 | I51: 0 | J51: 0 | K51: 0 | L51: 0 | M51: 0 | N51: 0 | O51: 0 | P51: 0 | Q51: 0
B52: Proceeds/(Repayment) of Other Borrowings | C52: -5.59 | D52: 49.08 | E52: 606.96 | F52: -193.67 | G52: 110.76 | H52: =SUM('Balance Sheet'!H51:H53)-SUM('Balance Sheet'!G51:G53) -> 233.5758 | I52: =SUM('Balance Sheet'!I51:I53)-SUM('Balance Sheet'!H51:H53) -> 44.667737 | J52: =SUM('Balance Sheet'!J51:J53)-SUM('Balance Sheet'!I51:I53) -> 46.180101 | K52: =SUM('Balance Sheet'!K51:K53)-SUM('Balance Sheet'!J51:J53) -> 47.323032 | L52: =SUM('Balance Sheet'!L51:L53)-SUM('Balance Sheet'!K51:K53) -> 48.097686 | M52: =SUM('Balance Sheet'!M51:M53)-SUM('Balance Sheet'!L51:L53) -> 48.514208 | N52: =SUM('Balance Sheet'!N51:N53)-SUM('Balance Sheet'!M51:M53) -> 48.590235 | O52: =SUM('Balance Sheet'!O51:O53)-SUM('Balance Sheet'!N51:N53) -> 48.349313 | ... Q52: =SUM('Balance Sheet'!Q51:Q53)-SUM('Balance Sheet'!P51:P53) -> 47.031043
B53: Increase in Equity through QIP Allotment (Net of Expenses) | C53: 0 | D53: 1186.69 | E53: 0 | F53: 0 | G53: 0.01 | H53: 0 | I53: ='Balance Sheet'!I43-'Balance Sheet'!H43 -> 0 | J53: ='Balance Sheet'!J43-'Balance Sheet'!I43 -> 0 | K53: ='Balance Sheet'!K43-'Balance Sheet'!J43 -> 0 | L53: ='Balance Sheet'!L43-'Balance Sheet'!K43 -> 0 | M53: ='Balance Sheet'!M43-'Balance Sheet'!L43 -> 0 | N53: ='Balance Sheet'!N43-'Balance Sheet'!M43 -> 0 | O53: ='Balance Sheet'!O43-'Balance Sheet'!N43 -> 0 | P53: ='Balance Sheet'!P43-'Balance Sheet'!O43 -> 0 | Q53: ='Balance Sheet'!Q43-'Balance Sheet'!P43 -> 0
B54: Finance Costs | C54: -86.37 | D54: -102.33 | E54: -168.28 | F54: -211.47 | G54: -275.44 | H54: ='Income statement'!H29 -> -245.18182 | I54: ='Income statement'!I29 -> -263.57577 | J54: ='Income statement'!J29 -> -296.19559 | K54: ='Income statement'!K29 -> -329.91985 | L54: ='Income statement'!L29 -> -364.47877 | M54: ='Income statement'!M29 -> -399.6034 | N54: ='Income statement'!N29 -> -435.0322 | O54: ='Income statement'!O29 -> -470.51653 | ... Q54: ='Income statement'!Q29 -> -540.74626
B55: Dividend Paid | C55: -45.09 | D55: -126.88 | E55: -90.63 | F55: -54.38 | G55: -36.25 | H55: ='Income statement'!H49 -> -97.154883 | I55: ='Income statement'!I49 -> -113.08532 | J55: ='Income statement'!J49 -> -127.20152 | K55: ='Income statement'!K49 -> -140.75475 | L55: ='Income statement'!L49 -> -153.55795 | M55: ='Income statement'!M49 -> -165.43691 | N55: ='Income statement'!N49 -> -176.23364 | O55: ='Income statement'!O49 -> -185.80883 | ... Q55: ='Income statement'!Q49 -> -200.83946
B56: Principal Repayment of Lease Liability | C56: 0 | D56: 0 | E56: 0 | F56: -9.19 | G56: -9.97 | H56: ='Balance Sheet'!H50-'Balance Sheet'!G50 -> -13.435763 | I56: ='Balance Sheet'!I50-'Balance Sheet'!H50 -> 4.1699576 | J56: ='Balance Sheet'!J50-'Balance Sheet'!I50 -> 4.3111444 | K56: ='Balance Sheet'!K50-'Balance Sheet'!J50 -> 4.4178427 | L56: ='Balance Sheet'!L50-'Balance Sheet'!K50 -> 4.4901605 | M56: ='Balance Sheet'!M50-'Balance Sheet'!L50 -> 4.5290449 | N56: ='Balance Sheet'!N50-'Balance Sheet'!M50 -> 4.5361425 | O56: ='Balance Sheet'!O50-'Balance Sheet'!N50 -> 4.5136512 | ... Q56: ='Balance Sheet'!Q50-'Balance Sheet'!P50 -> 4.390584
B57: Net Cash Flow from Financing Activities (C ) | C57: =SUM(C50:C56) -> 614.46 | D57: =SUM(D50:D56) -> 412.02 | E57: =SUM(E50:E56) -> 47.15 | F57: =SUM(F50:F56) -> 420.46 | G57: =SUM(G50:G56) -> -73.16 | H57: =SUM(H50:H56) -> -302.09769 | I57: =SUM(I50:I56) -> -118.97811 | J57: =SUM(J50:J56) -> -156.98948 | ... Q57: =SUM(Q50:Q56) -> -470.26911
B59: Net Increase/(Decrease) in Cash and Cash Equivalents (A+B+C) | C59: =C57+C47+C34 -> 165.03 | D59: =D57+D47+D34 -> -318.69 | E59: =E57+E47+E34 -> 73.82 | F59: =F57+F47+F34 -> 260.83 | G59: =G57+G47+G34 -> -228.89 | H59: =H57+H47+H34 -> 25.743069 | I59: =I57+I47+I34 -> 386.74913 | J59: =J57+J47+J34 -> 351.75107 | ... Q59: =Q57+Q47+Q34 -> -222.73586
B60: Cash and Cash Equivalents (Opening Balance) | C60: 247.29 | D60: =C61 -> 412.32 | E60: =D61 -> 93.63 | F60: =E61 -> 167.45 | G60: =F61 -> 428.28 | H60: =G61 -> 199.39 | I60: =H61 -> 225.13307 | J60: =I61 -> 611.8822 | K60: =J61 -> 963.63327 | ... Q60: =P61 -> 1672.0086
B61: Cash and Cash Equivalents (Closing Balance) | C61: =SUM(C59:C60) -> 412.32 | D61: =SUM(D59:D60) -> 93.63 | E61: =SUM(E59:E60) -> 167.45 | F61: =SUM(F59:F60) -> 428.28 | G61: =SUM(G59:G60) -> 199.39 | H61: =SUM(H59:H60) -> 225.13307 | I61: =SUM(I59:I60) -> 611.8822 | J61: =SUM(J59:J60) -> 963.63327 | ... Q61: =SUM(Q59:Q60) -> 1449.2727

Sheet Common Size Statement
B9: BSE: 524208 | NSE: AARTIIND
B10: Common Size Statement
B11: All Figure In INR Cr.
B12: Particulars | C12: 2021 | D12: =C12+1 -> 2022 | E12: =D12+1 -> 2023 | F12: =E12+1 -> 2024 | G12: =F12+1 -> 2025 | H12: =G12+1 -> 2026 | I12: =H12+1 -> 2027 | J12: =I12+1 -> 2028 | K12: =J12+1 -> 2029 | ... Q12: =P12+1 -> 2035
C13: Audited | D13: Audited | E13: Audited | F13: Audited | G13: Audited | H13: Forecasted | I13: Forecasted | J13: Forecasted | K13: Forecasted | L13: Forecasted | M13: Forecasted | N13: Forecasted | O13: Forecasted | P13: Forecasted | Q13: Forecasted
B15: Income Statement
B16: Revenue | C16: ='Income statement'!C13/'Income statement'!C$13 -> 1 | D16: ='Income statement'!D13/'Income statement'!D$13 -> 1 | E16: ='Income statement'!E13/'Income statement'!E$13 -> 1 | F16: ='Income statement'!F13/'Income statement'!F$13 -> 1 | G16: ='Income statement'!G13/'Income statement'!G$13 -> 1 | H16: ='Income statement'!H13/'Income statement'!H$13 -> 1 | I16: ='Income statement'!I13/'Income statement'!I$13 -> 1 | J16: ='Income statement'!J13/'Income statement'!J$13 -> 1 | ... Q16: ='Income statement'!Q13/'Income statement'!Q$13 -> 1
B17: COGS | C17: =-'Income statement'!C14/'Income statement'!C$13 -> 0.47237301 | D17: =-'Income statement'!D14/'Income statement'!D$13 -> 0.46905683 | E17: =-'Income statement'!E14/'Income statement'!E$13 -> 0.58043719 | F17: =-'Income statement'!F14/'Income statement'!F$13 -> 0.60932379 | G17: =-'Income statement'!G14/'Income statement'!G$13 -> 0.64020288 | H17: =-'Income statement'!H14/'Income statement'!H$13 -> 0.55427874 | I17: =-'Income statement'!I14/'Income statement'!I$13 -> 0.55427874 | J17: =-'Income statement'!J14/'Income statement'!J$13 -> 0.55427874 | ... Q17: =-'Income statement'!Q14/'Income statement'!Q$13 -> 0.55427874
B18: Gross Profit | C18: ='Income statement'!C15/'Income statement'!C$13 -> 0.52762699 | D18: ='Income statement'!D15/'Income statement'!D$13 -> 0.53094317 | E18: ='Income statement'!E15/'Income statement'!E$13 -> 0.41956281 | F18: ='Income statement'!F15/'Income statement'!F$13 -> 0.39067621 | G18: ='Income statement'!G15/'Income statement'!G$13 -> 0.35979712 | H18: ='Income statement'!H15/'Income statement'!H$13 -> 0.44572126 | I18: ='Income statement'!I15/'Income statement'!I$13 -> 0.44572126 | J18: ='Income statement'!J15/'Income statement'!J$13 -> 0.44572126 | ... Q18: ='Income statement'!Q15/'Income statement'!Q$13 -> 0.44572126
B21: Salaries & Benefits | C21: =-'Income statement'!C18/'Income statement'!C$13 -> 0.082417168 | D21: =-'Income statement'!D18/'Income statement'!D$13 -> 0.058657368 | E21: =-'Income statement'!E18/'Income statement'!E$13 -> 0.058219437 | F21: =-'Income statement'!F18/'Income statement'!F$13 -> 0.063373517 | G21: =-'Income statement'!G18/'Income statement'!G$13 -> 0.058093991 | H21: =-'Income statement'!H18/'Income statement'!H$13 -> 0.064152296 | I21: =-'Income statement'!I18/'Income statement'!I$13 -> 0.064152296 | J21: =-'Income statement'!J18/'Income statement'!J$13 -> 0.064152296 | ... Q21: =-'Income statement'!Q18/'Income statement'!Q$13 -> 0.064152296
B22: S&G Expenses | C22: =-'Income statement'!C19/'Income statement'!C$13 -> 0.22738732 | D22: =-'Income statement'!D19/'Income statement'!D$13 -> 0.18962914 | E22: =-'Income statement'!E19/'Income statement'!E$13 -> 0.1968111 | F22: =-'Income statement'!F19/'Income statement'!F$13 -> 0.17439411 | G22: =-'Income statement'!G19/'Income statement'!G$13 -> 0.16411463 | H22: =-'Income statement'!H19/'Income statement'!H$13 -> 0.19046726 | I22: =-'Income statement'!I19/'Income statement'!I$13 -> 0.19046726 | J22: =-'Income statement'!J19/'Income statement'!J$13 -> 0.19046726 | ... Q22: =-'Income statement'!Q19/'Income statement'!Q$13 -> 0.19046726
B24: EBITDA | C24: ='Income statement'!C21/'Income statement'!C$13 -> 0.21782251 | D24: ='Income statement'!D21/'Income statement'!D$13 -> 0.28265667 | E24: ='Income statement'!E21/'Income statement'!E$13 -> 0.16453227 | F24: ='Income statement'!F21/'Income statement'!F$13 -> 0.15290858 | G24: ='Income statement'!G21/'Income statement'!G$13 -> 0.1375885 | H24: ='Income statement'!H21/'Income statement'!H$13 -> 0.19110171 | I24: ='Income statement'!I21/'Income statement'!I$13 -> 0.19110171 | J24: ='Income statement'!J21/'Income statement'!J$13 -> 0.19110171 | ... Q24: ='Income statement'!Q21/'Income statement'!Q$13 -> 0.19110171
B27: Dep & Amortization | C27: =-'Income statement'!C24/'Income statement'!C$13 -> 0.051332638 | D27: =-'Income statement'!D24/'Income statement'!D$13 -> 0.040489622 | E27: =-'Income statement'!E24/'Income statement'!E$13 -> 0.046905832 | F27: =-'Income statement'!F24/'Income statement'!F$13 -> 0.059352044 | G27: =-'Income statement'!G24/'Income statement'!G$13 -> 0.059723682 | H27: =-'Income statement'!H24/'Income statement'!H$13 -> 0.057099876 | I27: =-'Income statement'!I24/'Income statement'!I$13 -> 0.054636025 | J27: =-'Income statement'!J24/'Income statement'!J$13 -> 0.053311434 | ... Q27: =-'Income statement'!Q24/'Income statement'!Q$13 -> 0.062295675
B29: EBIT | C29: ='Income statement'!C26/'Income statement'!C$13 -> 0.16648987 | D29: ='Income statement'!D26/'Income statement'!D$13 -> 0.24216705 | E29: ='Income statement'!E26/'Income statement'!E$13 -> 0.11762644 | F29: ='Income statement'!F26/'Income statement'!F$13 -> 0.093556539 | G29: ='Income statement'!G26/'Income statement'!G$13 -> 0.077864817 | H29: ='Income statement'!H26/'Income statement'!H$13 -> 0.13400183 | I29: ='Income statement'!I26/'Income statement'!I$13 -> 0.13646568 | J29: ='Income statement'!J26/'Income statement'!J$13 -> 0.13779027 | ... Q29: ='Income statement'!Q26/'Income statement'!Q$13 -> 0.12880603
B32: Interest Cost | C32: =-'Income statement'!C29/'Income statement'!C$13 -> 0.019167351 | D32: =-'Income statement'!D29/'Income statement'!D$13 -> 0.016815353 | E32: =-'Income statement'!E29/'Income statement'!E$13 -> 0.025425393 | F32: =-'Income statement'!F29/'Income statement'!F$13 -> 0.033193633 | G32: =-'Income statement'!G29/'Income statement'!G$13 -> 0.03788033 | H32: =-'Income statement'!H29/'Income statement'!H$13 -> 0.029817231 | I32: =-'Income statement'!I29/'Income statement'!I$13 -> 0.028524067 | J32: =-'Income statement'!J29/'Income statement'!J$13 -> 0.028777608 | ... Q32: =-'Income statement'!Q29/'Income statement'!Q$13 -> 0.030139829
B33: Other Income | C33: ='Income statement'!C30/'Income statement'!C$13 -> 0.00015534498 | D33: ='Income statement'!D30/'Income statement'!D$13 -> 0.00012653007 | E33: ='Income statement'!E30/'Income statement'!E$13 -> 0.00012993724 | F33: ='Income statement'!F30/'Income statement'!F$13 -> 0.0017046525 | G33: ='Income statement'!G30/'Income statement'!G$13 -> 0.0019418758 | H33: ='Income statement'!H30/'Income statement'!H$13 -> 0.0008116681 | I33: ='Income statement'!I30/'Income statement'!I$13 -> 0.0008116681 | J33: ='Income statement'!J30/'Income statement'!J$13 -> 0.0008116681 | ... Q33: ='Income statement'!Q30/'Income statement'!Q$13 -> 0.0008116681
B35: Profit before Expectional Items and tax | C35: ='Income statement'!C32/'Income statement'!C$13 -> 0.14747786 | D35: ='Income statement'!D32/'Income statement'!D$13 -> 0.22547823 | E35: ='Income statement'!E32/'Income statement'!E$13 -> 0.092330983 | F35: ='Income statement'!F32/'Income statement'!F$13 -> 0.062067558 | G35: ='Income statement'!G32/'Income statement'!G$13 -> 0.041926363 | H35: ='Income statement'!H32/'Income statement'!H$13 -> 0.10499627 | I35: ='Income statement'!I32/'Income statement'!I$13 -> 0.10875328 | J35: ='Income statement'!J32/'Income statement'!J$13 -> 0.10982433 | ... Q35: ='Income statement'!Q32/'Income statement'!Q$13 -> 0.09947787
B37: Exceptional item | C37: ='Income statement'!C34/'Income statement'!C$13 -> 0 | D37: ='Income statement'!D34/'Income statement'!D$13 -> 0 | E37: ='Income statement'!E34/'Income statement'!E$13 -> 0 | F37: ='Income statement'!F34/'Income statement'!F$13 -> 0 | G37: ='Income statement'!G34/'Income statement'!G$13 -> 0.00032593807 | H37: ='Income statement'!H34/'Income statement'!H$13 -> 0 | I37: ='Income statement'!I34/'Income statement'!I$13 -> 0 | J37: ='Income statement'!J34/'Income statement'!J$13 -> 0 | ... Q37: ='Income statement'!Q34/'Income statement'!Q$13 -> 0
B39: EBT | C39: ='Income statement'!C36/'Income statement'!C$13 -> 0.14747786 | D39: ='Income statement'!D36/'Income statement'!D$13 -> 0.22547823 | E39: ='Income statement'!E36/'Income statement'!E$13 -> 0.092330983 | F39: ='Income statement'!F36/'Income statement'!F$13 -> 0.062067558 | G39: ='Income statement'!G36/'Income statement'!G$13 -> 0.042252301 | H39: ='Income statement'!H36/'Income statement'!H$13 -> 0.10499627 | I39: ='Income statement'!I36/'Income statement'!I$13 -> 0.10875328 | J39: ='Income statement'!J36/'Income statement'!J$13 -> 0.10982433 | ... Q39: ='Income statement'!Q36/'Income statement'!Q$13 -> 0.09947787
B42: Tax | C42: =-'Income statement'!C39/'Income statement'!C$13 -> 0.028701094 | D42: =-'Income statement'!D39/'Income statement'!D$13 -> 0.030605487 | E42: =-'Income statement'!E39/'Income statement'!E$13 -> 0.0099522858 | F42: =-'Income statement'!F39/'Income statement'!F$13 -> -0.0033041376 | G42: =-'Income statement'!G39/'Income statement'!G$13 -> -0.0032511291 | H42: =-'Income statement'!H39/'Income statement'!H$13 -> 0.006454324 | I42: =-'Income statement'!I39/'Income statement'!I$13 -> 0.006685275 | J42: =-'Income statement'!J39/'Income statement'!J$13 -> 0.0067511146 | ... Q42: =-'Income statement'!Q39/'Income statement'!Q$13 -> 0.0061150975
B44: Profit After Tax Before Non Controlling Interest | C44: ='Income statement'!C41/'Income statement'!C$13 -> 0.11877677 | D44: ='Income statement'!D41/'Income statement'!D$13 -> 0.19487274 | E44: ='Income statement'!E41/'Income statement'!E$13 -> 0.082378698 | F44: ='Income statement'!F41/'Income statement'!F$13 -> 0.065371696 | G44: ='Income statement'!G41/'Income statement'!G$13 -> 0.04550343 | H44: ='Income statement'!H41/'Income statement'!H$13 -> 0.098541943 | I44: ='Income statement'!I41/'Income statement'!I$13 -> 0.10206801 | J44: ='Income statement'!J41/'Income statement'!J$13 -> 0.10307322 | ... Q44: ='Income statement'!Q41/'Income statement'!Q$13 -> 0.093362772
B45: Profit attributable to Non Controlling Interest | C45: ='Income statement'!C42/'Income statement'!C$13 -> -0.0026075764 | D45: ='Income statement'!D42/'Income statement'!D$13 -> -3.7794696e-05 | E45: ='Income statement'!E42/'Income statement'!E$13 -> 0 | F45: ='Income statement'!F42/'Income statement'!F$13 -> 0 | G45: ='Income statement'!G42/'Income statement'!G$13 -> 0 | H45: ='Income statement'!H42/'Income statement'!H$13 -> 0 | I45: ='Income statement'!I42/'Income statement'!I$13 -> 0 | J45: ='Income statement'!J42/'Income statement'!J$13 -> 0 | ... Q45: ='Income statement'!Q42/'Income statement'!Q$13 -> 0
B47: Net Profit | C47: ='Income statement'!C44/'Income statement'!C$13 -> 0.11616919 | D47: ='Income statement'!D44/'Income statement'!D$13 -> 0.19483494 | E47: ='Income statement'!E44/'Income statement'!E$13 -> 0.082378698 | F47: ='Income statement'!F44/'Income statement'!F$13 -> 0.065371696 | G47: ='Income statement'!G44/'Income statement'!G$13 -> 0.04550343 | H47: ='Income statement'!H44/'Income statement'!H$13 -> 0.098541943 | I47: ='Income statement'!I44/'Income statement'!I$13 -> 0.10206801 | J47: ='Income statement'!J44/'Income statement'!J$13 -> 0.10307322 | ... Q47: ='Income statement'!Q44/'Income statement'!Q$13 -> 0.093362772
B49: Balance Sheet
B51: Assets
B52: Non-Current Assets
B53: Property Plant and Equipment | C53: ='Balance Sheet'!C15/'Balance Sheet'!C$37 -> 0.63997576 | D53: ='Balance Sheet'!D15/'Balance Sheet'!D$37 -> 0.62932558 | E53: ='Balance Sheet'!E15/'Balance Sheet'!E$37 -> 0.69423604 | F53: ='Balance Sheet'!F15/'Balance Sheet'!F$37 -> 0.68001329 | G53: ='Balance Sheet'!G15/'Balance Sheet'!G$37 -> 0.70463723 | H53: ='Balance Sheet'!H15/'Balance Sheet'!H$37 -> 0.69451035 | I53: ='Balance Sheet'!I15/'Balance Sheet'!I$37 -> 0.66933765 | J53: ='Balance Sheet'!J15/'Balance Sheet'!J$37 -> 0.65354081 | ... Q53: ='Balance Sheet'!Q15/'Balance Sheet'!Q$37 -> 0.69544517
B54: Capital Work-in-Progress | C54: ='Balance Sheet'!#REF!/'Balance Sheet'!C$37 -> #REF! | D54: ='Balance Sheet'!#REF!/'Balance Sheet'!D$37 -> #REF! | E54: ='Balance Sheet'!#REF!/'Balance Sheet'!E$37 -> #REF! | F54: ='Balance Sheet'!#REF!/'Balance Sheet'!F$37 -> #REF! | G54: ='Balance Sheet'!#REF!/'Balance Sheet'!G$37 -> #REF! | H54: ='Balance Sheet'!#REF!/'Balance Sheet'!H$37 -> #REF! | I54: ='Balance Sheet'!#REF!/'Balance Sheet'!I$37 -> #REF! | J54: ='Balance Sheet'!#REF!/'Balance Sheet'!J$37 -> #REF! | ... Q54: ='Balance Sheet'!#REF!/'Balance Sheet'!Q$37 -> #REF!
B55: Right of use Assets | C55: ='Balance Sheet'!#REF!/'Balance Sheet'!C$37 -> #REF! | D55: ='Balance Sheet'!#REF!/'Balance Sheet'!D$37 -> #REF! | E55: ='Balance Sheet'!#REF!/'Balance Sheet'!E$37 -> #REF! | F55: ='Balance Sheet'!#REF!/'Balance Sheet'!F$37 -> #REF! | G55: ='Balance Sheet'!#REF!/'Balance Sheet'!G$37 -> #REF! | H55: ='Balance Sheet'!#REF!/'Balance Sheet'!H$37 -> #REF! | I55: ='Balance Sheet'!#REF!/'Balance Sheet'!I$37 -> #REF! | J55: ='Balance Sheet'!#REF!/'Balance Sheet'!J$37 -> #REF! | ... Q55: ='Balance Sheet'!#REF!/'Balance Sheet'!Q$37 -> #REF!
B56: Intangible Assets | C56: ='Balance Sheet'!#REF!/'Balance Sheet'!C$37 -> #REF! | D56: ='Balance Sheet'!#REF!/'Balance Sheet'!D$37 -> #REF! | E56: ='Balance Sheet'!#REF!/'Balance Sheet'!E$37 -> #REF! | F56: ='Balance Sheet'!#REF!/'Balance Sheet'!F$37 -> #REF! | G56: ='Balance Sheet'!#REF!/'Balance Sheet'!G$37 -> #REF! | H56: ='Balance Sheet'!#REF!/'Balance Sheet'!H$37 -> #REF! | I56: ='Balance Sheet'!#REF!/'Balance Sheet'!I$37 -> #REF! | J56: ='Balance Sheet'!#REF!/'Balance Sheet'!J$37 -> #REF! | ... Q56: ='Balance Sheet'!#REF!/'Balance Sheet'!Q$37 -> #REF!
B57: Intangible Assets under Development | C57: ='Balance Sheet'!#REF!/'Balance Sheet'!C$37 -> #REF! | D57: ='Balance Sheet'!#REF!/'Balance Sheet'!D$37 -> #REF! | E57: ='Balance Sheet'!#REF!/'Balance Sheet'!E$37 -> #REF! | F57: ='Balance Sheet'!#REF!/'Balance Sheet'!F$37 -> #REF! | G57: ='Balance Sheet'!#REF!/'Balance Sheet'!G$37 -> #REF! | H57: ='Balance Sheet'!#REF!/'Balance Sheet'!H$37 -> #REF! | I57: ='Balance Sheet'!#REF!/'Balance Sheet'!I$37 -> #REF! | J57: ='Balance Sheet'!#REF!/'Balance Sheet'!J$37 -> #REF! | ... Q57: ='Balance Sheet'!#REF!/'Balance Sheet'!Q$37 -> #REF!
B58: Financial Assets
B59: Investments | C59: ='Balance Sheet'!C17/'Balance Sheet'!C$37 -> 0.0083123083 | D59: ='Balance Sheet'!D17/'Balance Sheet'!D$37 -> 0.0036035049 | E59: ='Balance Sheet'!E17/'Balance Sheet'!E$37 -> 0.0020009556 | F59: ='Balance Sheet'!F17/'Balance Sheet'!F$37 -> 0.0022659036 | G59: ='Balance Sheet'!G17/'Balance Sheet'!G$37 -> 0.0042857708 | H59: ='Balance Sheet'!H17/'Balance Sheet'!H$37 -> 0.0042710346 | I59: ='Balance Sheet'!I17/'Balance Sheet'!I$37 -> 0.0042559997 | J59: ='Balance Sheet'!J17/'Balance Sheet'!J$37 -> 0.0042227845 | ... Q59: ='Balance Sheet'!Q17/'Balance Sheet'!Q$37 -> 0.0038066765
B60: Loans & Advances | C60: ='Balance Sheet'!C18/'Balance Sheet'!C$37 -> 0.041884769 | D60: ='Balance Sheet'!D18/'Balance Sheet'!D$37 -> 0 | E60: ='Balance Sheet'!E18/'Balance Sheet'!E$37 -> 1.1653789e-06 | F60: ='Balance Sheet'!F18/'Balance Sheet'!F$37 -> 2.9658424e-05 | G60: ='Balance Sheet'!G18/'Balance Sheet'!G$37 -> 5.3988295e-06 | H60: ='Balance Sheet'!H18/'Balance Sheet'!H$37 -> 9.6394839e-06 | I60: ='Balance Sheet'!I18/'Balance Sheet'!I$37 -> 9.6055511e-06 | J60: ='Balance Sheet'!J18/'Balance Sheet'!J$37 -> 9.5305864e-06 | ... Q60: ='Balance Sheet'!Q18/'Balance Sheet'!Q$37 -> 8.591454e-06
B61: Deferred Tax Assets | C61: ='Balance Sheet'!C19/'Balance Sheet'!C$37 -> 0 | D61: ='Balance Sheet'!D19/'Balance Sheet'!D$37 -> 0.0035334474 | E61: ='Balance Sheet'!E19/'Balance Sheet'!E$37 -> 0.00615087 | F61: ='Balance Sheet'!F19/'Balance Sheet'!F$37 -> 0.014191556 | G61: ='Balance Sheet'!G19/'Balance Sheet'!G$37 -> 0.019614848 | H61: ='Balance Sheet'!H19/'Balance Sheet'!H$37 -> 0.0088228326 | I61: ='Balance Sheet'!I19/'Balance Sheet'!I$37 -> 0.0087917746 | J61: ='Balance Sheet'!J19/'Balance Sheet'!J$37 -> 0.0087231608 | ... Q61: ='Balance Sheet'!Q19/'Balance Sheet'!Q$37 -> 0.0078635911
B62: Other Non-Current Assets | C62: ='Balance Sheet'!C20/'Balance Sheet'!C$37 -> 0 | D62: ='Balance Sheet'!D20/'Balance Sheet'!D$37 -> 0.019767689 | E62: ='Balance Sheet'!E20/'Balance Sheet'!E$37 -> 0.011012831 | F62: ='Balance Sheet'!F20/'Balance Sheet'!F$37 -> 0.010962742 | G62: ='Balance Sheet'!G20/'Balance Sheet'!G$37 -> 0.010986618 | H62: ='Balance Sheet'!H20/'Balance Sheet'!H$37 -> 0.010034488 | I62: ='Balance Sheet'!I20/'Balance Sheet'!I$37 -> 0.0099991643 | J62: ='Balance Sheet'!J20/'Balance Sheet'!J$37 -> 0.0099211276 | ... Q62: ='Balance Sheet'!Q20/'Balance Sheet'!Q$37 -> 0.0089435118
B64: Total Non-Current Assets | C64: ='Balance Sheet'!C22/'Balance Sheet'!C$37 -> 0.69017284 | D64: ='Balance Sheet'!D22/'Balance Sheet'!D$37 -> 0.65623022 | E64: ='Balance Sheet'!E22/'Balance Sheet'!E$37 -> 0.71340186 | F64: ='Balance Sheet'!F22/'Balance Sheet'!F$37 -> 0.70746315 | G64: ='Balance Sheet'!G22/'Balance Sheet'!G$37 -> 0.73952987 | H64: ='Balance Sheet'!H22/'Balance Sheet'!H$37 -> 0.71764834 | I64: ='Balance Sheet'!I22/'Balance Sheet'!I$37 -> 0.69239419 | J64: ='Balance Sheet'!J22/'Balance Sheet'!J$37 -> 0.67641742 | ... Q64: ='Balance Sheet'!Q22/'Balance Sheet'!Q$37 -> 0.71606754
B66: Current Assets:
B67: Inventories | C67: ='Balance Sheet'!C25/'Balance Sheet'!C$37 -> 0.12244428 | D67: ='Balance Sheet'!D25/'Balance Sheet'!D$37 -> 0.11898572 | E67: ='Balance Sheet'!E25/'Balance Sheet'!E$37 -> 0.12015639 | F67: ='Balance Sheet'!F25/'Balance Sheet'!F$37 -> 0.11464464 | G67: ='Balance Sheet'!G25/'Balance Sheet'!G$37 -> 0.13083344 | H67: ='Balance Sheet'!H25/'Balance Sheet'!H$37 -> 0.1237751 | I67: ='Balance Sheet'!I25/'Balance Sheet'!I$37 -> 0.12333939 | J67: ='Balance Sheet'!J25/'Balance Sheet'!J$37 -> 0.12237681 | ... Q67: ='Balance Sheet'!Q25/'Balance Sheet'!Q$37 -> 0.11031795
B68: Financial Assets:
B69: Trade Receivables | C69: ='Balance Sheet'!C27/'Balance Sheet'!C$37 -> 0.10386852 | D69: ='Balance Sheet'!D27/'Balance Sheet'!D$37 -> 0.13903491 | E69: ='Balance Sheet'!E27/'Balance Sheet'!E$37 -> 0.10960272 | F69: ='Balance Sheet'!F27/'Balance Sheet'!F$37 -> 0.084445442 | G69: ='Balance Sheet'!G27/'Balance Sheet'!G$37 -> 0.070730066 | H69: ='Balance Sheet'!H27/'Balance Sheet'!H$37 -> 0.1003468 | I69: ='Balance Sheet'!I27/'Balance Sheet'!I$37 -> 0.099993559 | J69: ='Balance Sheet'!J27/'Balance Sheet'!J$37 -> 0.099213177 | ... Q69: ='Balance Sheet'!Q27/'Balance Sheet'!Q$37 -> 0.089436831
B70: Cash and Cash Equivalents | C70: ='Balance Sheet'!C28/'Balance Sheet'!C$37 -> 0.053956722 | D70: ='Balance Sheet'!D28/'Balance Sheet'!D$37 -> 0.01192634 | E70: ='Balance Sheet'!E28/'Balance Sheet'!E$37 -> 0.01951427 | F70: ='Balance Sheet'!F28/'Balance Sheet'!F$37 -> 0.042341355 | G70: ='Balance Sheet'!G28/'Balance Sheet'!G$37 -> 0.01794121 | H70: ='Balance Sheet'!H28/'Balance Sheet'!H$37 -> 0.018568797 | I70: ='Balance Sheet'!I28/'Balance Sheet'!I$37 -> 0.04475151 | J70: ='Balance Sheet'!J28/'Balance Sheet'!J$37 -> 0.062779686 | ... Q70: ='Balance Sheet'!Q28/'Balance Sheet'!Q$37 -> 0.048828757
B71: Bank Balances | C71: ='Balance Sheet'!C29/'Balance Sheet'!C$37 -> 0 | D71: ='Balance Sheet'!D29/'Balance Sheet'!D$37 -> 0.010181271 | E71: ='Balance Sheet'!E29/'Balance Sheet'!E$37 -> 0.0038783811 | F71: ='Balance Sheet'!F29/'Balance Sheet'!F$37 -> 0.0086948613 | G71: ='Balance Sheet'!G29/'Balance Sheet'!G$37 -> 0.0086003354 | H71: ='Balance Sheet'!H29/'Balance Sheet'!H$37 -> 0 | I71: ='Balance Sheet'!I29/'Balance Sheet'!I$37 -> 0 | J71: ='Balance Sheet'!J29/'Balance Sheet'!J$37 -> 0 | ... Q71: ='Balance Sheet'!Q29/'Balance Sheet'!Q$37 -> 0
B72: Loans and Advances | C72: ='Balance Sheet'!C30/'Balance Sheet'!C$37 -> 0 | D72: ='Balance Sheet'!D30/'Balance Sheet'!D$37 -> 0 | E72: ='Balance Sheet'!E30/'Balance Sheet'!E$37 -> 0.0037327087 | F72: ='Balance Sheet'!F30/'Balance Sheet'!F$37 -> 0.0008185725 | G72: ='Balance Sheet'!G30/'Balance Sheet'!G$37 -> 0.00056417769 | H72: ='Balance Sheet'!H30/'Balance Sheet'!H$37 -> 0.00094968363 | I72: ='Balance Sheet'!I30/'Balance Sheet'!I$37 -> 0.00094634057 | J72: ='Balance Sheet'!J30/'Balance Sheet'!J$37 -> 0.00093895502 | ... Q72: ='Balance Sheet'!Q30/'Balance Sheet'!Q$37 -> 0.00084643154
B73: Others Current Financial Assets | C73: ='Balance Sheet'!C31/'Balance Sheet'!C$37 -> 0.024533872 | D73: ='Balance Sheet'!D31/'Balance Sheet'!D$37 -> 0.05188079 | E73: ='Balance Sheet'!E31/'Balance Sheet'!E$37 -> 0.018732301 | F73: ='Balance Sheet'!F31/'Balance Sheet'!F$37 -> 0.0016519742 | G73: ='Balance Sheet'!G31/'Balance Sheet'!G$37 -> 0.0014684816 | H73: ='Balance Sheet'!H31/'Balance Sheet'!H$37 -> 0.018676439 | I73: ='Balance Sheet'!I31/'Balance Sheet'!I$37 -> 0.018610694 | J73: ='Balance Sheet'!J31/'Balance Sheet'!J$37 -> 0.018465451 | ... Q73: ='Balance Sheet'!Q31/'Balance Sheet'!Q$37 -> 0.016645887
B74: Current Tax Assets (Net) | C74: ='Balance Sheet'!C32/'Balance Sheet'!C$37 -> 0 | D74: ='Balance Sheet'!D32/'Balance Sheet'!D$37 -> 0.0070592521 | E74: ='Balance Sheet'!E32/'Balance Sheet'!E$37 -> 0.0064655223 | F74: ='Balance Sheet'!F32/'Balance Sheet'!F$37 -> 0.0070349782 | G74: ='Balance Sheet'!G32/'Balance Sheet'!G$37 -> 0.001249829 | H74: ='Balance Sheet'!H32/'Balance Sheet'!H$37 -> 0.0041464923 | I74: ='Balance Sheet'!I32/'Balance Sheet'!I$37 -> 0.0041318959 | J74: ='Balance Sheet'!J32/'Balance Sheet'!J$37 -> 0.0040996493 | ... Q74: ='Balance Sheet'!Q32/'Balance Sheet'!Q$37 -> 0.0036956748
B75: Other Current Assets | C75: ='Balance Sheet'!C33/'Balance Sheet'!C$37 -> 0.0050237644 | D75: ='Balance Sheet'!D33/'Balance Sheet'!D$37 -> 0.0047014976 | E75: ='Balance Sheet'!E33/'Balance Sheet'!E$37 -> 0.0045158433 | F75: ='Balance Sheet'!F33/'Balance Sheet'!F$37 -> 0.032905033 | G75: ='Balance Sheet'!G33/'Balance Sheet'!G$37 -> 0.029082595 | H75: ='Balance Sheet'!H33/'Balance Sheet'!H$37 -> 0.01588835 | I75: ='Balance Sheet'!I33/'Balance Sheet'!I$37 -> 0.01583242 | J75: ='Balance Sheet'!J33/'Balance Sheet'!J$37 -> 0.015708859 | ... Q75: ='Balance Sheet'!Q33/'Balance Sheet'!Q$37 -> 0.014160927
B77: Total Current Assets | C77: ='Balance Sheet'!C35/'Balance Sheet'!C$37 -> 0.30982716 | D77: ='Balance Sheet'!D35/'Balance Sheet'!D$37 -> 0.34376978 | E77: ='Balance Sheet'!E35/'Balance Sheet'!E$37 -> 0.28659814 | F77: ='Balance Sheet'!F35/'Balance Sheet'!F$37 -> 0.29253685 | G77: ='Balance Sheet'!G35/'Balance Sheet'!G$37 -> 0.26047013 | H77: ='Balance Sheet'!H35/'Balance Sheet'!H$37 -> 0.28235166 | I77: ='Balance Sheet'!I35/'Balance Sheet'!I$37 -> 0.30760581 | J77: ='Balance Sheet'!J35/'Balance Sheet'!J$37 -> 0.32358258 | ... Q77: ='Balance Sheet'!Q35/'Balance Sheet'!Q$37 -> 0.28393246
B79: TOTAL ASSETS | C79: ='Balance Sheet'!C37/'Balance Sheet'!C$37 -> 1 | D79: ='Balance Sheet'!D37/'Balance Sheet'!D$37 -> 1 | E79: ='Balance Sheet'!E37/'Balance Sheet'!E$37 -> 1 | F79: ='Balance Sheet'!F37/'Balance Sheet'!F$37 -> 1 | G79: ='Balance Sheet'!G37/'Balance Sheet'!G$37 -> 1 | H79: ='Balance Sheet'!H37/'Balance Sheet'!H$37 -> 1 | I79: ='Balance Sheet'!I37/'Balance Sheet'!I$37 -> 1 | J79: ='Balance Sheet'!J37/'Balance Sheet'!J$37 -> 1 | ... Q79: ='Balance Sheet'!Q37/'Balance Sheet'!Q$37 -> 1
B81: EQUITY AND LIABILITIES
B82: EQUITY
B83: Equity Share Capital | C83: ='Balance Sheet'!C41/'Balance Sheet'!C$37 -> 0.011400634 | D83: ='Balance Sheet'!D41/'Balance Sheet'!D$37 -> 0.023087143 | E83: ='Balance Sheet'!E41/'Balance Sheet'!E$37 -> 0.021122493 | F83: ='Balance Sheet'!F41/'Balance Sheet'!F$37 -> 0.017918631 | G83: ='Balance Sheet'!G41/'Balance Sheet'!G$37 -> 0.016309864 | H83: ='Balance Sheet'!H41/'Balance Sheet'!H$37 -> 0.014950181 | I83: ='Balance Sheet'!I41/'Balance Sheet'!I$37 -> 0.013256896 | J83: ='Balance Sheet'!J41/'Balance Sheet'!J$37 -> 0.011808897 | ... Q83: ='Balance Sheet'!Q41/'Balance Sheet'!Q$37 -> 0.0061069946
B84: Other Equity | C84: ='Balance Sheet'!C42/'Balance Sheet'!C$37 -> 0.44699333 | D84: ='Balance Sheet'!D42/'Balance Sheet'!D$37 -> 0.55214637 | E84: ='Balance Sheet'!E42/'Balance Sheet'!E$37 -> 0.55225326 | F84: ='Balance Sheet'!F42/'Balance Sheet'!F$37 -> 0.50503551 | G84: ='Balance Sheet'!G42/'Balance Sheet'!G$37 -> 0.48804159 | H84: ='Balance Sheet'!H42/'Balance Sheet'!H$37 -> 0.50617472 | I84: ='Balance Sheet'!I42/'Balance Sheet'!I$37 -> 0.50955374 | J84: ='Balance Sheet'!J42/'Balance Sheet'!J$37 -> 0.51472588 | ... Q84: ='Balance Sheet'!Q42/'Balance Sheet'!Q$37 -> 0.56708247
B85: Non Controlling Interest | C85: ='Balance Sheet'!C43/'Balance Sheet'!C$37 -> 0.001601742 | D85: ='Balance Sheet'!D43/'Balance Sheet'!D$37 -> 9.1711684e-05 | E85: ='Balance Sheet'!E43/'Balance Sheet'!E$37 -> 8.3907282e-05 | F85: ='Balance Sheet'!F43/'Balance Sheet'!F$37 -> 7.1180217e-05 | G85: ='Balance Sheet'!G43/'Balance Sheet'!G$37 -> 8.9980492e-06 | H85: ='Balance Sheet'!H43/'Balance Sheet'!H$37 -> 0 | I85: ='Balance Sheet'!I43/'Balance Sheet'!I$37 -> 0 | J85: ='Balance Sheet'!J43/'Balance Sheet'!J$37 -> 0 | ... Q85: ='Balance Sheet'!Q43/'Balance Sheet'!Q$37 -> 0
B86: Total Equity | C86: ='Balance Sheet'!C44/'Balance Sheet'!C$37 -> 0.45999571 | D86: ='Balance Sheet'!D44/'Balance Sheet'!D$37 -> 0.57532523 | E86: ='Balance Sheet'!E44/'Balance Sheet'!E$37 -> 0.57345966 | F86: ='Balance Sheet'!F44/'Balance Sheet'!F$37 -> 0.52302532 | G86: ='Balance Sheet'!G44/'Balance Sheet'!G$37 -> 0.50436045 | H86: ='Balance Sheet'!H44/'Balance Sheet'!H$37 -> 0.52112491 | I86: ='Balance Sheet'!I44/'Balance Sheet'!I$37 -> 0.52281063 | J86: ='Balance Sheet'!J44/'Balance Sheet'!J$37 -> 0.52653477 | ... Q86: ='Balance Sheet'!Q44/'Balance Sheet'!Q$37 -> 0.57318946
B88: LIABILITIES
B89: Non-Current Liabilities:
B90: Financial Liabilities
B91: (i) Borrowings | C91: ='Balance Sheet'!C49/'Balance Sheet'!C$37 -> 0.16593864 | D91: ='Balance Sheet'!D49/'Balance Sheet'!D$37 -> 0.11844182 | E91: ='Balance Sheet'!E49/'Balance Sheet'!E$37 -> 0.073967766 | F91: ='Balance Sheet'!F49/'Balance Sheet'!F$37 -> 0.15065194 | G91: ='Balance Sheet'!G49/'Balance Sheet'!G$37 -> 0.16803137 | H91: ='Balance Sheet'!H49/'Balance Sheet'!H$37 -> 0.13918522 | I91: ='Balance Sheet'!I49/'Balance Sheet'!I$37 -> 0.13869527 | J91: ='Balance Sheet'!J49/'Balance Sheet'!J$37 -> 0.13761284 | ... Q91: ='Balance Sheet'!Q49/'Balance Sheet'!Q$37 -> 0.12405264
B92: (ii) Lease Liabilities | C92: ='Balance Sheet'!C50/'Balance Sheet'!C$37 -> 0 | D92: ='Balance Sheet'!D50/'Balance Sheet'!D$37 -> 0.0018991961 | E92: ='Balance Sheet'!E50/'Balance Sheet'!E$37 -> 0.0029437472 | F92: ='Balance Sheet'!F50/'Balance Sheet'!F$37 -> 0.0048748563 | G92: ='Balance Sheet'!G50/'Balance Sheet'!G$37 -> 0.0042407806 | H92: ='Balance Sheet'!H50/'Balance Sheet'!H$37 -> 0.0027790739 | I92: ='Balance Sheet'!I50/'Balance Sheet'!I$37 -> 0.002769291 | J92: ='Balance Sheet'!J50/'Balance Sheet'!J$37 -> 0.0027476786 | ... Q92: ='Balance Sheet'!Q50/'Balance Sheet'!Q$37 -> 0.0024769257
B93: Other Non-Current Liabilitie | C93: ='Balance Sheet'!C51/'Balance Sheet'!C$37 -> 0.029366579 | D93: ='Balance Sheet'!D51/'Balance Sheet'!D$37 -> 0.028479025 | E93: ='Balance Sheet'!E51/'Balance Sheet'!E$37 -> 0.02526658 | F93: ='Balance Sheet'!F51/'Balance Sheet'!F$37 -> 0.017329417 | G93: ='Balance Sheet'!G51/'Balance Sheet'!G$37 -> 0.010092212 | H93: ='Balance Sheet'!H51/'Balance Sheet'!H$37 -> 0.022006413 | I93: ='Balance Sheet'!I51/'Balance Sheet'!I$37 -> 0.021928947 | J93: ='Balance Sheet'!J51/'Balance Sheet'!J$37 -> 0.021757806 | ... Q93: ='Balance Sheet'!Q51/'Balance Sheet'!Q$37 -> 0.019613818
B94: Provisions | C94: ='Balance Sheet'!C52/'Balance Sheet'!C$37 -> 0 | D94: ='Balance Sheet'!D52/'Balance Sheet'!D$37 -> 0 | E94: ='Balance Sheet'!E52/'Balance Sheet'!E$37 -> 0 | F94: ='Balance Sheet'!F52/'Balance Sheet'!F$37 -> 0.001360333 | G94: ='Balance Sheet'!G52/'Balance Sheet'!G$37 -> 0.0013668037 | H94: ='Balance Sheet'!H52/'Balance Sheet'!H$37 -> 0.00072041086 | I94: ='Balance Sheet'!I52/'Balance Sheet'!I$37 -> 0.00071787488 | J94: ='Balance Sheet'!J52/'Balance Sheet'!J$37 -> 0.00071227236 | ... Q94: ='Balance Sheet'!Q52/'Balance Sheet'!Q$37 -> 0.0006420859
B96: Total Non-Current Liabilities | C96: ='Balance Sheet'!C54/'Balance Sheet'!C$37 -> 0.22591891 | D96: ='Balance Sheet'!D54/'Balance Sheet'!D$37 -> 0.14882004 | E96: ='Balance Sheet'!E54/'Balance Sheet'!E$37 -> 0.10217809 | F96: ='Balance Sheet'!F54/'Balance Sheet'!F$37 -> 0.17421655 | G96: ='Balance Sheet'!G54/'Balance Sheet'!G$37 -> 0.18373117 | H96: ='Balance Sheet'!H54/'Balance Sheet'!H$37 -> 0.17173317 | I96: ='Balance Sheet'!I54/'Balance Sheet'!I$37 -> 0.17112864 | J96: ='Balance Sheet'!J54/'Balance Sheet'!J$37 -> 0.1697931 | ... Q96: ='Balance Sheet'!Q54/'Balance Sheet'!Q$37 -> 0.15306189
B98: Current Liabilities:
B99: Financial Liabilities
B100: (i) Borrowings | C100: ='Balance Sheet'!C58/'Balance Sheet'!C$37 -> 0.16018336 | D100: ='Balance Sheet'!D58/'Balance Sheet'!D$37 -> 0.20865937 | E100: ='Balance Sheet'!E58/'Balance Sheet'!E$37 -> 0.26096563 | F100: ='Balance Sheet'!F58/'Balance Sheet'!F$37 -> 0.2017188 | G100: ='Balance Sheet'!G58/'Balance Sheet'!G$37 -> 0.1729542 | H100: ='Balance Sheet'!H58/'Balance Sheet'!H$37 -> 0.19855201 | I100: ='Balance Sheet'!I58/'Balance Sheet'!I$37 -> 0.19785307 | J100: ='Balance Sheet'!J58/'Balance Sheet'!J$37 -> 0.19630896 | ... Q100: ='Balance Sheet'!Q58/'Balance Sheet'!Q$37 -> 0.17696492
B101: (ii) Lease Liabilities | C101: ='Balance Sheet'!C59/'Balance Sheet'!C$37 -> 0 | D101: ='Balance Sheet'!D59/'Balance Sheet'!D$37 -> 0.00051842577 | E101: ='Balance Sheet'!E59/'Balance Sheet'!E$37 -> 0.0009346339 | F101: ='Balance Sheet'!F59/'Balance Sheet'!F$37 -> 0.00089667302 | G101: ='Balance Sheet'!G59/'Balance Sheet'!G$37 -> 0.00099968327 | H101: ='Balance Sheet'!H59/'Balance Sheet'!H$37 -> 0.00065544376 | I101: ='Balance Sheet'!I59/'Balance Sheet'!I$37 -> 0.00065313648 | J101: ='Balance Sheet'!J59/'Balance Sheet'!J$37 -> 0.0006480392 | ... Q101: ='Balance Sheet'!Q59/'Balance Sheet'!Q$37 -> 0.0005841822
B102: (iii) Trade Payables | C102: ='Balance Sheet'!C60/'Balance Sheet'!C$37 -> 0.07541928 | D102: ='Balance Sheet'!D60/'Balance Sheet'!D$37 -> 0.043926075 | E102: ='Balance Sheet'!E60/'Balance Sheet'!E$37 -> 0.02512557 | F102: ='Balance Sheet'!F60/'Balance Sheet'!F$37 -> 0.071666616 | G102: ='Balance Sheet'!G60/'Balance Sheet'!G$37 -> 0.11134906 | H102: ='Balance Sheet'!H60/'Balance Sheet'!H$37 -> 0.067685612 | I102: ='Balance Sheet'!I60/'Balance Sheet'!I$37 -> 0.067447346 | J102: ='Balance Sheet'!J60/'Balance Sheet'!J$37 -> 0.066920965 | ... Q102: ='Balance Sheet'!Q60/'Balance Sheet'!Q$37 -> 0.060326655
B103: (iv)Other Financial Liabilities | C103: ='Balance Sheet'!C61/'Balance Sheet'!C$37 -> 0 | D103: ='Balance Sheet'!D61/'Balance Sheet'!D$37 -> 0.00028405147 | E103: ='Balance Sheet'!E61/'Balance Sheet'!E$37 -> 0.022289037 | F103: ='Balance Sheet'!F61/'Balance Sheet'!F$37 -> 0.013500515 | G103: ='Balance Sheet'!G61/'Balance Sheet'!G$37 -> 0.018199454 | H103: ='Balance Sheet'!H61/'Balance Sheet'!H$37 -> 0.010650004 | I103: ='Balance Sheet'!I61/'Balance Sheet'!I$37 -> 0.010612514 | J103: ='Balance Sheet'!J61/'Balance Sheet'!J$37 -> 0.010529691 | ... Q103: ='Balance Sheet'!Q61/'Balance Sheet'!Q$37 -> 0.0094921077
B104: Other Current Liabilities | C104: ='Balance Sheet'!C62/'Balance Sheet'!C$37 -> 0.073232588 | D104: ='Balance Sheet'!D62/'Balance Sheet'!D$37 -> 0.018431501 | E104: ='Balance Sheet'!E62/'Balance Sheet'!E$37 -> 0.011567551 | F104: ='Balance Sheet'!F62/'Balance Sheet'!F$37 -> 0.012354711 | G104: ='Balance Sheet'!G62/'Balance Sheet'!G$37 -> 0.006974388 | H104: ='Balance Sheet'!H62/'Balance Sheet'!H$37 -> 0.026211855 | I104: ='Balance Sheet'!I62/'Balance Sheet'!I$37 -> 0.026119585 | J104: ='Balance Sheet'!J62/'Balance Sheet'!J$37 -> 0.025915739 | ... Q104: ='Balance Sheet'!Q62/'Balance Sheet'!Q$37 -> 0.023362034
B105: Provisions | C105: ='Balance Sheet'!C63/'Balance Sheet'!C$37 -> 0.0052501544 | D105: ='Balance Sheet'!D63/'Balance Sheet'!D$37 -> 0.0040353141 | E105: ='Balance Sheet'!E63/'Balance Sheet'!E$37 -> 0.0034798215 | F105: ='Balance Sheet'!F63/'Balance Sheet'!F$37 -> 0.0026208161 | G105: ='Balance Sheet'!G63/'Balance Sheet'!G$37 -> 0.0014315896 | H105: ='Balance Sheet'!H63/'Balance Sheet'!H$37 -> 0.0033869981 | I105: ='Balance Sheet'!I63/'Balance Sheet'!I$37 -> 0.0033750753 | J105: ='Balance Sheet'!J63/'Balance Sheet'!J$37 -> 0.0033487351 | ... Q105: ='Balance Sheet'!Q63/'Balance Sheet'!Q$37 -> 0.0030187548
B107: Total Current Liabilities | C107: ='Balance Sheet'!C65/'Balance Sheet'!C$37 -> 0.31408538 | D107: ='Balance Sheet'!D65/'Balance Sheet'!D$37 -> 0.27585473 | E107: ='Balance Sheet'!E65/'Balance Sheet'!E$37 -> 0.32436225 | F107: ='Balance Sheet'!F65/'Balance Sheet'!F$37 -> 0.30275813 | G107: ='Balance Sheet'!G65/'Balance Sheet'!G$37 -> 0.31190838 | H107: ='Balance Sheet'!H65/'Balance Sheet'!H$37 -> 0.30714192 | I107: ='Balance Sheet'!I65/'Balance Sheet'!I$37 -> 0.30606073 | J107: ='Balance Sheet'!J65/'Balance Sheet'!J$37 -> 0.30367213 | ... Q107: ='Balance Sheet'!Q65/'Balance Sheet'!Q$37 -> 0.27374865
B109: Total Liabilities | C109: ='Balance Sheet'!C67/'Balance Sheet'!C$37 -> 0.54000429 | D109: ='Balance Sheet'!D67/'Balance Sheet'!D$37 -> 0.42467477 | E109: ='Balance Sheet'!E67/'Balance Sheet'!E$37 -> 0.42654034 | F109: ='Balance Sheet'!F67/'Balance Sheet'!F$37 -> 0.47697468 | G109: ='Balance Sheet'!G67/'Balance Sheet'!G$37 -> 0.49563955 | H109: ='Balance Sheet'!H67/'Balance Sheet'!H$37 -> 0.47887509 | I109: ='Balance Sheet'!I67/'Balance Sheet'!I$37 -> 0.47718937 | J109: ='Balance Sheet'!J67/'Balance Sheet'!J$37 -> 0.47346523 | ... Q109: ='Balance Sheet'!Q67/'Balance Sheet'!Q$37 -> 0.42681054
B111: TOTAL EQUITY AND LIABILITIES | C111: ='Balance Sheet'!C69/'Balance Sheet'!C$37 -> 1 | D111: ='Balance Sheet'!D69/'Balance Sheet'!D$37 -> 1 | E111: ='Balance Sheet'!E69/'Balance Sheet'!E$37 -> 1 | F111: ='Balance Sheet'!F69/'Balance Sheet'!F$37 -> 1 | G111: ='Balance Sheet'!G69/'Balance Sheet'!G$37 -> 1 | H111: ='Balance Sheet'!H69/'Balance Sheet'!H$37 -> 1 | I111: ='Balance Sheet'!I69/'Balance Sheet'!I$37 -> 1 | J111: ='Balance Sheet'!J69/'Balance Sheet'!J$37 -> 1 | ... Q111: ='Balance Sheet'!Q69/'Balance Sheet'!Q$37 -> 1

Sheet Equity Market
B9: BSE: 524208 | NSE: AARTIIND
B10: Equity Market
B12: Date | C12: Close Price
B13: 42235 | C13: 27931.64 | E13: Year | F13: =YEARFRAC(B13,B2489) -> 10
B14: 42236 | C14: 27607.82 | E14: Return | F14: =_xlfn.RRI(F13,C13,C2489) -> 0.1132251
B15: 42237 | C15: 27366.07
B16: 42240 | C16: 25741.56
B17: 42241 | C17: 26032.38
B18: 42242 | C18: 25714.66
B19: 42243 | C19: 26231.19
B20: 42244 | C20: 26392.38
B21: 42247 | C21: 26283.09
B22: 42248 | C22: 25696.44
B23: 42249 | C23: 25453.56
B24: 42250 | C24: 25764.78
B25: 42251 | C25: 25201.9
B26: 42254 | C26: 24893.81
... B2489: 45888 | C2489: 81644.39

Sheet Beta
B9: BSE: 524208 | NSE: AARTIIND
B10: Beta Calculation
B12: Date | C12: Sensex | D12: % | F12: Stock | G12: %
C13: Close | D13: Change | F13: Close | G13: Change
B14: 42217 | C14: 26283.09 | F14: 423.35
B15: 42248 | C15: 26154.83 | D15: =C15/C14-1 -> -0.0048799437 | F15: 550.75 | G15: =F15/F14-1 -> 0.30093303 | I15: Beta | J15: =SLOPE(G15:G134,D15:D134) -> 1.2168905
B16: 42278 | C16: 26656.83 | D16: =C16/C15-1 -> 0.019193396 | F16: 511.95 | G16: =F16/F15-1 -> -0.070449387 | I16: Beta | J16: =+_xlfn.COVARIANCE.S(G15:G134,D15:D134)/_xlfn.VAR.S(D15:D134) -> 1.2168905
B17: 42309 | C17: 26145.67 | D17: =C17/C16-1 -> -0.019175573 | F17: 496.15 | G17: =F17/F16-1 -> -0.030862389 | I17: Bata | J17: =J36 -> 1.2168975
B18: 42339 | C18: 26117.54 | D18: =C18/C17-1 -> -0.0010758952 | F18: 523.35 | G18: =F18/F17-1 -> 0.05482213
B19: 42370 | C19: 24870.69 | D19: =C19/C18-1 -> -0.047739948 | F19: 491.5 | G19: =F19/F18-1 -> -0.060857934 | I19: SUMMARY OUTPUT
B20: 42401 | C20: 23002 | D20: =C20/C19-1 -> -0.075136235 | F20: 425.2 | G20: =F20/F19-1 -> -0.13489318
B21: 42430 | C21: 25341.86 | D21: =C21/C20-1 -> 0.1017242 | F21: 517.4 | G21: =F21/F20-1 -> 0.21683913 | I21: Regression Statistics
B22: 42461 | C22: 25606.62 | D22: =C22/C21-1 -> 0.010447536 | F22: 534.35 | G22: =F22/F21-1 -> 0.032759954 | I22: Multiple R | J22: 0.45074951
B23: 42491 | C23: 26667.96 | D23: =C23/C22-1 -> 0.041447876 | F23: 518.1 | G23: =F23/F22-1 -> -0.030410779 | I23: R Square | J23: 0.20317512
B24: 42522 | C24: 26999.72 | D24: =C24/C23-1 -> 0.012440397 | F24: 519.55 | G24: =F24/F23-1 -> 0.0027986875 | I24: Adjusted R Square | J24: 0.19642237
B25: 42552 | C25: 28051.86 | D25: =C25/C24-1 -> 0.038968552 | F25: 553.5 | G25: =F25/F24-1 -> 0.06534501 | I25: Standard Error | J25: 0.11185542
B26: 42583 | C26: 28452.17 | D26: =C26/C25-1 -> 0.014270355 | F26: 617.55 | G26: =F26/F25-1 -> 0.11571816 | I26: Observations | J26: 120
B27: 42614 | C27: 27865.96 | D27: =C27/C26-1 -> -0.020603349 | F27: 619.45 | G27: =F27/F26-1 -> 0.003076674
B28: 42644 | C28: 27930.21 | D28: =C28/C27-1 -> 0.0023056805 | F28: 757.95 | G28: =F28/F27-1 -> 0.22358544 | I28: ANOVA
B29: 42675 | C29: 26652.81 | D29: =C29/C28-1 -> -0.045735424 | F29: 724.85 | G29: =F29/F28-1 -> -0.043670427 | J29: df | K29: SS | L29: MS | M29: F | N29: Significance F
B30: 42705 | C30: 26626.46 | D30: =C30/C29-1 -> -0.00098863872 | F30: 683.15 | G30: =F30/F29-1 -> -0.057529144 | I30: Regression | J30: 1 | K30: 0.3764469 | L30: 0.3764469 | M30: 30.087746 | N30: 2.3897428e-07
B31: 42736 | C31: 27655.96 | D31: =C31/C30-1 -> 0.038664546 | F31: 718.7 | G31: =F31/F30-1 -> 0.052038352 | I31: Residual | J31: 118 | K31: 1.4763729 | L31: 0.012511635
B32: 42767 | C32: 28743.32 | D32: =C32/C31-1 -> 0.039317384 | F32: 778.5 | G32: =F32/F31-1 -> 0.083205788 | I32: Total | J32: 119 | K32: 1.8528198
B33: 42795 | C33: 29620.5 | D33: =C33/C32-1 -> 0.030517699 | F33: 765.75 | G33: =F33/F32-1 -> -0.016377649
B34: 42826 | C34: 29918.4 | D34: =C34/C33-1 -> 0.010057224 | F34: 873.25 | G34: =F34/F33-1 -> 0.14038524 | J34: Coefficients | K34: Standard Error | L34: t Stat | M34: P-value | N34: Lower 95% | O34: Upper 95% | P34: Lower 95.0% | Q34: Upper 95.0%
B35: 42856 | C35: 31145.8 | D35: =C35/C34-1 -> 0.041024921 | F35: 879.95 | G35: =F35/F34-1 -> 0.0076724878 | I35: Intercept | J35: -0.0046443527 | K35: 0.010471637 | L35: -0.44351737 | M35: 0.65820371 | N35: -0.025381044 | O35: 0.016092339 | P35: -0.025381044 | Q35: 0.016092339
B36: 42887 | C36: 30921.61 | D36: =C36/C35-1 -> -0.0071980813 | F36: 919.1 | G36: =F36/F35-1 -> 0.044491164 | I36: X Variable 1 | J36: 1.2168975 | K36: 0.22184987 | L36: 5.4852298 | M36: 2.3897428e-07 | N36: 0.77757438 | O36: 1.6562207 | P36: 0.77757438 | Q36: 1.6562207
B37: 42917 | C37: 32514.94 | D37: =C37/C36-1 -> 0.051528041 | F37: 969.85 | G37: =F37/F36-1 -> 0.05521706
B38: 42948 | C38: 31730.49 | D38: =C38/C37-1 -> -0.024125833 | F38: 871.35 | G38: =F38/F37-1 -> -0.1015621
B39: 42979 | C39: 31283.72 | D39: =C39/C38-1 -> -0.014080148 | F39: 890.4 | G39: =F39/F38-1 -> 0.021862627
B40: 43009 | C40: 33213.13 | D40: =C40/C39-1 -> 0.061674571 | F40: 951.45 | G40: =F40/F39-1 -> 0.06856469
B41: 43040 | C41: 33149.35 | D41: =C41/C40-1 -> -0.0019203249 | F41: 910.4 | G41: =F41/F40-1 -> -0.043144674
B42: 43070 | C42: 34056.83 | D42: =C42/C41-1 -> 0.027375499 | F42: 1135.5 | G42: =F42/F41-1 -> 0.24725395
B43: 43101 | C43: 35965.02 | D43: =C43/C42-1 -> 0.056029583 | F43: 1057.15 | G43: =F43/F42-1 -> -0.06900044
B44: 43132 | C44: 34184.04 | D44: =C44/C43-1 -> -0.049519783 | F44: 1176.1 | G44: =F44/F43-1 -> 0.11251951
B45: 43160 | C45: 32968.68 | D45: =C45/C44-1 -> -0.035553434 | F45: 1144.2 | G45: =F45/F44-1 -> -0.027123544
B46: 43191 | C46: 35160.36 | D46: =C46/C45-1 -> 0.066477639 | F46: 1344.6 | G46: =F46/F45-1 -> 0.17514421
B47: 43221 | C47: 35322.38 | D47: =C47/C46-1 -> 0.0046080302 | F47: 1243.3 | G47: =F47/F46-1 -> -0.075338391
B48: 43252 | C48: 35423.48 | D48: =C48/C47-1 -> 0.002862208 | F48: 1233.7 | G48: =F48/F47-1 -> -0.0077213866
... B134: 45870 | C134: 81644.39 | D134: =C134/C133-1 -> 0.0056513731 | F134: 389.35 | G134: =F134/F133-1 -> -0.073196858

Sheet Comps Data
B7: Comps Data
B8: All Figure In INR Cr.
B9: S.No. | C9: Name | D9: CMP Rs. | E9: No. Eq. Shares Cr. | F9: Debt Rs.Cr. | G9: Cash Rs.Cr. | H9: NP Ann Rs.Cr. | I9: Sales Ann Rs.Cr. | J9: Dep Ann Rs.Cr. | K9: EBIT Ann Rs.Cr. | L9: EV / EBITDA | M9: EV Rs.Cr. | N9: Mar Cap Rs.Cr. | O9: Tax 12M Rs.Cr.
B10: 1 | C10: BASF India | D10: 4526.4 | E10: 4.33 | F10: 156.76 | G10: 807.1 | H10: 499.2 | I10: 15162.35 | J10: 177.79 | K10: 648.26 | L10: 27.53 | M10: 20238.44 | N10: 20888.78 | O10: 148.05
B11: =B10+1 -> 2 | C11: Atul | D11: 6420 | E11: 2.94 | F11: 201.73 | G11: 64.66 | H11: 498.83 | I11: 5583.35 | J11: 316.82 | K11: 721.32 | L11: 18.21 | M11: 19249.19 | N11: 19112.12 | O11: 192.81
B12: =B11+1 -> 3 | C12: Vinati Organics | D12: 1743.65 | E12: 10.37 | F12: 62.62 | G12: 3.51 | H12: 415.23 | I12: 2248.1 | J12: 80.75 | K12: 548.75 | L12: 29.66 | M12: 18669.16 | N12: 18610.05 | O12: 133
B13: =B12+1 -> 4 | C13: Fine Organic | D13: 4865 | E13: 3.07 | F13: 2.65 | G13: 891.01 | H13: 389.66 | I13: 2205.2 | J13: 51.38 | K13: 526.33 | L13: 26.29 | M13: 15186.67 | N13: 16075.03 | O13: 134.99
B14: =B13+1 -> 5 | C14: Clean Science | D14: 1190.65 | E14: 10.63 | F14: 1.06 | G14: 14.86 | H14: 292.3 | I14: 922.32 | J14: 44.44 | K14: 390.83 | L14: 29.03 | M14: 12814.78 | N14: 12828.58 | O14: 100.01
B15: =B14+1 -> 6 | C15: Anupam Rasayan | D15: 1140.9 | E15: 10.99 | F15: 1373.39 | G15: 127.72 | H15: 159.97 | I15: 1436.97 | J15: 102.28 | K15: 310.07 | L15: 33.32 | M15: 13740.47 | N15: 12494.8 | O15: 37.88
B16: =B15+1 -> 7 | C16: Jubilant Ingrev. | D16: 701.4 | E16: 15.93 | F16: 763.78 | G16: 98.73 | H16: 251.17 | I16: 4177.61 | J16: 157.63 | K16: 399.25 | L16: 21.46 | M16: 12681.22 | N16: 12016.17 | O16: 99.82
B17: =B16+1 -> 8 | C17: Alkyl Amines | D17: 2104.1 | E17: 5.11 | F17: 5.52 | G17: 204.06 | H17: 186.11 | I17: 1571.82 | J17: 71.24 | K17: 249.92 | L17: 36.64 | M17: 11768.83 | N17: 11967.37 | O17: 62.53
B18: =B17+1 -> 9 | C18: Aether Industri. | D18: 765.1 | E18: 13.26 | F18: 137.07 | G18: 239.75 | H18: 152.09 | I18: 788.52 | J18: 42.8 | K18: 226.99 | L18: 34.55 | M18: 9887.99 | N18: 9990.67 | O18: 56.38
B19: =B18+1 -> 10 | C19: Privi Speci. | D19: 2419 | E19: 3.91 | F19: 1142.83 | G19: 50.19 | H19: 184.75 | I19: 2101.19 | J19: 131.75 | K19: 345.74 | L19: 20.6 | M19: 10675.11 | N19: 9582.47 | O19: 81.93
B22: =B13+1 -> 5 | C22: Aarti Industries | D22: 389.45 | E22: 36.26 | F22: 3847 | G22: 295 | H22: 331 | I22: 7271 | J22: 434 | K22: 580 | L22: 19.9 | M22: 18284.35 | N22: 14732.35 | O22: -33

Sheet Comps 
B9: BSE: 524208 | NSE: AARTIIND
B10: Comparable Analysis
B11: All Figure In INR Cr.
B12: Company Data | E12: Market Data | L12: Financial data | P12: Valution
E13: Price | F13: Share | G13: Market Cap | H13: Debt | I13: Cash | J13: EV | L13: Sales | M13: EBITDA | N13: Earnings | P13: EV/Sales | Q13: EV/EBITDA | R13: P/E
B14: Company Name | E14: (/share) | F14: Cr. | G14: ₹ Cr. | H14: ₹ Cr. | I14: ₹ Cr. | J14: ₹ Cr. | L14: ₹ Cr. | M14: ₹ Cr. | N14: ₹ Cr. | P14: x | Q14: x | R14: x
B15: BASF India | E15: ='Comps Data'!D10 -> 4526.4 | F15: ='Comps Data'!E10 -> 4.33 | G15: =F15*E15 -> 19599.312 | H15: ='Comps Data'!F10 -> 156.76 | I15: ='Comps Data'!G10 -> 807.1 | J15: =G15+H15-I15 -> 18948.972 | L15: ='Comps Data'!I10 -> 15162.35 | M15: ='Comps Data'!K10+'Comps Data'!J10 -> 826.05 | N15: ='Comps Data'!H10 -> 499.2 | P15: =J15/L15 -> 1.2497385 | Q15: =J15/M15 -> 22.939255 | R15: =G15/N15 -> 39.261442
B16: Atul | E16: ='Comps Data'!D11 -> 6420 | F16: ='Comps Data'!E11 -> 2.94 | G16: =F16*E16 -> 18874.8 | H16: ='Comps Data'!F11 -> 201.73 | I16: ='Comps Data'!G11 -> 64.66 | J16: =G16+H16-I16 -> 19011.87 | L16: ='Comps Data'!I11 -> 5583.35 | M16: ='Comps Data'!K11+'Comps Data'!J11 -> 1038.14 | N16: ='Comps Data'!H11 -> 498.83 | P16: =J16/L16 -> 3.4051009 | Q16: =J16/M16 -> 18.313397 | R16: =G16/N16 -> 37.838141
B17: Vinati Organics | E17: ='Comps Data'!D12 -> 1743.65 | F17: ='Comps Data'!E12 -> 10.37 | G17: =F17*E17 -> 18081.65 | H17: ='Comps Data'!F12 -> 62.62 | I17: ='Comps Data'!G12 -> 3.51 | J17: =G17+H17-I17 -> 18140.761 | L17: ='Comps Data'!I12 -> 2248.1 | M17: ='Comps Data'!K12+'Comps Data'!J12 -> 629.5 | N17: ='Comps Data'!H12 -> 415.23 | P17: =J17/L17 -> 8.0693744 | Q17: =J17/M17 -> 28.817729 | R17: =G17/N17 -> 43.546108
B18: Fine Organic | E18: ='Comps Data'!D13 -> 4865 | F18: ='Comps Data'!E13 -> 3.07 | G18: =F18*E18 -> 14935.55 | H18: ='Comps Data'!F13 -> 2.65 | I18: ='Comps Data'!G13 -> 891.01 | J18: =G18+H18-I18 -> 14047.19 | L18: ='Comps Data'!I13 -> 2205.2 | M18: ='Comps Data'!K13+'Comps Data'!J13 -> 577.71 | N18: ='Comps Data'!H13 -> 389.66 | P18: =J18/L18 -> 6.3700299 | Q18: =J18/M18 -> 24.315297 | R18: =G18/N18 -> 38.329698
B19: Clean Science | E19: ='Comps Data'!D14 -> 1190.65 | F19: ='Comps Data'!E14 -> 10.63 | G19: =F19*E19 -> 12656.61 | H19: ='Comps Data'!F14 -> 1.06 | I19: ='Comps Data'!G14 -> 14.86 | J19: =G19+H19-I19 -> 12642.81 | L19: ='Comps Data'!I14 -> 922.32 | M19: ='Comps Data'!K14+'Comps Data'!J14 -> 435.27 | N19: ='Comps Data'!H14 -> 292.3 | P19: =J19/L19 -> 13.707617 | Q19: =J19/M19 -> 29.045901 | R19: =G19/N19 -> 43.300067
B20: Anupam Rasayan | E20: ='Comps Data'!D15 -> 1140.9 | F20: ='Comps Data'!E15 -> 10.99 | G20: =F20*E20 -> 12538.491 | H20: ='Comps Data'!F15 -> 1373.39 | I20: ='Comps Data'!G15 -> 127.72 | J20: =G20+H20-I20 -> 13784.161 | L20: ='Comps Data'!I15 -> 1436.97 | M20: ='Comps Data'!K15+'Comps Data'!J15 -> 412.35 | N20: ='Comps Data'!H15 -> 159.97 | P20: =J20/L20 -> 9.5925183 | Q20: =J20/M20 -> 33.428304 | R20: =G20/N20 -> 78.380265
B21: Jubilant Ingrev. | E21: ='Comps Data'!D16 -> 701.4 | F21: ='Comps Data'!E16 -> 15.93 | G21: =F21*E21 -> 11173.302 | H21: ='Comps Data'!F16 -> 763.78 | I21: ='Comps Data'!G16 -> 98.73 | J21: =G21+H21-I21 -> 11838.352 | L21: ='Comps Data'!I16 -> 4177.61 | M21: ='Comps Data'!K16+'Comps Data'!J16 -> 556.88 | N21: ='Comps Data'!H16 -> 251.17 | P21: =J21/L21 -> 2.8337619 | Q21: =J21/M21 -> 21.258354 | R21: =G21/N21 -> 44.485018
B22: Alkyl Amines | E22: ='Comps Data'!D17 -> 2104.1 | F22: ='Comps Data'!E17 -> 5.11 | G22: =F22*E22 -> 10751.951 | H22: ='Comps Data'!F17 -> 5.52 | I22: ='Comps Data'!G17 -> 204.06 | J22: =G22+H22-I22 -> 10553.411 | L22: ='Comps Data'!I17 -> 1571.82 | M22: ='Comps Data'!K17+'Comps Data'!J17 -> 321.16 | N22: ='Comps Data'!H17 -> 186.11 | P22: =J22/L22 -> 6.7141346 | Q22: =J22/M22 -> 32.860291 | R22: =G22/N22 -> 57.772022
B23: Aether Industri. | E23: ='Comps Data'!D18 -> 765.1 | F23: ='Comps Data'!E18 -> 13.26 | G23: =F23*E23 -> 10145.226 | H23: ='Comps Data'!F18 -> 137.07 | I23: ='Comps Data'!G18 -> 239.75 | J23: =G23+H23-I23 -> 10042.546 | L23: ='Comps Data'!I18 -> 788.52 | M23: ='Comps Data'!K18+'Comps Data'!J18 -> 269.79 | N23: ='Comps Data'!H18 -> 152.09 | P23: =J23/L23 -> 12.735943 | Q23: =J23/M23 -> 37.223566 | R23: =G23/N23 -> 66.705411
B24: Privi Speci. | E24: ='Comps Data'!D19 -> 2419 | F24: ='Comps Data'!E19 -> 3.91 | G24: =F24*E24 -> 9458.29 | H24: ='Comps Data'!F19 -> 1142.83 | I24: ='Comps Data'!G19 -> 50.19 | J24: =G24+H24-I24 -> 10550.93 | L24: ='Comps Data'!I19 -> 2101.19 | M24: ='Comps Data'!K19+'Comps Data'!J19 -> 477.49 | N24: ='Comps Data'!H19 -> 184.75 | P24: =J24/L24 -> 5.0214069 | Q24: =J24/M24 -> 22.096651 | R24: =G24/N24 -> 51.195074
B27: High | P27: =MAX(P15:P24) -> 13.707617 | Q27: =MAX(Q15:Q24) -> 37.223566 | R27: =MAX(R15:R24) -> 78.380265
B28: 75th Percentile | P28: =QUARTILE(P15:P24,3) -> 9.2117323 | Q28: =QUARTILE(Q15:Q24,3) -> 31.906693 | R28: =QUARTILE(R15:R24,3) -> 56.127785
B29: Average | P29: =AVERAGE(P15:P24) -> 6.9699626 | Q29: =AVERAGE(Q15:Q24) -> 27.029875 | R29: =AVERAGE(R15:R24) -> 50.081325
B30: Median | P30: =MEDIAN(P15:P24) -> 6.5420822 | Q30: =MEDIAN(Q15:Q24) -> 26.566513 | R30: =MEDIAN(R15:R24) -> 44.015563
B31: 25th Percentile | P31: =QUARTILE(P15:P24,1) -> 3.8091774 | Q31: =QUARTILE(Q15:Q24,1) -> 22.307302 | R31: =QUARTILE(R15:R24,1) -> 40.271098
B32: Low | P32: =MIN(P15:P24) -> 1.2497385 | Q32: =MIN(Q15:Q24) -> 18.313397 | R32: =MIN(R15:R24) -> 37.838141
B34: Aarti Industries | E34: ='Comps Data'!D22 -> 389.45 | F34: ='Comps Data'!E22 -> 36.26 | G34: =F34*E34 -> 14121.457 | H34: ='Comps Data'!F22 -> 3847 | I34: ='Comps Data'!G22 -> 295 | J34: =G34+H34-I34 -> 17673.457 | L34: ='Comps Data'!I22 -> 7271 | M34: ='Income statement'!G21 -> 1000.45 | N34: ='Income statement'!G44 -> 330.87 | P34: =J34/L34 -> 2.4306776 | Q34: =J34/M34 -> 17.665508 | R34: =J34/N34 -> 53.415109
B37: Median
B38: Metric | E38: Comps | F38: EV | G38: Net Debt | H38: Equity Value | I38: no of Shares | J38: Share Price | L38: Prediction
B39: EV/REVENUE | E39: 6.9699626 | F39: =E39*L34 -> 50678.598 | G39: =$H$34-$I$34 -> 3552 | H39: =F39-G39 -> 47126.598 | I39: =$F$34 -> 36.26 | J39: =H39/I39 -> 1299.6855 | L39: =IF(J39>$E$34,"Undervalued","Overvalued") -> Undervalued
B40: EV/EBITDA | E40: 27.029875 | F40: =E40*M34 -> 27042.038 | G40: =$H$34-$I$34 -> 3552 | H40: =F40-G40 -> 23490.038 | I40: =$F$34 -> 36.26 | J40: =H40/I40 -> 647.82234 | L40: =IF(J40>$E$34,"Undervalued","Overvalued") -> Undervalued
B41: P/E | E41: 50.081325 | F41: =H41+G41 -> 20122.408 | G41: =$H$34-$I$34 -> 3552 | H41: =E41*N34 -> 16570.408 | I41: =$F$34 -> 36.26 | J41: =H41/I41 -> 456.98863 | L41: =IF(J41>$E$34,"Undervalued","Overvalued") -> Undervalued
B43: Average
B44: Metric | E44: Comps | F44: EV | G44: Net Debt | H44: Equity Value | I44: no of Shares | J44: Share Price | L44: Prediction
B45: EV/REVENUE | E45: 6.5420822 | F45: =E45*L34 -> 47567.48 | G45: =G39 -> 3552 | H45: =F45-G45 -> 44015.48 | I45: =I39 -> 36.26 | J45: =H45/I45 -> 1213.8853 | L45: =IF(J45>$E$34,"Undervalued","Overvalued") -> Undervalued
B46: EV/EBITDA | E46: 26.566513 | F46: =E46*M34 -> 26578.468 | G46: =G40 -> 3552 | H46: =F46-G46 -> 23026.468 | I46: =I40 -> 36.26 | J46: =H46/I46 -> 635.03772 | L46: =IF(J46>$E$34,"Undervalued","Overvalued") -> Undervalued
B47: P/E | E47: 44.015563 | F47: =H47+G47 -> 18115.429 | G47: =G41 -> 3552 | H47: =E47*N34 -> 14563.429 | I47: =I41 -> 36.26 | J47: =H47/I47 -> 401.63898 | L47: =IF(J47>$E$34,"Undervalued","Overvalued") -> Undervalued

Sheet WACC
B9: BSE: 524208 | NSE: AARTIIND
B10: Comparables Companies Beta
B11: All Figure In INR Cr.
B12: Name | D12: equity Value | E12: Total Debt | F12: Debt/Equity | G12: Debt/Capital | H12: Tax rate | I12: Levered Beta | J12: Unlevered Beta
B13: ='Comps '!B15 -> BASF India | D13: ='Comps '!G15 -> 19599.312 | E13: ='Comps '!H15 -> 156.76 | F13: =E13/D13 -> 0.0079982399 | G13: =E13/(SUM(D13:E13)) -> 0.0079347757 | H13: 0.2629 | I13: 0.59 | J13: =I13/(1+F13*(1-H13)) -> 0.58654204
B14: ='Comps '!B16 -> Atul | D14: ='Comps '!G16 -> 18874.8 | E14: ='Comps '!H16 -> 201.73 | F14: =E14/D14 -> 0.010687795 | G14: =E14/(SUM(D14:E14)) -> 0.010574774 | H14: 0.2708 | I14: 0.21 | J14: =I14/(1+F14*(1-H14)) -> 0.20837601
B15: ='Comps '!B17 -> Vinati Organics | D15: ='Comps '!G17 -> 18081.65 | E15: ='Comps '!H17 -> 62.62 | F15: =E15/D15 -> 0.0034631794 | G15: =E15/(SUM(D15:E15)) -> 0.0034512272 | H15: 0.2442 | I15: 0.17 | J15: =I15/(1+F15*(1-H15)) -> 0.16955619
B16: ='Comps '!B18 -> Fine Organic | D16: ='Comps '!G18 -> 14935.55 | E16: ='Comps '!H18 -> 2.65 | F16: =E16/D16 -> 0.00017742902 | G16: =E16/(SUM(D16:E16)) -> 0.00017739754 | H16: 0.2606 | I16: -0.11 | J16: =I16/(1+F16*(1-H16)) -> -0.10998557
B17: ='Comps '!B19 -> Clean Science | D17: ='Comps '!G19 -> 12656.61 | E17: ='Comps '!H19 -> 1.06 | F17: =E17/D17 -> 8.3750707e-05 | G17: =E17/(SUM(D17:E17)) -> 8.3743694e-05 | H17: 0.2594 | I17: 0.04 | J17: =I17/(1+F17*(1-H17)) -> 0.039997519
B18: ='Comps '!B20 -> Anupam Rasayan | D18: ='Comps '!G20 -> 12538.491 | E18: ='Comps '!H20 -> 1373.39 | F18: =E18/D18 -> 0.10953391 | G18: =E18/(SUM(D18:E18)) -> 0.098720655 | H18: 0.1915 | I18: 0.32 | J18: =I18/(1+F18*(1-H18)) -> 0.29396684
B19: ='Comps '!B21 -> Jubilant Ingrev. | D19: ='Comps '!G21 -> 11173.302 | E19: ='Comps '!H21 -> 763.78 | F19: =E19/D19 -> 0.06835759 | G19: =E19/(SUM(D19:E19)) -> 0.063983811 | H19: 0.2645 | I19: 0.41 | J19: =I19/(1+F19*(1-H19)) -> 0.3903732
B20: ='Comps '!B22 -> Alkyl Amines | D20: ='Comps '!G22 -> 10751.951 | E20: ='Comps '!H22 -> 5.52 | F20: =E20/D20 -> 0.0005133952 | G20: =E20/(SUM(D20:E20)) -> 0.00051313176 | H20: 0.2515 | I20: 0.64 | J20: =I20/(1+F20*(1-H20)) -> 0.63975416
B21: ='Comps '!B23 -> Aether Industri. | D21: ='Comps '!G23 -> 10145.226 | E21: ='Comps '!H23 -> 137.07 | F21: =E21/D21 -> 0.013510788 | G21: =E21/(SUM(D21:E21)) -> 0.01333068 | H21: 0.254 | I21: 0.05 | J21: =I21/(1+F21*(1-H21)) -> 0.049501076
B22: ='Comps '!B24 -> Privi Speci. | D22: ='Comps '!G24 -> 9458.29 | E22: ='Comps '!H24 -> 1142.83 | F22: =E22/D22 -> 0.12082839 | G22: =E22/(SUM(D22:E22)) -> 0.10780276 | H22: 0.2798 | I22: -0.37 | J22: =I22/(1+F22*(1-H22)) -> -0.34037993
B24: Average | F24: =AVERAGE(F13:F22) -> 0.033515448 | G24: =AVERAGE(G13:G22) -> 0.030657296 | H24: =AVERAGE(H13:H22) -> 0.25392 | I24: =AVERAGE(I13:I22) -> 0.195 | J24: =AVERAGE(J13:J22) -> 0.19277015
B25: Median | F25: =MEDIAN(F13:F22) -> 0.0093430177 | G25: =MEDIAN(G13:G22) -> 0.009254775 | H25: =MEDIAN(H13:H22) -> 0.26 | I25: =MEDIAN(I13:I22) -> 0.19 | J25: =MEDIAN(J13:J22) -> 0.1889661
B27: ='Comps '!B34 -> Aarti Industries | D27: ='Comps '!G34 -> 14121.457 | E27: ='Comps '!H34 -> 3847 | F27: =E27/D27 -> 0.27242231 | G27: =E27/(SUM(D27:E27)) -> 0.2140974 | H27: =Assumption!C20 -> 0.061471938 | I27: 0.54 | J27: =I27/(1+F27*(1-H27)) -> 0.43004725
B29: WACC Calculation
B31: Target Capital Structure
B33: Proportion of Debt | C33: =G25 -> 0.009254775
B34: Proportion of Equity | C34: =1-C33 -> 0.99074522
B36: Current Capital structure
B37: Market cap | C37: =D27 -> 14121.457
B38: Total Debt | C38: =E27 -> 3847
B39: Debt/equity | C39: =C38/C37 -> 0.27242231
B41: Cost of debt
B42: Pre-tax cost of debt | C42: ='Debt Schedules'!G16 -> 0.076032319
B43: tax rate | C43: =Assumption!C20 -> 0.061471938
B44: After -Tax cost of debt | C44: =C42*(1-C43) -> 0.071358465
B46: Cost of equity | E46: Cost of equity
B47: Risk free Rate | C47: =Assumption!C19 -> 0.06512 | E47: Risk free Rate | F47: =C47 -> 0.06512
B48: Equity Market Return | C48: ='Equity Market'!F14 -> 0.1132251 | E48: Equity Market Return | F48: ='Equity Market'!F14 -> 0.1132251
B49: Equity risk premium | C49: =C48-C47 -> 0.048105104 | E49: Equity risk premium | F49: =F48-F47 -> 0.048105104
B50: Levered Equity Beta | C50: =J25*(1+C39*(1-C43)) -> 0.2372802 | E50: Beta ( by market data) | F50: =Beta!J15 -> 1.2168905
B51: Cost of equity | C51: =C47+(C50*C49) -> 0.076534388 | E51: Cost of equity | F51: =F47+(F50*F49) -> 0.12365864
B53: WACC | C53: =(C51*C34)+(C44*C33) -> 0.076486486 | E53: WACC | F53: =(F51*(1-C39))+(C39*C44) -> 0.10941091

Sheet DCF
B9: BSE: 524208 | NSE: AARTIIND
B10: DCF Analysis
B11: All Figure In INR Cr.
B12: Particulars | C12: 2021 | D12: =C12+1 -> 2022 | E12: =D12+1 -> 2023 | F12: =E12+1 -> 2024 | G12: 2025 | H12: 2026 | I12: 2027 | J12: 2028 | K12: 2029 | L12: 2030 | M12: 2031 | N12: 2032 | O12: 2033 | P12: 2034 | Q12: 2035
C13: Audited | D13: Audited | E13: Audited | F13: Audited | G13: Audited | H13: Forecasted | I13: Forecasted | J13: Forecasted | K13: Forecasted | L13: Forecasted | M13: Forecasted | N13: Forecasted | O13: Forecasted | P13: Forecasted | Q13: Forecasted
G14: Entry | R14: Exit
B15: DATE | G15: =Assumption!C16 -> 45888 | H15: =DATE(YEAR(Assumption!$C$17)+DCF!H16,MONTH(Assumption!$C$17),DAY(Assumption!$C$17)) -> 46112 | I15: =DATE(YEAR(Assumption!$C$17)+DCF!I16,MONTH(Assumption!$C$17),DAY(Assumption!$C$17)) -> 46477 | J15: =DATE(YEAR(Assumption!$C$17)+DCF!J16,MONTH(Assumption!$C$17),DAY(Assumption!$C$17)) -> 46843 | K15: =DATE(YEAR(Assumption!$C$17)+DCF!K16,MONTH(Assumption!$C$17),DAY(Assumption!$C$17)) -> 47208 | L15: =DATE(YEAR(Assumption!$C$17)+DCF!L16,MONTH(Assumption!$C$17),DAY(Assumption!$C$17)) -> 47573 | M15: =DATE(YEAR(Assumption!$C$17)+DCF!M16,MONTH(Assumption!$C$17),DAY(Assumption!$C$17)) -> 47938 | N15: =DATE(YEAR(Assumption!$C$17)+DCF!N16,MONTH(Assumption!$C$17),DAY(Assumption!$C$17)) -> 48304 | O15: =DATE(YEAR(Assumption!$C$17)+DCF!O16,MONTH(Assumption!$C$17),DAY(Assumption!$C$17)) -> 48669 | ... Q15: =DATE(YEAR(Assumption!$C$17)+DCF!Q16,MONTH(Assumption!$C$17),DAY(Assumption!$C$17)) -> 49399 | R15: =Q15 -> 49399
B16: Time Periods | H16: 0 | I16: 1 | J16: 2 | K16: 3 | L16: 4 | M16: 5 | N16: 6 | O16: 7 | P16: 8 | Q16: 9
B17: Year Frac | C17: 0 | D17: 0 | E17: 0 | F17: 0 | G17: 0 | H17: =YEARFRAC(G15,H15) -> 0.61666667 | I17: =YEARFRAC(H15,I15) -> 1 | J17: =YEARFRAC(I15,J15) -> 1 | K17: =YEARFRAC(J15,K15) -> 1 | L17: =YEARFRAC(K15,L15) -> 1 | M17: =YEARFRAC(L15,M15) -> 1 | N17: =YEARFRAC(M15,N15) -> 1 | O17: =YEARFRAC(N15,O15) -> 1 | ... Q17: =YEARFRAC(P15,Q15) -> 1 | R17: 1
B19: EBIT/ Operating Income | C19: ='Income statement'!C26 -> 750.22 | D19: ='Income statement'!D26 -> 1473.71 | E19: ='Income statement'!E26 -> 778.52 | F19: ='Income statement'!F26 -> 596.03 | G19: ='Income statement'!G26 -> 566.18 | H19: ='Income statement'!H26 -> 1101.8733 | I19: ='Income statement'!I26 -> 1261.007 | J19: ='Income statement'!J26 -> 1418.2163 | ... Q19: ='Income statement'!Q26 -> 2310.9414
B20: Tax rate | C20: =-C19*'Cost Build_up'!C39 -> -146.00249 | D20: =-D19*'Cost Build_up'!D39 -> -200.03534 | E20: =-E19*'Cost Build_up'!E39 -> -83.916073 | F20: =-F19*'Cost Build_up'!F39 -> 31.72938 | G20: =-G19*'Cost Build_up'!G39 -> 43.903743 | H20: =-H19*'Cost Build_up'!H39 -> -67.73429 | I20: =-I19*'Cost Build_up'!I39 -> -77.516543 | J20: =-J19*'Cost Build_up'!J39 -> -87.180502 | ... Q20: =-Q19*'Cost Build_up'!Q39 -> -142.05805
B21: NOPAT | C21: =SUM(C19:C20) -> 604.21751 | D21: =SUM(D19:D20) -> 1273.6747 | E21: =SUM(E19:E20) -> 694.60393 | F21: =SUM(F19:F20) -> 627.75938 | G21: =SUM(G19:G20) -> 610.08374 | H21: =SUM(H19:H20) -> 1034.139 | I21: =SUM(I19:I20) -> 1183.4904 | J21: =SUM(J19:J20) -> 1331.0358 | ... Q21: =SUM(Q19:Q20) -> 2168.8834
B22: Add: Depreciation & Amortization | C22: =-'Income statement'!C24 -> 231.31 | D22: =-'Income statement'!D24 -> 246.4 | E22: =-'Income statement'!E24 -> 310.45 | F22: =-'Income statement'!F24 -> 378.12 | G22: =-'Income statement'!G24 -> 434.27 | H22: =-'Income statement'!H24 -> 469.52218 | I22: =-'Income statement'!I24 -> 504.86253 | J22: =-'Income statement'!J24 -> 548.71175 | ... Q22: =-'Income statement'!Q24 -> 1117.6624
B23: Less: CapEx | C23: ='Cashflow Statement'!C37 -> -1314.82 | D23: ='Cashflow Statement'!D37 -> -1165.42 | E23: ='Cashflow Statement'!E37 -> -1326.3 | F23: ='Cashflow Statement'!F37 -> -1328.06 | G23: ='Cashflow Statement'!G37 -> -1385.97 | H23: ='Cashflow Statement'!H37 -> -1058.9518 | I23: ='Cashflow Statement'!I37 -> -1236.2088 | J23: ='Cashflow Statement'!J37 -> -1428.424 | ... Q23: ='Cashflow Statement'!Q37 -> -3117.8671
B24: Less: Change in Working Capital | C24: =SUM('Cashflow Statement'!C28:C30) -> -7.23 | D24: =SUM('Cashflow Statement'!D28:D30) -> -955.44 | E24: =SUM('Cashflow Statement'!E28:E30) -> 311.76 | F24: =SUM('Cashflow Statement'!F28:F30) -> 322.5 | G24: =SUM('Cashflow Statement'!G28:G30) -> 230.16 | H24: =SUM('Cashflow Statement'!H28:H30) -> -340.93311 | I24: =SUM('Cashflow Statement'!I28:I30) -> 65.059606 | J24: =SUM('Cashflow Statement'!J28:J30) -> 67.262399 | ... Q24: =SUM('Cashflow Statement'!Q28:Q30) -> 68.501816
B25: Unlevered FCFF | C25: =SUM(C21:C24) -> -486.52249 | D25: =SUM(D21:D24) -> -600.78534 | E25: =SUM(E21:E24) -> -9.4860733 | F25: =SUM(F21:F24) -> 0.31938015 | G25: =SUM(G21:G24) -> -111.45626 | H25: =SUM(H21:H24) -> 103.77627 | I25: =SUM(I21:I24) -> 517.20379 | J25: =SUM(J21:J24) -> 518.58592 | ... Q25: =SUM(Q21:Q24) -> 237.18045
B27: Transaction FCFF | C27: =C25*C17 -> 0 | D27: =D25*D17 -> 0 | E27: =E25*E17 -> 0 | F27: =F25*F17 -> 0 | G27: =G25*G17 -> 0 | H27: =H25*H17 -> 63.995369 | I27: =I25*I17 -> 517.20379 | J27: =J25*J17 -> 518.58592 | ... Q27: =Q25*Q17 -> 237.18045 | R27: =C37 -> 48881.452
B30: EV/EBITDA Multiple | C30: =Assumption!C21 -> 27.029875 | H30: Sensitivity - Intrinsic Value (Rs/share)
B31: Perpetual Growth Rate | C31: =Assumption!C22 -> 0.06
B32: Discount Rate | C32: =Assumption!C23 -> 0.10941091 | J32: Perpetual Growth Rate
I33: =C47 -> 464.82184 | J33: 0.04 | K33: 0.05 | L33: 0.06 | M33: 0.065 | N33: 0.07
B34: Terminal Value | E34: Rate of Return | H34: Discount Rate | I34: =I35+2% -> 0.14941091 | J34: 301.88538 | K34: 302.79086 | L34: 303.89888 | M34: 304.55135 | N34: 305.28597
B35: EV/EBITDA | C35: =C30*(Q19+Q22) -> 92674.731 | E35: Current price | F35: =Assumption!C25 -> 389.45 | I35: =I36+2% -> 0.12941091 | J35: 371.51526 | K35: 373.12892 | L35: 375.20752 | M35: 376.48886 | N35: 377.98587
B36: Prep.Growth | C36: =Q27*(1+C31)/(C32-C31) -> 5088.1736 | E36: Target Price | F36: =C47 -> 464.82184 | I36: 0.10941091 | J36: 457.02819 | K36: 460.2691 | L36: 464.82184 | M36: 467.86706 | N36: 471.68496
B37: Average | C37: =AVERAGE(C35:C36) -> 48881.452 | E37: Target Price Upside | F37: =F36/F35-1 -> 0.19353405 | I37: =I36-1% -> 0.099410908 | J37: 507.51924 | K37: 512.44152 | L37: 519.86172 | M37: 525.18909 | N37: 532.32782
I38: 0.076064732 | J38: 655.85622 | K38: 674.35164 | L38: 715.87319 | M38: 764.77848 | N38: 894.3226
B40: Intrinsic Value
B41: Enterpreise Value | C41: =XNPV($C$32,G27:R27,G15:R15) -> 20406.54 | J41: Exit Multiple
B42: Plus: Cash & Cash equivalent | C42: ='Comps '!I34 -> 295 | I42: =C47 -> 464.82184 | J42: 36 | K42: 32 | L42: 27.88705 | M42: 23 | N42: 18.278026
B43: Less- Debt | C43: =-'Comps '!H34 -> -3847 | H43: Discount Rate | I43: 0.14510464 | J43: 433.20827 | K43: 381.84209 | L43: 329.02545 | M43: 266.26818 | N43: 205.63073
B44: Less-non- controlling interest | C44: =-'Balance Sheet'!G43 -> -0.1 | I44: 0.12510464 | J44: 529.16666 | K44: 468.31314 | L44: 405.74126 | M44: 331.39271 | N44: 259.55552
B45: Equity Value | C45: =SUM(C41:C44) -> 16854.44 | I45: 0.10941091 | J45: 621.03078 | K45: 551.37336 | L45: 479.74899 | M45: 394.64417 | N45: 312.41404
I46: 0.09510464 | J46: 723.6769 | K46: 644.75657 | L46: 563.60774 | M46: 467.18584 | N46: 374.0209
B47: Equity value/share | C47: =C45/Assumption!C24 -> 464.82184 | I47: 0.076064732 | J47: 925.38032 | K47: 831.95593 | L47: 735.89346 | M47: 621.75104 | N47: 511.46415

Sheet Football Field Analysis
B9: BSE: 524208 | NSE: AARTIIND
B10: Football Field Analysis
B12: Football Field Data
E13: Comps Median | F13: Comps Average | G13: DCF (Average) | H13: 52-Week Hi/LO | I13: Market Consenses
B14: High | E14: 1343.5718 | F14: 1337.4393 | G14: 2172 | H14: 766 | I14: 625
B15: High | E15: =E14 -> 1343.5718 | F15: =F14 -> 1337.4393 | G15: =G14 -> 2172 | H15: =H14 -> 766 | I15: =I14 -> 625
B16: Low | E16: 435.57919 | F16: 483.02775 | G16: 89 | H16: 344 | I16: 370
B17: Low | E17: =E16 -> 435.57919 | F17: =F16 -> 483.02775 | G17: =G16 -> 89 | H17: =H16 -> 344 | I17: =I16 -> 370

Sheet Ratio Analysis
B7: BSE: 524208 | NSE: AARTIIND
B8: Ratio Analysis & Interpretation
B10: Particulars | E10: 2021 | F10: =E10+1 -> 2022 | G10: =F10+1 -> 2023 | H10: =G10+1 -> 2024 | I10: =H10+1 -> 2025 | J10: =I10+1 -> 2026 | K10: =J10+1 -> 2027 | L10: =K10+1 -> 2028 | M10: =L10+1 -> 2029 | ... S10: =R10+1 -> 2035
E11: Aduited | F11: Aduited | G11: Aduited | H11: Aduited | I11: Aduited | J11: Forecasted | K11: Forecasted | L11: Forecasted | M11: Forecasted | N11: Forecasted | O11: Forecasted | P11: Forecasted | Q11: Forecasted | R11: Forecasted | S11: Forecasted
B13: Profitability Ratio | U13: Interpretation
B15: Gross Margin | E15: ='Income statement'!C16 -> 0.52762699 | F15: ='Income statement'!D16 -> 0.53094317 | G15: ='Income statement'!E16 -> 0.41956281 | H15: ='Income statement'!F16 -> 0.39067621 | I15: ='Income statement'!G16 -> 0.35979712 | J15: ='Income statement'!H16 -> 0.44572126 | K15: ='Income statement'!I16 -> 0.44572126 | L15: ='Income statement'!J16 -> 0.44572126 | ... S15: ='Income statement'!Q16 -> 0.44572126 | U15: The Gross Margin has shown decline trends during the audited years, declining from 52.76% and 53.09% in the early years to a low of 35.98% in 2025, reflecting rising cost pressures and reduced pricing efficiency.Our forecasts suggest that the Gross Margin will stabilize around 44.57% over the projection period, reflecting steady cost control and stable revenue generation.
B17: EBITDA Margin | E17: ='Income statement'!C22 -> 0.21782251 | F17: ='Income statement'!D22 -> 0.28265667 | G17: ='Income statement'!E22 -> 0.16453227 | H17: ='Income statement'!F22 -> 0.15290858 | I17: ='Income statement'!G22 -> 0.1375885 | J17: ='Income statement'!H22 -> 0.19110171 | K17: ='Income statement'!I22 -> 0.19110171 | L17: ='Income statement'!J22 -> 0.19110171 | ... S17: ='Income statement'!Q22 -> 0.19110171 | U17: The company’s EBITDA margin displayed considerable fluctuations, peaking at 28.27% before declining to a low of 13.76%, reflecting cost pressures and weaker operating leverage. However, margins later improved to around 19.11%, where they have stabilized in recent years. Our forecasts suggest the margin will remain steady at this level, supported by improved cost discipline and operational efficiency. While below the earlier peak, the stabilization highlights greater financial consistency, ensuring sustainable operating profitability and providing a solid foundation for long-term performance.
B19: Operating Margin | E19: ='Income statement'!C27 -> 0.16648987 | F19: ='Income statement'!D27 -> 0.24216705 | G19: ='Income statement'!E27 -> 0.11762644 | H19: ='Income statement'!F27 -> 0.093556539 | I19: ='Income statement'!G27 -> 0.077864817 | J19: ='Income statement'!H27 -> 0.13400183 | K19: ='Income statement'!I27 -> 0.13646568 | L19: ='Income statement'!J27 -> 0.13779027 | ... S19: ='Income statement'!Q27 -> 0.12880603 | U19: The company’s operating margin peaked at 24.22% in 2022 before declining to 7.79% in 2025, reflecting rising operating costs and weaker efficiency. However, forecasts suggest a gradual recovery, with margins expected to improve steadily to 12.88% by 2035. This indicates stronger cost discipline and operational improvements,
B21: Pretax Margin | E21: ='Income statement'!C37 -> 0.14747786 | F21: ='Income statement'!D37 -> 0.22547823 | G21: ='Income statement'!E37 -> 0.092330983 | H21: ='Income statement'!F37 -> 0.062067558 | I21: ='Income statement'!G37 -> 0.042252301 | J21: ='Income statement'!H37 -> 0.10499627 | K21: ='Income statement'!I37 -> 0.10875328 | L21: ='Income statement'!J37 -> 0.10982433 | ... S21: ='Income statement'!Q37 -> 0.09947787 | U21: The company’s pretax margin peaked at 22.55% in 2022, but declined sharply to 4.23% in 2025, reflecting rising expenses and weaker operating leverage. Forecasts suggest a steady recovery, with margins expected to improve gradually to 11.00% by 2029 and decline to 9.95% in 2035. the upward trajectory indicates improving efficiency and financial discipline.
B23: Effective Tax Rate | E23: ='Cost Build_up'!C39 -> 0.1946129 | F23: ='Cost Build_up'!D39 -> 0.13573589 | G23: ='Cost Build_up'!E39 -> 0.10778923 | H23: ='Cost Build_up'!F39 -> -0.053234535 | I23: ='Cost Build_up'!G39 -> -0.077543791 | J23: ='Cost Build_up'!H39 -> 0.061471938 | K23: ='Cost Build_up'!I39 -> 0.061471938 | L23: ='Cost Build_up'!J39 -> 0.061471938 | ... S23: ='Cost Build_up'!Q39 -> 0.061471938 | U23: he company’s effective tax rate was 19.46% in 2021, but turned negative in subsequent years, reaching -7.75% in 2025, likely due to tax credits or losses carried forward. Forecasts suggest normalization, with the rate stabilizing at 6.15% by 2035. While significantly below historical levels, the steady outlook reflects improved predictability, though the lower rate may also indicate limited taxable income growth compared to earlier years.
B25: Net Profit Margin | E25: ='Income statement'!C45 -> 0.11616919 | F25: ='Income statement'!D45 -> 0.19483494 | G25: ='Income statement'!E45 -> 0.082378698 | H25: ='Income statement'!F45 -> 0.065371696 | I25: ='Income statement'!G45 -> 0.04550343 | J25: ='Income statement'!H45 -> 0.098541943 | K25: ='Income statement'!I45 -> 0.10206801 | L25: ='Income statement'!J45 -> 0.10307322 | ... S25: ='Income statement'!Q45 -> 0.093362772 | U25: The company’s net profit margin peaked at 19.48% in 2022, but declined significantly to 4.55% in 2025, reflecting rising costs and weaker profitability. Forecasts suggest gradual improvement, with margins expected to reach 10.32% by 2029 and decline to 9.34% in 2035. the steady upward trend highlights improving efficiency, cost management, and a healthier long-term earnings outlook.
B27: Return on Equity | E27: ='Income statement'!C44/'Balance Sheet'!C44 -> 0.14891868 | F27: ='Income statement'!D44/'Balance Sheet'!D44 -> 0.26250803 | G27: ='Income statement'!E44/'Balance Sheet'!E44 -> 0.11080109 | H27: ='Income statement'!F44/'Balance Sheet'!F44 -> 0.078720497 | I27: ='Income statement'!G44/'Balance Sheet'!G44 -> 0.059028905 | J27: ='Income statement'!H44/'Balance Sheet'!H44 -> 0.12824626 | K27: ='Income statement'!I44/'Balance Sheet'!I44 -> 0.13194081 | L27: ='Income statement'!J44/'Balance Sheet'!J44 -> 0.13126533 | ... S27: ='Income statement'!Q44/'Balance Sheet'!Q44 -> 0.098458641 | U27: The company’s ROE reached a peak of 26.25% in 2022, reflecting strong profitability and efficient equity utilization. However, it declined to 5.90% in 2025, driven by weaker margins and reduced earnings growth. Forecasts suggest a continued downtrend, with ROE expected to fall further to 9.85% by 2035. This indicates declining returns for shareholders and highlights the need for improved profitability or capital efficiency to sustain investor confidence.
B29: Return on Capital Employed | E29: ='Income statement'!C26/('Balance Sheet'!C37-'Balance Sheet'!C65) -> 0.14312969 | F29: ='Income statement'!D26/('Balance Sheet'!D37-'Balance Sheet'!D65) -> 0.25922597 | G29: ='Income statement'!E26/('Balance Sheet'!E37-'Balance Sheet'!E65) -> 0.13428361 | H29: ='Income statement'!F26/('Balance Sheet'!F37-'Balance Sheet'!F65) -> 0.084510657 | I29: ='Income statement'!G26/('Balance Sheet'!G37-'Balance Sheet'!G65) -> 0.074038331 | J29: ='Income statement'!H26/('Balance Sheet'!H37-'Balance Sheet'!H65) -> 0.1311692 | K29: ='Income statement'!I26/('Balance Sheet'!I37-'Balance Sheet'!I65) -> 0.13290334 | L29: ='Income statement'!J26/('Balance Sheet'!J37-'Balance Sheet'!J65) -> 0.13268934 | ... S29: ='Income statement'!Q26/('Balance Sheet'!Q37-'Balance Sheet'!Q65) -> 0.10720809 | U29: The company’s ROCE peaked at 25.92% in 2022, supported by strong profitability and efficient capital utilization. However, it declined to 7.40% in 2025, reflecting reduced operating efficiency and weaker earnings generation. Forecasts indicate a further slowdown, with ROCE expected to fall to 10.72% by 2035. This suggests diminishing returns on invested capital over time, highlighting the need for improved operational performance and better deployment of resources to enhance long-term shareholder value.
B31: Return on Assets | E31: ='Income statement'!C44/'Balance Sheet'!C37 -> 0.068501952 | F31: ='Income statement'!D44/'Balance Sheet'!D37 -> 0.15102749 | G31: ='Income statement'!E44/'Balance Sheet'!E37 -> 0.063539955 | H31: ='Income statement'!F44/'Balance Sheet'!F37 -> 0.041172813 | I31: ='Income statement'!G44/'Balance Sheet'!G37 -> 0.029771845 | J31: ='Income statement'!H44/'Balance Sheet'!H37 -> 0.066832319 | K31: ='Income statement'!I44/'Balance Sheet'!I37 -> 0.068980058 | L31: ='Income statement'!J44/'Balance Sheet'!J37 -> 0.06911576 | ... S31: ='Income statement'!Q44/'Balance Sheet'!Q37 -> 0.056435456 | U31: The company’s ROA peaked at 15.10% in 2022, reflecting strong asset efficiency and profitability. However, it dropped to 2.98% in 2025, driven by weaker earnings relative to the asset base. Forecasts indicate a gradual decline, with ROA expected to fall further to 5.64% by 2035. This downward trend highlights reduced asset productivity and underscores the need for better earnings generation from existing resources to sustain long-term financial performance.
B34: Liquidity Ratio
B37: Current Ratio | E37: ='Balance Sheet'!C35/'Balance Sheet'!C65 -> 0.98644246 | F37: ='Balance Sheet'!D35/'Balance Sheet'!D65 -> 1.2461986 | G37: ='Balance Sheet'!E35/'Balance Sheet'!E65 -> 0.88357429 | H37: ='Balance Sheet'!F35/'Balance Sheet'!F65 -> 0.96623945 | I37: ='Balance Sheet'!G35/'Balance Sheet'!G65 -> 0.83508539 | J37: ='Balance Sheet'!H35/'Balance Sheet'!H65 -> 0.91928726 | K37: ='Balance Sheet'!I35/'Balance Sheet'!I65 -> 1.0050483 | L37: ='Balance Sheet'!J35/'Balance Sheet'!J65 -> 1.0655656 | ... S37: ='Balance Sheet'!Q35/'Balance Sheet'!Q65 -> 1.0372013 | U37: The Current Ratio begins at 0.99x (2021), peaks at 1.25x (2022), then dips to 0.84x (2025), reflecting weaker short-term solvency. However, from 0.92x onward, estimates show gradual strengthening, reaching a stable range of 1.13x (2030–2032) before slightly softening to 1.04x (2035). Overall, liquidity improves toward and above the ideal benchmark of 1.0x.
B39: Quick Ratio | E39: =('Balance Sheet'!C35-'Balance Sheet'!C25)/'Balance Sheet'!C65 -> 0.59659853 | F39: =('Balance Sheet'!D35-'Balance Sheet'!D25)/'Balance Sheet'!D65 -> 0.8148639 | G39: =('Balance Sheet'!E35-'Balance Sheet'!E25)/'Balance Sheet'!E65 -> 0.51313539 | H39: =('Balance Sheet'!F35-'Balance Sheet'!F25)/'Balance Sheet'!F65 -> 0.58757204 | I39: =('Balance Sheet'!G35-'Balance Sheet'!G25)/'Balance Sheet'!G65 -> 0.41562428 | J39: =('Balance Sheet'!H35-'Balance Sheet'!H25)/'Balance Sheet'!H65 -> 0.51629735 | K39: =('Balance Sheet'!I35-'Balance Sheet'!I25)/'Balance Sheet'!I65 -> 0.60205836 | L39: =('Balance Sheet'!J35-'Balance Sheet'!J25)/'Balance Sheet'!J65 -> 0.6625757 | ... S39: =('Balance Sheet'!Q35-'Balance Sheet'!Q25)/'Balance Sheet'!Q65 -> 0.63421138 | U39: The Quick Ratio shows weak liquidity historically, ranging from 0.60x (2021) to 0.42x (2025), all below the ideal 1.0x benchmark. However, estimates indicate gradual improvement from 0.52x to 0.73x by 2031, before slightly declining to 0.63x in 2035. This trend suggests cautious liquidity management but potential recovery in short-term solvency ahead.
B41: Cash Cycle Days | E41: ='Working Capital Schedules'!C24 -> 125.91358 | F41: ='Working Capital Schedules'!D24 -> 140.81804 | G41: ='Working Capital Schedules'!E24 -> 129.34246 | H41: ='Working Capital Schedules'!F24 -> 89.81442 | I41: ='Working Capital Schedules'!G24 -> 56.436553 | J41: ='Working Capital Schedules'!H24 -> 108.46501 | K41: ='Working Capital Schedules'!I24 -> 108.46501 | L41: ='Working Capital Schedules'!J24 -> 108.46501 | ... S41: ='Working Capital Schedules'!Q24 -> 108.46501 | U41: The cash conversion cycle stood at 126 days in 2021, reflecting a long duration to convert investments in inventory and receivables into cash inflows. By 2025, it improved significantly to 56 days, indicating better efficiency in managing working capital. Looking ahead to 2035, the CCC is projected to remain stable at 108 days, suggesting that the company has achieved a consistent and sustainable balance in receivables, payables, and inventory management. While stability is positive, further reduction could unlock additional efficiency and free up cash for growth opportunities.
B44: Solvency Ratio
B47: Asset/ Equity | E47: ='Balance Sheet'!C37/'Balance Sheet'!C44 -> 2.1739333 | F47: ='Balance Sheet'!D37/'Balance Sheet'!D44 -> 1.7381473 | G47: ='Balance Sheet'!E37/'Balance Sheet'!E44 -> 1.7438018 | H47: ='Balance Sheet'!F37/'Balance Sheet'!F44 -> 1.9119533 | I47: ='Balance Sheet'!G37/'Balance Sheet'!G44 -> 1.982709 | J47: ='Balance Sheet'!H37/'Balance Sheet'!H44 -> 1.9189257 | K47: ='Balance Sheet'!I37/'Balance Sheet'!I44 -> 1.9127384 | L47: ='Balance Sheet'!J37/'Balance Sheet'!J44 -> 1.8992098 | ... S47: ='Balance Sheet'!Q37/'Balance Sheet'!Q44 -> 1.7446238 | U47: In 2021, the Asset-to-Equity ratio stood at 2.17x, showing that the company used moderate leverage, with equity funding a fair share of assets. By 2025, it improved to 1.98x, reflecting a shift toward stronger equity backing and lower dependence on debt. Looking ahead to 2035, the ratio is forecasted at 1.74x, suggesting further deleveraging and a healthier balance sheet. This trend highlights growing financial stability, reduced risk from external liabilities, and long-term sustainability.
B49: Debt/ Equity | E49: ='Debt Schedules'!C15/'Balance Sheet'!C44 -> 0.70896749 | F49: ='Debt Schedules'!D15/'Balance Sheet'!D44 -> 0.57275223 | G49: ='Debt Schedules'!E15/'Balance Sheet'!E44 -> 0.5908206 | H49: ='Debt Schedules'!F15/'Balance Sheet'!F44 -> 0.68475132 | I49: ='Debt Schedules'!G15/'Balance Sheet'!G44 -> 0.68646547 | J49: ='Debt Schedules'!H15/'Balance Sheet'!H44 -> 0.65468326 | K49: ='Debt Schedules'!I15/'Balance Sheet'!I44 -> 0.65027515 | L49: ='Debt Schedules'!J15/'Balance Sheet'!J44 -> 0.64063675 | ... S49: ='Debt Schedules'!Q15/'Balance Sheet'!Q44 -> 0.53050289 | U49: The company’s debt-to-equity ratio was 0.71x in 2021, reflecting moderate leverage with debt forming just over half of equity. By 2025, the ratio declined to 0.69x, indicating reduced reliance on borrowings and a stronger equity position. Looking forward, the ratio is projected to fall further to 0.53x by 2035, highlighting a conservative capital structure with minimal financial risk. This declining leverage trend signals enhanced balance sheet strength, lower interest burden, and greater capacity to fund growth through internal accruals.
