Workbook

Sheet Assumptions
B8: Scenario
B9: Base | C9: =IF(B9="Base",2,IF(B9="Best",1,3)) -> 2
B11: Assumptions
B12: Transaction Date | C12: 45879
B13: Fiscal Year End | C13: 46112
B14: Risk Free Rate | C14: 0.0637
B15: Tax Rate | C15: ='Cost Build_Up'!H38 -> 0.25354554
B16: Perpetual Growth Rate | C16: 0.05
B17: Discount Rate | C17: =WACC!C25 -> 0.10338768
B18: Shares Outstanding(Mn) | C18: 580.8
B19: Current Market Price | C19: 1042
B20: Market Cap (mn.) | C20: =C19*C18 -> 605193.6

Sheet P&L
B6: P&L Statement
B8: Particulars | C8: 2020 | D8: =C8+1 -> 2021 | E8: =D8+1 -> 2022 | F8: =E8+1 -> 2023 | G8: =F8+1 -> 2024
B9: INCOME
B10: Revenue from operations | C10: 230985.1 | D10: 247746.2 | E10: 234554.9 | F10: 248553.8 | G10: 290018.7
B11: Other income | C11: 1918.7 | D11: 3808.5 | E11: 3203.5 | F11: 2905.9 | G11: 5573.8
B12: Total Income | C12: =SUM(C10:C11) -> 232903.8 | D12: =SUM(D10:D11) -> 251554.7 | E12: =SUM(E10:E11) -> 237758.4 | F12: =SUM(F10:F11) -> 251459.7 | G12: =SUM(G10:G11) -> 295592.5
B13: EXPENSES
B14: Cost of materials consumed | C14: 77249.8 | D14: 83172.6 | E14: 73718.3 | F14: 96525.1 | G14: 107761.4
B15: Purchases of stock-in-trade | C15: 21121.1 | D15: 23154.2 | E15: 19517.7 | F15: 20504.3 | G15: 27729.3
B16: Changes in inventories of finished goods, stock-in-trade and wip | C16: -1018.6 | D16: -7302.1 | E16: 8166.8 | F16: -4096.8 | G16: -9461.7
B17: Employee benefits expense | C17: 32191.8 | D17: 35350.2 | E17: 34509.2 | F17: 35222.5 | G17: 39229.4
B18: Finance costs | C18: 3051.3 | D18: 744.9 | E18: 486.4 | F18: 1404.8 | G18: 2897.1
B19: Depreciation, amortisation and impairment expense | C19: 9667.1 | D19: 10553.9 | E19: 11265.2 | F19: 12445.8 | G19: 15216.6
B20: Other expenses | C20: 52797.9 | D20: 60037.3 | E20: 54775.2 | F20: 63212.3 | G20: 66330.3
B21: Total Expenses | C21: =-SUM(C14:C20) -> -195060.4 | D21: =-SUM(D14:D20) -> -205711 | E21: =-SUM(E14:E20) -> -202438.8 | F21: =-SUM(F14:F20) -> -225218 | G21: =-SUM(G14:G20) -> -249702.4
B23: PROFIT BEFORE SHARE OF LOSS OF JOINT VENTURES AND ASSOCIATES, EXCEPTIONAL ITEMS AND TAX | C23: =SUM(C12,C21) -> 37843.4 | D23: =SUM(D12,D21) -> 45843.7 | E23: =SUM(E12,E21) -> 35319.6 | F23: =SUM(F12,F21) -> 26241.7 | G23: =SUM(G12,G21) -> 45890.1
B24: Share of loss of joint ventures and associates (net of tax) | C24: -151.7 | D24: -553.6 | E24: -312.5 | F24: -116.7 | G24: -171.6
B25: PROFIT BEFORE EXCEPTIONAL ITEMS AND TAX | C25: =SUM(C23:C24) -> 37691.7 | D25: =SUM(D23:D24) -> 45290.1 | E25: =SUM(E23:E24) -> 35007.1 | F25: =SUM(F23:F24) -> 26125 | G25: =SUM(G23:G24) -> 45718.5
B26: Exceptional items | C26: 261.3 | D26: -28145.8 | E26: 1279.7 | G26: 1918.6
B27: PROFIT BEFORE TAX | C27: =C25-C26 -> 37430.4 | D27: =D25-D26 -> 73435.9 | E27: =E25-E26 -> 33727.4 | F27: =F25-F26 -> 26125 | G27: =G25-G26 -> 43799.9
B28: TAX | C28: -8993.5 | D28: -20097.7 | E28: -7256.3 | F28: -6848.5 | G28: -12110.2
B29: PROFIT FOR THE YEAR | C29: =SUM(C27:C28) -> 28436.9 | D29: =SUM(D27:D28) -> 53338.2 | E29: =SUM(E27:E28) -> 26471.1 | F29: =SUM(F27:F28) -> 19276.5 | G29: =SUM(G27:G28) -> 31689.7

Sheet Balance_sheet
B6: Balance Sheet
B8: Particulars | C8: 2020 | D8: =C8+1 -> 2021 | E8: =D8+1 -> 2022 | F8: =E8+1 -> 2023 | G8: =F8+1 -> 2024 | H8: =G8+1 -> 2025 | I8: =H8+1 -> 2026 | J8: =I8+1 -> 2027 | K8: =J8+1 -> 2028 | ... Q8: =P8+1 -> 2034
B9: ASSETS
B10: Non-current assets
B11: Property, plant and equipment | C11: 64948.1 | D11: 64731.7 | E11: 72204.3 | F11: 75433.7 | G11: 112608.3 | H11: =FAS!H27 -> 118858.13 | I11: =FAS!I27 -> 125349.44 | J11: =FAS!J27 -> 132102.43 | K11: =FAS!K27 -> 139137.4 | L11: =FAS!L27 -> 146474.84 | M11: =FAS!M27 -> 154135.52 | N11: =FAS!N27 -> 162140.6 | O11: =FAS!O27 -> 170511.74 | ... Q11: =FAS!Q27 -> 188441.71
B12: Capital work-in-progress | C12: 16218 | D12: 24288.9 | E12: 29375.6 | F12: 44964 | G12: 27393.9 | H12: =FAS!H97 -> 30187.875 | I12: =FAS!I97 -> 33261.247 | J12: =FAS!J97 -> 36641.957 | K12: =FAS!K97 -> 40360.738 | L12: =FAS!L97 -> 44451.397 | M12: =FAS!M97 -> 48951.121 | N12: =FAS!N97 -> 53900.819 | O12: =FAS!O97 -> 59345.485 | ... Q12: =FAS!Q97 -> 71922.666
B13: Right-of-use assets | D13: 4134.5 | E13: 5080.1 | F13: 4520.1 | G13: 2846.8 | H13: =FAS!H69 -> 2776.3869 | I13: =FAS!I69 -> 2753.1831 | J13: =FAS!J69 -> 2772.5736 | K13: =FAS!K69 -> 2830.9875 | L13: =FAS!L69 -> 2925.7512 | M13: =FAS!M69 -> 3054.9677 | N13: =FAS!N69 -> 3217.4186 | O13: =FAS!O69 -> 3412.4845 | ... Q13: =FAS!Q69 -> 3900.613
B14: Goodwill | C14: 9159.4 | D14: 4289 | E14: 4754.2 | F14: 5960.7 | G14: 5951.5 | H14: =G14 -> 5951.5 | I14: =H14 -> 5951.5 | J14: =I14 -> 5951.5 | K14: =J14 -> 5951.5 | L14: =K14 -> 5951.5 | M14: =L14 -> 5951.5 | N14: =M14 -> 5951.5 | O14: =N14 -> 5951.5 | ... Q14: =P14 -> 5951.5
B15: Other intangible assets | C15: 19857.2 | D15: 20580.6 | E15: 23282.3 | F15: 24322.4 | G15: 23521.3 | H15: =FAS!H48 -> 23752.566 | I15: =FAS!I48 -> 24674.701 | J15: =FAS!J48 -> 26220.862 | K15: =FAS!K48 -> 28352.374 | L15: =FAS!L48 -> 31053.681 | M15: =FAS!M48 -> 34328.7 | N15: =FAS!N48 -> 38198.264 | O15: =FAS!O48 -> 42698.433 | ... Q15: =FAS!Q48 -> 53805.558
B16: Intangible assets under development | C16: 3641.2 | D16: 6326.4 | E16: 8096.4 | F16: 8936.1 | G16: 11293.3
B17: Investments accounted for using the equity method | C17: 4096.1 | D17: 947 | E17: 793.5 | F17: 900 | G17: 947.8
B18: Financial assets
B19: Investments | C19: 1450.8 | D19: 3365.2 | E19: 5389.5 | F19: 3017.4 | G19: 2268.7 | H19: ='BalanceSheet Forecast'!H11 -> 3918.8579 | I19: ='BalanceSheet Forecast'!I11 -> 4233.0472 | J19: ='BalanceSheet Forecast'!J11 -> 4592.5312 | K19: ='BalanceSheet Forecast'!K11 -> 5005.8769 | L19: ='BalanceSheet Forecast'!L11 -> 5483.456 | M19: ='BalanceSheet Forecast'!M11 -> 6037.8409 | N19: ='BalanceSheet Forecast'!N11 -> 6684.2903 | O19: ='BalanceSheet Forecast'!O11 -> 7441.3428 | ... Q19: ='BalanceSheet Forecast'!Q11 -> 9382.3361
B20: Loans | C20: 58.4 | D20: 72.6 | E20: 63.2 | F20: 55.7 | G20: 58.3 | H20: ='BalanceSheet Forecast'!H13 -> 77.400816 | I20: ='BalanceSheet Forecast'!I13 -> 83.606325 | J20: ='BalanceSheet Forecast'!J13 -> 90.706442 | K20: ='BalanceSheet Forecast'!K13 -> 98.870376 | L20: ='BalanceSheet Forecast'!L13 -> 108.30297 | M20: ='BalanceSheet Forecast'!M13 -> 119.25255 | N20: ='BalanceSheet Forecast'!N13 -> 132.02049 | O20: ='BalanceSheet Forecast'!O13 -> 146.97292 | ... Q20: ='BalanceSheet Forecast'!Q13 -> 185.30921
B21: Other financial assets | C21: 1170.3 | D21: 1433 | E21: 1289.2 | F21: 1503.7 | G21: 3510 | H21: ='BalanceSheet Forecast'!H15 -> 2152.7041 | I21: ='BalanceSheet Forecast'!I15 -> 2325.2943 | J21: ='BalanceSheet Forecast'!J15 -> 2522.7657 | K21: ='BalanceSheet Forecast'!K15 -> 2749.8245 | L21: ='BalanceSheet Forecast'!L15 -> 3012.1679 | M21: ='BalanceSheet Forecast'!M15 -> 3316.7022 | N21: ='BalanceSheet Forecast'!N15 -> 3671.8093 | O21: ='BalanceSheet Forecast'!O15 -> 4087.6728 | ... Q21: ='BalanceSheet Forecast'!Q15 -> 5153.8977
B22: Deferred tax assets (net | C22: 1632 | D22: 4526.8 | E22: 2885.9 | F22: 6774.9 | G22: 12126.4 | H22: ='BalanceSheet Forecast'!H17 -> 6658.5462 | I22: ='BalanceSheet Forecast'!I17 -> 7192.3864 | J22: ='BalanceSheet Forecast'!J17 -> 7803.187 | K22: ='BalanceSheet Forecast'!K17 -> 8505.5042 | L22: ='BalanceSheet Forecast'!L17 -> 9316.9606 | M22: ='BalanceSheet Forecast'!M17 -> 10258.918 | N22: ='BalanceSheet Forecast'!N17 -> 11357.303 | O22: ='BalanceSheet Forecast'!O17 -> 12643.614 | ... Q22: ='BalanceSheet Forecast'!Q17 -> 15941.562
B23: Non-current tax assets (net) | C23: 845.3 | D23: 1282.6 | E23: 3189.7 | F23: 2885.2 | G23: 3832.9 | H23: ='BalanceSheet Forecast'!H19 -> 2948.9045 | I23: ='BalanceSheet Forecast'!I19 -> 3185.329 | J23: ='BalanceSheet Forecast'!J19 -> 3455.8374 | K23: ='BalanceSheet Forecast'!K19 -> 3766.8762 | L23: ='BalanceSheet Forecast'!L19 -> 4126.2501 | M23: ='BalanceSheet Forecast'!M19 -> 4543.4196 | N23: ='BalanceSheet Forecast'!N19 -> 5029.8669 | O23: ='BalanceSheet Forecast'!O19 -> 5599.5419 | ... Q23: ='BalanceSheet Forecast'!Q19 -> 7060.1214
B24: Other non-current asset | C24: 2075.5 | D24: 4326.5 | E24: 1586.4 | F24: 4169.3 | G24: 2299.6 | H24: ='BalanceSheet Forecast'!H21 -> 3613.8265 | I24: ='BalanceSheet Forecast'!I21 -> 3903.5603 | J24: ='BalanceSheet Forecast'!J21 -> 4235.0632 | K24: ='BalanceSheet Forecast'!K21 -> 4616.2354 | L24: ='BalanceSheet Forecast'!L21 -> 5056.6412 | M24: ='BalanceSheet Forecast'!M21 -> 5567.8746 | N24: ='BalanceSheet Forecast'!N21 -> 6164.0065 | O24: ='BalanceSheet Forecast'!O21 -> 6862.1324 | ... Q24: ='BalanceSheet Forecast'!Q21 -> 8652.0449
B26: Total non-current assets | C26: =SUM(C11:C24) -> 125152.3 | D26: =SUM(D11:D24) -> 140304.8 | E26: =SUM(E11:E24) -> 157990.3 | F26: =SUM(F11:F24) -> 183443.2 | G26: =SUM(G11:G24) -> 208658.8 | H26: =SUM(H11:H24) -> 200896.7 | I26: =SUM(I11:I24) -> 212913.29 | J26: =SUM(J11:J24) -> 226389.41 | ... Q26: =SUM(Q11:Q24) -> 370397.32
B28: Current assets
B29: Inventories | C29: 76998.7 | D29: 90265.7 | E29: 75538.5 | F29: 85112.3 | G29: 98082.3 | H29: ='Working Capital'!H11 -> 106392.4 | I29: ='Working Capital'!I11 -> 114922.27 | J29: ='Working Capital'!J11 -> 124681.84 | K29: ='Working Capital'!K11 -> 135903.69 | L29: ='Working Capital'!L11 -> 148869.4 | M29: ='Working Capital'!M11 -> 163920.3 | N29: ='Working Capital'!N11 -> 181470.64 | O29: ='Working Capital'!O11 -> 202023.73 | ... Q29: ='Working Capital'!Q11 -> 254719.42
B30: Financial assets
B31: Investments | C31: 0.2 | D31: 1597.9 | E31: 3788.5 | F31: 1510 | G31: 505.8 | H31: ='BalanceSheet Forecast'!H26 -> 1898.2517 | I31: ='BalanceSheet Forecast'!I26 -> 2050.4416 | J31: ='BalanceSheet Forecast'!J26 -> 2224.5716 | K31: ='BalanceSheet Forecast'!K26 -> 2424.7918 | L31: ='BalanceSheet Forecast'!L26 -> 2656.1258 | M31: ='BalanceSheet Forecast'!M26 -> 2924.6638 | N31: ='BalanceSheet Forecast'!N26 -> 3237.7968 | O31: ='BalanceSheet Forecast'!O26 -> 3604.5047 | ... Q31: ='BalanceSheet Forecast'!Q26 -> 4544.7005
B32: Trade receivables | C32: 43151.6 | D32: 35032.8 | E32: 40122.6 | F32: 44663.8 | G32: 48167.4 | H32: ='Working Capital'!H12 -> 52730.003 | I32: ='Working Capital'!I12 -> 56957.561 | J32: ='Working Capital'!J12 -> 61794.58 | K32: ='Working Capital'!K12 -> 67356.334 | L32: ='Working Capital'!L12 -> 73782.376 | M32: ='Working Capital'!M12 -> 81241.875 | N32: ='Working Capital'!N12 -> 89940.144 | O32: ='Working Capital'!O12 -> 100126.63 | ... Q32: ='Working Capital'!Q12 -> 126243.57
B33: Cash and cash equivalents | C33: 27637.1 | D33: 53734.7 | E33: 41625.1 | F33: 43962.9 | G33: 33934.8 | H33: =H79-SUM(H35:H39,H29:H32,H26) -> 96054.64 | I33: =I79-SUM(I35:I39,I29:I32,I26) -> 113759.93 | J33: =J79-SUM(J35:J39,J29:J32,J26) -> 132845.46 | K33: =K79-SUM(K35:K39,K29:K32,K26) -> 153642.81 | L33: =L79-SUM(L35:L39,L29:L32,L26) -> 176548.41 | M33: =M79-SUM(M35:M39,M29:M32,M26) -> 202041.42 | N33: =N79-SUM(N35:N39,N29:N32,N26) -> 230705.12 | O33: =O79-SUM(O35:O39,O29:O32,O26) -> 263252.68 | ... Q33: =Q79-SUM(Q35:Q39,Q29:Q32,Q26) -> 343696.36
B34: Bank balances | C34: 784.4 | D34: 1008.1 | E34: 275 | F34: 16879.1 | G34: 28848.2
B35: Loans | C35: 136.8 | D35: 143.2 | E35: 127.1 | F35: 124.3 | G35: 128.6 | H35: ='BalanceSheet Forecast'!H28 -> 165.7072 | I35: ='BalanceSheet Forecast'!I28 -> 178.99256 | J35: ='BalanceSheet Forecast'!J28 -> 194.19318 | K35: ='BalanceSheet Forecast'!K28 -> 211.67132 | L35: ='BalanceSheet Forecast'!L28 -> 231.86554 | M35: ='BalanceSheet Forecast'!M28 -> 255.30747 | N35: ='BalanceSheet Forecast'!N28 -> 282.6423 | O35: ='BalanceSheet Forecast'!O28 -> 314.65394 | ... Q35: ='BalanceSheet Forecast'!Q28 -> 396.72799
B36: Other financial assets | C36: 400.8 | D36: 338.7 | E36: 709.1 | F36: 2903.5 | G36: 2631.1 | H36: ='BalanceSheet Forecast'!H30 -> 1677.2113 | I36: ='BalanceSheet Forecast'!I30 -> 1811.6795 | J36: ='BalanceSheet Forecast'!J30 -> 1965.5331 | K36: ='BalanceSheet Forecast'!K30 -> 2142.4388 | L36: ='BalanceSheet Forecast'!L30 -> 2346.8353 | M36: ='BalanceSheet Forecast'!M30 -> 2584.1036 | N36: ='BalanceSheet Forecast'!N30 -> 2860.774 | O36: ='BalanceSheet Forecast'!O30 -> 3184.7809 | ... Q36: ='BalanceSheet Forecast'!Q30 -> 4015.4963
B37: Current tax assets (net | C37: 157.6 | D37: 789.8 | E37: 2699.9 | F37: 756.2 | G37: 56.7 | H37: ='BalanceSheet Forecast'!H32 -> 1161.7817 | I37: ='BalanceSheet Forecast'!I32 -> 1254.926 | J37: ='BalanceSheet Forecast'!J32 -> 1361.4984 | K37: ='BalanceSheet Forecast'!K32 -> 1484.0386 | L37: ='BalanceSheet Forecast'!L32 -> 1625.6213 | M37: ='BalanceSheet Forecast'!M32 -> 1789.9738 | N37: ='BalanceSheet Forecast'!N32 -> 1981.6197 | O37: ='BalanceSheet Forecast'!O32 -> 2206.055 | ... Q37: ='BalanceSheet Forecast'!Q32 -> 2781.4804
B38: Other current assets | C38: 14857.9 | D38: 14488.1 | E38: 15550.1 | F38: 18687 | G38: 25364.3 | H38: ='BalanceSheet Forecast'!H34 -> 21947.907 | I38: ='BalanceSheet Forecast'!I34 -> 23707.552 | J38: ='BalanceSheet Forecast'!J34 -> 25720.874 | K38: ='BalanceSheet Forecast'!K34 -> 28035.853 | L38: ='BalanceSheet Forecast'!L34 -> 30710.576 | M38: ='BalanceSheet Forecast'!M34 -> 33815.457 | N38: ='BalanceSheet Forecast'!N34 -> 37435.954 | O38: ='BalanceSheet Forecast'!O34 -> 41675.893 | ... Q38: ='BalanceSheet Forecast'!Q34 -> 52546.596
B39: Assets held for sale | D39: 836.1 | E39: 791 | F39: 857.6 | G39: 4337.1 | H39: ='BalanceSheet Forecast'!H36 -> 1569.441 | I39: ='BalanceSheet Forecast'!I36 -> 1695.2688 | J39: ='BalanceSheet Forecast'!J36 -> 1839.2365 | K39: ='BalanceSheet Forecast'!K36 -> 2004.775 | L39: ='BalanceSheet Forecast'!L36 -> 2196.0379 | M39: ='BalanceSheet Forecast'!M36 -> 2418.0603 | N39: ='BalanceSheet Forecast'!N36 -> 2676.9532 | O39: ='BalanceSheet Forecast'!O36 -> 2980.1408 | ... Q39: ='BalanceSheet Forecast'!Q36 -> 3757.4781
B41: Total current assets | C41: =SUM(C29:C39) -> 164125.1 | D41: =SUM(D29:D39) -> 198235.1 | E41: =SUM(E29:E39) -> 181226.9 | F41: =SUM(F29:F39) -> 215456.7 | G41: =SUM(G29:G39) -> 242056.3 | H41: =SUM(H29:H39) -> 283597.34 | I41: =SUM(I29:I39) -> 316338.62 | J41: =SUM(J29:J39) -> 352627.79 | ... Q41: =SUM(Q29:Q39) -> 792701.83
B43: TOTAL ASSETS | C43: =SUM(C41,C26) -> 289277.4 | D43: =SUM(D41,D26) -> 338539.9 | E43: =SUM(E41,E26) -> 339217.2 | F43: =SUM(F41,F26) -> 398899.9 | G43: =SUM(G41,G26) -> 450715.1 | H43: =SUM(H41,H26) -> 484494.04 | I43: =SUM(I41,I26) -> 529251.91 | J43: =SUM(J41,J26) -> 579017.2 | ... Q43: =SUM(Q41,Q26) -> 1163099.1
B45: EQUITY AND LIABILITIES
B46: Equity
B47: Equity share capital | C47: 585.9 | D47: 585.9 | E47: 585.9 | F47: 585.9 | G47: 585.9 | H47: =G47 -> 585.9 | I47: =H47 -> 585.9 | J47: =I47 -> 585.9 | K47: =J47 -> 585.9 | L47: =K47 -> 585.9 | M47: =L47 -> 585.9 | N47: =M47 -> 585.9 | O47: =N47 -> 585.9 | ... Q47: =P47 -> 585.9
B48: Other equity | C48: 167660.8 | D48: 218712.8 | E48: 245173.9 | F48: 267812.6 | G48: 297842.1 | H48: =G48+'Income Statement'!H33+'Income Statement'!H39 -> 330881.01 | I48: =H48+'Income Statement'!I33+'Income Statement'!I39 -> 363376.55 | J48: =I48+'Income Statement'!J33+'Income Statement'!J39 -> 399111.71 | K48: =J48+'Income Statement'!K33+'Income Statement'!K39 -> 438544.85 | L48: =K48+'Income Statement'!L33+'Income Statement'!L39 -> 482251.26 | M48: =L48+'Income Statement'!M33+'Income Statement'!M39 -> 530943.23 | N48: =M48+'Income Statement'!N33+'Income Statement'!N39 -> 585495.85 | O48: =N48+'Income Statement'!O33+'Income Statement'!O39 -> 646979.66 | ... Q48: =P48+'Income Statement'!Q33+'Income Statement'!Q39 -> 796254.78
B49: Equity attributable to owners of the Parent Company | C49: =SUM(C47:C48) -> 168246.7 | D49: =SUM(D47:D48) -> 219298.7 | E49: =SUM(E47:E48) -> 245759.8 | F49: =SUM(F47:F48) -> 268398.5 | G49: =SUM(G47:G48) -> 298428 | H49: =SUM(H47:H48) -> 331466.91 | I49: =SUM(I47:I48) -> 363962.45 | J49: =SUM(J47:J48) -> 399697.61 | ... Q49: =SUM(Q47:Q48) -> 796840.68
B50: Non-controlling interest | C50: 1.4 | D50: -8.8 | E50: -19.3 | F50: 120 | G50: 80 | H50: 80 | I50: 80 | J50: 80 | K50: 80 | L50: 80 | M50: 80 | N50: 80 | O50: 80 | P50: 80 | Q50: 80
B51: Total equity | C51: =SUM(C49:C50) -> 168248.1 | D51: =SUM(D49:D50) -> 219289.9 | E51: =SUM(E49:E50) -> 245740.5 | F51: =SUM(F49:F50) -> 268518.5 | G51: =SUM(G49:G50) -> 298508 | H51: =SUM(H49:H50) -> 331546.91 | I51: =SUM(I49:I50) -> 364042.45 | J51: =SUM(J49:J50) -> 399777.61 | ... Q51: =SUM(Q49:Q50) -> 796920.68
B53: Liabilities
B54: Non-current liabilities
B55: Financial liabilities
B56: Borrowings | D56: 1684.9 | E56: 2492.1 | F56: 6189.6 | G56: 21349 | H56: ='BalanceSheet Forecast'!H40 -> 7234.472 | I56: ='BalanceSheet Forecast'!I40 -> 7814.4862 | J56: ='BalanceSheet Forecast'!J40 -> 8478.1175 | K56: ='BalanceSheet Forecast'!K40 -> 9241.1812 | L56: ='BalanceSheet Forecast'!L40 -> 10122.824 | M56: ='BalanceSheet Forecast'!M40 -> 11146.255 | N56: ='BalanceSheet Forecast'!N40 -> 12339.644 | O56: ='BalanceSheet Forecast'!O40 -> 13737.213 | ... Q56: ='BalanceSheet Forecast'!Q40 -> 17320.415
B57: Lease liabilities | D57: 2661.9 | E57: 3186.1 | F57: 3215.3 | G57: 2525.3 | H57: ='BalanceSheet Forecast'!H42 -> 2868.53 | I57: ='BalanceSheet Forecast'!I42 -> 3098.5106 | J57: ='BalanceSheet Forecast'!J42 -> 3361.6461 | K57: ='BalanceSheet Forecast'!K42 -> 3664.2074 | L57: ='BalanceSheet Forecast'!L42 -> 4013.7862 | M57: ='BalanceSheet Forecast'!M42 -> 4419.5855 | N57: ='BalanceSheet Forecast'!N42 -> 4892.7743 | O57: ='BalanceSheet Forecast'!O42 -> 5446.9224 | ... Q57: ='BalanceSheet Forecast'!Q42 -> 6867.6928
B58: Others | C58: 2644.1 | D58: 541 | E58: 113.5 | F58: 125 | G58: 154.2 | H58: ='BalanceSheet Forecast'!H44 -> 945.28306 | I58: ='BalanceSheet Forecast'!I44 -> 1021.0699 | J58: ='BalanceSheet Forecast'!J44 -> 1107.7824 | K58: ='BalanceSheet Forecast'!K44 -> 1207.4872 | L58: ='BalanceSheet Forecast'!L44 -> 1322.6859 | M58: ='BalanceSheet Forecast'!M44 -> 1456.4112 | N58: ='BalanceSheet Forecast'!N44 -> 1612.3438 | O58: ='BalanceSheet Forecast'!O44 -> 1794.9554 | ... Q58: ='BalanceSheet Forecast'!Q44 -> 2263.15
B59: Provisions | C59: 747.1 | D59: 1571.1 | E59: 1717.9 | F59: 1727.2 | G59: 2257 | H59: ='BalanceSheet Forecast'!H46 -> 1973.7327 | I59: ='BalanceSheet Forecast'!I46 -> 2131.9741 | J59: ='BalanceSheet Forecast'!J46 -> 2313.0282 | K59: ='BalanceSheet Forecast'!K46 -> 2521.2098 | L59: ='BalanceSheet Forecast'!L46 -> 2761.7425 | M59: ='BalanceSheet Forecast'!M46 -> 3040.9585 | N59: ='BalanceSheet Forecast'!N46 -> 3366.5427 | O59: ='BalanceSheet Forecast'!O46 -> 3747.8322 | ... Q59: ='BalanceSheet Forecast'!Q46 -> 4725.4134
B60: Deferred tax liabilities (net) | C60: 2916.9 | D60: 5745.6 | E60: 4109.6 | F60: 3896.1 | G60: 3565.6 | H60: ='BalanceSheet Forecast'!H48 -> 5073.5773 | I60: ='BalanceSheet Forecast'!I48 -> 5480.3447 | J60: ='BalanceSheet Forecast'!J48 -> 5945.7532 | K60: ='BalanceSheet Forecast'!K48 -> 6480.8942 | L60: ='BalanceSheet Forecast'!L48 -> 7099.1953 | M60: ='BalanceSheet Forecast'!M48 -> 7816.9337 | N60: ='BalanceSheet Forecast'!N48 -> 8653.8641 | O60: ='BalanceSheet Forecast'!O48 -> 9633.9875 | ... Q60: ='BalanceSheet Forecast'!Q48 -> 12146.908
B61: Other non-current liabilities | C61: 874.8 | D61: 395 | E61: 297.7 | F61: 290.4 | G61: 364.7 | H61: ='BalanceSheet Forecast'!H50 -> 566.36886 | I61: ='BalanceSheet Forecast'!I50 -> 611.77674 | J61: ='BalanceSheet Forecast'!J50 -> 663.73079 | K61: ='BalanceSheet Forecast'!K50 -> 723.46915 | L61: ='BalanceSheet Forecast'!L50 -> 792.49077 | M61: ='BalanceSheet Forecast'!M50 -> 872.61267 | N61: ='BalanceSheet Forecast'!N50 -> 966.0401 | O61: ='BalanceSheet Forecast'!O50 -> 1075.4523 | ... Q61: ='BalanceSheet Forecast'!Q50 -> 1355.9724
B63: Total non-current liabilities | C63: =SUM(C56:C62) -> 7182.9 | D63: =SUM(D56:D62) -> 12599.5 | E63: =SUM(E56:E62) -> 11916.9 | F63: =SUM(F56:F62) -> 15443.6 | G63: =SUM(G56:G62) -> 30215.8 | H63: =SUM(H56:H62) -> 18661.964 | I63: =SUM(I56:I62) -> 20158.162 | J63: =SUM(J56:J62) -> 21870.058 | ... Q63: =SUM(Q56:Q62) -> 44679.552
B65: Current liabilities
B66: Financial liabilities
B67: Borrowings | C67: 54223 | D67: 48037.8 | E67: 21235.6 | F67: 42425.6 | G67: 41803.2 | H67: ='BalanceSheet Forecast'!H54 -> 52040.675 | I67: ='BalanceSheet Forecast'!I54 -> 56212.968 | J67: ='BalanceSheet Forecast'!J54 -> 60986.754 | K67: ='BalanceSheet Forecast'!K54 -> 66475.8 | L67: ='BalanceSheet Forecast'!L54 -> 72817.836 | M67: ='BalanceSheet Forecast'!M54 -> 80179.819 | N67: ='BalanceSheet Forecast'!N54 -> 88764.378 | O67: ='BalanceSheet Forecast'!O54 -> 98817.695 | ... Q67: ='BalanceSheet Forecast'!Q54 -> 124593.21
B68: Lease liabilities | D68: 1006.2 | E68: 1598.9 | F68: 1031.6 | G68: 798.8 | H68: ='BalanceSheet Forecast'!H56 -> 1109.6165 | I68: ='BalanceSheet Forecast'!I56 -> 1198.5785 | J68: ='BalanceSheet Forecast'!J56 -> 1300.3657 | K68: ='BalanceSheet Forecast'!K56 -> 1417.4036 | L68: ='BalanceSheet Forecast'!L56 -> 1552.6292 | M68: ='BalanceSheet Forecast'!M56 -> 1709.6021 | N68: ='BalanceSheet Forecast'!N56 -> 1892.6429 | O68: ='BalanceSheet Forecast'!O56 -> 2107.0007 | ... Q68: ='BalanceSheet Forecast'!Q56 -> 2656.589
B69: Trade payables
B70: total outstanding dues of micro enterprises and small enterprises and | C70: 427.8 | D70: 176.9 | E70: 384.7 | F70: 622.7 | G70: 791.5
B71: total outstanding dues of creditors other than micro enterprises and small enterprises | C71: 25332.8 | D71: 27769.9 | E71: 26645.8 | F71: 38090.4 | G71: 43750.1 | H71: ='Working Capital'!H13 -> 40361.708 | I71: ='Working Capital'!I13 -> 43597.655 | J71: ='Working Capital'!J13 -> 47300.108 | K71: ='Working Capital'!K13 -> 51557.302 | L71: ='Working Capital'!L13 -> 56476.058 | M71: ='Working Capital'!M13 -> 62185.865 | N71: ='Working Capital'!N13 -> 68843.877 | O71: ='Working Capital'!O13 -> 76641.029 | ... Q71: ='Working Capital'!Q13 -> 96632.007
B72: Other financial liabilities | C72: 22386.9 | D72: 20275 | E72: 17746.5 | F72: 17213.7 | G72: 21015.9 | H72: ='BalanceSheet Forecast'!H58 -> 24718.161 | I72: ='BalanceSheet Forecast'!I58 -> 26699.907 | J72: ='BalanceSheet Forecast'!J58 -> 28967.349 | K72: ='BalanceSheet Forecast'!K58 -> 31574.523 | L72: ='BalanceSheet Forecast'!L58 -> 34586.849 | M72: ='BalanceSheet Forecast'!M58 -> 38083.627 | N72: ='BalanceSheet Forecast'!N58 -> 42161.1 | O72: ='BalanceSheet Forecast'!O58 -> 46936.202 | ... Q72: ='BalanceSheet Forecast'!Q58 -> 59178.999
B73: Other current liabilities | C73: 6358.7 | D73: 5561.9 | E73: 11662.4 | F73: 11432.5 | G73: 8773.8 | H73: ='BalanceSheet Forecast'!H60 -> 10978.852 | I73: ='BalanceSheet Forecast'!I60 -> 11859.067 | J73: ='BalanceSheet Forecast'!J60 -> 12866.177 | K73: ='BalanceSheet Forecast'!K60 -> 14024.183 | L73: ='BalanceSheet Forecast'!L60 -> 15362.142 | M73: ='BalanceSheet Forecast'!M60 -> 16915.275 | N73: ='BalanceSheet Forecast'!N60 -> 18726.332 | O73: ='BalanceSheet Forecast'!O60 -> 20847.247 | ... Q73: ='BalanceSheet Forecast'!Q60 -> 26285.025
B74: Provisions | C74: 4166.4 | D74: 1719.3 | E74: 1705.6 | F74: 2005.3 | G74: 2567.9 | H74: ='BalanceSheet Forecast'!H62 -> 3068.1787 | I74: ='BalanceSheet Forecast'!I62 -> 3314.1658 | J74: ='BalanceSheet Forecast'!J62 -> 3595.6155 | K74: ='BalanceSheet Forecast'!K62 -> 3919.2349 | L74: ='BalanceSheet Forecast'!L62 -> 4293.1443 | M74: ='BalanceSheet Forecast'!M62 -> 4727.1871 | N74: ='BalanceSheet Forecast'!N62 -> 5233.3096 | O74: ='BalanceSheet Forecast'!O62 -> 5826.0263 | ... Q74: ='BalanceSheet Forecast'!Q62 -> 7345.6818
B75: Current tax liabilities (net) | C75: 950.8 | D75: 2103.5 | E75: 580.3 | F75: 2116 | G75: 2490.1 | H75: ='BalanceSheet Forecast'!H64 -> 2007.9769 | I75: ='BalanceSheet Forecast'!I64 -> 2168.9638 | J75: ='BalanceSheet Forecast'!J64 -> 2353.1591 | K75: ='BalanceSheet Forecast'!K64 -> 2564.9526 | L75: ='BalanceSheet Forecast'!L64 -> 2809.6586 | M75: ='BalanceSheet Forecast'!M64 -> 3093.7189 | N75: ='BalanceSheet Forecast'!N64 -> 3424.952 | O75: ='BalanceSheet Forecast'!O64 -> 3812.8568 | ... Q75: ='BalanceSheet Forecast'!Q64 -> 4807.399
B77: Total current liabilities | C77: =SUM(C67:C75) -> 113846.4 | D77: =SUM(D67:D75) -> 106650.5 | E77: =SUM(E67:E75) -> 81559.8 | F77: =SUM(F67:F75) -> 114937.8 | G77: =SUM(G67:G75) -> 121991.3 | H77: =SUM(H67:H75) -> 134285.17 | I77: =SUM(I67:I75) -> 145051.3 | J77: =SUM(J67:J75) -> 157369.53 | ... Q77: =SUM(Q67:Q75) -> 321498.92
B79: TOTAL EQUITY AND LIABILITIES | C79: =SUM(C77,C63,C51) -> 289277.4 | D79: =SUM(D77,D63,D51) -> 338539.9 | E79: =SUM(E77,E63,E51) -> 339217.2 | F79: =SUM(F77,F63,F51) -> 398899.9 | G79: =SUM(G77,G63,G51) -> 450715.1 | H79: =SUM(H77,H63,H51) -> 484494.04 | I79: =SUM(I77,I63,I51) -> 529251.91 | J79: =SUM(J77,J63,J51) -> 579017.2 | ... Q79: =SUM(Q77,Q63,Q51) -> 1163099.1
B81: CHECK | C81: =C79=C43 -> TRUE | D81: =D79=D43 -> TRUE | E81: =E79=E43 -> TRUE | F81: =F79=F43 -> TRUE | G81: =G79=G43 -> TRUE | H81: =H79=H43 -> TRUE | I81: =I79=I43 -> TRUE | J81: =J79=J43 -> TRUE | ... Q81: =Q79=Q43 -> TRUE

Sheet FAS
B6: Fixed Assets Schedules
B8: Particulars | C8: 2020 | D8: =C8+1 -> 2021 | E8: =D8+1 -> 2022 | F8: =E8+1 -> 2023 | G8: =F8+1 -> 2024 | H8: =G8+1 -> 2025 | I8: =H8+1 -> 2026 | J8: =I8+1 -> 2027 | K8: =J8+1 -> 2028 | ... Q8: =P8+1 -> 2034
B9: PPE
B10: Opening Gross | C10: 74283.3 | D10: =C18 -> 89775.2 | E10: 94579.4 | F10: =E18 -> 108972 | G10: =F18 -> 129175.1 | H10: =G18 -> 174703.9 | I10: =H18 -> 193864.76 | J10: =I18 -> 213983.66 | K10: =J18 -> 235108.51 | L10: =K18 -> 257289.6 | M10: =L18 -> 280579.75 | ... Q10: =P18 -> 385982.36
B11: Additions | C11: 15361.3 | D11: 9627.5 | E11: 16164.9 | F11: 8771.6 | G11: 45879 | H11: =AVERAGE(C11:G11) -> 19160.86 | I11: =H11*(1+5%) -> 20118.903 | J11: =I11*(1+5%) -> 21124.848 | K11: =J11*(1+5%) -> 22181.091 | L11: =K11*(1+5%) -> 23290.145 | M11: =L11*(1+5%) -> 24454.652 | N11: =M11*(1+5%) -> 25677.385 | O11: =N11*(1+5%) -> 26961.254 | P11: =O11*(1+5%) -> 28309.317 | Q11: =P11*(1+5%) -> 29724.783
B12: Disposals / adjustments | C12: -499.5 | D12: -2233.2 | E12: -2166.1 | F12: -540.1 | G12: -748.4
B13: Reclassified to Assets held for sale | D13: -995.3 | G13: -14.8
B14: Acquisition through business combination | D14: 5423.2 | F14: 10600.6
B15: Disposal of Subsidiary | D15: -970.7
B16: - Reclasified to Right-of-use assets | C16: -913
B17: Foreign currency translation adjustments | C17: 1543.1 | D17: -303.4 | E17: 393.8 | F17: 1371 | G17: 413
B18: Gross Closing | C18: =SUM(C10:C17) -> 89775.2 | D18: =SUM(D10:D17) -> 100323.3 | E18: =SUM(E10:E17) -> 108972 | F18: =SUM(F10:F17) -> 129175.1 | G18: =SUM(G10:G17) -> 174703.9 | H18: =SUM(H10:H17) -> 193864.76 | I18: =SUM(I10:I17) -> 213983.66 | J18: =SUM(J10:J17) -> 235108.51 | ... Q18: =SUM(Q10:Q17) -> 415707.14
B19: Accumulated depreciation | C19: -17346.8 | D19: -24827.1 | E19: -29847.7 | F19: -36767.8 | G19: -53741.4 | H19: =SUM(G19:G26) -> -62095.6 | I19: =SUM(H19:H26) -> -75006.629 | J19: =SUM(I19:I26) -> -88634.228 | K19: =SUM(J19:J26) -> -103006.08 | L19: =SUM(K19:K26) -> -118152.2 | M19: =SUM(L19:L26) -> -134104.9 | N19: =SUM(M19:M26) -> -150898.88 | O19: =SUM(N19:N26) -> -168571.18 | ... Q19: =SUM(P19:P26) -> -206711.21
B20: Charge for the year | C20: -7307 | D20: -8016.4 | E20: -7196.3 | F20: -7601.9 | G20: -8648.8 | H20: =G20/F27*G27 -> -12911.029 | I20: =H20/G27*H27 -> -13627.599 | J20: =I20/H27*I27 -> -14371.855 | K20: =J20/I27*J27 -> -15146.115 | L20: =K20/J27*K27 -> -15952.705 | M20: =L20/K27*L27 -> -16793.974 | N20: =M20/L27*M27 -> -17672.304 | O20: =N20/M27*N27 -> -18590.121 | ... Q20: =P20/O27*P27 -> -20554.212
B21: Disposals / adjustments | C21: 119.4 | D21: -1299.4 | E21: 405.4 | F21: 272.9 | G21: 519.3
B22: Reclassified to Assets held for sale | D22: -159.2 | G22: 6.8
B23: Acquisition through business combination | D23: -576.8 | F23: -9127.5
B24: Disposal of Subsidiary | D24: -410.4
B25: Reclasified to Right-of-use assets | C25: 115 | D25: -208.1
B26: Foreign currency translation adjustments | C26: -407.7 | D26: -94.2 | E26: -129.1 | F26: -517.1 | G26: -231.5
B27: Net PPE | C27: =SUM(C18:C26) -> 64948.1 | D27: =SUM(D18:D26) -> 64731.7 | E27: =SUM(E18:E26) -> 72204.3 | F27: =SUM(F18:F26) -> 75433.7 | G27: =SUM(G18:G26) -> 112608.3 | H27: =SUM(H18:H26) -> 118858.13 | I27: =SUM(I18:I26) -> 125349.44 | J27: =SUM(J18:J26) -> 132102.43 | ... Q27: =SUM(Q18:Q26) -> 188441.71
B30: Other intangible assets
B31: Opening Gross | C31: 22367.8 | D31: =C39 -> 25478 | E31: =D39 -> 27264 | F31: =E39 -> 34526.7 | G31: =F39 -> 39924.3 | H31: =G39 -> 44817.7 | I31: =H39 -> 50597.685 | J31: =I39 -> 57123.095 | K31: =J39 -> 64490.064 | ... Q31: =P39 -> 133530.14
B32: Additions | C32: 385.5 | D32: 3505.3 | E32: 2658.3 | F32: 2371.6 | G32: 5148.9 | H32: =G32/F39*G39 -> 5779.985 | I32: =H32/G39*H39 -> 6525.4098 | J32: =I32/H39*I39 -> 7366.9696 | K32: =J32/I39*J39 -> 8317.0624 | L32: =K32/J39*K39 -> 9389.6854 | M32: =L32/K39*L39 -> 10600.641 | N32: =M32/L39*M39 -> 11967.769 | O32: =N32/M39*N39 -> 13511.211 | ... Q32: =P32/O39*P39 -> 17220.924
B33: Disposals / adjustments | C33: -116.7 | D33: -198.5 | E33: -366.2 | F33: -287.8 | G33: -653
B34: Reclassified to Assets held for sale
B35: Acquisition through business combination | C35: 1244.8 | D35: 978.7 | E35: 4495.6 | F35: 888.3
B36: Disposal of Subsidiary | D36: -2433.1
B37: - Reclasified to Right-of-use assets | C37: -260
B38: Foreign currency translation adjustments | C38: 1856.6 | D38: -66.4 | E38: 475 | F38: 2425.5 | G38: 397.5
B39: Gross Closing | C39: =SUM(C31:C38) -> 25478 | D39: =SUM(D31:D38) -> 27264 | E39: =SUM(E31:E38) -> 34526.7 | F39: =SUM(F31:F38) -> 39924.3 | G39: =SUM(G31:G38) -> 44817.7 | H39: =SUM(H31:H38) -> 50597.685 | I39: =SUM(I31:I38) -> 57123.095 | J39: =SUM(J31:J38) -> 64490.064 | ... Q39: =SUM(Q31:Q38) -> 150751.06
B40: Accumulated depreciation | C40: -2880.9 | D40: -5620.8 | E40: -6683.4 | F40: -11244.4 | G40: -15601.9 | H40: =SUM(G40:G47) -> -21296.4 | I40: =SUM(H40:H47) -> -26845.119 | J40: =SUM(I40:I47) -> -32448.394 | K40: =SUM(J40:J47) -> -38269.203 | L40: =SUM(K40:K47) -> -44454.753 | M40: =SUM(L40:L47) -> -51143.132 | N40: =SUM(M40:M47) -> -58468.753 | O40: =SUM(N40:N47) -> -66566.958 | ... Q40: =SUM(P40:P47) -> -85650.641
B41: Charge for the year | C41: -2358.6 | D41: -2558.9 | E41: -3286.6 | F41: -4042.6 | G41: -5737.7 | H41: =G41/F48*G48 -> -5548.719 | I41: =H41/G48*H48 -> -5603.2751 | J41: =I41/H48*I48 -> -5820.8084 | K41: =J41/I48*J48 -> -6185.5507 | L41: =K41/J48*K48 -> -6688.3784 | M41: =L41/K48*L48 -> -7325.6218 | N41: =M41/L48*M48 -> -8098.2049 | O41: =N41/M48*N48 -> -9011.0424 | ... Q41: =P41/O48*P48 -> -11294.864
B42: Disposals / adjustments | C42: -26.9 | D42: -75.7 | E42: -1175.7 | F42: 576.9 | G42: 252.2
B43: Reclassified to Assets held for sale
B44: Acquisition through business combination | D44: 60.3
B45: Disposal of Subsidiary | D45: 1485.4
B46: Reclasified to Right-of-use assets | C46: 3
B47: Foreign currency translation adjustments | C47: -357.4 | D47: 4.5 | E47: -98.7 | F47: -891.8 | G47: -209
B48: Net other intangible assets | C48: =SUM(C39:C47) -> 19857.2 | D48: 20580.6 | E48: =SUM(E39:E47) -> 23282.3 | F48: =SUM(F39:F47) -> 24322.4 | G48: =SUM(G39:G47) -> 23521.3 | H48: =SUM(H39:H47) -> 23752.566 | I48: =SUM(I39:I47) -> 24674.701 | J48: =SUM(J39:J47) -> 26220.862 | K48: =SUM(K39:K47) -> 28352.374 | L48: =SUM(L39:L47) -> 31053.681 | ... Q48: =SUM(Q39:Q47) -> 53805.558
B51: Right-of-use assets
B52: Opening Gross | D52: 5298.3 | E52: =D60 -> 5743.9 | F52: =E60 -> 6992.6 | G52: =F60 -> 6372.2 | H52: =G60 -> 4478.1 | I52: =H60 -> 4877.3355 | J52: =I60 -> 5312.164 | K52: =J60 -> 5785.7588 | L52: =K60 -> 6301.5759 | ... Q52: =P60 -> 9658.1378
B53: Additions | D53: 1644 | E53: 2051.8 | F53: 1135 | G53: 568.1 | H53: =G53/F60*G60 -> 399.23552 | I53: =H53/G60*H60 -> 434.82852 | J53: =I53/H60*I60 -> 473.59474 | K53: =J53/I60*J60 -> 515.81708 | L53: =K53/J60*K60 -> 561.80365 | M53: =L53/K60*L60 -> 611.89007 | N53: =M53/L60*M60 -> 666.44183 | O53: =N53/M60*N60 -> 725.85704 | ... Q53: =P53/O60*P60 -> 861.05082
B54: Disposals / adjustments | D54: -1157.1 | E54: -905.9 | F54: -2141.6 | G54: -2534.4
B55: Reclassified to Assets held for sale
B56: Acquisition through business combination | F56: 0.6
B57: Disposal of Subsidiary
B58: - Reclasified to Right-of-use assets
B59: Foreign currency translation adjustments | D59: -41.3 | E59: 102.8 | F59: 385.6 | G59: 72.2
B60: Gross Closing | D60: =SUM(D52:D59) -> 5743.9 | E60: =SUM(E52:E59) -> 6992.6 | F60: =SUM(F52:F59) -> 6372.2 | G60: =SUM(G52:G59) -> 4478.1 | H60: =SUM(H52:H59) -> 4877.3355 | I60: =SUM(I52:I59) -> 5312.164 | J60: =SUM(J52:J59) -> 5785.7588 | K60: =SUM(K52:K59) -> 6301.5759 | ... Q60: =SUM(Q52:Q59) -> 10519.189
B61: Accumulated depreciation | D61: -1609.4 | E61: -1609.4 | F61: -1912.5 | G61: -1852.1 | H61: =SUM(G61:G68) -> -1631.3 | I61: =SUM(H61:H68) -> -2100.9486 | J61: =SUM(I61:I68) -> -2558.9809 | K61: =SUM(J61:J68) -> -3013.1852 | L61: =SUM(K61:K68) -> -3470.5884 | M61: =SUM(L61:L68) -> -3937.6283 | N61: =SUM(M61:M68) -> -4420.3019 | O61: =SUM(N61:N68) -> -4924.2928 | ... Q61: =SUM(P61:P68) -> -6018.0559
B62: Charge for the year | E62: -892.6 | F62: -895.2 | G62: -745.7 | H62: =G62/F69*G69 -> -469.64863 | I62: =H62/G69*H69 -> -458.03228 | J62: =I62/H69*I69 -> -454.20426 | K62: =J62/I69*J69 -> -457.40319 | L62: =K62/J69*K69 -> -467.03997 | M62: =L62/K69*L69 -> -482.67354 | N62: =M62/L69*M69 -> -503.99094 | O62: =N62/M69*N69 -> -530.79115 | ... Q62: =P62/O69*P69 -> -600.51968
B63: Disposals / adjustments | E63: 611.7 | G63: 990.9
B64: Reclassified to Assets held for sale
B65: Acquisition through business combination | F65: 1103.9
B66: Disposal of Subsidiary
B67: Reclasified to Right-of-use assets
B68: Foreign currency translation adjustments | E68: -22.2 | F68: -148.3 | G68: -24.4
B69: net right to used assets | D69: =SUM(D60:D68) -> 4134.5 | E69: =SUM(E60:E68) -> 5080.1 | F69: =SUM(F60:F68) -> 4520.1 | G69: =SUM(G60:G68) -> 2846.8 | H69: =SUM(H60:H68) -> 2776.3869 | I69: =SUM(I60:I68) -> 2753.1831 | J69: =SUM(J60:J68) -> 2772.5736 | K69: =SUM(K60:K68) -> 2830.9875 | ... Q69: =SUM(Q60:Q68) -> 3900.613
B72: Total fixed Assets
B73: Opening Gross | C73: =C10+C31+C52 -> 96651.1 | D73: =D10+D31+D52 -> 120551.5 | E73: =E10+E31+E52 -> 127587.3 | F73: =F10+F31+F52 -> 150491.3 | G73: =G10+G31+G52 -> 175471.6 | H73: =H10+H31+H52 -> 223999.7 | I73: =I10+I31+I52 -> 249339.78 | J73: =J10+J31+J52 -> 276418.92 | ... Q73: =Q10+Q31+Q52 -> 529170.63
B74: Additions | C74: =C11+C32+C53 -> 15746.8 | D74: =D11+D32+D53 -> 14776.8 | E74: =E11+E32+E53 -> 20875 | F74: =F11+F32+F53 -> 12278.2 | G74: =G11+G32+G53 -> 51596 | H74: =H11+H32+H53 -> 25340.081 | I74: =I11+I32+I53 -> 27079.141 | J74: =J11+J32+J53 -> 28965.412 | ... Q74: =Q11+Q32+Q53 -> 47806.758
B75: Disposals / adjustments | C75: =C12+C33+C54 -> -616.2 | D75: =D12+D33+D54 -> -3588.8 | E75: =E12+E33+E54 -> -3438.2 | F75: =F12+F33+F54 -> -2969.5 | G75: =G12+G33+G54 -> -3935.8 | H75: =H12+H33+H54 -> 0 | I75: =I12+I33+I54 -> 0 | J75: =J12+J33+J54 -> 0 | ... Q75: =Q12+Q33+Q54 -> 0
B76: Reclassified to Assets held for sale | C76: =C13+C34+C55 -> 0 | D76: =D13+D34+D55 -> -995.3 | E76: =E13+E34+E55 -> 0 | F76: =F13+F34+F55 -> 0 | G76: =G13+G34+G55 -> -14.8 | H76: =H13+H34+H55 -> 0 | I76: =I13+I34+I55 -> 0 | J76: =J13+J34+J55 -> 0 | ... Q76: =Q13+Q34+Q55 -> 0
B77: Acquisition through business combination | C77: =C14+C35+C56 -> 1244.8 | D77: =D14+D35+D56 -> 6401.9 | E77: =E14+E35+E56 -> 4495.6 | F77: =F14+F35+F56 -> 11489.5 | G77: =G14+G35+G56 -> 0 | H77: =H14+H35+H56 -> 0 | I77: =I14+I35+I56 -> 0 | J77: =J14+J35+J56 -> 0 | ... Q77: =Q14+Q35+Q56 -> 0
B78: Disposal of Subsidiary | C78: =C15+C36+C57 -> 0 | D78: =D15+D36+D57 -> -3403.8 | E78: =E15+E36+E57 -> 0 | F78: =F15+F36+F57 -> 0 | G78: =G15+G36+G57 -> 0 | H78: =H15+H36+H57 -> 0 | I78: =I15+I36+I57 -> 0 | J78: =J15+J36+J57 -> 0 | ... Q78: =Q15+Q36+Q57 -> 0
B79: - Reclasified to Right-of-use assets | C79: =C16+C37+C58 -> -1173 | D79: =D16+D37+D58 -> 0 | E79: =E16+E37+E58 -> 0 | F79: =F16+F37+F58 -> 0 | G79: =G16+G37+G58 -> 0 | H79: =H16+H37+H58 -> 0 | I79: =I16+I37+I58 -> 0 | J79: =J16+J37+J58 -> 0 | ... Q79: =Q16+Q37+Q58 -> 0
B80: Foreign currency translation adjustments | C80: =C17+C38+C59 -> 3399.7 | D80: =D17+D38+D59 -> -411.1 | E80: =E17+E38+E59 -> 971.6 | F80: =F17+F38+F59 -> 4182.1 | G80: =G17+G38+G59 -> 882.7 | H80: =H17+H38+H59 -> 0 | I80: =I17+I38+I59 -> 0 | J80: =J17+J38+J59 -> 0 | ... Q80: =Q17+Q38+Q59 -> 0
B81: Gross Closing | C81: =C18+C39+C60 -> 115253.2 | D81: =D18+D39+D60 -> 133331.2 | E81: =E18+E39+E60 -> 150491.3 | F81: =F18+F39+F60 -> 175471.6 | G81: =G18+G39+G60 -> 223999.7 | H81: =H18+H39+H60 -> 249339.78 | I81: =I18+I39+I60 -> 276418.92 | J81: =J18+J39+J60 -> 305384.33 | ... Q81: =Q18+Q39+Q60 -> 576977.39
B82: Accumulated depreciation | C82: =C19+C40+C61 -> -20227.7 | D82: =D19+D40+D61 -> -32057.3 | E82: =E19+E40+E61 -> -38140.5 | F82: =F19+F40+F61 -> -49924.7 | G82: =G19+G40+G61 -> -71195.4 | H82: =H19+H40+H61 -> -85023.3 | I82: =I19+I40+I61 -> -103952.7 | J82: =J19+J40+J61 -> -123641.6 | ... Q82: =Q19+Q40+Q61 -> -298379.91
B83: Charge for the year | C83: =C20+C41+C62 -> -9665.6 | D83: =D20+D41+D62 -> -10575.3 | E83: =E20+E41+E62 -> -11375.5 | F83: =F20+F41+F62 -> -12539.7 | G83: =G20+G41+G62 -> -15132.2 | H83: =H20+H41+H62 -> -18929.396 | I83: =I20+I41+I62 -> -19688.906 | J83: =J20+J41+J62 -> -20646.868 | ... Q83: =Q20+Q41+Q62 -> -32449.596
B84: Disposals / adjustments | C84: =C21+C42+C63 -> 92.5 | D84: =D21+D42+D63 -> -1375.1 | E84: =E21+E42+E63 -> -158.6 | F84: =F21+F42+F63 -> 849.8 | G84: =G21+G42+G63 -> 1762.4 | H84: =H21+H42+H63 -> 0 | I84: =I21+I42+I63 -> 0 | J84: =J21+J42+J63 -> 0 | ... Q84: =Q21+Q42+Q63 -> 0
... B90: net block | C90: =C27+C48+C69 -> 84805.3 | D90: =D27+D48+D69 -> 89446.8 | E90: =E27+E48+E69 -> 100566.7 | F90: =F27+F48+F69 -> 104276.2 | G90: =G27+G48+G69 -> 138976.4 | H90: =H27+H48+H69 -> 145387.08 | I90: =I27+I48+I69 -> 152777.32 | J90: =J27+J48+J69 -> 161095.86 | ... Q90: =Q27+Q48+Q69 -> 246147.89
B93: Total Fixed Assets - Net Block | C93: =C90 -> 84805.3 | D93: =D90 -> 89446.8 | E93: =E90 -> 100566.7 | F93: =F90 -> 104276.2 | G93: =G90 -> 138976.4 | H93: =H90 -> 145387.08 | I93: =I90 -> 152777.32 | J93: =J90 -> 161095.86 | ... Q93: =Q90 -> 246147.89
B94: Dep & Amortization | C94: =-'P&L'!C19 -> -9667.1 | D94: =-'P&L'!D19 -> -10553.9 | E94: =-'P&L'!E19 -> -11265.2 | F94: =-'P&L'!F19 -> -12445.8 | G94: =-'P&L'!G19 -> -15216.6 | H94: =H83 -> -18929.396 | I94: =I83 -> -19688.906 | J94: =J83 -> -20646.868 | K94: =K83 -> -21789.069 | L94: =L83 -> -23108.124 | M94: =M83 -> -24602.27 | N94: =N83 -> -26274.5 | O94: =O83 -> -28131.955 | ... Q94: =Q83 -> -32449.596
B95: Increase in Fixed Assets | D95: =D93-D94-C93 -> 15195.4 | E95: =E93-E94-D93 -> 22385.1 | F95: =F93-F94-E93 -> 16155.3 | G95: =G93-G94-F93 -> 49916.8 | H95: =H93-H94-G93 -> 25340.081 | I95: =I93-I94-H93 -> 27079.141 | J95: =J93-J94-I93 -> 28965.412 | K95: =K93-K94-J93 -> 31013.97 | ... Q95: =Q93-Q94-P93 -> 47806.758
B97: Capital work-in-progress | C97: =Balance_sheet!C12 -> 16218 | D97: =Balance_sheet!D12 -> 24288.9 | E97: =Balance_sheet!E12 -> 29375.6 | F97: =Balance_sheet!F12 -> 44964 | G97: =Balance_sheet!G12 -> 27393.9 | H97: =G97+H98 -> 30187.875 | I97: =H97+I98 -> 33261.247 | J97: =I97+J98 -> 36641.957 | K97: =J97+K98 -> 40360.738 | L97: =K97+L98 -> 44451.397 | M97: =L97+M98 -> 48951.121 | N97: =M97+N98 -> 53900.819 | O97: =N97+O98 -> 59345.485 | ... Q97: =P97+Q98 -> 71922.666
B98: Change in CWIP | D98: =D97-C97 -> 8070.9 | E98: =E97-D97 -> 5086.7 | F98: =F97-E97 -> 15588.4 | G98: =G97-F97 -> -17570.1 | H98: =AVERAGE(D98:G98) -> 2793.975 | I98: =H98*1.1 -> 3073.3725 | J98: =I98*1.1 -> 3380.7098 | K98: =J98*1.1 -> 3718.7807 | L98: =K98*1.1 -> 4090.6588 | M98: =L98*1.1 -> 4499.7247 | N98: =M98*1.1 -> 4949.6971 | O98: =N98*1.1 -> 5444.6669 | P98: =O98*1.1 -> 5989.1335 | Q98: =P98*1.1 -> 6588.0469
B100: CAPEX | D100: =D95+D98 -> 23266.3 | E100: =E95+E98 -> 27471.8 | F100: =F95+F98 -> 31743.7 | G100: =G95+G98 -> 32346.7 | H100: =H95+H98 -> 28134.056 | I100: =I95+I98 -> 30152.514 | J100: =J95+J98 -> 32346.122 | K100: =K95+K98 -> 34732.751 | ... Q100: =Q95+Q98 -> 54394.804

Sheet Income Statement
B6: Income Statement
B8: Particulars | C8: 2020 | D8: =C8+1 -> 2021 | E8: =D8+1 -> 2022 | F8: =E8+1 -> 2023 | G8: =F8+1 -> 2024 | H8: =G8+1 -> 2025 | I8: =H8+1 -> 2026 | J8: =I8+1 -> 2027 | K8: =J8+1 -> 2028 | ... Q8: =P8+1 -> 2034
B10: Revenue | C10: ='Revenue Build_up'!C10 -> 230985.1 | D10: ='Revenue Build_up'!D10 -> 247746.2 | E10: ='Revenue Build_up'!E10 -> 234554.9 | F10: ='Revenue Build_up'!F10 -> 248553.8 | G10: ='Revenue Build_up'!G10 -> 290018.7 | H10: ='Revenue Build_up'!H10 -> 311990.27 | I10: ='Revenue Build_up'!I10 -> 337003.68 | J10: ='Revenue Build_up'!J10 -> 365623.11 | ... Q10: ='Revenue Build_up'!Q10 -> 746951.69
B11: COGS | C11: =-'Cost Build_Up'!C12 -> -97352.3 | D11: =-'Cost Build_Up'!D12 -> -99024.7 | E11: =-'Cost Build_Up'!E12 -> -101402.8 | F11: =-'Cost Build_Up'!F12 -> -112932.6 | G11: =-'Cost Build_Up'!G12 -> -126029 | H11: =-'Cost Build_Up'!H12 -> -133681.69 | I11: =-'Cost Build_Up'!I12 -> -144399.44 | J11: =-'Cost Build_Up'!J12 -> -156662.3 | ... Q11: =-'Cost Build_Up'!Q12 -> -320054.09
B12: Gross Profit | C12: =SUM(C10:C11) -> 133632.8 | D12: =SUM(D10:D11) -> 148721.5 | E12: =SUM(E10:E11) -> 133152.1 | F12: =SUM(F10:F11) -> 135621.2 | G12: =SUM(G10:G11) -> 163989.7 | H12: =SUM(H10:H11) -> 178308.58 | I12: =SUM(I10:I11) -> 192604.24 | J12: =SUM(J10:J11) -> 208960.81 | ... Q12: =SUM(Q10:Q11) -> 426897.6
B13: Gross Margin | C13: =C12/C10 -> 0.57853429 | D13: =D12/D10 -> 0.6002978 | E13: =E12/E10 -> 0.56767989 | F13: =F12/F10 -> 0.54564123 | G13: =G12/G10 -> 0.56544526 | H13: =H12/H10 -> 0.57151969 | I13: =I12/I10 -> 0.57151969 | J13: =J12/J10 -> 0.57151969 | ... Q13: =Q12/Q10 -> 0.57151969
B15: Employee Expenses | C15: =-'Cost Build_Up'!C18 -> -32191.8 | D15: =-'Cost Build_Up'!D18 -> -35350.2 | E15: =-'Cost Build_Up'!E18 -> -34509.2 | F15: =-'Cost Build_Up'!F18 -> -35222.5 | G15: =-'Cost Build_Up'!G18 -> -39229.4 | H15: =-'Cost Build_Up'!H18 -> -44062.744 | I15: =-'Cost Build_Up'!I18 -> -47595.417 | J15: =-'Cost Build_Up'!J18 -> -51637.372 | ... Q15: =-'Cost Build_Up'!Q18 -> -105492.85
B16: S&G expenses | C16: =-'Cost Build_Up'!C21 -> -52797.9 | D16: =-'Cost Build_Up'!D21 -> -60037.3 | E16: =-'Cost Build_Up'!E21 -> -54775.2 | F16: =-'Cost Build_Up'!F21 -> -63212.3 | G16: =-'Cost Build_Up'!G21 -> -66330.3 | H16: =-'Cost Build_Up'!H21 -> -74095.821 | I16: =-'Cost Build_Up'!I21 -> -80036.356 | J16: =-'Cost Build_Up'!J21 -> -86833.3 | ... Q16: =-'Cost Build_Up'!Q21 -> -177396.55
B18: EBITDA | C18: =C12+SUM(C15:C16) -> 48643.1 | D18: =D12+SUM(D15:D16) -> 53334 | E18: =E12+SUM(E15:E16) -> 43867.7 | F18: =F12+SUM(F15:F16) -> 37186.4 | G18: =G12+SUM(G15:G16) -> 58430 | H18: =H12+SUM(H15:H16) -> 60150.019 | I18: =I12+SUM(I15:I16) -> 64972.467 | J18: =J12+SUM(J15:J16) -> 70490.138 | ... Q18: =Q12+SUM(Q15:Q16) -> 144008.2
B19: EBITDA Margin | C19: =C18/C10 -> 0.21058977 | D19: =D18/D10 -> 0.21527676 | E19: =E18/E10 -> 0.1870253 | F19: =F18/F10 -> 0.14961107 | G19: =G18/G10 -> 0.20146977 | H19: =H18/H10 -> 0.19279453 | I19: =I18/I10 -> 0.19279453 | J19: =J18/J10 -> 0.19279453 | ... Q19: =Q18/Q10 -> 0.19279453
B21: D&A | C21: =FAS!C94 -> -9667.1 | D21: =FAS!D94 -> -10553.9 | E21: =FAS!E94 -> -11265.2 | F21: =FAS!F94 -> -12445.8 | G21: =FAS!G94 -> -15216.6 | H21: =FAS!H94 -> -18929.396 | I21: =FAS!I94 -> -19688.906 | J21: =FAS!J94 -> -20646.868 | ... Q21: =FAS!Q94 -> -32449.596
B23: EBIT | C23: =SUM(C18,C21) -> 38976 | D23: =SUM(D18,D21) -> 42780.1 | E23: =SUM(E18,E21) -> 32602.5 | F23: =SUM(F18,F21) -> 24740.6 | G23: =SUM(G18,G21) -> 43213.4 | H23: =SUM(H18,H21) -> 41220.622 | I23: =SUM(I18,I21) -> 45283.561 | J23: =SUM(J18,J21) -> 49843.271 | ... Q23: =SUM(Q18,Q21) -> 111558.61
B24: EBIT Margin | C24: =C23/C10 -> 0.16873816 | D24: =D23/D10 -> 0.17267712 | E24: =E23/E10 -> 0.13899731 | F24: =F23/F10 -> 0.099538209 | G24: =G23/G10 -> 0.14900212 | H24: =H23/H10 -> 0.1321215 | I24: =I23/I10 -> 0.13437112 | J24: =J23/J10 -> 0.13632418 | ... Q24: =Q23/Q10 -> 0.14935184
B26: Interest Cost | C26: =-'P&L'!C18 -> -3051.3 | D26: =-'P&L'!D18 -> -744.9 | E26: =-'P&L'!E18 -> -486.4 | F26: =-'P&L'!F18 -> -1404.8 | G26: =-'P&L'!G18 -> -2897.1 | H26: =-'Debt Schedules'!H14 -> -2054.544 | I26: =-'Debt Schedules'!I14 -> -1335.3664 | J26: =-'Debt Schedules'!J14 -> -1445.7211 | K26: =-'Debt Schedules'!K14 -> -1572.3186 | L26: =-'Debt Schedules'!L14 -> -1718.2613 | M26: =-'Debt Schedules'!M14 -> -1887.3076 | N26: =-'Debt Schedules'!N14 -> -2084.0167 | O26: =-'Debt Schedules'!O14 -> -2313.9249 | ... Q26: =-'Debt Schedules'!Q14 -> -2901.7168
B27: Other Income | C27: ='P&L'!C11 -> 1918.7 | D27: ='P&L'!D11 -> 3808.5 | E27: ='P&L'!E11 -> 3203.5 | F27: ='P&L'!F11 -> 2905.9 | G27: ='P&L'!G11 -> 5573.8 | H27: ='Cost Build_Up'!H27 -> 4258.4774 | I27: ='Cost Build_Up'!I27 -> 4599.8952 | J27: ='Cost Build_Up'!J27 -> 4990.5331 | K27: ='Cost Build_Up'!K27 -> 5439.7006 | L27: ='Cost Build_Up'!L27 -> 5958.668 | M27: ='Cost Build_Up'!M27 -> 6561.0975 | N27: ='Cost Build_Up'!N27 -> 7263.5701 | O27: ='Cost Build_Up'!O27 -> 8086.231 | ... Q27: ='Cost Build_Up'!Q27 -> 10195.436
B28: Share of loss of joint ventures and associates (net of tax) | C28: ='Cost Build_Up'!C34 -> -151.7 | D28: ='Cost Build_Up'!D34 -> -553.6 | E28: ='Cost Build_Up'!E34 -> -312.5 | F28: ='Cost Build_Up'!F34 -> -116.7 | G28: ='Cost Build_Up'!G34 -> -171.6 | H28: ='Cost Build_Up'!H34 -> -329.76185
B29: Exceptional items | C29: ='Cost Build_Up'!C31 -> 261.3 | D29: ='Cost Build_Up'!D31 -> -28145.8 | E29: ='Cost Build_Up'!E31 -> 1279.7 | F29: ='Cost Build_Up'!F31 -> 0 | G29: ='Cost Build_Up'!G31 -> 1918.6 | H29: ='Cost Build_Up'!H31 -> -6265.0673
B30: EBT | C30: =SUM(C23,C26,C27,C28)-C29 -> 37430.4 | D30: =SUM(D23,D26,D27,D28)-D29 -> 73435.9 | E30: =SUM(E23,E26,E27,E28)-E29 -> 33727.4 | F30: =SUM(F23,F26,F27,F28)-F29 -> 26125 | G30: =SUM(G23,G26,G27,G28)-G29 -> 43799.9 | H30: =SUM(H23,H26,H27,H28)-H29 -> 49359.861 | I30: =SUM(I23,I26,I27,I28)-I29 -> 48548.09 | J30: =SUM(J23,J26,J27,J28)-J29 -> 53388.083 | ... Q30: =SUM(Q23,Q26,Q27,Q28)-Q29 -> 118852.33
B31: EBT Margin | C31: =C30/C10 -> 0.16204682 | D31: =D30/D10 -> 0.29641585 | E31: =E30/E10 -> 0.1437932 | F31: =F30/F10 -> 0.10510803 | G31: =G30/G10 -> 0.1510244 | H31: =H30/H10 -> 0.15820962 | I31: =I30/I10 -> 0.14405804 | J31: =J30/J10 -> 0.14601944 | ... Q31: =Q30/Q10 -> 0.15911648
B32: TAX | C32: ='P&L'!C28 -> -8993.5 | D32: ='P&L'!D28 -> -20097.7 | E32: ='P&L'!E28 -> -7256.3 | F32: ='P&L'!F28 -> -6848.5 | G32: ='P&L'!G28 -> -12110.2 | H32: ='Cost Build_Up'!H37 -> -12514.973 | I32: ='Cost Build_Up'!I37 -> -12309.152 | J32: ='Cost Build_Up'!J37 -> -13536.31 | K32: ='Cost Build_Up'!K37 -> -14937.087 | L32: ='Cost Build_Up'!L37 -> -16555.79 | M32: ='Cost Build_Up'!M37 -> -18444.302 | N32: ='Cost Build_Up'!N37 -> -20664.296 | O32: ='Cost Build_Up'!O37 -> -23289.809 | ... Q32: ='Cost Build_Up'!Q37 -> -30134.477
B33: Net Profit | C33: =SUM(C30:C32) -> 28437.062 | D33: =SUM(D30:D32) -> 53338.496 | E33: =SUM(E30:E32) -> 26471.244 | F33: =SUM(F30:F32) -> 19276.605 | G33: =SUM(G30:G32) -> 31689.851 | H33: =SUM(H30:H32) -> 36845.047 | I33: =SUM(I30:I32) -> 36239.082 | J33: =SUM(J30:J32) -> 39851.919 | ... Q33: =SUM(Q30:Q32) -> 88718.009
B34: Net Profit Margin | C34: =C33/C10 -> 0.12311211 | D34: =D33/D10 -> 0.21529491 | E34: =E33/E10 -> 0.11285735 | F34: =F33/F10 -> 0.077555061 | G34: =G33/G10 -> 0.1092683 | H34: =H33/H10 -> 0.11809678 | I34: =I33/I10 -> 0.1075332 | J34: =J33/J10 -> 0.10899726 | ... Q34: =Q33/Q10 -> 0.11877342
B37: EPS in Rs. | C37: =C33/580.8 -> 48.961884 | D37: =D33/580.8 -> 91.836254 | E37: =E33/580.8 -> 45.57721 | F37: =F33/580.8 -> 33.189747 | G37: =G33/580.8 -> 54.562416 | H37: =H33/580.8 -> 63.438442 | I37: =I33/580.8 -> 62.395114 | J37: =J33/580.8 -> 68.615562 | ... Q37: =Q33/580.8 -> 152.75139
B39: Dividend | C39: =CashFlow!C76 -> -1756.1 | D39: =CashFlow!D76 -> -2343.1 | E39: =CashFlow!E76 -> -2637 | F39: =CashFlow!F76 -> -4395.3 | G39: =CashFlow!G76 -> -2636.4 | H39: =-H40*H33 -> -3806.1397 | I39: =-I40*I33 -> -3743.5428 | J39: =-J40*J33 -> -4116.7533 | K39: =-K40*K33 -> -4542.7657 | L39: =-L40*L33 -> -5035.0547 | M39: =-M40*M33 -> -5609.3999 | N39: =-N40*N33 -> -6284.5569 | O39: =-O40*O33 -> -7083.0428 | ... Q39: =-Q40*Q33 -> -9164.682
B40: Dividend Payout % | C40: =-C39/C33 -> 0.061753918 | D40: =-D39/D33 -> 0.043928872 | E40: =-E39/E33 -> 0.099617533 | F40: =-F39/F33 -> 0.22801214 | G40: =-G39/G33 -> 0.083193828 | H40: =AVERAGE(C40:G40) -> 0.10330126 | I40: =H40 -> 0.10330126 | J40: =I40 -> 0.10330126 | K40: =J40 -> 0.10330126 | L40: =K40 -> 0.10330126 | M40: =L40 -> 0.10330126 | N40: =M40 -> 0.10330126 | O40: =N40 -> 0.10330126 | P40: =O40 -> 0.10330126 | Q40: =P40 -> 0.10330126
B42: Retained Earning | C42: =C33+C39 -> 26680.962 | D42: =D33+D39 -> 50995.396 | E42: =E33+E39 -> 23834.244 | F42: =F33+F39 -> 14881.305 | G42: =G33+G39 -> 29053.451 | H42: =H33+H39 -> 33038.907 | I42: =I33+I39 -> 32495.54 | J42: =J33+J39 -> 35735.165 | ... Q42: =Q33+Q39 -> 79553.327
B43: Retained % | C43: =C42/C33 -> 0.93824608 | D43: =D42/D33 -> 0.95607113 | E43: =E42/E33 -> 0.90038247 | F43: =F42/F33 -> 0.77198786 | G43: =G42/G33 -> 0.91680617 | H43: =H42/H33 -> 0.89669874 | I43: =I42/I33 -> 0.89669874 | J43: =J42/J33 -> 0.89669874 | ... Q43: =Q42/Q33 -> 0.89669874

Sheet CashFlow
B6: CashFlow Statement
B8: Particulars | C8: 2020 | D8: =C8+1 -> 2021 | E8: =D8+1 -> 2022 | F8: =E8+1 -> 2023 | G8: =F8+1 -> 2024 | H8: =G8+1 -> 2025 | I8: =H8+1 -> 2026 | J8: =I8+1 -> 2027 | K8: =J8+1 -> 2028 | ... Q8: =P8+1 -> 2034
B9: CASH FLOW FROM OPERATING ACTIVITIES
B10: Net profit before tax | C10: 37430.4 | D10: 73435.9 | E10: 33727.4 | F10: 26125 | G10: 43799.9 | H10: ='Income Statement'!H30 -> 49359.861 | I10: ='Income Statement'!I30 -> 48548.09 | J10: ='Income Statement'!J30 -> 53388.083 | K10: ='Income Statement'!K30 -> 58912.839 | L10: ='Income Statement'!L30 -> 65297.105 | M10: ='Income Statement'!M30 -> 72745.521 | N10: ='Income Statement'!N30 -> 81501.319 | O10: ='Income Statement'!O30 -> 91856.513 | ... Q10: ='Income Statement'!Q30 -> 118852.33
B11: Adjustment
B12: Depreciation, amortisation and impairment expense | C12: 9667.1 | D12: 10553.9 | E12: 11265.2 | F12: 12445.8 | G12: 15216.6 | H12: =-'Income Statement'!H21 -> 18929.396 | I12: =-'Income Statement'!I21 -> 19688.906 | J12: =-'Income Statement'!J21 -> 20646.868 | K12: =-'Income Statement'!K21 -> 21789.069 | L12: =-'Income Statement'!L21 -> 23108.124 | M12: =-'Income Statement'!M21 -> 24602.27 | N12: =-'Income Statement'!N21 -> 26274.5 | O12: =-'Income Statement'!O21 -> 28131.955 | ... Q12: =-'Income Statement'!Q21 -> 32449.596
B13: Allowance for credit losses on trade receivables and other advances(net) | C13: 615.9 | D13: -291.2 | E13: -61.1 | F13: 524.5 | G13: 232.8
B14: Liabilities no longer required written back (net) | C14: -263.2 | D14: -534 | E14: -137.8 | F14: -130.1 | G14: -100.5
B15: Stock written off | C15: 98.1 | D15: 486.8 | E15: 382.8 | F15: 56.8 | G15: 66.8
B16: Bad debts/advances written of | C16: 69.4
B17: Mark-to-market gain on derivative financial instruments (net) | C17: 22.3 | D17: -198.2 | E17: -320.2 | F17: -191.4 | G17: -27
B18: Unrealised foreign exchange gain (net) | C18: -745.6 | D18: -1089.5 | E18: -251.8
B19: Exchange differences on translation of assets and liabilities (net) | F19: 3104.6 | G19: -511.4
B20: Profit on sale of property, plant and equipment (net) | C20: 370.4 | D20: 1411.2 | E20: 1350.2 | F20: -132.3 | G20: -234.9
B21: Write off of intangible assets under development | D21: 4349.2 | E21: -396.3 | F21: 239.6 | G21: 326.2
B22: Share of loss of joint ventures and associates | C22: 151.7 | D22: 553.6 | E22: 312.5 | F22: 116.7 | G22: 171.5
B23: Gain on sale and lease back transactions | E23: 208.2
B24: Profit on sale of subsidiary and acquisition of non-controlling interest | D24: -32495
B25: Loss on liquidation of Joint venture/subsidiary | E25: 26.5
B26: Profit on sale of current investments | E26: -290.8 | G26: -1
B27: Finance costs | C27: 1416.3 | D27: 595.7 | E27: 368.4 | F27: 1289.5 | G27: 2680.9 | H27: =-'Income Statement'!H26 -> 2054.544 | I27: =-'Income Statement'!I26 -> 1335.3664 | J27: =-'Income Statement'!J26 -> 1445.7211 | K27: =-'Income Statement'!K26 -> 1572.3186 | L27: =-'Income Statement'!L26 -> 1718.2613 | M27: =-'Income Statement'!M26 -> 1887.3076 | N27: =-'Income Statement'!N26 -> 2084.0167 | O27: =-'Income Statement'!O26 -> 2313.9249 | ... Q27: =-'Income Statement'!Q26 -> 2901.7168
B28: Interest income | C28: -209.1 | D28: -223.7 | E28: -316 | F28: -1459 | G28: -2857.6 | H28: =-'Income Statement'!H27 -> -4258.4774 | I28: =-'Income Statement'!I27 -> -4599.8952 | J28: =-'Income Statement'!J27 -> -4990.5331 | K28: =-'Income Statement'!K27 -> -5439.7006 | L28: =-'Income Statement'!L27 -> -5958.668 | M28: =-'Income Statement'!M27 -> -6561.0975 | N28: =-'Income Statement'!N27 -> -7263.5701 | O28: =-'Income Statement'!O27 -> -8086.231 | ... Q28: =-'Income Statement'!Q27 -> -10195.436
B29: Effect of exchange rate changes | C29: -281.6 | D29: 254.8 | E29: 1301.5
B31: Operating profit before working capital changes | C31: =SUM(C10:C29) -> 48342.1 | D31: =SUM(D10:D29) -> 56809.5 | E31: =SUM(E10:E29) -> 47168.7 | F31: =SUM(F10:F29) -> 41989.7 | G31: =SUM(G10:G29) -> 58762.3 | H31: =SUM(H10:H29) -> 66085.324 | I31: =SUM(I10:I29) -> 64972.467 | J31: =SUM(J10:J29) -> 70490.138 | ... Q31: =SUM(Q10:Q29) -> 144008.2
B32: Movements in working capital :
B33: Increase in inventories | C33: -5269.8 | D33: -16217.4 | E33: 14975.2 | F33: -9267 | G33: -13036.8 | H33: =Balance_sheet!G29-Balance_sheet!H29 -> -8310.0969 | I33: =Balance_sheet!H29-Balance_sheet!I29 -> -8529.8706 | J33: =Balance_sheet!I29-Balance_sheet!J29 -> -9759.5683 | K33: =Balance_sheet!J29-Balance_sheet!K29 -> -11221.852 | L33: =Balance_sheet!K29-Balance_sheet!L29 -> -12965.711 | M33: =Balance_sheet!L29-Balance_sheet!M29 -> -15050.901 | N33: =Balance_sheet!M29-Balance_sheet!N29 -> -17550.344 | O33: =Balance_sheet!N29-Balance_sheet!O29 -> -20553.087 | ... Q33: =Balance_sheet!P29-Balance_sheet!Q29 -> -28527.778
B34: Increase in trade receivables | C34: -6561.2 | D34: 7440.4 | E34: -4108.4 | F34: -4321.1 | G34: -2641.9 | H34: =Balance_sheet!G32-Balance_sheet!H32 -> -4562.6025 | I34: =Balance_sheet!H32-Balance_sheet!I32 -> -4227.5587 | J34: =Balance_sheet!I32-Balance_sheet!J32 -> -4837.0192 | K34: =Balance_sheet!J32-Balance_sheet!K32 -> -5561.7534 | L34: =Balance_sheet!K32-Balance_sheet!L32 -> -6426.0418 | M34: =Balance_sheet!L32-Balance_sheet!M32 -> -7459.4995 | N34: =Balance_sheet!M32-Balance_sheet!N32 -> -8698.269 | O34: =Balance_sheet!N32-Balance_sheet!O32 -> -10186.483 | ... Q34: =Balance_sheet!P32-Balance_sheet!Q32 -> -14138.884
B35: Increase in other financial assets | C35: 12697.9 | D35: -84.2 | E35: 140.8 | F35: -2204 | G35: -1729.1 | H35: =SUM(Balance_sheet!G35:G39,Balance_sheet!G31)-SUM(Balance_sheet!H31,Balance_sheet!H35:H39) -> 4603.2997 | I35: =SUM(Balance_sheet!H35:H39,Balance_sheet!H31)-SUM(Balance_sheet!I31,Balance_sheet!I35:I39) -> -2278.5602 | J35: =SUM(Balance_sheet!I35:I39,Balance_sheet!I31)-SUM(Balance_sheet!J31,Balance_sheet!J35:J39) -> -2607.0459 | K35: =SUM(Balance_sheet!J35:J39,Balance_sheet!J31)-SUM(Balance_sheet!K31,Balance_sheet!K35:K39) -> -2997.6616 | L35: =SUM(Balance_sheet!K35:K39,Balance_sheet!K31)-SUM(Balance_sheet!L31,Balance_sheet!L35:L39) -> -3463.4938 | M35: =SUM(Balance_sheet!L35:L39,Balance_sheet!L31)-SUM(Balance_sheet!M31,Balance_sheet!M35:M39) -> -4020.5046 | N35: =SUM(Balance_sheet!M35:M39,Balance_sheet!M31)-SUM(Balance_sheet!N31,Balance_sheet!N35:N39) -> -4688.1738 | O35: =SUM(Balance_sheet!N35:N39,Balance_sheet!N31)-SUM(Balance_sheet!O31,Balance_sheet!O35:O39) -> -5490.2881 | ... Q35: =SUM(Balance_sheet!P35:P39,Balance_sheet!P31)-SUM(Balance_sheet!Q31,Balance_sheet!Q35:Q39) -> -7620.5446
B36: Increase in other current/non current assets | C36: -1277.8 | D36: 179.1 | E36: -34.9 | F36: -3549.6 | G36: -6689.7
B37: (Increase)/decrease in loans | C37: -28 | D37: -39 | E37: 25.5 | F37: 10.4 | G37: -6.9
B38: Increase in trade payables | C38: 2958.7 | D38: 1265.4 | E38: 1106.5 | F38: 7076.5 | G38: 5828.4 | H38: ='Working Capital'!H13-'Working Capital'!G13 -> -4179.8923 | I38: ='Working Capital'!I13-'Working Capital'!H13 -> 3235.9469 | J38: ='Working Capital'!J13-'Working Capital'!I13 -> 3702.453 | K38: ='Working Capital'!K13-'Working Capital'!J13 -> 4257.1943 | L38: ='Working Capital'!L13-'Working Capital'!K13 -> 4918.7561 | M38: ='Working Capital'!M13-'Working Capital'!L13 -> 5709.807 | N38: ='Working Capital'!N13-'Working Capital'!M13 -> 6658.012 | O38: ='Working Capital'!O13-'Working Capital'!N13 -> 7797.152 | ... Q38: ='Working Capital'!Q13-'Working Capital'!P13 -> 10822.482
B39: Increase in provisions | C39: 1010.4 | D39: -1736.1 | E39: 145.2 | F39: 217.5 | G39: 985.5
B40: Decrease in other current/non-current liabilities | C40: -779.2 | D40: -1466.8 | E40: 5573.1 | F40: -1240.5 | G40: -2634.3
B41: Increase in other financial liabilities | C41: 328.1 | D41: -7.9 | E41: -2245 | F41: 2328 | G41: 3174.1 | H41: =SUM(Balance_sheet!H67:H68,Balance_sheet!H72:H75)-SUM(Balance_sheet!G67:G68,Balance_sheet!G72:G75) -> 16473.76 | I41: =SUM(Balance_sheet!I67:I68,Balance_sheet!I72:I75)-SUM(Balance_sheet!H67:H68,Balance_sheet!H72:H75) -> 7530.19 | J41: =SUM(Balance_sheet!J67:J68,Balance_sheet!J72:J75)-SUM(Balance_sheet!I67:I68,Balance_sheet!I72:I75) -> 8615.77 | K41: =SUM(Balance_sheet!K67:K68,Balance_sheet!K72:K75)-SUM(Balance_sheet!J67:J68,Balance_sheet!J72:J75) -> 9906.6773 | L41: =SUM(Balance_sheet!L67:L68,Balance_sheet!L72:L75)-SUM(Balance_sheet!K67:K68,Balance_sheet!K72:K75) -> 11446.161 | M41: =SUM(Balance_sheet!M67:M68,Balance_sheet!M72:M75)-SUM(Balance_sheet!L67:L68,Balance_sheet!L72:L75) -> 13286.971 | N41: =SUM(Balance_sheet!N67:N68,Balance_sheet!N72:N75)-SUM(Balance_sheet!M67:M68,Balance_sheet!M72:M75) -> 15493.485 | O41: =SUM(Balance_sheet!O67:O68,Balance_sheet!O72:O75)-SUM(Balance_sheet!N67:N68,Balance_sheet!N72:N75) -> 18144.314 | ... Q41: =SUM(Balance_sheet!Q67:Q68,Balance_sheet!Q72:Q75)-SUM(Balance_sheet!P67:P68,Balance_sheet!P72:P75) -> 25184.39
B43: Cash generated from operating activities | C43: =SUM(C31:C41) -> 51421.2 | D43: =SUM(D31:D41) -> 46143 | E43: =SUM(E31:E41) -> 62746.7 | F43: =SUM(F31:F41) -> 31039.9 | G43: =SUM(G31:G41) -> 42011.6 | H43: =SUM(H31:H41) -> 70109.792 | I43: =SUM(I31:I41) -> 60702.615 | J43: =SUM(J31:J41) -> 65604.728 | ... Q43: =SUM(Q31:Q41) -> 129727.87
B44: Direct taxes paid (net of refunds) | C44: -7608.4 | D44: -12852.5 | E44: -12581.9 | F44: -7172.4 | G44: -17666.4 | H44: ='Income Statement'!H32 -> -12514.973 | I44: ='Income Statement'!I32 -> -12309.152 | J44: ='Income Statement'!J32 -> -13536.31 | K44: ='Income Statement'!K32 -> -14937.087 | L44: ='Income Statement'!L32 -> -16555.79 | M44: ='Income Statement'!M32 -> -18444.302 | N44: ='Income Statement'!N32 -> -20664.296 | O44: ='Income Statement'!O32 -> -23289.809 | ... Q44: ='Income Statement'!Q32 -> -30134.477
B46: Net cash generated from operating activities | C46: =SUM(C43:C44) -> 43812.8 | D46: =SUM(D43:D44) -> 33290.5 | E46: =SUM(E43:E44) -> 50164.8 | F46: =SUM(F43:F44) -> 23867.5 | G46: =SUM(G43:G44) -> 24345.2 | H46: =SUM(H43:H44) -> 57594.82 | I46: =SUM(I43:I44) -> 48393.463 | J46: =SUM(J43:J44) -> 52068.418 | ... Q46: =SUM(Q43:Q44) -> 99593.392
B48: CASH FLOW FROM INVESTING ACTIVITIES
B49: Purchase of property, plant and equipment, including movement in capital work- in- progress, capital advances and capital creditors | C49: -13827.5 | D49: -14379.4 | E49: -20529.1 | F49: -24038 | G49: -27803.3 | H49: =-(FAS!H100+Balance_sheet!H16-Balance_sheet!G16+Balance_sheet!H17-Balance_sheet!G17) -> -15892.956 | I49: =-(FAS!I100+Balance_sheet!I16-Balance_sheet!H16+Balance_sheet!I17-Balance_sheet!H17) -> -30152.514 | J49: =-(FAS!J100+Balance_sheet!J16-Balance_sheet!I16+Balance_sheet!J17-Balance_sheet!I17) -> -32346.122 | K49: =-(FAS!K100+Balance_sheet!K16-Balance_sheet!J16+Balance_sheet!K17-Balance_sheet!J17) -> -34732.751 | L49: =-(FAS!L100+Balance_sheet!L16-Balance_sheet!K16+Balance_sheet!L17-Balance_sheet!K17) -> -37332.293 | M49: =-(FAS!M100+Balance_sheet!M16-Balance_sheet!L16+Balance_sheet!M17-Balance_sheet!L17) -> -40166.908 | N49: =-(FAS!N100+Balance_sheet!N16-Balance_sheet!M16+Balance_sheet!N17-Balance_sheet!M17) -> -43261.293 | O49: =-(FAS!O100+Balance_sheet!O16-Balance_sheet!N16+Balance_sheet!O17-Balance_sheet!N17) -> -46642.989 | ... Q49: =-(FAS!Q100+Balance_sheet!Q16-Balance_sheet!P16+Balance_sheet!Q17-Balance_sheet!P17) -> -54394.804
B50: Purchase of intangible assets and intangible assets under development | C50: -483.4 | D50: -4358.7 | E50: -6517.3 | F50: -3166 | G50: -7811.7
B51: Proceeds from sale of property, plant and equipment and intangible assets | C51: 190 | D51: 481.7 | E51: 3809.4 | F51: 110.9 | G51: 602.8
B52: Acquisition of business | C52: 103.5 | E52: -5813.9 | F52: -1689.2
B53: Purchase of controlling interest in subsidiary | F53: -280.5
B54: Acquisition of subsidiaries, net of cash and cash equivalents acquired | D54: -2742.1
B55: Proceeds from sale of subsidiary, net of tax | D55: 31739.1
B56: Proceeds from liquidation of subsidiary | E56: 43.2
B57: Proceeds from liquidation of joint venture | E57: 249.7
B58: Proceeds from/(Purchase of) non-current investments in joint ventures (net) | C58: -1791 | D58: -1536.3 | E58: -726.5 | F58: 1053.8 | G58: -219.4
B59: Purchase of non-current investments | D59: -1540 | E59: -2999.2 | F59: -6769.4 | G59: -16.5
B60: Purchase of current investments | D60: -1597.8 | E60: -5250.3 | F60: -13371.6 | G60: -21.1
B61: Proceeds from sale of current investments | E61: 3264.3 | F61: 16341.5 | G61: 1026.4 | H61: =SUM(Balance_sheet!G19:G24)-SUM(Balance_sheet!H19:H24) -> 4725.6601 | I61: =SUM(Balance_sheet!H19:H24)-SUM(Balance_sheet!I19:I24) -> -1552.9835 | J61: =SUM(Balance_sheet!I19:I24)-SUM(Balance_sheet!J19:J24) -> -1776.8674 | K61: =SUM(Balance_sheet!J19:J24)-SUM(Balance_sheet!K19:K24) -> -2043.0968 | L61: =SUM(Balance_sheet!K19:K24)-SUM(Balance_sheet!L19:L24) -> -2360.5911 | M61: =SUM(Balance_sheet!L19:L24)-SUM(Balance_sheet!M19:M24) -> -2740.2293 | N61: =SUM(Balance_sheet!M19:M24)-SUM(Balance_sheet!N19:N24) -> -3195.2882 | O61: =SUM(Balance_sheet!N19:N24)-SUM(Balance_sheet!O19:O24) -> -3741.9801 | ... Q61: =SUM(Balance_sheet!P19:P24)-SUM(Balance_sheet!Q19:Q24) -> -5193.8852
B62: Proceeds from sale of non-current investments | E62: 1352.2 | F62: 7173.2 | G62: 765.1
B63: Margin money deposits not considered as cash and cash equivalents (net) | C63: -85.8 | D63: -271.1 | E63: 749.3 | F63: -16608.4 | G63: -11890.2 | H63: 28848.2 | I63: 0 | J63: 0 | K63: 0 | L63: 0 | M63: 0 | N63: 0 | O63: 0 | P63: 0 | Q63: 0
B64: Interest received | C64: 193.4 | D64: 191.5 | E64: 252.6 | F64: 1466.2 | G64: 2808.4 | H64: ='Income Statement'!H27 -> 4258.4774 | I64: ='Income Statement'!I27 -> 4599.8952 | J64: ='Income Statement'!J27 -> 4990.5331 | K64: ='Income Statement'!K27 -> 5439.7006 | L64: ='Income Statement'!L27 -> 5958.668 | M64: ='Income Statement'!M27 -> 6561.0975 | N64: ='Income Statement'!N27 -> 7263.5701 | O64: ='Income Statement'!O27 -> 8086.231 | ... Q64: ='Income Statement'!Q27 -> 10195.436
B65: Dividend received from joint venture | C65: 24.4
B67: Net cash used in investing activities | C67: =SUM(C49:C65) -> -15676.4 | D67: =SUM(D49:D65) -> 5986.9 | E67: =SUM(E49:E65) -> -32115.6 | F67: =SUM(F49:F65) -> -39777.5 | G67: =SUM(G49:G65) -> -42559.5 | H67: =SUM(H49:H65) -> 21939.382 | I67: =SUM(I49:I65) -> -27105.602 | J67: =SUM(J49:J65) -> -29132.456 | ... Q67: =SUM(Q49:Q65) -> -49393.253
B69: CASH FLOW FROM FINANCING ACTIVITIES
B70: Proceeds from issuance of equity share capital | C70: 1.9
B71: Proceeds from non-current borrowings | D71: 1769.8 | E71: 827.3 | F71: 3935.8 | G71: 15632.4
B72: Repayment of non-current borrowings | C72: -2169.8 | D72: -4681.2 | F72: -56.5 | G72: -171.7
B73: Proceeds from/(repayment) of current borrowings (net) | C73: -13129.7 | D73: -6678.2 | E73: -26366.6 | F73: 20696.8 | G73: -847.6
B74: Finance costs paid | C74: -1266.1 | D74: -493.5 | E74: -185 | F74: -1112 | G74: -2506.5 | H74: =SUM(Balance_sheet!H56:H61)-SUM(Balance_sheet!G56:G61) -> -11553.836 | I74: =SUM(Balance_sheet!I56:I61)-SUM(Balance_sheet!H56:H61) -> 1496.1984 | J74: =SUM(Balance_sheet!J56:J61)-SUM(Balance_sheet!I56:I61) -> 1711.8959 | K74: =SUM(Balance_sheet!K56:K61)-SUM(Balance_sheet!J56:J61) -> 1968.3906 | L74: =SUM(Balance_sheet!L56:L61)-SUM(Balance_sheet!K56:K61) -> 2274.2757 | M74: =SUM(Balance_sheet!M56:M61)-SUM(Balance_sheet!L56:L61) -> 2640.0323 | N74: =SUM(Balance_sheet!N56:N61)-SUM(Balance_sheet!M56:M61) -> 3078.452 | O74: =SUM(Balance_sheet!O56:O61)-SUM(Balance_sheet!N56:N61) -> 3605.1539 | ... Q74: =SUM(Balance_sheet!Q56:Q61)-SUM(Balance_sheet!P56:P61) -> 5003.9699
B75: Repayment of lease liabilities (net) | C75: -1024.1 | D75: -1223.2 | E75: -1331.4 | F75: -924.7 | G75: -1466
B76: Dividends paid on equity shares | C76: -1756.1 | D76: -2343.1 | E76: -2637 | F76: -4395.3 | G76: -2636.4 | H76: ='Income Statement'!H39 -> -3806.1397 | I76: ='Income Statement'!I39 -> -3743.5428 | J76: ='Income Statement'!J39 -> -4116.7533 | K76: ='Income Statement'!K39 -> -4542.7657 | L76: ='Income Statement'!L39 -> -5035.0547 | M76: ='Income Statement'!M39 -> -5609.3999 | N76: ='Income Statement'!N39 -> -6284.5569 | O76: ='Income Statement'!O39 -> -7083.0428 | ... Q76: ='Income Statement'!Q39 -> -9164.682
B77: Tax paid on equity dividend | C77: -127.9
B79: Net cash generated from financing activities | C79: =SUM(C70:C77) -> -19471.8 | D79: =SUM(D70:D77) -> -13649.4 | E79: =SUM(E70:E77) -> -29692.7 | F79: =SUM(F70:F77) -> 18144.1 | G79: =SUM(G70:G77) -> 8004.2 | H79: =SUM(H70:H77) -> -15359.976 | I79: =SUM(I70:I77) -> -2247.3444 | J79: =SUM(J70:J77) -> -2404.8574 | ... Q79: =SUM(Q70:Q77) -> -4160.7121
B81: Net increase/(decrease) in cash and cash equivalents (A + B + C) | C81: =SUM(C79,C67,C46) -> 8664.6 | D81: =SUM(D79,D67,D46) -> 25628 | E81: =SUM(E79,E67,E46) -> -11643.5 | F81: =SUM(F79,F67,F46) -> 2234.1 | G81: =SUM(G79,G67,G46) -> -10210.1 | H81: =SUM(H79,H67,H46) -> 64174.226 | I81: =SUM(I79,I67,I46) -> 19040.517 | J81: =SUM(J79,J67,J46) -> 20531.104 | ... Q81: =SUM(Q79,Q67,Q46) -> 46039.426
B82: Cash and cash equivalents at the beginning of the year | C82: 18755.8 | D82: 27468.2 | E82: 53299.1 | F82: 41625.1 | G82: 43922.7 | H82: =G85 -> 33854.3 | I82: =H85 -> 98028.526 | J82: =I85 -> 117069.04 | K82: =J85 -> 137600.15 | L82: =K85 -> 159969.67 | M82: =L85 -> 184593.37 | N82: =M85 -> 211973.54 | O82: =N85 -> 242721.1 | ... Q82: =P85 -> 317471.85
B83: Add: Cash and cash equivalents on acquisition of subsidiaries/business | D83: 224.1 | E83: -32.5
B84: Effect of exchange differences on cash and cash equivalents | C84: 47.8 | D84: -21.2 | E84: 2 | F84: -0.6 | G84: 141.7
B85: Cash and cash equivalents at the end of the year | C85: =SUM(C81:C84) -> 27468.2 | D85: =SUM(D81:D84) -> 53299.1 | E85: =SUM(E81:E84) -> 41625.1 | F85: =SUM(F81:F84) -> 43858.6 | G85: =SUM(G81:G84) -> 33854.3 | H85: =SUM(H81:H84) -> 98028.526 | I85: =SUM(I81:I84) -> 117069.04 | J85: =SUM(J81:J84) -> 137600.15 | ... Q85: =SUM(Q81:Q84) -> 363511.28

Sheet BalanceSheet Forecast
B6: Balance Sheet Forecast
B8: Particulars | C8: 2020 | D8: =C8+1 -> 2021 | E8: =D8+1 -> 2022 | F8: =E8+1 -> 2023 | G8: =F8+1 -> 2024 | H8: =G8+1 -> 2025 | I8: =H8+1 -> 2026 | J8: =I8+1 -> 2027 | K8: =J8+1 -> 2028 | ... Q8: =P8+1 -> 2034
B10: Non-current assets
B11: Investments | C11: =Balance_sheet!C19 -> 1450.8 | D11: =Balance_sheet!D19 -> 3365.2 | E11: =Balance_sheet!E19 -> 5389.5 | F11: =Balance_sheet!F19 -> 3017.4 | G11: =Balance_sheet!G19 -> 2268.7 | H11: =H12*'Revenue Build_up'!H$10 -> 3918.8579 | I11: =I12*'Revenue Build_up'!I$10 -> 4233.0472 | J11: =J12*'Revenue Build_up'!J$10 -> 4592.5312 | K11: =K12*'Revenue Build_up'!K$10 -> 5005.8769 | L11: =L12*'Revenue Build_up'!L$10 -> 5483.456 | M11: =M12*'Revenue Build_up'!M$10 -> 6037.8409 | N11: =N12*'Revenue Build_up'!N$10 -> 6684.2903 | O11: =O12*'Revenue Build_up'!O$10 -> 7441.3428 | ... Q11: =Q12*'Revenue Build_up'!Q$10 -> 9382.3361
B12: % of Revenue | C12: =C11/'Revenue Build_up'!C$10 -> 0.0062809246 | D12: =D11/'Revenue Build_up'!D$10 -> 0.013583256 | E12: =E11/'Revenue Build_up'!E$10 -> 0.022977563 | F12: =F11/'Revenue Build_up'!F$10 -> 0.012139826 | G12: =G11/'Revenue Build_up'!G$10 -> 0.007822599 | H12: =AVERAGE(C12:G12) -> 0.012560834 | I12: =H12 -> 0.012560834 | J12: =I12 -> 0.012560834 | K12: =J12 -> 0.012560834 | L12: =K12 -> 0.012560834 | M12: =L12 -> 0.012560834 | N12: =M12 -> 0.012560834 | O12: =N12 -> 0.012560834 | P12: =O12 -> 0.012560834 | Q12: =P12 -> 0.012560834
B13: =Balance_sheet!B20 -> Loans | C13: =Balance_sheet!C20 -> 58.4 | D13: =Balance_sheet!D20 -> 72.6 | E13: =Balance_sheet!E20 -> 63.2 | F13: =Balance_sheet!F20 -> 55.7 | G13: =Balance_sheet!G20 -> 58.3 | H13: =H14*'Revenue Build_up'!H$10 -> 77.400816 | I13: =I14*'Revenue Build_up'!I$10 -> 83.606325 | J13: =J14*'Revenue Build_up'!J$10 -> 90.706442 | K13: =K14*'Revenue Build_up'!K$10 -> 98.870376 | L13: =L14*'Revenue Build_up'!L$10 -> 108.30297 | M13: =M14*'Revenue Build_up'!M$10 -> 119.25255 | N13: =N14*'Revenue Build_up'!N$10 -> 132.02049 | O13: =O14*'Revenue Build_up'!O$10 -> 146.97292 | ... Q13: =Q14*'Revenue Build_up'!Q$10 -> 185.30921
B14: % of Revenue | C14: =C13/'Revenue Build_up'!C$10 -> 0.00025283016 | D14: =D13/'Revenue Build_up'!D$10 -> 0.00029304183 | E14: =E13/'Revenue Build_up'!E$10 -> 0.00026944651 | F14: =F13/'Revenue Build_up'!F$10 -> 0.00022409635 | G14: =G13/'Revenue Build_up'!G$10 -> 0.00020102152 | H14: =AVERAGE(C14:G14) -> 0.00024808728 | I14: =H14 -> 0.00024808728 | J14: =I14 -> 0.00024808728 | K14: =J14 -> 0.00024808728 | L14: =K14 -> 0.00024808728 | M14: =L14 -> 0.00024808728 | N14: =M14 -> 0.00024808728 | O14: =N14 -> 0.00024808728 | P14: =O14 -> 0.00024808728 | Q14: =P14 -> 0.00024808728
B15: =Balance_sheet!B21 -> Other financial assets | C15: =Balance_sheet!C21 -> 1170.3 | D15: =Balance_sheet!D21 -> 1433 | E15: =Balance_sheet!E21 -> 1289.2 | F15: =Balance_sheet!F21 -> 1503.7 | G15: =Balance_sheet!G21 -> 3510 | H15: =H16*'Revenue Build_up'!H$10 -> 2152.7041 | I15: =I16*'Revenue Build_up'!I$10 -> 2325.2943 | J15: =J16*'Revenue Build_up'!J$10 -> 2522.7657 | K15: =K16*'Revenue Build_up'!K$10 -> 2749.8245 | L15: =L16*'Revenue Build_up'!L$10 -> 3012.1679 | M15: =M16*'Revenue Build_up'!M$10 -> 3316.7022 | N15: =N16*'Revenue Build_up'!N$10 -> 3671.8093 | O15: =O16*'Revenue Build_up'!O$10 -> 4087.6728 | ... Q15: =Q16*'Revenue Build_up'!Q$10 -> 5153.8977
B16: % of Revenue | C16: =C15/'Revenue Build_up'!C$10 -> 0.0050665606 | D16: =D15/'Revenue Build_up'!D$10 -> 0.0057841452 | E16: =E15/'Revenue Build_up'!E$10 -> 0.0054963678 | F16: =F15/'Revenue Build_up'!F$10 -> 0.0060497969 | G16: =G15/'Revenue Build_up'!G$10 -> 0.012102668 | H16: =AVERAGE(C16:G16) -> 0.0068999077 | I16: =H16 -> 0.0068999077 | J16: =I16 -> 0.0068999077 | K16: =J16 -> 0.0068999077 | L16: =K16 -> 0.0068999077 | M16: =L16 -> 0.0068999077 | N16: =M16 -> 0.0068999077 | O16: =N16 -> 0.0068999077 | P16: =O16 -> 0.0068999077 | Q16: =P16 -> 0.0068999077
B17: =Balance_sheet!B22 -> Deferred tax assets (net | C17: =Balance_sheet!C22 -> 1632 | D17: =Balance_sheet!D22 -> 4526.8 | E17: =Balance_sheet!E22 -> 2885.9 | F17: =Balance_sheet!F22 -> 6774.9 | G17: =Balance_sheet!G22 -> 12126.4 | H17: =H18*'Revenue Build_up'!H$10 -> 6658.5462 | I17: =I18*'Revenue Build_up'!I$10 -> 7192.3864 | J17: =J18*'Revenue Build_up'!J$10 -> 7803.187 | K17: =K18*'Revenue Build_up'!K$10 -> 8505.5042 | L17: =L18*'Revenue Build_up'!L$10 -> 9316.9606 | M17: =M18*'Revenue Build_up'!M$10 -> 10258.918 | N17: =N18*'Revenue Build_up'!N$10 -> 11357.303 | O17: =O18*'Revenue Build_up'!O$10 -> 12643.614 | ... Q17: =Q18*'Revenue Build_up'!Q$10 -> 15941.562
B18: % of Revenue | C18: =C17/'Revenue Build_up'!C$10 -> 0.0070653908 | D18: =D17/'Revenue Build_up'!D$10 -> 0.018271925 | E18: =E17/'Revenue Build_up'!E$10 -> 0.012303729 | F18: =F17/'Revenue Build_up'!F$10 -> 0.027257278 | G18: =G17/'Revenue Build_up'!G$10 -> 0.041812476 | H18: =AVERAGE(C18:G18) -> 0.02134216 | I18: =H18 -> 0.02134216 | J18: =I18 -> 0.02134216 | K18: =J18 -> 0.02134216 | L18: =K18 -> 0.02134216 | M18: =L18 -> 0.02134216 | N18: =M18 -> 0.02134216 | O18: =N18 -> 0.02134216 | P18: =O18 -> 0.02134216 | Q18: =P18 -> 0.02134216
B19: =Balance_sheet!B23 -> Non-current tax assets (net) | C19: =Balance_sheet!C23 -> 845.3 | D19: =Balance_sheet!D23 -> 1282.6 | E19: =Balance_sheet!E23 -> 3189.7 | F19: =Balance_sheet!F23 -> 2885.2 | G19: =Balance_sheet!G23 -> 3832.9 | H19: =H20*'Revenue Build_up'!H$10 -> 2948.9045 | I19: =I20*'Revenue Build_up'!I$10 -> 3185.329 | J19: =J20*'Revenue Build_up'!J$10 -> 3455.8374 | K19: =K20*'Revenue Build_up'!K$10 -> 3766.8762 | L19: =L20*'Revenue Build_up'!L$10 -> 4126.2501 | M19: =M20*'Revenue Build_up'!M$10 -> 4543.4196 | N19: =N20*'Revenue Build_up'!N$10 -> 5029.8669 | O19: =O20*'Revenue Build_up'!O$10 -> 5599.5419 | ... Q19: =Q20*'Revenue Build_up'!Q$10 -> 7060.1214
B20: % of Revenue | C20: =C19/'Revenue Build_up'!C$10 -> 0.0036595434 | D20: =D19/'Revenue Build_up'!D$10 -> 0.0051770723 | E20: =E19/'Revenue Build_up'!E$10 -> 0.013598948 | F20: =F19/'Revenue Build_up'!F$10 -> 0.01160795 | G20: =G19/'Revenue Build_up'!G$10 -> 0.013216044 | H20: =AVERAGE(C20:G20) -> 0.0094519116 | I20: =H20 -> 0.0094519116 | J20: =I20 -> 0.0094519116 | K20: =J20 -> 0.0094519116 | L20: =K20 -> 0.0094519116 | M20: =L20 -> 0.0094519116 | N20: =M20 -> 0.0094519116 | O20: =N20 -> 0.0094519116 | P20: =O20 -> 0.0094519116 | Q20: =P20 -> 0.0094519116
B21: =Balance_sheet!B24 -> Other non-current asset | C21: =Balance_sheet!C24 -> 2075.5 | D21: =Balance_sheet!D24 -> 4326.5 | E21: =Balance_sheet!E24 -> 1586.4 | F21: =Balance_sheet!F24 -> 4169.3 | G21: =Balance_sheet!G24 -> 2299.6 | H21: =H22*'Revenue Build_up'!H$10 -> 3613.8265 | I21: =I22*'Revenue Build_up'!I$10 -> 3903.5603 | J21: =J22*'Revenue Build_up'!J$10 -> 4235.0632 | K21: =K22*'Revenue Build_up'!K$10 -> 4616.2354 | L21: =L22*'Revenue Build_up'!L$10 -> 5056.6412 | M21: =M22*'Revenue Build_up'!M$10 -> 5567.8746 | N21: =N22*'Revenue Build_up'!N$10 -> 6164.0065 | O21: =O22*'Revenue Build_up'!O$10 -> 6862.1324 | ... Q21: =Q22*'Revenue Build_up'!Q$10 -> 8652.0449
B22: % of Revenue | C22: =C21/'Revenue Build_up'!C$10 -> 0.0089854281 | D22: =D21/'Revenue Build_up'!D$10 -> 0.017463436 | E22: =E21/'Revenue Build_up'!E$10 -> 0.0067634486 | F22: =F21/'Revenue Build_up'!F$10 -> 0.016774236 | G22: =G21/'Revenue Build_up'!G$10 -> 0.0079291439 | H22: =AVERAGE(C22:G22) -> 0.011583138 | I22: =H22 -> 0.011583138 | J22: =I22 -> 0.011583138 | K22: =J22 -> 0.011583138 | L22: =K22 -> 0.011583138 | M22: =L22 -> 0.011583138 | N22: =M22 -> 0.011583138 | O22: =N22 -> 0.011583138 | P22: =O22 -> 0.011583138 | Q22: =P22 -> 0.011583138
B25: Current assets
B26: =Balance_sheet!B31 -> Investments | C26: =Balance_sheet!C31 -> 0.2 | D26: =Balance_sheet!D31 -> 1597.9 | E26: =Balance_sheet!E31 -> 3788.5 | F26: =Balance_sheet!F31 -> 1510 | G26: =Balance_sheet!G31 -> 505.8 | H26: =H27*'Revenue Build_up'!H$10 -> 1898.2517 | I26: =I27*'Revenue Build_up'!I$10 -> 2050.4416 | J26: =J27*'Revenue Build_up'!J$10 -> 2224.5716 | K26: =K27*'Revenue Build_up'!K$10 -> 2424.7918 | L26: =L27*'Revenue Build_up'!L$10 -> 2656.1258 | M26: =M27*'Revenue Build_up'!M$10 -> 2924.6638 | N26: =N27*'Revenue Build_up'!N$10 -> 3237.7968 | O26: =O27*'Revenue Build_up'!O$10 -> 3604.5047 | ... Q26: =Q27*'Revenue Build_up'!Q$10 -> 4544.7005
B27: % of Revenue | C27: =C26/'Revenue Build_up'!C$10 -> 8.6585672e-07 | D27: =D26/'Revenue Build_up'!D$10 -> 0.0064497457 | E27: =E26/'Revenue Build_up'!E$10 -> 0.016151869 | F27: =F26/'Revenue Build_up'!F$10 -> 0.0060751435 | G27: =G26/'Revenue Build_up'!G$10 -> 0.0017440255 | H27: =AVERAGE(C27:G27) -> 0.0060843299 | I27: =H27 -> 0.0060843299 | J27: =I27 -> 0.0060843299 | K27: =J27 -> 0.0060843299 | L27: =K27 -> 0.0060843299 | M27: =L27 -> 0.0060843299 | N27: =M27 -> 0.0060843299 | O27: =N27 -> 0.0060843299 | P27: =O27 -> 0.0060843299 | Q27: =P27 -> 0.0060843299
B28: =Balance_sheet!B35 -> Loans | C28: =Balance_sheet!C35 -> 136.8 | D28: =Balance_sheet!D35 -> 143.2 | E28: =Balance_sheet!E35 -> 127.1 | F28: =Balance_sheet!F35 -> 124.3 | G28: =Balance_sheet!G35 -> 128.6 | H28: =H29*'Revenue Build_up'!H$10 -> 165.7072 | I28: =I29*'Revenue Build_up'!I$10 -> 178.99256 | J28: =J29*'Revenue Build_up'!J$10 -> 194.19318 | K28: =K29*'Revenue Build_up'!K$10 -> 211.67132 | L28: =L29*'Revenue Build_up'!L$10 -> 231.86554 | M28: =M29*'Revenue Build_up'!M$10 -> 255.30747 | N28: =N29*'Revenue Build_up'!N$10 -> 282.6423 | O28: =O29*'Revenue Build_up'!O$10 -> 314.65394 | ... Q28: =Q29*'Revenue Build_up'!Q$10 -> 396.72799
B29: % of Revenue | C29: =C28/'Revenue Build_up'!C$10 -> 0.00059224599 | D29: =D28/'Revenue Build_up'!D$10 -> 0.00057801088 | E29: =E28/'Revenue Build_up'!E$10 -> 0.0005418774 | F29: =F28/'Revenue Build_up'!F$10 -> 0.00050009294 | G29: =G28/'Revenue Build_up'!G$10 -> 0.00044341968 | H29: =AVERAGE(C29:G29) -> 0.00053112938 | I29: =H29 -> 0.00053112938 | J29: =I29 -> 0.00053112938 | K29: =J29 -> 0.00053112938 | L29: =K29 -> 0.00053112938 | M29: =L29 -> 0.00053112938 | N29: =M29 -> 0.00053112938 | O29: =N29 -> 0.00053112938 | P29: =O29 -> 0.00053112938 | Q29: =P29 -> 0.00053112938
B30: =Balance_sheet!B36 -> Other financial assets | C30: =Balance_sheet!C36 -> 400.8 | D30: =Balance_sheet!D36 -> 338.7 | E30: =Balance_sheet!E36 -> 709.1 | F30: =Balance_sheet!F36 -> 2903.5 | G30: =Balance_sheet!G36 -> 2631.1 | H30: =H31*'Revenue Build_up'!H$10 -> 1677.2113 | I30: =I31*'Revenue Build_up'!I$10 -> 1811.6795 | J30: =J31*'Revenue Build_up'!J$10 -> 1965.5331 | K30: =K31*'Revenue Build_up'!K$10 -> 2142.4388 | L30: =L31*'Revenue Build_up'!L$10 -> 2346.8353 | M30: =M31*'Revenue Build_up'!M$10 -> 2584.1036 | N30: =N31*'Revenue Build_up'!N$10 -> 2860.774 | O30: =O31*'Revenue Build_up'!O$10 -> 3184.7809 | ... Q30: =Q31*'Revenue Build_up'!Q$10 -> 4015.4963
B31: % of Revenue | C31: =C30/'Revenue Build_up'!C$10 -> 0.0017351769 | D31: =D30/'Revenue Build_up'!D$10 -> 0.0013671249 | E31: =E30/'Revenue Build_up'!E$10 -> 0.0030231728 | F31: =F30/'Revenue Build_up'!F$10 -> 0.011681576 | G31: =G30/'Revenue Build_up'!G$10 -> 0.0090721736 | H31: =AVERAGE(C31:G31) -> 0.0053758448 | I31: =H31 -> 0.0053758448 | J31: =I31 -> 0.0053758448 | K31: =J31 -> 0.0053758448 | L31: =K31 -> 0.0053758448 | M31: =L31 -> 0.0053758448 | N31: =M31 -> 0.0053758448 | O31: =N31 -> 0.0053758448 | P31: =O31 -> 0.0053758448 | Q31: =P31 -> 0.0053758448
B32: =Balance_sheet!B37 -> Current tax assets (net | C32: =Balance_sheet!C37 -> 157.6 | D32: =Balance_sheet!D37 -> 789.8 | E32: =Balance_sheet!E37 -> 2699.9 | F32: =Balance_sheet!F37 -> 756.2 | G32: =Balance_sheet!G37 -> 56.7 | H32: =H33*'Revenue Build_up'!H$10 -> 1161.7817 | I32: =I33*'Revenue Build_up'!I$10 -> 1254.926 | J32: =J33*'Revenue Build_up'!J$10 -> 1361.4984 | K32: =K33*'Revenue Build_up'!K$10 -> 1484.0386 | L32: =L33*'Revenue Build_up'!L$10 -> 1625.6213 | M32: =M33*'Revenue Build_up'!M$10 -> 1789.9738 | N32: =N33*'Revenue Build_up'!N$10 -> 1981.6197 | O32: =O33*'Revenue Build_up'!O$10 -> 2206.055 | ... Q32: =Q33*'Revenue Build_up'!Q$10 -> 2781.4804
B33: % of Revenue | C33: =C32/'Revenue Build_up'!C$10 -> 0.00068229509 | D33: =D32/'Revenue Build_up'!D$10 -> 0.0031879399 | E33: =E32/'Revenue Build_up'!E$10 -> 0.011510738 | F33: =F32/'Revenue Build_up'!F$10 -> 0.0030423997 | G33: =G32/'Revenue Build_up'!G$10 -> 0.00019550463 | H33: =AVERAGE(C33:G33) -> 0.0037237755 | I33: =H33 -> 0.0037237755 | J33: =I33 -> 0.0037237755 | K33: =J33 -> 0.0037237755 | L33: =K33 -> 0.0037237755 | M33: =L33 -> 0.0037237755 | N33: =M33 -> 0.0037237755 | O33: =N33 -> 0.0037237755 | P33: =O33 -> 0.0037237755 | Q33: =P33 -> 0.0037237755
B34: =Balance_sheet!B38 -> Other current assets | C34: =Balance_sheet!C38 -> 14857.9 | D34: =Balance_sheet!D38 -> 14488.1 | E34: =Balance_sheet!E38 -> 15550.1 | F34: =Balance_sheet!F38 -> 18687 | G34: =Balance_sheet!G38 -> 25364.3 | H34: =H35*'Revenue Build_up'!H$10 -> 21947.907 | I34: =I35*'Revenue Build_up'!I$10 -> 23707.552 | J34: =J35*'Revenue Build_up'!J$10 -> 25720.874 | K34: =K35*'Revenue Build_up'!K$10 -> 28035.853 | L34: =L35*'Revenue Build_up'!L$10 -> 30710.576 | M34: =M35*'Revenue Build_up'!M$10 -> 33815.457 | N34: =N35*'Revenue Build_up'!N$10 -> 37435.954 | O34: =O35*'Revenue Build_up'!O$10 -> 41675.893 | ... Q34: =Q35*'Revenue Build_up'!Q$10 -> 52546.596
B35: % of Revenue | C35: =C34/'Revenue Build_up'!C$10 -> 0.064324062 | D35: =D34/'Revenue Build_up'!D$10 -> 0.058479605 | E35: =E34/'Revenue Build_up'!E$10 -> 0.066296206 | F35: =F34/'Revenue Build_up'!F$10 -> 0.075182918 | G35: =G34/'Revenue Build_up'!G$10 -> 0.087457464 | H35: =AVERAGE(C35:G35) -> 0.070348051 | I35: =H35 -> 0.070348051 | J35: =I35 -> 0.070348051 | K35: =J35 -> 0.070348051 | L35: =K35 -> 0.070348051 | M35: =L35 -> 0.070348051 | N35: =M35 -> 0.070348051 | O35: =N35 -> 0.070348051 | P35: =O35 -> 0.070348051 | Q35: =P35 -> 0.070348051
B36: =Balance_sheet!B39 -> Assets held for sale | C36: =Balance_sheet!C39 -> 0 | D36: =Balance_sheet!D39 -> 836.1 | E36: =Balance_sheet!E39 -> 791 | F36: =Balance_sheet!F39 -> 857.6 | G36: =Balance_sheet!G39 -> 4337.1 | H36: =H37*'Revenue Build_up'!H$10 -> 1569.441 | I36: =I37*'Revenue Build_up'!I$10 -> 1695.2688 | J36: =J37*'Revenue Build_up'!J$10 -> 1839.2365 | K36: =K37*'Revenue Build_up'!K$10 -> 2004.775 | L36: =L37*'Revenue Build_up'!L$10 -> 2196.0379 | M36: =M37*'Revenue Build_up'!M$10 -> 2418.0603 | N36: =N37*'Revenue Build_up'!N$10 -> 2676.9532 | O36: =O37*'Revenue Build_up'!O$10 -> 2980.1408 | ... Q36: =Q37*'Revenue Build_up'!Q$10 -> 3757.4781
B37: % of Revenue | C37: =C36/'Revenue Build_up'!C$10 -> 0 | D37: =D36/'Revenue Build_up'!D$10 -> 0.0033748247 | E37: =E36/'Revenue Build_up'!E$10 -> 0.0033723448 | F37: =F36/'Revenue Build_up'!F$10 -> 0.0034503596 | G37: =G36/'Revenue Build_up'!G$10 -> 0.014954553 | H37: =AVERAGE(C37:G37) -> 0.0050304164 | I37: =H37 -> 0.0050304164 | J37: =I37 -> 0.0050304164 | K37: =J37 -> 0.0050304164 | L37: =K37 -> 0.0050304164 | M37: =L37 -> 0.0050304164 | N37: =M37 -> 0.0050304164 | O37: =N37 -> 0.0050304164 | P37: =O37 -> 0.0050304164 | Q37: =P37 -> 0.0050304164
B39: Non-current liabilities
B40: =Balance_sheet!B56 -> Borrowings | C40: =Balance_sheet!C56 -> 0 | D40: =Balance_sheet!D56 -> 1684.9 | E40: =Balance_sheet!E56 -> 2492.1 | F40: =Balance_sheet!F56 -> 6189.6 | G40: =Balance_sheet!G56 -> 21349 | H40: =H41*'Revenue Build_up'!H$10 -> 7234.472 | I40: =I41*'Revenue Build_up'!I$10 -> 7814.4862 | J40: =J41*'Revenue Build_up'!J$10 -> 8478.1175 | K40: =K41*'Revenue Build_up'!K$10 -> 9241.1812 | L40: =L41*'Revenue Build_up'!L$10 -> 10122.824 | M40: =M41*'Revenue Build_up'!M$10 -> 11146.255 | N40: =N41*'Revenue Build_up'!N$10 -> 12339.644 | O40: =O41*'Revenue Build_up'!O$10 -> 13737.213 | ... Q40: =Q41*'Revenue Build_up'!Q$10 -> 17320.415
B41: % of Revenue | C41: =C40/'Revenue Build_up'!C$10 -> 0 | D41: =D40/'Revenue Build_up'!D$10 -> 0.0068009116 | E41: =E40/'Revenue Build_up'!E$10 -> 0.010624805 | F41: =F40/'Revenue Build_up'!F$10 -> 0.024902456 | G41: =G40/'Revenue Build_up'!G$10 -> 0.073612495 | H41: =AVERAGE(C41:G41) -> 0.023188133 | I41: =H41 -> 0.023188133 | J41: =I41 -> 0.023188133 | K41: =J41 -> 0.023188133 | L41: =K41 -> 0.023188133 | M41: =L41 -> 0.023188133 | N41: =M41 -> 0.023188133 | O41: =N41 -> 0.023188133 | P41: =O41 -> 0.023188133 | Q41: =P41 -> 0.023188133
B42: =Balance_sheet!B57 -> Lease liabilities | C42: =Balance_sheet!C57 -> 0 | D42: =Balance_sheet!D57 -> 2661.9 | E42: =Balance_sheet!E57 -> 3186.1 | F42: =Balance_sheet!F57 -> 3215.3 | G42: =Balance_sheet!G57 -> 2525.3 | H42: =H43*'Revenue Build_up'!H$10 -> 2868.53 | I42: =I43*'Revenue Build_up'!I$10 -> 3098.5106 | J42: =J43*'Revenue Build_up'!J$10 -> 3361.6461 | K42: =K43*'Revenue Build_up'!K$10 -> 3664.2074 | L42: =L43*'Revenue Build_up'!L$10 -> 4013.7862 | M42: =M43*'Revenue Build_up'!M$10 -> 4419.5855 | N42: =N43*'Revenue Build_up'!N$10 -> 4892.7743 | O42: =O43*'Revenue Build_up'!O$10 -> 5446.9224 | ... Q42: =Q43*'Revenue Build_up'!Q$10 -> 6867.6928
B43: % of Revenue | C43: =C42/'Revenue Build_up'!C$10 -> 0 | D43: =D42/'Revenue Build_up'!D$10 -> 0.010744463 | E43: =E42/'Revenue Build_up'!E$10 -> 0.0135836 | F43: =F42/'Revenue Build_up'!F$10 -> 0.012936032 | G43: =G42/'Revenue Build_up'!G$10 -> 0.0087073696 | H43: =AVERAGE(C43:G43) -> 0.0091942931 | I43: =H43 -> 0.0091942931 | J43: =I43 -> 0.0091942931 | K43: =J43 -> 0.0091942931 | L43: =K43 -> 0.0091942931 | M43: =L43 -> 0.0091942931 | N43: =M43 -> 0.0091942931 | O43: =N43 -> 0.0091942931 | P43: =O43 -> 0.0091942931 | Q43: =P43 -> 0.0091942931
B44: =Balance_sheet!B58 -> Others | C44: =Balance_sheet!C58 -> 2644.1 | D44: =Balance_sheet!D58 -> 541 | E44: =Balance_sheet!E58 -> 113.5 | F44: =Balance_sheet!F58 -> 125 | G44: =Balance_sheet!G58 -> 154.2 | H44: =H45*'Revenue Build_up'!H$10 -> 945.28306 | I44: =I45*'Revenue Build_up'!I$10 -> 1021.0699 | J44: =J45*'Revenue Build_up'!J$10 -> 1107.7824 | K44: =K45*'Revenue Build_up'!K$10 -> 1207.4872 | L44: =L45*'Revenue Build_up'!L$10 -> 1322.6859 | M44: =M45*'Revenue Build_up'!M$10 -> 1456.4112 | N44: =N45*'Revenue Build_up'!N$10 -> 1612.3438 | O44: =O45*'Revenue Build_up'!O$10 -> 1794.9554 | ... Q44: =Q45*'Revenue Build_up'!Q$10 -> 2263.15
B45: % of Revenue | C45: =C44/'Revenue Build_up'!C$10 -> 0.011447059 | D45: =D44/'Revenue Build_up'!D$10 -> 0.0021836864 | E45: =E44/'Revenue Build_up'!E$10 -> 0.00048389524 | F45: =F44/'Revenue Build_up'!F$10 -> 0.00050290923 | G45: =G44/'Revenue Build_up'!G$10 -> 0.00053168985 | H45: =AVERAGE(C45:G45) -> 0.0030298479 | I45: =H45 -> 0.0030298479 | J45: =I45 -> 0.0030298479 | K45: =J45 -> 0.0030298479 | L45: =K45 -> 0.0030298479 | M45: =L45 -> 0.0030298479 | N45: =M45 -> 0.0030298479 | O45: =N45 -> 0.0030298479 | P45: =O45 -> 0.0030298479 | Q45: =P45 -> 0.0030298479
B46: =Balance_sheet!B59 -> Provisions | C46: =Balance_sheet!C59 -> 747.1 | D46: =Balance_sheet!D59 -> 1571.1 | E46: =Balance_sheet!E59 -> 1717.9 | F46: =Balance_sheet!F59 -> 1727.2 | G46: =Balance_sheet!G59 -> 2257 | H46: =H47*'Revenue Build_up'!H$10 -> 1973.7327 | I46: =I47*'Revenue Build_up'!I$10 -> 2131.9741 | J46: =J47*'Revenue Build_up'!J$10 -> 2313.0282 | K46: =K47*'Revenue Build_up'!K$10 -> 2521.2098 | L46: =L47*'Revenue Build_up'!L$10 -> 2761.7425 | M46: =M47*'Revenue Build_up'!M$10 -> 3040.9585 | N46: =N47*'Revenue Build_up'!N$10 -> 3366.5427 | O46: =O47*'Revenue Build_up'!O$10 -> 3747.8322 | ... Q46: =Q47*'Revenue Build_up'!Q$10 -> 4725.4134
B47: % of Revenue | C47: =C46/'Revenue Build_up'!C$10 -> 0.0032344078 | D47: =D46/'Revenue Build_up'!D$10 -> 0.0063415705 | E47: =E46/'Revenue Build_up'!E$10 -> 0.0073240849 | F47: =F46/'Revenue Build_up'!F$10 -> 0.0069489986 | G47: =G46/'Revenue Build_up'!G$10 -> 0.0077822568 | H47: =AVERAGE(C47:G47) -> 0.0063262637 | I47: =H47 -> 0.0063262637 | J47: =I47 -> 0.0063262637 | K47: =J47 -> 0.0063262637 | L47: =K47 -> 0.0063262637 | M47: =L47 -> 0.0063262637 | N47: =M47 -> 0.0063262637 | O47: =N47 -> 0.0063262637 | P47: =O47 -> 0.0063262637 | Q47: =P47 -> 0.0063262637
B48: =Balance_sheet!B60 -> Deferred tax liabilities (net) | C48: =Balance_sheet!C60 -> 2916.9 | D48: =Balance_sheet!D60 -> 5745.6 | E48: =Balance_sheet!E60 -> 4109.6 | F48: =Balance_sheet!F60 -> 3896.1 | G48: =Balance_sheet!G60 -> 3565.6 | H48: =H49*'Revenue Build_up'!H$10 -> 5073.5773 | I48: =I49*'Revenue Build_up'!I$10 -> 5480.3447 | J48: =J49*'Revenue Build_up'!J$10 -> 5945.7532 | K48: =K49*'Revenue Build_up'!K$10 -> 6480.8942 | L48: =L49*'Revenue Build_up'!L$10 -> 7099.1953 | M48: =M49*'Revenue Build_up'!M$10 -> 7816.9337 | N48: =N49*'Revenue Build_up'!N$10 -> 8653.8641 | O48: =O49*'Revenue Build_up'!O$10 -> 9633.9875 | ... Q48: =Q49*'Revenue Build_up'!Q$10 -> 12146.908
B49: % of Revenue | C49: =C48/'Revenue Build_up'!C$10 -> 0.012628087 | D49: =D48/'Revenue Build_up'!D$10 -> 0.023191476 | E49: =E48/'Revenue Build_up'!E$10 -> 0.017520845 | F49: =F48/'Revenue Build_up'!F$10 -> 0.015675077 | G49: =G48/'Revenue Build_up'!G$10 -> 0.01229438 | H49: =AVERAGE(C49:G49) -> 0.016261973 | I49: =H49 -> 0.016261973 | J49: =I49 -> 0.016261973 | K49: =J49 -> 0.016261973 | L49: =K49 -> 0.016261973 | M49: =L49 -> 0.016261973 | N49: =M49 -> 0.016261973 | O49: =N49 -> 0.016261973 | P49: =O49 -> 0.016261973 | Q49: =P49 -> 0.016261973
B50: =Balance_sheet!B61 -> Other non-current liabilities | C50: =Balance_sheet!C61 -> 874.8 | D50: =Balance_sheet!D61 -> 395 | E50: =Balance_sheet!E61 -> 297.7 | F50: =Balance_sheet!F61 -> 290.4 | G50: =Balance_sheet!G61 -> 364.7 | H50: =H51*'Revenue Build_up'!H$10 -> 566.36886 | I50: =I51*'Revenue Build_up'!I$10 -> 611.77674 | J50: =J51*'Revenue Build_up'!J$10 -> 663.73079 | K50: =K51*'Revenue Build_up'!K$10 -> 723.46915 | L50: =L51*'Revenue Build_up'!L$10 -> 792.49077 | M50: =M51*'Revenue Build_up'!M$10 -> 872.61267 | N50: =N51*'Revenue Build_up'!N$10 -> 966.0401 | O50: =O51*'Revenue Build_up'!O$10 -> 1075.4523 | ... Q50: =Q51*'Revenue Build_up'!Q$10 -> 1355.9724
B51: % of Revenue | C51: =C50/'Revenue Build_up'!C$10 -> 0.0037872573 | D51: =D50/'Revenue Build_up'!D$10 -> 0.0015943736 | E51: =E50/'Revenue Build_up'!E$10 -> 0.0012692125 | F51: =F50/'Revenue Build_up'!F$10 -> 0.0011683587 | G51: =G50/'Revenue Build_up'!G$10 -> 0.0012575051 | H51: =AVERAGE(C51:G51) -> 0.0018153414 | I51: =H51 -> 0.0018153414 | J51: =I51 -> 0.0018153414 | K51: =J51 -> 0.0018153414 | L51: =K51 -> 0.0018153414 | M51: =L51 -> 0.0018153414 | N51: =M51 -> 0.0018153414 | O51: =N51 -> 0.0018153414 | P51: =O51 -> 0.0018153414 | Q51: =P51 -> 0.0018153414
B53: Current liabilities
B54: =Balance_sheet!B67 -> Borrowings | C54: =Balance_sheet!C67 -> 54223 | D54: =Balance_sheet!D67 -> 48037.8 | E54: =Balance_sheet!E67 -> 21235.6 | F54: =Balance_sheet!F67 -> 42425.6 | G54: =Balance_sheet!G67 -> 41803.2 | H54: =H55*'Revenue Build_up'!H$10 -> 52040.675 | I54: =I55*'Revenue Build_up'!I$10 -> 56212.968 | J54: =J55*'Revenue Build_up'!J$10 -> 60986.754 | K54: =K55*'Revenue Build_up'!K$10 -> 66475.8 | L54: =L55*'Revenue Build_up'!L$10 -> 72817.836 | M54: =M55*'Revenue Build_up'!M$10 -> 80179.819 | N54: =N55*'Revenue Build_up'!N$10 -> 88764.378 | O54: =O55*'Revenue Build_up'!O$10 -> 98817.695 | ... Q54: =Q55*'Revenue Build_up'!Q$10 -> 124593.21
B55: % of Revenue | C55: =C54/'Revenue Build_up'!C$10 -> 0.23474674 | D55: =D54/'Revenue Build_up'!D$10 -> 0.19389924 | E55: =E54/'Revenue Build_up'!E$10 -> 0.090535734 | F55: =F54/'Revenue Build_up'!F$10 -> 0.17068981 | G55: =G54/'Revenue Build_up'!G$10 -> 0.14413967 | H55: =AVERAGE(C55:G55) -> 0.16680224 | I55: =H55 -> 0.16680224 | J55: =I55 -> 0.16680224 | K55: =J55 -> 0.16680224 | L55: =K55 -> 0.16680224 | M55: =L55 -> 0.16680224 | N55: =M55 -> 0.16680224 | O55: =N55 -> 0.16680224 | P55: =O55 -> 0.16680224 | Q55: =P55 -> 0.16680224
B56: =Balance_sheet!B68 -> Lease liabilities | C56: =Balance_sheet!C68 -> 0 | D56: =Balance_sheet!D68 -> 1006.2 | E56: =Balance_sheet!E68 -> 1598.9 | F56: =Balance_sheet!F68 -> 1031.6 | G56: =Balance_sheet!G68 -> 798.8 | H56: =H57*'Revenue Build_up'!H$10 -> 1109.6165 | I56: =I57*'Revenue Build_up'!I$10 -> 1198.5785 | J56: =J57*'Revenue Build_up'!J$10 -> 1300.3657 | K56: =K57*'Revenue Build_up'!K$10 -> 1417.4036 | L56: =L57*'Revenue Build_up'!L$10 -> 1552.6292 | M56: =M57*'Revenue Build_up'!M$10 -> 1709.6021 | N56: =N57*'Revenue Build_up'!N$10 -> 1892.6429 | O56: =O57*'Revenue Build_up'!O$10 -> 2107.0007 | ... Q56: =Q57*'Revenue Build_up'!Q$10 -> 2656.589
B57: % of Revenue | C57: =C56/'Revenue Build_up'!C$10 -> 0 | D57: =D56/'Revenue Build_up'!D$10 -> 0.0040614145 | E57: =E56/'Revenue Build_up'!E$10 -> 0.006816741 | F57: =F56/'Revenue Build_up'!F$10 -> 0.0041504093 | G57: =G56/'Revenue Build_up'!G$10 -> 0.0027543052 | H57: =AVERAGE(C57:G57) -> 0.003556574 | I57: =H57 -> 0.003556574 | J57: =I57 -> 0.003556574 | K57: =J57 -> 0.003556574 | L57: =K57 -> 0.003556574 | M57: =L57 -> 0.003556574 | N57: =M57 -> 0.003556574 | O57: =N57 -> 0.003556574 | P57: =O57 -> 0.003556574 | Q57: =P57 -> 0.003556574
B58: =Balance_sheet!B72 -> Other financial liabilities | C58: =Balance_sheet!C72 -> 22386.9 | D58: =Balance_sheet!D72 -> 20275 | E58: =Balance_sheet!E72 -> 17746.5 | F58: =Balance_sheet!F72 -> 17213.7 | G58: =Balance_sheet!G72 -> 21015.9 | H58: =H59*'Revenue Build_up'!H$10 -> 24718.161 | I58: =I59*'Revenue Build_up'!I$10 -> 26699.907 | J58: =J59*'Revenue Build_up'!J$10 -> 28967.349 | K58: =K59*'Revenue Build_up'!K$10 -> 31574.523 | L58: =L59*'Revenue Build_up'!L$10 -> 34586.849 | M58: =M59*'Revenue Build_up'!M$10 -> 38083.627 | N58: =N59*'Revenue Build_up'!N$10 -> 42161.1 | O58: =O59*'Revenue Build_up'!O$10 -> 46936.202 | ... Q58: =Q59*'Revenue Build_up'!Q$10 -> 59178.999
B59: % of Revenue | C59: =C58/'Revenue Build_up'!C$10 -> 0.096919239 | D59: =D58/'Revenue Build_up'!D$10 -> 0.081837784 | E59: =E58/'Revenue Build_up'!E$10 -> 0.075660325 | F59: =F58/'Revenue Build_up'!F$10 -> 0.069255429 | G59: =G58/'Revenue Build_up'!G$10 -> 0.072463948 | H59: =AVERAGE(C59:G59) -> 0.079227345 | I59: =H59 -> 0.079227345 | J59: =I59 -> 0.079227345 | K59: =J59 -> 0.079227345 | L59: =K59 -> 0.079227345 | M59: =L59 -> 0.079227345 | N59: =M59 -> 0.079227345 | O59: =N59 -> 0.079227345 | P59: =O59 -> 0.079227345 | Q59: =P59 -> 0.079227345
B60: =Balance_sheet!B73 -> Other current liabilities | C60: =Balance_sheet!C73 -> 6358.7 | D60: =Balance_sheet!D73 -> 5561.9 | E60: =Balance_sheet!E73 -> 11662.4 | F60: =Balance_sheet!F73 -> 11432.5 | G60: =Balance_sheet!G73 -> 8773.8 | H60: =H61*'Revenue Build_up'!H$10 -> 10978.852 | I60: =I61*'Revenue Build_up'!I$10 -> 11859.067 | J60: =J61*'Revenue Build_up'!J$10 -> 12866.177 | K60: =K61*'Revenue Build_up'!K$10 -> 14024.183 | L60: =L61*'Revenue Build_up'!L$10 -> 15362.142 | M60: =M61*'Revenue Build_up'!M$10 -> 16915.275 | N60: =N61*'Revenue Build_up'!N$10 -> 18726.332 | O60: =O61*'Revenue Build_up'!O$10 -> 20847.247 | ... Q60: =Q61*'Revenue Build_up'!Q$10 -> 26285.025
B61: % of Revenue | C61: =C60/'Revenue Build_up'!C$10 -> 0.027528615 | D61: =D60/'Revenue Build_up'!D$10 -> 0.022449991 | E61: =E60/'Revenue Build_up'!E$10 -> 0.049721409 | F61: =F60/'Revenue Build_up'!F$10 -> 0.045996078 | G61: =G60/'Revenue Build_up'!G$10 -> 0.030252532 | H61: =AVERAGE(C61:G61) -> 0.035189725 | I61: =H61 -> 0.035189725 | J61: =I61 -> 0.035189725 | K61: =J61 -> 0.035189725 | L61: =K61 -> 0.035189725 | M61: =L61 -> 0.035189725 | N61: =M61 -> 0.035189725 | O61: =N61 -> 0.035189725 | P61: =O61 -> 0.035189725 | Q61: =P61 -> 0.035189725
B62: =Balance_sheet!B74 -> Provisions | C62: =Balance_sheet!C74 -> 4166.4 | D62: =Balance_sheet!D74 -> 1719.3 | E62: =Balance_sheet!E74 -> 1705.6 | F62: =Balance_sheet!F74 -> 2005.3 | G62: =Balance_sheet!G74 -> 2567.9 | H62: =H63*'Revenue Build_up'!H$10 -> 3068.1787 | I62: =I63*'Revenue Build_up'!I$10 -> 3314.1658 | J62: =J63*'Revenue Build_up'!J$10 -> 3595.6155 | K62: =K63*'Revenue Build_up'!K$10 -> 3919.2349 | L62: =L63*'Revenue Build_up'!L$10 -> 4293.1443 | M62: =M63*'Revenue Build_up'!M$10 -> 4727.1871 | N62: =N63*'Revenue Build_up'!N$10 -> 5233.3096 | O62: =O63*'Revenue Build_up'!O$10 -> 5826.0263 | ... Q62: =Q63*'Revenue Build_up'!Q$10 -> 7345.6818
B63: % of Revenue | C63: =C62/'Revenue Build_up'!C$10 -> 0.018037527 | D63: =D62/'Revenue Build_up'!D$10 -> 0.0069397634 | E63: =E62/'Revenue Build_up'!E$10 -> 0.0072716451 | F63: =F62/'Revenue Build_up'!F$10 -> 0.008067871 | G63: =G62/'Revenue Build_up'!G$10 -> 0.0088542566 | H63: =AVERAGE(C63:G63) -> 0.0098342127 | I63: =H63 -> 0.0098342127 | J63: =I63 -> 0.0098342127 | K63: =J63 -> 0.0098342127 | L63: =K63 -> 0.0098342127 | M63: =L63 -> 0.0098342127 | N63: =M63 -> 0.0098342127 | O63: =N63 -> 0.0098342127 | P63: =O63 -> 0.0098342127 | Q63: =P63 -> 0.0098342127
B64: =Balance_sheet!B75 -> Current tax liabilities (net) | C64: =Balance_sheet!C75 -> 950.8 | D64: =Balance_sheet!D75 -> 2103.5 | E64: =Balance_sheet!E75 -> 580.3 | F64: =Balance_sheet!F75 -> 2116 | G64: =Balance_sheet!G75 -> 2490.1 | H64: =H65*'Revenue Build_up'!H$10 -> 2007.9769 | I64: =I65*'Revenue Build_up'!I$10 -> 2168.9638 | J64: =J65*'Revenue Build_up'!J$10 -> 2353.1591 | K64: =K65*'Revenue Build_up'!K$10 -> 2564.9526 | L64: =L65*'Revenue Build_up'!L$10 -> 2809.6586 | M64: =M65*'Revenue Build_up'!M$10 -> 3093.7189 | N64: =N65*'Revenue Build_up'!N$10 -> 3424.952 | O64: =O65*'Revenue Build_up'!O$10 -> 3812.8568 | ... Q64: =Q65*'Revenue Build_up'!Q$10 -> 4807.399
B65: % of Revenue | C65: =C64/'Revenue Build_up'!C$10 -> 0.0041162828 | D65: =D64/'Revenue Build_up'!D$10 -> 0.008490544 | E65: =E64/'Revenue Build_up'!E$10 -> 0.0024740477 | F65: =F64/'Revenue Build_up'!F$10 -> 0.0085132474 | G65: =G64/'Revenue Build_up'!G$10 -> 0.0085859981 | H65: =AVERAGE(C65:G65) -> 0.006436024 | I65: =H65 -> 0.006436024 | J65: =I65 -> 0.006436024 | K65: =J65 -> 0.006436024 | L65: =K65 -> 0.006436024 | M65: =L65 -> 0.006436024 | N65: =M65 -> 0.006436024 | O65: =N65 -> 0.006436024 | P65: =O65 -> 0.006436024 | Q65: =P65 -> 0.006436024

Sheet Debt Schedules
B6: Debt Schedules
B8: Particulars | C8: 2020 | D8: =C8+1 -> 2021 | E8: =D8+1 -> 2022 | F8: =E8+1 -> 2023 | G8: =F8+1 -> 2024 | H8: =G8+1 -> 2025 | I8: =H8+1 -> 2026 | J8: =I8+1 -> 2027 | K8: =J8+1 -> 2028 | ... Q8: =P8+1 -> 2034
B10: Opening Balance | D10: =C12 -> 0 | E10: =D12 -> 5353 | F10: =E12 -> 7277.1 | G10: =F12 -> 10436.5 | H10: =G12 -> 24673.1 | I10: =H12 -> 11212.618 | J10: =I12 -> 12111.575 | K10: =J12 -> 13140.129 | ... Q10: =P12 -> 23838.175
B11: New Issuance/ Repayment | E11: =E12-E10 -> 1924.1 | F11: =F12-F10 -> 3159.4 | G11: =G12-G10 -> 14236.6 | H11: =H12-H10 -> -13460.482 | I11: =I12-I10 -> 898.95695 | J11: =J12-J10 -> 1028.5539 | K11: =K12-K10 -> 1182.6629 | L11: =L12-L10 -> 1366.447 | ... Q11: =Q12-Q10 -> 3006.522
B12: Closing Balance | C12: =Balance_sheet!C56+Balance_sheet!C57+Balance_sheet!C68 -> 0 | D12: =Balance_sheet!D56+Balance_sheet!D57+Balance_sheet!D68 -> 5353 | E12: =Balance_sheet!E56+Balance_sheet!E57+Balance_sheet!E68 -> 7277.1 | F12: =Balance_sheet!F56+Balance_sheet!F57+Balance_sheet!F68 -> 10436.5 | G12: =Balance_sheet!G56+Balance_sheet!G57+Balance_sheet!G68 -> 24673.1 | H12: =SUM('BalanceSheet Forecast'!H40,'BalanceSheet Forecast'!H42,'BalanceSheet Forecast'!H56) -> 11212.618 | I12: =SUM('BalanceSheet Forecast'!I40,'BalanceSheet Forecast'!I42,'BalanceSheet Forecast'!I56) -> 12111.575 | J12: =SUM('BalanceSheet Forecast'!J40,'BalanceSheet Forecast'!J42,'BalanceSheet Forecast'!J56) -> 13140.129 | K12: =SUM('BalanceSheet Forecast'!K40,'BalanceSheet Forecast'!K42,'BalanceSheet Forecast'!K56) -> 14322.792 | L12: =SUM('BalanceSheet Forecast'!L40,'BalanceSheet Forecast'!L42,'BalanceSheet Forecast'!L56) -> 15689.239 | M12: =SUM('BalanceSheet Forecast'!M40,'BalanceSheet Forecast'!M42,'BalanceSheet Forecast'!M56) -> 17275.443 | N12: =SUM('BalanceSheet Forecast'!N40,'BalanceSheet Forecast'!N42,'BalanceSheet Forecast'!N56) -> 19125.061 | O12: =SUM('BalanceSheet Forecast'!O40,'BalanceSheet Forecast'!O42,'BalanceSheet Forecast'!O56) -> 21291.136 | ... Q12: =SUM('BalanceSheet Forecast'!Q40,'BalanceSheet Forecast'!Q42,'BalanceSheet Forecast'!Q56) -> 26844.697
B13: Interest rate | D13: =D14/D12 -> 0.13915561 | E13: =E14/E12 -> 0.066839813 | F13: =F14/F12 -> 0.13460451 | G13: =G14/G12 -> 0.11741938 | H13: =AVERAGE(D13:G13) -> 0.11450483 | I13: =H13 -> 0.11450483 | J13: =I13 -> 0.11450483 | K13: =J13 -> 0.11450483 | L13: =K13 -> 0.11450483 | M13: =L13 -> 0.11450483 | N13: =M13 -> 0.11450483 | O13: =N13 -> 0.11450483 | P13: =O13 -> 0.11450483 | Q13: =P13 -> 0.11450483
B14: Interest Expense | D14: ='P&L'!D18 -> 744.9 | E14: ='P&L'!E18 -> 486.4 | F14: ='P&L'!F18 -> 1404.8 | G14: ='P&L'!G18 -> 2897.1 | H14: =AVERAGE(H12,H10)*H13 -> 2054.544 | I14: =AVERAGE(I12,I10)*I13 -> 1335.3664 | J14: =AVERAGE(J12,J10)*J13 -> 1445.7211 | K14: =AVERAGE(K12,K10)*K13 -> 1572.3186 | L14: =AVERAGE(L12,L10)*L13 -> 1718.2613 | M14: =AVERAGE(M12,M10)*M13 -> 1887.3076 | N14: =AVERAGE(N12,N10)*N13 -> 2084.0167 | O14: =AVERAGE(O12,O10)*O13 -> 2313.9249 | ... Q14: =AVERAGE(Q12,Q10)*Q13 -> 2901.7168

Sheet Revenue Build_up
B6: Revenue Build_up
B8: Particulars | C8: 2020 | D8: =C8+1 -> 2021 | E8: =D8+1 -> 2022 | F8: =E8+1 -> 2023 | G8: =F8+1 -> 2024 | H8: =G8+1 -> 2025 | I8: =H8+1 -> 2026 | J8: =I8+1 -> 2027 | K8: =J8+1 -> 2028 | ... Q8: =P8+1 -> 2034
B10: Revenue | C10: ='P&L'!C10 -> 230985.1 | D10: ='P&L'!D10 -> 247746.2 | E10: ='P&L'!E10 -> 234554.9 | F10: ='P&L'!F10 -> 248553.8 | G10: ='P&L'!G10 -> 290018.7 | H10: =H47 -> 311990.27 | I10: =I47 -> 337003.68 | J10: =J47 -> 365623.11 | K10: =K47 -> 398530.62 | L10: =L47 -> 436551.91 | M10: =M47 -> 480687.91 | N10: =N47 -> 532153.39 | O10: =O47 -> 592424.27 | ... Q10: =Q47 -> 746951.69
B11: Y-O-Y Growth | D11: =D10/C10-1 -> 0.072563555 | E11: =E10/D10-1 -> -0.053245216 | F11: =F10/E10-1 -> 0.059682829 | G11: =G10/F10-1 -> 0.16682465 | H11: =H10/G10-1 -> 0.075759147 | I11: =I10/H10-1 -> 0.080173686 | J11: =J10/I10-1 -> 0.084923214 | K11: =K10/J10-1 -> 0.090003903 | ... Q11: =Q10/P10-1 -> 0.12612215
B14: Revenue from external customers
B15: India | C15: 22415.2 | D15: 20138.1 | E15: 26699.8 | F15: 27481.5 | G15: 34019.5 | H15: =G15*(1+H17) -> 38199.056 | I15: =H15*(1+I17) -> 42892.103 | J15: =I15*(1+J17) -> 48161.727 | K15: =J15*(1+K17) -> 54078.764 | L15: =K15*(1+L17) -> 60722.755 | M15: =L15*(1+M17) -> 68183.011 | N15: =M15*(1+N17) -> 76559.817 | O15: =N15*(1+O17) -> 85965.777 | ... Q15: =P15*(1+Q17) -> 108386.45
B16: % of Revenue | C16: =C15/C$10 -> 0.097041757 | D16: =D15/D$10 -> 0.081285202 | E16: =E15/E$10 -> 0.11383177 | F16: =F15/F$10 -> 0.1105656 | G16: =G15/G$10 -> 0.11730106 | H16: =H15/H$10 -> 0.12243669 | I16: =I15/I$10 -> 0.12727488 | J16: =J15/J$10 -> 0.13172506 | ... Q16: =Q15/Q$10 -> 0.14510504
B17: Y-O-Y Growth | D17: =D15/C15-1 -> -0.10158732 | E17: =E15/D15-1 -> 0.32583511 | F17: =F15/E15-1 -> 0.029277373 | G17: =G15/F15-1 -> 0.2379055 | H17: =CHOOSE(Assumptions!$C$9,'Revenue Build_up'!$H$19:$Q$19,'Revenue Build_up'!H20:Q20,'Revenue Build_up'!$H$21:$Q$21) -> 0.12285767 | I17: =CHOOSE(Assumptions!$C$9,'Revenue Build_up'!$H$19:$Q$19,'Revenue Build_up'!I20:R20,'Revenue Build_up'!$H$21:$Q$21) -> 0.12285767 | J17: =CHOOSE(Assumptions!$C$9,'Revenue Build_up'!$H$19:$Q$19,'Revenue Build_up'!J20:S20,'Revenue Build_up'!$H$21:$Q$21) -> 0.12285767 | K17: =CHOOSE(Assumptions!$C$9,'Revenue Build_up'!$H$19:$Q$19,'Revenue Build_up'!K20:T20,'Revenue Build_up'!$H$21:$Q$21) -> 0.12285767 | L17: =CHOOSE(Assumptions!$C$9,'Revenue Build_up'!$H$19:$Q$19,'Revenue Build_up'!L20:U20,'Revenue Build_up'!$H$21:$Q$21) -> 0.12285767 | M17: =CHOOSE(Assumptions!$C$9,'Revenue Build_up'!$H$19:$Q$19,'Revenue Build_up'!M20:V20,'Revenue Build_up'!$H$21:$Q$21) -> 0.12285767 | N17: =CHOOSE(Assumptions!$C$9,'Revenue Build_up'!$H$19:$Q$19,'Revenue Build_up'!N20:W20,'Revenue Build_up'!$H$21:$Q$21) -> 0.12285767 | O17: =CHOOSE(Assumptions!$C$9,'Revenue Build_up'!$H$19:$Q$19,'Revenue Build_up'!O20:X20,'Revenue Build_up'!$H$21:$Q$21) -> 0.12285767 | ... Q17: =CHOOSE(Assumptions!$C$9,'Revenue Build_up'!$H$19:$Q$19,'Revenue Build_up'!Q20:Z20,'Revenue Build_up'!$H$21:$Q$21) -> 0.12285767
B18: Scenario
B19: Best | H19: =H20+5% -> 0.17285767 | I19: =H19 -> 0.17285767 | J19: =I19 -> 0.17285767 | K19: =J19 -> 0.17285767 | L19: =K19 -> 0.17285767 | M19: =L19 -> 0.17285767 | N19: =M19 -> 0.17285767 | O19: =N19 -> 0.17285767 | P19: =O19 -> 0.17285767 | Q19: =P19 -> 0.17285767
B20: Base | H20: =AVERAGE(D17:G17) -> 0.12285767 | I20: =H20 -> 0.12285767 | J20: =I20 -> 0.12285767 | K20: =J20 -> 0.12285767 | L20: =K20 -> 0.12285767 | M20: =L20 -> 0.12285767 | N20: =M20 -> 0.12285767 | O20: =N20 -> 0.12285767 | P20: =O20 -> 0.12285767 | Q20: =P20 -> 0.12285767
B21: Worst | H21: =H20-5% -> 0.072857666 | I21: =H21 -> 0.072857666 | J21: =I21 -> 0.072857666 | K21: =J21 -> 0.072857666 | L21: =K21 -> 0.072857666 | M21: =L21 -> 0.072857666 | N21: =M21 -> 0.072857666 | O21: =N21 -> 0.072857666 | P21: =O21 -> 0.072857666 | Q21: =P21 -> 0.072857666
B23: USA | C23: 116782.6 | D23: 121174.9 | E23: 105208 | F23: 112420.8 | G23: 139804.1 | H23: =G23*(1+H25) -> 147422.71 | I23: =H23*(1+I25) -> 155456.5 | J23: =I23*(1+J25) -> 163928.09 | K23: =J23*(1+K25) -> 172861.33 | L23: =K23*(1+L25) -> 182281.4 | M23: =L23*(1+M25) -> 192214.8 | N23: =M23*(1+N25) -> 202689.53 | O23: =N23*(1+O25) -> 213735.08 | ... Q23: =P23*(1+Q25) -> 237664.76
B24: % of Revenue | C24: =C23/C$10 -> 0.50558499 | D24: =D23/D$10 -> 0.48910902 | E24: =E23/E$10 -> 0.44854318 | F24: =F23/F$10 -> 0.45229966 | G24: =G23/G$10 -> 0.48205202 | H24: =H23/H$10 -> 0.47252343 | I24: =I23/I$10 -> 0.46129021 | J24: =J23/J$10 -> 0.44835264 | ... Q24: =Q23/Q$10 -> 0.31817955
B25: Y-O-Y Growth | D25: =D23/C23-1 -> 0.037610911 | E25: =E23/D23-1 -> -0.13176739 | F25: =F23/E23-1 -> 0.068557524 | G25: =G23/F23-1 -> 0.24357859 | H25: =CHOOSE(Assumptions!$C$9,'Revenue Build_up'!$H$27:$Q$27,'Revenue Build_up'!H28:Q28,'Revenue Build_up'!$H$29:$Q$29) -> 0.05449491 | I25: =CHOOSE(Assumptions!$C$9,'Revenue Build_up'!$H$19:$Q$19,'Revenue Build_up'!I28:R28,'Revenue Build_up'!$H$21:$Q$21) -> 0.05449491 | J25: =CHOOSE(Assumptions!$C$9,'Revenue Build_up'!$H$19:$Q$19,'Revenue Build_up'!J28:S28,'Revenue Build_up'!$H$21:$Q$21) -> 0.05449491 | K25: =CHOOSE(Assumptions!$C$9,'Revenue Build_up'!$H$19:$Q$19,'Revenue Build_up'!K28:T28,'Revenue Build_up'!$H$21:$Q$21) -> 0.05449491 | L25: =CHOOSE(Assumptions!$C$9,'Revenue Build_up'!$H$19:$Q$19,'Revenue Build_up'!L28:U28,'Revenue Build_up'!$H$21:$Q$21) -> 0.05449491 | M25: =CHOOSE(Assumptions!$C$9,'Revenue Build_up'!$H$19:$Q$19,'Revenue Build_up'!M28:V28,'Revenue Build_up'!$H$21:$Q$21) -> 0.05449491 | N25: =CHOOSE(Assumptions!$C$9,'Revenue Build_up'!$H$19:$Q$19,'Revenue Build_up'!N28:W28,'Revenue Build_up'!$H$21:$Q$21) -> 0.05449491 | O25: =CHOOSE(Assumptions!$C$9,'Revenue Build_up'!$H$19:$Q$19,'Revenue Build_up'!O28:X28,'Revenue Build_up'!$H$21:$Q$21) -> 0.05449491 | P25: =CHOOSE(Assumptions!$C$9,'Revenue Build_up'!$H$19:$Q$19,'Revenue Build_up'!P28:Y28,'Revenue Build_up'!$H$21:$Q$21) -> 0.05449491 | Q25: =CHOOSE(Assumptions!$C$9,'Revenue Build_up'!$H$19:$Q$19,'Revenue Build_up'!Q28:Z28,'Revenue Build_up'!$H$21:$Q$21) -> 0.05449491
B26: Scenario
B27: Best | H27: =H28+2% -> 0.07449491 | I27: =H27 -> 0.07449491 | J27: =I27 -> 0.07449491 | K27: =J27 -> 0.07449491 | L27: =K27 -> 0.07449491 | M27: =L27 -> 0.07449491 | N27: =M27 -> 0.07449491 | O27: =N27 -> 0.07449491 | P27: =O27 -> 0.07449491 | Q27: =P27 -> 0.07449491
B28: Base | H28: =AVERAGE(D25:G25) -> 0.05449491 | I28: =H28 -> 0.05449491 | J28: =I28 -> 0.05449491 | K28: =J28 -> 0.05449491 | L28: =K28 -> 0.05449491 | M28: =L28 -> 0.05449491 | N28: =M28 -> 0.05449491 | O28: =N28 -> 0.05449491 | P28: =O28 -> 0.05449491 | Q28: =P28 -> 0.05449491
B29: Worst | H29: =H28-2% -> 0.03449491 | I29: =H29 -> 0.03449491 | J29: =I29 -> 0.03449491 | K29: =J29 -> 0.03449491 | L29: =K29 -> 0.03449491 | M29: =L29 -> 0.03449491 | N29: =M29 -> 0.03449491 | O29: =N29 -> 0.03449491 | P29: =O29 -> 0.03449491 | Q29: =P29 -> 0.03449491
B31: Europe | C31: 72767.6 | D31: 81221.6 | E31: 78812.5 | F31: 72429.9 | G31: 75633.3 | H31: =G31*(1+H33) -> 76574.183 | I31: =H31*(1+I33) -> 77526.77 | J31: =I31*(1+J33) -> 78491.207 | K31: =J31*(1+K33) -> 79467.642 | L31: =K31*(1+L33) -> 80456.224 | M31: =L31*(1+M33) -> 81457.104 | N31: =M31*(1+N33) -> 82470.435 | O31: =N31*(1+O33) -> 83496.372 | ... Q31: =P31*(1+Q33) -> 85586.693
B32: % of Revenue | C32: =C31/C$10 -> 0.31503158 | D32: =D31/D$10 -> 0.32784196 | E32: =E31/E$10 -> 0.33600876 | F32: =F31/F$10 -> 0.29140532 | G32: =G31/G$10 -> 0.26078767 | H32: =H31/H$10 -> 0.24543773 | I32: =I31/I$10 -> 0.23004725 | J32: =J31/J$10 -> 0.21467791 | ... Q32: =Q31/Q$10 -> 0.1145813
B33: Y-O-Y Growth | D33: =D31/C31-1 -> 0.11617808 | E33: =E31/D31-1 -> -0.029660829 | F33: =F31/E31-1 -> -0.080984615 | G33: =G31/F31-1 -> 0.044227591 | H33: =CHOOSE(Assumptions!$C$9,'Revenue Build_up'!$H$27:$Q$27,'Revenue Build_up'!H36:Q36,'Revenue Build_up'!$H$29:$Q$29) -> 0.012440056 | I33: =CHOOSE(Assumptions!$C$9,'Revenue Build_up'!$H$19:$Q$19,'Revenue Build_up'!I36:R36,'Revenue Build_up'!$H$21:$Q$21) -> 0.012440056 | J33: =CHOOSE(Assumptions!$C$9,'Revenue Build_up'!$H$19:$Q$19,'Revenue Build_up'!J36:S36,'Revenue Build_up'!$H$21:$Q$21) -> 0.012440056 | K33: =CHOOSE(Assumptions!$C$9,'Revenue Build_up'!$H$19:$Q$19,'Revenue Build_up'!K36:T36,'Revenue Build_up'!$H$21:$Q$21) -> 0.012440056 | L33: =CHOOSE(Assumptions!$C$9,'Revenue Build_up'!$H$19:$Q$19,'Revenue Build_up'!L36:U36,'Revenue Build_up'!$H$21:$Q$21) -> 0.012440056 | M33: =CHOOSE(Assumptions!$C$9,'Revenue Build_up'!$H$19:$Q$19,'Revenue Build_up'!M36:V36,'Revenue Build_up'!$H$21:$Q$21) -> 0.012440056 | N33: =CHOOSE(Assumptions!$C$9,'Revenue Build_up'!$H$19:$Q$19,'Revenue Build_up'!N36:W36,'Revenue Build_up'!$H$21:$Q$21) -> 0.012440056 | O33: =CHOOSE(Assumptions!$C$9,'Revenue Build_up'!$H$19:$Q$19,'Revenue Build_up'!O36:X36,'Revenue Build_up'!$H$21:$Q$21) -> 0.012440056 | P33: =CHOOSE(Assumptions!$C$9,'Revenue Build_up'!$H$19:$Q$19,'Revenue Build_up'!P36:Y36,'Revenue Build_up'!$H$21:$Q$21) -> 0.012440056 | Q33: =CHOOSE(Assumptions!$C$9,'Revenue Build_up'!$H$19:$Q$19,'Revenue Build_up'!Q36:Z36,'Revenue Build_up'!$H$21:$Q$21) -> 0.012440056
B34: Scenario
B35: Best | H35: =H36+2% -> 0.032440056 | I35: =H35 -> 0.032440056 | J35: =I35 -> 0.032440056 | K35: =J35 -> 0.032440056 | L35: =K35 -> 0.032440056 | M35: =L35 -> 0.032440056 | N35: =M35 -> 0.032440056 | O35: =N35 -> 0.032440056 | P35: =O35 -> 0.032440056 | Q35: =P35 -> 0.032440056
B36: Base | H36: =AVERAGE(D33:G33) -> 0.012440056 | I36: =H36 -> 0.012440056 | J36: =I36 -> 0.012440056 | K36: =J36 -> 0.012440056 | L36: =K36 -> 0.012440056 | M36: =L36 -> 0.012440056 | N36: =M36 -> 0.012440056 | O36: =N36 -> 0.012440056 | P36: =O36 -> 0.012440056 | Q36: =P36 -> 0.012440056
B37: Worst | H37: =H36-2% -> -0.0075599435 | I37: =H37 -> -0.0075599435 | J37: =I37 -> -0.0075599435 | K37: =J37 -> -0.0075599435 | L37: =K37 -> -0.0075599435 | M37: =L37 -> -0.0075599435 | N37: =M37 -> -0.0075599435 | O37: =N37 -> -0.0075599435 | P37: =O37 -> -0.0075599435 | Q37: =P37 -> -0.0075599435
B39: Rest of the world | C39: 19019.7 | D39: 25211.6 | E39: 23834.6 | F39: 36221.6 | G39: 40561.8 | H39: =G39*(1+H41) -> 49794.319 | I39: =H39*(1+I41) -> 61128.307 | J39: =I39*(1+J41) -> 75042.094 | K39: =J39*(1+K41) -> 92122.882 | L39: =K39*(1+L41) -> 113091.53 | M39: =L39*(1+M41) -> 138832.99 | N39: =M39*(1+N41) -> 170433.61 | O39: =N39*(1+O41) -> 209227.04 | ... Q39: =P39*(1+Q41) -> 315313.79
B40: % of Revenue | C40: =C39/C$10 -> 0.082341675 | D40: =D39/D$10 -> 0.10176382 | E40: =E39/E$10 -> 0.1016163 | F40: =F39/F$10 -> 0.14572942 | G40: =G39/G$10 -> 0.13985926 | H40: =H39/H$10 -> 0.15960215 | I40: =I39/I$10 -> 0.18138765 | J40: =J39/J$10 -> 0.20524439 | ... Q40: =Q39/Q$10 -> 0.42213411
B41: Y-O-Y Growth | D41: =D39/C39-1 -> 0.32555193 | E41: =E39/D39-1 -> -0.054617716 | F41: =F39/E39-1 -> 0.51970664 | G41: =G39/F39-1 -> 0.11982353 | H41: =CHOOSE(Assumptions!$C$9,'Revenue Build_up'!$H$43:$Q$43,'Revenue Build_up'!H44:Q44,'Revenue Build_up'!$H$45:$Q$45) -> 0.2276161 | I41: =CHOOSE(Assumptions!$C$9,'Revenue Build_up'!$H$43:$Q$43,'Revenue Build_up'!I44:R44,'Revenue Build_up'!$H$45:$Q$45) -> 0.2276161 | J41: =CHOOSE(Assumptions!$C$9,'Revenue Build_up'!$H$43:$Q$43,'Revenue Build_up'!J44:S44,'Revenue Build_up'!$H$45:$Q$45) -> 0.2276161 | K41: =CHOOSE(Assumptions!$C$9,'Revenue Build_up'!$H$43:$Q$43,'Revenue Build_up'!K44:T44,'Revenue Build_up'!$H$45:$Q$45) -> 0.2276161 | L41: =CHOOSE(Assumptions!$C$9,'Revenue Build_up'!$H$43:$Q$43,'Revenue Build_up'!L44:U44,'Revenue Build_up'!$H$45:$Q$45) -> 0.2276161 | M41: =CHOOSE(Assumptions!$C$9,'Revenue Build_up'!$H$43:$Q$43,'Revenue Build_up'!M44:V44,'Revenue Build_up'!$H$45:$Q$45) -> 0.2276161 | N41: =CHOOSE(Assumptions!$C$9,'Revenue Build_up'!$H$43:$Q$43,'Revenue Build_up'!N44:W44,'Revenue Build_up'!$H$45:$Q$45) -> 0.2276161 | O41: =CHOOSE(Assumptions!$C$9,'Revenue Build_up'!$H$43:$Q$43,'Revenue Build_up'!O44:X44,'Revenue Build_up'!$H$45:$Q$45) -> 0.2276161 | ... Q41: =CHOOSE(Assumptions!$C$9,'Revenue Build_up'!$H$43:$Q$43,'Revenue Build_up'!Q44:Z44,'Revenue Build_up'!$H$45:$Q$45) -> 0.2276161
B42: Scenario
B43: Best | H43: =H44+5% -> 0.2776161 | I43: =H43 -> 0.2776161 | J43: =I43 -> 0.2776161 | K43: =J43 -> 0.2776161 | L43: =K43 -> 0.2776161 | M43: =L43 -> 0.2776161 | N43: =M43 -> 0.2776161 | O43: =N43 -> 0.2776161 | P43: =O43 -> 0.2776161 | Q43: =P43 -> 0.2776161
B44: Base | H44: =AVERAGE(D41:G41) -> 0.2276161 | I44: =H44 -> 0.2276161 | J44: =I44 -> 0.2276161 | K44: =J44 -> 0.2276161 | L44: =K44 -> 0.2276161 | M44: =L44 -> 0.2276161 | N44: =M44 -> 0.2276161 | O44: =N44 -> 0.2276161 | P44: =O44 -> 0.2276161 | Q44: =P44 -> 0.2276161
B45: Worst | H45: =H44-5% -> 0.1776161 | I45: =H45 -> 0.1776161 | J45: =I45 -> 0.1776161 | K45: =J45 -> 0.1776161 | L45: =K45 -> 0.1776161 | M45: =L45 -> 0.1776161 | N45: =M45 -> 0.1776161 | O45: =N45 -> 0.1776161 | P45: =O45 -> 0.1776161 | Q45: =P45 -> 0.1776161
B47: Total Revenue | C47: =SUM(C15,C23,C31,C39) -> 230985.1 | D47: =SUM(D15,D23,D31,D39) -> 247746.2 | E47: =SUM(E15,E23,E31,E39) -> 234554.9 | F47: =SUM(F15,F23,F31,F39) -> 248553.8 | G47: =SUM(G15,G23,G31,G39) -> 290018.7 | H47: =SUM(H39,H31,H23,H15) -> 311990.27 | I47: =SUM(I15,I23,I31,I39) -> 337003.68 | J47: =SUM(J15,J23,J31,J39) -> 365623.11 | K47: =SUM(K15,K23,K31,K39) -> 398530.62 | L47: =SUM(L15,L23,L31,L39) -> 436551.91 | M47: =SUM(M15,M23,M31,M39) -> 480687.91 | N47: =SUM(N15,N23,N31,N39) -> 532153.39 | O47: =SUM(O15,O23,O31,O39) -> 592424.27 | P47: =SUM(P15,P23,P31,P39) -> 663295.44 | Q47: =SUM(Q15,Q23,Q31,Q39) -> 746951.69

Sheet Cost Build_Up
B6: Cost Build_up
B8: Particulars | C8: 2020 | D8: =C8+1 -> 2021 | E8: =D8+1 -> 2022 | F8: =E8+1 -> 2023 | G8: =F8+1 -> 2024 | H8: =G8+1 -> 2025 | I8: =H8+1 -> 2026 | J8: =I8+1 -> 2027 | K8: =J8+1 -> 2028 | ... Q8: =P8+1 -> 2034
B10: Revenue | C10: ='Revenue Build_up'!C10 -> 230985.1 | D10: ='Revenue Build_up'!D10 -> 247746.2 | E10: ='Revenue Build_up'!E10 -> 234554.9 | F10: ='Revenue Build_up'!F10 -> 248553.8 | G10: ='Revenue Build_up'!G10 -> 290018.7 | H10: ='Revenue Build_up'!H10 -> 311990.27 | I10: ='Revenue Build_up'!I10 -> 337003.68 | J10: ='Revenue Build_up'!J10 -> 365623.11 | ... Q10: ='Revenue Build_up'!Q10 -> 746951.69
B12: COGS | C12: =SUM('P&L'!C14:C16) -> 97352.3 | D12: =SUM('P&L'!D14:D16) -> 99024.7 | E12: =SUM('P&L'!E14:E16) -> 101402.8 | F12: =SUM('P&L'!F14:F16) -> 112932.6 | G12: =SUM('P&L'!G14:G16) -> 126029 | H12: =H10*H13 -> 133681.69 | I12: =I10*I13 -> 144399.44 | J12: =J10*J13 -> 156662.3 | K12: =K10*K13 -> 170762.52 | L12: =L10*L13 -> 187053.9 | M12: =M10*M13 -> 205965.3 | N12: =N10*N13 -> 228017.25 | O12: =O10*O13 -> 253842.13 | ... Q12: =Q10*Q13 -> 320054.09
B13: % of Revenue | C13: =C12/C10 -> 0.42146571 | D13: =D12/D10 -> 0.3997022 | E13: =E12/E10 -> 0.43232011 | F13: =F12/F10 -> 0.45435877 | G13: =G12/G10 -> 0.43455474 | H13: =AVERAGE(C13:G13) -> 0.42848031 | I13: =H13 -> 0.42848031 | J13: =I13 -> 0.42848031 | K13: =J13 -> 0.42848031 | L13: =K13 -> 0.42848031 | M13: =L13 -> 0.42848031 | N13: =M13 -> 0.42848031 | O13: =N13 -> 0.42848031 | P13: =O13 -> 0.42848031 | Q13: =P13 -> 0.42848031
B15: Gross Margin | C15: =(C10-C12)/C10 -> 0.57853429 | D15: =(D10-D12)/D10 -> 0.6002978 | E15: =(E10-E12)/E10 -> 0.56767989 | F15: =(F10-F12)/F10 -> 0.54564123 | G15: =(G10-G12)/G10 -> 0.56544526 | H15: =(H10-H12)/H10 -> 0.57151969 | I15: =(I10-I12)/I10 -> 0.57151969 | J15: =(J10-J12)/J10 -> 0.57151969 | ... Q15: =(Q10-Q12)/Q10 -> 0.57151969
B17: OPEX
B18: ='P&L'!B17 -> Employee benefits expense | C18: ='P&L'!C17 -> 32191.8 | D18: ='P&L'!D17 -> 35350.2 | E18: ='P&L'!E17 -> 34509.2 | F18: ='P&L'!F17 -> 35222.5 | G18: ='P&L'!G17 -> 39229.4 | H18: =H19*H10 -> 44062.744 | I18: =I19*I10 -> 47595.417 | J18: =J19*J10 -> 51637.372 | K18: =K19*K10 -> 56284.937 | L18: =L19*L10 -> 61654.727 | M18: =M19*M10 -> 67888.105 | N18: =N19*N10 -> 75156.635 | O18: =O19*O10 -> 83668.76 | ... Q18: =Q19*Q10 -> 105492.85
B19: % of Revenue | C19: =C18/C10 -> 0.13936743 | D19: =D18/D10 -> 0.14268715 | E19: =E18/E10 -> 0.14712632 | F19: =F18/F10 -> 0.14170976 | G19: =G18/G10 -> 0.13526507 | H19: =AVERAGE(C19:G19) -> 0.14123115 | I19: =H19 -> 0.14123115 | J19: =I19 -> 0.14123115 | K19: =J19 -> 0.14123115 | L19: =K19 -> 0.14123115 | M19: =L19 -> 0.14123115 | N19: =M19 -> 0.14123115 | O19: =N19 -> 0.14123115 | P19: =O19 -> 0.14123115 | Q19: =P19 -> 0.14123115
B21: ='P&L'!B20 -> Other expenses | C21: ='P&L'!C20 -> 52797.9 | D21: ='P&L'!D20 -> 60037.3 | E21: ='P&L'!E20 -> 54775.2 | F21: ='P&L'!F20 -> 63212.3 | G21: ='P&L'!G20 -> 66330.3 | H21: =H22*H10 -> 74095.821 | I21: =I22*I10 -> 80036.356 | J21: =J22*J10 -> 86833.3 | K21: =K22*K10 -> 94648.636 | L21: =L22*L10 -> 103678.46 | M21: =M22*M10 -> 114160.5 | N21: =N22*N10 -> 126383.24 | O21: =O22*O10 -> 140697.22 | ... Q21: =Q22*Q10 -> 177396.55
B22: % of Revenue | C22: =C21/C10 -> 0.22857708 | D22: =D21/D10 -> 0.24233389 | E22: =E21/E10 -> 0.23352827 | F22: =F21/F10 -> 0.25432039 | G22: =G21/G10 -> 0.22871042 | H22: =AVERAGE(C22:G22) -> 0.23749401 | I22: =H22 -> 0.23749401 | J22: =I22 -> 0.23749401 | K22: =J22 -> 0.23749401 | L22: =K22 -> 0.23749401 | M22: =L22 -> 0.23749401 | N22: =M22 -> 0.23749401 | O22: =N22 -> 0.23749401 | P22: =O22 -> 0.23749401 | Q22: =P22 -> 0.23749401
B24: OPEX | C24: =C21+C18 -> 84989.7 | D24: =D21+D18 -> 95387.5 | E24: =E21+E18 -> 89284.4 | F24: =F21+F18 -> 98434.8 | G24: =G21+G18 -> 105559.7 | H24: =H21+H18 -> 118158.56 | I24: =I21+I18 -> 127631.77 | J24: =J21+J18 -> 138470.67 | ... Q24: =Q21+Q18 -> 282889.4
B27: Other Income | C27: ='P&L'!C11 -> 1918.7 | D27: ='P&L'!D11 -> 3808.5 | E27: ='P&L'!E11 -> 3203.5 | F27: ='P&L'!F11 -> 2905.9 | G27: ='P&L'!G11 -> 5573.8 | H27: =H28*H10 -> 4258.4774 | I27: =I28*I10 -> 4599.8952 | J27: =J28*J10 -> 4990.5331 | K27: =K28*K10 -> 5439.7006 | L27: =L28*L10 -> 5958.668 | M27: =M28*M10 -> 6561.0975 | N27: =N28*N10 -> 7263.5701 | O27: =O28*O10 -> 8086.231 | ... Q27: =Q28*Q10 -> 10195.436
B28: % of Revenue | C28: =C27/C10 -> 0.0083065964 | D28: =D27/D10 -> 0.015372587 | E28: =E27/E10 -> 0.013657783 | F28: =F27/F10 -> 0.011691231 | G28: =G27/G10 -> 0.019218761 | H28: =AVERAGE(C28:G28) -> 0.013649392 | I28: =H28 -> 0.013649392 | J28: =I28 -> 0.013649392 | K28: =J28 -> 0.013649392 | L28: =K28 -> 0.013649392 | M28: =L28 -> 0.013649392 | N28: =M28 -> 0.013649392 | O28: =N28 -> 0.013649392 | P28: =O28 -> 0.013649392 | Q28: =P28 -> 0.013649392
B31: Exceptional Items | C31: ='P&L'!C26 -> 261.3 | D31: ='P&L'!D26 -> -28145.8 | E31: ='P&L'!E26 -> 1279.7 | F31: ='P&L'!F26 -> 0 | G31: ='P&L'!G26 -> 1918.6 | H31: =H32*H10 -> -6265.0673 | I31: =I32*I10 -> -6767.3608 | J31: =J32*J10 -> -7342.0668 | K31: =K32*K10 -> -8002.8815 | L31: =L32*L10 -> -8766.3858 | M31: =M32*M10 -> -9652.6795 | N31: =N32*N10 -> -10686.156 | O31: =O32*O10 -> -11896.454 | ... Q31: =Q32*Q10 -> -14999.515
B32: % of Revenue | C32: =C31/C10 -> 0.0011312418 | D32: =D31/D10 -> -0.11360739 | E32: =E31/E10 -> 0.0054558656 | F32: =F31/F10 -> 0 | G32: =G31/G10 -> 0.0066154355 | H32: =AVERAGE(C32:G32) -> -0.02008097 | I32: =H32 -> -0.02008097 | J32: =I32 -> -0.02008097 | K32: =J32 -> -0.02008097 | L32: =K32 -> -0.02008097 | M32: =L32 -> -0.02008097 | N32: =M32 -> -0.02008097 | O32: =N32 -> -0.02008097 | P32: =O32 -> -0.02008097 | Q32: =P32 -> -0.02008097
B34: Share of loss of joint ventures and associates (net of tax) | C34: ='P&L'!C24 -> -151.7 | D34: ='P&L'!D24 -> -553.6 | E34: ='P&L'!E24 -> -312.5 | F34: ='P&L'!F24 -> -116.7 | G34: ='P&L'!G24 -> -171.6 | H34: =H35*H10 -> -329.76185 | I34: =I35*I10 -> -356.20008 | J34: =J35*J10 -> -386.44973 | K34: =K35*K10 -> -421.23172 | L34: =L35*L10 -> -461.41877 | M34: =M35*M10 -> -508.06884 | N34: =N35*N10 -> -562.46591 | O34: =O35*O10 -> -626.16993 | ... Q34: =Q35*Q10 -> -789.49954
B35: % of Revenue | C35: =C34/C10 -> -0.00065675232 | D35: =D34/D10 -> -0.0022345449 | E35: =E34/E10 -> -0.0013323107 | F35: =F34/F10 -> -0.00046951606 | G35: =G34/G10 -> -0.00059168598 | H35: =AVERAGE($C$35:$G$35) -> -0.001056962 | I35: =AVERAGE($C$35:$G$35) -> -0.001056962 | J35: =AVERAGE($C$35:$G$35) -> -0.001056962 | K35: =AVERAGE($C$35:$G$35) -> -0.001056962 | L35: =AVERAGE($C$35:$G$35) -> -0.001056962 | M35: =AVERAGE($C$35:$G$35) -> -0.001056962 | N35: =AVERAGE($C$35:$G$35) -> -0.001056962 | O35: =AVERAGE($C$35:$G$35) -> -0.001056962 | ... Q35: =AVERAGE($C$35:$G$35) -> -0.001056962
B37: Tax | C37: ='P&L'!C28 -> -8993.5 | D37: ='P&L'!D28 -> -20097.7 | E37: ='P&L'!E28 -> -7256.3 | F37: ='P&L'!F28 -> -6848.5 | G37: ='P&L'!G28 -> -12110.2 | H37: =-H38*'Income Statement'!H30 -> -12514.973 | I37: =-I38*'Income Statement'!I30 -> -12309.152 | J37: =-J38*'Income Statement'!J30 -> -13536.31 | K37: =-K38*'Income Statement'!K30 -> -14937.087 | L37: =-L38*'Income Statement'!L30 -> -16555.79 | M37: =-M38*'Income Statement'!M30 -> -18444.302 | N37: =-N38*'Income Statement'!N30 -> -20664.296 | O37: =-O38*'Income Statement'!O30 -> -23289.809 | ... Q37: =-Q38*'Income Statement'!Q30 -> -30134.477
B38: % of EBT | C38: =-C37/'P&L'!C27 -> 0.24027261 | D38: =-D37/'P&L'!D27 -> 0.27367677 | E38: =-E37/'P&L'!E27 -> 0.21514555 | F38: =-F37/'P&L'!F27 -> 0.26214354 | G38: =-G37/'P&L'!G27 -> 0.27648922 | H38: =AVERAGE(C38:G38) -> 0.25354554 | I38: =H38 -> 0.25354554 | J38: =I38 -> 0.25354554 | K38: =J38 -> 0.25354554 | L38: =K38 -> 0.25354554 | M38: =L38 -> 0.25354554 | N38: =M38 -> 0.25354554 | O38: =N38 -> 0.25354554 | P38: =O38 -> 0.25354554 | Q38: =P38 -> 0.25354554

Sheet Working Capital
B6: Working Capital
B8: Particulars | C8: 2020 | D8: =C8+1 -> 2021 | E8: =D8+1 -> 2022 | F8: =E8+1 -> 2023 | G8: =F8+1 -> 2024 | H8: =G8+1 -> 2025 | I8: =H8+1 -> 2026 | J8: =I8+1 -> 2027 | K8: =J8+1 -> 2028 | ... Q8: =P8+1 -> 2034
B9: Days of Operation | C9: 365 | D9: 365 | E9: 365 | F9: 365 | G9: 365 | H9: 365 | I9: 365 | J9: 365 | K9: 365 | L9: 365 | M9: 365 | N9: 365 | O9: 365 | P9: 365 | Q9: 365
B11: Inventories | C11: =Balance_sheet!C29 -> 76998.7 | D11: =Balance_sheet!D29 -> 90265.7 | E11: =Balance_sheet!E29 -> 75538.5 | F11: =Balance_sheet!F29 -> 85112.3 | G11: =Balance_sheet!G29 -> 98082.3 | H11: =H17*'Cost Build_Up'!H12/'Working Capital'!H9 -> 106392.4 | I11: =I17*'Cost Build_Up'!I12/'Working Capital'!I9 -> 114922.27 | J11: =J17*'Cost Build_Up'!J12/'Working Capital'!J9 -> 124681.84 | K11: =K17*'Cost Build_Up'!K12/'Working Capital'!K9 -> 135903.69 | L11: =L17*'Cost Build_Up'!L12/'Working Capital'!L9 -> 148869.4 | M11: =M17*'Cost Build_Up'!M12/'Working Capital'!M9 -> 163920.3 | N11: =N17*'Cost Build_Up'!N12/'Working Capital'!N9 -> 181470.64 | O11: =O17*'Cost Build_Up'!O12/'Working Capital'!O9 -> 202023.73 | ... Q11: =Q17*'Cost Build_Up'!Q12/'Working Capital'!Q9 -> 254719.42
B12: Trade receivables | C12: =Balance_sheet!C32 -> 43151.6 | D12: =Balance_sheet!D32 -> 35032.8 | E12: =Balance_sheet!E32 -> 40122.6 | F12: =Balance_sheet!F32 -> 44663.8 | G12: =Balance_sheet!G32 -> 48167.4 | H12: =H18*'Cost Build_Up'!H10/'Working Capital'!H9 -> 52730.003 | I12: =I18*'Cost Build_Up'!I10/'Working Capital'!I9 -> 56957.561 | J12: =J18*'Cost Build_Up'!J10/'Working Capital'!J9 -> 61794.58 | K12: =K18*'Cost Build_Up'!K10/'Working Capital'!K9 -> 67356.334 | L12: =L18*'Cost Build_Up'!L10/'Working Capital'!L9 -> 73782.376 | M12: =M18*'Cost Build_Up'!M10/'Working Capital'!M9 -> 81241.875 | N12: =N18*'Cost Build_Up'!N10/'Working Capital'!N9 -> 89940.144 | O12: =O18*'Cost Build_Up'!O10/'Working Capital'!O9 -> 100126.63 | ... Q12: =Q18*'Cost Build_Up'!Q10/'Working Capital'!Q9 -> 126243.57
B13: Trade payables | C13: =Balance_sheet!C70+Balance_sheet!C71 -> 25760.6 | D13: =Balance_sheet!D70+Balance_sheet!D71 -> 27946.8 | E13: =Balance_sheet!E70+Balance_sheet!E71 -> 27030.5 | F13: =Balance_sheet!F70+Balance_sheet!F71 -> 38713.1 | G13: =Balance_sheet!G70+Balance_sheet!G71 -> 44541.6 | H13: =H19*'Cost Build_Up'!H12/'Working Capital'!H9 -> 40361.708 | I13: =I19*'Cost Build_Up'!I12/'Working Capital'!I9 -> 43597.655 | J13: =J19*'Cost Build_Up'!J12/'Working Capital'!J9 -> 47300.108 | K13: =K19*'Cost Build_Up'!K12/'Working Capital'!K9 -> 51557.302 | L13: =L19*'Cost Build_Up'!L12/'Working Capital'!L9 -> 56476.058 | M13: =M19*'Cost Build_Up'!M12/'Working Capital'!M9 -> 62185.865 | N13: =N19*'Cost Build_Up'!N12/'Working Capital'!N9 -> 68843.877 | O13: =O19*'Cost Build_Up'!O12/'Working Capital'!O9 -> 76641.029 | ... Q13: =Q19*'Cost Build_Up'!Q12/'Working Capital'!Q9 -> 96632.007
B16: KPI
B17: DIO | C17: =C11/'Cost Build_Up'!C12*'Working Capital'!C9 -> 288.68887 | D17: =D11/'Cost Build_Up'!D12*'Working Capital'!D9 -> 332.71477 | E17: =E11/'Cost Build_Up'!E12*'Working Capital'!E9 -> 271.90129 | F17: =F11/'Cost Build_Up'!F12*'Working Capital'!F9 -> 275.08434 | G17: =G11/'Cost Build_Up'!G12*'Working Capital'!G9 -> 284.06192 | H17: =AVERAGE(C17:G17) -> 290.49024 | I17: =H17 -> 290.49024 | J17: =I17 -> 290.49024 | K17: =J17 -> 290.49024 | L17: =K17 -> 290.49024 | M17: =L17 -> 290.49024 | N17: =M17 -> 290.49024 | O17: =N17 -> 290.49024 | P17: =O17 -> 290.49024 | Q17: =P17 -> 290.49024
B18: DSO | C18: =C12/'Cost Build_Up'!C10*'Working Capital'!C9 -> 68.187662 | D18: =D12/'Cost Build_Up'!D10*'Working Capital'!D9 -> 51.613191 | E18: =E12/'Cost Build_Up'!E10*'Working Capital'!E9 -> 62.436338 | F18: =F12/'Cost Build_Up'!F10*'Working Capital'!F9 -> 65.588565 | G18: =G12/'Cost Build_Up'!G10*'Working Capital'!G9 -> 60.620577 | H18: =AVERAGE(C18:G18) -> 61.689267 | I18: =H18 -> 61.689267 | J18: =I18 -> 61.689267 | K18: =J18 -> 61.689267 | L18: =K18 -> 61.689267 | M18: =L18 -> 61.689267 | N18: =M18 -> 61.689267 | O18: =N18 -> 61.689267 | P18: =O18 -> 61.689267 | Q18: =P18 -> 61.689267
B19: DPO | C19: =C13/'Cost Build_Up'!C12*'Working Capital'!C9 -> 96.583429 | D19: =D13/'Cost Build_Up'!D12*'Working Capital'!D9 -> 103.01048 | E19: =E13/'Cost Build_Up'!E12*'Working Capital'!E9 -> 97.29645 | F19: =F13/'Cost Build_Up'!F12*'Working Capital'!F9 -> 125.12137 | G19: =G13/'Cost Build_Up'!G12*'Working Capital'!G9 -> 128.99955 | H19: =AVERAGE(C19:G19) -> 110.20226 | I19: =H19 -> 110.20226 | J19: =I19 -> 110.20226 | K19: =J19 -> 110.20226 | L19: =K19 -> 110.20226 | M19: =L19 -> 110.20226 | N19: =M19 -> 110.20226 | O19: =N19 -> 110.20226 | P19: =O19 -> 110.20226 | Q19: =P19 -> 110.20226

Sheet Beta
B6: Beta
B8: Date | C8: Sensex | D8: % | F8: Date | G8: Close Price
C9: Close | D9: Change
B10: 42217 | C10: 26283.09 | F10: 42217 | G10: 753.9
B11: 42248 | C11: 26154.83 | D11: =C11/C10-1 -> -0.0048799437 | F11: 42248 | G11: 768.1 | H11: =G11/G10-1 -> 0.018835389
B12: 42278 | C12: 26656.83 | D12: =C12/C11-1 -> 0.019193396 | F12: 42278 | G12: 834.9 | H12: =G12/G11-1 -> 0.086967843 | J12: Beta | K12: =SLOPE(H11:H130,D11:D130) -> 0.92524974
B13: 42309 | C13: 26145.67 | D13: =C13/C12-1 -> -0.019175573 | F13: 42309 | G13: 810.65 | H13: =G13/G12-1 -> -0.029045395
B14: 42339 | C14: 26117.54 | D14: =C14/C13-1 -> -0.0010758952 | F14: 42339 | G14: 875.4 | H14: =G14/G13-1 -> 0.079874175
B15: 42370 | C15: 24870.69 | D15: =C15/C14-1 -> -0.047739948 | F15: 42370 | G15: 833.25 | H15: =G15/G14-1 -> -0.048149417
B16: 42401 | C16: 23002 | D16: =C16/C15-1 -> -0.075136235 | F16: 42401 | G16: 655.15 | H16: =G16/G15-1 -> -0.21374137
B17: 42430 | C17: 25341.86 | D17: =C17/C16-1 -> 0.1017242 | F17: 42430 | G17: 745 | H17: =G17/G16-1 -> 0.13714417
B18: 42461 | C18: 25606.62 | D18: =C18/C17-1 -> 0.010447536 | F18: 42461 | G18: 760.95 | H18: =G18/G17-1 -> 0.021409396
B19: 42491 | C19: 26667.96 | D19: =C19/C18-1 -> 0.041447876 | F19: 42491 | G19: 785.55 | H19: =G19/G18-1 -> 0.032328011
B20: 42522 | C20: 26999.72 | D20: =C20/C19-1 -> 0.012440397 | F20: 42522 | G20: 743.4 | H20: =G20/G19-1 -> -0.053656674
B21: 42552 | C21: 28051.86 | D21: =C21/C20-1 -> 0.038968552 | F21: 42552 | G21: 792.3 | H21: =G21/G20-1 -> 0.065778854
B22: 42583 | C22: 28452.17 | D22: =C22/C21-1 -> 0.014270355 | F22: 42583 | G22: 790.65 | H22: =G22/G21-1 -> -0.0020825445
B23: 42614 | C23: 27865.96 | D23: =C23/C22-1 -> -0.020603349 | F23: 42614 | G23: 854.9 | H23: =G23/G22-1 -> 0.081262253
B24: 42644 | C24: 27930.21 | D24: =C24/C23-1 -> 0.0023056805 | F24: 42644 | G24: 817.35 | H24: =G24/G23-1 -> -0.043923266
... B130: 45870 | C130: 80599.91 | D130: =C130/C129-1 -> -0.0072139658 | F130: 45870 | G130: 1041.65 | H130: =G130/G129-1 -> -0.087032736

Sheet WACC
B6: WACC
B8: Current Capital structure
B9: Total Equity | C9: =Balance_sheet!G51 -> 298508
B10: Total Debt | C10: =Balance_sheet!G56+Balance_sheet!G57+Balance_sheet!G67+Balance_sheet!G68 -> 66476.3
B11: Debt/equity | C11: =C10/C9 -> 0.2226952
B13: Cost of debt
B14: Pre-tax cost of debt | C14: 0.11741938
B15: tax rate | C15: ='Cost Build_Up'!H38 -> 0.25354554
B16: After -Tax cost of debt | C16: =C14*(1-C15) -> 0.087648217
B18: Cost of equity
B19: Risk free Rate | C19: 0.06371
B20: Equity Market Return | C20: 0.11146681
B21: Equity risk premium | C21: =C20-C19 -> 0.047756811
B22: Equity Beta | C22: 0.92524974
B23: Cost of equity | C23: =C19+C22*C21 -> 0.10789698
B25: WACC | C25: =(C23*(1-C11))+(C16*C11) -> 0.10338768

Sheet DCF
B7: DCF Analysis
B9: Particulars | C9: 2020 | D9: =C9+1 -> 2021 | E9: =D9+1 -> 2022 | F9: =E9+1 -> 2023 | G9: =F9+1 -> 2024 | H9: =G9+1 -> 2025 | I9: =H9+1 -> 2026 | J9: =I9+1 -> 2027 | K9: =J9+1 -> 2028 | ... Q9: =P9+1 -> 2034
B10: EBIT/ Operating Income | H10: ='Income Statement'!H23 -> 41220.622 | I10: ='Income Statement'!I23 -> 45283.561 | J10: ='Income Statement'!J23 -> 49843.271 | K10: ='Income Statement'!K23 -> 55045.457 | L10: ='Income Statement'!L23 -> 61056.698 | M10: ='Income Statement'!M23 -> 68071.731 | N10: ='Income Statement'!N23 -> 76321.766 | O10: ='Income Statement'!O23 -> 86084.207 | ... Q10: ='Income Statement'!Q23 -> 111558.61
B11: Tax rate | H11: =-H10*'Cost Build_Up'!H38 -> -10451.305 | I11: =-I10*'Cost Build_Up'!I38 -> -11481.445 | J11: =-J10*'Cost Build_Up'!J38 -> -12637.539 | K11: =-K10*'Cost Build_Up'!K38 -> -13956.53 | L11: =-L10*'Cost Build_Up'!L38 -> -15480.653 | M11: =-M10*'Cost Build_Up'!M38 -> -17259.284 | N11: =-N10*'Cost Build_Up'!N38 -> -19351.043 | O11: =-O10*'Cost Build_Up'!O38 -> -21826.266 | ... Q11: =-Q10*'Cost Build_Up'!Q38 -> -28285.187
B12: NOPAT | H12: =SUM(H10:H11) -> 30769.318 | I12: =SUM(I10:I11) -> 33802.116 | J12: =SUM(J10:J11) -> 37205.732 | K12: =SUM(K10:K11) -> 41088.927 | L12: =SUM(L10:L11) -> 45576.045 | M12: =SUM(M10:M11) -> 50812.448 | N12: =SUM(N10:N11) -> 56970.722 | O12: =SUM(O10:O11) -> 64257.94 | ... Q12: =SUM(Q10:Q11) -> 83273.421
B13: Add: Depreciation & Amortization | H13: =-'Income Statement'!H21 -> 18929.396 | I13: =-'Income Statement'!I21 -> 19688.906 | J13: =-'Income Statement'!J21 -> 20646.868 | K13: =-'Income Statement'!K21 -> 21789.069 | L13: =-'Income Statement'!L21 -> 23108.124 | M13: =-'Income Statement'!M21 -> 24602.27 | N13: =-'Income Statement'!N21 -> 26274.5 | O13: =-'Income Statement'!O21 -> 28131.955 | ... Q13: =-'Income Statement'!Q21 -> 32449.596
B14: Less: CapEx | H14: =CashFlow!H49 -> -15892.956 | I14: =CashFlow!I49 -> -30152.514 | J14: =CashFlow!J49 -> -32346.122 | K14: =CashFlow!K49 -> -34732.751 | L14: =CashFlow!L49 -> -37332.293 | M14: =CashFlow!M49 -> -40166.908 | N14: =CashFlow!N49 -> -43261.293 | O14: =CashFlow!O49 -> -46642.989 | ... Q14: =CashFlow!Q49 -> -54394.804
B15: Less: Change in Working Capital | H15: =SUM(CashFlow!H33:H41) -> 4024.4679 | I15: =SUM(CashFlow!I33:I41) -> -4269.8527 | J15: =SUM(CashFlow!J33:J41) -> -4885.4104 | K15: =SUM(CashFlow!K33:K41) -> -5617.3951 | L15: =SUM(CashFlow!L33:L41) -> -6490.3302 | M15: =SUM(CashFlow!M33:M41) -> -7534.127 | N15: =SUM(CashFlow!N33:N41) -> -8785.2895 | O15: =SUM(CashFlow!O33:O41) -> -10288.392 | ... Q15: =SUM(CashFlow!Q33:Q41) -> -14280.335
B16: Unlevered FCFF | H16: =SUM(H12:H15) -> 37830.226 | I16: =SUM(I12:I15) -> 19068.656 | J16: =SUM(J12:J15) -> 20621.067 | K16: =SUM(K12:K15) -> 22527.85 | L16: =SUM(L12:L15) -> 24861.545 | M16: =SUM(M12:M15) -> 27713.682 | N16: =SUM(N12:N15) -> 31198.64 | O16: =SUM(O12:O15) -> 35458.514 | ... Q16: =SUM(Q12:Q15) -> 47047.877 | R16: =Q16*(1+Assumptions!C16)/(Assumptions!C17-Assumptions!C16) -> 925312.28
B18: Perpetual Growth Rate | C18: 0.05 | G18: Sensitivity Analysis
B19: Discount Rate | C19: 0.10338768
G20: Perpetual Growth Rate
B21: Intrinsic Value | H21: =C28 -> 967.73995 | I21: 0.03 | J21: 0.04 | K21: 0.05 | L21: 0.055 | M21: 0.06
B22: Enterpreise Value | C22: =NPV(C19,DCF!H16:R16) -> 490761.82 | G22: Discount Rate | H22: 0.14338768 | I22: 743.51936 | J22: 743.51936 | K22: 743.51936 | L22: 743.51936 | M22: 743.51936
B23: Plus: Cash & Cash equivalent | C23: =Balance_sheet!H33 -> 96054.64 | H23: 0.12338768 | I23: 844.59504 | J23: 844.59504 | K23: 844.59504 | L23: 844.59504 | M23: 844.59504
B24: Less- Debt | C24: =-'Debt Schedules'!G12 -> -24673.1 | H24: 0.10338768 | I24: 967.73995 | J24: 967.73995 | K24: 967.73995 | L24: 967.73995 | M24: 967.73995
B25: Less-non- controlling interest | C25: =-Balance_sheet!H50 -> -80 | H25: 0.093387675 | I25: 1039.2712 | J25: 1039.2712 | K25: 1039.2712 | L25: 1039.2712 | M25: 1039.2712
B26: Equity Value | C26: =SUM(C22:C25) -> 562063.36 | H26: 0.076064732 | I26: 1181.9868 | J26: 1181.9868 | K26: 1181.9868 | L26: 1181.9868 | M26: 1181.9868
B28: Equity value/share | C28: =C26/Assumptions!C18 -> 967.73995
B30: Rate of Return
B31: Current price | C31: =Assumptions!C19 -> 1042
B32: Target Price | C32: =C28 -> 967.73995
B33: Target Price Upside | C33: =C32/C31-1 -> -0.071266843
