Workbook

Sheet Assumption
B7: Scenario Manager | E7: Company Name | F7: Happiest Minds Technologies Ltd
B8: Base Case | C8: =IF(B8="Best Case",1,IF(B8="Base Case",2,3)) -> 2 | E8: ISIN Code | F8: INE419U01012
E9: Sector Name | F9: IT-Software
B10: Assumptions | E10: Industry | F10: Computers - Software & Consulting
B11: Transaction Date | C11: 46030 | E11: Exchange Name | F11: BSE: 543227 | NSE: HAPPSTMNDS
B12: Fiscal Year End | C12: 46112 | E12: Website | F12: happiestminds.com
B13: Risk Free Rate | C13: 0.06615 | E13: Company Description | F13: Happiest Minds Technologies Ltd. is a next-generation IT solutions and services company that was founded in 2011. It specializes in infrastructure management and security services, generative artificial intelligence, and product and digital engineering. It operates in the United States, United Kingdom, Canada, Australia, and the Middle East, with its headquarters located in Bengaluru, India. Clientele The company now has 281 active clients as of FY25, up from 206 in FY22. Of these, 85 are listed within the Fortune 2000 and Forbes 200 list of billion-dollar companies. Repeat business accounts for 94% of its revenue. In FY26 and beyond, the business anticipates robust double-digit organic growth.
B14: Addition In FSA | C14: 0.005
B15: Addition In Tax rate / 2 years | C15: 0.005
B16: Addition In Dep | C16: 0.005
B17: Tax Rate | C17: ='Cost Buildup'!G23 -> 0.27714711
B18: EV/EBITDA Multiple | C18: ='Comparable Valuation'!E36 -> 15.505377
B19: Perpetual Growth Rate | C19: 0.06
B20: Discount Rate | C20: ='Comps Beta'!F51 -> 0.12988112
B21: Shares Outstanding(Lakhs) | C21: ='Comparable Valuation'!F31 -> 1523
B22: Current Market Price | C22: 459
B23: Market Cap (Lakhs.) | C23: =C22*C21 -> 699057
B25: Colour Code
B26: Blue colour | C26: Hardcoded Figures
B27: Black colour | C27: Calculated Figures
B28: Green Colour | C28: Link Data figures
B31: Items | C31: Sheet | E31: Reference | F31: Assumptions
B33: Revenue Segment by Geography | C33: Revenue Buildup | D33: B13:Q54 | F33: For the forecasted year, the base growth rate is calculated as the average of the historical years. Best- and worst-case scenarios are set at ±5% around this base. Revenue is segmented across USA, India, Europe, and Other countries. A uniform annual tapering rate ( 14%) is applied across all segments, calibrated such that the highest revenue segment converges to the perpetual growth rate of 6%. This annual tapering also ensures that total company revenue gradually reaches the same perpetual growth rate of 6% over the forecast period.
B35: Revenue of India | C35: Revenue Buildup | D35: B15:Q23 | F35: India revenue growth is based on the average historical growth rate (from 2023-2025) for base case, with ±5% variation for best and Worst cases, and an annual tapering of 14% applied over the forecast period.
B36: Revenue of USA | C36: Revenue Buildup | D36: B26:Q34 | F36: USA revenue growth is based on the average historical growth rate for base case, with ±5% variation for best and Worst cases, and an annual tapering of 14% applied over the forecast period that reached at the perpetual growth rate of 6 %.
B37: Revenue of Europe | C37: Revenue Buildup | D37: B36:Q44 | F37: Europe revenue growth is based on the average historical growth rate(From 2023 to 2025) for base case, with ±5% variation for best and Worst cases, and an annual tapering of 14% applied over the forecast period.
B38: Revenue of Others | C38: Revenue Buildup | D38: B46:Q54 | F38: Historical revenue growth for other countries is highly irregular. therefore, a normalized growth rate of 25% is assumed for the forecast year, with an annual tapering of 14% applied to gradually converge to the perpetual growth rate.
B39: Total Revenue | C39: Revenue Buildup | D39: G6 | F39: The Segment wise total revenue and the total Revenue in Annual Report is differ by 1 in the year 2025, so in this case I take the P&L statement Revenue.
B40: Exceptional Items | C40: Revenue Buildup | D40: B37:Q38 | F40: exceptional Items Taken as a percentage of revenue. For forecasted years (2026–2035), derived from the historical average of 2021–2025.
B41: Other Income | C41: Revenue Buildup | D41: B33:Q34 | F41: Other Income: Taken as a percentage of revenue. For forecasted years (2026–2035), derived from the historical average of 2021–2025.
B43: Other Expenses | C43: Cost Build_up | D43: B15:Q16 | F43: The first five years show actual historical percentages of revenue. For the forecasted period (2026–2035), other expenses are assumed based on the average percentage of revenue from 2021–2025, stabilizing around 17% and increasing proportionally with revenue growth.
B47: Perpetual Growth Rate | C47: Assumptions | D47: C20 | F47: For calculating the Terminal Value in the DCF model, a perpetual growth rate of 6% has been assumed. This is aligned with India’s long-term GDP growth outlook, which is forecasted at approximately 6%
B49: Effective Tax Rate | C49: Cost Build_up | D49: B21:Q22 | F49: Taxes for the historical years are based on actual PBT percentages. For the forecasted years (2026–2035), taxes for projected year taken as the latest year of the tax ( which is 2025 tax rate ), and aslo adding the growing tax rate of 0.5 % every 2 year.
B51: Cash and Cash Equivalent | C51: Historical Balance Sheet | D51: B29:G29 | F51: Cash and cash equivalents have been adjusted by reducing the bank overdraft balances of ₹7,119 in FY2023 and ₹573 in FY2024, as disclosed under the Components of Cash and Cash Equivalents in the Annual Report (page 281), to ensure that the closing cash balance reconciles with the cash flow statement.
... B71: Interest Expenses | C71: Debt Schedules | D71: B14:Q15 | F71: Interest expenses are calculated as a percentage of the average of opening and closing debt for each year. For the forecasted period (FY2026–FY2035), the interest rate is assumed constant, based on the average percentage of debt from the last five years (FY2021–FY2025), reflecting a stable cost of borrowing trend

Sheet Historical P&L
B5: Income Statement
B6: (All amounts in INR Lakhs, unless otherwise stated)
A7: # | B7: Particulars | C7: 2021 | D7: =C7+1 -> 2022 | E7: =D7+1 -> 2023 | F7: =E7+1 -> 2024 | G7: =F7+1 -> 2025
C8: Audited | D8: Audited | E8: Audited | F8: Audited | G8: Audited
B9: income
B10: Revenue from contracts with customers | C10: 77341 | D10: 109365 | E10: 142929 | F10: 162466 | G10: 206084
B11: other income | C11: 2424 | D11: 3710 | E11: 2111 | F11: 8537 | G11: 10138
B12: total income | C12: =SUM(C10:C11) -> 79765 | D12: =SUM(D10:D11) -> 113075 | E12: =SUM(E10:E11) -> 145040 | F12: =SUM(F10:F11) -> 171003 | G12: =SUM(G10:G11) -> 216222
B14: expenses
B15: Employee benefits expense | C15: 45238 | D15: 62000 | E15: 80681 | F15: 101469 | G15: 136534
B16: Depreciation and amortisation | C16: 2274 | D16: 3288 | E16: 4191 | F16: 5829 | G16: 8870
B17: Finance cost | C17: 697 | D17: 995 | E17: 2186 | F17: 4227 | G17: 9948
B18: Other expenses | C18: 12954 | D18: 21598 | E18: 26362 | F18: 26882 | G18: 32518
B19: Impairment loss allowance on trade and unbilled receivables | F19: 530 | G19: 1590
B20: total expenses | C20: =SUM(C15:C19) -> 61163 | D20: =SUM(D15:D19) -> 87881 | E20: =SUM(E15:E19) -> 113420 | F20: =SUM(F15:F19) -> 138937 | G20: =SUM(G15:G19) -> 189460
B22: Profit before exceptional items and tax | C22: =C12-C20 -> 18602 | D22: =D12-D20 -> 25194 | E22: =E12-E20 -> 31620 | F22: =F12-F20 -> 32066 | G22: =G12-G20 -> 26762
B23: Exceptional Items | D23: -609 | E23: -634 | F23: 1402 | G23: -1216
B24: Profit before tax | C24: =SUM(C22:C23) -> 18602 | D24: =SUM(D22:D23) -> 24585 | E24: =SUM(E22:E23) -> 30986 | F24: =SUM(F22:F23) -> 33468 | G24: =SUM(G22:G23) -> 25546
B26: tax expense
B27: Current tax | C27: 3527 | D27: 6266 | E27: 8508 | F27: 9518 | G27: 8443
B28: Adjustment of tax relating to earlier periods | D28: 44
B29: Deferred tax charge/ (credit) | C29: -1171 | D29: 155 | E29: -621 | F29: -889 | G29: -1363
B31: Profit for the year | C31: =C24-SUM(C27:C29) -> 16246 | D31: =D24-SUM(D27:D29) -> 18120 | E31: =E24-SUM(E27:E29) -> 23099 | F31: =F24-SUM(F27:F29) -> 24839 | G31: =G24-SUM(G27:G29) -> 18466

Sheet Historical Balance Sheet
B5: Balance Sheet
B6: (All amounts in INR Lakhs, unless otherwise stated)
A7: # | B7: Particulars | C7: 2021 | D7: =C7+1 -> 2022 | E7: =D7+1 -> 2023 | F7: =E7+1 -> 2024 | G7: =F7+1 -> 2025
C8: Audited | D8: Audited | E8: Audited | F8: Audited | G8: Audited
B9: Assets
B10: Non-current assets
B11: Property, plant and equipment | C11: 69 | D11: 78 | E11: 13278 | F11: 13778 | G11: 14096
B12: Capital work-in-progress | C12: 14 | D12: 0 | E12: 185 | F12: 9 | G12: 0
B13: Goodwill | C13: 7644 | D13: 7896 | E13: 13913 | F13: 14032 | G13: 76230
B14: Other intangible assets | C14: 2966 | D14: 2396 | E14: 10182 | F14: 7786 | G14: 23831
B15: Intangible assets under development | D15: 35 | E15: 81 | F15: 22 | G15: 18
B16: Right-of-use assets | C16: 2150 | D16: 5390 | E16: 5786 | F16: 5698 | G16: 6958
B17: Financial assets
B18: Investments | C18: 0 | D18: 762 | E18: 1296 | F18: 0 | G18: 0
B19: Other financial assets | C19: 2458 | D19: 1827 | E19: 9389 | F19: 2480 | G19: 7358
B20: Income tax assets (net | C20: 1408 | D20: 680 | E20: 1310 | F20: 1529 | G20: 3537
B21: Other assets | C21: 7 | D21: 1 | E21: 119 | F21: 32 | G21: 170
B22: Deferred tax assets (net) | C22: 1026 | D22: 697 | E22: 1246 | F22: 1636 | G22: 3613
B24: Total non-current assets | C24: =SUM(C11:C22) -> 17742 | D24: =SUM(D11:D22) -> 19762 | E24: =SUM(E11:E22) -> 56785 | F24: =SUM(F11:F22) -> 47002 | G24: =SUM(G11:G22) -> 135811
B26: Current assets
B27: Financial assets
B28: Investments | C28: 39148 | D28: 46400 | E28: 0 | F28: 0 | G28: 35039
B29: Trade receivables | C29: 12192 | D29: 16738 | E29: 21319 | F29: 25444 | G29: 35813
B30: Cash and cash equivalents | C30: =CashFlow!C79 -> 8583 | D30: 6729 | E30: -120 | F30: 10897 | G30: 11912
B31: Bank balance other than cash and cash equivalents | C31: 5935 | D31: 10071 | E31: =62184+7119 -> 69303 | F31: =122183+573 -> 122756 | G31: 93911
B32: Loans | C32: 14 | D32: 4 | E32: 64 | F32: 37 | G32: 12
B33: Other financial assets | C33: 6779 | D33: 9405 | E33: 12237 | F33: 13850 | G33: 17726
B34: Other assets | C34: 1802 | D34: 3392 | E34: 4495 | F34: 4793 | G34: 5682
B36: Total current assets | C36: =SUM(C28:C35) -> 74453 | D36: =SUM(D28:D35) -> 92739 | E36: =SUM(E28:E35) -> 107298 | F36: =SUM(F28:F35) -> 177777 | G36: =SUM(G28:G35) -> 200095
B38: Total Assets | C38: =C36+C24 -> 92195 | D38: =D36+D24 -> 112501 | E38: =E36+E24 -> 164083 | F38: =F36+F24 -> 224779 | G38: =G36+G24 -> 335906
B40: Equity and liabilities
B41: Equity
B42: Equity share capital | C42: 2837 | D42: 2854 | E42: 2866 | F42: 2987 | G42: 3001
B43: Other equity | C43: 51762 | D43: 63726 | E43: 81016 | F43: 145037 | G43: 154457
B44: Equity attributable to equity holders of the parent | C44: =SUM(C42:C43) -> 54599 | D44: =SUM(D42:D43) -> 66580 | E44: =SUM(E42:E43) -> 83882 | F44: =SUM(F42:F43) -> 148024 | G44: =SUM(G42:G43) -> 157458
B45: Total equity | C45: =SUM(C44:C44) -> 54599 | D45: =SUM(D44:D44) -> 66580 | E45: =SUM(E44:E44) -> 83882 | F45: =SUM(F44:F44) -> 148024 | G45: =SUM(G44:G44) -> 157458
B47: Liabilities
B48: Non-current liabilities
B49: Financial liabilities
B50: Borrowings | C50: 3661 | D50: 1724 | E50: 11278 | F50: 10445 | G50: 33537
B51: Lease liabilities | C51: 1223 | D51: 4119 | E51: 4761 | F51: 4570 | G51: 5010
B52: Other financial liabilities | C52: 2455 | D52: 1291 | E52: 1996 | F52: 401 | G52: 8330
B53: Provisions | C53: 1653 | D53: 1618 | E53: 2466 | F53: 3338 | G53: 5940
B54: Deferred tax liabilities (net | C54: 725 | D54: 468 | E54: 2060 | F54: 1303 | G54: 4841
B56: Total non-current liabilities | C56: =SUM(C50:C55) -> 9717 | D56: =SUM(D50:D55) -> 9220 | E56: =SUM(E50:E55) -> 22561 | F56: =SUM(F50:F55) -> 20057 | G56: =SUM(G50:G55) -> 57658
B58: Current liabilities
B59: Contract liabilities | C59: 674 | D59: 1346 | E59: 1157 | F59: 1825 | G59: 2194
B60: Financial liabilities
B61: Borrowings | C61: 12969 | D61: 17340 | E61: 35477 | F61: 33792 | G61: 82554
B62: Lease liabilities | C62: 1422 | D62: 1792 | E62: 1859 | F62: 2412 | G62: 3258
B63: Trade payables
B64: Total outstanding dues of micro enterprises and small enterprises | C64: 95 | D64: 79 | E64: 83 | F64: 165 | G64: 225
B65: Total outstanding dues of creditors other than micro enterprises and small enterprises | C65: 4404 | D65: 5993 | E65: 6969 | F65: 7750 | G65: 10256
B66: Other financial liabilities | C66: 4877 | D66: 5788 | E66: 7428 | F66: 5810 | G66: 14526
B67: Income tax liabilities (net) | C67: 0 | D67: 239 | E67: 517 | F67: 12 | G67: 422
B68: Other current liabilities | C68: 1930 | D68: 2426 | E68: 2375 | F68: 2796 | G68: 3836
B69: Provisions | C69: 1508 | D69: 1698 | E69: 1775 | F69: 2136 | G69: 3519
B71: Total current liabilities | C71: =SUM(C59:C69) -> 27879 | D71: =SUM(D59:D69) -> 36701 | E71: =SUM(E59:E69) -> 57640 | F71: =SUM(F59:F69) -> 56698 | G71: =SUM(G59:G69) -> 120790
B73: Total liabilities | C73: =C71+C56 -> 37596 | D73: =D71+D56 -> 45921 | E73: =E71+E56 -> 80201 | F73: =F71+F56 -> 76755 | G73: =G71+G56 -> 178448
B75: Total equity and liabilities | C75: =C73+C45 -> 92195 | D75: =D73+D45 -> 112501 | E75: =E73+E45 -> 164083 | F75: =F73+F45 -> 224779 | G75: =G73+G45 -> 335906
B77: Check | C77: =C75=C38 -> TRUE | D77: =D75=D38 -> TRUE | E77: =E75=E38 -> TRUE | F77: =F75=F38 -> TRUE | G77: =G75=G38 -> TRUE

Sheet Revenue BuildUp
B5: Revenue Build_Up
B6: (All amounts in INR Lakhs, unless otherwise stated)
A7: # | B7: Particulars | C7: 2021 | D7: =C7+1 -> 2022 | E7: =D7+1 -> 2023 | F7: =E7+1 -> 2024 | G7: =F7+1 -> 2025 | H7: =G7+1 -> 2026 | I7: =H7+1 -> 2027 | J7: =I7+1 -> 2028 | K7: =J7+1 -> 2029 | ... Q7: =P7+1 -> 2035
C8: Audited | D8: Audited | E8: Audited | F8: Audited | G8: Audited | H8: Estimated | I8: Projected | J8: Projected | K8: Projected | L8: Projected | M8: Projected | N8: Projected | O8: Projected | P8: Projected | Q8: Projected
B10: Revenue | C10: ='Historical P&L'!C10 -> 77341 | D10: ='Historical P&L'!D10 -> 109365 | E10: ='Historical P&L'!E10 -> 142929 | F10: ='Historical P&L'!F10 -> 162466 | G10: ='Historical P&L'!G10 -> 206084 | H10: =SUM(H16,H27,H37,H47) -> 251738.78 | I10: =SUM(I16,I27,I37,I47) -> 299960.77 | J10: =SUM(J16,J27,J37,J47) -> 349602.74 | K10: =SUM(K16,K27,K37,K47) -> 399552.8 | L10: =SUM(L16,L27,L37,L47) -> 448807.82 | M10: =SUM(M16,M27,M37,M47) -> 496520.42 | N10: =SUM(N16,N27,N37,N47) -> 542021.63 | O10: =SUM(O16,O27,O37,O47) -> 584823.41 | ... Q10: =SUM(Q16,Q27,Q37,Q47) -> 661200.04
B11: Y-O-Y Growth | D11: =D10/C10-1 -> 0.4140624 | E11: =E10/D10-1 -> 0.30689892 | F11: =F10/E10-1 -> 0.13669024 | G11: =G10/F10-1 -> 0.26847463 | H11: =H10/G10-1 -> 0.22153481 | I11: =I10/H10-1 -> 0.19155565 | J11: =J10/I10-1 -> 0.1654949 | K11: =K10/J10-1 -> 0.14287662 | ... Q11: =Q10/P10-1 -> 0.058586316
B14: Revenue Segment by Geography
B16: India | C16: 10464 | D16: 20594 | E16: 22982 | F16: 26668 | G16: 32033 | H16: =G16*(1+H18) -> 37131.799 | I16: =H16*(1+I18) -> 42214.735 | J16: =I16*(1+J18) -> 47184.447 | K16: =J16*(1+K18) -> 51961.549 | L16: =K16*(1+L18) -> 56485.794 | M16: =L16*(1+M18) -> 60715.418 | N16: =M16*(1+N18) -> 64625.267 | O16: =N16*(1+O18) -> 68204.267 | ... Q16: =P16*(1+Q18) -> 74379.343
D18: =D16/C16-1 -> 0.96808104 | E18: =E16/D16-1 -> 0.1159561 | F18: =F16/E16-1 -> 0.16038639 | G18: =G16/F16-1 -> 0.20117744 | H18: =CHOOSE(Assumption!$C$8,'Revenue BuildUp'!$H$21:$Q$21,'Revenue BuildUp'!$H$22:$Q$22,'Revenue BuildUp'!$H$23:$Q$23) -> 0.15917331 | I18: =CHOOSE(Assumption!$C$8,'Revenue BuildUp'!$H$21:$Q$21,'Revenue BuildUp'!$H$22:$Q$22,'Revenue BuildUp'!$H$23:$Q$23) -> 0.13688905 | J18: =CHOOSE(Assumption!$C$8,'Revenue BuildUp'!$H$21:$Q$21,'Revenue BuildUp'!$H$22:$Q$22,'Revenue BuildUp'!$H$23:$Q$23) -> 0.11772458 | K18: =CHOOSE(Assumption!$C$8,'Revenue BuildUp'!$H$21:$Q$21,'Revenue BuildUp'!$H$22:$Q$22,'Revenue BuildUp'!$H$23:$Q$23) -> 0.10124314 | L18: =CHOOSE(Assumption!$C$8,'Revenue BuildUp'!$H$21:$Q$21,'Revenue BuildUp'!$H$22:$Q$22,'Revenue BuildUp'!$H$23:$Q$23) -> 0.0870691 | M18: =CHOOSE(Assumption!$C$8,'Revenue BuildUp'!$H$21:$Q$21,'Revenue BuildUp'!$H$22:$Q$22,'Revenue BuildUp'!$H$23:$Q$23) -> 0.074879426 | N18: =CHOOSE(Assumption!$C$8,'Revenue BuildUp'!$H$21:$Q$21,'Revenue BuildUp'!$H$22:$Q$22,'Revenue BuildUp'!$H$23:$Q$23) -> 0.064396306 | O18: =CHOOSE(Assumption!$C$8,'Revenue BuildUp'!$H$21:$Q$21,'Revenue BuildUp'!$H$22:$Q$22,'Revenue BuildUp'!$H$23:$Q$23) -> 0.055380824 | ... Q18: =CHOOSE(Assumption!$C$8,'Revenue BuildUp'!$H$21:$Q$21,'Revenue BuildUp'!$H$22:$Q$22,'Revenue BuildUp'!$H$23:$Q$23) -> 0.040959657
B20: Scenarios
B21: Best Case | H21: =H22+5% -> 0.20917331 | I21: =H21*(1-$C$24) -> 0.17988905 | J21: =I21*(1-$C$24) -> 0.15470458 | K21: =J21*(1-$C$24) -> 0.13304594 | L21: =K21*(1-$C$24) -> 0.11441951 | M21: =L21*(1-$C$24) -> 0.098400777 | N21: =M21*(1-$C$24) -> 0.084624668 | O21: =N21*(1-$C$24) -> 0.072777215 | P21: =O21*(1-$C$24) -> 0.062588405 | Q21: =P21*(1-$C$24) -> 0.053826028
B22: Base Case | H22: =AVERAGE(E18:G18) -> 0.15917331 | I22: =H22*(1-$C$24) -> 0.13688905 | J22: =I22*(1-$C$24) -> 0.11772458 | K22: =J22*(1-$C$24) -> 0.10124314 | L22: =K22*(1-$C$24) -> 0.0870691 | M22: =L22*(1-$C$24) -> 0.074879426 | N22: =M22*(1-$C$24) -> 0.064396306 | O22: =N22*(1-$C$24) -> 0.055380824 | P22: =O22*(1-$C$24) -> 0.047627508 | Q22: =P22*(1-$C$24) -> 0.040959657
B23: Worst Case | H23: =H22-5% -> 0.10917331 | I23: =H23*(1-$C$24) -> 0.093889048 | J23: =I23*(1-$C$24) -> 0.080744581 | K23: =J23*(1-$C$24) -> 0.06944034 | L23: =K23*(1-$C$24) -> 0.059718692 | M23: =L23*(1-$C$24) -> 0.051358075 | N23: =M23*(1-$C$24) -> 0.044167945 | O23: =N23*(1-$C$24) -> 0.037984432 | P23: =O23*(1-$C$24) -> 0.032666612 | Q23: =P23*(1-$C$24) -> 0.028093286
B24: Annual Trapering | C24: =C35 -> 0.14
B27: USA | C27: 56517 | D27: 71141 | E27: 97251 | F27: 114289 | G27: 133134 | H27: =G27*(1+H29) -> 165281.09 | I27: =H27*(1+I29) -> 199603.23 | J27: =I27*(1+J29) -> 235249.76 | K27: =J27*(1+K29) -> 271380.54 | L27: =K27*(1+L29) -> 307225.26 | M27: =L27*(1+M29) -> 342123.37 | N27: =M27*(1+N29) -> 375544.89 | O27: =N27*(1+O29) -> 407095.21 | ... Q27: =P27*(1+Q29) -> 463630.59
D29: =D27/C27-1 -> 0.258754 | E29: =E27/D27-1 -> 0.36701761 | F29: =F27/E27-1 -> 0.17519614 | G29: =G27/F27-1 -> 0.16488901 | H29: =CHOOSE(Assumption!$C$8,'Revenue BuildUp'!$H$32:$Q$32,'Revenue BuildUp'!$H$33:$Q$33,'Revenue BuildUp'!$H$34:$Q$34) -> 0.24146419 | I29: =CHOOSE(Assumption!$C$8,'Revenue BuildUp'!$H$32:$Q$32,'Revenue BuildUp'!$H$33:$Q$33,'Revenue BuildUp'!$H$34:$Q$34) -> 0.20765921 | J29: =CHOOSE(Assumption!$C$8,'Revenue BuildUp'!$H$32:$Q$32,'Revenue BuildUp'!$H$33:$Q$33,'Revenue BuildUp'!$H$34:$Q$34) -> 0.17858692 | K29: =CHOOSE(Assumption!$C$8,'Revenue BuildUp'!$H$32:$Q$32,'Revenue BuildUp'!$H$33:$Q$33,'Revenue BuildUp'!$H$34:$Q$34) -> 0.15358475 | L29: =CHOOSE(Assumption!$C$8,'Revenue BuildUp'!$H$32:$Q$32,'Revenue BuildUp'!$H$33:$Q$33,'Revenue BuildUp'!$H$34:$Q$34) -> 0.13208288 | M29: =CHOOSE(Assumption!$C$8,'Revenue BuildUp'!$H$32:$Q$32,'Revenue BuildUp'!$H$33:$Q$33,'Revenue BuildUp'!$H$34:$Q$34) -> 0.11359128 | N29: =CHOOSE(Assumption!$C$8,'Revenue BuildUp'!$H$32:$Q$32,'Revenue BuildUp'!$H$33:$Q$33,'Revenue BuildUp'!$H$34:$Q$34) -> 0.0976885 | O29: =CHOOSE(Assumption!$C$8,'Revenue BuildUp'!$H$32:$Q$32,'Revenue BuildUp'!$H$33:$Q$33,'Revenue BuildUp'!$H$34:$Q$34) -> 0.08401211 | ... Q29: =CHOOSE(Assumption!$C$8,'Revenue BuildUp'!$H$32:$Q$32,'Revenue BuildUp'!$H$33:$Q$33,'Revenue BuildUp'!$H$34:$Q$34) -> 0.062135357
B31: Scenarios
B32: Best Case | H32: =H33+5% -> 0.29146419 | I32: =H32*(1-$C$35) -> 0.25065921 | J32: =I32*(1-$C$35) -> 0.21556692 | K32: =J32*(1-$C$35) -> 0.18538755 | L32: =K32*(1-$C$35) -> 0.15943329 | M32: =L32*(1-$C$35) -> 0.13711263 | N32: =M32*(1-$C$35) -> 0.11791686 | O32: =N32*(1-$C$35) -> 0.1014085 | P32: =O32*(1-$C$35) -> 0.087211311 | Q32: =P32*(1-$C$35) -> 0.075001728
B33: Base Case | H33: =AVERAGE(D29:G29) -> 0.24146419 | I33: =H33*(1-$C$35) -> 0.20765921 | J33: =I33*(1-$C$35) -> 0.17858692 | K33: =J33*(1-$C$35) -> 0.15358475 | L33: =K33*(1-$C$35) -> 0.13208288 | M33: =L33*(1-$C$35) -> 0.11359128 | N33: =M33*(1-$C$35) -> 0.0976885 | O33: =N33*(1-$C$35) -> 0.08401211 | P33: =O33*(1-$C$35) -> 0.072250415 | Q33: =P33*(1-$C$35) -> 0.062135357
B34: Worst Case | H34: =H33-5% -> 0.19146419 | I34: =H34*(1-$C$35) -> 0.16465921 | J34: =I34*(1-$C$35) -> 0.14160692 | K34: =J34*(1-$C$35) -> 0.12178195 | L34: =K34*(1-$C$35) -> 0.10473248 | M34: =L34*(1-$C$35) -> 0.090069929 | N34: =M34*(1-$C$35) -> 0.077460139 | O34: =N34*(1-$C$35) -> 0.066615719 | P34: =O34*(1-$C$35) -> 0.057289519 | Q34: =P34*(1-$C$35) -> 0.049268986
B35: Annual Trapering | C35: 0.14
B37: Europe | C37: 7611 | D37: 11332 | E37: 13811 | F37: 14751 | G37: 16779 | H37: =G37*(1+H39) -> 19152.137 | I37: =H37*(1+I39) -> 21481.69 | J37: =I37*(1+J39) -> 23728.789 | K37: =J37*(1+K39) -> 25863.444 | L37: =K37*(1+L39) -> 27864.397 | M37: =L37*(1+M39) -> 29718.351 | N37: =M37*(1+N39) -> 31418.833 | O37: =N37*(1+O39) -> 32964.928 | ... Q37: =P37*(1+Q39) -> 35610.535
D39: =D37/C37-1 -> 0.48889765 | E39: =E37/D37-1 -> 0.21876103 | F39: =F37/E37-1 -> 0.06806169 | G39: =G37/F37-1 -> 0.1374822 | H39: =CHOOSE(Assumption!$C$8,'Revenue BuildUp'!$H$42:$Q$42,'Revenue BuildUp'!$H$43:$Q$43,'Revenue BuildUp'!$H$44:$Q$44) -> 0.14143498 | I39: =CHOOSE(Assumption!$C$8,'Revenue BuildUp'!$H$42:$Q$42,'Revenue BuildUp'!$H$43:$Q$43,'Revenue BuildUp'!$H$44:$Q$44) -> 0.12163408 | J39: =CHOOSE(Assumption!$C$8,'Revenue BuildUp'!$H$42:$Q$42,'Revenue BuildUp'!$H$43:$Q$43,'Revenue BuildUp'!$H$44:$Q$44) -> 0.10460531 | K39: =CHOOSE(Assumption!$C$8,'Revenue BuildUp'!$H$42:$Q$42,'Revenue BuildUp'!$H$43:$Q$43,'Revenue BuildUp'!$H$44:$Q$44) -> 0.089960565 | L39: =CHOOSE(Assumption!$C$8,'Revenue BuildUp'!$H$42:$Q$42,'Revenue BuildUp'!$H$43:$Q$43,'Revenue BuildUp'!$H$44:$Q$44) -> 0.077366085 | M39: =CHOOSE(Assumption!$C$8,'Revenue BuildUp'!$H$42:$Q$42,'Revenue BuildUp'!$H$43:$Q$43,'Revenue BuildUp'!$H$44:$Q$44) -> 0.066534834 | N39: =CHOOSE(Assumption!$C$8,'Revenue BuildUp'!$H$42:$Q$42,'Revenue BuildUp'!$H$43:$Q$43,'Revenue BuildUp'!$H$44:$Q$44) -> 0.057219957 | O39: =CHOOSE(Assumption!$C$8,'Revenue BuildUp'!$H$42:$Q$42,'Revenue BuildUp'!$H$43:$Q$43,'Revenue BuildUp'!$H$44:$Q$44) -> 0.049209163 | ... Q39: =CHOOSE(Assumption!$C$8,'Revenue BuildUp'!$H$42:$Q$42,'Revenue BuildUp'!$H$43:$Q$43,'Revenue BuildUp'!$H$44:$Q$44) -> 0.036395097
B41: Scenarios
B42: Best Case | H42: =H43+5% -> 0.19143498 | I42: =H42*(1-$C$45) -> 0.16463408 | J42: =I42*(1-$C$45) -> 0.14158531 | K42: =J42*(1-$C$45) -> 0.12176336 | L42: =K42*(1-$C$45) -> 0.10471649 | M42: =L42*(1-$C$45) -> 0.090056184 | N42: =M42*(1-$C$45) -> 0.077448319 | O42: =N42*(1-$C$45) -> 0.066605554 | P42: =O42*(1-$C$45) -> 0.057280776 | Q42: =P42*(1-$C$45) -> 0.049261468
B43: Base Case | H43: =AVERAGE(E39:G39) -> 0.14143498 | I43: =H43*(1-$C$45) -> 0.12163408 | J43: =I43*(1-$C$45) -> 0.10460531 | K43: =J43*(1-$C$45) -> 0.089960565 | L43: =K43*(1-$C$45) -> 0.077366085 | M43: =L43*(1-$C$45) -> 0.066534834 | N43: =M43*(1-$C$45) -> 0.057219957 | O43: =N43*(1-$C$45) -> 0.049209163 | P43: =O43*(1-$C$45) -> 0.04231988 | Q43: =P43*(1-$C$45) -> 0.036395097
B44: Worst Case | H44: =H43-5% -> 0.091434975 | I44: =H44*(1-$C$45) -> 0.078634079 | J44: =I44*(1-$C$45) -> 0.067625308 | K44: =J44*(1-$C$45) -> 0.058157765 | L44: =K44*(1-$C$45) -> 0.050015677 | M44: =L44*(1-$C$45) -> 0.043013483 | N44: =M44*(1-$C$45) -> 0.036991595 | O44: =N44*(1-$C$45) -> 0.031812772 | P44: =O44*(1-$C$45) -> 0.027358984 | Q44: =P44*(1-$C$45) -> 0.023528726
B45: Annual Trapering | C45: =C35 -> 0.14
B47: Others | C47: 2749 | D47: 6298 | E47: 8885 | F47: 6758 | G47: 24139 | H47: =G47*(1+H49) -> 30173.75 | I47: =H47*(1+I49) -> 36661.106 | J47: =I47*(1+J49) -> 43439.745 | K47: =J47*(1+K49) -> 50347.272 | L47: =K47*(1+L49) -> 57232.365 | M47: =L47*(1+M49) -> 63963.277 | N47: =M47*(1+N49) -> 70432.639 | O47: =N47*(1+O49) -> 76559.007 | ... Q47: =P47*(1+Q49) -> 87579.573
D49: =D47/C47-1 -> 1.2910149 | E49: =E47/D47-1 -> 0.41076532 | F49: =F47/E47-1 -> -0.23939223 | G49: =G47/F47-1 -> 2.5719148 | H49: =CHOOSE(Assumption!$C$8,'Revenue BuildUp'!$H$52:$Q$52,'Revenue BuildUp'!$H$53:$Q$53,'Revenue BuildUp'!$H$54:$Q$54) -> 0.25 | I49: =CHOOSE(Assumption!$C$8,'Revenue BuildUp'!$H$52:$Q$52,'Revenue BuildUp'!$H$53:$Q$53,'Revenue BuildUp'!$H$54:$Q$54) -> 0.215 | J49: =CHOOSE(Assumption!$C$8,'Revenue BuildUp'!$H$52:$Q$52,'Revenue BuildUp'!$H$53:$Q$53,'Revenue BuildUp'!$H$54:$Q$54) -> 0.1849 | K49: =CHOOSE(Assumption!$C$8,'Revenue BuildUp'!$H$52:$Q$52,'Revenue BuildUp'!$H$53:$Q$53,'Revenue BuildUp'!$H$54:$Q$54) -> 0.159014 | L49: =CHOOSE(Assumption!$C$8,'Revenue BuildUp'!$H$52:$Q$52,'Revenue BuildUp'!$H$53:$Q$53,'Revenue BuildUp'!$H$54:$Q$54) -> 0.13675204 | M49: =CHOOSE(Assumption!$C$8,'Revenue BuildUp'!$H$52:$Q$52,'Revenue BuildUp'!$H$53:$Q$53,'Revenue BuildUp'!$H$54:$Q$54) -> 0.11760675 | N49: =CHOOSE(Assumption!$C$8,'Revenue BuildUp'!$H$52:$Q$52,'Revenue BuildUp'!$H$53:$Q$53,'Revenue BuildUp'!$H$54:$Q$54) -> 0.10114181 | O49: =CHOOSE(Assumption!$C$8,'Revenue BuildUp'!$H$52:$Q$52,'Revenue BuildUp'!$H$53:$Q$53,'Revenue BuildUp'!$H$54:$Q$54) -> 0.086981956 | ... Q49: =CHOOSE(Assumption!$C$8,'Revenue BuildUp'!$H$52:$Q$52,'Revenue BuildUp'!$H$53:$Q$53,'Revenue BuildUp'!$H$54:$Q$54) -> 0.064331854
B51: Scenarios
B52: Best Case | H52: =H53+5% -> 0.3 | I52: =H52*(1-$C$55) -> 0.258 | J52: =I52*(1-$C$55) -> 0.22188 | K52: =J52*(1-$C$55) -> 0.1908168 | L52: =K52*(1-$C$55) -> 0.16410245 | M52: =L52*(1-$C$55) -> 0.14112811 | N52: =M52*(1-$C$55) -> 0.12137017 | O52: =N52*(1-$C$55) -> 0.10437835 | P52: =O52*(1-$C$55) -> 0.089765378 | Q52: =P52*(1-$C$55) -> 0.077198225
B53: Base Case | H53: 0.25 | I53: =H53*(1-$C$55) -> 0.215 | J53: =I53*(1-$C$55) -> 0.1849 | K53: =J53*(1-$C$55) -> 0.159014 | L53: =K53*(1-$C$55) -> 0.13675204 | M53: =L53*(1-$C$55) -> 0.11760675 | N53: =M53*(1-$C$55) -> 0.10114181 | O53: =N53*(1-$C$55) -> 0.086981956 | P53: =O53*(1-$C$55) -> 0.074804482 | Q53: =P53*(1-$C$55) -> 0.064331854
B54: Worst Case | H54: =H53-5% -> 0.2 | I54: =H54*(1-$C$55) -> 0.172 | J54: =I54*(1-$C$55) -> 0.14792 | K54: =J54*(1-$C$55) -> 0.1272112 | L54: =K54*(1-$C$55) -> 0.10940163 | M54: =L54*(1-$C$55) -> 0.094085404 | N54: =M54*(1-$C$55) -> 0.080913447 | O54: =N54*(1-$C$55) -> 0.069585564 | P54: =O54*(1-$C$55) -> 0.059843585 | Q54: =P54*(1-$C$55) -> 0.051465483
B55: Annual Trapering | C55: =C35 -> 0.14
B58: Other income | C58: ='Historical P&L'!C11 -> 2424 | D58: ='Historical P&L'!D11 -> 3710 | E58: ='Historical P&L'!E11 -> 2111 | F58: ='Historical P&L'!F11 -> 8537 | G58: ='Historical P&L'!G11 -> 10138 | H58: =H59*H10 -> 9151.9283 | I58: =I59*I10 -> 10905.032 | J58: =J59*J10 -> 12709.759 | K58: =K59*K10 -> 14525.686 | L58: =L59*L10 -> 16316.346 | M58: =M59*M10 -> 18050.931 | N58: =N59*N10 -> 19705.121 | O58: =O59*O10 -> 21261.174 | ... Q58: =Q59*Q10 -> 24037.835
B59: % of Revenue | C59: =C58/C10 -> 0.03134172 | D59: =D58/D10 -> 0.033923102 | E59: =E58/E10 -> 0.014769571 | F59: =F58/F10 -> 0.052546379 | G59: =G58/G10 -> 0.049193533 | H59: =AVERAGE(C59:G59) -> 0.036354861 | I59: =H59 -> 0.036354861 | J59: =I59 -> 0.036354861 | K59: =J59 -> 0.036354861 | L59: =K59 -> 0.036354861 | M59: =L59 -> 0.036354861 | N59: =M59 -> 0.036354861 | O59: =N59 -> 0.036354861 | P59: =O59 -> 0.036354861 | Q59: =P59 -> 0.036354861
B62: Exceptional Items | C62: ='Historical P&L'!C23 -> 0 | D62: ='Historical P&L'!D23 -> -609 | E62: ='Historical P&L'!E23 -> -634 | F62: ='Historical P&L'!F23 -> 1402 | G62: ='Historical P&L'!G23 -> -1216 | H62: =H63*H10 -> -366.29436 | I62: =I63*I10 -> -436.46011 | J62: =J63*J10 -> -508.69203 | K62: =K63*K10 -> -581.37223 | L62: =L63*L10 -> -653.0411 | M62: =M63*M10 -> -722.46567 | N62: =N63*N10 -> -788.67254 | O62: =O63*O10 -> -850.95159 | ... Q62: =Q63*Q10 -> -962.08396
B63: % of Revenue | C63: =C62/C10 -> 0 | D63: =D62/D10 -> -0.0055685091 | E63: =E62/E10 -> -0.0044357688 | F63: =F62/F10 -> 0.0086294979 | G63: =G62/G10 -> -0.0059005066 | H63: =AVERAGE(C63:G63) -> -0.0014550573 | I63: =H63 -> -0.0014550573 | J63: =I63 -> -0.0014550573 | K63: =J63 -> -0.0014550573 | L63: =K63 -> -0.0014550573 | M63: =L63 -> -0.0014550573 | N63: =M63 -> -0.0014550573 | O63: =N63 -> -0.0014550573 | P63: =O63 -> -0.0014550573 | Q63: =P63 -> -0.0014550573

Sheet Common Size Statement
B6: Common Size Statement
B7: (All amounts in INR Lakhs, unless otherwise stated)
B8: Particulars | C8: 2021 | D8: =C8+1 -> 2022 | E8: =D8+1 -> 2023 | F8: =E8+1 -> 2024 | G8: =F8+1 -> 2025 | H8: =G8+1 -> 2026 | I8: =H8+1 -> 2027 | J8: =I8+1 -> 2028 | K8: =J8+1 -> 2029 | ... Q8: =P8+1 -> 2035
C9: Audited | D9: Audited | E9: Audited | F9: Audited | G9: Audited | H9: Estimated | I9: Projected | J9: Projected | K9: Projected | L9: Projected | M9: Projected | N9: Projected | O9: Projected | P9: Projected | Q9: Projected
B11: Revenue | C11: ='Profit & Loss Statement'!C9/'Profit & Loss Statement'!C$9 -> 1 | D11: ='Profit & Loss Statement'!D9/'Profit & Loss Statement'!D$9 -> 1 | E11: ='Profit & Loss Statement'!E9/'Profit & Loss Statement'!E$9 -> 1 | F11: ='Profit & Loss Statement'!F9/'Profit & Loss Statement'!F$9 -> 1 | G11: ='Profit & Loss Statement'!G9/'Profit & Loss Statement'!G$9 -> 1 | H11: ='Profit & Loss Statement'!H9/'Profit & Loss Statement'!H$9 -> 1 | I11: ='Profit & Loss Statement'!I9/'Profit & Loss Statement'!I$9 -> 1 | J11: ='Profit & Loss Statement'!J9/'Profit & Loss Statement'!J$9 -> 1 | ... Q11: ='Profit & Loss Statement'!Q9/'Profit & Loss Statement'!Q$9 -> 1
B13: Expenses
B14: Employee Expenses | C14: ='Profit & Loss Statement'!C14/'Profit & Loss Statement'!C10 -> 0.58491615 | D14: ='Profit & Loss Statement'!D14/'Profit & Loss Statement'!D10 -> 0.56690897 | E14: ='Profit & Loss Statement'!E14/'Profit & Loss Statement'!E10 -> 0.56448307 | F14: ='Profit & Loss Statement'!F14/'Profit & Loss Statement'!F10 -> 0.62455529 | G14: ='Profit & Loss Statement'!G14/'Profit & Loss Statement'!G10 -> 0.66251626 | H14: ='Profit & Loss Statement'!H14/'Profit & Loss Statement'!H10 -> 0.60067595 | I14: ='Profit & Loss Statement'!I14/'Profit & Loss Statement'!I10 -> 0.60067595 | J14: ='Profit & Loss Statement'!J14/'Profit & Loss Statement'!J10 -> 0.60067595 | ... Q14: ='Profit & Loss Statement'!Q14/'Profit & Loss Statement'!Q10 -> 0.60067595
B15: Other expenses | C15: ='Profit & Loss Statement'!C15/'Profit & Loss Statement'!C$9 -> 0.16749202 | D15: ='Profit & Loss Statement'!D15/'Profit & Loss Statement'!D$9 -> 0.19748548 | E15: ='Profit & Loss Statement'!E15/'Profit & Loss Statement'!E$9 -> 0.18444123 | F15: ='Profit & Loss Statement'!F15/'Profit & Loss Statement'!F$9 -> 0.16546231 | G15: ='Profit & Loss Statement'!G15/'Profit & Loss Statement'!G$9 -> 0.15779003 | H15: ='Profit & Loss Statement'!H15/'Profit & Loss Statement'!H$9 -> 0.17453421 | I15: ='Profit & Loss Statement'!I15/'Profit & Loss Statement'!I$9 -> 0.17453421 | J15: ='Profit & Loss Statement'!J15/'Profit & Loss Statement'!J$9 -> 0.17453421 | ... Q15: ='Profit & Loss Statement'!Q15/'Profit & Loss Statement'!Q$9 -> 0.17453421
B16: Impairment loss allowance on trade and unbilled receivables | C16: ='Profit & Loss Statement'!C16/'Profit & Loss Statement'!C$9 -> 0 | D16: ='Profit & Loss Statement'!D16/'Profit & Loss Statement'!D$9 -> 0 | E16: ='Profit & Loss Statement'!E16/'Profit & Loss Statement'!E$9 -> 0 | F16: ='Profit & Loss Statement'!F16/'Profit & Loss Statement'!F$9 -> 0.003262221 | G16: ='Profit & Loss Statement'!G16/'Profit & Loss Statement'!G$9 -> 0.0077153006 | H16: ='Profit & Loss Statement'!H16/'Profit & Loss Statement'!H$9 -> 0.0021955043 | I16: ='Profit & Loss Statement'!I16/'Profit & Loss Statement'!I$9 -> 0.0021955043 | J16: ='Profit & Loss Statement'!J16/'Profit & Loss Statement'!J$9 -> 0.0021955043 | ... Q16: ='Profit & Loss Statement'!Q16/'Profit & Loss Statement'!Q$9 -> 0.0021955043
B17: Total Expenses | C17: ='Profit & Loss Statement'!C17/'Profit & Loss Statement'!C$9 -> 0.75240817 | D17: ='Profit & Loss Statement'!D17/'Profit & Loss Statement'!D$9 -> 0.76439446 | E17: ='Profit & Loss Statement'!E17/'Profit & Loss Statement'!E$9 -> 0.74892429 | F17: ='Profit & Loss Statement'!F17/'Profit & Loss Statement'!F$9 -> 0.79327982 | G17: ='Profit & Loss Statement'!G17/'Profit & Loss Statement'!G$9 -> 0.82802158 | H17: ='Profit & Loss Statement'!H17/'Profit & Loss Statement'!H$9 -> 0.77740566 | I17: ='Profit & Loss Statement'!I17/'Profit & Loss Statement'!I$9 -> 0.77740566 | J17: ='Profit & Loss Statement'!J17/'Profit & Loss Statement'!J$9 -> 0.77740566 | ... Q17: ='Profit & Loss Statement'!Q17/'Profit & Loss Statement'!Q$9 -> 0.77740566
B19: EBITDA | C19: ='Profit & Loss Statement'!C19/'Profit & Loss Statement'!C$9 -> 0.24759183 | D19: ='Profit & Loss Statement'!D19/'Profit & Loss Statement'!D$9 -> 0.23560554 | E19: ='Profit & Loss Statement'!E19/'Profit & Loss Statement'!E$9 -> 0.25107571 | F19: ='Profit & Loss Statement'!F19/'Profit & Loss Statement'!F$9 -> 0.20672018 | G19: ='Profit & Loss Statement'!G19/'Profit & Loss Statement'!G$9 -> 0.17197842 | H19: ='Profit & Loss Statement'!H19/'Profit & Loss Statement'!H$9 -> 0.22259434 | I19: ='Profit & Loss Statement'!I19/'Profit & Loss Statement'!I$9 -> 0.22259434 | J19: ='Profit & Loss Statement'!J19/'Profit & Loss Statement'!J$9 -> 0.22259434 | ... Q19: ='Profit & Loss Statement'!Q19/'Profit & Loss Statement'!Q$9 -> 0.22259434
B21: D&A | C21: ='Profit & Loss Statement'!C21/'Profit & Loss Statement'!C$9 -> 0.029402258 | D21: ='Profit & Loss Statement'!D21/'Profit & Loss Statement'!D$9 -> 0.030064463 | E21: ='Profit & Loss Statement'!E21/'Profit & Loss Statement'!E$9 -> 0.029322251 | F21: ='Profit & Loss Statement'!F21/'Profit & Loss Statement'!F$9 -> 0.035878276 | G21: ='Profit & Loss Statement'!G21/'Profit & Loss Statement'!G$9 -> 0.043040702 | H21: ='Profit & Loss Statement'!H21/'Profit & Loss Statement'!H$9 -> 0.019346245 | I21: ='Profit & Loss Statement'!I21/'Profit & Loss Statement'!I$9 -> 0.016317304 | J21: ='Profit & Loss Statement'!J21/'Profit & Loss Statement'!J$9 -> 0.014070324 | ... Q21: ='Profit & Loss Statement'!Q21/'Profit & Loss Statement'!Q$9 -> 0.0077038618
B23: EBIT | C23: ='Profit & Loss Statement'!C23/'Profit & Loss Statement'!C$9 -> 0.21818958 | D23: ='Profit & Loss Statement'!D23/'Profit & Loss Statement'!D$9 -> 0.20554108 | E23: ='Profit & Loss Statement'!E23/'Profit & Loss Statement'!E$9 -> 0.22175346 | F23: ='Profit & Loss Statement'!F23/'Profit & Loss Statement'!F$9 -> 0.1708419 | G23: ='Profit & Loss Statement'!G23/'Profit & Loss Statement'!G$9 -> 0.12893771 | H23: ='Profit & Loss Statement'!H23/'Profit & Loss Statement'!H$9 -> 0.20324809 | I23: ='Profit & Loss Statement'!I23/'Profit & Loss Statement'!I$9 -> 0.20627703 | J23: ='Profit & Loss Statement'!J23/'Profit & Loss Statement'!J$9 -> 0.20852401 | ... Q23: ='Profit & Loss Statement'!Q23/'Profit & Loss Statement'!Q$9 -> 0.21489047
B25: Finance Cost | C25: ='Profit & Loss Statement'!C25/'Profit & Loss Statement'!C$9 -> 0.0090120376 | D25: ='Profit & Loss Statement'!D25/'Profit & Loss Statement'!D$9 -> 0.0090979747 | E25: ='Profit & Loss Statement'!E25/'Profit & Loss Statement'!E$9 -> 0.015294307 | F25: ='Profit & Loss Statement'!F25/'Profit & Loss Statement'!F$9 -> 0.026017751 | G25: ='Profit & Loss Statement'!G25/'Profit & Loss Statement'!G$9 -> 0.048271579 | H25: ='Profit & Loss Statement'!H25/'Profit & Loss Statement'!H$9 -> 0.02807352 | I25: ='Profit & Loss Statement'!I25/'Profit & Loss Statement'!I$9 -> 0.021552733 | J25: ='Profit & Loss Statement'!J25/'Profit & Loss Statement'!J$9 -> 0.021772634 | ... Q25: ='Profit & Loss Statement'!Q25/'Profit & Loss Statement'!Q$9 -> 0.022788041
B26: Other Income | C26: ='Profit & Loss Statement'!C26/'Profit & Loss Statement'!C$9 -> 0.03134172 | D26: ='Profit & Loss Statement'!D26/'Profit & Loss Statement'!D$9 -> 0.033923102 | E26: ='Profit & Loss Statement'!E26/'Profit & Loss Statement'!E$9 -> 0.014769571 | F26: ='Profit & Loss Statement'!F26/'Profit & Loss Statement'!F$9 -> 0.052546379 | G26: ='Profit & Loss Statement'!G26/'Profit & Loss Statement'!G$9 -> 0.049193533 | H26: ='Profit & Loss Statement'!H26/'Profit & Loss Statement'!H$9 -> 0.036354861 | I26: ='Profit & Loss Statement'!I26/'Profit & Loss Statement'!I$9 -> 0.036354861 | J26: ='Profit & Loss Statement'!J26/'Profit & Loss Statement'!J$9 -> 0.036354861 | ... Q26: ='Profit & Loss Statement'!Q26/'Profit & Loss Statement'!Q$9 -> 0.036354861
B27: Exceptional Items | C27: ='Profit & Loss Statement'!C27/'Profit & Loss Statement'!C$9 -> 0 | D27: ='Profit & Loss Statement'!D27/'Profit & Loss Statement'!D$9 -> -0.0055685091 | E27: ='Profit & Loss Statement'!E27/'Profit & Loss Statement'!E$9 -> -0.0044357688 | F27: ='Profit & Loss Statement'!F27/'Profit & Loss Statement'!F$9 -> 0.0086294979 | G27: ='Profit & Loss Statement'!G27/'Profit & Loss Statement'!G$9 -> -0.0059005066 | H27: ='Profit & Loss Statement'!H27/'Profit & Loss Statement'!H$9 -> -0.0014550573 | I27: ='Profit & Loss Statement'!I27/'Profit & Loss Statement'!I$9 -> -0.0014550573 | J27: ='Profit & Loss Statement'!J27/'Profit & Loss Statement'!J$9 -> -0.0014550573 | ... Q27: ='Profit & Loss Statement'!Q27/'Profit & Loss Statement'!Q$9 -> -0.0014550573
B28: EBT | C28: ='Profit & Loss Statement'!C28/'Profit & Loss Statement'!C$9 -> 0.24051926 | D28: ='Profit & Loss Statement'!D28/'Profit & Loss Statement'!D$9 -> 0.2247977 | E28: ='Profit & Loss Statement'!E28/'Profit & Loss Statement'!E$9 -> 0.21679295 | F28: ='Profit & Loss Statement'!F28/'Profit & Loss Statement'!F$9 -> 0.20600002 | G28: ='Profit & Loss Statement'!G28/'Profit & Loss Statement'!G$9 -> 0.12395916 | H28: ='Profit & Loss Statement'!H28/'Profit & Loss Statement'!H$9 -> 0.21007437 | I28: ='Profit & Loss Statement'!I28/'Profit & Loss Statement'!I$9 -> 0.2196241 | J28: ='Profit & Loss Statement'!J28/'Profit & Loss Statement'!J$9 -> 0.22165118 | ... Q28: ='Profit & Loss Statement'!Q28/'Profit & Loss Statement'!Q$9 -> 0.22700224
B30: Taxes | C30: ='Profit & Loss Statement'!C30/'Profit & Loss Statement'!C$9 -> 0.030462497 | D30: ='Profit & Loss Statement'!D30/'Profit & Loss Statement'!D$9 -> 0.059113976 | E30: ='Profit & Loss Statement'!E30/'Profit & Loss Statement'!E$9 -> 0.055181244 | F30: ='Profit & Loss Statement'!F30/'Profit & Loss Statement'!F$9 -> 0.053112651 | G30: ='Profit & Loss Statement'!G30/'Profit & Loss Statement'!G$9 -> 0.034354923 | H30: ='Profit & Loss Statement'!H30/'Profit & Loss Statement'!H$9 -> 0.059271877 | I30: ='Profit & Loss Statement'!I30/'Profit & Loss Statement'!I$9 -> 0.061966305 | J30: ='Profit & Loss Statement'!J30/'Profit & Loss Statement'!J$9 -> 0.063646495 | ... Q30: ='Profit & Loss Statement'!Q30/'Profit & Loss Statement'!Q$9 -> 0.068100671
B32: Net Profit | C32: ='Profit & Loss Statement'!C32/'Profit & Loss Statement'!C$9 -> 0.21005676 | D32: ='Profit & Loss Statement'!D32/'Profit & Loss Statement'!D$9 -> 0.16568372 | E32: ='Profit & Loss Statement'!E32/'Profit & Loss Statement'!E$9 -> 0.16161171 | F32: ='Profit & Loss Statement'!F32/'Profit & Loss Statement'!F$9 -> 0.15288737 | G32: ='Profit & Loss Statement'!G32/'Profit & Loss Statement'!G$9 -> 0.089604239 | H32: ='Profit & Loss Statement'!H32/'Profit & Loss Statement'!H$9 -> 0.1508025 | I32: ='Profit & Loss Statement'!I32/'Profit & Loss Statement'!I$9 -> 0.1576578 | J32: ='Profit & Loss Statement'!J32/'Profit & Loss Statement'!J$9 -> 0.15800469 | ... Q32: ='Profit & Loss Statement'!Q32/'Profit & Loss Statement'!Q$9 -> 0.15890157
B34: Balance Sheet
B35: Non-current assets
B36: Property, plant and equipment | C36: ='Balance sheet'!C11/'Balance sheet'!C$34 -> 0.056391344 | D36: ='Balance sheet'!D11/'Balance sheet'!D$34 -> 0.070212709 | E36: ='Balance sheet'!E11/'Balance sheet'!E$34 -> 0.17986019 | F36: ='Balance sheet'!F11/'Balance sheet'!F$34 -> 0.12142149 | G36: ='Balance sheet'!G11/'Balance sheet'!G$34 -> 0.13367728 | H36: ='Balance sheet'!H11/'Balance sheet'!H$34 -> 0.14436122 | I36: ='Balance sheet'!I11/'Balance sheet'!I$34 -> 0.1273141 | J36: ='Balance sheet'!J11/'Balance sheet'!J$34 -> 0.11314868 | ... Q36: ='Balance sheet'!Q11/'Balance sheet'!Q$34 -> 0.062906062
B37: Goodwill | C37: ='Balance sheet'!C12/'Balance sheet'!C$34 -> 0.082911221 | D37: ='Balance sheet'!D12/'Balance sheet'!D$34 -> 0.070186043 | E37: ='Balance sheet'!E12/'Balance sheet'!E$34 -> 0.084792453 | F37: ='Balance sheet'!F12/'Balance sheet'!F$34 -> 0.06242576 | G37: ='Balance sheet'!G12/'Balance sheet'!G$34 -> 0.22693849 | H37: ='Balance sheet'!H12/'Balance sheet'!H$34 -> 0.2359752 | I37: ='Balance sheet'!I12/'Balance sheet'!I$34 -> 0.20038628 | J37: ='Balance sheet'!J12/'Balance sheet'!J$34 -> 0.17181312 | ... Q37: ='Balance sheet'!Q12/'Balance sheet'!Q$34 -> 0.076130184
B38: Financial assets
B39: Investments | C39: ='Balance sheet'!C14/'Balance sheet'!C$34 -> 0 | D39: ='Balance sheet'!D14/'Balance sheet'!D$34 -> 0.0067732731 | E39: ='Balance sheet'!E14/'Balance sheet'!E$34 -> 0.0078984416 | F39: ='Balance sheet'!F14/'Balance sheet'!F$34 -> 0 | G39: ='Balance sheet'!G14/'Balance sheet'!G$34 -> 0 | H39: ='Balance sheet'!H14/'Balance sheet'!H$34 -> 0.0024991235 | I39: ='Balance sheet'!I14/'Balance sheet'!I$34 -> 0.002528737 | J39: ='Balance sheet'!J14/'Balance sheet'!J$34 -> 0.0025269834 | ... Q39: ='Balance sheet'!Q14/'Balance sheet'!Q$34 -> 0.0021176831
B40: Other financial assets | C40: ='Balance sheet'!C15/'Balance sheet'!C$34 -> 0.026660882 | D40: ='Balance sheet'!D15/'Balance sheet'!D$34 -> 0.016239856 | E40: ='Balance sheet'!E15/'Balance sheet'!E$34 -> 0.057221041 | F40: ='Balance sheet'!F15/'Balance sheet'!F$34 -> 0.011033059 | G40: ='Balance sheet'!G15/'Balance sheet'!G$34 -> 0.021904938 | H40: ='Balance sheet'!H15/'Balance sheet'!H$34 -> 0.025738731 | I40: ='Balance sheet'!I15/'Balance sheet'!I$34 -> 0.026043724 | J40: ='Balance sheet'!J15/'Balance sheet'!J$34 -> 0.026025664 | ... Q40: ='Balance sheet'!Q15/'Balance sheet'!Q$34 -> 0.021810238
B41: Income tax assets (net | C41: ='Balance sheet'!C16/'Balance sheet'!C$34 -> 0.015271978 | D41: ='Balance sheet'!D16/'Balance sheet'!D$34 -> 0.0060443907 | E41: ='Balance sheet'!E16/'Balance sheet'!E$34 -> 0.0079837643 | F41: ='Balance sheet'!F16/'Balance sheet'!F$34 -> 0.0068022369 | G41: ='Balance sheet'!G16/'Balance sheet'!G$34 -> 0.010529732 | H41: ='Balance sheet'!H16/'Balance sheet'!H$34 -> 0.0093765909 | I41: ='Balance sheet'!I16/'Balance sheet'!I$34 -> 0.0094876994 | J41: ='Balance sheet'!J16/'Balance sheet'!J$34 -> 0.00948112 | ... Q41: ='Balance sheet'!Q16/'Balance sheet'!Q$34 -> 0.0079454452
B42: Other assets | C42: ='Balance sheet'!C17/'Balance sheet'!C$34 -> 7.5926026e-05 | D42: ='Balance sheet'!D17/'Balance sheet'!D$34 -> 8.8888099e-06 | E42: ='Balance sheet'!E17/'Balance sheet'!E$34 -> 0.00072524271 | F42: ='Balance sheet'!F17/'Balance sheet'!F$34 -> 0.00014236205 | G42: ='Balance sheet'!G17/'Balance sheet'!G$34 -> 0.00050609397 | H42: ='Balance sheet'!H17/'Balance sheet'!H$34 -> 0.00030455672 | I42: ='Balance sheet'!I17/'Balance sheet'!I$34 -> 0.00030816559 | J42: ='Balance sheet'!J17/'Balance sheet'!J$34 -> 0.00030795188 | ... Q42: ='Balance sheet'!Q17/'Balance sheet'!Q$34 -> 0.00025807234
B43: Deferred tax assets (net) | C43: ='Balance sheet'!C18/'Balance sheet'!C$34 -> 0.011128586 | D43: ='Balance sheet'!D18/'Balance sheet'!D$34 -> 0.0061955005 | E43: ='Balance sheet'!E18/'Balance sheet'!E$34 -> 0.0075937178 | F43: ='Balance sheet'!F18/'Balance sheet'!F$34 -> 0.00727826 | G43: ='Balance sheet'!G18/'Balance sheet'!G$34 -> 0.010755985 | H43: ='Balance sheet'!H18/'Balance sheet'!H$34 -> 0.0087213586 | I43: ='Balance sheet'!I18/'Balance sheet'!I$34 -> 0.0088247029 | J43: ='Balance sheet'!J18/'Balance sheet'!J$34 -> 0.0088185833 | ... Q43: ='Balance sheet'!Q18/'Balance sheet'!Q$34 -> 0.0073902207
B45: Total non-current assets | C45: ='Balance sheet'!C20/'Balance sheet'!C$34 -> 0.19243994 | D45: ='Balance sheet'!D20/'Balance sheet'!D$34 -> 0.17566066 | E45: ='Balance sheet'!E20/'Balance sheet'!E$34 -> 0.34607485 | F45: ='Balance sheet'!F20/'Balance sheet'!F$34 -> 0.20910316 | G45: ='Balance sheet'!G20/'Balance sheet'!G$34 -> 0.40431252 | H45: ='Balance sheet'!H20/'Balance sheet'!H$34 -> 0.42697678 | I45: ='Balance sheet'!I20/'Balance sheet'!I$34 -> 0.37489341 | J45: ='Balance sheet'!J20/'Balance sheet'!J$34 -> 0.3321221 | ... Q45: ='Balance sheet'!Q20/'Balance sheet'!Q$34 -> 0.17855791
B47: Current assets
B48: Financial assets
B49: Investments | C49: ='Balance sheet'!C24/'Balance sheet'!C$34 -> 0.42462173 | D49: ='Balance sheet'!D24/'Balance sheet'!D$34 -> 0.41244078 | E49: ='Balance sheet'!E24/'Balance sheet'!E$34 -> 0 | F49: ='Balance sheet'!F24/'Balance sheet'!F$34 -> 0 | G49: ='Balance sheet'!G24/'Balance sheet'!G$34 -> 0.10431192 | H49: ='Balance sheet'!H24/'Balance sheet'!H$34 -> 0.28585463 | I49: ='Balance sheet'!I24/'Balance sheet'!I$34 -> 0.28924189 | J49: ='Balance sheet'!J24/'Balance sheet'!J$34 -> 0.28904131 | ... Q49: ='Balance sheet'!Q24/'Balance sheet'!Q$34 -> 0.24222474
B50: Trade receivables | C50: ='Balance sheet'!C25/'Balance sheet'!C$34 -> 0.13224144 | D50: ='Balance sheet'!D25/'Balance sheet'!D$34 -> 0.1487809 | E50: ='Balance sheet'!E25/'Balance sheet'!E$34 -> 0.12992815 | F50: ='Balance sheet'!F25/'Balance sheet'!F$34 -> 0.11319563 | G50: ='Balance sheet'!G25/'Balance sheet'!G$34 -> 0.10661614 | H50: ='Balance sheet'!H25/'Balance sheet'!H$34 -> 0.12316195 | I50: ='Balance sheet'!I25/'Balance sheet'!I$34 -> 0.12462137 | J50: ='Balance sheet'!J25/'Balance sheet'!J$34 -> 0.12453495 | ... Q50: ='Balance sheet'!Q25/'Balance sheet'!Q$34 -> 0.10436379
B51: Cash and cash equivalents | C51: ='Balance sheet'!C26/'Balance sheet'!C$34 -> 0.093096155 | D51: ='Balance sheet'!D26/'Balance sheet'!D$34 -> 0.059812802 | E51: ='Balance sheet'!E26/'Balance sheet'!E$34 -> -0.00073133719 | F51: ='Balance sheet'!F26/'Balance sheet'!F$34 -> 0.048478728 | G51: ='Balance sheet'!G26/'Balance sheet'!G$34 -> 0.035462302 | H51: ='Balance sheet'!H26/'Balance sheet'!H$34 -> 0.074497051 | I51: ='Balance sheet'!I26/'Balance sheet'!I$34 -> 0.12067311 | J51: ='Balance sheet'!J26/'Balance sheet'!J$34 -> 0.16379422 | ... Q51: ='Balance sheet'!Q26/'Balance sheet'!Q$34 -> 0.3990058
B52: Bank balance other than cash and cash equivalents | C52: ='Balance sheet'!C27/'Balance sheet'!C$34 -> 0.064374424 | D52: ='Balance sheet'!D27/'Balance sheet'!D$34 -> 0.089519204 | E52: ='Balance sheet'!E27/'Balance sheet'!E$34 -> 0.42236551 | F52: ='Balance sheet'!F27/'Balance sheet'!F$34 -> 0.54611863 | G52: ='Balance sheet'!G27/'Balance sheet'!G$34 -> 0.27957524 | H52: ='Balance sheet'!H27/'Balance sheet'!H$34 -> 0 | I52: ='Balance sheet'!I27/'Balance sheet'!I$34 -> 0 | J52: ='Balance sheet'!J27/'Balance sheet'!J$34 -> 0 | ... Q52: ='Balance sheet'!Q27/'Balance sheet'!Q$34 -> 0
B53: Loans | C53: ='Balance sheet'!C28/'Balance sheet'!C$34 -> 0.00015185205 | D53: ='Balance sheet'!D28/'Balance sheet'!D$34 -> 3.555524e-05 | E53: ='Balance sheet'!E28/'Balance sheet'!E$34 -> 0.0003900465 | F53: ='Balance sheet'!F28/'Balance sheet'!F$34 -> 0.00016460612 | G53: ='Balance sheet'!G28/'Balance sheet'!G$34 -> 3.572428e-05 | H53: ='Balance sheet'!H28/'Balance sheet'!H$34 -> 0.00014827021 | I53: ='Balance sheet'!I28/'Balance sheet'!I$34 -> 0.00015002715 | J53: ='Balance sheet'!J28/'Balance sheet'!J$34 -> 0.00014992311 | ... Q53: ='Balance sheet'!Q28/'Balance sheet'!Q$34 -> 0.00012563978
B54: Other financial assets | C54: ='Balance sheet'!C29/'Balance sheet'!C$34 -> 0.073528933 | D54: ='Balance sheet'!D29/'Balance sheet'!D$34 -> 0.083599257 | E54: ='Balance sheet'!E29/'Balance sheet'!E$34 -> 0.07457811 | F54: ='Balance sheet'!F29/'Balance sheet'!F$34 -> 0.061616076 | G54: ='Balance sheet'!G29/'Balance sheet'!G$34 -> 0.052770716 | H54: ='Balance sheet'!H29/'Balance sheet'!H$34 -> 0.067099483 | I54: ='Balance sheet'!I29/'Balance sheet'!I$34 -> 0.067894583 | J54: ='Balance sheet'!J29/'Balance sheet'!J$34 -> 0.0678475 | ... Q54: ='Balance sheet'!Q29/'Balance sheet'!Q$34 -> 0.056858113
B55: Other assets | C55: ='Balance sheet'!C30/'Balance sheet'!C$34 -> 0.019545528 | D55: ='Balance sheet'!D30/'Balance sheet'!D$34 -> 0.030150843 | E55: ='Balance sheet'!E30/'Balance sheet'!E$34 -> 0.027394672 | F55: ='Balance sheet'!F30/'Balance sheet'!F$34 -> 0.021323166 | G55: ='Balance sheet'!G30/'Balance sheet'!G$34 -> 0.016915447 | H55: ='Balance sheet'!H30/'Balance sheet'!H$34 -> 0.022261827 | I55: ='Balance sheet'!I30/'Balance sheet'!I$34 -> 0.02252562 | J55: ='Balance sheet'!J30/'Balance sheet'!J$34 -> 0.022509999 | ... Q55: ='Balance sheet'!Q30/'Balance sheet'!Q$34 -> 0.018864012
B57: Total current assets | C57: ='Balance sheet'!C32/'Balance sheet'!C$34 -> 0.80756006 | D57: ='Balance sheet'!D32/'Balance sheet'!D$34 -> 0.82433934 | E57: ='Balance sheet'!E32/'Balance sheet'!E$34 -> 0.65392515 | F57: ='Balance sheet'!F32/'Balance sheet'!F$34 -> 0.79089684 | G57: ='Balance sheet'!G32/'Balance sheet'!G$34 -> 0.59568748 | H57: ='Balance sheet'!H32/'Balance sheet'!H$34 -> 0.57302322 | I57: ='Balance sheet'!I32/'Balance sheet'!I$34 -> 0.62510659 | J57: ='Balance sheet'!J32/'Balance sheet'!J$34 -> 0.6678779 | ... Q57: ='Balance sheet'!Q32/'Balance sheet'!Q$34 -> 0.82144209
B59: Total Assets | C59: ='Balance sheet'!C34/'Balance sheet'!C$34 -> 1 | D59: ='Balance sheet'!D34/'Balance sheet'!D$34 -> 1 | E59: ='Balance sheet'!E34/'Balance sheet'!E$34 -> 1 | F59: ='Balance sheet'!F34/'Balance sheet'!F$34 -> 1 | G59: ='Balance sheet'!G34/'Balance sheet'!G$34 -> 1 | H59: ='Balance sheet'!H34/'Balance sheet'!H$34 -> 1 | I59: ='Balance sheet'!I34/'Balance sheet'!I$34 -> 1 | J59: ='Balance sheet'!J34/'Balance sheet'!J$34 -> 1 | ... Q59: ='Balance sheet'!Q34/'Balance sheet'!Q$34 -> 1
B61: Equity and liabilities
B62: Equity
B63: Equity share capital | C63: ='Balance sheet'!C38/'Balance sheet'!C$34 -> 0.030771734 | D63: ='Balance sheet'!D38/'Balance sheet'!D$34 -> 0.025368663 | E63: ='Balance sheet'!E38/'Balance sheet'!E$34 -> 0.01746677 | F63: ='Balance sheet'!F38/'Balance sheet'!F$34 -> 0.013288608 | G63: ='Balance sheet'!G38/'Balance sheet'!G$34 -> 0.008934047 | H63: ='Balance sheet'!H38/'Balance sheet'!H$34 -> 0.0092898015 | I63: ='Balance sheet'!I38/'Balance sheet'!I$34 -> 0.0078887474 | J63: ='Balance sheet'!J38/'Balance sheet'!J$34 -> 0.0067638879 | ... Q63: ='Balance sheet'!Q38/'Balance sheet'!Q$34 -> 0.0029970705
B64: Other equity | C64: ='Balance sheet'!C39/'Balance sheet'!C$34 -> 0.56144043 | D64: ='Balance sheet'!D39/'Balance sheet'!D$34 -> 0.5664483 | E64: ='Balance sheet'!E39/'Balance sheet'!E$34 -> 0.49375011 | F64: ='Balance sheet'!F39/'Balance sheet'!F$34 -> 0.64524266 | G64: ='Balance sheet'!G39/'Balance sheet'!G$34 -> 0.45982209 | H64: ='Balance sheet'!H39/'Balance sheet'!H$34 -> 0.55346605 | I64: ='Balance sheet'!I39/'Balance sheet'!I$34 -> 0.54968595 | J64: ='Balance sheet'!J39/'Balance sheet'!J$34 -> 0.55111762 | ... Q64: ='Balance sheet'!Q39/'Balance sheet'!Q$34 -> 0.6264952
B65: Total equity | C65: ='Balance sheet'!C40/'Balance sheet'!C$34 -> 0.59221216 | D65: ='Balance sheet'!D40/'Balance sheet'!D$34 -> 0.59181696 | E65: ='Balance sheet'!E40/'Balance sheet'!E$34 -> 0.51121688 | F65: ='Balance sheet'!F40/'Balance sheet'!F$34 -> 0.65853127 | G65: ='Balance sheet'!G40/'Balance sheet'!G$34 -> 0.46875614 | H65: ='Balance sheet'!H40/'Balance sheet'!H$34 -> 0.56275585 | I65: ='Balance sheet'!I40/'Balance sheet'!I$34 -> 0.5575747 | J65: ='Balance sheet'!J40/'Balance sheet'!J$34 -> 0.55788151 | ... Q65: ='Balance sheet'!Q40/'Balance sheet'!Q$34 -> 0.62949227
B67: Liabilities
B68: Non-current liabilities
B69: Financial liabilities
B70: Borrowings | C70: ='Balance sheet'!C45/'Balance sheet'!C$34 -> 0.039709312 | D70: ='Balance sheet'!D45/'Balance sheet'!D$34 -> 0.015324308 | E70: ='Balance sheet'!E45/'Balance sheet'!E$34 -> 0.068733507 | F70: ='Balance sheet'!F45/'Balance sheet'!F$34 -> 0.046467864 | G70: ='Balance sheet'!G45/'Balance sheet'!G$34 -> 0.099840432 | H70: ='Balance sheet'!H45/'Balance sheet'!H$34 -> 0.057515279 | I70: ='Balance sheet'!I45/'Balance sheet'!I$34 -> 0.05819681 | J70: ='Balance sheet'!J45/'Balance sheet'!J$34 -> 0.058156452 | ... Q70: ='Balance sheet'!Q45/'Balance sheet'!Q$34 -> 0.048736742
B71: Lease liabilities | C71: ='Balance sheet'!C46/'Balance sheet'!C$34 -> 0.013265361 | D71: ='Balance sheet'!D46/'Balance sheet'!D$34 -> 0.036613008 | E71: ='Balance sheet'!E46/'Balance sheet'!E$34 -> 0.029015803 | F71: ='Balance sheet'!F46/'Balance sheet'!F$34 -> 0.020331081 | G71: ='Balance sheet'!G46/'Balance sheet'!G$34 -> 0.014914887 | H71: ='Balance sheet'!H46/'Balance sheet'!H$34 -> 0.021699003 | I71: ='Balance sheet'!I46/'Balance sheet'!I$34 -> 0.021956127 | J71: ='Balance sheet'!J46/'Balance sheet'!J$34 -> 0.021940901 | ... Q71: ='Balance sheet'!Q46/'Balance sheet'!Q$34 -> 0.018387092
B72: Other financial liabilities | C72: ='Balance sheet'!C47/'Balance sheet'!C$34 -> 0.026628342 | D72: ='Balance sheet'!D47/'Balance sheet'!D$34 -> 0.011475454 | E72: ='Balance sheet'!E47/'Balance sheet'!E$34 -> 0.012164575 | F72: ='Balance sheet'!F47/'Balance sheet'!F$34 -> 0.0017839745 | G72: ='Balance sheet'!G47/'Balance sheet'!G$34 -> 0.024798604 | H72: ='Balance sheet'!H47/'Balance sheet'!H$34 -> 0.015647936 | I72: ='Balance sheet'!I47/'Balance sheet'!I$34 -> 0.015833357 | J72: ='Balance sheet'!J47/'Balance sheet'!J$34 -> 0.015822377 | ... Q72: ='Balance sheet'!Q47/'Balance sheet'!Q$34 -> 0.013259597
B73: Provisions | C73: ='Balance sheet'!C48/'Balance sheet'!C$34 -> 0.017929389 | D73: ='Balance sheet'!D48/'Balance sheet'!D$34 -> 0.014382094 | E73: ='Balance sheet'!E48/'Balance sheet'!E$34 -> 0.015028979 | F73: ='Balance sheet'!F48/'Balance sheet'!F$34 -> 0.014850142 | G73: ='Balance sheet'!G48/'Balance sheet'!G$34 -> 0.017683519 | H73: ='Balance sheet'!H48/'Balance sheet'!H$34 -> 0.016020287 | I73: ='Balance sheet'!I48/'Balance sheet'!I$34 -> 0.016210121 | J73: ='Balance sheet'!J48/'Balance sheet'!J$34 -> 0.016198879 | ... Q73: ='Balance sheet'!Q48/'Balance sheet'!Q$34 -> 0.013575116
B74: Deferred tax liabilities (net | C74: ='Balance sheet'!C49/'Balance sheet'!C$34 -> 0.007863767 | D74: ='Balance sheet'!D49/'Balance sheet'!D$34 -> 0.004159963 | E74: ='Balance sheet'!E49/'Balance sheet'!E$34 -> 0.012554622 | F74: ='Balance sheet'!F49/'Balance sheet'!F$34 -> 0.0057968049 | G74: ='Balance sheet'!G49/'Balance sheet'!G$34 -> 0.01441177 | H74: ='Balance sheet'!H49/'Balance sheet'!H$34 -> 0.0092853119 | I74: ='Balance sheet'!I49/'Balance sheet'!I$34 -> 0.0093953387 | J74: ='Balance sheet'!J49/'Balance sheet'!J$34 -> 0.0093888234 | ... Q74: ='Balance sheet'!Q49/'Balance sheet'!Q$34 -> 0.007868098
B76: Total non-current liabilities | C76: ='Balance sheet'!C51/'Balance sheet'!C$34 -> 0.10539617 | D76: ='Balance sheet'!D51/'Balance sheet'!D$34 -> 0.081954827 | E76: ='Balance sheet'!E51/'Balance sheet'!E$34 -> 0.13749749 | F76: ='Balance sheet'!F51/'Balance sheet'!F$34 -> 0.089229866 | G76: ='Balance sheet'!G51/'Balance sheet'!G$34 -> 0.17164921 | H76: ='Balance sheet'!H51/'Balance sheet'!H$34 -> 0.12016782 | I76: ='Balance sheet'!I51/'Balance sheet'!I$34 -> 0.12159175 | J76: ='Balance sheet'!J51/'Balance sheet'!J$34 -> 0.12150743 | ... Q76: ='Balance sheet'!Q51/'Balance sheet'!Q$34 -> 0.10182665
B78: Current liabilities
B79: Contract liabilities | C79: ='Balance sheet'!C54/'Balance sheet'!C$34 -> 0.0073105917 | D79: ='Balance sheet'!D54/'Balance sheet'!D$34 -> 0.011964338 | E79: ='Balance sheet'!E54/'Balance sheet'!E$34 -> 0.0070513094 | F79: ='Balance sheet'!F54/'Balance sheet'!F$34 -> 0.0081190859 | G79: ='Balance sheet'!G54/'Balance sheet'!G$34 -> 0.0065315892 | H79: ='Balance sheet'!H54/'Balance sheet'!H$34 -> 0.0079480182 | I79: ='Balance sheet'!I54/'Balance sheet'!I$34 -> 0.0080421988 | J79: ='Balance sheet'!J54/'Balance sheet'!J$34 -> 0.0080366218 | ... Q79: ='Balance sheet'!Q54/'Balance sheet'!Q$34 -> 0.006734915
B80: Financial liabilities
B81: Borrowings | C81: ='Balance sheet'!C56/'Balance sheet'!C$34 -> 0.14066923 | D81: ='Balance sheet'!D56/'Balance sheet'!D$34 -> 0.15413196 | E81: ='Balance sheet'!E56/'Balance sheet'!E$34 -> 0.21621375 | F81: ='Balance sheet'!F56/'Balance sheet'!F$34 -> 0.15033433 | G81: ='Balance sheet'!G56/'Balance sheet'!G$34 -> 0.24576518 | H81: ='Balance sheet'!H56/'Balance sheet'!H$34 -> 0.1843811 | I81: ='Balance sheet'!I56/'Balance sheet'!I$34 -> 0.18656594 | J81: ='Balance sheet'!J56/'Balance sheet'!J$34 -> 0.18643656 | ... Q81: ='Balance sheet'!Q56/'Balance sheet'!Q$34 -> 0.15623908
B82: Lease liabilities | C82: ='Balance sheet'!C57/'Balance sheet'!C$34 -> 0.01542383 | D82: ='Balance sheet'!D57/'Balance sheet'!D$34 -> 0.015928747 | E82: ='Balance sheet'!E57/'Balance sheet'!E$34 -> 0.011329632 | F82: ='Balance sheet'!F57/'Balance sheet'!F$34 -> 0.01073054 | G82: ='Balance sheet'!G57/'Balance sheet'!G$34 -> 0.009699142 | H82: ='Balance sheet'!H57/'Balance sheet'!H$34 -> 0.012224222 | I82: ='Balance sheet'!I57/'Balance sheet'!I$34 -> 0.012369074 | J82: ='Balance sheet'!J57/'Balance sheet'!J$34 -> 0.012360496 | ... Q82: ='Balance sheet'!Q57/'Balance sheet'!Q$34 -> 0.010358444
B83: Trade payables | C83: ='Balance sheet'!C58/'Balance sheet'!C$34 -> 0.048798742 | D83: ='Balance sheet'!D58/'Balance sheet'!D$34 -> 0.053972854 | E83: ='Balance sheet'!E58/'Balance sheet'!E$34 -> 0.042978249 | F83: ='Balance sheet'!F58/'Balance sheet'!F$34 -> 0.035212364 | G83: ='Balance sheet'!G58/'Balance sheet'!G$34 -> 0.031202182 | H83: ='Balance sheet'!H58/'Balance sheet'!H$34 -> 0.040928508 | I83: ='Balance sheet'!I58/'Balance sheet'!I$34 -> 0.041413493 | J83: ='Balance sheet'!J58/'Balance sheet'!J$34 -> 0.041384774 | ... Q83: ='Balance sheet'!Q58/'Balance sheet'!Q$34 -> 0.034681605
B84: Other financial liabilities | C84: ='Balance sheet'!C59/'Balance sheet'!C$34 -> 0.052898747 | D84: ='Balance sheet'!D59/'Balance sheet'!D$34 -> 0.051448432 | E84: ='Balance sheet'!E59/'Balance sheet'!E$34 -> 0.045269772 | F84: ='Balance sheet'!F59/'Balance sheet'!F$34 -> 0.02584761 | G84: ='Balance sheet'!G59/'Balance sheet'!G$34 -> 0.043244241 | H84: ='Balance sheet'!H59/'Balance sheet'!H$34 -> 0.042735284 | I84: ='Balance sheet'!I59/'Balance sheet'!I$34 -> 0.043241679 | J84: ='Balance sheet'!J59/'Balance sheet'!J$34 -> 0.043211692 | ... Q84: ='Balance sheet'!Q59/'Balance sheet'!Q$34 -> 0.036212613
B85: Income tax liabilities (net) | C85: ='Balance sheet'!C60/'Balance sheet'!C$34 -> 0 | D85: ='Balance sheet'!D60/'Balance sheet'!D$34 -> 0.0021244256 | E85: ='Balance sheet'!E60/'Balance sheet'!E$34 -> 0.0031508444 | F85: ='Balance sheet'!F60/'Balance sheet'!F$34 -> 5.338577e-05 | G85: ='Balance sheet'!G60/'Balance sheet'!G$34 -> 0.0012563038 | H85: ='Balance sheet'!H60/'Balance sheet'!H$34 -> 0.0012350091 | I85: ='Balance sheet'!I60/'Balance sheet'!I$34 -> 0.0012496434 | J85: ='Balance sheet'!J60/'Balance sheet'!J$34 -> 0.0012487768 | ... Q85: ='Balance sheet'!Q60/'Balance sheet'!Q$34 -> 0.0010465101
B86: Other current liabilities | C86: ='Balance sheet'!C61/'Balance sheet'!C$34 -> 0.02093389 | D86: ='Balance sheet'!D61/'Balance sheet'!D$34 -> 0.021564253 | E86: ='Balance sheet'!E61/'Balance sheet'!E$34 -> 0.014474382 | F86: ='Balance sheet'!F61/'Balance sheet'!F$34 -> 0.012438884 | G86: ='Balance sheet'!G61/'Balance sheet'!G$34 -> 0.011419862 | H86: ='Balance sheet'!H61/'Balance sheet'!H$34 -> 0.015519596 | I86: ='Balance sheet'!I61/'Balance sheet'!I$34 -> 0.015703497 | J86: ='Balance sheet'!J61/'Balance sheet'!J$34 -> 0.015692607 | ... Q86: ='Balance sheet'!Q61/'Balance sheet'!Q$34 -> 0.013150846
B87: Provisions | C87: ='Balance sheet'!C62/'Balance sheet'!C$34 -> 0.016356635 | D87: ='Balance sheet'!D62/'Balance sheet'!D$34 -> 0.015093199 | E87: ='Balance sheet'!E62/'Balance sheet'!E$34 -> 0.010817696 | F87: ='Balance sheet'!F62/'Balance sheet'!F$34 -> 0.0095026671 | G87: ='Balance sheet'!G62/'Balance sheet'!G$34 -> 0.010476145 | H87: ='Balance sheet'!H62/'Balance sheet'!H$34 -> 0.012104589 | I87: ='Balance sheet'!I62/'Balance sheet'!I$34 -> 0.012248023 | J87: ='Balance sheet'!J62/'Balance sheet'!J$34 -> 0.012239529 | ... Q87: ='Balance sheet'!Q62/'Balance sheet'!Q$34 -> 0.01025707
C88: ='Balance sheet'!C63/'Balance sheet'!C$34 -> 0 | D88: ='Balance sheet'!D63/'Balance sheet'!D$34 -> 0 | E88: ='Balance sheet'!E63/'Balance sheet'!E$34 -> 0 | F88: ='Balance sheet'!F63/'Balance sheet'!F$34 -> 0 | G88: ='Balance sheet'!G63/'Balance sheet'!G$34 -> 0 | H88: ='Balance sheet'!H63/'Balance sheet'!H$34 -> 0 | I88: ='Balance sheet'!I63/'Balance sheet'!I$34 -> 0 | J88: ='Balance sheet'!J63/'Balance sheet'!J$34 -> 0 | ... Q88: ='Balance sheet'!Q63/'Balance sheet'!Q$34 -> 0
B89: Total current liabilities | C89: ='Balance sheet'!C64/'Balance sheet'!C$34 -> 0.30239167 | D89: ='Balance sheet'!D64/'Balance sheet'!D$34 -> 0.32622821 | E89: ='Balance sheet'!E64/'Balance sheet'!E$34 -> 0.35128563 | F89: ='Balance sheet'!F64/'Balance sheet'!F$34 -> 0.25223887 | G89: ='Balance sheet'!G64/'Balance sheet'!G$34 -> 0.35959465 | H89: ='Balance sheet'!H64/'Balance sheet'!H$34 -> 0.31707633 | I89: ='Balance sheet'!I64/'Balance sheet'!I$34 -> 0.32083355 | J89: ='Balance sheet'!J64/'Balance sheet'!J$34 -> 0.32061106 | ... Q89: ='Balance sheet'!Q64/'Balance sheet'!Q$34 -> 0.26868108
B91: Total liabilities | C91: ='Balance sheet'!C66/'Balance sheet'!C$34 -> 0.40778784 | D91: ='Balance sheet'!D66/'Balance sheet'!D$34 -> 0.40818304 | E91: ='Balance sheet'!E66/'Balance sheet'!E$34 -> 0.48878312 | F91: ='Balance sheet'!F66/'Balance sheet'!F$34 -> 0.34146873 | G91: ='Balance sheet'!G66/'Balance sheet'!G$34 -> 0.53124386 | H91: ='Balance sheet'!H66/'Balance sheet'!H$34 -> 0.43724415 | I91: ='Balance sheet'!I66/'Balance sheet'!I$34 -> 0.4424253 | J91: ='Balance sheet'!J66/'Balance sheet'!J$34 -> 0.44211849 | ... Q91: ='Balance sheet'!Q66/'Balance sheet'!Q$34 -> 0.37050773
B93: Total equity and liabilities | C93: ='Balance sheet'!C68/'Balance sheet'!C$34 -> 1 | D93: ='Balance sheet'!D68/'Balance sheet'!D$34 -> 1 | E93: ='Balance sheet'!E68/'Balance sheet'!E$34 -> 1 | F93: ='Balance sheet'!F68/'Balance sheet'!F$34 -> 1 | G93: ='Balance sheet'!G68/'Balance sheet'!G$34 -> 1 | H93: ='Balance sheet'!H68/'Balance sheet'!H$34 -> 1 | I93: ='Balance sheet'!I68/'Balance sheet'!I$34 -> 1 | J93: ='Balance sheet'!J68/'Balance sheet'!J$34 -> 1 | ... Q93: ='Balance sheet'!Q68/'Balance sheet'!Q$34 -> 1

Sheet Cost Buildup
B5: Cost Build_Up
B6: (All amounts in INR Lakhs, unless otherwise stated)
A7: # | B7: Particulars | C7: 2021 | D7: =C7+1 -> 2022 | E7: =D7+1 -> 2023 | F7: =E7+1 -> 2024 | G7: =F7+1 -> 2025 | H7: =G7+1 -> 2026 | I7: =H7+1 -> 2027 | J7: =I7+1 -> 2028 | K7: =J7+1 -> 2029 | ... Q7: =P7+1 -> 2035
C8: Audited | D8: Audited | E8: Audited | F8: Audited | G8: Audited | H8: Estimated | I8: Projected | J8: Projected | K8: Projected | L8: Projected | M8: Projected | N8: Projected | O8: Projected | P8: Projected | Q8: Projected
B10: Revenue | C10: ='Revenue BuildUp'!C10 -> 77341 | D10: ='Revenue BuildUp'!D10 -> 109365 | E10: ='Revenue BuildUp'!E10 -> 142929 | F10: ='Revenue BuildUp'!F10 -> 162466 | G10: ='Revenue BuildUp'!G10 -> 206084 | H10: ='Revenue BuildUp'!H10 -> 251738.78 | I10: ='Revenue BuildUp'!I10 -> 299960.77 | J10: ='Revenue BuildUp'!J10 -> 349602.74 | ... Q10: ='Revenue BuildUp'!Q10 -> 661200.04
B13: Employee benefits expense | C13: ='Historical P&L'!C15 -> 45238 | D13: ='Historical P&L'!D15 -> 62000 | E13: ='Historical P&L'!E15 -> 80681 | F13: ='Historical P&L'!F15 -> 101469 | G13: ='Historical P&L'!G15 -> 136534 | H13: =H14*H10 -> 151213.43 | I13: =I14*I10 -> 180179.22 | J13: =J14*J10 -> 209997.96 | K13: =K14*K10 -> 240001.76 | L13: =L14*L10 -> 269588.06 | M13: =M14*M10 -> 298247.87 | N13: =N14*N10 -> 325579.35 | O13: =O14*O10 -> 351289.36 | ... Q13: =Q14*Q10 -> 397166.96
B14: % of Revenue | C14: =C13/C10 -> 0.58491615 | D14: =D13/D10 -> 0.56690897 | E14: =E13/E10 -> 0.56448307 | F14: =F13/F10 -> 0.62455529 | G14: =G13/G10 -> 0.66251626 | H14: =AVERAGE(C14:G14) -> 0.60067595 | I14: =H14 -> 0.60067595 | J14: =I14 -> 0.60067595 | K14: =J14 -> 0.60067595 | L14: =K14 -> 0.60067595 | M14: =L14 -> 0.60067595 | N14: =M14 -> 0.60067595 | O14: =N14 -> 0.60067595 | P14: =O14 -> 0.60067595 | Q14: =P14 -> 0.60067595
B16: Other expenses | C16: ='Historical P&L'!C18 -> 12954 | D16: ='Historical P&L'!D18 -> 21598 | E16: ='Historical P&L'!E18 -> 26362 | F16: ='Historical P&L'!F18 -> 26882 | G16: ='Historical P&L'!G18 -> 32518 | H16: =H17*H10 -> 43937.03 | I16: =I17*I10 -> 52353.416 | J16: =J17*J10 -> 61017.639 | K16: =K17*K10 -> 69735.634 | L16: =L17*L10 -> 78332.319 | M16: =M17*M10 -> 86659.8 | N16: =N17*N10 -> 94601.318 | O16: =O17*O10 -> 102071.69 | ... Q16: =Q17*Q10 -> 115402.03
B17: % of Revenue | C17: =C16/C10 -> 0.16749202 | D17: =D16/D10 -> 0.19748548 | E17: =E16/E10 -> 0.18444123 | F17: =F16/F10 -> 0.16546231 | G17: =G16/G10 -> 0.15779003 | H17: =AVERAGE(C17:G17) -> 0.17453421 | I17: =H17 -> 0.17453421 | J17: =I17 -> 0.17453421 | K17: =J17 -> 0.17453421 | L17: =K17 -> 0.17453421 | M17: =L17 -> 0.17453421 | N17: =M17 -> 0.17453421 | O17: =N17 -> 0.17453421 | P17: =O17 -> 0.17453421 | Q17: =P17 -> 0.17453421
B19: Impairment loss allowance on trade and unbilled receivables | C19: ='Historical P&L'!C19 -> 0 | D19: ='Historical P&L'!D19 -> 0 | E19: ='Historical P&L'!E19 -> 0 | F19: ='Historical P&L'!F19 -> 530 | G19: ='Historical P&L'!G19 -> 1590 | H19: =H20*H10 -> 552.69358 | I19: =I20*I10 -> 658.56516 | J19: =J20*J10 -> 767.55433 | K19: =K20*K10 -> 877.2199 | L19: =L20*L10 -> 985.3595 | M19: =M20*M10 -> 1090.1127 | N19: =N20*N10 -> 1190.0108 | O19: =O20*O10 -> 1283.9823 | ... Q19: =Q20*Q10 -> 1451.6675
B20: % of Revenue | C20: =C19/C10 -> 0 | D20: =D19/D10 -> 0 | E20: =E19/E10 -> 0 | F20: =F19/F10 -> 0.003262221 | G20: =G19/G10 -> 0.0077153006 | H20: =AVERAGE(C20:G20) -> 0.0021955043 | I20: =H20 -> 0.0021955043 | J20: =I20 -> 0.0021955043 | K20: =J20 -> 0.0021955043 | L20: =K20 -> 0.0021955043 | M20: =L20 -> 0.0021955043 | N20: =M20 -> 0.0021955043 | O20: =N20 -> 0.0021955043 | P20: =O20 -> 0.0021955043 | Q20: =P20 -> 0.0021955043
B22: Taxes | C22: ='Historical P&L'!C27+'Historical P&L'!C28+'Historical P&L'!C29 -> 2356 | D22: ='Historical P&L'!D27+'Historical P&L'!D28+'Historical P&L'!D29 -> 6465 | E22: ='Historical P&L'!E27+'Historical P&L'!E28+'Historical P&L'!E29 -> 7887 | F22: ='Historical P&L'!F27+'Historical P&L'!F28+'Historical P&L'!F29 -> 8629 | G22: ='Historical P&L'!G27+'Historical P&L'!G28+'Historical P&L'!G29 -> 7080 | H22: =H23*'Profit & Loss Statement'!H28 -> 14921.03 | I22: =I23*'Profit & Loss Statement'!I28 -> 18587.46 | J22: =J23*'Profit & Loss Statement'!J28 -> 22250.989 | K22: =K23*'Profit & Loss Statement'!K28 -> 25602.055 | L22: =L23*'Profit & Loss Statement'!L28 -> 29406.275 | M22: =M23*'Profit & Loss Statement'!M28 -> 32656.288 | N22: =N23*'Profit & Loss Statement'!N28 -> 36364.659 | O22: =O23*'Profit & Loss Statement'!O28 -> 39324.647 | ... Q22: =Q23*'Profit & Loss Statement'!Q28 -> 45028.166
B23: % of EBT | C23: =C22/'Historical P&L'!C24 -> 0.12665305 | D23: =D22/'Historical P&L'!D24 -> 0.26296522 | E23: =E22/'Historical P&L'!E24 -> 0.25453431 | F23: =F22/'Historical P&L'!F24 -> 0.25782837 | G23: =G22/'Historical P&L'!G24 -> 0.27714711 | H23: =G23+Assumption!C15 -> 0.28214711 | I23: =H23 -> 0.28214711 | J23: =I23+Assumption!C15 -> 0.28714711 | K23: =J23 -> 0.28714711 | L23: =K23+Assumption!C15 -> 0.29214711 | M23: =L23 -> 0.29214711 | N23: =M23+Assumption!C15 -> 0.29714711 | O23: =N23 -> 0.29714711 | P23: 0.3 | Q23: =P23 -> 0.3

Sheet FAS
B7: Fixed Assets Schedules
B8: (All amounts in INR Lakhs, unless otherwise stated)
A9: # | B9: Particulars | C9: 2021 | D9: =C9+1 -> 2022 | E9: =D9+1 -> 2023 | F9: =E9+1 -> 2024 | G9: =F9+1 -> 2025 | H9: =G9+1 -> 2026 | I9: =H9+1 -> 2027 | J9: =I9+1 -> 2028 | K9: =J9+1 -> 2029 | ... Q9: =P9+1 -> 2035
C10: Audited | D10: Audited | E10: Audited | F10: Audited | G10: Audited | H10: Estimated | I10: Projected | J10: Projected | K10: Projected | L10: Projected | M10: Projected | N10: Projected | O10: Projected | P10: Projected | Q10: Projected
A11: # | B11: Property, plant and equipment
B13: Land
B14: Opening Gross Block | C14: 0 | D14: =C21 -> 0 | E14: =D21 -> 0 | F14: =E21 -> 4423 | G14: =F21 -> 4423 | H14: =G21 -> 4423 | I14: =H21 -> 5307.6 | J14: =I21 -> 6196.623 | K14: =J21 -> 7090.0911 | ... Q14: =P21 -> 12545.5
B15: Acquisition of subsidiary | C15: 0 | D15: 0 | E15: 0 | F15: 0 | G15: 0 | H15: 0 | I15: 0 | J15: 0 | K15: 0 | L15: 0 | M15: 0 | N15: 0 | O15: 0 | P15: 0 | Q15: 0
B16: Additions | C16: 0 | D16: 0 | E16: 4423 | F16: 0 | G16: 0 | H16: =AVERAGE(C16:G16) -> 884.6 | I16: =H16*(1+Assumption!$C$14) -> 889.023 | J16: =I16*(1+Assumption!$C$14) -> 893.46811 | K16: =J16*(1+Assumption!$C$14) -> 897.93546 | L16: =K16*(1+Assumption!$C$14) -> 902.42513 | M16: =L16*(1+Assumption!$C$14) -> 906.93726 | N16: =M16*(1+Assumption!$C$14) -> 911.47194 | O16: =N16*(1+Assumption!$C$14) -> 916.0293 | P16: =O16*(1+Assumption!$C$14) -> 920.60945 | Q16: =P16*(1+Assumption!$C$14) -> 925.2125
B17: Transfers from CWIP | C17: 0 | D17: 0 | E17: 0 | F17: 0 | G17: 0 | H17: 0 | I17: 0 | J17: 0 | K17: 0 | L17: 0 | M17: 0 | N17: 0 | O17: 0 | P17: 0 | Q17: 0
B18: Disposals | C18: 0 | D18: 0 | E18: 0 | F18: 0 | G18: 0 | H18: 0 | I18: 0 | J18: 0 | K18: 0 | L18: 0 | M18: 0 | N18: 0 | O18: 0 | P18: 0 | Q18: 0
B19: Deletion on liquidation of subsidiary | C19: 0 | D19: 0 | E19: 0 | F19: 0 | G19: 0 | H19: 0 | I19: 0 | J19: 0 | K19: 0 | L19: 0 | M19: 0 | N19: 0 | O19: 0 | P19: 0 | Q19: 0
B20: Exchange difference | C20: 0 | D20: 0 | E20: 0 | F20: 0 | G20: 0 | H20: 0 | I20: 0 | J20: 0 | K20: 0 | L20: 0 | M20: 0 | N20: 0 | O20: 0 | P20: 0 | Q20: 0
B21: Closing Gross Block | C21: =SUM(C14:C19) -> 0 | D21: =SUM(D14:D19) -> 0 | E21: =SUM(E14:E19) -> 4423 | F21: =SUM(F14:F19) -> 4423 | G21: =SUM(G14:G19) -> 4423 | H21: =SUM(H14:H19) -> 5307.6 | I21: =SUM(I14:I19) -> 6196.623 | J21: =SUM(J14:J19) -> 7090.0911 | ... Q21: =SUM(Q14:Q19) -> 13470.712
B22: Accumulated Dep | C22: 0 | D22: 0 | E22: 0 | F22: 0 | G22: 0 | H22: 0 | I22: 0 | J22: 0 | K22: 0 | L22: 0 | M22: 0 | N22: 0 | O22: 0 | P22: 0 | Q22: 0
B23: charge for the year | C23: 0 | D23: 0 | E23: 0 | F23: 0 | G23: 0 | H23: 0 | I23: 0 | J23: 0 | K23: 0 | L23: 0 | M23: 0 | N23: 0 | O23: 0 | P23: 0 | Q23: 0
B24: Disposals | C24: 0 | D24: 0 | E24: 0 | F24: 0 | G24: 0 | H24: 0 | I24: 0 | J24: 0 | K24: 0 | L24: 0 | M24: 0 | N24: 0 | O24: 0 | P24: 0 | Q24: 0
B25: Exchange difference | C25: 0 | D25: 0 | E25: 0 | F25: 0 | G25: 0 | H25: 0 | I25: 0 | J25: 0 | K25: 0 | L25: 0 | M25: 0 | N25: 0 | O25: 0 | P25: 0 | Q25: 0
B26: Deletion on liquidation of subsidiary | C26: 0 | D26: 0 | E26: 0 | F26: 0 | G26: 0 | H26: 0 | I26: 0 | J26: 0 | K26: 0 | L26: 0 | M26: 0 | N26: 0 | O26: 0 | P26: 0 | Q26: 0
B27: Total | C27: 0 | D27: 0 | E27: =SUM(E22:E26) -> 0 | F27: =SUM(F22:F26) -> 0 | G27: =SUM(G22:G26) -> 0 | H27: =SUM(H22:H26) -> 0 | I27: =SUM(I22:I26) -> 0 | J27: =SUM(J22:J26) -> 0 | K27: =SUM(K22:K26) -> 0 | L27: =SUM(L22:L26) -> 0 | ... Q27: =SUM(Q22:Q26) -> 0
B29: Net Block | C29: 0 | D29: 0 | E29: =E21-E27 -> 4423 | F29: =F21-F27 -> 4423 | G29: =G21-G27 -> 4423 | H29: =H21-H27 -> 5307.6 | I29: =I21-I27 -> 6196.623 | J29: =J21-J27 -> 7090.0911 | K29: =K21-K27 -> 7988.0266 | L29: =L21-L27 -> 8890.4517 | ... Q29: =Q21-Q27 -> 13470.712
B32: Building
B33: Opening Gross Block | C33: 0 | D33: 0 | E33: 0 | F33: =E40 -> 8354 | G33: =F40 -> 8486 | H33: =G40 -> 8486 | I33: =H40 -> 10156.8 | J33: =I40 -> 11835.954 | K33: =J40 -> 13523.504 | L33: =K40 -> 15219.491 | M33: =L40 -> 16923.959 | ... Q33: =P40 -> 23827.479
B34: Acquisition of subsidiary | C34: 0 | D34: 0 | E34: 0 | F34: 0 | G34: 0 | H34: 0 | I34: 0 | J34: 0 | K34: 0 | L34: 0 | M34: 0 | N34: 0 | O34: 0 | P34: 0 | Q34: 0
B35: Additions | C35: 0 | D35: 0 | E35: 8354 | F35: 0 | G35: 0 | H35: =AVERAGE(C35:G35) -> 1670.8 | I35: =H35*(1+Assumption!$C$14) -> 1679.154 | J35: =I35*(1+Assumption!$C$14) -> 1687.5498 | K35: =J35*(1+Assumption!$C$14) -> 1695.9875 | L35: =K35*(1+Assumption!$C$14) -> 1704.4675 | M35: =L35*(1+Assumption!$C$14) -> 1712.9898 | N35: =M35*(1+Assumption!$C$14) -> 1721.5547 | O35: =N35*(1+Assumption!$C$14) -> 1730.1625 | P35: =O35*(1+Assumption!$C$14) -> 1738.8133 | Q35: =P35*(1+Assumption!$C$14) -> 1747.5074
B36: Transfers from CWIP | C36: 0 | D36: 0 | E36: 0 | F36: 132 | G36: 0 | H36: 0 | I36: 0 | J36: 0 | K36: 0 | L36: 0 | M36: 0 | N36: 0 | O36: 0 | P36: 0 | Q36: 0
B37: Disposals | C37: 0 | D37: 0 | E37: 0 | F37: 0 | G37: 0 | H37: 0 | I37: 0 | J37: 0 | K37: 0 | L37: 0 | M37: 0 | N37: 0 | O37: 0 | P37: 0 | Q37: 0
B38: Deletion on liquidation of subsidiary | C38: 0 | D38: 0 | E38: 0 | F38: 0 | G38: 0 | H38: 0 | I38: 0 | J38: 0 | K38: 0 | L38: 0 | M38: 0 | N38: 0 | O38: 0 | P38: 0 | Q38: 0
B39: Exchange difference | C39: 0 | D39: 0 | E39: 0 | F39: 0 | G39: 0 | H39: 0 | I39: 0 | J39: 0 | K39: 0 | L39: 0 | M39: 0 | N39: 0 | O39: 0 | P39: 0 | Q39: 0
B40: Closing Gross Block | C40: 0 | D40: 0 | E40: =SUM(E33:E38) -> 8354 | F40: =SUM(F33:F38) -> 8486 | G40: =SUM(G33:G38) -> 8486 | H40: =SUM(H33:H38) -> 10156.8 | I40: =SUM(I33:I38) -> 11835.954 | J40: =SUM(J33:J38) -> 13523.504 | K40: =SUM(K33:K38) -> 15219.491 | L40: =SUM(L33:L38) -> 16923.959 | ... Q40: =SUM(Q33:Q38) -> 25574.987
B41: Accumulated Dep | C41: 0 | D41: 0 | E41: 0 | F41: =E46 -> 119 | G41: =F46 -> 287 | H41: =G46 -> 476 | I41: =H46 -> 571.2 | J41: =I46 -> 666.876 | K41: =J46 -> 763.03038 | L41: =K46 -> 859.66553 | M41: =L46 -> 956.78386 | ... Q41: =P46 -> 1350.1374
B42: charge for the year | C42: 0 | D42: 0 | E42: 119 | F42: 168 | G42: 189 | H42: =AVERAGE(C42:G42) -> 95.2 | I42: =H42*(1+Assumption!$C$16) -> 95.676 | J42: =I42*(1+Assumption!$C$16) -> 96.15438 | K42: =J42*(1+Assumption!$C$16) -> 96.635152 | L42: =K42*(1+Assumption!$C$16) -> 97.118328 | M42: =L42*(1+Assumption!$C$16) -> 97.603919 | N42: =M42*(1+Assumption!$C$16) -> 98.091939 | O42: =N42*(1+Assumption!$C$16) -> 98.582399 | P42: =O42*(1+Assumption!$C$16) -> 99.075311 | Q42: =P42*(1+Assumption!$C$16) -> 99.570687
B43: Disposals | C43: 0 | D43: 0 | E43: 0 | F43: 0 | G43: 0 | H43: 0 | I43: 0 | J43: 0 | K43: 0 | L43: 0 | M43: 0 | N43: 0 | O43: 0 | P43: 0 | Q43: 0
B44: Exchange difference | C44: 0 | D44: 0 | E44: 0 | F44: 0 | G44: 0 | H44: 0 | I44: 0 | J44: 0 | K44: 0 | L44: 0 | M44: 0 | N44: 0 | O44: 0 | P44: 0 | Q44: 0
B45: Deletion on liquidation of subsidiary | C45: 0 | D45: 0 | E45: 0 | F45: 0 | G45: 0 | H45: 0 | I45: 0 | J45: 0 | K45: 0 | L45: 0 | M45: 0 | N45: 0 | O45: 0 | P45: 0 | Q45: 0
B46: Total | E46: =SUM(E41:E45) -> 119 | F46: =SUM(F41:F45) -> 287 | G46: =SUM(G41:G45) -> 476 | H46: =SUM(H41:H45) -> 571.2 | I46: =SUM(I41:I45) -> 666.876 | J46: =SUM(J41:J45) -> 763.03038 | K46: =SUM(K41:K45) -> 859.66553 | L46: =SUM(L41:L45) -> 956.78386 | ... Q46: =SUM(Q41:Q45) -> 1449.7081
B48: Net Block | E48: =E40-E46 -> 8235 | F48: =F40-F46 -> 8199 | G48: =G40-G46 -> 8010 | H48: =H40-H46 -> 9585.6 | I48: =I40-I46 -> 11169.078 | J48: =J40-J46 -> 12760.473 | K48: =K40-K46 -> 14359.826 | L48: =L40-L46 -> 15967.175 | ... Q48: =Q40-Q46 -> 24125.278
B51: computer Systems
B52: Opening Gross Block | C52: 217 | D52: =C59 -> 247 | E52: =D59 -> 265 | F52: =E59 -> 509 | G52: =F59 -> 850 | H52: =G59 -> 1479 | I52: =H59 -> 1656.2 | J52: =I59 -> 1834.286 | K52: =J59 -> 2013.2624 | ... Q52: =P59 -> 3106.0709
B53: Acquisition of subsidiary | C53: 0 | D53: 0 | E53: 126 | F53: 0 | G53: 310 | H53: 0 | I53: 0 | J53: 0 | K53: 0 | L53: 0 | M53: 0 | N53: 0 | O53: 0 | P53: 0 | Q53: 0
B54: Additions | C54: 44 | D54: 45 | E54: 166 | F54: 188 | G54: 443 | H54: =AVERAGE(C54:G54) -> 177.2 | I54: =H54*(1+Assumption!$C$14) -> 178.086 | J54: =I54*(1+Assumption!$C$14) -> 178.97643 | K54: =J54*(1+Assumption!$C$14) -> 179.87131 | L54: =K54*(1+Assumption!$C$14) -> 180.77067 | M54: =L54*(1+Assumption!$C$14) -> 181.67452 | N54: =M54*(1+Assumption!$C$14) -> 182.58289 | O54: =N54*(1+Assumption!$C$14) -> 183.49581 | P54: =O54*(1+Assumption!$C$14) -> 184.41329 | Q54: =P54*(1+Assumption!$C$14) -> 185.33535
B55: Transfers from CWIP | C55: 0 | D55: 0 | E55: 0 | F55: 169 | G55: 0 | H55: 0 | I55: 0 | J55: 0 | K55: 0 | L55: 0 | M55: 0 | N55: 0 | O55: 0 | P55: 0 | Q55: 0
B56: Disposals | C56: -13 | D56: -27 | E56: -48 | F56: -16 | G56: -128 | H56: 0 | I56: 0 | J56: 0 | K56: 0 | L56: 0 | M56: 0 | N56: 0 | O56: 0 | P56: 0 | Q56: 0
B57: Deletion on liquidation of subsidiary | C57: -1 | D57: 0 | E57: 0 | F57: 0 | G57: 0 | H57: 0 | I57: 0 | J57: 0 | K57: 0 | L57: 0 | M57: 0 | N57: 0 | O57: 0 | P57: 0 | Q57: 0
B58: Exchange difference | C58: 0 | D58: 0 | E58: 0 | F58: 0 | G58: 3 | H58: 0 | I58: 0 | J58: 0 | K58: 0 | L58: 0 | M58: 0 | N58: 0 | O58: 0 | P58: 0 | Q58: 0
B59: Closing Gross Block | C59: =SUM(C52:C57) -> 247 | D59: =SUM(D52:D57) -> 265 | E59: =SUM(E52:E57) -> 509 | F59: =SUM(F52:F57) -> 850 | G59: 1479 | H59: =SUM(H52:H57) -> 1656.2 | I59: =SUM(I52:I57) -> 1834.286 | J59: =SUM(J52:J57) -> 2013.2624 | K59: =SUM(K52:K57) -> 2193.1337 | L59: =SUM(L52:L57) -> 2373.9044 | M59: =SUM(M52:M57) -> 2555.5789 | N59: =SUM(N52:N57) -> 2738.1618 | O59: =SUM(O52:O57) -> 2921.6576 | ... Q59: =SUM(Q52:Q57) -> 3291.4063
B60: Accumulated Dep | C60: 188 | D60: =C65 -> 218 | E60: =D65 -> 228 | F60: =E65 -> 257 | G60: =F65 -> 439 | H60: =G65 -> 782 | I60: =H65 -> 946.2 | J60: =I65 -> 1111.221 | K60: =J65 -> 1277.0671 | ... Q60: =P65 -> 2289.7034
B61: charge for the year | C61: 44 | D61: 37 | E61: 77 | F61: 198 | G61: 465 | H61: =AVERAGE(C61:G61) -> 164.2 | I61: =H61*(1+Assumption!$C$16) -> 165.021 | J61: =I61*(1+Assumption!$C$16) -> 165.8461 | K61: =J61*(1+Assumption!$C$16) -> 166.67534 | L61: =K61*(1+Assumption!$C$16) -> 167.50871 | M61: =L61*(1+Assumption!$C$16) -> 168.34626 | N61: =M61*(1+Assumption!$C$16) -> 169.18799 | O61: =N61*(1+Assumption!$C$16) -> 170.03393 | P61: =O61*(1+Assumption!$C$16) -> 170.8841 | Q61: =P61*(1+Assumption!$C$16) -> 171.73852
B62: Disposals | C62: -13 | D62: -27 | E62: -48 | F62: -16 | G62: -124 | H62: 0 | I62: 0 | J62: 0 | K62: 0 | L62: 0 | M62: 0 | N62: 0 | O62: 0 | P62: 0 | Q62: 0
B63: Exchange difference | C63: 0 | D63: 0 | E63: 0 | F63: 0 | G63: 3 | H63: 0 | I63: 0 | J63: 0 | K63: 0 | L63: 0 | M63: 0 | N63: 0 | O63: 0 | P63: 0 | Q63: 0
B64: Deletion on liquidation of subsidiary | C64: -1 | D64: 0 | E64: 0 | F64: 0 | G64: 0 | H64: 0 | I64: 0 | J64: 0 | K64: 0 | L64: 0 | M64: 0 | N64: 0 | O64: 0 | P64: 0 | Q64: 0
B65: Total | C65: =SUM(C60:C64) -> 218 | D65: =SUM(D60:D64) -> 228 | E65: =SUM(E60:E64) -> 257 | F65: =SUM(F60:F64) -> 439 | G65: 782 | H65: =SUM(H60:H64) -> 946.2 | I65: =SUM(I60:I64) -> 1111.221 | J65: =SUM(J60:J64) -> 1277.0671 | K65: =SUM(K60:K64) -> 1443.7424 | L65: =SUM(L60:L64) -> 1611.2512 | M65: =SUM(M60:M64) -> 1779.5974 | N65: =SUM(N60:N64) -> 1948.7854 | O65: =SUM(O60:O64) -> 2118.8193 | ... Q65: =SUM(Q60:Q64) -> 2461.4419
B67: Net Block | C67: =C59-C65 -> 29 | D67: =D59-D65 -> 37 | E67: =E59-E65 -> 252 | F67: =F59-F65 -> 411 | G67: =G59-G65 -> 697 | H67: =H59-H65 -> 710 | I67: =I59-I65 -> 723.065 | J67: =J59-J65 -> 736.19533 | ... Q67: =Q59-Q65 -> 829.96434
B70: Office equipments
B71: Opening Gross Block | C71: 116 | D71: =C78 -> 134 | E71: =D78 -> 144 | F71: =E78 -> 276 | G71: =F78 -> 562 | H71: =G78 -> 707 | I71: =H78 -> 776 | J71: =I78 -> 845.345 | K71: =J78 -> 915.03673 | ... Q71: =P78 -> 1340.566
B72: Acquisition of subsidiary | C72: 0 | D72: 0 | E72: 10 | F72: 0 | G72: 55 | H72: 0 | I72: 0 | J72: 0 | K72: 0 | L72: 0 | M72: 0 | N72: 0 | O72: 0 | P72: 0 | Q72: 0
B73: Additions | C73: 18 | D73: 11 | E73: 122 | F73: 103 | G73: 91 | H73: =AVERAGE(C73:G73) -> 69 | I73: =H73*(1+Assumption!$C$14) -> 69.345 | J73: =I73*(1+Assumption!$C$14) -> 69.691725 | K73: =J73*(1+Assumption!$C$14) -> 70.040184 | L73: =K73*(1+Assumption!$C$14) -> 70.390385 | M73: =L73*(1+Assumption!$C$14) -> 70.742336 | N73: =M73*(1+Assumption!$C$14) -> 71.096048 | O73: =N73*(1+Assumption!$C$14) -> 71.451528 | P73: =O73*(1+Assumption!$C$14) -> 71.808786 | Q73: =P73*(1+Assumption!$C$14) -> 72.16783
B74: Transfers from CWIP | C74: 0 | D74: 0 | E74: 0 | F74: 183 | G74: 0 | H74: 0 | I74: 0 | J74: 0 | K74: 0 | L74: 0 | M74: 0 | N74: 0 | O74: 0 | P74: 0 | Q74: 0
B75: Disposals | C75: 0 | D75: -1 | E75: 0 | F75: 0 | G75: -2 | H75: 0 | I75: 0 | J75: 0 | K75: 0 | L75: 0 | M75: 0 | N75: 0 | O75: 0 | P75: 0 | Q75: 0
B76: Deletion on liquidation of subsidiary | C76: 0 | D76: 0 | E76: 0 | F76: 0 | G76: 0 | H76: 0 | I76: 0 | J76: 0 | K76: 0 | L76: 0 | M76: 0 | N76: 0 | O76: 0 | P76: 0 | Q76: 0
B77: Exchange difference | C77: 0 | D77: 0 | E77: 0 | F77: 0 | G77: 0 | H77: 0 | I77: 0 | J77: 0 | K77: 0 | L77: 0 | M77: 0 | N77: 0 | O77: 0 | P77: 0 | Q77: 0
B78: Closing Gross Block | C78: =SUM(C71:C76) -> 134 | D78: =SUM(D71:D76) -> 144 | E78: =SUM(E71:E76) -> 276 | F78: =SUM(F71:F76) -> 562 | G78: 707 | H78: =SUM(H71:H76) -> 776 | I78: =SUM(I71:I76) -> 845.345 | J78: =SUM(J71:J76) -> 915.03673 | K78: =SUM(K71:K76) -> 985.07691 | L78: =SUM(L71:L76) -> 1055.4673 | M78: =SUM(M71:M76) -> 1126.2096 | N78: =SUM(N71:N76) -> 1197.3057 | O78: =SUM(O71:O76) -> 1268.7572 | ... Q78: =SUM(Q71:Q76) -> 1412.7338
B79: Accumulated Dep | C79: 78 | D79: =C84 -> 98 | E79: =D84 -> 116 | F79: =E84 -> 138 | G79: =F84 -> 195 | H79: =G84 -> 289 | I79: =H84 -> 331.4 | J79: =I84 -> 374.012 | K79: =J84 -> 416.83706 | ... Q79: =P84 -> 678.32171
B80: charge for the year | C80: 20 | D80: 18 | E80: 22 | F80: 57 | G80: 95 | H80: =AVERAGE(C80:G80) -> 42.4 | I80: =H80*(1+Assumption!$C$16) -> 42.612 | J80: =I80*(1+Assumption!$C$16) -> 42.82506 | K80: =J80*(1+Assumption!$C$16) -> 43.039185 | L80: =K80*(1+Assumption!$C$16) -> 43.254381 | M80: =L80*(1+Assumption!$C$16) -> 43.470653 | N80: =M80*(1+Assumption!$C$16) -> 43.688006 | O80: =N80*(1+Assumption!$C$16) -> 43.906446 | P80: =O80*(1+Assumption!$C$16) -> 44.125979 | Q80: =P80*(1+Assumption!$C$16) -> 44.346609
B81: Disposals | C81: 0 | D81: 0 | E81: 0 | F81: 0 | G81: -2 | H81: 0 | I81: 0 | J81: 0 | K81: 0 | L81: 0 | M81: 0 | N81: 0 | O81: 0 | P81: 0 | Q81: 0
B82: Exchange difference | C82: 0 | D82: 0 | E82: 0 | F82: 0 | G82: 0 | H82: 0 | I82: 0 | J82: 0 | K82: 0 | L82: 0 | M82: 0 | N82: 0 | O82: 0 | P82: 0 | Q82: 0
B83: Deletion on liquidation of subsidiary | C83: 0 | D83: 0 | E83: 0 | F83: 0 | G83: 0 | H83: 0 | I83: 0 | J83: 0 | K83: 0 | L83: 0 | M83: 0 | N83: 0 | O83: 0 | P83: 0 | Q83: 0
B84: Total | C84: =SUM(C79:C83) -> 98 | D84: =SUM(D79:D83) -> 116 | E84: =SUM(E79:E83) -> 138 | F84: =SUM(F79:F83) -> 195 | G84: 289 | H84: =SUM(H79:H83) -> 331.4 | I84: =SUM(I79:I83) -> 374.012 | J84: =SUM(J79:J83) -> 416.83706 | K84: =SUM(K79:K83) -> 459.87625 | L84: =SUM(L79:L83) -> 503.13063 | M84: =SUM(M79:M83) -> 546.60128 | N84: =SUM(N79:N83) -> 590.28929 | O84: =SUM(O79:O83) -> 634.19573 | ... Q84: =SUM(Q79:Q83) -> 722.66832
B86: Net Block | C86: =C78-C84 -> 36 | D86: =D78-D84 -> 28 | E86: =E78-E84 -> 138 | F86: =F78-F84 -> 367 | G86: =G78-G84 -> 418 | H86: =H78-H84 -> 444.6 | I86: =I78-I84 -> 471.333 | J86: =J78-J84 -> 498.19967 | ... Q86: =Q78-Q84 -> 690.0655
B89: Furniture and fixtures
B90: Opening Gross Block | C90: 24 | D90: =C97 -> 25 | E90: =D97 -> 25 | F90: =E97 -> 79 | G90: =F97 -> 215 | H90: =G97 -> 264 | I90: =H97 -> 276.6 | J90: =I97 -> 289.263 | K90: =J97 -> 301.98932 | ... Q90: =P97 -> 379.69466
B91: Acquisition of subsidiary | C91: 0 | D91: 0 | E91: 5 | F91: 0 | G91: 19 | H91: 0 | I91: 0 | J91: 0 | K91: 0 | L91: 0 | M91: 0 | N91: 0 | O91: 0 | P91: 0 | Q91: 0
B92: Additions | C92: 2 | D92: 0 | E92: 50 | F92: 3 | G92: 8 | H92: =AVERAGE(C92:G92) -> 12.6 | I92: =H92*(1+Assumption!$C$14) -> 12.663 | J92: =I92*(1+Assumption!$C$14) -> 12.726315 | K92: =J92*(1+Assumption!$C$14) -> 12.789947 | L92: =K92*(1+Assumption!$C$14) -> 12.853896 | M92: =L92*(1+Assumption!$C$14) -> 12.918166 | N92: =M92*(1+Assumption!$C$14) -> 12.982757 | O92: =N92*(1+Assumption!$C$14) -> 13.04767 | P92: =O92*(1+Assumption!$C$14) -> 13.112909 | Q92: =P92*(1+Assumption!$C$14) -> 13.178473
B93: Transfers from CWIP | C93: 0 | D93: 0 | E93: 0 | F93: 133 | G93: 22 | H93: 0 | I93: 0 | J93: 0 | K93: 0 | L93: 0 | M93: 0 | N93: 0 | O93: 0 | P93: 0 | Q93: 0
B94: Disposals | C94: 0 | D94: 0 | E94: -1 | F94: 0 | G94: 0 | H94: 0 | I94: 0 | J94: 0 | K94: 0 | L94: 0 | M94: 0 | N94: 0 | O94: 0 | P94: 0 | Q94: 0
B95: Deletion on liquidation of subsidiary | C95: -1 | D95: 0 | E95: 0 | F95: 0 | G95: 0 | H95: 0 | I95: 0 | J95: 0 | K95: 0 | L95: 0 | M95: 0 | N95: 0 | O95: 0 | P95: 0 | Q95: 0
B96: Exchange difference | C96: 0 | D96: 0 | E96: 0 | F96: 0 | G96: 0 | H96: 0 | I96: 0 | J96: 0 | K96: 0 | L96: 0 | M96: 0 | N96: 0 | O96: 0 | P96: 0 | Q96: 0
B97: Closing Gross Block | C97: =SUM(C90:C95) -> 25 | D97: =SUM(D90:D95) -> 25 | E97: =SUM(E90:E95) -> 79 | F97: =SUM(F90:F95) -> 215 | G97: =SUM(G90:G95) -> 264 | H97: =SUM(H90:H95) -> 276.6 | I97: =SUM(I90:I95) -> 289.263 | J97: =SUM(J90:J95) -> 301.98932 | ... Q97: =SUM(Q90:Q95) -> 392.87313
B98: Accumulated Dep | C98: 16 | D98: =C103 -> 24 | E98: =D103 -> 24 | F98: =E103 -> 29 | G98: =F103 -> 54 | H98: =G103 -> 99 | I98: =H103 -> 116 | J98: =I103 -> 133.085 | K98: =J103 -> 150.25543 | ... Q98: =P103 -> 255.09597
B99: charge for the year | C99: 9 | D99: 0 | E99: 6 | F99: 25 | G99: 45 | H99: =AVERAGE(C99:G99) -> 17 | I99: =H99*(1+Assumption!$C$16) -> 17.085 | J99: =I99*(1+Assumption!$C$16) -> 17.170425 | K99: =J99*(1+Assumption!$C$16) -> 17.256277 | L99: =K99*(1+Assumption!$C$16) -> 17.342559 | M99: =L99*(1+Assumption!$C$16) -> 17.429271 | N99: =M99*(1+Assumption!$C$16) -> 17.516418 | O99: =N99*(1+Assumption!$C$16) -> 17.604 | P99: =O99*(1+Assumption!$C$16) -> 17.69202 | Q99: =P99*(1+Assumption!$C$16) -> 17.78048
B100: Disposals | C100: 0 | D100: 0 | E100: -1 | F100: 0 | G100: 0 | H100: 0 | I100: 0 | J100: 0 | K100: 0 | L100: 0 | M100: 0 | N100: 0 | O100: 0 | P100: 0 | Q100: 0
B101: Exchange difference | C101: 0 | D101: 0 | E101: 0 | F101: 0 | G101: 0 | H101: 0 | I101: 0 | J101: 0 | K101: 0 | L101: 0 | M101: 0 | N101: 0 | O101: 0 | P101: 0 | Q101: 0
B102: Deletion on liquidation of subsidiary | C102: -1 | D102: 0 | E102: 0 | F102: 0 | G102: 0 | H102: 0 | I102: 0 | J102: 0 | K102: 0 | L102: 0 | M102: 0 | N102: 0 | O102: 0 | P102: 0 | Q102: 0
B103: Total | C103: =SUM(C98:C102) -> 24 | D103: =SUM(D98:D102) -> 24 | E103: =SUM(E98:E102) -> 29 | F103: =SUM(F98:F102) -> 54 | G103: =SUM(G98:G102) -> 99 | H103: =SUM(H98:H102) -> 116 | I103: =SUM(I98:I102) -> 133.085 | J103: =SUM(J98:J102) -> 150.25543 | ... Q103: =SUM(Q98:Q102) -> 272.87645
B105: Net Block | C105: =C97-C103 -> 1 | D105: =D97-D103 -> 1 | E105: =E97-E103 -> 50 | F105: =F97-F103 -> 161 | G105: =G97-G103 -> 165 | H105: =H97-H103 -> 160.6 | I105: =I97-I103 -> 156.178 | J105: =J97-J103 -> 151.73389 | ... Q105: =Q97-Q103 -> 119.99668
B108: Vechiles
B109: Opening Gross Block | F109: =E116 -> 33 | G109: =F116 -> 29 | H109: =G116 -> 38 | I109: =H116 -> 38 | J109: =I116 -> 38 | K109: =J116 -> 38 | L109: =K116 -> 38 | M109: =L116 -> 38 | ... Q109: =P116 -> 38
B110: Acquisition of subsidiary | C110: 0 | D110: 0 | E110: 33 | F110: 0 | G110: 22 | H110: 0 | I110: 0 | J110: 0 | K110: 0 | L110: 0 | M110: 0 | N110: 0 | O110: 0 | P110: 0 | Q110: 0
B111: Additions | C111: 0 | D111: 0 | E111: 0 | F111: 0 | G111: 0 | H111: =AVERAGE(C111:G111) -> 0 | I111: =H111*(1+Assumption!$C$14) -> 0 | J111: =I111*(1+Assumption!$C$14) -> 0 | K111: =J111*(1+Assumption!$C$14) -> 0 | L111: =K111*(1+Assumption!$C$14) -> 0 | M111: =L111*(1+Assumption!$C$14) -> 0 | N111: =M111*(1+Assumption!$C$14) -> 0 | O111: =N111*(1+Assumption!$C$14) -> 0 | P111: =O111*(1+Assumption!$C$14) -> 0 | Q111: =P111*(1+Assumption!$C$14) -> 0
B112: Transfers from CWIP | C112: 0 | D112: 0 | E112: 0 | F112: 0 | G112: 0 | H112: 0 | I112: 0 | J112: 0 | K112: 0 | L112: 0 | M112: 0 | N112: 0 | O112: 0 | P112: 0 | Q112: 0
B113: Disposals | C113: 0 | D113: 0 | E113: 0 | F113: -4 | G113: -14 | H113: 0 | I113: 0 | J113: 0 | K113: 0 | L113: 0 | M113: 0 | N113: 0 | O113: 0 | P113: 0 | Q113: 0
B114: Deletion on liquidation of subsidiary | C114: 0 | D114: 0 | E114: 0 | F114: 0 | G114: 0 | H114: 0 | I114: 0 | J114: 0 | K114: 0 | L114: 0 | M114: 0 | N114: 0 | O114: 0 | P114: 0 | Q114: 0
B115: Exchange difference | C115: 0 | D115: 0 | E115: 0 | F115: 0 | G115: 0 | H115: 0 | I115: 0 | J115: 0 | K115: 0 | L115: 0 | M115: 0 | N115: 0 | O115: 0 | P115: 0 | Q115: 0
B116: Closing Gross Block | C116: =SUM(C109:C114) -> 0 | D116: =SUM(D109:D114) -> 0 | E116: =SUM(E109:E114) -> 33 | F116: =SUM(F109:F114) -> 29 | G116: 38 | H116: =SUM(H109:H114) -> 38 | I116: =SUM(I109:I114) -> 38 | J116: =SUM(J109:J114) -> 38 | K116: =SUM(K109:K114) -> 38 | L116: =SUM(L109:L114) -> 38 | M116: =SUM(M109:M114) -> 38 | N116: =SUM(N109:N114) -> 38 | O116: =SUM(O109:O114) -> 38 | ... Q116: =SUM(Q109:Q114) -> 38
B117: Accumulated Dep | C117: 0 | D117: 0 | E117: 0 | F117: =E122 -> 1 | G117: =F122 -> 9 | H117: =G124 -> 26 | I117: =H124 -> 7.6 | J117: =I124 -> 25.978 | K117: =J124 -> 7.57789 | L117: =K124 -> 25.955779 | M117: =L124 -> 7.5555583 | N117: =M124 -> 25.933336 | O117: =N124 -> 7.5330028 | ... Q117: =P124 -> 7.5102212
B118: charge for the year | C118: 0 | D118: 0 | E118: 1 | F118: 8 | G118: 13 | H118: =AVERAGE(C118:G118) -> 4.4 | I118: =H118*(1+Assumption!$C$16) -> 4.422 | J118: =I118*(1+Assumption!$C$16) -> 4.44411 | K118: =J118*(1+Assumption!$C$16) -> 4.4663305 | L118: =K118*(1+Assumption!$C$16) -> 4.4886622 | M118: =L118*(1+Assumption!$C$16) -> 4.5111055 | N118: =M118*(1+Assumption!$C$16) -> 4.533661 | O118: =N118*(1+Assumption!$C$16) -> 4.5563293 | P118: =O118*(1+Assumption!$C$16) -> 4.579111 | Q118: =P118*(1+Assumption!$C$16) -> 4.6020065
B119: Disposals | C119: 0 | D119: 0 | E119: 0 | F119: 0 | G119: -11 | H119: 0 | I119: 0 | J119: 0 | K119: 0 | L119: 0 | M119: 0 | N119: 0 | O119: 0 | P119: 0 | Q119: 0
B120: Exchange difference | C120: 0 | D120: 0 | E120: 0 | F120: 0 | G120: 0 | H120: 0 | I120: 0 | J120: 0 | K120: 0 | L120: 0 | M120: 0 | N120: 0 | O120: 0 | P120: 0 | Q120: 0
B121: Deletion on liquidation of subsidiary | C121: 0 | D121: 0 | E121: 0 | F121: 0 | G121: 0 | H121: 0 | I121: 0 | J121: 0 | K121: 0 | L121: 0 | M121: 0 | N121: 0 | O121: 0 | P121: 0 | Q121: 0
B122: Total | C122: 0 | D122: 0 | E122: =SUM(E117:E121) -> 1 | F122: =SUM(F117:F121) -> 9 | G122: =SUM(G117:G121) -> 11 | H122: =SUM(H117:H121) -> 30.4 | I122: =SUM(I117:I121) -> 12.022 | J122: =SUM(J117:J121) -> 30.42211 | K122: =SUM(K117:K121) -> 12.044221 | L122: =SUM(L117:L121) -> 30.444442 | ... Q122: =SUM(Q117:Q121) -> 12.112228
...

Sheet BS Items
B5: Forecasted Balance sheet
B6: (All amounts in INR Lakhs, unless otherwise stated)
A7: # | B7: Particulars | C7: 2021 | D7: =C7+1 -> 2022 | E7: =D7+1 -> 2023 | F7: =E7+1 -> 2024 | G7: =F7+1 -> 2025 | H7: =G7+1 -> 2026 | I7: =H7+1 -> 2027 | J7: =I7+1 -> 2028 | K7: =J7+1 -> 2029 | ... Q7: =P7+1 -> 2035
C8: Audited | D8: Audited | E8: Audited | F8: Audited | G8: Audited | H8: Estimated | I8: Projected | J8: Projected | K8: Projected | L8: Projected | M8: Projected | N8: Projected | O8: Projected | P8: Projected | Q8: Projected
B10: Assets
B11: Non-current assets
B13: Investments | C13: ='Historical Balance Sheet'!C18 -> 0 | D13: ='Historical Balance Sheet'!D18 -> 762 | E13: ='Historical Balance Sheet'!E18 -> 1296 | F13: ='Historical Balance Sheet'!F18 -> 0 | G13: ='Historical Balance Sheet'!G18 -> 0 | H13: =H14*'Revenue BuildUp'!H$10 -> 807.32291 | I13: =I14*'Revenue BuildUp'!I$10 -> 961.97017 | J13: =J14*'Revenue BuildUp'!J$10 -> 1121.1713 | K13: =K14*'Revenue BuildUp'!K$10 -> 1281.3605 | L13: =L14*'Revenue BuildUp'!L$10 -> 1439.3207 | M13: =M14*'Revenue BuildUp'!M$10 -> 1592.3343 | N13: =N14*'Revenue BuildUp'!N$10 -> 1738.2561 | O13: =O14*'Revenue BuildUp'!O$10 -> 1875.5209 | ... Q13: =Q14*'Revenue BuildUp'!Q$10 -> 2120.4597
B14: % of Revenue | C14: =C13/'Revenue BuildUp'!C$10 -> 0 | D14: =D13/'Revenue BuildUp'!D$10 -> 0.0069674942 | E14: =E13/'Revenue BuildUp'!E$10 -> 0.0090674391 | F14: =F13/'Revenue BuildUp'!F$10 -> 0 | G14: =G13/'Revenue BuildUp'!G$10 -> 0 | H14: =AVERAGE(C14:G14) -> 0.0032069866 | I14: =H14 -> 0.0032069866 | J14: =I14 -> 0.0032069866 | K14: =J14 -> 0.0032069866 | L14: =K14 -> 0.0032069866 | M14: =L14 -> 0.0032069866 | N14: =M14 -> 0.0032069866 | O14: =N14 -> 0.0032069866 | P14: =O14 -> 0.0032069866 | Q14: =P14 -> 0.0032069866
B15: Other financial assets | C15: ='Historical Balance Sheet'!C19 -> 2458 | D15: ='Historical Balance Sheet'!D19 -> 1827 | E15: ='Historical Balance Sheet'!E19 -> 9389 | F15: ='Historical Balance Sheet'!F19 -> 2480 | G15: ='Historical Balance Sheet'!G19 -> 7358 | H15: =H16*'Revenue BuildUp'!H$10 -> 8314.7022 | I15: =I16*'Revenue BuildUp'!I$10 -> 9907.4304 | J15: =J16*'Revenue BuildUp'!J$10 -> 11547.06 | K15: =K16*'Revenue BuildUp'!K$10 -> 13196.864 | L15: =L16*'Revenue BuildUp'!L$10 -> 14823.713 | M15: =M16*'Revenue BuildUp'!M$10 -> 16399.616 | N15: =N16*'Revenue BuildUp'!N$10 -> 17902.48 | O15: =O16*'Revenue BuildUp'!O$10 -> 19316.184 | ... Q15: =Q16*'Revenue BuildUp'!Q$10 -> 21838.834
B16: % of Revenue | C16: =C15/'Revenue BuildUp'!C$10 -> 0.031781332 | D16: =D15/'Revenue BuildUp'!D$10 -> 0.016705527 | E16: =E15/'Revenue BuildUp'!E$10 -> 0.065689958 | F16: =F15/'Revenue BuildUp'!F$10 -> 0.015264732 | G16: =G15/'Revenue BuildUp'!G$10 -> 0.035703888 | H16: =AVERAGE(C16:G16) -> 0.033029087 | I16: =H16 -> 0.033029087 | J16: =I16 -> 0.033029087 | K16: =J16 -> 0.033029087 | L16: =K16 -> 0.033029087 | M16: =L16 -> 0.033029087 | N16: =M16 -> 0.033029087 | O16: =N16 -> 0.033029087 | P16: =O16 -> 0.033029087 | Q16: =P16 -> 0.033029087
B17: Income tax assets (net | C17: ='Historical Balance Sheet'!C20 -> 1408 | D17: ='Historical Balance Sheet'!D20 -> 680 | E17: ='Historical Balance Sheet'!E20 -> 1310 | F17: ='Historical Balance Sheet'!F20 -> 1529 | G17: ='Historical Balance Sheet'!G20 -> 3537 | H17: =H18*'Revenue BuildUp'!H$10 -> 3029.0367 | I17: =I18*'Revenue BuildUp'!I$10 -> 3609.2657 | J17: =J18*'Revenue BuildUp'!J$10 -> 4206.5808 | K17: =K18*'Revenue BuildUp'!K$10 -> 4807.6029 | L17: =L18*'Revenue BuildUp'!L$10 -> 5400.2618 | M17: =M18*'Revenue BuildUp'!M$10 -> 5974.3618 | N17: =N18*'Revenue BuildUp'!N$10 -> 6521.8532 | O17: =O18*'Revenue BuildUp'!O$10 -> 7036.864 | ... Q17: =Q18*'Revenue BuildUp'!Q$10 -> 7955.8626
B18: % of Revenue | C18: =C17/'Revenue BuildUp'!C$10 -> 0.018205092 | D18: =D17/'Revenue BuildUp'!D$10 -> 0.0062177113 | E18: =E17/'Revenue BuildUp'!E$10 -> 0.0091653898 | F18: =F17/'Revenue BuildUp'!F$10 -> 0.0094111999 | G18: =G17/'Revenue BuildUp'!G$10 -> 0.017162904 | H18: =AVERAGE(C18:G18) -> 0.012032459 | I18: =H18 -> 0.012032459 | J18: =I18 -> 0.012032459 | K18: =J18 -> 0.012032459 | L18: =K18 -> 0.012032459 | M18: =L18 -> 0.012032459 | N18: =M18 -> 0.012032459 | O18: =N18 -> 0.012032459 | P18: =O18 -> 0.012032459 | Q18: =P18 -> 0.012032459
B19: Other assets | C19: ='Historical Balance Sheet'!C21 -> 7 | D19: ='Historical Balance Sheet'!D21 -> 1 | E19: ='Historical Balance Sheet'!E21 -> 119 | F19: ='Historical Balance Sheet'!F21 -> 32 | G19: ='Historical Balance Sheet'!G21 -> 170 | H19: =H20*'Revenue BuildUp'!H$10 -> 98.384742 | I19: =I20*'Revenue BuildUp'!I$10 -> 117.2309 | J19: =J20*'Revenue BuildUp'!J$10 -> 136.63201 | K19: =K20*'Revenue BuildUp'!K$10 -> 156.15353 | L19: =L20*'Revenue BuildUp'!L$10 -> 175.40341 | M19: =M20*'Revenue BuildUp'!M$10 -> 194.05049 | N19: =N20*'Revenue BuildUp'!N$10 -> 211.83331 | O19: =O20*'Revenue BuildUp'!O$10 -> 228.56113 | ... Q19: =Q20*'Revenue BuildUp'!Q$10 -> 258.4107
B20: % of Revenue | C20: =C19/'Revenue BuildUp'!C$10 -> 9.0508269e-05 | D20: =D19/'Revenue BuildUp'!D$10 -> 9.1436931e-06 | E20: =E19/'Revenue BuildUp'!E$10 -> 0.00083258121 | F20: =F19/'Revenue BuildUp'!F$10 -> 0.00019696429 | G20: =G19/'Revenue BuildUp'!G$10 -> 0.00082490635 | H20: =AVERAGE(C20:G20) -> 0.00039082076 | I20: =H20 -> 0.00039082076 | J20: =I20 -> 0.00039082076 | K20: =J20 -> 0.00039082076 | L20: =K20 -> 0.00039082076 | M20: =L20 -> 0.00039082076 | N20: =M20 -> 0.00039082076 | O20: =N20 -> 0.00039082076 | P20: =O20 -> 0.00039082076 | Q20: =P20 -> 0.00039082076
B21: Deferred tax assets (net) | C21: ='Historical Balance Sheet'!C22 -> 1026 | D21: ='Historical Balance Sheet'!D22 -> 697 | E21: ='Historical Balance Sheet'!E22 -> 1246 | F21: ='Historical Balance Sheet'!F22 -> 1636 | G21: ='Historical Balance Sheet'!G22 -> 3613 | H21: =H22*'Revenue BuildUp'!H$10 -> 2817.3688 | I21: =I22*'Revenue BuildUp'!I$10 -> 3357.0517 | J21: =J22*'Revenue BuildUp'!J$10 -> 3912.6267 | K21: =K22*'Revenue BuildUp'!K$10 -> 4471.6496 | L21: =L22*'Revenue BuildUp'!L$10 -> 5022.8938 | M21: =M22*'Revenue BuildUp'!M$10 -> 5556.8758 | N21: =N22*'Revenue BuildUp'!N$10 -> 6066.1088 | O21: =O22*'Revenue BuildUp'!O$10 -> 6545.1308 | ... Q21: =Q22*'Revenue BuildUp'!Q$10 -> 7399.9102
B22: % of Revenue | C22: =C21/'Revenue BuildUp'!C$10 -> 0.013265926 | D22: =D21/'Revenue BuildUp'!D$10 -> 0.0063731541 | E22: =E21/'Revenue BuildUp'!E$10 -> 0.008717615 | F22: =F21/'Revenue BuildUp'!F$10 -> 0.010069799 | G22: =G21/'Revenue BuildUp'!G$10 -> 0.017531686 | H22: =AVERAGE(C22:G22) -> 0.011191636 | I22: =H22 -> 0.011191636 | J22: =I22 -> 0.011191636 | K22: =J22 -> 0.011191636 | L22: =K22 -> 0.011191636 | M22: =L22 -> 0.011191636 | N22: =M22 -> 0.011191636 | O22: =N22 -> 0.011191636 | P22: =O22 -> 0.011191636 | Q22: =P22 -> 0.011191636
B23: Total non-current assets
B25: Current assets
B27: Investments | C27: ='Historical Balance Sheet'!C28 -> 39148 | D27: ='Historical Balance Sheet'!D28 -> 46400 | E27: ='Historical Balance Sheet'!E28 -> 0 | F27: ='Historical Balance Sheet'!F28 -> 0 | G27: ='Historical Balance Sheet'!G28 -> 35039 | H27: =H28*'Revenue BuildUp'!H$10 -> 92343.173 | I27: =I28*'Revenue BuildUp'!I$10 -> 110032.03 | J27: =J28*'Revenue BuildUp'!J$10 -> 128241.77 | K27: =K28*'Revenue BuildUp'!K$10 -> 146564.52 | L27: =L28*'Revenue BuildUp'!L$10 -> 164632.31 | M27: =M28*'Revenue BuildUp'!M$10 -> 182134.32 | N27: =N28*'Revenue BuildUp'!N$10 -> 198825.14 | O27: =O28*'Revenue BuildUp'!O$10 -> 214525.75 | ... Q27: =Q28*'Revenue BuildUp'!Q$10 -> 242542.33
B28: % of Revenue | C28: =C27/'Revenue BuildUp'!C$10 -> 0.50617396 | D28: =D27/'Revenue BuildUp'!D$10 -> 0.42426736 | E28: =E27/'Revenue BuildUp'!E$10 -> 0 | F28: =F27/'Revenue BuildUp'!F$10 -> 0 | G28: =G27/'Revenue BuildUp'!G$10 -> 0.1700229 | H28: =AVERAGE(C28:D28,G28) -> 0.36682141 | I28: =H28 -> 0.36682141 | J28: =I28 -> 0.36682141 | K28: =J28 -> 0.36682141 | L28: =K28 -> 0.36682141 | M28: =L28 -> 0.36682141 | N28: =M28 -> 0.36682141 | O28: =N28 -> 0.36682141 | P28: =O28 -> 0.36682141 | Q28: =P28 -> 0.36682141
B29: Loans | C29: ='Historical Balance Sheet'!C32 -> 14 | D29: ='Historical Balance Sheet'!D32 -> 4 | E29: ='Historical Balance Sheet'!E32 -> 64 | F29: ='Historical Balance Sheet'!F32 -> 37 | G29: ='Historical Balance Sheet'!G32 -> 12 | H29: =H30*'Revenue BuildUp'!H$10 -> 47.897568 | I29: =I30*'Revenue BuildUp'!I$10 -> 57.072618 | J29: =J30*'Revenue BuildUp'!J$10 -> 66.517845 | K29: =K30*'Revenue BuildUp'!K$10 -> 76.02169 | L29: =L30*'Revenue BuildUp'!L$10 -> 85.393292 | M29: =M30*'Revenue BuildUp'!M$10 -> 94.471422 | N29: =N30*'Revenue BuildUp'!N$10 -> 103.1288 | O29: =O30*'Revenue BuildUp'!O$10 -> 111.27256 | ... Q29: =Q30*'Revenue BuildUp'!Q$10 -> 125.80451
B30: % of Revenue | C30: =C29/'Revenue BuildUp'!C$10 -> 0.00018101654 | D30: =D29/'Revenue BuildUp'!D$10 -> 3.6574773e-05 | E30: =E29/'Revenue BuildUp'!E$10 -> 0.00044777477 | F30: =F29/'Revenue BuildUp'!F$10 -> 0.00022773996 | G30: =G29/'Revenue BuildUp'!G$10 -> 5.8228683e-05 | H30: =AVERAGE(C30:G30) -> 0.00019026694 | I30: =H30 -> 0.00019026694 | J30: =I30 -> 0.00019026694 | K30: =J30 -> 0.00019026694 | L30: =K30 -> 0.00019026694 | M30: =L30 -> 0.00019026694 | N30: =M30 -> 0.00019026694 | O30: =N30 -> 0.00019026694 | P30: =O30 -> 0.00019026694 | Q30: =P30 -> 0.00019026694
B31: Other financial assets | C31: ='Historical Balance Sheet'!C33 -> 6779 | D31: ='Historical Balance Sheet'!D33 -> 9405 | E31: ='Historical Balance Sheet'!E33 -> 12237 | F31: ='Historical Balance Sheet'!F33 -> 13850 | G31: ='Historical Balance Sheet'!G33 -> 17726 | H31: =H32*'Revenue BuildUp'!H$10 -> 21675.98 | I31: =I32*'Revenue BuildUp'!I$10 -> 25828.136 | J31: =J32*'Revenue BuildUp'!J$10 -> 30102.561 | K31: =K32*'Revenue BuildUp'!K$10 -> 34403.513 | L31: =L32*'Revenue BuildUp'!L$10 -> 38644.618 | M31: =M32*'Revenue BuildUp'!M$10 -> 42752.914 | N31: =N32*'Revenue BuildUp'!N$10 -> 46670.798 | O31: =O32*'Revenue BuildUp'!O$10 -> 50356.248 | ... Q31: =Q32*'Revenue BuildUp'!Q$10 -> 56932.661
B32: % of Revenue | C32: =C31/'Revenue BuildUp'!C$10 -> 0.087650793 | D32: =D31/'Revenue BuildUp'!D$10 -> 0.085996434 | E32: =E31/'Revenue BuildUp'!E$10 -> 0.085615935 | F32: =F31/'Revenue BuildUp'!F$10 -> 0.085248606 | G32: =G31/'Revenue BuildUp'!G$10 -> 0.08601347 | H32: =AVERAGE(C32:G32) -> 0.086105048 | I32: =H32 -> 0.086105048 | J32: =I32 -> 0.086105048 | K32: =J32 -> 0.086105048 | L32: =K32 -> 0.086105048 | M32: =L32 -> 0.086105048 | N32: =M32 -> 0.086105048 | O32: =N32 -> 0.086105048 | P32: =O32 -> 0.086105048 | Q32: =P32 -> 0.086105048
B33: Other assets | C33: ='Historical Balance Sheet'!C34 -> 1802 | D33: ='Historical Balance Sheet'!D34 -> 3392 | E33: ='Historical Balance Sheet'!E34 -> 4495 | F33: ='Historical Balance Sheet'!F34 -> 4793 | G33: ='Historical Balance Sheet'!G34 -> 5682 | H33: =H34*'Revenue BuildUp'!H$10 -> 7191.5144 | I33: =I34*'Revenue BuildUp'!I$10 -> 8569.0897 | J33: =J34*'Revenue BuildUp'!J$10 -> 9987.2303 | K33: =K34*'Revenue BuildUp'!K$10 -> 11414.172 | L33: =L34*'Revenue BuildUp'!L$10 -> 12821.258 | M33: =M34*'Revenue BuildUp'!M$10 -> 14184.282 | N33: =N34*'Revenue BuildUp'!N$10 -> 15484.131 | O33: =O34*'Revenue BuildUp'!O$10 -> 16706.866 | ... Q33: =Q34*'Revenue BuildUp'!Q$10 -> 18888.745
B34: % of Revenue | C34: =C33/'Revenue BuildUp'!C$10 -> 0.023299414 | D34: =D33/'Revenue BuildUp'!D$10 -> 0.031015407 | E34: =E33/'Revenue BuildUp'!E$10 -> 0.031449181 | F34: =F33/'Revenue BuildUp'!F$10 -> 0.029501557 | G34: =G33/'Revenue BuildUp'!G$10 -> 0.027571282 | H34: =AVERAGE(C34:G34) -> 0.028567368 | I34: =H34 -> 0.028567368 | J34: =I34 -> 0.028567368 | K34: =J34 -> 0.028567368 | L34: =K34 -> 0.028567368 | M34: =L34 -> 0.028567368 | N34: =M34 -> 0.028567368 | O34: =N34 -> 0.028567368 | P34: =O34 -> 0.028567368 | Q34: =P34 -> 0.028567368
B35: Total current assets
B37: Liabilities
B38: Non-current liabilities
B39: Financial liabilities
B40: Borrowings | C40: ='Historical Balance Sheet'!C50 -> 3661 | D40: ='Historical Balance Sheet'!D50 -> 1724 | E40: ='Historical Balance Sheet'!E50 -> 11278 | F40: ='Historical Balance Sheet'!F50 -> 10445 | G40: ='Historical Balance Sheet'!G50 -> 33537 | H40: =H41*'Revenue BuildUp'!H$10 -> 18579.875 | I40: =I41*'Revenue BuildUp'!I$10 -> 22138.955 | J40: =J41*'Revenue BuildUp'!J$10 -> 25802.839 | K40: =K41*'Revenue BuildUp'!K$10 -> 29489.462 | L40: =L41*'Revenue BuildUp'!L$10 -> 33124.786 | M40: =M41*'Revenue BuildUp'!M$10 -> 36646.27 | N40: =N41*'Revenue BuildUp'!N$10 -> 40004.54 | O40: =O41*'Revenue BuildUp'!O$10 -> 43163.576 | ... Q40: =Q41*'Revenue BuildUp'!Q$10 -> 48800.642
B41: % of Revenue | C41: =C40/'Revenue BuildUp'!C$10 -> 0.047335824 | D41: =D40/'Revenue BuildUp'!D$10 -> 0.015763727 | E41: =E40/'Revenue BuildUp'!E$10 -> 0.07890631 | F41: =F40/'Revenue BuildUp'!F$10 -> 0.064290375 | G41: =G40/'Revenue BuildUp'!G$10 -> 0.16273461 | H41: =AVERAGE(C41:G41) -> 0.07380617 | I41: =H41 -> 0.07380617 | J41: =I41 -> 0.07380617 | K41: =J41 -> 0.07380617 | L41: =K41 -> 0.07380617 | M41: =L41 -> 0.07380617 | N41: =M41 -> 0.07380617 | O41: =N41 -> 0.07380617 | P41: =O41 -> 0.07380617 | Q41: =P41 -> 0.07380617
B42: Lease liabilities | C42: ='Historical Balance Sheet'!C51 -> 1223 | D42: ='Historical Balance Sheet'!D51 -> 4119 | E42: ='Historical Balance Sheet'!E51 -> 4761 | F42: ='Historical Balance Sheet'!F51 -> 4570 | G42: ='Historical Balance Sheet'!G51 -> 5010 | H42: =H43*'Revenue BuildUp'!H$10 -> 7009.6987 | I42: =I43*'Revenue BuildUp'!I$10 -> 8352.446 | J42: =J43*'Revenue BuildUp'!J$10 -> 9734.7332 | K42: =K43*'Revenue BuildUp'!K$10 -> 11125.599 | L42: =L43*'Revenue BuildUp'!L$10 -> 12497.111 | M42: =M43*'Revenue BuildUp'!M$10 -> 13825.675 | N42: =N43*'Revenue BuildUp'!N$10 -> 15092.662 | O42: =O43*'Revenue BuildUp'!O$10 -> 16284.483 | ... Q42: =Q43*'Revenue BuildUp'!Q$10 -> 18411.2
B43: % of Revenue | C43: =C42/'Revenue BuildUp'!C$10 -> 0.015813087 | D43: =D42/'Revenue BuildUp'!D$10 -> 0.037662872 | E43: =E42/'Revenue BuildUp'!E$10 -> 0.033310245 | F43: =F42/'Revenue BuildUp'!F$10 -> 0.028128962 | G43: =G42/'Revenue BuildUp'!G$10 -> 0.024310475 | H43: =AVERAGE(C43:G43) -> 0.027845128 | I43: =H43 -> 0.027845128 | J43: =I43 -> 0.027845128 | K43: =J43 -> 0.027845128 | L43: =K43 -> 0.027845128 | M43: =L43 -> 0.027845128 | N43: =M43 -> 0.027845128 | O43: =N43 -> 0.027845128 | P43: =O43 -> 0.027845128 | Q43: =P43 -> 0.027845128
B44: Other financial liabilities | C44: ='Historical Balance Sheet'!C52 -> 2455 | D44: ='Historical Balance Sheet'!D52 -> 1291 | E44: ='Historical Balance Sheet'!E52 -> 1996 | F44: ='Historical Balance Sheet'!F52 -> 401 | G44: ='Historical Balance Sheet'!G52 -> 8330 | H44: =H45*'Revenue BuildUp'!H$10 -> 5054.9472 | I44: =I45*'Revenue BuildUp'!I$10 -> 6023.2509 | J44: =J45*'Revenue BuildUp'!J$10 -> 7020.0682 | K44: =K45*'Revenue BuildUp'!K$10 -> 8023.0719 | L44: =L45*'Revenue BuildUp'!L$10 -> 9012.1189 | M44: =M45*'Revenue BuildUp'!M$10 -> 9970.1941 | N44: =N45*'Revenue BuildUp'!N$10 -> 10883.864 | O44: =O45*'Revenue BuildUp'!O$10 -> 11743.33 | ... Q44: =Q45*'Revenue BuildUp'!Q$10 -> 13276.982
B45: % of Revenue | C45: =C44/'Revenue BuildUp'!C$10 -> 0.031742543 | D45: =D44/'Revenue BuildUp'!D$10 -> 0.011804508 | E45: =E44/'Revenue BuildUp'!E$10 -> 0.013964976 | F45: =F44/'Revenue BuildUp'!F$10 -> 0.0024682087 | G45: =G44/'Revenue BuildUp'!G$10 -> 0.040420411 | H45: =AVERAGE(C45:G45) -> 0.020080129 | I45: =H45 -> 0.020080129 | J45: =I45 -> 0.020080129 | K45: =J45 -> 0.020080129 | L45: =K45 -> 0.020080129 | M45: =L45 -> 0.020080129 | N45: =M45 -> 0.020080129 | O45: =N45 -> 0.020080129 | P45: =O45 -> 0.020080129 | Q45: =P45 -> 0.020080129
B46: Provisions | C46: ='Historical Balance Sheet'!C53 -> 1653 | D46: ='Historical Balance Sheet'!D53 -> 1618 | E46: ='Historical Balance Sheet'!E53 -> 2466 | F46: ='Historical Balance Sheet'!F53 -> 3338 | G46: ='Historical Balance Sheet'!G53 -> 5940 | H46: =H47*'Revenue BuildUp'!H$10 -> 5175.2324 | I46: =I47*'Revenue BuildUp'!I$10 -> 6166.5775 | J46: =J47*'Revenue BuildUp'!J$10 -> 7187.1145 | K46: =K47*'Revenue BuildUp'!K$10 -> 8213.9852 | L46: =L47*'Revenue BuildUp'!L$10 -> 9226.5672 | M46: =M47*'Revenue BuildUp'!M$10 -> 10207.44 | N46: =N47*'Revenue BuildUp'!N$10 -> 11142.852 | O46: =O47*'Revenue BuildUp'!O$10 -> 12022.769 | ... Q46: =Q47*'Revenue BuildUp'!Q$10 -> 13592.915
B47: % of Revenue | C47: =C46/'Revenue BuildUp'!C$10 -> 0.021372881 | D47: =D46/'Revenue BuildUp'!D$10 -> 0.014794495 | E47: =E46/'Revenue BuildUp'!E$10 -> 0.017253322 | F47: =F46/'Revenue BuildUp'!F$10 -> 0.020545837 | G47: =G46/'Revenue BuildUp'!G$10 -> 0.028823198 | H47: =AVERAGE(C47:G47) -> 0.020557947 | I47: =H47 -> 0.020557947 | J47: =I47 -> 0.020557947 | K47: =J47 -> 0.020557947 | L47: =K47 -> 0.020557947 | M47: =L47 -> 0.020557947 | N47: =M47 -> 0.020557947 | O47: =N47 -> 0.020557947 | P47: =O47 -> 0.020557947 | Q47: =P47 -> 0.020557947
B48: Deferred tax liabilities (net | C48: ='Historical Balance Sheet'!C54 -> 725 | D48: ='Historical Balance Sheet'!D54 -> 468 | E48: ='Historical Balance Sheet'!E54 -> 2060 | F48: ='Historical Balance Sheet'!F54 -> 1303 | G48: ='Historical Balance Sheet'!G54 -> 4841 | H48: =H49*'Revenue BuildUp'!H$10 -> 2999.5497 | I48: =I49*'Revenue BuildUp'!I$10 -> 3574.1303 | J48: =J49*'Revenue BuildUp'!J$10 -> 4165.6307 | K48: =K49*'Revenue BuildUp'!K$10 -> 4760.8019 | L48: =L49*'Revenue BuildUp'!L$10 -> 5347.6915 | M48: =M49*'Revenue BuildUp'!M$10 -> 5916.2027 | N48: =N49*'Revenue BuildUp'!N$10 -> 6458.3644 | O48: =O49*'Revenue BuildUp'!O$10 -> 6968.3616 | ... Q48: =Q49*'Revenue BuildUp'!Q$10 -> 7878.414
B49: % of Revenue | C49: =C48/'Revenue BuildUp'!C$10 -> 0.0093740707 | D49: =D48/'Revenue BuildUp'!D$10 -> 0.0042792484 | E49: =E48/'Revenue BuildUp'!E$10 -> 0.01441275 | F49: =F48/'Revenue BuildUp'!F$10 -> 0.0080201396 | G49: =G48/'Revenue BuildUp'!G$10 -> 0.023490421 | H49: =AVERAGE(C49:G49) -> 0.011915326 | I49: =H49 -> 0.011915326 | J49: =I49 -> 0.011915326 | K49: =J49 -> 0.011915326 | L49: =K49 -> 0.011915326 | M49: =L49 -> 0.011915326 | N49: =M49 -> 0.011915326 | O49: =N49 -> 0.011915326 | P49: =O49 -> 0.011915326 | Q49: =P49 -> 0.011915326
B51: Total non-current liabilities
B53: Current liabilities
B54: Contract liabilities | C54: ='Historical Balance Sheet'!C59 -> 674 | D54: ='Historical Balance Sheet'!D59 -> 1346 | E54: ='Historical Balance Sheet'!E59 -> 1157 | F54: ='Historical Balance Sheet'!F59 -> 1825 | G54: ='Historical Balance Sheet'!G59 -> 2194 | H54: =H55*'Revenue BuildUp'!H$10 -> 2567.5471 | I54: =I55*'Revenue BuildUp'!I$10 -> 3059.3752 | J54: =J55*'Revenue BuildUp'!J$10 -> 3565.6862 | K54: =K55*'Revenue BuildUp'!K$10 -> 4075.1394 | L54: =L55*'Revenue BuildUp'!L$10 -> 4577.5037 | M54: =M55*'Revenue BuildUp'!M$10 -> 5064.1365 | N54: =N55*'Revenue BuildUp'!N$10 -> 5528.2148 | O54: =O55*'Revenue BuildUp'!O$10 -> 5964.7609 | ... Q54: =Q55*'Revenue BuildUp'!Q$10 -> 6743.7453
B55: % of Revenue | C55: =C54/'Revenue BuildUp'!C$10 -> 0.0087146533 | D55: =D54/'Revenue BuildUp'!D$10 -> 0.012307411 | E55: =E54/'Revenue BuildUp'!E$10 -> 0.0080949283 | F55: =F54/'Revenue BuildUp'!F$10 -> 0.01123312 | G55: =G54/'Revenue BuildUp'!G$10 -> 0.010646144 | H55: =AVERAGE(C55:G55) -> 0.010199251 | I55: =H55 -> 0.010199251 | J55: =I55 -> 0.010199251 | K55: =J55 -> 0.010199251 | L55: =K55 -> 0.010199251 | M55: =L55 -> 0.010199251 | N55: =M55 -> 0.010199251 | O55: =N55 -> 0.010199251 | P55: =O55 -> 0.010199251 | Q55: =P55 -> 0.010199251
B56: Borrowings | C56: ='Historical Balance Sheet'!C61 -> 12969 | D56: ='Historical Balance Sheet'!D61 -> 17340 | E56: ='Historical Balance Sheet'!E61 -> 35477 | F56: ='Historical Balance Sheet'!F61 -> 33792 | G56: ='Historical Balance Sheet'!G61 -> 82554 | H56: =H57*'Revenue BuildUp'!H$10 -> 59562.919 | I56: =I57*'Revenue BuildUp'!I$10 -> 70972.533 | J56: =J57*'Revenue BuildUp'!J$10 -> 82718.125 | K56: =K57*'Revenue BuildUp'!K$10 -> 94536.611 | L56: =L57*'Revenue BuildUp'!L$10 -> 106190.65 | M56: =M57*'Revenue BuildUp'!M$10 -> 117479.74 | N56: =N57*'Revenue BuildUp'!N$10 -> 128245.6 | O56: =O57*'Revenue BuildUp'!O$10 -> 138372.76 | ... Q56: =Q57*'Revenue BuildUp'!Q$10 -> 156443.93
B57: % of Revenue | C57: =C56/'Revenue BuildUp'!C$10 -> 0.16768596 | D57: =D56/'Revenue BuildUp'!D$10 -> 0.15855164 | E57: =E56/'Revenue BuildUp'!E$10 -> 0.24821415 | F57: =F56/'Revenue BuildUp'!F$10 -> 0.20799429 | G57: =G56/'Revenue BuildUp'!G$10 -> 0.40058423 | H57: =AVERAGE(C57:G57) -> 0.23660605 | I57: =H57 -> 0.23660605 | J57: =I57 -> 0.23660605 | K57: =J57 -> 0.23660605 | L57: =K57 -> 0.23660605 | M57: =L57 -> 0.23660605 | N57: =M57 -> 0.23660605 | O57: =N57 -> 0.23660605 | P57: =O57 -> 0.23660605 | Q57: =P57 -> 0.23660605
B58: Lease liabilities | C58: ='Historical Balance Sheet'!C62 -> 1422 | D58: ='Historical Balance Sheet'!D62 -> 1792 | E58: ='Historical Balance Sheet'!E62 -> 1859 | F58: ='Historical Balance Sheet'!F62 -> 2412 | G58: ='Historical Balance Sheet'!G62 -> 3258 | H58: =H59*'Revenue BuildUp'!H$10 -> 3948.9424 | I58: =I59*'Revenue BuildUp'!I$10 -> 4705.3846 | J58: =J59*'Revenue BuildUp'!J$10 -> 5484.1018 | K58: =K59*'Revenue BuildUp'!K$10 -> 6267.6517 | L58: =L59*'Revenue BuildUp'!L$10 -> 7040.2987 | M58: =M59*'Revenue BuildUp'!M$10 -> 7788.7504 | N58: =N59*'Revenue BuildUp'!N$10 -> 8502.5128 | O58: =O59*'Revenue BuildUp'!O$10 -> 9173.9301 | ... Q58: =Q59*'Revenue BuildUp'!Q$10 -> 10372.025
B59: % of Revenue | C59: =C58/'Revenue BuildUp'!C$10 -> 0.018386108 | D59: =D58/'Revenue BuildUp'!D$10 -> 0.016385498 | E59: =E58/'Revenue BuildUp'!E$10 -> 0.013006458 | F59: =F58/'Revenue BuildUp'!F$10 -> 0.014846183 | G59: =G58/'Revenue BuildUp'!G$10 -> 0.015809088 | H59: =AVERAGE(C59:G59) -> 0.015686667 | I59: =H59 -> 0.015686667 | J59: =I59 -> 0.015686667 | K59: =J59 -> 0.015686667 | L59: =K59 -> 0.015686667 | M59: =L59 -> 0.015686667 | N59: =M59 -> 0.015686667 | O59: =N59 -> 0.015686667 | P59: =O59 -> 0.015686667 | Q59: =P59 -> 0.015686667
B60: Other financial liabilities | C60: ='Historical Balance Sheet'!C66 -> 4877 | D60: ='Historical Balance Sheet'!D66 -> 5788 | E60: ='Historical Balance Sheet'!E66 -> 7428 | F60: ='Historical Balance Sheet'!F66 -> 5810 | G60: ='Historical Balance Sheet'!G66 -> 14526 | H60: =H61*'Revenue BuildUp'!H$10 -> 13805.31 | I60: =I61*'Revenue BuildUp'!I$10 -> 16449.795 | J60: =J61*'Revenue BuildUp'!J$10 -> 19172.152 | K60: =K61*'Revenue BuildUp'!K$10 -> 21911.404 | L60: =L61*'Revenue BuildUp'!L$10 -> 24612.541 | M60: =M61*'Revenue BuildUp'!M$10 -> 27229.091 | N60: =N61*'Revenue BuildUp'!N$10 -> 29724.369 | O60: =O61*'Revenue BuildUp'!O$10 -> 32071.612 | ... Q60: =Q61*'Revenue BuildUp'!Q$10 -> 36260.092
B61: % of Revenue | C61: =C60/'Revenue BuildUp'!C$10 -> 0.063058404 | D61: =D60/'Revenue BuildUp'!D$10 -> 0.052923696 | E61: =E60/'Revenue BuildUp'!E$10 -> 0.051969859 | F61: =F60/'Revenue BuildUp'!F$10 -> 0.035761329 | G61: =G60/'Revenue BuildUp'!G$10 -> 0.070485821 | H61: =AVERAGE(C61:G61) -> 0.054839822 | I61: =H61 -> 0.054839822 | J61: =I61 -> 0.054839822 | K61: =J61 -> 0.054839822 | L61: =K61 -> 0.054839822 | M61: =L61 -> 0.054839822 | N61: =M61 -> 0.054839822 | O61: =N61 -> 0.054839822 | P61: =O61 -> 0.054839822 | Q61: =P61 -> 0.054839822
B62: Income tax liabilities (net) | C62: ='Historical Balance Sheet'!C67 -> 0 | D62: ='Historical Balance Sheet'!D67 -> 239 | E62: ='Historical Balance Sheet'!E67 -> 517 | F62: ='Historical Balance Sheet'!F67 -> 12 | G62: ='Historical Balance Sheet'!G67 -> 422 | H62: =H63*'Revenue BuildUp'!H$10 -> 398.96033 | I62: =I63*'Revenue BuildUp'!I$10 -> 475.38343 | J62: =J63*'Revenue BuildUp'!J$10 -> 554.05696 | K62: =K63*'Revenue BuildUp'!K$10 -> 633.21875 | L62: =L63*'Revenue BuildUp'!L$10 -> 711.27902 | M62: =M63*'Revenue BuildUp'!M$10 -> 786.89484 | N62: =N63*'Revenue BuildUp'!N$10 -> 859.00601 | O62: =O63*'Revenue BuildUp'!O$10 -> 926.83908 | ... Q62: =Q63*'Revenue BuildUp'!Q$10 -> 1047.8822
B63: % of Revenue | C63: =C62/'Revenue BuildUp'!C$10 -> 0 | D63: =D62/'Revenue BuildUp'!D$10 -> 0.0021853427 | E63: =E62/'Revenue BuildUp'!E$10 -> 0.0036171806 | F63: =F62/'Revenue BuildUp'!F$10 -> 7.3861608e-05 | G63: =G62/'Revenue BuildUp'!G$10 -> 0.0020477087 | H63: =AVERAGE(C63:G63) -> 0.0015848187 | I63: =H63 -> 0.0015848187 | J63: =I63 -> 0.0015848187 | K63: =J63 -> 0.0015848187 | L63: =K63 -> 0.0015848187 | M63: =L63 -> 0.0015848187 | N63: =M63 -> 0.0015848187 | O63: =N63 -> 0.0015848187 | P63: =O63 -> 0.0015848187 | Q63: =P63 -> 0.0015848187
B64: Other current liabilities | C64: ='Historical Balance Sheet'!C68 -> 1930 | D64: ='Historical Balance Sheet'!D68 -> 2426 | E64: ='Historical Balance Sheet'!E68 -> 2375 | F64: ='Historical Balance Sheet'!F68 -> 2796 | G64: ='Historical Balance Sheet'!G68 -> 3836 | H64: =H65*'Revenue BuildUp'!H$10 -> 5013.488 | I64: =I65*'Revenue BuildUp'!I$10 -> 5973.8499 | J64: =J65*'Revenue BuildUp'!J$10 -> 6962.4916 | K64: =K65*'Revenue BuildUp'!K$10 -> 7957.2689 | L64: =L65*'Revenue BuildUp'!L$10 -> 8938.204 | M64: =M65*'Revenue BuildUp'!M$10 -> 9888.4213 | N64: =N65*'Revenue BuildUp'!N$10 -> 10794.598 | O64: =O65*'Revenue BuildUp'!O$10 -> 11647.014 | ... Q64: =Q65*'Revenue BuildUp'!Q$10 -> 13168.088
B65: % of Revenue | C65: =C64/'Revenue BuildUp'!C$10 -> 0.024954423 | D65: =D64/'Revenue BuildUp'!D$10 -> 0.0221826 | E65: =E64/'Revenue BuildUp'!E$10 -> 0.016616642 | F65: =F64/'Revenue BuildUp'!F$10 -> 0.017209755 | G65: =G64/'Revenue BuildUp'!G$10 -> 0.018613769 | H65: =AVERAGE(C65:G65) -> 0.019915438 | I65: =H65 -> 0.019915438 | J65: =I65 -> 0.019915438 | K65: =J65 -> 0.019915438 | L65: =K65 -> 0.019915438 | M65: =L65 -> 0.019915438 | N65: =M65 -> 0.019915438 | O65: =N65 -> 0.019915438 | P65: =O65 -> 0.019915438 | Q65: =P65 -> 0.019915438
B66: Provisions | C66: ='Historical Balance Sheet'!C69 -> 1508 | D66: ='Historical Balance Sheet'!D69 -> 1698 | E66: ='Historical Balance Sheet'!E69 -> 1775 | F66: ='Historical Balance Sheet'!F69 -> 2136 | G66: ='Historical Balance Sheet'!G69 -> 3519 | H66: =H67*'Revenue BuildUp'!H$10 -> 3910.2957 | I66: =I67*'Revenue BuildUp'!I$10 -> 4659.3349 | J66: =J67*'Revenue BuildUp'!J$10 -> 5430.431 | K66: =K67*'Revenue BuildUp'!K$10 -> 6206.3127 | L66: =L67*'Revenue BuildUp'!L$10 -> 6971.3981 | M66: =M67*'Revenue BuildUp'!M$10 -> 7712.525 | N66: =N67*'Revenue BuildUp'!N$10 -> 8419.302 | O66: =O67*'Revenue BuildUp'!O$10 -> 9084.1484 | ... Q66: =Q67*'Revenue BuildUp'!Q$10 -> 10270.518
B67: % of Revenue | C67: =C66/'Revenue BuildUp'!C$10 -> 0.019498067 | D67: =D66/'Revenue BuildUp'!D$10 -> 0.015525991 | E67: =E66/'Revenue BuildUp'!E$10 -> 0.012418753 | F67: =F66/'Revenue BuildUp'!F$10 -> 0.013147366 | G67: =G66/'Revenue BuildUp'!G$10 -> 0.017075561 | H67: =AVERAGE(C67:G67) -> 0.015533148 | I67: =H67 -> 0.015533148 | J67: =I67 -> 0.015533148 | K67: =J67 -> 0.015533148 | L67: =K67 -> 0.015533148 | M67: =L67 -> 0.015533148 | N67: =M67 -> 0.015533148 | O67: =N67 -> 0.015533148 | P67: =O67 -> 0.015533148 | Q67: =P67 -> 0.015533148

Sheet Working Capital
B5: Working Capital
B6: (All amounts in INR Lakhs, unless otherwise stated)
A7: # | B7: Particulars | C7: 2021 | D7: =C7+1 -> 2022 | E7: =D7+1 -> 2023 | F7: =E7+1 -> 2024 | G7: =F7+1 -> 2025 | H7: =G7+1 -> 2026 | I7: =H7+1 -> 2027 | J7: =I7+1 -> 2028 | K7: =J7+1 -> 2029 | ... Q7: =P7+1 -> 2035
C8: Audited | D8: Audited | E8: Audited | F8: Audited | G8: Audited | H8: Estimated | I8: Projected | J8: Projected | K8: Projected | L8: Projected | M8: Projected | N8: Projected | O8: Projected | P8: Projected | Q8: Projected
B9: No of Days | C9: 365 | D9: 365 | E9: 365 | F9: 365 | G9: 365 | H9: 365 | I9: 365 | J9: 365 | K9: 365 | L9: 365 | M9: 365 | N9: 365 | O9: 365 | P9: 365 | Q9: 365
B11: Trade receivables | C11: ='Historical Balance Sheet'!C29 -> 12192 | D11: ='Historical Balance Sheet'!D29 -> 16738 | E11: ='Historical Balance Sheet'!E29 -> 21319 | F11: ='Historical Balance Sheet'!F29 -> 25444 | G11: ='Historical Balance Sheet'!G29 -> 35813 | H11: =H12*'Revenue BuildUp'!H10 -> 39786.536 | I11: =I12*'Revenue BuildUp'!I10 -> 47407.871 | J11: =J12*'Revenue BuildUp'!J10 -> 55253.632 | K11: =K12*'Revenue BuildUp'!K10 -> 63148.084 | L11: =L12*'Revenue BuildUp'!L10 -> 70932.687 | M11: =M12*'Revenue BuildUp'!M10 -> 78473.516 | N11: =N12*'Revenue BuildUp'!N10 -> 85664.842 | O11: =O12*'Revenue BuildUp'!O10 -> 92429.531 | ... Q11: =Q12*'Revenue BuildUp'!Q10 -> 104500.62
B12: % of Revenue | C12: =C11/'Historical P&L'!C10 -> 0.15763954 | D12: =D11/'Historical P&L'!D10 -> 0.15304714 | E12: =E11/'Historical P&L'!E10 -> 0.14915797 | F12: =F11/'Historical P&L'!F10 -> 0.15661123 | G12: =G11/'Historical P&L'!G10 -> 0.17377865 | H12: =AVERAGE(C12:G12) -> 0.15804691 | I12: =H12 -> 0.15804691 | J12: =I12 -> 0.15804691 | K12: =J12 -> 0.15804691 | L12: =K12 -> 0.15804691 | M12: =L12 -> 0.15804691 | N12: =M12 -> 0.15804691 | O12: =N12 -> 0.15804691 | P12: =O12 -> 0.15804691 | Q12: =P12 -> 0.15804691
B14: Trade payables | C14: =SUM('Historical Balance Sheet'!C64:C65) -> 4499 | D14: =SUM('Historical Balance Sheet'!D64:D65) -> 6072 | E14: =SUM('Historical Balance Sheet'!E64:E65) -> 7052 | F14: =SUM('Historical Balance Sheet'!F64:F65) -> 7915 | G14: =SUM('Historical Balance Sheet'!G64:G65) -> 10481 | H14: =H15*'Revenue BuildUp'!H10 -> 13221.645 | I14: =I15*'Revenue BuildUp'!I10 -> 15754.325 | J14: =J15*'Revenue BuildUp'!J10 -> 18361.586 | K14: =K15*'Revenue BuildUp'!K10 -> 20985.027 | L14: =L15*'Revenue BuildUp'!L10 -> 23571.964 | M14: =M15*'Revenue BuildUp'!M10 -> 26077.891 | N14: =N15*'Revenue BuildUp'!N10 -> 28467.673 | O14: =O15*'Revenue BuildUp'!O10 -> 30715.678 | ... Q14: =Q15*'Revenue BuildUp'!Q10 -> 34727.077
B15: % of Revenue | C15: =C14/'Historical P&L'!C10 -> 0.058170957 | D15: =D14/'Historical P&L'!D10 -> 0.055520505 | E15: =E14/'Historical P&L'!E10 -> 0.049339182 | F15: =F14/'Historical P&L'!F10 -> 0.048717886 | G15: =G14/'Historical P&L'!G10 -> 0.050857903 | H15: =AVERAGE(C15:G15) -> 0.052521287 | I15: =H15 -> 0.052521287 | J15: =I15 -> 0.052521287 | K15: =J15 -> 0.052521287 | L15: =K15 -> 0.052521287 | M15: =L15 -> 0.052521287 | N15: =M15 -> 0.052521287 | O15: =N15 -> 0.052521287 | P15: =O15 -> 0.052521287 | Q15: =P15 -> 0.052521287

Sheet Debt Schedules
B5: Debt Schedules
B6: (All amounts in INR Lakhs, unless otherwise stated)
A7: # | B7: Particulars | C7: 2021 | D7: =C7+1 -> 2022 | E7: =D7+1 -> 2023 | F7: =E7+1 -> 2024 | G7: =F7+1 -> 2025 | H7: =G7+1 -> 2026 | I7: =H7+1 -> 2027 | J7: =I7+1 -> 2028 | K7: =J7+1 -> 2029 | ... Q7: =P7+1 -> 2035
C8: Audited | D8: Audited | E8: Audited | F8: Audited | G8: Audited | H8: Estimated | I8: Projected | J8: Projected | K8: Projected | L8: Projected | M8: Projected | N8: Projected | O8: Projected | P8: Projected | Q8: Projected
B9: Debt
B10: Opening Balance | D10: =C12 -> 19275 | E10: =D12 -> 24975 | F10: =E12 -> 53375 | G10: =F12 -> 51219 | H10: =G12 -> 124359 | I10: =H12 -> 89101.435 | J10: =I12 -> 106169.32 | K10: =J12 -> 123739.8 | ... Q10: =P12 -> 221075.78
B11: Addition/ Repayment | D11: =D12-D10 -> 5700 | E11: =E12-E10 -> 28400 | F11: =F12-F10 -> -2156 | G11: =G12-G10 -> 73140 | H11: =H12-H10 -> -35257.565 | I11: =I12-I10 -> 17067.883 | J11: =J12-J10 -> 17570.48 | K11: =K12-K10 -> 17679.525 | ... Q11: =Q12-Q10 -> 12952.016
B12: Closing Balance | C12: ='BS Items'!C40+'BS Items'!C42+'BS Items'!C56+'BS Items'!C58 -> 19275 | D12: ='BS Items'!D40+'BS Items'!D42+'BS Items'!D56+'BS Items'!D58 -> 24975 | E12: ='BS Items'!E40+'BS Items'!E42+'BS Items'!E56+'BS Items'!E58 -> 53375 | F12: ='BS Items'!F40+'BS Items'!F42+'BS Items'!F56+'BS Items'!F58 -> 51219 | G12: ='BS Items'!G40+'BS Items'!G42+'BS Items'!G56+'BS Items'!G58 -> 124359 | H12: ='BS Items'!H40+'BS Items'!H42+'BS Items'!H56+'BS Items'!H58 -> 89101.435 | I12: ='BS Items'!I40+'BS Items'!I42+'BS Items'!I56+'BS Items'!I58 -> 106169.32 | J12: ='BS Items'!J40+'BS Items'!J42+'BS Items'!J56+'BS Items'!J58 -> 123739.8 | ... Q12: ='BS Items'!Q40+'BS Items'!Q42+'BS Items'!Q56+'BS Items'!Q58 -> 234027.8
B14: Interest Expenses | C14: ='Historical P&L'!C17 -> 697 | D14: ='Historical P&L'!D17 -> 995 | E14: ='Historical P&L'!E17 -> 2186 | F14: ='Historical P&L'!F17 -> 4227 | G14: ='Historical P&L'!G17 -> 9948 | H14: =H15*AVERAGE(H12,H10) -> 7067.1936 | I14: =I15*AVERAGE(I12,I10) -> 6464.9743 | J14: =J15*AVERAGE(J12,J10) -> 7611.7724 | K14: =K15*AVERAGE(K12,K10) -> 8778.8206 | L14: =L15*AVERAGE(L12,L10) -> 9941.3343 | M14: =M15*AVERAGE(M12,M10) -> 11077.629 | N14: =N15*AVERAGE(N12,N10) -> 12169.935 | O14: =O15*AVERAGE(O12,O10) -> 13204.695 | ... Q14: =Q15*AVERAGE(Q12,Q10) -> 15067.453
B15: % of Debt | C15: =C14/AVERAGE(C12,C10) -> 0.03616083 | D15: =D14/AVERAGE(D12,D10) -> 0.044971751 | E15: =E14/AVERAGE(E12,E10) -> 0.055800893 | F15: =F14/AVERAGE(F12,F10) -> 0.080826816 | G15: =G14/AVERAGE(G12,G10) -> 0.11331716 | H15: =AVERAGE(C15:G15) -> 0.06621549 | I15: =H15 -> 0.06621549 | J15: =I15 -> 0.06621549 | K15: =J15 -> 0.06621549 | L15: =K15 -> 0.06621549 | M15: =L15 -> 0.06621549 | N15: =M15 -> 0.06621549 | O15: =N15 -> 0.06621549 | P15: =O15 -> 0.06621549 | Q15: =P15 -> 0.06621549

Sheet Profit & Loss Statement
B5: Profit & Loss Statement
B6: (All amounts in INR Lakhs, unless otherwise stated)
A7: # | B7: Particulars | C7: 2021 | D7: =C7+1 -> 2022 | E7: =D7+1 -> 2023 | F7: =E7+1 -> 2024 | G7: =F7+1 -> 2025 | H7: =G7+1 -> 2026 | I7: =H7+1 -> 2027 | J7: =I7+1 -> 2028 | K7: =J7+1 -> 2029 | ... Q7: =P7+1 -> 2035
C8: Audited | D8: Audited | E8: Audited | F8: Audited | G8: Audited | H8: Estimated | I8: Projected | J8: Projected | K8: Projected | L8: Projected | M8: Projected | N8: Projected | O8: Projected | P8: Projected | Q8: Projected
B9: Revenue | C9: ='Revenue BuildUp'!C10 -> 77341 | D9: ='Revenue BuildUp'!D10 -> 109365 | E9: ='Revenue BuildUp'!E10 -> 142929 | F9: ='Revenue BuildUp'!F10 -> 162466 | G9: ='Revenue BuildUp'!G10 -> 206084 | H9: ='Revenue BuildUp'!H10 -> 251738.78 | I9: ='Revenue BuildUp'!I10 -> 299960.77 | J9: ='Revenue BuildUp'!J10 -> 349602.74 | ... Q9: ='Revenue BuildUp'!Q10 -> 661200.04
B10: Total Income | C10: =C9 -> 77341 | D10: =D9 -> 109365 | E10: =E9 -> 142929 | F10: =F9 -> 162466 | G10: =G9 -> 206084 | H10: =H9 -> 251738.78 | I10: =I9 -> 299960.77 | J10: =J9 -> 349602.74 | ... Q10: =Q9 -> 661200.04
B12: Expenses
B14: Employee Expenses | C14: ='Cost Buildup'!C13 -> 45238 | D14: ='Cost Buildup'!D13 -> 62000 | E14: ='Cost Buildup'!E13 -> 80681 | F14: ='Cost Buildup'!F13 -> 101469 | G14: ='Cost Buildup'!G13 -> 136534 | H14: ='Cost Buildup'!H13 -> 151213.43 | I14: ='Cost Buildup'!I13 -> 180179.22 | J14: ='Cost Buildup'!J13 -> 209997.96 | ... Q14: ='Cost Buildup'!Q13 -> 397166.96
B15: Other expenses | C15: ='Cost Buildup'!C16 -> 12954 | D15: ='Cost Buildup'!D16 -> 21598 | E15: ='Cost Buildup'!E16 -> 26362 | F15: ='Cost Buildup'!F16 -> 26882 | G15: ='Cost Buildup'!G16 -> 32518 | H15: ='Cost Buildup'!H16 -> 43937.03 | I15: ='Cost Buildup'!I16 -> 52353.416 | J15: ='Cost Buildup'!J16 -> 61017.639 | ... Q15: ='Cost Buildup'!Q16 -> 115402.03
B16: Impairment loss allowance on trade and unbilled receivables | C16: ='Cost Buildup'!C19 -> 0 | D16: ='Cost Buildup'!D19 -> 0 | E16: ='Cost Buildup'!E19 -> 0 | F16: ='Cost Buildup'!F19 -> 530 | G16: ='Cost Buildup'!G19 -> 1590 | H16: ='Cost Buildup'!H19 -> 552.69358 | I16: ='Cost Buildup'!I19 -> 658.56516 | J16: ='Cost Buildup'!J19 -> 767.55433 | ... Q16: ='Cost Buildup'!Q19 -> 1451.6675
B17: Total Expenses | C17: =SUM(C14:C16) -> 58192 | D17: =SUM(D14:D16) -> 83598 | E17: =SUM(E14:E16) -> 107043 | F17: =SUM(F14:F16) -> 128881 | G17: =SUM(G14:G16) -> 170642 | H17: =SUM(H14:H16) -> 195703.15 | I17: =SUM(I14:I16) -> 233191.2 | J17: =SUM(J14:J16) -> 271783.15 | ... Q17: =SUM(Q14:Q16) -> 514020.65
B19: EBITDA | C19: =C10-C17 -> 19149 | D19: =D10-D17 -> 25767 | E19: =E10-E17 -> 35886 | F19: =F10-F17 -> 33585 | G19: =G10-G17 -> 35442 | H19: =H10-H17 -> 56035.626 | I19: =I10-I17 -> 66769.567 | J19: =J10-J17 -> 77819.59 | ... Q19: =Q10-Q17 -> 147179.38
B21: D&A | C21: =FAS!C369 -> 2274 | D21: =FAS!D369 -> 3288 | E21: =FAS!E369 -> 4191 | F21: =FAS!F369 -> 5829 | G21: =FAS!G369 -> 8870 | H21: =FAS!H369 -> 4870.2 | I21: =FAS!I369 -> 4894.551 | J21: =FAS!J369 -> 4919.0238 | ... Q21: =FAS!Q369 -> 5093.7937
B23: EBIT | C23: =C19-C21 -> 16875 | D23: =D19-D21 -> 22479 | E23: =E19-E21 -> 31695 | F23: =F19-F21 -> 27756 | G23: =G19-G21 -> 26572 | H23: =H19-H21 -> 51165.426 | I23: =I19-I21 -> 61875.016 | J23: =J19-J21 -> 72900.566 | ... Q23: =Q19-Q21 -> 142085.59
B25: Finance Cost | C25: ='Debt Schedules'!C14 -> 697 | D25: ='Debt Schedules'!D14 -> 995 | E25: ='Debt Schedules'!E14 -> 2186 | F25: ='Debt Schedules'!F14 -> 4227 | G25: ='Debt Schedules'!G14 -> 9948 | H25: ='Debt Schedules'!H14 -> 7067.1936 | I25: ='Debt Schedules'!I14 -> 6464.9743 | J25: ='Debt Schedules'!J14 -> 7611.7724 | ... Q25: ='Debt Schedules'!Q14 -> 15067.453
B26: Other Income | C26: ='Revenue BuildUp'!C58 -> 2424 | D26: ='Revenue BuildUp'!D58 -> 3710 | E26: ='Revenue BuildUp'!E58 -> 2111 | F26: ='Revenue BuildUp'!F58 -> 8537 | G26: ='Revenue BuildUp'!G58 -> 10138 | H26: ='Revenue BuildUp'!H58 -> 9151.9283 | I26: ='Revenue BuildUp'!I58 -> 10905.032 | J26: ='Revenue BuildUp'!J58 -> 12709.759 | ... Q26: ='Revenue BuildUp'!Q58 -> 24037.835
B27: Exceptional Items | C27: ='Revenue BuildUp'!C62 -> 0 | D27: ='Revenue BuildUp'!D62 -> -609 | E27: ='Revenue BuildUp'!E62 -> -634 | F27: ='Revenue BuildUp'!F62 -> 1402 | G27: ='Revenue BuildUp'!G62 -> -1216 | H27: ='Revenue BuildUp'!H62 -> -366.29436 | I27: ='Revenue BuildUp'!I62 -> -436.46011 | J27: ='Revenue BuildUp'!J62 -> -508.69203 | ... Q27: ='Revenue BuildUp'!Q62 -> -962.08396
B28: EBT | C28: =C23-C25+C26-C27 -> 18602 | D28: =D23-D25+D26+D27 -> 24585 | E28: =E23-E25+E26+E27 -> 30986 | F28: =F23-F25+F26+F27 -> 33468 | G28: =G23-G25+G26+G27 -> 25546 | H28: =H23-H25+H26+H27 -> 52883.867 | I28: =I23-I25+I26+I27 -> 65878.614 | J28: =J23-J25+J26+J27 -> 77489.861 | K28: =K23-K25+K26+K27 -> 89160.065 | ... Q28: =Q23-Q25+Q26+Q27 -> 150093.89
B30: Taxes | C30: ='Cost Buildup'!C22 -> 2356 | D30: ='Cost Buildup'!D22 -> 6465 | E30: ='Cost Buildup'!E22 -> 7887 | F30: ='Cost Buildup'!F22 -> 8629 | G30: ='Cost Buildup'!G22 -> 7080 | H30: ='Cost Buildup'!H22 -> 14921.03 | I30: ='Cost Buildup'!I22 -> 18587.46 | J30: ='Cost Buildup'!J22 -> 22250.989 | ... Q30: ='Cost Buildup'!Q22 -> 45028.166
B32: Net Profit | C32: =C28-C30 -> 16246 | D32: =D28-D30 -> 18120 | E32: =E28-E30 -> 23099 | F32: =F28-F30 -> 24839 | G32: =G28-G30 -> 18466 | H32: =H28-H30 -> 37962.837 | I32: =I28-I30 -> 47291.153 | J32: =J28-J30 -> 55238.871 | ... Q32: =Q28-Q30 -> 105065.72
B34: Dividend Paid | C34: =CashFlow!C68 -> 0 | D34: =CashFlow!D68 -> -6830 | E34: =CashFlow!E68 -> -5715 | F34: =CashFlow!F68 -> -8604 | G34: =CashFlow!G68 -> -8588 | H34: =-H35*H32 -> -13626.823 | I34: =-I35*I32 -> -16975.237 | J34: =-J35*J32 -> -19828.084 | K34: =-K35*K32 -> -22814.252 | L34: =-L35*L32 -> -25575.102 | M34: =-M35*M32 -> -28401.69 | N34: =-N35*N32 -> -30875.101 | O34: =-O35*O32 -> -33388.254 | ... Q34: =-Q35*Q32 -> -37713.513
B35: Dividened PayOut Ratio | C35: =-C34/C32 -> 0 | D35: =-D34/D32 -> 0.37693157 | E35: =-E34/E32 -> 0.24741331 | F35: =-F34/F32 -> 0.34639076 | G35: =-G34/G32 -> 0.46507094 | H35: =AVERAGE(D35:G35) -> 0.35895164 | I35: =H35 -> 0.35895164 | J35: =I35 -> 0.35895164 | K35: =J35 -> 0.35895164 | L35: =K35 -> 0.35895164 | M35: =L35 -> 0.35895164 | N35: =M35 -> 0.35895164 | O35: =N35 -> 0.35895164 | P35: =O35 -> 0.35895164 | Q35: =P35 -> 0.35895164
B37: Retained Earning | C37: =C32+C34 -> 16246 | D37: =D32+D34 -> 11290 | E37: =E32+E34 -> 17384 | F37: =F32+F34 -> 16235 | G37: =G32+G34 -> 9878 | H37: =H32+H34 -> 24336.014 | I37: =I32+I34 -> 30315.916 | J37: =J32+J34 -> 35410.788 | ... Q37: =Q32+Q34 -> 67352.208
B38: Retained Earning % | C38: =C37/C32 -> 1 | D38: =D37/D32 -> 0.62306843 | E38: =E37/E32 -> 0.75258669 | F38: =F37/F32 -> 0.65360924 | G38: =G37/G32 -> 0.53492906 | H38: =H37/H32 -> 0.64104836 | I38: =I37/I32 -> 0.64104836 | J38: =J37/J32 -> 0.64104836 | ... Q38: =Q37/Q32 -> 0.64104836
C51: ='Profit & Loss Statement'!C23/'Profit & Loss Statement'!B241 -> #DIV/0!

Sheet Balance sheet
B5: Balance Sheet
B6: (All amounts in INR Lakhs, unless otherwise stated)
B7: Master Check | C7: =IF(SUM(C70:Q70)=0, "OK", "Error") -> OK
A8: # | B8: Particulars | C8: 2021 | D8: =C8+1 -> 2022 | E8: =D8+1 -> 2023 | F8: =E8+1 -> 2024 | G8: =F8+1 -> 2025 | H8: =G8+1 -> 2026 | I8: =H8+1 -> 2027 | J8: =I8+1 -> 2028 | K8: =J8+1 -> 2029 | ... Q8: =P8+1 -> 2035
C9: Audited | D9: Audited | E9: Audited | F9: Audited | G9: Audited | H9: Estimated | I9: Projected | J9: Projected | K9: Projected | L9: Projected | M9: Projected | N9: Projected | O9: Projected | P9: Projected | Q9: Projected
B10: Non-current assets
B11: Property, plant and equipment | C11: =SUM(FAS!C368,FAS!C372,FAS!C374) -> 5199 | D11: =SUM(FAS!D368,FAS!D372,FAS!D374) -> 7899 | E11: =SUM(FAS!E368,FAS!E372,FAS!E374) -> 29512 | F11: =SUM(FAS!F368,FAS!F372,FAS!F374) -> 27293 | G11: =SUM(FAS!G368,FAS!G372,FAS!G374) -> 44903 | H11: =SUM(FAS!H368,FAS!H372,FAS!H374) -> 46634.8 | I11: =SUM(FAS!I368,FAS!I372,FAS!I374) -> 48432.229 | J11: =SUM(FAS!J368,FAS!J372,FAS!J374) -> 50201.775 | ... Q11: =SUM(FAS!Q368,FAS!Q372,FAS!Q374) -> 62988.54
B12: Goodwill | C12: ='Historical Balance Sheet'!C13 -> 7644 | D12: ='Historical Balance Sheet'!D13 -> 7896 | E12: ='Historical Balance Sheet'!E13 -> 13913 | F12: ='Historical Balance Sheet'!F13 -> 14032 | G12: ='Historical Balance Sheet'!G13 -> 76230 | H12: =G12 -> 76230 | I12: =H12 -> 76230 | J12: =I12 -> 76230 | K12: =J12 -> 76230 | L12: =K12 -> 76230 | M12: =L12 -> 76230 | N12: =M12 -> 76230 | O12: =N12 -> 76230 | ... Q12: =P12 -> 76230
B13: Financial assets
B14: Investments | C14: ='BS Items'!C13 -> 0 | D14: ='BS Items'!D13 -> 762 | E14: ='BS Items'!E13 -> 1296 | F14: ='BS Items'!F13 -> 0 | G14: ='BS Items'!G13 -> 0 | H14: ='BS Items'!H13 -> 807.32291 | I14: ='BS Items'!I13 -> 961.97017 | J14: ='BS Items'!J13 -> 1121.1713 | ... Q14: ='BS Items'!Q13 -> 2120.4597
B15: Other financial assets | C15: ='BS Items'!C15 -> 2458 | D15: ='BS Items'!D15 -> 1827 | E15: ='BS Items'!E15 -> 9389 | F15: ='BS Items'!F15 -> 2480 | G15: ='BS Items'!G15 -> 7358 | H15: ='BS Items'!H15 -> 8314.7022 | I15: ='BS Items'!I15 -> 9907.4304 | J15: ='BS Items'!J15 -> 11547.06 | ... Q15: ='BS Items'!Q15 -> 21838.834
B16: Income tax assets (net | C16: ='BS Items'!C17 -> 1408 | D16: ='BS Items'!D17 -> 680 | E16: ='BS Items'!E17 -> 1310 | F16: ='BS Items'!F17 -> 1529 | G16: ='BS Items'!G17 -> 3537 | H16: ='BS Items'!H17 -> 3029.0367 | I16: ='BS Items'!I17 -> 3609.2657 | J16: ='BS Items'!J17 -> 4206.5808 | ... Q16: ='BS Items'!Q17 -> 7955.8626
B17: Other assets | C17: ='BS Items'!C19 -> 7 | D17: ='BS Items'!D19 -> 1 | E17: ='BS Items'!E19 -> 119 | F17: ='BS Items'!F19 -> 32 | G17: ='BS Items'!G19 -> 170 | H17: ='BS Items'!H19 -> 98.384742 | I17: ='BS Items'!I19 -> 117.2309 | J17: ='BS Items'!J19 -> 136.63201 | ... Q17: ='BS Items'!Q19 -> 258.4107
B18: Deferred tax assets (net) | C18: ='BS Items'!C21 -> 1026 | D18: ='BS Items'!D21 -> 697 | E18: ='BS Items'!E21 -> 1246 | F18: ='BS Items'!F21 -> 1636 | G18: ='BS Items'!G21 -> 3613 | H18: ='BS Items'!H21 -> 2817.3688 | I18: ='BS Items'!I21 -> 3357.0517 | J18: ='BS Items'!J21 -> 3912.6267 | ... Q18: ='BS Items'!Q21 -> 7399.9102
B20: Total non-current assets | C20: =SUM(C11:C18) -> 17742 | D20: =SUM(D11:D18) -> 19762 | E20: =SUM(E11:E18) -> 56785 | F20: =SUM(F11:F18) -> 47002 | G20: =SUM(G11:G18) -> 135811 | H20: =SUM(H11:H18) -> 137931.62 | I20: =SUM(I11:I18) -> 142615.18 | J20: =SUM(J11:J18) -> 147355.85 | ... Q20: =SUM(Q11:Q18) -> 178792.02
B22: Current assets
B23: Financial assets
B24: Investments | C24: ='BS Items'!C27 -> 39148 | D24: ='BS Items'!D27 -> 46400 | E24: ='BS Items'!E27 -> 0 | F24: ='BS Items'!F27 -> 0 | G24: ='BS Items'!G27 -> 35039 | H24: ='BS Items'!H27 -> 92343.173 | I24: ='BS Items'!I27 -> 110032.03 | J24: ='BS Items'!J27 -> 128241.77 | ... Q24: ='BS Items'!Q27 -> 242542.33
B25: Trade receivables | C25: ='Working Capital'!C11 -> 12192 | D25: ='Working Capital'!D11 -> 16738 | E25: ='Working Capital'!E11 -> 21319 | F25: ='Working Capital'!F11 -> 25444 | G25: ='Working Capital'!G11 -> 35813 | H25: ='Working Capital'!H11 -> 39786.536 | I25: ='Working Capital'!I11 -> 47407.871 | J25: ='Working Capital'!J11 -> 55253.632 | ... Q25: ='Working Capital'!Q11 -> 104500.62
B26: Cash and cash equivalents | C26: ='Historical Balance Sheet'!C30 -> 8583 | D26: ='Historical Balance Sheet'!D30 -> 6729 | E26: ='Historical Balance Sheet'!E30 -> -120 | F26: ='Historical Balance Sheet'!F30 -> 10897 | G26: ='Historical Balance Sheet'!G30 -> 11912 | H26: =CashFlow!H79 -> 24065.708 | I26: =CashFlow!I79 -> 45905.894 | J26: =CashFlow!J79 -> 72672.178 | K26: =CashFlow!K79 -> 104683.05 | L26: =CashFlow!L79 -> 141748.55 | M26: =CashFlow!M79 -> 184029.82 | N26: =CashFlow!N79 -> 231062.3 | O26: =CashFlow!O79 -> 282910.94 | ... Q26: =CashFlow!Q79 -> 399528.95
B27: Bank balance other than cash and cash equivalents | C27: ='Historical Balance Sheet'!C31 -> 5935 | D27: ='Historical Balance Sheet'!D31 -> 10071 | E27: ='Historical Balance Sheet'!E31 -> 69303 | F27: ='Historical Balance Sheet'!F31 -> 122756 | G27: ='Historical Balance Sheet'!G31 -> 93911 | H27: 0 | I27: =H27 -> 0 | J27: =I27 -> 0 | K27: =J27 -> 0 | L27: =K27 -> 0 | M27: =L27 -> 0 | N27: =M27 -> 0 | O27: =N27 -> 0 | P27: =O27 -> 0 | Q27: =P27 -> 0
B28: Loans | C28: ='BS Items'!C29 -> 14 | D28: ='BS Items'!D29 -> 4 | E28: ='BS Items'!E29 -> 64 | F28: ='BS Items'!F29 -> 37 | G28: ='BS Items'!G29 -> 12 | H28: ='BS Items'!H29 -> 47.897568 | I28: ='BS Items'!I29 -> 57.072618 | J28: ='BS Items'!J29 -> 66.517845 | ... Q28: ='BS Items'!Q29 -> 125.80451
B29: Other financial assets | C29: ='BS Items'!C31 -> 6779 | D29: ='BS Items'!D31 -> 9405 | E29: ='BS Items'!E31 -> 12237 | F29: ='BS Items'!F31 -> 13850 | G29: ='BS Items'!G31 -> 17726 | H29: ='BS Items'!H31 -> 21675.98 | I29: ='BS Items'!I31 -> 25828.136 | J29: ='BS Items'!J31 -> 30102.561 | ... Q29: ='BS Items'!Q31 -> 56932.661
B30: Other assets | C30: ='BS Items'!C33 -> 1802 | D30: ='BS Items'!D33 -> 3392 | E30: ='BS Items'!E33 -> 4495 | F30: ='BS Items'!F33 -> 4793 | G30: ='BS Items'!G33 -> 5682 | H30: ='BS Items'!H33 -> 7191.5144 | I30: ='BS Items'!I33 -> 8569.0897 | J30: ='BS Items'!J33 -> 9987.2303 | ... Q30: ='BS Items'!Q33 -> 18888.745
B32: Total current assets | C32: =SUM(C24:C31) -> 74453 | D32: =SUM(D24:D31) -> 92739 | E32: =SUM(E24:E31) -> 107298 | F32: =SUM(F24:F31) -> 177777 | G32: =SUM(G24:G31) -> 200095 | H32: =SUM(H24:H31) -> 185110.81 | I32: =SUM(I24:I31) -> 237800.09 | J32: =SUM(J24:J31) -> 296323.89 | ... Q32: =SUM(Q24:Q31) -> 822519.11
B34: Total Assets | C34: =C32+C20 -> 92195 | D34: =D32+D20 -> 112501 | E34: =E32+E20 -> 164083 | F34: =F32+F20 -> 224779 | G34: =G32+G20 -> 335906 | H34: =H32+H20 -> 323042.42 | I34: =I32+I20 -> 380415.27 | J34: =J32+J20 -> 443679.73 | ... Q34: =Q32+Q20 -> 1001311.1
B36: Equity and liabilities
B37: Equity
B38: Equity share capital | C38: ='Historical Balance Sheet'!C42 -> 2837 | D38: ='Historical Balance Sheet'!D42 -> 2854 | E38: ='Historical Balance Sheet'!E42 -> 2866 | F38: ='Historical Balance Sheet'!F42 -> 2987 | G38: ='Historical Balance Sheet'!G42 -> 3001 | H38: =G38 -> 3001 | I38: =H38 -> 3001 | J38: =I38 -> 3001 | K38: =J38 -> 3001 | L38: =K38 -> 3001 | M38: =L38 -> 3001 | N38: =M38 -> 3001 | O38: =N38 -> 3001 | ... Q38: =P38 -> 3001
B39: Other equity | C39: ='Historical Balance Sheet'!C43 -> 51762 | D39: ='Historical Balance Sheet'!D43 -> 63726 | E39: ='Historical Balance Sheet'!E43 -> 81016 | F39: ='Historical Balance Sheet'!F43 -> 145037 | G39: ='Historical Balance Sheet'!G43 -> 154457 | H39: =G39+'Profit & Loss Statement'!H37 -> 178793.01 | I39: =H39+'Profit & Loss Statement'!I37 -> 209108.93 | J39: =I39+'Profit & Loss Statement'!J37 -> 244519.72 | K39: =J39+'Profit & Loss Statement'!K37 -> 285263.48 | L39: =K39+'Profit & Loss Statement'!L37 -> 330937.81 | M39: =L39+'Profit & Loss Statement'!M37 -> 381660.12 | N39: =M39+'Profit & Loss Statement'!N37 -> 436799.67 | O39: =N39+'Profit & Loss Statement'!O37 -> 496427.44 | ... Q39: =P39+'Profit & Loss Statement'!Q37 -> 627316.61
B40: Total equity | C40: =SUM(C38:C39) -> 54599 | D40: =SUM(D38:D39) -> 66580 | E40: =SUM(E38:E39) -> 83882 | F40: =SUM(F38:F39) -> 148024 | G40: =SUM(G38:G39) -> 157458 | H40: =SUM(H38:H39) -> 181794.01 | I40: =SUM(I38:I39) -> 212109.93 | J40: =SUM(J38:J39) -> 247520.72 | ... Q40: =SUM(Q38:Q39) -> 630317.61
B42: Liabilities
B43: Non-current liabilities
B44: Financial liabilities
B45: Borrowings | C45: ='BS Items'!C40 -> 3661 | D45: ='BS Items'!D40 -> 1724 | E45: ='BS Items'!E40 -> 11278 | F45: ='BS Items'!F40 -> 10445 | G45: ='BS Items'!G40 -> 33537 | H45: ='BS Items'!H40 -> 18579.875 | I45: ='BS Items'!I40 -> 22138.955 | J45: ='BS Items'!J40 -> 25802.839 | ... Q45: ='BS Items'!Q40 -> 48800.642
B46: Lease liabilities | C46: ='BS Items'!C42 -> 1223 | D46: ='BS Items'!D42 -> 4119 | E46: ='BS Items'!E42 -> 4761 | F46: ='BS Items'!F42 -> 4570 | G46: ='BS Items'!G42 -> 5010 | H46: ='BS Items'!H42 -> 7009.6987 | I46: ='BS Items'!I42 -> 8352.446 | J46: ='BS Items'!J42 -> 9734.7332 | ... Q46: ='BS Items'!Q42 -> 18411.2
B47: Other financial liabilities | C47: ='BS Items'!C44 -> 2455 | D47: ='BS Items'!D44 -> 1291 | E47: ='BS Items'!E44 -> 1996 | F47: ='BS Items'!F44 -> 401 | G47: ='BS Items'!G44 -> 8330 | H47: ='BS Items'!H44 -> 5054.9472 | I47: ='BS Items'!I44 -> 6023.2509 | J47: ='BS Items'!J44 -> 7020.0682 | ... Q47: ='BS Items'!Q44 -> 13276.982
B48: Provisions | C48: ='BS Items'!C46 -> 1653 | D48: ='BS Items'!D46 -> 1618 | E48: ='BS Items'!E46 -> 2466 | F48: ='BS Items'!F46 -> 3338 | G48: ='BS Items'!G46 -> 5940 | H48: ='BS Items'!H46 -> 5175.2324 | I48: ='BS Items'!I46 -> 6166.5775 | J48: ='BS Items'!J46 -> 7187.1145 | ... Q48: ='BS Items'!Q46 -> 13592.915
B49: Deferred tax liabilities (net | C49: ='BS Items'!C48 -> 725 | D49: ='BS Items'!D48 -> 468 | E49: ='BS Items'!E48 -> 2060 | F49: ='BS Items'!F48 -> 1303 | G49: ='BS Items'!G48 -> 4841 | H49: ='BS Items'!H48 -> 2999.5497 | I49: ='BS Items'!I48 -> 3574.1303 | J49: ='BS Items'!J48 -> 4165.6307 | ... Q49: ='BS Items'!Q48 -> 7878.414
B51: Total non-current liabilities | C51: =SUM(C45:C50) -> 9717 | D51: =SUM(D45:D50) -> 9220 | E51: =SUM(E45:E50) -> 22561 | F51: =SUM(F45:F50) -> 20057 | G51: =SUM(G45:G50) -> 57658 | H51: =SUM(H45:H50) -> 38819.303 | I51: =SUM(I45:I50) -> 46255.36 | J51: =SUM(J45:J50) -> 53910.386 | ... Q51: =SUM(Q45:Q50) -> 101960.15
B53: Current liabilities
B54: Contract liabilities | C54: ='BS Items'!C54 -> 674 | D54: ='BS Items'!D54 -> 1346 | E54: ='BS Items'!E54 -> 1157 | F54: ='BS Items'!F54 -> 1825 | G54: ='BS Items'!G54 -> 2194 | H54: ='BS Items'!H54 -> 2567.5471 | I54: ='BS Items'!I54 -> 3059.3752 | J54: ='BS Items'!J54 -> 3565.6862 | ... Q54: ='BS Items'!Q54 -> 6743.7453
B55: Financial liabilities
B56: Borrowings | C56: ='BS Items'!C56 -> 12969 | D56: ='BS Items'!D56 -> 17340 | E56: ='BS Items'!E56 -> 35477 | F56: ='BS Items'!F56 -> 33792 | G56: ='BS Items'!G56 -> 82554 | H56: ='BS Items'!H56 -> 59562.919 | I56: ='BS Items'!I56 -> 70972.533 | J56: ='BS Items'!J56 -> 82718.125 | ... Q56: ='BS Items'!Q56 -> 156443.93
B57: Lease liabilities | C57: ='BS Items'!C58 -> 1422 | D57: ='BS Items'!D58 -> 1792 | E57: ='BS Items'!E58 -> 1859 | F57: ='BS Items'!F58 -> 2412 | G57: ='BS Items'!G58 -> 3258 | H57: ='BS Items'!H58 -> 3948.9424 | I57: ='BS Items'!I58 -> 4705.3846 | J57: ='BS Items'!J58 -> 5484.1018 | ... Q57: ='BS Items'!Q58 -> 10372.025
B58: Trade payables | C58: ='Working Capital'!C14 -> 4499 | D58: ='Working Capital'!D14 -> 6072 | E58: ='Working Capital'!E14 -> 7052 | F58: ='Working Capital'!F14 -> 7915 | G58: ='Working Capital'!G14 -> 10481 | H58: ='Working Capital'!H14 -> 13221.645 | I58: ='Working Capital'!I14 -> 15754.325 | J58: ='Working Capital'!J14 -> 18361.586 | ... Q58: ='Working Capital'!Q14 -> 34727.077
B59: Other financial liabilities | C59: ='BS Items'!C60 -> 4877 | D59: ='BS Items'!D60 -> 5788 | E59: ='BS Items'!E60 -> 7428 | F59: ='BS Items'!F60 -> 5810 | G59: ='BS Items'!G60 -> 14526 | H59: ='BS Items'!H60 -> 13805.31 | I59: ='BS Items'!I60 -> 16449.795 | J59: ='BS Items'!J60 -> 19172.152 | ... Q59: ='BS Items'!Q60 -> 36260.092
B60: Income tax liabilities (net) | C60: ='BS Items'!C62 -> 0 | D60: ='BS Items'!D62 -> 239 | E60: ='BS Items'!E62 -> 517 | F60: ='BS Items'!F62 -> 12 | G60: ='BS Items'!G62 -> 422 | H60: ='BS Items'!H62 -> 398.96033 | I60: ='BS Items'!I62 -> 475.38343 | J60: ='BS Items'!J62 -> 554.05696 | ... Q60: ='BS Items'!Q62 -> 1047.8822
B61: Other current liabilities | C61: ='BS Items'!C64 -> 1930 | D61: ='BS Items'!D64 -> 2426 | E61: ='BS Items'!E64 -> 2375 | F61: ='BS Items'!F64 -> 2796 | G61: ='BS Items'!G64 -> 3836 | H61: ='BS Items'!H64 -> 5013.488 | I61: ='BS Items'!I64 -> 5973.8499 | J61: ='BS Items'!J64 -> 6962.4916 | ... Q61: ='BS Items'!Q64 -> 13168.088
B62: Provisions | C62: ='BS Items'!C66 -> 1508 | D62: ='BS Items'!D66 -> 1698 | E62: ='BS Items'!E66 -> 1775 | F62: ='BS Items'!F66 -> 2136 | G62: ='BS Items'!G66 -> 3519 | H62: ='BS Items'!H66 -> 3910.2957 | I62: ='BS Items'!I66 -> 4659.3349 | J62: ='BS Items'!J66 -> 5430.431 | ... Q62: ='BS Items'!Q66 -> 10270.518
B64: Total current liabilities | C64: =SUM(C54:C62) -> 27879 | D64: =SUM(D54:D62) -> 36701 | E64: =SUM(E54:E62) -> 57640 | F64: =SUM(F54:F62) -> 56698 | G64: =SUM(G54:G62) -> 120790 | H64: =SUM(H54:H62) -> 102429.11 | I64: =SUM(I54:I62) -> 122049.98 | J64: =SUM(J54:J62) -> 142248.63 | ... Q64: =SUM(Q54:Q62) -> 269033.36
B66: Total liabilities | C66: =C64+C51 -> 37596 | D66: =D64+D51 -> 45921 | E66: =E64+E51 -> 80201 | F66: =F64+F51 -> 76755 | G66: =G64+G51 -> 178448 | H66: =H64+H51 -> 141248.41 | I66: =I64+I51 -> 168305.34 | J66: =J64+J51 -> 196159.02 | ... Q66: =Q64+Q51 -> 370993.51
B68: Total equity and liabilities | C68: =C66+C40 -> 92195 | D68: =D66+D40 -> 112501 | E68: =E66+E40 -> 164083 | F68: =F66+F40 -> 224779 | G68: =G66+G40 -> 335906 | H68: =H66+H40 -> 323042.42 | I68: =I66+I40 -> 380415.27 | J68: =J66+J40 -> 443679.73 | ... Q68: =Q66+Q40 -> 1001311.1
B70: Check | C70: =C68-C34 -> 0 | D70: =D68-D34 -> 0 | E70: =E68-E34 -> 0 | F70: =F68-F34 -> 0 | G70: =G68-G34 -> 0 | H70: =H68-H34 -> 0 | I70: =I68-I34 -> 0 | J70: =J68-J34 -> 0 | ... Q70: =Q68-Q34 -> 0

Sheet CashFlow
B5: Cash Flow
B6: (All amounts in INR Lakhs, unless otherwise stated)
A7: # | B7: Particulars | C7: 2021 | D7: =C7+1 -> 2022 | E7: =D7+1 -> 2023 | F7: =E7+1 -> 2024 | G7: =F7+1 -> 2025 | H7: =G7+1 -> 2026 | I7: =H7+1 -> 2027 | J7: =I7+1 -> 2028 | K7: =J7+1 -> 2029 | ... Q7: =P7+1 -> 2035
C8: Audited | D8: Audited | E8: Audited | F8: Audited | G8: Audited | H8: Estimated | I8: Projected | J8: Projected | K8: Projected | L8: Projected | M8: Projected | N8: Projected | O8: Projected | P8: Projected | Q8: Projected
B9: Operating activities
B10: Profit before tax | C10: 18602 | D10: 24585 | E10: 30986 | F10: 33468 | G10: 25546 | H10: ='Profit & Loss Statement'!H28 -> 52883.867 | I10: ='Profit & Loss Statement'!I28 -> 65878.614 | J10: ='Profit & Loss Statement'!J28 -> 77489.861 | K10: ='Profit & Loss Statement'!K28 -> 89160.065 | L10: ='Profit & Loss Statement'!L28 -> 100655.71 | M10: ='Profit & Loss Statement'!M28 -> 111780.29 | N10: ='Profit & Loss Statement'!N28 -> 122379.31 | O10: ='Profit & Loss Statement'!O28 -> 132340.67 | ... Q10: ='Profit & Loss Statement'!Q28 -> 150093.89
B11: Adjustments to reconcile profit before tax to net cash flows:
B12: Depreciation/ amortisation of property, plant and equipment, intangibles and right-of-use assets | C12: 2274 | D12: 3288 | E12: 4191 | F12: 5829 | G12: 8870 | H12: ='Profit & Loss Statement'!H21 -> 4870.2 | I12: ='Profit & Loss Statement'!I21 -> 4894.551 | J12: ='Profit & Loss Statement'!J21 -> 4919.0238 | K12: ='Profit & Loss Statement'!K21 -> 4943.6189 | L12: ='Profit & Loss Statement'!L21 -> 4968.337 | M12: ='Profit & Loss Statement'!M21 -> 4993.1787 | N12: ='Profit & Loss Statement'!N21 -> 5018.1445 | O12: ='Profit & Loss Statement'!O21 -> 5043.2353 | ... Q12: ='Profit & Loss Statement'!Q21 -> 5093.7937
B13: (Gain)/ loss on disposal of property, plant and equipment, net | D13: -10 | G13: -19
B14: Share-based payment expense | C14: 297 | D14: 300 | E14: 120 | F14: 47
B15: Gain on investment carried at fair value through profit and loss | C15: -184 | D15: -368
B16: Gain on sale of investment carried at fair value through profit and loss | C16: -671 | D16: -1377 | E16: -803 | F16: -18 | G16: -1240
B17: Interest income | C17: -838 | D17: -636 | E17: -2610 | F17: -7958 | G17: -8976 | H17: =-'Profit & Loss Statement'!H26 -> -9151.9283 | I17: =-'Profit & Loss Statement'!I26 -> -10905.032 | J17: =-'Profit & Loss Statement'!J26 -> -12709.759 | K17: =-'Profit & Loss Statement'!K26 -> -14525.686 | L17: =-'Profit & Loss Statement'!L26 -> -16316.346 | M17: =-'Profit & Loss Statement'!M26 -> -18050.931 | N17: =-'Profit & Loss Statement'!N26 -> -19705.121 | O17: =-'Profit & Loss Statement'!O26 -> -21261.174 | ... Q17: =-'Profit & Loss Statement'!Q26 -> -24037.835
B18: Fair value loss on contingent consideration | D18: 609 | E18: 634
B19: Gain on derecognition of contingent consideration | F19: -1402 | G19: 1216
B20: Gain on liquidation of subsidiary | C20: -82
B21: Net unrealised foreign exchange loss | C21: 66 | D21: 404 | E21: 1219 | F21: -84 | G21: -102
B22: Rent concession | C22: -302 | D22: -323 | E22: -71
B23: Impairment loss on financial assets | C23: 1021 | D23: 189 | F23: 530 | G23: 1590
B24: Provision no longer required/ written-of | F24: -78
B25: Finance costs | C25: 649 | D25: 995 | E25: 2186 | F25: 4227 | G25: 9948 | H25: ='Profit & Loss Statement'!H25 -> 7067.1936 | I25: ='Profit & Loss Statement'!I25 -> 6464.9743 | J25: ='Profit & Loss Statement'!J25 -> 7611.7724 | K25: ='Profit & Loss Statement'!K25 -> 8778.8206 | L25: ='Profit & Loss Statement'!L25 -> 9941.3343 | M25: ='Profit & Loss Statement'!M25 -> 11077.629 | N25: ='Profit & Loss Statement'!N25 -> 12169.935 | O25: ='Profit & Loss Statement'!O25 -> 13204.695 | ... Q25: ='Profit & Loss Statement'!Q25 -> 15067.453
B26: Operating cash flow before working capital changes | C26: =SUM(C10:C25) -> 20832 | D26: =SUM(D10:D25) -> 27656 | E26: =SUM(E10:E25) -> 35852 | F26: =SUM(F10:F25) -> 34561 | G26: =SUM(G10:G25) -> 36833 | H26: =SUM(H10:H25) -> 55669.332 | I26: =SUM(I10:I25) -> 66333.107 | J26: =SUM(J10:J25) -> 77310.898 | ... Q26: =SUM(Q10:Q25) -> 146217.3
B28: Movements in working capital:
B29: Increase in trade receivables | C29: -511 | D29: -4526 | E29: -3468 | F29: -4533 | G29: -2114 | H29: ='Balance sheet'!G25-'Balance sheet'!H25 -> -3973.5356 | I29: ='Balance sheet'!H25-'Balance sheet'!I25 -> -7621.3357 | J29: ='Balance sheet'!I25-'Balance sheet'!J25 -> -7845.7607 | K29: ='Balance sheet'!J25-'Balance sheet'!K25 -> -7894.4524 | L29: ='Balance sheet'!K25-'Balance sheet'!L25 -> -7784.6027 | M29: ='Balance sheet'!L25-'Balance sheet'!M25 -> -7540.8288 | N29: ='Balance sheet'!M25-'Balance sheet'!N25 -> -7191.3258 | O29: ='Balance sheet'!N25-'Balance sheet'!O25 -> -6764.6893 | ... Q29: ='Balance sheet'!P25-'Balance sheet'!Q25 -> -5783.4739
B30: Decrease/Increase in loans | C30: 50 | D30: 10 | E30: 964 | F30: 27 | G30: 33 | H30: ='Balance sheet'!G28-'Balance sheet'!H28 -> -35.897568 | I30: ='Balance sheet'!H28-'Balance sheet'!I28 -> -9.1750499 | J30: ='Balance sheet'!I28-'Balance sheet'!J28 -> -9.445227 | K30: ='Balance sheet'!J28-'Balance sheet'!K28 -> -9.5038452 | L30: ='Balance sheet'!K28-'Balance sheet'!L28 -> -9.3716011 | M30: ='Balance sheet'!L28-'Balance sheet'!M28 -> -9.0781306 | N30: ='Balance sheet'!M28-'Balance sheet'!N28 -> -8.6573765 | O30: ='Balance sheet'!N28-'Balance sheet'!O28 -> -8.1437643 | ... Q30: ='Balance sheet'!P28-'Balance sheet'!Q28 -> -6.9625147
B31: Increase/decrease in non-financial assets | C31: -279 | D31: -1610 | E31: -1190 | F31: -210 | G31: 533 | H31: ='Balance sheet'!G30-'Balance sheet'!H30 -> -1509.5144 | I31: ='Balance sheet'!H30-'Balance sheet'!I30 -> -1377.5752 | J31: ='Balance sheet'!I30-'Balance sheet'!J30 -> -1418.1406 | K31: ='Balance sheet'!J30-'Balance sheet'!K30 -> -1426.9417 | L31: ='Balance sheet'!K30-'Balance sheet'!L30 -> -1407.0861 | M31: ='Balance sheet'!L30-'Balance sheet'!M30 -> -1363.0234 | N31: ='Balance sheet'!M30-'Balance sheet'!N30 -> -1299.8499 | O31: ='Balance sheet'!N30-'Balance sheet'!O30 -> -1222.7343 | ... Q31: ='Balance sheet'!P30-'Balance sheet'!Q30 -> -1045.3772
B32: Increase in financial assets | C32: -1429 | D32: -3078 | E32: -1961 | F32: -1240 | G32: -2686 | H32: =('Balance sheet'!G29+'Balance sheet'!G24)-('Balance sheet'!H24+'Balance sheet'!H29) -> -61254.153 | I32: =('Balance sheet'!H29+'Balance sheet'!H24)-('Balance sheet'!I24+'Balance sheet'!I29) -> -21841.013 | J32: =('Balance sheet'!I29+'Balance sheet'!I24)-('Balance sheet'!J24+'Balance sheet'!J29) -> -22484.164 | K32: =('Balance sheet'!J29+'Balance sheet'!J24)-('Balance sheet'!K24+'Balance sheet'!K29) -> -22623.703 | L32: =('Balance sheet'!K29+'Balance sheet'!K24)-('Balance sheet'!L24+'Balance sheet'!L29) -> -22308.899 | M32: =('Balance sheet'!L29+'Balance sheet'!L24)-('Balance sheet'!M24+'Balance sheet'!M29) -> -21610.299 | N32: =('Balance sheet'!M29+'Balance sheet'!M24)-('Balance sheet'!N24+'Balance sheet'!N29) -> -20608.703 | O32: =('Balance sheet'!N29+'Balance sheet'!N24)-('Balance sheet'!O24+'Balance sheet'!O29) -> -19386.06 | ... Q32: =('Balance sheet'!P29+'Balance sheet'!P24)-('Balance sheet'!Q24+'Balance sheet'!Q29) -> -16574.12
B33: Increase/ (decrease) in trade payables | C33: -644 | D33: 1489 | E33: 756 | F33: 823 | G33: 937 | H33: ='Balance sheet'!H58-'Balance sheet'!G58 -> 2740.6446 | I33: ='Balance sheet'!I58-'Balance sheet'!H58 -> 2532.6807 | J33: ='Balance sheet'!J58-'Balance sheet'!I58 -> 2607.2604 | K33: ='Balance sheet'!K58-'Balance sheet'!J58 -> 2623.4414 | L33: ='Balance sheet'!L58-'Balance sheet'!K58 -> 2586.9367 | M33: ='Balance sheet'!M58-'Balance sheet'!L58 -> 2505.9271 | N33: ='Balance sheet'!N58-'Balance sheet'!M58 -> 2389.7822 | O33: ='Balance sheet'!O58-'Balance sheet'!N58 -> 2248.0047 | ... Q33: ='Balance sheet'!Q58-'Balance sheet'!P58 -> 1921.9325
B34: Increase/ (decrease) in financial liabilities | C34: -1684 | D34: 1004 | E34: -1362 | F34: 35 | G34: 731 | H34: =SUM('Balance sheet'!H56,'Balance sheet'!H57,'Balance sheet'!H59)-SUM('Balance sheet'!G56,'Balance sheet'!G57,'Balance sheet'!G59) -> -23020.829 | I34: =SUM('Balance sheet'!I56,'Balance sheet'!I57,'Balance sheet'!I59)-SUM('Balance sheet'!H56,'Balance sheet'!H57,'Balance sheet'!H59) -> 14810.541 | J34: =SUM('Balance sheet'!J56,'Balance sheet'!J57,'Balance sheet'!J59)-SUM('Balance sheet'!I56,'Balance sheet'!I57,'Balance sheet'!I59) -> 15246.666 | K34: =SUM('Balance sheet'!K56,'Balance sheet'!K57,'Balance sheet'!K59)-SUM('Balance sheet'!J56,'Balance sheet'!J57,'Balance sheet'!J59) -> 15341.289 | L34: =SUM('Balance sheet'!L56,'Balance sheet'!L57,'Balance sheet'!L59)-SUM('Balance sheet'!K56,'Balance sheet'!K57,'Balance sheet'!K59) -> 15127.818 | M34: =SUM('Balance sheet'!M56,'Balance sheet'!M57,'Balance sheet'!M59)-SUM('Balance sheet'!L56,'Balance sheet'!L57,'Balance sheet'!L59) -> 14654.092 | N34: =SUM('Balance sheet'!N56,'Balance sheet'!N57,'Balance sheet'!N59)-SUM('Balance sheet'!M56,'Balance sheet'!M57,'Balance sheet'!M59) -> 13974.903 | O34: =SUM('Balance sheet'!O56,'Balance sheet'!O57,'Balance sheet'!O59)-SUM('Balance sheet'!N56,'Balance sheet'!N57,'Balance sheet'!N59) -> 13145.82 | ... Q34: =SUM('Balance sheet'!Q56,'Balance sheet'!Q57,'Balance sheet'!Q59)-SUM('Balance sheet'!P56,'Balance sheet'!P57,'Balance sheet'!P59) -> 11239.024
B35: Increase in provisions | C35: 516 | D35: 58 | E35: 478 | F35: 887 | G35: 23 | H35: ='Balance sheet'!H62-'Balance sheet'!G62 -> 391.29567 | I35: ='Balance sheet'!I62-'Balance sheet'!H62 -> 749.03923 | J35: ='Balance sheet'!J62-'Balance sheet'!I62 -> 771.09614 | K35: ='Balance sheet'!K62-'Balance sheet'!J62 -> 775.88166 | L35: ='Balance sheet'!L62-'Balance sheet'!K62 -> 765.08542 | M35: ='Balance sheet'!M62-'Balance sheet'!L62 -> 741.12687 | N35: ='Balance sheet'!N62-'Balance sheet'!M62 -> 706.77705 | O35: ='Balance sheet'!O62-'Balance sheet'!N62 -> 664.84641 | ... Q35: ='Balance sheet'!Q62-'Balance sheet'!P62 -> 568.41071
B36: Increase/ (decrease) in contract liabilities | C36: -43 | D36: 660 | E36: -225 | F36: 737 | G36: 369 | H36: ='Balance sheet'!H54-'Balance sheet'!G54 -> 373.54707 | I36: ='Balance sheet'!I54-'Balance sheet'!H54 -> 491.82815 | J36: ='Balance sheet'!J54-'Balance sheet'!I54 -> 506.31098 | K36: ='Balance sheet'!K54-'Balance sheet'!J54 -> 509.45321 | L36: ='Balance sheet'!L54-'Balance sheet'!K54 -> 502.36427 | M36: ='Balance sheet'!M54-'Balance sheet'!L54 -> 486.63279 | N36: ='Balance sheet'!N54-'Balance sheet'!M54 -> 464.07829 | O36: ='Balance sheet'!O54-'Balance sheet'!N54 -> 436.54613 | ... Q36: ='Balance sheet'!Q54-'Balance sheet'!P54 -> 373.2253
B37: Increase in other non-financial liabilities | C37: 1109 | D37: 496 | E37: -245 | F37: 411 | G37: -1020 | H37: =('Balance sheet'!H60+'Balance sheet'!H61)-('Balance sheet'!G60+'Balance sheet'!G61) -> 1154.4483 | I37: =('Balance sheet'!I60+'Balance sheet'!I61)-('Balance sheet'!H60+'Balance sheet'!H61) -> 1036.7851 | J37: =('Balance sheet'!J60+'Balance sheet'!J61)-('Balance sheet'!I60+'Balance sheet'!I61) -> 1067.3152 | K37: =('Balance sheet'!K60+'Balance sheet'!K61)-('Balance sheet'!J60+'Balance sheet'!J61) -> 1073.9391 | L37: =('Balance sheet'!L60+'Balance sheet'!L61)-('Balance sheet'!K60+'Balance sheet'!K61) -> 1058.9954 | M37: =('Balance sheet'!M60+'Balance sheet'!M61)-('Balance sheet'!L60+'Balance sheet'!L61) -> 1025.8331 | N37: =('Balance sheet'!N60+'Balance sheet'!N61)-('Balance sheet'!M60+'Balance sheet'!M61) -> 978.28772 | O37: =('Balance sheet'!O60+'Balance sheet'!O61)-('Balance sheet'!N60+'Balance sheet'!N61) -> 920.24929 | ... Q37: =('Balance sheet'!Q60+'Balance sheet'!Q61)-('Balance sheet'!P60+'Balance sheet'!P61) -> 786.76751
C38: =SUM(C26:C37) -> 17917 | D38: =SUM(D26:D37) -> 22159 | E38: =SUM(E26:E37) -> 29599 | F38: =SUM(F26:F37) -> 31498 | G38: =SUM(G26:G37) -> 33639 | H38: =SUM(H26:H37) -> -29464.662 | I38: =SUM(I26:I37) -> 55104.882 | J38: =SUM(J26:J37) -> 65752.036 | ... Q38: =SUM(Q26:Q37) -> 137696.73
B39: Income tax paid, net of refunds | C39: -3600 | D39: -5347 | E39: -8882 | F39: -10242 | G39: -9997 | H39: =-'Cost Buildup'!H22 -> -14921.03 | I39: =-'Cost Buildup'!I22 -> -18587.46 | J39: =-'Cost Buildup'!J22 -> -22250.989 | K39: =-'Cost Buildup'!K22 -> -25602.055 | L39: =-'Cost Buildup'!L22 -> -29406.275 | M39: =-'Cost Buildup'!M22 -> -32656.288 | N39: =-'Cost Buildup'!N22 -> -36364.659 | O39: =-'Cost Buildup'!O22 -> -39324.647 | ... Q39: =-'Cost Buildup'!Q22 -> -45028.166
B41: Net cash flows from Operating Activities | C41: =SUM(C38:C39) -> 14317 | D41: =SUM(D38:D39) -> 16812 | E41: =SUM(E38:E39) -> 20717 | F41: =SUM(F38:F39) -> 21256 | G41: =SUM(G38:G39) -> 23642 | H41: =SUM(H38:H39) -> -44385.692 | I41: =SUM(I38:I39) -> 36517.422 | J41: =SUM(J38:J39) -> 43501.047 | ... Q41: =SUM(Q38:Q39) -> 92668.56
B43: Investing activities
B44: Purchase of property, plant and equipment | C44: -78 | D44: -67 | E44: -13106 | F44: -823 | G44: -766 | H44: =-FAS!H376+(-FAS!H374+FAS!G374) -> -6602 | I44: =-FAS!I376+(-FAS!I374+FAS!H374) -> -6691.98 | J44: =-FAS!J376+(-FAS!J374+FAS!I374) -> -6688.5699 | K44: =-FAS!K376+(-FAS!K374+FAS!J374) -> -6758.8827 | L44: =-FAS!L376+(-FAS!L374+FAS!K374) -> -6755.8072 | M44: =-FAS!M376+(-FAS!M374+FAS!L374) -> -6826.4562 | N44: =-FAS!N376+(-FAS!N374+FAS!M374) -> -6823.7185 | O44: =-FAS!O376+(-FAS!O374+FAS!N374) -> -6894.7071 | ... Q44: =-FAS!Q376+(-FAS!Q374+FAS!P374) -> -6963.6422
B45: Purchase of intangible assets | C45: -19 | D45: -346 | E45: -835 | F45: -207 | G45: -351
B46: Proceeds from sale of property, plant and equipment | D46: 10 | F46: 4 | G46: 19
B47: Proceeds from subleasing the premises | C47: 7
B48: Investment in equity shares of TECH4TH Solutions Inc. | D48: -762 | E48: -827 | G48: -503
B49: Investment in bank deposit, net | C49: 6931 | D49: -3020 | E49: -56995 | F49: -52847 | G49: 23647 | H49: ='Balance sheet'!G27-'Balance sheet'!H27 -> 93911 | I49: ='Balance sheet'!H27-'Balance sheet'!I27 -> 0 | J49: ='Balance sheet'!I27-'Balance sheet'!J27 -> 0 | K49: ='Balance sheet'!J27-'Balance sheet'!K27 -> 0 | L49: ='Balance sheet'!K27-'Balance sheet'!L27 -> 0 | M49: ='Balance sheet'!L27-'Balance sheet'!M27 -> 0 | N49: ='Balance sheet'!M27-'Balance sheet'!N27 -> 0 | O49: ='Balance sheet'!N27-'Balance sheet'!O27 -> 0 | ... Q49: ='Balance sheet'!P27-'Balance sheet'!Q27 -> 0
B50: Acquisition of subsidiary | C50: -6025 | E50: -10987 | G50: -73121
B51: Proceeds from sale of mutual funds | C51: 39313 | D51: 34542 | E51: 47203 | F51: 2568 | G51: 3751
B52: Purchase of mutual funds | C52: -69269 | D52: -40049 | F52: -2550 | G52: -37549
B53: Interest received | C53: 777 | D53: 84 | E53: 445 | F53: 7214 | G53: 8657 | H53: ='Profit & Loss Statement'!H26 -> 9151.9283 | I53: ='Profit & Loss Statement'!I26 -> 10905.032 | J53: ='Profit & Loss Statement'!J26 -> 12709.759 | K53: ='Profit & Loss Statement'!K26 -> 14525.686 | L53: ='Profit & Loss Statement'!L26 -> 16316.346 | M53: ='Profit & Loss Statement'!M26 -> 18050.931 | N53: ='Profit & Loss Statement'!N26 -> 19705.121 | O53: ='Profit & Loss Statement'!O26 -> 21261.174 | ... Q53: ='Profit & Loss Statement'!Q26 -> 24037.835
B54: Financial Assets | H54: =SUM('Balance sheet'!G14:G18)-SUM('Balance sheet'!H14:H18) -> -388.81531 | I54: =SUM('Balance sheet'!H14:H18)-SUM('Balance sheet'!I14:I18) -> -2886.1336 | J54: =SUM('Balance sheet'!I14:I18)-SUM('Balance sheet'!J14:J18) -> -2971.1214 | K54: =SUM('Balance sheet'!J14:J18)-SUM('Balance sheet'!K14:K18) -> -2989.5605 | L54: =SUM('Balance sheet'!K14:K18)-SUM('Balance sheet'!L14:L18) -> -2947.9614 | M54: =SUM('Balance sheet'!L14:L18)-SUM('Balance sheet'!M14:M18) -> -2855.6464 | N54: =SUM('Balance sheet'!M14:M18)-SUM('Balance sheet'!N14:N18) -> -2723.2926 | O54: =SUM('Balance sheet'!N14:N18)-SUM('Balance sheet'!O14:O18) -> -2561.7291 | ... Q54: =SUM('Balance sheet'!P14:P18)-SUM('Balance sheet'!Q14:Q18) -> -2190.1513
B55: Net Cash flow used in Investing Activities | C55: =SUM(C44:C53) -> -28363 | D55: =SUM(D44:D53) -> -9608 | E55: =SUM(E44:E53) -> -35102 | F55: =SUM(F44:F53) -> -46641 | G55: =SUM(G44:G53) -> -76216 | H55: =SUM(H44:H54) -> 96072.113 | I55: =SUM(I44:I54) -> 1326.9183 | J55: =SUM(J44:J54) -> 3050.0677 | K55: =SUM(K44:K54) -> 4777.2432 | L55: =SUM(L44:L54) -> 6612.5771 | M55: =SUM(M44:M54) -> 8368.8281 | N55: =SUM(N44:N54) -> 10158.11 | O55: =SUM(O44:O54) -> 11804.738 | ... Q55: =SUM(Q44:Q54) -> 14884.042
B57: Financing activities
B58: Repayment of long-term borrowings | C58: -1256 | D58: -2053 | E58: -2609 | F58: -2608 | G58: -834
B59: Proceeds from long-term borrowings | C59: 5981 | E59: 12383 | G59: 24061
B60: Proceeds / (Repayment) of short-term borrowings (net) | C60: 4213 | D60: 4012 | E60: 4617 | F60: -1439 | G60: 53322
B61: Proceeds from issue of redeemable non-convertible debentures | E61: 4500 | F61: 8000
B62: Repayment of redeemable non-convertible debentures | G62: -4500
B63: Security deposits given | C63: -300 | H63: ='Balance sheet'!H51-'Balance sheet'!G51 -> -18838.697 | I63: ='Balance sheet'!I51-'Balance sheet'!H51 -> 7436.0569 | J63: ='Balance sheet'!J51-'Balance sheet'!I51 -> 7655.0259 | K63: ='Balance sheet'!K51-'Balance sheet'!J51 -> 7702.534 | L63: ='Balance sheet'!L51-'Balance sheet'!K51 -> 7595.3548 | M63: ='Balance sheet'!M51-'Balance sheet'!L51 -> 7357.5072 | N63: ='Balance sheet'!N51-'Balance sheet'!M51 -> 7016.5007 | O63: ='Balance sheet'!O51-'Balance sheet'!N51 -> 6600.236 | ... Q63: ='Balance sheet'!Q51-'Balance sheet'!P51 -> 5642.8745
B64: Payment of principal portion of lease liabilities | C64: -1661 | D64: -1702 | E64: -2004 | F64: -2161 | G64: -3172
B65: Payment of interest portion of lease liabilities | C65: -328 | D65: -487 | E65: -544 | F65: -614 | G65: -727
B66: Payment of contingent consideration | D66: -1861 | E66: -2034 | F66: -1659 | G66: -1401
B67: Proceeds from issue of Equity share capital (net of transaction costs) | C67: 10544 | F67: 48556
B68: Dividend paid | D68: -6830 | E68: -5715 | F68: -8604 | G68: -8588 | H68: ='Profit & Loss Statement'!H34 -> -13626.823 | I68: ='Profit & Loss Statement'!I34 -> -16975.237 | J68: ='Profit & Loss Statement'!J34 -> -19828.084 | K68: ='Profit & Loss Statement'!K34 -> -22814.252 | L68: ='Profit & Loss Statement'!L34 -> -25575.102 | M68: ='Profit & Loss Statement'!M34 -> -28401.69 | N68: ='Profit & Loss Statement'!N34 -> -30875.101 | O68: ='Profit & Loss Statement'!O34 -> -33388.254 | ... Q68: ='Profit & Loss Statement'!Q34 -> -37713.513
B69: Proceeds from exercise of share options | C69: 72 | D69: 171 | E69: 147 | F69: 181 | G69: 185
B70: Interest paid | C70: -281 | D70: -328 | E70: -1534 | F70: -3305 | G70: -8401 | H70: =-'Profit & Loss Statement'!H25 -> -7067.1936 | I70: =-'Profit & Loss Statement'!I25 -> -6464.9743 | J70: =-'Profit & Loss Statement'!J25 -> -7611.7724 | K70: =-'Profit & Loss Statement'!K25 -> -8778.8206 | L70: =-'Profit & Loss Statement'!L25 -> -9941.3343 | M70: =-'Profit & Loss Statement'!M25 -> -11077.629 | N70: =-'Profit & Loss Statement'!N25 -> -12169.935 | O70: =-'Profit & Loss Statement'!O25 -> -13204.695 | ... Q70: =-'Profit & Loss Statement'!Q25 -> -15067.453
B72: Net cash flows from/ (used) in financing activities | C72: =SUM(C58:C70) -> 16984 | D72: =SUM(D58:D70) -> -9078 | E72: =SUM(E58:E70) -> 7207 | F72: =SUM(F58:F70) -> 36347 | G72: =SUM(G58:G70) -> 49945 | H72: =SUM(H58:H70) -> -39532.713 | I72: =SUM(I58:I70) -> -16004.155 | J72: =SUM(J58:J70) -> -19784.83 | ... Q72: =SUM(Q58:Q70) -> -47138.092
B74: Net increase in cash and cash equivalents | C74: =C72+C55+C41 -> 2938 | D74: =D72+D55+D41 -> -1874 | E74: =E72+E55+E41 -> -7178 | F74: =F72+F55+F41 -> 10962 | G74: -2628 | H74: =H72+H55+H41 -> 12153.708 | I74: =I72+I55+I41 -> 21840.186 | J74: =J72+J55+J41 -> 26766.284 | K74: =K72+K55+K41 -> 32010.87 | L74: =L72+L55+L41 -> 37065.497 | M74: =M72+M55+M41 -> 42281.277 | N74: =N72+N55+N41 -> 47032.479 | O74: =O72+O55+O41 -> 51848.643 | ... Q74: =Q72+Q55+Q41 -> 60414.51
B75: Net foreign exchange difference | C75: -6 | D75: 20 | E75: 323 | F75: 55 | G75: 19
B76: Cash and cash equivalents at the beginning of the year | C76: 4353 | D76: =C79 -> 8583 | E76: =D79 -> 6729 | F76: 6999 | G76: 11470 | H76: =G79 -> 11912 | I76: =H79 -> 24065.708 | J76: =I79 -> 45905.894 | K76: =J79 -> 72672.178 | L76: =K79 -> 104683.05 | M76: =L79 -> 141748.55 | N76: =M79 -> 184029.82 | O76: =N79 -> 231062.3 | ... Q76: =P79 -> 339114.44
B77: Cash acquired on acquisition of subsidiary | C77: 1298 | E77: 6 | G77: 3624
B78: Less : Bank overdraft at the beginning of the year | F78: -7119 | G78: -573
B79: Cash and cash equivalents at the end of the year | C79: =SUM(C74:C78) -> 8583 | D79: =SUM(D74:D78) -> 6729 | E79: =SUM(E74:E78) -> -120 | F79: =SUM(F74:F78) -> 10897 | G79: =SUM(G74:G78) -> 11912 | H79: =SUM(H74:H78) -> 24065.708 | I79: =SUM(I74:I78) -> 45905.894 | J79: =SUM(J74:J78) -> 72672.178 | ... Q79: =SUM(Q74:Q78) -> 399528.95

Sheet  Market Return
B5: Market Return
B7: BSE Sensex | E7: Source - | F7: Historical - Indices
B9: Date | C9: Close Price | E9: Year | F9: =YEARFRAC(B10,B2488) -> 10
B10: 42376 | C10: 24851.83 | E10: Return | F10: =_xlfn.RRI(F9,C10,C2488) -> 0.13080103
B11: 42377 | C11: 24934.33
B12: 42380 | C12: 24825.04
B13: 42381 | C13: 24682.03
B14: 42382 | C14: 24854.11
B15: 42383 | C15: 24772.97
B16: 42384 | C16: 24455.04
B17: 42387 | C17: 24188.37
B18: 42388 | C18: 24479.84
B19: 42389 | C19: 24062.04
B20: 42390 | C20: 23962.21
B21: 42391 | C21: 24435.66
B22: 42394 | C22: 24485.95
... B2488: 46029 | C2488: 84961.14

Sheet Equity Return
B5: Equity Return
B7: Month | C7: Closing price of Sensex | D7: % Change Of Return | E7: Closing Price Of Stocks | F7: % Change Of Return | H7: Source - | I7: Historical - Indices
B9: 44197 | C9: 46285.77 | E9: 347.25 | H9: Beta | I9: =SLOPE(F10:F69,D10:D69) -> 1.2602979
B10: 44228 | C10: 49099.99 | D10: =C10/C9-1 -> 0.060800976 | E10: 531.85 | F10: =E10/E9-1 -> 0.53160547 | H10: Beta | I10: =_xlfn.COVARIANCE.S(F10:F69,D10:D69)/_xlfn.VAR.S(D10:D69) -> 1.2602979
B11: 44256 | C11: 49509.15 | D11: =C11/C10-1 -> 0.0083331993 | E11: 540.1 | F11: =E11/E10-1 -> 0.015511892 | H11: Beta | I11: =I30 -> 1.2602979
B12: 44287 | C12: 48782.36 | D12: =C12/C11-1 -> -0.014679913 | E12: 723.8 | F12: =E12/E11-1 -> 0.3401222
B13: 44317 | C13: 51937.44 | D13: =C13/C12-1 -> 0.064676658 | E13: 868.3 | F13: =E13/E12-1 -> 0.19964078 | H13: SUMMARY OUTPUT
B14: 44348 | C14: 52482.71 | D14: =C14/C13-1 -> 0.010498592 | E14: 1006.8 | F14: =E14/E13-1 -> 0.15950708
B15: 44378 | C15: 52586.84 | D15: =C15/C14-1 -> 0.001984082 | E15: 1361.65 | F15: =E15/E14-1 -> 0.35245332 | H15: Regression Statistics
B16: 44409 | C16: 57552.39 | D16: =C16/C15-1 -> 0.094425716 | E16: 1428.7 | F16: =E16/E15-1 -> 0.049241729 | H16: Multiple R | I16: 0.37127903
B17: 44440 | C17: 59126.36 | D17: =C17/C16-1 -> 0.027348473 | E17: 1382.95 | F17: =E17/E16-1 -> -0.032022118 | H17: R Square | I17: 0.13784812
B18: 44470 | C18: 59306.93 | D18: =C18/C17-1 -> 0.0030539678 | E18: 1271.85 | F18: =E18/E17-1 -> -0.080335515 | H18: Adjusted R Square | I18: 0.12298343
B19: 44501 | C19: 57064.87 | D19: =C19/C18-1 -> -0.037804351 | E19: 1206.75 | F19: =E19/E18-1 -> -0.051185281 | H19: Standard Error | I19: 0.11168833
B20: 44531 | C20: 58253.82 | D20: =C20/C19-1 -> 0.02083506 | E20: 1296.35 | F20: =E20/E19-1 -> 0.074249016 | H20: Observations | I20: 60
B21: 44562 | C21: 58014.17 | D21: =C21/C20-1 -> -0.0041138933 | E21: 1150.75 | F21: =E21/E20-1 -> -0.11231535
B22: 44593 | C22: 56247.28 | D22: =C22/C21-1 -> -0.03045618 | E22: 979.55 | F22: =E22/E21-1 -> -0.14877254 | H22: ANOVA
B23: 44621 | C23: 58568.51 | D23: =C23/C22-1 -> 0.041268307 | E23: 1055.2 | F23: =E23/E22-1 -> 0.07722934 | I23: df | J23: SS | K23: MS | L23: F | M23: Significance F
B24: 44652 | C24: 57060.87 | D24: =C24/C23-1 -> -0.025741478 | E24: 1000.15 | F24: =E24/E23-1 -> -0.052170205 | H24: Regression | I24: 1 | J24: 0.11568063 | K24: 0.11568063 | L24: 9.2735293 | M24: 0.0034936684
B25: 44682 | C25: 55566.41 | D25: =C25/C24-1 -> -0.026190628 | E25: 904.8 | F25: =E25/E24-1 -> -0.0953357 | H25: Residual | I25: 58 | J25: 0.7235084 | K25: 0.012474283
B26: 44713 | C26: 53018.94 | D26: =C26/C25-1 -> -0.045845503 | E26: 829.5 | F26: =E26/E25-1 -> -0.083222812 | H26: Total | I26: 59 | J26: 0.83918903
B27: 44743 | C27: 57570.25 | D27: =C27/C26-1 -> 0.085843097 | E27: 967.3 | F27: =E27/E26-1 -> 0.16612417
B28: 44774 | C28: 59537.07 | D28: =C28/C27-1 -> 0.034163826 | E28: 1031.8 | F28: =E28/E27-1 -> 0.066680451 | I28: Coefficients | J28: Standard Error | K28: t Stat | L28: P-value | M28: Lower 95% | N28: Upper 95% | O28: Lower 95.0% | P28: Upper 95.0%
B29: 44805 | C29: 57426.92 | D29: =C29/C28-1 -> -0.035442624 | E29: 992.95 | F29: =E29/E28-1 -> -0.037652646 | H29: Intercept | I29: -0.0030299462 | J29: 0.015097844 | K29: -0.20068734 | L29: 0.84164514 | M29: -0.033251564 | N29: 0.027191672 | O29: -0.033251564 | P29: 0.027191672
B30: 44835 | C30: 60746.59 | D30: =C30/C29-1 -> 0.057806861 | E30: 970.85 | F30: =E30/E29-1 -> -0.022256911 | H30: X Variable 1 | I30: 1.2602979 | J30: 0.41385738 | K30: 3.045247 | L30: 0.0034936684 | M30: 0.43187239 | N30: 2.0887235 | O30: 0.43187239 | P30: 2.0887235
B31: 44866 | C31: 63099.65 | D31: =C31/C30-1 -> 0.038735672 | E31: 947.85 | F31: =E31/E30-1 -> -0.02369058
B32: 44896 | C32: 60840.74 | D32: =C32/C31-1 -> -0.035799089 | E32: 880.6 | F32: =E32/E31-1 -> -0.070950045
B33: 44927 | C33: 59549.9 | D33: =C33/C32-1 -> -0.021216704 | E33: 846.95 | F33: =E33/E32-1 -> -0.038212582
B34: 44958 | C34: 58962.12 | D34: =C34/C33-1 -> -0.0098703776 | E34: 855.3 | F34: =E34/E33-1 -> 0.0098589055
B35: 44986 | C35: 58991.52 | D35: =C35/C34-1 -> 0.00049862522 | E35: 767.8 | F35: =E35/E34-1 -> -0.10230329
B36: 45017 | C36: 61112.44 | D36: =C36/C35-1 -> 0.035952964 | E36: 822.4 | F36: =E36/E35-1 -> 0.071112269
B37: 45047 | C37: 62622.24 | D37: =C37/C36-1 -> 0.024705281 | E37: 919.4 | F37: =E37/E36-1 -> 0.11794747
B38: 45078 | C38: 64718.56 | D38: =C38/C37-1 -> 0.033475647 | E38: 978.2 | F38: =E38/E37-1 -> 0.063954753
B39: 45108 | C39: 66527.67 | D39: =C39/C38-1 -> 0.027953496 | E39: 924.9 | F39: =E39/E38-1 -> -0.054487835
B40: 45139 | C40: 64831.41 | D40: =C40/C39-1 -> -0.02549706 | E40: 927.45 | F40: =E40/E39-1 -> 0.0027570548
B41: 45170 | C41: 65828.41 | D41: =C41/C40-1 -> 0.015378348 | E41: 873.95 | F41: =E41/E40-1 -> -0.05768505
B42: 45200 | C42: 63874.93 | D42: =C42/C41-1 -> -0.029675333 | E42: 819.2 | F42: =E42/E41-1 -> -0.062646604
... B69: 46023 | C69: 85188.6 | D69: =C69/C68-1 -> -0.00037549607 | E69: 456 | F69: =E69/E68-1 -> -0.0093417337

Sheet Comps Beta
B6: Comparables Companies Beta
B7: (All amounts in INR Lakhs, unless otherwise stated)
B8: Name | D8: equity Value | E8: Total Debt | F8: Debt/Equity | G8: Debt/Capital | H8: Tax rate | I8: Levered Beta | J8: Unlevered Beta
B10: ='Comparable Valuation'!B12 -> TCS | D10: ='Comparable Valuation'!G12 -> 115960105 | E10: ='Comparable Valuation'!H12 -> 1093200 | F10: =E10/D10 -> 0.0094273802 | G10: =E10/(D10+E10) -> 0.0093393348 | H10: 0.2485 | I10: 0.31 | J10: =I10/(1+F10*(1-H10)) -> 0.3078192
B11: ='Comparable Valuation'!B13 -> Infosys | D11: ='Comparable Valuation'!G13 -> 67384368 | E11: ='Comparable Valuation'!H13 -> 848500 | F11: =E11/D11 -> 0.012591941 | G11: =E11/(D11+E11) -> 0.012435356 | H11: 0.2878 | I11: 0.34 | J11: =I11/(1+F11*(1-H11)) -> 0.33697799
B12: ='Comparable Valuation'!B14 -> HCL Technologies | D12: ='Comparable Valuation'!G14 -> 44586091 | E12: ='Comparable Valuation'!H14 -> 627600 | F12: =E12/D12 -> 0.014076139 | G12: =E12/(D12+E12) -> 0.013880751 | H12: 0.253 | I12: 0.22 | J12: =I12/(1+F12*(1-H12)) -> 0.2177108
B13: ='Comparable Valuation'!B15 -> Wipro | D13: ='Comparable Valuation'!G15 -> 27886908 | E13: ='Comparable Valuation'!H15 -> 1920350 | F13: =E13/D13 -> 0.068862062 | G13: =E13/(D13+E13) -> 0.064425584 | H13: 0.2377 | I13: 0.58 | J13: =I13/(1+F13*(1-H13)) -> 0.55107226
B14: ='Comparable Valuation'!B16 -> LTIMindtree | D14: ='Comparable Valuation'!G16 -> 17872920 | E14: ='Comparable Valuation'!H16 -> 218730 | F14: =E14/D14 -> 0.012238067 | G14: =E14/(D14+E14) -> 0.012090108 | H14: 0.264 | I14: 0.42 | J14: =I14/(1+F14*(1-H14)) -> 0.41625074
B15: ='Comparable Valuation'!B17 -> Tech Mahindra | D15: ='Comparable Valuation'!G17 -> 15683396 | E15: ='Comparable Valuation'!H17 -> 202520 | F15: =E15/D15 -> 0.01291302 | G15: =E15/(D15+E15) -> 0.012748399 | H15: 0.2587 | I15: 0.3 | J15: =I15/(1+F15*(1-H15)) -> 0.2971555
B16: ='Comparable Valuation'!B18 -> Newgen Software | D16: ='Comparable Valuation'!G18 -> 1171859 | E16: ='Comparable Valuation'!H18 -> 5348 | F16: =E16/D16 -> 0.004563689 | G16: =E16/(D16+E16) -> 0.0045429563 | H16: 0.2155 | I16: 0.7 | J16: =I16/(1+F16*(1-H16)) -> 0.69750279
B17: ='Comparable Valuation'!B19 -> Sonata Software | D17: ='Comparable Valuation'!G19 -> 1017852 | E17: ='Comparable Valuation'!H19 -> 51602 | F17: =E17/D17 -> 0.050696958 | G17: =E17/(D17+E17) -> 0.04825079 | H17: 0.2673 | I17: 0.34 | J17: =I17/(1+F17*(1-H17)) -> 0.32782281
B18: ='Comparable Valuation'!B20 -> Birlasoft Ltd | D18: ='Comparable Valuation'!G20 -> 1217045 | E18: ='Comparable Valuation'!H20 -> 15100 | F18: =E18/D18 -> 0.012407101 | G18: =E18/(D18+E18) -> 0.012255051 | H18: 0.2813 | I18: 0.52 | J18: =I18/(1+F18*(1-H18)) -> 0.51540415
B22: Average | F22: =AVERAGE(F10:F19) -> 0.021975151 | G22: =AVERAGE(G10:G19) -> 0.021107592 | H22: =AVERAGE(H10:H19) -> 0.25708889 | I22: =AVERAGE(I10:I19) -> 0.41444444 | J22: =AVERAGE(J10:J18) -> 0.40752403
B23: Median | F23: =MEDIAN(F10:F19) -> 0.012591941 | G23: =MEDIAN(G10:G19) -> 0.012435356 | H23: =MEDIAN(H10:H19) -> 0.2587 | I23: =MEDIAN(I10:I19) -> 0.34 | J23: =MEDIAN(J10:J18) -> 0.33697799
B25: ='Comparable Valuation'!B31 -> Happiest Minds | D25: ='Comparable Valuation'!G31 -> 699057 | E25: ='Comparable Valuation'!H31 -> 124359 | F25: =E25/D25 -> 0.17789536 | G25: =E25/(D25+E25) -> 0.15102816 | H25: 0.2772 | I25: 0.05
B28: WACC Calculation
B30: Target Capital Structure | E30: Equity Market Beta
B32: Proportion of Debt | C32: =G22 -> 0.021107592 | E32: WACC
B33: Proportion of Equity | C33: =1-C32 -> 0.97889241
B34: Current Capital structure | E34: Current Capital structure
B35: Market cap | C35: =D25 -> 699057 | E35: Market cap | F35: =D25 -> 699057
B36: Total Debt | C36: =E25 -> 124359 | E36: Total Debt | F36: =E25 -> 124359
B37: Debt/equity | C37: =C36/C35 -> 0.17789536 | E37: Total Equity | F37: =(F35-F36)/F35 -> 0.82210464
B39: Cost of debt | E39: Cost of debt
B40: Pre-tax cost of debt | C40: ='Debt Schedules'!H15 -> 0.06621549 | E40: Pre-tax cost of debt | F40: ='Debt Schedules'!H15 -> 0.06621549
B41: tax rate | C41: =H25 -> 0.2772 | E41: tax rate | F41: =H25 -> 0.2772
B42: After -Tax cost of debt | C42: =C40*(1-+C41) -> 0.047860556 | E42: After -Tax cost of debt | F42: =F40*(1-F41) -> 0.047860556
B44: Cost of equity | E44: Cost of equity
B45: Risk free Rate | C45: =Assumption!C13 -> 0.06615 | E45: Risk free Rate | F45: =Assumption!C13 -> 0.06615
B46: Equity Market Return | C46: =' Market Return'!F10 -> 0.13080103 | E46: Equity Market Return | F46: =' Market Return'!F10 -> 0.13080103
B47: Equity risk premium | C47: =C46-C45 -> 0.064651031 | E47: Equity risk premium | F47: =F46-F45 -> 0.064651031
B48: Levered Equity Beta | C48: =J23*(1+C37*(1-C41)) -> 0.38030755 | E48: Beta | F48: ='Equity Return'!I9 -> 1.2602979
B49: Cost of equity | C49: =C45+(C47*C48) -> 0.090737275 | E49: Cost of equity | F49: =F45+(F48*F47) -> 0.14762956
B51: WACC | C51: =(C42*C32)+(C49*C33) -> 0.089832251 | E51: WACC | F51: =(F49*F37)+((1-F37)*F42) -> 0.12988112

Sheet DCF Valuation
B5: DCF Analysis
B6: (All amounts in INR Lakhs, unless otherwise stated)
B7: Particulars | C7: 2021 | D7: =C7+1 -> 2022 | E7: =D7+1 -> 2023 | F7: =E7+1 -> 2024 | G7: =F7+1 -> 2025 | H7: =G7+1 -> 2026 | I7: =H7+1 -> 2027 | J7: =I7+1 -> 2028 | K7: =J7+1 -> 2029 | ... Q7: =P7+1 -> 2035
C8: Audited | D8: Audited | E8: Audited | F8: Audited | G8: Audited | H8: Estimated | I8: Projected | J8: Projected | K8: Projected | L8: Projected | M8: Projected | N8: Projected | O8: Projected | P8: Projected | Q8: Projected
G9: Entry | R9: Exit
B10: DATE | G10: =Assumption!C11 -> 46030 | H10: =DATE(YEAR(Assumption!$C$12)+H11,MONTH(Assumption!$C$12),DAY(Assumption!$C$12)) -> 46112 | I10: =DATE(YEAR(Assumption!$C$12)+I11,MONTH(Assumption!$C$12),DAY(Assumption!$C$12)) -> 46477 | J10: =DATE(YEAR(Assumption!$C$12)+J11,MONTH(Assumption!$C$12),DAY(Assumption!$C$12)) -> 46843 | K10: =DATE(YEAR(Assumption!$C$12)+K11,MONTH(Assumption!$C$12),DAY(Assumption!$C$12)) -> 47208 | L10: =DATE(YEAR(Assumption!$C$12)+L11,MONTH(Assumption!$C$12),DAY(Assumption!$C$12)) -> 47573 | M10: =DATE(YEAR(Assumption!$C$12)+M11,MONTH(Assumption!$C$12),DAY(Assumption!$C$12)) -> 47938 | N10: =DATE(YEAR(Assumption!$C$12)+N11,MONTH(Assumption!$C$12),DAY(Assumption!$C$12)) -> 48304 | O10: =DATE(YEAR(Assumption!$C$12)+O11,MONTH(Assumption!$C$12),DAY(Assumption!$C$12)) -> 48669 | ... Q10: =DATE(YEAR(Assumption!$C$12)+Q11,MONTH(Assumption!$C$12),DAY(Assumption!$C$12)) -> 49399 | R10: =Q10 -> 49399
B11: Time Periods | H11: 0 | I11: 1 | J11: 2 | K11: 3 | L11: 4 | M11: 5 | N11: 6 | O11: 7 | P11: 8 | Q11: 9
B12: Year Frac | C12: 0 | D12: 0 | E12: 0 | F12: 0 | G12: 0 | H12: =YEARFRAC(G10,H10) -> 0.23055556 | I12: =YEARFRAC(H10,I10) -> 1 | J12: =YEARFRAC(I10,J10) -> 1 | K12: =YEARFRAC(J10,K10) -> 1 | L12: =YEARFRAC(K10,L10) -> 1 | M12: =YEARFRAC(L10,M10) -> 1 | N12: =YEARFRAC(M10,N10) -> 1 | O12: =YEARFRAC(N10,O10) -> 1 | ... Q12: =YEARFRAC(P10,Q10) -> 1 | R12: 1
B13: EBIT/ Operating Income | C13: ='Profit & Loss Statement'!C23 -> 16875 | D13: ='Profit & Loss Statement'!D23 -> 22479 | E13: ='Profit & Loss Statement'!E23 -> 31695 | F13: ='Profit & Loss Statement'!F23 -> 27756 | G13: ='Profit & Loss Statement'!G23 -> 26572 | H13: ='Profit & Loss Statement'!H23 -> 51165.426 | I13: ='Profit & Loss Statement'!I23 -> 61875.016 | J13: ='Profit & Loss Statement'!J23 -> 72900.566 | ... Q13: ='Profit & Loss Statement'!Q23 -> 142085.59
B14: Tax rate | C14: =C13*'Cost Buildup'!C23 -> 2137.2702 | D14: =D13*'Cost Buildup'!D23 -> 5911.1952 | E14: =E13*'Cost Buildup'!E23 -> 8067.4648 | F14: =F13*'Cost Buildup'!F23 -> 7156.2843 | G14: =G13*'Cost Buildup'!G23 -> 7364.3529 | H14: =H13*'Cost Buildup'!H23 -> 14436.177 | I14: =I13*'Cost Buildup'!I23 -> 17457.857 | J14: =J13*'Cost Buildup'!J23 -> 20933.187 | ... Q14: =Q13*'Cost Buildup'!Q23 -> 42625.677
B15: NOPAT | C15: =C13-C14 -> 14737.73 | D15: =D13-D14 -> 16567.805 | E15: =E13-E14 -> 23627.535 | F15: =F13-F14 -> 20599.716 | G15: =G13-G14 -> 19207.647 | H15: =H13-H14 -> 36729.249 | I15: =I13-I14 -> 44417.159 | J15: =J13-J14 -> 51967.379 | ... Q15: =Q13-Q14 -> 99459.912
B16: Add: Depreciation & Amortization | C16: ='Profit & Loss Statement'!C21 -> 2274 | D16: ='Profit & Loss Statement'!D21 -> 3288 | E16: ='Profit & Loss Statement'!E21 -> 4191 | F16: ='Profit & Loss Statement'!F21 -> 5829 | G16: ='Profit & Loss Statement'!G21 -> 8870 | H16: ='Profit & Loss Statement'!H21 -> 4870.2 | I16: ='Profit & Loss Statement'!I21 -> 4894.551 | J16: ='Profit & Loss Statement'!J21 -> 4919.0238 | ... Q16: ='Profit & Loss Statement'!Q21 -> 5093.7937
B17: Less: CapEx | D17: =-FAS!D376 -> -5953 | E17: =-FAS!E376 -> -25758 | F17: =-FAS!F376 -> -3669 | G17: =-FAS!G376 -> -26484 | H17: =-FAS!H376 -> -6620 | I17: =-FAS!I376 -> -6691.98 | J17: =-FAS!J376 -> -6688.5699 | K17: =-FAS!K376 -> -6758.8827 | ... Q17: =-FAS!Q376 -> -6963.6422
B18: Less: Change in Working Capital | D18: =(SUM('Balance sheet'!C25,'Balance sheet'!C28:C30)-SUM('Balance sheet'!D25,'Balance sheet'!D28:D30))+('Balance sheet'!D64-'Balance sheet'!C64) -> 70 | E18: =(SUM('Balance sheet'!D25,'Balance sheet'!D28:D30)-SUM('Balance sheet'!E25,'Balance sheet'!E28:E30))+('Balance sheet'!E64-'Balance sheet'!D64) -> 12363 | F18: =(SUM('Balance sheet'!E25,'Balance sheet'!E28:E30)-SUM('Balance sheet'!F25,'Balance sheet'!F28:F30))+('Balance sheet'!F64-'Balance sheet'!E64) -> -6951 | G18: =(SUM('Balance sheet'!F25,'Balance sheet'!F28:F30)-SUM('Balance sheet'!G25,'Balance sheet'!G28:G30))+('Balance sheet'!G64-'Balance sheet'!F64) -> 48983 | H18: =(SUM('Balance sheet'!G25,'Balance sheet'!G28:G30)-SUM('Balance sheet'!H25,'Balance sheet'!H28:H30))+('Balance sheet'!H64-'Balance sheet'!G64) -> -27829.82 | I18: =(SUM('Balance sheet'!H25,'Balance sheet'!H28:H30)-SUM('Balance sheet'!I25,'Balance sheet'!I28:I30))+('Balance sheet'!I64-'Balance sheet'!H64) -> 6460.6319 | J18: =(SUM('Balance sheet'!I25,'Balance sheet'!I28:I30)-SUM('Balance sheet'!J25,'Balance sheet'!J28:J30))+('Balance sheet'!J64-'Balance sheet'!I64) -> 6650.8777 | K18: =(SUM('Balance sheet'!J25,'Balance sheet'!J28:J30)-SUM('Balance sheet'!K25,'Balance sheet'!K28:K30))+('Balance sheet'!K64-'Balance sheet'!J64) -> 6692.1538 | ... Q18: =(SUM('Balance sheet'!P25,'Balance sheet'!P28:P30)-SUM('Balance sheet'!Q25,'Balance sheet'!Q28:Q30))+('Balance sheet'!Q64-'Balance sheet'!P64) -> 4902.6703
B20: Unlevered FCFF | C20: =C15+C16+C17+C18 -> 17011.73 | D20: =D15+D16+D17+D18 -> 13972.805 | E20: =E15+E16+E17+E18 -> 14423.535 | F20: =F15+F16+F17+F18 -> 15808.716 | G20: =G15+G16+G17+G18 -> 50576.647 | H20: =H15+H16+H17+H18 -> 7149.629 | I20: =I15+I16+I17+I18 -> 49080.362 | J20: =J15+J16+J17+J18 -> 56848.711 | ... Q20: =Q15+Q16+Q17+Q18 -> 102492.73 | R20: =C32 -> 1918372.5
B22: Transaction FCFF | C22: =C20*C12 -> 0 | D22: =D20*D12 -> 0 | E22: =E20*E12 -> 0 | F22: =F20*F12 -> 0 | G22: =G20*G12 -> 0 | H22: =H20*H12 -> 1648.3867 | I22: =I20*I12 -> 49080.362 | J22: =J20*J12 -> 56848.711 | ... R22: =R20*R12 -> 1918372.5
B25: EV/EBITDA Multiple | C25: ='Comparable Valuation'!E36 -> 15.505377
B26: Perpetual Growth Rate | C26: =Assumption!C19 -> 0.06
B27: Discount Rate | C27: ='Comps Beta'!F51 -> 0.12988112
B29: Terminal Value
B30: EV/EBITDA | C30: =C25*(Q13+Q16) -> 2282071.8
B31: Prep.Growth | C31: =Q22*(1+C26)/(C27-C26) -> 1554673.2
B32: Average | C32: =AVERAGE(C30:C31) -> 1918372.5
B34: Intrinsic Value
B35: Enterpreise Value | C35: =XNPV(C27,G22:R22,G10:R10) -> 983943.65
B36: Plus: Cash & Cash equivalent | C36: ='Balance sheet'!G24+'Balance sheet'!G26+'Balance sheet'!G27+'Balance sheet'!G29 -> 158588
B37: Less- Debt | C37: =-SUM('Balance sheet'!G45,'Balance sheet'!G56) -> -116091
B38: Less-non- controlling interest | C38: 0
B39: Equity Value | C39: =SUM(C35:C38) -> 1026440.6
B41: Equity value/share | C41: =C39/'Comparable Valuation'!F31 -> 673.95972
B43: Upside Potentail | C43: =C41/Assumption!C22-1 -> 0.46832182

Sheet Comps Data
B6: Comps Data
B7: (All amounts in INR Lakhs, unless otherwise stated)
B8: Name | C8: CMP Rs. | D8: No. Eq. Shares Cr. | E8: Debt Rs.lakhs | F8: Cash Rs.lakhs | G8: NP Ann Rs.lakhs | H8: Sales Ann Rs.lakhs | I8: Dep Amt Rs.Lakhs | J8: EBIT Ann Rs.lakhs | K8: EV / EBITDA | L8: EV Rs.lakhs | M8: Mar Cap Rs.lakhs | N8: Tax 12M Rs.lakhs | O8: P/E
B9: TCS | C9: 3205 | D9: 36181 | E9: 1093200 | F9: 1445300 | G9: 4879700 | H9: 25532400 | I9: 524200 | J9: 6608100 | K9: 1482 | L9: 109205499 | M9: 109557599 | N9: 16428 | O9: 21.79
B10: Infosys | C10: 1622 | D10: 41544 | E10: 848500 | F10: 2745900 | G10: 2675000 | H10: 16299000 | I10: 481200 | J10: 3773300 | K10: 1402 | L10: 61033457 | M10: 62930857 | N10: 11026 | O10: 23.08
B11: HCL Technologies | C11: 1643 | D11: 27137 | E11: 627600 | F11: 2128900 | G11: 1739900 | H11: 11705500 | I11: 408400 | J11: 2370300 | K11: 1417 | L11: 39084292 | M11: 40585592 | N11: 5759 | O11: 23.91
B12: Wipro | C12: 266 | D12: 104838 | E12: 1920350 | F12: 1219740 | G12: 1321800 | H12: 8908840 | I12: 295790 | J12: 1891210 | K12: 1209 | L12: 26784338 | M12: 26083728 | N12: 4214.5 | O12: 19.37
B13: LTIMindtree | C13: 6030 | D13: 2964 | E13: 218730 | F13: 358820 | G13: 460200 | H13: 3800810 | I13: 99150 | J13: 649310 | K13: 2090 | L13: 16075817 | M13: 16215907 | N13: 1693.3 | O13: 34.36
B14: Tech Mahindra | C14: 1601 | D14: 9796 | E14: 202520 | F14: 454220 | G14: 425300 | H14: 5298830 | I14: 185290 | J14: 552130 | K14: 1696 | L14: 14025403 | M14: 14277103 | N14: 1576.2 | O14: 31.44
B15: Newgen Software | C15: 827 | D15: 1417 | E15: 5348 | F15: 41550 | G15: 31524 | H15: 148688 | I15: 3304 | J15: 39747 | K15: 2704 | L15: 1200371 | M15: 1236573 | N15: 87.19 | O15: 38.96
B16: Sonata Software | C16: 363 | D16: 2804 | E16: 51602 | F16: 44943 | G16: 42467 | H16: 1015725 | I16: 12149 | J16: 63930 | K16: 1390 | L16: 1041276 | M16: 1034617 | N16: 156.25 | O16: 24.15
B17: Birlasoft Ltd | C17: 437 | D17: 2785 | E17: 15100 | F17: 44488 | G17: 51676 | H17: 537524 | I17: 8571 | J17: 70894 | K17: 1265 | L17: 971696 | M17: 1001084 | N17: 185.16 | O17: 21.17
B20: Happiest Minds | C20: =Assumption!C22 -> 459 | D20: 1523 | E20: 124359 | F20: 105823 | G20: 18466 | H20: 206084 | I20: 8870 | J20: 36691 | K20: 1664 | L20: 781205 | M20: 762669 | N20: 7316 | O20: 38
B22: Source-
B23: IT - Software Companies - Screener

Sheet Comparable Valuation
B6: Comparable Valuation
B7: (All amounts in INR Lakhs, unless otherwise stated)
B8: Companies | E8: Market Data | L8: Financial data | P8: Valution
E9: Price | F9: Share | G9: Market Cap | H9: Debt | I9: Cash | J9: EV | L9: Sales | M9: EBITDA | N9: Earnings | P9: EV/Sales | Q9: EV/EBITDA | R9: P/E
B10: Company Name | E10: (/share) | F10: (INR Lakhs) | G10: (INR Lakhs) | H10: (INR Lakhs) | I10: (INR Lakhs) | J10: (INR Lakhs) | L10: (INR Lakhs) | M10: (INR Lakhs) | N10: (INR Lakhs) | P10: x | Q10: x | R10: x
B12: ='Comps Data'!B9 -> TCS | E12: ='Comps Data'!C9 -> 3205 | F12: ='Comps Data'!D9 -> 36181 | G12: =F12*E12 -> 115960105 | H12: ='Comps Data'!E9 -> 1093200 | I12: ='Comps Data'!F9 -> 1445300 | J12: =G12+H12-I12 -> 115608005 | L12: ='Comps Data'!H9 -> 25532400 | M12: ='Comps Data'!J9+'Comps Data'!I9 -> 7132300 | N12: ='Comps Data'!G9 -> 4879700 | P12: =J12/L12 -> 4.5278942 | Q12: =J12/M12 -> 16.209078 | R12: =G12/N12 -> 23.763777
B13: ='Comps Data'!B10 -> Infosys | E13: ='Comps Data'!C10 -> 1622 | F13: ='Comps Data'!D10 -> 41544 | G13: =F13*E13 -> 67384368 | H13: ='Comps Data'!E10 -> 848500 | I13: ='Comps Data'!F10 -> 2745900 | J13: =G13+H13-I13 -> 65486968 | L13: ='Comps Data'!H10 -> 16299000 | M13: ='Comps Data'!J10+'Comps Data'!I10 -> 4254500 | N13: ='Comps Data'!G10 -> 2675000 | P13: =J13/L13 -> 4.0178519 | Q13: =J13/M13 -> 15.392401 | R13: =G13/N13 -> 25.190418
B14: ='Comps Data'!B11 -> HCL Technologies | E14: ='Comps Data'!C11 -> 1643 | F14: ='Comps Data'!D11 -> 27137 | G14: =F14*E14 -> 44586091 | H14: ='Comps Data'!E11 -> 627600 | I14: ='Comps Data'!F11 -> 2128900 | J14: =G14+H14-I14 -> 43084791 | L14: ='Comps Data'!H11 -> 11705500 | M14: ='Comps Data'!J11+'Comps Data'!I11 -> 2778700 | N14: ='Comps Data'!G11 -> 1739900 | P14: =J14/L14 -> 3.6807305 | Q14: =J14/M14 -> 15.505377 | R14: =G14/N14 -> 25.625663
B15: ='Comps Data'!B12 -> Wipro | E15: ='Comps Data'!C12 -> 266 | F15: ='Comps Data'!D12 -> 104838 | G15: =F15*E15 -> 27886908 | H15: ='Comps Data'!E12 -> 1920350 | I15: ='Comps Data'!F12 -> 1219740 | J15: =G15+H15-I15 -> 28587518 | L15: ='Comps Data'!H12 -> 8908840 | M15: ='Comps Data'!J12+'Comps Data'!I12 -> 2187000 | N15: ='Comps Data'!G12 -> 1321800 | P15: =J15/L15 -> 3.2088934 | Q15: =J15/M15 -> 13.071567 | R15: =G15/N15 -> 21.097676
B16: ='Comps Data'!B13 -> LTIMindtree | E16: ='Comps Data'!C13 -> 6030 | F16: ='Comps Data'!D13 -> 2964 | G16: =F16*E16 -> 17872920 | H16: ='Comps Data'!E13 -> 218730 | I16: ='Comps Data'!F13 -> 358820 | J16: =G16+H16-I16 -> 17732830 | L16: ='Comps Data'!H13 -> 3800810 | M16: ='Comps Data'!J13+'Comps Data'!I13 -> 748460 | N16: ='Comps Data'!G13 -> 460200 | P16: =J16/L16 -> 4.6655397 | Q16: =J16/M16 -> 23.692422 | R16: =G16/N16 -> 38.837288
B17: ='Comps Data'!B14 -> Tech Mahindra | E17: ='Comps Data'!C14 -> 1601 | F17: ='Comps Data'!D14 -> 9796 | G17: =F17*E17 -> 15683396 | H17: ='Comps Data'!E14 -> 202520 | I17: ='Comps Data'!F14 -> 454220 | J17: =G17+H17-I17 -> 15431696 | L17: ='Comps Data'!H14 -> 5298830 | M17: ='Comps Data'!J14+'Comps Data'!I14 -> 737420 | N17: ='Comps Data'!G14 -> 425300 | P17: =J17/L17 -> 2.9122837 | Q17: =J17/M17 -> 20.926604 | R17: =G17/N17 -> 36.876078
B18: ='Comps Data'!B15 -> Newgen Software | E18: ='Comps Data'!C15 -> 827 | F18: ='Comps Data'!D15 -> 1417 | G18: =F18*E18 -> 1171859 | H18: ='Comps Data'!E15 -> 5348 | I18: ='Comps Data'!F15 -> 41550 | J18: =G18+H18-I18 -> 1135657 | L18: ='Comps Data'!H15 -> 148688 | M18: ='Comps Data'!J15+'Comps Data'!I15 -> 43051 | N18: ='Comps Data'!G15 -> 31524 | P18: =J18/L18 -> 7.6378524 | Q18: =J18/M18 -> 26.379341 | R18: =G18/N18 -> 37.17355
B19: ='Comps Data'!B16 -> Sonata Software | E19: ='Comps Data'!C16 -> 363 | F19: ='Comps Data'!D16 -> 2804 | G19: =F19*E19 -> 1017852 | H19: ='Comps Data'!E16 -> 51602 | I19: ='Comps Data'!F16 -> 44943 | J19: =G19+H19-I19 -> 1024511 | L19: ='Comps Data'!H16 -> 1015725 | M19: ='Comps Data'!J16+'Comps Data'!I16 -> 76079 | N19: ='Comps Data'!G16 -> 42467 | P19: =J19/L19 -> 1.00865 | Q19: =J19/M19 -> 13.46641 | R19: =G19/N19 -> 23.968069
B20: ='Comps Data'!B17 -> Birlasoft Ltd | E20: ='Comps Data'!C17 -> 437 | F20: ='Comps Data'!D17 -> 2785 | G20: =F20*E20 -> 1217045 | H20: ='Comps Data'!E17 -> 15100 | I20: ='Comps Data'!F17 -> 44488 | J20: =G20+H20-I20 -> 1187657 | L20: ='Comps Data'!H17 -> 537524 | M20: ='Comps Data'!J17+'Comps Data'!I17 -> 79465 | N20: ='Comps Data'!G17 -> 51676 | P20: =J20/L20 -> 2.2094958 | Q20: =J20/M20 -> 14.945662 | R20: =G20/N20 -> 23.551455
B24: High | P24: =MAX(P12:P20) -> 7.6378524 | Q24: =MAX(Q12:Q20) -> 26.379341 | R24: =MAX(R12:R20) -> 38.837288
B25: 75th Percentile | P25: =_xlfn.QUARTILE.EXC(P12:P20,3) -> 4.5967169 | Q25: =_xlfn.QUARTILE.EXC(Q12:Q20,3) -> 22.309513 | R25: =_xlfn.QUARTILE.EXC(R12:R20,3) -> 37.024814
B26: Average | P26: =AVERAGE(P12:P20) -> 3.7632435 | Q26: =AVERAGE(Q12:Q20) -> 17.732096 | R26: =AVERAGE(R12:R20) -> 28.453775
B27: Median | P27: =MEDIAN(P12:P20) -> 3.6807305 | Q27: =MEDIAN(Q12:Q20) -> 15.505377 | R27: =MEDIAN(R12:R20) -> 25.190418
B28: 25th Percentile | P28: =_xlfn.QUARTILE.EXC(P12:P20,1) -> 2.5608897 | Q28: =_xlfn.QUARTILE.EXC(Q12:Q20,1) -> 14.206036 | R28: =_xlfn.QUARTILE.EXC(R12:R20,1) -> 23.657616
B29: Low | P29: =MIN(P16:P20) -> 1.00865 | Q29: =MIN(Q16:Q20) -> 13.46641 | R29: =MIN(R16:R20) -> 23.551455
B31: ='Comps Data'!B20 -> Happiest Minds | E31: ='Comps Data'!C20 -> 459 | F31: ='Comps Data'!D20 -> 1523 | G31: =F31*E31 -> 699057 | H31: ='Comps Data'!E20 -> 124359 | I31: ='Comps Data'!F20 -> 105823 | J31: =G31+H31-I31 -> 717593 | L31: ='Comps Data'!H20 -> 206084 | M31: ='Comps Data'!I20+'Comps Data'!J20 -> 45561 | N31: ='Comps Data'!G20 -> 18466 | P31: =J31/L31 -> 3.4820413 | Q31: =J31/M31 -> 15.750159 | R31: =G31/N31 -> 37.856439
B33: Median
B34: Metric | E34: Comps | F34: EV (₹ Lakhs.) | G34: Net Debt (₹ Lakhs.) | H34: Equity Value (₹ Lakhs.) | I34: Shares (Lakhs) | J34: Share Price | L34: Stock Value
B35: EV/REVENUE | E35: =P27 -> 3.6807305 | F35: =E35*L31 -> 758539.67 | G35: =$H$31-$I$31 -> 18536 | H35: =F35-G35 -> 740003.67 | I35: =$F$31 -> 1523 | J35: =H35/I35 -> 485.88553 | L35: =IF(J35>$E$31,"Undervalued","Overvalued") -> Undervalued
B36: EV/EBITDA | E36: =Q27 -> 15.505377 | F36: =E36*M31 -> 706440.48 | G36: =$H$31-$I$31 -> 18536 | H36: =F36-G36 -> 687904.48 | I36: =$F$31 -> 1523 | J36: =H36/I36 -> 451.67727 | L36: =IF(J36>$E$31,"Undervalued","Overvalued") -> Overvalued
B37: P/E | E37: =R27 -> 25.190418 | F37: =H37+G37 -> 483702.26 | G37: =$H$31-$I$31 -> 18536 | H37: =E37*N31 -> 465166.26 | I37: =$F$31 -> 1523 | J37: =H37/I37 -> 305.42762 | L37: =IF(J37>$E$31,"Undervalued","Overvalued") -> Overvalued
B39: Average
B40: Metric | E40: Comps | F40: EV (₹ Lakhs.) | G40: Net Debt (₹ Lakhs.) | H40: Equity Value (₹ Lakhs.) | I40: Shares (Lakhs) | J40: Share Price | L40: Stock Value
B41: EV/REVENUE | E41: =P26 -> 3.7632435 | F41: =E41*L31 -> 775544.27 | G41: =G35 -> 18536 | H41: =F41-G41 -> 757008.27 | I41: =$F$31 -> 1523 | J41: =H41/I41 -> 497.05074 | L41: =IF(J41>$E$31,"Undervalued","Overvalued") -> Undervalued
B42: EV/EBITDA | E42: =Q26 -> 17.732096 | F42: =E42*M31 -> 807892.01 | G42: =G36 -> 18536 | H42: =F42-G42 -> 789356.01 | I42: =$F$31 -> 1523 | J42: =H42/I42 -> 518.29022 | L42: =IF(J42>$E$31,"Undervalued","Overvalued") -> Undervalued
B43: P/E | E43: =R26 -> 28.453775 | F43: =H43+G43 -> 543963.41 | G43: =G37 -> 18536 | H43: =E43*N31 -> 525427.41 | I43: =$F$31 -> 1523 | J43: =H43/I43 -> 344.99502 | L43: =IF(J43>$E$31,"Undervalued","Overvalued") -> Overvalued

Sheet Ratio Analysis
B6: Ratio Analysis & Interpretation
B8: Particulars | C8: 2021 | D8: =C8+1 -> 2022 | E8: =D8+1 -> 2023 | F8: =E8+1 -> 2024 | G8: =F8+1 -> 2025 | H8: =G8+1 -> 2026 | I8: =H8+1 -> 2027 | J8: =I8+1 -> 2028 | K8: =J8+1 -> 2029 | ... Q8: =P8+1 -> 2035 | S8: Ratio Interpretation
C9: Audited | D9: Audited | E9: Audited | F9: Audited | G9: Audited | H9: Estimated | I9: Projected | J9: Projected | K9: Projected | L9: Projected | M9: Projected | N9: Projected | O9: Projected | P9: Projected | Q9: Projected
B10: Profitability Ratio
B12: EBITDA Margin | C12: ='Profit & Loss Statement'!C19/'Profit & Loss Statement'!C10 -> 0.24759183 | D12: ='Profit & Loss Statement'!D19/'Profit & Loss Statement'!D10 -> 0.23560554 | E12: ='Profit & Loss Statement'!E19/'Profit & Loss Statement'!E10 -> 0.25107571 | F12: ='Profit & Loss Statement'!F19/'Profit & Loss Statement'!F10 -> 0.20672018 | G12: ='Profit & Loss Statement'!G19/'Profit & Loss Statement'!G10 -> 0.17197842 | H12: ='Profit & Loss Statement'!H19/'Profit & Loss Statement'!H10 -> 0.22259434 | I12: ='Profit & Loss Statement'!I19/'Profit & Loss Statement'!I10 -> 0.22259434 | J12: ='Profit & Loss Statement'!J19/'Profit & Loss Statement'!J10 -> 0.22259434 | ... Q12: ='Profit & Loss Statement'!Q19/'Profit & Loss Statement'!Q10 -> 0.22259434 | S12: The EBITDA margin during the historical period (FY2021–FY2025) showed volatility, declining from 24.76% in FY2021 to 23.56% in FY2022, improving to 25.11% in FY2023, and then falling sharply to 20.67% in FY2024 and 17.20% in FY2025, indicating increasing pressure on operating efficiency due to rising costs and margin compression. The significant decline from the peak highlights weakened cost control and reduced profitability in recent years. For the forecast period (FY2026–FY2035), the margin is assumed to stabilize at 22.26%, reflecting normalized operations, improved expense management, and sustainable profitability, supporting steady long-term cash flow generation without assuming aggressive margin expansion.
B15: Operating Margin | C15: ='Profit & Loss Statement'!C23/'Profit & Loss Statement'!C10 -> 0.21818958 | D15: ='Profit & Loss Statement'!D23/'Profit & Loss Statement'!D10 -> 0.20554108 | E15: ='Profit & Loss Statement'!E23/'Profit & Loss Statement'!E10 -> 0.22175346 | F15: ='Profit & Loss Statement'!F23/'Profit & Loss Statement'!F10 -> 0.1708419 | G15: ='Profit & Loss Statement'!G23/'Profit & Loss Statement'!G10 -> 0.12893771 | H15: ='Profit & Loss Statement'!H23/'Profit & Loss Statement'!H10 -> 0.20324809 | I15: ='Profit & Loss Statement'!I23/'Profit & Loss Statement'!I10 -> 0.20627703 | J15: ='Profit & Loss Statement'!J23/'Profit & Loss Statement'!J10 -> 0.20852401 | ... Q15: ='Profit & Loss Statement'!Q23/'Profit & Loss Statement'!Q10 -> 0.21489047 | S15: The Operating Margin during the historical period (FY2021–FY2025) showed a declining and volatile trend, decreasing from 21.82% in FY2021 to 20.55% in FY2022, improving to 22.18% in FY2023, and then falling sharply to 17.08% in FY2024 and 12.89% in FY2025. This significant deterioration indicates rising operating costs, margin compression, and reduced operating efficiency, suggesting challenges in cost control and profitability in recent years. For the forecast period (FY2026–FY2035), the operating margin is expected to gradually improve and stabilize from 20.32% to 21.49%, reflecting operational normalization, improved cost management, and a return to sustainable profitability levels over the long term.
B18: Pretax Margin | C18: ='Profit & Loss Statement'!C28/'Profit & Loss Statement'!C10 -> 0.24051926 | D18: ='Profit & Loss Statement'!D28/'Profit & Loss Statement'!D10 -> 0.2247977 | E18: ='Profit & Loss Statement'!E28/'Profit & Loss Statement'!E10 -> 0.21679295 | F18: ='Profit & Loss Statement'!F28/'Profit & Loss Statement'!F10 -> 0.20600002 | G18: ='Profit & Loss Statement'!G28/'Profit & Loss Statement'!G10 -> 0.12395916 | H18: ='Profit & Loss Statement'!H28/'Profit & Loss Statement'!H10 -> 0.21007437 | I18: ='Profit & Loss Statement'!I28/'Profit & Loss Statement'!I10 -> 0.2196241 | J18: ='Profit & Loss Statement'!J28/'Profit & Loss Statement'!J10 -> 0.22165118 | ... Q18: ='Profit & Loss Statement'!Q28/'Profit & Loss Statement'!Q10 -> 0.22700224 | S18: The Pretax margin during the historical period (FY2021–FY2025) followed a declining trend, decreasing from 24.05% in FY2021 to 22.48% in FY2022, further moderating to 21.68% in FY2023 and 20.60% in FY2024, before falling sharply to 12.40% in FY2025. This significant compression indicates pressure from higher operating costs, increased interest burden, or non-operating expenses affecting overall profitability before tax. For the forecast period (FY2026–FY2035), the pretax margin is expected to recover and gradually improve from 21.01% to 22.70%, reflecting normalization of costs, improved operating performance, and stable financial structure, supporting sustainable profitability over the long term.
B21: Effective Tax Rate | C21: ='Cost Buildup'!C23 -> 0.12665305 | D21: ='Cost Buildup'!D23 -> 0.26296522 | E21: ='Cost Buildup'!E23 -> 0.25453431 | F21: ='Cost Buildup'!F23 -> 0.25782837 | G21: ='Cost Buildup'!G23 -> 0.27714711 | H21: ='Cost Buildup'!H23 -> 0.28214711 | I21: ='Cost Buildup'!I23 -> 0.28214711 | J21: ='Cost Buildup'!J23 -> 0.28714711 | ... Q21: ='Cost Buildup'!Q23 -> 0.3 | S21: The Effective Tax Rate (ETR) during the historical period (FY2021–FY2025) exhibited a rising trend, increasing from 12.67% in FY2021 to 27.71% in FY2025, indicating higher tax obligations relative to pre-tax profits, possibly due to improved profitability, changes in statutory rates, or reduced tax exemptions. For the forecast period (FY2026–FY2035), the ETR is expected to stabilize around 28.21%–30.00%, reflecting consistent tax policies and normalized earnings composition. The gradual increase and subsequent stabilization suggest predictable tax planning and reduced volatility in post-tax profitability, supporting more reliable net income projections over the long term.
