Workbook

Sheet Assumption
B8: Scenario
B9: Base | C9: =IF(B9="Best",1,IF(B9="Base",2,3)) -> 2
B12: Assumptions
B13: Transaction Date | C13: 45883
B14: Fiscal Year End | C14: 46112
B15: Risk Free Rate | C15: 0.06463
B16: Tax Rate | C16: 0.22228215
B17: EV/EBITDA Multiple | C17: ='Comps Valuation'!E36 -> 37.419896
B18: Perpetual Growth Rate | C18: 0.05
B19: Discount Rate | C19: =WACC!C52 -> 0.080628449
B20: Shares Outstanding(Cr.) | C20: 129.78
B21: Current market price | C21: 711
B22: Market Cap (Cr.) | C22: =C21*C20 -> 92273.58
B24: Color Code
B25: Blue color | C25: Hardcoded Figures
B26: Black color | C26: Calculated/Formula Figures
B27: Green color | C27: Linked sheet

Sheet Income Statement
B6: Income Statement
B7: All Figure In INR Cr.
B8: Particular | C8: 2021 | D8: =C8+1 -> 2022 | E8: =D8+1 -> 2023 | F8: =E8+1 -> 2024 | G8: =F8+1 -> 2025
B9: Income
B10: Revenue from operations | C10: 8048 | D10: 9512 | E10: 9764 | F10: 9653 | G10: 10831
B11: Other income | C11: 94 | D11: 98 | E11: 144 | F11: 142 | G11: 208
B12: Total Income | C12: =SUM(C10:C11) -> 8142 | D12: =SUM(D10:D11) -> 9610 | E12: =SUM(E10:E11) -> 9908 | F12: =SUM(F10:F11) -> 9795 | G12: =SUM(G10:G11) -> 11039
B13: Expenses
B14: Cost of materials consumed | C14: 3884 | D14: 5061 | E14: 4649 | F14: 3941 | G14: 4572
B15: Purchases of stock-in-trade | C15: 339 | D15: 491 | E15: 541 | F15: 752 | G15: 960
B16: Changes in inventories of finished goods, stock-in-trade and work-in progress | C16: 47 | D16: -116 | E16: 161 | F16: 55 | G16: -144
B17: Employee benefit expense | C17: 570 | D17: 586 | E17: 653 | F17: 743 | G17: 831
B18: Finance costs | C18: 34 | D18: 39 | E18: 56 | F18: 73 | G18: 53
B19: Depreciation and amortization expense | C19: 139 | D19: 139 | E19: 155 | F19: 158 | G19: 178
B20: Other expenses | C20: 1617 | D20: 1809 | E20: 1950 | F20: 2136 | G20: 2473
B21: Total expenses | C21: =SUM(C14:C20) -> 6630 | D21: =SUM(D14:D20) -> 8009 | E21: =SUM(E14:E20) -> 8165 | F21: =SUM(F14:F20) -> 7858 | G21: =SUM(G14:G20) -> 8923
B22: Profit before exceptional items and tax | C22: =C12-C21 -> 1512 | D22: =D12-D21 -> 1601 | E22: =E12-E21 -> 1743 | F22: =F12-F21 -> 1937 | G22: =G12-G21 -> 2116
B23: Share of net gain/(loss) of joint ventures | C23: -2
B24: Profit before exceptional items and tax | C24: =C22+C23 -> 1510 | D24: =D22+D23 -> 1601 | E24: =E22+E23 -> 1743 | F24: =F22+F23 -> 1937 | G24: =G22+G23 -> 2116
B25: Exceptional items | C25: 13
B26: Profit before tax | C26: =C24+C25 -> 1523 | D26: =D24+D25 -> 1601 | E26: =E24+E25 -> 1743 | F26: =F24+F25 -> 1937 | G26: =G24+G25 -> 2116
B27: Income tax expense
B28: Tax expense for the current year | C28: 324 | D28: 346 | E28: 421 | F28: 435 | G28: 458
B29: Profit for the year (A) | C29: =C26-C28 -> 1199 | D29: =D26-D28 -> 1255 | E29: =E26-E28 -> 1322 | F29: =F26-F28 -> 1502 | G29: =G26-G28 -> 1658

Sheet P&L Statement 
B6: Income Statement
B7: All Figure In INR Cr.
B8: Particulars | C8: 2021 | D8: =C8+1 -> 2022 | E8: =D8+1 -> 2023 | F8: =E8+1 -> 2024 | G8: =F8+1 -> 2025 | H8: =G8+1 -> 2026 | I8: =H8+1 -> 2027 | J8: =I8+1 -> 2028 | K8: =J8+1 -> 2029 | ... Q8: =P8+1 -> 2035
B10: Revenue | C10: ='Revenue BuildUp'!C11 -> 8048 | D10: ='Revenue BuildUp'!D11 -> 9512 | E10: ='Revenue BuildUp'!E11 -> 9764 | F10: ='Revenue BuildUp'!F11 -> 9653 | G10: ='Revenue BuildUp'!G11 -> 10831 | H10: ='Revenue BuildUp'!H11 -> 11829.458 | I10: ='Revenue BuildUp'!I11 -> 12984.788 | J10: ='Revenue BuildUp'!J11 -> 14334.34 | ... Q10: ='Revenue BuildUp'!Q11 -> 35620.804
B11: COGS | C11: =-'Cost BuildUp'!C13 -> -4270 | D11: =-'Cost BuildUp'!D13 -> -5436 | E11: =-'Cost BuildUp'!E13 -> -5351 | F11: =-'Cost BuildUp'!F13 -> -4748 | G11: =-'Cost BuildUp'!G13 -> -5388 | H11: =-'Cost BuildUp'!H13 -> -6244.576 | I11: =-'Cost BuildUp'!I13 -> -6854.4558 | J11: =-'Cost BuildUp'!J13 -> -7566.8621 | ... Q11: =-'Cost BuildUp'!Q13 -> -18803.636
B12: Gross Profit | C12: =SUM(C10:C11) -> 3778 | D12: =SUM(D10:D11) -> 4076 | E12: =SUM(E10:E11) -> 4413 | F12: =SUM(F10:F11) -> 4905 | G12: =SUM(G10:G11) -> 5443 | H12: =SUM(H10:H11) -> 5584.8819 | I12: =SUM(I10:I11) -> 6130.3324 | J12: =SUM(J10:J11) -> 6767.4782 | ... Q12: =SUM(Q10:Q11) -> 16817.168
B13: Gross Margin | C13: =C12/C10 -> 0.4694334 | D13: =D12/D10 -> 0.42851135 | E13: =E12/E10 -> 0.45196641 | F13: =F12/F10 -> 0.50813219 | G13: =G12/G10 -> 0.50253901 | H13: =H12/H10 -> 0.47211647 | I13: =I12/I10 -> 0.47211647 | J13: =J12/J10 -> 0.47211647 | ... Q13: =Q12/Q10 -> 0.47211647
B15: Salaries & Benefits | C15: =-'Cost BuildUp'!C26 -> -570 | D15: =-'Cost BuildUp'!D26 -> -586 | E15: =-'Cost BuildUp'!E26 -> -653 | F15: =-'Cost BuildUp'!F26 -> -743 | G15: =-'Cost BuildUp'!G26 -> -831 | H15: =-'Cost BuildUp'!H26 -> -835.17126 | I15: =-'Cost BuildUp'!I26 -> -916.73871 | J15: =-'Cost BuildUp'!J26 -> -1012.0184 | ... Q15: =-'Cost BuildUp'!Q26 -> -2514.8635
B16: S&G Expenses | C16: =-'Cost BuildUp'!C29 -> -1617 | D16: =-'Cost BuildUp'!D29 -> -1809 | E16: =-'Cost BuildUp'!E29 -> -1950 | F16: =-'Cost BuildUp'!F29 -> -2136 | G16: =-'Cost BuildUp'!G29 -> -2473 | H16: =-'Cost BuildUp'!H29 -> -2461.5162 | I16: =-'Cost BuildUp'!I29 -> -2701.9215 | J16: =-'Cost BuildUp'!J29 -> -2982.7411 | ... Q16: =-'Cost BuildUp'!Q29 -> -7412.1051
B18: EBITDA | C18: =SUM(C12,C15:C16) -> 1591 | D18: =SUM(D12,D15:D16) -> 1681 | E18: =SUM(E12,E15:E16) -> 1810 | F18: =SUM(F12,F15:F16) -> 2026 | G18: =SUM(G12,G15:G16) -> 2139 | H18: =SUM(H12,H15:H16) -> 2288.1945 | I18: =SUM(I12,I15:I16) -> 2511.6722 | J18: =SUM(J12,J15:J16) -> 2772.7186 | ... Q18: =SUM(Q12,Q15:Q16) -> 6890.1996
B19: EBITDA Margin | C19: =C18/C10 -> 0.19768887 | D19: =D18/D10 -> 0.17672414 | E19: =E18/E10 -> 0.18537485 | F19: =F18/F10 -> 0.20988294 | G19: =G18/G10 -> 0.19748869 | H19: =H18/H10 -> 0.1934319 | I19: =I18/I10 -> 0.1934319 | J19: =J18/J10 -> 0.1934319 | ... Q19: =Q18/Q10 -> 0.1934319
B21: Dep & Amortization | C21: =-'Income Statement'!C19 -> -139 | D21: =-'Income Statement'!D19 -> -139 | E21: =-'Income Statement'!E19 -> -155 | F21: =-'Income Statement'!F19 -> -158 | G21: =-'Income Statement'!G19 -> -178 | H21: =-'FAS Seechules'!H86 -> -160.8108 | I21: =-'FAS Seechules'!I86 -> -195.72191 | J21: =-'FAS Seechules'!J86 -> -238.54858 | K21: =-'FAS Seechules'!K86 -> -291.16514 | L21: =-'FAS Seechules'!L86 -> -355.90783 | M21: =-'FAS Seechules'!M86 -> -435.69258 | N21: =-'FAS Seechules'!N86 -> -534.1636 | O21: =-'FAS Seechules'!O86 -> -655.88117 | ... Q21: =-'FAS Seechules'!Q86 -> -993.36431
B23: EBIT | C23: =SUM(C18,C21) -> 1452 | D23: =SUM(D18,D21) -> 1542 | E23: =SUM(E18,E21) -> 1655 | F23: =SUM(F18,F21) -> 1868 | G23: =SUM(G18,G21) -> 1961 | H23: =SUM(H18,H21) -> 2127.3837 | I23: =SUM(I18,I21) -> 2315.9503 | J23: =SUM(J18,J21) -> 2534.17 | ... Q23: =SUM(Q18,Q21) -> 5896.8353
B24: EBIT Margin | C24: =C23/C10 -> 0.1804175 | D24: =D23/D10 -> 0.16211102 | E24: =E23/E10 -> 0.1695002 | F24: =F23/F10 -> 0.19351497 | G24: =G23/G10 -> 0.18105438 | H24: =H23/H10 -> 0.1798378 | I24: =I23/I10 -> 0.17835873 | J24: =J23/J10 -> 0.17679014 | ... Q24: =Q23/Q10 -> 0.1655447
B26: Interest Cost | C26: =-'Income Statement'!C18 -> -34 | D26: =-'Income Statement'!D18 -> -39 | E26: =-'Income Statement'!E18 -> -56 | F26: =-'Income Statement'!F18 -> -73 | G26: =-'Income Statement'!G18 -> -53 | H26: =-'Debt Schedules'!H14 -> -63.701955 | I26: =-'Debt Schedules'!I14 -> -69.958187 | J26: =-'Debt Schedules'!J14 -> -77.272682 | K26: =-'Debt Schedules'!K14 -> -85.907524 | L26: =-'Debt Schedules'!L14 -> -96.20011 | M26: =-'Debt Schedules'!M14 -> -108.58572 | N26: =-'Debt Schedules'!N14 -> -123.62692 | O26: =-'Debt Schedules'!O14 -> -142.05187 | ... Q26: =-'Debt Schedules'!Q14 -> -175.12579
B27: Other Income | C27: ='Revenue BuildUp'!C63 -> 94 | D27: ='Revenue BuildUp'!D63 -> 98 | E27: ='Revenue BuildUp'!E63 -> 144 | F27: ='Revenue BuildUp'!F63 -> 142 | G27: ='Revenue BuildUp'!G63 -> 208 | H27: ='Revenue BuildUp'!H63 -> 167.13921 | I27: ='Revenue BuildUp'!I63 -> 183.46295 | J27: ='Revenue BuildUp'!J63 -> 202.53087 | ... Q27: ='Revenue BuildUp'!Q63 -> 503.28875
B29: Profit before share of profit/ (loss) of associates and tax | C29: =SUM(C23,C26,C27) -> 1512 | D29: =SUM(D23,D26,D27) -> 1601 | E29: =SUM(E23,E26,E27) -> 1743 | F29: =SUM(F23,F26,F27) -> 1937 | G29: =SUM(G23,G26,G27) -> 2116 | H29: =SUM(H23,H26,H27) -> 2230.8209 | I29: =SUM(I23,I26,I27) -> 2429.455 | J29: =SUM(J23,J26,J27) -> 2659.4282 | ... Q29: =SUM(Q23,Q26,Q27) -> 6224.9982
B31: Share in profit/(loss) of associates (net of tax) | C31: ='Income Statement'!C23 -> -2 | D31: ='Income Statement'!D23 -> 0 | E31: ='Income Statement'!E23 -> 0 | F31: ='Income Statement'!F23 -> 0 | G31: ='Income Statement'!G23 -> 0 | H31: ='Income Statement'!H23 -> 0 | I31: ='Income Statement'!I23 -> 0 | J31: ='Income Statement'!J23 -> 0 | ... Q31: ='Income Statement'!Q23 -> 0
B32: Exceptional item | C32: ='Income Statement'!C25 -> 13 | D32: ='Income Statement'!D25 -> 0 | E32: ='Income Statement'!E25 -> 0 | F32: ='Income Statement'!F25 -> 0 | G32: ='Income Statement'!G25 -> 0 | H32: ='Income Statement'!H25 -> 0 | I32: ='Income Statement'!I25 -> 0 | J32: ='Income Statement'!J25 -> 0 | ... Q32: ='Income Statement'!Q25 -> 0
B34: EBT | C34: =SUM(C29:C33) -> 1523 | D34: =SUM(D29:D33) -> 1601 | E34: =SUM(E29:E33) -> 1743 | F34: =SUM(F29:F33) -> 1937 | G34: =SUM(G29:G33) -> 2116 | H34: =SUM(H29:H33) -> 2230.8209 | I34: =SUM(I29:I33) -> 2429.455 | J34: =SUM(J29:J33) -> 2659.4282 | ... Q34: =SUM(Q29:Q33) -> 6224.9982
B35: EBT Margin | C35: =C34/C10 -> 0.18923956 | D35: =D34/D10 -> 0.16831371 | E35: =E34/E10 -> 0.1785129 | F35: =F34/F10 -> 0.20066301 | G35: =G34/G10 -> 0.19536516 | H35: =H34/H10 -> 0.18858184 | I35: =I34/I10 -> 0.18710009 | J35: =J34/J10 -> 0.18552847 | ... Q35: =Q34/Q10 -> 0.17475738
B37: Tax | C37: ='Income Statement'!C28 -> 324 | D37: ='Income Statement'!D28 -> 346 | E37: ='Income Statement'!E28 -> 421 | F37: ='Income Statement'!F28 -> 435 | G37: ='Income Statement'!G28 -> 458 | H37: =H34*'Revenue BuildUp'!H67 -> 495.87166 | I37: =I34*'Revenue BuildUp'!I67 -> 540.02448 | J37: =J34*'Revenue BuildUp'!J67 -> 591.14342 | K37: =K34*'Revenue BuildUp'!K67 -> 650.9658 | L37: =L34*'Revenue BuildUp'!L67 -> 721.74464 | M37: =M34*'Revenue BuildUp'!M67 -> 806.40772 | N37: =N34*'Revenue BuildUp'!N67 -> 908.76586 | O37: =O34*'Revenue BuildUp'!O67 -> 1033.7857 | ... Q37: =Q34*'Revenue BuildUp'!Q67 -> 1383.706
B39: Net Profit | C39: =C34-C37 -> 1199 | D39: =D34-D37 -> 1255 | E39: =E34-E37 -> 1322 | F39: =F34-F37 -> 1502 | G39: =G34-G37 -> 1658 | H39: =H34-H37 -> 1734.9493 | I39: =I34-I37 -> 1889.4306 | J39: =J34-J37 -> 2068.2848 | ... Q39: =Q34-Q37 -> 4841.2923
B40: Net Profit Margin | C40: =C39/C10 -> 0.14898111 | D40: =D39/D10 -> 0.1319386 | E40: =E39/E10 -> 0.13539533 | F40: =F39/F10 -> 0.1555993 | G40: =G39/G10 -> 0.15307912 | H40: =H39/H10 -> 0.14666346 | I40: =I39/I10 -> 0.14551108 | J40: =J39/J10 -> 0.1442888 | ... Q40: =Q39/Q10 -> 0.13591193
B42: EPS in Rs. | C42: =C39/129 -> 9.2945736 | D42: =D39/129 -> 9.7286822 | E42: =E39/129 -> 10.248062 | F42: =F39/129 -> 11.643411 | G42: =G39/129 -> 12.852713 | H42: =H39/129 -> 13.449219 | I42: =I39/129 -> 14.646749 | J42: =J39/129 -> 16.033216 | ... Q42: =Q39/129 -> 37.529397
B44: Dividend | C44: ='Cash Flow '!C64 -> -968 | D44: ='Cash Flow '!D64 -> -1195 | E44: ='Cash Flow '!E64 -> -582 | F44: ='Cash Flow '!F64 -> -1229 | G44: ='Cash Flow '!G64 -> -453 | H44: =H45*-H39 -> -1142.0254 | I44: =I45*-I39 -> -1243.7123 | J44: =J45*-J39 -> -1361.4426 | K44: =K45*-K39 -> -1499.2175 | L44: =L45*-L39 -> -1662.2259 | M44: =M45*-M39 -> -1857.2106 | N44: =N45*-N39 -> -2092.9483 | O44: =O45*-O39 -> -2380.8773 | ... Q44: =Q45*-Q39 -> -3186.7669
B45: Dividend Payout % | C45: =-C44/C39 -> 0.80733945 | D45: =-D44/D39 -> 0.95219124 | E45: =-E44/E39 -> 0.44024206 | F45: =-F44/F39 -> 0.81824234 | G45: =-G44/G39 -> 0.27322075 | H45: =AVERAGE(C45:G45) -> 0.65824717 | I45: =H45 -> 0.65824717 | J45: =I45 -> 0.65824717 | K45: =J45 -> 0.65824717 | L45: =K45 -> 0.65824717 | M45: =L45 -> 0.65824717 | N45: =M45 -> 0.65824717 | O45: =N45 -> 0.65824717 | P45: =O45 -> 0.65824717 | Q45: =P45 -> 0.65824717
B47: Retained Earning | C47: =C39+C44 -> 231 | D47: =D39+D44 -> 60 | E47: =E39+E44 -> 740 | F47: =F39+F44 -> 273 | G47: =G39+G44 -> 1205 | H47: =H39+H44 -> 592.92382 | I47: =I39+I44 -> 645.71825 | J47: =J39+J44 -> 706.8422 | ... Q47: =Q39+Q44 -> 1654.5253
B48: Retained % | C48: =C47/C39 -> 0.19266055 | D48: =D47/D39 -> 0.047808765 | E48: =E47/E39 -> 0.55975794 | F48: =F47/F39 -> 0.18175766 | G48: =G47/G39 -> 0.72677925 | H48: =H47/H39 -> 0.34175283 | I48: =I47/I39 -> 0.34175283 | J48: =J47/J39 -> 0.34175283 | ... Q48: =Q47/Q39 -> 0.34175283

Sheet Balance Sheet
B4: Balance Sheet
B5: All Figure In INR Cr.
B6: Particulars | C6: 2021 | D6: =C6+1 -> 2022 | E6: =D6+1 -> 2023 | F6: =E6+1 -> 2024 | G6: =F6+1 -> 2025 | H6: =G6+1 -> 2026 | I6: =H6+1 -> 2027 | J6: =I6+1 -> 2028 | K6: =J6+1 -> 2029 | ... Q6: =P6+1 -> 2035
B7: Master Check | C7: =IF(SUM(C75:Q75)=0,"OK","Error") -> OK
B8: Balance Sheet
B9: ASSETS
B10: Non-current assets
B11: Property, plant and equipment | C11: 572 | D11: 600 | E11: 633 | F11: 700 | G11: 710 | H11: ='FAS Seechules'!H26 -> 740.95968 | I11: ='FAS Seechules'!I26 -> 767.18738 | J11: ='FAS Seechules'!J26 -> 786.72483 | K11: ='FAS Seechules'!K26 -> 797.14068 | L11: ='FAS Seechules'!L26 -> 795.43184 | M11: ='FAS Seechules'!M26 -> 777.90554 | N11: ='FAS Seechules'!N26 -> 740.03844 | O11: ='FAS Seechules'!O26 -> 676.3083 | ... Q11: ='FAS Seechules'!Q26 -> 442.93257
B12: Capital work-in-progress | C12: 24 | D12: 39 | E12: 67 | F12: 44 | G12: 40 | H12: ='FAS Seechules'!H89 -> 44.8 | I12: ='FAS Seechules'!I89 -> 50.56 | J12: ='FAS Seechules'!J89 -> 57.472 | K12: ='FAS Seechules'!K89 -> 65.7664 | L12: ='FAS Seechules'!L89 -> 75.71968 | M12: ='FAS Seechules'!M89 -> 87.663616 | N12: ='FAS Seechules'!N89 -> 101.99634 | O12: ='FAS Seechules'!O89 -> 119.19561 | ... Q12: ='FAS Seechules'!Q89 -> 164.60167
B13: Right of use assets | C13: 180 | D13: 178 | E13: 175 | F13: 209 | G13: 230 | H13: ='FAS Seechules'!H45 -> 277.32026 | I13: ='FAS Seechules'!I45 -> 333.81101 | J13: ='FAS Seechules'!J45 -> 401.06465 | K13: ='FAS Seechules'!K45 -> 480.8859 | L13: ='FAS Seechules'!L45 -> 575.2953 | M13: ='FAS Seechules'!M45 -> 686.52019 | N13: ='FAS Seechules'!N45 -> 816.96639 | O13: ='FAS Seechules'!O45 -> 969.16144 | ... Q13: ='FAS Seechules'!Q45 -> 1348.8659
B14: Investment properties | C14: 17 | D14: 22 | E14: 16 | F14: 15 | G14: 15 | H14: =G14 -> 15 | I14: =H14 -> 15 | J14: =I14 -> 15 | K14: =J14 -> 15 | L14: =K14 -> 15 | M14: =L14 -> 15 | N14: =M14 -> 15 | O14: =N14 -> 15 | ... Q14: =P14 -> 15
B15: Goodwill | C15: 613 | D15: 654 | E15: 862 | F15: 863 | G15: 857 | H15: =G15 -> 857 | I15: =H15 -> 857 | J15: =I15 -> 857 | K15: =J15 -> 857 | L15: =K15 -> 857 | M15: =L15 -> 857 | N15: =M15 -> 857 | O15: =N15 -> 857 | ... Q15: =P15 -> 857
B16: Other intangible assets | C16: 230 | D16: 306 | E16: 560 | F16: 937 | G16: 946 | H16: ='FAS Seechules'!H64 -> 952.82962 | I16: ='FAS Seechules'!I64 -> 956.60695 | J16: ='FAS Seechules'!J64 -> 956.45323 | K16: ='FAS Seechules'!K64 -> 951.2629 | L16: ='FAS Seechules'!L64 -> 939.64554 | M16: ='FAS Seechules'!M64 -> 919.85295 | N16: ='FAS Seechules'!N64 -> 889.68762 | O16: ='FAS Seechules'!O64 -> 846.38768 | ... Q16: ='FAS Seechules'!Q64 -> 705.61158
B17: Financial assets
B18: (i) Investments | C18: 226 | D18: 187 | E18: 518 | F18: 343 | G18: 215 | H18: ='B_Sheet Forecast'!H9 -> 369.49629 | I18: ='B_Sheet Forecast'!I9 -> 405.58334 | J18: ='B_Sheet Forecast'!J9 -> 447.73696 | K18: ='B_Sheet Forecast'!K9 -> 497.45485 | L18: ='B_Sheet Forecast'!L9 -> 556.66468 | M18: ='B_Sheet Forecast'!M9 -> 627.85287 | N18: ='B_Sheet Forecast'!N9 -> 714.23248 | O18: ='B_Sheet Forecast'!O9 -> 819.9618 | ... Q18: ='B_Sheet Forecast'!Q9 -> 1112.6254
B19: (ii) Loans | C19: 4 | D19: 4 | E19: 4 | F19: 4 | G19: 6 | H19: ='B_Sheet Forecast'!H11 -> 5.431027 | I19: ='B_Sheet Forecast'!I11 -> 5.9614511 | J19: ='B_Sheet Forecast'!J11 -> 6.5810445 | K19: ='B_Sheet Forecast'!K11 -> 7.311821 | L19: ='B_Sheet Forecast'!L11 -> 8.1821143 | M19: ='B_Sheet Forecast'!M11 -> 9.2284713 | N19: ='B_Sheet Forecast'!N11 -> 10.498119 | O19: ='B_Sheet Forecast'!O11 -> 12.052177 | ... Q19: ='B_Sheet Forecast'!Q11 -> 16.353881
B20: (iii) Other financial assets | C20: 41 | D20: 17 | E20: 32 | F20: 100 | G20: 22 | H20: ='B_Sheet Forecast'!H13 -> 53.350087 | I20: ='B_Sheet Forecast'!I13 -> 58.560551 | J20: ='B_Sheet Forecast'!J13 -> 64.646944 | K20: ='B_Sheet Forecast'!K13 -> 71.825511 | L20: ='B_Sheet Forecast'!L13 -> 80.37458 | M20: ='B_Sheet Forecast'!M13 -> 90.653158 | N20: ='B_Sheet Forecast'!N13 -> 103.12516 | O20: ='B_Sheet Forecast'!O13 -> 118.391 | ... Q20: ='B_Sheet Forecast'!Q13 -> 160.64751
B21: Deferred tax assets (net) | C21: 186 | D21: 187 | E21: 146 | F21: 68 | G21: 57 | H21: ='B_Sheet Forecast'!H15 -> 165.68507 | I21: ='B_Sheet Forecast'!I15 -> 181.86679 | J21: ='B_Sheet Forecast'!J15 -> 200.76881 | K21: ='B_Sheet Forecast'!K15 -> 223.06271 | L21: ='B_Sheet Forecast'!L15 -> 249.61286 | M21: ='B_Sheet Forecast'!M15 -> 281.53422 | N21: ='B_Sheet Forecast'!N15 -> 320.26752 | O21: ='B_Sheet Forecast'!O15 -> 367.67739 | ... Q21: ='B_Sheet Forecast'!Q15 -> 498.91005
B22: Non current tax assets (net) | C22: 55 | D22: 57 | E22: 67 | F22: 95 | G22: 108 | H22: ='B_Sheet Forecast'!H17 -> 93.455667 | I22: ='B_Sheet Forecast'!I17 -> 102.58306 | J22: ='B_Sheet Forecast'!J17 -> 113.24486 | K22: ='B_Sheet Forecast'!K17 -> 125.81987 | L22: ='B_Sheet Forecast'!L17 -> 140.79565 | M22: ='B_Sheet Forecast'!M17 -> 158.80108 | N22: ='B_Sheet Forecast'!N17 -> 180.64883 | O22: ='B_Sheet Forecast'!O17 -> 207.39066 | ... Q22: ='B_Sheet Forecast'!Q17 -> 281.41323
B23: Other non-current assets | C23: 26 | D23: 30 | E23: 46 | F23: 40 | G23: 49 | H23: ='B_Sheet Forecast'!H19 -> 46.758421 | I23: ='B_Sheet Forecast'!I19 -> 51.325107 | J23: ='B_Sheet Forecast'!J19 -> 56.659496 | K23: ='B_Sheet Forecast'!K19 -> 62.951115 | L23: ='B_Sheet Forecast'!L19 -> 70.443905 | M23: ='B_Sheet Forecast'!M19 -> 79.452514 | N23: ='B_Sheet Forecast'!N19 -> 90.383541 | O23: ='B_Sheet Forecast'!O19 -> 103.76321 | ... Q23: ='B_Sheet Forecast'!Q19 -> 140.79872
B24: Total non-current assets | C24: =SUM(C11:C23) -> 2174 | D24: =SUM(D11:D23) -> 2281 | E24: =SUM(E11:E23) -> 3126 | F24: =SUM(F11:F23) -> 3418 | G24: =SUM(G11:G23) -> 3255 | H24: =SUM(H11:H23) -> 3622.0861 | I24: =SUM(I11:I23) -> 3786.0456 | J24: =SUM(J11:J23) -> 3963.3528 | ... Q24: =SUM(Q11:Q23) -> 5744.7605
B25: Current assets
B26: Inventories | C26: 1126 | D26: 1412 | E26: 1225 | F26: 1336 | G26: 1235 | H26: ='Working Capital'!H12 -> 1577.3473 | I26: ='Working Capital'!I12 -> 1731.3998 | J26: ='Working Capital'!J12 -> 1911.3499 | K26: ='Working Capital'!K12 -> 2123.5912 | L26: ='Working Capital'!L12 -> 2376.3528 | M26: ='Working Capital'!M12 -> 2680.249 | N26: ='Working Capital'!N12 -> 3048.996 | O26: ='Working Capital'!O12 -> 3500.3452 | ... Q26: ='Working Capital'!Q12 -> 4749.7003
B27: Financial assets
B28: (i) Investments | C28: 628 | D28: 641 | E28: 578 | F28: 259 | G28: 1375 | H28: ='B_Sheet Forecast'!H24 -> 847.93289 | I28: ='B_Sheet Forecast'!I24 -> 930.7467 | J28: ='B_Sheet Forecast'!J24 -> 1027.4823 | K28: ='B_Sheet Forecast'!K24 -> 1141.5766 | L28: ='B_Sheet Forecast'!L24 -> 1277.4534 | M28: ='B_Sheet Forecast'!M24 -> 1440.8185 | N28: ='B_Sheet Forecast'!N24 -> 1639.0454 | O28: ='B_Sheet Forecast'!O24 -> 1881.6768 | ... Q28: ='B_Sheet Forecast'!Q24 -> 2553.2912
B29: (ii) Trade receivables | C29: 388 | D29: 652 | E29: 1015 | F29: 1069 | G29: 1271 | H29: ='Working Capital'!H13 -> 1061.8125 | I29: ='Working Capital'!I13 -> 1165.515 | J29: ='Working Capital'!J13 -> 1286.6508 | K29: ='Working Capital'!K13 -> 1429.5239 | L29: ='Working Capital'!L13 -> 1599.6738 | M29: ='Working Capital'!M13 -> 1804.2456 | N29: ='Working Capital'!N13 -> 2052.4725 | O29: ='Working Capital'!O13 -> 2356.3043 | ... Q29: ='Working Capital'!Q13 -> 3197.3244
B30: (iii) Cash and cash equivalents | C30: 109 | D30: 276 | E30: 207 | F30: 228 | G30: 321 | H30: ='Cash Flow '!H70 -> 587.50131 | I30: ='Cash Flow '!I70 -> 1050.3777 | J30: ='Cash Flow '!J70 -> 1557.8561 | K30: ='Cash Flow '!K70 -> 2118.0857 | L30: ='Cash Flow '!L70 -> 2741.4249 | M30: ='Cash Flow '!M70 -> 3441.1158 | N30: ='Cash Flow '!N70 -> 4234.1683 | O30: ='Cash Flow '!O70 -> 5142.5199 | ... Q30: ='Cash Flow '!Q70 -> 7431.8919
B31: (iv) Bank balances other than (iii) above | C31: 835 | D31: 303 | E31: 549 | F31: 715 | G31: 456 | H31: 456 | I31: 456 | J31: 456 | K31: 456 | L31: 456 | M31: 456 | N31: 456 | O31: 456 | P31: 456 | Q31: 456
B32: (v) Loans | C32: 6 | D32: 5 | E32: 4 | F32: 6 | G32: 7 | H32: ='B_Sheet Forecast'!H26 -> 6.9763241 | I32: ='B_Sheet Forecast'!I26 -> 7.6576705 | J32: ='B_Sheet Forecast'!J26 -> 8.4535576 | K32: ='B_Sheet Forecast'!K26 -> 9.3922629 | L32: ='B_Sheet Forecast'!L26 -> 10.510182 | M32: ='B_Sheet Forecast'!M26 -> 11.85426 | N32: ='B_Sheet Forecast'!N26 -> 13.485162 | O32: ='B_Sheet Forecast'!O26 -> 15.481399 | ... Q32: ='B_Sheet Forecast'!Q26 -> 21.007072
B33: (vi) Other financial assets | C33: 5 | D33: 2 | E33: 4 | F33: 5 | G33: 3 | H33: ='B_Sheet Forecast'!H28 -> 4.8173283 | I33: ='B_Sheet Forecast'!I28 -> 5.2878152 | J33: ='B_Sheet Forecast'!J28 -> 5.8373954 | K33: ='B_Sheet Forecast'!K28 -> 6.4855952 | L33: ='B_Sheet Forecast'!L28 -> 7.2575465 | M33: ='B_Sheet Forecast'!M28 -> 8.1856666 | N33: ='B_Sheet Forecast'!N28 -> 9.3118455 | O33: ='B_Sheet Forecast'!O28 -> 10.690297 | ... Q33: ='B_Sheet Forecast'!Q28 -> 14.505915
B34: Current tax asset (net) | C34: 1 | D34: 1 | E34: 2 | F34: 2 | G34: 2 | H34: ='B_Sheet Forecast'!H30 -> 1.9543768 | I34: ='B_Sheet Forecast'!I30 -> 2.145252 | J34: ='B_Sheet Forecast'!J30 -> 2.3682152 | K34: ='B_Sheet Forecast'!K30 -> 2.6311881 | L34: ='B_Sheet Forecast'!L30 -> 2.9443666 | M34: ='B_Sheet Forecast'!M30 -> 3.3209023 | N34: ='B_Sheet Forecast'!N30 -> 3.77779 | O34: ='B_Sheet Forecast'!O30 -> 4.3370241 | ... Q34: ='B_Sheet Forecast'!Q30 -> 5.8850095
B35: Other current assets | C35: 224 | D35: 213 | E35: 229 | F35: 378 | G35: 413 | H35: ='B_Sheet Forecast'!H32 -> 357.17717 | I35: ='B_Sheet Forecast'!I32 -> 392.06106 | J35: ='B_Sheet Forecast'!J32 -> 432.80927 | K35: ='B_Sheet Forecast'!K32 -> 480.86955 | L35: ='B_Sheet Forecast'!L32 -> 538.1053 | M35: ='B_Sheet Forecast'!M32 -> 606.92006 | N35: ='B_Sheet Forecast'!N32 -> 690.41975 | O35: ='B_Sheet Forecast'!O32 -> 792.62402 | ... Q35: ='B_Sheet Forecast'!Q32 -> 1075.5301
B36: Assets classified as held for sale | C36: 14 | D36: 0 | E36: 7 | F36: 5 | H36: ='B_Sheet Forecast'!H34 -> 7.0372394 | I36: ='B_Sheet Forecast'!I34 -> 7.7245352 | J36: ='B_Sheet Forecast'!J34 -> 8.5273718 | K36: ='B_Sheet Forecast'!K34 -> 9.4742736 | L36: ='B_Sheet Forecast'!L34 -> 10.601954 | M36: ='B_Sheet Forecast'!M34 -> 11.957768 | N36: ='B_Sheet Forecast'!N34 -> 13.602911 | O36: ='B_Sheet Forecast'!O34 -> 15.616578 | ... Q36: ='B_Sheet Forecast'!Q34 -> 21.1905
B37: Total current assets | C37: =SUM(C26:C36) -> 3336 | D37: =SUM(D26:D36) -> 3505 | E37: =SUM(E26:E36) -> 3820 | F37: =SUM(F26:F36) -> 4003 | G37: =SUM(G26:G36) -> 5083 | H37: =SUM(H26:H36) -> 4908.5564 | I37: =SUM(I26:I36) -> 5748.9155 | J37: =SUM(J26:J36) -> 6697.335 | ... Q37: =SUM(Q26:Q36) -> 19526.326
B38: Total assets | C38: =C24+C37 -> 5510 | D38: =D24+D37 -> 5786 | E38: =E24+E37 -> 6946 | F38: =F24+F37 -> 7421 | G38: =G24+G37 -> 8338 | H38: =H24+H37 -> 8530.6426 | I38: =I24+I37 -> 9534.9612 | J38: =J24+J37 -> 10660.688 | ... Q38: =Q24+Q37 -> 25271.087
B39: EQUITY AND LIABILITIES
B40: Equity
B41: Equity share capital | C41: 129 | D41: 129 | E41: 129 | F41: 129 | G41: 129 | H41: =G41 -> 129 | I41: =H41 -> 129 | J41: =I41 -> 129 | K41: =J41 -> 129 | L41: =K41 -> 129 | M41: =L41 -> 129 | N41: =M41 -> 129 | O41: =N41 -> 129 | ... Q41: =P41 -> 129
B42: Other equity
B43: Reserves and surplus | C43: 3111 | D43: 3189 | E43: 3674 | F43: 3782 | G43: 3997 | H43: =G43+'P&L Statement '!H39+'P&L Statement '!H44 -> 4589.9238 | I43: =H43+'P&L Statement '!I39+'P&L Statement '!I44 -> 5235.6421 | J43: =I43+'P&L Statement '!J39+'P&L Statement '!J44 -> 5942.4843 | K43: =J43+'P&L Statement '!K39+'P&L Statement '!K44 -> 6720.8573 | L43: =K43+'P&L Statement '!L39+'P&L Statement '!L44 -> 7583.862 | M43: =L43+'P&L Statement '!M39+'P&L Statement '!M44 -> 8548.1001 | N43: =M43+'P&L Statement '!N39+'P&L Statement '!N44 -> 9634.7299 | O43: =N43+'P&L Statement '!O39+'P&L Statement '!O44 -> 10870.849 | ... Q43: =P43+'P&L Statement '!Q39+'P&L Statement '!Q44 -> 13945.826
B44: Other reserves | C44: 0 | D44: 30 | E44: -4 | F44: -79 | G44: -152 | H44: =G44 -> -152 | I44: =H44 -> -152 | J44: =I44 -> -152 | K44: =J44 -> -152 | L44: =K44 -> -152 | M44: =L44 -> -152 | N44: =M44 -> -152 | O44: =N44 -> -152 | ... Q44: =P44 -> -152
B45: Share application money pending allotment | G45: 1 | H45: =G45 -> 1 | I45: =H45 -> 1 | J45: =I45 -> 1 | K45: =J45 -> 1 | L45: =K45 -> 1 | M45: =L45 -> 1 | N45: =M45 -> 1 | O45: =N45 -> 1 | ... Q45: =P45 -> 1
B46: Equity attributable to owners | C46: =SUM(C41:C45) -> 3240 | D46: =SUM(D41:D45) -> 3348 | E46: =SUM(E41:E45) -> 3799 | F46: =SUM(F41:F45) -> 3832 | G46: =SUM(G41:G45) -> 3975 | H46: =SUM(H41:H45) -> 4567.9238 | I46: =SUM(I41:I45) -> 5213.6421 | J46: =SUM(J41:J45) -> 5920.4843 | ... Q46: =SUM(Q41:Q45) -> 13923.826
B47: Non-controlling interests | C47: 18 | D47: 57 | E47: 157 | F47: 337 | G47: 291 | H47: 291 | I47: 291 | J47: 291 | K47: 291 | L47: 291 | M47: 291 | N47: 291 | O47: 291 | P47: 291 | Q47: 291
B48: Total equity | C48: =SUM(C46:C47) -> 3258 | D48: =SUM(D46:D47) -> 3405 | E48: =SUM(E46:E47) -> 3956 | F48: =SUM(F46:F47) -> 4169 | G48: =SUM(G46:G47) -> 4266 | H48: =SUM(H46:H47) -> 4858.9238 | I48: =SUM(I46:I47) -> 5504.6421 | J48: =SUM(J46:J47) -> 6211.4843 | ... Q48: =SUM(Q46:Q47) -> 14214.826
B49: Liabilities
B50: Non-current liabilities
B51: Financial liabilities
B52: i) Borrowings | C52: 8 | E52: 2 | H52: ='B_Sheet Forecast'!H39 -> 2.8363961 | I52: ='B_Sheet Forecast'!I39 -> 3.1134143 | J52: ='B_Sheet Forecast'!J39 -> 3.4370017 | K52: ='B_Sheet Forecast'!K39 -> 3.8186555 | L52: ='B_Sheet Forecast'!L39 -> 4.2731729 | M52: ='B_Sheet Forecast'!M39 -> 4.819641 | N52: ='B_Sheet Forecast'!N39 -> 5.4827242 | O52: ='B_Sheet Forecast'!O39 -> 6.2943433 | ... Q52: ='B_Sheet Forecast'!Q39 -> 8.5409416
B53: ii) Lease liabilities | C53: 122 | D53: 91 | E53: 91 | F53: 104 | G53: 124 | H53: ='B_Sheet Forecast'!H41 -> 133.12477 | I53: ='B_Sheet Forecast'!I41 -> 146.12647 | J53: ='B_Sheet Forecast'!J41 -> 161.31388 | K53: ='B_Sheet Forecast'!K41 -> 179.2266 | L53: ='B_Sheet Forecast'!L41 -> 200.55914 | M53: ='B_Sheet Forecast'!M41 -> 226.20734 | N53: ='B_Sheet Forecast'!N41 -> 257.3288 | O53: ='B_Sheet Forecast'!O41 -> 295.42172 | ... Q53: ='B_Sheet Forecast'!Q41 -> 400.86464
B54: iii) Other financial liabilities | E54: 266 | F54: 405 | G54: 1211 | H54: ='B_Sheet Forecast'!H43 -> 428.24412 | I54: ='B_Sheet Forecast'!I43 -> 470.06881 | J54: ='B_Sheet Forecast'!J43 -> 518.92462 | K54: ='B_Sheet Forecast'!K43 -> 576.54737 | L54: ='B_Sheet Forecast'!L43 -> 645.17123 | M54: ='B_Sheet Forecast'!M43 -> 727.67795 | N54: ='B_Sheet Forecast'!N43 -> 827.79142 | O54: ='B_Sheet Forecast'!O43 -> 950.33111 | ... Q54: ='B_Sheet Forecast'!Q43 -> 1289.5265
B55: Provisions | C55: 1 | D55: 1 | E55: 4 | F55: 1 | G55: 1 | H55: ='B_Sheet Forecast'!H45 -> 1.9754611 | I55: ='B_Sheet Forecast'!I45 -> 2.1683955 | J55: ='B_Sheet Forecast'!J45 -> 2.3937641 | K55: ='B_Sheet Forecast'!K45 -> 2.6595739 | L55: ='B_Sheet Forecast'!L45 -> 2.9761311 | M55: ='B_Sheet Forecast'!M45 -> 3.356729 | N55: ='B_Sheet Forecast'!N45 -> 3.8185457 | O55: ='B_Sheet Forecast'!O45 -> 4.383813 | ... Q55: ='B_Sheet Forecast'!Q45 -> 5.9484984
B56: Employee benefit obligations (net) | C56: 24 | D56: 27 | E56: 20 | F56: 19 | G56: 27 | H56: ='B_Sheet Forecast'!H47 -> 29.171709 | I56: ='B_Sheet Forecast'!I47 -> 32.02078 | J56: ='B_Sheet Forecast'!J47 -> 35.348806 | K56: ='B_Sheet Forecast'!K47 -> 39.274031 | L56: ='B_Sheet Forecast'!L47 -> 43.948642 | M56: ='B_Sheet Forecast'!M47 -> 49.568946 | N56: ='B_Sheet Forecast'!N47 -> 56.388611 | O56: ='B_Sheet Forecast'!O47 -> 64.735935 | ... Q56: ='B_Sheet Forecast'!Q47 -> 87.841704
B57: Deferred tax liabilities (net) | C57: 84 | D57: 109 | E57: 178 | F57: 279 | G57: 248 | H57: ='B_Sheet Forecast'!H49 -> 217.48929 | I57: ='B_Sheet Forecast'!I49 -> 238.7305 | J57: ='B_Sheet Forecast'!J49 -> 263.54255 | K57: ='B_Sheet Forecast'!K49 -> 292.80701 | L57: ='B_Sheet Forecast'!L49 -> 327.65852 | M57: ='B_Sheet Forecast'!M49 -> 369.56062 | N57: ='B_Sheet Forecast'!N49 -> 420.40454 | O57: ='B_Sheet Forecast'!O49 -> 482.6379 | ... Q57: ='B_Sheet Forecast'!Q49 -> 654.90265
B58: Total non-current liabilities | C58: =SUM(C52:C57) -> 239 | D58: =SUM(D52:D57) -> 228 | E58: =SUM(E52:E57) -> 561 | F58: =SUM(F52:F57) -> 808 | G58: =SUM(G52:G57) -> 1611 | H58: =SUM(H52:H57) -> 812.84175 | I58: =SUM(I52:I57) -> 892.22837 | J58: =SUM(J52:J57) -> 984.96062 | ... Q58: =SUM(Q52:Q57) -> 2447.625
B59: Current liabilities
B60: Financial liabilities
B61: (i) Borrowings | C61: 340 | D61: 345 | E61: 473 | F61: 383 | G61: 379 | H61: ='B_Sheet Forecast'!H54 -> 477.03163 | I61: ='B_Sheet Forecast'!I54 -> 523.62117 | J61: ='B_Sheet Forecast'!J54 -> 578.04286 | K61: ='B_Sheet Forecast'!K54 -> 642.23026 | L61: ='B_Sheet Forecast'!L54 -> 718.67205 | M61: ='B_Sheet Forecast'!M54 -> 810.57831 | N61: ='B_Sheet Forecast'!N54 -> 922.09717 | O61: ='B_Sheet Forecast'!O54 -> 1058.5971 | ... Q61: ='B_Sheet Forecast'!Q54 -> 1436.4352
B62: (ii) Lease liabilities | C62: 38 | D62: 43 | E62: 42 | F62: 41 | G62: 51 | H62: ='B_Sheet Forecast'!H56 -> 53.232281 | I62: ='B_Sheet Forecast'!I56 -> 58.43124 | J62: ='B_Sheet Forecast'!J56 -> 64.504193 | K62: ='B_Sheet Forecast'!K56 -> 71.666909 | L62: ='B_Sheet Forecast'!L56 -> 80.1971 | M62: ='B_Sheet Forecast'!M56 -> 90.452981 | N62: ='B_Sheet Forecast'!N56 -> 102.89745 | O62: ='B_Sheet Forecast'!O56 -> 118.12957 | ... Q62: ='B_Sheet Forecast'!Q56 -> 160.29278
B63: (iii) Trade payables
B64: Total outstanding dues of micro enterprises and small enterprises | C64: 50 | D64: 76 | E64: 68 | F64: 71 | G64: 89
B65: Total outstanding dues of creditors other than micro enterprises and small enterprises | C65: 1084 | D65: 1268 | E65: 1384 | F65: 1510 | G65: 1274 | H65: ='Working Capital'!H14 -> 1711.1604 | I65: ='Working Capital'!I14 -> 1878.2818 | J65: ='Working Capital'!J14 -> 2073.4979 | K65: ='Working Capital'!K14 -> 2303.7446 | L65: ='Working Capital'!L14 -> 2577.949 | M65: ='Working Capital'!M14 -> 2907.626 | N65: ='Working Capital'!N14 -> 3307.6553 | O65: ='Working Capital'!O14 -> 3797.2945 | ... Q65: ='Working Capital'!Q14 -> 5152.6377
B66: (iv) Other financial liabilities | C66: 44 | D66: 45 | E66: 40 | F66: 59 | G66: 231 | H66: ='B_Sheet Forecast'!H58 -> 98.739313 | I66: ='B_Sheet Forecast'!I58 -> 108.38274 | J66: ='B_Sheet Forecast'!J58 -> 119.64732 | K66: ='B_Sheet Forecast'!K58 -> 132.93327 | L66: ='B_Sheet Forecast'!L58 -> 148.75572 | M66: ='B_Sheet Forecast'!M58 -> 167.77912 | N66: ='B_Sheet Forecast'!N58 -> 190.86207 | O66: ='B_Sheet Forecast'!O58 -> 219.11577 | ... Q66: ='B_Sheet Forecast'!Q58 -> 297.32332
B67: Other current liabilities | C67: 287 | D67: 224 | E67: 217 | F67: 211 | G67: 232 | H67: ='B_Sheet Forecast'!H60 -> 295.05796 | I67: ='B_Sheet Forecast'!I60 -> 323.87495 | J67: ='B_Sheet Forecast'!J60 -> 357.53635 | K67: ='B_Sheet Forecast'!K60 -> 397.23813 | L67: ='B_Sheet Forecast'!L60 -> 444.5196 | M67: ='B_Sheet Forecast'!M60 -> 501.3663 | N67: ='B_Sheet Forecast'!N60 -> 570.34396 | O67: ='B_Sheet Forecast'!O60 -> 654.77317 | ... Q67: ='B_Sheet Forecast'!Q60 -> 888.47703
B68: Provisions | C68: 20 | D68: 21 | E68: 44 | F68: 7 | G68: 21 | H68: ='B_Sheet Forecast'!H62 -> 28.06709 | I68: ='B_Sheet Forecast'!I62 -> 30.808278 | J68: ='B_Sheet Forecast'!J62 -> 34.010284 | K68: ='B_Sheet Forecast'!K62 -> 37.786876 | L68: ='B_Sheet Forecast'!L62 -> 42.284478 | M68: ='B_Sheet Forecast'!M62 -> 47.691963 | N68: ='B_Sheet Forecast'!N62 -> 54.253394 | O68: ='B_Sheet Forecast'!O62 -> 62.284637 | ... Q68: ='B_Sheet Forecast'!Q62 -> 84.51548
B69: Employee benefit obligations (net) | C69: 78 | D69: 64 | E69: 74 | F69: 79 | G69: 92 | H69: ='B_Sheet Forecast'!H64 -> 96.237785 | I69: ='B_Sheet Forecast'!I64 -> 105.6369 | J69: ='B_Sheet Forecast'!J64 -> 116.61609 | K69: ='B_Sheet Forecast'!K64 -> 129.56545 | L69: ='B_Sheet Forecast'!L64 -> 144.98705 | M69: ='B_Sheet Forecast'!M64 -> 163.52849 | N69: ='B_Sheet Forecast'!N64 -> 186.02664 | O69: ='B_Sheet Forecast'!O64 -> 213.56455 | ... Q69: ='B_Sheet Forecast'!Q64 -> 289.79073
B70: Current tax liabilities (net) | C70: 72 | D70: 67 | E70: 87 | F70: 83 | G70: 92 | H70: ='B_Sheet Forecast'!H66 -> 99.350505 | I70: ='B_Sheet Forecast'!I66 -> 109.05362 | J70: ='B_Sheet Forecast'!J66 -> 120.38793 | K70: ='B_Sheet Forecast'!K66 -> 133.75612 | L70: ='B_Sheet Forecast'!L66 -> 149.67652 | M70: ='B_Sheet Forecast'!M66 -> 168.81766 | N70: ='B_Sheet Forecast'!N66 -> 192.04349 | O70: ='B_Sheet Forecast'!O66 -> 220.47209 | ... Q70: ='B_Sheet Forecast'!Q66 -> 299.16374
B71: Total current liabilities | C71: =SUM(C61:C70) -> 2013 | D71: =SUM(D61:D70) -> 2153 | E71: =SUM(E61:E70) -> 2429 | F71: =SUM(F61:F70) -> 2444 | G71: =SUM(G61:G70) -> 2461 | H71: =SUM(H61:H70) -> 2858.877 | I71: =SUM(I61:I70) -> 3138.0907 | J71: =SUM(J61:J70) -> 3464.2429 | ... Q71: =SUM(Q61:Q70) -> 8608.636
B72: Total liabilities | C72: =C58+C71 -> 2252 | D72: =D58+D71 -> 2381 | E72: =E58+E71 -> 2990 | F72: =F58+F71 -> 3252 | G72: =G58+G71 -> 4072 | H72: =H58+H71 -> 3671.7187 | I72: =I58+I71 -> 4030.3191 | J72: =J58+J71 -> 4449.2036 | ... Q72: =Q58+Q71 -> 11056.261
B73: Total equity and liabilities | C73: =C72+C48 -> 5510 | D73: =D72+D48 -> 5786 | E73: =E72+E48 -> 6946 | F73: =F72+F48 -> 7421 | G73: =G72+G48 -> 8338 | H73: =H72+H48 -> 8530.6426 | I73: =I72+I48 -> 9534.9612 | J73: =J72+J48 -> 10660.688 | ... Q73: =Q72+Q48 -> 25271.087
B75: Check | C75: =ROUND(C73,0)-ROUND(C38,0) -> 0 | D75: =ROUND(D73,0)-ROUND(D38,0) -> 0 | E75: =ROUND(E73,0)-ROUND(E38,0) -> 0 | F75: =ROUND(F73,0)-ROUND(F38,0) -> 0 | G75: =ROUND(G73,0)-ROUND(G38,0) -> 0 | H75: =ROUND(H73,0)-ROUND(H38,0) -> 0 | I75: =ROUND(I73,0)-ROUND(I38,0) -> 0 | J75: =ROUND(J73,0)-ROUND(J38,0) -> 0 | ... Q75: =ROUND(Q73,0)-ROUND(Q38,0) -> 0
BJ179: Q

Sheet Common Size Statement
B4: Common Size Statement
B5: All Figure In INR Cr.
B6: Particulars | C6: 2021 | D6: =C6+1 -> 2022 | E6: =D6+1 -> 2023 | F6: =E6+1 -> 2024 | G6: =F6+1 -> 2025 | H6: =G6+1 -> 2026 | I6: =H6+1 -> 2027 | J6: =I6+1 -> 2028 | K6: =J6+1 -> 2029 | ... Q6: =P6+1 -> 2035
B7: Income Statement
B8: Revenue | C8: ='P&L Statement '!C10/'P&L Statement '!C$10 -> 1 | D8: ='P&L Statement '!D10/'P&L Statement '!D$10 -> 1 | E8: ='P&L Statement '!E10/'P&L Statement '!E$10 -> 1 | F8: ='P&L Statement '!F10/'P&L Statement '!F$10 -> 1 | G8: ='P&L Statement '!G10/'P&L Statement '!G$10 -> 1 | H8: ='P&L Statement '!H10/'P&L Statement '!H$10 -> 1 | I8: ='P&L Statement '!I10/'P&L Statement '!I$10 -> 1 | J8: ='P&L Statement '!J10/'P&L Statement '!J$10 -> 1 | ... Q8: ='P&L Statement '!Q10/'P&L Statement '!Q$10 -> 1
B9: COGS | C9: =-'P&L Statement '!C11/'P&L Statement '!C$10 -> 0.5305666 | D9: =-'P&L Statement '!D11/'P&L Statement '!D$10 -> 0.57148865 | E9: =-'P&L Statement '!E11/'P&L Statement '!E$10 -> 0.54803359 | F9: =-'P&L Statement '!F11/'P&L Statement '!F$10 -> 0.49186781 | G9: =-'P&L Statement '!G11/'P&L Statement '!G$10 -> 0.49746099 | H9: =-'P&L Statement '!H11/'P&L Statement '!H$10 -> 0.52788353 | I9: =-'P&L Statement '!I11/'P&L Statement '!I$10 -> 0.52788353 | J9: =-'P&L Statement '!J11/'P&L Statement '!J$10 -> 0.52788353 | ... Q9: =-'P&L Statement '!Q11/'P&L Statement '!Q$10 -> 0.52788353
B10: Gross Profit | C10: ='P&L Statement '!C12/'P&L Statement '!C$10 -> 0.4694334 | D10: ='P&L Statement '!D12/'P&L Statement '!D$10 -> 0.42851135 | E10: ='P&L Statement '!E12/'P&L Statement '!E$10 -> 0.45196641 | F10: ='P&L Statement '!F12/'P&L Statement '!F$10 -> 0.50813219 | G10: ='P&L Statement '!G12/'P&L Statement '!G$10 -> 0.50253901 | H10: ='P&L Statement '!H12/'P&L Statement '!H$10 -> 0.47211647 | I10: ='P&L Statement '!I12/'P&L Statement '!I$10 -> 0.47211647 | J10: ='P&L Statement '!J12/'P&L Statement '!J$10 -> 0.47211647 | ... Q10: ='P&L Statement '!Q12/'P&L Statement '!Q$10 -> 0.47211647
B12: Salaries & Benefits | C12: =-'P&L Statement '!C15/'P&L Statement '!C$10 -> 0.07082505 | D12: =-'P&L Statement '!D15/'P&L Statement '!D$10 -> 0.061606392 | E12: =-'P&L Statement '!E15/'P&L Statement '!E$10 -> 0.066878329 | F12: =-'P&L Statement '!F15/'P&L Statement '!F$10 -> 0.07697089 | G12: =-'P&L Statement '!G15/'P&L Statement '!G$10 -> 0.076724218 | H12: =-'P&L Statement '!H15/'P&L Statement '!H$10 -> 0.070600976 | I12: =-'P&L Statement '!I15/'P&L Statement '!I$10 -> 0.070600976 | J12: =-'P&L Statement '!J15/'P&L Statement '!J$10 -> 0.070600976 | ... Q12: =-'P&L Statement '!Q15/'P&L Statement '!Q$10 -> 0.070600976
B13: S&G Expenses | C13: =-'P&L Statement '!C16/'P&L Statement '!C$10 -> 0.20091948 | D13: =-'P&L Statement '!D16/'P&L Statement '!D$10 -> 0.19018082 | E13: =-'P&L Statement '!E16/'P&L Statement '!E$10 -> 0.19971323 | F13: =-'P&L Statement '!F16/'P&L Statement '!F$10 -> 0.22127836 | G13: =-'P&L Statement '!G16/'P&L Statement '!G$10 -> 0.2283261 | H13: =-'P&L Statement '!H16/'P&L Statement '!H$10 -> 0.2080836 | I13: =-'P&L Statement '!I16/'P&L Statement '!I$10 -> 0.2080836 | J13: =-'P&L Statement '!J16/'P&L Statement '!J$10 -> 0.2080836 | ... Q13: =-'P&L Statement '!Q16/'P&L Statement '!Q$10 -> 0.2080836
B15: EBITDA | C15: ='P&L Statement '!C18/'P&L Statement '!C$10 -> 0.19768887 | D15: ='P&L Statement '!D18/'P&L Statement '!D$10 -> 0.17672414 | E15: ='P&L Statement '!E18/'P&L Statement '!E$10 -> 0.18537485 | F15: ='P&L Statement '!F18/'P&L Statement '!F$10 -> 0.20988294 | G15: ='P&L Statement '!G18/'P&L Statement '!G$10 -> 0.19748869 | H15: ='P&L Statement '!H18/'P&L Statement '!H$10 -> 0.1934319 | I15: ='P&L Statement '!I18/'P&L Statement '!I$10 -> 0.1934319 | J15: ='P&L Statement '!J18/'P&L Statement '!J$10 -> 0.1934319 | ... Q15: ='P&L Statement '!Q18/'P&L Statement '!Q$10 -> 0.1934319
B16: Dep & Amortization | C16: =-'P&L Statement '!C21/'P&L Statement '!C$10 -> 0.017271372 | D16: =-'P&L Statement '!D21/'P&L Statement '!D$10 -> 0.01461312 | E16: =-'P&L Statement '!E21/'P&L Statement '!E$10 -> 0.015874642 | F16: =-'P&L Statement '!F21/'P&L Statement '!F$10 -> 0.016367969 | G16: =-'P&L Statement '!G21/'P&L Statement '!G$10 -> 0.016434309 | H16: =-'P&L Statement '!H21/'P&L Statement '!H$10 -> 0.013594097 | I16: =-'P&L Statement '!I21/'P&L Statement '!I$10 -> 0.015073169 | J16: =-'P&L Statement '!J21/'P&L Statement '!J$10 -> 0.016641755 | ... Q16: =-'P&L Statement '!Q21/'P&L Statement '!Q$10 -> 0.027887195
B18: EBIT | C18: ='P&L Statement '!C23/'P&L Statement '!C$10 -> 0.1804175 | D18: ='P&L Statement '!D23/'P&L Statement '!D$10 -> 0.16211102 | E18: ='P&L Statement '!E23/'P&L Statement '!E$10 -> 0.1695002 | F18: ='P&L Statement '!F23/'P&L Statement '!F$10 -> 0.19351497 | G18: ='P&L Statement '!G23/'P&L Statement '!G$10 -> 0.18105438 | H18: ='P&L Statement '!H23/'P&L Statement '!H$10 -> 0.1798378 | I18: ='P&L Statement '!I23/'P&L Statement '!I$10 -> 0.17835873 | J18: ='P&L Statement '!J23/'P&L Statement '!J$10 -> 0.17679014 | ... Q18: ='P&L Statement '!Q23/'P&L Statement '!Q$10 -> 0.1655447
B20: Interest Cost | C20: =-'P&L Statement '!C26/'P&L Statement '!C$10 -> 0.0042246521 | D20: =-'P&L Statement '!D26/'P&L Statement '!D$10 -> 0.0041000841 | E20: =-'P&L Statement '!E26/'P&L Statement '!E$10 -> 0.0057353544 | F20: =-'P&L Statement '!F26/'P&L Statement '!F$10 -> 0.0075624158 | G20: =-'P&L Statement '!G26/'P&L Statement '!G$10 -> 0.0048933616 | H20: =-'P&L Statement '!H26/'P&L Statement '!H$10 -> 0.0053850274 | I20: =-'P&L Statement '!I26/'P&L Statement '!I$10 -> 0.0053877034 | J20: =-'P&L Statement '!J26/'P&L Statement '!J$10 -> 0.0053907386 | ... Q20: =-'P&L Statement '!Q26/'P&L Statement '!Q$10 -> 0.0049163909
B21: Other Income | C21: ='P&L Statement '!C27/'P&L Statement '!C$10 -> 0.01167992 | D21: ='P&L Statement '!D27/'P&L Statement '!D$10 -> 0.010302775 | E21: ='P&L Statement '!E27/'P&L Statement '!E$10 -> 0.014748054 | F21: ='P&L Statement '!F27/'P&L Statement '!F$10 -> 0.014710453 | G21: ='P&L Statement '!G27/'P&L Statement '!G$10 -> 0.019204136 | H21: ='P&L Statement '!H27/'P&L Statement '!H$10 -> 0.014129068 | I21: ='P&L Statement '!I27/'P&L Statement '!I$10 -> 0.014129068 | J21: ='P&L Statement '!J27/'P&L Statement '!J$10 -> 0.014129068 | ... Q21: ='P&L Statement '!Q27/'P&L Statement '!Q$10 -> 0.014129068
B23: Profit before share of profit/ (loss) of associates and tax | C23: ='P&L Statement '!C29/'P&L Statement '!C$10 -> 0.18787276 | D23: ='P&L Statement '!D29/'P&L Statement '!D$10 -> 0.16831371 | E23: ='P&L Statement '!E29/'P&L Statement '!E$10 -> 0.1785129 | F23: ='P&L Statement '!F29/'P&L Statement '!F$10 -> 0.20066301 | G23: ='P&L Statement '!G29/'P&L Statement '!G$10 -> 0.19536516 | H23: ='P&L Statement '!H29/'P&L Statement '!H$10 -> 0.18858184 | I23: ='P&L Statement '!I29/'P&L Statement '!I$10 -> 0.18710009 | J23: ='P&L Statement '!J29/'P&L Statement '!J$10 -> 0.18552847 | ... Q23: ='P&L Statement '!Q29/'P&L Statement '!Q$10 -> 0.17475738
B24: Share in profit/(loss) of associates (net of tax) | C24: ='P&L Statement '!C31/'P&L Statement '!C$10 -> -0.00024850895 | D24: ='P&L Statement '!D31/'P&L Statement '!D$10 -> 0 | E24: ='P&L Statement '!E31/'P&L Statement '!E$10 -> 0 | F24: ='P&L Statement '!F31/'P&L Statement '!F$10 -> 0 | G24: ='P&L Statement '!G31/'P&L Statement '!G$10 -> 0 | H24: ='P&L Statement '!H31/'P&L Statement '!H$10 -> 0 | I24: ='P&L Statement '!I31/'P&L Statement '!I$10 -> 0 | J24: ='P&L Statement '!J31/'P&L Statement '!J$10 -> 0 | ... Q24: ='P&L Statement '!Q31/'P&L Statement '!Q$10 -> 0
B25: Exceptional item | C25: ='P&L Statement '!C32/'P&L Statement '!C$10 -> 0.0016153082 | D25: ='P&L Statement '!D32/'P&L Statement '!D$10 -> 0 | E25: ='P&L Statement '!E32/'P&L Statement '!E$10 -> 0 | F25: ='P&L Statement '!F32/'P&L Statement '!F$10 -> 0 | G25: ='P&L Statement '!G32/'P&L Statement '!G$10 -> 0 | H25: ='P&L Statement '!H32/'P&L Statement '!H$10 -> 0 | I25: ='P&L Statement '!I32/'P&L Statement '!I$10 -> 0 | J25: ='P&L Statement '!J32/'P&L Statement '!J$10 -> 0 | ... Q25: ='P&L Statement '!Q32/'P&L Statement '!Q$10 -> 0
B27: EBT | C27: ='P&L Statement '!C34/'P&L Statement '!C$10 -> 0.18923956 | D27: ='P&L Statement '!D34/'P&L Statement '!D$10 -> 0.16831371 | E27: ='P&L Statement '!E34/'P&L Statement '!E$10 -> 0.1785129 | F27: ='P&L Statement '!F34/'P&L Statement '!F$10 -> 0.20066301 | G27: ='P&L Statement '!G34/'P&L Statement '!G$10 -> 0.19536516 | H27: ='P&L Statement '!H34/'P&L Statement '!H$10 -> 0.18858184 | I27: ='P&L Statement '!I34/'P&L Statement '!I$10 -> 0.18710009 | J27: ='P&L Statement '!J34/'P&L Statement '!J$10 -> 0.18552847 | ... Q27: ='P&L Statement '!Q34/'P&L Statement '!Q$10 -> 0.17475738
B29: Tax | C29: ='P&L Statement '!C37/'P&L Statement '!C$10 -> 0.040258449 | D29: ='P&L Statement '!D37/'P&L Statement '!D$10 -> 0.036375105 | E29: ='P&L Statement '!E37/'P&L Statement '!E$10 -> 0.043117575 | F29: ='P&L Statement '!F37/'P&L Statement '!F$10 -> 0.045063711 | G29: ='P&L Statement '!G37/'P&L Statement '!G$10 -> 0.042286031 | H29: ='P&L Statement '!H37/'P&L Statement '!H$10 -> 0.041918376 | I29: ='P&L Statement '!I37/'P&L Statement '!I$10 -> 0.04158901 | J29: ='P&L Statement '!J37/'P&L Statement '!J$10 -> 0.041239667 | ... Q29: ='P&L Statement '!Q37/'P&L Statement '!Q$10 -> 0.038845445
B31: Net Profit | C31: ='P&L Statement '!C39/'P&L Statement '!C$10 -> 0.14898111 | D31: ='P&L Statement '!D39/'P&L Statement '!D$10 -> 0.1319386 | E31: ='P&L Statement '!E39/'P&L Statement '!E$10 -> 0.13539533 | F31: ='P&L Statement '!F39/'P&L Statement '!F$10 -> 0.1555993 | G31: ='P&L Statement '!G39/'P&L Statement '!G$10 -> 0.15307912 | H31: ='P&L Statement '!H39/'P&L Statement '!H$10 -> 0.14666346 | I31: ='P&L Statement '!I39/'P&L Statement '!I$10 -> 0.14551108 | J31: ='P&L Statement '!J39/'P&L Statement '!J$10 -> 0.1442888 | ... Q31: ='P&L Statement '!Q39/'P&L Statement '!Q$10 -> 0.13591193
B33: Balance Sheet
B34: ASSETS
B35: Non-current assets
B36: Property, plant and equipment | C36: ='Balance Sheet'!C11/'Balance Sheet'!C$38 -> 0.10381125 | D36: ='Balance Sheet'!D11/'Balance Sheet'!D$38 -> 0.10369858 | E36: ='Balance Sheet'!E11/'Balance Sheet'!E$38 -> 0.091131587 | F36: ='Balance Sheet'!F11/'Balance Sheet'!F$38 -> 0.09432691 | G36: ='Balance Sheet'!G11/'Balance Sheet'!G$38 -> 0.085152315 | H36: ='Balance Sheet'!H11/'Balance Sheet'!H$38 -> 0.086858602 | I36: ='Balance Sheet'!I11/'Balance Sheet'!I$38 -> 0.080460462 | J36: ='Balance Sheet'!J11/'Balance Sheet'!J$38 -> 0.073796817 | ... Q36: ='Balance Sheet'!Q11/'Balance Sheet'!Q$38 -> 0.017527246
B37: Capital work-in-progress | C37: ='Balance Sheet'!C12/'Balance Sheet'!C$38 -> 0.0043557169 | D37: ='Balance Sheet'!D12/'Balance Sheet'!D$38 -> 0.0067404079 | E37: ='Balance Sheet'!E12/'Balance Sheet'!E$38 -> 0.0096458393 | F37: ='Balance Sheet'!F12/'Balance Sheet'!F$38 -> 0.0059291201 | G37: ='Balance Sheet'!G12/'Balance Sheet'!G$38 -> 0.0047973135 | H37: ='Balance Sheet'!H12/'Balance Sheet'!H$38 -> 0.005251656 | I37: ='Balance Sheet'!I12/'Balance Sheet'!I$38 -> 0.0053025911 | J37: ='Balance Sheet'!J12/'Balance Sheet'!J$38 -> 0.0053910218 | ... Q37: ='Balance Sheet'!Q12/'Balance Sheet'!Q$38 -> 0.0065134387
B38: Right of use assets | C38: ='Balance Sheet'!C13/'Balance Sheet'!C$38 -> 0.032667877 | D38: ='Balance Sheet'!D13/'Balance Sheet'!D$38 -> 0.030763913 | E38: ='Balance Sheet'!E13/'Balance Sheet'!E$38 -> 0.025194356 | F38: ='Balance Sheet'!F13/'Balance Sheet'!F$38 -> 0.02816332 | G38: ='Balance Sheet'!G13/'Balance Sheet'!G$38 -> 0.027584553 | H38: ='Balance Sheet'!H13/'Balance Sheet'!H$38 -> 0.032508719 | I38: ='Balance Sheet'!I13/'Balance Sheet'!I$38 -> 0.035009163 | J38: ='Balance Sheet'!J13/'Balance Sheet'!J$38 -> 0.037620898 | ... Q38: ='Balance Sheet'!Q13/'Balance Sheet'!Q$38 -> 0.053375858
B39: Investment properties | C39: ='Balance Sheet'!C14/'Balance Sheet'!C$38 -> 0.0030852995 | D39: ='Balance Sheet'!D14/'Balance Sheet'!D$38 -> 0.0038022814 | E39: ='Balance Sheet'!E14/'Balance Sheet'!E$38 -> 0.002303484 | F39: ='Balance Sheet'!F14/'Balance Sheet'!F$38 -> 0.0020212909 | G39: ='Balance Sheet'!G14/'Balance Sheet'!G$38 -> 0.0017989926 | H39: ='Balance Sheet'!H14/'Balance Sheet'!H$38 -> 0.001758367 | I39: ='Balance Sheet'!I14/'Balance Sheet'!I$38 -> 0.001573158 | J39: ='Balance Sheet'!J14/'Balance Sheet'!J$38 -> 0.0014070387 | ... Q39: ='Balance Sheet'!Q14/'Balance Sheet'!Q$38 -> 0.00059356371
B40: Goodwill | C40: ='Balance Sheet'!C15/'Balance Sheet'!C$38 -> 0.11125227 | D40: ='Balance Sheet'!D15/'Balance Sheet'!D$38 -> 0.11303146 | E40: ='Balance Sheet'!E15/'Balance Sheet'!E$38 -> 0.1241002 | F40: ='Balance Sheet'!F15/'Balance Sheet'!F$38 -> 0.1162916 | G40: ='Balance Sheet'!G15/'Balance Sheet'!G$38 -> 0.10278244 | H40: ='Balance Sheet'!H15/'Balance Sheet'!H$38 -> 0.10046137 | I40: ='Balance Sheet'!I15/'Balance Sheet'!I$38 -> 0.089879758 | J40: ='Balance Sheet'!J15/'Balance Sheet'!J$38 -> 0.080388809 | ... Q40: ='Balance Sheet'!Q15/'Balance Sheet'!Q$38 -> 0.033912273
B41: Other intangible assets | C41: ='Balance Sheet'!C16/'Balance Sheet'!C$38 -> 0.041742287 | D41: ='Balance Sheet'!D16/'Balance Sheet'!D$38 -> 0.052886277 | E41: ='Balance Sheet'!E16/'Balance Sheet'!E$38 -> 0.080621941 | F41: ='Balance Sheet'!F16/'Balance Sheet'!F$38 -> 0.12626331 | G41: ='Balance Sheet'!G16/'Balance Sheet'!G$38 -> 0.11345646 | H41: ='Balance Sheet'!H16/'Balance Sheet'!H$38 -> 0.11169494 | I41: ='Balance Sheet'!I16/'Balance Sheet'!I$38 -> 0.10032625 | J41: ='Balance Sheet'!J16/'Balance Sheet'!J$38 -> 0.089717778 | ... Q41: ='Balance Sheet'!Q16/'Balance Sheet'!Q$38 -> 0.027921695
B42: Financial assets
B43: (i) Investments | C43: ='Balance Sheet'!C18/'Balance Sheet'!C$38 -> 0.041016334 | D43: ='Balance Sheet'!D18/'Balance Sheet'!D$38 -> 0.032319392 | E43: ='Balance Sheet'!E18/'Balance Sheet'!E$38 -> 0.074575295 | F43: ='Balance Sheet'!F18/'Balance Sheet'!F$38 -> 0.046220186 | G43: ='Balance Sheet'!G18/'Balance Sheet'!G$38 -> 0.02578556 | H43: ='Balance Sheet'!H18/'Balance Sheet'!H$38 -> 0.043314004 | I43: ='Balance Sheet'!I18/'Balance Sheet'!I$38 -> 0.042536444 | J43: ='Balance Sheet'!J18/'Balance Sheet'!J$38 -> 0.041998881 | ... Q43: ='Balance Sheet'!Q18/'Balance Sheet'!Q$38 -> 0.044027602
B44: (ii) Loans | C44: ='Balance Sheet'!C19/'Balance Sheet'!C$38 -> 0.00072595281 | D44: ='Balance Sheet'!D19/'Balance Sheet'!D$38 -> 0.00069132389 | E44: ='Balance Sheet'!E19/'Balance Sheet'!E$38 -> 0.000575871 | F44: ='Balance Sheet'!F19/'Balance Sheet'!F$38 -> 0.00053901091 | G44: ='Balance Sheet'!G19/'Balance Sheet'!G$38 -> 0.00071959703 | H44: ='Balance Sheet'!H19/'Balance Sheet'!H$38 -> 0.00063664922 | I44: ='Balance Sheet'!I19/'Balance Sheet'!I$38 -> 0.00062522028 | J44: ='Balance Sheet'!J19/'Balance Sheet'!J$38 -> 0.00061731894 | ... Q44: ='Balance Sheet'!Q19/'Balance Sheet'!Q$38 -> 0.00064713801
B45: (iii) Other financial assets | C45: ='Balance Sheet'!C20/'Balance Sheet'!C$38 -> 0.0074410163 | D45: ='Balance Sheet'!D20/'Balance Sheet'!D$38 -> 0.0029381265 | E45: ='Balance Sheet'!E20/'Balance Sheet'!E$38 -> 0.004606968 | F45: ='Balance Sheet'!F20/'Balance Sheet'!F$38 -> 0.013475273 | G45: ='Balance Sheet'!G20/'Balance Sheet'!G$38 -> 0.0026385224 | H45: ='Balance Sheet'!H20/'Balance Sheet'!H$38 -> 0.0062539353 | I45: ='Balance Sheet'!I20/'Balance Sheet'!I$38 -> 0.0061416665 | J45: ='Balance Sheet'!J20/'Balance Sheet'!J$38 -> 0.00606405 | ... Q45: ='Balance Sheet'!Q20/'Balance Sheet'!Q$38 -> 0.0063569688
B46: Deferred tax assets (net) | C46: ='Balance Sheet'!C21/'Balance Sheet'!C$38 -> 0.033756806 | D46: ='Balance Sheet'!D21/'Balance Sheet'!D$38 -> 0.032319392 | E46: ='Balance Sheet'!E21/'Balance Sheet'!E$38 -> 0.021019292 | F46: ='Balance Sheet'!F21/'Balance Sheet'!F$38 -> 0.0091631856 | G46: ='Balance Sheet'!G21/'Balance Sheet'!G$38 -> 0.0068361717 | H46: ='Balance Sheet'!H21/'Balance Sheet'!H$38 -> 0.019422344 | I46: ='Balance Sheet'!I21/'Balance Sheet'!I$38 -> 0.019073679 | J46: ='Balance Sheet'!J21/'Balance Sheet'!J$38 -> 0.018832632 | ... Q46: ='Balance Sheet'!Q21/'Balance Sheet'!Q$38 -> 0.019742326
B47: Non current tax assets (net) | C47: ='Balance Sheet'!C22/'Balance Sheet'!C$38 -> 0.0099818512 | D47: ='Balance Sheet'!D22/'Balance Sheet'!D$38 -> 0.0098513654 | E47: ='Balance Sheet'!E22/'Balance Sheet'!E$38 -> 0.0096458393 | F47: ='Balance Sheet'!F22/'Balance Sheet'!F$38 -> 0.012801509 | G47: ='Balance Sheet'!G22/'Balance Sheet'!G$38 -> 0.012952746 | H47: ='Balance Sheet'!H22/'Balance Sheet'!H$38 -> 0.01095529 | I47: ='Balance Sheet'!I22/'Balance Sheet'!I$38 -> 0.010758624 | J47: ='Balance Sheet'!J22/'Balance Sheet'!J$38 -> 0.01062266 | ... Q47: ='Balance Sheet'!Q22/'Balance Sheet'!Q$38 -> 0.011135779
B48: Other non-current assets | C48: ='Balance Sheet'!C23/'Balance Sheet'!C$38 -> 0.0047186933 | D48: ='Balance Sheet'!D23/'Balance Sheet'!D$38 -> 0.0051849291 | E48: ='Balance Sheet'!E23/'Balance Sheet'!E$38 -> 0.0066225166 | F48: ='Balance Sheet'!F23/'Balance Sheet'!F$38 -> 0.0053901091 | G48: ='Balance Sheet'!G23/'Balance Sheet'!G$38 -> 0.005876709 | H48: ='Balance Sheet'!H23/'Balance Sheet'!H$38 -> 0.0054812308 | I48: ='Balance Sheet'!I23/'Balance Sheet'!I$38 -> 0.0053828333 | J48: ='Balance Sheet'!J23/'Balance Sheet'!J$38 -> 0.0053148068 | ... Q48: ='Balance Sheet'!Q23/'Balance Sheet'!Q$38 -> 0.005571534
B49: Total non-current assets | C49: ='Balance Sheet'!C24/'Balance Sheet'!C$38 -> 0.39455535 | D49: ='Balance Sheet'!D24/'Balance Sheet'!D$38 -> 0.39422745 | E49: ='Balance Sheet'!E24/'Balance Sheet'!E$38 -> 0.45004319 | F49: ='Balance Sheet'!F24/'Balance Sheet'!F$38 -> 0.46058483 | G49: ='Balance Sheet'!G24/'Balance Sheet'!G$38 -> 0.39038139 | H49: ='Balance Sheet'!H24/'Balance Sheet'!H$38 -> 0.4245971 | I49: ='Balance Sheet'!I24/'Balance Sheet'!I$38 -> 0.39706985 | J49: ='Balance Sheet'!J24/'Balance Sheet'!J$38 -> 0.37177271 | ... Q49: ='Balance Sheet'!Q24/'Balance Sheet'!Q$38 -> 0.22732542
B50: Current assets
B51: Inventories | C51: ='Balance Sheet'!C26/'Balance Sheet'!C$38 -> 0.20435572 | D51: ='Balance Sheet'!D26/'Balance Sheet'!D$38 -> 0.24403733 | E51: ='Balance Sheet'!E26/'Balance Sheet'!E$38 -> 0.1763605 | F51: ='Balance Sheet'!F26/'Balance Sheet'!F$38 -> 0.18002965 | G51: ='Balance Sheet'!G26/'Balance Sheet'!G$38 -> 0.14811705 | H51: ='Balance Sheet'!H26/'Balance Sheet'!H$38 -> 0.18490369 | I51: ='Balance Sheet'!I26/'Balance Sheet'!I$38 -> 0.18158436 | J51: ='Balance Sheet'!J26/'Balance Sheet'!J$38 -> 0.17928955 | ... Q51: ='Balance Sheet'!Q26/'Balance Sheet'!Q$38 -> 0.18794998
B52: Financial assets
B53: (i) Investments | C53: ='Balance Sheet'!C28/'Balance Sheet'!C$38 -> 0.11397459 | D53: ='Balance Sheet'!D28/'Balance Sheet'!D$38 -> 0.11078465 | E53: ='Balance Sheet'!E28/'Balance Sheet'!E$38 -> 0.08321336 | F53: ='Balance Sheet'!F28/'Balance Sheet'!F$38 -> 0.034900957 | G53: ='Balance Sheet'!G28/'Balance Sheet'!G$38 -> 0.16490765 | H53: ='Balance Sheet'!H28/'Balance Sheet'!H$38 -> 0.099398478 | I53: ='Balance Sheet'!I28/'Balance Sheet'!I$38 -> 0.097614105 | J53: ='Balance Sheet'!J28/'Balance Sheet'!J$38 -> 0.096380488 | ... Q53: ='Balance Sheet'!Q28/'Balance Sheet'!Q$38 -> 0.10103607
B54: (ii) Trade receivables | C54: ='Balance Sheet'!C29/'Balance Sheet'!C$38 -> 0.070417423 | D54: ='Balance Sheet'!D29/'Balance Sheet'!D$38 -> 0.11268579 | E54: ='Balance Sheet'!E29/'Balance Sheet'!E$38 -> 0.14612727 | F54: ='Balance Sheet'!F29/'Balance Sheet'!F$38 -> 0.14405067 | G54: ='Balance Sheet'!G29/'Balance Sheet'!G$38 -> 0.15243464 | H54: ='Balance Sheet'!H29/'Balance Sheet'!H$38 -> 0.1244704 | I54: ='Balance Sheet'!I29/'Balance Sheet'!I$38 -> 0.12223594 | J54: ='Balance Sheet'!J29/'Balance Sheet'!J$38 -> 0.12069116 | ... Q54: ='Balance Sheet'!Q29/'Balance Sheet'!Q$38 -> 0.12652105
B55: (iii) Cash and cash equivalents | C55: ='Balance Sheet'!C30/'Balance Sheet'!C$38 -> 0.019782214 | D55: ='Balance Sheet'!D30/'Balance Sheet'!D$38 -> 0.047701348 | E55: ='Balance Sheet'!E30/'Balance Sheet'!E$38 -> 0.029801325 | F55: ='Balance Sheet'!F30/'Balance Sheet'!F$38 -> 0.030723622 | G55: ='Balance Sheet'!G30/'Balance Sheet'!G$38 -> 0.038498441 | H55: ='Balance Sheet'!H30/'Balance Sheet'!H$38 -> 0.068869526 | I55: ='Balance Sheet'!I30/'Balance Sheet'!I$38 -> 0.11016067 | J55: ='Balance Sheet'!J30/'Balance Sheet'!J$38 -> 0.14613092 | ... Q55: ='Balance Sheet'!Q30/'Balance Sheet'!Q$38 -> 0.29408675
B56: (iv) Bank balances other than (iii) above | C56: ='Balance Sheet'!C31/'Balance Sheet'!C$38 -> 0.15154265 | D56: ='Balance Sheet'!D31/'Balance Sheet'!D$38 -> 0.052367784 | E56: ='Balance Sheet'!E31/'Balance Sheet'!E$38 -> 0.079038295 | F56: ='Balance Sheet'!F31/'Balance Sheet'!F$38 -> 0.096348201 | G56: ='Balance Sheet'!G31/'Balance Sheet'!G$38 -> 0.054689374 | H56: ='Balance Sheet'!H31/'Balance Sheet'!H$38 -> 0.053454355 | I56: ='Balance Sheet'!I31/'Balance Sheet'!I$38 -> 0.047824002 | J56: ='Balance Sheet'!J31/'Balance Sheet'!J$38 -> 0.042773975 | ... Q56: ='Balance Sheet'!Q31/'Balance Sheet'!Q$38 -> 0.018044337
B57: (v) Loans | C57: ='Balance Sheet'!C32/'Balance Sheet'!C$38 -> 0.0010889292 | D57: ='Balance Sheet'!D32/'Balance Sheet'!D$38 -> 0.00086415486 | E57: ='Balance Sheet'!E32/'Balance Sheet'!E$38 -> 0.000575871 | F57: ='Balance Sheet'!F32/'Balance Sheet'!F$38 -> 0.00080851637 | G57: ='Balance Sheet'!G32/'Balance Sheet'!G$38 -> 0.00083952986 | H57: ='Balance Sheet'!H32/'Balance Sheet'!H$38 -> 0.00081779585 | I57: ='Balance Sheet'!I32/'Balance Sheet'!I$38 -> 0.00080311501 | J57: ='Balance Sheet'!J32/'Balance Sheet'!J$38 -> 0.0007929655 | ... Q57: ='Balance Sheet'!Q32/'Balance Sheet'!Q$38 -> 0.00083126903
B58: (vi) Other financial assets | C58: ='Balance Sheet'!C33/'Balance Sheet'!C$38 -> 0.00090744102 | D58: ='Balance Sheet'!D33/'Balance Sheet'!D$38 -> 0.00034566194 | E58: ='Balance Sheet'!E33/'Balance Sheet'!E$38 -> 0.000575871 | F58: ='Balance Sheet'!F33/'Balance Sheet'!F$38 -> 0.00067376364 | G58: ='Balance Sheet'!G33/'Balance Sheet'!G$38 -> 0.00035979851 | H58: ='Balance Sheet'!H33/'Balance Sheet'!H$38 -> 0.00056470873 | I58: ='Balance Sheet'!I33/'Balance Sheet'!I$38 -> 0.00055457124 | J58: ='Balance Sheet'!J33/'Balance Sheet'!J$38 -> 0.00054756274 | ... Q58: ='Balance Sheet'!Q33/'Balance Sheet'!Q$38 -> 0.00057401229
B59: Current tax asset (net) | C59: ='Balance Sheet'!C34/'Balance Sheet'!C$38 -> 0.0001814882 | D59: ='Balance Sheet'!D34/'Balance Sheet'!D$38 -> 0.00017283097 | E59: ='Balance Sheet'!E34/'Balance Sheet'!E$38 -> 0.0002879355 | F59: ='Balance Sheet'!F34/'Balance Sheet'!F$38 -> 0.00026950546 | G59: ='Balance Sheet'!G34/'Balance Sheet'!G$38 -> 0.00023986568 | H59: ='Balance Sheet'!H34/'Balance Sheet'!H$38 -> 0.00022910077 | I59: ='Balance Sheet'!I34/'Balance Sheet'!I$38 -> 0.00022498802 | J59: ='Balance Sheet'!J34/'Balance Sheet'!J$38 -> 0.00022214469 | ... Q59: ='Balance Sheet'!Q34/'Balance Sheet'!Q$38 -> 0.0002328752
B60: Other current assets | C60: ='Balance Sheet'!C35/'Balance Sheet'!C$38 -> 0.040653358 | D60: ='Balance Sheet'!D35/'Balance Sheet'!D$38 -> 0.036812997 | E60: ='Balance Sheet'!E35/'Balance Sheet'!E$38 -> 0.032968615 | F60: ='Balance Sheet'!F35/'Balance Sheet'!F$38 -> 0.050936531 | G60: ='Balance Sheet'!G35/'Balance Sheet'!G$38 -> 0.049532262 | H60: ='Balance Sheet'!H35/'Balance Sheet'!H$38 -> 0.041869902 | I60: ='Balance Sheet'!I35/'Balance Sheet'!I$38 -> 0.041118265 | J60: ='Balance Sheet'!J35/'Balance Sheet'!J$38 -> 0.040598625 | ... Q60: ='Balance Sheet'!Q35/'Balance Sheet'!Q$38 -> 0.042559708
B61: Assets classified as held for sale | C61: ='Balance Sheet'!C36/'Balance Sheet'!C$38 -> 0.0025408348 | D61: ='Balance Sheet'!D36/'Balance Sheet'!D$38 -> 0 | E61: ='Balance Sheet'!E36/'Balance Sheet'!E$38 -> 0.0010077743 | F61: ='Balance Sheet'!F36/'Balance Sheet'!F$38 -> 0.00067376364 | G61: ='Balance Sheet'!G36/'Balance Sheet'!G$38 -> 0 | H61: ='Balance Sheet'!H36/'Balance Sheet'!H$38 -> 0.00082493662 | I61: ='Balance Sheet'!I36/'Balance Sheet'!I$38 -> 0.0008101276 | J61: ='Balance Sheet'!J36/'Balance Sheet'!J$38 -> 0.00079988945 | ... Q61: ='Balance Sheet'!Q36/'Balance Sheet'!Q$38 -> 0.00083852744
B62: Total current assets | C62: ='Balance Sheet'!C37/'Balance Sheet'!C$38 -> 0.60544465 | D62: ='Balance Sheet'!D37/'Balance Sheet'!D$38 -> 0.60577255 | E62: ='Balance Sheet'!E37/'Balance Sheet'!E$38 -> 0.54995681 | F62: ='Balance Sheet'!F37/'Balance Sheet'!F$38 -> 0.53941517 | G62: ='Balance Sheet'!G37/'Balance Sheet'!G$38 -> 0.60961861 | H62: ='Balance Sheet'!H37/'Balance Sheet'!H$38 -> 0.5754029 | I62: ='Balance Sheet'!I37/'Balance Sheet'!I$38 -> 0.60293015 | J62: ='Balance Sheet'!J37/'Balance Sheet'!J$38 -> 0.62822729 | ... Q62: ='Balance Sheet'!Q37/'Balance Sheet'!Q$38 -> 0.77267458
B63: Total assets | C63: ='Balance Sheet'!C38/'Balance Sheet'!C$38 -> 1 | D63: ='Balance Sheet'!D38/'Balance Sheet'!D$38 -> 1 | E63: ='Balance Sheet'!E38/'Balance Sheet'!E$38 -> 1 | F63: ='Balance Sheet'!F38/'Balance Sheet'!F$38 -> 1 | G63: ='Balance Sheet'!G38/'Balance Sheet'!G$38 -> 1 | H63: ='Balance Sheet'!H38/'Balance Sheet'!H$38 -> 1 | I63: ='Balance Sheet'!I38/'Balance Sheet'!I$38 -> 1 | J63: ='Balance Sheet'!J38/'Balance Sheet'!J$38 -> 1 | ... Q63: ='Balance Sheet'!Q38/'Balance Sheet'!Q$38 -> 1
B64: EQUITY AND LIABILITIES
B65: Equity
B66: Equity share capital | C66: ='Balance Sheet'!C41/'Balance Sheet'!C$38 -> 0.023411978 | D66: ='Balance Sheet'!D41/'Balance Sheet'!D$38 -> 0.022295195 | E66: ='Balance Sheet'!E41/'Balance Sheet'!E$38 -> 0.01857184 | F66: ='Balance Sheet'!F41/'Balance Sheet'!F$38 -> 0.017383102 | G66: ='Balance Sheet'!G41/'Balance Sheet'!G$38 -> 0.015471336 | H66: ='Balance Sheet'!H41/'Balance Sheet'!H$38 -> 0.015121956 | I66: ='Balance Sheet'!I41/'Balance Sheet'!I$38 -> 0.013529158 | J66: ='Balance Sheet'!J41/'Balance Sheet'!J$38 -> 0.012100533 | ... Q66: ='Balance Sheet'!Q41/'Balance Sheet'!Q$38 -> 0.0051046479
B67: Other equity
B68: Reserves and surplus | C68: ='Balance Sheet'!C43/'Balance Sheet'!C$38 -> 0.5646098 | D68: ='Balance Sheet'!D43/'Balance Sheet'!D$38 -> 0.55115797 | E68: ='Balance Sheet'!E43/'Balance Sheet'!E$38 -> 0.52893752 | F68: ='Balance Sheet'!F43/'Balance Sheet'!F$38 -> 0.50963482 | G68: ='Balance Sheet'!G43/'Balance Sheet'!G$38 -> 0.47937155 | H68: ='Balance Sheet'!H43/'Balance Sheet'!H$38 -> 0.53805136 | I68: ='Balance Sheet'!I43/'Balance Sheet'!I$38 -> 0.54909946 | J68: ='Balance Sheet'!J43/'Balance Sheet'!J$38 -> 0.55742034 | ... Q68: ='Balance Sheet'!Q43/'Balance Sheet'!Q$38 -> 0.55184908
B69: Other reserves | C69: ='Balance Sheet'!C44/'Balance Sheet'!C$38 -> 0 | D69: ='Balance Sheet'!D44/'Balance Sheet'!D$38 -> 0.0051849291 | E69: ='Balance Sheet'!E44/'Balance Sheet'!E$38 -> -0.000575871 | F69: ='Balance Sheet'!F44/'Balance Sheet'!F$38 -> -0.010645466 | G69: ='Balance Sheet'!G44/'Balance Sheet'!G$38 -> -0.018229791 | H69: ='Balance Sheet'!H44/'Balance Sheet'!H$38 -> -0.017818118 | I69: ='Balance Sheet'!I44/'Balance Sheet'!I$38 -> -0.015941334 | J69: ='Balance Sheet'!J44/'Balance Sheet'!J$38 -> -0.014257992 | ... Q69: ='Balance Sheet'!Q44/'Balance Sheet'!Q$38 -> -0.0060147789
B70: Share application money pending allotment | C70: ='Balance Sheet'!C45/'Balance Sheet'!C$38 -> 0 | D70: ='Balance Sheet'!D45/'Balance Sheet'!D$38 -> 0 | E70: ='Balance Sheet'!E45/'Balance Sheet'!E$38 -> 0 | F70: ='Balance Sheet'!F45/'Balance Sheet'!F$38 -> 0 | G70: ='Balance Sheet'!G45/'Balance Sheet'!G$38 -> 0.00011993284 | H70: ='Balance Sheet'!H45/'Balance Sheet'!H$38 -> 0.00011722446 | I70: ='Balance Sheet'!I45/'Balance Sheet'!I$38 -> 0.0001048772 | J70: ='Balance Sheet'!J45/'Balance Sheet'!J$38 -> 9.3802578e-05 | ... Q70: ='Balance Sheet'!Q45/'Balance Sheet'!Q$38 -> 3.9570914e-05
B71: Equity attributable to owners | C71: ='Balance Sheet'!C46/'Balance Sheet'!C$38 -> 0.58802178 | D71: ='Balance Sheet'!D46/'Balance Sheet'!D$38 -> 0.57863809 | E71: ='Balance Sheet'!E46/'Balance Sheet'!E$38 -> 0.54693349 | F71: ='Balance Sheet'!F46/'Balance Sheet'!F$38 -> 0.51637246 | G71: ='Balance Sheet'!G46/'Balance Sheet'!G$38 -> 0.47673303 | H71: ='Balance Sheet'!H46/'Balance Sheet'!H$38 -> 0.53547242 | I71: ='Balance Sheet'!I46/'Balance Sheet'!I$38 -> 0.54679217 | J71: ='Balance Sheet'!J46/'Balance Sheet'!J$38 -> 0.55535669 | ... Q71: ='Balance Sheet'!Q46/'Balance Sheet'!Q$38 -> 0.55097852
B72: Non-controlling interests | C72: ='Balance Sheet'!C47/'Balance Sheet'!C$38 -> 0.0032667877 | D72: ='Balance Sheet'!D47/'Balance Sheet'!D$38 -> 0.0098513654 | E72: ='Balance Sheet'!E47/'Balance Sheet'!E$38 -> 0.022602937 | F72: ='Balance Sheet'!F47/'Balance Sheet'!F$38 -> 0.04541167 | G72: ='Balance Sheet'!G47/'Balance Sheet'!G$38 -> 0.034900456 | H72: ='Balance Sheet'!H47/'Balance Sheet'!H$38 -> 0.034112319 | I72: ='Balance Sheet'!I47/'Balance Sheet'!I$38 -> 0.030519264 | J72: ='Balance Sheet'!J47/'Balance Sheet'!J$38 -> 0.02729655 | ... Q72: ='Balance Sheet'!Q47/'Balance Sheet'!Q$38 -> 0.011515136
B73: Total equity | C73: ='Balance Sheet'!C48/'Balance Sheet'!C$38 -> 0.59128857 | D73: ='Balance Sheet'!D48/'Balance Sheet'!D$38 -> 0.58848946 | E73: ='Balance Sheet'!E48/'Balance Sheet'!E$38 -> 0.56953642 | F73: ='Balance Sheet'!F48/'Balance Sheet'!F$38 -> 0.56178413 | G73: ='Balance Sheet'!G48/'Balance Sheet'!G$38 -> 0.51163349 | H73: ='Balance Sheet'!H48/'Balance Sheet'!H$38 -> 0.56958474 | I73: ='Balance Sheet'!I48/'Balance Sheet'!I$38 -> 0.57731143 | J73: ='Balance Sheet'!J48/'Balance Sheet'!J$38 -> 0.58265324 | ... Q73: ='Balance Sheet'!Q48/'Balance Sheet'!Q$38 -> 0.56249365
B74: Liabilities
B75: Non-current liabilities
B76: Financial liabilities
B77: i) Borrowings | C77: ='Balance Sheet'!C52/'Balance Sheet'!C$38 -> 0.0014519056 | D77: ='Balance Sheet'!D52/'Balance Sheet'!D$38 -> 0 | E77: ='Balance Sheet'!E52/'Balance Sheet'!E$38 -> 0.0002879355 | F77: ='Balance Sheet'!F52/'Balance Sheet'!F$38 -> 0 | G77: ='Balance Sheet'!G52/'Balance Sheet'!G$38 -> 0 | H77: ='Balance Sheet'!H52/'Balance Sheet'!H$38 -> 0.00033249501 | I77: ='Balance Sheet'!I52/'Balance Sheet'!I$38 -> 0.00032652616 | J77: ='Balance Sheet'!J52/'Balance Sheet'!J$38 -> 0.00032239962 | ... Q77: ='Balance Sheet'!Q52/'Balance Sheet'!Q$38 -> 0.00033797287
B78: ii) Lease liabilities | C78: ='Balance Sheet'!C53/'Balance Sheet'!C$38 -> 0.022141561 | D78: ='Balance Sheet'!D53/'Balance Sheet'!D$38 -> 0.015727618 | E78: ='Balance Sheet'!E53/'Balance Sheet'!E$38 -> 0.013101065 | F78: ='Balance Sheet'!F53/'Balance Sheet'!F$38 -> 0.014014284 | G78: ='Balance Sheet'!G53/'Balance Sheet'!G$38 -> 0.014871672 | H78: ='Balance Sheet'!H53/'Balance Sheet'!H$38 -> 0.01560548 | I78: ='Balance Sheet'!I53/'Balance Sheet'!I$38 -> 0.015325335 | J78: ='Balance Sheet'!J53/'Balance Sheet'!J$38 -> 0.015131658 | ... Q78: ='Balance Sheet'!Q53/'Balance Sheet'!Q$38 -> 0.01586258
B79: iii) Other financial liabilities | C79: ='Balance Sheet'!C54/'Balance Sheet'!C$38 -> 0 | D79: ='Balance Sheet'!D54/'Balance Sheet'!D$38 -> 0 | E79: ='Balance Sheet'!E54/'Balance Sheet'!E$38 -> 0.038295422 | F79: ='Balance Sheet'!F54/'Balance Sheet'!F$38 -> 0.054574855 | G79: ='Balance Sheet'!G54/'Balance Sheet'!G$38 -> 0.14523867 | H79: ='Balance Sheet'!H54/'Balance Sheet'!H$38 -> 0.050200687 | I79: ='Balance Sheet'!I54/'Balance Sheet'!I$38 -> 0.049299499 | J79: ='Balance Sheet'!J54/'Balance Sheet'!J$38 -> 0.048676467 | ... Q79: ='Balance Sheet'!Q54/'Balance Sheet'!Q$38 -> 0.051027743
B80: Provisions | C80: ='Balance Sheet'!C55/'Balance Sheet'!C$38 -> 0.0001814882 | D80: ='Balance Sheet'!D55/'Balance Sheet'!D$38 -> 0.00017283097 | E80: ='Balance Sheet'!E55/'Balance Sheet'!E$38 -> 0.000575871 | F80: ='Balance Sheet'!F55/'Balance Sheet'!F$38 -> 0.00013475273 | G80: ='Balance Sheet'!G55/'Balance Sheet'!G$38 -> 0.00011993284 | H80: ='Balance Sheet'!H55/'Balance Sheet'!H$38 -> 0.00023157236 | I80: ='Balance Sheet'!I55/'Balance Sheet'!I$38 -> 0.00022741524 | J80: ='Balance Sheet'!J55/'Balance Sheet'!J$38 -> 0.00022454124 | ... Q80: ='Balance Sheet'!Q55/'Balance Sheet'!Q$38 -> 0.00023538752
B81: Employee benefit obligations (net) | C81: ='Balance Sheet'!C56/'Balance Sheet'!C$38 -> 0.0043557169 | D81: ='Balance Sheet'!D56/'Balance Sheet'!D$38 -> 0.0046664362 | E81: ='Balance Sheet'!E56/'Balance Sheet'!E$38 -> 0.002879355 | F81: ='Balance Sheet'!F56/'Balance Sheet'!F$38 -> 0.0025603018 | G81: ='Balance Sheet'!G56/'Balance Sheet'!G$38 -> 0.0032381866 | H81: ='Balance Sheet'!H56/'Balance Sheet'!H$38 -> 0.003419638 | I81: ='Balance Sheet'!I56/'Balance Sheet'!I$38 -> 0.0033582496 | J81: ='Balance Sheet'!J56/'Balance Sheet'!J$38 -> 0.0033158091 | ... Q81: ='Balance Sheet'!Q56/'Balance Sheet'!Q$38 -> 0.0034759765
B82: Deferred tax liabilities (net) | C82: ='Balance Sheet'!C57/'Balance Sheet'!C$38 -> 0.015245009 | D82: ='Balance Sheet'!D57/'Balance Sheet'!D$38 -> 0.018838576 | E82: ='Balance Sheet'!E57/'Balance Sheet'!E$38 -> 0.02562626 | F82: ='Balance Sheet'!F57/'Balance Sheet'!F$38 -> 0.037596011 | G82: ='Balance Sheet'!G57/'Balance Sheet'!G$38 -> 0.029743344 | H82: ='Balance Sheet'!H57/'Balance Sheet'!H$38 -> 0.025495065 | I82: ='Balance Sheet'!I57/'Balance Sheet'!I$38 -> 0.025037385 | J82: ='Balance Sheet'!J57/'Balance Sheet'!J$38 -> 0.024720971 | ... Q82: ='Balance Sheet'!Q57/'Balance Sheet'!Q$38 -> 0.025915096
B83: Total non-current liabilities | C83: ='Balance Sheet'!C58/'Balance Sheet'!C$38 -> 0.043375681 | D83: ='Balance Sheet'!D58/'Balance Sheet'!D$38 -> 0.039405461 | E83: ='Balance Sheet'!E58/'Balance Sheet'!E$38 -> 0.080765908 | F83: ='Balance Sheet'!F58/'Balance Sheet'!F$38 -> 0.1088802 | G83: ='Balance Sheet'!G58/'Balance Sheet'!G$38 -> 0.1932118 | H83: ='Balance Sheet'!H58/'Balance Sheet'!H$38 -> 0.095284938 | I83: ='Balance Sheet'!I58/'Balance Sheet'!I$38 -> 0.09357441 | J83: ='Balance Sheet'!J58/'Balance Sheet'!J$38 -> 0.092391846 | ... Q83: ='Balance Sheet'!Q58/'Balance Sheet'!Q$38 -> 0.096854756
B84: Current liabilities
B85: Financial liabilities
B86: (i) Borrowings | C86: ='Balance Sheet'!C61/'Balance Sheet'!C$38 -> 0.061705989 | D86: ='Balance Sheet'!D61/'Balance Sheet'!D$38 -> 0.059626685 | E86: ='Balance Sheet'!E61/'Balance Sheet'!E$38 -> 0.068096746 | F86: ='Balance Sheet'!F61/'Balance Sheet'!F$38 -> 0.051610295 | G86: ='Balance Sheet'!G61/'Balance Sheet'!G$38 -> 0.045454545 | H86: ='Balance Sheet'!H61/'Balance Sheet'!H$38 -> 0.055919776 | I86: ='Balance Sheet'!I61/'Balance Sheet'!I$38 -> 0.054915921 | J86: ='Balance Sheet'!J61/'Balance Sheet'!J$38 -> 0.05422191 | ... Q86: ='Balance Sheet'!Q61/'Balance Sheet'!Q$38 -> 0.056841054
B87: (ii) Lease liabilities | C87: ='Balance Sheet'!C62/'Balance Sheet'!C$38 -> 0.0068965517 | D87: ='Balance Sheet'!D62/'Balance Sheet'!D$38 -> 0.0074317318 | E87: ='Balance Sheet'!E62/'Balance Sheet'!E$38 -> 0.0060466456 | F87: ='Balance Sheet'!F62/'Balance Sheet'!F$38 -> 0.0055248619 | G87: ='Balance Sheet'!G62/'Balance Sheet'!G$38 -> 0.0061165747 | H87: ='Balance Sheet'!H62/'Balance Sheet'!H$38 -> 0.0062401256 | I87: ='Balance Sheet'!I62/'Balance Sheet'!I$38 -> 0.0061281047 | J87: ='Balance Sheet'!J62/'Balance Sheet'!J$38 -> 0.0060506596 | ... Q87: ='Balance Sheet'!Q62/'Balance Sheet'!Q$38 -> 0.0063429316
B88: (iii) Trade payables
B89: Total outstanding dues of micro enterprises and small enterprises | C89: ='Balance Sheet'!C64/'Balance Sheet'!C$38 -> 0.0090744102 | D89: ='Balance Sheet'!D64/'Balance Sheet'!D$38 -> 0.013135154 | E89: ='Balance Sheet'!E64/'Balance Sheet'!E$38 -> 0.0097898071 | F89: ='Balance Sheet'!F64/'Balance Sheet'!F$38 -> 0.0095674437 | G89: ='Balance Sheet'!G64/'Balance Sheet'!G$38 -> 0.010674023 | H89: ='Balance Sheet'!H64/'Balance Sheet'!H$38 -> 0 | I89: ='Balance Sheet'!I64/'Balance Sheet'!I$38 -> 0 | J89: ='Balance Sheet'!J64/'Balance Sheet'!J$38 -> 0 | ... Q89: ='Balance Sheet'!Q64/'Balance Sheet'!Q$38 -> 0
B90: Total outstanding dues of creditors other than micro enterprises and small enterprises | C90: ='Balance Sheet'!C65/'Balance Sheet'!C$38 -> 0.19673321 | D90: ='Balance Sheet'!D65/'Balance Sheet'!D$38 -> 0.21914967 | E90: ='Balance Sheet'!E65/'Balance Sheet'!E$38 -> 0.19925137 | F90: ='Balance Sheet'!F65/'Balance Sheet'!F$38 -> 0.20347662 | G90: ='Balance Sheet'!G65/'Balance Sheet'!G$38 -> 0.15279444 | H90: ='Balance Sheet'!H65/'Balance Sheet'!H$38 -> 0.20058987 | I90: ='Balance Sheet'!I65/'Balance Sheet'!I$38 -> 0.19698893 | J90: ='Balance Sheet'!J65/'Balance Sheet'!J$38 -> 0.19449945 | ... Q90: ='Balance Sheet'!Q65/'Balance Sheet'!Q$38 -> 0.20389458
B91: (iv) Other financial liabilities | C91: ='Balance Sheet'!C66/'Balance Sheet'!C$38 -> 0.0079854809 | D91: ='Balance Sheet'!D66/'Balance Sheet'!D$38 -> 0.0077773937 | E91: ='Balance Sheet'!E66/'Balance Sheet'!E$38 -> 0.00575871 | F91: ='Balance Sheet'!F66/'Balance Sheet'!F$38 -> 0.007950411 | G91: ='Balance Sheet'!G66/'Balance Sheet'!G$38 -> 0.027704485 | H91: ='Balance Sheet'!H66/'Balance Sheet'!H$38 -> 0.011574663 | I91: ='Balance Sheet'!I66/'Balance Sheet'!I$38 -> 0.011366878 | J91: ='Balance Sheet'!J66/'Balance Sheet'!J$38 -> 0.011223227 | ... Q91: ='Balance Sheet'!Q66/'Balance Sheet'!Q$38 -> 0.011765355
B92: Other current liabilities | C92: ='Balance Sheet'!C67/'Balance Sheet'!C$38 -> 0.052087114 | D92: ='Balance Sheet'!D67/'Balance Sheet'!D$38 -> 0.038714138 | E92: ='Balance Sheet'!E67/'Balance Sheet'!E$38 -> 0.031241002 | F92: ='Balance Sheet'!F67/'Balance Sheet'!F$38 -> 0.028432826 | G92: ='Balance Sheet'!G67/'Balance Sheet'!G$38 -> 0.027824418 | H92: ='Balance Sheet'!H67/'Balance Sheet'!H$38 -> 0.034588011 | I92: ='Balance Sheet'!I67/'Balance Sheet'!I$38 -> 0.033967097 | J92: ='Balance Sheet'!J67/'Balance Sheet'!J$38 -> 0.033537831 | ... Q92: ='Balance Sheet'!Q67/'Balance Sheet'!Q$38 -> 0.035157848
B93: Provisions | C93: ='Balance Sheet'!C68/'Balance Sheet'!C$38 -> 0.0036297641 | D93: ='Balance Sheet'!D68/'Balance Sheet'!D$38 -> 0.0036294504 | E93: ='Balance Sheet'!E68/'Balance Sheet'!E$38 -> 0.0063345811 | F93: ='Balance Sheet'!F68/'Balance Sheet'!F$38 -> 0.0009432691 | G93: ='Balance Sheet'!G68/'Balance Sheet'!G$38 -> 0.0025185896 | H93: ='Balance Sheet'!H68/'Balance Sheet'!H$38 -> 0.0032901496 | I93: ='Balance Sheet'!I68/'Balance Sheet'!I$38 -> 0.0032310858 | J93: ='Balance Sheet'!J68/'Balance Sheet'!J$38 -> 0.0031902523 | ... Q93: ='Balance Sheet'!Q68/'Balance Sheet'!Q$38 -> 0.0033443548
B94: Employee benefit obligations (net) | C94: ='Balance Sheet'!C69/'Balance Sheet'!C$38 -> 0.01415608 | D94: ='Balance Sheet'!D69/'Balance Sheet'!D$38 -> 0.011061182 | E94: ='Balance Sheet'!E69/'Balance Sheet'!E$38 -> 0.010653614 | F94: ='Balance Sheet'!F69/'Balance Sheet'!F$38 -> 0.010645466 | G94: ='Balance Sheet'!G69/'Balance Sheet'!G$38 -> 0.011033821 | H94: ='Balance Sheet'!H69/'Balance Sheet'!H$38 -> 0.011281423 | I94: ='Balance Sheet'!I69/'Balance Sheet'!I$38 -> 0.011078902 | J94: ='Balance Sheet'!J69/'Balance Sheet'!J$38 -> 0.01093889 | ... Q94: ='Balance Sheet'!Q69/'Balance Sheet'!Q$38 -> 0.011467284
B95: Current tax liabilities (net) | C95: ='Balance Sheet'!C70/'Balance Sheet'!C$38 -> 0.013067151 | D95: ='Balance Sheet'!D70/'Balance Sheet'!D$38 -> 0.011579675 | E95: ='Balance Sheet'!E70/'Balance Sheet'!E$38 -> 0.012525194 | F95: ='Balance Sheet'!F70/'Balance Sheet'!F$38 -> 0.011184476 | G95: ='Balance Sheet'!G70/'Balance Sheet'!G$38 -> 0.011033821 | H95: ='Balance Sheet'!H70/'Balance Sheet'!H$38 -> 0.01164631 | I95: ='Balance Sheet'!I70/'Balance Sheet'!I$38 -> 0.011437238 | J95: ='Balance Sheet'!J70/'Balance Sheet'!J$38 -> 0.011292698 | ... Q95: ='Balance Sheet'!Q70/'Balance Sheet'!Q$38 -> 0.011838182
B96: Total current liabilities | C96: ='Balance Sheet'!C71/'Balance Sheet'!C$38 -> 0.36533575 | D96: ='Balance Sheet'!D71/'Balance Sheet'!D$38 -> 0.37210508 | E96: ='Balance Sheet'!E71/'Balance Sheet'!E$38 -> 0.34969767 | F96: ='Balance Sheet'!F71/'Balance Sheet'!F$38 -> 0.32933567 | G96: ='Balance Sheet'!G71/'Balance Sheet'!G$38 -> 0.29515471 | H96: ='Balance Sheet'!H71/'Balance Sheet'!H$38 -> 0.33513032 | I96: ='Balance Sheet'!I71/'Balance Sheet'!I$38 -> 0.32911416 | J96: ='Balance Sheet'!J71/'Balance Sheet'!J$38 -> 0.32495492 | ... Q96: ='Balance Sheet'!Q71/'Balance Sheet'!Q$38 -> 0.34065159
B97: Total liabilities | C97: ='Balance Sheet'!C72/'Balance Sheet'!C$38 -> 0.40871143 | D97: ='Balance Sheet'!D72/'Balance Sheet'!D$38 -> 0.41151054 | E97: ='Balance Sheet'!E72/'Balance Sheet'!E$38 -> 0.43046358 | F97: ='Balance Sheet'!F72/'Balance Sheet'!F$38 -> 0.43821587 | G97: ='Balance Sheet'!G72/'Balance Sheet'!G$38 -> 0.48836651 | H97: ='Balance Sheet'!H72/'Balance Sheet'!H$38 -> 0.43041526 | I97: ='Balance Sheet'!I72/'Balance Sheet'!I$38 -> 0.42268857 | J97: ='Balance Sheet'!J72/'Balance Sheet'!J$38 -> 0.41734676 | ... Q97: ='Balance Sheet'!Q72/'Balance Sheet'!Q$38 -> 0.43750635
B98: Total equity and liabilities | C98: ='Balance Sheet'!C73/'Balance Sheet'!C$38 -> 1 | D98: ='Balance Sheet'!D73/'Balance Sheet'!D$38 -> 1 | E98: ='Balance Sheet'!E73/'Balance Sheet'!E$38 -> 1 | F98: ='Balance Sheet'!F73/'Balance Sheet'!F$38 -> 1 | G98: ='Balance Sheet'!G73/'Balance Sheet'!G$38 -> 1 | H98: ='Balance Sheet'!H73/'Balance Sheet'!H$38 -> 1 | I98: ='Balance Sheet'!I73/'Balance Sheet'!I$38 -> 1 | J98: ='Balance Sheet'!J73/'Balance Sheet'!J$38 -> 1 | ... Q98: ='Balance Sheet'!Q73/'Balance Sheet'!Q$38 -> 1

Sheet Cash Flow 
B4: CashFlow Statement
B5: All Figure In INR Cr.
B6: Particulars | C6: 2021 | D6: =C6+1 -> 2022 | E6: =D6+1 -> 2023 | F6: =E6+1 -> 2024 | G6: =F6+1 -> 2025 | H6: =G6+1 -> 2026 | I6: =H6+1 -> 2027 | J6: =I6+1 -> 2028 | K6: =J6+1 -> 2029 | ... Q6: =P6+1 -> 2035
B8: CASH FLOW FROM OPERATING ACTIVITIES
B9: PROFIT BEFORE INCOME TAX | C9: 1523 | D9: 1601 | E9: 1743 | F9: 1937 | G9: 2116 | H9: ='P&L Statement '!H34 -> 2230.8209 | I9: ='P&L Statement '!I34 -> 2429.455 | J9: ='P&L Statement '!J34 -> 2659.4282 | K9: ='P&L Statement '!K34 -> 2928.5564 | L9: ='P&L Statement '!L34 -> 3246.9753 | M9: ='P&L Statement '!M34 -> 3627.8565 | N9: ='P&L Statement '!N34 -> 4088.3439 | O9: ='P&L Statement '!O34 -> 4650.7816 | ... Q9: ='P&L Statement '!Q34 -> 6224.9982
B10: Adjustments for:
B11: Depreciation and amortization expense/impairment | C11: 139 | D11: 139 | E11: 155 | F11: 158 | G11: 178 | H11: =-'P&L Statement '!H21 -> 160.8108 | I11: =-'P&L Statement '!I21 -> 195.72191 | J11: =-'P&L Statement '!J21 -> 238.54858 | K11: =-'P&L Statement '!K21 -> 291.16514 | L11: =-'P&L Statement '!L21 -> 355.90783 | M11: =-'P&L Statement '!M21 -> 435.69258 | N11: =-'P&L Statement '!N21 -> 534.1636 | O11: =-'P&L Statement '!O21 -> 655.88117 | ... Q11: =-'P&L Statement '!Q21 -> 993.36431
B12: Share of net loss /(gain) of joint ventures accounted for using the equity method | C12: 2 | D12: 0 | E12: 0 | F12: 0 | G12: 0 | H12: 0 | I12: 0 | J12: 0 | K12: 0 | L12: 0 | M12: 0 | N12: 0 | O12: 0 | P12: 0 | Q12: 0
B13: Finance costs | C13: 34 | D13: 39 | E13: 56 | F13: 73 | G13: 53 | H13: =-'P&L Statement '!H26 -> 63.701955 | I13: =-'P&L Statement '!I26 -> 69.958187 | J13: =-'P&L Statement '!J26 -> 77.272682 | K13: =-'P&L Statement '!K26 -> 85.907524 | L13: =-'P&L Statement '!L26 -> 96.20011 | M13: =-'P&L Statement '!M26 -> 108.58572 | N13: =-'P&L Statement '!N26 -> 123.62692 | O13: =-'P&L Statement '!O26 -> 142.05187 | ... Q13: =-'P&L Statement '!Q26 -> 175.12579
B14: Interest income from financial assets | C14: -59 | D14: -59 | E14: -49 | F14: -77 | G14: -77 | H14: 0 | I14: 0 | J14: 0 | K14: 0 | L14: 0 | M14: 0 | N14: 0 | O14: 0 | P14: 0 | Q14: 0
B15: (Gain)/ Loss on disposal of property, plant and equipment (NET) | C15: 0 | D15: 0 | E15: -28 | F15: -15 | G15: -20 | H15: 0 | I15: 0 | J15: 0 | K15: 0 | L15: 0 | M15: 0 | N15: 0 | O15: 0 | P15: 0 | Q15: 0
B16: Net fair value changes financial assets (including net gain on sale) | C16: -21 | D16: -29 | E16: -50 | F16: -73 | G16: -76 | H16: 0 | I16: 0 | J16: 0 | K16: 0 | L16: 0 | M16: 0 | N16: 0 | O16: 0 | P16: 0 | Q16: 0
B17: Employees stock option charge | C17: 9 | D17: 10 | E17: 19 | F17: 35 | G17: 43 | H17: 0 | I17: 0 | J17: 0 | K17: 0 | L17: 0 | M17: 0 | N17: 0 | O17: 0 | P17: 0 | Q17: 0
B18: Impairment of Non-current assets and Inventory (refer note 39) | C18: 51 | D18: 0 | E18: 0 | F18: 0 | G18: 0 | H18: 0 | I18: 0 | J18: 0 | K18: 0 | L18: 0 | M18: 0 | N18: 0 | O18: 0 | P18: 0 | Q18: 0
B19: Fair valuation gain on existing stake of Joint venture (refer note 42)/FA and Invstmnt | C19: -64 | D19: 0 | E19: 0 | F19: 0 | G19: 0 | H19: 0 | I19: 0 | J19: 0 | K19: 0 | L19: 0 | M19: 0 | N19: 0 | O19: 0 | P19: 0 | Q19: 0
B20: Bad debt written off and Provision for doubtful debts | C20: 3 | D20: 8 | E20: 1 | F20: 2 | G20: 2 | H20: 0 | I20: 0 | J20: 0 | K20: 0 | L20: 0 | M20: 0 | N20: 0 | O20: 0 | P20: 0 | Q20: 0
B21: Stock appreciation rights expense charge
B22: Sum of Adjustments | C22: =SUM(C11:C21) -> 94 | D22: =SUM(D11:D21) -> 108 | E22: =SUM(E11:E21) -> 104 | F22: =SUM(F11:F21) -> 103 | G22: =SUM(G11:G21) -> 103 | H22: =SUM(H11:H21) -> 224.51275 | I22: =SUM(I11:I21) -> 265.6801 | J22: =SUM(J11:J21) -> 315.82126 | ... Q22: =SUM(Q11:Q21) -> 1168.4901
B23: Sub total of Adjustment | C23: =SUM(C22,C9) -> 1617 | D23: =SUM(D22,D9) -> 1709 | E23: =SUM(E22,E9) -> 1847 | F23: =SUM(F22,F9) -> 2040 | G23: =SUM(G22,G9) -> 2219 | H23: =SUM(H22,H9) -> 2455.3337 | I23: =SUM(I22,I9) -> 2695.1351 | J23: =SUM(J22,J9) -> 2975.2495 | ... Q23: =SUM(Q22,Q9) -> 7393.4883
B24: Change in operating assets and liabilities:
B25: (Increase) / Decrease in inventories | C25: 251 | D25: -286 | E25: 191 | F25: -101 | G25: 101 | H25: ='Balance Sheet'!G26-'Balance Sheet'!H26 -> -342.34732 | I25: ='Balance Sheet'!H26-'Balance Sheet'!I26 -> -154.05247 | J25: ='Balance Sheet'!I26-'Balance Sheet'!J26 -> -179.95013 | K25: ='Balance Sheet'!J26-'Balance Sheet'!K26 -> -212.24133 | L25: ='Balance Sheet'!K26-'Balance Sheet'!L26 -> -252.76156 | M25: ='Balance Sheet'!L26-'Balance Sheet'!M26 -> -303.89618 | N25: ='Balance Sheet'!M26-'Balance Sheet'!N26 -> -368.74698 | O25: ='Balance Sheet'!N26-'Balance Sheet'!O26 -> -451.34923 | ... Q25: ='Balance Sheet'!P26-'Balance Sheet'!Q26 -> -692.40043
B26: (Increase) in trade receivables/decrease | C26: 147 | D26: -272 | E26: -360 | F26: -52 | G26: -205 | H26: ='Balance Sheet'!G29-'Balance Sheet'!H29 -> 209.18749 | I26: ='Balance Sheet'!H29-'Balance Sheet'!I29 -> -103.70248 | J26: ='Balance Sheet'!I29-'Balance Sheet'!J29 -> -121.13584 | K26: ='Balance Sheet'!J29-'Balance Sheet'!K29 -> -142.8731 | L26: ='Balance Sheet'!K29-'Balance Sheet'!L29 -> -170.14983 | M26: ='Balance Sheet'!L29-'Balance Sheet'!M29 -> -204.57179 | N26: ='Balance Sheet'!M29-'Balance Sheet'!N29 -> -248.22698 | O26: ='Balance Sheet'!N29-'Balance Sheet'!O29 -> -303.83179 | ... Q26: ='Balance Sheet'!P29-'Balance Sheet'!Q29 -> -466.09863
B27: (Increase) / Decrease in other financials assets | C27: -4 | D27: 3 | E27: 13 | F27: -4 | G27: 3 | H27: ='Balance Sheet'!G33-'Balance Sheet'!H33 -> -1.8173283 | I27: ='Balance Sheet'!H33-'Balance Sheet'!I33 -> -0.47048693 | J27: ='Balance Sheet'!I33-'Balance Sheet'!J33 -> -0.54958019 | K27: ='Balance Sheet'!J33-'Balance Sheet'!K33 -> -0.64819977 | L27: ='Balance Sheet'!K33-'Balance Sheet'!L33 -> -0.77195135 | M27: ='Balance Sheet'!L33-'Balance Sheet'!M33 -> -0.92812005 | N27: ='Balance Sheet'!M33-'Balance Sheet'!N33 -> -1.1261789 | O27: ='Balance Sheet'!N33-'Balance Sheet'!O33 -> -1.3784519 | ... Q27: ='Balance Sheet'!P33-'Balance Sheet'!Q33 -> -2.114639
B28: (Increase) in other non-current assets/decrease | C28: 2 | D28: 0 | E28: -4 | F28: -6 | G28: 2 | H28: =SUM('Balance Sheet'!G28,'Balance Sheet'!G34,'Balance Sheet'!G36)-SUM('Balance Sheet'!H28,'Balance Sheet'!H34,'Balance Sheet'!H36) -> 520.0755 | I28: =SUM('Balance Sheet'!H28,'Balance Sheet'!H34,'Balance Sheet'!H36)-SUM('Balance Sheet'!I28,'Balance Sheet'!I34,'Balance Sheet'!I36) -> -83.691988 | J28: =SUM('Balance Sheet'!I28,'Balance Sheet'!I34,'Balance Sheet'!I36)-SUM('Balance Sheet'!J28,'Balance Sheet'!J34,'Balance Sheet'!J36) -> -97.761395 | K28: =SUM('Balance Sheet'!J28,'Balance Sheet'!J34,'Balance Sheet'!J36)-SUM('Balance Sheet'!K28,'Balance Sheet'!K34,'Balance Sheet'!K36) -> -115.30422 | L28: =SUM('Balance Sheet'!K28,'Balance Sheet'!K34,'Balance Sheet'!K36)-SUM('Balance Sheet'!L28,'Balance Sheet'!L34,'Balance Sheet'!L36) -> -137.31761 | M28: =SUM('Balance Sheet'!L28,'Balance Sheet'!L34,'Balance Sheet'!L36)-SUM('Balance Sheet'!M28,'Balance Sheet'!M34,'Balance Sheet'!M36) -> -165.09749 | N28: =SUM('Balance Sheet'!M28,'Balance Sheet'!M34,'Balance Sheet'!M36)-SUM('Balance Sheet'!N28,'Balance Sheet'!N34,'Balance Sheet'!N36) -> -200.32895 | O28: =SUM('Balance Sheet'!N28,'Balance Sheet'!N34,'Balance Sheet'!N36)-SUM('Balance Sheet'!O28,'Balance Sheet'!O34,'Balance Sheet'!O36) -> -245.20421 | ... Q28: =SUM('Balance Sheet'!P28,'Balance Sheet'!P34,'Balance Sheet'!P36)-SUM('Balance Sheet'!Q28,'Balance Sheet'!Q34,'Balance Sheet'!Q36) -> -376.15995
B29: (Increase) in other current assets/decrease | C29: 83 | D29: 11 | E29: -13 | F29: -145 | G29: -33 | H29: ='Balance Sheet'!G35-'Balance Sheet'!H35 -> 55.822835 | I29: ='Balance Sheet'!H35-'Balance Sheet'!I35 -> -34.883898 | J29: ='Balance Sheet'!I35-'Balance Sheet'!J35 -> -40.748208 | K29: ='Balance Sheet'!J35-'Balance Sheet'!K35 -> -48.060282 | L29: ='Balance Sheet'!K35-'Balance Sheet'!L35 -> -57.235749 | M29: ='Balance Sheet'!L35-'Balance Sheet'!M35 -> -68.814759 | N29: ='Balance Sheet'!M35-'Balance Sheet'!N35 -> -83.499684 | O29: ='Balance Sheet'!N35-'Balance Sheet'!O35 -> -102.20427 | ... Q29: ='Balance Sheet'!P35-'Balance Sheet'!Q35 -> -156.78831
B30: (Increase) / Decrease in loans and other assets | C30: -60 | D30: 1 | E30: 1 | F30: 9 | G30: -3 | H30: ='Balance Sheet'!G32-'Balance Sheet'!H32 -> 0.023675914 | I30: ='Balance Sheet'!H32-'Balance Sheet'!I32 -> -0.6813464 | J30: ='Balance Sheet'!I32-'Balance Sheet'!J32 -> -0.79588712 | K30: ='Balance Sheet'!J32-'Balance Sheet'!K32 -> -0.93870531 | L30: ='Balance Sheet'!K32-'Balance Sheet'!L32 -> -1.117919 | M30: ='Balance Sheet'!L32-'Balance Sheet'!M32 -> -1.3440783 | N30: ='Balance Sheet'!M32-'Balance Sheet'!N32 -> -1.6309017 | O30: ='Balance Sheet'!N32-'Balance Sheet'!O32 -> -1.9962366 | ... Q30: ='Balance Sheet'!P32-'Balance Sheet'!Q32 -> -3.0623628
B31: (Decrease)/ Increase in provisions | C31: -39 | D31: 1 | E31: 26 | F31: -40 | G31: 14 | H31: ='Balance Sheet'!H68-'Balance Sheet'!G68 -> 7.0670904 | I31: ='Balance Sheet'!I68-'Balance Sheet'!H68 -> 2.7411873 | J31: ='Balance Sheet'!J68-'Balance Sheet'!I68 -> 3.2020066 | K31: ='Balance Sheet'!K68-'Balance Sheet'!J68 -> 3.7765916 | L31: ='Balance Sheet'!L68-'Balance Sheet'!K68 -> 4.4976026 | M31: ='Balance Sheet'!M68-'Balance Sheet'!L68 -> 5.4074847 | N31: ='Balance Sheet'!N68-'Balance Sheet'!M68 -> 6.5614306 | O31: ='Balance Sheet'!O68-'Balance Sheet'!N68 -> 8.0312429 | ... Q31: ='Balance Sheet'!Q68-'Balance Sheet'!P68 -> 12.320473
B32: Increase in employee benefit obligations/(decrease) | C32: 26 | D32: -7 | E32: 5 | F32: 5 | G32: 21 | H32: ='Balance Sheet'!H69-'Balance Sheet'!G69 -> 4.2377846 | I32: ='Balance Sheet'!I69-'Balance Sheet'!H69 -> 9.3991144 | J32: ='Balance Sheet'!J69-'Balance Sheet'!I69 -> 10.979194 | K32: ='Balance Sheet'!K69-'Balance Sheet'!J69 -> 12.949358 | L32: ='Balance Sheet'!L69-'Balance Sheet'!K69 -> 15.421595 | M32: ='Balance Sheet'!M69-'Balance Sheet'!L69 -> 18.541443 | N32: ='Balance Sheet'!N69-'Balance Sheet'!M69 -> 22.498148 | O32: ='Balance Sheet'!O69-'Balance Sheet'!N69 -> 27.537911 | ... Q32: ='Balance Sheet'!Q69-'Balance Sheet'!P69 -> 42.245029
B33: (Decrease) in other current liabilities/increase | C33: 77 | D33: -3 | E33: -9 | F33: -7 | G33: 21 | H33: ='Balance Sheet'!H67-'Balance Sheet'!G67 -> 63.057958 | I33: ='Balance Sheet'!I67-'Balance Sheet'!H67 -> 28.816992 | J33: ='Balance Sheet'!J67-'Balance Sheet'!I67 -> 33.661399 | K33: ='Balance Sheet'!K67-'Balance Sheet'!J67 -> 39.701778 | L33: ='Balance Sheet'!L67-'Balance Sheet'!K67 -> 47.281475 | M33: ='Balance Sheet'!M67-'Balance Sheet'!L67 -> 56.846698 | N33: ='Balance Sheet'!N67-'Balance Sheet'!M67 -> 68.977663 | O33: ='Balance Sheet'!O67-'Balance Sheet'!N67 -> 84.429205 | ... Q33: ='Balance Sheet'!Q67-'Balance Sheet'!P67 -> 129.52015
B34: Increase in trade payables/(decrease) | C34: 184 | D34: 210 | E34: 99 | F34: 106 | G34: -218 | H34: ='Working Capital'!H14-'Working Capital'!G14 -> 348.16045 | I34: ='Working Capital'!I14-'Working Capital'!H14 -> 167.1214 | J34: ='Working Capital'!J14-'Working Capital'!I14 -> 195.21607 | K34: ='Working Capital'!K14-'Working Capital'!J14 -> 230.24667 | L34: ='Working Capital'!L14-'Working Capital'!K14 -> 274.2044 | M34: ='Working Capital'!M14-'Working Capital'!L14 -> 329.67699 | N34: ='Working Capital'!N14-'Working Capital'!M14 -> 400.02937 | O34: ='Working Capital'!O14-'Working Capital'!N14 -> 489.63911 | ... Q34: ='Working Capital'!Q14-'Working Capital'!P14 -> 751.13972
B35: Increase / (Decrease) in other financial liabilities | C35: 8 | D35: 0 | E35: -8 | F35: 9 | G35: 4 | H35: =SUM('Balance Sheet'!H61,'Balance Sheet'!H62,'Balance Sheet'!H66,'Balance Sheet'!H70)-SUM('Balance Sheet'!G61:G62,'Balance Sheet'!G66,'Balance Sheet'!G70) -> -24.646275 | I35: =SUM('Balance Sheet'!I61,'Balance Sheet'!I62,'Balance Sheet'!I66,'Balance Sheet'!I70)-SUM('Balance Sheet'!H61:H62,'Balance Sheet'!H66,'Balance Sheet'!H70) -> 71.135054 | J35: =SUM('Balance Sheet'!J61,'Balance Sheet'!J62,'Balance Sheet'!J66,'Balance Sheet'!J70)-SUM('Balance Sheet'!I61:I62,'Balance Sheet'!I66,'Balance Sheet'!I70) -> 83.093524 | K35: =SUM('Balance Sheet'!K61,'Balance Sheet'!K62,'Balance Sheet'!K66,'Balance Sheet'!K70)-SUM('Balance Sheet'!J61:J62,'Balance Sheet'!J66,'Balance Sheet'!J70) -> 98.004264 | L35: =SUM('Balance Sheet'!L61,'Balance Sheet'!L62,'Balance Sheet'!L66,'Balance Sheet'!L70)-SUM('Balance Sheet'!K61:K62,'Balance Sheet'!K66,'Balance Sheet'!K70) -> 116.71483 | M35: =SUM('Balance Sheet'!M61,'Balance Sheet'!M62,'Balance Sheet'!M66,'Balance Sheet'!M70)-SUM('Balance Sheet'!L61:L62,'Balance Sheet'!L66,'Balance Sheet'!L70) -> 140.32668 | N35: =SUM('Balance Sheet'!N61,'Balance Sheet'!N62,'Balance Sheet'!N66,'Balance Sheet'!N70)-SUM('Balance Sheet'!M61:M62,'Balance Sheet'!M66,'Balance Sheet'!M70) -> 170.2721 | O35: =SUM('Balance Sheet'!O61,'Balance Sheet'!O62,'Balance Sheet'!O66,'Balance Sheet'!O70)-SUM('Balance Sheet'!N61:N62,'Balance Sheet'!N66,'Balance Sheet'!N70) -> 208.4144 | ... Q35: =SUM('Balance Sheet'!Q61,'Balance Sheet'!Q62,'Balance Sheet'!Q66,'Balance Sheet'!Q70)-SUM('Balance Sheet'!P61:P62,'Balance Sheet'!P66,'Balance Sheet'!P70) -> 319.72187
B36: Changes in working capital | C36: =SUM(C25:C35) -> 675 | D36: =SUM(D25:D35) -> -342 | E36: =SUM(E25:E35) -> -59 | F36: =SUM(F25:F35) -> -226 | G36: =SUM(G25:G35) -> -293 | H36: =SUM(H25:H35) -> 838.82186 | I36: =SUM(I25:I35) -> -98.268924 | J36: =SUM(J25:J35) -> -114.78885 | ... Q36: =SUM(Q25:Q35) -> -441.67709
B37: Cash generated from operations | C37: =C23+C36 -> 2292 | D37: =D23+D36 -> 1367 | E37: =E23+E36 -> 1788 | F37: =F23+F36 -> 1814 | G37: =G23+G36 -> 1926 | H37: =H23+H36 -> 3294.1555 | I37: =I23+I36 -> 2596.8662 | J37: =J23+J36 -> 2860.4606 | ... Q37: =Q23+Q36 -> 6951.8112
B38: Income taxes paid (net of refunds) | C38: -285 | D38: -351 | E38: -369 | F38: -378 | G38: -484 | H38: =-'P&L Statement '!H37 -> -495.87166 | I38: =-'P&L Statement '!I37 -> -540.02448 | J38: =-'P&L Statement '!J37 -> -591.14342 | K38: =-'P&L Statement '!K37 -> -650.9658 | L38: =-'P&L Statement '!L37 -> -721.74464 | M38: =-'P&L Statement '!M37 -> -806.40772 | N38: =-'P&L Statement '!N37 -> -908.76586 | O38: =-'P&L Statement '!O37 -> -1033.7857 | ... Q38: =-'P&L Statement '!Q37 -> -1383.706
B39: Net cash generated from operating activities (A) | C39: =SUM(C37:C38) -> 2007 | D39: =SUM(D37:D38) -> 1016 | E39: =SUM(E37:E38) -> 1419 | F39: =SUM(F37:F38) -> 1436 | G39: =SUM(G37:G38) -> 1442 | H39: =SUM(H37:H38) -> 2798.2839 | I39: =SUM(I37:I38) -> 2056.8417 | J39: =SUM(J37:J38) -> 2269.3172 | ... Q39: =SUM(Q37:Q38) -> 5568.1053
B41: CASH FLOW FROM INVESTING ACTIVITIES
B42: Payment for property, plant and equipment and intangible assets | C42: -142 | D42: -132 | E42: -182 | F42: -153 | G42: -161 | H42: =-'FAS Seechules'!H92 -> -250.72036 | I42: =-'FAS Seechules'!I92 -> -287.97769 | J42: =-'FAS Seechules'!J92 -> -332.09794 | K42: =-'FAS Seechules'!K92 -> -384.5063 | L42: =-'FAS Seechules'!L92 -> -446.94432 | M42: =-'FAS Seechules'!M92 -> -521.54252 | N42: =-'FAS Seechules'!N92 -> -610.91009 | O42: =-'FAS Seechules'!O92 -> -718.2454 | ... Q42: =-'FAS Seechules'!Q92 -> -1003.4095
B43: Acquisition of subsidiary under business combination net of cash (refer note 42) | C43: -132 | D43: -55 | E43: -277 | F43: -103 | G43: 0 | H43: 0 | I43: 0 | J43: 0 | K43: 0 | L43: 0 | M43: 0 | N43: 0 | O43: 0 | P43: 0 | Q43: 0
B44: Proceeds from sale of property, plant and equipment | C44: 5 | D44: 3 | E44: 25 | F44: 18 | G44: 39 | H44: 0 | I44: 0 | J44: 0 | K44: 0 | L44: 0 | M44: 0 | N44: 0 | O44: 0 | P44: 0 | Q44: 0
B45: Purchase of non current investments | C45: 0 | D45: 0 | E45: 0 | F45: 0 | G45: -46 | H45: ='Balance Sheet'!G18-'Balance Sheet'!H18 -> -154.49629 | I45: ='Balance Sheet'!H18-'Balance Sheet'!I18 -> -36.087052 | J45: ='Balance Sheet'!I18-'Balance Sheet'!J18 -> -42.153623 | K45: ='Balance Sheet'!J18-'Balance Sheet'!K18 -> -49.717892 | L45: ='Balance Sheet'!K18-'Balance Sheet'!L18 -> -59.209824 | M45: ='Balance Sheet'!L18-'Balance Sheet'!M18 -> -71.188196 | N45: ='Balance Sheet'!M18-'Balance Sheet'!N18 -> -86.379607 | O45: ='Balance Sheet'!N18-'Balance Sheet'!O18 -> -105.72932 | ... Q45: ='Balance Sheet'!P18-'Balance Sheet'!Q18 -> -162.19598
B46: Proceeds from sale of non current investments | C46: 0 | D46: 0 | E46: 0 | F46: 233 | G46: 60 | H46: =SUM('Balance Sheet'!G19:G23)-SUM('Balance Sheet'!H19:H23) -> -122.68027 | I46: =SUM('Balance Sheet'!H19:H23)-SUM('Balance Sheet'!I19:I23) -> -35.616693 | J46: =SUM('Balance Sheet'!I19:I23)-SUM('Balance Sheet'!J19:J23) -> -41.604193 | K46: =SUM('Balance Sheet'!J19:J23)-SUM('Balance Sheet'!K19:K23) -> -49.069869 | L46: =SUM('Balance Sheet'!K19:K23)-SUM('Balance Sheet'!L19:L23) -> -58.438083 | M46: =SUM('Balance Sheet'!L19:L23)-SUM('Balance Sheet'!M19:M23) -> -70.260329 | N46: =SUM('Balance Sheet'!M19:M23)-SUM('Balance Sheet'!N19:N23) -> -85.253735 | O46: =SUM('Balance Sheet'!N19:N23)-SUM('Balance Sheet'!O19:O23) -> -104.35125 | ... Q46: =SUM('Balance Sheet'!P19:P23)-SUM('Balance Sheet'!Q19:Q23) -> -160.08191
B47: (Payment for)/ proceeds from purchase / sale of investments (net) | C47: 164 | D47: -146 | E47: -130 | F47: 147 | G47: -926 | H47: 0 | I47: 0 | J47: 0 | K47: 0 | L47: 0 | M47: 0 | N47: 0 | O47: 0 | P47: 0 | Q47: 0
B48: Proceeds from sale of investments in Joint venture | C48: 1 | D48: 0 | E48: 0 | F48: 0 | G48: 0 | H48: 0 | I48: 0 | J48: 0 | K48: 0 | L48: 0 | M48: 0 | N48: 0 | O48: 0 | P48: 0 | Q48: 0
B49: Other bank balance taken over pursuant to Business combination | C49: 0 | D49: 3 | E49: 0 | F49: 0 | G49: 0 | H49: 0 | I49: 0 | J49: 0 | K49: 0 | L49: 0 | M49: 0 | N49: 0 | O49: 0 | P49: 0 | Q49: 0
B50: (Purchase) / redemption of Inter-corporate deposits (net) | C50: -295 | D50: 215 | E50: -90 | F50: 200 | G50: 0 | H50: 0 | I50: 0 | J50: 0 | K50: 0 | L50: 0 | M50: 0 | N50: 0 | O50: 0 | P50: 0 | Q50: 0
B51: Investment in bank deposits (having original maturity more than 3 months) (net) | C51: -591 | D51: 483 | E51: -259 | F51: -232 | G51: 343 | H51: 0 | I51: 0 | J51: 0 | K51: 0 | L51: 0 | M51: 0 | N51: 0 | O51: 0 | P51: 0 | Q51: 0
B52: Interest received | C52: 52 | D52: 57 | E52: 48 | F52: 66 | G52: 70 | H52: 0 | I52: 0 | J52: 0 | K52: 0 | L52: 0 | M52: 0 | N52: 0 | O52: 0 | P52: 0 | Q52: 0
B53: Net cash generated / (utilised) in investing activities (B) | C53: =SUM(C42:C52) -> -938 | D53: =SUM(D42:D52) -> 428 | E53: =SUM(E42:E52) -> -865 | F53: =SUM(F42:F52) -> 176 | G53: =SUM(G42:G52) -> -621 | H53: =SUM(H42:H52) -> -527.89692 | I53: =SUM(I42:I52) -> -359.68143 | J53: =SUM(J42:J52) -> -415.85576 | ... Q53: =SUM(Q42:Q52) -> -1325.6874
B55: CASH FLOW FROM FINANCING ACTIVITIES
B56: Proceeds from issuance of share capital | C56: 6 | D56: 41 | E56: 9 | F56: 34 | G56: 46 | H56: 0 | I56: 0 | J56: 0 | K56: 0 | L56: 0 | M56: 0 | N56: 0 | O56: 0 | P56: 0 | Q56: 0
B57: (Purchase)/ sale of investments by WEOMA trust (net) | C57: -9 | D57: -8 | E57: 4 | F57: 2 | G57: -12 | H57: 0 | I57: 0 | J57: 0 | K57: 0 | L57: 0 | M57: 0 | N57: 0 | O57: 0 | P57: 0 | Q57: 0
B58: Other borrowings (repaid) / taken (net) | C58: 13 | D58: -3 | E58: 128 | F58: -91 | G58: -5 | H58: 0 | I58: 0 | J58: 0 | K58: 0 | L58: 0 | M58: 0 | N58: 0 | O58: 0 | P58: 0 | Q58: 0
B59: Dividend paid to minority Interest | C59: -22 | D59: -22 | E59: -25 | F59: 0 | G59: -47 | H59: 0 | I59: 0 | J59: 0 | K59: 0 | L59: 0 | M59: 0 | N59: 0 | O59: 0 | P59: 0 | Q59: 0
B60: Acquisition of non controlling interest | C60: 0 | D60: 0 | E60: 0 | F60: -141 | G60: -70 | H60: 0 | I60: 0 | J60: 0 | K60: 0 | L60: 0 | M60: 0 | N60: 0 | O60: 0 | P60: 0 | Q60: 0
B61: Interest paid | C61: -21 | D61: -28 | E61: -42 | F61: -54 | G61: -51 | H61: ='P&L Statement '!H26 -> -63.701955 | I61: ='P&L Statement '!I26 -> -69.958187 | J61: ='P&L Statement '!J26 -> -77.272682 | K61: ='P&L Statement '!K26 -> -85.907524 | L61: ='P&L Statement '!L26 -> -96.20011 | M61: ='P&L Statement '!M26 -> -108.58572 | N61: ='P&L Statement '!N26 -> -123.62692 | O61: ='P&L Statement '!O26 -> -142.05187 | ... Q61: ='P&L Statement '!Q26 -> -175.12579
B62: Repayment of principal portion of lease liabilities | C62: -44 | D62: -64 | E62: -41 | F62: -52 | G62: -43 | H62: 0 | I62: 0 | J62: 0 | K62: 0 | L62: 0 | M62: 0 | N62: 0 | O62: 0 | P62: 0 | Q62: 0
B63: Interest on lease liabilities | C63: -13 | D63: -11 | E63: -11 | F63: -11 | G63: -14 | H63: =SUM('Balance Sheet'!H52:H57)-SUM('Balance Sheet'!G52:G57) -> -798.15825 | I63: =SUM('Balance Sheet'!I52:I57)-SUM('Balance Sheet'!H52:H57) -> 79.386622 | J63: =SUM('Balance Sheet'!J52:J57)-SUM('Balance Sheet'!I52:I57) -> 92.732257 | K63: =SUM('Balance Sheet'!K52:K57)-SUM('Balance Sheet'!J52:J57) -> 109.37262 | L63: =SUM('Balance Sheet'!L52:L57)-SUM('Balance Sheet'!K52:K57) -> 130.25359 | M63: =SUM('Balance Sheet'!M52:M57)-SUM('Balance Sheet'!L52:L57) -> 156.60438 | N63: =SUM('Balance Sheet'!N52:N57)-SUM('Balance Sheet'!M52:M57) -> 190.02343 | O63: =SUM('Balance Sheet'!O52:O57)-SUM('Balance Sheet'!N52:N57) -> 232.59018 | ... Q63: =SUM('Balance Sheet'!Q52:Q57)-SUM('Balance Sheet'!P52:P57) -> 356.80916
B64: Dividends paid to company's shareholders | C64: -968 | D64: -1195 | E64: -582 | F64: -1229 | G64: -453 | H64: ='P&L Statement '!H44 -> -1142.0254 | I64: ='P&L Statement '!I44 -> -1243.7123 | J64: ='P&L Statement '!J44 -> -1361.4426 | K64: ='P&L Statement '!K44 -> -1499.2175 | L64: ='P&L Statement '!L44 -> -1662.2259 | M64: ='P&L Statement '!M44 -> -1857.2106 | N64: ='P&L Statement '!N44 -> -2092.9483 | O64: ='P&L Statement '!O44 -> -2380.8773 | ... Q64: ='P&L Statement '!Q44 -> -3186.7669
B65: Net cash utilised in financing activities (C) | C65: =SUM(C56:C64) -> -1058 | D65: =SUM(D56:D64) -> -1290 | E65: =SUM(E56:E64) -> -560 | F65: =SUM(F56:F64) -> -1542 | G65: =SUM(G56:G64) -> -649 | H65: =SUM(H56:H64) -> -2003.8856 | I65: =SUM(I56:I64) -> -1234.2839 | J65: =SUM(J56:J64) -> -1345.983 | ... Q65: =SUM(Q56:Q64) -> -3005.0835
B66: Effect of exchange difference on translation of foreign currency (D) | C66: 5 | D66: 2 | E66: -63 | F66: -49 | G66: -79 | H66: 0 | I66: 0 | J66: 0 | K66: 0 | L66: 0 | M66: 0 | N66: 0 | O66: 0 | P66: 0 | Q66: 0
B67: NET INCREASE / (DECREASE) IN CASH & CASH EQUIVALENTS (A+B+C+D) | C67: =C39+C53+C65+C66 -> 16 | D67: =D39+D53+D65+D66 -> 156 | E67: =E39+E53+E65+E66 -> -69 | F67: =F39+F53+F65+F66 -> 21 | G67: =G39+G53+G65+G66 -> 93 | H67: =H39+H53+H65+H66 -> 266.50131 | I67: =I39+I53+I65+I66 -> 462.87642 | J67: =J39+J53+J65+J66 -> 507.47842 | ... Q67: =Q39+Q53+Q65+Q66 -> 1237.3343
B68: Cash and cash equivalents at the beginning of the financial year | C68: 93 | D68: 109 | E68: 276 | F68: 207 | G68: 228 | H68: =G70 -> 321 | I68: =H70 -> 587.50131 | J68: =I70 -> 1050.3777 | K68: =J70 -> 1557.8561 | L68: =K70 -> 2118.0857 | M68: =L70 -> 2741.4249 | N68: =M70 -> 3441.1158 | O68: =N70 -> 4234.1683 | ... Q68: =P70 -> 6194.5575
B69: Cash and cash equivalents acquired on Business Combination | D69: 11
B70: Cash and cash equivalents at end of the year (Refer note 6 (d)) | C70: =C67+C68+C69 -> 109 | D70: =D67+D68+D69 -> 276 | E70: =E67+E68+E69 -> 207 | F70: =F67+F68+F69 -> 228 | G70: =G67+G68+G69 -> 321 | H70: =H67+H68+H69 -> 587.50131 | I70: =I67+I68+I69 -> 1050.3777 | J70: =J67+J68+J69 -> 1557.8561 | ... Q70: =Q67+Q68+Q69 -> 7431.8919

Sheet B_Sheet Forecast
B4: Balance Sheet Forecast
B5: All Figure In INR Cr.
B6: Particulars | C6: 2021 | D6: =C6+1 -> 2022 | E6: =D6+1 -> 2023 | F6: =E6+1 -> 2024 | G6: =F6+1 -> 2025 | H6: =G6+1 -> 2026 | I6: =H6+1 -> 2027 | J6: =I6+1 -> 2028 | K6: =J6+1 -> 2029 | ... Q6: =P6+1 -> 2035
B7: Non-current assets
B9: (i) Investments | C9: ='Balance Sheet'!C18 -> 226 | D9: ='Balance Sheet'!D18 -> 187 | E9: ='Balance Sheet'!E18 -> 518 | F9: ='Balance Sheet'!F18 -> 343 | G9: ='Balance Sheet'!G18 -> 215 | H9: =H10*'Revenue BuildUp'!H$11 -> 369.49629 | I9: =I10*'Revenue BuildUp'!I$11 -> 405.58334 | J9: =J10*'Revenue BuildUp'!J$11 -> 447.73696 | K9: =K10*'Revenue BuildUp'!K$11 -> 497.45485 | L9: =L10*'Revenue BuildUp'!L$11 -> 556.66468 | M9: =M10*'Revenue BuildUp'!M$11 -> 627.85287 | N9: =N10*'Revenue BuildUp'!N$11 -> 714.23248 | O9: =O10*'Revenue BuildUp'!O$11 -> 819.9618 | ... Q9: =Q10*'Revenue BuildUp'!Q$11 -> 1112.6254
B10: % of Revenue | C10: =C9/'Revenue BuildUp'!C$11 -> 0.028081511 | D10: =D9/'Revenue BuildUp'!D$11 -> 0.019659378 | E10: =E9/'Revenue BuildUp'!E$11 -> 0.053052028 | F10: =F9/'Revenue BuildUp'!F$11 -> 0.035532995 | G10: =G9/'Revenue BuildUp'!G$11 -> 0.019850429 | H10: =AVERAGE(C10:G10) -> 0.031235268 | I10: =H10 -> 0.031235268 | J10: =I10 -> 0.031235268 | K10: =J10 -> 0.031235268 | L10: =K10 -> 0.031235268 | M10: =L10 -> 0.031235268 | N10: =M10 -> 0.031235268 | O10: =N10 -> 0.031235268 | P10: =O10 -> 0.031235268 | Q10: =P10 -> 0.031235268
B11: (ii) Loans | C11: ='Balance Sheet'!C19 -> 4 | D11: ='Balance Sheet'!D19 -> 4 | E11: ='Balance Sheet'!E19 -> 4 | F11: ='Balance Sheet'!F19 -> 4 | G11: ='Balance Sheet'!G19 -> 6 | H11: =H12*'Revenue BuildUp'!H$11 -> 5.431027 | I11: =I12*'Revenue BuildUp'!I$11 -> 5.9614511 | J11: =J12*'Revenue BuildUp'!J$11 -> 6.5810445 | K11: =K12*'Revenue BuildUp'!K$11 -> 7.311821 | L11: =L12*'Revenue BuildUp'!L$11 -> 8.1821143 | M11: =M12*'Revenue BuildUp'!M$11 -> 9.2284713 | N11: =N12*'Revenue BuildUp'!N$11 -> 10.498119 | O11: =O12*'Revenue BuildUp'!O$11 -> 12.052177 | ... Q11: =Q12*'Revenue BuildUp'!Q$11 -> 16.353881
B12: % of Revenue | C12: =C11/'Revenue BuildUp'!C$11 -> 0.00049701789 | D12: =D11/'Revenue BuildUp'!D$11 -> 0.00042052145 | E12: =E11/'Revenue BuildUp'!E$11 -> 0.00040966817 | F12: =F11/'Revenue BuildUp'!F$11 -> 0.00041437895 | G12: =G11/'Revenue BuildUp'!G$11 -> 0.00055396547 | H12: =AVERAGE(C12:G12) -> 0.00045911039 | I12: =H12 -> 0.00045911039 | J12: =I12 -> 0.00045911039 | K12: =J12 -> 0.00045911039 | L12: =K12 -> 0.00045911039 | M12: =L12 -> 0.00045911039 | N12: =M12 -> 0.00045911039 | O12: =N12 -> 0.00045911039 | P12: =O12 -> 0.00045911039 | Q12: =P12 -> 0.00045911039
B13: (iii) Other financial assets | C13: ='Balance Sheet'!C20 -> 41 | D13: ='Balance Sheet'!D20 -> 17 | E13: ='Balance Sheet'!E20 -> 32 | F13: ='Balance Sheet'!F20 -> 100 | G13: ='Balance Sheet'!G20 -> 22 | H13: =H14*'Revenue BuildUp'!H$11 -> 53.350087 | I13: =I14*'Revenue BuildUp'!I$11 -> 58.560551 | J13: =J14*'Revenue BuildUp'!J$11 -> 64.646944 | K13: =K14*'Revenue BuildUp'!K$11 -> 71.825511 | L13: =L14*'Revenue BuildUp'!L$11 -> 80.37458 | M13: =M14*'Revenue BuildUp'!M$11 -> 90.653158 | N13: =N14*'Revenue BuildUp'!N$11 -> 103.12516 | O13: =O14*'Revenue BuildUp'!O$11 -> 118.391 | ... Q13: =Q14*'Revenue BuildUp'!Q$11 -> 160.64751
B14: % of Revenue | C14: =C13/'Revenue BuildUp'!C$11 -> 0.0050944334 | D14: =D13/'Revenue BuildUp'!D$11 -> 0.0017872161 | E14: =E13/'Revenue BuildUp'!E$11 -> 0.0032773454 | F14: =F13/'Revenue BuildUp'!F$11 -> 0.010359474 | G14: =G13/'Revenue BuildUp'!G$11 -> 0.0020312067 | H14: =AVERAGE(C14:G14) -> 0.0045099351 | I14: =H14 -> 0.0045099351 | J14: =I14 -> 0.0045099351 | K14: =J14 -> 0.0045099351 | L14: =K14 -> 0.0045099351 | M14: =L14 -> 0.0045099351 | N14: =M14 -> 0.0045099351 | O14: =N14 -> 0.0045099351 | P14: =O14 -> 0.0045099351 | Q14: =P14 -> 0.0045099351
B15: Deferred tax assets (net) | C15: ='Balance Sheet'!C21 -> 186 | D15: ='Balance Sheet'!D21 -> 187 | E15: ='Balance Sheet'!E21 -> 146 | F15: ='Balance Sheet'!F21 -> 68 | G15: ='Balance Sheet'!G21 -> 57 | H15: =H16*'Revenue BuildUp'!H$11 -> 165.68507 | I15: =I16*'Revenue BuildUp'!I$11 -> 181.86679 | J15: =J16*'Revenue BuildUp'!J$11 -> 200.76881 | K15: =K16*'Revenue BuildUp'!K$11 -> 223.06271 | L15: =L16*'Revenue BuildUp'!L$11 -> 249.61286 | M15: =M16*'Revenue BuildUp'!M$11 -> 281.53422 | N15: =N16*'Revenue BuildUp'!N$11 -> 320.26752 | O15: =O16*'Revenue BuildUp'!O$11 -> 367.67739 | ... Q15: =Q16*'Revenue BuildUp'!Q$11 -> 498.91005
B16: % of Revenue | C16: =C15/'Revenue BuildUp'!C$11 -> 0.023111332 | D16: =D15/'Revenue BuildUp'!D$11 -> 0.019659378 | E16: =E15/'Revenue BuildUp'!E$11 -> 0.014952888 | F16: =F15/'Revenue BuildUp'!F$11 -> 0.0070444421 | G16: =G15/'Revenue BuildUp'!G$11 -> 0.005262672 | H16: =AVERAGE(C16:G16) -> 0.014006142 | I16: =H16 -> 0.014006142 | J16: =I16 -> 0.014006142 | K16: =J16 -> 0.014006142 | L16: =K16 -> 0.014006142 | M16: =L16 -> 0.014006142 | N16: =M16 -> 0.014006142 | O16: =N16 -> 0.014006142 | P16: =O16 -> 0.014006142 | Q16: =P16 -> 0.014006142
B17: Non current tax assets (net) | C17: ='Balance Sheet'!C22 -> 55 | D17: ='Balance Sheet'!D22 -> 57 | E17: ='Balance Sheet'!E22 -> 67 | F17: ='Balance Sheet'!F22 -> 95 | G17: ='Balance Sheet'!G22 -> 108 | H17: =H18*'Revenue BuildUp'!H$11 -> 93.455667 | I17: =I18*'Revenue BuildUp'!I$11 -> 102.58306 | J17: =J18*'Revenue BuildUp'!J$11 -> 113.24486 | K17: =K18*'Revenue BuildUp'!K$11 -> 125.81987 | L17: =L18*'Revenue BuildUp'!L$11 -> 140.79565 | M17: =M18*'Revenue BuildUp'!M$11 -> 158.80108 | N17: =N18*'Revenue BuildUp'!N$11 -> 180.64883 | O17: =O18*'Revenue BuildUp'!O$11 -> 207.39066 | ... Q17: =Q18*'Revenue BuildUp'!Q$11 -> 281.41323
B18: % of Revenue | C18: =C17/'Revenue BuildUp'!C$11 -> 0.006833996 | D18: =D17/'Revenue BuildUp'!D$11 -> 0.0059924306 | E18: =E17/'Revenue BuildUp'!E$11 -> 0.0068619418 | F18: =F17/'Revenue BuildUp'!F$11 -> 0.0098415001 | G18: =G17/'Revenue BuildUp'!G$11 -> 0.0099713785 | H18: =AVERAGE(C18:G18) -> 0.0079002494 | I18: =H18 -> 0.0079002494 | J18: =I18 -> 0.0079002494 | K18: =J18 -> 0.0079002494 | L18: =K18 -> 0.0079002494 | M18: =L18 -> 0.0079002494 | N18: =M18 -> 0.0079002494 | O18: =N18 -> 0.0079002494 | P18: =O18 -> 0.0079002494 | Q18: =P18 -> 0.0079002494
B19: Other non-current assets | C19: ='Balance Sheet'!C23 -> 26 | D19: ='Balance Sheet'!D23 -> 30 | E19: ='Balance Sheet'!E23 -> 46 | F19: ='Balance Sheet'!F23 -> 40 | G19: ='Balance Sheet'!G23 -> 49 | H19: =H20*'Revenue BuildUp'!H$11 -> 46.758421 | I19: =I20*'Revenue BuildUp'!I$11 -> 51.325107 | J19: =J20*'Revenue BuildUp'!J$11 -> 56.659496 | K19: =K20*'Revenue BuildUp'!K$11 -> 62.951115 | L19: =L20*'Revenue BuildUp'!L$11 -> 70.443905 | M19: =M20*'Revenue BuildUp'!M$11 -> 79.452514 | N19: =N20*'Revenue BuildUp'!N$11 -> 90.383541 | O19: =O20*'Revenue BuildUp'!O$11 -> 103.76321 | ... Q19: =Q20*'Revenue BuildUp'!Q$11 -> 140.79872
B20: % of Revenue | C20: =C19/'Revenue BuildUp'!C$11 -> 0.0032306163 | D20: =D19/'Revenue BuildUp'!D$11 -> 0.0031539108 | E20: =E19/'Revenue BuildUp'!E$11 -> 0.0047111839 | F20: =F19/'Revenue BuildUp'!F$11 -> 0.0041437895 | G20: =G19/'Revenue BuildUp'!G$11 -> 0.0045240513 | H20: =AVERAGE(C20:G20) -> 0.0039527104 | I20: =H20 -> 0.0039527104 | J20: =I20 -> 0.0039527104 | K20: =J20 -> 0.0039527104 | L20: =K20 -> 0.0039527104 | M20: =L20 -> 0.0039527104 | N20: =M20 -> 0.0039527104 | O20: =N20 -> 0.0039527104 | P20: =O20 -> 0.0039527104 | Q20: =P20 -> 0.0039527104
B22: Current assets
B24: (i) Investments | C24: ='Balance Sheet'!C28 -> 628 | D24: ='Balance Sheet'!D28 -> 641 | E24: ='Balance Sheet'!E28 -> 578 | F24: ='Balance Sheet'!F28 -> 259 | G24: ='Balance Sheet'!G28 -> 1375 | H24: =H25*'Revenue BuildUp'!H$11 -> 847.93289 | I24: =I25*'Revenue BuildUp'!I$11 -> 930.7467 | J24: =J25*'Revenue BuildUp'!J$11 -> 1027.4823 | K24: =K25*'Revenue BuildUp'!K$11 -> 1141.5766 | L24: =L25*'Revenue BuildUp'!L$11 -> 1277.4534 | M24: =M25*'Revenue BuildUp'!M$11 -> 1440.8185 | N24: =N25*'Revenue BuildUp'!N$11 -> 1639.0454 | O24: =O25*'Revenue BuildUp'!O$11 -> 1881.6768 | ... Q24: =Q25*'Revenue BuildUp'!Q$11 -> 2553.2912
B25: % of Revenue | C25: =C24/'Revenue BuildUp'!C$11 -> 0.078031809 | D25: =D24/'Revenue BuildUp'!D$11 -> 0.067388562 | E25: =E24/'Revenue BuildUp'!E$11 -> 0.05919705 | F25: =F24/'Revenue BuildUp'!F$11 -> 0.026831037 | G25: =G24/'Revenue BuildUp'!G$11 -> 0.12695042 | H25: =AVERAGE(C25:G25) -> 0.071679776 | I25: =H25 -> 0.071679776 | J25: =I25 -> 0.071679776 | K25: =J25 -> 0.071679776 | L25: =K25 -> 0.071679776 | M25: =L25 -> 0.071679776 | N25: =M25 -> 0.071679776 | O25: =N25 -> 0.071679776 | P25: =O25 -> 0.071679776 | Q25: =P25 -> 0.071679776
B26: (v) Loans | C26: ='Balance Sheet'!C32 -> 6 | D26: ='Balance Sheet'!D32 -> 5 | E26: ='Balance Sheet'!E32 -> 4 | F26: ='Balance Sheet'!F32 -> 6 | G26: ='Balance Sheet'!G32 -> 7 | H26: =H27*'Revenue BuildUp'!H$11 -> 6.9763241 | I26: =I27*'Revenue BuildUp'!I$11 -> 7.6576705 | J26: =J27*'Revenue BuildUp'!J$11 -> 8.4535576 | K26: =K27*'Revenue BuildUp'!K$11 -> 9.3922629 | L26: =L27*'Revenue BuildUp'!L$11 -> 10.510182 | M26: =M27*'Revenue BuildUp'!M$11 -> 11.85426 | N26: =N27*'Revenue BuildUp'!N$11 -> 13.485162 | O26: =O27*'Revenue BuildUp'!O$11 -> 15.481399 | ... Q26: =Q27*'Revenue BuildUp'!Q$11 -> 21.007072
B27: % of Revenue | C27: =C26/'Revenue BuildUp'!C$11 -> 0.00074552684 | D27: =D26/'Revenue BuildUp'!D$11 -> 0.00052565181 | E27: =E26/'Revenue BuildUp'!E$11 -> 0.00040966817 | F27: =F26/'Revenue BuildUp'!F$11 -> 0.00062156842 | G27: =G26/'Revenue BuildUp'!G$11 -> 0.00064629305 | H27: =AVERAGE(C27:G27) -> 0.00058974166 | I27: =H27 -> 0.00058974166 | J27: =I27 -> 0.00058974166 | K27: =J27 -> 0.00058974166 | L27: =K27 -> 0.00058974166 | M27: =L27 -> 0.00058974166 | N27: =M27 -> 0.00058974166 | O27: =N27 -> 0.00058974166 | P27: =O27 -> 0.00058974166 | Q27: =P27 -> 0.00058974166
B28: (vi) Other financial assets | C28: ='Balance Sheet'!C33 -> 5 | D28: ='Balance Sheet'!D33 -> 2 | E28: ='Balance Sheet'!E33 -> 4 | F28: ='Balance Sheet'!F33 -> 5 | G28: ='Balance Sheet'!G33 -> 3 | H28: =H29*'Revenue BuildUp'!H$11 -> 4.8173283 | I28: =I29*'Revenue BuildUp'!I$11 -> 5.2878152 | J28: =J29*'Revenue BuildUp'!J$11 -> 5.8373954 | K28: =K29*'Revenue BuildUp'!K$11 -> 6.4855952 | L28: =L29*'Revenue BuildUp'!L$11 -> 7.2575465 | M28: =M29*'Revenue BuildUp'!M$11 -> 8.1856666 | N28: =N29*'Revenue BuildUp'!N$11 -> 9.3118455 | O28: =O29*'Revenue BuildUp'!O$11 -> 10.690297 | ... Q28: =Q29*'Revenue BuildUp'!Q$11 -> 14.505915
B29: % of Revenue | C29: =C28/'Revenue BuildUp'!C$11 -> 0.00062127237 | D29: =D28/'Revenue BuildUp'!D$11 -> 0.00021026072 | E29: =E28/'Revenue BuildUp'!E$11 -> 0.00040966817 | F29: =F28/'Revenue BuildUp'!F$11 -> 0.00051797369 | G29: =G28/'Revenue BuildUp'!G$11 -> 0.00027698273 | H29: =AVERAGE(C29:G29) -> 0.00040723154 | I29: =H29 -> 0.00040723154 | J29: =I29 -> 0.00040723154 | K29: =J29 -> 0.00040723154 | L29: =K29 -> 0.00040723154 | M29: =L29 -> 0.00040723154 | N29: =M29 -> 0.00040723154 | O29: =N29 -> 0.00040723154 | P29: =O29 -> 0.00040723154 | Q29: =P29 -> 0.00040723154
B30: Current tax asset (net) | C30: ='Balance Sheet'!C34 -> 1 | D30: ='Balance Sheet'!D34 -> 1 | E30: ='Balance Sheet'!E34 -> 2 | F30: ='Balance Sheet'!F34 -> 2 | G30: ='Balance Sheet'!G34 -> 2 | H30: =H31*'Revenue BuildUp'!H$11 -> 1.9543768 | I30: =I31*'Revenue BuildUp'!I$11 -> 2.145252 | J30: =J31*'Revenue BuildUp'!J$11 -> 2.3682152 | K30: =K31*'Revenue BuildUp'!K$11 -> 2.6311881 | L30: =L31*'Revenue BuildUp'!L$11 -> 2.9443666 | M30: =M31*'Revenue BuildUp'!M$11 -> 3.3209023 | N30: =N31*'Revenue BuildUp'!N$11 -> 3.77779 | O30: =O31*'Revenue BuildUp'!O$11 -> 4.3370241 | ... Q30: =Q31*'Revenue BuildUp'!Q$11 -> 5.8850095
B31: % of Revenue | C31: =C30/'Revenue BuildUp'!C$11 -> 0.00012425447 | D31: =D30/'Revenue BuildUp'!D$11 -> 0.00010513036 | E31: =E30/'Revenue BuildUp'!E$11 -> 0.00020483408 | F31: =F30/'Revenue BuildUp'!F$11 -> 0.00020718947 | G31: =G30/'Revenue BuildUp'!G$11 -> 0.00018465516 | H31: =AVERAGE(C31:G31) -> 0.00016521271 | I31: =H31 -> 0.00016521271 | J31: =I31 -> 0.00016521271 | K31: =J31 -> 0.00016521271 | L31: =K31 -> 0.00016521271 | M31: =L31 -> 0.00016521271 | N31: =M31 -> 0.00016521271 | O31: =N31 -> 0.00016521271 | P31: =O31 -> 0.00016521271 | Q31: =P31 -> 0.00016521271
B32: Other current assets | C32: ='Balance Sheet'!C35 -> 224 | D32: ='Balance Sheet'!D35 -> 213 | E32: ='Balance Sheet'!E35 -> 229 | F32: ='Balance Sheet'!F35 -> 378 | G32: ='Balance Sheet'!G35 -> 413 | H32: =H33*'Revenue BuildUp'!H$11 -> 357.17717 | I32: =I33*'Revenue BuildUp'!I$11 -> 392.06106 | J32: =J33*'Revenue BuildUp'!J$11 -> 432.80927 | K32: =K33*'Revenue BuildUp'!K$11 -> 480.86955 | L32: =L33*'Revenue BuildUp'!L$11 -> 538.1053 | M32: =M33*'Revenue BuildUp'!M$11 -> 606.92006 | N32: =N33*'Revenue BuildUp'!N$11 -> 690.41975 | O32: =O33*'Revenue BuildUp'!O$11 -> 792.62402 | ... Q32: =Q33*'Revenue BuildUp'!Q$11 -> 1075.5301
B33: % of Revenue | C33: =C32/'Revenue BuildUp'!C$11 -> 0.027833002 | D33: =D32/'Revenue BuildUp'!D$11 -> 0.022392767 | E33: =E32/'Revenue BuildUp'!E$11 -> 0.023453503 | F33: =F32/'Revenue BuildUp'!F$11 -> 0.039158811 | G33: =G32/'Revenue BuildUp'!G$11 -> 0.03813129 | H33: =AVERAGE(C33:G33) -> 0.030193874 | I33: =H33 -> 0.030193874 | J33: =I33 -> 0.030193874 | K33: =J33 -> 0.030193874 | L33: =K33 -> 0.030193874 | M33: =L33 -> 0.030193874 | N33: =M33 -> 0.030193874 | O33: =N33 -> 0.030193874 | P33: =O33 -> 0.030193874 | Q33: =P33 -> 0.030193874
B34: Assets classified as held for sale | C34: ='Balance Sheet'!C36 -> 14 | D34: ='Balance Sheet'!D36 -> 0 | E34: ='Balance Sheet'!E36 -> 7 | F34: ='Balance Sheet'!F36 -> 5 | G34: ='Balance Sheet'!G36 -> 0 | H34: =H35*'Revenue BuildUp'!H$11 -> 7.0372394 | I34: =I35*'Revenue BuildUp'!I$11 -> 7.7245352 | J34: =J35*'Revenue BuildUp'!J$11 -> 8.5273718 | K34: =K35*'Revenue BuildUp'!K$11 -> 9.4742736 | L34: =L35*'Revenue BuildUp'!L$11 -> 10.601954 | M34: =M35*'Revenue BuildUp'!M$11 -> 11.957768 | N34: =N35*'Revenue BuildUp'!N$11 -> 13.602911 | O34: =O35*'Revenue BuildUp'!O$11 -> 15.616578 | ... Q34: =Q35*'Revenue BuildUp'!Q$11 -> 21.1905
B35: % of Revenue | C35: =C34/'Revenue BuildUp'!C$11 -> 0.0017395626 | D35: =D34/'Revenue BuildUp'!D$11 -> 0 | E35: =E34/'Revenue BuildUp'!E$11 -> 0.0007169193 | F35: =F34/'Revenue BuildUp'!F$11 -> 0.00051797369 | G35: =G34/'Revenue BuildUp'!G$11 -> 0 | H35: =AVERAGE(C35:G35) -> 0.00059489112 | I35: =H35 -> 0.00059489112 | J35: =I35 -> 0.00059489112 | K35: =J35 -> 0.00059489112 | L35: =K35 -> 0.00059489112 | M35: =L35 -> 0.00059489112 | N35: =M35 -> 0.00059489112 | O35: =N35 -> 0.00059489112 | P35: =O35 -> 0.00059489112 | Q35: =P35 -> 0.00059489112
B37: Non-current liabilities
B39: i) Borrowings | C39: ='Balance Sheet'!C52 -> 8 | D39: ='Balance Sheet'!D52 -> 0 | E39: ='Balance Sheet'!E52 -> 2 | F39: ='Balance Sheet'!F52 -> 0 | G39: ='Balance Sheet'!G52 -> 0 | H39: =H40*'Revenue BuildUp'!H$11 -> 2.8363961 | I39: =I40*'Revenue BuildUp'!I$11 -> 3.1134143 | J39: =J40*'Revenue BuildUp'!J$11 -> 3.4370017 | K39: =K40*'Revenue BuildUp'!K$11 -> 3.8186555 | L39: =L40*'Revenue BuildUp'!L$11 -> 4.2731729 | M39: =M40*'Revenue BuildUp'!M$11 -> 4.819641 | N39: =N40*'Revenue BuildUp'!N$11 -> 5.4827242 | O39: =O40*'Revenue BuildUp'!O$11 -> 6.2943433 | ... Q39: =Q40*'Revenue BuildUp'!Q$11 -> 8.5409416
B40: % of Revenue | C40: =C39/'Revenue BuildUp'!C$11 -> 0.00099403579 | D40: =D39/'Revenue BuildUp'!D$11 -> 0 | E40: =E39/'Revenue BuildUp'!E$11 -> 0.00020483408 | F40: =F39/'Revenue BuildUp'!F$11 -> 0 | G40: =G39/'Revenue BuildUp'!G$11 -> 0 | H40: =AVERAGE(C40:G40) -> 0.00023977397 | I40: =H40 -> 0.00023977397 | J40: =I40 -> 0.00023977397 | K40: =J40 -> 0.00023977397 | L40: =K40 -> 0.00023977397 | M40: =L40 -> 0.00023977397 | N40: =M40 -> 0.00023977397 | O40: =N40 -> 0.00023977397 | P40: =O40 -> 0.00023977397 | Q40: =P40 -> 0.00023977397
B41: ii) Lease liabilities | C41: ='Balance Sheet'!C53 -> 122 | D41: ='Balance Sheet'!D53 -> 91 | E41: ='Balance Sheet'!E53 -> 91 | F41: ='Balance Sheet'!F53 -> 104 | G41: ='Balance Sheet'!G53 -> 124 | H41: =H42*'Revenue BuildUp'!H$11 -> 133.12477 | I41: =I42*'Revenue BuildUp'!I$11 -> 146.12647 | J41: =J42*'Revenue BuildUp'!J$11 -> 161.31388 | K41: =K42*'Revenue BuildUp'!K$11 -> 179.2266 | L41: =L42*'Revenue BuildUp'!L$11 -> 200.55914 | M41: =M42*'Revenue BuildUp'!M$11 -> 226.20734 | N41: =N42*'Revenue BuildUp'!N$11 -> 257.3288 | O41: =O42*'Revenue BuildUp'!O$11 -> 295.42172 | ... Q41: =Q42*'Revenue BuildUp'!Q$11 -> 400.86464
B42: % of Revenue | C42: =C41/'Revenue BuildUp'!C$11 -> 0.015159046 | D42: =D41/'Revenue BuildUp'!D$11 -> 0.0095668629 | E42: =E41/'Revenue BuildUp'!E$11 -> 0.0093199508 | F42: =F41/'Revenue BuildUp'!F$11 -> 0.010773853 | G42: =G41/'Revenue BuildUp'!G$11 -> 0.01144862 | H42: =AVERAGE(C42:G42) -> 0.011253666 | I42: =H42 -> 0.011253666 | J42: =I42 -> 0.011253666 | K42: =J42 -> 0.011253666 | L42: =K42 -> 0.011253666 | M42: =L42 -> 0.011253666 | N42: =M42 -> 0.011253666 | O42: =N42 -> 0.011253666 | P42: =O42 -> 0.011253666 | Q42: =P42 -> 0.011253666
B43: iii) Other financial liabilities | C43: ='Balance Sheet'!C54 -> 0 | D43: ='Balance Sheet'!D54 -> 0 | E43: ='Balance Sheet'!E54 -> 266 | F43: ='Balance Sheet'!F54 -> 405 | G43: ='Balance Sheet'!G54 -> 1211 | H43: =H44*'Revenue BuildUp'!H$11 -> 428.24412 | I43: =I44*'Revenue BuildUp'!I$11 -> 470.06881 | J43: =J44*'Revenue BuildUp'!J$11 -> 518.92462 | K43: =K44*'Revenue BuildUp'!K$11 -> 576.54737 | L43: =L44*'Revenue BuildUp'!L$11 -> 645.17123 | M43: =M44*'Revenue BuildUp'!M$11 -> 727.67795 | N43: =N44*'Revenue BuildUp'!N$11 -> 827.79142 | O43: =O44*'Revenue BuildUp'!O$11 -> 950.33111 | ... Q43: =Q44*'Revenue BuildUp'!Q$11 -> 1289.5265
B44: % of Revenue | C44: =C43/'Revenue BuildUp'!C$11 -> 0 | D44: =D43/'Revenue BuildUp'!D$11 -> 0 | E44: =E43/'Revenue BuildUp'!E$11 -> 0.027242933 | F44: =F43/'Revenue BuildUp'!F$11 -> 0.041955869 | G44: =G43/'Revenue BuildUp'!G$11 -> 0.1118087 | H44: =AVERAGE(C44:G44) -> 0.0362015 | I44: =H44 -> 0.0362015 | J44: =I44 -> 0.0362015 | K44: =J44 -> 0.0362015 | L44: =K44 -> 0.0362015 | M44: =L44 -> 0.0362015 | N44: =M44 -> 0.0362015 | O44: =N44 -> 0.0362015 | P44: =O44 -> 0.0362015 | Q44: =P44 -> 0.0362015
B45: Provisions | C45: ='Balance Sheet'!C55 -> 1 | D45: ='Balance Sheet'!D55 -> 1 | E45: ='Balance Sheet'!E55 -> 4 | F45: ='Balance Sheet'!F55 -> 1 | G45: ='Balance Sheet'!G55 -> 1 | H45: =H46*'Revenue BuildUp'!H$11 -> 1.9754611 | I45: =I46*'Revenue BuildUp'!I$11 -> 2.1683955 | J45: =J46*'Revenue BuildUp'!J$11 -> 2.3937641 | K45: =K46*'Revenue BuildUp'!K$11 -> 2.6595739 | L45: =L46*'Revenue BuildUp'!L$11 -> 2.9761311 | M45: =M46*'Revenue BuildUp'!M$11 -> 3.356729 | N45: =N46*'Revenue BuildUp'!N$11 -> 3.8185457 | O45: =O46*'Revenue BuildUp'!O$11 -> 4.383813 | ... Q45: =Q46*'Revenue BuildUp'!Q$11 -> 5.9484984
B46: % of Revenue | C46: =C45/'Revenue BuildUp'!C$11 -> 0.00012425447 | D46: =D45/'Revenue BuildUp'!D$11 -> 0.00010513036 | E46: =E45/'Revenue BuildUp'!E$11 -> 0.00040966817 | F46: =F45/'Revenue BuildUp'!F$11 -> 0.00010359474 | G46: =G45/'Revenue BuildUp'!G$11 -> 9.2327578e-05 | H46: =AVERAGE(C46:G46) -> 0.00016699506 | I46: =H46 -> 0.00016699506 | J46: =I46 -> 0.00016699506 | K46: =J46 -> 0.00016699506 | L46: =K46 -> 0.00016699506 | M46: =L46 -> 0.00016699506 | N46: =M46 -> 0.00016699506 | O46: =N46 -> 0.00016699506 | P46: =O46 -> 0.00016699506 | Q46: =P46 -> 0.00016699506
B47: Employee benefit obligations (net) | C47: ='Balance Sheet'!C56 -> 24 | D47: ='Balance Sheet'!D56 -> 27 | E47: ='Balance Sheet'!E56 -> 20 | F47: ='Balance Sheet'!F56 -> 19 | G47: ='Balance Sheet'!G56 -> 27 | H47: =H48*'Revenue BuildUp'!H$11 -> 29.171709 | I47: =I48*'Revenue BuildUp'!I$11 -> 32.02078 | J47: =J48*'Revenue BuildUp'!J$11 -> 35.348806 | K47: =K48*'Revenue BuildUp'!K$11 -> 39.274031 | L47: =L48*'Revenue BuildUp'!L$11 -> 43.948642 | M47: =M48*'Revenue BuildUp'!M$11 -> 49.568946 | N47: =N48*'Revenue BuildUp'!N$11 -> 56.388611 | O47: =O48*'Revenue BuildUp'!O$11 -> 64.735935 | ... Q47: =Q48*'Revenue BuildUp'!Q$11 -> 87.841704
B48: % of Revenue | C48: =C47/'Revenue BuildUp'!C$11 -> 0.0029821074 | D48: =D47/'Revenue BuildUp'!D$11 -> 0.0028385198 | E48: =E47/'Revenue BuildUp'!E$11 -> 0.0020483408 | F48: =F47/'Revenue BuildUp'!F$11 -> 0.0019683 | G48: =G47/'Revenue BuildUp'!G$11 -> 0.0024928446 | H48: =AVERAGE(C48:G48) -> 0.0024660225 | I48: =H48 -> 0.0024660225 | J48: =I48 -> 0.0024660225 | K48: =J48 -> 0.0024660225 | L48: =K48 -> 0.0024660225 | M48: =L48 -> 0.0024660225 | N48: =M48 -> 0.0024660225 | O48: =N48 -> 0.0024660225 | P48: =O48 -> 0.0024660225 | Q48: =P48 -> 0.0024660225
B49: Deferred tax liabilities (net) | C49: ='Balance Sheet'!C57 -> 84 | D49: ='Balance Sheet'!D57 -> 109 | E49: ='Balance Sheet'!E57 -> 178 | F49: ='Balance Sheet'!F57 -> 279 | G49: ='Balance Sheet'!G57 -> 248 | H49: =H50*'Revenue BuildUp'!H$11 -> 217.48929 | I49: =I50*'Revenue BuildUp'!I$11 -> 238.7305 | J49: =J50*'Revenue BuildUp'!J$11 -> 263.54255 | K49: =K50*'Revenue BuildUp'!K$11 -> 292.80701 | L49: =L50*'Revenue BuildUp'!L$11 -> 327.65852 | M49: =M50*'Revenue BuildUp'!M$11 -> 369.56062 | N49: =N50*'Revenue BuildUp'!N$11 -> 420.40454 | O49: =O50*'Revenue BuildUp'!O$11 -> 482.6379 | ... Q49: =Q50*'Revenue BuildUp'!Q$11 -> 654.90265
B50: % of Revenue | C50: =C49/'Revenue BuildUp'!C$11 -> 0.010437376 | D50: =D49/'Revenue BuildUp'!D$11 -> 0.011459209 | E50: =E49/'Revenue BuildUp'!E$11 -> 0.018230234 | F50: =F49/'Revenue BuildUp'!F$11 -> 0.028902932 | G50: =G49/'Revenue BuildUp'!G$11 -> 0.022897239 | H50: =AVERAGE(C50:G50) -> 0.018385398 | I50: =H50 -> 0.018385398 | J50: =I50 -> 0.018385398 | K50: =J50 -> 0.018385398 | L50: =K50 -> 0.018385398 | M50: =L50 -> 0.018385398 | N50: =M50 -> 0.018385398 | O50: =N50 -> 0.018385398 | P50: =O50 -> 0.018385398 | Q50: =P50 -> 0.018385398
B52: Current liabilities
B54: (i) Borrowings | C54: ='Balance Sheet'!C61 -> 340 | D54: ='Balance Sheet'!D61 -> 345 | E54: ='Balance Sheet'!E61 -> 473 | F54: ='Balance Sheet'!F61 -> 383 | G54: ='Balance Sheet'!G61 -> 379 | H54: =H55*'Revenue BuildUp'!H$11 -> 477.03163 | I54: =I55*'Revenue BuildUp'!I$11 -> 523.62117 | J54: =J55*'Revenue BuildUp'!J$11 -> 578.04286 | K54: =K55*'Revenue BuildUp'!K$11 -> 642.23026 | L54: =L55*'Revenue BuildUp'!L$11 -> 718.67205 | M54: =M55*'Revenue BuildUp'!M$11 -> 810.57831 | N54: =N55*'Revenue BuildUp'!N$11 -> 922.09717 | O54: =O55*'Revenue BuildUp'!O$11 -> 1058.5971 | ... Q54: =Q55*'Revenue BuildUp'!Q$11 -> 1436.4352
B55: % of Revenue | C55: =C54/'Revenue BuildUp'!C$11 -> 0.042246521 | D55: =D54/'Revenue BuildUp'!D$11 -> 0.036269975 | E55: =E54/'Revenue BuildUp'!E$11 -> 0.048443261 | F55: =F54/'Revenue BuildUp'!F$11 -> 0.039676784 | G55: =G54/'Revenue BuildUp'!G$11 -> 0.034992152 | H55: =AVERAGE(C55:G55) -> 0.040325739 | I55: =H55 -> 0.040325739 | J55: =I55 -> 0.040325739 | K55: =J55 -> 0.040325739 | L55: =K55 -> 0.040325739 | M55: =L55 -> 0.040325739 | N55: =M55 -> 0.040325739 | O55: =N55 -> 0.040325739 | P55: =O55 -> 0.040325739 | Q55: =P55 -> 0.040325739
B56: (ii) Lease liabilities | C56: ='Balance Sheet'!C62 -> 38 | D56: ='Balance Sheet'!D62 -> 43 | E56: ='Balance Sheet'!E62 -> 42 | F56: ='Balance Sheet'!F62 -> 41 | G56: ='Balance Sheet'!G62 -> 51 | H56: =H57*'Revenue BuildUp'!H$11 -> 53.232281 | I56: =I57*'Revenue BuildUp'!I$11 -> 58.43124 | J56: =J57*'Revenue BuildUp'!J$11 -> 64.504193 | K56: =K57*'Revenue BuildUp'!K$11 -> 71.666909 | L56: =L57*'Revenue BuildUp'!L$11 -> 80.1971 | M56: =M57*'Revenue BuildUp'!M$11 -> 90.452981 | N56: =N57*'Revenue BuildUp'!N$11 -> 102.89745 | O56: =O57*'Revenue BuildUp'!O$11 -> 118.12957 | ... Q56: =Q57*'Revenue BuildUp'!Q$11 -> 160.29278
B57: % of Revenue | C57: =C56/'Revenue BuildUp'!C$11 -> 0.00472167 | D57: =D56/'Revenue BuildUp'!D$11 -> 0.0045206056 | E57: =E56/'Revenue BuildUp'!E$11 -> 0.0043015158 | F57: =F56/'Revenue BuildUp'!F$11 -> 0.0042473842 | G57: =G56/'Revenue BuildUp'!G$11 -> 0.0047087065 | H57: =AVERAGE(C57:G57) -> 0.0044999764 | I57: =H57 -> 0.0044999764 | J57: =I57 -> 0.0044999764 | K57: =J57 -> 0.0044999764 | L57: =K57 -> 0.0044999764 | M57: =L57 -> 0.0044999764 | N57: =M57 -> 0.0044999764 | O57: =N57 -> 0.0044999764 | P57: =O57 -> 0.0044999764 | Q57: =P57 -> 0.0044999764
B58: (iv) Other financial liabilities | C58: ='Balance Sheet'!C66 -> 44 | D58: ='Balance Sheet'!D66 -> 45 | E58: ='Balance Sheet'!E66 -> 40 | F58: ='Balance Sheet'!F66 -> 59 | G58: ='Balance Sheet'!G66 -> 231 | H58: =H59*'Revenue BuildUp'!H$11 -> 98.739313 | I58: =I59*'Revenue BuildUp'!I$11 -> 108.38274 | J58: =J59*'Revenue BuildUp'!J$11 -> 119.64732 | K58: =K59*'Revenue BuildUp'!K$11 -> 132.93327 | L58: =L59*'Revenue BuildUp'!L$11 -> 148.75572 | M58: =M59*'Revenue BuildUp'!M$11 -> 167.77912 | N58: =N59*'Revenue BuildUp'!N$11 -> 190.86207 | O58: =O59*'Revenue BuildUp'!O$11 -> 219.11577 | ... Q58: =Q59*'Revenue BuildUp'!Q$11 -> 297.32332
B59: % of Revenue | C59: =C58/'Revenue BuildUp'!C$11 -> 0.0054671968 | D59: =D58/'Revenue BuildUp'!D$11 -> 0.0047308663 | E59: =E58/'Revenue BuildUp'!E$11 -> 0.0040966817 | F59: =F58/'Revenue BuildUp'!F$11 -> 0.0061120895 | G59: =G58/'Revenue BuildUp'!G$11 -> 0.021327671 | H59: =AVERAGE(C59:G59) -> 0.008346901 | I59: =H59 -> 0.008346901 | J59: =I59 -> 0.008346901 | K59: =J59 -> 0.008346901 | L59: =K59 -> 0.008346901 | M59: =L59 -> 0.008346901 | N59: =M59 -> 0.008346901 | O59: =N59 -> 0.008346901 | P59: =O59 -> 0.008346901 | Q59: =P59 -> 0.008346901
B60: Other current liabilities | C60: ='Balance Sheet'!C67 -> 287 | D60: ='Balance Sheet'!D67 -> 224 | E60: ='Balance Sheet'!E67 -> 217 | F60: ='Balance Sheet'!F67 -> 211 | G60: ='Balance Sheet'!G67 -> 232 | H60: =H61*'Revenue BuildUp'!H$11 -> 295.05796 | I60: =I61*'Revenue BuildUp'!I$11 -> 323.87495 | J60: =J61*'Revenue BuildUp'!J$11 -> 357.53635 | K60: =K61*'Revenue BuildUp'!K$11 -> 397.23813 | L60: =L61*'Revenue BuildUp'!L$11 -> 444.5196 | M60: =M61*'Revenue BuildUp'!M$11 -> 501.3663 | N60: =N61*'Revenue BuildUp'!N$11 -> 570.34396 | O60: =O61*'Revenue BuildUp'!O$11 -> 654.77317 | ... Q60: =Q61*'Revenue BuildUp'!Q$11 -> 888.47703
B61: % of Revenue | C61: =C60/'Revenue BuildUp'!C$11 -> 0.035661034 | D61: =D60/'Revenue BuildUp'!D$11 -> 0.023549201 | E61: =E60/'Revenue BuildUp'!E$11 -> 0.022224498 | F61: =F60/'Revenue BuildUp'!F$11 -> 0.02185849 | G61: =G60/'Revenue BuildUp'!G$11 -> 0.021419998 | H61: =AVERAGE(C61:G61) -> 0.024942644 | I61: =H61 -> 0.024942644 | J61: =I61 -> 0.024942644 | K61: =J61 -> 0.024942644 | L61: =K61 -> 0.024942644 | M61: =L61 -> 0.024942644 | N61: =M61 -> 0.024942644 | O61: =N61 -> 0.024942644 | P61: =O61 -> 0.024942644 | Q61: =P61 -> 0.024942644
B62: Provisions | C62: ='Balance Sheet'!C68 -> 20 | D62: ='Balance Sheet'!D68 -> 21 | E62: ='Balance Sheet'!E68 -> 44 | F62: ='Balance Sheet'!F68 -> 7 | G62: ='Balance Sheet'!G68 -> 21 | H62: =H63*'Revenue BuildUp'!H$11 -> 28.06709 | I62: =I63*'Revenue BuildUp'!I$11 -> 30.808278 | J62: =J63*'Revenue BuildUp'!J$11 -> 34.010284 | K62: =K63*'Revenue BuildUp'!K$11 -> 37.786876 | L62: =L63*'Revenue BuildUp'!L$11 -> 42.284478 | M62: =M63*'Revenue BuildUp'!M$11 -> 47.691963 | N62: =N63*'Revenue BuildUp'!N$11 -> 54.253394 | O62: =O63*'Revenue BuildUp'!O$11 -> 62.284637 | ... Q62: =Q63*'Revenue BuildUp'!Q$11 -> 84.51548
B63: % of Revenue | C63: =C62/'Revenue BuildUp'!C$11 -> 0.0024850895 | D63: =D62/'Revenue BuildUp'!D$11 -> 0.0022077376 | E63: =E62/'Revenue BuildUp'!E$11 -> 0.0045063499 | F63: =F62/'Revenue BuildUp'!F$11 -> 0.00072516316 | G63: =G62/'Revenue BuildUp'!G$11 -> 0.0019388791 | H63: =AVERAGE(C63:G63) -> 0.0023726438 | I63: =H63 -> 0.0023726438 | J63: =I63 -> 0.0023726438 | K63: =J63 -> 0.0023726438 | L63: =K63 -> 0.0023726438 | M63: =L63 -> 0.0023726438 | N63: =M63 -> 0.0023726438 | O63: =N63 -> 0.0023726438 | P63: =O63 -> 0.0023726438 | Q63: =P63 -> 0.0023726438
B64: Employee benefit obligations (net) | C64: ='Balance Sheet'!C69 -> 78 | D64: ='Balance Sheet'!D69 -> 64 | E64: ='Balance Sheet'!E69 -> 74 | F64: ='Balance Sheet'!F69 -> 79 | G64: ='Balance Sheet'!G69 -> 92 | H64: =H65*'Revenue BuildUp'!H$11 -> 96.237785 | I64: =I65*'Revenue BuildUp'!I$11 -> 105.6369 | J64: =J65*'Revenue BuildUp'!J$11 -> 116.61609 | K64: =K65*'Revenue BuildUp'!K$11 -> 129.56545 | L64: =L65*'Revenue BuildUp'!L$11 -> 144.98705 | M64: =M65*'Revenue BuildUp'!M$11 -> 163.52849 | N64: =N65*'Revenue BuildUp'!N$11 -> 186.02664 | O64: =O65*'Revenue BuildUp'!O$11 -> 213.56455 | ... Q64: =Q65*'Revenue BuildUp'!Q$11 -> 289.79073
B65: % of Revenue | C65: =C64/'Revenue BuildUp'!C$11 -> 0.0096918489 | D65: =D64/'Revenue BuildUp'!D$11 -> 0.0067283431 | E65: =E64/'Revenue BuildUp'!E$11 -> 0.0075788611 | F65: =F64/'Revenue BuildUp'!F$11 -> 0.0081839843 | G65: =G64/'Revenue BuildUp'!G$11 -> 0.0084941372 | H65: =AVERAGE(C65:G65) -> 0.0081354349 | I65: =H65 -> 0.0081354349 | J65: =I65 -> 0.0081354349 | K65: =J65 -> 0.0081354349 | L65: =K65 -> 0.0081354349 | M65: =L65 -> 0.0081354349 | N65: =M65 -> 0.0081354349 | O65: =N65 -> 0.0081354349 | P65: =O65 -> 0.0081354349 | Q65: =P65 -> 0.0081354349
B66: Current tax liabilities (net) | C66: ='Balance Sheet'!C70 -> 72 | D66: ='Balance Sheet'!D70 -> 67 | E66: ='Balance Sheet'!E70 -> 87 | F66: ='Balance Sheet'!F70 -> 83 | G66: ='Balance Sheet'!G70 -> 92 | H66: =H67*'Revenue BuildUp'!H$11 -> 99.350505 | I66: =I67*'Revenue BuildUp'!I$11 -> 109.05362 | J66: =J67*'Revenue BuildUp'!J$11 -> 120.38793 | K66: =K67*'Revenue BuildUp'!K$11 -> 133.75612 | L66: =L67*'Revenue BuildUp'!L$11 -> 149.67652 | M66: =M67*'Revenue BuildUp'!M$11 -> 168.81766 | N66: =N67*'Revenue BuildUp'!N$11 -> 192.04349 | O66: =O67*'Revenue BuildUp'!O$11 -> 220.47209 | ... Q66: =Q67*'Revenue BuildUp'!Q$11 -> 299.16374
B67: % of Revenue | C67: =C66/'Revenue BuildUp'!C$11 -> 0.0089463221 | D67: =D66/'Revenue BuildUp'!D$11 -> 0.0070437342 | E67: =E66/'Revenue BuildUp'!E$11 -> 0.0089102827 | F67: =F66/'Revenue BuildUp'!F$11 -> 0.0085983632 | G67: =G66/'Revenue BuildUp'!G$11 -> 0.0084941372 | H67: =AVERAGE(C67:G67) -> 0.0083985679 | I67: =H67 -> 0.0083985679 | J67: =I67 -> 0.0083985679 | K67: =J67 -> 0.0083985679 | L67: =K67 -> 0.0083985679 | M67: =L67 -> 0.0083985679 | N67: =M67 -> 0.0083985679 | O67: =N67 -> 0.0083985679 | P67: =O67 -> 0.0083985679 | Q67: =P67 -> 0.0083985679

Sheet FAS Seechules
B6: Fixed Asset Schedules
B7: All Figure In INR Cr.
B8: Particulars | C8: 2021 | D8: =C8+1 -> 2022 | E8: =D8+1 -> 2023 | F8: =E8+1 -> 2024 | G8: =F8+1 -> 2025 | H8: =G8+1 -> 2026 | I8: =H8+1 -> 2027 | J8: =I8+1 -> 2028 | K8: =J8+1 -> 2029 | ... Q8: =P8+1 -> 2035
B9: Property, Plant and Equipment
B11: Opening gross carrying amount | C11: 1010 | D11: =C17 -> 999 | E11: =D17 -> 1095 | F11: =E17 -> 1184 | G11: =F17 -> 1323 | H11: =G17 -> 1270 | I11: =H17 -> 1403.4316 | J11: =I17 -> 1550.8821 | K11: =J17 -> 1713.8243 | ... Q11: =P17 -> 3120.9835
B12: Acqusitions through business combinations | C12: 1 | D12: 1 | E12: 2 | F12: 1
B13: Additions | C13: 105 | D13: 115 | E13: 145 | F13: 171 | G13: 139 | H13: =G13/F17*G17 -> 133.43159 | I13: =H13/G17*H17 -> 147.45049 | J13: =I13/H17*I17 -> 162.94226 | K13: =J13/I17*J17 -> 180.06167 | L13: =K13/J17*K17 -> 198.97971 | M13: =L13/K17*L17 -> 219.88536 | N13: =M13/L17*M17 -> 242.98745 | O13: =N13/M17*N17 -> 268.51675 | ... Q13: =P13/O17*P17 -> 327.90379
B14: Disposals / transfers | C14: -21 | D14: -23 | E14: -35 | F14: -21 | G14: -177
B15: Adjustments | C15: -92 | E15: -2
B16: Exchange Differences | C16: -4 | D16: 3 | E16: -21 | F16: -12 | G16: -15
B17: Closing gross carrying amount | C17: =SUM(C11:C16) -> 999 | D17: =SUM(D11:D16) -> 1095 | E17: =SUM(E11:E16) -> 1184 | F17: =SUM(F11:F16) -> 1323 | G17: =SUM(G11:G16) -> 1270 | H17: =SUM(H11:H16) -> 1403.4316 | I17: =SUM(I11:I16) -> 1550.8821 | J17: =SUM(J11:J16) -> 1713.8243 | ... Q17: =SUM(Q11:Q16) -> 3448.8873
B18: Accumulated depreciation
B19: Opening accumulated depreciation | C19: 404 | D19: =C24 -> 426 | E19: =D24 -> 495 | F19: =E24 -> 551 | G19: =F24 -> 623 | H19: =G24 -> 560 | I19: =H24 -> 662.47191 | J19: =I24 -> 783.6947 | K19: =J24 -> 927.09951 | ... Q19: =P24 -> 2540.9902
B20: Depreciation charge during the year | C20: 94 | D20: 89 | E20: 102 | F20: 99 | G20: 114 | H20: =G20/F24*G24 -> 102.47191 | I20: =H20/G24*H24 -> 121.22279 | J20: =I20/H24*I24 -> 143.40481 | K20: =J20/I24*J24 -> 169.64582 | L20: =K20/J24*K24 -> 200.68855 | M20: =L20/K24*L24 -> 237.41166 | N20: =M20/L24*M24 -> 280.85456 | O20: =N20/M24*N24 -> 332.24689 | ... Q20: =P20/O24*P24 -> 464.96451
B21: Disposals / transfers | C21: -17 | D21: -21 | E21: -35 | F21: -21 | G21: -170
B22: Adjustments (refer note iii) | C22: -53 | E22: -11
B23: Exchange Differences | C23: -2 | D23: 1 | F23: -6 | G23: -7
B24: Closing accumulated depreciation | C24: =SUM(C19:C23) -> 426 | D24: =SUM(D19:D23) -> 495 | E24: =SUM(E19:E23) -> 551 | F24: =SUM(F19:F23) -> 623 | G24: =SUM(G19:G23) -> 560 | H24: =SUM(H19:H23) -> 662.47191 | I24: =SUM(I19:I23) -> 783.6947 | J24: =SUM(J19:J23) -> 927.09951 | ... Q24: =SUM(Q19:Q23) -> 3005.9548
B25: Closing impairment loss | C25: 1 | D25: 0 | E25: 0 | F25: 0 | G25: 0
B26: Net carrying amount | C26: =C17-C24-C25 -> 572 | D26: =D17-D24-D25 -> 600 | E26: =E17-E24-E25 -> 633 | F26: =F17-F24-F25 -> 700 | G26: =G17-G24-G25 -> 710 | H26: =H17-H24-H25 -> 740.95968 | I26: =I17-I24-I25 -> 767.18738 | J26: =J17-J24-J25 -> 786.72483 | ... Q26: =Q17-Q24-Q25 -> 442.93257
B29: Right of use Assets
B30: Opening gross carrying amount | C30: 318 | D30: =C36 -> 323 | E30: =D36 -> 345 | F30: =E36 -> 354 | G30: =F36 -> 396 | H30: =G36 -> 388 | I30: =H36 -> 480.10101 | J30: =I36 -> 594.06438 | K30: =J36 -> 735.07966 | ... Q30: =P36 -> 2638.3947
B31: Acqusitions through business combinations | D31: 1 | E31: 1 | F31: 3
B32: Additions | C32: 34 | D32: 31 | E32: 61 | F32: 99 | G32: 94 | H32: =G32/F36*G36 -> 92.10101 | I32: =H32/G36*H36 -> 113.96337 | J32: =I32/H36*I36 -> 141.01528 | K32: =J32/I36*J36 -> 174.48861 | L32: =K32/J36*K36 -> 215.90762 | M32: =L32/K36*L36 -> 267.15842 | N32: =M32/L36*M36 -> 330.57481 | O32: =N32/M36*N36 -> 409.04459 | ... Q32: =P32/O36*P36 -> 626.28562
B33: Disposals / transfers | C33: -29 | D33: -21 | E33: -48 | F33: -55 | G33: -101
B34: Adjustments | D34: 7
B35: Exchange Differences | D35: 4 | E35: -5 | F35: -5 | G35: -1
B36: Closing gross carrying amount | C36: =SUM(C30:C35) -> 323 | D36: =SUM(D30:D35) -> 345 | E36: =SUM(E30:E35) -> 354 | F36: =SUM(F30:F35) -> 396 | G36: =SUM(G30:G35) -> 388 | H36: =SUM(H30:H35) -> 480.10101 | I36: =SUM(I30:I35) -> 594.06438 | J36: =SUM(J30:J35) -> 735.07966 | ... Q36: =SUM(Q30:Q35) -> 3264.6804
B37: Accumulated depreciation
B38: Opening accumulated depreciation | C38: 120 | D38: =C43 -> 143 | E38: =D43 -> 167 | F38: =E43 -> 179 | G38: =F43 -> 187 | H38: =G43 -> 158 | I38: =H43 -> 202.78075 | J38: =I43 -> 260.25337 | K38: =J43 -> 334.01502 | ... Q38: =P43 -> 1492.7387
B39: Depreciation charge during the year | C39: 38 | D39: 40 | E39: 44 | F39: 48 | G39: 53 | H39: =G39/F43*G43 -> 44.780749 | I39: =H39/G43*H43 -> 57.472619 | J39: =I39/H43*I43 -> 73.76165 | K39: =J39/I43*J43 -> 94.667358 | L39: =K39/J43*K43 -> 121.49821 | M39: =L39/K43*L43 -> 155.93354 | N39: =M39/L43*M43 -> 200.1286 | O39: =N39/M43*N43 -> 256.84954 | ... Q39: =P39/O43*P43 -> 423.07569
B40: Disposals / transfers | C40: -16 | D40: -16 | E40: -30 | F40: -27 | G40: -82
B41: Adjustments (refer note iii)
B42: Exchange Differences | C42: 1 | E42: -2 | F42: -13
B43: Closing accumulated depreciation | C43: =SUM(C38:C42) -> 143 | D43: =SUM(D38:D42) -> 167 | E43: =SUM(E38:E42) -> 179 | F43: =SUM(F38:F42) -> 187 | G43: =SUM(G38:G42) -> 158 | H43: =SUM(H38:H42) -> 202.78075 | I43: =SUM(I38:I42) -> 260.25337 | J43: =SUM(J38:J42) -> 334.01502 | ... Q43: =SUM(Q38:Q42) -> 1915.8144
B44: Closing impairment loss
B45: Net carrying amount | C45: =C36-C43-C44 -> 180 | D45: =D36-D43-D44 -> 178 | E45: =E36-E43-E44 -> 175 | F45: =F36-F43-F44 -> 209 | G45: =G36-G43-G44 -> 230 | H45: =H36-H43-H44 -> 277.32026 | I45: =I36-I43-I44 -> 333.81101 | J45: =J36-J43-J44 -> 401.06465 | ... Q45: =Q36-Q43-Q44 -> 1348.8659
B48: Other intangible assets
B49: Opening gross carrying amount | C49: 57 | D49: =C55 -> 252 | E49: =D55 -> 335 | F49: =E55 -> 593 | G49: =F55 -> 980 | H49: =G55 -> 999 | I49: =H55 -> 1019.3878 | J49: =I55 -> 1040.1916 | K49: =J55 -> 1061.42 | ... Q49: =P55 -> 1198.2041
B50: Acqusitions through business combinations | C50: 174 | D50: 81 | E50: 266 | F50: 363
B51: Additions | C51: 4 | D51: 1 | E51: 1 | F51: 3 | G51: 20 | H51: =G51/F55*G55 -> 20.387755 | I51: =H51/G55*H55 -> 20.803832 | J51: =I51/H55*I55 -> 21.2284 | K51: =J51/I55*J55 -> 21.661632 | L51: =K51/J55*K55 -> 22.103707 | M51: =L51/K55*L55 -> 22.554803 | N51: =M51/L55*M55 -> 23.015105 | O51: =N51/M55*N55 -> 23.484801 | ... Q51: =P51/O55*P55 -> 24.453145
B52: Disposals / transfers | E52: -5 | G52: -1
B53: Adjustments | C53: 7 | F53: 22
B54: Exchange Differences | C54: 10 | D54: 1 | E54: -4 | F54: -1
B55: Closing gross carrying amount | C55: =SUM(C49:C54) -> 252 | D55: =SUM(D49:D54) -> 335 | E55: =SUM(E49:E54) -> 593 | F55: =SUM(F49:F54) -> 980 | G55: =SUM(G49:G54) -> 999 | H55: =SUM(H49:H54) -> 1019.3878 | I55: =SUM(I49:I54) -> 1040.1916 | J55: =SUM(J49:J54) -> 1061.42 | ... Q55: =SUM(Q49:Q54) -> 1222.6573
B56: Accumulated depreciation
B57: Opening accumulated depreciation | D57: =C62 -> 22 | E57: =D62 -> 29 | F57: =E62 -> 33 | G57: =F62 -> 43 | H57: =G62 -> 53 | I57: =H62 -> 66.55814 | J57: =I62 -> 83.58464 | K57: =J62 -> 104.96676 | ... Q57: =P62 -> 411.72156
B58: Depreciation charge during the year | C58: 16 | D58: 7 | E58: 8 | F58: 10 | G58: 11 | H58: =G58/F62*G62 -> 13.55814 | I58: =H58/G62*H62 -> 17.026501 | J58: =I58/H62*I62 -> 21.382117 | K58: =J58/I62*J62 -> 26.851961 | L58: =K58/J62*K62 -> 33.721068 | M58: =L58/K62*L62 -> 42.347387 | N58: =M58/L62*M62 -> 53.18044 | O58: =N58/M62*N62 -> 66.784738 | ... Q58: =P58/O62*P62 -> 105.32412
B59: Disposals / transfers | C59: 6 | E59: -4 | G59: -1
B60: Adjustments (refer note iii)
B61: Exchange Differences
B62: Closing accumulated depreciation | C62: =SUM(C56:C61) -> 22 | D62: =SUM(D56:D61) -> 29 | E62: =SUM(E56:E61) -> 33 | F62: =SUM(F56:F61) -> 43 | G62: =SUM(G56:G61) -> 53 | H62: =SUM(H56:H61) -> 66.55814 | I62: =SUM(I56:I61) -> 83.58464 | J62: =SUM(J56:J61) -> 104.96676 | ... Q62: =SUM(Q56:Q61) -> 517.04568
B63: Closing impairment loss
B64: Net carrying amount | C64: =C55-C62-C63 -> 230 | D64: =D55-D62-D63 -> 306 | E64: =E55-E62-E63 -> 560 | F64: =F55-F62-F63 -> 937 | G64: =G55-G62-G63 -> 946 | H64: =H55-H62-H63 -> 952.82962 | I64: =I55-I62-I63 -> 956.60695 | J64: =J55-J62-J63 -> 956.45323 | ... Q64: =Q55-Q62-Q63 -> 705.61158
B67: Total
B68: Opening gross carrying amount | C68: =C49+C30+C11 -> 1385 | D68: =D49+D30+D11 -> 1574 | E68: =E49+E30+E11 -> 1775 | F68: =F49+F30+F11 -> 2131 | G68: =G49+G30+G11 -> 2699 | H68: =H49+H30+H11 -> 2657 | I68: =I49+I30+I11 -> 2902.9204 | J68: =J49+J30+J11 -> 3185.138 | ... Q68: =Q49+Q30+Q11 -> 6957.5824
B69: Acqusitions through business combinations | C69: =C50+C31+C12 -> 175 | D69: =D50+D31+D12 -> 83 | E69: =E50+E31+E12 -> 269 | F69: =F50+F31+F12 -> 367 | G69: =G50+G31+G12 -> 0 | H69: =H50+H31+H12 -> 0 | I69: =I50+I31+I12 -> 0 | J69: =J50+J31+J12 -> 0 | ... Q69: =Q50+Q31+Q12 -> 0
B70: Additions | C70: =C51+C32+C13 -> 143 | D70: =D51+D32+D13 -> 147 | E70: =E51+E32+E13 -> 207 | F70: =F51+F32+F13 -> 273 | G70: =G51+G32+G13 -> 253 | H70: =H51+H32+H13 -> 245.92036 | I70: =I51+I32+I13 -> 282.21769 | J70: =J51+J32+J13 -> 325.18594 | ... Q70: =Q51+Q32+Q13 -> 978.64255
B71: Disposals / transfers | C71: =C52+C33+C14 -> -50 | D71: =D52+D33+D14 -> -44 | E71: =E52+E33+E14 -> -88 | F71: =F52+F33+F14 -> -76 | G71: =G52+G33+G14 -> -279 | H71: =H52+H33+H14 -> 0 | I71: =I52+I33+I14 -> 0 | J71: =J52+J33+J14 -> 0 | ... Q71: =Q52+Q33+Q14 -> 0
B72: Adjustments | C72: =C53+C34+C15 -> -85 | D72: =D53+D34+D15 -> 7 | E72: =E53+E34+E15 -> -2 | F72: =F53+F34+F15 -> 22 | G72: =G53+G34+G15 -> 0 | H72: =H53+H34+H15 -> 0 | I72: =I53+I34+I15 -> 0 | J72: =J53+J34+J15 -> 0 | ... Q72: =Q53+Q34+Q15 -> 0
B73: Exchange Differences | C73: =C54+C35+C16 -> 6 | D73: =D54+D35+D16 -> 8 | E73: =E54+E35+E16 -> -30 | F73: =F54+F35+F16 -> -18 | G73: =G54+G35+G16 -> -16 | H73: =H54+H35+H16 -> 0 | I73: =I54+I35+I16 -> 0 | J73: =J54+J35+J16 -> 0 | ... Q73: =Q54+Q35+Q16 -> 0
B74: Closing gross carrying amount | C74: =C55+C36+C17 -> 1574 | D74: =D55+D36+D17 -> 1775 | E74: =E55+E36+E17 -> 2131 | F74: =F55+F36+F17 -> 2699 | G74: =G55+G36+G17 -> 2657 | H74: =H55+H36+H17 -> 2902.9204 | I74: =I55+I36+I17 -> 3185.138 | J74: =J55+J36+J17 -> 3510.324 | ... Q74: =Q55+Q36+Q17 -> 7936.2249
B75: Accumulated depreciation | C75: =C56+C37+C18 -> 0 | D75: =D56+D37+D18 -> 0 | E75: =E56+E37+E18 -> 0 | F75: =F56+F37+F18 -> 0 | G75: =G56+G37+G18 -> 0 | H75: =H56+H37+H18 -> 0 | I75: =I56+I37+I18 -> 0 | J75: =J56+J37+J18 -> 0 | ... Q75: =Q56+Q37+Q18 -> 0
B76: Opening accumulated depreciation | C76: =C57+C38+C19 -> 524 | D76: =D57+D38+D19 -> 591 | E76: =E57+E38+E19 -> 691 | F76: =F57+F38+F19 -> 763 | G76: =G57+G38+G19 -> 853 | H76: =H57+H38+H19 -> 771 | I76: =I57+I38+I19 -> 931.8108 | J76: =J57+J38+J19 -> 1127.5327 | ... Q76: =Q57+Q38+Q19 -> 4445.4505
B77: Depreciation charge during the year | C77: =C58+C39+C20 -> 148 | D77: =D58+D39+D20 -> 136 | E77: =E58+E39+E20 -> 154 | F77: =F58+F39+F20 -> 157 | G77: =G58+G39+G20 -> 178 | H77: =H58+H39+H20 -> 160.8108 | I77: =I58+I39+I20 -> 195.72191 | J77: =J58+J39+J20 -> 238.54858 | ... Q77: =Q58+Q39+Q20 -> 993.36431
B78: Disposals / transfers | C78: =C59+C40+C21 -> -27 | D78: =D59+D40+D21 -> -37 | E78: =E59+E40+E21 -> -69 | F78: =F59+F40+F21 -> -48 | G78: =G59+G40+G21 -> -253 | H78: =H59+H40+H21 -> 0 | I78: =I59+I40+I21 -> 0 | J78: =J59+J40+J21 -> 0 | ... Q78: =Q59+Q40+Q21 -> 0
B79: Adjustments (refer note iii) | C79: =C60+C41+C22 -> -53 | D79: =D60+D41+D22 -> 0 | E79: =E60+E41+E22 -> -11 | F79: =F60+F41+F22 -> 0 | G79: =G60+G41+G22 -> 0 | H79: =H60+H41+H22 -> 0 | I79: =I60+I41+I22 -> 0 | J79: =J60+J41+J22 -> 0 | ... Q79: =Q60+Q41+Q22 -> 0
... B83: Net carrying amount | C83: =C64+C45+C26 -> 982 | D83: =D64+D45+D26 -> 1084 | E83: =E64+E45+E26 -> 1368 | F83: =F64+F45+F26 -> 1846 | G83: =G64+G45+G26 -> 1886 | H83: =H64+H45+H26 -> 1971.1096 | I83: =I64+I45+I26 -> 2057.6053 | J83: =J64+J45+J26 -> 2144.2427 | ... Q83: =Q64+Q45+Q26 -> 2497.4101
B85: Net Block | C85: =C83 -> 982 | D85: =D83 -> 1084 | E85: =E83 -> 1368 | F85: =F83 -> 1846 | G85: =G83 -> 1886 | H85: =H83 -> 1971.1096 | I85: =I83 -> 2057.6053 | J85: =J83 -> 2144.2427 | ... Q85: =Q83 -> 2497.4101
B86: Dep | C86: 139 | D86: 139 | E86: 155 | F86: 158 | G86: 178 | H86: =H77 -> 160.8108 | I86: =I77 -> 195.72191 | J86: =J77 -> 238.54858 | K86: =K77 -> 291.16514 | L86: =L77 -> 355.90783 | M86: =M77 -> 435.69258 | N86: =N77 -> 534.1636 | O86: =O77 -> 655.88117 | ... Q86: =Q77 -> 993.36431
B87: Increse In fixed Assets | D87: =D85+D86-C85 -> 241 | E87: =E85+E86-D85 -> 439 | F87: =F85+F86-E85 -> 636 | G87: =G85+G86-F85 -> 218 | H87: =H85+H86-G85 -> 245.92036 | I87: =I85+I86-H85 -> 282.21769 | J87: =J85+J86-I85 -> 325.18594 | K87: =K85+K86-J85 -> 376.2119 | ... Q87: =Q85+Q86-P85 -> 978.64255
B89: Capital Work in Progress | C89: ='Balance Sheet'!C12 -> 24 | D89: ='Balance Sheet'!D12 -> 39 | E89: ='Balance Sheet'!E12 -> 67 | F89: ='Balance Sheet'!F12 -> 44 | G89: ='Balance Sheet'!G12 -> 40 | H89: =G89+H90 -> 44.8 | I89: =H89+I90 -> 50.56 | J89: =I89+J90 -> 57.472 | K89: =J89+K90 -> 65.7664 | L89: =K89+L90 -> 75.71968 | M89: =L89+M90 -> 87.663616 | N89: =M89+N90 -> 101.99634 | O89: =N89+O90 -> 119.19561 | ... Q89: =P89+Q90 -> 164.60167
B90: Increse In CWP | D90: =D89-C89 -> 15 | E90: =E89-D89 -> 28 | F90: =F89-E89 -> -23 | G90: =G89-F89 -> -4 | H90: =-G90*1.2 -> 4.8 | I90: =H90*1.2 -> 5.76 | J90: =I90*1.2 -> 6.912 | K90: =J90*1.2 -> 8.2944 | L90: =K90*1.2 -> 9.95328 | M90: =L90*1.2 -> 11.943936 | N90: =M90*1.2 -> 14.332723 | O90: =N90*1.2 -> 17.199268 | P90: =O90*1.2 -> 20.639121 | Q90: =P90*1.2 -> 24.766946
B92: CAPEX | D92: =D87+D90 -> 256 | E92: =E87+E90 -> 467 | F92: =F87+F90 -> 613 | G92: =G87+G90 -> 214 | H92: =H87+H90 -> 250.72036 | I92: =I87+I90 -> 287.97769 | J92: =J87+J90 -> 332.09794 | K92: =K87+K90 -> 384.5063 | ... Q92: =Q87+Q90 -> 1003.4095

Sheet Revenue BuildUp
B7: Revenue Build_Up
B8: All Figure In INR Cr.
B9: Particulars | C9: 2021 | D9: =C9+1 -> 2022 | E9: =D9+1 -> 2023 | F9: =E9+1 -> 2024 | G9: =F9+1 -> 2025 | H9: =G9+1 -> 2026 | I9: =H9+1 -> 2027 | J9: =I9+1 -> 2028 | K9: =J9+1 -> 2029 | ... Q9: =P9+1 -> 2035
B11: Revenue | C11: ='Income Statement'!C10 -> 8048 | D11: ='Income Statement'!D10 -> 9512 | E11: ='Income Statement'!E10 -> 9764 | F11: ='Income Statement'!F10 -> 9653 | G11: ='Income Statement'!G10 -> 10831 | H11: =H43 -> 11829.458 | I11: =I43 -> 12984.788 | J11: =J43 -> 14334.34 | K11: =K43 -> 15926.063 | L11: =L43 -> 17821.671 | M11: =M43 -> 20100.768 | N11: =N43 -> 22866.219 | O11: =O43 -> 26251.153 | ... Q11: =Q43 -> 35620.804
B12: Growth | D12: =D11/C11-1 -> 0.18190855 | E12: =E11/D11-1 -> 0.026492851 | F12: =F11/E11-1 -> -0.011368292 | G12: =G11/F11-1 -> 0.1220346 | H12: =H11/G11-1 -> 0.092185196 | I12: =I11/H11-1 -> 0.097665532 | J12: =J11/I11-1 -> 0.10393332 | K12: =K11/J11-1 -> 0.11104263 | ... Q12: =Q11/P11-1 -> 0.17065547
B14: SEGMENTED REVENUES | C14: 2021 | D14: 2022 | E14: 2023 | F14: 2024 | G14: 2025 | H14: =G14+1 -> 2026 | I14: =H14+1 -> 2027 | J14: =I14+1 -> 2028 | K14: =J14+1 -> 2029 | L14: =K14+1 -> 2030 | M14: =L14+1 -> 2031 | N14: =M14+1 -> 2032 | O14: =N14+1 -> 2033 | ... Q14: =P14+1 -> 2035
B15: India | C15: 6189 | D15: 7333 | E15: 7351 | F15: 7132 | G15: 8110 | H15: =G15*(1+H16) -> 8707.3731 | I15: =H15*(1+I16) -> 9348.748 | J15: =I15*(1+J16) -> 10037.366 | K15: =J15*(1+K16) -> 10776.706 | L15: =K15*(1+L16) -> 11570.506 | M15: =L15*(1+M16) -> 12422.776 | N15: =M15*(1+N16) -> 13337.823 | O15: =N15*(1+O16) -> 14320.271 | ... Q15: =P15*(1+Q16) -> 16507.596
B16: Forecasted growth | H16: =CHOOSE(Assumption!$C$9,'Revenue BuildUp'!$H$19:$Q$19,'Revenue BuildUp'!$H$20:$Q$20,'Revenue BuildUp'!$H$21:$Q$21) -> 0.073658826 | I16: =CHOOSE(Assumption!$C$9,'Revenue BuildUp'!$H$19:$Q$19,'Revenue BuildUp'!$H$20:$Q$20,'Revenue BuildUp'!$H$21:$Q$21) -> 0.073658826 | J16: =CHOOSE(Assumption!$C$9,'Revenue BuildUp'!$H$19:$Q$19,'Revenue BuildUp'!$H$20:$Q$20,'Revenue BuildUp'!$H$21:$Q$21) -> 0.073658826 | K16: =CHOOSE(Assumption!$C$9,'Revenue BuildUp'!$H$19:$Q$19,'Revenue BuildUp'!$H$20:$Q$20,'Revenue BuildUp'!$H$21:$Q$21) -> 0.073658826 | L16: =CHOOSE(Assumption!$C$9,'Revenue BuildUp'!$H$19:$Q$19,'Revenue BuildUp'!$H$20:$Q$20,'Revenue BuildUp'!$H$21:$Q$21) -> 0.073658826 | M16: =CHOOSE(Assumption!$C$9,'Revenue BuildUp'!$H$19:$Q$19,'Revenue BuildUp'!$H$20:$Q$20,'Revenue BuildUp'!$H$21:$Q$21) -> 0.073658826 | N16: =CHOOSE(Assumption!$C$9,'Revenue BuildUp'!$H$19:$Q$19,'Revenue BuildUp'!$H$20:$Q$20,'Revenue BuildUp'!$H$21:$Q$21) -> 0.073658826 | O16: =CHOOSE(Assumption!$C$9,'Revenue BuildUp'!$H$19:$Q$19,'Revenue BuildUp'!$H$20:$Q$20,'Revenue BuildUp'!$H$21:$Q$21) -> 0.073658826 | ... Q16: =CHOOSE(Assumption!$C$9,'Revenue BuildUp'!$H$19:$Q$19,'Revenue BuildUp'!$H$20:$Q$20,'Revenue BuildUp'!$H$21:$Q$21) -> 0.073658826
B17: Y-O-Y Growth | D17: =D15/C15-1 -> 0.18484408 | E17: =E15/D15-1 -> 0.002454657 | F17: =F15/E15-1 -> -0.029791865 | G17: =G15/F15-1 -> 0.13712844
B18: Scenario
B19: Best | H19: =H20+3% -> 0.10365883 | I19: =H19 -> 0.10365883 | J19: =I19 -> 0.10365883 | K19: =J19 -> 0.10365883 | L19: =K19 -> 0.10365883 | M19: =L19 -> 0.10365883 | N19: =M19 -> 0.10365883 | O19: =N19 -> 0.10365883 | P19: =O19 -> 0.10365883 | Q19: =P19 -> 0.10365883
B20: Base | H20: =AVERAGE(D17:G17) -> 0.073658826 | I20: =H20 -> 0.073658826 | J20: =I20 -> 0.073658826 | K20: =J20 -> 0.073658826 | L20: =K20 -> 0.073658826 | M20: =L20 -> 0.073658826 | N20: =M20 -> 0.073658826 | O20: =N20 -> 0.073658826 | P20: =O20 -> 0.073658826 | Q20: =P20 -> 0.073658826
B21: Worst | H21: =H20-3% -> 0.043658826 | I21: =H21 -> 0.043658826 | J21: =I21 -> 0.043658826 | K21: =J21 -> 0.043658826 | L21: =K21 -> 0.043658826 | M21: =L21 -> 0.043658826 | N21: =M21 -> 0.043658826 | O21: =N21 -> 0.043658826 | P21: =O21 -> 0.043658826 | Q21: =P21 -> 0.043658826
B22: Bangladesh | C22: 990 | D22: 1139 | E22: 1159 | F22: 1103 | G22: 1065 | H22: =G22*(1+H23) -> 1087.7099 | I22: =H22*(1+I23) -> 1110.904 | J22: =I22*(1+J23) -> 1134.5927 | K22: =J22*(1+K23) -> 1158.7866 | L22: =K22*(1+L23) -> 1183.4964 | M22: =L22*(1+M23) -> 1208.733 | N22: =M22*(1+N23) -> 1234.5078 | O22: =N22*(1+O23) -> 1260.8323 | ... Q22: =P22*(1+Q23) -> 1315.1771
B23: Forecasted growth | H23: =CHOOSE(Assumption!$C$9,'Revenue BuildUp'!$H$26:$Q$26,'Revenue BuildUp'!$H$27:$Q$27,'Revenue BuildUp'!$H$28:$Q$28) -> 0.021323825 | I23: =CHOOSE(Assumption!$C$9,'Revenue BuildUp'!$H$26:$Q$26,'Revenue BuildUp'!$H$27:$Q$27,'Revenue BuildUp'!$H$28:$Q$28) -> 0.021323825 | J23: =CHOOSE(Assumption!$C$9,'Revenue BuildUp'!$H$26:$Q$26,'Revenue BuildUp'!$H$27:$Q$27,'Revenue BuildUp'!$H$28:$Q$28) -> 0.021323825 | K23: =CHOOSE(Assumption!$C$9,'Revenue BuildUp'!$H$26:$Q$26,'Revenue BuildUp'!$H$27:$Q$27,'Revenue BuildUp'!$H$28:$Q$28) -> 0.021323825 | L23: =CHOOSE(Assumption!$C$9,'Revenue BuildUp'!$H$26:$Q$26,'Revenue BuildUp'!$H$27:$Q$27,'Revenue BuildUp'!$H$28:$Q$28) -> 0.021323825 | M23: =CHOOSE(Assumption!$C$9,'Revenue BuildUp'!$H$26:$Q$26,'Revenue BuildUp'!$H$27:$Q$27,'Revenue BuildUp'!$H$28:$Q$28) -> 0.021323825 | N23: =CHOOSE(Assumption!$C$9,'Revenue BuildUp'!$H$26:$Q$26,'Revenue BuildUp'!$H$27:$Q$27,'Revenue BuildUp'!$H$28:$Q$28) -> 0.021323825 | O23: =CHOOSE(Assumption!$C$9,'Revenue BuildUp'!$H$26:$Q$26,'Revenue BuildUp'!$H$27:$Q$27,'Revenue BuildUp'!$H$28:$Q$28) -> 0.021323825 | ... Q23: =CHOOSE(Assumption!$C$9,'Revenue BuildUp'!$H$26:$Q$26,'Revenue BuildUp'!$H$27:$Q$27,'Revenue BuildUp'!$H$28:$Q$28) -> 0.021323825
B24: Y-O-Y Growth | D24: =D22/C22-1 -> 0.15050505 | E24: =E22/D22-1 -> 0.017559263 | F24: =F22/E22-1 -> -0.048317515 | G24: =G22/F22-1 -> -0.034451496
B25: Scenario
B26: Best | H26: =H27+5% -> 0.071323825 | I26: =H26 -> 0.071323825 | J26: =I26 -> 0.071323825 | K26: =J26 -> 0.071323825 | L26: =K26 -> 0.071323825 | M26: =L26 -> 0.071323825 | N26: =M26 -> 0.071323825 | O26: =N26 -> 0.071323825 | P26: =O26 -> 0.071323825 | Q26: =P26 -> 0.071323825
B27: Base | H27: =AVERAGE(D24:G24) -> 0.021323825 | I27: =H27 -> 0.021323825 | J27: =I27 -> 0.021323825 | K27: =J27 -> 0.021323825 | L27: =K27 -> 0.021323825 | M27: =L27 -> 0.021323825 | N27: =M27 -> 0.021323825 | O27: =N27 -> 0.021323825 | P27: =O27 -> 0.021323825 | Q27: =P27 -> 0.021323825
B28: Worst | H28: =H27-5% -> -0.028676175 | I28: =H28 -> -0.028676175 | J28: =I28 -> -0.028676175 | K28: =J28 -> -0.028676175 | L28: =K28 -> -0.028676175 | M28: =L28 -> -0.028676175 | N28: =M28 -> -0.028676175 | O28: =N28 -> -0.028676175 | P28: =O28 -> -0.028676175 | Q28: =P28 -> -0.028676175
B29: Vietnam | C29: 440 | D29: 495 | E29: 593 | F29: 626 | G29: 441 | H29: =G29*(1+H30) -> 450.16198 | I29: =H29*(1+I30) -> 459.51431 | J29: =I29*(1+J30) -> 469.06094 | K29: =J29*(1+K30) -> 478.8059 | L29: =K29*(1+L30) -> 488.75332 | M29: =L29*(1+M30) -> 498.9074 | N29: =M29*(1+N30) -> 509.27243 | O29: =N29*(1+O30) -> 519.85281 | ... Q29: =P29*(1+Q30) -> 541.67756
B30: Forecasted growth | H30: =CHOOSE(Assumption!$C$9,'Revenue BuildUp'!$H$33:$Q$33,'Revenue BuildUp'!$H$34:$Q$34,'Revenue BuildUp'!$H$35:$Q$35) -> 0.020775471 | I30: =CHOOSE(Assumption!$C$9,'Revenue BuildUp'!$H$33:$Q$33,'Revenue BuildUp'!$H$34:$Q$34,'Revenue BuildUp'!$H$35:$Q$35) -> 0.020775471 | J30: =CHOOSE(Assumption!$C$9,'Revenue BuildUp'!$H$33:$Q$33,'Revenue BuildUp'!$H$34:$Q$34,'Revenue BuildUp'!$H$35:$Q$35) -> 0.020775471 | K30: =CHOOSE(Assumption!$C$9,'Revenue BuildUp'!$H$33:$Q$33,'Revenue BuildUp'!$H$34:$Q$34,'Revenue BuildUp'!$H$35:$Q$35) -> 0.020775471 | L30: =CHOOSE(Assumption!$C$9,'Revenue BuildUp'!$H$33:$Q$33,'Revenue BuildUp'!$H$34:$Q$34,'Revenue BuildUp'!$H$35:$Q$35) -> 0.020775471 | M30: =CHOOSE(Assumption!$C$9,'Revenue BuildUp'!$H$33:$Q$33,'Revenue BuildUp'!$H$34:$Q$34,'Revenue BuildUp'!$H$35:$Q$35) -> 0.020775471 | N30: =CHOOSE(Assumption!$C$9,'Revenue BuildUp'!$H$33:$Q$33,'Revenue BuildUp'!$H$34:$Q$34,'Revenue BuildUp'!$H$35:$Q$35) -> 0.020775471 | O30: =CHOOSE(Assumption!$C$9,'Revenue BuildUp'!$H$33:$Q$33,'Revenue BuildUp'!$H$34:$Q$34,'Revenue BuildUp'!$H$35:$Q$35) -> 0.020775471 | ... Q30: =CHOOSE(Assumption!$C$9,'Revenue BuildUp'!$H$33:$Q$33,'Revenue BuildUp'!$H$34:$Q$34,'Revenue BuildUp'!$H$35:$Q$35) -> 0.020775471
B31: Y-O-Y Growth | D31: =D29/C29-1 -> 0.125 | E31: =E29/D29-1 -> 0.1979798 | F31: =F29/E29-1 -> 0.055649241 | G31: =G29/F29-1 -> -0.29552716
B32: Scenario
B33: Best | H33: =H34+10% -> 0.12077547 | I33: =H33 -> 0.12077547 | J33: =I33 -> 0.12077547 | K33: =J33 -> 0.12077547 | L33: =K33 -> 0.12077547 | M33: =L33 -> 0.12077547 | N33: =M33 -> 0.12077547 | O33: =N33 -> 0.12077547 | P33: =O33 -> 0.12077547 | Q33: =P33 -> 0.12077547
B34: Base | H34: =AVERAGE(D31:G31) -> 0.020775471 | I34: =H34 -> 0.020775471 | J34: =I34 -> 0.020775471 | K34: =J34 -> 0.020775471 | L34: =K34 -> 0.020775471 | M34: =L34 -> 0.020775471 | N34: =M34 -> 0.020775471 | O34: =N34 -> 0.020775471 | P34: =O34 -> 0.020775471 | Q34: =P34 -> 0.020775471
B35: Worst | H35: =H34-10% -> -0.079224529 | I35: =H35 -> -0.079224529 | J35: =I35 -> -0.079224529 | K35: =J35 -> -0.079224529 | L35: =K35 -> -0.079224529 | M35: =L35 -> -0.079224529 | N35: =M35 -> -0.079224529 | O35: =N35 -> -0.079224529 | P35: =O35 -> -0.079224529 | Q35: =P35 -> -0.079224529
B36: Others | C36: 429 | D36: 545 | E36: 661 | F36: 792 | G36: 1215 | H36: =G36*(1+H37) -> 1584.2129 | I36: =H36*(1+I37) -> 2065.6219 | J36: =I36*(1+J37) -> 2693.3209 | K36: =J36*(1+K37) -> 3511.7644 | L36: =K36*(1+L37) -> 4578.9156 | M36: =L36*(1+M37) -> 5970.3517 | N36: =M36*(1+N37) -> 7784.6159 | O36: =N36*(1+O37) -> 10150.197 | ... Q36: =P36*(1+Q37) -> 17256.353
B37: Forecasted growth | H37: =CHOOSE(Assumption!$C$9,'Revenue BuildUp'!$H$40:$Q$40,'Revenue BuildUp'!$H$41:$Q$41,'Revenue BuildUp'!$H$42:$Q$42) -> 0.30387895 | I37: =CHOOSE(Assumption!$C$9,'Revenue BuildUp'!$H$40:$Q$40,'Revenue BuildUp'!$H$41:$Q$41,'Revenue BuildUp'!$H$42:$Q$42) -> 0.30387895 | J37: =CHOOSE(Assumption!$C$9,'Revenue BuildUp'!$H$40:$Q$40,'Revenue BuildUp'!$H$41:$Q$41,'Revenue BuildUp'!$H$42:$Q$42) -> 0.30387895 | K37: =CHOOSE(Assumption!$C$9,'Revenue BuildUp'!$H$40:$Q$40,'Revenue BuildUp'!$H$41:$Q$41,'Revenue BuildUp'!$H$42:$Q$42) -> 0.30387895 | L37: =CHOOSE(Assumption!$C$9,'Revenue BuildUp'!$H$40:$Q$40,'Revenue BuildUp'!$H$41:$Q$41,'Revenue BuildUp'!$H$42:$Q$42) -> 0.30387895 | M37: =CHOOSE(Assumption!$C$9,'Revenue BuildUp'!$H$40:$Q$40,'Revenue BuildUp'!$H$41:$Q$41,'Revenue BuildUp'!$H$42:$Q$42) -> 0.30387895 | N37: =CHOOSE(Assumption!$C$9,'Revenue BuildUp'!$H$40:$Q$40,'Revenue BuildUp'!$H$41:$Q$41,'Revenue BuildUp'!$H$42:$Q$42) -> 0.30387895 | O37: =CHOOSE(Assumption!$C$9,'Revenue BuildUp'!$H$40:$Q$40,'Revenue BuildUp'!$H$41:$Q$41,'Revenue BuildUp'!$H$42:$Q$42) -> 0.30387895 | ... Q37: =CHOOSE(Assumption!$C$9,'Revenue BuildUp'!$H$40:$Q$40,'Revenue BuildUp'!$H$41:$Q$41,'Revenue BuildUp'!$H$42:$Q$42) -> 0.30387895
B38: Y-O-Y Growth | D38: =D36/C36-1 -> 0.27039627 | E38: =E36/D36-1 -> 0.21284404 | F38: =F36/E36-1 -> 0.19818457 | G38: =G36/F36-1 -> 0.53409091
B39: Scenario
B40: Best | H40: =H41+10% -> 0.40387895 | I40: =H40 -> 0.40387895 | J40: =I40 -> 0.40387895 | K40: =J40 -> 0.40387895 | L40: =K40 -> 0.40387895 | M40: =L40 -> 0.40387895 | N40: =M40 -> 0.40387895 | O40: =N40 -> 0.40387895 | P40: =O40 -> 0.40387895 | Q40: =P40 -> 0.40387895
B41: Base | H41: =AVERAGE(D38:G38) -> 0.30387895 | I41: =H41 -> 0.30387895 | J41: =I41 -> 0.30387895 | K41: =J41 -> 0.30387895 | L41: =K41 -> 0.30387895 | M41: =L41 -> 0.30387895 | N41: =M41 -> 0.30387895 | O41: =N41 -> 0.30387895 | P41: =O41 -> 0.30387895 | Q41: =P41 -> 0.30387895
B42: Worst | H42: =H41-10% -> 0.20387895 | I42: =H42 -> 0.20387895 | J42: =I42 -> 0.20387895 | K42: =J42 -> 0.20387895 | L42: =K42 -> 0.20387895 | M42: =L42 -> 0.20387895 | N42: =M42 -> 0.20387895 | O42: =N42 -> 0.20387895 | P42: =O42 -> 0.20387895 | Q42: =P42 -> 0.20387895
B43: Total | C43: =SUM(C36,C29,C22,C15) -> 8048 | D43: =SUM(D36,D29,D22,D15) -> 9512 | E43: =SUM(E36,E29,E22,E15) -> 9764 | F43: =SUM(F36,F29,F22,F15) -> 9653 | G43: =SUM(G36,G29,G22,G15) -> 10831 | H43: =SUM(H36,H29,H22,H15) -> 11829.458 | I43: =SUM(I36,I29,I22,I15) -> 12984.788 | J43: =SUM(J36,J29,J22,J15) -> 14334.34 | ... Q43: =SUM(Q36,Q29,Q22,Q15) -> 35620.804
B46: Particulars | C46: 2021 | D46: 2022 | E46: 2023 | F46: 2024 | G46: 2025 | H46: =G46+1 -> 2026 | I46: =H46+1 -> 2027 | J46: =I46+1 -> 2028 | K46: =J46+1 -> 2029 | L46: =K46+1 -> 2030 | M46: =L46+1 -> 2031 | N46: =M46+1 -> 2032 | O46: =N46+1 -> 2033 | ... Q46: =P46+1 -> 2035
B47: Edible Oils | C47: 5082 | D47: 5593 | E47: 5356 | F47: 4919 | G47: 5494 | H47: =H48*H11 -> 6588.6088 | I47: =I48*I11 -> 7232.0888 | J47: =J48*J11 -> 7983.7438 | K47: =K48*K11 -> 8870.2797 | L47: =L48*L11 -> 9926.0694 | M47: =M48*M11 -> 11195.449 | N47: =N48*N11 -> 12735.712 | O47: =O48*O11 -> 14621.006 | ... Q47: =Q48*Q11 -> 19839.585
B48: % of Revenue | C48: =C47/C$11 -> 0.63146123 | D48: =D47/D$11 -> 0.58799411 | E48: =E47/E$11 -> 0.54854568 | F48: =F47/F$11 -> 0.50958251 | G48: =G47/G$11 -> 0.50724771 | H48: =AVERAGE(C48:G48) -> 0.55696625 | I48: =H48 -> 0.55696625 | J48: =I48 -> 0.55696625 | K48: =J48 -> 0.55696625 | L48: =K48 -> 0.55696625 | M48: =L48 -> 0.55696625 | N48: =M48 -> 0.55696625 | O48: =N48 -> 0.55696625 | P48: =O48 -> 0.55696625 | Q48: =P48 -> 0.55696625
B50: Hair oils | C50: 1789 | D50: 2003 | E50: 2111 | F50: 2043 | G50: 2115 | H50: =H51*H11 -> 2498.3498 | I50: =I51*I11 -> 2742.3525 | J50: =J51*J11 -> 3027.3743 | K50: =K51*K11 -> 3363.5419 | L50: =L51*L11 -> 3763.8893 | M50: =M51*M11 -> 4245.2284 | N50: =N51*N11 -> 4829.2843 | O50: =O51*O11 -> 5544.1733 | ... Q50: =Q51*Q11 -> 7523.0184
B51: % of Revenue | C51: =C50/C$11 -> 0.22229125 | D51: =D50/D$11 -> 0.21057611 | E51: =E50/E$11 -> 0.21620238 | F51: =F50/F$11 -> 0.21164405 | G51: =G50/G$11 -> 0.19527283 | H51: =AVERAGE(C51:G51) -> 0.21119732 | I51: =H51 -> 0.21119732 | J51: =I51 -> 0.21119732 | K51: =J51 -> 0.21119732 | L51: =K51 -> 0.21119732 | M51: =L51 -> 0.21119732 | N51: =M51 -> 0.21119732 | O51: =N51 -> 0.21119732 | P51: =O51 -> 0.21119732 | Q51: =P51 -> 0.21119732
B53: Personal care | C53: 773 | D53: 1031 | E53: 1254 | F53: 1593 | G53: 1886 | H53: =H54*H11 -> 1589.939 | I53: =I54*I11 -> 1745.2213 | J53: =J54*J11 -> 1926.6079 | K53: =K54*K11 -> 2140.5435 | L53: =L54*L11 -> 2395.3228 | M53: =M54*M11 -> 2701.645 | N53: =N54*N11 -> 3073.3356 | O53: =O54*O11 -> 3528.2879 | ... Q53: =Q54*Q11 -> 4787.6163
B54: % of Revenue | C54: =C53/C$11 -> 0.096048708 | D54: =D53/D$11 -> 0.1083894 | E54: =E53/E$11 -> 0.12843097 | F54: =F53/F$11 -> 0.16502642 | G54: =G53/G$11 -> 0.17412981 | H54: =AVERAGE(C54:G54) -> 0.13440506 | I54: =H54 -> 0.13440506 | J54: =I54 -> 0.13440506 | K54: =J54 -> 0.13440506 | L54: =K54 -> 0.13440506 | M54: =L54 -> 0.13440506 | N54: =M54 -> 0.13440506 | O54: =N54 -> 0.13440506 | P54: =O54 -> 0.13440506 | Q54: =P54 -> 0.13440506
B56: Others | C56: 404 | D56: 885 | E56: 1043 | F56: 1098 | G56: 1336 | H56: =H57*H11 -> 1152.5602 | I56: =I57*I11 -> 1265.1256 | J56: =J57*J11 -> 1396.6143 | K56: =K57*K11 -> 1551.6981 | L56: =L57*L11 -> 1736.3897 | M56: =M57*M11 -> 1958.4452 | N56: =N57*N11 -> 2227.8869 | O56: =O57*O11 -> 2557.6856 | ... Q56: =Q57*Q11 -> 3470.5835
B57: % of Revenue | C57: =C56/C$11 -> 0.050198807 | D57: =D56/D$11 -> 0.09304037 | E57: =E56/E$11 -> 0.10682098 | F57: =F56/F$11 -> 0.11374702 | G57: =G56/G$11 -> 0.12334964 | H57: =AVERAGE(C57:G57) -> 0.097431364 | I57: =H57 -> 0.097431364 | J57: =I57 -> 0.097431364 | K57: =J57 -> 0.097431364 | L57: =K57 -> 0.097431364 | M57: =L57 -> 0.097431364 | N57: =M57 -> 0.097431364 | O57: =N57 -> 0.097431364 | P57: =O57 -> 0.097431364 | Q57: =P57 -> 0.097431364
B59: Total | C59: =SUM(C56,C53,C50,C47) -> 8048 | D59: =SUM(D56,D53,D50,D47) -> 9512 | E59: =SUM(E56,E53,E50,E47) -> 9764 | F59: =SUM(F56,F53,F50,F47) -> 9653 | G59: =SUM(G56,G53,G50,G47) -> 10831 | H59: =SUM(H56,H53,H50,H47) -> 11829.458 | I59: =SUM(I56,I53,I50,I47) -> 12984.788 | J59: =SUM(J56,J53,J50,J47) -> 14334.34 | ... Q59: =SUM(Q56,Q53,Q50,Q47) -> 35620.804
B63: Other income | C63: ='Income Statement'!C11 -> 94 | D63: ='Income Statement'!D11 -> 98 | E63: ='Income Statement'!E11 -> 144 | F63: ='Income Statement'!F11 -> 142 | G63: ='Income Statement'!G11 -> 208 | H63: =H64*H11 -> 167.13921 | I63: =I64*I11 -> 183.46295 | J63: =J64*J11 -> 202.53087 | K63: =K64*K11 -> 225.02043 | L63: =L64*L11 -> 251.8036 | M63: =M64*M11 -> 284.00511 | N63: =N64*N11 -> 323.07836 | O63: =O64*O11 -> 370.90432 | ... Q63: =Q64*Q11 -> 503.28875
B64: % of Revenue | C64: =C63/C11 -> 0.01167992 | D64: =D63/D11 -> 0.010302775 | E64: =E63/E11 -> 0.014748054 | F64: =F63/F11 -> 0.014710453 | G64: =G63/G11 -> 0.019204136 | H64: =AVERAGE(C64:G64) -> 0.014129068 | I64: =H64 -> 0.014129068 | J64: =I64 -> 0.014129068 | K64: =J64 -> 0.014129068 | L64: =K64 -> 0.014129068 | M64: =L64 -> 0.014129068 | N64: =M64 -> 0.014129068 | O64: =N64 -> 0.014129068 | P64: =O64 -> 0.014129068 | Q64: =P64 -> 0.014129068
B66: Tax | C66: ='Income Statement'!C28 -> 324 | D66: ='Income Statement'!D28 -> 346 | E66: ='Income Statement'!E28 -> 421 | F66: ='Income Statement'!F28 -> 435 | G66: ='Income Statement'!G28 -> 458 | H66: =H67*'P&L Statement '!H34 -> 495.87166 | I66: =I67*'P&L Statement '!I34 -> 540.02448 | J66: =J67*'P&L Statement '!J34 -> 591.14342 | K66: =K67*'P&L Statement '!K34 -> 650.9658 | L66: =L67*'P&L Statement '!L34 -> 721.74464 | M66: =M67*'P&L Statement '!M34 -> 806.40772 | N66: =N67*'P&L Statement '!N34 -> 908.76586 | O66: =O67*'P&L Statement '!O34 -> 1033.7857 | ... Q66: =Q67*'P&L Statement '!Q34 -> 1383.706
B67: Tax Rate | C67: =C66/'Income Statement'!C26 -> 0.21273802 | D67: =D66/'Income Statement'!D26 -> 0.21611493 | E67: =E66/'Income Statement'!E26 -> 0.24153758 | F67: =F66/'Income Statement'!F26 -> 0.22457408 | G67: =G66/'Income Statement'!G26 -> 0.21644612 | H67: =AVERAGE(C67:G67) -> 0.22228215 | I67: =H67 -> 0.22228215 | J67: =I67 -> 0.22228215 | K67: =J67 -> 0.22228215 | L67: =K67 -> 0.22228215 | M67: =L67 -> 0.22228215 | N67: =M67 -> 0.22228215 | O67: =N67 -> 0.22228215 | P67: =O67 -> 0.22228215 | Q67: =P67 -> 0.22228215

Sheet Cost BuildUp
B7: Cost Build_Up
B8: All Figure In INR Cr.
B9: Particulars | C9: 2021 | D9: =C9+1 -> 2022 | E9: =D9+1 -> 2023 | F9: =E9+1 -> 2024 | G9: =F9+1 -> 2025 | H9: =G9+1 -> 2026 | I9: =H9+1 -> 2027 | J9: =I9+1 -> 2028 | K9: =J9+1 -> 2029 | ... Q9: =P9+1 -> 2035
B11: Revenue | C11: ='Revenue BuildUp'!C11 -> 8048 | D11: ='Revenue BuildUp'!D11 -> 9512 | E11: ='Revenue BuildUp'!E11 -> 9764 | F11: ='Revenue BuildUp'!F11 -> 9653 | G11: ='Revenue BuildUp'!G11 -> 10831 | H11: ='Revenue BuildUp'!H11 -> 11829.458 | I11: ='Revenue BuildUp'!I11 -> 12984.788 | J11: ='Revenue BuildUp'!J11 -> 14334.34 | ... Q11: ='Revenue BuildUp'!Q11 -> 35620.804
B13: COGS | C13: =SUM(C16,C19,C22) -> 4270 | D13: =SUM(D16,D19,D22) -> 5436 | E13: =SUM(E16,E19,E22) -> 5351 | F13: =SUM(F16,F19,F22) -> 4748 | G13: =SUM(G16,G19,G22) -> 5388 | H13: =SUM(H16,H19,H22) -> 6244.576 | I13: =SUM(I16,I19,I22) -> 6854.4558 | J13: =SUM(J16,J19,J22) -> 7566.8621 | ... Q13: =SUM(Q16,Q19,Q22) -> 18803.636
B14: % of Revenue | C14: =C13/C11 -> 0.5305666 | D14: =D13/D11 -> 0.57148865 | E14: =E13/E11 -> 0.54803359 | F14: =F13/F11 -> 0.49186781 | G14: =G13/G11 -> 0.49746099 | H14: =H13/H11 -> 0.52788353 | I14: =I13/I11 -> 0.52788353 | J14: =J13/J11 -> 0.52788353 | ... Q14: =Q13/Q11 -> 0.52788353
B16: Cost of materials consumed | C16: ='Income Statement'!C14 -> 3884 | D16: ='Income Statement'!D14 -> 5061 | E16: ='Income Statement'!E14 -> 4649 | F16: ='Income Statement'!F14 -> 3941 | G16: ='Income Statement'!G14 -> 4572 | H16: =H17*H11 -> 5491.6945 | I16: =I17*I11 -> 6028.0438 | J16: =J17*J11 -> 6654.5584 | K16: =K17*K11 -> 7393.4981 | L16: =L17*L11 -> 8273.5131 | M16: =M17*M11 -> 9331.5584 | N16: =N17*N11 -> 10615.388 | O16: =O17*O11 -> 12186.806 | ... Q16: =Q17*Q11 -> 16536.563
B17: % of Revenue | C17: =C16/C11 -> 0.48260437 | D17: =D16/D11 -> 0.53206476 | E17: =E16/E11 -> 0.47613683 | F17: =F16/F11 -> 0.40826686 | G17: =G16/G11 -> 0.42212169 | H17: =AVERAGE(C17:G17) -> 0.4642389 | I17: =H17 -> 0.4642389 | J17: =I17 -> 0.4642389 | K17: =J17 -> 0.4642389 | L17: =K17 -> 0.4642389 | M17: =L17 -> 0.4642389 | N17: =M17 -> 0.4642389 | O17: =N17 -> 0.4642389 | P17: =O17 -> 0.4642389 | Q17: =P17 -> 0.4642389
B19: Purchases of stock-in-trade | C19: ='Income Statement'!C15 -> 339 | D19: ='Income Statement'!D15 -> 491 | E19: ='Income Statement'!E15 -> 541 | F19: ='Income Statement'!F15 -> 752 | G19: ='Income Statement'!G15 -> 960 | H19: =H20*H11 -> 746.88029 | I19: =I20*I11 -> 819.82475 | J19: =J20*J11 -> 905.03186 | K19: =K20*K11 -> 1005.529 | L19: =L20*L11 -> 1125.2126 | M19: =M20*M11 -> 1269.1087 | N19: =N20*N11 -> 1443.7118 | O19: =O20*O11 -> 1657.4275 | ... Q19: =Q20*Q11 -> 2249.0022
B20: % of Revenue | C20: =C19/C11 -> 0.042122266 | D20: =D19/D11 -> 0.051619008 | E20: =E19/E11 -> 0.05540762 | F20: =F19/F11 -> 0.077903243 | G20: =G19/G11 -> 0.088634475 | H20: =AVERAGE(C20:G20) -> 0.063137322 | I20: =H20 -> 0.063137322 | J20: =I20 -> 0.063137322 | K20: =J20 -> 0.063137322 | L20: =K20 -> 0.063137322 | M20: =L20 -> 0.063137322 | N20: =M20 -> 0.063137322 | O20: =N20 -> 0.063137322 | P20: =O20 -> 0.063137322 | Q20: =P20 -> 0.063137322
B22: Changes in inventories of finished goods, stock-in-trade and work-in progress | C22: ='Income Statement'!C16 -> 47 | D22: ='Income Statement'!D16 -> -116 | E22: ='Income Statement'!E16 -> 161 | F22: ='Income Statement'!F16 -> 55 | G22: ='Income Statement'!G16 -> -144 | H22: =H23*H11 -> 6.0011345 | I22: =I23*I11 -> 6.5872385 | J22: =J23*J11 -> 7.2718721 | K22: =K23*K11 -> 8.0793599 | L22: =L23*L11 -> 9.04101 | M22: =M23*M11 -> 10.197205 | N22: =N23*N11 -> 11.600131 | O22: =O23*O11 -> 13.317322 | ... Q22: =Q23*Q11 -> 18.070586
B23: % of Revenue | C23: =C22/C11 -> 0.0058399602 | D23: =D22/D11 -> -0.012195122 | E23: =E22/E11 -> 0.016489144 | F23: =F22/F11 -> 0.0056977106 | G23: =G22/G11 -> -0.013295171 | H23: =AVERAGE(C23:G23) -> 0.00050730427 | I23: =H23 -> 0.00050730427 | J23: =I23 -> 0.00050730427 | K23: =J23 -> 0.00050730427 | L23: =K23 -> 0.00050730427 | M23: =L23 -> 0.00050730427 | N23: =M23 -> 0.00050730427 | O23: =N23 -> 0.00050730427 | P23: =O23 -> 0.00050730427 | Q23: =P23 -> 0.00050730427
B26: Employee benefit expense | C26: ='Income Statement'!C17 -> 570 | D26: ='Income Statement'!D17 -> 586 | E26: ='Income Statement'!E17 -> 653 | F26: ='Income Statement'!F17 -> 743 | G26: ='Income Statement'!G17 -> 831 | H26: =H27*H11 -> 835.17126 | I26: =I27*I11 -> 916.73871 | J26: =J27*J11 -> 1012.0184 | K26: =K27*K11 -> 1124.3956 | L26: =L27*L11 -> 1258.2274 | M26: =M27*M11 -> 1419.1338 | N26: =N27*N11 -> 1614.3774 | O26: =O27*O11 -> 1853.357 | ... Q26: =Q27*Q11 -> 2514.8635
B27: % of Revenue | C27: =C26/C11 -> 0.07082505 | D27: =D26/D11 -> 0.061606392 | E27: =E26/E11 -> 0.066878329 | F27: =F26/F11 -> 0.07697089 | G27: =G26/G11 -> 0.076724218 | H27: =AVERAGE(C27:G27) -> 0.070600976 | I27: =H27 -> 0.070600976 | J27: =I27 -> 0.070600976 | K27: =J27 -> 0.070600976 | L27: =K27 -> 0.070600976 | M27: =L27 -> 0.070600976 | N27: =M27 -> 0.070600976 | O27: =N27 -> 0.070600976 | P27: =O27 -> 0.070600976 | Q27: =P27 -> 0.070600976
B29: Other expenses | C29: ='Income Statement'!C20 -> 1617 | D29: ='Income Statement'!D20 -> 1809 | E29: ='Income Statement'!E20 -> 1950 | F29: ='Income Statement'!F20 -> 2136 | G29: ='Income Statement'!G20 -> 2473 | H29: =H30*H11 -> 2461.5162 | I29: =I30*I11 -> 2701.9215 | J29: =J30*J11 -> 2982.7411 | K29: =K30*K11 -> 3313.9526 | L29: =L30*L11 -> 3708.3975 | M29: =M30*M11 -> 4182.6401 | N29: =N30*N11 -> 4758.0852 | O29: =O30*O11 -> 5462.4344 | ... Q29: =Q30*Q11 -> 7412.1051
B30: % of Revenue | C30: =C29/C11 -> 0.20091948 | D30: =D29/D11 -> 0.19018082 | E30: =E29/E11 -> 0.19971323 | F30: =F29/F11 -> 0.22127836 | G30: =G29/G11 -> 0.2283261 | H30: =AVERAGE(C30:G30) -> 0.2080836 | I30: =H30 -> 0.2080836 | J30: =I30 -> 0.2080836 | K30: =J30 -> 0.2080836 | L30: =K30 -> 0.2080836 | M30: =L30 -> 0.2080836 | N30: =M30 -> 0.2080836 | O30: =N30 -> 0.2080836 | P30: =O30 -> 0.2080836 | Q30: =P30 -> 0.2080836
B33: OPEX | C33: =C29+C26 -> 2187 | D33: =D29+D26 -> 2395 | E33: =E29+E26 -> 2603 | F33: =F29+F26 -> 2879 | G33: =G29+G26 -> 3304 | H33: =H29+H26 -> 3296.6874 | I33: =I29+I26 -> 3618.6602 | J33: =J29+J26 -> 3994.7595 | ... Q33: =Q29+Q26 -> 9926.9685

Sheet Debt Schedules
B7: Debt Schedules
B8: All Figure In INR Cr.
B9: Particulars | C9: 2021 | D9: =C9+1 -> 2022 | E9: =D9+1 -> 2023 | F9: =E9+1 -> 2024 | G9: =F9+1 -> 2025 | H9: =G9+1 -> 2026 | I9: =H9+1 -> 2027 | J9: =I9+1 -> 2028 | K9: =J9+1 -> 2029 | ... Q9: =P9+1 -> 2035
B11: Debt Opening | D11: =C13 -> 508 | E11: =D13 -> 479 | F11: =E13 -> 608 | G11: =F13 -> 528 | H11: =G13 -> 554 | I11: =H13 -> 671.42403 | J11: =I13 -> 737.36525 | K11: =J13 -> 814.46065 | ... Q11: =P13 -> 1737.0511
B12: Issuance (Repayments) | D12: =D13-D11 -> -29 | E12: =E13-E11 -> 129 | F12: =F13-F11 -> -80 | G12: =G13-G11 -> 26 | H12: =H13-H11 -> 117.42403 | I12: =I13-I11 -> 65.94122 | J12: =J13-J11 -> 77.0954 | K12: =K13-K11 -> 91.011966 | ... Q12: =Q13-Q11 -> 108.78967
B13: Debt Closing | C13: ='Balance Sheet'!C52+'Balance Sheet'!C53+'Balance Sheet'!C61+'Balance Sheet'!C62 -> 508 | D13: ='Balance Sheet'!D52+'Balance Sheet'!D53+'Balance Sheet'!D61+'Balance Sheet'!D62 -> 479 | E13: ='Balance Sheet'!E52+'Balance Sheet'!E53+'Balance Sheet'!E61+'Balance Sheet'!E62 -> 608 | F13: ='Balance Sheet'!F52+'Balance Sheet'!F53+'Balance Sheet'!F61+'Balance Sheet'!F62 -> 528 | G13: ='Balance Sheet'!G52+'Balance Sheet'!G53+'Balance Sheet'!G61+'Balance Sheet'!G62 -> 554 | H13: =SUM('B_Sheet Forecast'!H39,'B_Sheet Forecast'!H41,'B_Sheet Forecast'!H54,'B_Sheet Forecast'!I56) -> 671.42403 | I13: =SUM('B_Sheet Forecast'!I39,'B_Sheet Forecast'!I41,'B_Sheet Forecast'!I54,'B_Sheet Forecast'!J56) -> 737.36525 | J13: =SUM('B_Sheet Forecast'!J39,'B_Sheet Forecast'!J41,'B_Sheet Forecast'!J54,'B_Sheet Forecast'!K56) -> 814.46065 | K13: =SUM('B_Sheet Forecast'!K39,'B_Sheet Forecast'!K41,'B_Sheet Forecast'!K54,'B_Sheet Forecast'!L56) -> 905.47262 | L13: =SUM('B_Sheet Forecast'!L39,'B_Sheet Forecast'!L41,'B_Sheet Forecast'!L54,'B_Sheet Forecast'!M56) -> 1013.9574 | M13: =SUM('B_Sheet Forecast'!M39,'B_Sheet Forecast'!M41,'B_Sheet Forecast'!M54,'B_Sheet Forecast'!N56) -> 1144.5027 | N13: =SUM('B_Sheet Forecast'!N39,'B_Sheet Forecast'!N41,'B_Sheet Forecast'!N54,'B_Sheet Forecast'!O56) -> 1303.0383 | O13: =SUM('B_Sheet Forecast'!O39,'B_Sheet Forecast'!O41,'B_Sheet Forecast'!O54,'B_Sheet Forecast'!P56) -> 1497.2389 | ... Q13: =SUM('B_Sheet Forecast'!Q39,'B_Sheet Forecast'!Q41,'B_Sheet Forecast'!Q54,'B_Sheet Forecast'!R56) -> 1845.8408
B14: Interest Expenses | C14: ='Income Statement'!C18 -> 34 | D14: ='Income Statement'!D18 -> 39 | E14: ='Income Statement'!E18 -> 56 | F14: ='Income Statement'!F18 -> 73 | G14: ='Income Statement'!G18 -> 53 | H14: =H13*H15 -> 63.701955 | I14: =I13*I15 -> 69.958187 | J14: =J13*J15 -> 77.272682 | K14: =K13*K15 -> 85.907524 | L14: =L13*L15 -> 96.20011 | M14: =M13*M15 -> 108.58572 | N14: =N13*N15 -> 123.62692 | O14: =O13*O15 -> 142.05187 | ... Q14: =Q13*Q15 -> 175.12579
B15: Interest rate | C15: =C14/C13 -> 0.066929134 | D15: =D14/D13 -> 0.081419624 | E15: =E14/E13 -> 0.092105263 | F15: =F14/F13 -> 0.13825758 | G15: =G14/G13 -> 0.09566787 | H15: =AVERAGE(C15:G15) -> 0.094875893 | I15: =H15 -> 0.094875893 | J15: =I15 -> 0.094875893 | K15: =J15 -> 0.094875893 | L15: =K15 -> 0.094875893 | M15: =L15 -> 0.094875893 | N15: =M15 -> 0.094875893 | O15: =N15 -> 0.094875893 | P15: =O15 -> 0.094875893 | Q15: =P15 -> 0.094875893

Sheet Working Capital
B7: Working Capital
B8: All Figure In INR Cr.
B9: Particulars | C9: 2021 | D9: =C9+1 -> 2022 | E9: =D9+1 -> 2023 | F9: =E9+1 -> 2024 | G9: =F9+1 -> 2025 | H9: =G9+1 -> 2026 | I9: =H9+1 -> 2027 | J9: =I9+1 -> 2028 | K9: =J9+1 -> 2029 | ... Q9: =P9+1 -> 2035
B10: Days of Operation | C10: 365 | D10: 365 | E10: 365 | F10: 365 | G10: 365 | H10: 365 | I10: 365 | J10: 365 | K10: 365 | L10: 365 | M10: 365 | N10: 365 | O10: 365 | P10: 365 | Q10: 365
B12: Inventories | C12: ='Balance Sheet'!C26 -> 1126 | D12: ='Balance Sheet'!D26 -> 1412 | E12: ='Balance Sheet'!E26 -> 1225 | F12: ='Balance Sheet'!F26 -> 1336 | G12: ='Balance Sheet'!G26 -> 1235 | H12: =H17*'Cost BuildUp'!H13/'Working Capital'!H10 -> 1577.3473 | I12: =I17*'Cost BuildUp'!I13/'Working Capital'!I10 -> 1731.3998 | J12: =J17*'Cost BuildUp'!J13/'Working Capital'!J10 -> 1911.3499 | K12: =K17*'Cost BuildUp'!K13/'Working Capital'!K10 -> 2123.5912 | L12: =L17*'Cost BuildUp'!L13/'Working Capital'!L10 -> 2376.3528 | M12: =M17*'Cost BuildUp'!M13/'Working Capital'!M10 -> 2680.249 | N12: =N17*'Cost BuildUp'!N13/'Working Capital'!N10 -> 3048.996 | O12: =O17*'Cost BuildUp'!O13/'Working Capital'!O10 -> 3500.3452 | ... Q12: =Q17*'Cost BuildUp'!Q13/'Working Capital'!Q10 -> 4749.7003
B13: Trade receivables | C13: ='Balance Sheet'!C29 -> 388 | D13: ='Balance Sheet'!D29 -> 652 | E13: ='Balance Sheet'!E29 -> 1015 | F13: ='Balance Sheet'!F29 -> 1069 | G13: ='Balance Sheet'!G29 -> 1271 | H13: =H18*'Cost BuildUp'!H11/'Working Capital'!H10 -> 1061.8125 | I13: =I18*'Cost BuildUp'!I11/'Working Capital'!I10 -> 1165.515 | J13: =J18*'Cost BuildUp'!J11/'Working Capital'!J10 -> 1286.6508 | K13: =K18*'Cost BuildUp'!K11/'Working Capital'!K10 -> 1429.5239 | L13: =L18*'Cost BuildUp'!L11/'Working Capital'!L10 -> 1599.6738 | M13: =M18*'Cost BuildUp'!M11/'Working Capital'!M10 -> 1804.2456 | N13: =N18*'Cost BuildUp'!N11/'Working Capital'!N10 -> 2052.4725 | O13: =O18*'Cost BuildUp'!O11/'Working Capital'!O10 -> 2356.3043 | ... Q13: =Q18*'Cost BuildUp'!Q11/'Working Capital'!Q10 -> 3197.3244
B14: Trade Payables | C14: =SUM('Balance Sheet'!C64:C65) -> 1134 | D14: =SUM('Balance Sheet'!D64:D65) -> 1344 | E14: =SUM('Balance Sheet'!E64:E65) -> 1452 | F14: =SUM('Balance Sheet'!F64:F65) -> 1581 | G14: =SUM('Balance Sheet'!G64:G65) -> 1363 | H14: =H19*'Cost BuildUp'!H13/'Working Capital'!H10 -> 1711.1604 | I14: =I19*'Cost BuildUp'!I13/'Working Capital'!I10 -> 1878.2818 | J14: =J19*'Cost BuildUp'!J13/'Working Capital'!J10 -> 2073.4979 | K14: =K19*'Cost BuildUp'!K13/'Working Capital'!K10 -> 2303.7446 | L14: =L19*'Cost BuildUp'!L13/'Working Capital'!L10 -> 2577.949 | M14: =M19*'Cost BuildUp'!M13/'Working Capital'!M10 -> 2907.626 | N14: =N19*'Cost BuildUp'!N13/'Working Capital'!N10 -> 3307.6553 | O14: =O19*'Cost BuildUp'!O13/'Working Capital'!O10 -> 3797.2945 | ... Q14: =Q19*'Cost BuildUp'!Q13/'Working Capital'!Q10 -> 5152.6377
B16: KPI
B17: DIO | C17: =C12/'Cost BuildUp'!C13*'Working Capital'!C10 -> 96.250585 | D17: =D12/'Cost BuildUp'!D13*'Working Capital'!D10 -> 94.808683 | E17: =E12/'Cost BuildUp'!E13*'Working Capital'!E10 -> 83.559148 | F17: =F12/'Cost BuildUp'!F13*'Working Capital'!F10 -> 102.7043 | G17: =G12/'Cost BuildUp'!G13*'Working Capital'!G10 -> 83.662769 | H17: =AVERAGE(C17:G17) -> 92.197096 | I17: =H17 -> 92.197096 | J17: =I17 -> 92.197096 | K17: =J17 -> 92.197096 | L17: =K17 -> 92.197096 | M17: =L17 -> 92.197096 | N17: =M17 -> 92.197096 | O17: =N17 -> 92.197096 | P17: =O17 -> 92.197096 | Q17: =P17 -> 92.197096
B18: DSO | C18: =C13/'Cost BuildUp'!C11*'Working Capital'!C10 -> 17.596918 | D18: =D13/'Cost BuildUp'!D11*'Working Capital'!D10 -> 25.018923 | E18: =E13/'Cost BuildUp'!E11*'Working Capital'!E10 -> 37.942954 | F18: =F13/'Cost BuildUp'!F11*'Working Capital'!F10 -> 40.421113 | G18: =G13/'Cost BuildUp'!G11*'Working Capital'!G10 -> 42.832148 | H18: =AVERAGE(C18:G18) -> 32.762411 | I18: =H18 -> 32.762411 | J18: =I18 -> 32.762411 | K18: =J18 -> 32.762411 | L18: =K18 -> 32.762411 | M18: =L18 -> 32.762411 | N18: =M18 -> 32.762411 | O18: =N18 -> 32.762411 | P18: =O18 -> 32.762411 | Q18: =P18 -> 32.762411
B19: DPO | C19: =C14/'Cost BuildUp'!C13*'Working Capital'!C10 -> 96.934426 | D19: =D14/'Cost BuildUp'!D13*'Working Capital'!D10 -> 90.242826 | E19: =E14/'Cost BuildUp'!E13*'Working Capital'!E10 -> 99.04317 | F19: =F14/'Cost BuildUp'!F13*'Working Capital'!F10 -> 121.53854 | G19: =G14/'Cost BuildUp'!G13*'Working Capital'!G10 -> 92.33389 | H19: =AVERAGE(C19:G19) -> 100.01857 | I19: =H19 -> 100.01857 | J19: =I19 -> 100.01857 | K19: =J19 -> 100.01857 | L19: =K19 -> 100.01857 | M19: =L19 -> 100.01857 | N19: =M19 -> 100.01857 | O19: =N19 -> 100.01857 | P19: =O19 -> 100.01857 | Q19: =P19 -> 100.01857

Sheet Equity Market
B8: Equity Marekt Return
B10: Date | C10: Close
B11: 42229 | C11: 27549.53 | E11: Year | F11: =YEARFRAC(B2488,B11) -> 10
B12: 42230 | C12: 28067.31 | E12: RRI | F12: =_xlfn.RRI(F11,C11,C2488) -> 0.11324229
B13: 42233 | C13: 27878.27
B14: 42234 | C14: 27831.54
B15: 42235 | C15: 27931.64
B16: 42236 | C16: 27607.82
B17: 42237 | C17: 27366.07
B18: 42240 | C18: 25741.56
B19: 42241 | C19: 26032.38
B20: 42242 | C20: 25714.66
B21: 42243 | C21: 26231.19
B22: 42244 | C22: 26392.38
B23: 42247 | C23: 26283.09
B24: 42248 | C24: 25696.44
... B2488: 45882 | C2488: 80539.91

Sheet Beta
B8: Beta
B10: Date | C10: Sensex | D10: % | F10: Date | G10: Stock Closing Price | H10: %
C11: Closing Price | D11: Change | H11: Change
B12: 42217 | C12: 26283.09 | F12: 42217 | G12: 406.1 | K12: Beta | L12: =SLOPE(H13:H132,D13:D132) -> 0.42148317 | M12: =_xlfn.FORMULATEXT(L12) -> =SLOPE(H13:H132,D13:D132)
B13: 42248 | C13: 26154.83 | D13: =C13/C12-1 -> -0.0048799437 | F13: 42248 | G13: 404.4 | H13: =G13/G12-1 -> -0.004186161 | K13: Beta | L13: =_xlfn.COVARIANCE.S(H13:H132,D13:D132)/_xlfn.VAR.S(D13:D132) -> 0.42148317 | M13: =_xlfn.FORMULATEXT(L13) -> =COVARIANCE.S(H13:H132,D13:D132)/VAR.S(D13:D132)
B14: 42278 | C14: 26656.83 | D14: =C14/C13-1 -> 0.019193396 | F14: 42278 | G14: 387.2 | H14: =G14/G13-1 -> -0.042532146 | K14: Beta | L14: =L33 -> 0.42148317 | M14: Regression Method
B15: 42309 | C15: 26145.67 | D15: =C15/C14-1 -> -0.019175573 | F15: 42309 | G15: 423.2 | H15: =G15/G14-1 -> 0.092975207
B16: 42339 | C16: 26117.54 | D16: =C16/C15-1 -> -0.0010758952 | F16: 42339 | G16: 226.3 | H16: =G16/G15-1 -> -0.46526465 | K16: SUMMARY OUTPUT
B17: 42370 | C17: 24870.69 | D17: =C17/C16-1 -> -0.047739948 | F17: 42370 | G17: 222.1 | H17: =G17/G16-1 -> -0.018559434
B18: 42401 | C18: 23002 | D18: =C18/C17-1 -> -0.075136235 | F18: 42401 | G18: 236.85 | H18: =G18/G17-1 -> 0.066411526 | K18: Regression Statistics
B19: 42430 | C19: 25341.86 | D19: =C19/C18-1 -> 0.1017242 | F19: 42430 | G19: 242.5 | H19: =G19/G18-1 -> 0.02385476 | K19: Multiple R | L19: 0.27514388
B20: 42461 | C20: 25606.62 | D20: =C20/C19-1 -> 0.010447536 | F20: 42461 | G20: 258.3 | H20: =G20/G19-1 -> 0.065154639 | K20: R Square | L20: 0.075704156
B21: 42491 | C21: 26667.96 | D21: =C21/C20-1 -> 0.041447876 | F21: 42491 | G21: 249.15 | H21: =G21/G20-1 -> -0.035423926 | K21: Adjusted R Square | L21: 0.06787114
B22: 42522 | C22: 26999.72 | D22: =C22/C21-1 -> 0.012440397 | F22: 42522 | G22: 264.35 | H22: =G22/G21-1 -> 0.061007425 | K22: Standard Error | L22: 0.068360543
B23: 42552 | C23: 28051.86 | D23: =C23/C22-1 -> 0.038968552 | F23: 42552 | G23: 284.15 | H23: =G23/G22-1 -> 0.0749007 | K23: Observations | L23: 120
B24: 42583 | C24: 28452.17 | D24: =C24/C23-1 -> 0.014270355 | F24: 42583 | G24: 291.6 | H24: =G24/G23-1 -> 0.026218547
B25: 42614 | C25: 27865.96 | D25: =C25/C24-1 -> -0.020603349 | F25: 42614 | G25: 275.2 | H25: =G25/G24-1 -> -0.056241427 | K25: ANOVA
B26: 42644 | C26: 27930.21 | D26: =C26/C25-1 -> 0.0023056805 | F26: 42644 | G26: 278.45 | H26: =G26/G25-1 -> 0.011809593 | L26: df | M26: SS | N26: MS | O26: F | P26: Significance F
B27: 42675 | C27: 26652.81 | D27: =C27/C26-1 -> -0.045735424 | F27: 42675 | G27: 252.3 | H27: =G27/G26-1 -> -0.093912731 | K27: Regression | L27: 1 | M27: 0.045164972 | N27: 0.045164972 | O27: 9.6647523 | P27: 0.0023545634
B28: 42705 | C28: 26626.46 | D28: =C28/C27-1 -> -0.00098863872 | F28: 42705 | G28: 260.25 | H28: =G28/G27-1 -> 0.031510107 | K28: Residual | L28: 118 | M28: 0.55143334 | N28: 0.0046731639
B29: 42736 | C29: 27655.96 | D29: =C29/C28-1 -> 0.038664546 | F29: 42736 | G29: 257.25 | H29: =G29/G28-1 -> -0.011527378 | K29: Total | L29: 119 | M29: 0.59659831
B30: 42767 | C30: 28743.32 | D30: =C30/C29-1 -> 0.039317384 | F30: 42767 | G30: 280.5 | H30: =G30/G29-1 -> 0.090379009
B31: 42795 | C31: 29620.5 | D31: =C31/C30-1 -> 0.030517699 | F31: 42795 | G31: 294.35 | H31: =G31/G30-1 -> 0.049376114 | L31: Coefficients | M31: Standard Error | N31: t Stat | O31: P-value | P31: Lower 95% | Q31: Upper 95% | R31: Lower 95.0% | S31: Upper 95.0%
B32: 42826 | C32: 29918.4 | D32: =C32/C31-1 -> 0.010057224 | F32: 42826 | G32: 314.9 | H32: =G32/G31-1 -> 0.069814846 | K32: Intercept | L32: 0.0031555941 | M32: 0.0063995488 | N32: 0.49309635 | O32: 0.62286091 | P32: -0.0095172548 | Q32: 0.015828443 | R32: -0.0095172548 | S32: 0.015828443
B33: 42856 | C33: 31145.8 | D33: =C33/C32-1 -> 0.041024921 | F33: 42856 | G33: 313.9 | H33: =G33/G32-1 -> -0.0031756113 | K33: X Variable 1 | L33: 0.42148317 | M33: 0.13557664 | N33: 3.1088185 | O33: 0.0023545634 | P33: 0.15300451 | Q33: 0.68996183 | R33: 0.15300451 | S33: 0.68996183
B34: 42887 | C34: 30921.61 | D34: =C34/C33-1 -> -0.0071980813 | F34: 42887 | G34: 313.95 | H34: =G34/G33-1 -> 0.0001592864
B35: 42917 | C35: 32514.94 | D35: =C35/C34-1 -> 0.051528041 | F35: 42917 | G35: 333.55 | H35: =G35/G34-1 -> 0.062430323
B36: 42948 | C36: 31730.49 | D36: =C36/C35-1 -> -0.024125833 | F36: 42948 | G36: 314.5 | H36: =G36/G35-1 -> -0.057112877
B37: 42979 | C37: 31283.72 | D37: =C37/C36-1 -> -0.014080148 | F37: 42979 | G37: 310.75 | H37: =G37/G36-1 -> -0.011923688
B38: 43009 | C38: 33213.13 | D38: =C38/C37-1 -> 0.061674571 | F38: 43009 | G38: 315.2 | H38: =G38/G37-1 -> 0.014320193
B39: 43040 | C39: 33149.35 | D39: =C39/C38-1 -> -0.0019203249 | F39: 43040 | G39: 305.7 | H39: =G39/G38-1 -> -0.030139594
B40: 43070 | C40: 34056.83 | D40: =C40/C39-1 -> 0.027375499 | F40: 43070 | G40: 322.15 | H40: =G40/G39-1 -> 0.053810926
B41: 43101 | C41: 35965.02 | D41: =C41/C40-1 -> 0.056029583 | F41: 43101 | G41: 309.6 | H41: =G41/G40-1 -> -0.038957008
B42: 43132 | C42: 34184.04 | D42: =C42/C41-1 -> -0.049519783 | F42: 43132 | G42: 308.75 | H42: =G42/G41-1 -> -0.002745478
B43: 43160 | C43: 32968.68 | D43: =C43/C42-1 -> -0.035553434 | F43: 43160 | G43: 326.1 | H43: =G43/G42-1 -> 0.056194332
B44: 43191 | C44: 35160.36 | D44: =C44/C43-1 -> 0.066477639 | F44: 43191 | G44: 332.85 | H44: =G44/G43-1 -> 0.020699172
B45: 43221 | C45: 35322.38 | D45: =C45/C44-1 -> 0.0046080302 | F45: 43221 | G45: 322.15 | H45: =G45/G44-1 -> -0.032146613
... B132: 45870 | C132: 80539.91 | D132: =C132/C131-1 -> -0.0079530133 | F132: 45870 | G132: 710.6 | H132: =G132/G131-1 -> 0.0020447014

Sheet Comps Valuation
B8: Comparable Valuation
B9: All Figure In INR Cr.
B10: Company | E10: Market Data | L10: Financial data | P10: Valution
E11: Price | F11: Share | G11: Market Cap | H11: Debt | I11: Cash | J11: EV | L11: Sales | M11: EBITDA | N11: Earnings | P11: EV/Sales | Q11: EV/EBITDA | R11: P/E
B12: Company Name | C12: Ticker | E12: (/share) | F12: (Cr.) | G12: ₹ Cr. | H12: ₹ Cr. | I12: ₹ Cr. | J12: ₹ Cr. | L12: ₹ Cr. | M12: ₹ Cr. | N12: ₹ Cr. | P12: x | Q12: x | R12: x
B13: ='Comps Data'!C9 -> Hind. Unilever | E13: ='Comps Data'!D9 -> 2502.45 | F13: ='Comps Data'!E9 -> 234.96 | G13: =F13*E13 -> 587975.65 | H13: ='Comps Data'!F9 -> 1648 | I13: ='Comps Data'!G9 -> 7554 | J13: =G13+H13-I13 -> 582069.65 | L13: ='Comps Data'!I9 -> 63121 | M13: ='Comps Data'!K9+'Comps Data'!J9 -> 15860 | N13: ='Comps Data'!H9 -> 10671 | P13: =J13/L13 -> 9.2214897 | Q13: =J13/M13 -> 36.700482 | R13: =G13/N13 -> 55.100333
B14: ='Comps Data'!C10 -> Nestle India | E14: ='Comps Data'!D10 -> 1098.5 | F14: ='Comps Data'!E10 -> 192.83 | G14: =F14*E14 -> 211823.76 | H14: ='Comps Data'!F10 -> 1166.85 | I14: ='Comps Data'!G10 -> 95.65 | J14: =G14+H14-I14 -> 212894.96 | L14: ='Comps Data'!I10 -> 20201.56 | M14: ='Comps Data'!K10+'Comps Data'!J10 -> 4830.19 | N14: ='Comps Data'!H10 -> 3314.5 | P14: =J14/L14 -> 10.53854 | Q14: =J14/M14 -> 44.075897 | R14: =G14/N14 -> 63.908208
B15: ='Comps Data'!C11 -> Britannia Inds. | E15: ='Comps Data'!D11 -> 5352.1 | F15: ='Comps Data'!E11 -> 24.09 | G15: =F15*E15 -> 128932.09 | H15: ='Comps Data'!F11 -> 1246.51 | I15: ='Comps Data'!G11 -> 312.48 | J15: =G15+H15-I15 -> 129866.12 | L15: ='Comps Data'!I11 -> 17942.67 | M15: ='Comps Data'!K11+'Comps Data'!J11 -> 3402.26 | N15: ='Comps Data'!H11 -> 2177.86 | P15: =J15/L15 -> 7.2378369 | Q15: =J15/M15 -> 38.170545 | R15: =G15/N15 -> 59.201275
B16: ='Comps Data'!C12 -> Godrej Consumer | E16: ='Comps Data'!D12 -> 1192.55 | F16: ='Comps Data'!E12 -> 102.31 | G16: =F16*E16 -> 122009.79 | H16: ='Comps Data'!F12 -> 4009.19 | I16: ='Comps Data'!G12 -> 483.06 | J16: =G16+H16-I16 -> 125535.92 | L16: ='Comps Data'!I12 -> 14364.29 | M16: ='Comps Data'!K12+'Comps Data'!J12 -> 3291.51 | N16: ='Comps Data'!H12 -> 1852.3 | P16: =J16/L16 -> 8.7394449 | Q16: =J16/M16 -> 38.13931 | R16: =G16/N16 -> 65.869346
B17: ='Comps Data'!C13 -> Tata Consumer | E17: ='Comps Data'!D13 -> 1056.05 | F17: ='Comps Data'!E13 -> 98.95 | G17: =F17*E17 -> 104496.15 | H17: ='Comps Data'!F13 -> 2392.68 | I17: ='Comps Data'!G13 -> 2817.86 | J17: =G17+H17-I17 -> 104070.97 | L17: ='Comps Data'!I13 -> 17618.3 | M17: ='Comps Data'!K13+'Comps Data'!J13 -> 2647.81 | N17: ='Comps Data'!H13 -> 1287.1 | P17: =J17/L17 -> 5.9069812 | Q17: =J17/M17 -> 39.304545 | R17: =G17/N17 -> 81.18728
B18: ='Comps Data'!C14 -> Dabur India | E18: ='Comps Data'!D14 -> 503.5 | F18: ='Comps Data'!E14 -> 177.37 | G18: =F18*E18 -> 89305.795 | H18: ='Comps Data'!F14 -> 950.37 | I18: ='Comps Data'!G14 -> 578.01 | J18: =G18+H18-I18 -> 89678.155 | L18: ='Comps Data'!I14 -> 12563.09 | M18: ='Comps Data'!K14+'Comps Data'!J14 -> 2857.67 | N18: ='Comps Data'!H14 -> 1740.42 | P18: =J18/L18 -> 7.1382244 | Q18: =J18/M18 -> 31.381564 | R18: =G18/N18 -> 51.312784
B19: ='Comps Data'!C15 -> Patanjali Foods | E19: ='Comps Data'!D15 -> 1778 | F19: ='Comps Data'!E15 -> 36.25 | G19: =F19*E19 -> 64452.5 | H19: ='Comps Data'!F15 -> 787.68 | I19: ='Comps Data'!G15 -> 275.3 | J19: =G19+H19-I19 -> 64964.88 | L19: ='Comps Data'!I15 -> 34156.97 | M19: ='Comps Data'!K15+'Comps Data'!J15 -> 2079.05 | N19: ='Comps Data'!H15 -> 1301.34 | P19: =J19/L19 -> 1.9019509 | Q19: =J19/M19 -> 31.247387 | R19: =G19/N19 -> 49.527794
B20: ='Comps Data'!C16 -> Emami | E20: ='Comps Data'!D16 -> 580.1 | F20: ='Comps Data'!E16 -> 43.65 | G20: =F20*E20 -> 25321.365 | H20: ='Comps Data'!F16 -> 89.79 | I20: ='Comps Data'!G16 -> 272.9 | J20: =G20+H20-I20 -> 25138.255 | L20: ='Comps Data'!I16 -> 3809.19 | M20: ='Comps Data'!K16+'Comps Data'!J16 -> 1043.04 | N20: ='Comps Data'!H16 -> 802.75 | P20: =J20/L20 -> 6.5993702 | Q20: =J20/M20 -> 24.10095 | R20: =G20/N20 -> 31.543276
B21: ='Comps Data'!C17 -> Bikaji Foods | E21: ='Comps Data'!D17 -> 724.8 | F21: ='Comps Data'!E17 -> 25.06 | G21: =F21*E21 -> 18163.488 | H21: ='Comps Data'!F17 -> 230.94 | I21: ='Comps Data'!G17 -> 219.05 | J21: =G21+H21-I21 -> 18175.378 | L21: ='Comps Data'!I17 -> 2621.85 | M21: ='Comps Data'!K17+'Comps Data'!J17 -> 361.15 | N21: ='Comps Data'!H17 -> 194.35 | P21: =J21/L21 -> 6.9322723 | Q21: =J21/M21 -> 50.326396 | R21: =G21/N21 -> 93.457618
B22: ='Comps Data'!C18 -> AWL Agri Busine. | E22: ='Comps Data'!D18 -> 252.15 | F22: ='Comps Data'!E18 -> 129.97 | G22: =F22*E22 -> 32771.935 | H22: ='Comps Data'!F18 -> 1937.32 | I22: ='Comps Data'!G18 -> 2325.14 | J22: =G22+H22-I22 -> 32384.115 | L22: ='Comps Data'!I18 -> 63672.24 | M22: ='Comps Data'!K18+'Comps Data'!J18 -> 2724.36 | N22: ='Comps Data'!H18 -> 1225.81 | P22: =J22/L22 -> 0.50860651 | Q22: =J22/M22 -> 11.886871 | R22: =G22/N22 -> 26.734923
B24: High | P24: =MAX(P13:P22) -> 10.53854 | Q24: =MAX(Q13:Q22) -> 50.326396 | R24: =MAX(R13:R22) -> 93.457618
B25: 75th Percentile | P25: =_xlfn.QUARTILE.EXC(P13:P22,3) -> 8.8599561 | Q25: =_xlfn.QUARTILE.EXC(Q13:Q22,3) -> 40.497383 | R25: =_xlfn.QUARTILE.EXC(R13:R22,3) -> 69.69883
B26: Average | P26: =AVERAGE(P13:P22) -> 6.4724717 | Q26: =AVERAGE(Q13:Q22) -> 34.533395 | R26: =AVERAGE(R13:R22) -> 57.784284
B27: Median | P27: =MEDIAN(P13:P22) -> 7.0352483 | Q27: =MEDIAN(Q13:Q22) -> 37.419896 | R27: =MEDIAN(R13:R22) -> 57.150804
B28: 25th Percentile | P28: =_xlfn.QUARTILE.EXC(P13:P22,1) -> 4.9057237 | Q28: =_xlfn.QUARTILE.EXC(Q13:Q22,1) -> 29.460778 | R28: =_xlfn.QUARTILE.EXC(R13:R22,1) -> 45.031665
B29: Low | P29: =MIN(P13:P22) -> 0.50860651 | Q29: =MIN(Q13:Q22) -> 11.886871 | R29: =MIN(R13:R22) -> 26.734923
B31: ='Comps Data'!C20 -> Marico | E31: ='Comps Data'!D20 -> 711 | F31: ='Comps Data'!E20 -> 129.78 | G31: =F31*E31 -> 92273.58 | H31: ='Comps Data'!F20 -> 554 | I31: ='Comps Data'!G20 -> 777 | J31: =G31+H31-I31 -> 92050.58 | L31: ='Comps Data'!I20 -> 10831 | M31: ='P&L Statement '!G18 -> 2139 | N31: ='P&L Statement '!G39 -> 1658 | P31: =J31/L31 -> 8.4988071 | Q31: =J31/M31 -> 43.034399 | R31: =G31/N31 -> 55.653546
B33: Median
B34: Metric | E34: Comps | F34: EV | G34: Net Debt | H34: Equity Value | I34: Share | J34: Share Price | L34: Stock Value
B35: EV/REVENUE | E35: 7.0352483 | F35: =E35*L31 -> 76198.774 | G35: =$H$31-$I$31 -> -223 | H35: =F35-G35 -> 76421.774 | I35: =$F$31 -> 129.78 | J35: =H35/I35 -> 588.85633 | L35: =IF(J35>$E$31,"Undervalued","Overvalued") -> Overvalued
B36: EV/EBITDA | E36: 37.419896 | F36: =E36*M31 -> 80041.158 | G36: =$H$31-$I$31 -> -223 | H36: =F36-G36 -> 80264.158 | I36: =$F$31 -> 129.78 | J36: =H36/I36 -> 618.46323 | L36: =IF(J36>$E$31,"Undervalued","Overvalued") -> Overvalued
B37: P/E | E37: 57.150804 | F37: =G37+H37 -> 94533.033 | G37: =$H$31-$I$31 -> -223 | H37: =E37*N31 -> 94756.033 | I37: =$F$31 -> 129.78 | J37: =H37/I37 -> 730.12816 | L37: =IF(J37>$E$31,"Undervalued","Overvalued") -> Undervalued
B39: Average
B40: Metric | E40: Comps | F40: EV | G40: Net Debt | H40: Equity Value | I40: Share | J40: Share Price | L40: Stock Value
B41: EV/REVENUE | E41: 6.4724717 | F41: =E41*L31 -> 70103.341 | G41: =$H$31-$I$31 -> -223 | H41: =F41-G41 -> 70326.341 | I41: =$F$31 -> 129.78 | J41: =H41/I41 -> 541.8889 | L41: =IF(J41>$E$31,"Undervalued","Overvalued") -> Overvalued
B42: EV/EBITDA | E42: 34.533395 | F42: =E42*M31 -> 73866.931 | G42: =$H$31-$I$31 -> -223 | H42: =F42-G42 -> 74089.931 | I42: =$F$31 -> 129.78 | J42: =H42/I42 -> 570.88867 | L42: =IF(J42>$E$31,"Undervalued","Overvalued") -> Overvalued
B43: P/E | E43: 57.784284 | F43: =G43+H43 -> 95583.342 | G43: =$H$31-$I$31 -> -223 | H43: =E43*N31 -> 95806.342 | I43: =$F$31 -> 129.78 | J43: =H43/I43 -> 738.22116 | L43: =IF(J43>$E$31,"Undervalued","Overvalued") -> Undervalued

Sheet Comps Data
B6: Comps Data
B7: All Figure In INR Cr.
B8: S.No. | C8: Name | D8: CMP Rs. | E8: No. Eq. Shares Cr. | F8: Debt Rs.Cr. | G8: Cash Rs.Cr. | H8: NP Ann Rs.Cr. | I8: Sales Ann Rs.Cr. | J8: Dep Ann Rs.Cr. | K8: EBIT Ann Rs.Cr. | L8: EV / EBITDA | M8: EV Rs.Cr. | N8: Mar Cap Rs.Cr. | O8: Tax 12M Rs.Cr. | P8: P/E
B9: 1 | C9: Hind. Unilever | D9: 2502.45 | E9: 234.96 | F9: 1648 | G9: 7554 | H9: 10671 | I9: 63121 | J9: 1355 | K9: 14505 | L9: 36.89 | M9: 582067.47 | N9: 587973.47 | O9: 3362 | P9: 55.29
B10: =B9+1 -> 2 | C10: Nestle India | D10: 1098.5 | E10: 192.83 | F10: 1166.85 | G10: 95.65 | H10: 3314.5 | I10: 20201.56 | J10: 539.92 | K10: 4290.27 | L10: 44.51 | M10: 212896.53 | N10: 211825.33 | O10: 1111.75 | P10: 70.43
B11: =B10+1 -> 3 | C11: Britannia Inds. | D11: 5352.1 | E11: 24.09 | F11: 1246.51 | G11: 312.48 | H11: 2177.86 | I11: 17942.67 | J11: 313.34 | K11: 3088.92 | L11: 38.15 | M11: 129849.16 | N11: 128915.13 | O11: 753.37 | P11: 58.79
B12: =B11+1 -> 4 | C12: Godrej Consumer | D12: 1192.55 | E12: 102.31 | F12: 4009.19 | G12: 483.06 | H12: 1852.3 | I12: 14364.29 | J12: 234 | K12: 3057.51 | L12: 38.08 | M12: 125532.85 | N12: 122006.72 | O12: 787.5 | P12: 64.3
B13: =B12+1 -> 5 | C13: Tata Consumer | D13: 1056.05 | E13: 98.95 | F13: 2392.68 | G13: 2817.86 | H13: 1287.1 | I13: 17618.3 | J13: 600.74 | K13: 2047.07 | L13: 39.81 | M13: 104074.5 | N13: 104499.68 | O13: 381.52 | P13: 79.62
B14: =B13+1 -> 6 | C14: Dabur India | D14: 503.5 | E14: 177.37 | F14: 950.37 | G14: 578.01 | H14: 1740.42 | I14: 12563.09 | J14: 445.6 | K14: 2412.07 | L14: 30.99 | M14: 89677.67 | N14: 89305.31 | O14: 523.7 | P14: 50.94
B15: =B14+1 -> 7 | C15: Patanjali Foods | D15: 1778 | E15: 36.25 | F15: 787.68 | G15: 275.3 | H15: 1301.34 | I15: 34156.97 | J15: 268.39 | K15: 1810.66 | L15: 31.25 | M15: 64966.02 | N15: 64453.64 | O15: 424.83 | P15: 49.54
B16: =B15+1 -> 8 | C16: Emami | D16: 580.1 | E16: 43.65 | F16: 89.79 | G16: 272.9 | H16: 802.75 | I16: 3809.19 | J16: 178.21 | K16: 864.83 | L16: 23.06 | M16: 25138.27 | N16: 25321.38 | O16: 85.85 | P16: 31.02
B17: =B16+1 -> 9 | C17: Bikaji Foods | D17: 724.8 | E17: 25.06 | F17: 230.94 | G17: 219.05 | H17: 194.35 | I17: 2621.85 | J17: 81.53 | K17: 279.62 | L17: 49.33 | M17: 18174.82 | N17: 18162.93 | O17: 69.99 | P17: 93.15
B18: =B17+1 -> 10 | C18: AWL Agri Busine. | D18: 252.15 | E18: 129.97 | F18: 1937.32 | G18: 2325.14 | H18: 1225.81 | I18: 63672.24 | J18: 395.1 | K18: 2329.26 | L18: 12.4 | M18: 32383.51 | N18: 32771.33 | O18: 409.68 | P18: 28.51
B20: 11 | C20: Marico | D20: 711 | E20: 129.78 | F20: 554 | G20: 777 | H20: 1658 | I20: 10831 | J20: 178 | K20: 2149 | L20: 38.44 | M20: 92052.41 | N20: 92275.41 | O20: 470 | P20: 55.31

Sheet WACC
B10: Comparables Companies Beta
B11: All Figure In INR Cr.
B12: Company Name | D12: equity Value | E12: Total Debt | F12: Debt/Equity | G12: Debt/Capital | H12: Tax rate | I12: Levered Beta | J12: Unlevered Beta
B13: ='Comps Valuation'!B13 -> Hind. Unilever | D13: ='Comps Valuation'!G13 -> 587975.65 | E13: ='Comps Valuation'!H13 -> 1648 | F13: =E13/D13 -> 0.0028028371 | G13: =E13/(D13+E13) -> 0.0027950032 | H13: 0.2369 | I13: 0.37 | J13: =I13/(1+F13*(1-H13)) -> 0.36921032
B14: ='Comps Valuation'!B14 -> Nestle India | D14: ='Comps Valuation'!G14 -> 211823.76 | E14: ='Comps Valuation'!H14 -> 1166.85 | F14: =E14/D14 -> 0.005508589 | G14: =E14/(D14+E14) -> 0.0054784107 | H14: 0.2592 | I14: 0.24 | J14: =I14/(1+F14*(1-H14)) -> 0.2390246
B15: ='Comps Valuation'!B15 -> Britannia Inds. | D15: ='Comps Valuation'!G15 -> 128932.09 | E15: ='Comps Valuation'!H15 -> 1246.51 | F15: =E15/D15 -> 0.0096679578 | G15: =E15/(D15+E15) -> 0.0095753834 | H15: 0.2557 | I15: 0.53 | J15: =I15/(1+F15*(1-H15)) -> 0.52621344
B16: ='Comps Valuation'!B16 -> Godrej Consumer | D16: ='Comps Valuation'!G16 -> 122009.79 | E16: ='Comps Valuation'!H16 -> 4009.19 | F16: =E16/D16 -> 0.032859576 | G16: =E16/(D16+E16) -> 0.031814176 | H16: 0.2981 | I16: 0.27 | J16: =I16/(1+F16*(1-H16)) -> 0.26391307
B17: ='Comps Valuation'!B17 -> Tata Consumer | D17: ='Comps Valuation'!G17 -> 104496.15 | E17: ='Comps Valuation'!H17 -> 2392.68 | F17: =E17/D17 -> 0.022897303 | G17: =E17/(D17+E17) -> 0.022384753 | H17: 0.223 | I17: 0.42 | J17: =I17/(1+F17*(1-H17)) -> 0.41265831
B18: ='Comps Valuation'!B18 -> Dabur India | D18: ='Comps Valuation'!G18 -> 89305.795 | E18: ='Comps Valuation'!H18 -> 950.37 | F18: =E18/D18 -> 0.010641751 | G18: =E18/(D18+E18) -> 0.010529696 | H18: 0.2299 | I18: 0.24 | J18: =I18/(1+F18*(1-H18)) -> 0.23804914
B19: ='Comps Valuation'!B19 -> Patanjali Foods | D19: ='Comps Valuation'!G19 -> 64452.5 | E19: ='Comps Valuation'!H19 -> 787.68 | F19: =E19/D19 -> 0.012221093 | G19: =E19/(D19+E19) -> 0.012073541 | H19: 0.2462 | I19: 0.06 | J19: =I19/(1+F19*(1-H19)) -> 0.05945231
B20: ='Comps Valuation'!B20 -> Emami | D20: ='Comps Valuation'!G20 -> 25321.365 | E20: ='Comps Valuation'!H20 -> 89.79 | F20: =E20/D20 -> 0.0035460174 | G20: =E20/(D20+E20) -> 0.0035334876 | H20: 0.0952 | I20: 0.33 | J20: =I20/(1+F20*(1-H20)) -> 0.3289446
B21: ='Comps Valuation'!B21 -> Bikaji Foods | D21: ='Comps Valuation'!G21 -> 18163.488 | E21: ='Comps Valuation'!H21 -> 230.94 | F21: =E21/D21 -> 0.012714518 | G21: =E21/(D21+E21) -> 0.012554889 | H21: 0.2636 | I21: 0.63 | J21: =I21/(1+F21*(1-H21)) -> 0.62415604
B23: Average | F23: =AVERAGE(F13:F21) -> 0.01253996 | G23: =AVERAGE(G13:G21) -> 0.012304371 | H23: =AVERAGE(H13:H21) -> 0.2342 | I23: =AVERAGE(I13:I21) -> 0.34333333 | J23: =AVERAGE(J13:J21) -> 0.3401802
B24: Median | F24: =MEDIAN(F13:F21) -> 0.010641751 | G24: =MEDIAN(G13:G21) -> 0.010529696 | H24: =MEDIAN(H13:H21) -> 0.2462 | I24: =MEDIAN(I13:I21) -> 0.33 | J24: =MEDIAN(J13:J21) -> 0.3289446
B26: ='Comps Valuation'!B31 -> Marico | D26: ='Comps Valuation'!G31 -> 92273.58 | E26: ='Comps Valuation'!H31 -> 554 | F26: =E26/D26 -> 0.0060038854 | G26: =E26/(D26+E26) -> 0.0059680539 | H26: 0.22228215 | I26: 0.16 | J26: =I26/(1+F26*(1-H26)) -> 0.15925638
B28: Target Capital Structure
B30: Proportion of Debt | C30: =F24 -> 0.010641751
B31: Proportion of Equity | C31: =1-C30 -> 0.98935825
B34: Current Capital structure
B36: Market cap | C36: =D26 -> 92273.58
B37: Total Debt | C37: =E26 -> 554
B38: Debt/equity | C38: =C37/C36 -> 0.0060038854
B40: Cost of debt
B41: Pre-tax cost of debt | C41: ='Debt Schedules'!G15 -> 0.09566787
B42: tax rate | C42: =Assumption!C16 -> 0.22228215
B43: After -Tax cost of debt | C43: =C41*(1-C42) -> 0.074402611
B45: Cost of equity | E45: Cost of equity
B46: Risk free Rate | C46: =Assumption!C15 -> 0.06463 | E46: Risk free Rate | F46: =Assumption!C15 -> 0.06463
B47: Equity Market Return | C47: ='Equity Market'!F12 -> 0.11324229 | E47: Equity Market Return | F47: 0.11324229
B48: Equity risk premium | C48: =C47-C46 -> 0.048612286 | E48: Equity risk premium | F48: =F47-F46 -> 0.048612286
B49: Levered Equity Beta | C49: =J24*(1+C38*(1-C42)) -> 0.33048055 | E49: Levered Equity Beta | F49: =Beta!L14 -> 0.42148317
B50: Cost of equity | C50: =C46+(C49*C48) -> 0.080695415 | E50: Cost of equity | F50: =F46+(F49*F48) -> 0.08511926
B52: WACC | C52: =(C50*C31)+(C30*C43) -> 0.080628449 | E52: WACC | F52: =(F50*(1-C38))+(C43*C38) -> 0.085054919

Sheet DCF Model
B8: DCF Analysis
B9: All Figure In INR Cr.
B10: Particulars | C10: 2021 | D10: =C10+1 -> 2022 | E10: =D10+1 -> 2023 | F10: =E10+1 -> 2024 | G10: =F10+1 -> 2025 | H10: =G10+1 -> 2026 | I10: =H10+1 -> 2027 | J10: =I10+1 -> 2028 | K10: =J10+1 -> 2029 | ... Q10: =P10+1 -> 2035
G11: Entry | R11: Exit
B12: DATE | G12: =Assumption!C13 -> 45883 | H12: =DATE(YEAR(Assumption!$C$14)+'DCF Model'!H13,MONTH(Assumption!$C$14),DAY(Assumption!$C$14)) -> 46112 | I12: =DATE(YEAR(Assumption!$C$14)+'DCF Model'!I13,MONTH(Assumption!$C$14),DAY(Assumption!$C$14)) -> 46477 | J12: =DATE(YEAR(Assumption!$C$14)+'DCF Model'!J13,MONTH(Assumption!$C$14),DAY(Assumption!$C$14)) -> 46843 | K12: =DATE(YEAR(Assumption!$C$14)+'DCF Model'!K13,MONTH(Assumption!$C$14),DAY(Assumption!$C$14)) -> 47208 | L12: =DATE(YEAR(Assumption!$C$14)+'DCF Model'!L13,MONTH(Assumption!$C$14),DAY(Assumption!$C$14)) -> 47573 | M12: =DATE(YEAR(Assumption!$C$14)+'DCF Model'!M13,MONTH(Assumption!$C$14),DAY(Assumption!$C$14)) -> 47938 | N12: =DATE(YEAR(Assumption!$C$14)+'DCF Model'!N13,MONTH(Assumption!$C$14),DAY(Assumption!$C$14)) -> 48304 | O12: =DATE(YEAR(Assumption!$C$14)+'DCF Model'!O13,MONTH(Assumption!$C$14),DAY(Assumption!$C$14)) -> 48669 | ... Q12: =DATE(YEAR(Assumption!$C$14)+'DCF Model'!Q13,MONTH(Assumption!$C$14),DAY(Assumption!$C$14)) -> 49399 | R12: =Q12 -> 49399
B13: Time Periods | H13: 0 | I13: =H13+1 -> 1 | J13: =I13+1 -> 2 | K13: =J13+1 -> 3 | L13: =K13+1 -> 4 | M13: =L13+1 -> 5 | N13: =M13+1 -> 6 | O13: =N13+1 -> 7 | P13: =O13+1 -> 8 | Q13: =P13+1 -> 9
B14: Year Frac | H14: =YEARFRAC(G12,H12) -> 0.63055556 | I14: =YEARFRAC(H12,I12) -> 1 | J14: =YEARFRAC(I12,J12) -> 1 | K14: =YEARFRAC(J12,K12) -> 1 | L14: =YEARFRAC(K12,L12) -> 1 | M14: =YEARFRAC(L12,M12) -> 1 | N14: =YEARFRAC(M12,N12) -> 1 | O14: =YEARFRAC(N12,O12) -> 1 | ... Q14: =YEARFRAC(P12,Q12) -> 1 | R14: =Q14 -> 1
B15: EBIT/ Operating Income | G15: ='P&L Statement '!G23 -> 1961 | H15: ='P&L Statement '!H23 -> 2127.3837 | I15: ='P&L Statement '!I23 -> 2315.9503 | J15: ='P&L Statement '!J23 -> 2534.17 | K15: ='P&L Statement '!K23 -> 2789.4435 | L15: ='P&L Statement '!L23 -> 3091.3718 | M15: ='P&L Statement '!M23 -> 3452.4371 | N15: ='P&L Statement '!N23 -> 3888.8925 | ... Q15: ='P&L Statement '!Q23 -> 5896.8353
B16: Tax rate | G16: =G15*'Revenue BuildUp'!G67 -> 424.45085 | H16: =H15*'Revenue BuildUp'!H67 -> 472.87941 | I16: =I15*'Revenue BuildUp'!I67 -> 514.7944 | J16: =J15*'Revenue BuildUp'!J67 -> 563.30076 | K16: =K15*'Revenue BuildUp'!K67 -> 620.04348 | L16: =L15*'Revenue BuildUp'!L67 -> 687.15676 | M16: =M15*'Revenue BuildUp'!M67 -> 767.41512 | N16: =N15*'Revenue BuildUp'!N67 -> 864.43137 | ... Q16: =Q15*'Revenue BuildUp'!Q67 -> 1310.7612
B17: NOPAT | G17: =G15-G16 -> 1536.5491 | H17: =H15-H16 -> 1654.5043 | I17: =I15-I16 -> 1801.1559 | J17: =J15-J16 -> 1970.8693 | K17: =K15-K16 -> 2169.4 | L17: =L15-L16 -> 2404.2151 | M17: =M15-M16 -> 2685.0219 | N17: =N15-N16 -> 3024.4611 | ... Q17: =Q15-Q16 -> 4586.0741
