Workbook

Sheet Assumption
B8: Scenario Manager | E8: Company Name | F8: Paradeep Phosphates Ltd
B9: Best Case | C9: =IF(B9="Best Case",1,IF(B9="Base Case",2,3)) -> 1 | E9: ISIN Code | F9: INE088F01024
E10: Sector Name | F10: Fertilizers
E11: Industry | F11: Fertilizers & Agrochemicals
E12: Exchange Name | F12: NSE: PARADEEP / BSE: 543530
B13: Assumptions | E13: Website | F13: www.paradeepphosphates.com
B14: Addition In FAS | C14: 0.005 | E14: Company Description | F14: Incorporated in 1981, Paradeep Phosphates Limited is a manufacturer of non-urea fertilizers and India’s second largest private sector phosphatic company. The company is engaged in manufacturing, trading, distribution, and sales of a variety of complex fertilizers such as DAP, three grades of Nitrogen-Phosphorus-Potassium (namely NPK-10, NPK-12, and NP-20), Zypmite, Phospho-gypsum, and Hydroflorosilicic Acid. The company serves over 9 Million farmers across 15 states in India. Its network includes 22 regional offices, 529 stock points, over 5,000 dealers, and 75,000 retailers
B15: Annual growth Tapering | C15: ='Revenue BuildUp'!C23 -> 0.2
B16: Risk Free Rate | C16: 0.06519
B17: Tax Rate | C17: ='cost Build_up'!$G$35 -> 0.29058993
B18: EV/EBITDA Multiple | C18: ='Comps Valuation'!E34 -> 12.828106
B19: Perpetual Growth Rate | C19: 0.05
B20: Discount Rate | C20: =WACC!C28 -> 0.08201757
B21: Shares Outstanding(Lakhs) | C21: ='Balance Sheet'!F39/Assumption!C22 -> 8147.786
B22: Face Value | C22: 10
B23: Current Market Price | C23: 220.13
B24: Market Cap (Lakhs) | C24: =C23*C21 -> 1793572.1

Sheet Income statement
B6: Historical Income Statement
B8: Particulars | C8: 2021 | D8: =C8+1 -> 2022 | E8: =D8+1 -> 2023 | F8: =E8+1 -> 2024
B9: Revenue
B10: Revenue from Operations | C10: 516473.35 | D10: 785871.92 | E10: 1334072.2 | F10: 1157512
B11: Other income | C11: 1920.6 | D11: 3926.99 | E11: 9107 | F11: 6883.51
B12: Total Income | C12: =SUM(C10:C11) -> 518393.95 | D12: =SUM(D10:D11) -> 789798.91 | E12: =SUM(E10:E11) -> 1343179.2 | F12: =SUM(F10:F11) -> 1164395.5
B13: Expenses
B14: Cost of materials consumed | C14: 226512.43 | D14: 524622.29 | E14: 1043969.5 | F14: 760903.84
B15: Purchase of stock-in-trade | C15: 138020.07 | D15: 142828.18 | E15: 18226.12 | F15: 105508.61
B16: Changes in Inventories of Finished Goods, Work-in-progress and Stock-in-Trade | C16: 22583.41 | D16: -39324.17 | E16: -877.73 | F16: 33431.87
B17: Employee Benefits Expenses | C17: 13919 | D17: 13850.44 | E17: 21320.25 | F17: 22978.77
B18: Finance cost | C18: 11142.53 | D18: 8554.14 | E18: 29124.25 | F18: 36602.7
B19: Depreciation and Amortisation Expenses | C19: 8332.81 | D19: 9045.72 | E19: 17515.31 | F19: 21067.03
B20: Other Expenses | C20: 61213.9 | D20: 76784.2 | E20: 171335.01 | F20: 169885.95
B21: Total Expenses | C21: =SUM(C14:C20) -> 481724.15 | D21: =SUM(D14:D20) -> 736360.8 | E21: =SUM(E14:E20) -> 1300612.7 | F21: =SUM(F14:F20) -> 1150378.8
B23: Profit before share of equity accounted investee and tax | C23: =C12-C21 -> 36669.8 | D23: =D12-D21 -> 53438.11 | E23: =E12-E21 -> 42566.46 | F23: =F12-F21 -> 14016.72
B24: Share of net profit/(loss) of associate accounted for using the equity method | C24: -19.5 | D24: 61.12 | E24: 50.52 | F24: 66.7
B26: Profit before tax | C26: =SUM(C23:C24) -> 36650.3 | D26: =SUM(D23:D24) -> 53499.23 | E26: =SUM(E23:E24) -> 42616.98 | F26: =SUM(F23:F24) -> 14083.42
B27: Tax expenses | C27: 14323.48 | D27: 13653.91 | E27: 12197.72 | F27: 4092.5
B28: Profit for the year | C28: =C26-C27 -> 22326.82 | D28: =D26-D27 -> 39845.32 | E28: =E26-E27 -> 30419.26 | F28: =F26-F27 -> 9990.92
B31: Earnings per equity share
B32: Basic | C32: 3.88 | D32: 6.91 | E32: 3.9 | F32: 1.22
B33: Diluted | C33: 3.88 | D33: 6.91 | E33: 3.9 | F33: 1.22

Sheet Balance Sheet
B6: Historical BalanceSheet
B8: Particulars | C8: 2021 | D8: =C8+1 -> 2022 | E8: =D8+1 -> 2023 | F8: =E8+1 -> 2024
B10: Assets
B11: Non-Current Assets
B12: Property Plant and Equipment | C12: 122510.42 | D12: 125973.84 | E12: 279571.01 | F12: 335317.89
B13: Capital Work-in-Progress | C13: 22005.97 | D13: 33629.46 | E13: 69686.32 | F13: 37219.28
B14: Right of use Assets | C14: 0 | D14: 0 | E14: 1619.27 | F14: 1790.53
B15: Goodwill | C15: 0 | D15: 0 | E15: 5806.94 | F15: 5806.94
B16: Intangible Assets | C16: 110.55 | D16: 86.23 | E16: 177.84 | F16: 184.5
B17: Equity accounted investment | C17: 278.52 | D17: 289.43 | E17: 315.29 | F17: 324.63
C18: 0 | D18: 0 | E18: 0 | F18: 0
B19: Other income tax assets | C19: 1246.99 | D19: 1236.5 | E19: 1106.62 | F19: 5950.43
B20: Other Non-Current Assets | C20: 2321.36 | D20: 118276.53 | E20: 5900.04 | F20: 3828.56
B22: Total Non-Current Assets | C22: =SUM(C12:C21) -> 148473.81 | D22: =SUM(D12:D21) -> 279491.99 | E22: =SUM(E12:E21) -> 364183.33 | F22: =SUM(F12:F21) -> 390422.76
B24: Current Assets:
B25: Inventories | C25: 89905.36 | D25: 229322.24 | E25: 223767.72 | F25: 183082.95
B26: Investments | C26: 12204 | D26: 55036.14 | E26: 0 | F26: 0
B27: Trade Receivables | C27: 115559.36 | D27: 90247.54 | E27: 368973.75 | F27: 272047.93
B28: Cash and Cash Equivalents | C28: 9152.45 | D28: 53784.1 | E28: 4303.42 | F28: 9071.79
B29: Bank Balances | C29: 167.32 | D29: 5987.37 | E29: 6681.98 | F29: 2730.57
B30: Others Current Financial Assets | C30: 19591.9 | D30: 33844.36 | E30: 33718.27 | F30: 50419.05
B31: Other Current Assets | C31: 47238.04 | D31: 45080.39 | E31: 64048.36 | F31: 58314.22
B32: Assets classified as held for sale | C32: 24.32 | D32: 23.96 | E32: 23.26 | F32: 23.26
B33: Total Current Assets | C33: =SUM(C25:C32) -> 293842.75 | D33: =SUM(D25:D32) -> 513326.1 | E33: =SUM(E25:E32) -> 701516.76 | F33: =SUM(F25:F32) -> 575689.77
B35: TOTAL ASSETS | C35: =C33+C22 -> 442316.56 | D35: =D33+D22 -> 792818.09 | E35: =E33+E22 -> 1065700.1 | F35: =F33+F22 -> 966112.53
B37: EQUITY AND LIABILITIES
B38: EQUITY
B39: Equity Share Capital | C39: 57545 | D39: 57545 | E39: 81449.76 | F39: 81477.86
B40: Other Equity | C40: 125205.97 | D40: 164954.74 | E40: 269020.47 | F40: 274962.15
B42: Total Equity | C42: =SUM(C39:C40) -> 182750.97 | D42: =SUM(D39:D40) -> 222499.74 | E42: =SUM(E39:E40) -> 350470.23 | F42: =SUM(F39:F40) -> 356440.01
B44: LIABILITIES
B45: Non-Current Liabilities:
B46: Financial Liabilities
B47: (i) Borrowings | C47: 11341.13 | D47: 52817.08 | E47: 61188.79 | F47: 67650.58
B48: (ii) Lease Liabilities | C48: 0 | D48: 0 | E48: 1603.78 | F48: 1722.29
B49: Other financial liabilities | C49: 10.05 | D49: 286.71 | E49: 180.42 | F49: 0
B50: Provisions | C50: 1974.99 | D50: 2654.83 | E50: 2379.21 | F50: 2621.4
B51: Deferred Tax Liabilities (Net) | C51: 9301.23 | D51: 9218.11 | E51: 10778.02 | F51: 15085.16
B52: Total Non-Current Liabilities | C52: =SUM(C47:C51) -> 22627.4 | D52: =SUM(D47:D51) -> 64976.73 | E52: =SUM(E47:E51) -> 76130.22 | F52: =SUM(F47:F51) -> 87079.43
B54: Current Liabilities:
B55: Financial Liabilities
B56: (i) Borrowings | C56: 113776.12 | D56: 242612.49 | E56: 401921.53 | F56: 331786.96
B57: (ii) Lease Liabilities | C57: 0 | D57: 0 | E57: 77.32 | F57: 210.89
B58: (iii) Trade Payables
B59: Total outstanding dues of micro enterprises and small enterprises | C59: 625.56 | D59: 818.76 | E59: 667.47 | F59: 929.88
B60: Total outstanding dues of creditors other than micro enterprises and small enterprises | C60: 93327.61 | D60: 226521.11 | E60: 190580.2 | F60: 147881.85
B61: (iv)Other Financial Liabilities | C61: 8245.64 | D61: 7766.76 | E61: 24003.11 | F61: 22455.43
B62: Other Current Liabilities | C62: 12638.96 | D62: 14900.85 | E62: 11554.5 | F62: 12020.43
B63: Provisions | C63: 8301.55 | D63: 7524.57 | E63: 9000.56 | F63: 7284.9
B64: Current tax liabilities | C64: 22.75 | D64: 5197.08 | E64: 1294.95 | F64: 22.75
B65: Total Current Liabilities | C65: =SUM(C56:C64) -> 236938.19 | D65: =SUM(D56:D64) -> 505341.62 | E65: =SUM(E56:E64) -> 639099.64 | F65: =SUM(F56:F64) -> 522593.09
B67: Total Liabilities | C67: =C65+C52 -> 259565.59 | D67: =D65+D52 -> 570318.35 | E67: =E65+E52 -> 715229.86 | F67: =F65+F52 -> 609672.52
B69: TOTAL EQUITY AND LIABILITIES | C69: =C67+C42 -> 442316.56 | D69: =D67+D42 -> 792818.09 | E69: =E67+E42 -> 1065700.1 | F69: =F67+F42 -> 966112.53
B71: Check | C71: =C69=C35 -> TRUE | D71: =D69=D35 -> TRUE | E71: =E69=E35 -> TRUE | F71: =F69=F35 -> TRUE

Sheet Revenue BuildUp
B6: Revenue Build_up
B8: Particulars | C8: 2021 | D8: =C8+1 -> 2022 | E8: =D8+1 -> 2023 | F8: =E8+1 -> 2024 | G8: =F8+1 -> 2025 | H8: =G8+1 -> 2026 | I8: =H8+1 -> 2027 | J8: =I8+1 -> 2028 | K8: =J8+1 -> 2029
B10: Revenue | C10: ='Income statement'!C10 -> 516473.35 | D10: ='Income statement'!D10 -> 785871.92 | E10: ='Income statement'!E10 -> 1334072.2 | F10: ='Income statement'!F10 -> 1157512 | G10: =F10*(1+G11) -> 1750480.1 | H10: =G10*(1+H11) -> 2467866.2 | I10: =H10*(1+I11) -> 3276975.9 | J10: =I10*(1+J11) -> 4136482.1 | K10: =J10*(1+K11) -> 5004436.6
B11: Growth Rate | D11: =D10/C10-1 -> 0.52161175 | E11: =E10/D10-1 -> 0.69756948 | F11: =F10/E10-1 -> -0.13234682 | G11: =CHOOSE(Assumption!$C$9,'Revenue BuildUp'!G20:K20,'Revenue BuildUp'!G21:K21,'Revenue BuildUp'!G22:K22) -> 0.51227814 | H11: =CHOOSE(Assumption!$C$9,'Revenue BuildUp'!H20:L20,'Revenue BuildUp'!H21:L21,'Revenue BuildUp'!H22:L22) -> 0.40982251 | I11: =CHOOSE(Assumption!$C$9,'Revenue BuildUp'!I20:M20,'Revenue BuildUp'!I21:M21,'Revenue BuildUp'!I22:M22) -> 0.32785801 | J11: =CHOOSE(Assumption!$C$9,'Revenue BuildUp'!J20:N20,'Revenue BuildUp'!J21:N21,'Revenue BuildUp'!J22:N22) -> 0.26228641 | K11: =CHOOSE(Assumption!$C$9,'Revenue BuildUp'!K20:O20,'Revenue BuildUp'!K21:O21,'Revenue BuildUp'!K22:O22) -> 0.20982913
B13: Other Income | C13: ='Income statement'!C11 -> 1920.6 | D13: ='Income statement'!D11 -> 3926.99 | E13: ='Income statement'!E11 -> 9107 | F13: ='Income statement'!F11 -> 6883.51 | G13: =G10*G14 -> 9403.9942 | H13: =H10*H14 -> 13257.963 | I13: =I10*I14 -> 17604.692 | J13: =J10*J14 -> 22222.163 | K13: =K10*K14 -> 26885.021
B14: % of Revenue | C14: =C13/C10 -> 0.0037186817 | D14: =D13/D10 -> 0.0049969848 | E14: =E13/E10 -> 0.0068264672 | F14: =F13/F10 -> 0.0059468153 | G14: =AVERAGE(C14:F14) -> 0.0053722372 | H14: =G14 -> 0.0053722372 | I14: =H14 -> 0.0053722372 | J14: =I14 -> 0.0053722372 | K14: =J14 -> 0.0053722372
B16: Share of net profit/(loss) of associate accounted for using the equity method | C16: ='Income statement'!C24 -> -19.5 | D16: ='Income statement'!D24 -> 61.12 | E16: ='Income statement'!E24 -> 50.52 | F16: ='Income statement'!F24 -> 66.7 | G16: =G17*G10 -> 59.301903 | H16: =H17*H10 -> 83.605158 | I16: =I17*I10 -> 111.01578 | J16: =J17*J10 -> 140.13371 | K16: =K17*K10 -> 169.53784
B17: % of Revenue | C17: =C16/C10 -> -3.7756062e-05 | D17: =D16/D10 -> 7.7773488e-05 | E17: =E16/E10 -> 3.7869015e-05 | F17: =F16/F10 -> 5.7623594e-05 | G17: =AVERAGE(C17:F17) -> 3.3877509e-05 | H17: =G17 -> 3.3877509e-05 | I17: =H17 -> 3.3877509e-05 | J17: =I17 -> 3.3877509e-05 | K17: =J17 -> 3.3877509e-05
B19: Scenario | C19: Growth
B20: Best Case | C20: =C21+15% -> 0.51227814 | G20: =C20 -> 0.51227814 | H20: =G20*(1-$C$23) -> 0.40982251 | I20: =H20*(1-$C$23) -> 0.32785801 | J20: =I20*(1-$C$23) -> 0.26228641 | K20: =J20*(1-$C$23) -> 0.20982913
B21: Base Case | C21: =AVERAGE(D11:F11) -> 0.36227814 | G21: =C21 -> 0.36227814 | H21: =G21*(1-$C$23) -> 0.28982251 | I21: =H21*(1-$C$23) -> 0.23185801 | J21: =I21*(1-$C$23) -> 0.18548641 | K21: =J21*(1-$C$23) -> 0.14838913
B22: Worst Case | C22: =C21-15% -> 0.21227814 | G22: =C22 -> 0.21227814 | H22: =G22*(1-$C$23) -> 0.16982251 | I22: =H22*(1-$C$23) -> 0.13585801 | J22: =I22*(1-$C$23) -> 0.10868641 | K22: =J22*(1-$C$23) -> 0.086949126
B23: Annual growth Tapering | C23: 0.2

Sheet cost Build_up
B6: Cost Build_up
B8: Particulars | C8: 2021 | D8: =C8+1 -> 2022 | E8: =D8+1 -> 2023 | F8: =E8+1 -> 2024 | G8: =F8+1 -> 2025 | H8: =G8+1 -> 2026 | I8: =H8+1 -> 2027 | J8: =I8+1 -> 2028 | K8: =J8+1 -> 2029
B10: Revenue | C10: ='Revenue BuildUp'!C10 -> 516473.35 | D10: ='Revenue BuildUp'!D10 -> 785871.92 | E10: ='Revenue BuildUp'!E10 -> 1334072.2 | F10: ='Revenue BuildUp'!F10 -> 1157512 | G10: ='Revenue BuildUp'!G10 -> 1750480.1 | H10: ='Revenue BuildUp'!H10 -> 2467866.2 | I10: ='Revenue BuildUp'!I10 -> 3276975.9 | J10: ='Revenue BuildUp'!J10 -> 4136482.1 | K10: ='Revenue BuildUp'!K10 -> 5004436.6
B12: Cost of materials consumed | C12: ='Income statement'!C14 -> 226512.43 | D12: ='Income statement'!D14 -> 524622.29 | E12: ='Income statement'!E14 -> 1043969.5 | F12: ='Income statement'!F14 -> 760903.84 | G12: =G10*G13 -> 1114201.3 | H12: =H10*H13 -> 1570826.1 | I12: =I10*I13 -> 2085834 | J12: =J10*J13 -> 2632919.9 | K12: =K10*K13 -> 3185383.2
B13: % of Revenue | C13: =C12/C10 -> 0.43857525 | D13: =D12/D10 -> 0.66756717 | E13: =E12/E10 -> 0.7825435 | F13: =F12/F10 -> 0.65736152 | G13: =AVERAGE(C13:F13) -> 0.63651186 | H13: =G13 -> 0.63651186 | I13: =H13 -> 0.63651186 | J13: =I13 -> 0.63651186 | K13: =J13 -> 0.63651186
B15: Purchases of stock-in-trade | C15: ='Income statement'!C15 -> 138020.07 | D15: ='Income statement'!D15 -> 142828.18 | E15: ='Income statement'!E15 -> 18226.12 | F15: ='Income statement'!F15 -> 105508.61 | G15: =G16*G10 -> 242351.2 | H15: =H16*H10 -> 341672.18 | I15: =I16*I10 -> 453692.14 | J15: =J16*J10 -> 572689.43 | K15: =K16*K10 -> 692856.35
B16: % of Revenue | C16: =C15/C10 -> 0.26723561 | D16: =D15/D10 -> 0.18174486 | E16: =E15/E10 -> 0.013662019 | F16: =F15/F10 -> 0.091151203 | G16: =AVERAGE($C$16:$F$16) -> 0.13844842 | H16: =AVERAGE($C$16:$F$16) -> 0.13844842 | I16: =AVERAGE($C$16:$F$16) -> 0.13844842 | J16: =AVERAGE($C$16:$F$16) -> 0.13844842 | K16: =AVERAGE($C$16:$F$16) -> 0.13844842
B18: Changes in inventories of finished goods, work-in-progress and stock in-trade | C18: ='Income statement'!C16 -> 22583.41 | D18: ='Income statement'!D16 -> -39324.17 | E18: ='Income statement'!E16 -> -877.73 | F18: ='Income statement'!F16 -> 33431.87 | G18: =G19*G10 -> 9589.0751 | H18: =H19*H10 -> 13518.894 | I18: =I19*I10 -> 17951.172 | J18: =J19*J10 -> 22659.52 | K18: =K19*K10 -> 27414.147
B19: % of Revenue | C19: =C18/C10 -> 0.043726186 | D19: =D18/D10 -> -0.050038905 | E19: =E18/E10 -> -0.00065793291 | F19: =F18/F10 -> 0.028882526 | G19: =AVERAGE($C$19:$F$19) -> 0.0054779688 | H19: =AVERAGE($C$19:$F$19) -> 0.0054779688 | I19: =AVERAGE($C$19:$F$19) -> 0.0054779688 | J19: =AVERAGE($C$19:$F$19) -> 0.0054779688 | K19: =AVERAGE($C$19:$F$19) -> 0.0054779688
B21: COGS | C21: =C18+C15+C12 -> 387115.91 | D21: =D18+D15+D12 -> 628126.3 | E21: =E18+E15+E12 -> 1061317.9 | F21: =F18+F15+F12 -> 899844.32 | G21: =G18+G15+G12 -> 1366141.6 | H21: =H18+H15+H12 -> 1926017.2 | I21: =I18+I15+I12 -> 2557477.3 | J21: =J18+J15+J12 -> 3228268.9 | K21: =K18+K15+K12 -> 3905653.7
B22: % of Revenue | C22: =C21/C10 -> 0.74953705 | D22: =D21/D10 -> 0.79927312 | E22: =E21/E10 -> 0.79554759 | F22: =F21/F10 -> 0.77739525 | G22: =G21/G10 -> 0.78043825 | H22: =H21/H10 -> 0.78043825 | I22: =I21/I10 -> 0.78043825 | J22: =J21/J10 -> 0.78043825 | K22: =K21/K10 -> 0.78043825
B24: Gross Profit Margin | C24: =(C10-C21)/C10 -> 0.25046295 | D24: =(D10-D21)/D10 -> 0.20072688 | E24: =(E10-E21)/E10 -> 0.20445241 | F24: =(F10-F21)/F10 -> 0.22260475 | G24: =(G10-G21)/G10 -> 0.21956175 | H24: =(H10-H21)/H10 -> 0.21956175 | I24: =(I10-I21)/I10 -> 0.21956175 | J24: =(J10-J21)/J10 -> 0.21956175 | K24: =(K10-K21)/K10 -> 0.21956175
B26: Employee benefits expense | C26: ='Income statement'!C17 -> 13919 | D26: ='Income statement'!D17 -> 13850.44 | E26: ='Income statement'!E17 -> 21320.25 | F26: ='Income statement'!F17 -> 22978.77 | G26: =G27*G10 -> 35187.965 | H26: =H27*H10 -> 49608.785 | I26: =I27*I10 -> 65873.422 | J26: =J27*J10 -> 83151.125 | K26: =K27*K10 -> 100598.65
B27: % of Revenue | C27: =C26/C10 -> 0.026950084 | D27: =D26/D10 -> 0.017624297 | E27: =E26/E10 -> 0.015981332 | F27: =F26/F10 -> 0.019851864 | G27: =AVERAGE($C$27:$F$27) -> 0.020101894 | H27: =AVERAGE($C$27:$F$27) -> 0.020101894 | I27: =AVERAGE($C$27:$F$27) -> 0.020101894 | J27: =AVERAGE($C$27:$F$27) -> 0.020101894 | K27: =AVERAGE($C$27:$F$27) -> 0.020101894
B29: Other expenses | C29: ='Income statement'!C20 -> 61213.9 | D29: ='Income statement'!D20 -> 76784.2 | E29: ='Income statement'!E20 -> 171335.01 | F29: ='Income statement'!F20 -> 169885.95 | G29: =G30*G10 -> 215058.25 | H29: =H30*H10 -> 303193.96 | I29: =I30*I10 -> 402598.52 | J29: =J30*J10 -> 508194.64 | K29: =K30*K10 -> 614828.68
B30: % of Revenue | C30: =C29/C10 -> 0.11852286 | D30: =D29/D10 -> 0.097705743 | E30: =E29/E10 -> 0.12843009 | F30: =F29/F10 -> 0.1467682 | G30: =AVERAGE($C$30:$F$30) -> 0.12285672 | H30: =AVERAGE($C$30:$F$30) -> 0.12285672 | I30: =AVERAGE($C$30:$F$30) -> 0.12285672 | J30: =AVERAGE($C$30:$F$30) -> 0.12285672 | K30: =AVERAGE($C$30:$F$30) -> 0.12285672
B32: Opex | C32: =C29+C26 -> 75132.9 | D32: =D29+D26 -> 90634.64 | E32: =E29+E26 -> 192655.26 | F32: =F29+F26 -> 192864.72 | G32: =G29+G26 -> 250246.21 | H32: =H29+H26 -> 352802.74 | I32: =I29+I26 -> 468471.95 | J32: =J29+J26 -> 591345.77 | K32: =K29+K26 -> 715427.33
B33: % of Revenue | C33: =C32/C10 -> 0.14547295 | D33: =D32/D10 -> 0.11533004 | E33: =E32/E10 -> 0.14441142 | F33: =F32/F10 -> 0.16662006 | G33: =G32/G10 -> 0.14295862 | H33: =H32/H10 -> 0.14295862 | I33: =I32/I10 -> 0.14295862 | J33: =J32/J10 -> 0.14295862 | K33: =K32/K10 -> 0.14295862
B35: Effective Tax Rate | C35: ='Income statement'!C27/'Income statement'!C26 -> 0.39081481 | D35: ='Income statement'!D27/'Income statement'!D26 -> 0.25521694 | E35: ='Income statement'!E27/'Income statement'!E26 -> 0.28621737 | F35: ='Income statement'!F27/'Income statement'!F26 -> 0.29058993 | G35: =F35 -> 0.29058993 | H35: =G35 -> 0.29058993 | I35: =H35 -> 0.29058993 | J35: =I35 -> 0.29058993 | K35: =J35 -> 0.29058993

Sheet Working Capital
B6: Working Capital
B8: Particulars | C8: 2021 | D8: =C8+1 -> 2022 | E8: =D8+1 -> 2023 | F8: =E8+1 -> 2024 | G8: =F8+1 -> 2025 | H8: =G8+1 -> 2026 | I8: =H8+1 -> 2027 | J8: =I8+1 -> 2028 | K8: =J8+1 -> 2029
B9: Days of operation | C9: 365 | D9: =C9 -> 365 | E9: =D9 -> 365 | F9: =E9 -> 365 | G9: =F9 -> 365 | H9: =G9 -> 365 | I9: =H9 -> 365 | J9: =I9 -> 365 | K9: =J9 -> 365
B11: Inventores | C11: ='Balance Sheet'!C25 -> 89905.36 | D11: ='Balance Sheet'!D25 -> 229322.24 | E11: ='Balance Sheet'!E25 -> 223767.72 | F11: ='Balance Sheet'!F25 -> 183082.95 | G11: =G18*'cost Build_up'!G21/'Working Capital'!G9 -> 345508.68 | H11: =H18*'cost Build_up'!H21/'Working Capital'!H9 -> 487105.92 | I11: =I18*'cost Build_up'!I21/'Working Capital'!I9 -> 646807.5 | J11: =J18*'cost Build_up'!J21/'Working Capital'!J9 -> 816456.31 | K11: =K18*'cost Build_up'!K21/'Working Capital'!K9 -> 987772.62
B12: Recievables | C12: ='Balance Sheet'!C27 -> 115559.36 | D12: ='Balance Sheet'!D27 -> 90247.54 | E12: ='Balance Sheet'!E27 -> 368973.75 | F12: ='Balance Sheet'!F27 -> 272047.93 | G12: =G19*'cost Build_up'!G10/'Working Capital'!G9 -> 372060.02 | H12: =H19*'cost Build_up'!H10/'Working Capital'!H9 -> 524538.6 | I12: =I19*'cost Build_up'!I10/'Working Capital'!I9 -> 696512.78 | J12: =J19*'cost Build_up'!J10/'Working Capital'!J9 -> 879198.61 | K12: =K19*'cost Build_up'!K10/'Working Capital'!K9 -> 1063680.1
B13: Trade payables | C13: =SUM('Balance Sheet'!C59:C60) -> 93953.17 | D13: =SUM('Balance Sheet'!D59:D60) -> 227339.87 | E13: =SUM('Balance Sheet'!E59:E60) -> 191247.67 | F13: =SUM('Balance Sheet'!F59:F60) -> 148811.73 | G13: =G20*'cost Build_up'!G21/'Working Capital'!G9 -> 324529.32 | H13: =H20*'cost Build_up'!H21/'Working Capital'!H9 -> 457528.75 | I13: =I20*'cost Build_up'!I21/'Working Capital'!I9 -> 607533.21 | J13: =J20*'cost Build_up'!J21/'Working Capital'!J9 -> 766880.92 | K13: =K20*'cost Build_up'!K21/'Working Capital'!K9 -> 927794.87
B14: Net Working Capital | C14: =C11+C12-C13 -> 111511.55 | D14: =D11+D12-D13 -> 92229.91 | E14: =E11+E12-E13 -> 401493.8 | F14: =F11+F12-F13 -> 306319.15 | G14: =G11+G12-G13 -> 393039.38 | H14: =H11+H12-H13 -> 554115.77 | I14: =I11+I12-I13 -> 735787.06 | J14: =J11+J12-J13 -> 928774.01 | K14: =K11+K12-K13 -> 1123657.8
B17: KPI
B18: DIO | C18: =C11/'cost Build_up'!C21*'Working Capital'!C9 -> 84.769072 | D18: =D11/'cost Build_up'!D21*'Working Capital'!D9 -> 133.25762 | E18: =E11/'cost Build_up'!E21*'Working Capital'!E9 -> 76.956411 | F18: =F11/'cost Build_up'!F21*'Working Capital'!F9 -> 74.263153 | G18: =AVERAGE(C18:F18) -> 92.311565 | H18: =G18 -> 92.311565 | I18: =H18 -> 92.311565 | J18: =I18 -> 92.311565 | K18: =J18 -> 92.311565
B19: DSO | C19: =C12/'cost Build_up'!C10*'Working Capital'!C9 -> 81.667653 | D19: =D12/'cost Build_up'!D10*'Working Capital'!D9 -> 41.915675 | E19: =E12/'cost Build_up'!E10*'Working Capital'!E9 -> 100.95062 | F19: =F12/'cost Build_up'!F10*'Working Capital'!F9 -> 85.785284 | G19: =AVERAGE(C19:F19) -> 77.579809 | H19: =G19 -> 77.579809 | I19: =H19 -> 77.579809 | J19: =I19 -> 77.579809 | K19: =J19 -> 77.579809
B20: DPO | C20: =C13/'cost Build_up'!C21*'Working Capital'!C9 -> 88.585631 | D20: =D13/'cost Build_up'!D21*'Working Capital'!D9 -> 132.10568 | E20: =E13/'cost Build_up'!E21*'Working Capital'!E9 -> 65.772375 | F20: =F13/'cost Build_up'!F21*'Working Capital'!F9 -> 60.361865 | G20: =AVERAGE(C20:F20) -> 86.706388 | H20: =G20 -> 86.706388 | I20: =H20 -> 86.706388 | J20: =I20 -> 86.706388 | K20: =J20 -> 86.706388
B21: Net Trade Cycle | C21: =C18+C19-C20 -> 77.851094 | D21: =D18+D19-D20 -> 43.067617 | E21: =E18+E19-E20 -> 112.13466 | F21: =F18+F19-F20 -> 99.686573 | G21: =G18+G19-G20 -> 83.184986 | H21: =H18+H19-H20 -> 83.184986 | I21: =I18+I19-I20 -> 83.184986 | J21: =J18+J19-J20 -> 83.184986 | K21: =K18+K19-K20 -> 83.184986

Sheet Debt Schedules
B6: Debt Schedules
B8: Particulars | C8: 2021 | D8: =C8+1 -> 2022 | E8: =D8+1 -> 2023 | F8: =E8+1 -> 2024 | G8: =F8+1 -> 2025 | H8: =G8+1 -> 2026 | I8: =H8+1 -> 2027 | J8: =I8+1 -> 2028 | K8: =J8+1 -> 2029
B10: Opening Balance | D10: =C12 -> 125117.25 | E10: =D12 -> 295429.57 | F10: =E12 -> 464791.42 | G10: =F12 -> 401370.72 | H10: =G12 -> 574740.54 | I10: =H12 -> 810282.15 | J10: =I12 -> 1075939.6 | K10: =J12 -> 1358144
B11: New Issuance/ Repayment | D11: =D12-D10 -> 170312.32 | E11: =E12-E10 -> 169361.85 | F11: =F12-F10 -> -63420.7 | G11: =G12-G10 -> 173369.82 | H11: =H12-H10 -> 235541.61 | I11: =I12-I10 -> 265657.49 | J11: =J12-J10 -> 282204.34 | K11: =K12-K10 -> 284978.17
B12: Closing Balance | C12: =SUM('Balance Sheet'!C47:C48,'Balance Sheet'!C56:C57) -> 125117.25 | D12: =SUM('Balance Sheet'!D47:D48,'Balance Sheet'!D56:D57) -> 295429.57 | E12: =SUM('Balance Sheet'!E47:E48,'Balance Sheet'!E56:E57) -> 464791.42 | F12: =SUM('Balance Sheet'!F47:F48,'Balance Sheet'!F56:F57) -> 401370.72 | G12: =SUM('B_Sheet '!G29,'B_Sheet '!G31,'B_Sheet '!G41,'B_Sheet '!G43) -> 574740.54 | H12: =SUM('B_Sheet '!H29,'B_Sheet '!H31,'B_Sheet '!H41,'B_Sheet '!H43) -> 810282.15 | I12: =SUM('B_Sheet '!I29,'B_Sheet '!I31,'B_Sheet '!I41,'B_Sheet '!I43) -> 1075939.6 | J12: =SUM('B_Sheet '!J29,'B_Sheet '!J31,'B_Sheet '!J41,'B_Sheet '!J43) -> 1358144 | K12: =SUM('B_Sheet '!K29,'B_Sheet '!K31,'B_Sheet '!K41,'B_Sheet '!K43) -> 1643122.2
B13: Interest rate | C13: =C14/C12 -> 0.089056705 | D13: =D14/D12 -> 0.028954921 | E13: =E14/E12 -> 0.062660903 | F13: =F14/F12 -> 0.091194246 | G13: =AVERAGE(C13:F13) -> 0.067966694 | H13: =G13 -> 0.067966694 | I13: =H13 -> 0.067966694 | J13: =I13 -> 0.067966694 | K13: =J13 -> 0.067966694
B14: Interest Expense | C14: ='Income statement'!C18 -> 11142.53 | D14: ='Income statement'!D18 -> 8554.14 | E14: ='Income statement'!E18 -> 29124.25 | F14: ='Income statement'!F18 -> 36602.7 | G14: =G13*G12 -> 39063.214 | H14: =H13*H12 -> 55072.199 | I14: =I13*I12 -> 73128.06 | J14: =J13*J12 -> 92308.556 | K14: =K13*K12 -> 111677.58

Sheet CashFlow 
B6: CashFlow Statement
B8: Particulars | C8: 2021 | D8: =C8+1 -> 2022 | E8: =D8+1 -> 2023 | F8: =E8+1 -> 2024 | G8: =F8+1 -> 2025 | H8: =G8+1 -> 2026 | I8: =H8+1 -> 2027 | J8: =I8+1 -> 2028 | K8: =J8+1 -> 2029
B10: Cash Flow from Operating Activities:
B11: Profit before tax | C11: 36650.3 | D11: 53499.23 | E11: 42616.98 | F11: 14083.42 | G11: ='P&L Statement'!G28 -> 79252.793 | H11: ='P&L Statement'!H28 -> 118551.87 | I11: ='P&L Statement'!I28 -> 163562.79 | J11: ='P&L Statement'!J28 -> 211800.66 | K11: ='P&L Statement'!K28 -> 260744.85
B12: Adjustments for:
B13: Depreciation | C13: 8332.81 | D13: 9045.72 | E13: 17515.31 | F13: 21067.03 | G13: =-'P&L Statement'!G19 -> 25239.542 | H13: =-'P&L Statement'!H19 -> 28763.777 | I13: =-'P&L Statement'!I19 -> 32051.471 | J13: =-'P&L Statement'!J19 -> 35120.568 | K13: =-'P&L Statement'!K19 -> 37987.636
B14: Finance Cost | C14: 10158.34 | D14: 6151.37 | E14: 25151.99 | F14: 32128.33 | G14: =-'P&L Statement'!G24 -> 39063.214 | H14: =-'P&L Statement'!H24 -> 55072.199 | I14: =-'P&L Statement'!I24 -> 73128.06 | J14: =-'P&L Statement'!J24 -> 92308.556 | K14: =-'P&L Statement'!K24 -> 111677.58
B15: Interest income | C15: -55.86 | D15: -299.99 | E15: -986.5 | F15: -625.86 | G15: 0 | H15: 0 | I15: 0 | J15: 0 | K15: 0
B16: Profit on sale of current investments | C16: -23.43 | D16: -635.85 | E16: -93.36 | F16: -111.58 | G16: 0 | H16: 0 | I16: 0 | J16: 0 | K16: 0
B17: Gain on fair valuation of investments measured at fair value through profit or loss | C17: -3.99 | D17: -38.13 | G17: 0 | H17: 0 | I17: 0 | J17: 0 | K17: 0
B18: Loss on sale / discard of property,plant and equipment (net) | C18: 689.9 | D18: 1289.42 | E18: 1511.9 | F18: 2431.13 | G18: 0 | H18: 0 | I18: 0 | J18: 0 | K18: 0
B19: Loss allowance | C19: 764.91 | D19: 2095.78 | E19: 1239.9 | F19: 797.88 | G19: 0 | H19: 0 | I19: 0 | J19: 0 | K19: 0
B20: Bad debts, claims and advances written off | D20: 10.23 | E20: 68.73 | F20: 33.76 | G20: 0 | H20: 0 | I20: 0 | J20: 0 | K20: 0
B21: Unspent liabilities/provision no longer required written back | C21: -359.88 | D21: -1727.47 | E21: -6883.44 | F21: -3850.13 | G21: 0 | H21: 0 | I21: 0 | J21: 0 | K21: 0
B22: Foreign exchange fluctuation loss unrealised (net) | C22: 2400.17 | D22: 3922.46 | E22: 2586.92 | F22: 180.32 | G22: 0 | H22: 0 | I22: 0 | J22: 0 | K22: 0
B23: Share of profit from associate | C23: 19.5 | D23: -61.12 | E23: -50.52 | F23: -66.7 | G23: =-'Revenue BuildUp'!G16 -> -59.301903 | H23: =-'Revenue BuildUp'!H16 -> -83.605158 | I23: =-'Revenue BuildUp'!I16 -> -111.01578 | J23: =-'Revenue BuildUp'!J16 -> -140.13371 | K23: =-'Revenue BuildUp'!K16 -> -169.53784
B24: Operating Profit before Working Capital Changes | C24: =SUM(C11:C23) -> 58572.77 | D24: =SUM(D11:D23) -> 73251.65 | E24: =SUM(E11:E23) -> 82677.91 | F24: =SUM(F11:F23) -> 66067.6 | G24: =SUM(G11:G23) -> 143496.25 | H24: =SUM(H11:H23) -> 202304.24 | I24: =SUM(I11:I23) -> 268631.31 | J24: =SUM(J11:J23) -> 339089.65 | K24: =SUM(K11:K23) -> 410240.53
B26: Adjustments for:
B27: (Increase)/Decrease in Inventories | C27: 17948.45 | D27: -139416.88 | E27: 14748.72 | F27: 40684.77 | G27: =Balance_Sheet!F25-Balance_Sheet!G25 -> -162425.73 | H27: =Balance_Sheet!G25-Balance_Sheet!H25 -> -141597.24 | I27: =Balance_Sheet!H25-Balance_Sheet!I25 -> -159701.58 | J27: =Balance_Sheet!I25-Balance_Sheet!J25 -> -169648.81 | K27: =Balance_Sheet!J25-Balance_Sheet!K25 -> -171316.31
B28: Increase in trade receivables | C28: 98565.79 | D28: -10627.34 | E28: -242375.3 | F28: 96429.76 | G28: =Balance_Sheet!F27-Balance_Sheet!G27 -> -100012.09 | H28: =Balance_Sheet!G27-Balance_Sheet!H27 -> -152478.57 | I28: =Balance_Sheet!H27-Balance_Sheet!I27 -> -171974.18 | J28: =Balance_Sheet!I27-Balance_Sheet!J27 -> -182685.83 | K28: =Balance_Sheet!J27-Balance_Sheet!K27 -> -184481.48
B29: Increase in financial and other assets | C29: -33083.24 | D29: -51707.35 | E29: -4033.41 | F29: -10696.24 | G29: =SUM(Balance_Sheet!F30:F32)-SUM(Balance_Sheet!G30:G32) -> -65049.838 | H29: =SUM(Balance_Sheet!G30:G32)-SUM(Balance_Sheet!H30:H32) -> -71229.762 | I29: =SUM(Balance_Sheet!H30:H32)-SUM(Balance_Sheet!I30:I32) -> -80337.058 | J29: =SUM(Balance_Sheet!I30:I32)-SUM(Balance_Sheet!J30:J32) -> -85340.965 | K29: =SUM(Balance_Sheet!J30:J32)-SUM(Balance_Sheet!K30:K32) -> -86179.792
B30: (Decrease)/increase in trade payables and other current liabilities | C30: 15688.45 | D30: 132807.79 | E30: -74426.45 | F30: -41241.6 | G30: =SUM(Balance_Sheet!G56:G62,Balance_Sheet!G64)-SUM(Balance_Sheet!F56:F62,Balance_Sheet!F64) -> 356478.31 | H30: =SUM(Balance_Sheet!H56:H62,Balance_Sheet!H64)-SUM(Balance_Sheet!G56:G62,Balance_Sheet!G64) -> 357277.73 | I30: =SUM(Balance_Sheet!I56:I62,Balance_Sheet!I64)-SUM(Balance_Sheet!H56:H62,Balance_Sheet!H64) -> 402958.55 | J30: =SUM(Balance_Sheet!J56:J62,Balance_Sheet!J64)-SUM(Balance_Sheet!I56:I62,Balance_Sheet!I64) -> 428057.39 | K30: =SUM(Balance_Sheet!K56:K62,Balance_Sheet!K64)-SUM(Balance_Sheet!J56:J62,Balance_Sheet!J64) -> 432264.82
B31: Decrease in provisions | C31: 135.21 | D31: -143.48 | E31: -523.43 | F31: -1732.2 | G31: =Balance_Sheet!G63-Balance_Sheet!F63 -> 9646.0062 | H31: =Balance_Sheet!H63-Balance_Sheet!G63 -> 6938.6665 | I31: =Balance_Sheet!I63-Balance_Sheet!H63 -> 7825.8306 | J31: =Balance_Sheet!J63-Balance_Sheet!I63 -> 8313.2735 | K31: =Balance_Sheet!K63-Balance_Sheet!J63 -> 8394.9857
B32: Cash Generated from Operations | C32: =C24+SUM(C27:C31) -> 157827.43 | D32: =D24+SUM(D27:D31) -> 4164.39 | E32: =E24+SUM(E27:E31) -> -223931.96 | F32: =F24+SUM(F27:F31) -> 149512.09 | G32: =G24+SUM(G27:G31) -> 182132.9 | H32: =H24+SUM(H27:H31) -> 201215.07 | I32: =I24+SUM(I27:I31) -> 267402.87 | J32: =J24+SUM(J27:J31) -> 337784.7 | K32: =K24+SUM(K27:K31) -> 408922.76
B33: Direct Taxes Paid | C33: -7712.66 | D33: -8552.21 | E33: -13735.33 | F33: -5836.25 | G33: =-'P&L Statement'!G31 -> -23030.064 | H33: =-'P&L Statement'!H31 -> -34449.979 | I33: =-'P&L Statement'!I31 -> -47529.699 | J33: =-'P&L Statement'!J31 -> -61547.137 | K33: =-'P&L Statement'!K31 -> -75769.828
B35: Net Cash Flow from Operating Activities (A) | C35: =SUM(C32:C33) -> 150114.77 | D35: =SUM(D32:D33) -> -4387.82 | E35: =SUM(E32:E33) -> -237667.29 | F35: =SUM(F32:F33) -> 143675.84 | G35: =SUM(G32:G33) -> 159102.83 | H35: =SUM(H32:H33) -> 166765.09 | I35: =SUM(I32:I33) -> 219873.17 | J35: =SUM(J32:J33) -> 276237.56 | K35: =SUM(K32:K33) -> 333152.93
B37: Cash Flow from Investing Activities:
B38: Proceeds from sale of property, plant and equipment | C38: 11.04 | D38: 38.4 | E38: 37.73 | F38: 38.78 | G38: 0 | H38: 0 | I38: 0 | J38: 0 | K38: 0
B39: Acquisition of property, plant and equipment, including capital work in progress, capital advances and capital creditors | C39: -16883.28 | D39: -62022.19 | E39: -43618.36 | F39: -41150.29 | G39: =-FAS!G75 -> -75720.75 | H39: =-FAS!H75 -> -76099.354 | I39: =-FAS!I75 -> -76479.85 | J39: =-FAS!J75 -> -76862.25 | K39: =-FAS!K75 -> -77246.561
B40: Purchase of business | C40: 0 | D40: 0 | E40: -53700 | F40: 0 | G40: 0 | H40: 0 | I40: 0 | J40: 0
B41: Investments in current investments - mutual funds | C41: -76004 | D41: -537889.63 | E41: -440021.35 | F41: -126805.24 | G41: =SUM(Balance_Sheet!F19:F20)-SUM(Balance_Sheet!G19:G20) -> -65792.044 | H41: =SUM(Balance_Sheet!G19:G20)-SUM(Balance_Sheet!H19:H20) -> -30970.711 | I41: =SUM(Balance_Sheet!H19:H20)-SUM(Balance_Sheet!I19:I20) -> -34930.564 | J41: =SUM(Balance_Sheet!I19:I20)-SUM(Balance_Sheet!J19:J20) -> -37106.264 | K41: =SUM(Balance_Sheet!J19:J20)-SUM(Balance_Sheet!K19:K20) -> -37470.986
B42: Proceeds from sale of current investments - mutual fund | C42: 63827.42 | D42: 495731.47 | E42: 495150.85 | F42: 126916.82 | G42: 0 | H42: 0 | I42: 0 | J42: 0 | K42: 0
B43: Investment in Joint Venture | C43: 0 | D43: 0 | E43: 0 | F43: 0 | G43: 0 | H43: 0 | I43: 0 | J43: 0 | K43: 0
B44: Interest received | C44: 58.52 | D44: 326.12 | E44: 891.16 | F44: 372.52 | G44: 0 | H44: 0 | I44: 0 | J44: 0 | K44: 0
B45: Investment in deposits with maturity of more than three months | C45: 57.87 | D45: -6062.09 | E45: -610.42 | F45: 3941.87 | G45: =Balance_Sheet!F29-Balance_Sheet!G29 -> 2730.57 | H45: =Balance_Sheet!G29-Balance_Sheet!H29 -> 0 | I45: =Balance_Sheet!H29-Balance_Sheet!I29 -> 0 | J45: =Balance_Sheet!I29-Balance_Sheet!J29 -> 0 | K45: =Balance_Sheet!J29-Balance_Sheet!K29 -> 0
B48: Net Cash Flow from Investing Activities (B) | C48: =SUM(C38:C45) -> -28932.43 | D48: =SUM(D38:D45) -> -109877.92 | E48: =SUM(E38:E45) -> -41870.39 | F48: =SUM(F38:F45) -> -36685.54 | G48: =SUM(G38:G45) -> -138782.22 | H48: =SUM(H38:H45) -> -107070.06 | I48: =SUM(I38:I45) -> -111410.41 | J48: =SUM(J38:J45) -> -113968.51 | K48: =SUM(K38:K45) -> -114717.55
B50: Cash Flow from Financing Activities:
B51: Proceeds from issue of share capital | C51: 0 | D51: 0 | E51: 97506.79 | F51: 303.53 | G51: 0 | H51: 0 | I51: 0 | J51: 0 | K51: 0
B52: Proceeds from non-current borrowings | C52: 6878.77 | D52: 57247.95 | E52: 43921.48 | F52: 46105.98 | G52: =SUM(Balance_Sheet!G47:G51)-SUM(Balance_Sheet!F47:F51) -> 26171.511 | H52: =SUM(Balance_Sheet!H47:H51)-SUM(Balance_Sheet!G47:G51) -> 46412.785 | I52: =SUM(Balance_Sheet!I47:I51)-SUM(Balance_Sheet!H47:H51) -> 52347.031 | J52: =SUM(Balance_Sheet!J47:J51)-SUM(Balance_Sheet!I47:I51) -> 55607.54 | K52: =SUM(Balance_Sheet!K47:K51)-SUM(Balance_Sheet!J47:J51) -> 56154.113
B53: Repayment of non-current borrowings | C53: -9878.77 | D53: -6611.19 | E53: -18217.42 | F53: -37308.27 | G53: 0 | H53: 0 | I53: 0 | J53: 0 | K53: 0
B54: Proceeds from current borrowings | C54: 627200.75 | D54: 568106.27 | E54: 1449982.8 | F54: 1845800.3 | G54: 0 | H54: 0 | I54: 0 | J54: 0 | K54: 0
B55: Repayment of current borrowings | C55: -724825.6 | D55: -455856.89 | E55: -1321402.6 | F55: -1919803.1 | G55: 0 | H55: 0 | I55: 0 | J55: 0 | K55: 0
B56: Interest paid | C56: -11813.59 | D56: -3988.75 | E56: -21734.06 | F56: -32959.9 | G56: ='P&L Statement'!G24 -> -39063.214 | H56: ='P&L Statement'!H24 -> -55072.199 | I56: ='P&L Statement'!I24 -> -73128.06 | J56: ='P&L Statement'!J24 -> -92308.556 | K56: ='P&L Statement'!K24 -> -111677.58
B57: Dividend Paid | C57: 0 | D57: 0 | E57: 0 | F57: -4073.7 | G57: ='P&L Statement'!G38 -> -5731.0672 | H57: ='P&L Statement'!H38 -> -8572.931 | I57: ='P&L Statement'!I38 -> -11827.84 | J57: ='P&L Statement'!J38 -> -15316.101 | K57: ='P&L Statement'!K38 -> -18855.44
B58: Repayment of lease laibilities | C58: 0 | D58: 0 | E58: 0 | F58: -286.73 | G58: 0 | H58: 0 | I58: 0 | J58: 0 | K58: 0
B60: Net Cash Flow from Financing Activities (C ) | C60: =SUM(C52:C59) -> -112438.44 | D60: =SUM(D52:D59) -> 158897.39 | E60: =SUM(E51:E59) -> 230057 | F60: =SUM(F51:F59) -> -102221.93 | G60: =SUM(G51:G59) -> -18622.771 | H60: =SUM(H51:H59) -> -17232.345 | I60: =SUM(I51:I59) -> -32608.869 | J60: =SUM(J51:J59) -> -52017.118 | K60: =SUM(K51:K59) -> -74378.906
B62: Net Increase/(Decrease) in Cash and Cash Equivalents (A+B+C) | C62: =C60+C48+C35 -> 8743.9 | D62: =D60+D48+D35 -> 44631.65 | E62: =E60+E48+E35 -> -49480.68 | F62: =F60+F48+F35 -> 4768.37 | G62: =G60+G48+G35 -> 1697.8403 | H62: =H60+H48+H35 -> 42462.679 | I62: =I60+I48+I35 -> 75853.891 | J62: =J60+J48+J35 -> 110251.93 | K62: =K60+K48+K35 -> 144056.48
B63: Cash and Cash Equivalents (Opening Balance) | C63: 408.55 | D63: =C64 -> 9152.45 | E63: =D64 -> 53784.1 | F63: =E64 -> 4303.42 | G63: =F64 -> 9071.79 | H63: =G64 -> 10769.63 | I63: =H64 -> 53232.309 | J63: =I64 -> 129086.2 | K63: =J64 -> 239338.13
B64: Cash and Cash Equivalents (Closing Balance) | C64: =SUM(C62:C63) -> 9152.45 | D64: =SUM(D62:D63) -> 53784.1 | E64: =SUM(E62:E63) -> 4303.42 | F64: =SUM(F62:F63) -> 9071.79 | G64: =SUM(G62:G63) -> 10769.63 | H64: =SUM(H62:H63) -> 53232.309 | I64: =SUM(I62:I63) -> 129086.2 | J64: =SUM(J62:J63) -> 239338.13 | K64: =SUM(K62:K63) -> 383394.61

Sheet CommonSize Statement
B6: Common Size Statement
B8: Particulars | C8: 2021 | D8: =C8+1 -> 2022 | E8: =D8+1 -> 2023 | F8: =E8+1 -> 2024 | G8: =F8+1 -> 2025 | H8: =G8+1 -> 2026 | I8: =H8+1 -> 2027 | J8: =I8+1 -> 2028 | K8: =J8+1 -> 2029
B9: Income Statement
B10: Revenue | C10: ='P&L Statement'!C9/'P&L Statement'!C$9 -> 1 | D10: ='P&L Statement'!D9/'P&L Statement'!D$9 -> 1 | E10: ='P&L Statement'!E9/'P&L Statement'!E$9 -> 1 | F10: ='P&L Statement'!F9/'P&L Statement'!F$9 -> 1 | G10: ='P&L Statement'!G9/'P&L Statement'!G$9 -> 1 | H10: ='P&L Statement'!H9/'P&L Statement'!H$9 -> 1 | I10: ='P&L Statement'!I9/'P&L Statement'!I$9 -> 1 | J10: ='P&L Statement'!J9/'P&L Statement'!J$9 -> 1 | K10: ='P&L Statement'!K9/'P&L Statement'!K$9 -> 1
B11: COGS | C11: =-'P&L Statement'!C10/'P&L Statement'!C$9 -> 0.74953705 | D11: =-'P&L Statement'!D10/'P&L Statement'!D$9 -> 0.79927312 | E11: =-'P&L Statement'!E10/'P&L Statement'!E$9 -> 0.79554759 | F11: =-'P&L Statement'!F10/'P&L Statement'!F$9 -> 0.77739525 | G11: =-'P&L Statement'!G10/'P&L Statement'!G$9 -> 0.78043825 | H11: =-'P&L Statement'!H10/'P&L Statement'!H$9 -> 0.78043825 | I11: =-'P&L Statement'!I10/'P&L Statement'!I$9 -> 0.78043825 | J11: =-'P&L Statement'!J10/'P&L Statement'!J$9 -> 0.78043825 | K11: =-'P&L Statement'!K10/'P&L Statement'!K$9 -> 0.78043825
B12: Gross Profit | C12: ='P&L Statement'!C11/'P&L Statement'!C$9 -> 0.25046295 | D12: ='P&L Statement'!D11/'P&L Statement'!D$9 -> 0.20072688 | E12: ='P&L Statement'!E11/'P&L Statement'!E$9 -> 0.20445241 | F12: ='P&L Statement'!F11/'P&L Statement'!F$9 -> 0.22260475 | G12: ='P&L Statement'!G11/'P&L Statement'!G$9 -> 0.21956175 | H12: ='P&L Statement'!H11/'P&L Statement'!H$9 -> 0.21956175 | I12: ='P&L Statement'!I11/'P&L Statement'!I$9 -> 0.21956175 | J12: ='P&L Statement'!J11/'P&L Statement'!J$9 -> 0.21956175 | K12: ='P&L Statement'!K11/'P&L Statement'!K$9 -> 0.21956175
B14: Salaries & Benefits | C14: =-'P&L Statement'!C14/'P&L Statement'!C$9 -> 0.026950084 | D14: =-'P&L Statement'!D14/'P&L Statement'!D$9 -> 0.017624297 | E14: =-'P&L Statement'!E14/'P&L Statement'!E$9 -> 0.015981332 | F14: =-'P&L Statement'!F14/'P&L Statement'!F$9 -> 0.019851864 | G14: =-'P&L Statement'!G14/'P&L Statement'!G$9 -> 0.020101894 | H14: =-'P&L Statement'!H14/'P&L Statement'!H$9 -> 0.020101894 | I14: =-'P&L Statement'!I14/'P&L Statement'!I$9 -> 0.020101894 | J14: =-'P&L Statement'!J14/'P&L Statement'!J$9 -> 0.020101894 | K14: =-'P&L Statement'!K14/'P&L Statement'!K$9 -> 0.020101894
B15: S&G Expenses | C15: =-'P&L Statement'!C15/'P&L Statement'!C$9 -> 0.11852286 | D15: =-'P&L Statement'!D15/'P&L Statement'!D$9 -> 0.097705743 | E15: =-'P&L Statement'!E15/'P&L Statement'!E$9 -> 0.12843009 | F15: =-'P&L Statement'!F15/'P&L Statement'!F$9 -> 0.1467682 | G15: =-'P&L Statement'!G15/'P&L Statement'!G$9 -> 0.12285672 | H15: =-'P&L Statement'!H15/'P&L Statement'!H$9 -> 0.12285672 | I15: =-'P&L Statement'!I15/'P&L Statement'!I$9 -> 0.12285672 | J15: =-'P&L Statement'!J15/'P&L Statement'!J$9 -> 0.12285672 | K15: =-'P&L Statement'!K15/'P&L Statement'!K$9 -> 0.12285672
B16: EBITDA | C16: ='P&L Statement'!C16/'P&L Statement'!C$9 -> 0.10499001 | D16: ='P&L Statement'!D16/'P&L Statement'!D$9 -> 0.085396842 | E16: ='P&L Statement'!E16/'P&L Statement'!E$9 -> 0.060040994 | F16: ='P&L Statement'!F16/'P&L Statement'!F$9 -> 0.055984682 | G16: ='P&L Statement'!G16/'P&L Statement'!G$9 -> 0.076603131 | H16: ='P&L Statement'!H16/'P&L Statement'!H$9 -> 0.076603131 | I16: ='P&L Statement'!I16/'P&L Statement'!I$9 -> 0.076603131 | J16: ='P&L Statement'!J16/'P&L Statement'!J$9 -> 0.076603131 | K16: ='P&L Statement'!K16/'P&L Statement'!K$9 -> 0.076603131
B18: Dep & Amo | C18: =-'P&L Statement'!C19/'P&L Statement'!C$9 -> 0.016134056 | D18: =-'P&L Statement'!D19/'P&L Statement'!D$9 -> 0.011510425 | E18: =-'P&L Statement'!E19/'P&L Statement'!E$9 -> 0.013129207 | F18: =-'P&L Statement'!F19/'P&L Statement'!F$9 -> 0.01820027 | G18: =-'P&L Statement'!G19/'P&L Statement'!G$9 -> 0.01441864 | H18: =-'P&L Statement'!H19/'P&L Statement'!H$9 -> 0.011655323 | I18: =-'P&L Statement'!I19/'P&L Statement'!I$9 -> 0.0097808077 | J18: =-'P&L Statement'!J19/'P&L Statement'!J$9 -> 0.0084904434 | K18: =-'P&L Statement'!K19/'P&L Statement'!K$9 -> 0.0075907918
B20: EBIT | C20: ='P&L Statement'!C21/'P&L Statement'!C$9 -> 0.08885595 | D20: ='P&L Statement'!D21/'P&L Statement'!D$9 -> 0.073886417 | E20: ='P&L Statement'!E21/'P&L Statement'!E$9 -> 0.046911787 | F20: ='P&L Statement'!F21/'P&L Statement'!F$9 -> 0.037784412 | G20: ='P&L Statement'!G21/'P&L Statement'!G$9 -> 0.062184491 | H20: ='P&L Statement'!H21/'P&L Statement'!H$9 -> 0.064947808 | I20: ='P&L Statement'!I21/'P&L Statement'!I$9 -> 0.066822323 | J20: ='P&L Statement'!J21/'P&L Statement'!J$9 -> 0.068112687 | K20: ='P&L Statement'!K21/'P&L Statement'!K$9 -> 0.069012339
B22: Interest Cost | C22: =-'P&L Statement'!C24/'P&L Statement'!C$9 -> 0.021574259 | D22: =-'P&L Statement'!D24/'P&L Statement'!D$9 -> 0.010884903 | E22: =-'P&L Statement'!E24/'P&L Statement'!E$9 -> 0.02183109 | F22: =-'P&L Statement'!F24/'P&L Statement'!F$9 -> 0.031621876 | G22: =-'P&L Statement'!G24/'P&L Statement'!G$9 -> 0.022315715 | H22: =-'P&L Statement'!H24/'P&L Statement'!H$9 -> 0.022315715 | I22: =-'P&L Statement'!I24/'P&L Statement'!I$9 -> 0.022315715 | J22: =-'P&L Statement'!J24/'P&L Statement'!J$9 -> 0.022315715 | K22: =-'P&L Statement'!K24/'P&L Statement'!K$9 -> 0.022315715
B23: Other Income | C23: ='P&L Statement'!C25/'P&L Statement'!C$9 -> 0.0037186817 | D23: ='P&L Statement'!D25/'P&L Statement'!D$9 -> 0.0049969848 | E23: ='P&L Statement'!E25/'P&L Statement'!E$9 -> 0.0068264672 | F23: ='P&L Statement'!F25/'P&L Statement'!F$9 -> 0.0059468153 | G23: ='P&L Statement'!G25/'P&L Statement'!G$9 -> 0.0053722372 | H23: ='P&L Statement'!H25/'P&L Statement'!H$9 -> 0.0053722372 | I23: ='P&L Statement'!I25/'P&L Statement'!I$9 -> 0.0053722372 | J23: ='P&L Statement'!J25/'P&L Statement'!J$9 -> 0.0053722372 | K23: ='P&L Statement'!K25/'P&L Statement'!K$9 -> 0.0053722372
B24: Share of net profit/(loss) of associate accounted for using the equity method | C24: ='P&L Statement'!C26/'P&L Statement'!C$9 -> -3.7756062e-05 | D24: ='P&L Statement'!D26/'P&L Statement'!D$9 -> 7.7773488e-05 | E24: ='P&L Statement'!E26/'P&L Statement'!E$9 -> 3.7869015e-05 | F24: ='P&L Statement'!F26/'P&L Statement'!F$9 -> 5.7623594e-05 | G24: ='P&L Statement'!G26/'P&L Statement'!G$9 -> 3.3877509e-05 | H24: ='P&L Statement'!H26/'P&L Statement'!H$9 -> 3.3877509e-05 | I24: ='P&L Statement'!I26/'P&L Statement'!I$9 -> 3.3877509e-05 | J24: ='P&L Statement'!J26/'P&L Statement'!J$9 -> 3.3877509e-05 | K24: ='P&L Statement'!K26/'P&L Statement'!K$9 -> 3.3877509e-05
B26: EBT | C26: ='P&L Statement'!C28/'P&L Statement'!C$9 -> 0.070962616 | D26: ='P&L Statement'!D28/'P&L Statement'!D$9 -> 0.068076271 | E26: ='P&L Statement'!E28/'P&L Statement'!E$9 -> 0.031945033 | F26: ='P&L Statement'!F28/'P&L Statement'!F$9 -> 0.012166976 | G26: ='P&L Statement'!G28/'P&L Statement'!G$9 -> 0.045274891 | H26: ='P&L Statement'!H28/'P&L Statement'!H$9 -> 0.048038208 | I26: ='P&L Statement'!I28/'P&L Statement'!I$9 -> 0.049912723 | J26: ='P&L Statement'!J28/'P&L Statement'!J$9 -> 0.051203087 | K26: ='P&L Statement'!K28/'P&L Statement'!K$9 -> 0.052102739
B28: Tax | C28: ='P&L Statement'!C31/'P&L Statement'!C$9 -> 0.027733241 | D28: ='P&L Statement'!D31/'P&L Statement'!D$9 -> 0.017374218 | E28: ='P&L Statement'!E31/'P&L Statement'!E$9 -> 0.0091432234 | F28: ='P&L Statement'!F31/'P&L Statement'!F$9 -> 0.0035356006 | G28: ='P&L Statement'!G31/'P&L Statement'!G$9 -> 0.013156427 | H28: ='P&L Statement'!H31/'P&L Statement'!H$9 -> 0.013959419 | I28: ='P&L Statement'!I31/'P&L Statement'!I$9 -> 0.014504135 | J28: ='P&L Statement'!J31/'P&L Statement'!J$9 -> 0.014879101 | K28: ='P&L Statement'!K31/'P&L Statement'!K$9 -> 0.015140531
B30: Net Profit | C30: ='P&L Statement'!C33/'P&L Statement'!C$9 -> 0.043229375 | D30: ='P&L Statement'!D33/'P&L Statement'!D$9 -> 0.050702053 | E30: ='P&L Statement'!E33/'P&L Statement'!E$9 -> 0.02280181 | F30: ='P&L Statement'!F33/'P&L Statement'!F$9 -> 0.008631375 | G30: ='P&L Statement'!G33/'P&L Statement'!G$9 -> 0.032118463 | H30: ='P&L Statement'!H33/'P&L Statement'!H$9 -> 0.034078788 | I30: ='P&L Statement'!I33/'P&L Statement'!I$9 -> 0.035408588 | J30: ='P&L Statement'!J33/'P&L Statement'!J$9 -> 0.036323986 | K30: ='P&L Statement'!K33/'P&L Statement'!K$9 -> 0.036962208
B33: Balance Sheet
B34: Assets
B35: Non-Current Assets
B36: Property Plant and Equipment | C36: =Balance_Sheet!C12/Balance_Sheet!C$35 -> 0.27697453 | D36: =Balance_Sheet!D12/Balance_Sheet!D$35 -> 0.15889375 | E36: =Balance_Sheet!E12/Balance_Sheet!E$35 -> 0.26233554 | F36: =Balance_Sheet!F12/Balance_Sheet!F$35 -> 0.34707954 | G36: =Balance_Sheet!G12/Balance_Sheet!G$35 -> 0.27142543 | H36: =Balance_Sheet!H12/Balance_Sheet!H$35 -> 0.22498613 | I36: =Balance_Sheet!I12/Balance_Sheet!I$35 -> 0.18981729 | J36: =Balance_Sheet!J12/Balance_Sheet!J$35 -> 0.16371279 | K36: =Balance_Sheet!K12/Balance_Sheet!K$35 -> 0.14434763
B37: Capital Work-in-Progress | C37: =Balance_Sheet!C13/Balance_Sheet!C$35 -> 0.04975163 | D37: =Balance_Sheet!D13/Balance_Sheet!D$35 -> 0.042417624 | E37: =Balance_Sheet!E13/Balance_Sheet!E$35 -> 0.065390179 | F37: =Balance_Sheet!F13/Balance_Sheet!F$35 -> 0.038524788 | G37: =Balance_Sheet!G13/Balance_Sheet!G$35 -> 0.028723957 | H37: =Balance_Sheet!H13/Balance_Sheet!H$35 -> 0.023078563 | I37: =Balance_Sheet!I13/Balance_Sheet!I$35 -> 0.01909423 | J37: =Balance_Sheet!J13/Balance_Sheet!J$35 -> 0.016287217 | K37: =Balance_Sheet!K13/Balance_Sheet!K$35 -> 0.014293196
B38: Right of use Assets | C38: =Balance_Sheet!C14/Balance_Sheet!C$35 -> 0 | D38: =Balance_Sheet!D14/Balance_Sheet!D$35 -> 0 | E38: =Balance_Sheet!E14/Balance_Sheet!E$35 -> 0.0015194425 | F38: =Balance_Sheet!F14/Balance_Sheet!F$35 -> 0.0018533348 | G38: =Balance_Sheet!G14/Balance_Sheet!G$35 -> 0.0013778846 | H38: =Balance_Sheet!H14/Balance_Sheet!H$35 -> 0.0010945347 | I38: =Balance_Sheet!I14/Balance_Sheet!I$35 -> 0.000890029 | J38: =Balance_Sheet!J14/Balance_Sheet!J$35 -> 0.00074305812 | K38: =Balance_Sheet!K14/Balance_Sheet!K$35 -> 0.00063636297
B39: Goodwill | C39: =Balance_Sheet!C15/Balance_Sheet!C$35 -> 0 | D39: =Balance_Sheet!D15/Balance_Sheet!D$35 -> 0 | E39: =Balance_Sheet!E15/Balance_Sheet!E$35 -> 0.0054489439 | F39: =Balance_Sheet!F15/Balance_Sheet!F$35 -> 0.0060106249 | G39: =Balance_Sheet!G15/Balance_Sheet!G$35 -> 0.004121786 | H39: =Balance_Sheet!H15/Balance_Sheet!H$35 -> 0.0030644853 | I39: =Balance_Sheet!I15/Balance_Sheet!I$35 -> 0.0023584922 | J39: =Balance_Sheet!J15/Balance_Sheet!J$35 -> 0.0018799279 | K39: =Balance_Sheet!K15/Balance_Sheet!K$35 -> 0.0015478238
B40: Intangible Assets | C40: =Balance_Sheet!C16/Balance_Sheet!C$35 -> 0.00024993412 | D40: =Balance_Sheet!D16/Balance_Sheet!D$35 -> 0.00010876392 | E40: =Balance_Sheet!E16/Balance_Sheet!E$35 -> 0.00016687622 | F40: =Balance_Sheet!F16/Balance_Sheet!F$35 -> 0.00019097154 | G40: =Balance_Sheet!G16/Balance_Sheet!G$35 -> 0.00013451864 | H40: =Balance_Sheet!H16/Balance_Sheet!H$35 -> 0.00010204451 | I40: =Balance_Sheet!I16/Balance_Sheet!I$35 -> 7.9764433e-05 | J40: =Balance_Sheet!J16/Balance_Sheet!J$35 -> 6.4369939e-05 | K40: =Balance_Sheet!K16/Balance_Sheet!K$35 -> 5.3539502e-05
B41: Equity accounted investment | C41: =Balance_Sheet!C17/Balance_Sheet!C$35 -> 0.00062968477 | D41: =Balance_Sheet!D17/Balance_Sheet!D$35 -> 0.00036506483 | E41: =Balance_Sheet!E17/Balance_Sheet!E$35 -> 0.00029585247 | F41: =Balance_Sheet!F17/Balance_Sheet!F$35 -> 0.00033601676 | G41: =Balance_Sheet!G17/Balance_Sheet!G$35 -> 0.00023042349 | H41: =Balance_Sheet!H17/Balance_Sheet!H$35 -> 0.00017131637 | I41: =Balance_Sheet!I17/Balance_Sheet!I$35 -> 0.00013184867 | J41: =Balance_Sheet!J17/Balance_Sheet!J$35 -> 0.00010509511 | K41: =Balance_Sheet!K17/Balance_Sheet!K$35 -> 8.6529227e-05
B43: Other income tax assets | C43: =Balance_Sheet!C19/Balance_Sheet!C$35 -> 0.0028192252 | D43: =Balance_Sheet!D19/Balance_Sheet!D$35 -> 0.0015596264 | E43: =Balance_Sheet!E19/Balance_Sheet!E$35 -> 0.0010383972 | F43: =Balance_Sheet!F19/Balance_Sheet!F$35 -> 0.0061591479 | G43: =Balance_Sheet!G19/Balance_Sheet!G$35 -> 0.0030932133 | H43: =Balance_Sheet!H19/Balance_Sheet!H$35 -> 0.0032422493 | I43: =Balance_Sheet!I19/Balance_Sheet!I$35 -> 0.0033134081 | J43: =Balance_Sheet!J19/Balance_Sheet!J$35 -> 0.0033338004 | K43: =Balance_Sheet!K19/Balance_Sheet!K$35 -> 0.0033208094
B44: Other Non-Current Assets | C44: =Balance_Sheet!C20/Balance_Sheet!C$35 -> 0.005248187 | D44: =Balance_Sheet!D20/Balance_Sheet!D$35 -> 0.14918495 | E44: =Balance_Sheet!E20/Balance_Sheet!E$35 -> 0.0055363043 | F44: =Balance_Sheet!F20/Balance_Sheet!F$35 -> 0.003962851 | G44: =Balance_Sheet!G20/Balance_Sheet!G$35 -> 0.050547367 | H44: =Balance_Sheet!H20/Balance_Sheet!H$35 -> 0.052982822 | I44: =Balance_Sheet!I20/Balance_Sheet!I$35 -> 0.054145655 | J44: =Balance_Sheet!J20/Balance_Sheet!J$35 -> 0.054478892 | K44: =Balance_Sheet!K20/Balance_Sheet!K$35 -> 0.054266602
B46: Total Non-Current Assets | C46: =Balance_Sheet!C22/Balance_Sheet!C$35 -> 0.33567319 | D46: =Balance_Sheet!D22/Balance_Sheet!D$35 -> 0.35252978 | E46: =Balance_Sheet!E22/Balance_Sheet!E$35 -> 0.34173154 | F46: =Balance_Sheet!F22/Balance_Sheet!F$35 -> 0.40411727 | G46: =Balance_Sheet!G22/Balance_Sheet!G$35 -> 0.35965458 | H46: =Balance_Sheet!H22/Balance_Sheet!H$35 -> 0.30872214 | I46: =Balance_Sheet!I22/Balance_Sheet!I$35 -> 0.26983072 | J46: =Balance_Sheet!J22/Balance_Sheet!J$35 -> 0.24060515 | K46: =Balance_Sheet!K22/Balance_Sheet!K$35 -> 0.21855249
B48: Current Assets:
B49: Inventories | C49: =Balance_Sheet!C25/Balance_Sheet!C$35 -> 0.20326022 | D49: =Balance_Sheet!D25/Balance_Sheet!D$35 -> 0.2892495 | E49: =Balance_Sheet!E25/Balance_Sheet!E$35 -> 0.20997251 | F49: =Balance_Sheet!F25/Balance_Sheet!F$35 -> 0.18950479 | G49: =Balance_Sheet!G25/Balance_Sheet!G$35 -> 0.24524325 | H49: =Balance_Sheet!H25/Balance_Sheet!H$35 -> 0.25705947 | I49: =Balance_Sheet!I25/Balance_Sheet!I$35 -> 0.26270125 | J49: =Balance_Sheet!J25/Balance_Sheet!J$35 -> 0.26431803 | K49: =Balance_Sheet!K25/Balance_Sheet!K$35 -> 0.26328805
B50: Investments | C50: =Balance_Sheet!C26/Balance_Sheet!C$35 -> 0.027591099 | D50: =Balance_Sheet!D26/Balance_Sheet!D$35 -> 0.069418371 | E50: =Balance_Sheet!E26/Balance_Sheet!E$35 -> 0 | F50: =Balance_Sheet!F26/Balance_Sheet!F$35 -> 0 | G50: =Balance_Sheet!G26/Balance_Sheet!G$35 -> 0 | H50: =Balance_Sheet!H26/Balance_Sheet!H$35 -> 0 | I50: =Balance_Sheet!I26/Balance_Sheet!I$35 -> 0 | J50: =Balance_Sheet!J26/Balance_Sheet!J$35 -> 0 | K50: =Balance_Sheet!K26/Balance_Sheet!K$35 -> 0
B51: Trade Receivables | C51: =Balance_Sheet!C27/Balance_Sheet!C$35 -> 0.2612594 | D51: =Balance_Sheet!D27/Balance_Sheet!D$35 -> 0.11383133 | E51: =Balance_Sheet!E27/Balance_Sheet!E$35 -> 0.34622663 | F51: =Balance_Sheet!F27/Balance_Sheet!F$35 -> 0.28159031 | G51: =Balance_Sheet!G27/Balance_Sheet!G$35 -> 0.26408949 | H51: =Balance_Sheet!H27/Balance_Sheet!H$35 -> 0.27681375 | I51: =Balance_Sheet!I27/Balance_Sheet!I$35 -> 0.28288908 | J51: =Balance_Sheet!J27/Balance_Sheet!J$35 -> 0.28463011 | K51: =Balance_Sheet!K27/Balance_Sheet!K$35 -> 0.28352098
B52: Cash and Cash Equivalents | C52: =Balance_Sheet!C28/Balance_Sheet!C$35 -> 0.020692081 | D52: =Balance_Sheet!D28/Balance_Sheet!D$35 -> 0.067839143 | E52: =Balance_Sheet!E28/Balance_Sheet!E$35 -> 0.0040381155 | F52: =Balance_Sheet!F28/Balance_Sheet!F$35 -> 0.0093899931 | G52: =Balance_Sheet!G28/Balance_Sheet!G$35 -> 0.0076443207 | H52: =Balance_Sheet!H28/Balance_Sheet!H$35 -> 0.028092185 | I52: =Balance_Sheet!I28/Balance_Sheet!I$35 -> 0.052428437 | J52: =Balance_Sheet!J28/Balance_Sheet!J$35 -> 0.077482877 | K52: =Balance_Sheet!K28/Balance_Sheet!K$35 -> 0.10219277
B53: Bank Balances | C53: =Balance_Sheet!C29/Balance_Sheet!C$35 -> 0.00037828111 | D53: =Balance_Sheet!D29/Balance_Sheet!D$35 -> 0.0075520098 | E53: =Balance_Sheet!E29/Balance_Sheet!E$35 -> 0.0062700379 | F53: =Balance_Sheet!F29/Balance_Sheet!F$35 -> 0.0028263478 | G53: =Balance_Sheet!G29/Balance_Sheet!G$35 -> 0 | H53: =Balance_Sheet!H29/Balance_Sheet!H$35 -> 0 | I53: =Balance_Sheet!I29/Balance_Sheet!I$35 -> 0 | J53: =Balance_Sheet!J29/Balance_Sheet!J$35 -> 0 | K53: =Balance_Sheet!K29/Balance_Sheet!K$35 -> 0
B54: Others Current Financial Assets | C54: =Balance_Sheet!C30/Balance_Sheet!C$35 -> 0.044293842 | D54: =Balance_Sheet!D30/Balance_Sheet!D$35 -> 0.042688683 | E54: =Balance_Sheet!E30/Balance_Sheet!E$35 -> 0.031639549 | F54: =Balance_Sheet!F30/Balance_Sheet!F$35 -> 0.052187554 | G54: =Balance_Sheet!G30/Balance_Sheet!G$35 -> 0.046541699 | H54: =Balance_Sheet!H30/Balance_Sheet!H$35 -> 0.048784154 | I54: =Balance_Sheet!I30/Balance_Sheet!I$35 -> 0.049854838 | J54: =Balance_Sheet!J30/Balance_Sheet!J$35 -> 0.050161667 | K54: =Balance_Sheet!K30/Balance_Sheet!K$35 -> 0.0499662
B55: Other Current Assets | C55: =Balance_Sheet!C31/Balance_Sheet!C$35 -> 0.10679691 | D55: =Balance_Sheet!D31/Balance_Sheet!D$35 -> 0.05686095 | E55: =Balance_Sheet!E31/Balance_Sheet!E$35 -> 0.060099798 | F55: =Balance_Sheet!F31/Balance_Sheet!F$35 -> 0.060359656 | G55: =Balance_Sheet!G31/Balance_Sheet!G$35 -> 0.076790905 | H55: =Balance_Sheet!H31/Balance_Sheet!H$35 -> 0.080490816 | I55: =Balance_Sheet!I31/Balance_Sheet!I$35 -> 0.082257377 | J55: =Balance_Sheet!J31/Balance_Sheet!J$35 -> 0.082763626 | K55: =Balance_Sheet!K31/Balance_Sheet!K$35 -> 0.082441117
B56: Assets classified as held for sale | C56: =Balance_Sheet!C32/Balance_Sheet!C$35 -> 5.4983245e-05 | D56: =Balance_Sheet!D32/Balance_Sheet!D$35 -> 3.0221308e-05 | E56: =Balance_Sheet!E32/Balance_Sheet!E$35 -> 2.1826028e-05 | F56: =Balance_Sheet!F32/Balance_Sheet!F$35 -> 2.407587e-05 | G56: =Balance_Sheet!G32/Balance_Sheet!G$35 -> 3.5755075e-05 | H56: =Balance_Sheet!H32/Balance_Sheet!H$35 -> 3.7477812e-05 | I56: =Balance_Sheet!I32/Balance_Sheet!I$35 -> 3.8300351e-05 | J56: =Balance_Sheet!J32/Balance_Sheet!J$35 -> 3.8536069e-05 | K56: =Balance_Sheet!K32/Balance_Sheet!K$35 -> 3.8385904e-05
B57: Total Current Assets | C57: =Balance_Sheet!C33/Balance_Sheet!C$35 -> 0.66432681 | D57: =Balance_Sheet!D33/Balance_Sheet!D$35 -> 0.64747022 | E57: =Balance_Sheet!E33/Balance_Sheet!E$35 -> 0.65826846 | F57: =Balance_Sheet!F33/Balance_Sheet!F$35 -> 0.59588273 | G57: =Balance_Sheet!G33/Balance_Sheet!G$35 -> 0.64034542 | H57: =Balance_Sheet!H33/Balance_Sheet!H$35 -> 0.69127786 | I57: =Balance_Sheet!I33/Balance_Sheet!I$35 -> 0.73016928 | J57: =Balance_Sheet!J33/Balance_Sheet!J$35 -> 0.75939485 | K57: =Balance_Sheet!K33/Balance_Sheet!K$35 -> 0.78144751
B59: TOTAL ASSETS | C59: =Balance_Sheet!C35/Balance_Sheet!C$35 -> 1 | D59: =Balance_Sheet!D35/Balance_Sheet!D$35 -> 1 | E59: =Balance_Sheet!E35/Balance_Sheet!E$35 -> 1 | F59: =Balance_Sheet!F35/Balance_Sheet!F$35 -> 1 | G59: =Balance_Sheet!G35/Balance_Sheet!G$35 -> 1 | H59: =Balance_Sheet!H35/Balance_Sheet!H$35 -> 1 | I59: =Balance_Sheet!I35/Balance_Sheet!I$35 -> 1 | J59: =Balance_Sheet!J35/Balance_Sheet!J$35 -> 1 | K59: =Balance_Sheet!K35/Balance_Sheet!K$35 -> 1
B61: EQUITY AND LIABILITIES
B62: EQUITY
B63: Equity Share Capital | C63: =Balance_Sheet!C39/Balance_Sheet!C$35 -> 0.13009913 | D63: =Balance_Sheet!D39/Balance_Sheet!D$35 -> 0.072582854 | E63: =Balance_Sheet!E39/Balance_Sheet!E$35 -> 0.076428407 | F63: =Balance_Sheet!F39/Balance_Sheet!F$35 -> 0.084335786 | G63: =Balance_Sheet!G39/Balance_Sheet!G$35 -> 0.057833266 | H63: =Balance_Sheet!H39/Balance_Sheet!H$35 -> 0.042998155 | I63: =Balance_Sheet!I39/Balance_Sheet!I$35 -> 0.033092282 | J63: =Balance_Sheet!J39/Balance_Sheet!J$35 -> 0.02637749 | K63: =Balance_Sheet!K39/Balance_Sheet!K$35 -> 0.021717698
B64: Other Equity | C64: =Balance_Sheet!C40/Balance_Sheet!C$35 -> 0.28306869 | D64: =Balance_Sheet!D40/Balance_Sheet!D$35 -> 0.20806127 | E64: =Balance_Sheet!E40/Balance_Sheet!E$35 -> 0.25243544 | F64: =Balance_Sheet!F40/Balance_Sheet!F$35 -> 0.28460675 | G64: =Balance_Sheet!G40/Balance_Sheet!G$35 -> 0.23096615 | H64: =Balance_Sheet!H40/Balance_Sheet!H$35 -> 0.21153445 | I64: =Balance_Sheet!I40/Balance_Sheet!I$35 -> 0.20507929 | J64: =Balance_Sheet!J40/Balance_Sheet!J$35 -> 0.20710544 | K64: =Balance_Sheet!K40/Balance_Sheet!K$35 -> 0.21475215
B66: Total Equity | C66: =Balance_Sheet!C42/Balance_Sheet!C$35 -> 0.41316782 | D66: =Balance_Sheet!D42/Balance_Sheet!D$35 -> 0.28064413 | E66: =Balance_Sheet!E42/Balance_Sheet!E$35 -> 0.32886385 | F66: =Balance_Sheet!F42/Balance_Sheet!F$35 -> 0.36894254 | G66: =Balance_Sheet!G42/Balance_Sheet!G$35 -> 0.28879941 | H66: =Balance_Sheet!H42/Balance_Sheet!H$35 -> 0.25453261 | I66: =Balance_Sheet!I42/Balance_Sheet!I$35 -> 0.23817157 | J66: =Balance_Sheet!J42/Balance_Sheet!J$35 -> 0.23348293 | K66: =Balance_Sheet!K42/Balance_Sheet!K$35 -> 0.23646985
B68: LIABILITIES
B69: Non-Current Liabilities:
B70: Financial Liabilities
B71: (i) Borrowings | C71: =Balance_Sheet!C47/Balance_Sheet!C$35 -> 0.025640302 | D71: =Balance_Sheet!D47/Balance_Sheet!D$35 -> 0.066619418 | E71: =Balance_Sheet!E47/Balance_Sheet!E$35 -> 0.05741652 | F71: =Balance_Sheet!F47/Balance_Sheet!F$35 -> 0.070023499 | G71: =Balance_Sheet!G47/Balance_Sheet!G$35 -> 0.060098961 | H71: =Balance_Sheet!H47/Balance_Sheet!H$35 -> 0.062994627 | I71: =Balance_Sheet!I47/Balance_Sheet!I$35 -> 0.064377193 | J71: =Balance_Sheet!J47/Balance_Sheet!J$35 -> 0.0647734 | K71: =Balance_Sheet!K47/Balance_Sheet!K$35 -> 0.064520994
B72: (ii) Lease Liabilities | C72: =Balance_Sheet!C48/Balance_Sheet!C$35 -> 0 | D72: =Balance_Sheet!D48/Balance_Sheet!D$35 -> 0 | E72: =Balance_Sheet!E48/Balance_Sheet!E$35 -> 0.0015049074 | F72: =Balance_Sheet!F48/Balance_Sheet!F$35 -> 0.0017827012 | G72: =Balance_Sheet!G48/Balance_Sheet!G$35 -> 0.00083560796 | H72: =Balance_Sheet!H48/Balance_Sheet!H$35 -> 0.00087586892 | I72: =Balance_Sheet!I48/Balance_Sheet!I$35 -> 0.00089509193 | J72: =Balance_Sheet!J48/Balance_Sheet!J$35 -> 0.00090060073 | K72: =Balance_Sheet!K48/Balance_Sheet!K$35 -> 0.00089709132
B73: Other financial liabilities | C73: =Balance_Sheet!C49/Balance_Sheet!C$35 -> 2.2721284e-05 | D73: =Balance_Sheet!D49/Balance_Sheet!D$35 -> 0.00036163403 | E73: =Balance_Sheet!E49/Balance_Sheet!E$35 -> 0.00016929716 | F73: =Balance_Sheet!F49/Balance_Sheet!F$35 -> 0 | G73: =Balance_Sheet!G49/Balance_Sheet!G$35 -> 0.0001613784 | H73: =Balance_Sheet!H49/Balance_Sheet!H$35 -> 0.00016915387 | I73: =Balance_Sheet!I49/Balance_Sheet!I$35 -> 0.00017286636 | J73: =Balance_Sheet!J49/Balance_Sheet!J$35 -> 0.00017393025 | K73: =Balance_Sheet!K49/Balance_Sheet!K$35 -> 0.00017325249
B74: Provisions | C74: =Balance_Sheet!C50/Balance_Sheet!C$35 -> 0.0044651053 | D74: =Balance_Sheet!D50/Balance_Sheet!D$35 -> 0.0033485992 | E74: =Balance_Sheet!E50/Balance_Sheet!E$35 -> 0.0022325324 | F74: =Balance_Sheet!F50/Balance_Sheet!F$35 -> 0.0027133485 | G74: =Balance_Sheet!G50/Balance_Sheet!G$35 -> 0.0034946133 | H74: =Balance_Sheet!H50/Balance_Sheet!H$35 -> 0.0036629894 | I74: =Balance_Sheet!I50/Balance_Sheet!I$35 -> 0.0037433824 | J74: =Balance_Sheet!J50/Balance_Sheet!J$35 -> 0.0037664208 | K74: =Balance_Sheet!K50/Balance_Sheet!K$35 -> 0.0037517441
B75: Deferred Tax Liabilities (Net) | C75: =Balance_Sheet!C51/Balance_Sheet!C$35 -> 0.021028446 | D75: =Balance_Sheet!D51/Balance_Sheet!D$35 -> 0.011627018 | E75: =Balance_Sheet!E51/Balance_Sheet!E$35 -> 0.010113558 | F75: =Balance_Sheet!F51/Balance_Sheet!F$35 -> 0.015614289 | G75: =Balance_Sheet!G51/Balance_Sheet!G$35 -> 0.015795347 | H75: =Balance_Sheet!H51/Balance_Sheet!H$35 -> 0.016556393 | I75: =Balance_Sheet!I51/Balance_Sheet!I$35 -> 0.016919762 | J75: =Balance_Sheet!J51/Balance_Sheet!J$35 -> 0.017023894 | K75: =Balance_Sheet!K51/Balance_Sheet!K$35 -> 0.016957556
B76: Total Non-Current Liabilities | C76: =Balance_Sheet!C52/Balance_Sheet!C$35 -> 0.051156574 | D76: =Balance_Sheet!D52/Balance_Sheet!D$35 -> 0.081956669 | E76: =Balance_Sheet!E52/Balance_Sheet!E$35 -> 0.071436815 | F76: =Balance_Sheet!F52/Balance_Sheet!F$35 -> 0.090133838 | G76: =Balance_Sheet!G52/Balance_Sheet!G$35 -> 0.080385908 | H76: =Balance_Sheet!H52/Balance_Sheet!H$35 -> 0.084259032 | I76: =Balance_Sheet!I52/Balance_Sheet!I$35 -> 0.086108296 | J76: =Balance_Sheet!J52/Balance_Sheet!J$35 -> 0.086638245 | K76: =Balance_Sheet!K52/Balance_Sheet!K$35 -> 0.086300638
B78: Current Liabilities:
B79: Financial Liabilities
B80: (i) Borrowings | C80: =Balance_Sheet!C56/Balance_Sheet!C$35 -> 0.25722781 | D80: =Balance_Sheet!D56/Balance_Sheet!D$35 -> 0.30601281 | E80: =Balance_Sheet!E56/Balance_Sheet!E$35 -> 0.37714319 | F80: =Balance_Sheet!F56/Balance_Sheet!F$35 -> 0.34342476 | G80: =Balance_Sheet!G56/Balance_Sheet!G$35 -> 0.34694365 | H80: =Balance_Sheet!H56/Balance_Sheet!H$35 -> 0.36365996 | I80: =Balance_Sheet!I56/Balance_Sheet!I$35 -> 0.37164134 | J80: =Balance_Sheet!J56/Balance_Sheet!J$35 -> 0.37392859 | K80: =Balance_Sheet!K56/Balance_Sheet!K$35 -> 0.37247148
B81: (ii) Lease Liabilities | C81: =Balance_Sheet!C57/Balance_Sheet!C$35 -> 0 | D81: =Balance_Sheet!D57/Balance_Sheet!D$35 -> 0 | E81: =Balance_Sheet!E57/Balance_Sheet!E$35 -> 7.2553245e-05 | F81: =Balance_Sheet!F57/Balance_Sheet!F$35 -> 0.0002182872 | G81: =Balance_Sheet!G57/Balance_Sheet!G$35 -> 7.4596519e-05 | H81: =Balance_Sheet!H57/Balance_Sheet!H$35 -> 7.8190701e-05 | I81: =Balance_Sheet!I57/Balance_Sheet!I$35 -> 7.9906781e-05 | J81: =Balance_Sheet!J57/Balance_Sheet!J$35 -> 8.0398564e-05 | K81: =Balance_Sheet!K57/Balance_Sheet!K$35 -> 8.0085271e-05
B82: (iii) Trade Payables
B83: Total outstanding dues of micro enterprises and small enterprises | C83: =Balance_Sheet!C59/Balance_Sheet!C$35 -> 0.0014142812 | D83: =Balance_Sheet!D59/Balance_Sheet!D$35 -> 0.0010327211 | E83: =Balance_Sheet!E59/Balance_Sheet!E$35 -> 0.00062632068 | F83: =Balance_Sheet!F59/Balance_Sheet!F$35 -> 0.00096249657 | G83: =Balance_Sheet!G59/Balance_Sheet!G$35 -> 0 | H83: =Balance_Sheet!H59/Balance_Sheet!H$35 -> 0 | I83: =Balance_Sheet!I59/Balance_Sheet!I$35 -> 0 | J83: =Balance_Sheet!J59/Balance_Sheet!J$35 -> 0 | K83: =Balance_Sheet!K59/Balance_Sheet!K$35 -> 0
B84: Total outstanding dues of creditors other than micro enterprises and small enterprises | C84: =Balance_Sheet!C60/Balance_Sheet!C$35 -> 0.21099732 | D84: =Balance_Sheet!D60/Balance_Sheet!D$35 -> 0.28571637 | E84: =Balance_Sheet!E60/Balance_Sheet!E$35 -> 0.17883099 | F84: =Balance_Sheet!F60/Balance_Sheet!F$35 -> 0.15306897 | G84: =Balance_Sheet!G60/Balance_Sheet!G$35 -> 0.23035203 | H84: =Balance_Sheet!H60/Balance_Sheet!H$35 -> 0.24145077 | I84: =Balance_Sheet!I60/Balance_Sheet!I$35 -> 0.24674998 | J84: =Balance_Sheet!J60/Balance_Sheet!J$35 -> 0.24826859 | K84: =Balance_Sheet!K60/Balance_Sheet!K$35 -> 0.24730115
B85: (iv)Other Financial Liabilities | C85: =Balance_Sheet!C61/Balance_Sheet!C$35 -> 0.018641943 | D85: =Balance_Sheet!D61/Balance_Sheet!D$35 -> 0.009796396 | E85: =Balance_Sheet!E61/Balance_Sheet!E$35 -> 0.022523325 | F85: =Balance_Sheet!F61/Balance_Sheet!F$35 -> 0.023243079 | G85: =Balance_Sheet!G61/Balance_Sheet!G$35 -> 0.019643987 | H85: =Balance_Sheet!H61/Balance_Sheet!H$35 -> 0.020590466 | I85: =Balance_Sheet!I61/Balance_Sheet!I$35 -> 0.021042372 | J85: =Balance_Sheet!J61/Balance_Sheet!J$35 -> 0.021171877 | K85: =Balance_Sheet!K61/Balance_Sheet!K$35 -> 0.021089375
B86: Other Current Liabilities | C86: =Balance_Sheet!C62/Balance_Sheet!C$35 -> 0.028574467 | D86: =Balance_Sheet!D62/Balance_Sheet!D$35 -> 0.018794791 | E86: =Balance_Sheet!E62/Balance_Sheet!E$35 -> 0.010842169 | F86: =Balance_Sheet!F62/Balance_Sheet!F$35 -> 0.01244206 | G86: =Balance_Sheet!G62/Balance_Sheet!G$35 -> 0.019407291 | H86: =Balance_Sheet!H62/Balance_Sheet!H$35 -> 0.020342366 | I86: =Balance_Sheet!I62/Balance_Sheet!I$35 -> 0.020788827 | J86: =Balance_Sheet!J62/Balance_Sheet!J$35 -> 0.020916771 | K86: =Balance_Sheet!K62/Balance_Sheet!K$35 -> 0.020835264
B87: Provisions | C87: =Balance_Sheet!C63/Balance_Sheet!C$35 -> 0.018768345 | D87: =Balance_Sheet!D63/Balance_Sheet!D$35 -> 0.0094909161 | E87: =Balance_Sheet!E63/Balance_Sheet!E$35 -> 0.0084456782 | F87: =Balance_Sheet!F63/Balance_Sheet!F$35 -> 0.007540426 | G87: =Balance_Sheet!G63/Balance_Sheet!G$35 -> 0.012017616 | H87: =Balance_Sheet!H63/Balance_Sheet!H$35 -> 0.012596644 | I87: =Balance_Sheet!I63/Balance_Sheet!I$35 -> 0.012873107 | J87: =Balance_Sheet!J63/Balance_Sheet!J$35 -> 0.012952334 | K87: =Balance_Sheet!K63/Balance_Sheet!K$35 -> 0.012901862
B88: Current tax liabilities | C88: =Balance_Sheet!C64/Balance_Sheet!C$35 -> 5.1433751e-05 | D88: =Balance_Sheet!D64/Balance_Sheet!D$35 -> 0.0065551986 | E88: =Balance_Sheet!E64/Balance_Sheet!E$35 -> 0.0012151167 | F88: =Balance_Sheet!F64/Balance_Sheet!F$35 -> 2.3547982e-05 | G88: =Balance_Sheet!G64/Balance_Sheet!G$35 -> 0.0023755036 | H88: =Balance_Sheet!H64/Balance_Sheet!H$35 -> 0.0024899592 | I88: =Balance_Sheet!I64/Balance_Sheet!I$35 -> 0.0025446073 | J88: =Balance_Sheet!J64/Balance_Sheet!J$35 -> 0.0025602679 | K88: =Balance_Sheet!K64/Balance_Sheet!K$35 -> 0.0025502912
B89: Total Current Liabilities | C89: =Balance_Sheet!C65/Balance_Sheet!C$35 -> 0.5356756 | D89: =Balance_Sheet!D65/Balance_Sheet!D$35 -> 0.6373992 | E89: =Balance_Sheet!E65/Balance_Sheet!E$35 -> 0.59969934 | F89: =Balance_Sheet!F65/Balance_Sheet!F$35 -> 0.54092362 | G89: =Balance_Sheet!G65/Balance_Sheet!G$35 -> 0.63081468 | H89: =Balance_Sheet!H65/Balance_Sheet!H$35 -> 0.66120836 | I89: =Balance_Sheet!I65/Balance_Sheet!I$35 -> 0.67572014 | J89: =Balance_Sheet!J65/Balance_Sheet!J$35 -> 0.67987883 | K89: =Balance_Sheet!K65/Balance_Sheet!K$35 -> 0.67722951
B91: Total Liabilities | C91: =Balance_Sheet!C67/Balance_Sheet!C$35 -> 0.58683218 | D91: =Balance_Sheet!D67/Balance_Sheet!D$35 -> 0.71935587 | E91: =Balance_Sheet!E67/Balance_Sheet!E$35 -> 0.67113615 | F91: =Balance_Sheet!F67/Balance_Sheet!F$35 -> 0.63105746 | G91: =Balance_Sheet!G67/Balance_Sheet!G$35 -> 0.71120059 | H91: =Balance_Sheet!H67/Balance_Sheet!H$35 -> 0.74546739 | I91: =Balance_Sheet!I67/Balance_Sheet!I$35 -> 0.76182843 | J91: =Balance_Sheet!J67/Balance_Sheet!J$35 -> 0.76651707 | K91: =Balance_Sheet!K67/Balance_Sheet!K$35 -> 0.76353015
B93: TOTAL EQUITY AND LIABILITIES | C93: =Balance_Sheet!C69/Balance_Sheet!C$35 -> 1 | D93: =Balance_Sheet!D69/Balance_Sheet!D$35 -> 1 | E93: =Balance_Sheet!E69/Balance_Sheet!E$35 -> 1 | F93: =Balance_Sheet!F69/Balance_Sheet!F$35 -> 1 | G93: =Balance_Sheet!G69/Balance_Sheet!G$35 -> 1 | H93: =Balance_Sheet!H69/Balance_Sheet!H$35 -> 1 | I93: =Balance_Sheet!I69/Balance_Sheet!I$35 -> 1 | J93: =Balance_Sheet!J69/Balance_Sheet!J$35 -> 1 | K93: =Balance_Sheet!K69/Balance_Sheet!K$35 -> 1

Sheet B_Sheet 
B6: Balance Sheet Forecasting
B8: Particulars | C8: 2021 | D8: =C8+1 -> 2022 | E8: =D8+1 -> 2023 | F8: =E8+1 -> 2024 | G8: =F8+1 -> 2025 | H8: =G8+1 -> 2026 | I8: =H8+1 -> 2027 | J8: =I8+1 -> 2028 | K8: =J8+1 -> 2029
B10: Non-Current Assets
B11: Other income tax assets | C11: ='Balance Sheet'!C19 -> 1246.99 | D11: ='Balance Sheet'!D19 -> 1236.5 | E11: ='Balance Sheet'!E19 -> 1106.62 | F11: ='Balance Sheet'!F19 -> 5950.43 | G11: =G12*'Revenue BuildUp'!G$10 -> 4357.8448 | H11: =H12*'Revenue BuildUp'!H$10 -> 6143.7877 | I11: =I12*'Revenue BuildUp'!I$10 -> 8158.0777 | J11: =J12*'Revenue BuildUp'!J$10 -> 10297.831 | K11: =K12*'Revenue BuildUp'!K$10 -> 12458.615
B12: % of Revenue | C12: =C11/'Revenue BuildUp'!C$10 -> 0.0024144324 | D12: =D11/'Revenue BuildUp'!D$10 -> 0.0015734116 | E12: =E11/'Revenue BuildUp'!E$10 -> 0.00082950534 | F12: =F11/'Revenue BuildUp'!F$10 -> 0.0051407071 | G12: =AVERAGE($C$12:$F$12) -> 0.0024895141 | H12: =AVERAGE($C$12:$F$12) -> 0.0024895141 | I12: =AVERAGE($C$12:$F$12) -> 0.0024895141 | J12: =AVERAGE($C$12:$F$12) -> 0.0024895141 | K12: =AVERAGE($C$12:$F$12) -> 0.0024895141
B13: Other Non-Current Assets | C13: ='Balance Sheet'!C20 -> 2321.36 | D13: ='Balance Sheet'!D20 -> 118276.53 | E13: ='Balance Sheet'!E20 -> 5900.04 | F13: ='Balance Sheet'!F20 -> 3828.56 | G13: =G14*'Revenue BuildUp'!G$10 -> 71213.189 | H13: =H14*'Revenue BuildUp'!H$10 -> 100397.96 | I13: =I14*'Revenue BuildUp'!I$10 -> 133314.23 | J13: =J14*'Revenue BuildUp'!J$10 -> 168280.74 | K13: =K14*'Revenue BuildUp'!K$10 -> 203590.94
B14: % of Revenue | C14: =C13/'Revenue BuildUp'!C$10 -> 0.0044946366 | D14: =D13/'Revenue BuildUp'!D$10 -> 0.15050357 | E14: =E13/'Revenue BuildUp'!E$10 -> 0.0044225793 | F14: =F13/'Revenue BuildUp'!F$10 -> 0.003307577 | G14: =AVERAGE(C14:F14) -> 0.040682091 | H14: =G14 -> 0.040682091 | I14: =H14 -> 0.040682091 | J14: =I14 -> 0.040682091 | K14: =J14 -> 0.040682091
B17: Current Assets:
B18: Investments | C18: ='Balance Sheet'!C26 -> 12204 | D18: ='Balance Sheet'!D26 -> 55036.14 | E18: ='Balance Sheet'!E26 -> 0 | F18: ='Balance Sheet'!F26 -> 0 | G18: =G19*'Revenue BuildUp'!G$10 -> 0 | H18: =H19*'Revenue BuildUp'!H$10 -> 0 | I18: =I19*'Revenue BuildUp'!I$10 -> 0 | J18: =J19*'Revenue BuildUp'!J$10 -> 0 | K18: =K19*'Revenue BuildUp'!K$10 -> 0
B19: % of Revenue | C19: =C18/'Revenue BuildUp'!C$10 -> 0.023629486 | D19: =D18/'Revenue BuildUp'!D$10 -> 0.070031946 | E19: =E18/'Revenue BuildUp'!E$10 -> 0 | F19: =F18/'Revenue BuildUp'!F$10 -> 0 | G19: =F19 -> 0 | H19: =G19 -> 0 | I19: =H19 -> 0 | J19: =I19 -> 0 | K19: =J19 -> 0
B20: Others Current Financial Assets | C20: ='Balance Sheet'!C30 -> 19591.9 | D20: ='Balance Sheet'!D30 -> 33844.36 | E20: ='Balance Sheet'!E30 -> 33718.27 | F20: ='Balance Sheet'!F30 -> 50419.05 | G20: =G21*'Revenue BuildUp'!G$10 -> 65569.841 | H20: =H21*'Revenue BuildUp'!H$10 -> 92441.838 | I20: =I21*'Revenue BuildUp'!I$10 -> 122749.64 | J20: =J21*'Revenue BuildUp'!J$10 -> 154945.2 | K20: =K21*'Revenue BuildUp'!K$10 -> 187457.21
B21: % of Revenue | C21: =C20/'Revenue BuildUp'!C$10 -> 0.037934 | D21: =D20/'Revenue BuildUp'!D$10 -> 0.043066 | E21: =E20/'Revenue BuildUp'!E$10 -> 0.025274697 | F21: =F20/'Revenue BuildUp'!F$10 -> 0.043558124 | G21: =AVERAGE(C21:F21) -> 0.037458205 | H21: =G21 -> 0.037458205 | I21: =H21 -> 0.037458205 | J21: =I21 -> 0.037458205 | K21: =J21 -> 0.037458205
B22: Other Current Assets | C22: ='Balance Sheet'!C31 -> 47238.04 | D22: ='Balance Sheet'!D31 -> 45080.39 | E22: ='Balance Sheet'!E31 -> 64048.36 | F22: ='Balance Sheet'!F31 -> 58314.22 | G22: =G23*'Revenue BuildUp'!G$10 -> 108186.15 | H22: =H23*'Revenue BuildUp'!H$10 -> 152523.27 | I22: =I23*'Revenue BuildUp'!I$10 -> 202529.25 | J22: =J23*'Revenue BuildUp'!J$10 -> 255649.92 | K22: =K23*'Revenue BuildUp'!K$10 -> 309292.72
B23: % of Revenue | C23: =C22/'Revenue BuildUp'!C$10 -> 0.091462686 | D23: =D22/'Revenue BuildUp'!D$10 -> 0.057363533 | E23: =E22/'Revenue BuildUp'!E$10 -> 0.048009666 | F23: =F22/'Revenue BuildUp'!F$10 -> 0.050378934 | G23: =AVERAGE(C23:F23) -> 0.061803705 | H23: =G23 -> 0.061803705 | I23: =H23 -> 0.061803705 | J23: =I23 -> 0.061803705 | K23: =J23 -> 0.061803705
B24: Assets classified as held for sale | C24: ='Balance Sheet'!C32 -> 24.32 | D24: ='Balance Sheet'!D32 -> 23.96 | E24: ='Balance Sheet'!E32 -> 23.26 | F24: ='Balance Sheet'!F32 -> 23.26 | G24: =G25*'Revenue BuildUp'!G$10 -> 50.373205 | H24: =H25*'Revenue BuildUp'!H$10 -> 71.017278 | I24: =I25*'Revenue BuildUp'!I$10 -> 94.300862 | J24: =J25*'Revenue BuildUp'!J$10 -> 119.0347 | K24: =K25*'Revenue BuildUp'!K$10 -> 144.01164
B25: % of Revenue | C25: =C24/'Revenue BuildUp'!C$10 -> 4.7088586e-05 | D25: =D24/'Revenue BuildUp'!D$10 -> 3.0488429e-05 | E25: =E24/'Revenue BuildUp'!E$10 -> 1.7435338e-05 | F25: =F24/'Revenue BuildUp'!F$10 -> 2.0094824e-05 | G25: =AVERAGE(C25:F25) -> 2.8776794e-05 | H25: =G25 -> 2.8776794e-05 | I25: =H25 -> 2.8776794e-05 | J25: =I25 -> 2.8776794e-05 | K25: =J25 -> 2.8776794e-05
B27: LIABILITIES
B28: Non-Current Liabilities:
B29: (i) Borrowings | C29: ='Balance Sheet'!C47 -> 11341.13 | D29: ='Balance Sheet'!D47 -> 52817.08 | E29: ='Balance Sheet'!E47 -> 61188.79 | F29: ='Balance Sheet'!F47 -> 67650.58 | G29: =G30*'Revenue BuildUp'!G$10 -> 84669.864 | H29: =H30*'Revenue BuildUp'!H$10 -> 119369.48 | I29: =I30*'Revenue BuildUp'!I$10 -> 158505.72 | J29: =J30*'Revenue BuildUp'!J$10 -> 200079.62 | K29: =K30*'Revenue BuildUp'!K$10 -> 242062.15
B30: % of Revenue | C30: =C29/'Revenue BuildUp'!C$10 -> 0.02195879 | D30: =D29/'Revenue BuildUp'!D$10 -> 0.067208254 | E30: =E29/'Revenue BuildUp'!E$10 -> 0.045866176 | F30: =F29/'Revenue BuildUp'!F$10 -> 0.058444821 | G30: =AVERAGE(C30:F30) -> 0.04836951 | H30: =G30 -> 0.04836951 | I30: =H30 -> 0.04836951 | J30: =I30 -> 0.04836951 | K30: =J30 -> 0.04836951
B31: (ii) Lease Liabilities | C31: ='Balance Sheet'!C48 -> 0 | D31: ='Balance Sheet'!D48 -> 0 | E31: ='Balance Sheet'!E48 -> 1603.78 | F31: ='Balance Sheet'!F48 -> 1722.29 | G31: =G32*'Revenue BuildUp'!G$10 -> 1177.2385 | H31: =H32*'Revenue BuildUp'!H$10 -> 1659.6974 | I31: =I32*'Revenue BuildUp'!I$10 -> 2203.8424 | J31: =J32*'Revenue BuildUp'!J$10 -> 2781.8804 | K31: =K32*'Revenue BuildUp'!K$10 -> 3365.5999
B32: % of Revenue | C32: =C31/'Revenue BuildUp'!C$10 -> 0 | D32: =D31/'Revenue BuildUp'!D$10 -> 0 | E32: =E31/'Revenue BuildUp'!E$10 -> 0.0012021688 | F32: =F31/'Revenue BuildUp'!F$10 -> 0.0014879241 | G32: =AVERAGE(C32:F32) -> 0.00067252324 | H32: =G32 -> 0.00067252324 | I32: =H32 -> 0.00067252324 | J32: =I32 -> 0.00067252324 | K32: =J32 -> 0.00067252324
B33: Other financial liabilities | C33: ='Balance Sheet'!C49 -> 10.05 | D33: ='Balance Sheet'!D49 -> 286.71 | E33: ='Balance Sheet'!E49 -> 180.42 | F33: ='Balance Sheet'!F49 -> 0 | G33: =G34*'Revenue BuildUp'!G$10 -> 227.35646 | H33: =H34*'Revenue BuildUp'!H$10 -> 320.53226 | I33: =I34*'Revenue BuildUp'!I$10 -> 425.62133 | J33: =J34*'Revenue BuildUp'!J$10 -> 537.25601 | K33: =K34*'Revenue BuildUp'!K$10 -> 649.98797
B34: % of Revenue | C34: =C33/'Revenue BuildUp'!C$10 -> 1.9458894e-05 | D34: =D33/'Revenue BuildUp'!D$10 -> 0.00036483044 | E34: =E33/'Revenue BuildUp'!E$10 -> 0.00013524006 | F34: =F33/'Revenue BuildUp'!F$10 -> 0 | G34: =AVERAGE(C34:F34) -> 0.00012988235 | H34: =G34 -> 0.00012988235 | I34: =H34 -> 0.00012988235 | J34: =I34 -> 0.00012988235 | K34: =J34 -> 0.00012988235
B35: Provisions | C35: ='Balance Sheet'!C50 -> 1974.99 | D35: ='Balance Sheet'!D50 -> 2654.83 | E35: ='Balance Sheet'!E50 -> 2379.21 | F35: ='Balance Sheet'!F50 -> 2621.4 | G35: =G36*'Revenue BuildUp'!G$10 -> 4923.3534 | H35: =H36*'Revenue BuildUp'!H$10 -> 6941.0545 | I35: =I36*'Revenue BuildUp'!I$10 -> 9216.7348 | J35: =J36*'Revenue BuildUp'!J$10 -> 11634.159 | K35: =K36*'Revenue BuildUp'!K$10 -> 14075.345
B36: % of Revenue | C36: =C35/'Revenue BuildUp'!C$10 -> 0.0038239921 | D36: =D35/'Revenue BuildUp'!D$10 -> 0.0033781968 | E36: =E35/'Revenue BuildUp'!E$10 -> 0.0017834192 | F36: =F35/'Revenue BuildUp'!F$10 -> 0.002264685 | G36: =AVERAGE(C36:F36) -> 0.0028125733 | H36: =G36 -> 0.0028125733 | I36: =H36 -> 0.0028125733 | J36: =I36 -> 0.0028125733 | K36: =J36 -> 0.0028125733
B37: Deferred Tax Liabilities (Net) | C37: ='Balance Sheet'!C51 -> 9301.23 | D37: ='Balance Sheet'!D51 -> 9218.11 | E37: ='Balance Sheet'!E51 -> 10778.02 | F37: ='Balance Sheet'!F51 -> 15085.16 | G37: =G38*'Revenue BuildUp'!G$10 -> 22253.129 | H37: =H38*'Revenue BuildUp'!H$10 -> 31372.962 | I37: =I38*'Revenue BuildUp'!I$10 -> 41658.838 | J37: =J38*'Revenue BuildUp'!J$10 -> 52585.385 | K37: =K38*'Revenue BuildUp'!K$10 -> 63619.331
B38: % of Revenue | C38: =C37/'Revenue BuildUp'!C$10 -> 0.018009119 | D38: =D37/'Revenue BuildUp'!D$10 -> 0.011729787 | E38: =E37/'Revenue BuildUp'!E$10 -> 0.0080790381 | F38: =F37/'Revenue BuildUp'!F$10 -> 0.013032401 | G38: =AVERAGE(C38:F38) -> 0.012712586 | H38: =G38 -> 0.012712586 | I38: =H38 -> 0.012712586 | J38: =I38 -> 0.012712586 | K38: =J38 -> 0.012712586
B40: Current Liabilities:
B41: (i) Borrowings | C41: ='Balance Sheet'!C56 -> 113776.12 | D41: ='Balance Sheet'!D56 -> 242612.49 | E41: ='Balance Sheet'!E56 -> 401921.53 | F41: ='Balance Sheet'!F56 -> 331786.96 | G41: =G42*'Revenue BuildUp'!G$10 -> 488788.34 | H41: =H42*'Revenue BuildUp'!H$10 -> 689104.81 | I41: =I42*'Revenue BuildUp'!I$10 -> 915033.34 | J41: =J42*'Revenue BuildUp'!J$10 -> 1155034.1 | K41: =K42*'Revenue BuildUp'!K$10 -> 1397394
B42: % of Revenue | C42: =C41/'Revenue BuildUp'!C$10 -> 0.22029427 | D42: =D41/'Revenue BuildUp'!D$10 -> 0.3087176 | E42: =E41/'Revenue BuildUp'!E$10 -> 0.3012742 | F42: =F41/'Revenue BuildUp'!F$10 -> 0.28663804 | G42: =AVERAGE(C42:F42) -> 0.27923103 | H42: =G42 -> 0.27923103 | I42: =H42 -> 0.27923103 | J42: =I42 -> 0.27923103 | K42: =J42 -> 0.27923103
B43: (ii) Lease Liabilities | C43: ='Balance Sheet'!C57 -> 0 | D43: ='Balance Sheet'!D57 -> 0 | E43: ='Balance Sheet'!E57 -> 77.32 | F43: ='Balance Sheet'!F57 -> 210.89 | G43: =G44*'Revenue BuildUp'!G$10 -> 105.09461 | H43: =H44*'Revenue BuildUp'!H$10 -> 148.16475 | I43: =I44*'Revenue BuildUp'!I$10 -> 196.74175 | J43: =J44*'Revenue BuildUp'!J$10 -> 248.34444 | K43: =K44*'Revenue BuildUp'!K$10 -> 300.45434
B44: % of Revenue | C44: =C43/'Revenue BuildUp'!C$10 -> 0 | D44: =D43/'Revenue BuildUp'!D$10 -> 0 | E44: =E43/'Revenue BuildUp'!E$10 -> 5.7957883e-05 | F44: =F43/'Revenue BuildUp'!F$10 -> 0.0001821925 | G44: =AVERAGE(C44:F44) -> 6.0037595e-05 | H44: =G44 -> 6.0037595e-05 | I44: =H44 -> 6.0037595e-05 | J44: =I44 -> 6.0037595e-05 | K44: =J44 -> 6.0037595e-05
B45: (iv)Other Financial Liabilities | C45: ='Balance Sheet'!C61 -> 8245.64 | D45: ='Balance Sheet'!D61 -> 7766.76 | E45: ='Balance Sheet'!E61 -> 24003.11 | F45: ='Balance Sheet'!F61 -> 22455.43 | G45: =G46*'Revenue BuildUp'!G$10 -> 27675.248 | H45: =H46*'Revenue BuildUp'!H$10 -> 39017.188 | I45: =I46*'Revenue BuildUp'!I$10 -> 51809.286 | J45: =J46*'Revenue BuildUp'!J$10 -> 65398.157 | K45: =K46*'Revenue BuildUp'!K$10 -> 79120.595
B46: % of Revenue | C46: =C45/'Revenue BuildUp'!C$10 -> 0.015965277 | D46: =D45/'Revenue BuildUp'!D$10 -> 0.0098829845 | E46: =E45/'Revenue BuildUp'!E$10 -> 0.017992362 | F46: =F45/'Revenue BuildUp'!F$10 -> 0.019399739 | G46: =AVERAGE(C46:F46) -> 0.015810091 | H46: =G46 -> 0.015810091 | I46: =H46 -> 0.015810091 | J46: =I46 -> 0.015810091 | K46: =J46 -> 0.015810091
B47: Other Current Liabilities | C47: ='Balance Sheet'!C62 -> 12638.96 | D47: ='Balance Sheet'!D62 -> 14900.85 | E47: ='Balance Sheet'!E62 -> 11554.5 | F47: ='Balance Sheet'!F62 -> 12020.43 | G47: =G48*'Revenue BuildUp'!G$10 -> 27341.782 | H47: =H48*'Revenue BuildUp'!H$10 -> 38547.06 | I47: =I48*'Revenue BuildUp'!I$10 -> 51185.022 | J47: =J48*'Revenue BuildUp'!J$10 -> 64610.158 | K47: =K48*'Revenue BuildUp'!K$10 -> 78167.251
B48: % of Revenue | C48: =C47/'Revenue BuildUp'!C$10 -> 0.02447166 | D48: =D47/'Revenue BuildUp'!D$10 -> 0.018960914 | E48: =E47/'Revenue BuildUp'!E$10 -> 0.0086610755 | F48: =F47/'Revenue BuildUp'!F$10 -> 0.010384713 | G48: =AVERAGE(C48:F48) -> 0.015619591 | H48: =G48 -> 0.015619591 | I48: =H48 -> 0.015619591 | J48: =I48 -> 0.015619591 | K48: =J48 -> 0.015619591
B49: Provisions | C49: ='Balance Sheet'!C63 -> 8301.55 | D49: ='Balance Sheet'!D63 -> 7524.57 | E49: ='Balance Sheet'!E63 -> 9000.56 | F49: ='Balance Sheet'!F63 -> 7284.9 | G49: =G50*'Revenue BuildUp'!G$10 -> 16930.906 | H49: =H50*'Revenue BuildUp'!H$10 -> 23869.573 | I49: =I50*'Revenue BuildUp'!I$10 -> 31695.403 | J49: =J50*'Revenue BuildUp'!J$10 -> 40008.677 | K49: =K50*'Revenue BuildUp'!K$10 -> 48403.663
B50: % of Revenue | C50: =C49/'Revenue BuildUp'!C$10 -> 0.01607353 | D50: =D49/'Revenue BuildUp'!D$10 -> 0.0095748045 | E50: =E49/'Revenue BuildUp'!E$10 -> 0.0067466814 | F50: =F49/'Revenue BuildUp'!F$10 -> 0.006293585 | G50: =AVERAGE(C50:F50) -> 0.0096721503 | H50: =G50 -> 0.0096721503 | I50: =H50 -> 0.0096721503 | J50: =I50 -> 0.0096721503 | K50: =J50 -> 0.0096721503
B51: Current tax liabilities | C51: ='Balance Sheet'!C64 -> 22.75 | D51: ='Balance Sheet'!D64 -> 5197.08 | E51: ='Balance Sheet'!E64 -> 1294.95 | F51: ='Balance Sheet'!F64 -> 22.75 | G51: =G52*'Revenue BuildUp'!G$10 -> 3346.7062 | H51: =H52*'Revenue BuildUp'!H$10 -> 4718.2617 | I51: =I52*'Revenue BuildUp'!I$10 -> 6265.1816 | J51: =J52*'Revenue BuildUp'!J$10 -> 7908.4536 | K51: =K52*'Revenue BuildUp'!K$10 -> 9567.8775
B52: % of Revenue | C52: =C51/'Revenue BuildUp'!C$10 -> 4.4048739e-05 | D52: =D51/'Revenue BuildUp'!D$10 -> 0.0066131387 | E52: =E51/'Revenue BuildUp'!E$10 -> 0.00097067461 | F52: =F51/'Revenue BuildUp'!F$10 -> 1.9654224e-05 | G52: =AVERAGE(C52:F52) -> 0.0019118791 | H52: =G52 -> 0.0019118791 | I52: =H52 -> 0.0019118791 | J52: =I52 -> 0.0019118791 | K52: =J52 -> 0.0019118791

Sheet FAS
B6: Fixed Assets Schedules
B8: Particulars | C8: 2021 | D8: =C8+1 -> 2022 | E8: =D8+1 -> 2023 | F8: =E8+1 -> 2024 | G8: =F8+1 -> 2025 | H8: =G8+1 -> 2026 | I8: =H8+1 -> 2027 | J8: =I8+1 -> 2028 | K8: =J8+1 -> 2029
B10: PPE
B11: Gross Opening PPE | C11: 149172.97 | D11: =C15 -> 158441.78 | E11: =D15 -> 170563.75 | F11: =E15 -> 340846.44 | G11: =F15 -> 416270.26 | H11: =G15 -> 488298.33 | I11: =H15 -> 560686.54 | J11: =I15 -> 633436.69 | K11: =J15 -> 706550.59
B12: Additions during the year | C12: 9544.83 | D12: 13319.39 | E12: 23144.36 | F12: 71669.72 | G12: =F12*(1+Assumption!$C$14) -> 72028.069 | H12: =G12*(1+Assumption!$C$14) -> 72388.209 | I12: =H12*(1+Assumption!$C$14) -> 72750.15 | J12: =I12*(1+Assumption!$C$14) -> 73113.901 | K12: =J12*(1+Assumption!$C$14) -> 73479.47
B13: Disposals/ discard during the year | C13: 974.64 | D13: 1685.79 | E13: 2174.24 | F13: 3595.64 | G13: 0 | H13: 0 | I13: 0 | J13: 0 | K13: 0
B14: Adjustment | C14: 698.62 | D14: 488.37 | E14: 149312.57 | F14: 7349.74 | G14: 0 | H14: 0 | I14: 0 | J14: 0 | K14: 0
B15: Gross Closing PPE | C15: =SUM(C11:C12)-C13+C14 -> 158441.78 | D15: =SUM(D11:D12)-D13+D14 -> 170563.75 | E15: =SUM(E11:E12)-E13+E14 -> 340846.44 | F15: =F11+F12-F13+F14 -> 416270.26 | G15: =G11+G12-G13+G14 -> 488298.33 | H15: =H11+H12-H13+H14 -> 560686.54 | I15: =I11+I12-I13+I14 -> 633436.69 | J15: =J11+J12-J13+J14 -> 706550.59 | K15: =K11+K12-K13+K14 -> 780030.06
B16: Accumulated depreciation | C16: 27905.6 | D16: =C19 -> 35931.36 | E16: =D19 -> 44589.91 | F16: =E19 -> 61275.43 | G16: =F19 -> 80952.37 | H16: =G19 -> 105903.14 | I16: =H19 -> 134356.89 | J16: =I19 -> 166079.78 | K16: =J19 -> 200855.47
B17: Charge for the year | C17: 8299.72 | D17: 9016.88 | E17: 17310.83 | F17: 20802.68 | G17: =F17/E20*F20 -> 24950.766 | H17: =G17/F20*G20 -> 28453.754 | I17: =H17/G20*H20 -> 31722.886 | J17: =I17/H20*I20 -> 34775.695 | K17: =J17/I20*J20 -> 37628.414
B18: Deductions | C18: 273.96 | D18: 358.33 | E18: 625.31 | F18: 1125.74 | G18: 0 | H18: 0 | I18: 0 | J18: 0 | K18: 0
B19: Total | C19: =C16+C17-C18 -> 35931.36 | D19: =D16+D17-D18 -> 44589.91 | E19: =E16+E17-E18 -> 61275.43 | F19: =F16+F17-F18 -> 80952.37 | G19: =G16+G17-G18 -> 105903.14 | H19: =H16+H17-H18 -> 134356.89 | I19: =I16+I17-I18 -> 166079.78 | J19: =J16+J17-J18 -> 200855.47 | K19: =K16+K17-K18 -> 238483.89
B20: Net PPE | C20: =C15-C19 -> 122510.42 | D20: =D15-D19 -> 125973.84 | E20: =E15-E19 -> 279571.01 | F20: =F15-F19 -> 335317.89 | G20: =G15-G19 -> 382395.19 | H20: =H15-H19 -> 426329.65 | I20: =I15-I19 -> 467356.91 | J20: =J15-J19 -> 505695.12 | K20: =K15-K19 -> 541546.17
B22: Intangible assets
B23: Gross Opening | C23: 413.52 | D23: =C27 -> 421.36 | E23: =D27 -> 425.88 | F23: =E27 -> 606.25 | G23: =F27 -> 664.62 | H23: =G27 -> 723.28185 | I23: =H27 -> 782.23701 | J23: =I27 -> 841.48694 | K23: =J27 -> 901.03313
B24: Additions during the year | C24: 7.84 | D24: 4.52 | E24: 104.24 | F24: 58.37 | G24: =F24*(1+Assumption!$C$14) -> 58.66185 | H24: =G24*(1+Assumption!$C$14) -> 58.955159 | I24: =H24*(1+Assumption!$C$14) -> 59.249935 | J24: =I24*(1+Assumption!$C$14) -> 59.546185 | K24: =J24*(1+Assumption!$C$14) -> 59.843916
B25: Disposals/ discard during the year | C25: 0 | D25: 0 | E25: 0 | F25: 0 | G25: 0 | H25: 0 | I25: 0 | J25: 0 | K25: 0
B26: Adjustment | C26: 0 | D26: 0 | E26: 76.13 | F26: 0 | G26: 0 | H26: 0 | I26: 0 | J26: 0 | K26: 0
B27: Gross Closing | C27: =SUM(C23:C24)-C25+C26 -> 421.36 | D27: =SUM(D23:D24)-D25+D26 -> 425.88 | E27: =SUM(E23:E24)-E25+E26 -> 606.25 | F27: =SUM(F23:F24)-F25+F26 -> 664.62 | G27: =SUM(G23:G24)-G25+G26 -> 723.28185 | H27: =SUM(H23:H24)-H25+H26 -> 782.23701 | I27: =SUM(I23:I24)-I25+I26 -> 841.48694 | J27: =SUM(J23:J24)-J25+J26 -> 901.03313 | K27: =SUM(K23:K24)-K25+K26 -> 960.87704
B28: Accumulated depreciation | C28: 277.72 | D28: =C31 -> 310.81 | E28: =D31 -> 339.65 | F28: =E31 -> 428.41 | G28: =F31 -> 480.12 | H28: =G31 -> 533.76651 | I28: =H31 -> 588.87131 | J28: =I31 -> 645.09567 | K28: =J31 -> 702.19977
B29: Charge for the year | C29: 33.09 | D29: 28.84 | E29: 88.76 | F29: 51.71 | G29: =F29/E32*F32 -> 53.646508 | H29: =G29/F32*G32 -> 55.104804 | I29: =H29/G32*H32 -> 56.22436 | J29: =I29/H32*I32 -> 57.104097 | K29: =J29/I32*J32 -> 57.814176
B30: Deductions
B31: Total | C31: =C28+C29-C30 -> 310.81 | D31: =D28+D29-D30 -> 339.65 | E31: =E28+E29-E30 -> 428.41 | F31: =F28+F29-F30 -> 480.12 | G31: =G28+G29-G30 -> 533.76651 | H31: =H28+H29-H30 -> 588.87131 | I31: =I28+I29-I30 -> 645.09567 | J31: =J28+J29-J30 -> 702.19977 | K31: =K28+K29-K30 -> 760.01395
B32: Net | C32: =C27-C31 -> 110.55 | D32: =D27-D31 -> 86.23 | E32: =E27-E31 -> 177.84 | F32: =F27-F31 -> 184.5 | G32: =G27-G31 -> 189.51534 | H32: =H27-H31 -> 193.3657 | I32: =I27-I31 -> 196.39127 | J32: =J27-J31 -> 198.83336 | K32: =K27-K31 -> 200.8631
B35: RIGHT-OF-USE ASSETS
B36: Gross Opening | C36: 0 | D36: 0 | E36: 1497.44 | F36: =E40 -> 1734.99 | G36: =F40 -> 2118.89 | H36: =G40 -> 2504.7095 | I36: =H40 -> 2892.4581 | J36: =I40 -> 3282.1454 | K36: =J40 -> 3673.7812
B37: Additions during the year | C37: 0 | D37: 0 | E37: 237.55 | F37: 383.9 | G37: =F37*(1+Assumption!$C$14) -> 385.8195 | H37: =G37*(1+Assumption!$C$14) -> 387.7486 | I37: =H37*(1+Assumption!$C$14) -> 389.68734 | J37: =I37*(1+Assumption!$C$14) -> 391.63578 | K37: =J37*(1+Assumption!$C$14) -> 393.59396
B38: Disposals/ discard during the year | C38: 0 | D38: 0 | E38: 0 | F38: 0 | G38: 0 | H38: 0 | I38: 0 | J38: 0 | K38: 0
B39: Adjustment | C39: 0 | D39: 0 | E39: 0 | F39: 0 | G39: 0 | H39: 0 | I39: 0 | J39: 0 | K39: 0
B40: Gross Closing | C40: 0 | D40: 0 | E40: =SUM(E36:E37)-E38+E39 -> 1734.99 | F40: =SUM(F36:F37)-F38+F39 -> 2118.89 | G40: =SUM(G36:G37)-G38+G39 -> 2504.7095 | H40: =SUM(H36:H37)-H38+H39 -> 2892.4581 | I40: =SUM(I36:I37)-I38+I39 -> 3282.1454 | J40: =SUM(J36:J37)-J38+J39 -> 3673.7812 | K40: =SUM(K36:K37)-K38+K39 -> 4067.3752
B41: Accumulated depreciation | C41: 0 | D41: 0 | E41: 0 | F41: =E44 -> 115.72 | G41: =F44 -> 328.36 | H41: =G44 -> 563.48959 | I41: =H44 -> 818.40755 | J41: =I44 -> 1090.7686 | K41: =J44 -> 1378.5368
B42: Charge for the year | C42: 0 | D42: 0 | E42: 115.72 | F42: 212.64 | G42: =F42/E45*F45 -> 235.12959 | H42: =G42/F45*G45 -> 254.91796 | I42: =H42/G45*H45 -> 272.36107 | J42: =I42/H45*I45 -> 287.76817 | K42: =J42/I45*J45 -> 301.4079
B43: Deductions | C43: 0 | D43: 0 | E43: 0 | F43: 0 | G43: 0 | H43: 0 | I43: 0 | J43: 0 | K43: 0
B44: Total | C44: 0 | D44: 0 | E44: =E41+E42-E43 -> 115.72 | F44: =F41+F42-F43 -> 328.36 | G44: =G41+G42-G43 -> 563.48959 | H44: =H41+H42-H43 -> 818.40755 | I44: =I41+I42-I43 -> 1090.7686 | J44: =J41+J42-J43 -> 1378.5368 | K44: =K41+K42-K43 -> 1679.9447
B45: Net | C45: 0 | D45: 0 | E45: =E40-E44 -> 1619.27 | F45: =F40-F44 -> 1790.53 | G45: =G40-G44 -> 1941.2199 | H45: =H40-H44 -> 2074.0505 | I45: =I40-I44 -> 2191.3768 | J45: =J40-J44 -> 2295.2444 | K45: =K40-K44 -> 2387.4305
B48: Gross Opening | C48: =C36+C23+C11 -> 149586.49 | D48: =D36+D23+D11 -> 158863.14 | E48: =E36+E23+E11 -> 172487.07 | F48: =F36+F23+F11 -> 343187.68 | G48: =G36+G23+G11 -> 419053.77 | H48: =H36+H23+H11 -> 491526.32 | I48: =I36+I23+I11 -> 564361.23 | J48: =J36+J23+J11 -> 637560.32 | K48: =K36+K23+K11 -> 711125.4
B49: Additions during the year | C49: =C37+C24+C12 -> 9552.67 | D49: =D37+D24+D12 -> 13323.91 | E49: =E37+E24+E12 -> 23486.15 | F49: =F37+F24+F12 -> 72111.99 | G49: =G37+G24+G12 -> 72472.55 | H49: =H37+H24+H12 -> 72834.913 | I49: =I37+I24+I12 -> 73199.087 | J49: =J37+J24+J12 -> 73565.083 | K49: =K37+K24+K12 -> 73932.908
B50: Disposals/ discard during the year | C50: =C38+C25+C13 -> 974.64 | D50: =D38+D25+D13 -> 1685.79 | E50: =E38+E25+E13 -> 2174.24 | F50: =F38+F25+F13 -> 3595.64 | G50: =G38+G25+G13 -> 0 | H50: =H38+H25+H13 -> 0 | I50: =I38+I25+I13 -> 0 | J50: =J38+J25+J13 -> 0 | K50: =K38+K25+K13 -> 0
B51: Adjustment | C51: =C39+C26+C14 -> 698.62 | D51: =D39+D26+D14 -> 488.37 | E51: =E39+E26+E14 -> 149388.7 | F51: =F39+F26+F14 -> 7349.74 | G51: =G39+G26+G14 -> 0 | H51: =H39+H26+H14 -> 0 | I51: =I39+I26+I14 -> 0 | J51: =J39+J26+J14 -> 0 | K51: =K39+K26+K14 -> 0
B52: Gross Closing PPE | C52: =C40+C27+C15 -> 158863.14 | D52: =D40+D27+D15 -> 170989.63 | E52: =E40+E27+E15 -> 343187.68 | F52: =F40+F27+F15 -> 419053.77 | G52: =G40+G27+G15 -> 491526.32 | H52: =H40+H27+H15 -> 564361.23 | I52: =I40+I27+I15 -> 637560.32 | J52: =J40+J27+J15 -> 711125.4 | K52: =K40+K27+K15 -> 785058.31
B53: Accumulated depreciation | C53: =C41+C28+C16 -> 28183.32 | D53: =D41+D28+D16 -> 36242.17 | E53: =E41+E28+E16 -> 44929.56 | F53: =F41+F28+F16 -> 61819.56 | G53: =G41+G28+G16 -> 81760.85 | H53: =H41+H28+H16 -> 107000.39 | I53: =I41+I28+I16 -> 135764.17 | J53: =J41+J28+J16 -> 167815.64 | K53: =K41+K28+K16 -> 202936.21
B54: Charge for the year | C54: =C42+C29+C17 -> 8332.81 | D54: =D42+D29+D17 -> 9045.72 | E54: =E42+E29+E17 -> 17515.31 | F54: =F42+F29+F17 -> 21067.03 | G54: =G42+G29+G17 -> 25239.542 | H54: =H42+H29+H17 -> 28763.777 | I54: =I42+I29+I17 -> 32051.471 | J54: =J42+J29+J17 -> 35120.568 | K54: =K42+K29+K17 -> 37987.636
B55: Deductions | C55: =C43+C30+C18 -> 273.96 | D55: =D43+D30+D18 -> 358.33 | E55: =E43+E30+E18 -> 625.31 | F55: =F43+F30+F18 -> 1125.74 | G55: =G43+G30+G18 -> 0 | H55: =H43+H30+H18 -> 0 | I55: =I43+I30+I18 -> 0 | J55: =J43+J30+J18 -> 0 | K55: =K43+K30+K18 -> 0
B56: Total | C56: =C44+C31+C19 -> 36242.17 | D56: =D44+D31+D19 -> 44929.56 | E56: =E44+E31+E19 -> 61819.56 | F56: =F44+F31+F19 -> 81760.85 | G56: =G44+G31+G19 -> 107000.39 | H56: =H44+H31+H19 -> 135764.17 | I56: =I44+I31+I19 -> 167815.64 | J56: =J44+J31+J19 -> 202936.21 | K56: =K44+K31+K19 -> 240923.84
B57: Net Block | C57: =C45+C32+C20 -> 122620.97 | D57: =D45+D32+D20 -> 126060.07 | E57: =E45+E32+E20 -> 281368.12 | F57: =F45+F32+F20 -> 337292.92 | G57: =G45+G32+G20 -> 384525.93 | H57: =H45+H32+H20 -> 428597.06 | I57: =I45+I32+I20 -> 469744.68 | J57: =J45+J32+J20 -> 508189.19 | K57: =K45+K32+K20 -> 544134.47
B60: Total Fixed Assets - Net Block | C60: =C57 -> 122620.97 | D60: =D57 -> 126060.07 | E60: =E57 -> 281368.12 | F60: =F57 -> 337292.92 | G60: =G57 -> 384525.93 | H60: =H57 -> 428597.06 | I60: =I57 -> 469744.68 | J60: =J57 -> 508189.19 | K60: =K57 -> 544134.47
B61: Depreciation for year | C61: =C54 -> 8332.81 | D61: =D54 -> 9045.72 | E61: =E54 -> 17515.31 | F61: =F54 -> 21067.03 | G61: =G54 -> 25239.542 | H61: =H54 -> 28763.777 | I61: =I54 -> 32051.471 | J61: =J54 -> 35120.568 | K61: =K54 -> 37987.636
B62: Increase in Fixed Assets | D62: =D60+D61-C61 -> 126772.98 | E62: =E60+E61-D61 -> 289837.71 | F62: =F60+F61-E61 -> 340844.64 | G62: =G60+G61-F61 -> 388698.44 | H62: =H60+H61-G61 -> 432121.3 | I62: =I60+I61-H61 -> 473032.37 | J62: =J60+J61-I61 -> 511258.29 | K62: =K60+K61-J61 -> 547001.54
B64: Capital work-in-progress
B65: Opening balance | C65: 14904.45 | D65: =C69 -> 22005.97 | E65: =D69 -> 33629.46 | F65: =E69 -> 69686.32 | G65: =F69 -> 37219.28 | H65: =G69 -> 40467.48 | I65: =H69 -> 43731.921 | J65: =I69 -> 47012.684 | K65: =J69 -> 50309.851
B66: Adjustment | C66: 17352.81 | D66: 25431.25 | E66: 48557.23 | F66: 45264.86 | G66: 0 | H66: 0 | I66: 0 | J66: 0 | K66: 0
B67: Add: Addition during the year | C67: 0 | D67: 0 | E67: 12992.8 | F67: 0 | G67: =AVERAGE(C67:F67) -> 3248.2 | H67: =G67*(1+Assumption!$C$14) -> 3264.441 | I67: =H67*(1+Assumption!$C$14) -> 3280.7632 | J67: =I67*(1+Assumption!$C$14) -> 3297.167 | K67: =J67*(1+Assumption!$C$14) -> 3313.6529
B68: Less: Capitalisation during the year | C68: 10251.29 | D68: 13807.76 | E68: 25493.17 | F68: 77731.9 | G68: 0 | H68: 0 | I68: 0 | J68: 0 | K68: 0
B69: Closing balance | C69: =SUM(C65:C67)-C68 -> 22005.97 | D69: =SUM(D65:D67)-D68 -> 33629.46 | E69: =SUM(E65:E67)-E68 -> 69686.32 | F69: =SUM(F65:F67)-F68 -> 37219.28 | G69: =SUM(G65:G67)-G68 -> 40467.48 | H69: =SUM(H65:H67)-H68 -> 43731.921 | I69: =SUM(I65:I67)-I68 -> 47012.684 | J69: =SUM(J65:J67)-J68 -> 50309.851 | K69: =SUM(K65:K67)-K68 -> 53623.504
B73: Deperciation schedules
B74: PPE Opening | D74: =C77 -> 144626.94 | E74: =D77 -> 159689.53 | F74: =E77 -> 351054.44 | G74: =F77 -> 374512.2 | H74: =G77 -> 424993.41 | I74: =H77 -> 472328.98 | J74: =I77 -> 516757.36 | K74: =J77 -> 558499.05
B75: Plus -Capex | D75: =D77-D74+D76 -> 24108.31 | E75: =E77-E74+E76 -> 208880.22 | F75: =F77-F74+F76 -> 44524.79 | G75: =G77+G76-G74 -> 75720.75 | H75: =H77+H76-H74 -> 76099.354 | I75: =I77+I76-I74 -> 76479.85 | J75: =J77+J76-J74 -> 76862.25 | K75: =K77+K76-K74 -> 77246.561
B76: Less-Dep | C76: =C61 -> 8332.81 | D76: =D61 -> 9045.72 | E76: =E61 -> 17515.31 | F76: =F61 -> 21067.03 | G76: =G61 -> 25239.542 | H76: =H61 -> 28763.777 | I76: =I61 -> 32051.471 | J76: =J61 -> 35120.568 | K76: =K61 -> 37987.636
B77: PPE Closing | C77: =C69+C57 -> 144626.94 | D77: =D69+D57 -> 159689.53 | E77: =E69+E57 -> 351054.44 | F77: =F69+F57 -> 374512.2 | G77: =G69+G57 -> 424993.41 | H77: =H69+H57 -> 472328.98 | I77: =I69+I57 -> 516757.36 | J77: =J69+J57 -> 558499.05 | K77: =K69+K57 -> 597757.97

Sheet P&L Statement
B6: Profit & Loss Statement
B8: Particulars | C8: 2021 | D8: =C8+1 -> 2022 | E8: =D8+1 -> 2023 | F8: =E8+1 -> 2024 | G8: =F8+1 -> 2025 | H8: =G8+1 -> 2026 | I8: =H8+1 -> 2027 | J8: =I8+1 -> 2028 | K8: =J8+1 -> 2029
B9: Revenue | C9: ='Revenue BuildUp'!C10 -> 516473.35 | D9: ='Revenue BuildUp'!D10 -> 785871.92 | E9: ='Revenue BuildUp'!E10 -> 1334072.2 | F9: ='Revenue BuildUp'!F10 -> 1157512 | G9: ='Revenue BuildUp'!G10 -> 1750480.1 | H9: ='Revenue BuildUp'!H10 -> 2467866.2 | I9: ='Revenue BuildUp'!I10 -> 3276975.9 | J9: ='Revenue BuildUp'!J10 -> 4136482.1 | K9: ='Revenue BuildUp'!K10 -> 5004436.6
B10: COGS | C10: =-'cost Build_up'!C21 -> -387115.91 | D10: =-'cost Build_up'!D21 -> -628126.3 | E10: =-'cost Build_up'!E21 -> -1061317.9 | F10: =-'cost Build_up'!F21 -> -899844.32 | G10: =-'cost Build_up'!G21 -> -1366141.6 | H10: =-'cost Build_up'!H21 -> -1926017.2 | I10: =-'cost Build_up'!I21 -> -2557477.3 | J10: =-'cost Build_up'!J21 -> -3228268.9 | K10: =-'cost Build_up'!K21 -> -3905653.7
B11: Gross Profit | C11: =SUM(C9:C10) -> 129357.44 | D11: =SUM(D9:D10) -> 157745.62 | E11: =SUM(E9:E10) -> 272754.28 | F11: =SUM(F9:F10) -> 257667.66 | G11: =SUM(G9:G10) -> 384338.46 | H11: =SUM(H9:H10) -> 541849.02 | I11: =SUM(I9:I10) -> 719498.56 | J11: =SUM(J9:J10) -> 908213.25 | K11: =SUM(K9:K10) -> 1098782.8
B12: Gross Margin | C12: =C11/C9 -> 0.25046295 | D12: =D11/D9 -> 0.20072688 | E12: =E11/E9 -> 0.20445241 | F12: =F11/F9 -> 0.22260475 | G12: =G11/G9 -> 0.21956175 | H12: =H11/H9 -> 0.21956175 | I12: =I11/I9 -> 0.21956175 | J12: =J11/J9 -> 0.21956175 | K12: =K11/K9 -> 0.21956175
B14: Salaries & Benefits | C14: =-'cost Build_up'!C26 -> -13919 | D14: =-'cost Build_up'!D26 -> -13850.44 | E14: =-'cost Build_up'!E26 -> -21320.25 | F14: =-'cost Build_up'!F26 -> -22978.77 | G14: =-'cost Build_up'!G26 -> -35187.965 | H14: =-'cost Build_up'!H26 -> -49608.785 | I14: =-'cost Build_up'!I26 -> -65873.422 | J14: =-'cost Build_up'!J26 -> -83151.125 | K14: =-'cost Build_up'!K26 -> -100598.65
B15: S&G Expenses | C15: =-'cost Build_up'!C29 -> -61213.9 | D15: =-'cost Build_up'!D29 -> -76784.2 | E15: =-'cost Build_up'!E29 -> -171335.01 | F15: =-'cost Build_up'!F29 -> -169885.95 | G15: =-'cost Build_up'!G29 -> -215058.25 | H15: =-'cost Build_up'!H29 -> -303193.96 | I15: =-'cost Build_up'!I29 -> -402598.52 | J15: =-'cost Build_up'!J29 -> -508194.64 | K15: =-'cost Build_up'!K29 -> -614828.68
B16: EBITDA | C16: =SUM(C11,C14:C15) -> 54224.54 | D16: =SUM(D11,D14:D15) -> 67110.98 | E16: =SUM(E11,E14:E15) -> 80099.02 | F16: =SUM(F11,F14:F15) -> 64802.94 | G16: =SUM(G11,G14:G15) -> 134092.25 | H16: =SUM(H11,H14:H15) -> 189046.28 | I16: =SUM(I11,I14:I15) -> 251026.61 | J16: =SUM(J11,J14:J15) -> 316867.48 | K16: =SUM(K11,K14:K15) -> 383355.51
B17: EBITDA Margin | C17: =C16/C9 -> 0.10499001 | D17: =D16/D9 -> 0.085396842 | E17: =E16/E9 -> 0.060040994 | F17: =F16/F9 -> 0.055984682 | G17: =G16/G9 -> 0.076603131 | H17: =H16/H9 -> 0.076603131 | I17: =I16/I9 -> 0.076603131 | J17: =J16/J9 -> 0.076603131 | K17: =K16/K9 -> 0.076603131
B19: Dep & Amo | C19: =-FAS!C76 -> -8332.81 | D19: =-FAS!D76 -> -9045.72 | E19: =-FAS!E76 -> -17515.31 | F19: =-FAS!F76 -> -21067.03 | G19: =-FAS!G76 -> -25239.542 | H19: =-FAS!H76 -> -28763.777 | I19: =-FAS!I76 -> -32051.471 | J19: =-FAS!J76 -> -35120.568 | K19: =-FAS!K76 -> -37987.636
B21: EBIT | C21: =SUM(C16,C19) -> 45891.73 | D21: =SUM(D16,D19) -> 58065.26 | E21: =SUM(E16,E19) -> 62583.71 | F21: =SUM(F16,F19) -> 43735.91 | G21: =SUM(G16,G19) -> 108852.71 | H21: =SUM(H16,H19) -> 160282.5 | I21: =SUM(I16,I19) -> 218975.14 | J21: =SUM(J16,J19) -> 281746.91 | K21: =SUM(K16,K19) -> 345367.87
B22: EBIT Margin | C22: =C21/C9 -> 0.08885595 | D22: =D21/D9 -> 0.073886417 | E22: =E21/E9 -> 0.046911787 | F22: =F21/F9 -> 0.037784412 | G22: =G21/G9 -> 0.062184491 | H22: =H21/H9 -> 0.064947808 | I22: =I21/I9 -> 0.066822323 | J22: =J21/J9 -> 0.068112687 | K22: =K21/K9 -> 0.069012339
B24: Interest Cost | C24: =-'Debt Schedules'!C14 -> -11142.53 | D24: =-'Debt Schedules'!D14 -> -8554.14 | E24: =-'Debt Schedules'!E14 -> -29124.25 | F24: =-'Debt Schedules'!F14 -> -36602.7 | G24: =-'Debt Schedules'!G14 -> -39063.214 | H24: =-'Debt Schedules'!H14 -> -55072.199 | I24: =-'Debt Schedules'!I14 -> -73128.06 | J24: =-'Debt Schedules'!J14 -> -92308.556 | K24: =-'Debt Schedules'!K14 -> -111677.58
B25: Other Income | C25: ='Revenue BuildUp'!C13 -> 1920.6 | D25: ='Revenue BuildUp'!D13 -> 3926.99 | E25: ='Revenue BuildUp'!E13 -> 9107 | F25: ='Revenue BuildUp'!F13 -> 6883.51 | G25: ='Revenue BuildUp'!G13 -> 9403.9942 | H25: ='Revenue BuildUp'!H13 -> 13257.963 | I25: ='Revenue BuildUp'!I13 -> 17604.692 | J25: ='Revenue BuildUp'!J13 -> 22222.163 | K25: ='Revenue BuildUp'!K13 -> 26885.021
B26: Share of net profit/(loss) of associate accounted for using the equity method | C26: ='Revenue BuildUp'!C16 -> -19.5 | D26: ='Revenue BuildUp'!D16 -> 61.12 | E26: ='Revenue BuildUp'!E16 -> 50.52 | F26: ='Revenue BuildUp'!F16 -> 66.7 | G26: ='Revenue BuildUp'!G16 -> 59.301903 | H26: ='Revenue BuildUp'!H16 -> 83.605158 | I26: ='Revenue BuildUp'!I16 -> 111.01578 | J26: ='Revenue BuildUp'!J16 -> 140.13371 | K26: ='Revenue BuildUp'!K16 -> 169.53784
B28: EBT | C28: =SUM(C21,C24:C26) -> 36650.3 | D28: =SUM(D21,D24:D26) -> 53499.23 | E28: =SUM(E21,E24:E26) -> 42616.98 | F28: =SUM(F21,F24:F26) -> 14083.42 | G28: =SUM(G21,G24:G26) -> 79252.793 | H28: =SUM(H21,H24:H26) -> 118551.87 | I28: =SUM(I21,I24:I26) -> 163562.79 | J28: =SUM(J21,J24:J26) -> 211800.66 | K28: =SUM(K21,K24:K26) -> 260744.85
B29: EBT Margin | C29: =C28/C9 -> 0.070962616 | D29: =D28/D9 -> 0.068076271 | E29: =E28/E9 -> 0.031945033 | F29: =F28/F9 -> 0.012166976 | G29: =G28/G9 -> 0.045274891 | H29: =H28/H9 -> 0.048038208 | I29: =I28/I9 -> 0.049912723 | J29: =J28/J9 -> 0.051203087 | K29: =K28/K9 -> 0.052102739
B31: Tax | C31: ='Income statement'!C27 -> 14323.48 | D31: ='Income statement'!D27 -> 13653.91 | E31: ='Income statement'!E27 -> 12197.72 | F31: ='Income statement'!F27 -> 4092.5 | G31: =G28*'cost Build_up'!G35 -> 23030.064 | H31: =H28*'cost Build_up'!H35 -> 34449.979 | I31: =I28*'cost Build_up'!I35 -> 47529.699 | J31: =J28*'cost Build_up'!J35 -> 61547.137 | K31: =K28*'cost Build_up'!K35 -> 75769.828
B33: Net Profit | C33: =C28-C31 -> 22326.82 | D33: =D28-D31 -> 39845.32 | E33: =E28-E31 -> 30419.26 | F33: =F28-F31 -> 9990.92 | G33: =G28-G31 -> 56222.73 | H33: =H28-H31 -> 84101.89 | I33: =I28-I31 -> 116033.09 | J33: =J28-J31 -> 150253.52 | K33: =K28-K31 -> 184975.02
B34: Net Profit Margin | C34: =C33/C9 -> 0.043229375 | D34: =D33/D9 -> 0.050702053 | E34: =E33/E9 -> 0.02280181 | F34: =F33/F9 -> 0.008631375 | G34: =G33/G9 -> 0.032118463 | H34: =H33/H9 -> 0.034078788 | I34: =I33/I9 -> 0.035408588 | J34: =J33/J9 -> 0.036323986 | K34: =K33/K9 -> 0.036962208
B36: EPS in Rs. | C36: =C33/Assumption!$C$21 -> 2.7402315 | D36: =D33/Assumption!$C$21 -> 4.8903248 | E36: =E33/Assumption!$C$21 -> 3.7334388 | F36: =F33/Assumption!$C$21 -> 1.2262129 | G36: =G33/Assumption!$C$21 -> 6.900369 | H36: =H33/Assumption!$C$21 -> 10.322054 | I36: =I33/Assumption!$C$21 -> 14.241058 | J36: =J33/Assumption!$C$21 -> 18.441024 | K36: =K33/Assumption!$C$21 -> 22.702489
B38: Dividend | C38: ='CashFlow '!C57 -> 0 | D38: ='CashFlow '!D57 -> 0 | E38: ='CashFlow '!E57 -> 0 | F38: ='CashFlow '!F57 -> -4073.7 | G38: =-G39*G33 -> -5731.0672 | H38: =-H39*H33 -> -8572.931 | I38: =-I39*I33 -> -11827.84 | J38: =-J39*J33 -> -15316.101 | K38: =-K39*K33 -> -18855.44
B39: Dividend Payout % | C39: =-C38/C33 -> 0 | D39: =-D38/D33 -> 0 | E39: =-E38/E33 -> 0 | F39: =-F38/F33 -> 0.40774023 | G39: =AVERAGE(C39:F39) -> 0.10193506 | H39: =G39 -> 0.10193506 | I39: =H39 -> 0.10193506 | J39: =I39 -> 0.10193506 | K39: =J39 -> 0.10193506
B41: Retained Earning | C41: =C33-C38 -> 22326.82 | D41: =D33-D38 -> 39845.32 | E41: =E33-E38 -> 30419.26 | F41: =F33+F38 -> 5917.22 | G41: =G33+G38 -> 50491.663 | H41: =H33+H38 -> 75528.959 | I41: =I33+I38 -> 104205.25 | J41: =J33+J38 -> 134937.42 | K41: =K33+K38 -> 166119.58
B42: Retained % | C42: =C41/C33 -> 1 | D42: =D41/D33 -> 1 | E42: =E41/E33 -> 1 | F42: =F41/F33 -> 0.59225977 | G42: =G41/G33 -> 0.89806494 | H42: =H41/H33 -> 0.89806494 | I42: =I41/I33 -> 0.89806494 | J42: =J41/J33 -> 0.89806494 | K42: =K41/K33 -> 0.89806494

Sheet Balance_Sheet
B6: BalanceSheet Statement
B8: Particulars | C8: 2021 | D8: =C8+1 -> 2022 | E8: =D8+1 -> 2023 | F8: =E8+1 -> 2024 | G8: =F8+1 -> 2025 | H8: =G8+1 -> 2026 | I8: =H8+1 -> 2027 | J8: =I8+1 -> 2028 | K8: =J8+1 -> 2029
B10: Assets
B11: Non-Current Assets
B12: Property Plant and Equipment | C12: ='Balance Sheet'!C12 -> 122510.42 | D12: ='Balance Sheet'!D12 -> 125973.84 | E12: ='Balance Sheet'!E12 -> 279571.01 | F12: ='Balance Sheet'!F12 -> 335317.89 | G12: =FAS!G20 -> 382395.19 | H12: =FAS!H20 -> 426329.65 | I12: =FAS!I20 -> 467356.91 | J12: =FAS!J20 -> 505695.12 | K12: =FAS!K20 -> 541546.17
B13: Capital Work-in-Progress | C13: ='Balance Sheet'!C13 -> 22005.97 | D13: ='Balance Sheet'!D13 -> 33629.46 | E13: ='Balance Sheet'!E13 -> 69686.32 | F13: ='Balance Sheet'!F13 -> 37219.28 | G13: =FAS!G69 -> 40467.48 | H13: =FAS!H69 -> 43731.921 | I13: =FAS!I69 -> 47012.684 | J13: =FAS!J69 -> 50309.851 | K13: =FAS!K69 -> 53623.504
B14: Right of use Assets | C14: ='Balance Sheet'!C14 -> 0 | D14: ='Balance Sheet'!D14 -> 0 | E14: ='Balance Sheet'!E14 -> 1619.27 | F14: ='Balance Sheet'!F14 -> 1790.53 | G14: =FAS!G45 -> 1941.2199 | H14: =FAS!H45 -> 2074.0505 | I14: =FAS!I45 -> 2191.3768 | J14: =FAS!J45 -> 2295.2444 | K14: =FAS!K45 -> 2387.4305
B15: Goodwill | C15: ='Balance Sheet'!C15 -> 0 | D15: ='Balance Sheet'!D15 -> 0 | E15: ='Balance Sheet'!E15 -> 5806.94 | F15: ='Balance Sheet'!F15 -> 5806.94 | G15: =F15 -> 5806.94 | H15: =G15 -> 5806.94 | I15: =H15 -> 5806.94 | J15: =I15 -> 5806.94 | K15: =J15 -> 5806.94
B16: Intangible Assets | C16: ='Balance Sheet'!C16 -> 110.55 | D16: ='Balance Sheet'!D16 -> 86.23 | E16: ='Balance Sheet'!E16 -> 177.84 | F16: ='Balance Sheet'!F16 -> 184.5 | G16: =FAS!G32 -> 189.51534 | H16: =FAS!H32 -> 193.3657 | I16: =FAS!I32 -> 196.39127 | J16: =FAS!J32 -> 198.83336 | K16: =FAS!K32 -> 200.8631
B17: Equity accounted investment | C17: ='Balance Sheet'!C17 -> 278.52 | D17: ='Balance Sheet'!D17 -> 289.43 | E17: ='Balance Sheet'!E17 -> 315.29 | F17: ='Balance Sheet'!F17 -> 324.63 | G17: =F17 -> 324.63 | H17: =G17 -> 324.63 | I17: =H17 -> 324.63 | J17: =I17 -> 324.63 | K17: =J17 -> 324.63
B19: Other income tax assets | C19: ='Balance Sheet'!C19 -> 1246.99 | D19: ='Balance Sheet'!D19 -> 1236.5 | E19: ='Balance Sheet'!E19 -> 1106.62 | F19: ='Balance Sheet'!F19 -> 5950.43 | G19: ='B_Sheet '!G11 -> 4357.8448 | H19: ='B_Sheet '!H11 -> 6143.7877 | I19: ='B_Sheet '!I11 -> 8158.0777 | J19: ='B_Sheet '!J11 -> 10297.831 | K19: ='B_Sheet '!K11 -> 12458.615
B20: Other Non-Current Assets | C20: ='Balance Sheet'!C20 -> 2321.36 | D20: ='Balance Sheet'!D20 -> 118276.53 | E20: ='Balance Sheet'!E20 -> 5900.04 | F20: ='Balance Sheet'!F20 -> 3828.56 | G20: ='B_Sheet '!G13 -> 71213.189 | H20: ='B_Sheet '!H13 -> 100397.96 | I20: ='B_Sheet '!I13 -> 133314.23 | J20: ='B_Sheet '!J13 -> 168280.74 | K20: ='B_Sheet '!K13 -> 203590.94
B22: Total Non-Current Assets | C22: =SUM(C12:C20) -> 148473.81 | D22: =SUM(D12:D20) -> 279491.99 | E22: =SUM(E12:E20) -> 364183.33 | F22: =SUM(F12:F20) -> 390422.76 | G22: =SUM(G12:G20) -> 506696.01 | H22: =SUM(H12:H20) -> 585002.3 | I22: =SUM(I12:I20) -> 664361.24 | J22: =SUM(J12:J20) -> 743209.19 | K22: =SUM(K12:K20) -> 819939.1
B24: Current Assets:
B25: Inventories | C25: ='Balance Sheet'!C25 -> 89905.36 | D25: ='Balance Sheet'!D25 -> 229322.24 | E25: ='Balance Sheet'!E25 -> 223767.72 | F25: ='Balance Sheet'!F25 -> 183082.95 | G25: ='Working Capital'!G11 -> 345508.68 | H25: ='Working Capital'!H11 -> 487105.92 | I25: ='Working Capital'!I11 -> 646807.5 | J25: ='Working Capital'!J11 -> 816456.31 | K25: ='Working Capital'!K11 -> 987772.62
B26: Investments | C26: ='Balance Sheet'!C26 -> 12204 | D26: ='Balance Sheet'!D26 -> 55036.14 | E26: ='Balance Sheet'!E26 -> 0 | F26: ='Balance Sheet'!F26 -> 0 | G26: ='B_Sheet '!G18 -> 0 | H26: ='B_Sheet '!H18 -> 0 | I26: ='B_Sheet '!I18 -> 0 | J26: ='B_Sheet '!J18 -> 0 | K26: ='B_Sheet '!K18 -> 0
B27: Trade Receivables | C27: ='Balance Sheet'!C27 -> 115559.36 | D27: ='Balance Sheet'!D27 -> 90247.54 | E27: ='Balance Sheet'!E27 -> 368973.75 | F27: ='Balance Sheet'!F27 -> 272047.93 | G27: ='Working Capital'!G12 -> 372060.02 | H27: ='Working Capital'!H12 -> 524538.6 | I27: ='Working Capital'!I12 -> 696512.78 | J27: ='Working Capital'!J12 -> 879198.61 | K27: ='Working Capital'!K12 -> 1063680.1
B28: Cash and Cash Equivalents | C28: ='Balance Sheet'!C28 -> 9152.45 | D28: ='Balance Sheet'!D28 -> 53784.1 | E28: ='Balance Sheet'!E28 -> 4303.42 | F28: ='Balance Sheet'!F28 -> 9071.79 | G28: ='CashFlow '!G64 -> 10769.63 | H28: ='CashFlow '!H64 -> 53232.309 | I28: ='CashFlow '!I64 -> 129086.2 | J28: ='CashFlow '!J64 -> 239338.13 | K28: ='CashFlow '!K64 -> 383394.61
B29: Bank Balances | C29: ='Balance Sheet'!C29 -> 167.32 | D29: ='Balance Sheet'!D29 -> 5987.37 | E29: ='Balance Sheet'!E29 -> 6681.98 | F29: ='Balance Sheet'!F29 -> 2730.57
B30: Others Current Financial Assets | C30: ='Balance Sheet'!C30 -> 19591.9 | D30: ='Balance Sheet'!D30 -> 33844.36 | E30: ='Balance Sheet'!E30 -> 33718.27 | F30: ='Balance Sheet'!F30 -> 50419.05 | G30: ='B_Sheet '!G20 -> 65569.841 | H30: ='B_Sheet '!H20 -> 92441.838 | I30: ='B_Sheet '!I20 -> 122749.64 | J30: ='B_Sheet '!J20 -> 154945.2 | K30: ='B_Sheet '!K20 -> 187457.21
B31: Other Current Assets | C31: ='Balance Sheet'!C31 -> 47238.04 | D31: ='Balance Sheet'!D31 -> 45080.39 | E31: ='Balance Sheet'!E31 -> 64048.36 | F31: ='Balance Sheet'!F31 -> 58314.22 | G31: ='B_Sheet '!G22 -> 108186.15 | H31: ='B_Sheet '!H22 -> 152523.27 | I31: ='B_Sheet '!I22 -> 202529.25 | J31: ='B_Sheet '!J22 -> 255649.92 | K31: ='B_Sheet '!K22 -> 309292.72
B32: Assets classified as held for sale | C32: ='Balance Sheet'!C32 -> 24.32 | D32: ='Balance Sheet'!D32 -> 23.96 | E32: ='Balance Sheet'!E32 -> 23.26 | F32: ='Balance Sheet'!F32 -> 23.26 | G32: ='B_Sheet '!G24 -> 50.373205 | H32: ='B_Sheet '!H24 -> 71.017278 | I32: ='B_Sheet '!I24 -> 94.300862 | J32: ='B_Sheet '!J24 -> 119.0347 | K32: ='B_Sheet '!K24 -> 144.01164
B33: Total Current Assets | C33: =SUM(C25:C32) -> 293842.75 | D33: =SUM(D25:D32) -> 513326.1 | E33: =SUM(E25:E32) -> 701516.76 | F33: =SUM(F25:F32) -> 575689.77 | G33: =SUM(G25:G32) -> 902144.7 | H33: =SUM(H25:H32) -> 1309913 | I33: =SUM(I25:I32) -> 1797779.7 | J33: =SUM(J25:J32) -> 2345707.2 | K33: =SUM(K25:K32) -> 2931741.3
B35: TOTAL ASSETS | C35: =C33+C22 -> 442316.56 | D35: =D33+D22 -> 792818.09 | E35: =E33+E22 -> 1065700.1 | F35: =F33+F22 -> 966112.53 | G35: =G33+G22 -> 1408840.7 | H35: =H33+H22 -> 1894915.3 | I35: =I33+I22 -> 2462140.9 | J35: =J33+J22 -> 3088916.4 | K35: =K33+K22 -> 3751680.4
B37: EQUITY AND LIABILITIES
B38: EQUITY
B39: Equity Share Capital | C39: ='Balance Sheet'!C39 -> 57545 | D39: ='Balance Sheet'!D39 -> 57545 | E39: ='Balance Sheet'!E39 -> 81449.76 | F39: ='Balance Sheet'!F39 -> 81477.86 | G39: =F39 -> 81477.86 | H39: =G39 -> 81477.86 | I39: =H39 -> 81477.86 | J39: =I39 -> 81477.86 | K39: =J39 -> 81477.86
B40: Other Equity | C40: ='Balance Sheet'!C40 -> 125205.97 | D40: ='Balance Sheet'!D40 -> 164954.74 | E40: ='Balance Sheet'!E40 -> 269020.47 | F40: ='Balance Sheet'!F40 -> 274962.15 | G40: =F40+'P&L Statement'!G33+'P&L Statement'!G38-'P&L Statement'!G26 -> 325394.51 | H40: =G40+'P&L Statement'!H33+'P&L Statement'!H38-'P&L Statement'!H26 -> 400839.86 | I40: =H40+'P&L Statement'!I33+'P&L Statement'!I38-'P&L Statement'!I26 -> 504934.1 | J40: =I40+'P&L Statement'!J33+'P&L Statement'!J38-'P&L Statement'!J26 -> 639731.38 | K40: =J40+'P&L Statement'!K33+'P&L Statement'!K38-'P&L Statement'!K26 -> 805681.43
B42: Total Equity | C42: =SUM(C39:C41) -> 182750.97 | D42: =SUM(D39:D41) -> 222499.74 | E42: =SUM(E39:E41) -> 350470.23 | F42: =SUM(F39:F41) -> 356440.01 | G42: =SUM(G39:G41) -> 406872.37 | H42: =SUM(H39:H41) -> 482317.72 | I42: =SUM(I39:I41) -> 586411.96 | J42: =SUM(J39:J41) -> 721209.24 | K42: =SUM(K39:K41) -> 887159.29
B44: LIABILITIES
B45: Non-Current Liabilities:
B46: Financial Liabilities
B47: (i) Borrowings | C47: ='Balance Sheet'!C47 -> 11341.13 | D47: ='Balance Sheet'!D47 -> 52817.08 | E47: ='Balance Sheet'!E47 -> 61188.79 | F47: ='Balance Sheet'!F47 -> 67650.58 | G47: ='B_Sheet '!G29 -> 84669.864 | H47: ='B_Sheet '!H29 -> 119369.48 | I47: ='B_Sheet '!I29 -> 158505.72 | J47: ='B_Sheet '!J29 -> 200079.62 | K47: ='B_Sheet '!K29 -> 242062.15
B48: (ii) Lease Liabilities | C48: ='Balance Sheet'!C48 -> 0 | D48: ='Balance Sheet'!D48 -> 0 | E48: ='Balance Sheet'!E48 -> 1603.78 | F48: ='Balance Sheet'!F48 -> 1722.29 | G48: ='B_Sheet '!G31 -> 1177.2385 | H48: ='B_Sheet '!H31 -> 1659.6974 | I48: ='B_Sheet '!I31 -> 2203.8424 | J48: ='B_Sheet '!J31 -> 2781.8804 | K48: ='B_Sheet '!K31 -> 3365.5999
B49: Other financial liabilities | C49: ='Balance Sheet'!C49 -> 10.05 | D49: ='Balance Sheet'!D49 -> 286.71 | E49: ='Balance Sheet'!E49 -> 180.42 | F49: ='Balance Sheet'!F49 -> 0 | G49: ='B_Sheet '!G33 -> 227.35646 | H49: ='B_Sheet '!H33 -> 320.53226 | I49: ='B_Sheet '!I33 -> 425.62133 | J49: ='B_Sheet '!J33 -> 537.25601 | K49: ='B_Sheet '!K33 -> 649.98797
B50: Provisions | C50: ='Balance Sheet'!C50 -> 1974.99 | D50: ='Balance Sheet'!D50 -> 2654.83 | E50: ='Balance Sheet'!E50 -> 2379.21 | F50: ='Balance Sheet'!F50 -> 2621.4 | G50: ='B_Sheet '!G35 -> 4923.3534 | H50: ='B_Sheet '!H35 -> 6941.0545 | I50: ='B_Sheet '!I35 -> 9216.7348 | J50: ='B_Sheet '!J35 -> 11634.159 | K50: ='B_Sheet '!K35 -> 14075.345
B51: Deferred Tax Liabilities (Net) | C51: ='Balance Sheet'!C51 -> 9301.23 | D51: ='Balance Sheet'!D51 -> 9218.11 | E51: ='Balance Sheet'!E51 -> 10778.02 | F51: ='Balance Sheet'!F51 -> 15085.16 | G51: ='B_Sheet '!G37 -> 22253.129 | H51: ='B_Sheet '!H37 -> 31372.962 | I51: ='B_Sheet '!I37 -> 41658.838 | J51: ='B_Sheet '!J37 -> 52585.385 | K51: ='B_Sheet '!K37 -> 63619.331
B52: Total Non-Current Liabilities | C52: =SUM(C47:C51) -> 22627.4 | D52: =SUM(D47:D51) -> 64976.73 | E52: =SUM(E47:E51) -> 76130.22 | F52: =SUM(F47:F51) -> 87079.43 | G52: =SUM(G47:G51) -> 113250.94 | H52: =SUM(H47:H51) -> 159663.73 | I52: =SUM(I47:I51) -> 212010.76 | J52: =SUM(J47:J51) -> 267618.3 | K52: =SUM(K47:K51) -> 323772.41
B54: Current Liabilities:
B55: Financial Liabilities
B56: (i) Borrowings | C56: ='Balance Sheet'!C56 -> 113776.12 | D56: ='Balance Sheet'!D56 -> 242612.49 | E56: ='Balance Sheet'!E56 -> 401921.53 | F56: ='Balance Sheet'!F56 -> 331786.96 | G56: ='B_Sheet '!G41 -> 488788.34 | H56: ='B_Sheet '!H41 -> 689104.81 | I56: ='B_Sheet '!I41 -> 915033.34 | J56: ='B_Sheet '!J41 -> 1155034.1 | K56: ='B_Sheet '!K41 -> 1397394
B57: (ii) Lease Liabilities | C57: ='Balance Sheet'!C57 -> 0 | D57: ='Balance Sheet'!D57 -> 0 | E57: ='Balance Sheet'!E57 -> 77.32 | F57: ='Balance Sheet'!F57 -> 210.89 | G57: ='B_Sheet '!G43 -> 105.09461 | H57: ='B_Sheet '!H43 -> 148.16475 | I57: ='B_Sheet '!I43 -> 196.74175 | J57: ='B_Sheet '!J43 -> 248.34444 | K57: ='B_Sheet '!K43 -> 300.45434
B58: (iii) Trade Payables
B59: Total outstanding dues of micro enterprises and small enterprises | C59: ='Balance Sheet'!C59 -> 625.56 | D59: ='Balance Sheet'!D59 -> 818.76 | E59: ='Balance Sheet'!E59 -> 667.47 | F59: ='Balance Sheet'!F59 -> 929.88
B60: Total outstanding dues of creditors other than micro enterprises and small enterprises | C60: ='Balance Sheet'!C60 -> 93327.61 | D60: ='Balance Sheet'!D60 -> 226521.11 | E60: ='Balance Sheet'!E60 -> 190580.2 | F60: ='Balance Sheet'!F60 -> 147881.85 | G60: ='Working Capital'!G13 -> 324529.32 | H60: ='Working Capital'!H13 -> 457528.75 | I60: ='Working Capital'!I13 -> 607533.21 | J60: ='Working Capital'!J13 -> 766880.92 | K60: ='Working Capital'!K13 -> 927794.87
B61: (iv)Other Financial Liabilities | C61: ='Balance Sheet'!C61 -> 8245.64 | D61: ='Balance Sheet'!D61 -> 7766.76 | E61: ='Balance Sheet'!E61 -> 24003.11 | F61: ='Balance Sheet'!F61 -> 22455.43 | G61: ='B_Sheet '!G45 -> 27675.248 | H61: ='B_Sheet '!H45 -> 39017.188 | I61: ='B_Sheet '!I45 -> 51809.286 | J61: ='B_Sheet '!J45 -> 65398.157 | K61: ='B_Sheet '!K45 -> 79120.595
B62: Other Current Liabilities | C62: ='Balance Sheet'!C62 -> 12638.96 | D62: ='Balance Sheet'!D62 -> 14900.85 | E62: ='Balance Sheet'!E62 -> 11554.5 | F62: ='Balance Sheet'!F62 -> 12020.43 | G62: ='B_Sheet '!G47 -> 27341.782 | H62: ='B_Sheet '!H47 -> 38547.06 | I62: ='B_Sheet '!I47 -> 51185.022 | J62: ='B_Sheet '!J47 -> 64610.158 | K62: ='B_Sheet '!K47 -> 78167.251
B63: Provisions | C63: ='Balance Sheet'!C63 -> 8301.55 | D63: ='Balance Sheet'!D63 -> 7524.57 | E63: ='Balance Sheet'!E63 -> 9000.56 | F63: ='Balance Sheet'!F63 -> 7284.9 | G63: ='B_Sheet '!G49 -> 16930.906 | H63: ='B_Sheet '!H49 -> 23869.573 | I63: ='B_Sheet '!I49 -> 31695.403 | J63: ='B_Sheet '!J49 -> 40008.677 | K63: ='B_Sheet '!K49 -> 48403.663
B64: Current tax liabilities | C64: ='Balance Sheet'!C64 -> 22.75 | D64: ='Balance Sheet'!D64 -> 5197.08 | E64: ='Balance Sheet'!E64 -> 1294.95 | F64: ='Balance Sheet'!F64 -> 22.75 | G64: ='B_Sheet '!G51 -> 3346.7062 | H64: ='B_Sheet '!H51 -> 4718.2617 | I64: ='B_Sheet '!I51 -> 6265.1816 | J64: ='B_Sheet '!J51 -> 7908.4536 | K64: ='B_Sheet '!K51 -> 9567.8775
B65: Total Current Liabilities | C65: =SUM(C56:C64) -> 236938.19 | D65: =SUM(D56:D64) -> 505341.62 | E65: =SUM(E56:E64) -> 639099.64 | F65: =SUM(F56:F64) -> 522593.09 | G65: =SUM(G56:G64) -> 888717.41 | H65: =SUM(H56:H64) -> 1252933.8 | I65: =SUM(I56:I64) -> 1663718.2 | J65: =SUM(J56:J64) -> 2100088.9 | K65: =SUM(K56:K64) -> 2540748.7
B67: Total Liabilities | C67: =C65+C52 -> 259565.59 | D67: =D65+D52 -> 570318.35 | E67: =E65+E52 -> 715229.86 | F67: =F65+F52 -> 609672.52 | G67: =G65+G52 -> 1001968.3 | H67: =H65+H52 -> 1412597.5 | I67: =I65+I52 -> 1875728.9 | J67: =J65+J52 -> 2367707.2 | K67: =K65+K52 -> 2864521.1
B69: TOTAL EQUITY AND LIABILITIES | C69: =C67+C42 -> 442316.56 | D69: =D67+D42 -> 792818.09 | E69: =E67+E42 -> 1065700.1 | F69: =F67+F42 -> 966112.53 | G69: =G67+G42 -> 1408840.7 | H69: =H67+H42 -> 1894915.3 | I69: =I67+I42 -> 2462140.9 | J69: =J67+J42 -> 3088916.4 | K69: =K67+K42 -> 3751680.4
B71: Check | C71: =C69-C35 -> 0 | D71: =D69-D35 -> 0 | E71: =E69-E35 -> 0 | F71: =F69-F35 -> 0 | G71: =G69-G35 -> 0 | H71: =H69-H35 -> 0 | I71: =I69-I35 -> 0 | J71: =J69-J35 -> 0 | K71: =K69-K35 -> 0

Sheet Equity Market
B8: Equity Market
B10: Date | C10: Close Price | E10: Year | F10: =YEARFRAC(B11,B2486) -> 9.9972222
B11: 42237 | C11: 27366.07 | E11: RRI | F11: =_xlfn.RRI(F10,C11,C2486) -> 0.11582993
B12: 42240 | C12: 25741.56
B13: 42241 | C13: 26032.38
B14: 42242 | C14: 25714.66
B15: 42243 | C15: 26231.19
B16: 42244 | C16: 26392.38
B17: 42247 | C17: 26283.09
B18: 42248 | C18: 25696.44
B19: 42249 | C19: 25453.56
B20: 42250 | C20: 25764.78
B21: 42251 | C21: 25201.9
B22: 42254 | C22: 24893.81
B23: 42255 | C23: 25317.87
... B2486: 45889 | C2486: 81857.84

Sheet Beta
B6: Beta
B9: Date | C9: Sensex | D9: % | F9: Stock | G9: %
C10: Close | D10: Change | F10: Close | G10: Change
B11: 44774 | C11: 59537.07 | F11: 54.25
B12: 44805 | C12: 57426.92 | D12: =C12/C11-1 -> -0.035442624 | F12: 62 | G12: =F12/F11-1 -> 0.14285714 | J12: Beta | K12: =SLOPE(G12:G47,D12:D47) -> 0.4421136
B13: 44835 | C13: 60746.59 | D13: =C13/C12-1 -> 0.057806861 | F13: 59.35 | G13: =F13/F12-1 -> -0.042741935 | J13: Beta | K13: =_xlfn.COVARIANCE.S(G12:G47,D12:D47)/_xlfn.VAR.S(D12:D47) -> 0.4421136
B14: 44866 | C14: 63099.65 | D14: =C14/C13-1 -> 0.038735672 | F14: 56.75 | G14: =F14/F13-1 -> -0.043807919 | J14: Beta | K14: =K34 -> 0.4421136
B15: 44896 | C15: 60840.74 | D15: =C15/C14-1 -> -0.035799089 | F15: 58.9 | G15: =F15/F14-1 -> 0.037885463
B16: 44927 | C16: 59549.9 | D16: =C16/C15-1 -> -0.021216704 | F16: 62.75 | G16: =F16/F15-1 -> 0.065365025
B17: 44958 | C17: 58962.12 | D17: =C17/C16-1 -> -0.0098703776 | F17: 54.45 | G17: =F17/F16-1 -> -0.13227092 | J17: SUMMARY OUTPUT
B18: 44986 | C18: 58991.52 | D18: =C18/C17-1 -> 0.00049862522 | F18: 50.32 | G18: =F18/F17-1 -> -0.075849403
B19: 45017 | C19: 61112.44 | D19: =C19/C18-1 -> 0.035952964 | F19: 51.63 | G19: =F19/F18-1 -> 0.026033386 | J19: Regression Statistics
B20: 45047 | C20: 62622.24 | D20: =C20/C19-1 -> 0.024705281 | F20: 54.02 | G20: =F20/F19-1 -> 0.046290916 | J20: Multiple R | K20: 0.11054372
B21: 45078 | C21: 64718.56 | D21: =C21/C20-1 -> 0.033475647 | F21: 63.18 | G21: =F21/F20-1 -> 0.16956683 | J21: R Square | K21: 0.012219914
B22: 45108 | C22: 66527.67 | D22: =C22/C21-1 -> 0.027953496 | F22: 64.97 | G22: =F22/F21-1 -> 0.028331751 | J22: Adjusted R Square | K22: -0.016832441
B23: 45139 | C23: 64831.41 | D23: =C23/C22-1 -> -0.02549706 | F23: 70.43 | G23: =F23/F22-1 -> 0.084038787 | J23: Standard Error | K23: 0.1353053
B24: 45170 | C24: 65828.41 | D24: =C24/C23-1 -> 0.015378348 | F24: 71.63 | G24: =F24/F23-1 -> 0.017038194 | J24: Observations | K24: 36
B25: 45200 | C25: 63874.93 | D25: =C25/C24-1 -> -0.029675333 | F25: 61.42 | G25: =F25/F24-1 -> -0.14253804
B26: 45231 | C26: 66988.44 | D26: =C26/C25-1 -> 0.04874385 | F26: 65.12 | G26: =F26/F25-1 -> 0.060240964 | J26: ANOVA
B27: 45261 | C27: 72240.26 | D27: =C27/C26-1 -> 0.0783989 | F27: 67.86 | G27: =F27/F26-1 -> 0.042076167 | K27: df | L27: SS | M27: MS | N27: F | O27: Significance F
B28: 45292 | C28: 71752.11 | D28: =C28/C27-1 -> -0.0067573123 | F28: 79.69 | G28: =F28/F27-1 -> 0.1743295 | J28: Regression | K28: 1 | L28: 0.0077004556 | M28: 0.0077004556 | N28: 0.42061699 | O28: 0.52098594
B29: 45323 | C29: 72500.3 | D29: =C29/C28-1 -> 0.010427429 | F29: 76.03 | G29: =F29/F28-1 -> -0.045927971 | J29: Residual | K29: 34 | L29: 0.62245582 | M29: 0.018307524
B30: 45352 | C30: 73651.35 | D30: =C30/C29-1 -> 0.015876486 | F30: 66.39 | G30: =F30/F29-1 -> -0.12679206 | J30: Total | K30: 35 | L30: 0.63015628
B31: 45383 | C31: 74482.78 | D31: =C31/C30-1 -> 0.011288727 | F31: 69.86 | G31: =F31/F30-1 -> 0.052266908
B32: 45413 | C32: 73961.31 | D32: =C32/C31-1 -> -0.0070012156 | F32: 69.9 | G32: =F32/F31-1 -> 0.00057257372 | K32: Coefficients | L32: Standard Error | M32: t Stat | N32: P-value | O32: Lower 95% | P32: Upper 95% | Q32: Lower 95.0% | R32: Upper 95.0%
B33: 45444 | C33: 79032.73 | D33: =C33/C32-1 -> 0.068568553 | F33: 83.47 | G33: =F33/F32-1 -> 0.19413448 | J33: Intercept | K33: 0.042976447 | L33: 0.023434957 | M33: 1.8338607 | N33: 0.07544028 | O33: -0.0046491161 | P33: 0.090602011 | Q33: -0.0046491161 | R33: 0.090602011
B34: 45474 | C34: 81741.34 | D34: =C34/C33-1 -> 0.034272004 | F34: 91.88 | G34: =F34/F33-1 -> 0.10075476 | J34: X Variable 1 | K34: 0.4421136 | L34: 0.68169557 | M34: 0.64854991 | N34: 0.52098594 | O34: -0.94325847 | P34: 1.8274857 | Q34: -0.94325847 | R34: 1.8274857
B35: 45505 | C35: 82365.77 | D35: =C35/C34-1 -> 0.0076390967 | F35: 83.33 | G35: =F35/F34-1 -> -0.09305616
B36: 45536 | C36: 84299.78 | D36: =C36/C35-1 -> 0.023480749 | F36: 82.87 | G36: =F36/F35-1 -> -0.0055202208
B37: 45566 | C37: 79389.06 | D37: =C37/C36-1 -> -0.058253058 | F37: 104.61 | G37: =F37/F36-1 -> 0.2623386
B38: 45597 | C38: 79802.79 | D38: =C38/C37-1 -> 0.0052114233 | F38: 111.1 | G38: =F38/F37-1 -> 0.062039958
B39: 45627 | C39: 78139.01 | D39: =C39/C38-1 -> -0.020848645 | F39: 110.2 | G39: =F39/F38-1 -> -0.0081008101
B40: 45658 | C40: 77500.57 | D40: =C40/C39-1 -> -0.0081705668 | F40: 112.8 | G40: =F40/F39-1 -> 0.023593466
B41: 45689 | C41: 73198.1 | D41: =C41/C40-1 -> -0.055515334 | F41: 86.85 | G41: =F41/F40-1 -> -0.23005319
B42: 45717 | C42: 77414.92 | D42: =C42/C41-1 -> 0.057608326 | F42: 103.29 | G42: =F42/F41-1 -> 0.18929188
B43: 45748 | C43: 80242.24 | D43: =C43/C42-1 -> 0.036521642 | F43: 143.7 | G43: =F43/F42-1 -> 0.39122858
B44: 45778 | C44: 81451.01 | D44: =C44/C43-1 -> 0.015064011 | F44: 173.45 | G44: =F44/F43-1 -> 0.20702853
B45: 45809 | C45: 83606.46 | D45: =C45/C44-1 -> 0.026463146 | F45: 160 | G45: =F45/F44-1 -> -0.077543961
B46: 45839 | C46: 81185.58 | D46: =C46/C45-1 -> -0.028955657 | F46: 215.35 | G46: =F46/F45-1 -> 0.3459375
B47: 45870 | C47: 81644.39 | D47: =C47/C46-1 -> 0.0056513731 | F47: 214.7 | G47: =F47/F46-1 -> -0.0030183422

Sheet Comps Data
C7: Comps Data
C9: Name | D9: CMP Rs. | E9: No. Eq. Shares Cr. | F9: Debt Rs.Cr. | G9: Cash Rs.Cr. | H9: NP Ann Rs.Cr. | I9: Sales Ann Rs.Cr. | J9: Dep Ann Rs.Cr. | K9: EBIT Ann Rs.Cr. | L9: EV / EBITDA | M9: EV Rs.Cr. | N9: Mar Cap Rs.Cr. | O9: Tax 12M Rs.Cr. | P9: P/E
C10: Coromandel Inter | D10: 2466.2 | E10: 29.48 | F10: 780.38 | G10: 3538.34 | H10: 2054.71 | I10: 24085.24 | J10: 290.39 | K10: 2545.58 | L10: 21.49 | M10: 69954.99 | N10: 72712.95 | O10: 736.01 | P10: 36.65
C11: F A C T | D11: 1018.5 | E11: 64.71 | F11: 1804.63 | G11: 2777.37 | H11: 41.23 | I11: 4050.91 | J11: 36.62 | K11: 274.67 | L11: 165.52 | M11: 64931.54 | N11: 65904.28 | O11: 30.97 | P11: 813.22
C12: Chambal Fert. | D12: 559.75 | E12: 40.07 | F12: 98.76 | G12: 236.32 | H12: 1649.39 | I12: 16646.2 | J12: 330.15 | K12: 2400.88 | L12: 7.87 | M12: 22288.97 | N12: 22426.53 | O12: 739.42 | P12: 12.79
C13: R C F | D13: 157.9 | E13: 55.17 | F13: 2762.21 | G13: 1035.74 | H13: 242.45 | I13: 16933.64 | J13: 262.76 | K13: 577.63 | L13: 11.71 | M13: 10437.64 | N13: 8711.17 | O13: 101.02 | P13: 30.73
C14: G S F C | D14: 212.85 | E14: 39.85 | F14: 1.76 | G14: 1907.28 | H14: 591.16 | I14: 9533.96 | J14: 192.02 | K14: 766.36 | L14: 6.34 | M14: 6576.06 | N14: 8481.58 | O14: 185.72 | P14: 13.24
C15: Natl.Fertilizer | D15: 97.78 | E15: 49.06 | F15: 2001.05 | G15: 32.78 | H15: 183.98 | I15: 19794.5 | J15: 373 | K15: 437.48 | L15: 9.13 | M15: 6765.2 | N15: 4796.93 | O15: 27.77 | P15: 31.32
C16: Mangalore Chem. | D16: 358.25 | E16: 11.85 | F16: 741.28 | G16: 132.5 | H16: 143.71 | I16: 3331.9 | J16: 76.12 | K16: 290.61 | L16: 13.32 | M16: 4854.8 | N16: 4246.02 | O16: 59.5 | P16: 26.36
C17: M B Agro Prod. | D17: 444.05 | E17: 8.76 | F17: 318.36 | G17: 11.88 | H17: 57.48 | I17: 1057.61 | J17: 33.99 | K17: 122.7 | L17: 23.13 | M17: 4197.58 | N17: 3891.1 | O17: 46.6 | P17: 52.46
C18: Krishana Phosch. | D18: 587.4 | E18: 6.06 | F18: 376.21 | G18: 27.84 | H18: 86.54 | I18: 1358.24 | J18: 31.18 | K18: 162.71 | L18: 17.79 | M18: 3905.21 | N18: 3556.84 | O18: 51.14 | P18: 35.33
C20: Paradeep Phosph. | D20: 221 | E20: 81.54 | F20: 4358.46 | G20: 903.8 | H20: 551.79 | I20: 13820.21 | J20: 251.81 | K20: 1114.71 | L20: 12.68 | M20: 21474.04 | N20: 18019.38 | O20: 278.78 | P20: 22.42

Sheet Comps Valuation
B6: Comparable valuation
B8: Company Data | E8: Market Data | L8: Financial data | P8: Valution
E9: Price | F9: Share | G9: Market Cap | H9: Debt | I9: Cash | J9: EV | L9: Sales | M9: EBITDA | N9: Earnings | P9: EV/Sales | Q9: EV/EBITDA | R9: P/E
B10: Company Name | E10: (/share) | F10: Lakhs | G10: Lakhs | H10: Lakhs | I10: Lakhs | J10: Lakhs | L10: Lakhs | M10: Lakhs | N10: Lakhs | P10: x | Q10: x | R10: x
B11: ='Comps Data'!C10 -> Coromandel Inter | E11: ='Comps Data'!D10 -> 2466.2 | F11: 2948 | G11: =F11*E11 -> 7270357.6 | H11: 78038 | I11: 353834 | J11: =G11+H11-I11 -> 6994561.6 | L11: 2408524 | M11: 283597 | N11: 205471 | P11: =J11/L11 -> 2.9040863 | Q11: =J11/M11 -> 24.663736 | R11: =G11/N11 -> 35.383862
B12: ='Comps Data'!C12 -> Chambal Fert. | E12: ='Comps Data'!D12 -> 559.75 | F12: 4007 | G12: =F12*E12 -> 2242918.2 | H12: 9876 | I12: 23632 | J12: =G12+H12-I12 -> 2229162.2 | L12: 1664620 | M12: 273103 | N12: 164939 | P12: =J12/L12 -> 1.3391418 | Q12: =J12/M12 -> 8.1623499 | R12: =G12/N12 -> 13.598471
B13: ='Comps Data'!C13 -> R C F | E13: ='Comps Data'!D13 -> 157.9 | F13: 5517 | G13: =F13*E13 -> 871134.3 | H13: 276221 | I13: 103574 | J13: =G13+H13-I13 -> 1043781.3 | L13: 1693364 | M13: 84039 | N13: 24245 | P13: =J13/L13 -> 0.61639512 | Q13: =J13/M13 -> 12.420201 | R13: =G13/N13 -> 35.930472
B14: ='Comps Data'!C14 -> G S F C | E14: ='Comps Data'!D14 -> 212.85 | F14: 3985 | G14: =F14*E14 -> 848207.25 | H14: 176 | I14: 190728 | J14: =G14+H14-I14 -> 657655.25 | L14: 953396 | M14: 95838 | N14: 59116 | P14: =J14/L14 -> 0.68980282 | Q14: =J14/M14 -> 6.8621554 | R14: =G14/N14 -> 14.348184 | X14: 100
B15: ='Comps Data'!C15 -> Natl.Fertilizer | E15: ='Comps Data'!D15 -> 97.78 | F15: 4906 | G15: =F15*E15 -> 479708.68 | H15: 200105 | I15: 3278 | J15: =G15+H15-I15 -> 676535.68 | L15: 1979450 | M15: 81048 | N15: 18398 | P15: =J15/L15 -> 0.34177963 | Q15: =J15/M15 -> 8.3473458 | R15: =G15/N15 -> 26.073958
B16: ='Comps Data'!C16 -> Mangalore Chem. | E16: ='Comps Data'!D16 -> 358.25 | F16: 1185 | G16: =F16*E16 -> 424526.25 | H16: 74128 | I16: 13250 | J16: =G16+H16-I16 -> 485404.25 | L16: 333190 | M16: 36673 | N16: 14371 | P16: =J16/L16 -> 1.4568392 | Q16: =J16/M16 -> 13.236012 | R16: =G16/N16 -> 29.540481
B17: ='Comps Data'!C17 -> M B Agro Prod. | E17: ='Comps Data'!D17 -> 444.05 | F17: 876 | G17: =F17*E17 -> 388987.8 | H17: 31836 | I17: 1188 | J17: =G17+H17-I17 -> 419635.8 | L17: 105761 | M17: 15669 | N17: 5748 | P17: =J17/L17 -> 3.9677745 | Q17: =J17/M17 -> 26.781275 | R17: =G17/N17 -> 67.673591
B18: ='Comps Data'!C18 -> Krishana Phosch. | E18: ='Comps Data'!D18 -> 587.4 | F18: 606 | G18: =F18*E18 -> 355964.4 | H18: 37621 | I18: 2784 | J18: =G18+H18-I18 -> 390801.4 | L18: 135824 | M18: 19389 | N18: 8654 | P18: =J18/L18 -> 2.8772632 | Q18: =J18/M18 -> 20.155831 | R18: =G18/N18 -> 41.132933
B21: High | P21: =MAX(P11:P18) -> 3.9677745 | Q21: =MAX(Q11:Q18) -> 26.781275 | R21: =MAX(R11:R18) -> 67.673591
B22: 75th Percentile | P22: =QUARTILE(P11:P18,3) -> 2.883969 | Q22: =QUARTILE(Q11:Q18,3) -> 21.282807 | R22: =QUARTILE(R11:R18,3) -> 37.231087
B23: Average | P23: =AVERAGE(P11:P18) -> 1.7741353 | Q23: =AVERAGE(Q11:Q18) -> 15.078613 | R23: =AVERAGE(R11:R18) -> 32.960244
B24: Median | P24: =MEDIAN(P11:P18) -> 1.3979905 | Q24: =MEDIAN(Q11:Q18) -> 12.828106 | R24: =MEDIAN(R11:R18) -> 32.462172
B25: 25th Percentile | P25: =QUARTILE(P11:P18,1) -> 0.67145089 | Q25: =QUARTILE(Q11:Q18,1) -> 8.3010968 | R25: =QUARTILE(R11:R18,1) -> 23.142515
B26: Low | P26: =MIN(P11:P18) -> 0.34177963 | Q26: =MIN(Q11:Q18) -> 6.8621554 | R26: =MIN(R11:R18) -> 13.598471
B28: Paradeep Phosph. | E28: =Assumption!C23 -> 220.13 | F28: =Assumption!C21 -> 8147.786 | G28: =E28*F28 -> 1793572.1 | H28: 435846 | I28: 90380 | J28: =G28+H28-I28 -> 2139038.1 | L28: 1382021 | M28: 136652 | N28: 55179 | P28: =J28/L28 -> 1.5477609 | Q28: =J28/M28 -> 15.653178 | R28: =G28/N28 -> 32.504615
B31: Median
B32: Metric | E32: Comps | F32: EV | G32: Net Debt | H32: Equity Value | I32: no of Shares | J32: Share Price | L32: Prediction
B33: EV/REVENUE | E33: 1.3979905 | F33: =E33*L28 -> 1932052.2 | G33: =$H$28-$I$28 -> 345466 | H33: =F33-G33 -> 1586586.2 | I33: =$F$28 -> 8147.786 | J33: =H33/I33 -> 194.72606 | L33: =IF(J33>$E$28,"UnderValued","OverValued") -> OverValued
B34: EV/EBITDA | E34: 12.828106 | F34: =E34*M28 -> 1752986.4 | G34: =$H$28-$I$28 -> 345466 | H34: =F34-G34 -> 1407520.4 | I34: =$F$28 -> 8147.786 | J34: =H34/I34 -> 172.74882 | L34: =IF(J34>$E$28,"UnderValued","OverValued") -> OverValued
B35: P/E | E35: 32.462172 | F35: =H35+G35 -> 2136696.2 | G35: =$H$28-$I$28 -> 345466 | H35: =E35*N28 -> 1791230.2 | I35: =$F$28 -> 8147.786 | J35: =H35/I35 -> 219.84256 | L35: =IF(J35>$E$28,"UnderValued","OverValued") -> OverValued
B38: Average
B39: Metric | E39: Comps | F39: EV | G39: Net Debt | H39: Equity Value | I39: no of Shares | J39: Share Price | L39: Prediction
B40: EV/REVENUE | E40: 1.7741353 | F40: =E40*L28 -> 2451892.3 | G40: =$H$28-$I$28 -> 345466 | H40: =F40-G40 -> 2106426.3 | I40: =$F$28 -> 8147.786 | J40: =H40/I40 -> 258.52744 | L40: =IF(J40>$E$28,"UnderValued","OverValued") -> UnderValued
B41: EV/EBITDA | E41: 15.078613 | F41: =E41*M28 -> 2060522.7 | G41: =$H$28-$I$28 -> 345466 | H41: =F41-G41 -> 1715056.7 | I41: =$F$28 -> 8147.786 | J41: =H41/I41 -> 210.49358 | L41: =IF(J41>$E$28,"UnderValued","OverValued") -> OverValued
B42: P/E | E42: 32.960244 | F42: =H42+G42 -> 2164179.3 | G42: =$H$28-$I$28 -> 345466 | H42: =E42*N28 -> 1818713.3 | I42: =$F$28 -> 8147.786 | J42: =H42/I42 -> 223.21564 | L42: =IF(J42>$E$28,"UnderValued","OverValued") -> UnderValued

Sheet WACC
B8: WACC
B10: Current Capital structure
B12: Market cap | C12: ='Comps Valuation'!G28 -> 1793572.1
B13: Total Debt | C13: ='Comps Valuation'!H28 -> 435846
B14: Debt/equity | C14: =C13/C12 -> 0.24300444
B16: Cost of debt
B17: Pre-tax cost of debt | C17: ='Debt Schedules'!F13 -> 0.091194246
B18: tax rate | C18: ='cost Build_up'!G35 -> 0.29058993
B19: After -Tax cost of debt | C19: =C17*(1-C18) -> 0.064694116
B21: Cost of equity
B22: Risk free Rate | C22: =Assumption!C16 -> 0.06519
B23: Equity Market Return | C23: ='Equity Market'!F11 -> 0.11582993
B24: Equity risk premium | C24: =C23-C22 -> 0.05063993
B25: Equity Beta | C25: =Beta!K14 -> 0.4421136
B26: Cost of equity | C26: =C22+(C25*C24) -> 0.087578602
B28: WACC | C28: =(C26*(1-C14))+(C19*C14) -> 0.08201757

Sheet DCF Valuation
B7: DCF Valuation
B9: Particulars | C9: 2021 | D9: =C9+1 -> 2022 | E9: =D9+1 -> 2023 | F9: =E9+1 -> 2024 | G9: =F9+1 -> 2025 | H9: =G9+1 -> 2026 | I9: =H9+1 -> 2027 | J9: =I9+1 -> 2028 | K9: =J9+1 -> 2029 | L9: Terminal Values
B10: Year Frac | C10: 0 | D10: 0 | E10: 0 | F10: 0 | G10: 1 | H10: =G10 -> 1 | I10: =H10 -> 1 | J10: =I10 -> 1 | K10: =J10 -> 1 | L10: 1
B12: EBIT | C12: ='P&L Statement'!C21 -> 45891.73 | D12: ='P&L Statement'!D21 -> 58065.26 | E12: ='P&L Statement'!E21 -> 62583.71 | F12: ='P&L Statement'!F21 -> 43735.91 | G12: ='P&L Statement'!G21 -> 108852.71 | H12: ='P&L Statement'!H21 -> 160282.5 | I12: ='P&L Statement'!I21 -> 218975.14 | J12: ='P&L Statement'!J21 -> 281746.91 | K12: ='P&L Statement'!K21 -> 345367.87
B13: Taxes | C13: =C12*'cost Build_up'!C35 -> 17935.168 | D13: =D12*'cost Build_up'!D35 -> 14819.238 | E13: =E12*'cost Build_up'!E35 -> 17912.545 | F13: =F12*'cost Build_up'!F35 -> 12709.215 | G13: =G12*'cost Build_up'!G35 -> 31631.502 | H13: =H12*'cost Build_up'!H35 -> 46576.48 | I13: =I12*'cost Build_up'!I35 -> 63631.971 | J13: =J12*'cost Build_up'!J35 -> 81872.816 | K13: =K12*'cost Build_up'!K35 -> 100360.43
B14: NOPAT | C14: =C12-C13 -> 27956.562 | D14: =D12-D13 -> 43246.022 | E14: =E12-E13 -> 44671.165 | F14: =F12-F13 -> 31026.695 | G14: =G12-G13 -> 77221.21 | H14: =H12-H13 -> 113706.02 | I14: =I12-I13 -> 155343.17 | J14: =J12-J13 -> 199874.1 | K14: =K12-K13 -> 245007.45
B15: Add- Dep | C15: =-'P&L Statement'!C19 -> 8332.81 | D15: =-'P&L Statement'!D19 -> 9045.72 | E15: =-'P&L Statement'!E19 -> 17515.31 | F15: =-'P&L Statement'!F19 -> 21067.03 | G15: =-'P&L Statement'!G19 -> 25239.542 | H15: =-'P&L Statement'!H19 -> 28763.777 | I15: =-'P&L Statement'!I19 -> 32051.471 | J15: =-'P&L Statement'!J19 -> 35120.568 | K15: =-'P&L Statement'!K19 -> 37987.636
B16: Less- Capex | C16: ='CashFlow '!C39 -> -16883.28 | D16: ='CashFlow '!D39 -> -62022.19 | E16: ='CashFlow '!E39 -> -43618.36 | F16: ='CashFlow '!F39 -> -41150.29 | G16: ='CashFlow '!G39 -> -75720.75 | H16: ='CashFlow '!H39 -> -76099.354 | I16: ='CashFlow '!I39 -> -76479.85 | J16: ='CashFlow '!J39 -> -76862.25 | K16: ='CashFlow '!K39 -> -77246.561
B17: Less Working Capital | C17: =SUM('CashFlow '!C27:C31) -> 99254.66 | D17: =SUM('CashFlow '!D27:D31) -> -69087.26 | E17: =SUM('CashFlow '!E27:E31) -> -306609.87 | F17: =SUM('CashFlow '!F27:F31) -> 83444.49 | G17: =SUM('CashFlow '!G27:G31) -> 38636.651 | H17: =SUM('CashFlow '!H27:H31) -> -1089.1727 | I17: =SUM('CashFlow '!I27:I31) -> -1228.4321 | J17: =SUM('CashFlow '!J27:J31) -> -1304.9467 | K17: =SUM('CashFlow '!K27:K31) -> -1317.7732
B18: Unlevered FCFF | C18: =SUM(C14:C17) -> 118660.75 | D18: =SUM(D14:D17) -> -78817.708 | E18: =SUM(E14:E17) -> -288041.75 | F18: =SUM(F14:F17) -> 94387.925 | G18: =SUM(G14:G17) -> 65376.653 | H18: =SUM(H14:H17) -> 65281.271 | I18: =SUM(I14:I17) -> 109686.36 | J18: =SUM(J14:J17) -> 156827.47 | K18: =SUM(K14:K17) -> 204430.75 | L18: =C30 -> 5810964.1
B20: Trancaction FCFF | C20: =C18*C10 -> 0 | D20: =D18*D10 -> 0 | E20: =E18*E10 -> 0 | F20: =F18*F10 -> 0 | G20: =G18*G10 -> 65376.653 | H20: =H18*H10 -> 65281.271 | I20: =I18*I10 -> 109686.36 | J20: =J18*J10 -> 156827.47 | ... L20: =L18*L10 -> 5810964.1
B23: EV/EBITDA Multiple | C23: =Assumption!C18 -> 12.828106 | E23: Sensitivity - Intrinsic Value (Rs/share)
B24: Perpetual Growth Rate | C24: =Assumption!C19 -> 0.05
B25: Discount Rate | C25: =Assumption!C20 -> 0.08201757 | G25: Perpetual Growth Rate
F26: =C40 -> 457.87548 | G26: 0.03 | H26: 0.04 | I26: 0.05 | J26: 0.055 | K26: 0.06
B27: Terminal Value | E27: Discount Rate | F27: 0.10188488 | G27: 279.08317 | H27: 296.44411 | I27: 320.49716 | J27: 336.37136 | K27: 356.03552
B28: EV/EBITDA | C28: =C23*(K12+K15) -> 4917725.3 | F28: 0.091884881 | G28: 313.02286 | H28: 338.19771 | I28: 375.39354 | J28: 401.55468 | K28: 435.92069
B29: Prep.Growth | C29: =K18*(1+C24)/(C25-C24) -> 6704202.9 | F29: 0.081884881 | G29: 356.97049 | H29: 395.91742 | I29: 459.29407 | J29: 508.6624 | K29: 580.58891
B30: Average | C30: =AVERAGE(C28:C29) -> 5810964.1 | F30: 0.071884881 | G30: 417.69009 | H30: 484.07874 | I30: 611.13816 | J30: 731.10568 | K30: 952.01449
F31: 0.061884881 | G31: 510.37535 | H31: 643.53125 | I31: 1000.7633 | J31: 1568.5276 | K31: 5148.4943
B33: Intrinsic Value
B34: Enterpreise Value | C34: =NPV(C25,G20:L20) -> 4076137.4 | E34: Discount Rate | G34: Exit Multiple
B35: Plus: Cash & Cash equivalent | C35: ='Comps Valuation'!I28 -> 90380 | F35: =C40 -> 457.87548 | G35: 6.8281064 | H35: 9.8281064 | I35: 12.828106 | J35: 15.828106 | K35: 18.828106
B36: Less- Debt | C36: =-'Comps Valuation'!H28 -> -435846 | F36: 0.10188488 | G36: 241.63548 | H36: 281.06632 | I36: 320.49716 | J36: 359.928 | K36: 399.35884
B37: Less-non- controlling interest | C37: 0 | F37: 0.091884881 | G37: 292.0979 | H37: 333.74572 | I37: 375.39354 | J37: 417.04135 | K37: 458.68917
B38: Equity Value | C38: =SUM(C34:C37) -> 3730671.4 | F38: 0.081884881 | G38: 371.27089 | H38: 415.28248 | I38: 459.29407 | J38: 503.30565 | K38: 547.31724
F39: 0.071884881 | G39: 518.07143 | H39: 564.60479 | I39: 611.13816 | J39: 657.67153 | K39: 704.2049
B40: Equity value/share | C40: =C38/Assumption!C21 -> 457.87548 | F40: 0.061884881 | G40: 902.31259 | H40: 951.53793 | I40: 1000.7633 | J40: 1049.9886 | K40: 1099.214
B42: Rate of Return
B43: Current price | C43: =Assumption!C23 -> 220.13
B44: Target Price | C44: =C40 -> 457.87548
B45: Target Price Upside | C45: =C44/C43-1 -> 1.0800231

Sheet FootBall Field Analysis
B8: Football Field Analysis
B10: Football Field Data
E11: Comps Median | F11: Comps Average | G11: DCF | H11: 52-Week Hi/LO | I11: Market Consenses
B12: High | E12: ='Comps Valuation'!$J$35 -> 219.84256 | F12: ='Comps Valuation'!$J$40 -> 258.52744 | G12: 458 | H12: 234 | I12: 250
B13: High | E13: =E12 -> 219.84256 | F13: =F12 -> 258.52744 | G13: =G12 -> 458 | H13: =H12 -> 234 | I13: =I12 -> 250
B14: Low | E14: ='Comps Valuation'!$J$34 -> 172.74882 | F14: ='Comps Valuation'!$J$41 -> 210.49358 | G14: 131 | H14: 79 | I14: 170
B15: Low | E15: =E14 -> 172.74882 | F15: =F14 -> 210.49358 | G15: =G14 -> 131 | H15: =H14 -> 79 | I15: =I14 -> 170
