Workbook

Sheet SBI
D13: NSE : | E13: SBIN
D14: BSE : | E14: 500112
B16: Detailed DCF Financial Analysis
J20: - Dhiraj Mehta

Sheet Assumptions
B1: State Bank of India
B2: BSE: 500112 | NSE: SBIN
C3: 10000
B9: Scenario Manager | E9: Company Name | F9: State Bank of India
B10: Base Case | C10: =IF(B10="Best Case",1,IF(B10="Base Case",2,3)) -> 2 | E10: ISIN Code | F10: INE062A01020
E11: Sector Name | F11: Financial Services
B12: Assumptions | E12: Industry | F12: Banks
B13: Transaction Date | C13: 46063 | E13: Exchange Name | F13: BSE: 500112 | NSE: SBIN
B14: Fiscal Year End | C14: 46112 | E14: Website | F14: sbi.co.in
B15: Risk Free Rate | C15: 0.06715 | E15: Company Description | F15: The State Bank of India (SBI) is the nation's largest bank, boasting a distinguished heritage that spans more than 200 years. Under the current leadership of Chairman Challa Sreenivasulu Setty, the institution continues to pursue its vision of being the "bank of choice for a transforming India" for its customer base of over 52 crores. The bank maintains an unrivalled physical and digital reach, operating 22,937 domestic branches and 63,791 ATMs. Globally, it acts as India’s partner with 244 overseas offices across 29 countries. Its digital transformation is led by the YONO app, which has 8.77 crore registered users, and the bank now processes approximately 220 million financial UPI transactions every day.
B16: Addition In FSA | C16: 0.005
B17: Addition In Dep | C17: 0.005
B18: Tax Rate | C18: =Cost_BuildUp!G22 -> 0.30327525
B19: EV/EBITDA Multiple | C19: ='Comparable Valuation'!E35 -> 17.648039
B20: Perpetual Growth Rate | C20: 0.04
B21: Discount Rate | C21: ='DCF Analysis'!C43 -> 0.1030778
B22: Shares Outstanding(Cr) | C22: ='Comparable Valuation'!F30 -> 923.06
B23: Current Market Price | C23: ='Comparable Valuation'!E30 -> 1144.1
B24: Market Cap (Cr.) | C24: =C23*C22 -> 1056072.9
B26: Colour Code
B27: Blue colour | C27: Hardcoded Figures
B28: Black colour | C28: Calculated Figures
B29: Green Colour | C29: Link Data figures from Different Sheets
B30: Purple Colour | C30: Link Data figures in same sheet
B32: Items | C32: Sheet | E32: Reference | F32: Assumptions
B33: Treasury | C33: Revenue_Build_Up | E33: B31:Q37 | F33: Treasury revenues are forecast using the average growth rate (10.10%) of the last five years as the base case. The best and worst cases are derived by applying a ±5% variation to the base growth rate. A 12% annual tapering is applied from 2026 to 2035 to ensure revenues converge toward a sustainable perpetual growth rate.
B36: Corporate/Wholesale | C36: Revenue_Build_Up | E36: B39:Q45 | F36: Corporate/Wholesale revenues are forecast as 14 % for the base , This avlue is given by the SBI Management for the future year, ±5% adjustments for best and worst cases. A 12% annual tapering is applied from 2026 to 2035 to ensure revenues converge toward a sustainable perpetual growth rate.
B39: Digital Banking | C39: Revenue_Build_Up | E39: B56:Q62 | F39: To forecast the business segment "digital banking", CAGR was used as a reference for future years' projections for the Base scenario. +5% and -5% were calculated for the best and worst case scenarios, respectively. Additionally, a 12% annual tapering rate is applied.
B42: Other Retail Banking | C42: Revenue_Build_Up | E42: B47:Q54 | F42: Retail revenue is projected based on IBEF forecasts for housing, auto, and credit cards, with an initial growth rate of 13%, . grow by 13% in the base case scenario, with ±5% variations for best and worst scenarios. Given the segment’s large contribution, a 12% annual Tapering rate is applied to gradually moderate growth and align it with a perpetual growth rate of ~4%, ensuring consistency and sustainability across all segments.
B45: Insurance Business | C45: Revenue_Build_Up | E45: B64:Q70 | F45: Insurance Business are projected using the historical five-year average growth rate as the base case, with ±5% adjustments applied for best and worst scenarios. A 12% annual tapering is applied from 2026 to 2035 to ensure revenues converge toward a sustainable perpetual growth rate.
B48: Other Banking Operations | C48: Revenue_Build_Up | E48: B72:Q78 | F48: Other Banking Operations are projected using the historical five-year Min growth rate as the base case, with ±5% adjustments applied for best and worst scenarios. A 12% annual tapering is applied from 2026 to 2035 to ensure revenues converge toward a sustainable perpetual growth rate.
B51: Unalloacated Revenue | C51: Revenue_Build_Up | E51: B14:Q20 | F51: Unallocated income is projected based on a minimum inflation rate of 3% growth rate as the base case, with ±2% adjustments applied for best and worst scenarios. A 12% annual tapering is applied from 2026 to 2035 to ensure revenues converge toward a sustainable perpetual growth rate.
B54: Inter Segment Revenue | C54: Revenue_Build_Up | E54: B22:Q28 | F54: Inter segment Revenue are projected using the historical year average growth rate of year 2022 and 2025 only (other years growth rate is outlier) for base case, with ±5% adjustments applied for best and worst scenarios. A 12% annual tapering is applied from 2026 to 2035 to ensure revenues converge toward a sustainable perpetual growth rate.
B57: Share of earnings in Associates | C57: Revenue_Build_Up | E57: B80:Q81 | F57: The "Share of Earnings in Associates" estimate is based on the average percentage of income/revenue from prior years.
B60: Minority Expense | C60: Revenue_Build_Up | E60: B83:Q84 | F60: The "Minority Expense" estimate is based on the average percentage of income/revenue from prior years.
B64: Interest of Deposits, Operating Expenses, Provisions & Contingencies | C64: Cost_Build_Up | E64: B12:Q19 | F64: Interest on deposits, operating expenses, and provisions and contingencies have been analysed by calculating the average percentage of these expenses relative to income/revenue.
... B90: Riskfree Rate | C90: Assumptions | E90: C15 | F90: The risk-free rate is based on the 10-year Indian government bond yield, reflecting long-term returns with minimal default risk.

Sheet P&L_Input
B1: State Bank of India
B2: BSE: 500112 | NSE: SBIN
C3: 10000
B4: (INR in Crores)
B5: Income Statement
B7: Particular | C7: 2021 | D7: =C7+1 -> 2022 | E7: =D7+1 -> 2023 | F7: =E7+1 -> 2024 | G7: =F7+1 -> 2025
B8: INCOME
B9: Interest earned | C9: 278115.48 | D9: 289972.69 | E9: 350844.58 | F9: 439188.51 | G9: 490937.79
B10: Other Income | C10: 107222.41 | D10: 117000.4 | E10: 122533.56 | F10: 155386.39 | G10: 172405.53
B11: Total Income | C11: =SUM(C9:C10) -> 385337.89 | D11: =SUM(D9:D10) -> 406973.09 | E11: =SUM(E9:E10) -> 473378.14 | F11: =SUM(F9:F10) -> 594574.9 | G11: =SUM(G9:G10) -> 663343.32
G12: =G10/'Revenue_Build Up'!G10 -> 0.25990393
B13: EXPENDITURE
B14: Interest on Deposit | C14: 143060.45 | D14: 141765.28 | E14: 163518.78 | F14: 223278.71 | G14: 259228.12
B15: Operating expenses | C15: 142899.04 | D15: 161647.85 | E15: 168795.17 | F15: 200776.45 | G15: 198820.6
B16: Provisions and contingencies | C16: 54618.409 | D16: 40059.148 | E16: 37024.409 | F16: 30806.757 | G16: 46809.309
B17: Total | C17: =SUM(C14:C16) -> 340577.89 | D17: =SUM(D14:D16) -> 343472.28 | E17: =SUM(E14:E16) -> 369338.36 | F17: =SUM(F14:F16) -> 454861.92 | G17: =SUM(G14:G16) -> 504858.03
B19: EBITDA | C19: =C11-C17 -> 44759.997 | D19: =D11-D17 -> 63500.806 | E19: =E11-E17 -> 104039.78 | F19: =F11-F17 -> 139712.99 | G19: =G11-G17 -> 158485.29
B21: Depreciation & Amortization Expenses | C21: 3711.0636 | D21: 3691.27 | E21: 3695.5986 | F21: 3849.1245 | G21: 3991.4767
B23: EBIT | C23: =C19-C21 -> 41048.934 | D23: =D19-D21 -> 59809.536 | E23: =E19-E21 -> 100344.19 | F23: =F19-F21 -> 135863.86 | G23: =G19-G21 -> 154493.82
B25: Interest on Borrowings | C25: 12949.721 | D25: 14429.061 | E25: 26462.034 | F25: 36457.335 | G25: 41715.216
B26: Add: Share in Profit/(Loss) of Associates | C26: -391.9045 | D26: 827.0133 | E26: 1191.4521 | F26: 1405.1543 | G26: 1505.4709
B27: Less: Minority Interest | C27: 1482.3573 | D27: 1809.3049 | E27: 2101.7092 | F27: 2458.7491 | G27: 2961.2882
B29: EBT | C29: =C23-C25+C26-C27 -> 26224.951 | D29: =D23-D25+D26-D27 -> 44398.183 | E29: =E23-E25+E26-E27 -> 72971.895 | F29: =F23-F25+F26-F27 -> 98352.934 | G29: =G23-G25+G26-G27 -> 111322.78
B31: Tax Expenses | C31: -3819.4934 | D31: -9024.303 | E31: -17323.722 | F31: -31268.268 | G31: -33761.445
B33: Post Tax Income | C33: =C29+C31 -> 22405.458 | D33: =D29+D31 -> 35373.88 | E33: =E29+E31 -> 55648.173 | F33: =F29+F31 -> 67084.666 | G33: =G29+G31 -> 77561.337

Sheet BS_Input
B1: State Bank of India
B2: BSE: 500112 | NSE: SBIN
C3: 10000
B4: (INR in Crores)
B5: Balance Sheet
B7: Particular | C7: 2021 | D7: =C7+1 -> 2022 | E7: =D7+1 -> 2023 | F7: =E7+1 -> 2024 | G7: =F7+1 -> 2025
B8: CAPITAL AND LIABILITIES
B9: Capital | C9: 892.4612 | D9: 892.4612 | E9: 892.4612 | F9: 892.4612 | G9: 892.462
B10: Reserves & Surplus | C10: 274669.1 | D10: 304695.58 | E10: 358038.86 | F10: 414046.71 | G10: 486144.3
B11: Minority Interest | C11: 9625.9166 | D11: 11207.423 | E11: 12836.619 | F11: 15617.962 | G11: 18025.839
B12: CASA Deposits | C12: 1686779.5 | D12: 1819712 | E12: 1906519.4 | F12: 1982929.8 | G12: 2108936.6 | K12: 10000
B13: Fixed Deposits | C13: 2028551.7 | D13: 2267698.6 | E13: 2562016.1 | F13: 2983607.7 | G13: 3330961.4
B14: Borrowings | C14: 433796.21 | D14: 449159.78 | E14: 521151.95 | F14: 639609.5 | G14: 610857.24
B15: Other Liabilities and Provisions | C15: 411303.62 | D15: 507517.68 | E15: 592962.92 | F15: 697074.68 | G15: 758367.48
B16: TOTAL | C16: =SUM(C9:C15) -> 4845618.5 | D16: =SUM(D9:D15) -> 5360883.5 | E16: =SUM(E9:E15) -> 5954418.3 | F16: =SUM(F9:F15) -> 6733778.8 | G16: =SUM(G9:G15) -> 7314185.3
B18: ASSETS
B19: Cash and Balances with Reserve Bank of India | C19: 213498.62 | D19: 318492.43 | E19: 247321.05 | F19: 225356.34 | G19: 227485.16
B20: Balances with Banks and Money at Call & Short Notice | C20: 134208.42 | D20: 80412.692 | E20: 70990.86 | F20: 101215.97 | G20: 130447.79
B21: Investments | C21: 1595100.3 | D21: 1776489.9 | E21: 1913107.9 | F21: 2110548.2 | G21: 2205601.1
B22: Advances | C22: 2500599 | D22: 2794076 | E22: 3267902.1 | F22: 3784272.7 | G22: 4250830.7
B23: Fixed Assets | C23: 40166.788 | D23: 39510.031 | E23: 44407.381 | F23: 44708.177 | G23: 46337.695
B24: Other Assets | C24: 362045.47 | D24: 351902.48 | E24: 410689.04 | F24: 467677.42 | G24: 453482.86
B25: TOTAL | C25: =SUM(C19:C24) -> 4845618.5 | D25: =SUM(D19:D24) -> 5360883.5 | E25: =SUM(E19:E24) -> 5954418.3 | F25: =SUM(F19:F24) -> 6733778.8 | G25: =SUM(G19:G24) -> 7314185.3
B27: Check | C27: =C25=C16 -> TRUE | D27: =D25=D16 -> TRUE | E27: =E25=E16 -> TRUE | F27: =F25=F16 -> TRUE | G27: =G25=G16 -> TRUE

Sheet Revenue_Build Up
B1: State Bank of India
B2: BSE: 500112 | NSE: SBIN
C3: 10000
B4: (INR in Crores)
B5: Revenue BuildUp
B7: Particular | C7: 2021 | D7: =C7+1 -> 2022 | E7: =D7+1 -> 2023 | F7: =E7+1 -> 2024 | G7: =F7+1 -> 2025 | H7: =G7+1 -> 2026 | I7: =H7+1 -> 2027 | J7: =I7+1 -> 2028 | K7: =J7+1 -> 2029 | ... Q7: =P7+1 -> 2035
C8: Audited | D8: Audited | E8: Audited | F8: Audited | G8: Audited | H8: Forecasted | I8: Forecasted | J8: Forecasted | K8: Forecasted | L8: Forecasted | M8: Forecasted | N8: Forecasted | O8: Forecasted | P8: Forecasted | Q8: Forecasted
B10: Total Income | C10: 385337.89 | D10: 406973.09 | E10: 473378.14 | F10: 594574.9 | G10: 663343.32 | H10: =H14-H22+H31+H39+H48+H56+H64+H72 -> 747480.98 | I10: =I14-I22+I31+I39+I48+I56+I64+I72 -> 831100.29 | J10: =J14-J22+J31+J39+J48+J56+J64+J72 -> 913085.46 | K10: =K14-K22+K31+K39+K48+K56+K64+K72 -> 992499.22 | L10: =L14-L22+L31+L39+L48+L56+L64+L72 -> 1068593 | M10: =M14-M22+M31+M39+M48+M56+M64+M72 -> 1140803.7 | N10: =N14-N22+N31+N39+N48+N56+N64+N72 -> 1208741.4 | O10: =O14-O22+O31+O39+O48+O56+O64+O72 -> 1272170.5 | ... Q10: =Q14-Q22+Q31+Q39+Q48+Q56+Q64+Q72 -> 1385198
B11: Y-O-Y Growth Rate | D11: =D10/C10-1 -> 0.056146047 | E11: =E10/D10-1 -> 0.16316816 | F11: =F10/E10-1 -> 0.25602526 | G11: =G10/F10-1 -> 0.1156598 | H11: =H10/G10-1 -> 0.12683879 | I11: =I10/H10-1 -> 0.11186814 | J11: =J10/I10-1 -> 0.09864654 | K11: =K10/J10-1 -> 0.08697298 | ... Q11: =Q10/P10-1 -> 0.040729599
B14: Unalloacated Revenue | C14: 1651.31 | D14: 3155.89 | E14: 1861.43 | F14: 2261.66 | G14: 1815.45 | H14: =G14*(1+H15) -> 1869.9135 | I14: =H14*(1+I15) -> 1919.2792 | J14: =I14*(1+J15) -> 1963.8679 | K14: =J14*(1+K15) -> 2004.0175 | L14: =K14*(1+L15) -> 2040.0715 | M14: =L14*(1+M15) -> 2072.3699 | N14: =M14*(1+N15) -> 2101.2424 | O14: =N14*(1+O15) -> 2127.0042 | ... Q14: =P14*(1+Q15) -> 2170.3649
B15: Y-O-Y Growth Rate | D15: =IFERROR(D14/C14-1,0) -> 0.91114327 | E15: =IFERROR(E14/D14-1,0) -> -0.41017272 | F15: =IFERROR(F14/E14-1,0) -> 0.21501211 | G15: =IFERROR(G14/F14-1,0) -> -0.19729314 | H15: =CHOOSE(Assumptions!$C$10,'Revenue_Build Up'!$H17:$Q17,'Revenue_Build Up'!$H18:$Q18,'Revenue_Build Up'!$H19:$Q19) -> 0.03 | I15: =CHOOSE(Assumptions!$C$10,'Revenue_Build Up'!$H17:$Q17,'Revenue_Build Up'!$H18:$Q18,'Revenue_Build Up'!$H19:$Q19) -> 0.0264 | J15: =CHOOSE(Assumptions!$C$10,'Revenue_Build Up'!$H17:$Q17,'Revenue_Build Up'!$H18:$Q18,'Revenue_Build Up'!$H19:$Q19) -> 0.023232 | K15: =CHOOSE(Assumptions!$C$10,'Revenue_Build Up'!$H17:$Q17,'Revenue_Build Up'!$H18:$Q18,'Revenue_Build Up'!$H19:$Q19) -> 0.02044416 | L15: =CHOOSE(Assumptions!$C$10,'Revenue_Build Up'!$H17:$Q17,'Revenue_Build Up'!$H18:$Q18,'Revenue_Build Up'!$H19:$Q19) -> 0.017990861 | M15: =CHOOSE(Assumptions!$C$10,'Revenue_Build Up'!$H17:$Q17,'Revenue_Build Up'!$H18:$Q18,'Revenue_Build Up'!$H19:$Q19) -> 0.015831958 | N15: =CHOOSE(Assumptions!$C$10,'Revenue_Build Up'!$H17:$Q17,'Revenue_Build Up'!$H18:$Q18,'Revenue_Build Up'!$H19:$Q19) -> 0.013932123 | O15: =CHOOSE(Assumptions!$C$10,'Revenue_Build Up'!$H17:$Q17,'Revenue_Build Up'!$H18:$Q18,'Revenue_Build Up'!$H19:$Q19) -> 0.012260268 | ... Q15: =CHOOSE(Assumptions!$C$10,'Revenue_Build Up'!$H17:$Q17,'Revenue_Build Up'!$H18:$Q18,'Revenue_Build Up'!$H19:$Q19) -> 0.0094943515
B17: Best Case | H17: =H18+2% -> 0.05 | I17: =H17*(1-$C$20) -> 0.044 | J17: =I17*(1-$C$20) -> 0.03872 | K17: =J17*(1-$C$20) -> 0.0340736 | L17: =K17*(1-$C$20) -> 0.029984768 | M17: =L17*(1-$C$20) -> 0.026386596 | N17: =M17*(1-$C$20) -> 0.023220204 | O17: =N17*(1-$C$20) -> 0.02043378 | P17: =O17*(1-$C$20) -> 0.017981726 | Q17: =P17*(1-$C$20) -> 0.015823919
B18: Base Case | H18: 0.03 | I18: =H18*(1-$C$20) -> 0.0264 | J18: =I18*(1-$C$20) -> 0.023232 | K18: =J18*(1-$C$20) -> 0.02044416 | L18: =K18*(1-$C$20) -> 0.017990861 | M18: =L18*(1-$C$20) -> 0.015831958 | N18: =M18*(1-$C$20) -> 0.013932123 | O18: =N18*(1-$C$20) -> 0.012260268 | P18: =O18*(1-$C$20) -> 0.010789036 | Q18: =P18*(1-$C$20) -> 0.0094943515
B19: Worst Case | H19: =H18-2% -> 0.01 | I19: =H19*(1-$C$20) -> 0.0088 | J19: =I19*(1-$C$20) -> 0.007744 | K19: =J19*(1-$C$20) -> 0.00681472 | L19: =K19*(1-$C$20) -> 0.0059969536 | M19: =L19*(1-$C$20) -> 0.0052773192 | N19: =M19*(1-$C$20) -> 0.0046440409 | O19: =N19*(1-$C$20) -> 0.004086756 | P19: =O19*(1-$C$20) -> 0.0035963452 | Q19: =P19*(1-$C$20) -> 0.0031647838
B20: Annual Tapering Rate | C20: 0.12
B22: Less : Inter Segment Revenue | C22: 3097.34 | D22: 3717.19 | E22: 5566.62 | F22: 7569.44 | G22: 9025.12 | H22: =G22*(1+H23) -> 10796 | I22: =H22*(1+I23) -> 12660.153 | J22: =I22*(1+J23) -> 14583.866 | K22: =J22*(1+K23) -> 16533.965 | L22: =K22*(1+L23) -> 18479.521 | M22: =L22*(1+M23) -> 20393.072 | N22: =M22*(1+N23) -> 22251.368 | O22: =N22*(1+O23) -> 24035.682 | ... Q22: =P22*(1+Q23) -> 27329.694
B23: Y-O-Y Growth Rate | D23: =IFERROR(D22/C22-1,0) -> 0.20012333 | E23: =IFERROR(E22/D22-1,0) -> 0.49753443 | F23: =IFERROR(F22/E22-1,0) -> 0.35979104 | G23: =IFERROR(G22/F22-1,0) -> 0.19231013 | H23: =CHOOSE(Assumptions!$C$10,'Revenue_Build Up'!$H25:$Q25,'Revenue_Build Up'!$H26:$Q26,'Revenue_Build Up'!$H27:$Q27) -> 0.19621673 | I23: =CHOOSE(Assumptions!$C$10,'Revenue_Build Up'!$H25:$Q25,'Revenue_Build Up'!$H26:$Q26,'Revenue_Build Up'!$H27:$Q27) -> 0.17267072 | J23: =CHOOSE(Assumptions!$C$10,'Revenue_Build Up'!$H25:$Q25,'Revenue_Build Up'!$H26:$Q26,'Revenue_Build Up'!$H27:$Q27) -> 0.15195024 | K23: =CHOOSE(Assumptions!$C$10,'Revenue_Build Up'!$H25:$Q25,'Revenue_Build Up'!$H26:$Q26,'Revenue_Build Up'!$H27:$Q27) -> 0.13371621 | L23: =CHOOSE(Assumptions!$C$10,'Revenue_Build Up'!$H25:$Q25,'Revenue_Build Up'!$H26:$Q26,'Revenue_Build Up'!$H27:$Q27) -> 0.11767026 | M23: =CHOOSE(Assumptions!$C$10,'Revenue_Build Up'!$H25:$Q25,'Revenue_Build Up'!$H26:$Q26,'Revenue_Build Up'!$H27:$Q27) -> 0.10354983 | N23: =CHOOSE(Assumptions!$C$10,'Revenue_Build Up'!$H25:$Q25,'Revenue_Build Up'!$H26:$Q26,'Revenue_Build Up'!$H27:$Q27) -> 0.091123852 | O23: =CHOOSE(Assumptions!$C$10,'Revenue_Build Up'!$H25:$Q25,'Revenue_Build Up'!$H26:$Q26,'Revenue_Build Up'!$H27:$Q27) -> 0.08018899 | ... Q23: =CHOOSE(Assumptions!$C$10,'Revenue_Build Up'!$H25:$Q25,'Revenue_Build Up'!$H26:$Q26,'Revenue_Build Up'!$H27:$Q27) -> 0.062098354
B25: Best Case | H25: =H26+5% -> 0.24621673 | I25: =H25*(1-$C$28) -> 0.21667072 | J25: =I25*(1-$C$28) -> 0.19067024 | K25: =J25*(1-$C$28) -> 0.16778981 | L25: =K25*(1-$C$28) -> 0.14765503 | M25: =L25*(1-$C$28) -> 0.12993643 | N25: =M25*(1-$C$28) -> 0.11434406 | O25: =N25*(1-$C$28) -> 0.10062277 | P25: =O25*(1-$C$28) -> 0.088548037 | Q25: =P25*(1-$C$28) -> 0.077922273
B26: Base Case | H26: =AVERAGE(G23,D23) -> 0.19621673 | I26: =H26*(1-$C$28) -> 0.17267072 | J26: =I26*(1-$C$28) -> 0.15195024 | K26: =J26*(1-$C$28) -> 0.13371621 | L26: =K26*(1-$C$28) -> 0.11767026 | M26: =L26*(1-$C$28) -> 0.10354983 | N26: =M26*(1-$C$28) -> 0.091123852 | O26: =N26*(1-$C$28) -> 0.08018899 | P26: =O26*(1-$C$28) -> 0.070566311 | Q26: =P26*(1-$C$28) -> 0.062098354
B27: Worst Case | H27: =H26-5% -> 0.14621673 | I27: =H27*(1-$C$28) -> 0.12867072 | J27: =I27*(1-$C$28) -> 0.11323024 | K27: =J27*(1-$C$28) -> 0.099642608 | L27: =K27*(1-$C$28) -> 0.087685495 | M27: =L27*(1-$C$28) -> 0.077163236 | N27: =M27*(1-$C$28) -> 0.067903648 | O27: =N27*(1-$C$28) -> 0.05975521 | P27: =O27*(1-$C$28) -> 0.052584585 | Q27: =P27*(1-$C$28) -> 0.046274435
B28: Annual Tapering Rate | C28: 0.12
B30: Bussiness Segment
B31: Treasury | C31: 92399.77 | D31: 99649.8 | E31: 101804.55 | F31: 124225.02 | G31: 134627.51 | H31: =G31*(1+H32) -> 148226.79 | I31: =H31*(1+I32) -> 161403.03 | J31: =I31*(1+J32) -> 174028.84 | K31: =J31*(1+K32) -> 186008.69 | L31: =K31*(1+L32) -> 197276.68 | M31: =L31*(1+M32) -> 207793.18 | N31: =M31*(1+N32) -> 217541.04 | O31: =N31*(1+O32) -> 226521.57 | ... Q31: =P31*(1+Q32) -> 242255.39
B32: Y-O-Y Growth Rate | D32: =IFERROR(D31/C31-1,0) -> 0.078463723 | E32: =IFERROR(E31/D31-1,0) -> 0.021623225 | F32: =IFERROR(F31/E31-1,0) -> 0.22023053 | G32: =IFERROR(G31/F31-1,0) -> 0.083739089 | H32: =CHOOSE(Assumptions!$C$10,'Revenue_Build Up'!$H34:$Q34,'Revenue_Build Up'!$H35:$Q35,'Revenue_Build Up'!$H36:$Q36) -> 0.10101414 | I32: =CHOOSE(Assumptions!$C$10,'Revenue_Build Up'!$H34:$Q34,'Revenue_Build Up'!$H35:$Q35,'Revenue_Build Up'!$H36:$Q36) -> 0.088892445 | J32: =CHOOSE(Assumptions!$C$10,'Revenue_Build Up'!$H34:$Q34,'Revenue_Build Up'!$H35:$Q35,'Revenue_Build Up'!$H36:$Q36) -> 0.078225351 | K32: =CHOOSE(Assumptions!$C$10,'Revenue_Build Up'!$H34:$Q34,'Revenue_Build Up'!$H35:$Q35,'Revenue_Build Up'!$H36:$Q36) -> 0.068838309 | L32: =CHOOSE(Assumptions!$C$10,'Revenue_Build Up'!$H34:$Q34,'Revenue_Build Up'!$H35:$Q35,'Revenue_Build Up'!$H36:$Q36) -> 0.060577712 | M32: =CHOOSE(Assumptions!$C$10,'Revenue_Build Up'!$H34:$Q34,'Revenue_Build Up'!$H35:$Q35,'Revenue_Build Up'!$H36:$Q36) -> 0.053308387 | N32: =CHOOSE(Assumptions!$C$10,'Revenue_Build Up'!$H34:$Q34,'Revenue_Build Up'!$H35:$Q35,'Revenue_Build Up'!$H36:$Q36) -> 0.04691138 | O32: =CHOOSE(Assumptions!$C$10,'Revenue_Build Up'!$H34:$Q34,'Revenue_Build Up'!$H35:$Q35,'Revenue_Build Up'!$H36:$Q36) -> 0.041282015 | ... Q32: =CHOOSE(Assumptions!$C$10,'Revenue_Build Up'!$H34:$Q34,'Revenue_Build Up'!$H35:$Q35,'Revenue_Build Up'!$H36:$Q36) -> 0.031968792
B34: Best Case | H34: =H35+5% -> 0.15101414 | I34: =H34*(1-$C$37) -> 0.13289244 | J34: =I34*(1-$C$37) -> 0.11694535 | K34: =J34*(1-$C$37) -> 0.10291191 | L34: =K34*(1-$C$37) -> 0.09056248 | M34: =L34*(1-$C$37) -> 0.079694982 | N34: =M34*(1-$C$37) -> 0.070131585 | O34: =N34*(1-$C$37) -> 0.061715794 | P34: =O34*(1-$C$37) -> 0.054309899 | Q34: =P34*(1-$C$37) -> 0.047792711
B35: Base Case | H35: =AVERAGE(D32:G32) -> 0.10101414 | I35: =H35*(1-$C$37) -> 0.088892445 | J35: =I35*(1-$C$37) -> 0.078225351 | K35: =J35*(1-$C$37) -> 0.068838309 | L35: =K35*(1-$C$37) -> 0.060577712 | M35: =L35*(1-$C$37) -> 0.053308387 | N35: =M35*(1-$C$37) -> 0.04691138 | O35: =N35*(1-$C$37) -> 0.041282015 | P35: =O35*(1-$C$37) -> 0.036328173 | Q35: =P35*(1-$C$37) -> 0.031968792
B36: Worst Case | H36: =H35-5% -> 0.051014142 | I36: =H36*(1-$C$37) -> 0.044892445 | J36: =I36*(1-$C$37) -> 0.039505351 | K36: =J36*(1-$C$37) -> 0.034764709 | L36: =K36*(1-$C$37) -> 0.030592944 | M36: =L36*(1-$C$37) -> 0.026921791 | N36: =M36*(1-$C$37) -> 0.023691176 | O36: =N36*(1-$C$37) -> 0.020848235 | P36: =O36*(1-$C$37) -> 0.018346447 | Q36: =P36*(1-$C$37) -> 0.016144873
B37: Annual Tapering Rate | C37: 0.12
B39: Corporate / Wholesale Banking | C39: 83073.07 | D39: 75675.43 | E39: 100160.24 | F39: 132845.5 | G39: 148999.81 | H39: =G39*(1+H40) -> 169859.78 | I39: =H39*(1+I40) -> 190786.51 | J39: =I39*(1+J40) -> 211470.82 | K39: =J39*(1+K40) -> 231646.42 | L39: =K39*(1+L40) -> 251094.84 | M39: =L39*(1+M40) -> 269646.35 | N39: =M39*(1+N40) -> 287177.83 | O39: =N39*(1+O40) -> 303608.59 | ... Q39: =P39*(1+Q40) -> 333024.2
B40: Y-O-Y Growth Rate | D40: =IFERROR(D39/C39-1,0) -> -0.089049797 | E40: =IFERROR(E39/D39-1,0) -> 0.32355033 | F40: =IFERROR(F39/E39-1,0) -> 0.32632969 | G40: =IFERROR(G39/F39-1,0) -> 0.12160224 | H40: =CHOOSE(Assumptions!$C$10,'Revenue_Build Up'!$H42:$Q42,'Revenue_Build Up'!$H43:$Q43,'Revenue_Build Up'!$H44:$Q44) -> 0.14 | I40: =CHOOSE(Assumptions!$C$10,'Revenue_Build Up'!$H42:$Q42,'Revenue_Build Up'!$H43:$Q43,'Revenue_Build Up'!$H44:$Q44) -> 0.1232 | J40: =CHOOSE(Assumptions!$C$10,'Revenue_Build Up'!$H42:$Q42,'Revenue_Build Up'!$H43:$Q43,'Revenue_Build Up'!$H44:$Q44) -> 0.108416 | K40: =CHOOSE(Assumptions!$C$10,'Revenue_Build Up'!$H42:$Q42,'Revenue_Build Up'!$H43:$Q43,'Revenue_Build Up'!$H44:$Q44) -> 0.09540608 | L40: =CHOOSE(Assumptions!$C$10,'Revenue_Build Up'!$H42:$Q42,'Revenue_Build Up'!$H43:$Q43,'Revenue_Build Up'!$H44:$Q44) -> 0.08395735 | M40: =CHOOSE(Assumptions!$C$10,'Revenue_Build Up'!$H42:$Q42,'Revenue_Build Up'!$H43:$Q43,'Revenue_Build Up'!$H44:$Q44) -> 0.073882468 | N40: =CHOOSE(Assumptions!$C$10,'Revenue_Build Up'!$H42:$Q42,'Revenue_Build Up'!$H43:$Q43,'Revenue_Build Up'!$H44:$Q44) -> 0.065016572 | O40: =CHOOSE(Assumptions!$C$10,'Revenue_Build Up'!$H42:$Q42,'Revenue_Build Up'!$H43:$Q43,'Revenue_Build Up'!$H44:$Q44) -> 0.057214583 | ... Q40: =CHOOSE(Assumptions!$C$10,'Revenue_Build Up'!$H42:$Q42,'Revenue_Build Up'!$H43:$Q43,'Revenue_Build Up'!$H44:$Q44) -> 0.044306973
B42: Best Case | H42: =H43+5% -> 0.19 | I42: =H42*(1-$C$45) -> 0.1672 | J42: =I42*(1-$C$45) -> 0.147136 | K42: =J42*(1-$C$45) -> 0.12947968 | L42: =K42*(1-$C$45) -> 0.11394212 | M42: =L42*(1-$C$45) -> 0.10026906 | N42: =M42*(1-$C$45) -> 0.088236776 | O42: =N42*(1-$C$45) -> 0.077648363 | P42: =O42*(1-$C$45) -> 0.06833056 | Q42: =P42*(1-$C$45) -> 0.060130893
B43: Base Case | H43: 0.14 | I43: =H43*(1-$C$45) -> 0.1232 | J43: =I43*(1-$C$45) -> 0.108416 | K43: =J43*(1-$C$45) -> 0.09540608 | L43: =K43*(1-$C$45) -> 0.08395735 | M43: =L43*(1-$C$45) -> 0.073882468 | N43: =M43*(1-$C$45) -> 0.065016572 | O43: =N43*(1-$C$45) -> 0.057214583 | P43: =O43*(1-$C$45) -> 0.050348833 | Q43: =P43*(1-$C$45) -> 0.044306973
B44: Worst Case | H44: =H43-5% -> 0.09 | I44: =H44*(1-$C$45) -> 0.0792 | J44: =I44*(1-$C$45) -> 0.069696 | K44: =J44*(1-$C$45) -> 0.06133248 | L44: =K44*(1-$C$45) -> 0.053972582 | M44: =L44*(1-$C$45) -> 0.047495873 | N44: =M44*(1-$C$45) -> 0.041796368 | O44: =N44*(1-$C$45) -> 0.036780804 | P44: =O44*(1-$C$45) -> 0.032367107 | Q44: =P44*(1-$C$45) -> 0.028483054
B45: Annual Tapering Rate | C45: 0.12
B47: Retail Banking
B48: Other Retail Banking | C48: 132094.86 | D48: 138896.25 | E48: 163755.15 | F48: 204491.84 | G48: 233942.93 | H48: =G48*(1+H49) -> 264355.51 | I48: =H48*(1+I49) -> 294597.78 | J48: =I48*(1+J49) -> 324255.53 | K48: =J48*(1+K49) -> 352981.77 | L48: =K48*(1+L49) -> 380500.37 | M48: =L48*(1+M49) -> 406604.65 | N48: =M48*(1+N49) -> 431152.4 | O48: =N48*(1+O49) -> 454058.59 | ... Q48: =P48*(1+Q49) -> 494841.31
B49: Y-O-Y Growth Rate | D49: =IFERROR(D48/C48-1,0) -> 0.05148868 | E49: =IFERROR(E48/D48-1,0) -> 0.17897459 | F49: =IFERROR(F48/E48-1,0) -> 0.24876586 | G49: =IFERROR(G48/F48-1,0) -> 0.14402086 | H49: =CHOOSE(Assumptions!$C$10,'Revenue_Build Up'!$H51:$Q51,'Revenue_Build Up'!$H52:$Q52,'Revenue_Build Up'!$H53:$Q53) -> 0.13 | I49: =CHOOSE(Assumptions!$C$10,'Revenue_Build Up'!$H51:$Q51,'Revenue_Build Up'!$H52:$Q52,'Revenue_Build Up'!$H53:$Q53) -> 0.1144 | J49: =CHOOSE(Assumptions!$C$10,'Revenue_Build Up'!$H51:$Q51,'Revenue_Build Up'!$H52:$Q52,'Revenue_Build Up'!$H53:$Q53) -> 0.100672 | K49: =CHOOSE(Assumptions!$C$10,'Revenue_Build Up'!$H51:$Q51,'Revenue_Build Up'!$H52:$Q52,'Revenue_Build Up'!$H53:$Q53) -> 0.08859136 | L49: =CHOOSE(Assumptions!$C$10,'Revenue_Build Up'!$H51:$Q51,'Revenue_Build Up'!$H52:$Q52,'Revenue_Build Up'!$H53:$Q53) -> 0.077960397 | M49: =CHOOSE(Assumptions!$C$10,'Revenue_Build Up'!$H51:$Q51,'Revenue_Build Up'!$H52:$Q52,'Revenue_Build Up'!$H53:$Q53) -> 0.068605149 | N49: =CHOOSE(Assumptions!$C$10,'Revenue_Build Up'!$H51:$Q51,'Revenue_Build Up'!$H52:$Q52,'Revenue_Build Up'!$H53:$Q53) -> 0.060372531 | O49: =CHOOSE(Assumptions!$C$10,'Revenue_Build Up'!$H51:$Q51,'Revenue_Build Up'!$H52:$Q52,'Revenue_Build Up'!$H53:$Q53) -> 0.053127828 | ... Q49: =CHOOSE(Assumptions!$C$10,'Revenue_Build Up'!$H51:$Q51,'Revenue_Build Up'!$H52:$Q52,'Revenue_Build Up'!$H53:$Q53) -> 0.04114219
B51: Best Case | H51: =H52+5% -> 0.18 | I51: =H51*(1-$C$54) -> 0.1584 | J51: =I51*(1-$C$54) -> 0.139392 | K51: =J51*(1-$C$54) -> 0.12266496 | L51: =K51*(1-$C$54) -> 0.10794516 | M51: =L51*(1-$C$54) -> 0.094991745 | N51: =M51*(1-$C$54) -> 0.083592736 | O51: =N51*(1-$C$54) -> 0.073561607 | P51: =O51*(1-$C$54) -> 0.064734214 | Q51: =P51*(1-$C$54) -> 0.056966109
B52: Base Case | H52: 0.13 | I52: =H52*(1-$C$54) -> 0.1144 | J52: =I52*(1-$C$54) -> 0.100672 | K52: =J52*(1-$C$54) -> 0.08859136 | L52: =K52*(1-$C$54) -> 0.077960397 | M52: =L52*(1-$C$54) -> 0.068605149 | N52: =M52*(1-$C$54) -> 0.060372531 | O52: =N52*(1-$C$54) -> 0.053127828 | P52: =O52*(1-$C$54) -> 0.046752488 | Q52: =P52*(1-$C$54) -> 0.04114219
B53: Worst Case | H53: =H52-5% -> 0.08 | I53: =H53*(1-$C$54) -> 0.0704 | J53: =I53*(1-$C$54) -> 0.061952 | K53: =J53*(1-$C$54) -> 0.05451776 | L53: =K53*(1-$C$54) -> 0.047975629 | M53: =L53*(1-$C$54) -> 0.042218553 | N53: =M53*(1-$C$54) -> 0.037152327 | O53: =N53*(1-$C$54) -> 0.032694048 | P53: =O53*(1-$C$54) -> 0.028770762 | Q53: =P53*(1-$C$54) -> 0.025318271
B54: Annual Tapering Rate | C54: 0.12
B56: Digital Banking | C56: 0 | D56: 0 | E56: 3766.65 | F56: 5244.9 | G56: 7731.44 | H56: =G56*(1+H57) -> 9664.3 | I56: =H56*(1+I57) -> 11790.446 | J56: =I56*(1+J57) -> 14073.076 | K56: =J56*(1+K57) -> 16470.678 | L56: =K56*(1+L57) -> 18940.026 | M56: =L56*(1+M57) -> 21438.84 | N56: =M56*(1+N57) -> 23927.911 | O56: =N56*(1+O57) -> 26372.599 | ... Q56: =P56*(1+Q57) -> 31017.915
B57: Y-O-Y Growth Rate | D57: =IFERROR(D56/C56-1,0) -> 0 | E57: =IFERROR(E56/D56-1,0) -> 0 | F57: =IFERROR(F56/E56-1,0) -> 0.39245749 | G57: =IFERROR(G56/F56-1,0) -> 0.47408721 | H57: =CHOOSE(Assumptions!$C$10,'Revenue_Build Up'!$H59:$Q59,'Revenue_Build Up'!$H60:$Q60,'Revenue_Build Up'!$H61:$Q61) -> 0.25 | I57: =CHOOSE(Assumptions!$C$10,'Revenue_Build Up'!$H59:$Q59,'Revenue_Build Up'!$H60:$Q60,'Revenue_Build Up'!$H61:$Q61) -> 0.22 | J57: =CHOOSE(Assumptions!$C$10,'Revenue_Build Up'!$H59:$Q59,'Revenue_Build Up'!$H60:$Q60,'Revenue_Build Up'!$H61:$Q61) -> 0.1936 | K57: =CHOOSE(Assumptions!$C$10,'Revenue_Build Up'!$H59:$Q59,'Revenue_Build Up'!$H60:$Q60,'Revenue_Build Up'!$H61:$Q61) -> 0.170368 | L57: =CHOOSE(Assumptions!$C$10,'Revenue_Build Up'!$H59:$Q59,'Revenue_Build Up'!$H60:$Q60,'Revenue_Build Up'!$H61:$Q61) -> 0.14992384 | M57: =CHOOSE(Assumptions!$C$10,'Revenue_Build Up'!$H59:$Q59,'Revenue_Build Up'!$H60:$Q60,'Revenue_Build Up'!$H61:$Q61) -> 0.13193298 | N57: =CHOOSE(Assumptions!$C$10,'Revenue_Build Up'!$H59:$Q59,'Revenue_Build Up'!$H60:$Q60,'Revenue_Build Up'!$H61:$Q61) -> 0.11610102 | O57: =CHOOSE(Assumptions!$C$10,'Revenue_Build Up'!$H59:$Q59,'Revenue_Build Up'!$H60:$Q60,'Revenue_Build Up'!$H61:$Q61) -> 0.1021689 | ... Q57: =CHOOSE(Assumptions!$C$10,'Revenue_Build Up'!$H59:$Q59,'Revenue_Build Up'!$H60:$Q60,'Revenue_Build Up'!$H61:$Q61) -> 0.079119595
B59: Best Case | H59: =H60+5% -> 0.3 | I59: =H59*(1-$C$62) -> 0.264 | J59: =I59*(1-$C$62) -> 0.23232 | K59: =J59*(1-$C$62) -> 0.2044416 | L59: =K59*(1-$C$62) -> 0.17990861 | M59: =L59*(1-$C$62) -> 0.15831958 | N59: =M59*(1-$C$62) -> 0.13932123 | O59: =N59*(1-$C$62) -> 0.12260268 | P59: =O59*(1-$C$62) -> 0.10789036 | Q59: =P59*(1-$C$62) -> 0.094943515
B60: Base Case | H60: 0.25 | I60: =H60*(1-$C$62) -> 0.22 | J60: =I60*(1-$C$62) -> 0.1936 | K60: =J60*(1-$C$62) -> 0.170368 | L60: =K60*(1-$C$62) -> 0.14992384 | M60: =L60*(1-$C$62) -> 0.13193298 | N60: =M60*(1-$C$62) -> 0.11610102 | O60: =N60*(1-$C$62) -> 0.1021689 | P60: =O60*(1-$C$62) -> 0.089908631 | Q60: =P60*(1-$C$62) -> 0.079119595
B61: Worst Case | H61: =H60-5% -> 0.2 | I61: =H61*(1-$C$62) -> 0.176 | J61: =I61*(1-$C$62) -> 0.15488 | K61: =J61*(1-$C$62) -> 0.1362944 | L61: =K61*(1-$C$62) -> 0.11993907 | M61: =L61*(1-$C$62) -> 0.10554638 | N61: =M61*(1-$C$62) -> 0.092880817 | O61: =N61*(1-$C$62) -> 0.081735119 | P61: =O61*(1-$C$62) -> 0.071926905 | Q61: =P61*(1-$C$62) -> 0.063295676
B62: Annual Tapering Rate | C62: 0.12
B64: Insurance Business | C64: 64569.16 | D64: 76586.87 | E64: 86451.82 | F64: 105459.4 | G64: 114142.61 | H64: =G64*(1+H65) -> 129257.6 | I64: =H64*(1+I65) -> 144320.15 | J64: =I64*(1+J65) -> 159119.83 | K64: =J64*(1+K65) -> 173479.1 | L64: =K64*(1+L65) -> 187255.57 | M64: =L64*(1+M65) -> 200341.6 | N64: =M64*(1+N65) -> 212662.07 | O64: =N64*(1+O65) -> 224170.83 | ... Q64: =P64*(1+Q65) -> 244688.74
B65: Y-O-Y Growth Rate | D65: =IFERROR(D64/C64-1,0) -> 0.18612152 | E65: =IFERROR(E64/D64-1,0) -> 0.12880733 | F65: =IFERROR(F64/E64-1,0) -> 0.21986327 | G65: =IFERROR(G64/F64-1,0) -> 0.082336994 | H65: =CHOOSE(Assumptions!$C$10,'Revenue_Build Up'!$H67:$Q67,'Revenue_Build Up'!$H68:$Q68,'Revenue_Build Up'!$H69:$Q69) -> 0.13242195 | I65: =CHOOSE(Assumptions!$C$10,'Revenue_Build Up'!$H67:$Q67,'Revenue_Build Up'!$H68:$Q68,'Revenue_Build Up'!$H69:$Q69) -> 0.11653131 | J65: =CHOOSE(Assumptions!$C$10,'Revenue_Build Up'!$H67:$Q67,'Revenue_Build Up'!$H68:$Q68,'Revenue_Build Up'!$H69:$Q69) -> 0.10254755 | K65: =CHOOSE(Assumptions!$C$10,'Revenue_Build Up'!$H67:$Q67,'Revenue_Build Up'!$H68:$Q68,'Revenue_Build Up'!$H69:$Q69) -> 0.090241848 | L65: =CHOOSE(Assumptions!$C$10,'Revenue_Build Up'!$H67:$Q67,'Revenue_Build Up'!$H68:$Q68,'Revenue_Build Up'!$H69:$Q69) -> 0.079412827 | M65: =CHOOSE(Assumptions!$C$10,'Revenue_Build Up'!$H67:$Q67,'Revenue_Build Up'!$H68:$Q68,'Revenue_Build Up'!$H69:$Q69) -> 0.069883287 | N65: =CHOOSE(Assumptions!$C$10,'Revenue_Build Up'!$H67:$Q67,'Revenue_Build Up'!$H68:$Q68,'Revenue_Build Up'!$H69:$Q69) -> 0.061497293 | O65: =CHOOSE(Assumptions!$C$10,'Revenue_Build Up'!$H67:$Q67,'Revenue_Build Up'!$H68:$Q68,'Revenue_Build Up'!$H69:$Q69) -> 0.054117618 | ... Q65: =CHOOSE(Assumptions!$C$10,'Revenue_Build Up'!$H67:$Q67,'Revenue_Build Up'!$H68:$Q68,'Revenue_Build Up'!$H69:$Q69) -> 0.041908683
B67: Best Case | H67: =H68+5% -> 0.18242195 | I67: =H67*(1-$C$70) -> 0.16053131 | J67: =I67*(1-$C$70) -> 0.14126755 | K67: =J67*(1-$C$70) -> 0.12431545 | L67: =K67*(1-$C$70) -> 0.10939759 | M67: =L67*(1-$C$70) -> 0.096269883 | N67: =M67*(1-$C$70) -> 0.084717497 | O67: =N67*(1-$C$70) -> 0.074551398 | P67: =O67*(1-$C$70) -> 0.06560523 | Q67: =P67*(1-$C$70) -> 0.057732602
B68: Base Case | H68: =AVERAGE(G65,D65:E65) -> 0.13242195 | I68: =H68*(1-$C$70) -> 0.11653131 | J68: =I68*(1-$C$70) -> 0.10254755 | K68: =J68*(1-$C$70) -> 0.090241848 | L68: =K68*(1-$C$70) -> 0.079412827 | M68: =L68*(1-$C$70) -> 0.069883287 | N68: =M68*(1-$C$70) -> 0.061497293 | O68: =N68*(1-$C$70) -> 0.054117618 | P68: =O68*(1-$C$70) -> 0.047623504 | Q68: =P68*(1-$C$70) -> 0.041908683
B69: Worst Case | H69: =H68-5% -> 0.082421946 | I69: =H69*(1-$C$70) -> 0.072531312 | J69: =I69*(1-$C$70) -> 0.063827555 | K69: =J69*(1-$C$70) -> 0.056168248 | L69: =K69*(1-$C$70) -> 0.049428059 | M69: =L69*(1-$C$70) -> 0.043496692 | N69: =M69*(1-$C$70) -> 0.038277089 | O69: =N69*(1-$C$70) -> 0.033683838 | P69: =O69*(1-$C$70) -> 0.029641777 | Q69: =P69*(1-$C$70) -> 0.026084764
B70: Annual Tapering Rate | C70: 0.12
B72: Other Banking Operations | C72: 14647.06 | D72: 16726.04 | E72: 21144.92 | F72: 27616.02 | G72: 31108.69 | H72: =G72*(1+H73) -> 35043.087 | I72: =H72*(1+I73) -> 38943.239 | J72: =I72*(1+J73) -> 42757.355 | K72: =J72*(1+K73) -> 46442.506 | L72: =K72*(1+L73) -> 49964.939 | M72: =L72*(1+M73) -> 53299.781 | N72: =M72*(1+N73) -> 56430.311 | O72: =N72*(1+O73) -> 59346.983 | ... Q72: =P72*(1+Q73) -> 64529.773
B73: Y-O-Y Growth Rate | D73: =IFERROR(D72/C72-1,0) -> 0.14193838 | E73: =IFERROR(E72/D72-1,0) -> 0.26419164 | F73: =IFERROR(F72/E72-1,0) -> 0.30603568 | G73: =IFERROR(G72/F72-1,0) -> 0.12647261 | H73: =CHOOSE(Assumptions!$C$10,'Revenue_Build Up'!$H75:$Q75,'Revenue_Build Up'!$H76:$Q76,'Revenue_Build Up'!$H77:$Q77) -> 0.12647261 | I73: =CHOOSE(Assumptions!$C$10,'Revenue_Build Up'!$H75:$Q75,'Revenue_Build Up'!$H76:$Q76,'Revenue_Build Up'!$H77:$Q77) -> 0.11129589 | J73: =CHOOSE(Assumptions!$C$10,'Revenue_Build Up'!$H75:$Q75,'Revenue_Build Up'!$H76:$Q76,'Revenue_Build Up'!$H77:$Q77) -> 0.097940386 | K73: =CHOOSE(Assumptions!$C$10,'Revenue_Build Up'!$H75:$Q75,'Revenue_Build Up'!$H76:$Q76,'Revenue_Build Up'!$H77:$Q77) -> 0.086187539 | L73: =CHOOSE(Assumptions!$C$10,'Revenue_Build Up'!$H75:$Q75,'Revenue_Build Up'!$H76:$Q76,'Revenue_Build Up'!$H77:$Q77) -> 0.075845035 | M73: =CHOOSE(Assumptions!$C$10,'Revenue_Build Up'!$H75:$Q75,'Revenue_Build Up'!$H76:$Q76,'Revenue_Build Up'!$H77:$Q77) -> 0.06674363 | N73: =CHOOSE(Assumptions!$C$10,'Revenue_Build Up'!$H75:$Q75,'Revenue_Build Up'!$H76:$Q76,'Revenue_Build Up'!$H77:$Q77) -> 0.058734395 | O73: =CHOOSE(Assumptions!$C$10,'Revenue_Build Up'!$H75:$Q75,'Revenue_Build Up'!$H76:$Q76,'Revenue_Build Up'!$H77:$Q77) -> 0.051686267 | ... Q73: =CHOOSE(Assumptions!$C$10,'Revenue_Build Up'!$H75:$Q75,'Revenue_Build Up'!$H76:$Q76,'Revenue_Build Up'!$H77:$Q77) -> 0.040025846
B75: Best Case | H75: =H76+5% -> 0.17647261 | I75: =H75*(1-$C$78) -> 0.15529589 | J75: =I75*(1-$C$78) -> 0.13666039 | K75: =J75*(1-$C$78) -> 0.12026114 | L75: =K75*(1-$C$78) -> 0.1058298 | M75: =L75*(1-$C$78) -> 0.093130226 | N75: =M75*(1-$C$78) -> 0.081954599 | O75: =N75*(1-$C$78) -> 0.072120047 | P75: =O75*(1-$C$78) -> 0.063465642 | Q75: =P75*(1-$C$78) -> 0.055849765
B76: Base Case | H76: =MIN(D73:G73) -> 0.12647261 | I76: =H76*(1-$C$78) -> 0.11129589 | J76: =I76*(1-$C$78) -> 0.097940386 | K76: =J76*(1-$C$78) -> 0.086187539 | L76: =K76*(1-$C$78) -> 0.075845035 | M76: =L76*(1-$C$78) -> 0.06674363 | N76: =M76*(1-$C$78) -> 0.058734395 | O76: =N76*(1-$C$78) -> 0.051686267 | P76: =O76*(1-$C$78) -> 0.045483915 | Q76: =P76*(1-$C$78) -> 0.040025846
B77: Worst Case | H77: =H76-5% -> 0.076472605 | I77: =H77*(1-$C$78) -> 0.067295893 | J77: =I77*(1-$C$78) -> 0.059220386 | K77: =J77*(1-$C$78) -> 0.052113939 | L77: =K77*(1-$C$78) -> 0.045860267 | M77: =L77*(1-$C$78) -> 0.040357035 | N77: =M77*(1-$C$78) -> 0.03551419 | O77: =N77*(1-$C$78) -> 0.031252488 | P77: =O77*(1-$C$78) -> 0.027502189 | Q77: =P77*(1-$C$78) -> 0.024201926
B78: Annual Tapering Rate | C78: 0.12
B80: Share in Profit/(Loss) of Associates | C80: ='P&L_Input'!C26 -> -391.9045 | D80: ='P&L_Input'!D26 -> 827.0133 | E80: ='P&L_Input'!E26 -> 1191.4521 | F80: ='P&L_Input'!F26 -> 1405.1543 | G80: ='P&L_Input'!G26 -> 1505.4709 | H80: =H81*H10 -> 1220.6055 | I80: =I81*I10 -> 1357.1524 | J80: =J81*J10 -> 1491.0308 | K80: =K81*K10 -> 1620.7102 | L80: =L81*L10 -> 1744.9681 | M80: =M81*M10 -> 1862.8853 | N80: =N81*N10 -> 1973.8248 | O80: =O81*O10 -> 2077.4018 | ... Q80: =Q81*Q10 -> 2261.971
B81: % of Revenue | C81: =C80/C10 -> -0.0010170412 | D81: =D80/D10 -> 0.0020321081 | E81: =E80/E10 -> 0.0025169141 | F81: =F80/F10 -> 0.0023632923 | G81: =G80/G10 -> 0.00226952 | H81: =AVERAGE($C$81:$G$81) -> 0.0016329586 | I81: =AVERAGE($C$81:$G$81) -> 0.0016329586 | J81: =AVERAGE($C$81:$G$81) -> 0.0016329586 | K81: =AVERAGE($C$81:$G$81) -> 0.0016329586 | L81: =AVERAGE($C$81:$G$81) -> 0.0016329586 | M81: =AVERAGE($C$81:$G$81) -> 0.0016329586 | N81: =AVERAGE($C$81:$G$81) -> 0.0016329586 | O81: =AVERAGE($C$81:$G$81) -> 0.0016329586 | ... Q81: =AVERAGE($C$81:$G$81) -> 0.0016329586
B83: Minority Interest | C83: ='P&L_Input'!C27 -> 1482.3573 | D83: ='P&L_Input'!D27 -> 1809.3049 | E83: ='P&L_Input'!E27 -> 2101.7092 | F83: ='P&L_Input'!F27 -> 2458.7491 | G83: ='P&L_Input'!G27 -> 2961.2882 | H83: =H84*H10 -> 3189.0477 | I83: =I84*I10 -> 3545.8006 | J83: =J84*J10 -> 3895.5815 | K83: =K84*K10 -> 4234.3919 | L83: =L84*L10 -> 4559.0377 | M83: =M84*M10 -> 4867.1171 | N83: =N84*N10 -> 5156.9662 | O83: =O84*O10 -> 5427.5795 | ... Q83: =Q84*Q10 -> 5909.7992
B84: % of Revenue | C84: =C83/C10 -> 0.0038469025 | D84: =D83/D10 -> 0.0044457605 | E84: =E83/E10 -> 0.0044398104 | F84: =F83/F10 -> 0.0041353059 | G84: =G83/G10 -> 0.0044641864 | H84: =AVERAGE($C$84:$G$84) -> 0.0042663931 | I84: =AVERAGE($C$84:$G$84) -> 0.0042663931 | J84: =AVERAGE($C$84:$G$84) -> 0.0042663931 | K84: =AVERAGE($C$84:$G$84) -> 0.0042663931 | L84: =AVERAGE($C$84:$G$84) -> 0.0042663931 | M84: =AVERAGE($C$84:$G$84) -> 0.0042663931 | N84: =AVERAGE($C$84:$G$84) -> 0.0042663931 | O84: =AVERAGE($C$84:$G$84) -> 0.0042663931 | ... Q84: =AVERAGE($C$84:$G$84) -> 0.0042663931
C90: =C48+C56 -> 132094.86 | D90: =D48+D56 -> 138896.25 | E90: =E48+E56 -> 167521.8 | F90: =F48+F56 -> 209736.74 | G90: =G48+G56 -> 241674.37 | H90: =H48+H56 -> 274019.81 | I90: =I48+I56 -> 306388.23 | J90: =J48+J56 -> 338328.61 | ... Q90: =Q48+Q56 -> 525859.22
D91: =D90/C90-1 -> 0.05148868 | E91: =E90/D90-1 -> 0.20609304 | F91: =F90/E90-1 -> 0.2519967 | G91: =G90/F90-1 -> 0.15227485 | H91: =H90/G90-1 -> 0.13383894 | I91: =I90/H90-1 -> 0.11812437 | J91: =J90/I90-1 -> 0.10424806 | K91: =K90/J90-1 -> 0.091992931 | ... Q91: =Q90/P90-1 -> 0.043307955

Sheet Cost_BuildUp
B1: State Bank of India
B2: BSE: 500112 | NSE: SBIN
C3: 10000
B4: (INR in Crores)
B5: Cost BuildUp
B7: Particular | C7: 2021 | D7: =C7+1 -> 2022 | E7: =D7+1 -> 2023 | F7: =E7+1 -> 2024 | G7: =F7+1 -> 2025 | H7: =G7+1 -> 2026 | I7: =H7+1 -> 2027 | J7: =I7+1 -> 2028 | K7: =J7+1 -> 2029 | ... Q7: =P7+1 -> 2035
C8: Audited | D8: Audited | E8: Audited | F8: Audited | G8: Audited | H8: Forecasted | I8: Forecasted | J8: Forecasted | K8: Forecasted | L8: Forecasted | M8: Forecasted | N8: Forecasted | O8: Forecasted | P8: Forecasted | Q8: Forecasted
B10: Total Income | C10: ='Revenue_Build Up'!C10 -> 385337.89 | D10: ='Revenue_Build Up'!D10 -> 406973.09 | E10: ='Revenue_Build Up'!E10 -> 473378.14 | F10: ='Revenue_Build Up'!F10 -> 594574.9 | G10: ='Revenue_Build Up'!G10 -> 663343.32 | H10: ='Revenue_Build Up'!H10 -> 747480.98 | I10: ='Revenue_Build Up'!I10 -> 831100.29 | J10: ='Revenue_Build Up'!J10 -> 913085.46 | ... Q10: ='Revenue_Build Up'!Q10 -> 1385198
B12: Interest on Deposits | C12: ='P&L_Input'!C14 -> 143060.45 | D12: ='P&L_Input'!D14 -> 141765.28 | E12: ='P&L_Input'!E14 -> 163518.78 | F12: ='P&L_Input'!F14 -> 223278.71 | G12: ='P&L_Input'!G14 -> 259228.12 | H12: =H13*H$10 -> 273779.39 | I12: =I13*I$10 -> 304406.58 | J12: =J13*J$10 -> 334435.24 | K12: =K13*K$10 -> 363522.06 | L12: =L13*L$10 -> 391392.87 | M12: =M13*M$10 -> 417841.45 | N12: =N13*N$10 -> 442724.97 | O12: =O13*O$10 -> 465957.09 | ... Q12: =Q13*Q$10 -> 507355.6
B13: % of Revenue | C13: =C12/C$10 -> 0.37125974 | D13: =D12/D$10 -> 0.34834068 | E13: =E12/E$10 -> 0.34542952 | F13: =F12/F$10 -> 0.37552664 | G13: =G12/G$10 -> 0.39079028 | H13: =AVERAGE($C$13:$G$13) -> 0.36626937 | I13: =AVERAGE($C$13:$G$13) -> 0.36626937 | J13: =AVERAGE($C$13:$G$13) -> 0.36626937 | K13: =AVERAGE($C$13:$G$13) -> 0.36626937 | L13: =AVERAGE($C$13:$G$13) -> 0.36626937 | M13: =AVERAGE($C$13:$G$13) -> 0.36626937 | N13: =AVERAGE($C$13:$G$13) -> 0.36626937 | O13: =AVERAGE($C$13:$G$13) -> 0.36626937 | ... Q13: =AVERAGE($C$13:$G$13) -> 0.36626937
B15: Operating Expenses | C15: ='P&L_Input'!C15 -> 142899.04 | D15: ='P&L_Input'!D15 -> 161647.85 | E15: ='P&L_Input'!E15 -> 168795.17 | F15: ='P&L_Input'!F15 -> 200776.45 | G15: ='P&L_Input'!G15 -> 198820.6 | H15: =H16*H$10 -> 263414.95 | I15: =I16*I$10 -> 292882.69 | J15: =J16*J$10 -> 321774.56 | K15: =K16*K$10 -> 349760.25 | L15: =L16*L$10 -> 376575.95 | M15: =M16*M$10 -> 402023.27 | N15: =N16*N$10 -> 425964.77 | O15: =O16*O$10 -> 448317.4 | ... Q15: =Q16*Q$10 -> 488148.69
B16: % of Revenue | C16: =C15/C$10 -> 0.37084087 | D16: =D15/D$10 -> 0.39719543 | E16: =E15/E$10 -> 0.35657575 | F16: =F15/F$10 -> 0.33768066 | G16: =G15/G$10 -> 0.29972503 | H16: =AVERAGE($C$16:$G$16) -> 0.35240355 | I16: =AVERAGE($C$16:$G$16) -> 0.35240355 | J16: =AVERAGE($C$16:$G$16) -> 0.35240355 | K16: =AVERAGE($C$16:$G$16) -> 0.35240355 | L16: =AVERAGE($C$16:$G$16) -> 0.35240355 | M16: =AVERAGE($C$16:$G$16) -> 0.35240355 | N16: =AVERAGE($C$16:$G$16) -> 0.35240355 | O16: =AVERAGE($C$16:$G$16) -> 0.35240355 | ... Q16: =AVERAGE($C$16:$G$16) -> 0.35240355
B18: Provisions and Contingencies | C18: ='P&L_Input'!C16 -> 54618.409 | D18: ='P&L_Input'!D16 -> 40059.148 | E18: ='P&L_Input'!E16 -> 37024.409 | F18: ='P&L_Input'!F16 -> 30806.757 | G18: ='P&L_Input'!G16 -> 46809.309 | H18: =H19*H$10 -> 65892.77 | I18: =I19*I$10 -> 73264.071 | J18: =J19*J$10 -> 80491.318 | K18: =K19*K$10 -> 87491.888 | L18: =L19*L$10 -> 94199.788 | M18: =M19*M$10 -> 100565.39 | N18: =N19*N$10 -> 106554.31 | O18: =O19*O$10 -> 112145.78 | ... Q18: =Q19*Q$10 -> 122109.5
B19: % of Revenue | C19: =C18/C$10 -> 0.1417416 | D19: =D18/D$10 -> 0.098431934 | E19: =E18/E$10 -> 0.078213178 | F19: =F18/F$10 -> 0.051813079 | G19: =G18/G$10 -> 0.070565736 | H19: =AVERAGE($C$19:$G$19) -> 0.088153105 | I19: =AVERAGE($C$19:$G$19) -> 0.088153105 | J19: =AVERAGE($C$19:$G$19) -> 0.088153105 | K19: =AVERAGE($C$19:$G$19) -> 0.088153105 | L19: =AVERAGE($C$19:$G$19) -> 0.088153105 | M19: =AVERAGE($C$19:$G$19) -> 0.088153105 | N19: =AVERAGE($C$19:$G$19) -> 0.088153105 | O19: =AVERAGE($C$19:$G$19) -> 0.088153105 | ... Q19: =AVERAGE($C$19:$G$19) -> 0.088153105
B21: Tax Expense | C21: ='P&L_Input'!C31 -> -3819.4934 | D21: ='P&L_Input'!D31 -> -9024.303 | E21: ='P&L_Input'!E31 -> -17323.722 | F21: ='P&L_Input'!F31 -> -31268.268 | G21: ='P&L_Input'!G31 -> -33761.445 | H21: =H22*-'Income Statement'!H28 -> -31282.518 | I21: =I22*-'Income Statement'!I28 -> -34025.674 | J21: =J22*-'Income Statement'!J28 -> -37401.596 | K21: =K22*-'Income Statement'!K28 -> -40663.653 | L21: =L22*-'Income Statement'!L28 -> -43782.342 | M21: =M22*-'Income Statement'!M28 -> -46735.82 | N21: =N22*-'Income Statement'!N28 -> -49509.306 | O21: =O22*-'Income Statement'!O28 -> -52094.258 | ... Q21: =Q22*-'Income Statement'!Q28 -> -56689.941
B22: % of EBT | C22: =-C21/'P&L_Input'!C29 -> 0.14564349 | D22: =-D21/'P&L_Input'!D29 -> 0.20325839 | E22: =-E21/'P&L_Input'!E29 -> 0.23740266 | F22: =-F21/'P&L_Input'!F29 -> 0.31791902 | G22: =-G21/'P&L_Input'!G29 -> 0.30327525 | H22: 0.3 | I22: 0.3 | J22: 0.3 | K22: 0.3 | L22: 0.3 | M22: 0.3 | N22: 0.3 | O22: 0.3 | P22: 0.3 | Q22: 0.3

Sheet Debt Schedules
B1: State Bank of India
B2: BSE: 500112 | NSE: SBIN
C3: 10000
B4: (INR in Crores)
B5: Borrowing Schedule
B7: Particular | C7: 2021 | D7: =C7+1 -> 2022 | E7: =D7+1 -> 2023 | F7: =E7+1 -> 2024 | G7: =F7+1 -> 2025 | H7: =G7+1 -> 2026 | I7: =H7+1 -> 2027 | J7: =I7+1 -> 2028 | K7: =J7+1 -> 2029 | ... Q7: =P7+1 -> 2035
C8: Audited | D8: Audited | E8: Audited | F8: Audited | G8: Audited | H8: Forecasted | I8: Forecasted | J8: Forecasted | K8: Forecasted | L8: Forecasted | M8: Forecasted | N8: Forecasted | O8: Forecasted | P8: Forecasted | Q8: Forecasted
B10: Opening Balance | D10: =C12 -> 433796.21 | E10: =D12 -> 449159.78 | F10: =E12 -> 521151.95 | G10: =F12 -> 639609.5 | H10: =G12 -> 610857.24 | I10: =H12 -> 796359.52 | J10: =I12 -> 885446.78 | K10: =J12 -> 972793.04 | ... Q10: =P12 -> 1418022
B11: Addition / Repayment' | D11: =D12-D10 -> 15363.576 | E11: =E12-E10 -> 71992.166 | F11: =F12-F10 -> 118457.55 | G11: =G12-G10 -> -28752.258 | H11: =H12-H10 -> 185502.28 | I11: =I12-I10 -> 89087.256 | J11: =J12-J10 -> 87346.261 | K11: =K12-K10 -> 84606.709 | ... Q11: =Q12-Q10 -> 57755.468
B12: Ending Balance | C12: =BS_Items!C18 -> 433796.21 | D12: =BS_Items!D18 -> 449159.78 | E12: =BS_Items!E18 -> 521151.95 | F12: =BS_Items!F18 -> 639609.5 | G12: =BS_Items!G18 -> 610857.24 | H12: =BS_Items!H18 -> 796359.52 | I12: =BS_Items!I18 -> 885446.78 | J12: =BS_Items!J18 -> 972793.04 | ... Q12: =BS_Items!Q18 -> 1475777.5
B14: Interest on Borrowing | C14: ='P&L_Input'!C25 -> 12949.721 | D14: ='P&L_Input'!D25 -> 14429.061 | E14: ='P&L_Input'!E25 -> 26462.034 | F14: ='P&L_Input'!F25 -> 36457.335 | G14: ='P&L_Input'!G25 -> 41715.216 | H14: =H15*AVERAGE(H12,H10) -> 34704.028 | I14: =I15*AVERAGE(I12,I10) -> 41475.808 | J14: =J15*AVERAGE(J12,J10) -> 45826.917 | K14: =K15*AVERAGE(K12,K10) -> 50067.529 | L14: =L15*AVERAGE(L12,L10) -> 54153.35 | M14: =M15*AVERAGE(M12,M10) -> 58049.917 | N14: =N15*AVERAGE(N12,N10) -> 61732.192 | O14: =O15*AVERAGE(O12,O10) -> 65183.737 | ... Q14: =Q15*AVERAGE(Q12,Q10) -> 71365.337
B15: % of Borrowing | C15: =C14/AVERAGE(C12,C10) -> 0.029852084 | D15: =D14/AVERAGE(D12,D10) -> 0.032683534 | E15: =E14/AVERAGE(E12,E10) -> 0.054543365 | F15: =F14/AVERAGE(F12,F10) -> 0.062816239 | G15: =G14/AVERAGE(G12,G10) -> 0.066719433 | H15: =AVERAGE(C15:G15) -> 0.049322931 | I15: =H15 -> 0.049322931 | J15: =I15 -> 0.049322931 | K15: =J15 -> 0.049322931 | L15: =K15 -> 0.049322931 | M15: =L15 -> 0.049322931 | N15: =M15 -> 0.049322931 | O15: =N15 -> 0.049322931 | P15: =O15 -> 0.049322931 | Q15: =P15 -> 0.049322931

Sheet FAS
B1: State Bank of India
B2: BSE: 500112 | NSE: SBIN
C3: 10000
B4: (INR in Crores)
B5: Fixed Assets Schedules
B7: Particular | C7: 2021 | D7: =C7+1 -> 2022 | E7: =D7+1 -> 2023 | F7: =E7+1 -> 2024 | G7: =F7+1 -> 2025 | H7: =G7+1 -> 2026 | I7: =H7+1 -> 2027 | J7: =I7+1 -> 2028 | K7: =J7+1 -> 2029 | ... Q7: =P7+1 -> 2035
C8: Audited | D8: Audited | E8: Audited | F8: Audited | G8: Audited | H8: Forecasted | I8: Forecasted | J8: Forecasted | K8: Forecasted | L8: Forecasted | M8: Forecasted | N8: Forecasted | O8: Forecasted | P8: Forecasted | Q8: Forecasted
C9: 10000
A11: # | B11: Premises
B12: Opening Gross Block | C12: 31094.355 | D12: =C15 -> 31130.034 | E12: =D15 -> 31336.609 | F12: =E15 -> 35945.976 | G12: =F15 -> 36023.909 | H12: =G15 -> 36413.533 | I12: =H15 -> 37858.756 | J12: =I15 -> 39311.206 | K12: =J15 -> 40770.917 | ... Q12: =P15 -> 49683.74
B13: Additions: | C13: 81.6496 | D13: 226.5368 | E13: 6445.0955 | F13: 82.6219 | G13: 390.212 | H13: =AVERAGE(C13:G13) -> 1445.2232 | I13: =H13*(1+Assumptions!$C$16) -> 1452.4493 | J13: =I13*(1+Assumptions!$C$16) -> 1459.7115 | K13: =J13*(1+Assumptions!$C$16) -> 1467.0101 | L13: =K13*(1+Assumptions!$C$16) -> 1474.3451 | M13: =L13*(1+Assumptions!$C$16) -> 1481.7169 | N13: =M13*(1+Assumptions!$C$16) -> 1489.1254 | O13: =N13*(1+Assumptions!$C$16) -> 1496.5711 | P13: =O13*(1+Assumptions!$C$16) -> 1504.0539 | Q13: =P13*(1+Assumptions!$C$16) -> 1511.5742
B14: Deductions | C14: -45.9707 | D14: -19.9624 | E14: -1835.7277 | F14: -4.6892 | G14: -0.5881
B15: Closing Gross Block | C15: =SUM(C12:C14) -> 31130.034 | D15: =SUM(D12:D14) -> 31336.609 | E15: =SUM(E12:E14) -> 35945.976 | F15: =SUM(F12:F14) -> 36023.909 | G15: =SUM(G12:G14) -> 36413.533 | H15: =SUM(H12:H14) -> 37858.756 | I15: =SUM(I12:I14) -> 39311.206 | J15: =SUM(J12:J14) -> 40770.917 | ... Q15: =SUM(Q12:Q14) -> 51195.314
B16: Depreciation to date | C16: 1893.9793 | D16: 2197.6739 | E16: 2545.9369 | F16: 2885.7395 | G16: 3227.4558 | H16: =AVERAGE(C16:G16) -> 2550.1571 | I16: =H16*(1+Assumptions!$C$17) -> 2562.9079 | J16: =I16*(1+Assumptions!$C$17) -> 2575.7224 | K16: =J16*(1+Assumptions!$C$17) -> 2588.601 | L16: =K16*(1+Assumptions!$C$17) -> 2601.544 | M16: =L16*(1+Assumptions!$C$17) -> 2614.5517 | N16: =M16*(1+Assumptions!$C$17) -> 2627.6245 | O16: =N16*(1+Assumptions!$C$17) -> 2640.7626 | P16: =O16*(1+Assumptions!$C$17) -> 2653.9664 | Q16: =P16*(1+Assumptions!$C$17) -> 2667.2363
B17: Net Block | C17: =C15-C16 -> 29236.055 | D17: =D15-D16 -> 29138.935 | E17: =E15-E16 -> 33400.04 | F17: =F15-F16 -> 33138.17 | G17: =G15-G16 -> 33186.077 | H17: =H15-H16 -> 35308.599 | I17: =I15-I16 -> 36748.298 | J17: =J15-J16 -> 38195.195 | ... Q17: =Q15-Q16 -> 48528.077
B18: Premises under construction | C18: 351.8345 | D18: 252.9655 | E18: 317.546 | F18: 528.4341 | G18: 532.8122 | H18: 0 | I18: 0 | J18: 0 | K18: 0 | L18: 0 | M18: 0 | N18: 0 | O18: 0 | P18: 0 | Q18: 0
A20: # | B20: Other Fixed Assets
B21: Opening Gross Block | C21: 36021.193 | D21: =C24 -> 38991.323 | E21: =D24 -> 41202.178 | F21: =E24 -> 44177.262 | G21: =F24 -> 46975.335 | H21: =G24 -> 51314.365 | I21: =H24 -> 55265.463 | J21: =I24 -> 59236.316 | K21: =J24 -> 63227.024 | ... Q21: =P24 -> 87593.803
B22: Addition | C22: 3753.8335 | D22: 2952.3616 | E22: 3771.9049 | F22: 3832.0094 | G22: 5445.3796 | H22: =AVERAGE(C22:G22) -> 3951.0978 | I22: =H22*(1+Assumptions!$C$16) -> 3970.8533 | J22: =I22*(1+Assumptions!$C$16) -> 3990.7076 | K22: =J22*(1+Assumptions!$C$16) -> 4010.6611 | L22: =K22*(1+Assumptions!$C$16) -> 4030.7144 | M22: =L22*(1+Assumptions!$C$16) -> 4050.868 | N22: =M22*(1+Assumptions!$C$16) -> 4071.1223 | O22: =N22*(1+Assumptions!$C$16) -> 4091.4779 | P22: =O22*(1+Assumptions!$C$16) -> 4111.9353 | Q22: =P22*(1+Assumptions!$C$16) -> 4132.495
B23: Deductions/ Adjustments | C23: -783.7042 | D23: -741.506 | E23: -796.8209 | F23: -1033.9367 | G23: -1106.3492
B24: Closing Gross Block | C24: =SUM(C21:C23) -> 38991.323 | D24: =SUM(D21:D23) -> 41202.178 | E24: =SUM(E21:E23) -> 44177.262 | F24: =SUM(F21:F23) -> 46975.335 | G24: =SUM(G21:G23) -> 51314.365 | H24: =SUM(H21:H23) -> 55265.463 | I24: =SUM(I21:I23) -> 59236.316 | J24: =SUM(J21:J23) -> 63227.024 | ... Q24: =SUM(Q21:Q23) -> 91726.298
B25: Depreciation to date | C25: 28686.495 | D25: 31339.276 | E25: 33883.54 | F25: 36342.875 | G25: 38907.426 | H25: =AVERAGE(C25:G25) -> 33831.923 | I25: =H25*(1+Assumptions!$C$17) -> 34001.082 | J25: =I25*(1+Assumptions!$C$17) -> 34171.088 | K25: =J25*(1+Assumptions!$C$17) -> 34341.943 | L25: =K25*(1+Assumptions!$C$17) -> 34513.653 | M25: =L25*(1+Assumptions!$C$17) -> 34686.221 | N25: =M25*(1+Assumptions!$C$17) -> 34859.652 | O25: =N25*(1+Assumptions!$C$17) -> 35033.95 | P25: =O25*(1+Assumptions!$C$17) -> 35209.12 | Q25: =P25*(1+Assumptions!$C$17) -> 35385.166
B26: Net Block | C26: =C24-C25 -> 10304.827 | D26: =D24-D25 -> 9862.902 | E26: =E24-E25 -> 10293.723 | F26: =F24-F25 -> 10632.46 | G26: =G24-G25 -> 12406.94 | H26: =H24-H25 -> 21433.541 | I26: =I24-I25 -> 25235.234 | J26: =J24-J25 -> 29055.937 | ... Q26: =Q24-Q25 -> 56341.132
A29: # | B29: Leased Assets
B30: Opening Gross Block | C30: 240.3884 | D30: =C33 -> 288.8563 | E30: =D33 -> 397.9402 | F30: =E33 -> 505.9027 | G30: =F33 -> 621.7792 | H30: =G33 -> 393.8593 | I30: =H33 -> 499.2106 | J30: =I33 -> 605.08866 | K30: =J33 -> 711.4961 | ... Q30: =P33 -> 1361.2071
B31: Addition | C31: 74.3419 | D31: 126.3617 | E31: 178.4134 | F31: 136.0071 | G31: 11.6324 | H31: =AVERAGE(C31:G31) -> 105.3513 | I31: =H31*(1+Assumptions!$C$16) -> 105.87806 | J31: =I31*(1+Assumptions!$C$16) -> 106.40745 | K31: =J31*(1+Assumptions!$C$16) -> 106.93948 | L31: =K31*(1+Assumptions!$C$16) -> 107.47418 | M31: =L31*(1+Assumptions!$C$16) -> 108.01155 | N31: =M31*(1+Assumptions!$C$16) -> 108.55161 | O31: =N31*(1+Assumptions!$C$16) -> 109.09437 | P31: =O31*(1+Assumptions!$C$16) -> 109.63984 | Q31: =P31*(1+Assumptions!$C$16) -> 110.18804
B32: Deductions/ Adjustments | C32: -25.874 | D32: -17.2778 | E32: -70.4509 | F32: -20.1306 | G32: -239.5523
B33: Closing Gross Block | C33: =SUM(C30:C32) -> 288.8563 | D33: =SUM(D30:D32) -> 397.9402 | E33: =SUM(E30:E32) -> 505.9027 | F33: =SUM(F30:F32) -> 621.7792 | G33: =SUM(G30:G32) -> 393.8593 | H33: =SUM(H30:H32) -> 499.2106 | I33: =SUM(I30:I32) -> 605.08866 | J33: =SUM(J30:J32) -> 711.4961 | ... Q33: =SUM(Q30:Q32) -> 1471.3952
B34: Depreciation to date | C34: 131.1319 | D34: 170.2788 | E34: 175.8503 | F34: 255.1177 | G34: 223.3958 | H34: =AVERAGE(C34:G34) -> 191.1549 | I34: =H34*(1+Assumptions!$C$17) -> 192.11067 | J34: =I34*(1+Assumptions!$C$17) -> 193.07123 | K34: =J34*(1+Assumptions!$C$17) -> 194.03658 | L34: =K34*(1+Assumptions!$C$17) -> 195.00677 | M34: =L34*(1+Assumptions!$C$17) -> 195.9818 | N34: =M34*(1+Assumptions!$C$17) -> 196.96171 | O34: =N34*(1+Assumptions!$C$17) -> 197.94652 | P34: =O34*(1+Assumptions!$C$17) -> 198.93625 | Q34: =P34*(1+Assumptions!$C$17) -> 199.93093
B35: Net Block | C35: =C33-C34 -> 157.7244 | D35: =D33-D34 -> 227.6614 | E35: =E33-E34 -> 330.0524 | F35: =F33-F34 -> 366.6615 | G35: =G33-G34 -> 170.4635 | H35: =H33-H34 -> 308.0557 | I35: =I33-I34 -> 412.97798 | J35: =J33-J34 -> 518.42488 | ... Q35: =Q33-Q34 -> 1271.4642
A38: # | B38: Fixed Assets
B39: Opening Gross Block | C39: =C30+C21+C12 -> 67355.937 | D39: =D30+D21+D12 -> 70410.213 | E39: =E30+E21+E12 -> 72936.727 | F39: =F30+F21+F12 -> 80629.141 | G39: =G30+G21+G12 -> 83621.023 | H39: =H30+H21+H12 -> 88121.758 | I39: =I30+I21+I12 -> 93623.43 | J39: =J30+J21+J12 -> 99152.611 | ... Q39: =Q30+Q21+Q12 -> 138638.75
B40: Additions: | C40: =C31+C22+C13 -> 3909.825 | D40: =D31+D22+D13 -> 3305.2601 | E40: =E31+E22+E13 -> 10395.414 | F40: =F31+F22+F13 -> 4050.6384 | G40: =G31+G22+G13 -> 5847.224 | H40: =H31+H22+H13 -> 5501.6723 | I40: =I31+I22+I13 -> 5529.1806 | J40: =J31+J22+J13 -> 5556.8265 | ... Q40: =Q31+Q22+Q13 -> 5754.2572
B41: Deductions | C41: =C32+C23+C14 -> -855.5489 | D41: =D32+D23+D14 -> -778.7462 | E41: =E32+E23+E14 -> -2702.9995 | F41: =F32+F23+F14 -> -1058.7565 | G41: =G32+G23+G14 -> -1346.4896 | H41: =H32+H23+H14 -> 0 | I41: =I32+I23+I14 -> 0 | J41: =J32+J23+J14 -> 0 | ... Q41: =Q32+Q23+Q14 -> 0
B42: Closing Gross Block | C42: =SUM(C39:C41) -> 70410.213 | D42: =SUM(D39:D41) -> 72936.727 | E42: =SUM(E39:E41) -> 80629.141 | F42: =SUM(F39:F41) -> 83621.023 | G42: =SUM(G39:G41) -> 88121.758 | H42: =SUM(H39:H41) -> 93623.43 | I42: =SUM(I39:I41) -> 99152.611 | J42: =SUM(J39:J41) -> 104709.44 | ... Q42: =SUM(Q39:Q41) -> 144393.01
B43: Depreciation to date | C43: =C34+C25+C16 -> 30711.606 | D43: =D34+D25+D16 -> 33707.229 | E43: =E34+E25+E16 -> 36605.327 | F43: =F34+F25+F16 -> 39483.733 | G43: =G34+G25+G16 -> 42358.278 | H43: =H34+H25+H16 -> 36573.234 | I43: =I34+I25+I16 -> 36756.101 | J43: =J34+J25+J16 -> 36939.881 | ... Q43: =Q34+Q25+Q16 -> 38252.333
B45: Net Block | C45: =C42-C43 -> 39698.607 | D45: =D42-D43 -> 39229.498 | E45: =E42-E43 -> 44023.815 | F45: =F42-F43 -> 44137.291 | G45: =G42-G43 -> 45763.48 | H45: =H42-H43 -> 57050.196 | I45: =I42-I43 -> 62396.51 | J45: =J42-J43 -> 67769.556 | ... Q45: =Q42-Q43 -> 106140.67
B46: Premises under construction | C46: =C18 -> 351.8345 | D46: =D18 -> 252.9655 | E46: =E18 -> 317.546 | F46: =F18 -> 528.4341 | G46: =G18 -> 532.8122 | H46: =H18 -> 0 | I46: =I18 -> 0 | J46: =J18 -> 0 | ... Q46: =Q18 -> 0
B47: Net Block + Premises Under Construction | C47: =C45+C46 -> 40050.441 | D47: =D45+D46 -> 39482.464 | E47: =E45+E46 -> 44341.361 | F47: =F45+F46 -> 44665.725 | G47: =G45+G46 -> 46296.292 | H47: =H45+H46 -> 57050.196 | I47: =I45+I46 -> 62396.51 | J47: =J45+J46 -> 67769.556 | ... Q47: =Q45+Q46 -> 106140.67
B48: CWIP | C48: 116.3469 | D48: 27.5668 | E48: 66.0204 | F48: 42.4523 | G48: 41.4029 | H48: 0 | I48: 0 | J48: 0 | K48: 0 | L48: 0 | M48: 0 | N48: 0 | O48: 0 | P48: 0 | Q48: 0
A50: # | B50: Net Fixed Assets | C50: =C48+C45+C46 -> 40166.788 | D50: =D48+D45+D46 -> 39510.031 | E50: =E48+E45+E46 -> 44407.381 | F50: =F48+F45+F46 -> 44708.177 | G50: =G48+G45+G46 -> 46337.695 | H50: =H48+H45+H46 -> 57050.196 | I50: =I48+I45+I46 -> 62396.51 | J50: =J48+J45+J46 -> 67769.556 | ... Q50: =Q48+Q45+Q46 -> 106140.67
A52: # | B52: Capex | C52: 0 | D52: =SUM(D47:D48)-SUM(C47:C48)+D54 -> 3034.5123 | E52: =SUM(E47:E48)-SUM(D47:D48)+E54 -> 8592.9491 | F52: =SUM(F47:F48)-SUM(E47:E48)+F54 -> 4149.9208 | G52: =SUM(G47:G48)-SUM(F47:F48)+G54 -> 5620.9948 | H52: =SUM(H47:H48)-SUM(G47:G48)+H54 -> 14158.845 | I52: =SUM(I47:I48)-SUM(H47:H48)+I54 -> 8809.8906 | J52: =SUM(J47:J48)-SUM(I47:I48)+J54 -> 8853.94 | K52: =SUM(K47:K48)-SUM(J47:J48)+K54 -> 8898.2097 | ... Q52: =SUM(Q47:Q48)-SUM(P47:P48)+Q54 -> 9168.5152
A54: # | B54: Dep For the Year | C54: ='P&L_Input'!C21 -> 3711.0636 | D54: ='P&L_Input'!D21 -> 3691.27 | E54: ='P&L_Input'!E21 -> 3695.5986 | F54: ='P&L_Input'!F21 -> 3849.1245 | G54: ='P&L_Input'!G21 -> 3991.4767 | H54: =G54/G43*H43 -> 3446.3444 | I54: =H54/H43*I43 -> 3463.5761 | J54: =I54/I43*J43 -> 3480.894 | K54: =J54/J43*K43 -> 3498.2985 | L54: =K54/K43*L43 -> 3515.79 | M54: =L54/L43*M43 -> 3533.3689 | N54: =M54/M43*N43 -> 3551.0358 | O54: =N54/N43*O43 -> 3568.791 | ... Q54: =P54/P43*Q43 -> 3604.5681
B56: Accumulated Dep | C56: =C43-C54 -> 27000.543 | D56: =D43-D54 -> 30015.959 | E56: =E43-E54 -> 32909.728 | F56: =F43-F54 -> 35634.608 | G56: =G43-G54 -> 38366.801 | H56: =G56/G43*H43 -> 33126.89 | I56: =H56/H43*I43 -> 33292.525 | J56: =I56/I43*J43 -> 33458.987 | K56: =J56/J43*K43 -> 33626.282 | L56: =K56/K43*L43 -> 33794.413 | M56: =L56/L43*M43 -> 33963.386 | N56: =M56/M43*N43 -> 34133.202 | O56: =N56/N43*O43 -> 34303.868 | ... Q56: =P56/P43*Q43 -> 34647.765

Sheet Working Capital
B1: State Bank of India
B2: BSE: 500112 | NSE: SBIN
C3: 10000
B4: (INR in Crores)
B5: Change in Working Capital
B7: Particular | C7: 2021 | D7: =C7+1 -> 2022 | E7: =D7+1 -> 2023 | F7: =E7+1 -> 2024 | G7: =F7+1 -> 2025 | H7: =G7+1 -> 2026 | I7: =H7+1 -> 2027 | J7: =I7+1 -> 2028 | K7: =J7+1 -> 2029 | ... Q7: =P7+1 -> 2035
C8: Audited | D8: Audited | E8: Audited | F8: Audited | G8: Audited | H8: Forecasted | I8: Forecasted | J8: Forecasted | K8: Forecasted | L8: Forecasted | M8: Forecasted | N8: Forecasted | O8: Forecasted | P8: Forecasted | Q8: Forecasted
B10: CASA Deposits | D10: ='Balance Sheet'!D18-'Balance Sheet'!C18 -> 132932.47 | E10: ='Balance Sheet'!E18-'Balance Sheet'!D18 -> 86807.464 | F10: ='Balance Sheet'!F18-'Balance Sheet'!E18 -> 76410.384 | G10: ='Balance Sheet'!G18-'Balance Sheet'!F18 -> 126006.76 | H10: ='Balance Sheet'!H18-'Balance Sheet'!G18 -> 789870.05 | I10: ='Balance Sheet'!I18-'Balance Sheet'!H18 -> 324284.1 | J10: ='Balance Sheet'!J18-'Balance Sheet'!I18 -> 317946.75 | K10: ='Balance Sheet'!K18-'Balance Sheet'!J18 -> 307974.58 | ... Q10: ='Balance Sheet'!Q18-'Balance Sheet'!P18 -> 210234.11
B11: Borrowings | D11: ='Balance Sheet'!D20-'Balance Sheet'!C20 -> 15363.576 | E11: ='Balance Sheet'!E20-'Balance Sheet'!D20 -> 71992.166 | F11: ='Balance Sheet'!F20-'Balance Sheet'!E20 -> 118457.55 | G11: ='Balance Sheet'!G20-'Balance Sheet'!F20 -> -28752.258 | H11: ='Balance Sheet'!H20-'Balance Sheet'!G20 -> 185502.28 | I11: ='Balance Sheet'!I20-'Balance Sheet'!H20 -> 89087.256 | J11: ='Balance Sheet'!J20-'Balance Sheet'!I20 -> 87346.261 | K11: ='Balance Sheet'!K20-'Balance Sheet'!J20 -> 84606.709 | ... Q11: ='Balance Sheet'!Q20-'Balance Sheet'!P20 -> 57755.468
B12: Other Liabilities and Provisions | D12: ='Balance Sheet'!D21-'Balance Sheet'!C21 -> 96214.057 | E12: ='Balance Sheet'!E21-'Balance Sheet'!D21 -> 85445.246 | F12: ='Balance Sheet'!F21-'Balance Sheet'!E21 -> 104111.75 | G12: ='Balance Sheet'!G21-'Balance Sheet'!F21 -> 61292.803 | H12: ='Balance Sheet'!H21-'Balance Sheet'!G21 -> 121073.94 | I12: ='Balance Sheet'!I21-'Balance Sheet'!H21 -> 98381.474 | J12: ='Balance Sheet'!J21-'Balance Sheet'!I21 -> 96458.845 | K12: ='Balance Sheet'!K21-'Balance Sheet'!J21 -> 93433.484 | ... Q12: ='Balance Sheet'!Q21-'Balance Sheet'!P21 -> 63780.93
B13: Total | D13: =SUM(D10:D12) -> 244510.1 | E13: =SUM(E10:E12) -> 244244.88 | F13: =SUM(F10:F12) -> 298979.69 | G13: =SUM(G10:G12) -> 158547.31 | H13: =SUM(H10:H12) -> 1096446.3 | I13: =SUM(I10:I12) -> 511752.83 | J13: =SUM(J10:J12) -> 501751.85 | K13: =SUM(K10:K12) -> 486014.77 | ... Q13: =SUM(Q10:Q12) -> 331770.51
B16: Advances | D16: ='Balance Sheet'!C30-'Balance Sheet'!D30 -> -293477.02 | E16: ='Balance Sheet'!D30-'Balance Sheet'!E30 -> -473826.13 | F16: ='Balance Sheet'!E30-'Balance Sheet'!F30 -> -516370.54 | G16: ='Balance Sheet'!F30-'Balance Sheet'!G30 -> -466558.07 | H16: ='Balance Sheet'!G30-'Balance Sheet'!H30 -> -687192.8 | I16: ='Balance Sheet'!H30-'Balance Sheet'!I30 -> -552407.5 | J16: ='Balance Sheet'!I30-'Balance Sheet'!J30 -> -541612.02 | K16: ='Balance Sheet'!J30-'Balance Sheet'!K30 -> -524624.76 | ... Q16: ='Balance Sheet'!P30-'Balance Sheet'!Q30 -> -358127.02
B17: Other Assets | D17: ='Balance Sheet'!C32-'Balance Sheet'!D32 -> 10142.993 | E17: ='Balance Sheet'!D32-'Balance Sheet'!E32 -> -58786.566 | F17: ='Balance Sheet'!E32-'Balance Sheet'!F32 -> -56988.38 | G17: ='Balance Sheet'!F32-'Balance Sheet'!G32 -> 14194.565 | H17: ='Balance Sheet'!G32-'Balance Sheet'!H32 -> -165732.35 | I17: ='Balance Sheet'!H32-'Balance Sheet'!I32 -> -69270.452 | J17: ='Balance Sheet'!I32-'Balance Sheet'!J32 -> -67916.728 | K17: ='Balance Sheet'!J32-'Balance Sheet'!K32 -> -65786.569 | ... Q17: ='Balance Sheet'!P32-'Balance Sheet'!Q32 -> -44908.189
B18: Total | D18: =SUM(D16:D17) -> -283334.02 | E18: =SUM(E15:E17) -> -532612.69 | F18: =SUM(F15:F17) -> -573358.92 | G18: =SUM(G15:G17) -> -452363.5 | H18: =SUM(H15:H17) -> -852925.15 | I18: =SUM(I15:I17) -> -621677.95 | J18: =SUM(J15:J17) -> -609528.75 | K18: =SUM(K15:K17) -> -590411.33 | L18: =SUM(L15:L17) -> -565728.24 | ... Q18: =SUM(Q15:Q17) -> -403035.21
B20: Change in Net Working Capital | D20: =D13+D18 -> -38823.918 | E20: =E13+E18 -> -288367.82 | F20: =F13+F18 -> -274379.23 | G20: =G13+G18 -> -293816.19 | H20: =H13+H18 -> 243521.13 | I20: =I13+I18 -> -109925.12 | J20: =J13+J18 -> -107776.9 | K20: =K13+K18 -> -104396.55 | ... Q20: =Q13+Q18 -> -71264.7

Sheet BS_Items
B1: State Bank of India
B2: BSE: 500112 | NSE: SBIN
C3: 10000
B4: (INR in Crores)
B5: Balance Sheet Forecast
B7: Particular | C7: 2021 | D7: =C7+1 -> 2022 | E7: =D7+1 -> 2023 | F7: =E7+1 -> 2024 | G7: =F7+1 -> 2025 | H7: =G7+1 -> 2026 | I7: =H7+1 -> 2027 | J7: =I7+1 -> 2028 | K7: =J7+1 -> 2029 | ... Q7: =P7+1 -> 2035
C8: Audited | D8: Audited | E8: Audited | F8: Audited | G8: Audited | H8: Forecasted | I8: Forecasted | J8: Forecasted | K8: Forecasted | L8: Forecasted | M8: Forecasted | N8: Forecasted | O8: Forecasted | P8: Forecasted | Q8: Forecasted
B10: Total Income | C10: ='Revenue_Build Up'!C10 -> 385337.89 | D10: ='Revenue_Build Up'!D10 -> 406973.09 | E10: ='Revenue_Build Up'!E10 -> 473378.14 | F10: ='Revenue_Build Up'!F10 -> 594574.9 | G10: ='Revenue_Build Up'!G10 -> 663343.32 | H10: ='Revenue_Build Up'!H10 -> 747480.98 | I10: ='Revenue_Build Up'!I10 -> 831100.29 | J10: ='Revenue_Build Up'!J10 -> 913085.46 | ... Q10: ='Revenue_Build Up'!Q10 -> 1385198
B12: =BS_Input!B12 -> CASA Deposits | C12: =BS_Input!C12 -> 1686779.5 | D12: =BS_Input!D12 -> 1819712 | E12: =BS_Input!E12 -> 1906519.4 | F12: =BS_Input!F12 -> 1982929.8 | G12: =BS_Input!G12 -> 2108936.6 | H12: =H$10*H13 -> 2898806.6 | I12: =I$10*I13 -> 3223090.7 | J12: =J$10*J13 -> 3541037.5 | K12: =K$10*K13 -> 3849012.1 | L12: =L$10*L13 -> 4144111.3 | M12: =M$10*M13 -> 4424151.8 | N12: =N$10*N13 -> 4687621.2 | O12: =O$10*O13 -> 4933605.5 | ... Q12: =Q$10*Q13 -> 5371937.5
B13: =B12&" x of Total Income" -> CASA Deposits x of Total Income | C13: =C12/C$10 -> 4.3774037 | D13: =D12/D$10 -> 4.4713324 | E13: =E12/E$10 -> 4.0274767 | F13: =F12/F$10 -> 3.3350379 | G13: =G12/G$10 -> 3.1792535 | H13: =AVERAGE(C13:G13) -> 3.8781008 | I13: =H13 -> 3.8781008 | J13: =I13 -> 3.8781008 | K13: =J13 -> 3.8781008 | L13: =K13 -> 3.8781008 | M13: =L13 -> 3.8781008 | N13: =M13 -> 3.8781008 | O13: =N13 -> 3.8781008 | P13: =O13 -> 3.8781008 | Q13: =P13 -> 3.8781008
B15: =BS_Input!B13 -> Fixed Deposits | C15: =BS_Input!C13 -> 2028551.7 | D15: =BS_Input!D13 -> 2267698.6 | E15: =BS_Input!E13 -> 2562016.1 | F15: =BS_Input!F13 -> 2983607.7 | G15: =BS_Input!G13 -> 3330961.4 | H15: =H$10*H16 -> 3929982.7 | I15: =I$10*I16 -> 4369622.6 | J15: =J$10*J16 -> 4800670.7 | K15: =K$10*K16 -> 5218199.4 | L15: =L$10*L16 -> 5618272.5 | M15: =M$10*M16 -> 5997930.3 | N15: =N$10*N16 -> 6355122.2 | O15: =O$10*O16 -> 6688609 | ... Q15: =Q$10*Q16 -> 7282866.5
B16: =B15 & " x of Total Inomce" -> Fixed Deposits x of Total Inomce | C16: =C15/C$10 -> 5.2643454 | D16: =D15/D$10 -> 5.5721095 | E16: =E15/E$10 -> 5.4121977 | F16: =F15/F$10 -> 5.0180518 | G16: =G15/G$10 -> 5.0214743 | H16: =AVERAGE(C16:G16) -> 5.2576357 | I16: =H16 -> 5.2576357 | J16: =I16 -> 5.2576357 | K16: =J16 -> 5.2576357 | L16: =K16 -> 5.2576357 | M16: =L16 -> 5.2576357 | N16: =M16 -> 5.2576357 | O16: =N16 -> 5.2576357 | P16: =O16 -> 5.2576357 | Q16: =P16 -> 5.2576357
B18: Borrowings | C18: =BS_Input!C14 -> 433796.21 | D18: =BS_Input!D14 -> 449159.78 | E18: =BS_Input!E14 -> 521151.95 | F18: =BS_Input!F14 -> 639609.5 | G18: =BS_Input!G14 -> 610857.24 | H18: =H$10*H19 -> 796359.52 | I18: =I$10*I19 -> 885446.78 | J18: =J$10*J19 -> 972793.04 | K18: =K$10*K19 -> 1057399.7 | L18: =L$10*L19 -> 1138469.3 | M18: =M$10*M19 -> 1215402 | N18: =N$10*N19 -> 1287782.3 | O18: =O$10*O19 -> 1355359 | ... Q18: =Q$10*Q19 -> 1475777.5
B19: =B18 & " x of Total Inomce" -> Borrowings x of Total Inomce | C19: =C18/C$10 -> 1.1257554 | D19: =D18/D$10 -> 1.1036597 | E19: =E18/E$10 -> 1.100921 | F19: =F18/F$10 -> 1.0757425 | G19: =G18/G$10 -> 0.92087646 | H19: =AVERAGE(C19:G19) -> 1.065391 | I19: =H19 -> 1.065391 | J19: =I19 -> 1.065391 | K19: =J19 -> 1.065391 | L19: =K19 -> 1.065391 | M19: =L19 -> 1.065391 | N19: =M19 -> 1.065391 | O19: =N19 -> 1.065391 | P19: =O19 -> 1.065391 | Q19: =P19 -> 1.065391
B21: Other Liabilities and Provisions | C21: =BS_Input!C15 -> 411303.62 | D21: =BS_Input!D15 -> 507517.68 | E21: =BS_Input!E15 -> 592962.92 | F21: =BS_Input!F15 -> 697074.68 | G21: =BS_Input!G15 -> 758367.48 | H21: =H$10*H22 -> 879441.42 | I21: =I$10*I22 -> 977822.9 | J21: =J$10*J22 -> 1074281.7 | K21: =K$10*K22 -> 1167715.2 | L21: =L$10*L22 -> 1257242.6 | M21: =M$10*M22 -> 1342201.4 | N21: =N$10*N22 -> 1422132.9 | O21: =O$10*O22 -> 1496759.7 | ... Q21: =Q$10*Q22 -> 1629741.1
B22: =B21 & " x of Income" -> Other Liabilities and Provisions x of Income | C22: =C21/C$10 -> 1.0673843 | D22: =D21/D$10 -> 1.2470546 | E22: =E21/E$10 -> 1.25262 | F22: =F21/F$10 -> 1.1723917 | G22: =G21/G$10 -> 1.1432503 | H22: =AVERAGE(C22:G22) -> 1.1765402 | I22: =H22 -> 1.1765402 | J22: =I22 -> 1.1765402 | K22: =J22 -> 1.1765402 | L22: =K22 -> 1.1765402 | M22: =L22 -> 1.1765402 | N22: =M22 -> 1.1765402 | O22: =N22 -> 1.1765402 | P22: =O22 -> 1.1765402 | Q22: =P22 -> 1.1765402
B24: Investments | C24: =BS_Input!C21 -> 1595100.3 | D24: =BS_Input!D21 -> 1776489.9 | E24: =BS_Input!E21 -> 1913107.9 | F24: =BS_Input!F21 -> 2110548.2 | G24: =BS_Input!G21 -> 2205601.1 | H24: =H$10*H25 -> 2903314.9 | I24: =I$10*I25 -> 3228103.3 | J24: =J$10*J25 -> 3546544.5 | K24: =K$10*K25 -> 3854998.1 | L24: =L$10*L25 -> 4150556.2 | M24: =M$10*M25 -> 4431032.3 | N24: =N$10*N25 -> 4694911.4 | O24: =O$10*O25 -> 4941278.2 | ... Q24: =Q$10*Q25 -> 5380292
B25: =B24 & " x of Income" -> Investments x of Income | C25: =C24/C$10 -> 4.1394846 | D25: =D24/D$10 -> 4.3651287 | E25: =E24/E$10 -> 4.0413946 | F25: =F24/F$10 -> 3.5496759 | G25: =G24/G$10 -> 3.3249768 | H25: =AVERAGE(C25:G25) -> 3.8841321 | I25: =H25 -> 3.8841321 | J25: =I25 -> 3.8841321 | K25: =J25 -> 3.8841321 | L25: =K25 -> 3.8841321 | M25: =L25 -> 3.8841321 | N25: =M25 -> 3.8841321 | O25: =N25 -> 3.8841321 | P25: =O25 -> 3.8841321 | Q25: =P25 -> 3.8841321
B27: Advances | C27: =BS_Input!C22 -> 2500599 | D27: =BS_Input!D22 -> 2794076 | E27: =BS_Input!E22 -> 3267902.1 | F27: =BS_Input!F22 -> 3784272.7 | G27: =BS_Input!G22 -> 4250830.7 | H27: =H$10*H28 -> 4938023.5 | I27: =I$10*I28 -> 5490431 | J27: =J$10*J28 -> 6032043.1 | K27: =K$10*K28 -> 6556667.8 | L27: =L$10*L28 -> 7059359.8 | M27: =M$10*M28 -> 7536399.7 | N27: =N$10*N28 -> 7985211.4 | O27: =O$10*O28 -> 8404237.6 | ... Q27: =Q$10*Q28 -> 9150922.1
B28: =B27 & " x of Income" -> Advances x of Income | C28: =C27/C$10 -> 6.489367 | D28: =D27/D$10 -> 6.8655055 | E28: =E27/E$10 -> 6.9033651 | F28: =F27/F$10 -> 6.3646693 | G28: =G27/G$10 -> 6.4081911 | H28: =AVERAGE(C28:G28) -> 6.6062196 | I28: =H28 -> 6.6062196 | J28: =I28 -> 6.6062196 | K28: =J28 -> 6.6062196 | L28: =K28 -> 6.6062196 | M28: =L28 -> 6.6062196 | N28: =M28 -> 6.6062196 | O28: =N28 -> 6.6062196 | P28: =O28 -> 6.6062196 | Q28: =P28 -> 6.6062196
B30: Other Assets | C30: =BS_Input!C24 -> 362045.47 | D30: =BS_Input!D24 -> 351902.48 | E30: =BS_Input!E24 -> 410689.04 | F30: =BS_Input!F24 -> 467677.42 | G30: =BS_Input!G24 -> 453482.86 | H30: =H$10*H31 -> 619215.21 | I30: =I$10*I31 -> 688485.66 | J30: =J$10*J31 -> 756402.39 | K30: =K$10*K31 -> 822188.96 | L30: =L$10*L31 -> 885225.21 | M30: =M$10*M31 -> 945044.77 | N30: =N$10*N31 -> 1001324.6 | O30: =O$10*O31 -> 1053869.4 | ... Q30: =Q$10*Q31 -> 1147501.6
B31: =B30 & " x of Income" -> Other Assets x of Income | C31: =C30/C$10 -> 0.93955326 | D31: =D30/D$10 -> 0.86468242 | E31: =E30/E$10 -> 0.86757078 | F31: =F30/F$10 -> 0.78657444 | G31: =G30/G$10 -> 0.68363221 | H31: =AVERAGE(C31:G31) -> 0.82840262 | I31: =H31 -> 0.82840262 | J31: =I31 -> 0.82840262 | K31: =J31 -> 0.82840262 | L31: =K31 -> 0.82840262 | M31: =L31 -> 0.82840262 | N31: =M31 -> 0.82840262 | O31: =N31 -> 0.82840262 | P31: =O31 -> 0.82840262 | Q31: =P31 -> 0.82840262

Sheet Income Statement
B1: State Bank of India
B2: BSE: 500112 | NSE: SBIN
C3: 10000
B4: (INR in Crores)
B5: Income Statement
B7: Particular | C7: 2021 | D7: =C7+1 -> 2022 | E7: =D7+1 -> 2023 | F7: =E7+1 -> 2024 | G7: =F7+1 -> 2025 | H7: =G7+1 -> 2026 | I7: =H7+1 -> 2027 | J7: =I7+1 -> 2028 | K7: =J7+1 -> 2029 | ... Q7: =P7+1 -> 2035
C8: Audited | D8: Audited | E8: Audited | F8: Audited | G8: Audited | H8: Forecasted | I8: Forecasted | J8: Forecasted | K8: Forecasted | L8: Forecasted | M8: Forecasted | N8: Forecasted | O8: Forecasted | P8: Forecasted | Q8: Forecasted
B10: Total Income | C10: ='Revenue_Build Up'!C10 -> 385337.89 | D10: ='Revenue_Build Up'!D10 -> 406973.09 | E10: ='Revenue_Build Up'!E10 -> 473378.14 | F10: ='Revenue_Build Up'!F10 -> 594574.9 | G10: ='Revenue_Build Up'!G10 -> 663343.32 | H10: ='Revenue_Build Up'!H10 -> 747480.98 | I10: ='Revenue_Build Up'!I10 -> 831100.29 | J10: ='Revenue_Build Up'!J10 -> 913085.46 | ... Q10: ='Revenue_Build Up'!Q10 -> 1385198
B12: EXPENDITURE
B13: Interest on Deposit | C13: =Cost_BuildUp!C12 -> 143060.45 | D13: =Cost_BuildUp!D12 -> 141765.28 | E13: =Cost_BuildUp!E12 -> 163518.78 | F13: =Cost_BuildUp!F12 -> 223278.71 | G13: =Cost_BuildUp!G12 -> 259228.12 | H13: =Cost_BuildUp!H12 -> 273779.39 | I13: =Cost_BuildUp!I12 -> 304406.58 | J13: =Cost_BuildUp!J12 -> 334435.24 | ... Q13: =Cost_BuildUp!Q12 -> 507355.6
B14: Operating expenses | C14: =Cost_BuildUp!C15 -> 142899.04 | D14: =Cost_BuildUp!D15 -> 161647.85 | E14: =Cost_BuildUp!E15 -> 168795.17 | F14: =Cost_BuildUp!F15 -> 200776.45 | G14: =Cost_BuildUp!G15 -> 198820.6 | H14: =Cost_BuildUp!H15 -> 263414.95 | I14: =Cost_BuildUp!I15 -> 292882.69 | J14: =Cost_BuildUp!J15 -> 321774.56 | ... Q14: =Cost_BuildUp!Q15 -> 488148.69
B15: Provisions and contingencies | C15: =Cost_BuildUp!C18 -> 54618.409 | D15: =Cost_BuildUp!D18 -> 40059.148 | E15: =Cost_BuildUp!E18 -> 37024.409 | F15: =Cost_BuildUp!F18 -> 30806.757 | G15: =Cost_BuildUp!G18 -> 46809.309 | H15: =Cost_BuildUp!H18 -> 65892.77 | I15: =Cost_BuildUp!I18 -> 73264.071 | J15: =Cost_BuildUp!J18 -> 80491.318 | ... Q15: =Cost_BuildUp!Q18 -> 122109.5
B16: Total | C16: =SUM(C13:C15) -> 340577.89 | D16: =SUM(D13:D15) -> 343472.28 | E16: =SUM(E13:E15) -> 369338.36 | F16: =SUM(F13:F15) -> 454861.92 | G16: =SUM(G13:G15) -> 504858.03 | H16: =SUM(H13:H15) -> 603087.11 | I16: =SUM(I13:I15) -> 670553.34 | J16: =SUM(J13:J15) -> 736701.11 | ... Q16: =SUM(Q13:Q15) -> 1117613.8
B18: EBITDA | C18: =C10-C16 -> 44759.997 | D18: =D10-D16 -> 63500.806 | E18: =E10-E16 -> 104039.78 | F18: =F10-F16 -> 139712.99 | G18: =G10-G16 -> 158485.29 | H18: =H10-H16 -> 144393.87 | I18: =I10-I16 -> 160546.95 | J18: =J10-J16 -> 176384.35 | ... Q18: =Q10-Q16 -> 267584.2
B20: Depreciation & Amortization Expenses | C20: =FAS!C54 -> 3711.0636 | D20: =FAS!D54 -> 3691.27 | E20: =FAS!E54 -> 3695.5986 | F20: =FAS!F54 -> 3849.1245 | G20: =FAS!G54 -> 3991.4767 | H20: =FAS!H54 -> 3446.3444 | I20: =FAS!I54 -> 3463.5761 | J20: =FAS!J54 -> 3480.894 | ... Q20: =FAS!Q54 -> 3604.5681
B22: EBIT | C22: =C18-C20 -> 41048.934 | D22: =D18-D20 -> 59809.536 | E22: =E18-E20 -> 100344.19 | F22: =F18-F20 -> 135863.86 | G22: =G18-G20 -> 154493.82 | H22: =H18-H20 -> 140947.53 | I22: =I18-I20 -> 157083.37 | J22: =J18-J20 -> 172903.45 | ... Q22: =Q18-Q20 -> 263979.63
B24: Interest on Borrowings | C24: ='Debt Schedules'!C14 -> 12949.721 | D24: ='Debt Schedules'!D14 -> 14429.061 | E24: ='Debt Schedules'!E14 -> 26462.034 | F24: ='Debt Schedules'!F14 -> 36457.335 | G24: ='Debt Schedules'!G14 -> 41715.216 | H24: ='Debt Schedules'!H14 -> 34704.028 | I24: ='Debt Schedules'!I14 -> 41475.808 | J24: ='Debt Schedules'!J14 -> 45826.917 | ... Q24: ='Debt Schedules'!Q14 -> 71365.337
B25: Add: Share in Profit/(Loss) of Associates | C25: ='Revenue_Build Up'!C80 -> -391.9045 | D25: ='Revenue_Build Up'!D80 -> 827.0133 | E25: ='Revenue_Build Up'!E80 -> 1191.4521 | F25: ='Revenue_Build Up'!F80 -> 1405.1543 | G25: ='Revenue_Build Up'!G80 -> 1505.4709 | H25: ='Revenue_Build Up'!H80 -> 1220.6055 | I25: ='Revenue_Build Up'!I80 -> 1357.1524 | J25: ='Revenue_Build Up'!J80 -> 1491.0308 | ... Q25: ='Revenue_Build Up'!Q80 -> 2261.971
B26: Less: Minority Interest | C26: ='Revenue_Build Up'!C83 -> 1482.3573 | D26: ='Revenue_Build Up'!D83 -> 1809.3049 | E26: ='Revenue_Build Up'!E83 -> 2101.7092 | F26: ='Revenue_Build Up'!F83 -> 2458.7491 | G26: ='Revenue_Build Up'!G83 -> 2961.2882 | H26: ='Revenue_Build Up'!H83 -> 3189.0477 | I26: ='Revenue_Build Up'!I83 -> 3545.8006 | J26: ='Revenue_Build Up'!J83 -> 3895.5815 | ... Q26: ='Revenue_Build Up'!Q83 -> 5909.7992
B28: EBT | C28: =C22-C24+C25-C26 -> 26224.951 | D28: =D22-D24+D25-D26 -> 44398.183 | E28: =E22-E24+E25-E26 -> 72971.895 | F28: =F22-F24+F25-F26 -> 98352.934 | G28: =G22-G24+G25-G26 -> 111322.78 | H28: =H22-H24+H25-H26 -> 104275.06 | I28: =I22-I24+I25-I26 -> 113418.91 | J28: =J22-J24+J25-J26 -> 124671.99 | ... Q28: =Q22-Q24+Q25-Q26 -> 188966.47
B30: Tax Expenses | C30: =Cost_BuildUp!C21 -> -3819.4934 | D30: =Cost_BuildUp!D21 -> -9024.303 | E30: =Cost_BuildUp!E21 -> -17323.722 | F30: =Cost_BuildUp!F21 -> -31268.268 | G30: =Cost_BuildUp!G21 -> -33761.445 | H30: =Cost_BuildUp!H21 -> -31282.518 | I30: =Cost_BuildUp!I21 -> -34025.674 | J30: =Cost_BuildUp!J21 -> -37401.596 | ... Q30: =Cost_BuildUp!Q21 -> -56689.941
B32: Post Tax Income | C32: =SUM(C28:C30) -> 22405.458 | D32: =SUM(D28:D30) -> 35373.88 | E32: =SUM(E28:E30) -> 55648.173 | F32: =SUM(F28:F30) -> 67084.666 | G32: =SUM(G28:G30) -> 77561.337 | H32: =SUM(H28:H30) -> 72992.541 | I32: =SUM(I28:I30) -> 79393.24 | J32: =SUM(J28:J30) -> 87270.39 | ... Q32: =SUM(Q28:Q30) -> 132276.53
B34: Dividends Paid | C34: ='Cash Flow'!C52 -> 0 | D34: ='Cash Flow'!D52 -> -3569.8446 | E34: ='Cash Flow'!E52 -> -6336.7216 | F34: ='Cash Flow'!F52 -> -10084.811 | G34: ='Cash Flow'!G52 -> -12226.718 | H34: =H35*-H32 -> -9539.352 | I34: =I35*-I32 -> -10375.856 | J34: =J35*-J32 -> -11405.316 | K34: =K35*-K32 -> -12400.054 | L34: =L35*-L32 -> -13351.073 | M34: =M35*-M32 -> -14251.712 | N34: =N35*-N32 -> -15097.464 | O34: =O35*-O32 -> -15885.725 | ... Q34: =Q35*-Q32 -> -17287.141
B35: Dividened PayOut | C35: =-C34/C32 -> 0 | D35: =-D34/D32 -> 0.10091753 | E35: =-E34/E32 -> 0.11387115 | F35: =-F34/F32 -> 0.15032961 | G35: =-G34/G32 -> 0.15763934 | H35: =AVERAGE(D35:G35) -> 0.13068941 | I35: =H35 -> 0.13068941 | J35: =I35 -> 0.13068941 | K35: =J35 -> 0.13068941 | L35: =K35 -> 0.13068941 | M35: =L35 -> 0.13068941 | N35: =M35 -> 0.13068941 | O35: =N35 -> 0.13068941 | P35: =O35 -> 0.13068941 | Q35: =P35 -> 0.13068941
B37: Retained Earning | C37: =C32+C34 -> 22405.458 | D37: =D32+D34 -> 31804.035 | E37: =E32+E34 -> 49311.451 | F37: =F32+F34 -> 56999.855 | G37: =G32+G34 -> 65334.619 | H37: =H32+H34 -> 63453.189 | I37: =I32+I34 -> 69017.384 | J37: =J32+J34 -> 75865.074 | ... Q37: =Q32+Q34 -> 114989.39
B38: Retained Earning % | C38: =C37/C32 -> 1 | D38: =D37/D32 -> 0.89908247 | E38: =E37/E32 -> 0.88612885 | F38: =F37/F32 -> 0.84967039 | G38: =G37/G32 -> 0.84236066 | H38: =H37/H32 -> 0.86931059 | I38: =I37/I32 -> 0.86931059 | J38: =J37/J32 -> 0.86931059 | ... Q38: =Q37/Q32 -> 0.86931059

Sheet Balance Sheet
B1: State Bank of India
B2: BSE: 500112 | NSE: SBIN
C3: 10000
B4: (INR in Crores)
B5: Balance Sheet
B7: Particular | C7: 2021 | D7: =C7+1 -> 2022 | E7: =D7+1 -> 2023 | F7: =E7+1 -> 2024 | G7: =F7+1 -> 2025 | H7: =G7+1 -> 2026 | I7: =H7+1 -> 2027 | J7: =I7+1 -> 2028 | K7: =J7+1 -> 2029 | ... Q7: =P7+1 -> 2035
C8: Audited | D8: Audited | E8: Audited | F8: Audited | G8: Audited | H8: Forecasted | I8: Forecasted | J8: Forecasted | K8: Forecasted | L8: Forecasted | M8: Forecasted | N8: Forecasted | O8: Forecasted | P8: Forecasted | Q8: Forecasted
B9: Master Check | C9: =IF(SUM(C35:Q35)=0,"OK","ERROR") -> OK
B10: EQUITY AND LIABILITIES
B11: EQUITY
B12: Capital | C12: =BS_Input!C9 -> 892.4612 | D12: =BS_Input!D9 -> 892.4612 | E12: =BS_Input!E9 -> 892.4612 | F12: =BS_Input!F9 -> 892.4612 | G12: =BS_Input!G9 -> 892.462 | H12: =G12 -> 892.462 | I12: =H12 -> 892.462 | J12: =I12 -> 892.462 | K12: =J12 -> 892.462 | L12: =K12 -> 892.462 | M12: =L12 -> 892.462 | N12: =M12 -> 892.462 | O12: =N12 -> 892.462 | ... Q12: =P12 -> 892.462
B13: Reserves & Surplus | C13: =BS_Input!C10 -> 274669.1 | D13: =BS_Input!D10 -> 304695.58 | E13: =BS_Input!E10 -> 358038.86 | F13: =BS_Input!F10 -> 414046.71 | G13: =BS_Input!G10 -> 486144.3 | H13: =G13+'Income Statement'!H37 -> 549597.49 | I13: =H13+'Income Statement'!I37 -> 618614.87 | J13: =I13+'Income Statement'!J37 -> 694479.94 | K13: =J13+'Income Statement'!K37 -> 776961.75 | L13: =K13+'Income Statement'!L37 -> 865769.47 | M13: =L13+'Income Statement'!M37 -> 960568.01 | N13: =M13+'Income Statement'!N37 -> 1060992.3 | O13: =N13+'Income Statement'!O37 -> 1166659.8 | ... Q13: =P13+'Income Statement'!Q37 -> 1392171
B14: Minority Interest | C14: =BS_Input!C11 -> 9625.9166 | D14: =BS_Input!D11 -> 11207.423 | E14: =BS_Input!E11 -> 12836.619 | F14: =BS_Input!F11 -> 15617.962 | G14: =BS_Input!G11 -> 18025.839 | H14: =(G14/SUM(G12:G13))*SUM(H12:H13) -> 20374.321 | I14: =(H14/SUM(H12:H13))*SUM(I12:I13) -> 22928.74 | J14: =(I14/SUM(I12:I13))*SUM(J12:J13) -> 25736.601 | K14: =(J14/SUM(J12:J13))*SUM(K12:K13) -> 28789.356 | L14: =(K14/SUM(K12:K13))*SUM(L12:L13) -> 32076.241 | M14: =(L14/SUM(L12:L13))*SUM(M12:M13) -> 35584.853 | N14: =(M14/SUM(M12:M13))*SUM(N12:N13) -> 39301.68 | O14: =(N14/SUM(N12:N13))*SUM(O12:O13) -> 43212.568 | ... Q14: =(P14/SUM(P12:P13))*SUM(Q12:Q13) -> 51559.02
B15: TOTAL EQUITY | C15: =SUM(C12:C14) -> 285187.48 | D15: =SUM(D12:D14) -> 316795.47 | E15: =SUM(E12:E14) -> 371767.94 | F15: =SUM(F12:F14) -> 430557.13 | G15: =SUM(G12:G14) -> 505062.6 | H15: =SUM(H12:H14) -> 570864.27 | I15: =SUM(I12:I14) -> 642436.07 | J15: =SUM(J12:J14) -> 721109.01 | ... Q15: =SUM(Q12:Q14) -> 1444622.5
B17: LIABILITIES
B18: CASA Deposits | C18: =BS_Items!C12 -> 1686779.5 | D18: =BS_Items!D12 -> 1819712 | E18: =BS_Items!E12 -> 1906519.4 | F18: =BS_Items!F12 -> 1982929.8 | G18: =BS_Items!G12 -> 2108936.6 | H18: =BS_Items!H12 -> 2898806.6 | I18: =BS_Items!I12 -> 3223090.7 | J18: =BS_Items!J12 -> 3541037.5 | ... Q18: =BS_Items!Q12 -> 5371937.5
B19: Fixed Deposits | C19: =BS_Items!C15 -> 2028551.7 | D19: =BS_Items!D15 -> 2267698.6 | E19: =BS_Items!E15 -> 2562016.1 | F19: =BS_Items!F15 -> 2983607.7 | G19: =BS_Items!G15 -> 3330961.4 | H19: =BS_Items!H15 -> 3929982.7 | I19: =BS_Items!I15 -> 4369622.6 | J19: =BS_Items!J15 -> 4800670.7 | ... Q19: =BS_Items!Q15 -> 7282866.5
B20: Borrowings | C20: =BS_Input!C14 -> 433796.21 | D20: =BS_Input!D14 -> 449159.78 | E20: =BS_Input!E14 -> 521151.95 | F20: =BS_Input!F14 -> 639609.5 | G20: =BS_Input!G14 -> 610857.24 | H20: =BS_Items!H18 -> 796359.52 | I20: =BS_Items!I18 -> 885446.78 | J20: =BS_Items!J18 -> 972793.04 | K20: =BS_Items!K18 -> 1057399.7 | L20: =BS_Items!L18 -> 1138469.3 | M20: =BS_Items!M18 -> 1215402 | N20: =BS_Items!N18 -> 1287782.3 | O20: =BS_Items!O18 -> 1355359 | ... Q20: =BS_Items!Q18 -> 1475777.5
B21: Other Liabilities and Provisions | C21: =BS_Input!C15 -> 411303.62 | D21: =BS_Input!D15 -> 507517.68 | E21: =BS_Input!E15 -> 592962.92 | F21: =BS_Input!F15 -> 697074.68 | G21: =BS_Input!G15 -> 758367.48 | H21: =BS_Items!H21 -> 879441.42 | I21: =BS_Items!I21 -> 977822.9 | J21: =BS_Items!J21 -> 1074281.7 | K21: =BS_Items!K21 -> 1167715.2 | L21: =BS_Items!L21 -> 1257242.6 | M21: =BS_Items!M21 -> 1342201.4 | N21: =BS_Items!N21 -> 1422132.9 | O21: =BS_Items!O21 -> 1496759.7 | ... Q21: =BS_Items!Q21 -> 1629741.1
B22: TOTAL LIABILITIES | C22: =SUM(C18:C21) -> 4560431.1 | D22: =SUM(D18:D21) -> 5044088.1 | E22: =SUM(E18:E21) -> 5582650.4 | F22: =SUM(F18:F21) -> 6303221.7 | G22: =SUM(G18:G21) -> 6809122.7 | H22: =SUM(H18:H21) -> 8504590.3 | I22: =SUM(I18:I21) -> 9455983 | J22: =SUM(J18:J21) -> 10388783 | ... Q22: =SUM(Q18:Q21) -> 15760323
B24: TOTAL EQUITY & LIABILITIES | C24: =C22+C15 -> 4845618.5 | D24: =D22+D15 -> 5360883.5 | E24: =E22+E15 -> 5954418.3 | F24: =F22+F15 -> 6733778.8 | G24: =G22+G15 -> 7314185.3 | H24: =H22+H15 -> 9075454.6 | I24: =I22+I15 -> 10098419 | J24: =J22+J15 -> 11109892 | ... Q24: =Q22+Q15 -> 17204945
B26: ASSETS
B27: Cash and Balances with Reserve Bank of India | C27: =BS_Input!C19 -> 213498.62 | D27: =BS_Input!D19 -> 318492.43 | E27: =BS_Input!E19 -> 247321.05 | F27: =BS_Input!F19 -> 225356.34 | G27: =BS_Input!G19 -> 227485.16 | H27: ='Cash Flow'!H64-'Balance Sheet'!H28 -> 427402.97 | I27: ='Cash Flow'!I64-'Balance Sheet'!I28 -> 498554.76 | J27: ='Cash Flow'!J64-'Balance Sheet'!J28 -> 576684.68 | K27: ='Cash Flow'!K64-'Balance Sheet'!K28 -> 661497.86 | L27: ='Cash Flow'!L64-'Balance Sheet'!L28 -> 752648.51 | M27: ='Cash Flow'!M64-'Balance Sheet'!M28 -> 849755.79 | N27: ='Cash Flow'!N64-'Balance Sheet'!N28 -> 952418 | O27: ='Cash Flow'!O64-'Balance Sheet'!O28 -> 1060224.5 | ... Q27: ='Cash Flow'!Q64-'Balance Sheet'!Q28 -> 1289640.8
B28: Balances with Banks and Money at Call & Short Notice | C28: =BS_Input!C20 -> 134208.42 | D28: =BS_Input!D20 -> 80412.692 | E28: =BS_Input!E20 -> 70990.86 | F28: =BS_Input!F20 -> 101215.97 | G28: =BS_Input!G20 -> 130447.79 | H28: =G28 -> 130447.79 | I28: =H28 -> 130447.79 | J28: =I28 -> 130447.79 | K28: =J28 -> 130447.79 | L28: =K28 -> 130447.79 | M28: =L28 -> 130447.79 | N28: =M28 -> 130447.79 | O28: =N28 -> 130447.79 | ... Q28: =P28 -> 130447.79
B29: Investments | C29: =BS_Input!C21 -> 1595100.3 | D29: =BS_Input!D21 -> 1776489.9 | E29: =BS_Input!E21 -> 1913107.9 | F29: =BS_Input!F21 -> 2110548.2 | G29: =BS_Input!G21 -> 2205601.1 | H29: =BS_Items!H24 -> 2903314.9 | I29: =BS_Items!I24 -> 3228103.3 | J29: =BS_Items!J24 -> 3546544.5 | K29: =BS_Items!K24 -> 3854998.1 | L29: =BS_Items!L24 -> 4150556.2 | M29: =BS_Items!M24 -> 4431032.3 | N29: =BS_Items!N24 -> 4694911.4 | O29: =BS_Items!O24 -> 4941278.2 | ... Q29: =BS_Items!Q24 -> 5380292
B30: Advances | C30: =BS_Input!C22 -> 2500599 | D30: =BS_Input!D22 -> 2794076 | E30: =BS_Input!E22 -> 3267902.1 | F30: =BS_Input!F22 -> 3784272.7 | G30: =BS_Input!G22 -> 4250830.7 | H30: =BS_Items!H27 -> 4938023.5 | I30: =BS_Items!I27 -> 5490431 | J30: =BS_Items!J27 -> 6032043.1 | K30: =BS_Items!K27 -> 6556667.8 | L30: =BS_Items!L27 -> 7059359.8 | M30: =BS_Items!M27 -> 7536399.7 | N30: =BS_Items!N27 -> 7985211.4 | O30: =BS_Items!O27 -> 8404237.6 | ... Q30: =BS_Items!Q27 -> 9150922.1
B31: Fixed Assets | C31: =BS_Input!C23 -> 40166.788 | D31: =BS_Input!D23 -> 39510.031 | E31: =BS_Input!E23 -> 44407.381 | F31: =BS_Input!F23 -> 44708.177 | G31: =BS_Input!G23 -> 46337.695 | H31: =FAS!H50 -> 57050.196 | I31: =FAS!I50 -> 62396.51 | J31: =FAS!J50 -> 67769.556 | K31: =FAS!K50 -> 73169.467 | L31: =FAS!L50 -> 78596.378 | M31: =FAS!M50 -> 84050.423 | N31: =FAS!N50 -> 89531.739 | O31: =FAS!O50 -> 95040.461 | ... Q31: =FAS!Q50 -> 106140.67
B32: Other Assets | C32: =BS_Input!C24 -> 362045.47 | D32: =BS_Input!D24 -> 351902.48 | E32: =BS_Input!E24 -> 410689.04 | F32: =BS_Input!F24 -> 467677.42 | G32: =BS_Input!G24 -> 453482.86 | H32: =BS_Items!H30 -> 619215.21 | I32: =BS_Items!I30 -> 688485.66 | J32: =BS_Items!J30 -> 756402.39 | K32: =BS_Items!K30 -> 822188.96 | L32: =BS_Items!L30 -> 885225.21 | M32: =BS_Items!M30 -> 945044.77 | N32: =BS_Items!N30 -> 1001324.6 | O32: =BS_Items!O30 -> 1053869.4 | ... Q32: =BS_Items!Q30 -> 1147501.6
B33: TOTAL | C33: =SUM(C27:C32) -> 4845618.5 | D33: =SUM(D27:D32) -> 5360883.5 | E33: =SUM(E27:E32) -> 5954418.3 | F33: =SUM(F27:F32) -> 6733778.8 | G33: =SUM(G27:G32) -> 7314185.3 | H33: =SUM(H27:H32) -> 9075454.6 | I33: =SUM(I27:I32) -> 10098419 | J33: =SUM(J27:J32) -> 11109892 | ... Q33: =SUM(Q27:Q32) -> 17204945
B35: Check | C35: =ROUND(C33,0)-ROUND(C24,0) -> 0 | D35: =ROUND(D33,0)-ROUND(D24,0) -> 0 | E35: =ROUND(E33,0)-ROUND(E24,0) -> 0 | F35: =ROUND(F33,0)-ROUND(F24,0) -> 0 | G35: =ROUND(G33,0)-ROUND(G24,0) -> 0 | H35: =ROUND(H33,0)-ROUND(H24,0) -> 0 | I35: =ROUND(I33,0)-ROUND(I24,0) -> 0 | J35: =ROUND(J33,0)-ROUND(J24,0) -> 0 | ... Q35: =ROUND(Q33,0)-ROUND(Q24,0) -> 0

Sheet Cash Flow
B1: State Bank of India
B2: BSE: 500112 | NSE: SBIN
C3: 10000
B4: (INR in Crores)
B5: CashFlow Statement
B6: Particular | C6: 2021 | D6: =C6+1 -> 2022 | E6: =D6+1 -> 2023 | F6: =E6+1 -> 2024 | G6: =F6+1 -> 2025 | H6: =G6+1 -> 2026 | I6: =H6+1 -> 2027 | J6: =I6+1 -> 2028 | K6: =J6+1 -> 2029 | ... Q6: =P6+1 -> 2035
C7: Audited | D7: Audited | E7: Audited | F7: Audited | G7: Audited | H7: Forecasted | I7: Forecasted | J7: Forecasted | K7: Forecasted | L7: Forecasted | M7: Forecasted | N7: Forecasted | O7: Forecasted | P7: Forecasted | Q7: Forecasted
A8: # | B8: CASH FLOW FROM OPERATING ACTIVITIES
B9: Net Profit/(Loss) before taxes (including share in profit from associates and net of minority interest) | C9: 30921.708 | D9: 48756.343 | E9: 74488.304 | F9: 90186.447 | G9: 104909.48 | H9: ='Income Statement'!H28+'Income Statement'!H25 -> 105495.66 | I9: ='Income Statement'!I28+'Income Statement'!I25 -> 114776.07 | J9: ='Income Statement'!J28+'Income Statement'!J25 -> 126163.02 | K9: ='Income Statement'!K28+'Income Statement'!K25 -> 137166.22 | L9: ='Income Statement'!L28+'Income Statement'!L25 -> 147686.11 | M9: ='Income Statement'!M28+'Income Statement'!M25 -> 157648.95 | N9: ='Income Statement'!N28+'Income Statement'!N25 -> 167004.84 | O9: ='Income Statement'!O28+'Income Statement'!O25 -> 175724.93 | ... Q9: ='Income Statement'!Q28+'Income Statement'!Q25 -> 191228.44
B10: Adjustments for :
B11: Depreciation on Fixed Assets | C11: 3711.0636 | D11: 3691.27 | E11: 3695.5986 | F11: 3849.1245 | G11: 3991.4767 | H11: ='Income Statement'!H20 -> 3446.3444 | I11: ='Income Statement'!I20 -> 3463.5761 | J11: ='Income Statement'!J20 -> 3480.894 | K11: ='Income Statement'!K20 -> 3498.2985 | L11: ='Income Statement'!L20 -> 3515.79 | M11: ='Income Statement'!M20 -> 3533.3689 | N11: ='Income Statement'!N20 -> 3551.0358 | O11: ='Income Statement'!O20 -> 3568.791 | ... Q11: ='Income Statement'!Q20 -> 3604.5681
B12: (Profit)/Loss on sale of Fixed Assets (Net) | C12: 28.3364 | D12: 16.4047 | E12: 29.0316 | F12: 25.2054 | G12: 16.2293
B13: (Profit)/Loss on revaluation of Investments (Net) | C13: 5.1548 | D13: 445.7369 | E13: 4922.6098 | F13: -4892.7872 | G13: -5179.3794
B14: (Profit) on sale of Investments in Subsidiaries/Joint Ventures/ Associates | C14: -1577.8431 | D14: -9.7432 | E14: 0 | F14: 0 | G14: 7.519
B15: Loss on sale of Investments in Subsidiaries/Joint Ventures/ Associates | C15: 254.4131 | D15: 0 | E15: 0 | F15: 0 | G15: 0
B16: Provision for diminution in fair value & Non Performing Assets | C16: 29732.653 | D16: 15845.9 | E16: 10826.882 | F16: 12241.867 | G16: 18505.515
B17: Provision on Standard Assets | C17: 3601.3226 | D17: 4581.8142 | E17: 5641.5051 | F17: -1264.4725 | G17: 338.0915
B18: Provision on non-performing Investments | C18: 2820.9883 | D18: 3471.788 | E18: 1483.8759 | F18: -604.1107 | G18: 482.8852
B19: Other Provisions including provision for contingencies | C19: 9947.1949 | D19: 2777.1833 | E19: 232.0148 | F19: -2668.3083 | G19: 134.6773
B20: Share in Profit of Associates | C20: 391.9045 | D20: -827.0133 | E20: -1191.4521 | F20: -1405.1543 | G20: -1505.4709 | H20: =-'Income Statement'!H25 -> -1220.6055 | I20: =-'Income Statement'!I25 -> -1357.1524 | J20: =-'Income Statement'!J25 -> -1491.0308 | K20: =-'Income Statement'!K25 -> -1620.7102 | L20: =-'Income Statement'!L25 -> -1744.9681 | M20: =-'Income Statement'!M25 -> -1862.8853 | N20: =-'Income Statement'!N25 -> -1973.8248 | O20: =-'Income Statement'!O25 -> -2077.4018 | ... Q20: =-'Income Statement'!Q25 -> -2261.971
B21: Dividend from Associates | C21: -3.195 | D21: -3.195 | E21: -2.6625 | F21: -5.5719 | G21: -8.8146
B22: Interest charged on Capital Instruments | C22: 5900.3121 | D22: 5587.8874 | E22: 6543.7306 | F22: 9661.5237 | G22: 11922.815 | H22: ='Income Statement'!H24 -> 34704.028 | I22: ='Income Statement'!I24 -> 41475.808 | J22: ='Income Statement'!J24 -> 45826.917 | K22: ='Income Statement'!K24 -> 50067.529 | L22: ='Income Statement'!L24 -> 54153.35 | M22: ='Income Statement'!M24 -> 58049.917 | N22: ='Income Statement'!N24 -> 61732.192 | O22: ='Income Statement'!O24 -> 65183.737 | ... Q22: ='Income Statement'!Q24 -> 71365.337
C23: =SUM(C9:C22) -> 85734.013 | D23: =SUM(D9:D22) -> 84334.376 | E23: =SUM(E9:E22) -> 106669.44 | F23: =SUM(F9:F22) -> 105123.76 | G23: =SUM(G9:G22) -> 133615.02 | H23: =SUM(H9:H22) -> 142425.43 | I23: =SUM(I9:I22) -> 158358.3 | J23: =SUM(J9:J22) -> 173979.8 | ... Q23: =SUM(Q9:Q22) -> 263936.37
B24: Adjustments for :
B25: Increase/(Decrease) in Deposits | C25: 441170.62 | D25: 372079.36 | E25: 381124.91 | F25: 498001.98 | G25: 473360.53 | H25: =('Balance Sheet'!H19+'Balance Sheet'!H18)-('Balance Sheet'!G19+'Balance Sheet'!G18) -> 1388891.3 | I25: =('Balance Sheet'!I19+'Balance Sheet'!I18)-('Balance Sheet'!H19+'Balance Sheet'!H18) -> 763923.95 | J25: =('Balance Sheet'!J19+'Balance Sheet'!J18)-('Balance Sheet'!I19+'Balance Sheet'!I18) -> 748994.89 | K25: =('Balance Sheet'!K19+'Balance Sheet'!K18)-('Balance Sheet'!J19+'Balance Sheet'!J18) -> 725503.22 | L25: =('Balance Sheet'!L19+'Balance Sheet'!L18)-('Balance Sheet'!K19+'Balance Sheet'!K18) -> 695172.4 | M25: =('Balance Sheet'!M19+'Balance Sheet'!M18)-('Balance Sheet'!L19+'Balance Sheet'!L18) -> 659698.2 | N25: =('Balance Sheet'!N19+'Balance Sheet'!N18)-('Balance Sheet'!M19+'Balance Sheet'!M18) -> 620661.32 | O25: =('Balance Sheet'!O19+'Balance Sheet'!O18)-('Balance Sheet'!N19+'Balance Sheet'!N18) -> 579471.14 | ... Q25: =('Balance Sheet'!Q19+'Balance Sheet'!Q18)-('Balance Sheet'!P19+'Balance Sheet'!P18) -> 495253.61
B26: Increase/(Decrease) in Borrowings other than Capital Instruments | C26: 90438.852 | D26: 11807.876 | E26: 54584.074 | F26: 112581.11 | G26: -35148.358 | H26: ='Balance Sheet'!H20-'Balance Sheet'!G20 -> 185502.28 | I26: ='Balance Sheet'!I20-'Balance Sheet'!H20 -> 89087.256 | J26: ='Balance Sheet'!J20-'Balance Sheet'!I20 -> 87346.261 | K26: ='Balance Sheet'!K20-'Balance Sheet'!J20 -> 84606.709 | L26: ='Balance Sheet'!L20-'Balance Sheet'!K20 -> 81069.591 | M26: ='Balance Sheet'!M20-'Balance Sheet'!L20 -> 76932.662 | N26: ='Balance Sheet'!N20-'Balance Sheet'!M20 -> 72380.26 | O26: ='Balance Sheet'!O20-'Balance Sheet'!N20 -> 67576.745 | ... Q26: ='Balance Sheet'!Q20-'Balance Sheet'!P20 -> 57755.468
B27: (Increase)/Decrease in Investments other than Investment in Subsidiaries / Joint Ventures / Associates | C27: -368800.15 | D27: -183899.64 | E27: -141597.38 | F27: -190457.11 | G27: -81890.967 | H27: ='Balance Sheet'!G29-'Balance Sheet'!H29 -> -697713.78 | I27: ='Balance Sheet'!H29-'Balance Sheet'!I29 -> -324788.43 | J27: ='Balance Sheet'!I29-'Balance Sheet'!J29 -> -318441.22 | K27: ='Balance Sheet'!J29-'Balance Sheet'!K29 -> -308453.55 | L27: ='Balance Sheet'!K29-'Balance Sheet'!L29 -> -295558.15 | M27: ='Balance Sheet'!L29-'Balance Sheet'!M29 -> -280476.01 | N27: ='Balance Sheet'!M29-'Balance Sheet'!N29 -> -263879.17 | O27: ='Balance Sheet'!N29-'Balance Sheet'!O29 -> -246366.83 | ... Q27: ='Balance Sheet'!P29-'Balance Sheet'!Q29 -> -210561.07
B28: (Increase)/Decrease in Advances | C28: -156020.46 | D28: -309322.91 | E28: -484653.01 | F28: -528612.41 | G28: -485063.58 | H28: ='Balance Sheet'!G30-'Balance Sheet'!H30 -> -687192.8 | I28: ='Balance Sheet'!H30-'Balance Sheet'!I30 -> -552407.5 | J28: ='Balance Sheet'!I30-'Balance Sheet'!J30 -> -541612.02 | K28: ='Balance Sheet'!J30-'Balance Sheet'!K30 -> -524624.76 | L28: ='Balance Sheet'!K30-'Balance Sheet'!L30 -> -502691.98 | M28: ='Balance Sheet'!L30-'Balance Sheet'!M30 -> -477039.94 | N28: ='Balance Sheet'!M30-'Balance Sheet'!N30 -> -448811.65 | O28: ='Balance Sheet'!N30-'Balance Sheet'!O30 -> -419026.27 | ... Q28: ='Balance Sheet'!P30-'Balance Sheet'!Q30 -> -358127.02
B29: Increase/(Decrease) in Other Liabilities | C29: 67465.501 | D29: 86464.266 | E29: 75713.74 | F29: 102500.28 | G29: 56832.988 | H29: ='Balance Sheet'!H21-'Balance Sheet'!G21 -> 121073.94 | I29: ='Balance Sheet'!I21-'Balance Sheet'!H21 -> 98381.474 | J29: ='Balance Sheet'!J21-'Balance Sheet'!I21 -> 96458.845 | K29: ='Balance Sheet'!K21-'Balance Sheet'!J21 -> 93433.484 | L29: ='Balance Sheet'!L21-'Balance Sheet'!K21 -> 89527.348 | M29: ='Balance Sheet'!M21-'Balance Sheet'!L21 -> 84958.826 | N29: ='Balance Sheet'!N21-'Balance Sheet'!M21 -> 79931.485 | O29: ='Balance Sheet'!O21-'Balance Sheet'!N21 -> 74626.832 | ... Q29: ='Balance Sheet'!Q21-'Balance Sheet'!P21 -> 63780.93
B30: (Increase)/Decrease in Other Assets | C30: -66249.946 | D30: 5255.8279 | E30: -60531.723 | F30: -46236.906 | G30: 20542.105 | H30: ='Balance Sheet'!G32-'Balance Sheet'!H32 -> -165732.35 | I30: ='Balance Sheet'!H32-'Balance Sheet'!I32 -> -69270.452 | J30: ='Balance Sheet'!I32-'Balance Sheet'!J32 -> -67916.728 | K30: ='Balance Sheet'!J32-'Balance Sheet'!K32 -> -65786.569 | L30: ='Balance Sheet'!K32-'Balance Sheet'!L32 -> -63036.257 | M30: ='Balance Sheet'!L32-'Balance Sheet'!M32 -> -59819.557 | N30: ='Balance Sheet'!M32-'Balance Sheet'!N32 -> -56279.804 | O30: ='Balance Sheet'!N32-'Balance Sheet'!O32 -> -52544.795 | ... Q30: ='Balance Sheet'!P32-'Balance Sheet'!Q32 -> -44908.189
C31: =SUM(C23:C30) -> 93738.423 | D31: =SUM(D23:D30) -> 66719.149 | E31: =SUM(E23:E30) -> -68689.957 | F31: =SUM(F23:F30) -> 52900.699 | G31: =SUM(G23:G30) -> 82247.74 | H31: =SUM(H23:H30) -> 287254.07 | I31: =SUM(I23:I30) -> 163284.6 | J31: =SUM(J23:J30) -> 178809.83 | ... Q31: =SUM(Q23:Q30) -> 267130.11
B32: Tax refund / (Taxes paid) | C32: -3819.4934 | D32: -9024.303 | E32: -17323.722 | F32: -31268.268 | G32: -33761.445 | H32: ='Income Statement'!H30 -> -31282.518 | I32: ='Income Statement'!I30 -> -34025.674 | J32: ='Income Statement'!J30 -> -37401.596 | K32: ='Income Statement'!K30 -> -40663.653 | L32: ='Income Statement'!L30 -> -43782.342 | M32: ='Income Statement'!M30 -> -46735.82 | N32: ='Income Statement'!N30 -> -49509.306 | O32: ='Income Statement'!O30 -> -52094.258 | ... Q32: ='Income Statement'!Q30 -> -56689.941
B34: NET CASH GENERATED FROM / (USED IN) OPERATING ACTIVITIES | C34: =SUM(C31:C32) -> 89918.93 | D34: =SUM(D31:D32) -> 57694.846 | E34: =SUM(E31:E32) -> -86013.68 | F34: =SUM(F31:F32) -> 21632.431 | G34: =SUM(G31:G32) -> 48486.295 | H34: =SUM(H31:H32) -> 255971.55 | I34: =SUM(I31:I32) -> 129258.93 | J34: =SUM(J31:J32) -> 141408.23 | ... Q34: =SUM(Q31:Q32) -> 210440.17
A36: # | B36: CASH FLOW FROM INVESTING ACTIVITIES
B37: Purchase of Shares in Subsidiaries/Joint Ventures/Associates | C37: -3176.9416 | D37: -582.764 | E37: 0 | F37: -82.161 | G37: 1
B38: Sale of Shares in Subsidiaries/Joint Ventures/Associates | C38: 1942.1097 | D38: 2.2296 | E38: 0 | F38: 0 | G38: 0
B39: Profit on sale of Investments in Subsidiaries/Joint Ventures/ Associates | C39: 1577.8431 | D39: 9.7432 | E39: 0 | F39: 0 | G39: -7.519
B40: (Loss) on sale of Investments in Subsidiaries/Joint Ventures/ Associates | C40: -254.4131 | D40: 0 | E40: 0 | F40: 0 | G40: 0
B41: Dividend from Associates | C41: 3.195 | D41: 3.195 | E41: 2.6625 | F41: 5.5719 | G41: 9.0009
B42: (Increase) in Fixed Assets | C42: -3909.825 | D42: -3305.2601 | E42: -4671.0213 | F42: -4175.1262 | G42: -5637.2241 | H42: =-FAS!H52 -> -14158.845 | I42: =-FAS!I52 -> -8809.8906 | J42: =-FAS!J52 -> -8853.94 | K42: =-FAS!K52 -> -8898.2097 | L42: =-FAS!L52 -> -8942.7008 | M42: =-FAS!M52 -> -8987.4143 | N42: =-FAS!N52 -> -9032.3514 | O42: =-FAS!O52 -> -9077.5131 | ... Q42: =-FAS!Q52 -> -9168.5152
B43: Decrease in Fixed Assets | C43: 81.8047 | D43: 254.3431 | E43: 627.3898 | F43: 0 | G43: 0
A45: # | B45: NET CASH GENERATED FROM / (USED IN) INVESTING ACTIVITIES | C45: =SUM(C37:C43) -> -3736.2272 | D45: =SUM(D37:D43) -> -3618.5132 | E45: =SUM(E37:E43) -> -4040.969 | F45: =SUM(F37:F43) -> -4251.7153 | G45: =SUM(G37:G43) -> -5634.7422 | H45: =SUM(H37:H43) -> -14158.845 | I45: =SUM(I37:I43) -> -8809.8906 | J45: =SUM(J37:J43) -> -8853.94 | ... Q45: =SUM(Q37:Q43) -> -9168.5152
B47: CASH FLOW FROM FINANCING ACTIVITIES
B48: Proceeds from issue of Equity shares including share premium (Net of share issue expenses) | C48: 0 | D48: 0 | E48: 0.0064 | F48: 0 | G48: 0.1288 | H48: ='Balance Sheet'!H12-'Balance Sheet'!G12 -> 0 | I48: ='Balance Sheet'!I12-'Balance Sheet'!H12 -> 0 | J48: ='Balance Sheet'!J12-'Balance Sheet'!I12 -> 0 | K48: ='Balance Sheet'!K12-'Balance Sheet'!J12 -> 0 | L48: ='Balance Sheet'!L12-'Balance Sheet'!K12 -> 0 | M48: ='Balance Sheet'!M12-'Balance Sheet'!L12 -> 0 | N48: ='Balance Sheet'!N12-'Balance Sheet'!M12 -> 0 | O48: ='Balance Sheet'!O12-'Balance Sheet'!N12 -> 0 | ... Q48: ='Balance Sheet'!Q12-'Balance Sheet'!P12 -> 0
B49: Issue of Capital Instruments | C49: 27431 | D49: 14074 | E49: 19533.093 | F49: 20164.648 | G49: 21500
B50: Redemption of Capital Instruments | C50: -16897.664 | D50: -10518.3 | E50: -2125 | F50: -14288.2 | G50: -15103.9
B51: Interest paid on Capital Instruments | C51: -5069.1088 | D51: -5411.0089 | E51: -6324.6256 | F51: -8589.2532 | G51: -10270.9 | H51: =-'Income Statement'!H24 -> -34704.028 | I51: =-'Income Statement'!I24 -> -41475.808 | J51: =-'Income Statement'!J24 -> -45826.917 | K51: =-'Income Statement'!K24 -> -50067.529 | L51: =-'Income Statement'!L24 -> -54153.35 | M51: =-'Income Statement'!M24 -> -58049.917 | N51: =-'Income Statement'!N24 -> -61732.192 | O51: =-'Income Statement'!O24 -> -65183.737 | ... Q51: =-'Income Statement'!Q24 -> -71365.337
B52: Dividend paid | C52: 0 | D52: -3569.8446 | E52: -6336.7216 | F52: -10084.811 | G52: -12226.718 | H52: ='Income Statement'!H34 -> -9539.352 | I52: ='Income Statement'!I34 -> -10375.856 | J52: ='Income Statement'!J34 -> -11405.316 | K52: ='Income Statement'!K34 -> -12400.054 | L52: ='Income Statement'!L34 -> -13351.073 | M52: ='Income Statement'!M34 -> -14251.712 | N52: ='Income Statement'!N34 -> -15097.464 | O52: ='Income Statement'!O34 -> -15885.725 | ... Q52: ='Income Statement'!Q34 -> -17287.141
B53: Dividend tax paid by Subsidiaries/Joint Ventures | C53: -3.6516 | D53: -0.8664 | E53: -1.2283 | F53: -12.4081 | G53: -31.8493
B54: Increase/(Decrease) in Minority Interest | C54: 1682.0946 | D54: 1581.5062 | E54: 1640.8585 | F54: 2913.7449 | G54: 2394.1588 | H54: ='Balance Sheet'!H14-'Balance Sheet'!G14 -> 2348.4818 | I54: ='Balance Sheet'!I14-'Balance Sheet'!H14 -> 2554.4196 | J54: ='Balance Sheet'!J14-'Balance Sheet'!I14 -> 2807.8612 | K54: ='Balance Sheet'!K14-'Balance Sheet'!J14 -> 3052.7546 | L54: ='Balance Sheet'!L14-'Balance Sheet'!K14 -> 3286.8849 | M54: ='Balance Sheet'!M14-'Balance Sheet'!L14 -> 3508.6122 | N54: ='Balance Sheet'!N14-'Balance Sheet'!M14 -> 3716.8269 | O54: ='Balance Sheet'!O14-'Balance Sheet'!N14 -> 3910.8878 | ... Q54: ='Balance Sheet'!Q14-'Balance Sheet'!P14 -> 4255.9009
A56: # | B56: NET CASH GENERATED FROM / (USED IN) FINANCING ACTIVITIES | C56: =SUM(C48:C54) -> 7142.6702 | D56: =SUM(D48:D54) -> -3844.5137 | E56: =SUM(E48:E54) -> 6386.382 | F56: =SUM(F48:F54) -> -9896.28 | G56: =SUM(G48:G54) -> -13739.08 | H56: =SUM(H48:H54) -> -41894.898 | I56: =SUM(I48:I54) -> -49297.244 | J56: =SUM(J48:J54) -> -54424.372 | ... Q56: =SUM(Q48:Q54) -> -84396.577
B58: EFFECT OF EXCHANGE FLUCTUATION ON TRANSLATION RESERVE | C58: 66.399 | D58: 966.2665 | E58: 3075.0546 | F58: 775.9581 | G58: 2248.1669
B60: NET INCREASE / (DECREASE) IN CASH AND CASH EQUIVALENTS | C60: =SUM(C34,C45,C56,C58) -> 93391.772 | D60: =SUM(D34,D45,D56,D58) -> 51198.086 | E60: =SUM(E34,E45,E56,E58) -> -80593.212 | F60: =SUM(F34,F45,F56,F58) -> 8260.3938 | G60: =SUM(G34,G45,G56,G58) -> 31360.639 | H60: =SUM(H34,H45,H56,H58) -> 199917.81 | I60: =SUM(I34,I45,I56,I58) -> 71151.791 | J60: =SUM(J34,J45,J56,J58) -> 78129.918 | ... Q60: =SUM(Q34,Q45,Q56,Q58) -> 116875.07
B62: CASH AND CASH EQUIVALENTS AS AT 1ST APRIL | C62: 254315.26 | D62: =C64 -> 347707.04 | E62: =D64 -> 398905.12 | F62: =E64 -> 318311.91 | G62: =F64 -> 326572.3 | H62: =G64 -> 357932.94 | I62: =H64 -> 557850.75 | J62: =I64 -> 629002.55 | K62: =J64 -> 707132.46 | ... Q62: =P64 -> 1303213.6
A64: # | B64: CASH AND CASH EQUIVALENTS AS AT THE PERIOD END | C64: =C60+C62 -> 347707.04 | D64: =D60+D62 -> 398905.12 | E64: =E60+E62 -> 318311.91 | F64: =F60+F62 -> 326572.3 | G64: =G60+G62 -> 357932.94 | H64: =H60+H62 -> 557850.75 | I64: =I60+I62 -> 629002.55 | J64: =J60+J62 -> 707132.46 | ... Q64: =Q60+Q62 -> 1420088.6

Sheet Common Size Statement
B1: State Bank of India
B2: BSE: 500112 | NSE: SBIN
C3: 10000
B5: Common Size Statement
B7: Particular | C7: 2021 | D7: =C7+1 -> 2022 | E7: =D7+1 -> 2023 | F7: =E7+1 -> 2024 | G7: =F7+1 -> 2025 | H7: =G7+1 -> 2026 | I7: =H7+1 -> 2027 | J7: =I7+1 -> 2028 | K7: =J7+1 -> 2029 | ... Q7: =P7+1 -> 2035
C8: Audited | D8: Audited | E8: Audited | F8: Audited | G8: Audited | H8: Forecasted | I8: Forecasted | J8: Forecasted | K8: Forecasted | L8: Forecasted | M8: Forecasted | N8: Forecasted | O8: Forecasted | P8: Forecasted | Q8: Forecasted
B9: Income Statement
B11: Income | C11: ='Income Statement'!C10/'Income Statement'!C$10 -> 1 | D11: ='Income Statement'!D10/'Income Statement'!D$10 -> 1 | E11: ='Income Statement'!E10/'Income Statement'!E$10 -> 1 | F11: ='Income Statement'!F10/'Income Statement'!F$10 -> 1 | G11: ='Income Statement'!G10/'Income Statement'!G$10 -> 1 | H11: ='Income Statement'!H10/'Income Statement'!H$10 -> 1 | I11: ='Income Statement'!I10/'Income Statement'!I$10 -> 1 | J11: ='Income Statement'!J10/'Income Statement'!J$10 -> 1 | ... Q11: ='Income Statement'!Q10/'Income Statement'!Q$10 -> 1
B13: EXPENDITURE
B14: Interest on Deposit | C14: ='Income Statement'!C13/'Income Statement'!C$10 -> 0.37125974 | D14: ='Income Statement'!D13/'Income Statement'!D$10 -> 0.34834068 | E14: ='Income Statement'!E13/'Income Statement'!E$10 -> 0.34542952 | F14: ='Income Statement'!F13/'Income Statement'!F$10 -> 0.37552664 | G14: ='Income Statement'!G13/'Income Statement'!G$10 -> 0.39079028 | H14: ='Income Statement'!H13/'Income Statement'!H$10 -> 0.36626937 | I14: ='Income Statement'!I13/'Income Statement'!I$10 -> 0.36626937 | J14: ='Income Statement'!J13/'Income Statement'!J$10 -> 0.36626937 | ... Q14: ='Income Statement'!Q13/'Income Statement'!Q$10 -> 0.36626937
B15: Operating expenses | C15: ='Income Statement'!C14/'Income Statement'!C$10 -> 0.37084087 | D15: ='Income Statement'!D14/'Income Statement'!D$10 -> 0.39719543 | E15: ='Income Statement'!E14/'Income Statement'!E$10 -> 0.35657575 | F15: ='Income Statement'!F14/'Income Statement'!F$10 -> 0.33768066 | G15: ='Income Statement'!G14/'Income Statement'!G$10 -> 0.29972503 | H15: ='Income Statement'!H14/'Income Statement'!H$10 -> 0.35240355 | I15: ='Income Statement'!I14/'Income Statement'!I$10 -> 0.35240355 | J15: ='Income Statement'!J14/'Income Statement'!J$10 -> 0.35240355 | ... Q15: ='Income Statement'!Q14/'Income Statement'!Q$10 -> 0.35240355
B16: Provisions and contingencies | C16: ='Income Statement'!C15/'Income Statement'!C$10 -> 0.1417416 | D16: ='Income Statement'!D15/'Income Statement'!D$10 -> 0.098431934 | E16: ='Income Statement'!E15/'Income Statement'!E$10 -> 0.078213178 | F16: ='Income Statement'!F15/'Income Statement'!F$10 -> 0.051813079 | G16: ='Income Statement'!G15/'Income Statement'!G$10 -> 0.070565736 | H16: ='Income Statement'!H15/'Income Statement'!H$10 -> 0.088153105 | I16: ='Income Statement'!I15/'Income Statement'!I$10 -> 0.088153105 | J16: ='Income Statement'!J15/'Income Statement'!J$10 -> 0.088153105 | ... Q16: ='Income Statement'!Q15/'Income Statement'!Q$10 -> 0.088153105
B17: Total | C17: ='Income Statement'!C16/'Income Statement'!C$10 -> 0.88384221 | D17: ='Income Statement'!D16/'Income Statement'!D$10 -> 0.84396805 | E17: ='Income Statement'!E16/'Income Statement'!E$10 -> 0.78021844 | F17: ='Income Statement'!F16/'Income Statement'!F$10 -> 0.76502037 | G17: ='Income Statement'!G16/'Income Statement'!G$10 -> 0.76108104 | H17: ='Income Statement'!H16/'Income Statement'!H$10 -> 0.80682602 | I17: ='Income Statement'!I16/'Income Statement'!I$10 -> 0.80682602 | J17: ='Income Statement'!J16/'Income Statement'!J$10 -> 0.80682602 | ... Q17: ='Income Statement'!Q16/'Income Statement'!Q$10 -> 0.80682602
B19: EBITDA | C19: ='Income Statement'!C18/'Income Statement'!C$10 -> 0.11615779 | D19: ='Income Statement'!D18/'Income Statement'!D$10 -> 0.15603195 | E19: ='Income Statement'!E18/'Income Statement'!E$10 -> 0.21978156 | F19: ='Income Statement'!F18/'Income Statement'!F$10 -> 0.23497963 | G19: ='Income Statement'!G18/'Income Statement'!G$10 -> 0.23891896 | H19: ='Income Statement'!H18/'Income Statement'!H$10 -> 0.19317398 | I19: ='Income Statement'!I18/'Income Statement'!I$10 -> 0.19317398 | J19: ='Income Statement'!J18/'Income Statement'!J$10 -> 0.19317398 | ... Q19: ='Income Statement'!Q18/'Income Statement'!Q$10 -> 0.19317398
B21: Depreciation & Amortization Expenses | C21: ='Income Statement'!C20/'Income Statement'!C$10 -> 0.009630674 | D21: ='Income Statement'!D20/'Income Statement'!D$10 -> 0.0090700592 | E21: ='Income Statement'!E20/'Income Statement'!E$10 -> 0.0078068636 | F21: ='Income Statement'!F20/'Income Statement'!F$10 -> 0.0064737419 | G21: ='Income Statement'!G20/'Income Statement'!G$10 -> 0.006017211 | H21: ='Income Statement'!H20/'Income Statement'!H$10 -> 0.0046106115 | I21: ='Income Statement'!I20/'Income Statement'!I$10 -> 0.0041674587 | J21: ='Income Statement'!J20/'Income Statement'!J$10 -> 0.0038122325 | ... Q21: ='Income Statement'!Q20/'Income Statement'!Q$10 -> 0.0026022042
B23: EBIT | C23: ='Income Statement'!C22/'Income Statement'!C$10 -> 0.10652711 | D23: ='Income Statement'!D22/'Income Statement'!D$10 -> 0.14696189 | E23: ='Income Statement'!E22/'Income Statement'!E$10 -> 0.21197469 | F23: ='Income Statement'!F22/'Income Statement'!F$10 -> 0.22850588 | G23: ='Income Statement'!G22/'Income Statement'!G$10 -> 0.23290174 | H23: ='Income Statement'!H22/'Income Statement'!H$10 -> 0.18856336 | I23: ='Income Statement'!I22/'Income Statement'!I$10 -> 0.18900652 | J23: ='Income Statement'!J22/'Income Statement'!J$10 -> 0.18936174 | ... Q23: ='Income Statement'!Q22/'Income Statement'!Q$10 -> 0.19057177
B25: Interest on Borrowings | C25: ='Income Statement'!C24/'Income Statement'!C$10 -> 0.033606145 | D25: ='Income Statement'!D24/'Income Statement'!D$10 -> 0.035454583 | E25: ='Income Statement'!E24/'Income Statement'!E$10 -> 0.055900413 | F25: ='Income Statement'!F24/'Income Statement'!F$10 -> 0.061316639 | G25: ='Income Statement'!G24/'Income Statement'!G$10 -> 0.062886314 | H25: ='Income Statement'!H24/'Income Statement'!H$10 -> 0.046427974 | I25: ='Income Statement'!I24/'Income Statement'!I$10 -> 0.049904697 | J25: ='Income Statement'!J24/'Income Statement'!J$10 -> 0.050189078 | ... Q25: ='Income Statement'!Q24/'Income Statement'!Q$10 -> 0.051519954
B26: Add: Share in Profit/(Loss) of Associates | C26: ='Income Statement'!C25/'Income Statement'!C$10 -> -0.0010170412 | D26: ='Income Statement'!D25/'Income Statement'!D$10 -> 0.0020321081 | E26: ='Income Statement'!E25/'Income Statement'!E$10 -> 0.0025169141 | F26: ='Income Statement'!F25/'Income Statement'!F$10 -> 0.0023632923 | G26: ='Income Statement'!G25/'Income Statement'!G$10 -> 0.00226952 | H26: ='Income Statement'!H25/'Income Statement'!H$10 -> 0.0016329586 | I26: ='Income Statement'!I25/'Income Statement'!I$10 -> 0.0016329586 | J26: ='Income Statement'!J25/'Income Statement'!J$10 -> 0.0016329586 | ... Q26: ='Income Statement'!Q25/'Income Statement'!Q$10 -> 0.0016329586
B27: Less: Minority Interest | C27: ='Income Statement'!C26/'Income Statement'!C$10 -> 0.0038469025 | D27: ='Income Statement'!D26/'Income Statement'!D$10 -> 0.0044457605 | E27: ='Income Statement'!E26/'Income Statement'!E$10 -> 0.0044398104 | F27: ='Income Statement'!F26/'Income Statement'!F$10 -> 0.0041353059 | G27: ='Income Statement'!G26/'Income Statement'!G$10 -> 0.0044641864 | H27: ='Income Statement'!H26/'Income Statement'!H$10 -> 0.0042663931 | I27: ='Income Statement'!I26/'Income Statement'!I$10 -> 0.0042663931 | J27: ='Income Statement'!J26/'Income Statement'!J$10 -> 0.0042663931 | ... Q27: ='Income Statement'!Q26/'Income Statement'!Q$10 -> 0.0042663931
B29: EBT | C29: ='Income Statement'!C28/'Income Statement'!C$10 -> 0.068057026 | D29: ='Income Statement'!D28/'Income Statement'!D$10 -> 0.10909366 | E29: ='Income Statement'!E28/'Income Statement'!E$10 -> 0.15415138 | F29: ='Income Statement'!F28/'Income Statement'!F$10 -> 0.16541723 | G29: ='Income Statement'!G28/'Income Statement'!G$10 -> 0.16782076 | H29: ='Income Statement'!H28/'Income Statement'!H$10 -> 0.13950196 | I29: ='Income Statement'!I28/'Income Statement'!I$10 -> 0.13646839 | J29: ='Income Statement'!J28/'Income Statement'!J$10 -> 0.13653923 | ... Q29: ='Income Statement'!Q28/'Income Statement'!Q$10 -> 0.13641838
B31: Tax Expenses | C31: ='Income Statement'!C30/'Income Statement'!C$10 -> -0.0099120629 | D31: ='Income Statement'!D30/'Income Statement'!D$10 -> -0.022174201 | E31: ='Income Statement'!E30/'Income Statement'!E$10 -> -0.036595949 | F31: ='Income Statement'!F30/'Income Statement'!F$10 -> -0.052589283 | G31: ='Income Statement'!G30/'Income Statement'!G$10 -> -0.050895885 | H31: ='Income Statement'!H30/'Income Statement'!H$10 -> -0.041850587 | I31: ='Income Statement'!I30/'Income Statement'!I$10 -> -0.040940516 | J31: ='Income Statement'!J30/'Income Statement'!J$10 -> -0.040961769 | ... Q31: ='Income Statement'!Q30/'Income Statement'!Q$10 -> -0.040925515
B33: Post Tax Income | C33: ='Income Statement'!C32/'Income Statement'!C$10 -> 0.058144964 | D33: ='Income Statement'!D32/'Income Statement'!D$10 -> 0.086919457 | E33: ='Income Statement'!E32/'Income Statement'!E$10 -> 0.11755543 | F33: ='Income Statement'!F32/'Income Statement'!F$10 -> 0.11282795 | G33: ='Income Statement'!G32/'Income Statement'!G$10 -> 0.11692488 | H33: ='Income Statement'!H32/'Income Statement'!H$10 -> 0.097651369 | I33: ='Income Statement'!I32/'Income Statement'!I$10 -> 0.09552787 | J33: ='Income Statement'!J32/'Income Statement'!J$10 -> 0.095577461 | ... Q33: ='Income Statement'!Q32/'Income Statement'!Q$10 -> 0.095492868
B35: Balance Sheet
B37: CAPITAL AND LIABILITIES
B38: Capital | C38: ='Balance Sheet'!C12/'Balance Sheet'!C$33 -> 0.000184179 | D38: ='Balance Sheet'!D12/'Balance Sheet'!D$33 -> 0.00016647651 | E38: ='Balance Sheet'!E12/'Balance Sheet'!E$33 -> 0.00014988218 | F38: ='Balance Sheet'!F12/'Balance Sheet'!F$33 -> 0.00013253497 | G38: ='Balance Sheet'!G12/'Balance Sheet'!G$33 -> 0.00012201796 | H38: ='Balance Sheet'!H12/'Balance Sheet'!H$33 -> 9.8337994e-05 | I38: ='Balance Sheet'!I12/'Balance Sheet'!I$33 -> 8.8376408e-05 | J38: ='Balance Sheet'!J12/'Balance Sheet'!J$33 -> 8.0330394e-05 | ... Q38: ='Balance Sheet'!Q12/'Balance Sheet'!Q$33 -> 5.1872412e-05
B39: Reserves & Surplus | C39: ='Balance Sheet'!C13/'Balance Sheet'!C$33 -> 0.056684012 | D39: ='Balance Sheet'!D13/'Balance Sheet'!D$33 -> 0.056836822 | E39: ='Balance Sheet'!E13/'Balance Sheet'!E$33 -> 0.060129947 | F39: ='Balance Sheet'!F13/'Balance Sheet'!F$33 -> 0.061488018 | G39: ='Balance Sheet'!G13/'Balance Sheet'!G$33 -> 0.066465953 | H39: ='Balance Sheet'!H13/'Balance Sheet'!H$33 -> 0.060558673 | I39: ='Balance Sheet'!I13/'Balance Sheet'!I$33 -> 0.061258586 | J39: ='Balance Sheet'!J13/'Balance Sheet'!J$33 -> 0.062510054 | ... Q39: ='Balance Sheet'!Q13/'Balance Sheet'!Q$33 -> 0.080916912
B40: Minority Interest | C40: ='Balance Sheet'!C14/'Balance Sheet'!C$33 -> 0.0019865197 | D40: ='Balance Sheet'!D14/'Balance Sheet'!D$33 -> 0.0020905925 | E40: ='Balance Sheet'!E14/'Balance Sheet'!E$33 -> 0.0021558142 | F40: ='Balance Sheet'!F14/'Balance Sheet'!F$33 -> 0.0023193459 | G40: ='Balance Sheet'!G14/'Balance Sheet'!G$33 -> 0.002464504 | H40: ='Balance Sheet'!H14/'Balance Sheet'!H$33 -> 0.0022449917 | I40: ='Balance Sheet'!I14/'Balance Sheet'!I$33 -> 0.0022705277 | J40: ='Balance Sheet'!J14/'Balance Sheet'!J$33 -> 0.0023165483 | ... Q40: ='Balance Sheet'!Q14/'Balance Sheet'!Q$33 -> 0.0029967559
B41: CASA Deposits | C41: ='Balance Sheet'!C18/'Balance Sheet'!C$33 -> 0.34810406 | D41: ='Balance Sheet'!D18/'Balance Sheet'!D$33 -> 0.33944255 | E41: ='Balance Sheet'!E18/'Balance Sheet'!E$33 -> 0.32018567 | F41: ='Balance Sheet'!F18/'Balance Sheet'!F$33 -> 0.29447505 | G41: ='Balance Sheet'!G18/'Balance Sheet'!G$33 -> 0.28833513 | H41: ='Balance Sheet'!H18/'Balance Sheet'!H$33 -> 0.31941173 | I41: ='Balance Sheet'!I18/'Balance Sheet'!I$33 -> 0.31916785 | J41: ='Balance Sheet'!J18/'Balance Sheet'!J$33 -> 0.31872834 | ... Q41: ='Balance Sheet'!Q18/'Balance Sheet'!Q$33 -> 0.31223218
B42: Fixed Deposits | C42: ='Balance Sheet'!C19/'Balance Sheet'!C$33 -> 0.41863628 | D42: ='Balance Sheet'!D19/'Balance Sheet'!D$33 -> 0.42300837 | E42: ='Balance Sheet'!E19/'Balance Sheet'!E$33 -> 0.43027143 | F42: ='Balance Sheet'!F19/'Balance Sheet'!F$33 -> 0.44308074 | G42: ='Balance Sheet'!G19/'Balance Sheet'!G$33 -> 0.45541113 | H42: ='Balance Sheet'!H19/'Balance Sheet'!H$33 -> 0.43303426 | I42: ='Balance Sheet'!I19/'Balance Sheet'!I$33 -> 0.43270363 | J42: ='Balance Sheet'!J19/'Balance Sheet'!J$33 -> 0.43210778 | ... Q42: ='Balance Sheet'!Q19/'Balance Sheet'!Q$33 -> 0.42330077
B43: Borrowings | C43: ='Balance Sheet'!C20/'Balance Sheet'!C$33 -> 0.089523392 | D43: ='Balance Sheet'!D20/'Balance Sheet'!D$33 -> 0.083784656 | E43: ='Balance Sheet'!E20/'Balance Sheet'!E$33 -> 0.08752357 | F43: ='Balance Sheet'!F20/'Balance Sheet'!F$33 -> 0.094985226 | G43: ='Balance Sheet'!G20/'Balance Sheet'!G$33 -> 0.083516785 | H43: ='Balance Sheet'!H20/'Balance Sheet'!H$33 -> 0.08774872 | I43: ='Balance Sheet'!I20/'Balance Sheet'!I$33 -> 0.087681723 | J43: ='Balance Sheet'!J20/'Balance Sheet'!J$33 -> 0.087560981 | ... Q43: ='Balance Sheet'!Q20/'Balance Sheet'!Q$33 -> 0.085776356
B44: Other Liabilities and Provisions | C44: ='Balance Sheet'!C21/'Balance Sheet'!C$33 -> 0.084881551 | D44: ='Balance Sheet'!D21/'Balance Sheet'!D$33 -> 0.094670529 | E44: ='Balance Sheet'!E21/'Balance Sheet'!E$33 -> 0.099583686 | F44: ='Balance Sheet'!F21/'Balance Sheet'!F$33 -> 0.10351909 | G44: ='Balance Sheet'!G21/'Balance Sheet'!G$33 -> 0.10368448 | H44: ='Balance Sheet'!H21/'Balance Sheet'!H$33 -> 0.096903292 | I44: ='Balance Sheet'!I21/'Balance Sheet'!I$33 -> 0.096829305 | J44: ='Balance Sheet'!J21/'Balance Sheet'!J$33 -> 0.096695966 | ... Q44: ='Balance Sheet'!Q21/'Balance Sheet'!Q$33 -> 0.094725157
B45: TOTAL | C45: ='Balance Sheet'!C22/'Balance Sheet'!C$33 -> 0.94114529 | D45: ='Balance Sheet'!D22/'Balance Sheet'!D$33 -> 0.94090611 | E45: ='Balance Sheet'!E22/'Balance Sheet'!E$33 -> 0.93756436 | F45: ='Balance Sheet'!F22/'Balance Sheet'!F$33 -> 0.9360601 | G45: ='Balance Sheet'!G22/'Balance Sheet'!G$33 -> 0.93094753 | H45: ='Balance Sheet'!H22/'Balance Sheet'!H$33 -> 0.937098 | I45: ='Balance Sheet'!I22/'Balance Sheet'!I$33 -> 0.93638251 | J45: ='Balance Sheet'!J22/'Balance Sheet'!J$33 -> 0.93509307 | ... Q45: ='Balance Sheet'!Q22/'Balance Sheet'!Q$33 -> 0.91603446
B47: ASSETS
B48: Cash and Balances with Reserve Bank of India | C48: ='Balance Sheet'!C27/'Balance Sheet'!C$33 -> 0.044060137 | D48: ='Balance Sheet'!D27/'Balance Sheet'!D$33 -> 0.059410436 | E48: ='Balance Sheet'!E27/'Balance Sheet'!E$33 -> 0.04153572 | F48: ='Balance Sheet'!F27/'Balance Sheet'!F$33 -> 0.033466549 | G48: ='Balance Sheet'!G27/'Balance Sheet'!G$33 -> 0.031101913 | H48: ='Balance Sheet'!H27/'Balance Sheet'!H$33 -> 0.047094387 | I48: ='Balance Sheet'!I27/'Balance Sheet'!I$33 -> 0.049369585 | J48: ='Balance Sheet'!J27/'Balance Sheet'!J$33 -> 0.051907316 | ... Q48: ='Balance Sheet'!Q27/'Balance Sheet'!Q$33 -> 0.074957568
B49: Balances with Banks and Money at Call & Short Notice | C49: ='Balance Sheet'!C28/'Balance Sheet'!C$33 -> 0.02769686 | D49: ='Balance Sheet'!D28/'Balance Sheet'!D$33 -> 0.014999895 | E49: ='Balance Sheet'!E28/'Balance Sheet'!E$33 -> 0.011922384 | F49: ='Balance Sheet'!F28/'Balance Sheet'!F$33 -> 0.01503108 | G49: ='Balance Sheet'!G28/'Balance Sheet'!G$33 -> 0.017834903 | H49: ='Balance Sheet'!H28/'Balance Sheet'!H$33 -> 0.014373692 | I49: ='Balance Sheet'!I28/'Balance Sheet'!I$33 -> 0.012917644 | J49: ='Balance Sheet'!J28/'Balance Sheet'!J$33 -> 0.011741589 | ... Q49: ='Balance Sheet'!Q28/'Balance Sheet'!Q$33 -> 0.0075819937
B50: Investments | C50: ='Balance Sheet'!C29/'Balance Sheet'!C$33 -> 0.32918404 | D50: ='Balance Sheet'!D29/'Balance Sheet'!D$33 -> 0.33138006 | E50: ='Balance Sheet'!E29/'Balance Sheet'!E$33 -> 0.32129215 | F50: ='Balance Sheet'!F29/'Balance Sheet'!F$33 -> 0.31342702 | G50: ='Balance Sheet'!G29/'Balance Sheet'!G$33 -> 0.30155116 | H50: ='Balance Sheet'!H29/'Balance Sheet'!H$33 -> 0.31990848 | I50: ='Balance Sheet'!I29/'Balance Sheet'!I$33 -> 0.31966423 | J50: ='Balance Sheet'!J29/'Balance Sheet'!J$33 -> 0.31922403 | ... Q50: ='Balance Sheet'!Q29/'Balance Sheet'!Q$33 -> 0.31271777
B51: Advances | C51: ='Balance Sheet'!C30/'Balance Sheet'!C$33 -> 0.51605362 | D51: ='Balance Sheet'!D30/'Balance Sheet'!D$33 -> 0.52119692 | E51: ='Balance Sheet'!E30/'Balance Sheet'!E$33 -> 0.54881971 | F51: ='Balance Sheet'!F30/'Balance Sheet'!F$33 -> 0.56198351 | G51: ='Balance Sheet'!G30/'Balance Sheet'!G$33 -> 0.58117624 | H51: ='Balance Sheet'!H30/'Balance Sheet'!H$33 -> 0.54410757 | I51: ='Balance Sheet'!I30/'Balance Sheet'!I$33 -> 0.54369214 | J51: ='Balance Sheet'!J30/'Balance Sheet'!J$33 -> 0.54294345 | ... Q51: ='Balance Sheet'!Q30/'Balance Sheet'!Q$33 -> 0.53187744
B52: Fixed Assets | C52: ='Balance Sheet'!C31/'Balance Sheet'!C$33 -> 0.0082893005 | D52: ='Balance Sheet'!D31/'Balance Sheet'!D$33 -> 0.0073700595 | E52: ='Balance Sheet'!E31/'Balance Sheet'!E$33 -> 0.0074578873 | F52: ='Balance Sheet'!F31/'Balance Sheet'!F$33 -> 0.0066393891 | G52: ='Balance Sheet'!G31/'Balance Sheet'!G$33 -> 0.0063353187 | H52: ='Balance Sheet'!H31/'Balance Sheet'!H$33 -> 0.006286208 | I52: ='Balance Sheet'!I31/'Balance Sheet'!I$33 -> 0.0061788394 | J52: ='Balance Sheet'!J31/'Balance Sheet'!J$33 -> 0.0060999293 | ... Q52: ='Balance Sheet'!Q31/'Balance Sheet'!Q$33 -> 0.0061691957
B53: Other Assets | C53: ='Balance Sheet'!C32/'Balance Sheet'!C$33 -> 0.074716048 | D53: ='Balance Sheet'!D32/'Balance Sheet'!D$33 -> 0.065642627 | E53: ='Balance Sheet'!E32/'Balance Sheet'!E$33 -> 0.068972152 | F53: ='Balance Sheet'!F32/'Balance Sheet'!F$33 -> 0.069452448 | G53: ='Balance Sheet'!G32/'Balance Sheet'!G$33 -> 0.06200046 | H53: ='Balance Sheet'!H32/'Balance Sheet'!H$33 -> 0.068229663 | I53: ='Balance Sheet'!I32/'Balance Sheet'!I$33 -> 0.068177569 | J53: ='Balance Sheet'!J32/'Balance Sheet'!J$33 -> 0.068083685 | ... Q53: ='Balance Sheet'!Q32/'Balance Sheet'!Q$33 -> 0.066696037
B54: TOTAL | C54: ='Balance Sheet'!C33/'Balance Sheet'!C$33 -> 1 | D54: ='Balance Sheet'!D33/'Balance Sheet'!D$33 -> 1 | E54: ='Balance Sheet'!E33/'Balance Sheet'!E$33 -> 1 | F54: ='Balance Sheet'!F33/'Balance Sheet'!F$33 -> 1 | G54: ='Balance Sheet'!G33/'Balance Sheet'!G$33 -> 1 | H54: ='Balance Sheet'!H33/'Balance Sheet'!H$33 -> 1 | I54: ='Balance Sheet'!I33/'Balance Sheet'!I$33 -> 1 | J54: ='Balance Sheet'!J33/'Balance Sheet'!J$33 -> 1 | ... Q54: ='Balance Sheet'!Q33/'Balance Sheet'!Q$33 -> 1

Sheet Ratio Analysis
B1: State Bank of India
B2: BSE: 500112 | NSE: SBIN
C3: 10000
B5: Ratio Analysis
B7: Particular | C7: 2021 | D7: =C7+1 -> 2022 | E7: =D7+1 -> 2023 | F7: =E7+1 -> 2024 | G7: =F7+1 -> 2025 | H7: =G7+1 -> 2026 | I7: =H7+1 -> 2027 | J7: =I7+1 -> 2028 | K7: =J7+1 -> 2029 | ... Q7: =P7+1 -> 2035 | R7: Trend | S7: Interpretation of ratios
C8: Audited | D8: Audited | E8: Audited | F8: Audited | G8: Audited | H8: Forecasted | I8: Forecasted | J8: Forecasted | K8: Forecasted | L8: Forecasted | M8: Forecasted | N8: Forecasted | O8: Forecasted | P8: Forecasted | Q8: Forecasted
B10: Profitability Ratios
B12: NIIs Margin | D12: =('Income Statement'!D10-'Income Statement'!D13)/AVERAGE(SUM('Balance Sheet'!C29:C30),SUM('Balance Sheet'!D29:D30)) -> 0.061204637 | E12: =('Income Statement'!E10-'Income Statement'!E13)/AVERAGE(SUM('Balance Sheet'!D29:D30),SUM('Balance Sheet'!E29:E30)) -> 0.063550622 | F12: =('Income Statement'!F10-'Income Statement'!F13)/AVERAGE(SUM('Balance Sheet'!E29:E30),SUM('Balance Sheet'!F29:F30)) -> 0.067046201 | G12: =('Income Statement'!G10-'Income Statement'!G13)/AVERAGE(SUM('Balance Sheet'!F29:F30),SUM('Balance Sheet'!G29:G30)) -> 0.065437119 | H12: =('Income Statement'!H10-'Income Statement'!H13)/AVERAGE(SUM('Balance Sheet'!G29:G30),SUM('Balance Sheet'!H29:H30)) -> 0.066262303 | I12: =('Income Statement'!I10-'Income Statement'!I13)/AVERAGE(SUM('Balance Sheet'!H29:H30),SUM('Balance Sheet'!I29:I30)) -> 0.06361084 | J12: =('Income Statement'!J10-'Income Statement'!J13)/AVERAGE(SUM('Balance Sheet'!I29:I30),SUM('Balance Sheet'!J29:J30)) -> 0.063250409 | K12: =('Income Statement'!K10-'Income Statement'!K13)/AVERAGE(SUM('Balance Sheet'!J29:J30),SUM('Balance Sheet'!K29:K30)) -> 0.062928382 | ... Q12: =('Income Statement'!Q10-'Income Statement'!Q13)/AVERAGE(SUM('Balance Sheet'!P29:P30),SUM('Balance Sheet'!Q29:Q30)) -> 0.061616509 | S12: The NII Margin demonstrated a strong upward trend during the historical period, increasing from 6.12% in 2022 to 6.36% in 2023 and reaching a peak of 6.70% in 2024, before slightly moderating to 6.54% in 2025. This improvement reflects better pricing power on loans, higher yields on earning assets, and effective control over funding costs, indicating efficient asset-liability management and strong core banking profitability. Looking ahead, the margin is projected to gradually decline from 6.63% in 2026 to 6.16% by 2035, indicating steady compression in spreads due to competitive intensity and normalization of interest rates. Despite this moderation, the margin remains consistently above 6.00%, suggesting sustainable profitability, stable operational performance, and no immediate concerns regarding earning efficiency over the forecast period.
B16: EBITDA Margin | C16: ='Income Statement'!C18/'Income Statement'!C10 -> 0.11615779 | D16: ='Income Statement'!D18/'Income Statement'!D10 -> 0.15603195 | E16: ='Income Statement'!E18/'Income Statement'!E10 -> 0.21978156 | F16: ='Income Statement'!F18/'Income Statement'!F10 -> 0.23497963 | G16: ='Income Statement'!G18/'Income Statement'!G10 -> 0.23891896 | H16: ='Income Statement'!H18/'Income Statement'!H10 -> 0.19317398 | I16: ='Income Statement'!I18/'Income Statement'!I10 -> 0.19317398 | J16: ='Income Statement'!J18/'Income Statement'!J10 -> 0.19317398 | ... Q16: ='Income Statement'!Q18/'Income Statement'!Q10 -> 0.19317398 | S16: The EBITDA Margin rose strongly from 11.62% in 2021 to 23.89% in 2025, indicating improved operational efficiency and strong cost control. However, during the forecast period, the margin is expected to decline to 19.32% in 2026 and remain stable at 19.32% through 2035. This reduction suggests normalization after peak performance, likely due to higher operating costs, competitive pricing pressure, or conservative growth assumptions. The flat trend reflects expectations of steady revenue growth aligned with expenses. Although lower than historical highs, maintaining a consistent 19.32% margin indicates sustainable profitability, stable operations, and predictable earnings over the long term.
B20: EBIT Margin | C20: ='Income Statement'!C22/'Income Statement'!C10 -> 0.10652711 | D20: ='Income Statement'!D22/'Income Statement'!D10 -> 0.14696189 | E20: ='Income Statement'!E22/'Income Statement'!E10 -> 0.21197469 | F20: ='Income Statement'!F22/'Income Statement'!F10 -> 0.22850588 | G20: ='Income Statement'!G22/'Income Statement'!G10 -> 0.23290174 | H20: ='Income Statement'!H22/'Income Statement'!H10 -> 0.18856336 | I20: ='Income Statement'!I22/'Income Statement'!I10 -> 0.18900652 | J20: ='Income Statement'!J22/'Income Statement'!J10 -> 0.18936174 | ... Q20: ='Income Statement'!Q22/'Income Statement'!Q10 -> 0.19057177 | S20: The EBIT Margin improved significantly during the historical period, increasing from 10.65% in 2021 to 23.29% in 2025, reflecting strong operating performance, better cost absorption, and improved efficiency after depreciation. However, in the forecast period, the margin is expected to decline to 18.86% in 2026 and gradually increase to 19.06% by 2035. The initial drop suggests normalization from peak levels, possibly due to higher depreciation, expansion investments, or moderate pricing pressure. The slow and steady rise from 18.86% to 19.06% indicates stable cost management and incremental operational improvements. Overall, the forecasted trend reflects sustainable operating profitability with controlled expenses, though without aggressive margin expansion, suggesting a mature and steady growth phase.
B24: Pre Provision Margin | C24: =('Income Statement'!C28+'Income Statement'!C15)/'Income Statement'!C10 -> 0.20979863 | D24: =('Income Statement'!D28+'Income Statement'!D15)/'Income Statement'!D10 -> 0.20752559 | E24: =('Income Statement'!E28+'Income Statement'!E15)/'Income Statement'!E10 -> 0.23236456 | F24: =('Income Statement'!F28+'Income Statement'!F15)/'Income Statement'!F10 -> 0.21723031 | G24: =('Income Statement'!G28+'Income Statement'!G15)/'Income Statement'!G10 -> 0.2383865 | H24: =('Income Statement'!H28+'Income Statement'!H15)/'Income Statement'!H10 -> 0.22765506 | I24: =('Income Statement'!I28+'Income Statement'!I15)/'Income Statement'!I10 -> 0.22462149 | J24: =('Income Statement'!J28+'Income Statement'!J15)/'Income Statement'!J10 -> 0.22469234 | ... Q24: =('Income Statement'!Q28+'Income Statement'!Q15)/'Income Statement'!Q10 -> 0.22457149 | S24: The Pre-Provision Margin remained relatively stable during the historical period, moving from 20.98% in 2021 to 23.84% in 2025, with some fluctuations in between. This indicates consistent operating strength before accounting for credit provisions, reflecting stable core income generation and expense control. In the forecast period, the margin is expected to moderate to 22.77% in 2026 and gradually stabilize around 22.46%–22.47% through 2035. The slight decline from the 2025 peak suggests normalization of operating income or marginal increase in operating expenses. However, the stable trend above 22.00% indicates sustained pre-provision profitability, strong internal accrual generation, and adequate buffer to absorb potential credit costs, supporting long-term financial stability.
B28: Pretax Margin | C28: ='Income Statement'!C28/'Income Statement'!C10 -> 0.068057026 | D28: ='Income Statement'!D28/'Income Statement'!D10 -> 0.10909366 | E28: ='Income Statement'!E28/'Income Statement'!E10 -> 0.15415138 | F28: ='Income Statement'!F28/'Income Statement'!F10 -> 0.16541723 | G28: ='Income Statement'!G28/'Income Statement'!G10 -> 0.16782076 | H28: ='Income Statement'!H28/'Income Statement'!H10 -> 0.13950196 | I28: ='Income Statement'!I28/'Income Statement'!I10 -> 0.13646839 | J28: ='Income Statement'!J28/'Income Statement'!J10 -> 0.13653923 | ... Q28: ='Income Statement'!Q28/'Income Statement'!Q10 -> 0.13641838 | S28: The pretax margin showed a strong and consistent improvement during the historical period, rising from 6.81% in 2021 to 16.78% in 2025, indicating robust growth in operating profitability, better cost control, and lower credit-related pressures. This expansion reflects improved income quality and operational efficiency across the business cycle. From 2026 onward, margins are forecast to moderate to 14.00% and gradually stabilize around 13.73%–13.74%, suggesting normalization after peak profitability. The softening trend implies higher operating or credit costs in a mature cycle; however, margins at these levels remain healthy, signaling sustained earnings resilience and a stable long-term profitability outlook.
B32: Effective Tax rate | C32: =Cost_BuildUp!C22 -> 0.14564349 | D32: =Cost_BuildUp!D22 -> 0.20325839 | E32: =Cost_BuildUp!E22 -> 0.23740266 | F32: =Cost_BuildUp!F22 -> 0.31791902 | G32: =Cost_BuildUp!G22 -> 0.30327525 | H32: =Cost_BuildUp!H22 -> 0.3 | I32: =Cost_BuildUp!I22 -> 0.3 | J32: =Cost_BuildUp!J22 -> 0.3 | ... Q32: =Cost_BuildUp!Q22 -> 0.3 | S32: The Pre-Tax Margin improved substantially during the historical period, rising from 6.81% in 2021 to 16.78% in 2025, reflecting stronger operating performance, improved cost efficiency, and better control over provisions and non-operating expenses. However, in the forecast period, the margin is expected to decline to 13.95% in 2026 and gradually stabilize around 13.64%–13.66% through 2035. The initial drop suggests normalization from peak profitability, possibly due to higher operating costs, increased provisions, or conservative growth assumptions. The stable trend thereafter indicates steady earnings before tax, controlled expense structure, and predictable profitability. Although lower than historical highs, maintaining margins above 13.60% reflects sustainable financial performance and operational stability over the long term.
B36: Net Margin | C36: ='Income Statement'!C32/'Income Statement'!C10 -> 0.058144964 | D36: ='Income Statement'!D32/'Income Statement'!D10 -> 0.086919457 | E36: ='Income Statement'!E32/'Income Statement'!E10 -> 0.11755543 | F36: ='Income Statement'!F32/'Income Statement'!F10 -> 0.11282795 | G36: ='Income Statement'!G32/'Income Statement'!G10 -> 0.11692488 | H36: ='Income Statement'!H32/'Income Statement'!H10 -> 0.097651369 | I36: ='Income Statement'!I32/'Income Statement'!I10 -> 0.09552787 | J36: ='Income Statement'!J32/'Income Statement'!J10 -> 0.095577461 | ... Q36: ='Income Statement'!Q32/'Income Statement'!Q10 -> 0.095492868 | S36: The Net Margin increased significantly during the historical period, rising from 5.81% in 2021 to 11.76% in 2023, before slightly moderating to 11.28% in 2024 and improving to 11.69% in 2025, reflecting strong bottom-line growth driven by higher operating efficiency and controlled tax and interest expenses. In the forecast period, the margin is expected to decline to 9.77% in 2026 and gradually stabilize around 9.55%–9.56% through 2035. The initial reduction suggests normalization of profitability due to higher costs, provisions, or conservative revenue assumptions. However, the stable trend above 9.50% indicates sustainable net profitability, steady earnings generation, and long-term financial resilience despite lower margins compared to historical peaks.
B40: Return on Capital Employed | C40: ='Income Statement'!C22/('Balance Sheet'!C33-'Balance Sheet'!C18-'Balance Sheet'!C20-'Balance Sheet'!C21) -> 0.017741383 | D40: ='Income Statement'!D22/('Balance Sheet'!D33-'Balance Sheet'!D18-'Balance Sheet'!D20-'Balance Sheet'!D21) -> 0.02314168 | E40: ='Income Statement'!E22/('Balance Sheet'!E33-'Balance Sheet'!E18-'Balance Sheet'!E20-'Balance Sheet'!E21) -> 0.03420299 | F40: ='Income Statement'!F22/('Balance Sheet'!F33-'Balance Sheet'!F18-'Balance Sheet'!F20-'Balance Sheet'!F21) -> 0.039794173 | G40: ='Income Statement'!G22/('Balance Sheet'!G33-'Balance Sheet'!G18-'Balance Sheet'!G20-'Balance Sheet'!G21) -> 0.040274465 | H40: ='Income Statement'!H22/('Balance Sheet'!H33-'Balance Sheet'!H18-'Balance Sheet'!H20-'Balance Sheet'!H21) -> 0.031315779 | I40: ='Income Statement'!I22/('Balance Sheet'!I33-'Balance Sheet'!I18-'Balance Sheet'!I20-'Balance Sheet'!I21) -> 0.031341088 | J40: ='Income Statement'!J22/('Balance Sheet'!J33-'Balance Sheet'!J18-'Balance Sheet'!J20-'Balance Sheet'!J21) -> 0.031312994 | ... Q40: ='Income Statement'!Q22/('Balance Sheet'!Q33-'Balance Sheet'!Q18-'Balance Sheet'!Q20-'Balance Sheet'!Q21) -> 0.030246917 | S40: The Return on Capital Employed (ROCE) improved during the historical period, increasing from 1.77% in 2021 to 4.03% in 2025, indicating better utilization of total capital and improved operating efficiency. This upward trend reflects stronger earnings generation relative to the capital invested in the business. However, in the forecast period, ROCE is expected to decline to 3.13% in 2026 and gradually moderate to 3.02% by 2035. The reduction suggests normalization of returns, possibly due to incremental capital deployment, moderate profit growth, or expansion-related investments. The gradual downward trend indicates slightly lower efficiency in capital utilization over time. Nevertheless, maintaining ROCE above 3.00% reflects stable operational performance and the company’s ability to generate consistent returns on its capital base over the long term.
B44: Return on Equity | D44: ='Income Statement'!D32/AVERAGE('Balance Sheet'!C15:D15) -> 0.11752452 | E44: ='Income Statement'!E32/AVERAGE('Balance Sheet'!D15:E15) -> 0.16163558 | F44: ='Income Statement'!F32/AVERAGE('Balance Sheet'!E15:F15) -> 0.16722565 | G44: ='Income Statement'!G32/AVERAGE('Balance Sheet'!F15:G15) -> 0.16579671 | H44: ='Income Statement'!H32/AVERAGE('Balance Sheet'!G15:H15) -> 0.13568309 | I44: ='Income Statement'!I32/AVERAGE('Balance Sheet'!H15:I15) -> 0.13087154 | J44: ='Income Statement'!J32/AVERAGE('Balance Sheet'!I15:J15) -> 0.12800514 | K44: ='Income Statement'!K32/AVERAGE('Balance Sheet'!J15:K15) -> 0.12421103 | ... Q44: ='Income Statement'!Q32/AVERAGE('Balance Sheet'!P15:Q15) -> 0.095506528 | S44: The Return on Equity (ROE) strengthened during the historical period, rising from 11.75% in 2022 to 16.16% in 2023 and peaking at 16.72% in 2024, before slightly moderating to 16.58% in 2025. This improvement reflects enhanced profitability and efficient utilization of shareholders’ funds. However, in the forecast period, ROE is projected to decline to 13.57% in 2026 and gradually decrease to 9.55% by 2035. The consistent downward trend suggests moderating earnings growth relative to equity expansion, possibly due to retained earnings accumulation or conservative profit assumptions. While the decline indicates reduced return efficiency over time, maintaining ROE near 9.55% still reflects stable profitability and reasonable shareholder value generation in the long term.
B48: Return on Assets | D48: ='Income Statement'!D32/AVERAGE('Balance Sheet'!C33:D33) -> 0.0069316362 | E48: ='Income Statement'!E32/AVERAGE('Balance Sheet'!D33:E33) -> 0.0098359149 | F48: ='Income Statement'!F32/AVERAGE('Balance Sheet'!E33:F33) -> 0.010574342 | G48: ='Income Statement'!G32/AVERAGE('Balance Sheet'!F33:G33) -> 0.01104236 | H48: ='Income Statement'!H32/AVERAGE('Balance Sheet'!G33:H33) -> 0.0089071562 | I48: ='Income Statement'!I32/AVERAGE('Balance Sheet'!H33:I33) -> 0.0082813981 | J48: ='Income Statement'!J32/AVERAGE('Balance Sheet'!I33:J33) -> 0.0082298293 | K48: ='Income Statement'!K32/AVERAGE('Balance Sheet'!J33:K33) -> 0.0081763472 | ... Q48: ='Income Statement'!Q32/AVERAGE('Balance Sheet'!P33:Q33) -> 0.0078563342 | S48: The Return on Assets (ROA) improved during the historical period, increasing from 0.69% in 2022 to 0.98% in 2023, further rising to 1.06% in 2024, and reaching 1.10% in 2025, reflecting improved asset utilization and stronger profitability relative to total assets. This upward trend indicates better operational efficiency and effective deployment of resources. However, in the forecast period, ROA is expected to decline to 0.89% in 2026 and gradually moderate to 0.79% by 2035. The consistent decline suggests normalization of returns due to asset base expansion or moderate earnings growth. Despite the reduction, maintaining ROA near 0.79% indicates stable asset productivity and sustainable long-term performance
B52: Dupont/Earning Power
B53: Asset Turnover | D53: ='Income Statement'!D10/AVERAGE('Balance Sheet'!C33:D33) -> 0.079747809 | E53: ='Income Statement'!E10/AVERAGE('Balance Sheet'!D33:E33) -> 0.08367044 | F53: ='Income Statement'!F10/AVERAGE('Balance Sheet'!E33:F33) -> 0.093720944 | G53: ='Income Statement'!G10/AVERAGE('Balance Sheet'!F33:G33) -> 0.094439779 | H53: ='Income Statement'!H10/AVERAGE('Balance Sheet'!G33:H33) -> 0.091213838 | I53: ='Income Statement'!I10/AVERAGE('Balance Sheet'!H33:I33) -> 0.086690911 | J53: ='Income Statement'!J10/AVERAGE('Balance Sheet'!I33:J33) -> 0.086106381 | K53: ='Income Statement'!K10/AVERAGE('Balance Sheet'!J33:K33) -> 0.085527608 | ... Q53: ='Income Statement'!Q10/AVERAGE('Balance Sheet'!P33:Q33) -> 0.082271424 | S53: The Asset Turnover ratio improved during the historical period, increasing from 7.97% in 2022 to 8.37% in 2023, further rising to 9.37% in 2024, and peaking at 9.44% in 2025, indicating more efficient utilization of assets to generate revenue. The improvement reflects stronger operational performance and better revenue generation from the existing asset base. However, in the forecast period, the ratio is expected to decline to 9.12% in 2026 and gradually moderate to 8.23% by 2035. The steady downward trend suggests that asset growth may outpace revenue growth, possibly due to expansion or conservative revenue assumptions. Despite the decline, maintaining levels above 8.00% indicates stable operational efficiency and sustainable revenue generation capacity over the long term.
B57: Pre tax ROA | D57: ='Income Statement'!D28/AVERAGE('Balance Sheet'!C33:D33) -> 0.0086999802 | E57: ='Income Statement'!E28/AVERAGE('Balance Sheet'!D33:E33) -> 0.012897914 | F57: ='Income Statement'!F28/AVERAGE('Balance Sheet'!E33:F33) -> 0.015503059 | G57: ='Income Statement'!G28/AVERAGE('Balance Sheet'!F33:G33) -> 0.015848956 | H57: ='Income Statement'!H28/AVERAGE('Balance Sheet'!G33:H33) -> 0.012724509 | I57: ='Income Statement'!I28/AVERAGE('Balance Sheet'!H33:I33) -> 0.011830569 | J57: ='Income Statement'!J28/AVERAGE('Balance Sheet'!I33:J33) -> 0.011756899 | K57: ='Income Statement'!K28/AVERAGE('Balance Sheet'!J33:K33) -> 0.011680496 | ... Q57: ='Income Statement'!Q28/AVERAGE('Balance Sheet'!P33:Q33) -> 0.011223335 | S57: The Pre-Tax Return on Assets (Pre-Tax ROA) improved during the historical period, increasing from 0.87% in 2022 to 1.29% in 2023, further rising to 1.55% in 2024, and reaching 1.58% in 2025, reflecting stronger operating profitability relative to the asset base before the impact of taxes. This upward trend indicates improved asset efficiency and better core earnings generation. However, in the forecast period, Pre-Tax ROA is expected to decline to 1.27% in 2026 and gradually moderate to 1.12% by 2035. The steady decline suggests normalization of profitability, possibly due to asset expansion or conservative earnings assumptions. Despite this moderation, maintaining Pre-Tax ROA above 1.10% indicates stable operating performance and sustainable asset productivity over the long term.
B61: Pre Tax ROE | D61: ='Income Statement'!D28/AVERAGE('Balance Sheet'!C15:D15) -> 0.14750645 | E61: ='Income Statement'!E28/AVERAGE('Balance Sheet'!D15:E15) -> 0.21195403 | F61: ='Income Statement'!F28/AVERAGE('Balance Sheet'!E15:F15) -> 0.24516979 | G61: ='Income Statement'!G28/AVERAGE('Balance Sheet'!F15:G15) -> 0.23796587 | H61: ='Income Statement'!H28/AVERAGE('Balance Sheet'!G15:H15) -> 0.19383299 | I61: ='Income Statement'!I28/AVERAGE('Balance Sheet'!H15:I15) -> 0.18695934 | J61: ='Income Statement'!J28/AVERAGE('Balance Sheet'!I15:J15) -> 0.18286449 | K61: ='Income Statement'!K28/AVERAGE('Balance Sheet'!J15:K15) -> 0.17744432 | ... Q61: ='Income Statement'!Q28/AVERAGE('Balance Sheet'!P15:Q15) -> 0.1364379 | S61: The Pre-Tax Return on Equity (Pre-Tax ROE) strengthened significantly during the historical period, rising from 14.75% in 2022 to 21.20% in 2023 and peaking at 24.52% in 2024, before slightly moderating to 23.80% in 2025, reflecting strong profitability and efficient utilization of shareholders’ funds before tax impact. However, in the forecast period, Pre-Tax ROE is expected to decline to 19.38% in 2026 and gradually decrease to 13.64% by 2035. The consistent downward trend suggests normalization of earnings growth relative to equity expansion, possibly due to retained earnings accumulation or moderate profit projections. Despite the decline, maintaining levels above 13.60% indicates sustainable pre-tax profitability and steady long-term value creation for shareholders.
B65: Tax Complement | C65: ='Income Statement'!C32/'Income Statement'!C28 -> 0.85435651 | D65: ='Income Statement'!D32/'Income Statement'!D28 -> 0.79674161 | E65: ='Income Statement'!E32/'Income Statement'!E28 -> 0.76259734 | F65: ='Income Statement'!F32/'Income Statement'!F28 -> 0.68208098 | G65: ='Income Statement'!G32/'Income Statement'!G28 -> 0.69672475 | H65: ='Income Statement'!H32/'Income Statement'!H28 -> 0.7 | I65: ='Income Statement'!I32/'Income Statement'!I28 -> 0.7 | J65: ='Income Statement'!J32/'Income Statement'!J28 -> 0.7 | ... Q65: ='Income Statement'!Q32/'Income Statement'!Q28 -> 0.7 | S65: The Tax Complement (1 – Tax Rate) declined during the historical period from 0.85x in 2021 to 0.80x in 2022 and 0.76x in 2023, further dropping to 0.68x in 2024, before slightly improving to 0.70x in 2025. The decline indicates an increase in the effective tax rate over time, reducing the proportion of pre-tax income retained as net profit. In the forecast period from 2026 to 2035, the Tax Complement is expected to remain stable at 0.70x throughout. This stability suggests a consistent effective tax rate assumption in projections, leading to predictable post-tax earnings. Maintaining a steady 0.70x implies stable tax planning and no significant anticipated changes in tax structure, supporting earnings visibility over the long term.
B69: Equity Retention | C69: ='Income Statement'!C37/'Income Statement'!C32 -> 1 | D69: ='Income Statement'!D37/'Income Statement'!D32 -> 0.89908247 | E69: ='Income Statement'!E37/'Income Statement'!E32 -> 0.88612885 | F69: ='Income Statement'!F37/'Income Statement'!F32 -> 0.84967039 | G69: ='Income Statement'!G37/'Income Statement'!G32 -> 0.84236066 | H69: ='Income Statement'!H37/'Income Statement'!H32 -> 0.86931059 | I69: ='Income Statement'!I37/'Income Statement'!I32 -> 0.86931059 | J69: ='Income Statement'!J37/'Income Statement'!J32 -> 0.86931059 | ... Q69: ='Income Statement'!Q37/'Income Statement'!Q32 -> 0.86931059 | S69: The Equity Retention Ratio declined during the historical period from 1.00x in 2021 to 0.90x in 2022, further moderating to 0.89x in 2023, 0.85x in 2024, and 0.84x in 2025. This downward trend indicates that a smaller proportion of earnings was retained within the business, possibly due to higher dividend payouts or profit distribution to shareholders. In the forecast period from 2026 to 2035, the ratio is expected to improve and stabilize at 0.87x throughout. The increase from 0.84x to 0.87x suggests a slightly higher retention of earnings to support growth and capital strengthening. The stable trend reflects a balanced dividend policy and consistent reinvestment strategy, supporting sustainable long-term expansion.
B73: Liquidity Ratio
B75: Loan to Deposit Ratio | C75: ='Balance Sheet'!C30/SUM('Balance Sheet'!C18:C19) -> 0.67304873 | D75: ='Balance Sheet'!D30/SUM('Balance Sheet'!D18:D19) -> 0.68358095 | E75: ='Balance Sheet'!E30/SUM('Balance Sheet'!E18:E19) -> 0.7313139 | F75: ='Balance Sheet'!F30/SUM('Balance Sheet'!F18:F19) -> 0.76195391 | G75: ='Balance Sheet'!G30/SUM('Balance Sheet'!G18:G19) -> 0.78141736 | H75: ='Balance Sheet'!H30/SUM('Balance Sheet'!H18:H19) -> 0.72311844 | I75: ='Balance Sheet'!I30/SUM('Balance Sheet'!I18:I19) -> 0.72311844 | J75: ='Balance Sheet'!J30/SUM('Balance Sheet'!J18:J19) -> 0.72311844 | ... Q75: ='Balance Sheet'!Q30/SUM('Balance Sheet'!Q18:Q19) -> 0.72311844 | S75: The Loan to Deposit Ratio increased during the historical period from 0.67x in 2021 to 0.68x in 2022, rising further to 0.73x in 2023, 0.76x in 2024, and peaking at 0.78x in 2025. This upward trend indicates stronger credit growth relative to deposit mobilization, reflecting improved lending activity and higher utilization of available funds. However, in the forecast period from 2026 to 2035, the ratio is projected to decline to 0.72x and remain stable at 0.72x throughout. The moderation suggests a more balanced approach between loan growth and deposit expansion, reducing liquidity risk. Maintaining a steady 0.72x indicates prudent asset-liability management, adequate liquidity buffers, and sustainable credit growth over the long term.
B79: Cash to Deposit Ratio | C79: =SUM('Balance Sheet'!C27:C28)/SUM('Balance Sheet'!C18:C19) -> 0.093587089 | D79: =SUM('Balance Sheet'!D27:D28)/SUM('Balance Sheet'!D18:D19) -> 0.097593602 | E79: =SUM('Balance Sheet'!E27:E28)/SUM('Balance Sheet'!E18:E19) -> 0.071234056 | F79: =SUM('Balance Sheet'!F27:F28)/SUM('Balance Sheet'!F18:F19) -> 0.065754523 | G79: =SUM('Balance Sheet'!G27:G28)/SUM('Balance Sheet'!G18:G19) -> 0.06579773 | H79: =SUM('Balance Sheet'!H27:H28)/SUM('Balance Sheet'!H18:H19) -> 0.081691018 | I79: =SUM('Balance Sheet'!I27:I28)/SUM('Balance Sheet'!I18:I19) -> 0.08284292 | J79: =SUM('Balance Sheet'!J27:J28)/SUM('Balance Sheet'!J18:J19) -> 0.084770702 | ... Q79: =SUM('Balance Sheet'!Q27:Q28)/SUM('Balance Sheet'!Q18:Q19) -> 0.11221735 | S79: The Cash to Deposit Ratio showed moderate fluctuations during the historical period, increasing from 0.09x in 2021 to 0.10x in 2022, before declining to 0.07x in 2023, and remaining at 0.07x through 2025. The decline suggests a lower proportion of deposits held in cash, possibly due to higher deployment of funds into earning assets to enhance profitability. In the forecast period from 2026 to 2035, the ratio is expected to gradually improve from 0.08x in 2026 to 0.11x by 2035. The steady increase indicates a strengthening liquidity position and a more conservative liquidity buffer. Maintaining levels around 0.10x–0.11x reflects improved cash reserves relative to deposits, supporting financial stability and risk management over the long term.
B83: Liquid Assets to Total Assets | C83: =SUM('Balance Sheet'!C27:C29)/'Balance Sheet'!C33 -> 0.40094103 | D83: =SUM('Balance Sheet'!D27:D29)/'Balance Sheet'!D33 -> 0.40579039 | E83: =SUM('Balance Sheet'!E27:E29)/'Balance Sheet'!E33 -> 0.37475025 | F83: =SUM('Balance Sheet'!F27:F29)/'Balance Sheet'!F33 -> 0.36192465 | G83: =SUM('Balance Sheet'!G27:G29)/'Balance Sheet'!G33 -> 0.35048798 | H83: =SUM('Balance Sheet'!H27:H29)/'Balance Sheet'!H33 -> 0.38137656 | I83: =SUM('Balance Sheet'!I27:I29)/'Balance Sheet'!I33 -> 0.38195146 | J83: =SUM('Balance Sheet'!J27:J29)/'Balance Sheet'!J33 -> 0.38287294 | ... Q83: =SUM('Balance Sheet'!Q27:Q29)/'Balance Sheet'!Q33 -> 0.39525733 | S83: The Liquid Assets to Total Assets ratio improved slightly from 0.40x in 2021 to 0.41x in 2022, but then declined to 0.37x in 2023, 0.36x in 2024, and 0.35x in 2025, indicating a gradual reduction in the proportion of highly liquid assets within the overall asset base. This decline suggests greater deployment of funds into loans or higher-yielding assets to enhance profitability. In the forecast period from 2026 to 2035, the ratio is expected to recover to 0.38x in 2026 and gradually increase to 0.40x by 2035. The upward trend reflects a strengthening liquidity position and a more balanced asset allocation. Maintaining levels near 0.40x indicates adequate liquidity buffers and prudent risk management over the long term.
B87: Short term Borrowings to Total Liabilities | C87: ='Balance Sheet'!C20/'Balance Sheet'!C22 -> 0.095121755 | D87: ='Balance Sheet'!D20/'Balance Sheet'!D22 -> 0.089046777 | E87: ='Balance Sheet'!E20/'Balance Sheet'!E22 -> 0.093352067 | F87: ='Balance Sheet'!F20/'Balance Sheet'!F22 -> 0.10147343 | G87: ='Balance Sheet'!G20/'Balance Sheet'!G22 -> 0.089711593 | H87: ='Balance Sheet'!H20/'Balance Sheet'!H22 -> 0.093638787 | I87: ='Balance Sheet'!I20/'Balance Sheet'!I22 -> 0.093638787 | J87: ='Balance Sheet'!J20/'Balance Sheet'!J22 -> 0.093638787 | ... Q87: ='Balance Sheet'!Q20/'Balance Sheet'!Q22 -> 0.093638787 | S87: The Short-Term Borrowings to Total Liabilities ratio remained relatively stable during the historical period, moving from 0.10x in 2021 to 0.09x in 2022 and 2023, rising slightly to 0.10x in 2024, and moderating again to 0.09x in 2025. This consistency indicates a controlled reliance on short-term funding within the overall liability structure, reflecting prudent liability management and limited refinancing risk. In the forecast period from 2026 to 2035, the ratio is expected to remain stable at 0.09x throughout. The flat trend suggests no significant shift toward short-term leverage, supporting financial stability, lower liquidity risk, and a well-balanced funding mix over the long term.
B91: Leverage Ratio
B93: Asset/Equity | C93: ='Balance Sheet'!C33/'Balance Sheet'!C15 -> 16.990993 | D93: ='Balance Sheet'!D33/'Balance Sheet'!D15 -> 16.922223 | E93: ='Balance Sheet'!E33/'Balance Sheet'!E15 -> 16.016492 | F93: ='Balance Sheet'!F33/'Balance Sheet'!F15 -> 15.639687 | G93: ='Balance Sheet'!G33/'Balance Sheet'!G15 -> 14.48174 | H93: ='Balance Sheet'!H33/'Balance Sheet'!H15 -> 15.897745 | I93: ='Balance Sheet'!I33/'Balance Sheet'!I15 -> 15.718948 | J93: ='Balance Sheet'!J33/'Balance Sheet'!J15 -> 15.406675 | ... Q93: ='Balance Sheet'!Q33/'Balance Sheet'!Q15 -> 11.909648 | S93: The Asset-to-Equity ratio declined during the historical period from 16.99x in 2021 to 16.92x in 2022, further decreasing to 16.02x in 2023, 15.64x in 2024, and 14.48x in 2025, indicating a gradual reduction in financial leverage. This trend suggests stronger equity growth relative to total assets, reflecting improved capitalization and lower dependency on debt funding. In the forecast period from 2026 to 2035, the ratio is projected to rise to 15.90x in 2026 but then steadily decline to 11.91x by 2035. The long-term downward trend implies continued strengthening of the equity base and a more conservative capital structure. Lower leverage enhances financial stability, reduces risk exposure, and improves the company’s resilience against economic volatility over time.
B97: Debt/Equity | C97: ='Balance Sheet'!C20/'Balance Sheet'!C15 -> 1.5210914 | D97: ='Balance Sheet'!D20/'Balance Sheet'!D15 -> 1.4178226 | E97: ='Balance Sheet'!E20/'Balance Sheet'!E15 -> 1.4018206 | F97: ='Balance Sheet'!F20/'Balance Sheet'!F15 -> 1.4855392 | G97: ='Balance Sheet'!G20/'Balance Sheet'!G15 -> 1.2094684 | H97: ='Balance Sheet'!H20/'Balance Sheet'!H15 -> 1.3950068 | I97: ='Balance Sheet'!I20/'Balance Sheet'!I15 -> 1.3782644 | J97: ='Balance Sheet'!J20/'Balance Sheet'!J15 -> 1.3490236 | ... Q97: ='Balance Sheet'!Q20/'Balance Sheet'!Q15 -> 1.0215662 | S97: The Debt-to-Equity ratio declined during the historical period from 1.52x in 2021 to 1.42x in 2022 and 1.40x in 2023, briefly increasing to 1.49x in 2024, before falling sharply to 1.21x in 2025. This overall downward movement indicates reduced financial leverage and strengthening of the equity base relative to debt. In the forecast period from 2026 to 2035, the ratio is projected to rise to 1.40x in 2026 and then gradually decline to 1.02x by 2035. The long-term decreasing trend suggests a shift toward a more conservative capital structure with lower reliance on external borrowings. A ratio nearing 1.00x reflects balanced financing, reduced financial risk, improved solvency, and stronger long-term financial stability.
B101: Efficiency Ratios
B103: Efficiency Ratio | C103: =('Income Statement'!C14+'Income Statement'!C15)/'Income Statement'!C10 -> 0.51258247 | D103: =('Income Statement'!D14+'Income Statement'!D15)/'Income Statement'!D10 -> 0.49562737 | E103: =('Income Statement'!E14+'Income Statement'!E15)/'Income Statement'!E10 -> 0.43478893 | F103: =('Income Statement'!F14+'Income Statement'!F15)/'Income Statement'!F10 -> 0.38949374 | G103: =('Income Statement'!G14+'Income Statement'!G15)/'Income Statement'!G10 -> 0.37029077 | H103: =('Income Statement'!H14+'Income Statement'!H15)/'Income Statement'!H10 -> 0.44055665 | I103: =('Income Statement'!I14+'Income Statement'!I15)/'Income Statement'!I10 -> 0.44055665 | J103: =('Income Statement'!J14+'Income Statement'!J15)/'Income Statement'!J10 -> 0.44055665 | ... Q103: =('Income Statement'!Q14+'Income Statement'!Q15)/'Income Statement'!Q10 -> 0.44055665 | S103: The Efficiency Ratio improved significantly during the historical period, declining from 51.00% in 2021 to 50.00% in 2022, further reducing to 43.00% in 2023, 39.00% in 2024, and reaching 37.00% in 2025. Since a lower ratio indicates better cost efficiency, this trend reflects strong expense control and improved operational productivity relative to revenue generation. However, in the forecast period from 2026 to 2035, the ratio is expected to increase to 44.00% and remain stable at 44.00% throughout. The rise suggests normalization of operating costs or conservative revenue assumptions. Despite the increase from peak efficiency, maintaining 44.00% still indicates healthy cost management and sustainable operational performance over the long term.
B107: Fixed Asset Turnover Ratio | D107: ='Income Statement'!D10/AVERAGE('Balance Sheet'!C31:D31) -> 10.215596 | E107: ='Income Statement'!E10/AVERAGE('Balance Sheet'!D31:E31) -> 11.282001 | F107: ='Income Statement'!F10/AVERAGE('Balance Sheet'!E31:F31) -> 13.343908 | G107: ='Income Statement'!G10/AVERAGE('Balance Sheet'!F31:G31) -> 14.571629 | H107: ='Income Statement'!H10/AVERAGE('Balance Sheet'!G31:H31) -> 14.459739 | I107: ='Income Statement'!I10/AVERAGE('Balance Sheet'!H31:I31) -> 13.915834 | J107: ='Income Statement'!J10/AVERAGE('Balance Sheet'!I31:J31) -> 14.029547 | K107: ='Income Statement'!K10/AVERAGE('Balance Sheet'!J31:K31) -> 14.084094 | ... Q107: ='Income Statement'!Q10/AVERAGE('Balance Sheet'!P31:Q31) -> 13.401852 | S107: The Fixed Asset Turnover Ratio improved during the historical period from 10.22x in 2022 to 11.28x in 2023, further rising to 13.34x in 2024 and reaching 14.57x in 2025, reflecting strong improvement in the company’s ability to generate revenue from its fixed asset base. This trend indicates better capacity utilization and operational efficiency. In the forecast period from 2026 to 2035, the ratio is expected to moderate from 14.46x in 2026 to 13.40x by 2035. The gradual decline suggests fixed asset growth may outpace revenue growth due to expansion or capital expenditure plans. However, maintaining levels above 13.00x indicates sustained asset productivity and stable long-term operational performance.

Sheet Charts
B1: State Bank of India
B2: BSE: 500112 | NSE: SBIN
C3: 10000
B5: Charts

Sheet Market Return
B1: State Bank of India
B2: BSE: 500112 | NSE: SBIN
C3: 10000
B5: BSE Sensex
B7: Date | C7: Close Price | E7: Year | F7: =YEARFRAC(B8,B2486) -> 10
B8: 42410 | C8: 23758.9 | E8: Return | F8: =_xlfn.RRI(F7,C8,C2486) -> 0.13497602
B9: 42411 | C9: 22951.83
B10: 42412 | C10: 22986.12 | E10: Source - | F10: Historical - Indices
B11: 42415 | C11: 23554.12
B12: 42416 | C12: 23191.97
B13: 42417 | C13: 23381.87
B14: 42418 | C14: 23649.22
B15: 42419 | C15: 23709.15
B16: 42422 | C16: 23788.79
B17: 42423 | C17: 23410.18
B18: 42424 | C18: 23088.93
B19: 42425 | C19: 22976
B20: 42426 | C20: 23154.3
B21: 42429 | C21: 23002
B22: 42430 | C22: 23779.35
... B2486: 46063 | C2486: 84273.92

Sheet Equity Beta
B1: State Bank of India
B2: BSE: 500112 | NSE: SBIN
C3: 10000
B5: Equity Return
B7: Month | C7: Closing price of Sensex | D7: % Change Of Return | E7: Closing Price Of Stocks | F7: % Change Of Return | H7: Source - | I7: Historical - Indices
B9: 44228 | C9: 49099.99 | E9: 390.2 | H9: Beta | I9: =SLOPE(F10:F69,D10:D69) -> 1.0123305
B10: 44256 | C10: 49509.15 | D10: =C10/C9-1 -> 0.0083331993 | E10: 364.35 | F10: =E10/E9-1 -> -0.066248078 | H10: Beta | I10: =_xlfn.COVARIANCE.S(F10:F69,D10:D69)/_xlfn.VAR.S(D10:D69) -> 1.0123305
B11: 44287 | C11: 48782.36 | D11: =C11/C10-1 -> -0.014679913 | E11: 353.45 | F11: =E11/E10-1 -> -0.029916289 | H11: Beta | I11: =I30 -> 1.0123305
B12: 44317 | C12: 51937.44 | D12: =C12/C11-1 -> 0.064676658 | E12: 424.25 | F12: =E12/E11-1 -> 0.20031122
B13: 44348 | C13: 52482.71 | D13: =C13/C12-1 -> 0.010498592 | E13: 419.25 | F13: =E13/E12-1 -> -0.011785504 | H13: SUMMARY OUTPUT
B14: 44378 | C14: 52586.84 | D14: =C14/C13-1 -> 0.001984082 | E14: 431.7 | F14: =E14/E13-1 -> 0.029695886
B15: 44409 | C15: 57552.39 | D15: =C15/C14-1 -> 0.094425716 | E15: 426 | F15: =E15/E14-1 -> -0.013203614 | H15: Regression Statistics
B16: 44440 | C16: 59126.36 | D16: =C16/C15-1 -> 0.027348473 | E16: 453.05 | F16: =E16/E15-1 -> 0.063497653 | H16: Multiple R | I16: 0.50508829
B17: 44470 | C17: 59306.93 | D17: =C17/C16-1 -> 0.0030539678 | E17: 502.4 | F17: =E17/E16-1 -> 0.10892837 | H17: R Square | I17: 0.25511418
B18: 44501 | C18: 57064.87 | D18: =C18/C17-1 -> -0.037804351 | E18: 460.6 | F18: =E18/E17-1 -> -0.083200637 | H18: Adjusted R Square | I18: 0.24227132
B19: 44531 | C19: 58253.82 | D19: =C19/C18-1 -> 0.02083506 | E19: 460.45 | F19: =E19/E18-1 -> -0.00032566218 | H19: Standard Error | I19: 0.061127309
B20: 44562 | C20: 58014.17 | D20: =C20/C19-1 -> -0.0041138933 | E20: 538.35 | F20: =E20/E19-1 -> 0.16918232 | H20: Observations | I20: 60
B21: 44593 | C21: 56247.28 | D21: =C21/C20-1 -> -0.03045618 | E21: 483.3 | F21: =E21/E20-1 -> -0.1022569
B22: 44621 | C22: 58568.51 | D22: =C22/C21-1 -> 0.041268307 | E22: 493.4 | F22: =E22/E21-1 -> 0.020897993 | H22: ANOVA
B23: 44652 | C23: 57060.87 | D23: =C23/C22-1 -> -0.025741478 | E23: 496.5 | F23: =E23/E22-1 -> 0.0062829347 | I23: df | J23: SS | K23: MS | L23: F | M23: Significance F
B24: 44682 | C24: 55566.41 | D24: =C24/C23-1 -> -0.026190628 | E24: 467.8 | F24: =E24/E23-1 -> -0.057804632 | H24: Regression | I24: 1 | J24: 0.074223843 | K24: 0.074223843 | L24: 19.864283 | M24: 3.8592211e-05
B25: 44713 | C25: 53018.94 | D25: =C25/C24-1 -> -0.045845503 | E25: 465.8 | F25: =E25/E24-1 -> -0.0042753313 | H25: Residual | I25: 58 | J25: 0.21671978 | K25: 0.0037365479
B26: 44743 | C26: 57570.25 | D26: =C26/C25-1 -> 0.085843097 | E26: 528.2 | F26: =E26/E25-1 -> 0.13396307 | H26: Total | I26: 59 | J26: 0.29094362
B27: 44774 | C27: 59537.07 | D27: =C27/C26-1 -> 0.034163826 | E27: 531.15 | F27: =E27/E26-1 -> 0.0055850057
B28: 44805 | C28: 57426.92 | D28: =C28/C27-1 -> -0.035442624 | E28: 531.05 | F28: =E28/E27-1 -> -0.00018827073 | I28: Coefficients | J28: Standard Error | K28: t Stat | L28: P-value | M28: Lower 95% | N28: Upper 95% | O28: Lower 95.0% | P28: Upper 95.0%
B29: 44835 | C29: 60746.59 | D29: =C29/C28-1 -> 0.057806861 | E29: 573.8 | F29: =E29/E28-1 -> 0.080500894 | H29: Intercept | I29: 0.0094054282 | J29: 0.0081582976 | K29: 1.1528665 | L29: 0.25369446 | M29: -0.0069251786 | N29: 0.025736035 | O29: -0.0069251786 | P29: 0.025736035
B30: 44866 | C30: 63099.65 | D30: =C30/C29-1 -> 0.038735672 | E30: 602.5 | F30: =E30/E29-1 -> 0.050017428 | H30: X Variable 1 | I30: 1.0123305 | J30: 0.22713596 | K30: 4.4569365 | L30: 3.8592211e-05 | M30: 0.55766852 | N30: 1.4669926 | O30: 0.55766852 | P30: 1.4669926
B31: 44896 | C31: 60840.74 | D31: =C31/C30-1 -> -0.035799089 | E31: 613.2 | F31: =E31/E30-1 -> 0.017759336
B32: 44927 | C32: 59549.9 | D32: =C32/C31-1 -> -0.021216704 | E32: 553.7 | F32: =E32/E31-1 -> -0.097031963
B33: 44958 | C33: 58962.12 | D33: =C33/C32-1 -> -0.0098703776 | E33: 522.75 | F33: =E33/E32-1 -> -0.055896695
B34: 44986 | C34: 58991.52 | D34: =C34/C33-1 -> 0.00049862522 | E34: 523.7 | F34: =E34/E33-1 -> 0.0018173123
B35: 45017 | C35: 61112.44 | D35: =C35/C34-1 -> 0.035952964 | E35: 578.05 | F35: =E35/E34-1 -> 0.10378079
B36: 45047 | C36: 62622.24 | D36: =C36/C35-1 -> 0.024705281 | E36: 580.55 | F36: =E36/E35-1 -> 0.0043248854
B37: 45078 | C37: 64718.56 | D37: =C37/C36-1 -> 0.033475647 | E37: 572.8 | F37: =E37/E36-1 -> -0.01334941
B38: 45108 | C38: 66527.67 | D38: =C38/C37-1 -> 0.027953496 | E38: 620.1 | F38: =E38/E37-1 -> 0.082576816
B39: 45139 | C39: 64831.41 | D39: =C39/C38-1 -> -0.02549706 | E39: 561.3 | F39: =E39/E38-1 -> -0.094823416
B40: 45170 | C40: 65828.41 | D40: =C40/C39-1 -> 0.015378348 | E40: 598.7 | F40: =E40/E39-1 -> 0.066631035
B41: 45200 | C41: 63874.93 | D41: =C41/C40-1 -> -0.029675333 | E41: 565.35 | F41: =E41/E40-1 -> -0.055704025
B42: 45231 | C42: 66988.44 | D42: =C42/C41-1 -> 0.04874385 | E42: 564.7 | F42: =E42/E41-1 -> -0.0011497303
... B69: 46054 | C69: 81666.46 | D69: =C69/C68-1 -> -0.007333434 | E69: 1028.45 | F69: =E69/E68-1 -> -0.045566331

Sheet Comps Data
B1: State Bank of India
B2: BSE: 500112 | NSE: SBIN
C3: 10000
B4: (INR in Crores)
B5: Comps Data
B7: Name | C7: CMP Rs. | D7: No. Eq. Shares Cr. | E7: Debt Rs.Cr. | F7: Cash End Rs.Cr. | G7: NP Ann Rs.Cr. | H7: Sales Rs.Cr. | I7: Dep Ann Rs.Cr. | J7: EBIT Ann Rs.Cr. | K7: EV / EBITDA | L7: EV Rs.Cr. | M7: Mar Cap Rs.Cr. | N7: Tax Ann Rs.Cr. | O7: P/E | P7: Debt / Eq | Q7: Tax 12M Rs.Cr.
B9: Bank of Baroda | C9: 290.35 | D9: 517.14 | E9: 1673450.5 | F9: 54139.23 | G9: 20865.26 | H9: 131574.32 | I9: 1466.95 | J9: 105844.24 | K9: 16.64 | L9: 1774606.3 | M9: 153149.89 | N9: 7159.61 | O9: 7.96 | P9: 10.53 | Q9: 6864.32
B10: Punjab Natl.Bank | C10: 122.96 | D10: 1149.29 | E10: 1788466.4 | F10: 61154.27 | G10: 18552.61 | H10: 130497.41 | I10: 957.51 | J10: 106715.25 | K10: 16.42 | L10: 1871143.4 | M10: 138087.71 | N10: 7462.87 | O10: 7.76 | P10: 12.01 | Q10: 9944.65
B11: Canara Bank | C11: 146.83 | D11: 907.07 | E11: 1618603 | F11: 86837.44 | G11: 17691.9 | H11: 125841.25 | I11: 869.77 | J11: 105703.43 | K11: 15.08 | L11: 1687376 | M11: 137701.56 | N11: 5689.03 | O11: 7.19 | P11: 14.05 | Q11: 5788.95
B12: Union Bank (I) | C12: 179.26 | D12: 763.36 | E12: 1304329.3 | F12: 87764.32 | G12: 18026.95 | H12: 108368.24 | I12: 1083.88 | J12: 94154.97 | K12: 14.72 | L12: 1392978 | M12: 131885.8 | N12: 5502.71 | O12: 6.96 | P12: 9.95 | Q12: 5085.83
B13: Indian Bank | C13: 906.05 | D13: 134.7 | E13: 839819 | F13: 24768.04 | G13: 11264.39 | H13: 65875.22 | I13: 542.94 | J13: 51688.06 | K13: 16.48 | L13: 927776.66 | M13: 118054.66 | N13: 3868.64 | O13: 9.82 | P13: 10.51 | Q13: 4580.36
B14: Bank of India | C14: 167.57 | D14: 455.27 | E14: 996990.99 | F14: 50343.93 | G14: 9552.17 | H14: 74518.88 | I14: 603.56 | J14: 59162.21 | K14: 16.38 | L14: 1035850.3 | M14: 72683.34 | N14: 3218.86 | O14: 7.13 | P14: 11.54 | Q14: 3337.38
B15: I O B | C15: 34.52 | D15: 1925.66 | E15: 396107.32 | F15: 16880.4 | G15: 3334.71 | H15: 31040.32 | I15: 394.46 | J15: 21750.71 | K15: 17.91 | L15: 447363.19 | M15: 65645.71 | N15: 1177.01 | O15: 13.81 | P15: 10.93 | Q15: 1409.74
B16: Bank of Maha | C16: 67.04 | D16: 769.16 | E16: 351995.89 | F16: 36967.7 | G16: 5541.78 | H16: 28257.38 | I16: 290.6 | J16: 18821.97 | K16: 17.61 | L16: 391797.24 | M16: 50479.68 | N16: 0 | O16: 7.8 | P16: 10.54 | Q16: 566.91
B17: UCO Bank | C17: 29.08 | D17: 1253.96 | E17: 335610.79 | F17: 9771.52 | G17: 2444.99 | H17: 26369.61 | I17: 311.26 | J17: 19270 | K17: 17.9 | L17: 362546.05 | M17: 36051.23 | N17: 1388.59 | O17: 13.76 | P17: 10.11 | Q17: 1543.38
B18: Central Bank | C18: 37.96 | D18: 905.14 | E18: 484345.89 | F18: 21511.09 | G18: 3943.21 | H18: 35123.16 | I18: 557.57 | J18: 24946.29 | K18: 18.2 | L18: 501017.54 | M18: 32865.64 | N18: 1149.01 | O18: 6.81 | P18: 12.26 | Q18: 1332.84
B21: SBI | C21: 1144.1 | D21: 923.06 | E21: 6305862.7 | F21: 208893.69 | G21: 80522.63 | H21: 505419.84 | I21: 3991.48 | J21: 407324.86 | K21: 16.66 | L21: 6982677.8 | M21: 950292.08 | N21: 27348.14 | O21: 12.09 | P21: 11.08 | Q21: 28101.11

Sheet Comparable Valuation
B1: State Bank of India
B2: BSE: 500112 | NSE: SBIN
C3: 10000
B5: Comparable Valuation
B6: (All amounts in INR Cr., unless otherwise stated)
B7: Companies | E7: Market Data | L7: Financial data | P7: Valution
E8: Price | F8: Share | G8: Market Cap | H8: Debt | I8: Cash | J8: EV | L8: Sales | M8: EBITDA | N8: Earnings | P8: EV/Sales | Q8: EV/EBITDA | R8: P/E
B9: Company Name | C9: Country | E9: (/share) | F9: (INR Cr) | G9: (INR Cr) | H9: (INR Cr) | I9: (INR Cr) | J9: (INR Cr) | L9: (INR Cr) | M9: (INR Cr) | N9: (INR Cr) | P9: x | Q9: x | R9: x
B11: ='Comps Data'!B9 -> Bank of Baroda | C11: India | E11: ='Comps Data'!C9 -> 290.35 | F11: ='Comps Data'!D9 -> 517.14 | G11: =F11*E11 -> 150151.6 | H11: ='Comps Data'!E9 -> 1673450.5 | I11: ='Comps Data'!F9 -> 54139.23 | J11: =G11+H11-I11 -> 1769462.9 | L11: ='Comps Data'!H9 -> 131574.32 | M11: ='Comps Data'!I9+'Comps Data'!J9 -> 107311.19 | N11: ='Comps Data'!G9 -> 20865.26 | P11: =J11/L11 -> 13.448391 | Q11: =J11/M11 -> 16.489081 | R11: =G11/N11 -> 7.1962486
B12: ='Comps Data'!B10 -> Punjab Natl.Bank | C12: India | E12: ='Comps Data'!C10 -> 122.96 | F12: ='Comps Data'!D10 -> 1149.29 | G12: =F12*E12 -> 141316.7 | H12: ='Comps Data'!E10 -> 1788466.4 | I12: ='Comps Data'!F10 -> 61154.27 | J12: =G12+H12-I12 -> 1868628.9 | L12: ='Comps Data'!H10 -> 130497.41 | M12: ='Comps Data'!I10+'Comps Data'!J10 -> 107672.76 | N12: ='Comps Data'!G10 -> 18552.61 | P12: =J12/L12 -> 14.319279 | Q12: =J12/M12 -> 17.354704 | R12: =G12/N12 -> 7.6170791
B13: ='Comps Data'!B11 -> Canara Bank | C13: India | E13: ='Comps Data'!C11 -> 146.83 | F13: ='Comps Data'!D11 -> 907.07 | G13: =F13*E13 -> 133185.09 | H13: ='Comps Data'!E11 -> 1618603 | I13: ='Comps Data'!F11 -> 86837.44 | J13: =G13+H13-I13 -> 1664950.6 | L13: ='Comps Data'!H11 -> 125841.25 | M13: ='Comps Data'!I11+'Comps Data'!J11 -> 106573.2 | N13: ='Comps Data'!G11 -> 17691.9 | P13: =J13/L13 -> 13.230563 | Q13: =J13/M13 -> 15.622602 | R13: =G13/N13 -> 7.5280263
B14: ='Comps Data'!B12 -> Union Bank (I) | C14: India | E14: ='Comps Data'!C12 -> 179.26 | F14: ='Comps Data'!D12 -> 763.36 | G14: =F14*E14 -> 136839.91 | H14: ='Comps Data'!E12 -> 1304329.3 | I14: ='Comps Data'!F12 -> 87764.32 | J14: =G14+H14-I14 -> 1353404.9 | L14: ='Comps Data'!H12 -> 108368.24 | M14: ='Comps Data'!I12+'Comps Data'!J12 -> 95238.85 | N14: ='Comps Data'!G12 -> 18026.95 | P14: =J14/L14 -> 12.488944 | Q14: =J14/M14 -> 14.210639 | R14: =G14/N14 -> 7.5908522
B15: ='Comps Data'!B13 -> Indian Bank | C15: India | E15: ='Comps Data'!C13 -> 906.05 | F15: ='Comps Data'!D13 -> 134.7 | G15: =F15*E15 -> 122044.93 | H15: ='Comps Data'!E13 -> 839819 | I15: ='Comps Data'!F13 -> 24768.04 | J15: =G15+H15-I15 -> 937095.89 | L15: ='Comps Data'!H13 -> 65875.22 | M15: ='Comps Data'!I13+'Comps Data'!J13 -> 52231 | N15: ='Comps Data'!G13 -> 11264.39 | P15: =J15/L15 -> 14.225317 | Q15: =J15/M15 -> 17.941374 | R15: =G15/N15 -> 10.83458
B16: ='Comps Data'!B14 -> Bank of India | C16: India | E16: ='Comps Data'!C14 -> 167.57 | F16: ='Comps Data'!D14 -> 455.27 | G16: =F16*E16 -> 76289.594 | H16: ='Comps Data'!E14 -> 996990.99 | I16: ='Comps Data'!F14 -> 50343.93 | J16: =G16+H16-I16 -> 1022936.7 | L16: ='Comps Data'!H14 -> 74518.88 | M16: ='Comps Data'!I14+'Comps Data'!J14 -> 59765.77 | N16: ='Comps Data'!G14 -> 9552.17 | P16: =J16/L16 -> 13.727215 | Q16: =J16/M16 -> 17.115761 | R16: =G16/N16 -> 7.9866244
B17: ='Comps Data'!B15 -> I O B | C17: India | E17: ='Comps Data'!C15 -> 34.52 | F17: ='Comps Data'!D15 -> 1925.66 | G17: =F17*E17 -> 66473.783 | H17: ='Comps Data'!E15 -> 396107.32 | I17: ='Comps Data'!F15 -> 16880.4 | J17: =G17+H17-I17 -> 445700.7 | L17: ='Comps Data'!H15 -> 31040.32 | M17: ='Comps Data'!I15+'Comps Data'!J15 -> 22145.17 | N17: ='Comps Data'!G15 -> 3334.71 | P17: =J17/L17 -> 14.358766 | Q17: =J17/M17 -> 20.126317 | R17: =G17/N17 -> 19.933902
B18: ='Comps Data'!B16 -> Bank of Maha | C18: India | E18: ='Comps Data'!C16 -> 67.04 | F18: ='Comps Data'!D16 -> 769.16 | G18: =F18*E18 -> 51564.486 | H18: ='Comps Data'!E16 -> 351995.89 | I18: ='Comps Data'!F16 -> 36967.7 | J18: =G18+H18-I18 -> 366592.68 | L18: ='Comps Data'!H16 -> 28257.38 | M18: ='Comps Data'!I16+'Comps Data'!J16 -> 19112.57 | N18: ='Comps Data'!G16 -> 5541.78 | P18: =J18/L18 -> 12.973343 | Q18: =J18/M18 -> 19.180711 | R18: =G18/N18 -> 9.3046794
B19: ='Comps Data'!B17 -> UCO Bank | C19: India | E19: ='Comps Data'!C17 -> 29.08 | F19: ='Comps Data'!D17 -> 1253.96 | G19: =F19*E19 -> 36465.157 | H19: ='Comps Data'!E17 -> 335610.79 | I19: ='Comps Data'!F17 -> 9771.52 | J19: =G19+H19-I19 -> 362304.43 | L19: ='Comps Data'!H17 -> 26369.61 | M19: ='Comps Data'!I17+'Comps Data'!J17 -> 19581.26 | N19: ='Comps Data'!G17 -> 2444.99 | P19: =J19/L19 -> 13.739469 | Q19: =J19/M19 -> 18.50261 | R19: =G19/N19 -> 14.914236
B20: ='Comps Data'!B18 -> Central Bank | C20: India | E20: ='Comps Data'!C18 -> 37.96 | F20: ='Comps Data'!D18 -> 905.14 | G20: =F20*E20 -> 34359.114 | H20: ='Comps Data'!E18 -> 484345.89 | I20: ='Comps Data'!F18 -> 21511.09 | J20: =G20+H20-I20 -> 497193.91 | L20: ='Comps Data'!H18 -> 35123.16 | M20: ='Comps Data'!I18+'Comps Data'!J18 -> 25503.86 | N20: ='Comps Data'!G18 -> 3943.21 | P20: =J20/L20 -> 14.155728 | Q20: =J20/M20 -> 19.49485 | R20: =G20/N20 -> 8.7134884
B23: High | P23: =MAX(P11:P20) -> 14.358766 | Q23: =MAX(Q11:Q20) -> 20.126317 | R23: =MAX(R11:R20) -> 19.933902
B24: 75th Percentile | P24: =_xlfn.QUARTILE.EXC(P11:P20,3) -> 14.248808 | Q24: =_xlfn.QUARTILE.EXC(Q11:Q20,3) -> 19.259245 | R24: =_xlfn.QUARTILE.EXC(R11:R20,3) -> 11.854494
B25: Average | P25: =AVERAGE(P11:P20) -> 13.666702 | Q25: =AVERAGE(Q11:Q20) -> 17.603865 | R25: =AVERAGE(R11:R20) -> 10.161972
B26: Median | P26: =MEDIAN(P11:P20) -> 13.733342 | Q26: =MEDIAN(Q11:Q20) -> 17.648039 | R26: =MEDIAN(R11:R20) -> 8.3500564
B27: 25th Percentile | P27: =_xlfn.QUARTILE.EXC(P11:P20,1) -> 13.166258 | Q27: =_xlfn.QUARTILE.EXC(Q11:Q20,1) -> 16.272461 | R27: =_xlfn.QUARTILE.EXC(R11:R20,1) -> 7.5751457
B28: Low | P28: =MIN(P15:P20) -> 12.973343 | Q28: =MIN(Q15:Q20) -> 17.115761 | R28: =MIN(R15:R20) -> 7.9866244
B30: ='Comps Data'!B21 -> SBI | C30: India | E30: ='Comps Data'!C21 -> 1144.1 | F30: ='Comps Data'!D21 -> 923.06 | G30: =F30*E30 -> 1056072.9 | H30: ='Comps Data'!E21 -> 6305862.7 | I30: ='Comps Data'!F21 -> 208893.69 | J30: =G30+H30-I30 -> 7153041.9 | L30: ='Comps Data'!H21 -> 505419.84 | M30: ='Comps Data'!J21+'Comps Data'!I21 -> 411316.34 | N30: ='Comps Data'!G21 -> 80522.63 | P30: =J30/L30 -> 14.152673 | Q30: =J30/M30 -> 17.39061 | R30: =G30/N30 -> 13.115232
B32: Median
B33: Metric | E33: Comps | F33: EV (₹ Cr.) | G33: Net Debt (₹ Cr.) | H33: Equity Value (₹ Cr.) | I33: Shares (Cr) | J33: Share Price | L33: Stock Value
B34: EV/REVENUE | E34: =P26 -> 13.733342 | F34: =E34*L30 -> 6941103.3 | G34: =$H$30-$I$30 -> 6096969 | H34: =F34-G34 -> 844134.28 | I34: =$F$30 -> 923.06 | J34: =H34/I34 -> 914.49557 | L34: =IF(J34>$E$30,"Undervalued","Overvalued") -> Overvalued
B35: EV/EBITDA | E35: =Q26 -> 17.648039 | F35: =E35*M30 -> 7258926.7 | G35: =$H$30-$I$30 -> 6096969 | H35: =F35-G35 -> 1161957.7 | I35: =$F$30 -> 923.06 | J35: =H35/I35 -> 1258.8106 | L35: =IF(J35>$E$30,"Undervalued","Overvalued") -> Undervalued
B36: P/E | E36: =R26 -> 8.3500564 | F36: =H36+G36 -> 6769337.5 | G36: =$H$30-$I$30 -> 6096969 | H36: =E36*N30 -> 672368.5 | I36: =$F$30 -> 923.06 | J36: =H36/I36 -> 728.41256 | L36: =IF(J36>$E$30,"Undervalued","Overvalued") -> Overvalued
B38: Average
B39: Metric | E39: Comps | F39: EV (₹ Cr.) | G39: Net Debt (₹ Cr.) | H39: Equity Value (₹ Cr.) | I39: Shares (Cr) | J39: Share Price | L39: Stock Value
B40: EV/REVENUE | E40: =P25 -> 13.666702 | F40: =E40*L30 -> 6907422.1 | G40: =G34 -> 6096969 | H40: =F40-G40 -> 810453.13 | I40: =$F$30 -> 923.06 | J40: =H40/I40 -> 878.00698 | L40: =IF(J40>$E$30,"Undervalued","Overvalued") -> Overvalued
B41: EV/EBITDA | E41: =Q25 -> 17.603865 | F41: =E41*M30 -> 7240757.2 | G41: =G35 -> 6096969 | H41: =F41-G41 -> 1143788.2 | I41: =$F$30 -> 923.06 | J41: =H41/I41 -> 1239.1266 | L41: =IF(J41>$E$30,"Undervalued","Overvalued") -> Undervalued
B42: P/E | E42: =R25 -> 10.161972 | F42: =H42+G42 -> 6915237.7 | G42: =G36 -> 6096969 | H42: =E42*N30 -> 818268.68 | I42: =$F$30 -> 923.06 | J42: =H42/I42 -> 886.47399 | L42: =IF(J42>$E$30,"Undervalued","Overvalued") -> Overvalued

Sheet DCF Analysis
B1: State Bank of India
B2: BSE: 500112 | NSE: SBIN
C3: 10000
B5: DCF Analysis
B6: All Fingure In INR Cr.
B7: Particulars | D7: 2021 | E7: =D7+1 -> 2022 | F7: =E7+1 -> 2023 | G7: =F7+1 -> 2024 | H7: =G7+1 -> 2025 | I7: =H7+1 -> 2026 | J7: =I7+1 -> 2027 | K7: =J7+1 -> 2028 | L7: =K7+1 -> 2029 | ... R7: =Q7+1 -> 2035
D8: Aduited | E8: Aduited | F8: Aduited | G8: Aduited | H8: Aduited | I8: Estimated | J8: Forecasted | K8: Forecasted | L8: Forecasted | M8: Forecasted | N8: Forecasted | O8: Forecasted | P8: Forecasted | Q8: Forecasted | R8: Forecasted
H9: Entry
B10: Date | H10: =Assumptions!C13 -> 46063 | I10: =DATE(YEAR(Assumptions!$C$14)+I11,MONTH(Assumptions!$C$14),DAY(Assumptions!$C$14)) -> 46112 | J10: =DATE(YEAR(Assumptions!$C$14)+J11,MONTH(Assumptions!$C$14),DAY(Assumptions!$C$14)) -> 46477 | K10: =DATE(YEAR(Assumptions!$C$14)+K11,MONTH(Assumptions!$C$14),DAY(Assumptions!$C$14)) -> 46843 | L10: =DATE(YEAR(Assumptions!$C$14)+L11,MONTH(Assumptions!$C$14),DAY(Assumptions!$C$14)) -> 47208 | M10: =DATE(YEAR(Assumptions!$C$14)+M11,MONTH(Assumptions!$C$14),DAY(Assumptions!$C$14)) -> 47573 | N10: =DATE(YEAR(Assumptions!$C$14)+N11,MONTH(Assumptions!$C$14),DAY(Assumptions!$C$14)) -> 47938 | O10: =DATE(YEAR(Assumptions!$C$14)+O11,MONTH(Assumptions!$C$14),DAY(Assumptions!$C$14)) -> 48304 | P10: =DATE(YEAR(Assumptions!$C$14)+P11,MONTH(Assumptions!$C$14),DAY(Assumptions!$C$14)) -> 48669 | ... R10: =DATE(YEAR(Assumptions!$C$14)+R11,MONTH(Assumptions!$C$14),DAY(Assumptions!$C$14)) -> 49399 | S10: =R10 -> 49399
B11: Time Period | I11: 0 | J11: =I11+1 -> 1 | K11: =J11+1 -> 2 | L11: =K11+1 -> 3 | M11: =L11+1 -> 4 | N11: =M11+1 -> 5 | O11: =N11+1 -> 6 | P11: =O11+1 -> 7 | Q11: =P11+1 -> 8 | R11: =Q11+1 -> 9
B12: Year | D12: 0 | E12: 0 | F12: 0 | G12: 0 | H12: 0 | I12: =YEARFRAC(H10,I10) -> 0.14166667 | J12: =YEARFRAC(I10,J10) -> 1 | K12: =YEARFRAC(J10,K10) -> 1 | L12: =YEARFRAC(K10,L10) -> 1 | M12: =YEARFRAC(L10,M10) -> 1 | N12: =YEARFRAC(M10,N10) -> 1 | O12: =YEARFRAC(N10,O10) -> 1 | P12: =YEARFRAC(O10,P10) -> 1 | ... R12: =YEARFRAC(Q10,R10) -> 1 | S12: =R12 -> 1
B14: EBIT | D14: ='Income Statement'!C22 -> 41048.934 | E14: ='Income Statement'!D22 -> 59809.536 | F14: ='Income Statement'!E22 -> 100344.19 | G14: ='Income Statement'!F22 -> 135863.86 | H14: ='Income Statement'!G22 -> 154493.82 | I14: ='Income Statement'!H22 -> 140947.53 | J14: ='Income Statement'!I22 -> 157083.37 | K14: ='Income Statement'!J22 -> 172903.45 | ... R14: ='Income Statement'!Q22 -> 263979.63
B15: Tax | D15: =D14*-Cost_BuildUp!C22 -> -5978.51 | E15: =E14*-Cost_BuildUp!D22 -> -12156.79 | F15: =F14*-Cost_BuildUp!E22 -> -23821.977 | G15: =G14*-Cost_BuildUp!F22 -> -43193.706 | H15: =H14*-Cost_BuildUp!G22 -> -46854.151 | I15: =I14*-Cost_BuildUp!H22 -> -42284.259 | J15: =J14*-Cost_BuildUp!I22 -> -47125.011 | K15: =K14*-Cost_BuildUp!J22 -> -51871.036 | ... R15: =R14*-Cost_BuildUp!Q22 -> -79193.89
B16: NOPAT | D16: =SUM(D14:D15) -> 35070.424 | E16: =SUM(E14:E15) -> 47652.746 | F16: =SUM(F14:F15) -> 76522.209 | G16: =SUM(G14:G15) -> 92670.158 | H16: =SUM(H14:H15) -> 107639.66 | I16: =SUM(I14:I15) -> 98663.27 | J16: =SUM(J14:J15) -> 109958.36 | K16: =SUM(K14:K15) -> 121032.42 | ... R16: =SUM(R14:R15) -> 184785.74
B17: Add: Depreciation & Amortization | D17: ='Income Statement'!C20 -> 3711.0636 | E17: ='Income Statement'!D20 -> 3691.27 | F17: ='Income Statement'!E20 -> 3695.5986 | G17: ='Income Statement'!F20 -> 3849.1245 | H17: ='Income Statement'!G20 -> 3991.4767 | I17: ='Income Statement'!H20 -> 3446.3444 | J17: ='Income Statement'!I20 -> 3463.5761 | K17: ='Income Statement'!J20 -> 3480.894 | ... R17: ='Income Statement'!Q20 -> 3604.5681
B18: Less: CapEx | D18: =-FAS!C52 -> 0 | E18: =-FAS!D52 -> -3034.5123 | F18: =-FAS!E52 -> -8592.9491 | G18: =-FAS!F52 -> -4149.9208 | H18: =-FAS!G52 -> -5620.9948 | I18: =-FAS!H52 -> -14158.845 | J18: =-FAS!I52 -> -8809.8906 | K18: =-FAS!J52 -> -8853.94 | ... R18: =-FAS!Q52 -> -9168.5152
B19: Change in working capital | E19: ='Working Capital'!D20 -> -38823.918 | F19: ='Working Capital'!E20 -> -288367.82 | G19: ='Working Capital'!F20 -> -274379.23 | H19: ='Working Capital'!G20 -> -293816.19 | I19: ='Working Capital'!H20 -> 243521.13 | J19: ='Working Capital'!I20 -> -109925.12 | K19: ='Working Capital'!J20 -> -107776.9 | L19: ='Working Capital'!K20 -> -104396.55 | ... R19: ='Working Capital'!Q20 -> -71264.7
B20: Unlevered FCFF | D20: =SUM(D16:D19) -> 38781.487 | E20: =SUM(E16:E19) -> 9485.5853 | F20: =SUM(F16:F19) -> -216742.96 | G20: =SUM(G16:G19) -> -182009.87 | H20: =SUM(H16:H19) -> -187806.05 | I20: =SUM(I16:I19) -> 331471.9 | J20: =SUM(J16:J19) -> -5313.0724 | K20: =SUM(K16:K19) -> 7882.4755 | ... R20: =SUM(R16:R19) -> 107957.1 | S20: =F32 -> 3251143.6
B22: Transaction FCFF | D22: =D20*D12 -> 0 | E22: =E20*E12 -> 0 | F22: =F20*F12 -> 0 | G22: =G20*G12 -> 0 | H22: =H20*H12 -> 0 | I22: =I20*I12 -> 46958.519 | J22: =J20*J12 -> -5313.0724 | K22: =K20*K12 -> 7882.4755 | ... S22: =S20*S12 -> 3251143.6
B25: Cost of Equity (Ke) | E25: Discount Rate | F25: =C43 -> 0.1030778 | H25: Sensitivity Analysis
E26: EV/EBITDA Multiple | F26: ='Comparable Valuation'!E35 -> 17.648039
B27: Risk-free Rate | C27: =Assumptions!C15 -> 0.06715
B28: Equity Market Returns | C28: ='Market Return'!F8 -> 0.13497602 | E28: Terminal Value | I28: Discount Rate
B29: Equity Market Premium | C29: =C28-C27 -> 0.067826022 | E29: Perpetual Growth rate | F29: =Assumptions!C20 -> 0.04 | H29: Terminal Growth Rate | I29: =F43 -> 1449.2379 | J29: =K29-0.5% -> 0.088077802 | K29: =L29-1% -> 0.093077802 | L29: 0.1030778 | M29: =L29+2% -> 0.1230778 | N29: =M29+2% -> 0.1430778
B30: Beta | C30: ='Equity Beta'!I9 -> 1.0123305 | E30: EV/EBITDA | F30: =F26*(R14+R17) -> 4722336.4 | I30: =I31-0.5% -> 0.03 | J30: 1699.158 | K30: 1585.9737 | L30: 1392.1522 | M30: 1092.9688 | N30: 868.92427
B31: Cost of Equity | C31: =C27+(C30*C29) -> 0.13581235 | E31: Prep.Growth | F31: =R22*(1+F29)/(F25-F29) -> 1779950.7 | I31: =I32-0.5% -> 0.035 | J31: 1746.871 | K31: 1624.6519 | L31: 1418.5987 | M31: 1106.834 | N31: 876.9804
E32: Average | F32: =AVERAGE(F30:F31) -> 3251143.6 | I32: 0.04 | J32: 1804.508 | K32: 1670.617 | L32: 1449.2379 | M32: 1122.3682 | N32: 885.81809
B33: Cost of Debt (Kd) | I33: =I32+1% -> 0.05 | J33: 1965.1921 | K33: 1794.5582 | L33: 1527.8337 | M33: 1159.8136 | N33: 906.34194
E34: Intrinsic Value | I34: =I33+1% -> 0.06 | J34: 2240.3325 | K34: 1993.4386 | L34: 1642.9197 | M34: 1209.1317 | N34: 931.80667
B35: Pre-tax Cost of Debt | C35: ='Debt Schedules'!G15 -> 0.066719433
B36: Tax Rate | C36: =Assumptions!C18 -> 0.30327525 | E36: Enterprise Value | F36: =XNPV(F25,H22:S22,H10:S10) -> 1608683.7
B37: Cost of Debt | C37: =C35*(1-C36) -> 0.04648508 | E37: Add: Cash | F37: =SUM('Balance Sheet'!G27:G28) -> 357932.94 | I37: Discount Rate
E38: Less: Debt | F38: =-'Debt Schedules'!G12 -> -610857.24 | H38: EV/EBITDA | I38: =F43 -> 1449.2379 | J38: 0.088073584 | K38: 0.093073584 | L38: 0.1030778 | M38: 0.12307358 | N38: 0.14307358
B39: Market Cap. | C39: ='Comparable Valuation'!G30 -> 1056072.9 | E39: Less: NCI | F39: =-'Balance Sheet'!G14 -> -18025.839 | I39: =I40-1 -> 15.648039 | J39: 1670.6049 | K39: 1542.198 | L39: 1330.9822 | M39: 1022.0767 | N39: 800.46326
B40: Total Borrowing | C40: ='Debt Schedules'!G12 -> 610857.24 | E40: Equity Value | F40: =SUM(F36:F39) -> 1337733.5 | I40: =I41-1 -> 16.648039 | J40: 1737.6171 | K40: 1606.4602 | L40: 1390.11 | M40: 1072.2513 | N40: 843.16233
B41: Total | C41: =SUM(C39:C40) -> 1666930.2 | I41: 17.648039 | J41: 1804.6293 | K41: 1670.7224 | L41: 1449.2379 | M41: 1122.4258 | N41: 885.86139
E42: Share Outstanding (cr) | F42: ='Comparable Valuation'!F30 -> 923.06 | I42: =I41+1.5 -> 19.148039 | J42: 1905.1477 | K42: 1767.1157 | L42: 1537.9296 | M42: 1197.6876 | N42: 949.90999
B43: WACC | C43: =(C31*(C39/C41))+(C37*(C40/C41)) -> 0.1030778 | E43: Equity Value/Share | F43: =F40/F42 -> 1449.2379 | I43: =I42+1.5 -> 20.648039 | J43: 2005.666 | K43: 1863.509 | L43: 1626.6214 | M43: 1272.9494 | N43: 1013.9586
E45: Target Price (Up side) | F45: =F43/'Comparable Valuation'!E30-1 -> 0.2667056

Sheet Football Field Analysis
B1: State Bank of India
B2: BSE: 500112 | NSE: SBIN
B5: Football Field Analysis
B7: Football Field Data
E8: Comps Median | F8: Comps Average | G8: DCF (Average) | H8: 52-Week Hi/LO | I8: Market Consenses
B9: High | E9: =MAX('Comparable Valuation'!J34:J36) -> 1258.8106 | F9: =MAX('Comparable Valuation'!J40:J42) -> 1239.1266 | G9: 1607.5265 | H9: 1188 | I9: 1300
B10: High | E10: =E9 -> 1258.8106 | F10: =F9 -> 1239.1266 | G10: =G9 -> 1607.5265 | H10: =H9 -> 1188 | I10: =I9 -> 1300
B11: Low | E11: =MIN('Comparable Valuation'!J34:J36) -> 728.41256 | F11: =MIN('Comparable Valuation'!J40:J42) -> 878.00698 | G11: 1292.861 | H11: 680 | I11: 1018
B12: Low | E12: =E11 -> 728.41256 | F12: =F11 -> 878.00698 | G12: =G11 -> 1292.861 | H12: =H11 -> 680 | I12: =I11 -> 1018
