Workbook

Sheet Assumptions
B7: Scenario | E7: Company Name | F7: Vardhman Holdings Ltd
B8: Base Case | C8: =IF(B8="Best Case",1,IF(B8="Base Case",2,3)) -> 2 | E8: ISIN Code | F8: INE701A01023
E9: Sector Name | F9: Investment Company
B10: Assumptions | E10: Industry | F10: Finance
B11: Transaction Date | C11: 45922 | E11: Exchange Name | F11: BSE: 500439 | NSE: VHL
B12: Fiscal Year End | C12: 46112 | E12: Website | F12: vardhman.in
B13: Annual growth Tapering | C13: =Revenue_BuildUp!C33 -> 0.2 | E13: Company Description | F13: VHL is a Non Deposit Taking Systemically Important Non Banking Finance Corporation which is mainly into investment activities. It primarily earns its income from investments. Company’s strategy is to adopt a systematic approach of investment into different asset classes and to keep the portfolio dynamic as per the changing market conditions. Company’s current portfolio consists of investments into debt, equity and real estate. Interest Income from investments ~43%, Dividend Income from investments ~25%, Net gain on trading portfolio ~8%, Receipt against License agreement ~24%, (Company has no debt, it is debt free).
B14: Risk Free Rate | C14: 0.06481
B15: Addition In CAPEX | C15: 0.005
B16: Addition In Tax rate / 2 years | C16: 0.005
B17: Addition In Dep / 3 years | C17: 0.0015
B18: Tax Rate | C18: =Cost_BuildUp!H19 -> 0.05984114
B19: Investment Growth rate / year | C19: 0.03
B20: Investments in associates Growth Rate / year | C20: 0.04
B21: EV/EBITDA Multiple | C21: ='Comps Valuation'!E37 -> 16.309294
B22: Perpetual Growth Rate | C22: 0.06
B23: Discount Rate | C23: =DCF!C43 -> 0.14212865
B24: Shares Outstanding(Lakhs) | C24: ='Comps Data'!D15 -> 31.9
B25: Current Market Price | C25: ='Comps Data'!C15 -> 3810 | E25: Associate Company | F25: a) Vardhman Textiles Limited (VTXL)- Company holds ~28.48% shares of VTXL. It is engaged in manufacturing of texiles. b) Vardhman Spinning and General Mills Limited (VSGM)- Company holds ~50% shares of VSGM. It deals in trading of Cotton and Fibre. In FY23, VSGM has not traded any goods
B26: Market Cap (Cr.) | C26: =C25*C24 -> 121539
B28: Colour Code
B29: Blue colour | C29: Hardcoded Figures
B30: Black colour | C30: Calculated Figures
B31: Green Colour | C31: Link Data figures
B33: Items | C33: Sheet | E33: Reference | F33: Assumptions
B35: Revenue from operation | C35: Revenue Buildup | D35: B28:Q33 | F35: Revenue has been forecasted using the historic average YoY growth of the last 5 years and tapered down to match the perpetual growth rate. Moreover, a Bull and a Bear Case has been calculated as +/-5% of Base Case respectively
B38: Share of Profit of Associates | C38: Revenue Buildup | D38: B22:Q23 | F38: Share of Profit of Associates: Taken as a multiple of revenue. For forecasted years (2026–2035), assumed at 8x revenue, based on the historical average of 2021–2025. (except 2023)
B41: Other Income | C41: Revenue Buildup | D41: B25:Q26 | F41: Other Income: Taken as a percentage of revenue. For forecasted years (2026–2035), assumed at 14% of revenue, derived from the historical average of 2021–2025.
B43: Investments | C43: Investment | D43: B16:Q21 | F43: Investment forecast is based on the historical average growth rate of Investment. For the forecasted period, we assumes a steady and conservative annual investment growth rate of 3% ( every 3 year). This simplified projection supports long-term financial planning by assuming stable, moderate expansion.
B45: Investments in associates accounted for using the equity method | C45: Investment | D45: B9:Q12 | F45: Investment in associates accounted for using the equity method forecast is based on the historical average growth rate of the investment. For the forecasted period, we assumes a steady and conservative annual investment growth rate of 4% ( every 3 year). This simplified projection supports long-term financial planning by assuming stable, moderate expansion.
B48: Other Expenses | C48: Cost Build_up | D48: B19:Q23 | F48: The first five years show actual historical percentages of revenue. For the forecasted period (2026–2035), other expenses are assumed based on the average percentage of revenue from 2021–2025, stabilizing around 24% and increasing proportionally with revenue growth.
B52: Employee benefits expense, | C52: Cost Build_up | D52: B30:Q34 | F52: From 2026 to 2035, the employee benefits expenses are forecasted using the average percentage of revenue from the historical five years (2021–2025), stabilizing at around 6% and reflecting growth in line with business expansion.
B55: Perpetual Growth Rate | C55: Assumptions | D55: C21 | F55: For calculating the Terminal Value in the DCF model, a perpetual growth rate of 6% has been assumed. This is aligned with India’s long-term GDP growth outlook, which is forecasted at approximately 6.4%
B57: Effective Tax Rate | C57: Cost Build_up | D57: B39:Q39 | F57: Taxes for the historical years are based on actual PBT percentages. For the forecasted years (2026–2035), taxes for projected year taken as the latest year of the tax ( which is 2025 tax rate ), and aslo adding the growing tax rate of 0.5 % every 2 year.
B59: Other Receivables , Other Financial assets | C59: Balance_Sheet_Forecast | D59: B11:Q37 | F59: The balances for Other Receivables and Other Financial Assets are forecasted based on their historical relationship to revenue. The specific percentage used for each forecast year is calculated as the average of their historical percentages of revenue.
B61: Current Tax assets (Net), , Other non-financial assets | C61: Balance_Sheet_Forecast | D61: B11:Q37 | F61: The balances for Current Tax Assets (Net), and Other Non-Financial Assets are forecasted based on their historical relationship to revenue. The specific amount for each forecast year is calculated as the average of their historical percentages of revenue.
B63: Other financial liabilities | C63: Balance_Sheet_Forecast | D63: B11:Q37 | F63: The balance for Other Financial Liabilities is forecasted based on its historical relationship to total revenue. The specific amount for each forecast year is calculated as the average of its historical percentage of revenue.
... B84: Net Working Capital | C84: Net Working Capital | D84: B43:Q43 | F84: Net Working Capital Consist Change of the Current portion of Current Assets and Current portion of Current Liabilities , The Current Assets & Current Liabilities are Taken from the annual Report based on their Maturity Paatern ( With in 12 Months) and some portion of Investment of Current Assets Taken as % of the total Investment and for forecasted year taken as the average of that.

Sheet Historical P&L
B6: (All amounts in INR Lakhs, unless otherwise stated)
B7: Particulars | C7: 2021 | D7: =C7+1 -> 2022 | E7: =D7+1 -> 2023 | F7: =E7+1 -> 2024 | G7: =F7+1 -> 2025
B9: Revenue from operations
B10: Interest Income | C10: 779.91 | D10: 393.67 | E10: 335.7 | F10: 102.87 | G10: 119.48
B11: Dividend Income | C11: 6.38 | D11: 263.68 | E11: 192.98 | F11: 229.05 | G11: 225.33
B12: Net gain on fair value changes | C12: 1192.22 | D12: 2651.6 | E12: 59.77 | F12: 1158.21 | G12: 1932.81
B13: Total Revenue from operations | C13: =SUM(C10:C12) -> 1978.51 | D13: =SUM(D10:D12) -> 3308.95 | E13: =SUM(E10:E12) -> 588.45 | F13: =SUM(F10:F12) -> 1490.13 | G13: =SUM(G10:G12) -> 2277.62
B14: Other income | C14: 124.69 | D14: 185.46 | E14: 188.17 | F14: 247.22 | G14: 185.66
B15: Total Income | C15: =SUM(C13:C14) -> 2103.2 | D15: =SUM(D13:D14) -> 3494.41 | E15: =SUM(E13:E14) -> 776.62 | F15: =SUM(F13:F14) -> 1737.35 | G15: =SUM(G13:G14) -> 2463.28
B16: Expenses
B17: Employee benefits expenses | C17: 56.11 | D17: 81.83 | E17: 124.52 | F17: 48.36 | G17: 62.01
B18: Depreciation and amortization expense | C18: 0.88 | D18: 0.77 | E18: 0.72 | F18: 0.72 | G18: 0.72
B19: Other expenses | C19: 170.92 | D19: 225.61 | E19: 312.42 | F19: 385.57 | G19: 556.24
B20: Total Expenses | C20: =SUM(C17:C19) -> 227.91 | D20: =SUM(D17:D19) -> 308.21 | E20: =SUM(E17:E19) -> 437.66 | F20: =SUM(F17:F19) -> 434.65 | G20: =SUM(G17:G19) -> 618.97
B22: Profit before Share of profit of Associates, Exeptional Items and tax | C22: =C15-C20 -> 1875.29 | D22: =D15-D20 -> 3186.2 | E22: =E15-E20 -> 338.96 | F22: =F15-F20 -> 1302.7 | G22: =G15-G20 -> 1844.31
B23: Share of Profit of Associates | C23: 11446.14 | D23: 42760.92 | E23: 22153.14 | F23: 18121.32 | G23: 25453.08
B24: Profit before exceptional Items and Tax | C24: =SUM(C22:C23) -> 13321.43 | D24: =SUM(D22:D23) -> 45947.12 | E24: =SUM(E22:E23) -> 22492.1 | F24: =SUM(F22:F23) -> 19424.02 | G24: =SUM(G22:G23) -> 27297.39
B25: Exeptional Items
B26: Profit before tax | C26: =SUM(C24:C25) -> 13321.43 | D26: =SUM(D24:D25) -> 45947.12 | E26: =SUM(E24:E25) -> 22492.1 | F26: =SUM(F24:F25) -> 19424.02 | G26: =SUM(G24:G25) -> 27297.39
B28: Tax expense :
B29: Current Tax | C29: 365.42 | D29: 2725.35 | E29: 347.67 | F29: 761.19 | G29: 1014.2
B30: Deferred tax | C30: 4.86 | D30: 313.95 | E30: -698.83 | F30: 174.77 | G30: 482.82
B31: Total Tax | C31: =SUM(C29:C30) -> 370.28 | D31: =SUM(D29:D30) -> 3039.3 | E31: =SUM(E29:E30) -> -351.16 | F31: =SUM(F29:F30) -> 935.96 | G31: =SUM(G29:G30) -> 1497.02
B33: Profit for the year | C33: =C26-C31 -> 12951.15 | D33: =D26-D31 -> 42907.82 | E33: =E26-E31 -> 22843.26 | F33: =F26-F31 -> 18488.06 | G33: =G26-G31 -> 25800.37

Sheet Historical B_Sheet
B6: (All amounts in INR Lakhs, unless otherwise stated)
B7: Particulars | C7: 2021 | D7: =C7+1 -> 2022 | E7: =D7+1 -> 2023 | F7: =E7+1 -> 2024 | G7: =F7+1 -> 2025
B9: Assets
B10: Financial Assets
B11: Cash and bank balances | C11: 7638.83 | D11: 120.99 | E11: 294.74 | F11: 284.7 | G11: 49.18
B12: Bank Balances | C12: 9.79 | D12: 152.78 | E12: 106.02 | F12: 98.22 | G12: 102.77
B13: Receivables
B14: Trade Receivables
B15: Other Receivables | C15: 577.05 | D15: 230.41 | E15: 262.69 | F15: 252.58 | G15: 199.46
B16: Investments in associates accounted for using the equity method | C16: 0 | D16: 229117.91 | E16: 262650.13 | F16: 281033.31 | G16: 304669.13
B17: Investments | C17: 216675.61 | D17: 44668.35 | E17: 43858.98 | F17: 45919.59 | G17: 48110.18
B18: Other Financial assets | C18: 1572.52 | D18: 609.68 | E18: 445.01 | F18: 227.74 | G18: 41.66
B20: Total Financial Assets | C20: =SUM(C11:C18) -> 226473.8 | D20: =SUM(D11:D18) -> 274900.12 | E20: =SUM(E11:E18) -> 307617.57 | F20: =SUM(F11:F18) -> 327816.14 | G20: =SUM(G11:G18) -> 353172.38
B22: Non Financial Assets
B23: Current Tax assets (Net) | C23: 0 | D23: 105.2 | E23: 306.77 | F23: 533.01 | G23: 373.39
B24: Deferred Tax Asset (Net) | C24: 3913.66 | D24: 2415.08 | E24: 1813.25 | F24: 1098.4 | G24: 223.85
B25: Property, Plant and Equipment | C25: 321.67 | D25: 320.9 | E25: 320.18 | F25: 319.46 | G25: 318.74
B26: Other non-financial assets | C26: 24.73 | D26: 9.95 | E26: 11.88 | F26: 10.09 | G26: 10.94
B28: Total Non Financial Assets | C28: =SUM(C23:C26) -> 4260.06 | D28: =SUM(D23:D26) -> 2851.13 | E28: =SUM(E23:E26) -> 2452.08 | F28: =SUM(F23:F26) -> 1960.96 | G28: =SUM(G23:G26) -> 926.92
B30: TOTAL ASSETS | C30: =C28+C20 -> 230733.86 | D30: =D28+D20 -> 277751.25 | E30: =E28+E20 -> 310069.65 | F30: =F28+F20 -> 329777.1 | G30: =G28+G20 -> 354099.3
B32: LIABILITIES AND EQUITY
B33: Liabilities
B34: Financial Liabilities
B35: Payables | C35: 0 | D35: 0 | E35: 0 | F35: 0 | G35: 0
B36: Trade Payables | C36: 0 | D36: 0 | E36: 0 | F36: 0 | G36: 0
B37: total outstanding dues of micro enterprises and small enterprises | C37: 0 | D37: 0 | E37: 0 | F37: 0 | G37: 0
B38: total outstanding dues of creditors other than micro enterprises and small enterprises | C38: 0 | D38: 0 | E38: 0 | F38: 0 | G38: 0
B39: Other financial liabilities | C39: 81.27 | D39: 18.35 | E39: 13.46 | F39: 16.6 | G39: 7
B41: Total Financial Liabilities | C41: =SUM(C35:C39) -> 81.27 | D41: =SUM(D35:D39) -> 18.35 | E41: =SUM(E35:E39) -> 13.46 | F41: =SUM(F35:F39) -> 16.6 | G41: =SUM(G35:G39) -> 7
B43: Non Financial Liabilities
B44: Current tax liabilities (Net) | C44: 43.3 | D44: 0 | E44: 0 | F44: 0 | G44: 0
B45: Provisions | C45: 2.9 | D45: 1.55 | E45: 5.52 | F45: 3.11 | G45: 6.75
B46: Other non-financial liabilities | C46: 27.11 | D46: 47.65 | E46: 90.95 | F46: 40.09 | G46: 39.1
B48: Total Non Financial Liabilities | C48: =SUM(C44:C46) -> 73.31 | D48: =SUM(D44:D46) -> 49.2 | E48: =SUM(E44:E46) -> 96.47 | F48: =SUM(F44:F46) -> 43.2 | G48: =SUM(G44:G46) -> 45.85
B50: Equity
B51: Equity Share Capital | C51: 319.24 | D51: 319.24 | E51: 319.24 | F51: 319.24 | G51: 319.24
B52: Other Equity | C52: 230260.04 | D52: 277364.46 | E52: 309640.48 | F52: 329398.06 | G52: 353727.21
B54: Total Equity | C54: =SUM(C51:C53) -> 230579.28 | D54: =SUM(D51:D53) -> 277683.7 | E54: =SUM(E51:E53) -> 309959.72 | F54: =SUM(F51:F53) -> 329717.3 | G54: =SUM(G51:G53) -> 354046.45
B56: TOTAL LIABILITIES AND EQUITY | C56: =C54+C48+C41 -> 230733.86 | D56: =D54+D48+D41 -> 277751.25 | E56: =E54+E48+E41 -> 310069.65 | F56: =F54+F48+F41 -> 329777.1 | G56: =G54+G48+G41 -> 354099.3
B58: CHECK | C58: =C56=C30 -> TRUE | D58: =D56=D30 -> TRUE | E58: =E56=E30 -> TRUE | F58: =F56=F30 -> TRUE | G58: =G56=G30 -> TRUE

Sheet Revenue_BuildUp
B6: (All amounts in INR Lakhs, unless otherwise stated)
B7: Particulars | C7: 2021 | D7: =C7+1 -> 2022 | E7: =D7+1 -> 2023 | F7: =E7+1 -> 2024 | G7: =F7+1 -> 2025 | H7: =G7+1 -> 2026 | I7: =H7+1 -> 2027 | J7: =I7+1 -> 2028 | K7: =J7+1 -> 2029 | ... Q7: =P7+1 -> 2035
B9: Total Operational Revenue | C9: ='Historical P&L'!C13 -> 1978.51 | D9: ='Historical P&L'!D13 -> 3308.95 | E9: ='Historical P&L'!E13 -> 588.45 | F9: ='Historical P&L'!F13 -> 1490.13 | G9: ='Historical P&L'!G13 -> 2277.62 | H9: =G9*(1+H10) -> 3365.7807 | I9: =H9*(1+I10) -> 4652.2148 | J9: =I9*(1+J10) -> 6074.7122 | K9: =J9*(1+K10) -> 7560.6733 | L9: =K9*(1+L10) -> 9040.2319 | M9: =L9*(1+M10) -> 10455.508 | N9: =M9*(1+N10) -> 11764.982 | O9: =N9*(1+O10) -> 12943.763 | ... Q9: =P9*(1+Q10) -> 14877.81
B10: Y-o-Y Growth | D10: =D9/C9-1 -> 0.67244543 | E10: =E9/D9-1 -> -0.82216413 | F10: =F9/E9-1 -> 1.5322967 | G10: =G9/F9-1 -> 0.52847067 | H10: =CHOOSE(Assumptions!$C$8,Revenue_BuildUp!$H$30:$Q$30,Revenue_BuildUp!$H$31:$Q$31,Revenue_BuildUp!$H$32:$Q$32) -> 0.47776217 | I10: =CHOOSE(Assumptions!$C$8,Revenue_BuildUp!$H$30:$Q$30,Revenue_BuildUp!$H$31:$Q$31,Revenue_BuildUp!$H$32:$Q$32) -> 0.38220974 | J10: =CHOOSE(Assumptions!$C$8,Revenue_BuildUp!$H$30:$Q$30,Revenue_BuildUp!$H$31:$Q$31,Revenue_BuildUp!$H$32:$Q$32) -> 0.30576779 | K10: =CHOOSE(Assumptions!$C$8,Revenue_BuildUp!$H$30:$Q$30,Revenue_BuildUp!$H$31:$Q$31,Revenue_BuildUp!$H$32:$Q$32) -> 0.24461423 | L10: =CHOOSE(Assumptions!$C$8,Revenue_BuildUp!$H$30:$Q$30,Revenue_BuildUp!$H$31:$Q$31,Revenue_BuildUp!$H$32:$Q$32) -> 0.19569138 | M10: =CHOOSE(Assumptions!$C$8,Revenue_BuildUp!$H$30:$Q$30,Revenue_BuildUp!$H$31:$Q$31,Revenue_BuildUp!$H$32:$Q$32) -> 0.15655311 | N10: =CHOOSE(Assumptions!$C$8,Revenue_BuildUp!$H$30:$Q$30,Revenue_BuildUp!$H$31:$Q$31,Revenue_BuildUp!$H$32:$Q$32) -> 0.12524249 | O10: =CHOOSE(Assumptions!$C$8,Revenue_BuildUp!$H$30:$Q$30,Revenue_BuildUp!$H$31:$Q$31,Revenue_BuildUp!$H$32:$Q$32) -> 0.10019399 | ... Q10: =CHOOSE(Assumptions!$C$8,Revenue_BuildUp!$H$30:$Q$30,Revenue_BuildUp!$H$31:$Q$31,Revenue_BuildUp!$H$32:$Q$32) -> 0.064124153
B12: Revenue Break
B13: Interest Income | C13: ='Historical P&L'!C10 -> 779.91 | D13: ='Historical P&L'!D10 -> 393.67 | E13: ='Historical P&L'!E10 -> 335.7 | F13: ='Historical P&L'!F10 -> 102.87 | G13: ='Historical P&L'!G10 -> 119.48 | H13: =H14*H9 -> 811.24479 | I13: =I14*I9 -> 1121.3104 | J13: =J14*J9 -> 1464.1711 | K13: =K14*K9 -> 1822.3281 | L13: =L14*L9 -> 2178.942 | M13: =M14*M9 -> 2520.0622 | N13: =N14*N9 -> 2835.681 | O13: =O14*O9 -> 3119.7992 | ... Q13: =Q14*Q9 -> 3585.9572
B14: % of Revenue | C14: =C13/C$9 -> 0.39419058 | D14: =D13/D$9 -> 0.11897127 | E14: =E13/E$9 -> 0.57048177 | F14: =F13/F$9 -> 0.069034245 | G14: =G13/G$9 -> 0.052458268 | H14: =AVERAGE(C14:G14) -> 0.24102723 | I14: =H14 -> 0.24102723 | J14: =I14 -> 0.24102723 | K14: =J14 -> 0.24102723 | L14: =K14 -> 0.24102723 | M14: =L14 -> 0.24102723 | N14: =M14 -> 0.24102723 | O14: =N14 -> 0.24102723 | P14: =O14 -> 0.24102723 | Q14: =P14 -> 0.24102723
B16: Dividend Income | C16: ='Historical P&L'!C11 -> 6.38 | D16: ='Historical P&L'!D11 -> 263.68 | E16: ='Historical P&L'!E11 -> 192.98 | F16: ='Historical P&L'!F11 -> 229.05 | G16: ='Historical P&L'!G11 -> 225.33 | H16: =H17*H9 -> 446.6401 | I16: =I17*I9 -> 617.3503 | J16: =J17*J9 -> 806.11614 | K16: =K17*K9 -> 1003.3036 | L16: =L17*L9 -> 1199.6415 | M16: =M17*M9 -> 1387.4491 | N16: =N17*N9 -> 1561.2167 | O16: =O17*O9 -> 1717.6412 | ... Q16: =Q17*Q9 -> 1974.2898
B17: % of Revenue | C17: =C16/C$9 -> 0.0032246489 | D17: =D16/D$9 -> 0.07968691 | E17: =E16/E$9 -> 0.3279463 | F17: =F16/F$9 -> 0.15371142 | G17: =G16/G$9 -> 0.098932219 | H17: =AVERAGE(C17:G17) -> 0.1327003 | I17: =H17 -> 0.1327003 | J17: =I17 -> 0.1327003 | K17: =J17 -> 0.1327003 | L17: =K17 -> 0.1327003 | M17: =L17 -> 0.1327003 | N17: =M17 -> 0.1327003 | O17: =N17 -> 0.1327003 | P17: =O17 -> 0.1327003 | Q17: =P17 -> 0.1327003
B19: Net gain on fair value changes | C19: ='Historical P&L'!C12 -> 1192.22 | D19: ='Historical P&L'!D12 -> 2651.6 | E19: ='Historical P&L'!E12 -> 59.77 | F19: ='Historical P&L'!F12 -> 1158.21 | G19: ='Historical P&L'!G12 -> 1932.81 | H19: =H20*H9 -> 2107.8958 | I19: =I20*I9 -> 2913.5541 | J19: =J20*J9 -> 3804.4251 | K19: =K20*K9 -> 4735.0416 | L19: =L20*L9 -> 5661.6484 | M19: =M20*M9 -> 6547.9971 | N19: =N20*N9 -> 7368.0845 | O19: =O20*O9 -> 8106.3223 | ... Q19: =Q20*Q9 -> 9317.5627
B20: % of Revenue | C20: =C19/C$9 -> 0.60258477 | D20: =D19/D$9 -> 0.80134182 | E20: =E19/E$9 -> 0.10157193 | F20: =F19/F$9 -> 0.77725433 | G20: =G19/G$9 -> 0.84860951 | H20: =AVERAGE(C20:G20) -> 0.62627247 | I20: =H20 -> 0.62627247 | J20: =I20 -> 0.62627247 | K20: =J20 -> 0.62627247 | L20: =K20 -> 0.62627247 | M20: =L20 -> 0.62627247 | N20: =M20 -> 0.62627247 | O20: =N20 -> 0.62627247 | P20: =O20 -> 0.62627247 | Q20: =P20 -> 0.62627247
B22: Share of Profit of Associates | C22: ='Historical P&L'!C23 -> 11446.14 | D22: ='Historical P&L'!D23 -> 42760.92 | E22: ='Historical P&L'!E23 -> 22153.14 | F22: ='Historical P&L'!F23 -> 18121.32 | G22: ='Historical P&L'!G23 -> 25453.08 | H22: =H23*H9 -> 26806.142 | I22: =I23*I9 -> 37051.711 | J22: =J23*J9 -> 48380.93 | K22: =K23*K9 -> 60215.595 | L22: =L23*L9 -> 71999.268 | M22: =M23*M9 -> 83270.977 | N22: =N23*N9 -> 93700.041 | O22: =O23*O9 -> 103088.22 | ... Q22: =Q23*Q9 -> 118491.58
B23: (x) of Revenue | C23: =C22/C9 -> 5.7852323 | D23: =D22/C22-1 -> 2.7358376 | E23: =E22/E9 -> 37.646597 | F23: =F22/F9 -> 12.160899 | G23: =G22/G9 -> 11.175297 | H23: =AVERAGE(C23:D23,F23:G23) -> 7.9643164 | I23: =H23 -> 7.9643164 | J23: =I23 -> 7.9643164 | K23: =J23 -> 7.9643164 | L23: =K23 -> 7.9643164 | M23: =L23 -> 7.9643164 | N23: =M23 -> 7.9643164 | O23: =N23 -> 7.9643164 | P23: =O23 -> 7.9643164 | Q23: =P23 -> 7.9643164
B25: Other Income | C25: ='Historical P&L'!C14 -> 124.69 | D25: ='Historical P&L'!D14 -> 185.46 | E25: ='Historical P&L'!E14 -> 188.17 | F25: ='Historical P&L'!F14 -> 247.22 | G25: ='Historical P&L'!G14 -> 185.66 | H25: =H26*H9 -> 461.96171 | I25: =I26*I9 -> 638.52797 | J25: =J26*J9 -> 833.76926 | K25: =K26*K9 -> 1037.7211 | L25: =L26*L9 -> 1240.7942 | M25: =M26*M9 -> 1435.0443 | N25: =N26*N9 -> 1614.7729 | O25: =O26*O9 -> 1776.5634 | ... Q25: =Q26*Q9 -> 2042.0161
B26: % of Revenue | C26: =C25/C9 -> 0.063022173 | D26: =D25/D9 -> 0.056047991 | E26: =E25/E9 -> 0.31977228 | F26: =F25/F9 -> 0.16590499 | G26: =G25/G9 -> 0.081514915 | H26: =AVERAGE(C26:G26) -> 0.13725247 | I26: =H26 -> 0.13725247 | J26: =I26 -> 0.13725247 | K26: =J26 -> 0.13725247 | L26: =K26 -> 0.13725247 | M26: =L26 -> 0.13725247 | N26: =M26 -> 0.13725247 | O26: =N26 -> 0.13725247 | P26: =O26 -> 0.13725247 | Q26: =P26 -> 0.13725247
B28: Scenario
B30: Best Case | H30: =H31+5% -> 0.52776217 | I30: =H30*(1-$C$33) -> 0.42220974 | J30: =I30*(1-$C$33) -> 0.33776779 | K30: =J30*(1-$C$33) -> 0.27021423 | L30: =K30*(1-$C$33) -> 0.21617138 | M30: =L30*(1-$C$33) -> 0.17293711 | N30: =M30*(1-$C$33) -> 0.13834969 | O30: =N30*(1-$C$33) -> 0.11067975 | P30: =O30*(1-$C$33) -> 0.088543799 | Q30: =P30*(1-$C$33) -> 0.070835039
B31: Base Case | H31: =AVERAGE(C10:G10) -> 0.47776217 | I31: =H31*(1-$C$33) -> 0.38220974 | J31: =I31*(1-$C$33) -> 0.30576779 | K31: =J31*(1-$C$33) -> 0.24461423 | L31: =K31*(1-$C$33) -> 0.19569138 | M31: =L31*(1-$C$33) -> 0.15655311 | N31: =M31*(1-$C$33) -> 0.12524249 | O31: =N31*(1-$C$33) -> 0.10019399 | P31: =O31*(1-$C$33) -> 0.080155191 | Q31: =P31*(1-$C$33) -> 0.064124153
B32: Worst Case | H32: =H31-5% -> 0.42776217 | I32: =H32*(1-$C$33) -> 0.34220974 | J32: =I32*(1-$C$33) -> 0.27376779 | K32: =J32*(1-$C$33) -> 0.21901423 | L32: =K32*(1-$C$33) -> 0.17521138 | M32: =L32*(1-$C$33) -> 0.14016911 | N32: =M32*(1-$C$33) -> 0.11213529 | O32: =N32*(1-$C$33) -> 0.089708229 | P32: =O32*(1-$C$33) -> 0.071766583 | Q32: =P32*(1-$C$33) -> 0.057413266
B33: Annual Growth Tapering | C33: 0.2

Sheet Cost_BuildUp
B6: (All amounts in INR Lakhs, unless otherwise stated)
B7: Particulars | C7: 2021 | D7: =C7+1 -> 2022 | E7: =D7+1 -> 2023 | F7: =E7+1 -> 2024 | G7: =F7+1 -> 2025 | H7: =G7+1 -> 2026 | I7: =H7+1 -> 2027 | J7: =I7+1 -> 2028 | K7: =J7+1 -> 2029 | ... Q7: =P7+1 -> 2035
B9: Revenue | C9: =Revenue_BuildUp!C9 -> 1978.51 | D9: =Revenue_BuildUp!D9 -> 3308.95 | E9: =Revenue_BuildUp!E9 -> 588.45 | F9: =Revenue_BuildUp!F9 -> 1490.13 | G9: =Revenue_BuildUp!G9 -> 2277.62 | H9: =Revenue_BuildUp!H9 -> 3365.7807 | I9: =Revenue_BuildUp!I9 -> 4652.2148 | J9: =Revenue_BuildUp!J9 -> 6074.7122 | ... Q9: =Revenue_BuildUp!Q9 -> 14877.81
B11: Employee benefits expenses | C11: ='Historical P&L'!C17 -> 56.11 | D11: ='Historical P&L'!D17 -> 81.83 | E11: ='Historical P&L'!E17 -> 124.52 | F11: ='Historical P&L'!F17 -> 48.36 | G11: ='Historical P&L'!G17 -> 62.01 | H11: =H12*H9 -> 218.35551 | I11: =I12*I9 -> 301.81311 | J11: =J12*J9 -> 394.09783 | K11: =K12*K9 -> 490.49977 | L11: =L12*L9 -> 586.48635 | M11: =M12*M9 -> 678.30261 | N11: =N12*N9 -> 763.25492 | O11: =O12*O9 -> 839.72847 | ... Q11: =Q12*Q9 -> 965.20005
B12: % of Revenue | C12: =C11/C9 -> 0.028359725 | D12: =D11/D9 -> 0.024729899 | E12: =E11/E9 -> 0.21160676 | F12: =F11/F9 -> 0.032453544 | G12: =G11/G9 -> 0.027225788 | H12: =AVERAGE(C12:G12) -> 0.064875144 | I12: =H12 -> 0.064875144 | J12: =I12 -> 0.064875144 | K12: =J12 -> 0.064875144 | L12: =K12 -> 0.064875144 | M12: =L12 -> 0.064875144 | N12: =M12 -> 0.064875144 | O12: =N12 -> 0.064875144 | P12: =O12 -> 0.064875144 | Q12: =P12 -> 0.064875144
B14: Other expenses | C14: ='Historical P&L'!C19 -> 170.92 | D14: ='Historical P&L'!D19 -> 225.61 | E14: ='Historical P&L'!E19 -> 312.42 | F14: ='Historical P&L'!F19 -> 385.57 | G14: ='Historical P&L'!G19 -> 556.24 | H14: =H15*H9 -> 800.01866 | I14: =I15*I9 -> 1105.7936 | J14: =J15*J9 -> 1443.9096 | K14: =K15*K9 -> 1797.1105 | L14: =L15*L9 -> 2148.7895 | M14: =M15*M9 -> 2485.1892 | N14: =N15*N9 -> 2796.4405 | O14: =O15*O9 -> 3076.627 | ... Q14: =Q15*Q9 -> 3536.3342
B15: % of Revenue | C15: =C14/C9 -> 0.086388242 | D15: =D14/D9 -> 0.068181749 | E15: =E14/E9 -> 0.53092021 | F15: =F14/F9 -> 0.25874924 | G15: =G14/G9 -> 0.24421984 | H15: =AVERAGE(C15:G15) -> 0.23769186 | I15: =H15 -> 0.23769186 | J15: =I15 -> 0.23769186 | K15: =J15 -> 0.23769186 | L15: =K15 -> 0.23769186 | M15: =L15 -> 0.23769186 | N15: =M15 -> 0.23769186 | O15: =N15 -> 0.23769186 | P15: =O15 -> 0.23769186 | Q15: =P15 -> 0.23769186
B18: Taxes | C18: =SUM('Historical P&L'!C29:C30) -> 370.28 | D18: =SUM('Historical P&L'!D29:D30) -> 3039.3 | E18: =SUM('Historical P&L'!E29:E30) -> -351.16 | F18: =SUM('Historical P&L'!F29:F30) -> 935.96 | G18: =SUM('Historical P&L'!G29:G30) -> 1497.02 | H18: =H19*'Income Statement'!H30 -> 1772.1537 | I18: =I19*'Income Statement'!I30 -> 2449.516 | J18: =J19*'Income Statement'!J30 -> 3465.7724 | K18: =K19*'Income Statement'!K30 -> 4313.5383 | L18: =L19*'Income Statement'!L30 -> 5555.3991 | M18: =M19*'Income Statement'!M30 -> 6425.1328 | N18: =N19*'Income Statement'!N30 -> 7747.4049 | O18: =O19*'Income Statement'!O30 -> 8523.6651 | ... Q18: =Q19*'Income Statement'!Q30 -> 10451.793
B19: % of PBT | C19: =C18/'Income Statement'!C30 -> 0.027795815 | D19: =D18/'Income Statement'!D30 -> 0.06614778 | E19: =E18/'Income Statement'!E30 -> -0.015612593 | F19: =F18/'Income Statement'!F30 -> 0.0481857 | G19: =G18/'Income Statement'!G30 -> 0.05484114 | H19: =G19+Assumptions!C16 -> 0.05984114 | I19: =H19 -> 0.05984114 | J19: =I19+Assumptions!$C$16 -> 0.06484114 | K19: =J19 -> 0.06484114 | L19: =K19+Assumptions!$C$16 -> 0.06984114 | M19: =L19 -> 0.06984114 | N19: =M19+Assumptions!$C$16 -> 0.07484114 | O19: =N19 -> 0.07484114 | P19: =O19+Assumptions!$C$16 -> 0.07984114 | Q19: =P19 -> 0.07984114

Sheet FSA
B6: (All amounts in INR Lakhs, unless otherwise stated)
B7: Particulars | C7: 2021 | D7: =C7+1 -> 2022 | E7: =D7+1 -> 2023 | F7: =E7+1 -> 2024 | G7: =F7+1 -> 2025 | H7: =G7+1 -> 2026 | I7: =H7+1 -> 2027 | J7: =I7+1 -> 2028 | K7: =J7+1 -> 2029 | ... Q7: =P7+1 -> 2035
B9: Deperciation schedules
B10: PPE Opening | D10: =C13 -> 321.67 | E10: =D13 -> 320.9 | F10: =E13 -> 320.18 | G10: =F13 -> 319.46 | H10: =G13 -> 318.74 | I10: =H13 -> 317.53357 | J10: =I13 -> 316.33171 | K10: =J13 -> 315.13439 | ... Q10: =P13 -> 303.89365
B11: Plus -Capex | D11: =D13-D10+D12 -> -3.8635761e-14 | E11: =E13-E10+E12 -> 2.9531932e-14 | F11: =F13-F10+F12 -> -2.7311486e-14 | G11: =G13-G10+G12 -> 2.9531932e-14 | H11: =AVERAGE(D11:G11)*(1+Assumptions!$C$15) -> -1.7294499e-15 | I11: =AVERAGE(E11:H11)*(1+Assumptions!$C$15) -> 7.5432608e-15 | J11: =AVERAGE(F11:I11)*(1+Assumptions!$C$15) -> 2.0186071e-15 | K11: =AVERAGE(G11:J11)*(1+Assumptions!$C$15) -> 9.387793e-15 | L11: =AVERAGE(H11:K11)*(1+Assumptions!$C$15) -> 4.326578e-15 | M11: =AVERAGE(I11:L11)*(1+Assumptions!$C$15) -> 5.848155e-15 | N11: =AVERAGE(J11:M11)*(1+Assumptions!$C$15) -> 5.4222597e-15 | O11: =AVERAGE(K11:N11)*(1+Assumptions!$C$15) -> 6.2774274e-15 | ... Q11: =AVERAGE(M11:P11)*(1+Assumptions!$C$15) -> 5.7897523e-15
B12: Less-Dep | C12: ='Historical P&L'!C18 -> 0.88 | D12: ='Historical P&L'!D18 -> 0.77 | E12: ='Historical P&L'!E18 -> 0.72 | F12: ='Historical P&L'!F18 -> 0.72 | G12: ='Historical P&L'!G18 -> 0.72 | H12: =H10*H15 -> 1.2064298 | I12: =I10*I15 -> 1.2018634 | J12: =J10*J15 -> 1.1973144 | K12: =K10*K15 -> 1.6654841 | L12: =L10*L15 -> 1.6566821 | M12: =M10*M15 -> 1.6479265 | N12: =N10*N15 -> 2.1044637 | O12: =O10*O15 -> 2.0901849 | ... Q12: =Q10*Q15 -> 2.5177578
B13: PPE Closing | C13: ='Historical B_Sheet'!C25 -> 321.67 | D13: ='Historical B_Sheet'!D25 -> 320.9 | E13: ='Historical B_Sheet'!E25 -> 320.18 | F13: ='Historical B_Sheet'!F25 -> 319.46 | G13: ='Historical B_Sheet'!G25 -> 318.74 | H13: =H10+H11-H12 -> 317.53357 | I13: =I10+I11-I12 -> 316.33171 | J13: =J10+J11-J12 -> 315.13439 | K13: =K10+K11-K12 -> 313.46891 | L13: =L10+L11-L12 -> 311.81223 | M13: =M10+M11-M12 -> 310.1643 | N13: =N10+N11-N12 -> 308.05984 | O13: =O10+O11-O12 -> 305.96965 | ... Q13: =Q10+Q11-Q12 -> 301.37589
B15: Deperciation & Amotisartion Exp. (%of Opening PPE) | D15: =D12/D10 -> 0.0023937576 | E15: =E12/E10 -> 0.0022436896 | F15: =F12/F10 -> 0.0022487351 | G15: =G12/G10 -> 0.0022538033 | H15: =AVERAGE(D15:G15)+Assumptions!$C$17 -> 0.0037849964 | I15: =H15 -> 0.0037849964 | J15: =I15 -> 0.0037849964 | K15: =J15+Assumptions!C17 -> 0.0052849964 | L15: =K15 -> 0.0052849964 | M15: =L15 -> 0.0052849964 | N15: =M15+Assumptions!C17 -> 0.0067849964 | O15: =N15 -> 0.0067849964 | P15: =O15 -> 0.0067849964 | Q15: =P15+Assumptions!C17 -> 0.0082849964

Sheet Investment
B6: (All amounts in INR Lakhs, unless otherwise stated)
B7: Particulars | C7: 2021 | D7: =C7+1 -> 2022 | E7: =D7+1 -> 2023 | F7: =E7+1 -> 2024 | G7: =F7+1 -> 2025 | H7: =G7+1 -> 2026 | I7: =H7+1 -> 2027 | J7: =I7+1 -> 2028 | K7: =J7+1 -> 2029 | ... Q7: =P7+1 -> 2035
A9: # | B9: Investments in associates accounted for using the equity method
B10: Opening Balance | D10: =C12 -> 216675.61 | E10: =D12 -> 229117.91 | F10: =E12 -> 262650.13 | G10: =F12 -> 281033.31 | H10: =G12 -> 304669.13 | I10: =H12 -> 326475.61 | J10: =I12 -> 350777.57 | K10: =J12 -> 377932.94 | ... Q10: =P12 -> 630311.13
B11: Purchase/sales of Investment | D11: =D12-D10 -> 12442.3 | E11: =E12-E10 -> 33532.22 | F11: =F12-F10 -> 18383.18 | G11: =G12-G10 -> 23635.82 | H11: =H12-H10 -> 21806.485 | I11: =I12-I10 -> 24301.96 | J11: =J12-J10 -> 27155.369 | K11: =K12-K10 -> 30427.9 | ... Q11: =Q12-Q10 -> 64211.415
B12: Closing Balance | C12: ='Historical B_Sheet'!C17 -> 216675.61 | D12: ='Historical B_Sheet'!D16 -> 229117.91 | E12: ='Historical B_Sheet'!E16 -> 262650.13 | F12: ='Historical B_Sheet'!F16 -> 281033.31 | G12: ='Historical B_Sheet'!G16 -> 304669.13 | H12: =G12*(1+H14) -> 326475.61 | I12: =H12*(1+I14) -> 350777.57 | J12: =I12*(1+J14) -> 377932.94 | K12: =J12*(1+K14) -> 408360.84 | L12: =K12*(1+L14) -> 442553.64 | M12: =L12*(1+M14) -> 481091.7 | N12: =M12*(1+N14) -> 524661.46 | O12: =N12*(1+O14) -> 574077.7 | ... Q12: =P12*(1+Q14) -> 694522.55
B14: Investment Growth rate | C14: 0 | D14: =D12/C12-1 -> 0.05742363 | E14: =E12/D12-1 -> 0.14635355 | F14: =F12/E12-1 -> 0.069991132 | G14: =G12/F12-1 -> 0.084103269 | H14: =AVERAGE(C14:G14) -> 0.071574317 | I14: =H14*(1+Assumptions!$C$20) -> 0.074437289 | J14: =I14*(1+Assumptions!$C$20) -> 0.077414781 | K14: =J14*(1+Assumptions!$C$20) -> 0.080511372 | L14: =K14*(1+Assumptions!$C$20) -> 0.083731827 | M14: =L14*(1+Assumptions!$C$20) -> 0.0870811 | N14: =M14*(1+Assumptions!$C$20) -> 0.090564344 | O14: =N14*(1+Assumptions!$C$20) -> 0.094186918 | P14: =O14*(1+Assumptions!$C$20) -> 0.097954394 | Q14: =P14*(1+Assumptions!$C$20) -> 0.10187257
B15: Standard Deviation | C15: =_xlfn.STDEV.S(D14:G14) -> 0.039458571
A17: # | B17: Investments
B18: Opening Balance | D18: =C20 -> 0 | E18: =D20 -> 44668.35 | F18: =E20 -> 43858.98 | G18: =F20 -> 45919.59 | H18: =G20 -> 48110.18 | I18: =H20 -> 49338.08 | J18: =I20 -> 50635.096 | K18: =J20 -> 52006.143 | ... Q18: =P20 -> 62121.737
B19: Purchase/sales of Investment | D19: =D20-D18 -> 44668.35 | E19: =E20-E18 -> -809.37 | F19: =F20-F18 -> 2060.61 | G19: =G20-G18 -> 2190.59 | H19: =H20-H18 -> 1227.9 | I19: =I20-I18 -> 1297.0165 | J19: =J20-J18 -> 1371.0463 | K19: =K20-K18 -> 1450.4152 | ... Q19: =Q20-Q18 -> 2068.7339
B20: Closing Balance | D20: ='Historical B_Sheet'!D17 -> 44668.35 | E20: ='Historical B_Sheet'!E17 -> 43858.98 | F20: ='Historical B_Sheet'!F17 -> 45919.59 | G20: ='Historical B_Sheet'!G17 -> 48110.18 | H20: =G20*(1+H22) -> 49338.08 | I20: =H20*(1+I22) -> 50635.096 | J20: =I20*(1+J22) -> 52006.143 | K20: =J20*(1+K22) -> 53456.558 | L20: =K20*(1+L22) -> 54992.15 | M20: =L20*(1+M22) -> 56619.245 | N20: =M20*(1+N22) -> 58344.739 | O20: =N20*(1+O22) -> 60176.16 | ... Q20: =P20*(1+Q22) -> 64190.471
B22: Investment Growth rate | C22: 0 | D22: 0 | E22: =E20/D20-1 -> -0.018119541 | F22: =F20/E20-1 -> 0.046982625 | G22: =G20/F20-1 -> 0.047704912 | H22: =AVERAGE(E22:G22) -> 0.025522665 | I22: =H22*(1+Assumptions!$C$19) -> 0.026288345 | J22: =I22*(1+Assumptions!$C$19) -> 0.027076996 | K22: =J22*(1+Assumptions!$C$19) -> 0.027889305 | L22: =K22*(1+Assumptions!$C$19) -> 0.028725985 | M22: =L22*(1+Assumptions!$C$19) -> 0.029587764 | N22: =M22*(1+Assumptions!$C$19) -> 0.030475397 | O22: =N22*(1+Assumptions!$C$19) -> 0.031389659 | P22: =O22*(1+Assumptions!$C$19) -> 0.032331349 | Q22: =P22*(1+Assumptions!$C$19) -> 0.033301289
B23: Standard Deviation | C23: =_xlfn.STDEV.S(D22:G22) -> 0.033395503

Sheet Income Statement
B6: (All amounts in INR Lakhs, unless otherwise stated)
B7: Particulars | C7: 2021 | D7: =C7+1 -> 2022 | E7: =D7+1 -> 2023 | F7: =E7+1 -> 2024 | G7: =F7+1 -> 2025 | H7: =G7+1 -> 2026 | I7: =H7+1 -> 2027 | J7: =I7+1 -> 2028 | K7: =J7+1 -> 2029 | ... Q7: =P7+1 -> 2035
B9: Revenue from operations
B10: Interest Income | C10: =Revenue_BuildUp!C13 -> 779.91 | D10: =Revenue_BuildUp!D13 -> 393.67 | E10: =Revenue_BuildUp!E13 -> 335.7 | F10: =Revenue_BuildUp!F13 -> 102.87 | G10: =Revenue_BuildUp!G13 -> 119.48 | H10: =Revenue_BuildUp!H13 -> 811.24479 | I10: =Revenue_BuildUp!I13 -> 1121.3104 | J10: =Revenue_BuildUp!J13 -> 1464.1711 | ... Q10: =Revenue_BuildUp!Q13 -> 3585.9572
B11: Dividend Income | C11: =Revenue_BuildUp!C16 -> 6.38 | D11: =Revenue_BuildUp!D16 -> 263.68 | E11: =Revenue_BuildUp!E16 -> 192.98 | F11: =Revenue_BuildUp!F16 -> 229.05 | G11: =Revenue_BuildUp!G16 -> 225.33 | H11: =Revenue_BuildUp!H16 -> 446.6401 | I11: =Revenue_BuildUp!I16 -> 617.3503 | J11: =Revenue_BuildUp!J16 -> 806.11614 | ... Q11: =Revenue_BuildUp!Q16 -> 1974.2898
B12: Net gain on fair value changes | C12: =Revenue_BuildUp!C19 -> 1192.22 | D12: =Revenue_BuildUp!D19 -> 2651.6 | E12: =Revenue_BuildUp!E19 -> 59.77 | F12: =Revenue_BuildUp!F19 -> 1158.21 | G12: =Revenue_BuildUp!G19 -> 1932.81 | H12: =Revenue_BuildUp!H19 -> 2107.8958 | I12: =Revenue_BuildUp!I19 -> 2913.5541 | J12: =Revenue_BuildUp!J19 -> 3804.4251 | ... Q12: =Revenue_BuildUp!Q19 -> 9317.5627
B13: Total Revenue from operations | C13: =SUM(C10:C12) -> 1978.51 | D13: =SUM(D10:D12) -> 3308.95 | E13: =SUM(E10:E12) -> 588.45 | F13: =SUM(F10:F12) -> 1490.13 | G13: =SUM(G10:G12) -> 2277.62 | H13: =SUM(H10:H12) -> 3365.7807 | I13: =SUM(I10:I12) -> 4652.2148 | J13: =SUM(J10:J12) -> 6074.7122 | ... Q13: =SUM(Q10:Q12) -> 14877.81
B15: Expenses
B16: Employee benefits expenses | C16: =Cost_BuildUp!C11 -> 56.11 | D16: =Cost_BuildUp!D11 -> 81.83 | E16: =Cost_BuildUp!E11 -> 124.52 | F16: =Cost_BuildUp!F11 -> 48.36 | G16: =Cost_BuildUp!G11 -> 62.01 | H16: =Cost_BuildUp!H11 -> 218.35551 | I16: =Cost_BuildUp!I11 -> 301.81311 | J16: =Cost_BuildUp!J11 -> 394.09783 | ... Q16: =Cost_BuildUp!Q11 -> 965.20005
B17: Other expenses | C17: =Cost_BuildUp!C14 -> 170.92 | D17: =Cost_BuildUp!D14 -> 225.61 | E17: =Cost_BuildUp!E14 -> 312.42 | F17: =Cost_BuildUp!F14 -> 385.57 | G17: =Cost_BuildUp!G14 -> 556.24 | H17: =Cost_BuildUp!H14 -> 800.01866 | I17: =Cost_BuildUp!I14 -> 1105.7936 | J17: =Cost_BuildUp!J14 -> 1443.9096 | ... Q17: =Cost_BuildUp!Q14 -> 3536.3342
B18: Total Expenses | C18: =SUM(C16:C17) -> 227.03 | D18: =SUM(D16:D17) -> 307.44 | E18: =SUM(E16:E17) -> 436.94 | F18: =SUM(F16:F17) -> 433.93 | G18: =SUM(G16:G17) -> 618.25 | H18: =SUM(H16:H17) -> 1018.3742 | I18: =SUM(I16:I17) -> 1407.6067 | J18: =SUM(J16:J17) -> 1838.0075 | ... Q18: =SUM(Q16:Q17) -> 4501.5343
B20: EBITDA | C20: =C13-C18 -> 1751.48 | D20: =D13-D18 -> 3001.51 | E20: =E13-E18 -> 151.51 | F20: =F13-F18 -> 1056.2 | G20: =G13-G18 -> 1659.37 | H20: =H13-H18 -> 2347.4065 | I20: =I13-I18 -> 3244.6081 | J20: =J13-J18 -> 4236.7048 | ... Q20: =Q13-Q18 -> 10376.275
B22: D&A | C22: =FSA!C12 -> 0.88 | D22: =FSA!D12 -> 0.77 | E22: =FSA!E12 -> 0.72 | F22: =FSA!F12 -> 0.72 | G22: =FSA!G12 -> 0.72 | H22: =FSA!H12 -> 1.2064298 | I22: =FSA!I12 -> 1.2018634 | J22: =FSA!J12 -> 1.1973144 | ... Q22: =FSA!Q12 -> 2.5177578
B24: EBIT | C24: =C20-C22 -> 1750.6 | D24: =D20-D22 -> 3000.74 | E24: =E20-E22 -> 150.79 | F24: =F20-F22 -> 1055.48 | G24: =G20-G22 -> 1658.65 | H24: =H20-H22 -> 2346.2001 | I24: =I20-I22 -> 3243.4063 | J24: =J20-J22 -> 4235.5075 | ... Q24: =Q20-Q22 -> 10373.758
B26: Other Income | C26: =Revenue_BuildUp!C25 -> 124.69 | D26: =Revenue_BuildUp!D25 -> 185.46 | E26: =Revenue_BuildUp!E25 -> 188.17 | F26: =Revenue_BuildUp!F25 -> 247.22 | G26: =Revenue_BuildUp!G25 -> 185.66 | H26: =Revenue_BuildUp!H25 -> 461.96171 | I26: =Revenue_BuildUp!I25 -> 638.52797 | J26: =Revenue_BuildUp!J25 -> 833.76926 | ... Q26: =Revenue_BuildUp!Q25 -> 2042.0161
B27: Share of Profit of Associates | C27: =Revenue_BuildUp!C22 -> 11446.14 | D27: =Revenue_BuildUp!D22 -> 42760.92 | E27: =Revenue_BuildUp!E22 -> 22153.14 | F27: =Revenue_BuildUp!F22 -> 18121.32 | G27: =Revenue_BuildUp!G22 -> 25453.08 | H27: =Revenue_BuildUp!H22 -> 26806.142 | I27: =Revenue_BuildUp!I22 -> 37051.711 | J27: =Revenue_BuildUp!J22 -> 48380.93 | ... Q27: =Revenue_BuildUp!Q22 -> 118491.58
B30: EBT | C30: =C24+C26+C27 -> 13321.43 | D30: =D24+D26+D27 -> 45947.12 | E30: =E24+E26+E27 -> 22492.1 | F30: =F24+F26+F27 -> 19424.02 | G30: =G24+G26+G27 -> 27297.39 | H30: =H24+H26+H27 -> 29614.304 | I30: =I24+I26+I27 -> 40933.645 | J30: =J24+J26+J27 -> 53450.207 | ... Q30: =Q24+Q26+Q27 -> 130907.36
B32: Tax | C32: ='Historical P&L'!C31 -> 370.28 | D32: ='Historical P&L'!D31 -> 3039.3 | E32: ='Historical P&L'!E31 -> -351.16 | F32: ='Historical P&L'!F31 -> 935.96 | G32: ='Historical P&L'!G31 -> 1497.02 | H32: =H30*Cost_BuildUp!H19 -> 1772.1537 | I32: =I30*Cost_BuildUp!I19 -> 2449.516 | J32: =J30*Cost_BuildUp!J19 -> 3465.7724 | K32: =K30*Cost_BuildUp!K19 -> 4313.5383 | L32: =L30*Cost_BuildUp!L19 -> 5555.3991 | M32: =M30*Cost_BuildUp!M19 -> 6425.1328 | N32: =N30*Cost_BuildUp!N19 -> 7747.4049 | O32: =O30*Cost_BuildUp!O19 -> 8523.6651 | ... Q32: =Q30*Cost_BuildUp!Q19 -> 10451.793
B34: Net Profit | C34: =C30-C32 -> 12951.15 | D34: =D30-D32 -> 42907.82 | E34: =E30-E32 -> 22843.26 | F34: =F30-F32 -> 18488.06 | G34: =G30-G32 -> 25800.37 | H34: =H30-H32 -> 27842.15 | I34: =I30-I32 -> 38484.129 | J34: =J30-J32 -> 49984.435 | ... Q34: =Q30-Q32 -> 120455.57
B35: Net Profit Margin | C35: =C34/C13 -> 6.5459108 | D35: =D34/D13 -> 12.967201 | E35: =E34/E13 -> 38.819373 | F35: =F34/F13 -> 12.407011 | G35: =G34/G13 -> 11.327776 | H35: =H34/H13 -> 8.2721226 | I35: =I34/I13 -> 8.2722167 | J35: =J34/J13 -> 8.2282802 | ... Q35: =Q34/Q13 -> 8.0963238
B37: Dividend | C37: =-'Cash flow'!C44 -> 2.31 | D37: =-'Cash flow'!D44 -> 159.58 | E37: =-'Cash flow'!E44 -> 159.49 | F37: =-'Cash flow'!F44 -> 160.22 | G37: =-'Cash flow'!G44 -> 160.46 | H37: =H38*H34 -> 143.46977 | I37: =I38*I34 -> 198.30757 | J37: =J38*J34 -> 257.5683 | K37: =K38*K34 -> 320.57233 | L37: =L38*L34 -> 381.25776 | M37: =M38*M34 -> 440.94613 | N37: =N38*N34 -> 493.503 | O37: =O38*O34 -> 542.9501 | ... Q37: =Q38*Q34 -> 620.70393
B38: Dividened PayOut Ratio | C38: =C37/C34 -> 0.00017836254 | D38: =D37/D34 -> 0.0037191356 | E38: =E37/E34 -> 0.0069819281 | F38: =F37/F34 -> 0.0086661337 | G38: =G37/G34 -> 0.0062192907 | H38: =AVERAGE(C38:G38) -> 0.0051529701 | I38: =H38 -> 0.0051529701 | J38: =I38 -> 0.0051529701 | K38: =J38 -> 0.0051529701 | L38: =K38 -> 0.0051529701 | M38: =L38 -> 0.0051529701 | N38: =M38 -> 0.0051529701 | O38: =N38 -> 0.0051529701 | P38: =O38 -> 0.0051529701 | Q38: =P38 -> 0.0051529701
B40: Retained Earning | C40: =C34-C37 -> 12948.84 | D40: =D34-D37 -> 42748.24 | E40: =E34-E37 -> 22683.77 | F40: =F34-F37 -> 18327.84 | G40: =G34-G37 -> 25639.91 | H40: =H34-H37 -> 27698.681 | I40: =I34-I37 -> 38285.821 | J40: =J34-J37 -> 49726.866 | ... Q40: =Q34-Q37 -> 119834.86
B41: Retained Earning % | C41: =C40/C34 -> 0.99982164 | D41: =D40/D34 -> 0.99628086 | E41: =E40/E34 -> 0.99301807 | F41: =F40/F34 -> 0.99133387 | G41: =G40/G34 -> 0.99378071 | H41: =H40/H34 -> 0.99484703 | I41: =I40/I34 -> 0.99484703 | J41: =J40/J34 -> 0.99484703 | ... Q41: =Q40/Q34 -> 0.99484703

Sheet Balance_Sheet_Forecast
B6: (All amounts in INR Lakhs, unless otherwise stated)
B7: Particulars | C7: 2021 | D7: =C7+1 -> 2022 | E7: =D7+1 -> 2023 | F7: =E7+1 -> 2024 | G7: =F7+1 -> 2025 | H7: =G7+1 -> 2026 | I7: =H7+1 -> 2027 | J7: =I7+1 -> 2028 | K7: =J7+1 -> 2029 | ... Q7: =P7+1 -> 2035
B9: Assets
B10: Financial Assets
B11: Other Receivables | C11: ='Historical B_Sheet'!C15 -> 577.05 | D11: ='Historical B_Sheet'!D15 -> 230.41 | E11: ='Historical B_Sheet'!E15 -> 262.69 | F11: ='Historical B_Sheet'!F15 -> 252.58 | G11: ='Historical B_Sheet'!G15 -> 199.46 | H11: =H12*Revenue_BuildUp!H$9 -> 716.76127 | I11: =I12*Revenue_BuildUp!I$9 -> 990.71441 | J11: =J12*Revenue_BuildUp!J$9 -> 1293.643 | K11: =K12*Revenue_BuildUp!K$9 -> 1610.0864 | L11: =L12*Revenue_BuildUp!L$9 -> 1925.1665 | M11: =M12*Revenue_BuildUp!M$9 -> 2226.5573 | N11: =N12*Revenue_BuildUp!N$9 -> 2505.4169 | O11: =O12*Revenue_BuildUp!O$9 -> 2756.4446 | ... Q11: =Q12*Revenue_BuildUp!Q$9 -> 3168.3104
B12: (x) of Revenue | C12: =C11/Revenue_BuildUp!C$9 -> 0.29165887 | D12: =D11/Revenue_BuildUp!D$9 -> 0.069632361 | E12: =E11/Revenue_BuildUp!E$9 -> 0.44641006 | F12: =F11/Revenue_BuildUp!F$9 -> 0.16950199 | G12: =G11/Revenue_BuildUp!G$9 -> 0.087573871 | H12: =AVERAGE(C12:G12) -> 0.21295543 | I12: =H12 -> 0.21295543 | J12: =I12 -> 0.21295543 | K12: =J12 -> 0.21295543 | L12: =K12 -> 0.21295543 | M12: =L12 -> 0.21295543 | N12: =M12 -> 0.21295543 | O12: =N12 -> 0.21295543 | P12: =O12 -> 0.21295543 | Q12: =P12 -> 0.21295543
B14: Other Financial assets | C14: ='Historical B_Sheet'!C18 -> 1572.52 | D14: ='Historical B_Sheet'!D18 -> 609.68 | E14: ='Historical B_Sheet'!E18 -> 445.01 | F14: ='Historical B_Sheet'!F18 -> 227.74 | G14: ='Historical B_Sheet'!G18 -> 41.66 | H14: =H15*Revenue_BuildUp!H$9 -> 1283.3158 | I14: =I15*Revenue_BuildUp!I$9 -> 1773.8116 | J14: =J15*Revenue_BuildUp!J$9 -> 2316.186 | K14: =K15*Revenue_BuildUp!K$9 -> 2882.7581 | L14: =L15*Revenue_BuildUp!L$9 -> 3446.889 | M14: =M15*Revenue_BuildUp!M$9 -> 3986.5102 | N14: =N15*Revenue_BuildUp!N$9 -> 4485.7906 | O14: =O15*Revenue_BuildUp!O$9 -> 4935.2399 | ... Q14: =Q15*Revenue_BuildUp!Q$9 -> 5672.6596
B15: (x) of Revenue | C15: =C14/Revenue_BuildUp!C$9 -> 0.79480013 | D15: =D14/Revenue_BuildUp!D$9 -> 0.1842518 | E15: =E14/Revenue_BuildUp!E$9 -> 0.75624097 | F15: =F14/Revenue_BuildUp!F$9 -> 0.1528323 | G15: =G14/Revenue_BuildUp!G$9 -> 0.018291023 | H15: =AVERAGE(C15:G15) -> 0.38128325 | I15: =H15 -> 0.38128325 | J15: =I15 -> 0.38128325 | K15: =J15 -> 0.38128325 | L15: =K15 -> 0.38128325 | M15: =L15 -> 0.38128325 | N15: =M15 -> 0.38128325 | O15: =N15 -> 0.38128325 | P15: =O15 -> 0.38128325 | Q15: =P15 -> 0.38128325
B17: Non Financial Assets
B18: Current Tax assets (Net) | C18: ='Historical B_Sheet'!C23 -> 0 | D18: ='Historical B_Sheet'!D23 -> 105.2 | E18: ='Historical B_Sheet'!E23 -> 306.77 | F18: ='Historical B_Sheet'!F23 -> 533.01 | G18: ='Historical B_Sheet'!G23 -> 373.39 | H18: =H19*Revenue_BuildUp!H$9 -> 723.47023 | I18: =I19*Revenue_BuildUp!I$9 -> 999.9876 | J18: =J19*Revenue_BuildUp!J$9 -> 1305.7516 | K18: =K19*Revenue_BuildUp!K$9 -> 1625.157 | L18: =L19*Revenue_BuildUp!L$9 -> 1943.1862 | M18: =M19*Revenue_BuildUp!M$9 -> 2247.3981 | N18: =N19*Revenue_BuildUp!N$9 -> 2528.8678 | O18: =O19*Revenue_BuildUp!O$9 -> 2782.2452 | ... Q18: =Q19*Revenue_BuildUp!Q$9 -> 3197.9661
B19: (x) of Revenue | C19: =C18/Revenue_BuildUp!C$9 -> 0 | D19: =D18/Revenue_BuildUp!D$9 -> 0.031792563 | E19: =E18/Revenue_BuildUp!E$9 -> 0.52131872 | F19: =F18/Revenue_BuildUp!F$9 -> 0.35769362 | G19: =G18/Revenue_BuildUp!G$9 -> 0.16393867 | H19: =AVERAGE(C19:G19) -> 0.21494872 | I19: =H19 -> 0.21494872 | J19: =I19 -> 0.21494872 | K19: =J19 -> 0.21494872 | L19: =K19 -> 0.21494872 | M19: =L19 -> 0.21494872 | N19: =M19 -> 0.21494872 | O19: =N19 -> 0.21494872 | P19: =O19 -> 0.21494872 | Q19: =P19 -> 0.21494872
B21: Deferred Tax Asset (Net) | C21: ='Historical B_Sheet'!C24 -> 3913.66 | D21: ='Historical B_Sheet'!D24 -> 2415.08 | E21: ='Historical B_Sheet'!E24 -> 1813.25 | F21: ='Historical B_Sheet'!F24 -> 1098.4 | G21: ='Historical B_Sheet'!G24 -> 223.85 | H21: =H22*Revenue_BuildUp!H$9 -> 330.79706 | I21: =I22*Revenue_BuildUp!I$9 -> 457.23092 | J21: =J22*Revenue_BuildUp!J$9 -> 597.03741 | K21: =K22*Revenue_BuildUp!K$9 -> 743.08125 | L21: =L22*Revenue_BuildUp!L$9 -> 888.49585 | M21: =M22*Revenue_BuildUp!M$9 -> 1027.5926 | N21: =N22*Revenue_BuildUp!N$9 -> 1156.2909 | O21: =O22*Revenue_BuildUp!O$9 -> 1272.1443 | ... Q21: =Q22*Revenue_BuildUp!Q$9 -> 1462.2271
B22: (x) of Revenue | C22: =C21/Revenue_BuildUp!C$9 -> 1.9780845 | D22: =D21/Revenue_BuildUp!D$9 -> 0.72986295 | E22: =E21/Revenue_BuildUp!E$9 -> 3.0814003 | F22: =F21/Revenue_BuildUp!F$9 -> 0.7371169 | G22: =G21/Revenue_BuildUp!G$9 -> 0.098282418 | H22: =G22 -> 0.098282418 | I22: =H22 -> 0.098282418 | J22: =I22 -> 0.098282418 | K22: =J22 -> 0.098282418 | L22: =K22 -> 0.098282418 | M22: =L22 -> 0.098282418 | N22: =M22 -> 0.098282418 | O22: =N22 -> 0.098282418 | ... Q22: =P22 -> 0.098282418
B24: Other non-financial assets | C24: ='Historical B_Sheet'!C26 -> 24.73 | D24: ='Historical B_Sheet'!D26 -> 9.95 | E24: ='Historical B_Sheet'!E26 -> 11.88 | F24: ='Historical B_Sheet'!F26 -> 10.09 | G24: ='Historical B_Sheet'!G26 -> 10.94 | H24: =H25*Revenue_BuildUp!H$9 -> 31.819695 | I24: =I25*Revenue_BuildUp!I$9 -> 43.981493 | J24: =J25*Revenue_BuildUp!J$9 -> 57.429617 | K24: =K25*Revenue_BuildUp!K$9 -> 71.477718 | L24: =L25*Revenue_BuildUp!L$9 -> 85.465292 | M24: =M25*Revenue_BuildUp!M$9 -> 98.845149 | N24: =N25*Revenue_BuildUp!N$9 -> 111.22476 | O24: =O25*Revenue_BuildUp!O$9 -> 122.36881 | ... Q24: =Q25*Revenue_BuildUp!Q$9 -> 140.65307
B25: (x) of Revenue | C25: =C24/Revenue_BuildUp!C$9 -> 0.012499305 | D25: =D24/Revenue_BuildUp!D$9 -> 0.0030069962 | E25: =E24/Revenue_BuildUp!E$9 -> 0.020188631 | F25: =F24/Revenue_BuildUp!F$9 -> 0.0067712213 | G25: =G24/Revenue_BuildUp!G$9 -> 0.0048032595 | H25: =AVERAGE(C25:G25) -> 0.0094538826 | I25: =H25 -> 0.0094538826 | J25: =I25 -> 0.0094538826 | K25: =J25 -> 0.0094538826 | L25: =K25 -> 0.0094538826 | M25: =L25 -> 0.0094538826 | N25: =M25 -> 0.0094538826 | O25: =N25 -> 0.0094538826 | P25: =O25 -> 0.0094538826 | Q25: =P25 -> 0.0094538826
B27: Liabilities
B28: Financial Liabilities
B29: Other financial liabilities | C29: ='Historical B_Sheet'!C39 -> 81.27 | D29: ='Historical B_Sheet'!D39 -> 18.35 | E29: ='Historical B_Sheet'!E39 -> 13.46 | F29: ='Historical B_Sheet'!F39 -> 16.6 | G29: ='Historical B_Sheet'!G39 -> 7 | H29: =H30*Revenue_BuildUp!H$9 -> 56.349182 | I29: =I30*Revenue_BuildUp!I$9 -> 77.886388 | J29: =J30*Revenue_BuildUp!J$9 -> 101.70154 | K29: =K30*Revenue_BuildUp!K$9 -> 126.57918 | L29: =L30*Revenue_BuildUp!L$9 -> 151.34964 | M29: =M30*Revenue_BuildUp!M$9 -> 175.04389 | N29: =N30*Revenue_BuildUp!N$9 -> 196.96682 | O29: =O30*Revenue_BuildUp!O$9 -> 216.70171 | ... Q29: =Q30*Revenue_BuildUp!Q$9 -> 249.08112
B30: (x) of Revenue | C30: =C29/Revenue_BuildUp!C$9 -> 0.041076366 | D30: =D29/Revenue_BuildUp!D$9 -> 0.0055455658 | E30: =E29/Revenue_BuildUp!E$9 -> 0.022873651 | F30: =F29/Revenue_BuildUp!F$9 -> 0.011139968 | G30: =G29/Revenue_BuildUp!G$9 -> 0.0030733836 | H30: =AVERAGE(C30:G30) -> 0.016741787 | I30: =H30 -> 0.016741787 | J30: =I30 -> 0.016741787 | K30: =J30 -> 0.016741787 | L30: =K30 -> 0.016741787 | M30: =L30 -> 0.016741787 | N30: =M30 -> 0.016741787 | O30: =N30 -> 0.016741787 | P30: =O30 -> 0.016741787 | Q30: =P30 -> 0.016741787
B32: Non Financial Liabilities
B33: Provisions | C33: ='Historical B_Sheet'!C45 -> 2.9 | D33: ='Historical B_Sheet'!D45 -> 1.55 | E33: ='Historical B_Sheet'!E45 -> 5.52 | F33: ='Historical B_Sheet'!F45 -> 3.11 | G33: ='Historical B_Sheet'!G45 -> 6.75 | H33: =H34*Revenue_BuildUp!H$9 -> 11.016495 | I33: =I34*Revenue_BuildUp!I$9 -> 15.227107 | J33: =J34*Revenue_BuildUp!J$9 -> 19.883066 | K33: =K34*Revenue_BuildUp!K$9 -> 24.746746 | L33: =L34*Revenue_BuildUp!L$9 -> 29.589472 | M33: =M34*Revenue_BuildUp!M$9 -> 34.221795 | N33: =N34*Revenue_BuildUp!N$9 -> 38.507818 | O33: =O34*Revenue_BuildUp!O$9 -> 42.36607 | ... Q33: =Q34*Revenue_BuildUp!Q$9 -> 48.696375
B34: (x) of Revenue | C34: =C33/Revenue_BuildUp!C$9 -> 0.0014657495 | D34: =D33/Revenue_BuildUp!D$9 -> 0.00046842654 | E34: =E33/Revenue_BuildUp!E$9 -> 0.0093805761 | F34: =F33/Revenue_BuildUp!F$9 -> 0.0020870662 | G34: =G33/Revenue_BuildUp!G$9 -> 0.0029636199 | H34: =AVERAGE(C34:G34) -> 0.0032730877 | I34: =H34 -> 0.0032730877 | J34: =I34 -> 0.0032730877 | K34: =J34 -> 0.0032730877 | L34: =K34 -> 0.0032730877 | M34: =L34 -> 0.0032730877 | N34: =M34 -> 0.0032730877 | O34: =N34 -> 0.0032730877 | P34: =O34 -> 0.0032730877 | Q34: =P34 -> 0.0032730877
B36: Other non-financial liabilities | C36: ='Historical B_Sheet'!C46 -> 27.11 | D36: ='Historical B_Sheet'!D46 -> 47.65 | E36: ='Historical B_Sheet'!E46 -> 90.95 | F36: ='Historical B_Sheet'!F46 -> 40.09 | G36: ='Historical B_Sheet'!G46 -> 39.1 | H36: =H37*Revenue_BuildUp!H$9 -> 152.62596 | I36: =I37*Revenue_BuildUp!I$9 -> 210.96109 | J36: =J37*Revenue_BuildUp!J$9 -> 275.4662 | K36: =K37*Revenue_BuildUp!K$9 -> 342.84915 | L36: =L37*Revenue_BuildUp!L$9 -> 409.94178 | M36: =M37*Revenue_BuildUp!M$9 -> 474.11944 | N36: =N37*Revenue_BuildUp!N$9 -> 533.49933 | O36: =O37*Revenue_BuildUp!O$9 -> 586.95276 | ... Q36: =Q37*Revenue_BuildUp!Q$9 -> 674.65479
B37: (x) of Revenue | C37: =C36/Revenue_BuildUp!C$9 -> 0.01370223 | D37: =D36/Revenue_BuildUp!D$9 -> 0.014400338 | E37: =E36/Revenue_BuildUp!E$9 -> 0.15455859 | F37: =F36/Revenue_BuildUp!F$9 -> 0.026903693 | G37: =G36/Revenue_BuildUp!G$9 -> 0.017167043 | H37: =AVERAGE(C37:G37) -> 0.045346378 | I37: =H37 -> 0.045346378 | J37: =I37 -> 0.045346378 | K37: =J37 -> 0.045346378 | L37: =K37 -> 0.045346378 | M37: =L37 -> 0.045346378 | N37: =M37 -> 0.045346378 | O37: =N37 -> 0.045346378 | P37: =O37 -> 0.045346378 | Q37: =P37 -> 0.045346378

Sheet Net Working Capital
B7: Calculation of Net Working Capital
B8: (All amounts in INR Lakhs, unless otherwise stated)
B9: Particulars | C9: 2021 | D9: =C9+1 -> 2022 | E9: =D9+1 -> 2023 | F9: =E9+1 -> 2024 | G9: =F9+1 -> 2025 | H9: =G9+1 -> 2026 | I9: =H9+1 -> 2027 | J9: =I9+1 -> 2028 | K9: =J9+1 -> 2029 | ... Q9: =P9+1 -> 2035
B10: Financial Assets
B11: Other Receivables | C11: 577.05 | D11: 230.41 | E11: 262.69 | F11: 252.58 | G11: 199.46 | H11: ='Balance Sheet'!H17 -> 716.76127 | I11: ='Balance Sheet'!I17 -> 990.71441 | J11: ='Balance Sheet'!J17 -> 1293.643 | K11: ='Balance Sheet'!K17 -> 1610.0864 | L11: ='Balance Sheet'!L17 -> 1925.1665 | M11: ='Balance Sheet'!M17 -> 2226.5573 | N11: ='Balance Sheet'!N17 -> 2505.4169 | O11: ='Balance Sheet'!O17 -> 2756.4446 | ... Q11: ='Balance Sheet'!Q17 -> 3168.3104
B12: Other Financial assets | C12: 1572.52 | D12: 609.68 | E12: 445.01 | F12: 227.74 | G12: 41.66 | H12: ='Balance Sheet'!H20 -> 1283.3158 | I12: ='Balance Sheet'!I20 -> 1773.8116 | J12: ='Balance Sheet'!J20 -> 2316.186 | K12: ='Balance Sheet'!K20 -> 2882.7581 | L12: ='Balance Sheet'!L20 -> 3446.889 | M12: ='Balance Sheet'!M20 -> 3986.5102 | N12: ='Balance Sheet'!N20 -> 4485.7906 | O12: ='Balance Sheet'!O20 -> 4935.2399 | ... Q12: ='Balance Sheet'!Q20 -> 5672.6596
B13: Current Portion of Other Investment | C13: 2907.29 | D13: 20886.95 | E13: 5854.29 | F13: 7789.29 | G13: 11776.92 | H13: =H14*Investment!H20 -> 10152.965 | I13: =I14*Investment!I20 -> 10419.87 | J13: =J14*Investment!J20 -> 10702.008 | K13: =K14*Investment!K20 -> 11000.48 | L13: =L14*Investment!L20 -> 11316.48 | M13: =M14*Investment!M20 -> 11651.309 | N13: =N14*Investment!N20 -> 12006.387 | O13: =O14*Investment!O20 -> 12383.264 | ... Q13: =Q14*Investment!Q20 -> 13209.343
B14: % of Total Other Investment | C14: =C13/'Balance Sheet'!C19 -> 0.013417708 | D14: =D13/'Balance Sheet'!D19 -> 0.46760066 | E14: =E13/'Balance Sheet'!E19 -> 0.13347985 | F14: =F13/'Balance Sheet'!F19 -> 0.16962891 | G14: =G13/'Balance Sheet'!G19 -> 0.2447906 | H14: =AVERAGE(C14:G14) -> 0.20578355 | I14: =H14 -> 0.20578355 | J14: =I14 -> 0.20578355 | K14: =J14 -> 0.20578355 | L14: =K14 -> 0.20578355 | M14: =L14 -> 0.20578355 | N14: =M14 -> 0.20578355 | O14: =N14 -> 0.20578355 | P14: =O14 -> 0.20578355 | Q14: =P14 -> 0.20578355
B15: Total | C15: =SUM(C11:C13) -> 5056.86 | D15: =SUM(D11:D13) -> 21727.04 | E15: =SUM(E11:E13) -> 6561.99 | F15: =SUM(F11:F13) -> 8269.61 | G15: =SUM(G11:G13) -> 12018.04 | H15: =SUM(H11:H13) -> 12153.042 | I15: =SUM(I11:I13) -> 13184.396 | J15: =SUM(J11:J13) -> 14311.837 | ... Q15: =SUM(Q11:Q13) -> 22050.313
B17: Non Financial Assets
B18: Current tax assets | C18: 0 | D18: 105.2 | E18: 306.77 | F18: 533.01 | G18: 373.39 | H18: ='Balance Sheet'!H25 -> 723.47023 | I18: ='Balance Sheet'!I25 -> 999.9876 | J18: ='Balance Sheet'!J25 -> 1305.7516 | K18: ='Balance Sheet'!K25 -> 1625.157 | L18: ='Balance Sheet'!L25 -> 1943.1862 | M18: ='Balance Sheet'!M25 -> 2247.3981 | N18: ='Balance Sheet'!N25 -> 2528.8678 | O18: ='Balance Sheet'!O25 -> 2782.2452 | ... Q18: ='Balance Sheet'!Q25 -> 3197.9661
B19: Other non- Financial assets | C19: 24.73 | D19: 9.95 | E19: 11.88 | F19: 10.09 | G19: 10.94 | H19: ='Balance Sheet'!H28 -> 31.819695 | I19: ='Balance Sheet'!I28 -> 43.981493 | J19: ='Balance Sheet'!J28 -> 57.429617 | K19: ='Balance Sheet'!K28 -> 71.477718 | L19: ='Balance Sheet'!L28 -> 85.465292 | M19: ='Balance Sheet'!M28 -> 98.845149 | N19: ='Balance Sheet'!N28 -> 111.22476 | O19: ='Balance Sheet'!O28 -> 122.36881 | ... Q19: ='Balance Sheet'!Q28 -> 140.65307
B20: Total | C20: =SUM(C18:C19) -> 24.73 | D20: =SUM(D18:D19) -> 115.15 | E20: =SUM(E18:E19) -> 318.65 | F20: =SUM(F18:F19) -> 543.1 | G20: =SUM(G18:G19) -> 384.33 | H20: =SUM(H18:H19) -> 755.28993 | I20: =SUM(I18:I19) -> 1043.9691 | J20: =SUM(J18:J19) -> 1363.1812 | ... Q20: =SUM(Q18:Q19) -> 3338.6192
B22: Total Current Assets | C22: =C20+C15 -> 5081.59 | D22: =D20+D15 -> 21842.19 | E22: =E20+E15 -> 6880.64 | F22: =F20+F15 -> 8812.71 | G22: =G20+G15 -> 12402.37 | H22: =H20+H15 -> 12908.332 | I22: =I20+I15 -> 14228.365 | J22: =J20+J15 -> 15675.019 | ... Q22: =Q20+Q15 -> 25388.932
B24: Change in Current Assets | D24: =C22-D22 -> -16760.6 | E24: =D22-E22 -> 14961.55 | F24: =E22-F22 -> -1932.07 | G24: =F22-G22 -> -3589.66 | H24: =G22-H22 -> -505.96205 | I24: =H22-I22 -> -1320.0327 | J24: =I22-J22 -> -1446.6539 | K24: =J22-K22 -> -1514.9406 | ... Q24: =P22-Q22 -> -1159.6538
B26: Liabilities
B27: Financial Liabilities
B28: Other financial liabilities | C28: ='Balance Sheet'!C37 -> 81.27 | D28: ='Balance Sheet'!D37 -> 18.35 | E28: ='Balance Sheet'!E37 -> 13.46 | F28: ='Balance Sheet'!F37 -> 16.6 | G28: ='Balance Sheet'!G37 -> 7 | H28: ='Balance Sheet'!H37 -> 56.349182 | I28: ='Balance Sheet'!I37 -> 77.886388 | J28: ='Balance Sheet'!J37 -> 101.70154 | ... Q28: ='Balance Sheet'!Q37 -> 249.08112
B30: Total Financial Liabilities | C30: =SUM(C28:C29) -> 81.27 | D30: =SUM(D28:D29) -> 18.35 | E30: =SUM(E28:E29) -> 13.46 | F30: =SUM(F28:F29) -> 16.6 | G30: =SUM(G28:G29) -> 7 | H30: =SUM(H28:H29) -> 56.349182 | I30: =SUM(I28:I29) -> 77.886388 | J30: =SUM(J28:J29) -> 101.70154 | ... Q30: =SUM(Q28:Q29) -> 249.08112
B32: Non Financial Liabilities
B33: Current tax liabilities (Net) | C33: ='Balance Sheet'!C42 -> 43.3 | D33: ='Balance Sheet'!D42 -> 0 | E33: ='Balance Sheet'!E42 -> 0 | F33: ='Balance Sheet'!F42 -> 0 | G33: ='Balance Sheet'!G42 -> 0 | H33: ='Balance Sheet'!H42 -> 0 | I33: ='Balance Sheet'!I42 -> 0 | J33: ='Balance Sheet'!J42 -> 0 | ... Q33: ='Balance Sheet'!Q42 -> 0
B34: Provisions | C34: ='Balance Sheet'!C43 -> 2.9 | D34: ='Balance Sheet'!D43 -> 1.55 | E34: ='Balance Sheet'!E43 -> 5.52 | F34: ='Balance Sheet'!F43 -> 3.11 | G34: ='Balance Sheet'!G43 -> 6.75 | H34: ='Balance Sheet'!H43 -> 11.016495 | I34: ='Balance Sheet'!I43 -> 15.227107 | J34: ='Balance Sheet'!J43 -> 19.883066 | ... Q34: ='Balance Sheet'!Q43 -> 48.696375
B35: Other non-financial liabilities | C35: ='Balance Sheet'!C44 -> 27.11 | D35: ='Balance Sheet'!D44 -> 47.65 | E35: ='Balance Sheet'!E44 -> 90.95 | F35: ='Balance Sheet'!F44 -> 40.09 | G35: ='Balance Sheet'!G44 -> 39.1 | H35: ='Balance Sheet'!H44 -> 152.62596 | I35: ='Balance Sheet'!I44 -> 210.96109 | J35: ='Balance Sheet'!J44 -> 275.4662 | ... Q35: ='Balance Sheet'!Q44 -> 674.65479
B37: Total Non Financial Liabilities | C37: =SUM(C33:C35) -> 73.31 | D37: =SUM(D33:D35) -> 49.2 | E37: =SUM(E33:E35) -> 96.47 | F37: =SUM(F33:F35) -> 43.2 | G37: =SUM(G33:G35) -> 45.85 | H37: =SUM(H33:H35) -> 163.64246 | I37: =SUM(I33:I35) -> 226.1882 | J37: =SUM(J33:J35) -> 295.34926 | ... Q37: =SUM(Q33:Q35) -> 723.35116
B39: Total Current Liabilities | C39: =C37+C30 -> 154.58 | D39: =D37+D30 -> 67.55 | E39: =E37+E30 -> 109.93 | F39: =F37+F30 -> 59.8 | G39: =G37+G30 -> 52.85 | H39: =H37+H30 -> 219.99164 | I39: =I37+I30 -> 304.07459 | J39: =J37+J30 -> 397.0508 | ... Q39: =Q37+Q30 -> 972.43228
B41: Change in Current Laibilities | D41: =D39-C39 -> -87.03 | E41: =E39-D39 -> 42.38 | F41: =F39-E39 -> -50.13 | G41: =G39-F39 -> -6.95 | H41: =H39-G39 -> 167.14164 | I41: =I39-H39 -> 84.082947 | J41: =J39-I39 -> 92.976214 | K41: =K39-J39 -> 97.124276 | ... Q41: =Q39-P39 -> 58.598798
B43: Net Working Capital | D43: =D24+D41 -> -16847.63 | E43: =E24+E41 -> 15003.93 | F43: =F24+F41 -> -1982.2 | G43: =G24+G41 -> -3596.61 | H43: =H24+H41 -> -338.82041 | I43: =I24+I41 -> -1235.9498 | J43: =J24+J41 -> -1353.6777 | K43: =K24+K41 -> -1417.8164 | ... Q43: =Q24+Q41 -> -1101.055

Sheet Balance Sheet
B6: (All amounts in INR Lakhs, unless otherwise stated)
B7: Master Check | C7: =IF(SUM(C57:Q57)=0,"OK","Error") -> OK
B9: Particulars | C9: 2021 | D9: =C9+1 -> 2022 | E9: =D9+1 -> 2023 | F9: =E9+1 -> 2024 | G9: =F9+1 -> 2025 | H9: =G9+1 -> 2026 | I9: =H9+1 -> 2027 | J9: =I9+1 -> 2028 | K9: =J9+1 -> 2029 | ... Q9: =P9+1 -> 2035
B11: Assets
B12: Financial Assets
B13: Cash and bank balances | C13: ='Historical B_Sheet'!C11 -> 7638.83 | D13: ='Historical B_Sheet'!D11 -> 120.99 | E13: ='Historical B_Sheet'!E11 -> 294.74 | F13: ='Historical B_Sheet'!F11 -> 284.7 | G13: ='Historical B_Sheet'!G11 -> 49.18 | H13: ='Cash flow'!H50 -> 2644.9598 | I13: ='Cash flow'!I50 -> 14237.528 | J13: ='Cash flow'!J50 -> 34227.831 | K13: ='Cash flow'!K50 -> 62976.395 | L13: ='Cash flow'!L50 -> 99596.428 | M13: ='Cash flow'!M50 -> 143358.04 | N13: ='Cash flow'!N50 -> 192226.88 | O13: ='Cash flow'!O50 -> 244800.99 | ... Q13: ='Cash flow'!Q50 -> 351148.2
B14: Bank Balances | C14: ='Historical B_Sheet'!C12 -> 9.79 | D14: ='Historical B_Sheet'!D12 -> 152.78 | E14: ='Historical B_Sheet'!E12 -> 106.02 | F14: ='Historical B_Sheet'!F12 -> 98.22 | G14: ='Historical B_Sheet'!G12 -> 102.77 | H14: =G14 -> 102.77 | I14: =H14 -> 102.77 | J14: =I14 -> 102.77 | K14: =J14 -> 102.77 | L14: =K14 -> 102.77 | M14: =L14 -> 102.77 | N14: =M14 -> 102.77 | O14: =N14 -> 102.77 | ... Q14: =P14 -> 102.77
B15: Receivables
B16: Trade Receivables
B17: Other Receivables | C17: ='Historical B_Sheet'!C15 -> 577.05 | D17: ='Historical B_Sheet'!D15 -> 230.41 | E17: ='Historical B_Sheet'!E15 -> 262.69 | F17: ='Historical B_Sheet'!F15 -> 252.58 | G17: ='Historical B_Sheet'!G15 -> 199.46 | H17: =Balance_Sheet_Forecast!H11 -> 716.76127 | I17: =Balance_Sheet_Forecast!I11 -> 990.71441 | J17: =Balance_Sheet_Forecast!J11 -> 1293.643 | K17: =Balance_Sheet_Forecast!K11 -> 1610.0864 | L17: =Balance_Sheet_Forecast!L11 -> 1925.1665 | M17: =Balance_Sheet_Forecast!M11 -> 2226.5573 | N17: =Balance_Sheet_Forecast!N11 -> 2505.4169 | O17: =Balance_Sheet_Forecast!O11 -> 2756.4446 | ... Q17: =Balance_Sheet_Forecast!Q11 -> 3168.3104
B18: Investments in associates accounted for using the equity method | C18: ='Historical B_Sheet'!C16 -> 0 | D18: ='Historical B_Sheet'!D16 -> 229117.91 | E18: ='Historical B_Sheet'!E16 -> 262650.13 | F18: ='Historical B_Sheet'!F16 -> 281033.31 | G18: ='Historical B_Sheet'!G16 -> 304669.13 | H18: =Investment!H12 -> 326475.61 | I18: =Investment!I12 -> 350777.57 | J18: =Investment!J12 -> 377932.94 | K18: =Investment!K12 -> 408360.84 | L18: =Investment!L12 -> 442553.64 | M18: =Investment!M12 -> 481091.7 | N18: =Investment!N12 -> 524661.46 | O18: =Investment!O12 -> 574077.7 | ... Q18: =Investment!Q12 -> 694522.55
B19: Investments | C19: ='Historical B_Sheet'!C17 -> 216675.61 | D19: ='Historical B_Sheet'!D17 -> 44668.35 | E19: ='Historical B_Sheet'!E17 -> 43858.98 | F19: ='Historical B_Sheet'!F17 -> 45919.59 | G19: ='Historical B_Sheet'!G17 -> 48110.18 | H19: =Investment!H20 -> 49338.08 | I19: =Investment!I20 -> 50635.096 | J19: =Investment!J20 -> 52006.143 | K19: =Investment!K20 -> 53456.558 | L19: =Investment!L20 -> 54992.15 | M19: =Investment!M20 -> 56619.245 | N19: =Investment!N20 -> 58344.739 | O19: =Investment!O20 -> 60176.16 | ... Q19: =Investment!Q20 -> 64190.471
B20: Other Financial assets | C20: ='Historical B_Sheet'!C18 -> 1572.52 | D20: ='Historical B_Sheet'!D18 -> 609.68 | E20: ='Historical B_Sheet'!E18 -> 445.01 | F20: ='Historical B_Sheet'!F18 -> 227.74 | G20: ='Historical B_Sheet'!G18 -> 41.66 | H20: =Balance_Sheet_Forecast!H14 -> 1283.3158 | I20: =Balance_Sheet_Forecast!I14 -> 1773.8116 | J20: =Balance_Sheet_Forecast!J14 -> 2316.186 | K20: =Balance_Sheet_Forecast!K14 -> 2882.7581 | L20: =Balance_Sheet_Forecast!L14 -> 3446.889 | M20: =Balance_Sheet_Forecast!M14 -> 3986.5102 | N20: =Balance_Sheet_Forecast!N14 -> 4485.7906 | O20: =Balance_Sheet_Forecast!O14 -> 4935.2399 | ... Q20: =Balance_Sheet_Forecast!Q14 -> 5672.6596
B22: Total Financial Assets | C22: =SUM(C13:C20) -> 226473.8 | D22: =SUM(D13:D20) -> 274900.12 | E22: =SUM(E13:E20) -> 307617.57 | F22: =SUM(F13:F20) -> 327816.14 | G22: =SUM(G13:G20) -> 353172.38 | H22: =SUM(H13:H20) -> 380561.5 | I22: =SUM(I13:I20) -> 418517.49 | J22: =SUM(J13:J20) -> 467879.52 | ... Q22: =SUM(Q13:Q20) -> 1118805
B24: Non Financial Assets
B25: Current Tax assets (Net) | C25: ='Historical B_Sheet'!C23 -> 0 | D25: ='Historical B_Sheet'!D23 -> 105.2 | E25: ='Historical B_Sheet'!E23 -> 306.77 | F25: ='Historical B_Sheet'!F23 -> 533.01 | G25: ='Historical B_Sheet'!G23 -> 373.39 | H25: =Balance_Sheet_Forecast!H18 -> 723.47023 | I25: =Balance_Sheet_Forecast!I18 -> 999.9876 | J25: =Balance_Sheet_Forecast!J18 -> 1305.7516 | K25: =Balance_Sheet_Forecast!K18 -> 1625.157 | L25: =Balance_Sheet_Forecast!L18 -> 1943.1862 | M25: =Balance_Sheet_Forecast!M18 -> 2247.3981 | N25: =Balance_Sheet_Forecast!N18 -> 2528.8678 | O25: =Balance_Sheet_Forecast!O18 -> 2782.2452 | ... Q25: =Balance_Sheet_Forecast!Q18 -> 3197.9661
B26: Deferred Tax Asset (Net) | C26: ='Historical B_Sheet'!C24 -> 3913.66 | D26: ='Historical B_Sheet'!D24 -> 2415.08 | E26: ='Historical B_Sheet'!E24 -> 1813.25 | F26: ='Historical B_Sheet'!F24 -> 1098.4 | G26: ='Historical B_Sheet'!G24 -> 223.85 | H26: =Balance_Sheet_Forecast!H21 -> 330.79706 | I26: =Balance_Sheet_Forecast!I21 -> 457.23092 | J26: =Balance_Sheet_Forecast!J21 -> 597.03741 | K26: =Balance_Sheet_Forecast!K21 -> 743.08125 | L26: =Balance_Sheet_Forecast!L21 -> 888.49585 | M26: =Balance_Sheet_Forecast!M21 -> 1027.5926 | N26: =Balance_Sheet_Forecast!N21 -> 1156.2909 | O26: =Balance_Sheet_Forecast!O21 -> 1272.1443 | ... Q26: =Balance_Sheet_Forecast!Q21 -> 1462.2271
B27: Property, Plant and Equipment | C27: ='Historical B_Sheet'!C25 -> 321.67 | D27: ='Historical B_Sheet'!D25 -> 320.9 | E27: ='Historical B_Sheet'!E25 -> 320.18 | F27: ='Historical B_Sheet'!F25 -> 319.46 | G27: ='Historical B_Sheet'!G25 -> 318.74 | H27: =FSA!H13 -> 317.53357 | I27: =FSA!I13 -> 316.33171 | J27: =FSA!J13 -> 315.13439 | K27: =FSA!K13 -> 313.46891 | L27: =FSA!L13 -> 311.81223 | M27: =FSA!M13 -> 310.1643 | N27: =FSA!N13 -> 308.05984 | O27: =FSA!O13 -> 305.96965 | ... Q27: =FSA!Q13 -> 301.37589
B28: Other non-financial assets | C28: ='Historical B_Sheet'!C26 -> 24.73 | D28: ='Historical B_Sheet'!D26 -> 9.95 | E28: ='Historical B_Sheet'!E26 -> 11.88 | F28: ='Historical B_Sheet'!F26 -> 10.09 | G28: ='Historical B_Sheet'!G26 -> 10.94 | H28: =Balance_Sheet_Forecast!H24 -> 31.819695 | I28: =Balance_Sheet_Forecast!I24 -> 43.981493 | J28: =Balance_Sheet_Forecast!J24 -> 57.429617 | K28: =Balance_Sheet_Forecast!K24 -> 71.477718 | L28: =Balance_Sheet_Forecast!L24 -> 85.465292 | M28: =Balance_Sheet_Forecast!M24 -> 98.845149 | N28: =Balance_Sheet_Forecast!N24 -> 111.22476 | O28: =Balance_Sheet_Forecast!O24 -> 122.36881 | ... Q28: =Balance_Sheet_Forecast!Q24 -> 140.65307
B30: Total Non Financial Assets | C30: =SUM(C25:C28) -> 4260.06 | D30: =SUM(D25:D28) -> 2851.13 | E30: =SUM(E25:E28) -> 2452.08 | F30: =SUM(F25:F28) -> 1960.96 | G30: =SUM(G25:G28) -> 926.92 | H30: =SUM(H25:H28) -> 1403.6206 | I30: =SUM(I25:I28) -> 1817.5317 | J30: =SUM(J25:J28) -> 2275.353 | ... Q30: =SUM(Q25:Q28) -> 5102.2222
B32: TOTAL ASSETS | C32: =C30+C22 -> 230733.86 | D32: =D30+D22 -> 277751.25 | E32: =E30+E22 -> 310069.65 | F32: =F30+F22 -> 329777.1 | G32: =G30+G22 -> 354099.3 | H32: =H30+H22 -> 381965.12 | I32: =I30+I22 -> 420335.03 | J32: =J30+J22 -> 470154.87 | ... Q32: =Q30+Q22 -> 1123907.2
D33: =D32/C32-1 -> 0.20377326 | E33: =E32/D32-1 -> 0.11635735 | F33: =F32/E32-1 -> 0.063558139 | G33: =G32/F32-1 -> 0.073753453 | H33: =H32/G32-1 -> 0.078694937 | I33: =I32/H32-1 -> 0.10045395 | J33: =J32/I32-1 -> 0.11852413 | K33: =K32/J32-1 -> 0.13184534
B34: LIABILITIES AND EQUITY
B35: Liabilities
B36: Financial Liabilities
B37: Other financial liabilities | C37: ='Historical B_Sheet'!C39 -> 81.27 | D37: ='Historical B_Sheet'!D39 -> 18.35 | E37: ='Historical B_Sheet'!E39 -> 13.46 | F37: ='Historical B_Sheet'!F39 -> 16.6 | G37: ='Historical B_Sheet'!G39 -> 7 | H37: =Balance_Sheet_Forecast!H29 -> 56.349182 | I37: =Balance_Sheet_Forecast!I29 -> 77.886388 | J37: =Balance_Sheet_Forecast!J29 -> 101.70154 | K37: =Balance_Sheet_Forecast!K29 -> 126.57918 | L37: =Balance_Sheet_Forecast!L29 -> 151.34964 | M37: =Balance_Sheet_Forecast!M29 -> 175.04389 | N37: =Balance_Sheet_Forecast!N29 -> 196.96682 | O37: =Balance_Sheet_Forecast!O29 -> 216.70171 | ... Q37: =Balance_Sheet_Forecast!Q29 -> 249.08112
B39: Total Financial Liabilities | C39: =SUM(C37) -> 81.27 | D39: =SUM(D37) -> 18.35 | E39: =SUM(E37) -> 13.46 | F39: =SUM(F37) -> 16.6 | G39: =SUM(G37) -> 7 | H39: =SUM(H37) -> 56.349182 | I39: =SUM(I37) -> 77.886388 | J39: =SUM(J37) -> 101.70154 | ... Q39: =SUM(Q37) -> 249.08112
B41: Non Financial Liabilities
B42: Current tax liabilities (Net) | C42: ='Historical B_Sheet'!C44 -> 43.3 | D42: ='Historical B_Sheet'!D44 -> 0 | E42: ='Historical B_Sheet'!E44 -> 0 | F42: ='Historical B_Sheet'!F44 -> 0 | G42: ='Historical B_Sheet'!G44 -> 0 | H42: =G42 -> 0 | I42: =H42 -> 0 | J42: =I42 -> 0 | K42: =J42 -> 0 | L42: =K42 -> 0 | M42: =L42 -> 0 | N42: =M42 -> 0 | O42: =N42 -> 0 | ... Q42: =P42 -> 0
B43: Provisions | C43: ='Historical B_Sheet'!C45 -> 2.9 | D43: ='Historical B_Sheet'!D45 -> 1.55 | E43: ='Historical B_Sheet'!E45 -> 5.52 | F43: ='Historical B_Sheet'!F45 -> 3.11 | G43: ='Historical B_Sheet'!G45 -> 6.75 | H43: =Balance_Sheet_Forecast!H33 -> 11.016495 | I43: =Balance_Sheet_Forecast!I33 -> 15.227107 | J43: =Balance_Sheet_Forecast!J33 -> 19.883066 | K43: =Balance_Sheet_Forecast!K33 -> 24.746746 | L43: =Balance_Sheet_Forecast!L33 -> 29.589472 | M43: =Balance_Sheet_Forecast!M33 -> 34.221795 | N43: =Balance_Sheet_Forecast!N33 -> 38.507818 | O43: =Balance_Sheet_Forecast!O33 -> 42.36607 | ... Q43: =Balance_Sheet_Forecast!Q33 -> 48.696375
B44: Other non-financial liabilities | C44: ='Historical B_Sheet'!C46 -> 27.11 | D44: ='Historical B_Sheet'!D46 -> 47.65 | E44: ='Historical B_Sheet'!E46 -> 90.95 | F44: ='Historical B_Sheet'!F46 -> 40.09 | G44: ='Historical B_Sheet'!G46 -> 39.1 | H44: =Balance_Sheet_Forecast!H36 -> 152.62596 | I44: =Balance_Sheet_Forecast!I36 -> 210.96109 | J44: =Balance_Sheet_Forecast!J36 -> 275.4662 | K44: =Balance_Sheet_Forecast!K36 -> 342.84915 | L44: =Balance_Sheet_Forecast!L36 -> 409.94178 | M44: =Balance_Sheet_Forecast!M36 -> 474.11944 | N44: =Balance_Sheet_Forecast!N36 -> 533.49933 | O44: =Balance_Sheet_Forecast!O36 -> 586.95276 | ... Q44: =Balance_Sheet_Forecast!Q36 -> 674.65479
B46: Total Non Financial Liabilities | C46: =SUM(C42:C44) -> 73.31 | D46: =SUM(D42:D44) -> 49.2 | E46: =SUM(E42:E44) -> 96.47 | F46: =SUM(F42:F44) -> 43.2 | G46: =SUM(G42:G44) -> 45.85 | H46: =SUM(H42:H44) -> 163.64246 | I46: =SUM(I42:I44) -> 226.1882 | J46: =SUM(J42:J44) -> 295.34926 | ... Q46: =SUM(Q42:Q44) -> 723.35116
B48: Equity
B49: Equity Share Capital | C49: ='Historical B_Sheet'!C51 -> 319.24 | D49: ='Historical B_Sheet'!D51 -> 319.24 | E49: ='Historical B_Sheet'!E51 -> 319.24 | F49: ='Historical B_Sheet'!F51 -> 319.24 | G49: ='Historical B_Sheet'!G51 -> 319.24 | H49: =G49 -> 319.24 | I49: =H49 -> 319.24 | J49: =I49 -> 319.24 | K49: =J49 -> 319.24 | L49: =K49 -> 319.24 | M49: =L49 -> 319.24 | N49: =M49 -> 319.24 | O49: =N49 -> 319.24 | ... Q49: =P49 -> 319.24
B50: Other Equity | C50: ='Historical B_Sheet'!C52 -> 230260.04 | D50: ='Historical B_Sheet'!D52 -> 277364.46 | E50: ='Historical B_Sheet'!E52 -> 309640.48 | F50: ='Historical B_Sheet'!F52 -> 329398.06 | G50: ='Historical B_Sheet'!G52 -> 353727.21 | H50: =G50+'Income Statement'!H34-'Income Statement'!H37 -> 381425.89 | I50: =H50+'Income Statement'!I34-'Income Statement'!I37 -> 419711.71 | J50: =I50+'Income Statement'!J34-'Income Statement'!J37 -> 469438.58 | K50: =J50+'Income Statement'!K34-'Income Statement'!K37 -> 531329.18 | L50: =K50+'Income Statement'!L34-'Income Statement'!L37 -> 604935.89 | M50: =L50+'Income Statement'!M34-'Income Statement'!M37 -> 690066.2 | N50: =M50+'Income Statement'!N34-'Income Statement'!N37 -> 785343.28 | O50: =N50+'Income Statement'!O34-'Income Statement'!O37 -> 890166.77 | ... Q50: =P50+'Income Statement'!Q34-'Income Statement'!Q37 -> 1122615.5
B52: Total Equity | C52: =SUM(C49:C50) -> 230579.28 | D52: =SUM(D49:D50) -> 277683.7 | E52: =SUM(E49:E50) -> 309959.72 | F52: =SUM(F49:F50) -> 329717.3 | G52: =SUM(G49:G50) -> 354046.45 | H52: =SUM(H49:H50) -> 381745.13 | I52: =SUM(I49:I50) -> 420030.95 | J52: =SUM(J49:J50) -> 469757.82 | ... Q52: =SUM(Q49:Q50) -> 1122934.7
B54: TOTAL LIABILITIES AND EQUITY | C54: =C52+C46+C39 -> 230733.86 | D54: =D52+D46+D39 -> 277751.25 | E54: =E52+E46+E39 -> 310069.65 | F54: =F52+F46+F39 -> 329777.1 | G54: =G52+G46+G39 -> 354099.3 | H54: =H52+H46+H39 -> 381965.12 | I54: =I52+I46+I39 -> 420335.03 | J54: =J52+J46+J39 -> 470154.87 | ... Q54: =Q52+Q46+Q39 -> 1123907.2
B57: Check | C57: =C54-C32 -> 0 | D57: =D54-D32 -> 0 | E57: =E54-E32 -> 0 | F57: =F54-F32 -> 0 | G57: =G54-G32 -> 0 | H57: =H54-H32 -> 0 | I57: =I54-I32 -> 0 | J57: =J54-J32 -> 0 | ... Q57: =Q54-Q32 -> 0

Sheet Cash flow
B6: (All amounts in INR Lakhs, unless otherwise stated)
B7: Particulars | C7: 2021 | D7: =C7+1 -> 2022 | E7: =D7+1 -> 2023 | F7: =E7+1 -> 2024 | G7: =F7+1 -> 2025 | H7: =G7+1 -> 2026 | I7: =H7+1 -> 2027 | J7: =I7+1 -> 2028 | K7: =J7+1 -> 2029 | ... Q7: =P7+1 -> 2035
B9: CASH FLOW FROM OPERATING ACTIVITIES
B10: Net Profit before tax and extraordinary items | C10: 13321.43 | D10: 45947.12 | E10: 22492.1 | F10: 19424.02 | G10: 27297.39 | H10: ='Income Statement'!H30 -> 29614.304 | I10: ='Income Statement'!I30 -> 40933.645 | J10: ='Income Statement'!J30 -> 53450.207 | K10: ='Income Statement'!K30 -> 66524.713 | L10: ='Income Statement'!L30 -> 79543.361 | M10: ='Income Statement'!M30 -> 91996.39 | N10: ='Income Statement'!N30 -> 103518 | O10: ='Income Statement'!O30 -> 113890.1 | ... Q10: ='Income Statement'!Q30 -> 130907.36
B11: Adjustments for :
B12: Depreciation and amortization | C12: 0.88 | D12: 0.77 | E12: 0.72 | F12: 0.72 | G12: 0.72 | H12: ='Income Statement'!H22 -> 1.2064298 | I12: ='Income Statement'!I22 -> 1.2018634 | J12: ='Income Statement'!J22 -> 1.1973144 | K12: ='Income Statement'!K22 -> 1.6654841 | L12: ='Income Statement'!L22 -> 1.6566821 | M12: ='Income Statement'!M22 -> 1.6479265 | N12: ='Income Statement'!N22 -> 2.1044637 | O12: ='Income Statement'!O22 -> 2.0901849 | ... Q12: ='Income Statement'!Q22 -> 2.5177578
B13: Income from associates | C13: -11446.14 | D13: -42760.92 | E13: -22153.14 | F13: -18121.32 | G13: -25453.08 | H13: =-'Income Statement'!H27 -> -26806.142 | I13: =-'Income Statement'!I27 -> -37051.711 | J13: =-'Income Statement'!J27 -> -48380.93 | K13: =-'Income Statement'!K27 -> -60215.595 | L13: =-'Income Statement'!L27 -> -71999.268 | M13: =-'Income Statement'!M27 -> -83270.977 | N13: =-'Income Statement'!N27 -> -93700.041 | O13: =-'Income Statement'!O27 -> -103088.22 | ... Q13: =-'Income Statement'!Q27 -> -118491.58
B14: Net (Profit)/Loss on sale of Current Investments | C14: -579.16 | D14: -838.7 | E14: -59.77 | F14: -1158.21 | G14: -1932.81
B15: Fair Valuation (Gain)/Loss on Current Investments | C15: -613.06 | D15: -1812.89
B16: Provision for Expected Credit Losses (ECL) | G16: 13.89
B17: Excess Income Written Off | F17: 46.23 | G17: 181.97
B18: Provisions no longer required written Back | F18: -4.62 | G18: -0.97
B20: Operating profit before working capital changes | C20: =SUM(C10:C19) -> 683.95 | D20: =SUM(D10:D19) -> 535.38 | E20: =SUM(E10:E19) -> 279.91 | F20: =SUM(F10:F19) -> 186.82 | G20: =SUM(G10:G19) -> 107.11 | H20: =SUM(H10:H19) -> 2809.3682 | I20: =SUM(I10:I19) -> 3883.1361 | J20: =SUM(J10:J19) -> 5070.474 | ... Q20: =SUM(Q10:Q19) -> 12418.292
B21: Adjustments for :
B22: (Increase)/Decrease in financial assets | D22: 1081.93 | E22: 132.39 | F22: 181.15 | G22: 43.34 | H22: =SUM('Balance Sheet'!G17,'Balance Sheet'!G20)-SUM('Balance Sheet'!H17,'Balance Sheet'!H20) -> -1758.9571 | I22: =SUM('Balance Sheet'!H17,'Balance Sheet'!H20)-SUM('Balance Sheet'!I17,'Balance Sheet'!I20) -> -764.44892 | J22: =SUM('Balance Sheet'!I17,'Balance Sheet'!I20)-SUM('Balance Sheet'!J17,'Balance Sheet'!J20) -> -845.30299 | K22: =SUM('Balance Sheet'!J17,'Balance Sheet'!J20)-SUM('Balance Sheet'!K17,'Balance Sheet'!K20) -> -883.01554 | L22: =SUM('Balance Sheet'!K17,'Balance Sheet'!K20)-SUM('Balance Sheet'!L17,'Balance Sheet'!L20) -> -879.21096 | M22: =SUM('Balance Sheet'!L17,'Balance Sheet'!L20)-SUM('Balance Sheet'!M17,'Balance Sheet'!M20) -> -841.01198 | N22: =SUM('Balance Sheet'!M17,'Balance Sheet'!M20)-SUM('Balance Sheet'!N17,'Balance Sheet'!N20) -> -778.14001 | O22: =SUM('Balance Sheet'!N17,'Balance Sheet'!N20)-SUM('Balance Sheet'!O17,'Balance Sheet'!O20) -> -700.47696 | ... Q22: =SUM('Balance Sheet'!P17,'Balance Sheet'!P20)-SUM('Balance Sheet'!Q17,'Balance Sheet'!Q20) -> -532.75711
B23: (Increase)/Decrease in non financial assets | C23: 8146.86 | D23: 14.78 | E23: -1.93 | F23: 1.79 | G23: -0.85 | H23: =SUM('Balance Sheet'!G25:G26,'Balance Sheet'!G28)-SUM('Balance Sheet'!H25:H26,'Balance Sheet'!H28) -> -477.90699 | I23: =SUM('Balance Sheet'!H25:H26,'Balance Sheet'!H28)-SUM('Balance Sheet'!I25:I26,'Balance Sheet'!I28) -> -415.11302 | J23: =SUM('Balance Sheet'!I25:I26,'Balance Sheet'!I28)-SUM('Balance Sheet'!J25:J26,'Balance Sheet'!J28) -> -459.01861 | K23: =SUM('Balance Sheet'!J25:J26,'Balance Sheet'!J28)-SUM('Balance Sheet'!K25:K26,'Balance Sheet'!K28) -> -479.49737 | L23: =SUM('Balance Sheet'!K25:K26,'Balance Sheet'!K28)-SUM('Balance Sheet'!L25:L26,'Balance Sheet'!L28) -> -477.4314 | M23: =SUM('Balance Sheet'!L25:L26,'Balance Sheet'!L28)-SUM('Balance Sheet'!M25:M26,'Balance Sheet'!M28) -> -456.68849 | N23: =SUM('Balance Sheet'!M25:M26,'Balance Sheet'!M28)-SUM('Balance Sheet'!N25:N26,'Balance Sheet'!N28) -> -422.54759 | O23: =SUM('Balance Sheet'!N25:N26,'Balance Sheet'!N28)-SUM('Balance Sheet'!O25:O26,'Balance Sheet'!O28) -> -380.3748 | ... Q23: =SUM('Balance Sheet'!P25:P26,'Balance Sheet'!P28)-SUM('Balance Sheet'!Q25:Q26,'Balance Sheet'!Q28) -> -289.29914
B24: Increase/(Decrease) in financial liabilities | D24: 62.92 | E24: -4.89 | F24: 7.76 | G24: -8.63 | H24: ='Balance Sheet'!H37-'Balance Sheet'!G37 -> 49.349182 | I24: ='Balance Sheet'!I37-'Balance Sheet'!H37 -> 21.537206 | J24: ='Balance Sheet'!J37-'Balance Sheet'!I37 -> 23.815149 | K24: ='Balance Sheet'!K37-'Balance Sheet'!J37 -> 24.877643 | L24: ='Balance Sheet'!L37-'Balance Sheet'!K37 -> 24.770455 | M24: ='Balance Sheet'!M37-'Balance Sheet'!L37 -> 23.694256 | N24: ='Balance Sheet'!N37-'Balance Sheet'!M37 -> 21.922932 | O24: ='Balance Sheet'!O37-'Balance Sheet'!N37 -> 19.734892 | ... Q24: ='Balance Sheet'!Q37-'Balance Sheet'!P37 -> 15.009636
B25: Increase/(Decrease) in non financial liabilities | C25: -259.43 | D25: -20.54 | E25: -4.58 | F25: -53.4 | G25: 3.3 | H25: =SUM('Balance Sheet'!H42:H44)-SUM('Balance Sheet'!G42:G44) -> 117.79246 | I25: =SUM('Balance Sheet'!I42:I44)-SUM('Balance Sheet'!H42:H44) -> 62.545741 | J25: =SUM('Balance Sheet'!J42:J44)-SUM('Balance Sheet'!I42:I44) -> 69.161065 | K25: =SUM('Balance Sheet'!K42:K44)-SUM('Balance Sheet'!J42:J44) -> 72.246633 | L25: =SUM('Balance Sheet'!L42:L44)-SUM('Balance Sheet'!K42:K44) -> 71.93535 | M25: =SUM('Balance Sheet'!M42:M44)-SUM('Balance Sheet'!L42:L44) -> 68.809983 | N25: =SUM('Balance Sheet'!N42:N44)-SUM('Balance Sheet'!M42:M44) -> 63.66592 | O25: =SUM('Balance Sheet'!O42:O44)-SUM('Balance Sheet'!N42:N44) -> 57.311678 | ... Q25: =SUM('Balance Sheet'!Q42:Q44)-SUM('Balance Sheet'!P42:P44) -> 43.589162
B27: Cash Generation from Operations | C27: =SUM(C20:C25) -> 8571.38 | D27: =SUM(D20:D25) -> 1674.47 | E27: =SUM(E20:E25) -> 400.9 | F27: =SUM(F20:F25) -> 324.12 | G27: =SUM(G20:G25) -> 144.27 | H27: =SUM(H20:H25) -> 739.64582 | I27: =SUM(I20:I25) -> 2787.6571 | J27: =SUM(J20:J25) -> 3859.1287 | ... Q27: =SUM(Q20:Q25) -> 11654.834
B28: Taxes Paid | C28: -357.11 | D28: -2173.74 | E28: -272.44 | F28: -613.24 | G28: -694.01 | H28: =-'Income Statement'!H32 -> -1772.1537 | I28: =-'Income Statement'!I32 -> -2449.516 | J28: =-'Income Statement'!J32 -> -3465.7724 | K28: =-'Income Statement'!K32 -> -4313.5383 | L28: =-'Income Statement'!L32 -> -5555.3991 | M28: =-'Income Statement'!M32 -> -6425.1328 | N28: =-'Income Statement'!N32 -> -7747.4049 | O28: =-'Income Statement'!O32 -> -8523.6651 | ... Q28: =-'Income Statement'!Q32 -> -10451.793
B30: Net Cash flow from / (used in) Operating activities | C30: =SUM(C27:C28) -> 8214.27 | D30: =SUM(D27:D28) -> -499.27 | E30: =SUM(E27:E28) -> 128.46 | F30: =SUM(F27:F28) -> -289.12 | G30: =SUM(G27:G28) -> -549.74 | H30: =SUM(H27:H28) -> -1032.5079 | I30: =SUM(I27:I28) -> 338.1411 | J30: =SUM(J27:J28) -> 393.35626 | ... Q30: =SUM(Q27:Q28) -> 1203.0414
B32: CASH FLOW FROM INVESTING ACTIVITIES
B33: Purchase of Investments in Associates | C33: -8909.84 | D33: -70.86 | E33: -9506.72 | F33: -3038.3 | G33: -1245.5 | H33: ='Balance Sheet'!G18-'Balance Sheet'!H18 -> -21806.485 | I33: ='Balance Sheet'!H18-'Balance Sheet'!I18 -> -24301.96 | J33: ='Balance Sheet'!I18-'Balance Sheet'!J18 -> -27155.369 | K33: ='Balance Sheet'!J18-'Balance Sheet'!K18 -> -30427.9 | L33: ='Balance Sheet'!K18-'Balance Sheet'!L18 -> -34192.799 | M33: ='Balance Sheet'!L18-'Balance Sheet'!M18 -> -38538.058 | N33: ='Balance Sheet'!M18-'Balance Sheet'!N18 -> -43569.754 | O33: ='Balance Sheet'!N18-'Balance Sheet'!O18 -> -49416.245 | ... Q33: ='Balance Sheet'!P18-'Balance Sheet'!Q18 -> -64211.415
B34: Purchase of Investments (other than associate) | D34: -18525.04 | E34: -23768.04 | F34: -10597.06 | G34: -12227.71 | H34: ='Balance Sheet'!G19-'Balance Sheet'!H19 -> -1227.9 | I34: ='Balance Sheet'!H19-'Balance Sheet'!I19 -> -1297.0165 | J34: ='Balance Sheet'!I19-'Balance Sheet'!J19 -> -1371.0463 | K34: ='Balance Sheet'!J19-'Balance Sheet'!K19 -> -1450.4152 | L34: ='Balance Sheet'!K19-'Balance Sheet'!L19 -> -1535.5923 | M34: ='Balance Sheet'!L19-'Balance Sheet'!M19 -> -1627.0948 | N34: ='Balance Sheet'!M19-'Balance Sheet'!N19 -> -1725.494 | O34: ='Balance Sheet'!N19-'Balance Sheet'!O19 -> -1831.4215 | ... Q34: ='Balance Sheet'!P19-'Balance Sheet'!Q19 -> -2068.7339
B35: Sale of Investments | C35: 7867.96 | D35: 11738.56 | E35: 33385.14 | F35: 11158.8 | G35: 10618.74
B36: Dividend received during the year from associate | F36: 2908.06 | G36: 3333.7
B37: Advance received against sale of land | E37: 47.64
B38: Income from associates | H38: ='Income Statement'!H27 -> 26806.142 | I38: ='Income Statement'!I27 -> 37051.711 | J38: ='Income Statement'!J27 -> 48380.93 | K38: ='Income Statement'!K27 -> 60215.595 | L38: ='Income Statement'!L27 -> 71999.268 | M38: ='Income Statement'!M27 -> 83270.977 | N38: ='Income Statement'!N27 -> 93700.041 | O38: ='Income Statement'!O27 -> 103088.22 | ... Q38: ='Income Statement'!Q27 -> 118491.58
B39: (Increase)/Decrease in Bank Balances not considered as cash and cash equivalents | D39: -1.64 | E39: 46.76 | F39: 7.8 | G39: -4.55 | H39: ='Balance Sheet'!G14-'Balance Sheet'!H14 -> 0 | I39: ='Balance Sheet'!H14-'Balance Sheet'!I14 -> 0 | J39: ='Balance Sheet'!I14-'Balance Sheet'!J14 -> 0 | K39: ='Balance Sheet'!J14-'Balance Sheet'!K14 -> 0 | L39: ='Balance Sheet'!K14-'Balance Sheet'!L14 -> 0 | M39: ='Balance Sheet'!L14-'Balance Sheet'!M14 -> 0 | N39: ='Balance Sheet'!M14-'Balance Sheet'!N14 -> 0 | O39: ='Balance Sheet'!N14-'Balance Sheet'!O14 -> 0 | ... Q39: ='Balance Sheet'!P14-'Balance Sheet'!Q14 -> 0
B41: Net Cash flow from / (used in) investing activities | C41: =SUM(C33:C39) -> -1041.88 | D41: =SUM(D33:D39) -> -6858.98 | E41: =SUM(E33:E39) -> 204.78 | F41: =SUM(F33:F39) -> 439.3 | G41: =SUM(G33:G39) -> 474.68 | H41: =SUM(H33:H39) -> 3771.7575 | I41: =SUM(I33:I39) -> 11452.735 | J41: =SUM(J33:J39) -> 19854.515 | ... Q41: =SUM(Q33:Q39) -> 52211.435
B43: CASH FLOW FROM FINANCING ACTIVITIES
B44: Dividend Paid (including tax thereon) | C44: -2.31 | D44: -159.58 | E44: -159.49 | F44: -160.22 | G44: -160.46 | H44: =-'Income Statement'!H37 -> -143.46977 | I44: =-'Income Statement'!I37 -> -198.30757 | J44: =-'Income Statement'!J37 -> -257.5683 | K44: =-'Income Statement'!K37 -> -320.57233 | L44: =-'Income Statement'!L37 -> -381.25776 | M44: =-'Income Statement'!M37 -> -440.94613 | N44: =-'Income Statement'!N37 -> -493.503 | O44: =-'Income Statement'!O37 -> -542.9501 | ... Q44: =-'Income Statement'!Q37 -> -620.70393
B46: Net Cash flow from / (used in) Financing Activities | C46: =SUM(C44) -> -2.31 | D46: =SUM(D44) -> -159.58 | E46: =SUM(E44) -> -159.49 | F46: =SUM(F44) -> -160.22 | G46: =SUM(G44) -> -160.46 | H46: =SUM(H44) -> -143.46977 | I46: =SUM(I44) -> -198.30757 | J46: =SUM(J44) -> -257.5683 | ... Q46: =SUM(Q44) -> -620.70393
B48: Net Increase in cash & cash equivalents | C48: =C46+C41+C30 -> 7170.08 | D48: =D46+D41+D30 -> -7517.83 | E48: =E46+E41+E30 -> 173.75 | F48: =F46+F41+F30 -> -10.04 | G48: =G46+G41+G30 -> -235.52 | H48: =H46+H41+H30 -> 2595.7798 | I48: =I46+I41+I30 -> 11592.568 | J48: =J46+J41+J30 -> 19990.303 | ... Q48: =Q46+Q41+Q30 -> 52793.772
B49: Cash & cash equivalents as at the beginning | C49: 468.75 | D49: =C50 -> 7638.83 | E49: =D50 -> 120.99 | F49: =E50 -> 294.74 | G49: =F50 -> 284.7 | H49: =G50 -> 49.18 | I49: =H50 -> 2644.9598 | J49: =I50 -> 14237.528 | K49: =J50 -> 34227.831 | ... Q49: =P50 -> 298354.42
B50: Cash & cash equivalents as at the end | C50: =SUM(C48:C49) -> 7638.83 | D50: 120.99 | E50: =SUM(E48:E49) -> 294.74 | F50: =SUM(F48:F49) -> 284.7 | G50: =SUM(G48:G49) -> 49.18 | H50: =SUM(H48:H49) -> 2644.9598 | I50: =SUM(I48:I49) -> 14237.528 | J50: =SUM(J48:J49) -> 34227.831 | K50: =SUM(K48:K49) -> 62976.395 | L50: =SUM(L48:L49) -> 99596.428 | ... Q50: =SUM(Q48:Q49) -> 351148.2

Sheet CommonSize Statement
B7: Common Size Statement
B8: Income Statement
B9: Particulars | C9: 2021 | D9: =C9+1 -> 2022 | E9: =D9+1 -> 2023 | F9: =E9+1 -> 2024 | G9: =F9+1 -> 2025 | H9: =G9+1 -> 2026 | I9: =H9+1 -> 2027 | J9: =I9+1 -> 2028 | K9: =J9+1 -> 2029 | ... Q9: =P9+1 -> 2035
B11: Revenue from operations
B12: Interest Income | C12: ='Income Statement'!C10/'Income Statement'!C$13 -> 0.39419058 | D12: ='Income Statement'!D10/'Income Statement'!D$13 -> 0.11897127 | E12: ='Income Statement'!E10/'Income Statement'!E$13 -> 0.57048177 | F12: ='Income Statement'!F10/'Income Statement'!F$13 -> 0.069034245 | G12: ='Income Statement'!G10/'Income Statement'!G$13 -> 0.052458268 | H12: ='Income Statement'!H10/'Income Statement'!H$13 -> 0.24102723 | I12: ='Income Statement'!I10/'Income Statement'!I$13 -> 0.24102723 | J12: ='Income Statement'!J10/'Income Statement'!J$13 -> 0.24102723 | ... Q12: ='Income Statement'!Q10/'Income Statement'!Q$13 -> 0.24102723
B13: Dividend Income | C13: ='Income Statement'!C11/'Income Statement'!C$13 -> 0.0032246489 | D13: ='Income Statement'!D11/'Income Statement'!D$13 -> 0.07968691 | E13: ='Income Statement'!E11/'Income Statement'!E$13 -> 0.3279463 | F13: ='Income Statement'!F11/'Income Statement'!F$13 -> 0.15371142 | G13: ='Income Statement'!G11/'Income Statement'!G$13 -> 0.098932219 | H13: ='Income Statement'!H11/'Income Statement'!H$13 -> 0.1327003 | I13: ='Income Statement'!I11/'Income Statement'!I$13 -> 0.1327003 | J13: ='Income Statement'!J11/'Income Statement'!J$13 -> 0.1327003 | ... Q13: ='Income Statement'!Q11/'Income Statement'!Q$13 -> 0.1327003
B14: Net gain on fair value changes | C14: ='Income Statement'!C12/'Income Statement'!C$13 -> 0.60258477 | D14: ='Income Statement'!D12/'Income Statement'!D$13 -> 0.80134182 | E14: ='Income Statement'!E12/'Income Statement'!E$13 -> 0.10157193 | F14: ='Income Statement'!F12/'Income Statement'!F$13 -> 0.77725433 | G14: ='Income Statement'!G12/'Income Statement'!G$13 -> 0.84860951 | H14: ='Income Statement'!H12/'Income Statement'!H$13 -> 0.62627247 | I14: ='Income Statement'!I12/'Income Statement'!I$13 -> 0.62627247 | J14: ='Income Statement'!J12/'Income Statement'!J$13 -> 0.62627247 | ... Q14: ='Income Statement'!Q12/'Income Statement'!Q$13 -> 0.62627247
B15: Total Revenue from operations | C15: ='Income Statement'!C13/'Income Statement'!C$13 -> 1 | D15: ='Income Statement'!D13/'Income Statement'!D$13 -> 1 | E15: ='Income Statement'!E13/'Income Statement'!E$13 -> 1 | F15: ='Income Statement'!F13/'Income Statement'!F$13 -> 1 | G15: ='Income Statement'!G13/'Income Statement'!G$13 -> 1 | H15: ='Income Statement'!H13/'Income Statement'!H$13 -> 1 | I15: ='Income Statement'!I13/'Income Statement'!I$13 -> 1 | J15: ='Income Statement'!J13/'Income Statement'!J$13 -> 1 | ... Q15: ='Income Statement'!Q13/'Income Statement'!Q$13 -> 1
B17: Expenses
B18: Employee benefits expenses | C18: ='Income Statement'!C16/'Income Statement'!C$13 -> 0.028359725 | D18: ='Income Statement'!D16/'Income Statement'!D$13 -> 0.024729899 | E18: ='Income Statement'!E16/'Income Statement'!E$13 -> 0.21160676 | F18: ='Income Statement'!F16/'Income Statement'!F$13 -> 0.032453544 | G18: ='Income Statement'!G16/'Income Statement'!G$13 -> 0.027225788 | H18: ='Income Statement'!H16/'Income Statement'!H$13 -> 0.064875144 | I18: ='Income Statement'!I16/'Income Statement'!I$13 -> 0.064875144 | J18: ='Income Statement'!J16/'Income Statement'!J$13 -> 0.064875144 | ... Q18: ='Income Statement'!Q16/'Income Statement'!Q$13 -> 0.064875144
B19: Other expenses | C19: ='Income Statement'!C17/'Income Statement'!C$13 -> 0.086388242 | D19: ='Income Statement'!D17/'Income Statement'!D$13 -> 0.068181749 | E19: ='Income Statement'!E17/'Income Statement'!E$13 -> 0.53092021 | F19: ='Income Statement'!F17/'Income Statement'!F$13 -> 0.25874924 | G19: ='Income Statement'!G17/'Income Statement'!G$13 -> 0.24421984 | H19: ='Income Statement'!H17/'Income Statement'!H$13 -> 0.23769186 | I19: ='Income Statement'!I17/'Income Statement'!I$13 -> 0.23769186 | J19: ='Income Statement'!J17/'Income Statement'!J$13 -> 0.23769186 | ... Q19: ='Income Statement'!Q17/'Income Statement'!Q$13 -> 0.23769186
B20: Total Expenses | C20: ='Income Statement'!C18/'Income Statement'!C$13 -> 0.11474797 | D20: ='Income Statement'!D18/'Income Statement'!D$13 -> 0.092911649 | E20: ='Income Statement'!E18/'Income Statement'!E$13 -> 0.74252698 | F20: ='Income Statement'!F18/'Income Statement'!F$13 -> 0.29120278 | G20: ='Income Statement'!G18/'Income Statement'!G$13 -> 0.27144563 | H20: ='Income Statement'!H18/'Income Statement'!H$13 -> 0.302567 | I20: ='Income Statement'!I18/'Income Statement'!I$13 -> 0.302567 | J20: ='Income Statement'!J18/'Income Statement'!J$13 -> 0.302567 | ... Q20: ='Income Statement'!Q18/'Income Statement'!Q$13 -> 0.302567
B22: EBITDA | C22: ='Income Statement'!C20/'Income Statement'!C$13 -> 0.88525203 | D22: ='Income Statement'!D20/'Income Statement'!D$13 -> 0.90708835 | E22: ='Income Statement'!E20/'Income Statement'!E$13 -> 0.25747302 | F22: ='Income Statement'!F20/'Income Statement'!F$13 -> 0.70879722 | G22: ='Income Statement'!G20/'Income Statement'!G$13 -> 0.72855437 | H22: ='Income Statement'!H20/'Income Statement'!H$13 -> 0.697433 | I22: ='Income Statement'!I20/'Income Statement'!I$13 -> 0.697433 | J22: ='Income Statement'!J20/'Income Statement'!J$13 -> 0.697433 | ... Q22: ='Income Statement'!Q20/'Income Statement'!Q$13 -> 0.697433
B24: D&A | C24: ='Income Statement'!C22/'Income Statement'!C$13 -> 0.00044477915 | D24: ='Income Statement'!D22/'Income Statement'!D$13 -> 0.00023270222 | E24: ='Income Statement'!E22/'Income Statement'!E$13 -> 0.0012235534 | F24: ='Income Statement'!F22/'Income Statement'!F$13 -> 0.00048317932 | G24: ='Income Statement'!G22/'Income Statement'!G$13 -> 0.00031611946 | H24: ='Income Statement'!H22/'Income Statement'!H$13 -> 0.0003584398 | I24: ='Income Statement'!I22/'Income Statement'!I$13 -> 0.0002583422 | J24: ='Income Statement'!J22/'Income Statement'!J$13 -> 0.00019709812 | ... Q24: ='Income Statement'!Q22/'Income Statement'!Q$13 -> 0.00016922906
B26: EBIT | C26: ='Income Statement'!C24/'Income Statement'!C$13 -> 0.88480725 | D26: ='Income Statement'!D24/'Income Statement'!D$13 -> 0.90685565 | E26: ='Income Statement'!E24/'Income Statement'!E$13 -> 0.25624947 | F26: ='Income Statement'!F24/'Income Statement'!F$13 -> 0.70831404 | G26: ='Income Statement'!G24/'Income Statement'!G$13 -> 0.72823825 | H26: ='Income Statement'!H24/'Income Statement'!H$13 -> 0.69707456 | I26: ='Income Statement'!I24/'Income Statement'!I$13 -> 0.69717466 | J26: ='Income Statement'!J24/'Income Statement'!J$13 -> 0.6972359 | ... Q26: ='Income Statement'!Q24/'Income Statement'!Q$13 -> 0.69726377
B28: other income | C28: ='Income Statement'!C26/'Income Statement'!C$13 -> 0.063022173 | D28: ='Income Statement'!D26/'Income Statement'!D$13 -> 0.056047991 | E28: ='Income Statement'!E26/'Income Statement'!E$13 -> 0.31977228 | F28: ='Income Statement'!F26/'Income Statement'!F$13 -> 0.16590499 | G28: ='Income Statement'!G26/'Income Statement'!G$13 -> 0.081514915 | H28: ='Income Statement'!H26/'Income Statement'!H$13 -> 0.13725247 | I28: ='Income Statement'!I26/'Income Statement'!I$13 -> 0.13725247 | J28: ='Income Statement'!J26/'Income Statement'!J$13 -> 0.13725247 | ... Q28: ='Income Statement'!Q26/'Income Statement'!Q$13 -> 0.13725247
B29: Share of Profit of Associates | C29: ='Income Statement'!C27/'Income Statement'!C$13 -> 5.7852323 | D29: ='Income Statement'!D27/'Income Statement'!D$13 -> 12.922806 | E29: ='Income Statement'!E27/'Income Statement'!E$13 -> 37.646597 | F29: ='Income Statement'!F27/'Income Statement'!F$13 -> 12.160899 | G29: ='Income Statement'!G27/'Income Statement'!G$13 -> 11.175297 | H29: ='Income Statement'!H27/'Income Statement'!H$13 -> 7.9643164 | I29: ='Income Statement'!I27/'Income Statement'!I$13 -> 7.9643164 | J29: ='Income Statement'!J27/'Income Statement'!J$13 -> 7.9643164 | ... Q29: ='Income Statement'!Q27/'Income Statement'!Q$13 -> 7.9643164
B30: EBT | C30: ='Income Statement'!C30/'Income Statement'!C$13 -> 6.7330617 | D30: ='Income Statement'!D30/'Income Statement'!D$13 -> 13.88571 | E30: ='Income Statement'!E30/'Income Statement'!E$13 -> 38.222619 | F30: ='Income Statement'!F30/'Income Statement'!F$13 -> 13.035118 | G30: ='Income Statement'!G30/'Income Statement'!G$13 -> 11.98505 | H30: ='Income Statement'!H30/'Income Statement'!H$13 -> 8.7986434 | I30: ='Income Statement'!I30/'Income Statement'!I$13 -> 8.7987435 | J30: ='Income Statement'!J30/'Income Statement'!J$13 -> 8.7988048 | ... Q30: ='Income Statement'!Q30/'Income Statement'!Q$13 -> 8.7988326
B32: Tax | C32: ='Income Statement'!C32/'Income Statement'!C$13 -> 0.18715094 | D32: ='Income Statement'!D32/'Income Statement'!D$13 -> 0.91850889 | E32: ='Income Statement'!E32/'Income Statement'!E$13 -> -0.59675418 | F32: ='Income Statement'!F32/'Income Statement'!F$13 -> 0.62810627 | G32: ='Income Statement'!G32/'Income Statement'!G$13 -> 0.65727382 | H32: ='Income Statement'!H32/'Income Statement'!H$13 -> 0.52652086 | I32: ='Income Statement'!I32/'Income Statement'!I$13 -> 0.52652685 | J32: ='Income Statement'!J32/'Income Statement'!J$13 -> 0.57052454 | ... Q32: ='Income Statement'!Q32/'Income Statement'!Q$13 -> 0.70250883
B34: Net Profit | C34: ='Income Statement'!C34/'Income Statement'!C$13 -> 6.5459108 | D34: ='Income Statement'!D34/'Income Statement'!D$13 -> 12.967201 | E34: ='Income Statement'!E34/'Income Statement'!E$13 -> 38.819373 | F34: ='Income Statement'!F34/'Income Statement'!F$13 -> 12.407011 | G34: ='Income Statement'!G34/'Income Statement'!G$13 -> 11.327776 | H34: ='Income Statement'!H34/'Income Statement'!H$13 -> 8.2721226 | I34: ='Income Statement'!I34/'Income Statement'!I$13 -> 8.2722167 | J34: ='Income Statement'!J34/'Income Statement'!J$13 -> 8.2282802 | ... Q34: ='Income Statement'!Q34/'Income Statement'!Q$13 -> 8.0963238
B36: Balance Sheet
B37: Assets
B38: Financial Assets
B39: Cash and bank balances | C39: ='Balance Sheet'!C13/'Balance Sheet'!C$32 -> 0.033106671 | D39: ='Balance Sheet'!D13/'Balance Sheet'!D$32 -> 0.0004356056 | E39: ='Balance Sheet'!E13/'Balance Sheet'!E$32 -> 0.00095056062 | F39: ='Balance Sheet'!F13/'Balance Sheet'!F$32 -> 0.0008633104 | G39: ='Balance Sheet'!G13/'Balance Sheet'!G$32 -> 0.00013888759 | H39: ='Balance Sheet'!H13/'Balance Sheet'!H$32 -> 0.0069246107 | I39: ='Balance Sheet'!I13/'Balance Sheet'!I$32 -> 0.033871857 | J39: ='Balance Sheet'!J13/'Balance Sheet'!J$32 -> 0.072801183 | ... Q39: ='Balance Sheet'!Q13/'Balance Sheet'!Q$32 -> 0.31243523
B40: Bank Balances | C40: ='Balance Sheet'!C14/'Balance Sheet'!C$32 -> 4.2429837e-05 | D40: ='Balance Sheet'!D14/'Balance Sheet'!D$32 -> 0.00055006053 | E40: ='Balance Sheet'!E14/'Balance Sheet'!E$32 -> 0.00034192318 | F40: ='Balance Sheet'!F14/'Balance Sheet'!F$32 -> 0.00029783754 | G40: ='Balance Sheet'!G14/'Balance Sheet'!G$32 -> 0.00029022932 | H40: ='Balance Sheet'!H14/'Balance Sheet'!H$32 -> 0.00026905598 | I40: ='Balance Sheet'!I14/'Balance Sheet'!I$32 -> 0.00024449545 | J40: ='Balance Sheet'!J14/'Balance Sheet'!J$32 -> 0.00021858755 | ... Q40: ='Balance Sheet'!Q14/'Balance Sheet'!Q$32 -> 9.1439936e-05
B41: Receivables
B42: Trade Receivables | C42: ='Balance Sheet'!C16/'Balance Sheet'!C$32 -> 0 | D42: ='Balance Sheet'!D16/'Balance Sheet'!D$32 -> 0 | E42: ='Balance Sheet'!E16/'Balance Sheet'!E$32 -> 0 | F42: ='Balance Sheet'!F16/'Balance Sheet'!F$32 -> 0 | G42: ='Balance Sheet'!G16/'Balance Sheet'!G$32 -> 0 | H42: ='Balance Sheet'!H16/'Balance Sheet'!H$32 -> 0 | I42: ='Balance Sheet'!I16/'Balance Sheet'!I$32 -> 0 | J42: ='Balance Sheet'!J16/'Balance Sheet'!J$32 -> 0 | ... Q42: ='Balance Sheet'!Q16/'Balance Sheet'!Q$32 -> 0
B43: Other Receivables | C43: ='Balance Sheet'!C17/'Balance Sheet'!C$32 -> 0.0025009333 | D43: ='Balance Sheet'!D17/'Balance Sheet'!D$32 -> 0.00082955522 | E43: ='Balance Sheet'!E17/'Balance Sheet'!E$32 -> 0.00084719675 | F43: ='Balance Sheet'!F17/'Balance Sheet'!F$32 -> 0.00076591128 | G43: ='Balance Sheet'!G17/'Balance Sheet'!G$32 -> 0.00056328832 | H43: ='Balance Sheet'!H17/'Balance Sheet'!H$32 -> 0.0018765097 | I43: ='Balance Sheet'!I17/'Balance Sheet'!I$32 -> 0.0023569637 | J43: ='Balance Sheet'!J17/'Balance Sheet'!J$32 -> 0.0027515252 | ... Q43: ='Balance Sheet'!Q17/'Balance Sheet'!Q$32 -> 0.0028190143
B44: Investments in associates accounted for using the equity method | C44: ='Balance Sheet'!C18/'Balance Sheet'!C$32 -> 0 | D44: ='Balance Sheet'!D18/'Balance Sheet'!D$32 -> 0.82490325 | E44: ='Balance Sheet'!E18/'Balance Sheet'!E$32 -> 0.84706817 | F44: ='Balance Sheet'!F18/'Balance Sheet'!F$32 -> 0.85219171 | G44: ='Balance Sheet'!G18/'Balance Sheet'!G$32 -> 0.86040591 | H44: ='Balance Sheet'!H18/'Balance Sheet'!H$32 -> 0.85472625 | I44: ='Balance Sheet'!I18/'Balance Sheet'!I$32 -> 0.83451902 | J44: ='Balance Sheet'!J18/'Balance Sheet'!J$32 -> 0.80384777 | ... Q44: ='Balance Sheet'!Q18/'Balance Sheet'!Q$32 -> 0.61795366
B45: Investments | C45: ='Balance Sheet'!C19/'Balance Sheet'!C$32 -> 0.93907158 | D45: ='Balance Sheet'!D19/'Balance Sheet'!D$32 -> 0.16082142 | E45: ='Balance Sheet'!E19/'Balance Sheet'!E$32 -> 0.1414488 | F45: ='Balance Sheet'!F19/'Balance Sheet'!F$32 -> 0.13924433 | G45: ='Balance Sheet'!G19/'Balance Sheet'!G$32 -> 0.13586635 | H45: ='Balance Sheet'!H19/'Balance Sheet'!H$32 -> 0.12916907 | I45: ='Balance Sheet'!I19/'Balance Sheet'!I$32 -> 0.12046366 | J45: ='Balance Sheet'!J19/'Balance Sheet'!J$32 -> 0.11061492 | ... Q45: ='Balance Sheet'!Q19/'Balance Sheet'!Q$32 -> 0.057113676
B46: Other Financial assets | C46: ='Balance Sheet'!C20/'Balance Sheet'!C$32 -> 0.0068152979 | D46: ='Balance Sheet'!D20/'Balance Sheet'!D$32 -> 0.0021950576 | E46: ='Balance Sheet'!E20/'Balance Sheet'!E$32 -> 0.0014351937 | F46: ='Balance Sheet'!F20/'Balance Sheet'!F$32 -> 0.00069058767 | G46: ='Balance Sheet'!G20/'Balance Sheet'!G$32 -> 0.00011765061 | H46: ='Balance Sheet'!H20/'Balance Sheet'!H$32 -> 0.0033597721 | I46: ='Balance Sheet'!I20/'Balance Sheet'!I$32 -> 0.0042199946 | J46: ='Balance Sheet'!J20/'Balance Sheet'!J$32 -> 0.004926432 | ... Q46: ='Balance Sheet'!Q20/'Balance Sheet'!Q$32 -> 0.005047267
B48: Total Financial Assets | C48: ='Balance Sheet'!C22/'Balance Sheet'!C$32 -> 0.98153691 | D48: ='Balance Sheet'!D22/'Balance Sheet'!D$32 -> 0.98973495 | E48: ='Balance Sheet'!E22/'Balance Sheet'!E$32 -> 0.99209184 | F48: ='Balance Sheet'!F22/'Balance Sheet'!F$32 -> 0.99405368 | G48: ='Balance Sheet'!G22/'Balance Sheet'!G$32 -> 0.99738232 | H48: ='Balance Sheet'!H22/'Balance Sheet'!H$32 -> 0.99632527 | I48: ='Balance Sheet'!I22/'Balance Sheet'!I$32 -> 0.99567599 | J48: ='Balance Sheet'!J22/'Balance Sheet'!J$32 -> 0.99516042 | ... Q48: ='Balance Sheet'!Q22/'Balance Sheet'!Q$32 -> 0.99546028
B50: Non Financial Assets
B51: Current Tax assets (Net) | C51: ='Balance Sheet'!C25/'Balance Sheet'!C$32 -> 0 | D51: ='Balance Sheet'!D25/'Balance Sheet'!D$32 -> 0.00037875617 | E51: ='Balance Sheet'!E25/'Balance Sheet'!E$32 -> 0.00098935836 | F51: ='Balance Sheet'!F25/'Balance Sheet'!F$32 -> 0.0016162735 | G51: ='Balance Sheet'!G25/'Balance Sheet'!G$32 -> 0.0010544782 | H51: ='Balance Sheet'!H25/'Balance Sheet'!H$32 -> 0.0018940741 | I51: ='Balance Sheet'!I25/'Balance Sheet'!I$32 -> 0.0023790251 | J51: ='Balance Sheet'!J25/'Balance Sheet'!J$32 -> 0.0027772797 | ... Q51: ='Balance Sheet'!Q25/'Balance Sheet'!Q$32 -> 0.0028454005
B52: Deferred Tax Asset (Net) | C52: ='Balance Sheet'!C26/'Balance Sheet'!C$32 -> 0.016961793 | D52: ='Balance Sheet'!D26/'Balance Sheet'!D$32 -> 0.0086951184 | E52: ='Balance Sheet'!E26/'Balance Sheet'!E$32 -> 0.0058478797 | F52: ='Balance Sheet'!F26/'Balance Sheet'!F$32 -> 0.0033307346 | G52: ='Balance Sheet'!G26/'Balance Sheet'!G$32 -> 0.0006321673 | H52: ='Balance Sheet'!H26/'Balance Sheet'!H$32 -> 0.00086603997 | I52: ='Balance Sheet'!I26/'Balance Sheet'!I$32 -> 0.0010877773 | J52: ='Balance Sheet'!J26/'Balance Sheet'!J$32 -> 0.0012698739 | ... Q52: ='Balance Sheet'!Q26/'Balance Sheet'!Q$32 -> 0.0013010212
B53: Property, Plant and Equipment | C53: ='Balance Sheet'!C27/'Balance Sheet'!C$32 -> 0.001394117 | D53: ='Balance Sheet'!D27/'Balance Sheet'!D$32 -> 0.0011553503 | E53: ='Balance Sheet'!E27/'Balance Sheet'!E$32 -> 0.0010326067 | F53: ='Balance Sheet'!F27/'Balance Sheet'!F$32 -> 0.00096871493 | G53: ='Balance Sheet'!G27/'Balance Sheet'!G$32 -> 0.00090014298 | H53: ='Balance Sheet'!H27/'Balance Sheet'!H$32 -> 0.00083131561 | I53: ='Balance Sheet'!I27/'Balance Sheet'!I$32 -> 0.00075257042 | J53: ='Balance Sheet'!J27/'Balance Sheet'!J$32 -> 0.00067027784 | ... Q53: ='Balance Sheet'!Q27/'Balance Sheet'!Q$32 -> 0.00026815016
B54: Other non-financial assets | C54: ='Balance Sheet'!C28/'Balance Sheet'!C$32 -> 0.00010717976 | D54: ='Balance Sheet'!D28/'Balance Sheet'!D$32 -> 3.5823421e-05 | E54: ='Balance Sheet'!E28/'Balance Sheet'!E$32 -> 3.8313972e-05 | F54: ='Balance Sheet'!F28/'Balance Sheet'!F$32 -> 3.0596424e-05 | G54: ='Balance Sheet'!G28/'Balance Sheet'!G$32 -> 3.0895288e-05 | H54: ='Balance Sheet'!H28/'Balance Sheet'!H$32 -> 8.3305238e-05 | I54: ='Balance Sheet'!I28/'Balance Sheet'!I$32 -> 0.00010463438 | J54: ='Balance Sheet'!J28/'Balance Sheet'!J$32 -> 0.00012215042 | ... Q54: ='Balance Sheet'!Q28/'Balance Sheet'!Q$32 -> 0.00012514652
B56: Total Non Financial Assets | C56: ='Balance Sheet'!C30/'Balance Sheet'!C$32 -> 0.01846309 | D56: ='Balance Sheet'!D30/'Balance Sheet'!D$32 -> 0.010265048 | E56: ='Balance Sheet'!E30/'Balance Sheet'!E$32 -> 0.0079081587 | F56: ='Balance Sheet'!F30/'Balance Sheet'!F$32 -> 0.0059463195 | G56: ='Balance Sheet'!G30/'Balance Sheet'!G$32 -> 0.0026176838 | H56: ='Balance Sheet'!H30/'Balance Sheet'!H$32 -> 0.0036747349 | I56: ='Balance Sheet'!I30/'Balance Sheet'!I$32 -> 0.0043240073 | J56: ='Balance Sheet'!J30/'Balance Sheet'!J$32 -> 0.0048395819 | ... Q56: ='Balance Sheet'!Q30/'Balance Sheet'!Q$32 -> 0.0045397185
B58: TOTAL ASSETS | C58: ='Balance Sheet'!C32/'Balance Sheet'!C$32 -> 1 | D58: ='Balance Sheet'!D32/'Balance Sheet'!D$32 -> 1 | E58: ='Balance Sheet'!E32/'Balance Sheet'!E$32 -> 1 | F58: ='Balance Sheet'!F32/'Balance Sheet'!F$32 -> 1 | G58: ='Balance Sheet'!G32/'Balance Sheet'!G$32 -> 1 | H58: ='Balance Sheet'!H32/'Balance Sheet'!H$32 -> 1 | I58: ='Balance Sheet'!I32/'Balance Sheet'!I$32 -> 1 | J58: ='Balance Sheet'!J32/'Balance Sheet'!J$32 -> 1 | ... Q58: ='Balance Sheet'!Q32/'Balance Sheet'!Q$32 -> 1
B60: LIABILITIES AND EQUITY
B61: Liabilities
B62: Financial Liabilities
B63: Other financial liabilities | C63: ='Balance Sheet'!C37/'Balance Sheet'!C$32 -> 0.00035222399 | D63: ='Balance Sheet'!D37/'Balance Sheet'!D$32 -> 6.6066309e-05 | E63: ='Balance Sheet'!E37/'Balance Sheet'!E$32 -> 4.3409602e-05 | F63: ='Balance Sheet'!F37/'Balance Sheet'!F$32 -> 5.0337031e-05 | G63: ='Balance Sheet'!G37/'Balance Sheet'!G$32 -> 1.9768466e-05 | H63: ='Balance Sheet'!H37/'Balance Sheet'!H$32 -> 0.00014752442 | I63: ='Balance Sheet'!I37/'Balance Sheet'!I$32 -> 0.00018529597 | J63: ='Balance Sheet'!J37/'Balance Sheet'!J$32 -> 0.00021631497 | ... Q63: ='Balance Sheet'!Q37/'Balance Sheet'!Q$32 -> 0.00022162072
B65: Total Financial Liabilities | C65: ='Balance Sheet'!C39/'Balance Sheet'!C$32 -> 0.00035222399 | D65: ='Balance Sheet'!D39/'Balance Sheet'!D$32 -> 6.6066309e-05 | E65: ='Balance Sheet'!E39/'Balance Sheet'!E$32 -> 4.3409602e-05 | F65: ='Balance Sheet'!F39/'Balance Sheet'!F$32 -> 5.0337031e-05 | G65: ='Balance Sheet'!G39/'Balance Sheet'!G$32 -> 1.9768466e-05 | H65: ='Balance Sheet'!H39/'Balance Sheet'!H$32 -> 0.00014752442 | I65: ='Balance Sheet'!I39/'Balance Sheet'!I$32 -> 0.00018529597 | J65: ='Balance Sheet'!J39/'Balance Sheet'!J$32 -> 0.00021631497 | ... Q65: ='Balance Sheet'!Q39/'Balance Sheet'!Q$32 -> 0.00022162072
B67: Non Financial Liabilities
B68: Current tax liabilities (Net) | C68: ='Balance Sheet'!C42/'Balance Sheet'!C$32 -> 0.0001876621 | D68: ='Balance Sheet'!D42/'Balance Sheet'!D$32 -> 0 | E68: ='Balance Sheet'!E42/'Balance Sheet'!E$32 -> 0 | F68: ='Balance Sheet'!F42/'Balance Sheet'!F$32 -> 0 | G68: ='Balance Sheet'!G42/'Balance Sheet'!G$32 -> 0 | H68: ='Balance Sheet'!H42/'Balance Sheet'!H$32 -> 0 | I68: ='Balance Sheet'!I42/'Balance Sheet'!I$32 -> 0 | J68: ='Balance Sheet'!J42/'Balance Sheet'!J$32 -> 0 | ... Q68: ='Balance Sheet'!Q42/'Balance Sheet'!Q$32 -> 0
B69: Provisions | C69: ='Balance Sheet'!C43/'Balance Sheet'!C$32 -> 1.2568593e-05 | D69: ='Balance Sheet'!D43/'Balance Sheet'!D$32 -> 5.5805329e-06 | E69: ='Balance Sheet'!E43/'Balance Sheet'!E$32 -> 1.7802452e-05 | F69: ='Balance Sheet'!F43/'Balance Sheet'!F$32 -> 9.4306124e-06 | G69: ='Balance Sheet'!G43/'Balance Sheet'!G$32 -> 1.9062449e-05 | H69: ='Balance Sheet'!H43/'Balance Sheet'!H$32 -> 2.8841626e-05 | I69: ='Balance Sheet'!I43/'Balance Sheet'!I$32 -> 3.6226119e-05 | J69: ='Balance Sheet'!J43/'Balance Sheet'!J$32 -> 4.229046e-05 | ... Q69: ='Balance Sheet'!Q43/'Balance Sheet'!Q$32 -> 4.3327755e-05
B70: Other non-financial liabilities | C70: ='Balance Sheet'!C44/'Balance Sheet'!C$32 -> 0.00011749468 | D70: ='Balance Sheet'!D44/'Balance Sheet'!D$32 -> 0.00017155638 | E70: ='Balance Sheet'!E44/'Balance Sheet'!E$32 -> 0.00029332119 | F70: ='Balance Sheet'!F44/'Balance Sheet'!F$32 -> 0.00012156696 | G70: ='Balance Sheet'!G44/'Balance Sheet'!G$32 -> 0.000110421 | H70: ='Balance Sheet'!H44/'Balance Sheet'!H$32 -> 0.00039958089 | I70: ='Balance Sheet'!I44/'Balance Sheet'!I$32 -> 0.00050188797 | J70: ='Balance Sheet'!J44/'Balance Sheet'!J$32 -> 0.00058590523 | ... Q70: ='Balance Sheet'!Q44/'Balance Sheet'!Q$32 -> 0.00060027625
B72: Total Non Financial Liabilities | C72: ='Balance Sheet'!C46/'Balance Sheet'!C$32 -> 0.00031772537 | D72: ='Balance Sheet'!D46/'Balance Sheet'!D$32 -> 0.00017713692 | E72: ='Balance Sheet'!E46/'Balance Sheet'!E$32 -> 0.00031112365 | F72: ='Balance Sheet'!F46/'Balance Sheet'!F$32 -> 0.00013099757 | G72: ='Balance Sheet'!G46/'Balance Sheet'!G$32 -> 0.00012948345 | H72: ='Balance Sheet'!H46/'Balance Sheet'!H$32 -> 0.00042842252 | I72: ='Balance Sheet'!I46/'Balance Sheet'!I$32 -> 0.00053811409 | J72: ='Balance Sheet'!J46/'Balance Sheet'!J$32 -> 0.00062819569 | ... Q72: ='Balance Sheet'!Q46/'Balance Sheet'!Q$32 -> 0.000643604
B74: Equity
B75: Equity Share Capital | C75: ='Balance Sheet'!C49/'Balance Sheet'!C$32 -> 0.0013835854 | D75: ='Balance Sheet'!D49/'Balance Sheet'!D$32 -> 0.0011493738 | E75: ='Balance Sheet'!E49/'Balance Sheet'!E$32 -> 0.0010295751 | F75: ='Balance Sheet'!F49/'Balance Sheet'!F$32 -> 0.00096804781 | G75: ='Balance Sheet'!G49/'Balance Sheet'!G$32 -> 0.00090155502 | H75: ='Balance Sheet'!H49/'Balance Sheet'!H$32 -> 0.00083578312 | I75: ='Balance Sheet'!I49/'Balance Sheet'!I$32 -> 0.00075948941 | J75: ='Balance Sheet'!J49/'Balance Sheet'!J$32 -> 0.0006790103 | ... Q75: ='Balance Sheet'!Q49/'Balance Sheet'!Q$32 -> 0.00028404481
B76: Other Equity | C76: ='Balance Sheet'!C50/'Balance Sheet'!C$32 -> 0.99794647 | D76: ='Balance Sheet'!D50/'Balance Sheet'!D$32 -> 0.99860742 | E76: ='Balance Sheet'!E50/'Balance Sheet'!E$32 -> 0.99861589 | F76: ='Balance Sheet'!F50/'Balance Sheet'!F$32 -> 0.99885062 | G76: ='Balance Sheet'!G50/'Balance Sheet'!G$32 -> 0.99894919 | H76: ='Balance Sheet'!H50/'Balance Sheet'!H$32 -> 0.99858827 | I76: ='Balance Sheet'!I50/'Balance Sheet'!I$32 -> 0.9985171 | J76: ='Balance Sheet'!J50/'Balance Sheet'!J$32 -> 0.99847648 | ... Q76: ='Balance Sheet'!Q50/'Balance Sheet'!Q$32 -> 0.99885073
B78: Total Equity | C78: ='Balance Sheet'!C52/'Balance Sheet'!C$32 -> 0.99933005 | D78: ='Balance Sheet'!D52/'Balance Sheet'!D$32 -> 0.9997568 | E78: ='Balance Sheet'!E52/'Balance Sheet'!E$32 -> 0.99964547 | F78: ='Balance Sheet'!F52/'Balance Sheet'!F$32 -> 0.99981867 | G78: ='Balance Sheet'!G52/'Balance Sheet'!G$32 -> 0.99985075 | H78: ='Balance Sheet'!H52/'Balance Sheet'!H$32 -> 0.99942405 | I78: ='Balance Sheet'!I52/'Balance Sheet'!I$32 -> 0.99927659 | J78: ='Balance Sheet'!J52/'Balance Sheet'!J$32 -> 0.99915549 | ... Q78: ='Balance Sheet'!Q52/'Balance Sheet'!Q$32 -> 0.99913478
B80: TOTAL LIABILITIES AND EQUITY | C80: ='Balance Sheet'!C54/'Balance Sheet'!C$32 -> 1 | D80: ='Balance Sheet'!D54/'Balance Sheet'!D$32 -> 1 | E80: ='Balance Sheet'!E54/'Balance Sheet'!E$32 -> 1 | F80: ='Balance Sheet'!F54/'Balance Sheet'!F$32 -> 1 | G80: ='Balance Sheet'!G54/'Balance Sheet'!G$32 -> 1 | H80: ='Balance Sheet'!H54/'Balance Sheet'!H$32 -> 1 | I80: ='Balance Sheet'!I54/'Balance Sheet'!I$32 -> 1 | J80: ='Balance Sheet'!J54/'Balance Sheet'!J$32 -> 1 | ... Q80: ='Balance Sheet'!Q54/'Balance Sheet'!Q$32 -> 1

Sheet Market Data
B7: BSE Sensex | E7: Source - | F7: Historical - Indices
B9: Date | C9: Close Price | E9: Year | F9: =YEARFRAC(B10,B2486) -> 9.9861111
B10: 42269 | C10: 25651.84 | E10: Return | F10: =_xlfn.RRI(F9,C10,C2486) -> 0.123633
B11: 42270 | C11: 25822.99
B12: 42271 | C12: 25863.5
B13: 42275 | C13: 25616.84
B14: 42276 | C14: 25778.66
B15: 42277 | C15: 26154.83
B16: 42278 | C16: 26220.95
B17: 42282 | C17: 26785.55
B18: 42283 | C18: 26932.88
B19: 42284 | C19: 27035.85
B20: 42285 | C20: 26845.81
B21: 42286 | C21: 27079.51
B22: 42289 | C22: 26904.11
... B2486: 45917 | C2486: 82159.97

Sheet Equity Return
B8: Month | C8: Closing price of Sensex | D8: % Change Of Return | E8: Closing Price Of Stocks | F8: % Change Of Return | H8: Source - | I8: Historical - Indices
B10: 42248 | C10: 26154.83 | E10: 1117 | H10: Beta | I10: =SLOPE(F11:F130,D11:D130) -> 1.3144289
B11: 42278 | C11: 26656.83 | D11: =C11/C10-1 -> 0.019193396 | E11: 1051 | F11: =E11/E10-1 -> -0.05908684 | H11: Beta | I11: =_xlfn.COVARIANCE.S(F11:F130,D11:D130)/_xlfn.VAR.S(D11:D130) -> 1.3144289
B12: 42309 | C12: 26145.67 | D12: =C12/C11-1 -> -0.019175573 | E12: 962.75 | F12: =E12/E11-1 -> -0.08396765 | H12: Beta | I12: =I31 -> 1.3144289
B13: 42339 | C13: 26117.54 | D13: =C13/C12-1 -> -0.0010758952 | E13: 959.25 | F13: =E13/E12-1 -> -0.0036354194
B14: 42370 | C14: 24870.69 | D14: =C14/C13-1 -> -0.047739948 | E14: 897.25 | F14: =E14/E13-1 -> -0.064633829 | H14: SUMMARY OUTPUT
B15: 42401 | C15: 23002 | D15: =C15/C14-1 -> -0.075136235 | E15: 878 | F15: =E15/E14-1 -> -0.021454444
B16: 42430 | C16: 25341.86 | D16: =C16/C15-1 -> 0.1017242 | E16: 886.25 | F16: =E16/E15-1 -> 0.0093963554 | H16: Regression Statistics
B17: 42461 | C17: 25606.62 | D17: =C17/C16-1 -> 0.010447536 | E17: 1040.25 | F17: =E17/E16-1 -> 0.17376587 | H17: Multiple R | I17: 0.47696651
B18: 42491 | C18: 26667.96 | D18: =C18/C17-1 -> 0.041447876 | E18: 1091.85 | F18: =E18/E17-1 -> 0.049603461 | H18: R Square | I18: 0.22749705
B19: 42522 | C19: 26999.72 | D19: =C19/C18-1 -> 0.012440397 | E19: 1170 | F19: =E19/E18-1 -> 0.071575766 | H19: Adjusted R Square | I19: 0.22095042
B20: 42552 | C20: 28051.86 | D20: =C20/C19-1 -> 0.038968552 | E20: 1325 | F20: =E20/E19-1 -> 0.13247863 | H20: Standard Error | I20: 0.1124683
B21: 42583 | C21: 28452.17 | D21: =C21/C20-1 -> 0.014270355 | E21: 1379.35 | F21: =E21/E20-1 -> 0.041018868 | H21: Observations | I21: 120
B22: 42614 | C22: 27865.96 | D22: =C22/C21-1 -> -0.020603349 | E22: 1454.95 | F22: =E22/E21-1 -> 0.054808424
B23: 42644 | C23: 27930.21 | D23: =C23/C22-1 -> 0.0023056805 | E23: 2070.5 | F23: =E23/E22-1 -> 0.42307296 | H23: ANOVA
B24: 42675 | C24: 26652.81 | D24: =C24/C23-1 -> -0.045735424 | E24: 1910 | F24: =E24/E23-1 -> -0.077517508 | I24: df | J24: SS | K24: MS | L24: F | M24: Significance F
B25: 42705 | C25: 26626.46 | D25: =C25/C24-1 -> -0.00098863872 | E25: 1845 | F25: =E25/E24-1 -> -0.034031414 | H25: Regression | I25: 1 | J25: 0.43955972 | K25: 0.43955972 | L25: 34.750226 | M25: 3.6405389e-08
B26: 42736 | C26: 27655.96 | D26: =C26/C25-1 -> 0.038664546 | E26: 2270.2 | F26: =E26/E25-1 -> 0.2304607 | H26: Residual | I26: 118 | J26: 1.4925959 | K26: 0.012649118
B27: 42767 | C27: 28743.32 | D27: =C27/C26-1 -> 0.039317384 | E27: 2757.95 | F27: =E27/E26-1 -> 0.21484891 | H27: Total | I27: 119 | J27: 1.9321557
B28: 42795 | C28: 29620.5 | D28: =C28/C27-1 -> 0.030517699 | E28: 2820 | F28: =E28/E27-1 -> 0.022498595
B29: 42826 | C29: 29918.4 | D29: =C29/C28-1 -> 0.010057224 | E29: 2855 | F29: =E29/E28-1 -> 0.012411348 | I29: Coefficients | J29: Standard Error | K29: t Stat | L29: P-value | M29: Lower 95% | N29: Upper 95% | O29: Lower 95.0% | P29: Upper 95.0%
B30: 42856 | C30: 31145.8 | D30: =C30/C29-1 -> 0.041024921 | E30: 3202.6 | F30: =E30/E29-1 -> 0.12175131 | H30: Intercept | I30: 0.0043400563 | J30: 0.010531463 | K30: 0.41210384 | L30: 0.68101099 | M30: -0.016515108 | N30: 0.02519522 | O30: -0.016515108 | P30: 0.02519522
B31: 42887 | C31: 30921.61 | D31: =C31/C30-1 -> -0.0071980813 | E31: 3280 | F31: =E31/E30-1 -> 0.024167864 | H31: X Variable 1 | I31: 1.3144289 | J31: 0.22297608 | K31: 5.8949323 | L31: 3.6405389e-08 | M31: 0.87287555 | N31: 1.7559822 | O31: 0.87287555 | P31: 1.7559822
B32: 42917 | C32: 32514.94 | D32: =C32/C31-1 -> 0.051528041 | E32: 3430.65 | F32: =E32/E31-1 -> 0.045929878
B33: 42948 | C33: 31730.49 | D33: =C33/C32-1 -> -0.024125833 | E33: 3007 | F33: =E33/E32-1 -> -0.12348972
B34: 42979 | C34: 31283.72 | D34: =C34/C33-1 -> -0.014080148 | E34: 3299.4 | F34: =E34/E33-1 -> 0.097239774
B35: 43009 | C35: 33213.13 | D35: =C35/C34-1 -> 0.061674571 | E35: 3266.05 | F35: =E35/E34-1 -> -0.010107898
B36: 43040 | C36: 33149.35 | D36: =C36/C35-1 -> -0.0019203249 | E36: 3720.45 | F36: =E36/E35-1 -> 0.1391283
B37: 43070 | C37: 34056.83 | D37: =C37/C36-1 -> 0.027375499 | E37: 5059.2 | F37: =E37/E36-1 -> 0.3598355
B38: 43101 | C38: 35965.02 | D38: =C38/C37-1 -> 0.056029583 | E38: 4724.4 | F38: =E38/E37-1 -> -0.066176471
B39: 43132 | C39: 34184.04 | D39: =C39/C38-1 -> -0.049519783 | E39: 4384.55 | F39: =E39/E38-1 -> -0.071935061
B40: 43160 | C40: 32968.68 | D40: =C40/C39-1 -> -0.035553434 | E40: 3798 | F40: =E40/E39-1 -> -0.13377656
B41: 43191 | C41: 35160.36 | D41: =C41/C40-1 -> 0.066477639 | E41: 4044.55 | F41: =E41/E40-1 -> 0.064915745
B42: 43221 | C42: 35322.38 | D42: =C42/C41-1 -> 0.0046080302 | E42: 3220 | F42: =E42/E41-1 -> -0.20386693
B43: 43252 | C43: 35423.48 | D43: =C43/C42-1 -> 0.002862208 | E43: 2914.95 | F43: =E43/E42-1 -> -0.094736025
... B130: 45901 | C130: 80710.76 | D130: =C130/C129-1 -> 0.01129074 | E130: 4017.1 | F130: =E130/E129-1 -> 0.078865031

Sheet Comps Data
E5: 100
B6: (All amounts in INR Lakhs, unless otherwise stated)
B7: Name | C7: CMP Rs. | D7: No. Eq. Shares lakhs | E7: Debt | F7: Cash | G7: NP Ann | H7: Sales Ann | I7: Dep Ann | J7: EBIT Ann | K7: EV / EBITDA | L7: EV | M7: Mar Cap | N7: Tax 12M | O7: P/E
B8: TVS Holdings | C8: 13428 | D8: 202 | E8: 3248934 | F8: 513511 | G8: 240925 | H8: 4499316 | I8: 106685 | J8: 577204 | K8: 700 | L8: 5199086 | M8: 2463663 | N8: 130880 | O8: 19.31
B9: Religare Enterp. | C9: 248.73 | D9: 3307 | E9: 23343 | F9: 108674 | G9: 18332 | H9: 735424 | I9: 6200 | J9: 28044 | K9: 2455 | L9: 751752 | M9: 837083 | N9: 5170 | O9: 71.27
B10: Elcid Investment | C10: 132296.75 | D10: 2 | E10: 0 | F10: 233 | G10: 15300 | H10: 21114 | I10: 110 | J10: 20605 | K10: 2177 | L10: 264991 | M10: 265224 | N10: 3297 | O10: 30.26
B11: Summit Securitie | C11: 2178.91 | D11: 109 | E11: 0 | F11: 303 | G11: 6860 | H11: 11903 | I11: 2 | J11: 11430 | K11: 2011 | L11: 243123 | M11: 243426 | N11: 3504 | O11: 28.36
B12: Kalyani Invest. | C12: 5018 | D12: 44 | E12: 0 | F12: 24650 | G12: 7154 | H12: 7822 | I12: 9 | J12: 9749 | K12: 2077 | L12: 182567 | M12: 207217 | N12: 2367 | O12: 32.28
B13: PNB Gilts | C13: 102.38 | D13: 1800 | E13: 2238401 | F13: 26370 | G13: 23303 | H13: 167616 | I13: 342 | J13: 162117 | K13: 1375 | L13: 2387865 | M13: 175834 | N13: 11342 | O13: 5.2
B15: Vardhman Hold. | C15: 3810 | D15: 31.9 | E15: 0 | F15: 152 | G15: 25800 | H15: 2277 | I15: 1 | J15: 27297 | K15: 490 | L15: 128277 | M15: 128429 | N15: 1458 | O15: 519
B17: Source - | C17: Investment Company Companies - Screener

Sheet Comps Valuation
B6: Comparable Valuation
B7: (All amounts in INR Lakhs, unless otherwise stated)
B8: Companies | E8: Market Data | L8: Financial data | P8: Valution
E9: Price | F9: Share | G9: Market Cap | H9: Debt | I9: Cash | J9: EV | L9: Sales | M9: EBITDA | N9: Earnings | P9: EV/Sales | Q9: EV/EBITDA | R9: P/E
B10: Company Name | E10: (/share) | F10: (Lakhs) | G10: (Lakhs) | H10: (Lakhs) | I10: (Lakhs) | J10: (Lakhs) | L10: (Lakhs) | M10: (Lakhs) | N10: (Lakhs) | P10: x | Q10: x | R10: x
B11: ='Comps Data'!B8 -> TVS Holdings | E11: ='Comps Data'!C8 -> 13428 | F11: ='Comps Data'!D8 -> 202 | G11: =F11*E11 -> 2712456 | H11: ='Comps Data'!E8 -> 3248934 | I11: ='Comps Data'!F8 -> 513511 | J11: =G11+H11-I11 -> 5447879 | L11: ='Comps Data'!H8 -> 4499316 | M11: ='Comps Data'!J8+'Comps Data'!I8 -> 683889 | N11: ='Comps Data'!G8 -> 240925 | P11: =J11/L11 -> 1.2108238 | Q11: =J11/M11 -> 7.9660281 | R11: =G11/N11 -> 11.258508
B12: ='Comps Data'!B9 -> Religare Enterp. | E12: ='Comps Data'!C9 -> 248.73 | F12: ='Comps Data'!D9 -> 3307 | G12: =F12*E12 -> 822550.11 | H12: ='Comps Data'!E9 -> 23343 | I12: ='Comps Data'!F9 -> 108674 | J12: =G12+H12-I12 -> 737219.11 | L12: ='Comps Data'!H9 -> 735424 | M12: ='Comps Data'!J9+'Comps Data'!I9 -> 34244 | N12: ='Comps Data'!G9 -> 18332 | P12: =J12/L12 -> 1.0024409 | Q12: =J12/M12 -> 21.528417 | R12: =G12/N12 -> 44.869633
B13: ='Comps Data'!B10 -> Elcid Investment | E13: ='Comps Data'!C10 -> 132296.75 | F13: ='Comps Data'!D10 -> 2 | G13: =F13*E13 -> 264593.5 | H13: ='Comps Data'!E10 -> 0 | I13: ='Comps Data'!F10 -> 233 | J13: =G13+H13-I13 -> 264360.5 | L13: ='Comps Data'!H10 -> 21114 | M13: ='Comps Data'!J10+'Comps Data'!I10 -> 20715 | N13: ='Comps Data'!G10 -> 15300 | P13: =J13/L13 -> 12.520626 | Q13: =J13/M13 -> 12.761791 | R13: =G13/N13 -> 17.293693
B14: ='Comps Data'!B11 -> Summit Securitie | E14: ='Comps Data'!C11 -> 2178.91 | F14: ='Comps Data'!D11 -> 109 | G14: =F14*E14 -> 237501.19 | H14: ='Comps Data'!E11 -> 0 | I14: ='Comps Data'!F11 -> 303 | J14: =G14+H14-I14 -> 237198.19 | L14: ='Comps Data'!H11 -> 11903 | M14: ='Comps Data'!J11+'Comps Data'!I11 -> 11432 | N14: ='Comps Data'!G11 -> 6860 | P14: =J14/L14 -> 19.927597 | Q14: =J14/M14 -> 20.748617 | R14: =G14/N14 -> 34.621165
B15: ='Comps Data'!B12 -> Kalyani Invest. | E15: ='Comps Data'!C12 -> 5018 | F15: ='Comps Data'!D12 -> 44 | G15: =F15*E15 -> 220792 | H15: ='Comps Data'!E12 -> 0 | I15: ='Comps Data'!F12 -> 24650 | J15: =G15+H15-I15 -> 196142 | L15: ='Comps Data'!H12 -> 7822 | M15: ='Comps Data'!J12+'Comps Data'!I12 -> 9758 | N15: ='Comps Data'!G12 -> 7154 | P15: =J15/L15 -> 25.075684 | Q15: =J15/M15 -> 20.100635 | R15: =G15/N15 -> 30.862734
B16: ='Comps Data'!B13 -> PNB Gilts | E16: ='Comps Data'!C13 -> 102.38 | F16: ='Comps Data'!D13 -> 1800 | G16: =F16*E16 -> 184284 | H16: ='Comps Data'!E13 -> 2238401 | I16: ='Comps Data'!F13 -> 26370 | J16: =G16+H16-I16 -> 2396315 | L16: ='Comps Data'!H13 -> 167616 | M16: ='Comps Data'!J13+'Comps Data'!I13 -> 162459 | N16: ='Comps Data'!G13 -> 23303 | P16: =J16/L16 -> 14.296457 | Q16: =J16/M16 -> 14.750275 | R16: =G16/N16 -> 7.9081663
B19: High | P19: =MAX(P11:P16) -> 25.075684 | Q19: =MAX(Q11:Q16) -> 21.528417 | R19: =MAX(R11:R16) -> 44.869633
B20: 75th Percentile | P20: =_xlfn.QUARTILE.EXC(P11:P16,3) -> 21.214619 | Q20: =_xlfn.QUARTILE.EXC(Q11:Q16,3) -> 20.943567 | R20: =_xlfn.QUARTILE.EXC(R11:R16,3) -> 37.183282
B21: Average | P21: =AVERAGE(P11:P16) -> 12.338938 | Q21: =AVERAGE(Q11:Q16) -> 16.309294 | R21: =AVERAGE(R11:R16) -> 24.468983
B22: Median | P22: =MEDIAN(P11:P16) -> 13.408542 | Q22: =MEDIAN(Q11:Q16) -> 17.425455 | R22: =MEDIAN(R11:R16) -> 24.078213
B23: 25th Percentile | P23: =_xlfn.QUARTILE.EXC(P11:P16,1) -> 1.1587281 | Q23: =_xlfn.QUARTILE.EXC(Q11:Q16,1) -> 11.56285 | R23: =_xlfn.QUARTILE.EXC(R11:R16,1) -> 10.420922
B24: Low | P24: =MIN(P11:P16) -> 1.0024409 | Q24: =MIN(Q11:Q16) -> 7.9660281 | R24: =MIN(R11:R16) -> 7.9081663
B26: ='Comps Data'!B15 -> Vardhman Hold. | E26: ='Comps Data'!C15 -> 3810 | F26: ='Comps Data'!D15 -> 31.9 | G26: =F26*E26 -> 121539 | H26: ='Comps Data'!E15 -> 0 | I26: ='Comps Data'!F15 -> 152 | J26: =G26+H26-I26 -> 121387 | L26: ='Comps Data'!H15 -> 2277 | M26: ='Comps Data'!I15+'Comps Data'!J15 -> 27298 | N26: ='Comps Data'!G15 -> 25800 | P26: =J26/L26 -> 53.310057 | Q26: =J26/M26 -> 4.446736 | R26: =G26/N26 -> 4.710814
B29: Metric | E29: Comps | F29: EV (₹ Lakhs.) | G29: Net Debt (₹ Lakhs.) | H29: Equity Value (₹ Lakhs.) | I29: Shares (Lakhs) | J29: Share Price | L29: Stock Value
B30: EV/REVENUE | E30: =P22 -> 13.408542 | F30: =E30*L26 -> 30531.25 | G30: =$H$26-$I$26 -> -152 | H30: =F30-G30 -> 30683.25 | I30: =$F$26 -> 31.9 | J30: =H30/I30 -> 961.85735 | L30: =IF(J30>$E$26,"Undervalued","Overvalued") -> Overvalued
B31: EV/EBITDA | E31: =Q22 -> 17.425455 | F31: =E31*M26 -> 475680.08 | G31: =$H$26-$I$26 -> -152 | H31: =F31-G31 -> 475832.08 | I31: =$F$26 -> 31.9 | J31: =H31/I31 -> 14916.366 | L31: =IF(J31>$E$26,"Undervalued","Overvalued") -> Undervalued
B32: P/E | E32: =R22 -> 24.078213 | F32: =H32+G32 -> 621065.91 | G32: =$H$26-$I$26 -> -152 | H32: =E32*N26 -> 621217.91 | I32: =$F$26 -> 31.9 | J32: =H32/I32 -> 19473.916 | L32: =IF(J32>$E$26,"Undervalued","Overvalued") -> Undervalued
B35: Metric | E35: Comps | F35: EV (₹ Lakhs.) | G35: Net Debt (₹ Lakhs.) | H35: Equity Value (₹ Lakhs.) | I35: Shares (Lakhs) | J35: Share Price | L35: Stock Value
B36: EV/REVENUE | E36: =P21 -> 12.338938 | F36: =E36*L26 -> 28095.762 | G36: =$H$26-$I$26 -> -152 | H36: =F36-G36 -> 28247.762 | I36: =$F$26 -> 31.9 | J36: =H36/I36 -> 885.50979 | L36: =IF(J36>$E$26,"Undervalued","Overvalued") -> Overvalued
B37: EV/EBITDA | E37: =Q21 -> 16.309294 | F37: =E37*M26 -> 445211.11 | G37: =$H$26-$I$26 -> -152 | H37: =F37-G37 -> 445363.11 | I37: =$F$26 -> 31.9 | J37: =H37/I37 -> 13961.226 | L37: =IF(J37>$E$26,"Undervalued","Overvalued") -> Undervalued
B38: P/E | E38: =R21 -> 24.468983 | F38: =H38+G38 -> 631147.76 | G38: =$H$26-$I$26 -> -152 | H38: =E38*N26 -> 631299.76 | I38: =$F$26 -> 31.9 | J38: =H38/I38 -> 19789.961 | L38: =IF(J38>$E$26,"Undervalued","Overvalued") -> Undervalued

Sheet DCF
B6: (All amounts in INR Lakhs, unless otherwise stated)
B7: Particulars | C7: 2021 | D7: =C7+1 -> 2022 | E7: =D7+1 -> 2023 | F7: =E7+1 -> 2024 | G7: =F7+1 -> 2025 | H7: =G7+1 -> 2026 | I7: =H7+1 -> 2027 | J7: =I7+1 -> 2028 | K7: =J7+1 -> 2029 | ... Q7: =P7+1 -> 2035
C8: Audited | D8: Audited | E8: Audited | F8: Audited | G8: Audited | H8: Forecasted | I8: Forecasted | J8: Forecasted | K8: Forecasted | L8: Forecasted | M8: Forecasted | N8: Forecasted | O8: Forecasted | P8: Forecasted | Q8: Forecasted
G9: Entry | R9: Exit
B10: DATE | G10: =Assumptions!C11 -> 45922 | H10: =DATE(YEAR(Assumptions!$C$12)+DCF!H11,MONTH(Assumptions!$C$12),DAY(Assumptions!$C$12)) -> 46112 | I10: =DATE(YEAR(Assumptions!$C$12)+DCF!I11,MONTH(Assumptions!$C$12),DAY(Assumptions!$C$12)) -> 46477 | J10: =DATE(YEAR(Assumptions!$C$12)+DCF!J11,MONTH(Assumptions!$C$12),DAY(Assumptions!$C$12)) -> 46843 | K10: =DATE(YEAR(Assumptions!$C$12)+DCF!K11,MONTH(Assumptions!$C$12),DAY(Assumptions!$C$12)) -> 47208 | L10: =DATE(YEAR(Assumptions!$C$12)+DCF!L11,MONTH(Assumptions!$C$12),DAY(Assumptions!$C$12)) -> 47573 | M10: =DATE(YEAR(Assumptions!$C$12)+DCF!M11,MONTH(Assumptions!$C$12),DAY(Assumptions!$C$12)) -> 47938 | N10: =DATE(YEAR(Assumptions!$C$12)+DCF!N11,MONTH(Assumptions!$C$12),DAY(Assumptions!$C$12)) -> 48304 | O10: =DATE(YEAR(Assumptions!$C$12)+DCF!O11,MONTH(Assumptions!$C$12),DAY(Assumptions!$C$12)) -> 48669 | ... Q10: =DATE(YEAR(Assumptions!$C$12)+DCF!Q11,MONTH(Assumptions!$C$12),DAY(Assumptions!$C$12)) -> 49399 | R10: =Q10 -> 49399
B11: Time Periods | H11: 0 | I11: 1 | J11: 2 | K11: 3 | L11: 4 | M11: 5 | N11: 6 | O11: 7 | P11: 8 | Q11: 9
B12: Year Frac | C12: 0 | D12: 0 | E12: 0 | F12: 0 | G12: 0 | H12: =YEARFRAC(G10,H10) -> 0.525 | I12: =YEARFRAC(H10,I10) -> 1 | J12: =YEARFRAC(I10,J10) -> 1 | K12: =YEARFRAC(J10,K10) -> 1 | L12: =YEARFRAC(K10,L10) -> 1 | M12: =YEARFRAC(L10,M10) -> 1 | N12: =YEARFRAC(M10,N10) -> 1 | O12: =YEARFRAC(N10,O10) -> 1 | ... Q12: =YEARFRAC(P10,Q10) -> 1 | R12: 1
B13: EBIT/ Operating Income | C13: ='Income Statement'!C24 -> 1750.6 | D13: ='Income Statement'!D24 -> 3000.74 | E13: ='Income Statement'!E24 -> 150.79 | F13: ='Income Statement'!F24 -> 1055.48 | G13: ='Income Statement'!G24 -> 1658.65 | H13: ='Income Statement'!H24 -> 2346.2001 | I13: ='Income Statement'!I24 -> 3243.4063 | J13: ='Income Statement'!J24 -> 4235.5075 | ... Q13: ='Income Statement'!Q24 -> 10373.758
B14: Tax rate | C14: =C13*Cost_BuildUp!C19 -> 48.659353 | D14: =D13*Cost_BuildUp!D19 -> 198.49229 | E14: =E13*Cost_BuildUp!E19 -> -2.3542229 | F14: =F13*Cost_BuildUp!F19 -> 50.859043 | G14: =G13*Cost_BuildUp!G19 -> 90.962258 | H14: =H13*Cost_BuildUp!H19 -> 140.39929 | I14: =I13*Cost_BuildUp!I19 -> 194.08913 | J14: =J13*Cost_BuildUp!J19 -> 274.63513 | ... Q14: =Q13*Cost_BuildUp!Q19 -> 828.25265
B15: NOPAT | C15: =C13-C14 -> 1701.9406 | D15: =D13-D14 -> 2802.2477 | E15: =E13-E14 -> 153.14422 | F15: =F13-F14 -> 1004.621 | G15: =G13-G14 -> 1567.6877 | H15: =H13-H14 -> 2205.8008 | I15: =I13-I14 -> 3049.3171 | J15: =J13-J14 -> 3960.8723 | ... Q15: =Q13-Q14 -> 9545.505
B16: Add: Depreciation & Amortization | C16: ='Income Statement'!C22 -> 0.88 | D16: ='Income Statement'!D22 -> 0.77 | E16: ='Income Statement'!E22 -> 0.72 | F16: ='Income Statement'!F22 -> 0.72 | G16: ='Income Statement'!G22 -> 0.72 | H16: ='Income Statement'!H22 -> 1.2064298 | I16: ='Income Statement'!I22 -> 1.2018634 | J16: ='Income Statement'!J22 -> 1.1973144 | ... Q16: ='Income Statement'!Q22 -> 2.5177578
B17: Less: CapEx | C17: =FSA!C11 -> 0 | D17: =FSA!D11 -> -3.8635761e-14 | E17: =FSA!E11 -> 2.9531932e-14 | F17: =FSA!F11 -> -2.7311486e-14 | G17: =FSA!G11 -> 2.9531932e-14 | H17: =FSA!H11 -> -1.7294499e-15 | I17: =FSA!I11 -> 7.5432608e-15 | J17: =FSA!J11 -> 2.0186071e-15 | ... Q17: =FSA!Q11 -> 5.7897523e-15
B18: Less: Change in Working Capital | C18: 0 | D18: ='Net Working Capital'!D43 -> -16847.63 | E18: ='Net Working Capital'!E43 -> 15003.93 | F18: ='Net Working Capital'!F43 -> -1982.2 | G18: ='Net Working Capital'!G43 -> -3596.61 | H18: ='Net Working Capital'!H43 -> -338.82041 | I18: ='Net Working Capital'!I43 -> -1235.9498 | J18: ='Net Working Capital'!J43 -> -1353.6777 | K18: ='Net Working Capital'!K43 -> -1417.8164 | ... Q18: ='Net Working Capital'!Q43 -> -1101.055
B20: Unlevered FCFF | C20: =C15+C16+C17+C18 -> 1702.8206 | D20: =D15+D16+D17+D18 -> -14044.612 | E20: =E15+E16+E17+E18 -> 15157.794 | F20: =F15+F16+F17+F18 -> -976.85904 | G20: =G15+G16+G17+G18 -> -2028.2023 | H20: =H15+H16+H17+H18 -> 1868.1868 | I20: =I15+I16+I17+I18 -> 1814.5692 | J20: =J15+J16+J17+J18 -> 2608.392 | ... Q20: =Q15+Q16+Q17+Q18 -> 8446.9678 | R20: =F34 -> 139125.59
B22: Transaction FCFF | C22: =C20*C12 -> 0 | D22: =D20*D12 -> 0 | E22: =E20*E12 -> 0 | F22: =F20*F12 -> 0 | G22: =G20*G12 -> 0 | H22: =H20*H12 -> 980.79808 | I22: =I20*I12 -> 1814.5692 | J22: =J20*J12 -> 2608.392 | ... R22: =R20*R12 -> 139125.59
B24: WACC | I24: Sensitivity - Intrinsic Value (Rs/share)
B26: Current Capital structure | I26: Discount Rate | J26: Perpetual Growth Rate
B27: Market cap | C27: ='Comps Valuation'!G26 -> 121539 | E27: EV/EBITDA Multiple | F27: =Assumptions!C21 -> 16.309294 | J27: =F43 -> 1911.6459 | K27: =L27-1% -> 0.04 | L27: =M27-1% -> 0.05 | M27: 0.06 | N27: =M27+1% -> 0.07 | O27: =N27+1% -> 0.08
B28: Total Debt | C28: 0 | E28: Perpetual Growth Rate | F28: =Assumptions!C22 -> 0.06 | J28: =J29-1% -> 0.12212865 | K28: 2197.6902 | L28: 2281.3685 | M28: 2391.9838 | N28: 2545.0385 | O28: 2770.7538
B29: Total Equity | C29: =1-C28 -> 1 | E29: Discount Rate | F29: =Assumptions!C23 -> 0.14212865 | J29: =J30-1% -> 0.13212865 | K29: 1987.8863 | L29: 2048.6261 | M29: 2126.2081 | N29: 2228.7647 | O29: 2370.6687
J30: 0.14212865 | K30: 1809.977 | L30: 1855.2937 | M30: 1911.6459 | N30: 1983.6235 | O30: 2078.7717
B31: Cost of debt | E31: Terminal Value | J31: =J30+1% -> 0.15212865 | K31: 1656.7011 | L31: 1691.2677 | M31: 1733.3383 | N31: 1785.654 | O31: 1852.4758
B32: Pre-tax cost of debt | C32: 0 | E32: EV/EBITDA | F32: =F27*(Q13+Q16) -> 169229.73 | J32: =J31+1% -> 0.16212865 | K32: 1523.0182 | L32: 1549.8708 | M32: 1581.982 | N32: 1621.0642 | O32: 1669.6636
B33: tax rate | C33: =Assumptions!C18 -> 0.05984114 | E33: Prep.Growth | F33: =Q22*(1+F28)/(F29-F28) -> 109021.46
B34: After -Tax cost of debt | C34: =C32*(1-C33) -> 0 | E34: Average | F34: =AVERAGE(F32:F33) -> 139125.59
B36: Cost of equity | E36: Intrinsic Value | I36: EV/EBITDA | J36: Perpetual Growth Rate
B37: Risk free Rate | C37: =Assumptions!C14 -> 0.06481 | E37: Enterpreise Value | F37: =XNPV($F$29,G22:R22,G10:R10) -> 60829.504 | J37: =F43 -> 1911.6459 | K37: =L37-1% -> 0.04 | L37: =M37-1% -> 0.05 | M37: 0.06 | N37: =M37+1% -> 0.07 | O37: =N37+1% -> 0.08
B38: Equity Market Return | C38: ='Market Data'!F10 -> 0.123633 | E38: Plus: Cash & Cash equivalent | F38: ='Comps Valuation'!I26 -> 152 | J38: =J39-4 -> 7.309294 | K38: 1397.2448 | L38: 1442.5615 | M38: 1498.9137 | N38: 1570.8913 | O38: 1666.0395
B39: Equity risk premium | C39: =C38-C37 -> 0.058823003 | E39: Less- Debt | F39: ='Comps Valuation'!H26 -> 0 | J39: =J40-5 -> 11.309294 | K39: 1580.6813 | L39: 1625.998 | M39: 1682.3502 | N39: 1754.3279 | O39: 1849.476
B40: Beta | C40: ='Equity Return'!I10 -> 1.3144289 | E40: Less-non- controlling interest | F40: 0 | J40: 16.309294 | K40: 1809.977 | L40: 1855.2937 | M40: 1911.6459 | N40: 1983.6235 | O40: 2078.7717
B41: Cost of equity | C41: =C37+(C40*C39) -> 0.14212865 | E41: Equity Value | F41: =SUM(F37:F40) -> 60981.504 | J41: =J40+5 -> 21.309294 | K41: 2039.2727 | L41: 2084.5894 | M41: 2140.9416 | N41: 2212.9192 | O41: 2308.0674
J42: =J41+5 -> 26.309294 | K42: 2268.5684 | L42: 2313.8851 | M42: 2370.2373 | N42: 2442.2149 | O42: 2537.3631
B43: WACC | C43: =(C41*C29)+(C34*C28) -> 0.14212865 | E43: Equity value/share | F43: =F41/'Comps Valuation'!F26 -> 1911.6459

Sheet Football Field Analysis
B7: Football Field Analysis
B9: Football Field Data
E10: Comps Median | F10: Comps Average | G10: DCF (Average) | H10: 52-Week Hi/LO | I10: Market Consenses
B11: High | E11: 19474 | F11: 19790 | G11: 2229 | H11: 5760 | I11: 13453.5
B12: High | E12: =E11 -> 19474 | F12: =F11 -> 19790 | G12: =G11 -> 2229 | H12: =H11 -> 5760 | I12: =I11 -> 13453.5
B13: Low | E13: 962 | F13: 886 | G13: 1635 | H13: 2850 | I13: 3000
B14: Low | E14: =E13 -> 962 | F14: =F13 -> 886 | G14: =G13 -> 1635 | H14: =H13 -> 2850 | I14: =I13 -> 3000

Sheet Ratio Analysis
B7: Ratio Analysis & Interpretation
B9: Particulars | C9: 2021 | D9: =C9+1 -> 2022 | E9: =D9+1 -> 2023 | F9: =E9+1 -> 2024 | G9: =F9+1 -> 2025 | H9: =G9+1 -> 2026 | I9: =H9+1 -> 2027 | J9: =I9+1 -> 2028 | K9: =J9+1 -> 2029 | ... Q9: =P9+1 -> 2035 | T9: Ratio Interpretation
B12: EBITDA Margin | C12: ='Income Statement'!C20/'Income Statement'!C13 -> 0.88525203 | D12: ='Income Statement'!D20/'Income Statement'!D13 -> 0.90708835 | E12: ='Income Statement'!E20/'Income Statement'!E13 -> 0.25747302 | F12: ='Income Statement'!F20/'Income Statement'!F13 -> 0.70879722 | G12: ='Income Statement'!G20/'Income Statement'!G13 -> 0.72855437 | H12: ='Income Statement'!H20/'Income Statement'!H13 -> 0.697433 | I12: ='Income Statement'!I20/'Income Statement'!I13 -> 0.697433 | J12: ='Income Statement'!J20/'Income Statement'!J13 -> 0.697433 | ... Q12: ='Income Statement'!Q20/'Income Statement'!Q13 -> 0.697433 | T12: The EBITDA Margin shows strong profitability historically, with 88.53% (2021) rising to 90.71% (2022), then sharply declining to 25.75% (2023). Recovery follows at 70.88% (2024) and 72.86% (2025). For the forecasted period (2026–2035), margins stabilize at 69.74%. The trend indicates an initial upside, then a downside dip, followed by partial recovery and long-term stability. This suggests improved efficiency post-2023 challenges, but moderate margins ahead, reflecting controlled operations without major upside growth potential.
B15: EBIT Margin | C15: ='Income Statement'!C24/'Income Statement'!C13 -> 0.88480725 | D15: ='Income Statement'!D24/'Income Statement'!D13 -> 0.90685565 | E15: ='Income Statement'!E24/'Income Statement'!E13 -> 0.25624947 | F15: ='Income Statement'!F24/'Income Statement'!F13 -> 0.70831404 | G15: ='Income Statement'!G24/'Income Statement'!G13 -> 0.72823825 | H15: ='Income Statement'!H24/'Income Statement'!H13 -> 0.69707456 | I15: ='Income Statement'!I24/'Income Statement'!I13 -> 0.69717466 | J15: ='Income Statement'!J24/'Income Statement'!J13 -> 0.6972359 | ... Q15: ='Income Statement'!Q24/'Income Statement'!Q13 -> 0.69726377 | T15: The EBIT Margin shows strong profitability historically, with 88.48% (2021) rising to 90.69% (2022), before sharply declining to 25.62% (2023). A recovery is observed at 70.83% (2024) and 72.82% (2025). For the forecasted period (2026–2035), margins stabilize around 69.71%–69.73%. The trend highlights an early peak, a sharp downturn, followed by recovery and long-term stabilization. This reflects improved cost control and operational efficiency post-2023 challenges, but indicates steady rather than high-growth profitability going forward.
B18: Pretax Margin | C18: ='Income Statement'!C30/'Income Statement'!C13 -> 6.7330617 | D18: ='Income Statement'!D30/'Income Statement'!D13 -> 13.88571 | E18: ='Income Statement'!E30/'Income Statement'!E13 -> 38.222619 | F18: ='Income Statement'!F30/'Income Statement'!F13 -> 13.035118 | G18: ='Income Statement'!G30/'Income Statement'!G13 -> 11.98505 | H18: ='Income Statement'!H30/'Income Statement'!H13 -> 8.7986434 | I18: ='Income Statement'!I30/'Income Statement'!I13 -> 8.7987435 | J18: ='Income Statement'!J30/'Income Statement'!J13 -> 8.7988048 | ... Q18: ='Income Statement'!Q30/'Income Statement'!Q13 -> 8.7988326 | T18: The Pretax Margin shows exceptionally high profitability historically, starting at 673.31% (2021) and surging to 1388.57% (2022) before peaking at 3822.26% (2023). It then declines to 1303.51% (2024) and 1198.51% (2025). For the forecasted period (2026–2035), margins stabilize around 879.86%–879.88%. The trend reflects an unusual spike in early years, followed by normalization at consistently high levels. Importantly, nearly 90% of the pretax profit is derived from the share of profit from associates, which significantly inflates margins. This indicates extraordinary gains from associate contributions rather than core operating performance, with sustained but more controlled profitability expected in the long term.
B21: Effective Tax Rate | C21: =Cost_BuildUp!C19 -> 0.027795815 | D21: =Cost_BuildUp!D19 -> 0.06614778 | E21: =Cost_BuildUp!E19 -> -0.015612593 | F21: =Cost_BuildUp!F19 -> 0.0481857 | G21: =Cost_BuildUp!G19 -> 0.05484114 | H21: =Cost_BuildUp!H19 -> 0.05984114 | I21: =Cost_BuildUp!I19 -> 0.05984114 | J21: =Cost_BuildUp!J19 -> 0.06484114 | ... Q21: =Cost_BuildUp!Q19 -> 0.07984114 | T21: The Effective Tax Rate shows fluctuations over the period, starting low at 2.78% (2021) and rising to 6.61% (2022), followed by an unusual negative rate of -1.56% (2023), likely due to tax credits or adjustments. It then normalizes to 4.82% (2024) and gradually increases to 5.48% (2025). For the forecasted period (2026–2035), the tax rate trends upward, stabilizing in the range of 5.98%–7.98%. This indicates a gradual normalization of tax liabilities, reflecting regulatory compliance and improved earnings quality, though the rates remain relatively low compared to standard corporate tax levels.
B24: Net Margin | C24: ='Income Statement'!C34/'Income Statement'!C13 -> 6.5459108 | D24: ='Income Statement'!D34/'Income Statement'!D13 -> 12.967201 | E24: ='Income Statement'!E34/'Income Statement'!E13 -> 38.819373 | F24: ='Income Statement'!F34/'Income Statement'!F13 -> 12.407011 | G24: ='Income Statement'!G34/'Income Statement'!G13 -> 11.327776 | H24: ='Income Statement'!H34/'Income Statement'!H13 -> 8.2721226 | I24: ='Income Statement'!I34/'Income Statement'!I13 -> 8.2722167 | J24: ='Income Statement'!J34/'Income Statement'!J13 -> 8.2282802 | ... Q24: ='Income Statement'!Q34/'Income Statement'!Q13 -> 8.0963238 | T24: The Net Margin shows extremely high profitability historically, starting at 654.59% (2021) and rising sharply to 1296.72% (2022), before peaking at 3881.94% (2023). It then declines to 1240.70% (2024) and further to 1132.78% (2025). For the forecasted period (2026–2035), margins stabilize in the range of 827.21%–809.63%. The trend reflects extraordinary margins driven largely by non-operational income, with around 90% of profits contributed by the share of profit from associates, rather than core operations. While margins remain exceptionally high, the stabilization phase suggests limited incremental upside, with future profitability heavily reliant on sustained associate performance rather than operational expansion.
B27: Return on Equity | C27: ='Income Statement'!C34/'Balance Sheet'!C52 -> 0.056167883 | D27: ='Income Statement'!D34/'Balance Sheet'!D52 -> 0.15452048 | E27: ='Income Statement'!E34/'Balance Sheet'!E52 -> 0.073697511 | F27: ='Income Statement'!F34/'Balance Sheet'!F52 -> 0.05607246 | G27: ='Income Statement'!G34/'Balance Sheet'!G52 -> 0.072872839 | H27: ='Income Statement'!H34/'Balance Sheet'!H52 -> 0.072933872 | I27: ='Income Statement'!I34/'Balance Sheet'!I52 -> 0.091622126 | J27: ='Income Statement'!J34/'Balance Sheet'!J52 -> 0.10640469 | ... Q27: ='Income Statement'!Q34/'Balance Sheet'!Q52 -> 0.10726854 | T27: The Return on Equity (ROE) shows fluctuations over the years, beginning at 5.62% (2021) and rising strongly to 15.45% (2022). It then declines to 7.37% (2023) and further moderates to 5.61% (2024), before improving again to 7.29% (2025). For the forecasted period (2026–2035), ROE gradually increases from 7.29% to a peak of 12.39% (2031), before slightly tapering to 10.73% (2035). The trend highlights initial volatility, followed by a steady improvement in shareholder returns, reflecting better earnings generation and efficient capital utilization over the long term, though not at exceptionally high levels.
B30: Return on Capital Employed | C30: ='Income Statement'!C24/(SUM('Balance Sheet'!C22)-SUM('Balance Sheet'!C39)) -> 0.0077325873 | D30: ='Income Statement'!D24/(SUM('Balance Sheet'!D22)-SUM('Balance Sheet'!D39)) -> 0.010916475 | E30: ='Income Statement'!E24/(SUM('Balance Sheet'!E22)-SUM('Balance Sheet'!E39)) -> 0.00049020801 | F30: ='Income Statement'!F24/(SUM('Balance Sheet'!F22)-SUM('Balance Sheet'!F39)) -> 0.0032198947 | G30: ='Income Statement'!G24/(SUM('Balance Sheet'!G22)-SUM('Balance Sheet'!G39)) -> 0.0046965249 | H30: ='Income Statement'!H24/(SUM('Balance Sheet'!H22)-SUM('Balance Sheet'!H39)) -> 0.0061660139 | I30: ='Income Statement'!I24/(SUM('Balance Sheet'!I22)-SUM('Balance Sheet'!I39)) -> 0.0077511932 | J30: ='Income Statement'!J24/(SUM('Balance Sheet'!J22)-SUM('Balance Sheet'!J39)) -> 0.0090545283 | ... Q30: ='Income Statement'!Q24/(SUM('Balance Sheet'!Q22)-SUM('Balance Sheet'!Q39)) -> 0.0092742418 | T30: The Return on Capital Employed (ROCE) shows very low efficiency levels, starting at 0.77% (2021) and improving slightly to 1.09% (2022). It then drops sharply to 0.05% (2023), indicating weak capital utilization during that year. A gradual recovery follows, reaching 0.32% (2024) and 0.47% (2025). For the forecasted period (2026–2035), ROCE shows steady but modest improvement, peaking at 0.97% (2031) before tapering down to 0.85% (2035). The trend reflects minimal returns from the capital base, highlighting limited operational efficiency and suggesting that profitability is not strongly driven by core capital-employed activities, but rather by external factors such as associate income.
B33: Return on Assets | C33: ='Income Statement'!C34/'Balance Sheet'!C32 -> 0.056130253 | D33: ='Income Statement'!D34/'Balance Sheet'!D32 -> 0.15448291 | E33: ='Income Statement'!E34/'Balance Sheet'!E32 -> 0.073671383 | F33: ='Income Statement'!F34/'Balance Sheet'!F32 -> 0.056062292 | G33: ='Income Statement'!G34/'Balance Sheet'!G32 -> 0.072861963 | H33: ='Income Statement'!H34/'Balance Sheet'!H32 -> 0.072891865 | I33: ='Income Statement'!I34/'Balance Sheet'!I32 -> 0.091555846 | J33: ='Income Statement'!J34/'Balance Sheet'!J32 -> 0.10631483 | ... Q33: ='Income Statement'!Q34/'Balance Sheet'!Q32 -> 0.10717572 | T33: The Return on Assets (ROA) shows fluctuations over the period, beginning at 5.61% (2021) and rising sharply to 15.45% (2022). It then declines to 7.37% (2023) and further moderates to 5.61% (2024), before improving again to 7.29% (2025). For the forecasted period (2026–2035), ROA gradually increases from 7.29% to a peak of 11.31% (2031), followed by a slight tapering to 9.86% (2035). The trend highlights early volatility, but steady improvement in asset utilization over the long term, suggesting better efficiency in generating profits from the asset base, though largely supported by associate income rather than core operational strength.
B36: Asset/ Equity | C36: ='Balance Sheet'!C32/'Balance Sheet'!C52 -> 1.0006704 | D36: ='Balance Sheet'!D32/'Balance Sheet'!D52 -> 1.0002433 | E36: ='Balance Sheet'!E32/'Balance Sheet'!E52 -> 1.0003547 | F36: ='Balance Sheet'!F32/'Balance Sheet'!F52 -> 1.0001814 | G36: ='Balance Sheet'!G32/'Balance Sheet'!G52 -> 1.0001493 | H36: ='Balance Sheet'!H32/'Balance Sheet'!H52 -> 1.0005763 | I36: ='Balance Sheet'!I32/'Balance Sheet'!I52 -> 1.0007239 | J36: ='Balance Sheet'!J32/'Balance Sheet'!J52 -> 1.0008452 | ... Q36: ='Balance Sheet'!Q32/'Balance Sheet'!Q52 -> 1.000866 | T36: The Asset/Equity ratio remains constant at 1.00 throughout the period (2021–2035), indicating that the company operates entirely on equity without relying on debt financing. This reflects a zero-leverage structure, suggesting financial stability and no external borrowings. While this eliminates financial risk from debt obligations, it also limits the potential benefits of leverage in enhancing returns, making profitability fully dependent on equity-funded operations and associate income contributions.
B39: Total Asset Turnover Ratio | C39: ='Income Statement'!C13/'Balance Sheet'!C32 -> 0.0085748576 | D39: ='Income Statement'!D13/'Balance Sheet'!D32 -> 0.011913358 | E39: ='Income Statement'!E13/'Balance Sheet'!E32 -> 0.0018977994 | F39: ='Income Statement'!F13/'Balance Sheet'!F32 -> 0.0045185976 | G39: ='Income Statement'!G13/'Balance Sheet'!G32 -> 0.0064321505 | H39: ='Income Statement'!H13/'Balance Sheet'!H32 -> 0.0088117487 | I39: ='Income Statement'!I13/'Balance Sheet'!I32 -> 0.011067873 | J39: ='Income Statement'!J13/'Balance Sheet'!J32 -> 0.012920662 | ... Q39: ='Income Statement'!Q13/'Balance Sheet'!Q32 -> 0.013237579 | T39: The Total Asset Turnover Ratio remains very low across the period, starting at 0.009x (2021) and improving slightly to 0.012x (2022), before dropping sharply to 0.002x (2023). A gradual recovery follows, reaching 0.005x (2024) and 0.006x (2025). For the forecasted period (2026–2035), efficiency improves modestly, peaking at 0.014x (2030–2032) before tapering to 0.012x (2035). The consistently low ratios indicate that the company generates minimal revenue relative to its asset base, reflecting weak operational efficiency. This further highlights that profitability is largely driven by associate income, rather than strong core revenue-generating capacity.
B42: Efficiency Ratio | C42: =('Income Statement'!C17+'Income Statement'!C16)/'Income Statement'!C13 -> 0.11474797 | D42: =('Income Statement'!D17+'Income Statement'!D16)/'Income Statement'!D13 -> 0.092911649 | E42: =('Income Statement'!E17+'Income Statement'!E16)/'Income Statement'!E13 -> 0.74252698 | F42: =('Income Statement'!F17+'Income Statement'!F16)/'Income Statement'!F13 -> 0.29120278 | G42: =('Income Statement'!G17+'Income Statement'!G16)/'Income Statement'!G13 -> 0.27144563 | H42: =('Income Statement'!H17+'Income Statement'!H16)/'Income Statement'!H13 -> 0.302567 | I42: =('Income Statement'!I17+'Income Statement'!I16)/'Income Statement'!I13 -> 0.302567 | J42: =('Income Statement'!J17+'Income Statement'!J16)/'Income Statement'!J13 -> 0.302567 | ... Q42: =('Income Statement'!Q17+'Income Statement'!Q16)/'Income Statement'!Q13 -> 0.302567 | T42: The Efficiency Ratio shows significant volatility in the initial years, starting at 0.11 (2021) and improving to 0.09 (2022), before worsening sharply to 0.74 (2023), indicating a spike in costs relative to income. It then recovers to 0.29 (2024) and stabilizes to 0.30 during 2025–2035. The trend highlights weak cost efficiency in 2023, followed by normalization and stability in the long term. However, the ratio levels suggest that while efficiency improves, operations remain only moderately cost-effective, with profitability still heavily dependent on income from associates rather than pure operational strength.
B45: Operating Leverage | C45: N/A | D45: =('Income Statement'!D24-'Income Statement'!C24)/('Income Statement'!D13-'Income Statement'!C13) -> 0.93964403 | E45: =('Income Statement'!E24-'Income Statement'!D24)/('Income Statement'!E13-'Income Statement'!D13) -> 1.0475832 | F45: =('Income Statement'!F24-'Income Statement'!E24)/('Income Statement'!F13-'Income Statement'!E13) -> 1.0033382 | G45: =('Income Statement'!G24-'Income Statement'!F24)/('Income Statement'!G13-'Income Statement'!F13) -> 0.76593988 | H45: =('Income Statement'!H24-'Income Statement'!G24)/('Income Statement'!H13-'Income Statement'!G13) -> 0.6318461 | I45: =('Income Statement'!I24-'Income Statement'!H24)/('Income Statement'!I13-'Income Statement'!H13) -> 0.69743655 | J45: =('Income Statement'!J24-'Income Statement'!I24)/('Income Statement'!J13-'Income Statement'!I13) -> 0.6974362 | K45: =('Income Statement'!K24-'Income Statement'!J24)/('Income Statement'!K13-'Income Statement'!J13) -> 0.69711794 | ... Q45: =('Income Statement'!Q24-'Income Statement'!P24)/('Income Statement'!Q13-'Income Statement'!P13) -> 0.69694026 | T45: The Operating Leverage shows variability over the years, beginning at 0.94 (2022) and rising slightly to 1.05 (2023), indicating higher sensitivity of operating profit to revenue changes during that period. It then normalizes to 1.00 (2024) before declining to 0.77 (2025) and further to 0.62 (2026). For the forecasted period (2027–2035), leverage stabilizes to 0.70. The trend suggests that the company initially experienced stronger operating leverage, but over time its cost structure became more flexible, reducing earnings volatility. This reflects controlled fixed costs and greater stability, though it also implies limited upside from revenue growth.
